Workbook

Sheet 00_使い方
A1: 川崎町第10期 保険料試算ワークブック
A2: ── 8ステップ準拠・3パターン(A/B/C)試算・9段階/13段階比較 ──
A4: 1．本ワークブックの目的
A5: 国基本指針に準拠した8ステップで川崎町第10期介護保険料(第1号被保険者基準月額)を試算します。基金取崩額により3パターン(A:取崩なし/B:50%取崩/C:全額取崩)を並列計算し、9段階と13段階区分の比較も実施。第3回策定委員会(R9.1中旬)で確定値を提示するための作業用シートです。
A7: 2．シート構成
A8: シート | B8: 内容 | F8: 対応ステップ
A9: 01_入力_基礎データ | B9: 人口・認定者・収納率・基金残高等の基礎数値 | F9: 全Step共通
A10: 02_Step1-2_標準給付費 | B10: サービス見込量と単価から3年間の標準給付費を算定 | F10: Step1-2
A11: 03_Step3-4_地域支援等 | B11: 地域支援事業費と第1号負担分相当額(23%)を算定 | F11: Step3-4
A12: 04_Step5_調整交付金 | B12: 国の調整交付金(5%基本+変動)を算定 | F12: Step5
A13: 05_Step6_基金3パターン | B13: 基金取崩額の3パターン設定(A/B/C) | F13: Step6
A14: 06_Step7-8_収納額・基準額 | B14: 保険料収納必要額と基準額(月額)の算定 | F14: Step7-8
A15: 07_所得段階_9段階版 | B15: 現行9段階区分での所得段階別保険料 | F15: Step8拡張
A16: 08_所得段階_13段階版 | B16: 13段階区分での所得段階別保険料(協議事項5) | F16: Step8拡張
A17: 09_比較分析 | B17: 3パターン×9/13段階のクロス比較・近隣比較 | F17: 総合
A19: 3．セルの色分け凡例
A20: 入力欄(黄色) | B20: 町担当課・弊社で入力する数値。基礎データ・基金残高等
A21: 既知数値(緑) | B21: 確定済の数値。R3給付実績・R7.6人口等
A22: 計算結果(青) | B22: 数式により自動算出される数値。手入力不要
A23: 重要結果(赤) | B23: 保険料基準額等の最重要算定結果
A25: 4．保険料算定の8ステップ全体像
A26: Step | B26: 内容 | E26: 数式・元データ | G26: シート
A27: Step1 | B27: サービス見込量×単価=標準給付費(年度別) | E27: 見込量(第7章7-1) × サービス単価 | G27: 02
A28: Step2 | B28: 標準給付費3年間総額 | E28: Step1の3年分(R9-R11)を合計 | G28: 02
A29: Step3 | B29: 地域支援事業費(包括的・任意事業) | E29: Step1の3〜4%相当(国基準) | G29: 03
A30: Step4 | B30: 第1号負担分相当額 | E30: (Step2+Step3)×23%(第1号負担割合) | G30: 03
A31: Step5 | B31: 調整交付金額 | E31: Step4×(調整交付金率5%-実績)補正 | G31: 04
A32: Step6 | B32: 基金取崩額の設定(3パターン) | E32: A:0/B:基金×50%/C:基金×100% | G32: 05
A33: Step7 | B33: 保険料収納必要額 | E33: Step4-Step5+Step6 | G33: 06
A34: Step8 | B34: 保険料基準月額 | E34: Step7÷(被保険者数×12×収納率×補正) | G34: 06
A36: 5．運用上の注意事項
A37: ※ 本ワークブックは作業用です。確定値は介護給付費準備基金残高(R8.6時点)の入手後にシート01で入力してください。
A38: ※ サービス見込量(Step1)は計画素案v1.5第7章7-1の暫定値を使用。Phase 2でアンケート補正後に更新します。
A39: ※ 見える化システムの仙南圏域他自治体保険料との比較は、町担当課が見える化システム登録完了後に実施します。
A40: ※ 13段階区分(シート08)は国推奨基準率に基づく試算。確定段階率は委員会協議事項5で確定します。
A41: ※ 3パターン試算の結果を第3回策定委員会(R9.1中旬)で提示し、委員協議の上、第10期保険料パターンを決定します。

Sheet 01_入力_基礎データ
A1: 01 基礎データ入力シート
A2: ── 8ステップ算定の前提となる基礎数値を入力 ──
A4: A. 第1号被保険者数の推計（Step8で使用）
A5: 年度 | B5: 65歳以上人口(人) | D5: 備考 | F5: 出典
A6: R7(2025) | B6: 3244 | D6: 実績(R7.6時点) | F6: 町保険者データ
A7: R8(2026) | B7: 3296 | D7: 推計値(町担当課入力) | F7: 町推計
A8: R9(2027) | B8: 3262 | D8: 第10期初年度推計 | F8: 社人研推計+補正
A9: R10(2028) | B9: 3234 | D9: 第10期中年度推計 | F9: 社人研推計+補正
A10: R11(2029) | B10: 3206 | D10: 第10期最終年度推計 | F10: 社人研推計+補正
A11: 3年合計 | B11: =SUM(B8:B10) -> 9702 | D11: R9-R11の合計(Step8で使用) | F11: 計算
A13: B. 介護給付費準備基金（Step6で使用）
A14: 項目 | B14: 金額(千円) | D14: 備考・時点
A15: 基金残高(R8.6時点) | B15: 53700 | D15: 第10期開始時(R8末)・計画ベース。R8.6確定値は町確認待ち
A16: (参考)第9期 基金残高/予定取崩 | B16: 131,700 / 78,000 | D16: 第9期計画 保険料算出より(千円)。第9期は6,500円を実現
A18: C. 保険料収納率の過去5年実績（Step8で使用）
A19: 年度 | B19: 総合収納率(%) | D19: 現年度分(%) | F19: 出典
A20: R3 | B20: 96.3 | D20: 99 | F20: 実績(MECEデータ既知)
A21: R4 | B21: [入力] | D21: [入力] | F21: 町担当課入力
A22: R5 | B22: [入力] | D22: [入力] | F22: 町担当課入力
A23: R6 | B23: [入力] | D23: [入力] | F23: 町担当課入力
A24: R7 | B24: [入力] | D24: [入力] | F24: 町担当課入力(R7.3末)
A25: 5年平均 | B25: =IFERROR(AVERAGE(B20:B24),"R4-R7入力後算定") -> 96.3 | D25: =IFERROR(AVERAGE(D20:D24),"R4-R7入力後算定") -> 99 | F25: 予定収納率(R4-R7町確認後に確定)。暫定はStep8で96%使用
A27: D. 第10期の制度パラメータ（国基準値）
A28: パラメータ | B28: 値 | D28: 備考
A29: 第1号被保険者負担割合 | B29: 23% | D29: Step4で使用。第10期も第9期と同じ23%(国基準)
A30: 第2号被保険者負担割合 | B30: 27% | D30: 参考。Step4対象外
A31: 公費負担割合(国) | B31: 25% | D31: 参考。調整交付金5%含む
A32: 公費負担割合(都道府県) | B32: 12.5% | D32: 参考
A33: 公費負担割合(市町村) | B33: 12.5% | D33: 参考
A34: 標準調整交付金率 | B34: 5% | D34: Step5で使用。実際は補正あり
A35: 地域支援事業費率(対給付費) | B35: 3〜4% | D35: Step3で使用。上限額管理あり

Sheet 02_Step1-2_標準給付費
A1: 02 Step1-2 標準給付費の算定
A2: ── サービス見込量×単価で年度別給付費を算定 ──
A4: Step1：サービス区分別の3年間給付費見込み（千円）
A5: サービス区分 | B5: R3実績(参考) | C5: R9見込み | D5: R10見込み | E5: R11見込み | F5: 3年合計 | G5: 備考
A6: 居宅サービス | B6: 365000 | C6: 390630 | D6: 395318 | E6: 400061 | F6: =SUM(C6:E6) -> 1186009 | G6: R3実績9.6億×38.1%(参考)
A7: 地域密着型サービス | B7: 152000 | C7: 162673 | D7: 164625 | E7: 166601 | F7: =SUM(C7:E7) -> 493899 | G7: R3実績9.6億×15.9%
A8: 施設サービス | B8: 441000 | C8: 471967 | D8: 477630 | E8: 483362 | F8: =SUM(C8:E8) -> 1432959 | G8: R3実績9.6億×46.0%(特養68・老健66)
A9: 住宅改修・福祉用具 | B9: 2857 | C9: 3058 | D9: 3094 | E9: 3131 | F9: =SUM(C9:E9) -> 9283 | G9: R3実績(参考値)
A10: 特定入所者・高額・審査支払手数料 等 | B10: 87402 | C10: 88451 | D10: 89512 | E10: 90586 | F10: =SUM(C10:E10) -> 268549 | G10: 第9期R8実績(特定入所者55,714+高額28,475+高額医療2,505+審査708)×年1.2%
A11: Step2: 標準給付費合計 | B11: =SUM(B6:B10) -> 1048259 | C11: =SUM(C6:C10) -> 1116779 | D11: =SUM(D6:D10) -> 1130179 | E11: =SUM(E6:E10) -> 1143741 | F11: =SUM(F6:F10) -> 3390699 | G11: Step3-5で使用(総給付額+補完項目=標準給付費見込額)
A12: ※ R9-R11は第9期計画R8実績(総給付額1,016,134千円)を基に年1.2%(後期高齢化・重度化・R9報酬改定)で推計し、サービス構成比(R3実績)で配分。
A13: ※ 補完項目=特定入所者介護サービス費・高額介護サービス費・高額医療合算・審査支払手数料。標準給付費見込額=総給付額+補完項目。
A14: ※ 確定値はアンケート結果反映後の見込量(Phase2 W8-W9)で更新。給付費の伸び率は前提値であり町データで精緻化。

Sheet 03_Step3-4_地域支援等
A1: 03 Step3-4 地域支援事業費と第1号負担分相当額
A2: ── 地域支援事業費(Step3)と第1号負担分23%(Step4)を算定 ──
A4: Step3：地域支援事業費（千円）
A5: 区分 | B5: R3実績 | C5: R9見込み | D5: R10見込み | E5: R11見込み | F5: 3年合計
A6: 総合事業(介護予防・生活支援) | B6: 5650 | C6: 5377 | D6: 5377 | E6: 5377 | F6: =SUM(C6:E6) -> 16131
A7: 一般介護予防事業 | B7: 1950 | C7: 1856 | D7: 1856 | E7: 1856 | F7: =SUM(C7:E7) -> 5568
A8: 包括的支援事業・任意事業 | B8: 24471 | C8: 23288 | D8: 23288 | E8: 23288 | F8: =SUM(C8:E8) -> 69864
A9: Step3 合計 | B9: =SUM(B6:B8) -> 32071 | C9: =SUM(C6:C8) -> 30521 | D9: =SUM(D6:D8) -> 30521 | E9: =SUM(E6:E8) -> 30521 | F9: =SUM(F6:F8) -> 91563
A10: ※ 地域支援事業費は第9期水準(30,520千円/年)を構成比配分。認知症基本法対応で上方圧力あり、確定はPhase2。
A11: Step4：第1号被保険者負担分相当額（千円・国基準23%）
A12: 計算式：(Step2:標準給付費合計 + Step3:地域支援事業費合計) × 23%
A13: 項目 | B13: 金額(千円・3年合計) | D13: 備考
A14: Step2 標準給付費合計 | B14: ='02_Step1-2_標準給付費'!F11 -> 3390699 | D14: シート02から自動参照
A15: Step3 地域支援事業費合計 | B15: =F9 -> 91563 | D15: 本シート上部から自動参照
A16: 保険給付費等合計 | B16: =B14+B15 -> 3482262 | D16: Step2 + Step3
A17: Step4 第1号負担分相当額 | B17: =B16*0.23 -> 800920.26 | D17: × 23%(第1号負担割合)= Step5で使用

Sheet 04_Step5_調整交付金
A1: 04 Step5 調整交付金
A2: ── 国の調整交付金(基準5%+変動)を算定 ──
A4: Step5：調整交付金額の算定（千円）
A5: 解説：調整交付金は標準調整交付金率5%を基本に、後期高齢者割合・所得段階分布等で町別に補正されます。実際の交付金率は5%±αで、町の状況により4-6%程度になります。
A6: 項目 | B6: 値 | D6: 備考
A7: 標準調整交付金率 | B7: 5.0% | D7: 国基準値
A8: 川崎町の調整交付金見込率(実績) | B8: 0.039 | D8: 第9期実績3.9%。ただし高齢化・低所得町は普通調整交付金が5%超となる例が多く、実際の交付実績の確認推奨(5%なら基準額は約4%低下)
A9: 標準給付費合計(Step2) | B9: ='02_Step1-2_標準給付費'!F11 -> 3390699 | D9: シート02から参照(千円)
A10: 調整交付金相当額(標準5%) | B10: =B9*0.05 -> 169534.95 | D10: 標準給付費×5%。Step7で加算
A11: 調整交付金見込額(実績率) | B11: =B9*B8 -> 132237.26 | D11: 標準給付費×実績率。Step7で減算
A12: ■ 保険料への影響(相当額−見込額)
A13: 相当額−見込額 | B13: =B10-B11 -> 37297.689 | D13: プラス=川崎町は標準5%より調整交付金が少なく、保険料の増要因(第1号負担に上乗せ)
A14: ※ 介護保険財政では第1号負担分(23%)に標準5%相当を加算し実際の調整交付金見込額を減算する(第9期計画と同方式)。 | B14: =B9-B13 -> 3353401.3 | D14: 差額がプラス→保険料軽減効果あり、マイナス→保険料追加負担

Sheet 05_Step6_基金3パターン
A1: 05 Step6 介護給付費準備基金取崩額の3パターン設定
A2: ── A:取崩なし / B:50%取崩 / C:全額取崩 ──
A4: ■ 基金残高（シート01から自動参照）
A5: 基金残高(R8.6時点・千円) | B5: =01_入力_基礎データ!B15 -> 53700 | D5: シート01のB15から自動参照
A7: ■ 3パターン基金取崩額設定
A8: パターン | B8: 取崩割合 | C8: 取崩額(千円) | D8: 残高(千円) | E8: 効果・想定
A9: A 取崩なし | B9: 0 | C9: =$B$5*B9 -> 0 | D9: =$B$5-C9 -> 53700 | E9: 基金温存・第11期負担緩和・給付費増を保険料に直接反映(最高水準)
A10: B 50%取崩 | B10: 0.5 | C10: =$B$5*B10 -> 26850 | D10: =$B$5-C10 -> 26850 | E10: 給付費増を一部相殺・次期負担との均衡(中位水準)
A11: C 全額取崩 | B11: 1 | C11: =$B$5*B11 -> 53700 | D11: =$B$5-C11 -> 0 | E11: 住民負担最小化・第11期負担増のリスクあり(最低水準)
A13: ※ 基金残高(B5)はシート01のB15(第10期開始時・計画ベース53,700千円)を参照。R8.6確定値受領後に更新。
A14: ※ パターンBの50%は標準的な選択肢ですが、25%/75%等の中間値も検討可能です(シート05_2を別途作成可)。
A15: ※ 基金取崩は計画期間(3年)の累計額です。年度別配分は別途検討します。
A16: ※ 国は基金残高の概ね半分以下を取崩水準として推奨しているため、パターンBが標準的とされます。

Sheet 06_Step7-8_収納額_基準額
A1: 06 Step7-8 保険料収納必要額と基準月額の算定
A2: ── 3パターン(A/B/C)で保険料基準月額を算定 ──
A4: Step7：保険料収納必要額（3パターン・千円）
A5: 計算式：Step4(第1号負担分) - Step5(調整交付金) - Step6(基金取崩額)
A6: 項目 | B6: 共通値 | C6: パターンA | D6: パターンB | E6: パターンC | F6: 備考
A7: Step4 第1号負担分(23%) | B7: ='03_Step3-4_地域支援等'!B17 -> 800920.26 | C7: =$B$7 -> 800920.26 | D7: =$B$7 -> 800920.26 | E7: =$B$7 -> 800920.26 | F7: 3パターン共通
A8: 調整交付金相当額(5%・加算) | B8: =04_Step5_調整交付金!B10 -> 169534.95 | C8: =$B$8 -> 169534.95 | D8: =$B$8 -> 169534.95 | E8: =$B$8 -> 169534.95 | F8: 3パターン共通(加算)
A9: 調整交付金見込額(実績・減算) | B9: =04_Step5_調整交付金!B11 -> 132237.26 | C9: =$B$9 -> 132237.26 | D9: =$B$9 -> 132237.26 | E9: =$B$9 -> 132237.26 | F9: 3パターン共通(減算)
A10: 保険者機能強化交付金(減算) | B10: 10800 | C10: =$B$10 -> 10800 | D10: =$B$10 -> 10800 | E10: =$B$10 -> 10800 | F10: 3パターン共通(減算)
A11: 基金取崩額(パターン別・減算) | B11: (パターン別) | C11: =05_Step6_基金3パターン!C9 -> 0 | D11: =05_Step6_基金3パターン!C10 -> 26850 | E11: =05_Step6_基金3パターン!C11 -> 53700 | F11: シート05から参照
A12: Step7 保険料収納必要額 | C12: =$B$7+$B$8-$B$9-$B$10-C11 -> 827417.95 | D12: =$B$7+$B$8-$B$9-$B$10-D11 -> 800567.95 | E12: =$B$7+$B$8-$B$9-$B$10-E11 -> 773717.95 | F12: 第1号負担分+調整交付金相当額−見込額−機能強化−基金取崩
A14: Step8：保険料基準月額の算定（円）
A15: 第1号被保険者数 3年合計 | B15: =01_入力_基礎データ!B11 -> 9702 | D15: シート01から自動参照(R9-R11合計)
A16: 予定収納率 | B16: 0.96 | D16: 第9期と同水準96%(暫定)
A17: 補正係数(所得段階分布) | B17: 0.97 | D17: 川崎町第9期実効値(逆算0.96-0.98)の中点。所得段階別人口で確定
A18: Step8 保険料基準月額(円) | C18: =IFERROR(C12*1000/($B$15*12*$B$16*$B$17),"町データ入力後算定") -> 7632.0192 | D18: =IFERROR(D12*1000/($B$15*12*$B$16*$B$17),"町データ入力後算定") -> 7384.3575 | E18: =IFERROR(E12*1000/($B$15*12*$B$16*$B$17),"町データ入力後算定") -> 7136.6958 | F18: 第10期基準月額(3パターン)
A19: 【精査メモ】① 補正係数は所得段階別人口で確定（1.0→0.97に補正、第9期実効値）。
A20: ■ 第9期との比較
A21: 比較項目 | B21: 第8期 | C21: 第9期 | D21: 第10期A | E21: 第10期B | F21: 第10期C
A22: 月額(円) | B22: 6380 | C22: 6500 | D22: =IFERROR(C18,"未算定") -> 7632.0192 | E22: =IFERROR(D18,"未算定") -> 7384.3575 | F22: =IFERROR(E18,"未算定") -> 7136.6958
A23: 第9期比増減率(%) | D23: =IFERROR((D18/$C$22-1)*100,"未算定") -> 13.6055 | E23: =IFERROR((E18/$C$22-1)*100,"未算定") -> 9.7953207 | F23: =IFERROR((F18/$C$22-1)*100,"未算定") -> 未算定

Sheet 07_所得段階_9段階
A1: 07 所得段階別保険料（9段階版・現行）
A2: ── 現行9段階区分での所得段階別年間保険料(月額×12) ──
A4: 段階 | B4: 対象 | C4: 係数 | D4: 月額A(円) | E4: 月額B(円) | F4: 月額C(円) | G4: 該当人数
A5: 第1段階 | B5: 生活保護・老齢福祉年金受給者・市町村民税非課税世帯+本人非課税 | C5: 0.3 | D5: =IFERROR('06_Step7-8_収納額_基準額'!C18*$C5,"未算定") -> 2289.6058 | E5: =IFERROR('06_Step7-8_収納額_基準額'!D18*$C5,"未算定") -> 2215.3073 | F5: =IFERROR('06_Step7-8_収納額_基準額'!E18*$C5,"未算定") -> 2141.0088
A6: 第2段階 | B6: 市町村民税非課税世帯+本人非課税(年金収入80万円超120万円以下) | C6: 0.5 | D6: =IFERROR('06_Step7-8_収納額_基準額'!C18*$C6,"未算定") -> 3816.0096 | E6: =IFERROR('06_Step7-8_収納額_基準額'!D18*$C6,"未算定") -> 3692.1788 | F6: =IFERROR('06_Step7-8_収納額_基準額'!E18*$C6,"未算定") -> 3568.3479
A7: 第3段階 | B7: 市町村民税非課税世帯+本人非課税(年金収入120万円超) | C7: 0.7 | D7: =IFERROR('06_Step7-8_収納額_基準額'!C18*$C7,"未算定") -> 5342.4134 | E7: =IFERROR('06_Step7-8_収納額_基準額'!D18*$C7,"未算定") -> 5169.0503 | F7: =IFERROR('06_Step7-8_収納額_基準額'!E18*$C7,"未算定") -> 4995.6871
A8: 第4段階 | B8: 本人市町村民税非課税(世帯課税)・課税年金収入80万円以下 | C8: 0.9 | D8: =IFERROR('06_Step7-8_収納額_基準額'!C18*$C8,"未算定") -> 6868.8173 | E8: =IFERROR('06_Step7-8_収納額_基準額'!D18*$C8,"未算定") -> 6645.9218 | F8: =IFERROR('06_Step7-8_収納額_基準額'!E18*$C8,"未算定") -> 6423.0263
A9: 第5段階(基準) | B9: 本人市町村民税非課税(世帯課税)・課税年金収入80万円超 | C9: 1 | D9: =IFERROR('06_Step7-8_収納額_基準額'!C18*$C9,"未算定") -> 7632.0192 | E9: =IFERROR('06_Step7-8_収納額_基準額'!D18*$C9,"未算定") -> 7384.3575 | F9: =IFERROR('06_Step7-8_収納額_基準額'!E18*$C9,"未算定") -> 7136.6958
A10: 第6段階 | B10: 本人市町村民税課税・合計所得120万円未満 | C10: 1.2 | D10: =IFERROR('06_Step7-8_収納額_基準額'!C18*$C10,"未算定") -> 9158.423 | E10: =IFERROR('06_Step7-8_収納額_基準額'!D18*$C10,"未算定") -> 8861.229 | F10: =IFERROR('06_Step7-8_収納額_基準額'!E18*$C10,"未算定") -> 8564.035
A11: 第7段階 | B11: 本人市町村民税課税・合計所得120万円以上210万円未満 | C11: 1.3 | D11: =IFERROR('06_Step7-8_収納額_基準額'!C18*$C11,"未算定") -> 9921.625 | E11: =IFERROR('06_Step7-8_収納額_基準額'!D18*$C11,"未算定") -> 9599.6648 | F11: =IFERROR('06_Step7-8_収納額_基準額'!E18*$C11,"未算定") -> 9277.7046
A12: 第8段階 | B12: 本人市町村民税課税・合計所得210万円以上320万円未満 | C12: 1.5 | D12: =IFERROR('06_Step7-8_収納額_基準額'!C18*$C12,"未算定") -> 11448.029 | E12: =IFERROR('06_Step7-8_収納額_基準額'!D18*$C12,"未算定") -> 11076.536 | F12: =IFERROR('06_Step7-8_収納額_基準額'!E18*$C12,"未算定") -> 10705.044
A13: 第9段階 | B13: 本人市町村民税課税・合計所得320万円以上 | C13: 1.7 | D13: =IFERROR('06_Step7-8_収納額_基準額'!C18*$C13,"未算定") -> 12974.433 | E13: =IFERROR('06_Step7-8_収納額_基準額'!D18*$C13,"未算定") -> 12553.408 | F13: =IFERROR('06_Step7-8_収納額_基準額'!E18*$C13,"未算定") -> 12132.383
A15: ※ 係数は国基準値です。市町村は条例により調整可能(±10%程度)。
A16: ※ 該当人数の合計は所得段階別R3末3,255人(第5基準697人)が参考値です。R7時点の確定値を入力してください。
A17: ※ 本シートはステップ8の算定結果を所得段階別に展開した参考表です。条例改正案作成の元データとなります。

Sheet 08_所得段階_13段階
A1: 08 所得段階別保険料（13段階版・協議事項5）
A2: ── 国推奨13段階区分での所得段階別保険料 ──
A4: 段階 | B4: 対象 | C4: 係数 | D4: 月額A(円) | E4: 月額B(円) | F4: 月額C(円) | G4: 該当人数
A5: 第1段階 | B5: 生活保護受給者・老齢福祉年金受給者・住民税非課税世帯本人収入80万円以下 | C5: 0.285 | D5: =IFERROR('06_Step7-8_収納額_基準額'!C18*$C5,"未算定") -> 2175.1255 | E5: =IFERROR('06_Step7-8_収納額_基準額'!D18*$C5,"未算定") -> 2104.5419 | F5: =IFERROR('06_Step7-8_収納額_基準額'!E18*$C5,"未算定") -> 2033.9583
A6: 第2段階 | B6: 住民税非課税世帯+本人収入80万円超120万円以下 | C6: 0.485 | D6: =IFERROR('06_Step7-8_収納額_基準額'!C18*$C6,"未算定") -> 3701.5293 | E6: =IFERROR('06_Step7-8_収納額_基準額'!D18*$C6,"未算定") -> 3581.4134 | F6: =IFERROR('06_Step7-8_収納額_基準額'!E18*$C6,"未算定") -> 3461.2975
A7: 第3段階 | B7: 住民税非課税世帯+本人収入120万円超 | C7: 0.685 | D7: =IFERROR('06_Step7-8_収納額_基準額'!C18*$C7,"未算定") -> 5227.9331 | E7: =IFERROR('06_Step7-8_収納額_基準額'!D18*$C7,"未算定") -> 5058.2849 | F7: =IFERROR('06_Step7-8_収納額_基準額'!E18*$C7,"未算定") -> 4888.6367
A8: 第4段階 | B8: 本人非課税(世帯課税)+課税年金収入80万円以下 | C8: 0.88 | D8: =IFERROR('06_Step7-8_収納額_基準額'!C18*$C8,"未算定") -> 6716.1769 | E8: =IFERROR('06_Step7-8_収納額_基準額'!D18*$C8,"未算定") -> 6498.2346 | F8: =IFERROR('06_Step7-8_収納額_基準額'!E18*$C8,"未算定") -> 6280.2923
A9: 第5段階(基準) | B9: 本人非課税(世帯課税)+課税年金収入80万円超 | C9: 1 | D9: =IFERROR('06_Step7-8_収納額_基準額'!C18*$C9,"未算定") -> 7632.0192 | E9: =IFERROR('06_Step7-8_収納額_基準額'!D18*$C9,"未算定") -> 7384.3575 | F9: =IFERROR('06_Step7-8_収納額_基準額'!E18*$C9,"未算定") -> 7136.6958
A10: 第6段階 | B10: 本人課税・合計所得120万円未満 | C10: 1.2 | D10: =IFERROR('06_Step7-8_収納額_基準額'!C18*$C10,"未算定") -> 9158.423 | E10: =IFERROR('06_Step7-8_収納額_基準額'!D18*$C10,"未算定") -> 8861.229 | F10: =IFERROR('06_Step7-8_収納額_基準額'!E18*$C10,"未算定") -> 8564.035
A11: 第7段階 | B11: 本人課税・合計所得120万円以上210万円未満 | C11: 1.3 | D11: =IFERROR('06_Step7-8_収納額_基準額'!C18*$C11,"未算定") -> 9921.625 | E11: =IFERROR('06_Step7-8_収納額_基準額'!D18*$C11,"未算定") -> 9599.6648 | F11: =IFERROR('06_Step7-8_収納額_基準額'!E18*$C11,"未算定") -> 9277.7046
A12: 第8段階 | B12: 本人課税・合計所得210万円以上320万円未満 | C12: 1.5 | D12: =IFERROR('06_Step7-8_収納額_基準額'!C18*$C12,"未算定") -> 11448.029 | E12: =IFERROR('06_Step7-8_収納額_基準額'!D18*$C12,"未算定") -> 11076.536 | F12: =IFERROR('06_Step7-8_収納額_基準額'!E18*$C12,"未算定") -> 10705.044
A13: 第9段階 | B13: 本人課税・合計所得320万円以上420万円未満 | C13: 1.7 | D13: =IFERROR('06_Step7-8_収納額_基準額'!C18*$C13,"未算定") -> 12974.433 | E13: =IFERROR('06_Step7-8_収納額_基準額'!D18*$C13,"未算定") -> 12553.408 | F13: =IFERROR('06_Step7-8_収納額_基準額'!E18*$C13,"未算定") -> 12132.383
A14: 第10段階(新) | B14: 本人課税・合計所得420万円以上520万円未満 | C14: 1.9 | D14: =IFERROR('06_Step7-8_収納額_基準額'!C18*$C14,"未算定") -> 14500.836 | E14: =IFERROR('06_Step7-8_収納額_基準額'!D18*$C14,"未算定") -> 14030.279 | F14: =IFERROR('06_Step7-8_収納額_基準額'!E18*$C14,"未算定") -> 13559.722
A15: 第11段階(新) | B15: 本人課税・合計所得520万円以上620万円未満 | C15: 2.1 | D15: =IFERROR('06_Step7-8_収納額_基準額'!C18*$C15,"未算定") -> 16027.24 | E15: =IFERROR('06_Step7-8_収納額_基準額'!D18*$C15,"未算定") -> 15507.151 | F15: =IFERROR('06_Step7-8_収納額_基準額'!E18*$C15,"未算定") -> 14987.061
A16: 第12段階(新) | B16: 本人課税・合計所得620万円以上720万円未満 | C16: 2.3 | D16: =IFERROR('06_Step7-8_収納額_基準額'!C18*$C16,"未算定") -> 17553.644 | E16: =IFERROR('06_Step7-8_収納額_基準額'!D18*$C16,"未算定") -> 16984.022 | F16: =IFERROR('06_Step7-8_収納額_基準額'!E18*$C16,"未算定") -> 16414.4
A17: 第13段階(新) | B17: 本人課税・合計所得720万円以上 | C17: 2.4 | D17: =IFERROR('06_Step7-8_収納額_基準額'!C18*$C17,"未算定") -> 18316.846 | E17: =IFERROR('06_Step7-8_収納額_基準額'!D18*$C17,"未算定") -> 17722.458 | F17: =IFERROR('06_Step7-8_収納額_基準額'!E18*$C17,"未算定") -> 17128.07
A19: ※ (新)マークは9段階版にはなかった新設段階(第10〜13段階)です。高所得層への応分負担で全体最適化。
A20: ※ 係数は国推奨値ですが、市町村は条例で調整可能。委員会協議で確定値を決定します。
A21: ※ 13段階への移行は、低所得層(1〜3段階・約30%)の負担軽減と、高所得層への応分負担拡大の効果を狙います。
A22: ※ 該当人数のR7時点確定値は町担当課入力後に9段階版と13段階版で再分布を計算します。

Sheet 09_比較分析
A1: 09 3パターン×9/13段階 比較分析
A2: ── 委員会協議に向けた総合比較表・推奨パターンの検討材料 ──
A4: ■ 第10期基準月額の3パターン比較
A5: パターン | B5: 月額 | C5: 第9期比 | D5: 基金活用 | E5: 推奨度・特徴
A6: A 取崩なし | B6: =IFERROR('06_Step7-8_収納額_基準額'!C18,"未算定") -> 7632.0192 | C6: 高 | D6: なし | E6: 基金温存・第11期負担緩和の安定性
A7: B 50%取崩 | B7: =IFERROR('06_Step7-8_収納額_基準額'!D18,"未算定") -> 7384.3575 | C7: 中 | D7: 50% | E7: 中庸選択・住民負担と次期均衡(国推奨水準)
A8: C 全額取崩 | B8: =IFERROR('06_Step7-8_収納額_基準額'!E18,"未算定") -> 7136.6958 | C8: 低 | D8: 100% | E8: 住民負担最小化・次期負担増リスク
A10: ■ 仙南圏域・宮城県との比較(見える化システム参考値)
A11: 自治体 | B11: 第9期月額 | C11: 第10期月額 | D11: 高齢化率 | E11: 備考
A12: 川崎町(本町) | B12: 6500 | C12: 試算後 | D12: 41.4 | E12: 本町（仙南最高水準タイ）
A13: 柴田町 | B13: 5600 | C13: — | D13: 県資料 | E13: 宮城県公表値（第9期R6-R8）
A14: 大河原町 | B14: 4000 | C14: — | D14: 県資料 | E14: 宮城県公表値（第9期R6-R8）
A15: 村田町 | B15: 6500 | C15: — | D15: 県資料 | E15: 宮城県公表値（第9期R6-R8）
A16: 蔵王町 | B16: 5400 | C16: — | D16: 県資料 | E16: 宮城県公表値（第9期R6-R8）
A17: 仙南圏域平均（9市町） | B17: 5761 | C17: — | D17: — | E17: 白石角田蔵王七ヶ宿大河原村田柴田川崎丸森の単純平均
A18: 宮城県加重平均 | B18: 6098 | C18: — | D18: 28.5 | E18: 宮城県公表値（35市町村加重平均）
A19: 全国加重平均 | B19: 6225 | C19: — | D19: 29.1 | E19: 厚労省 第9期保険料状況
A21: ■ 第3回策定委員会向け 委員協議のポイント
A22: ①住民負担vs持続可能性のバランス：基金温存(A)か、住民負担軽減(C)か、中庸(B)か。
A23: ②国推奨水準との比較：国はパターンB(50%取崩)を標準的水準として推奨。
A24: ③水準感：本町6,500円は県加重平均6,098円を+402円上回る県内上位（10-12位/35）。仙南圏域では最高水準タイ。高齢化率41.4%（県内5位）と整合的で妥当。
A25: ④第11期(R12〜)の予測：給付費上昇傾向の中で、第11期負担増のリスクを勘案。
A26: ⑤所得段階区分(9→13段階)の影響：低所得層負担軽減と高所得層応分負担のバランス。
A27: ⑥委員会では各委員にA/B/Cの選好を伺い、論点整理→次回再協議の流れを推奨。

Sheet 10_長期推計サマリー
A1: 10 長期推計サマリー（人口・高齢化率・給付費・保険料）
A2: ── 社人研R5推計・第9期計画の確定データに基づく ──
A4: A. 人口・高齢化率の長期推移（社人研R5推計）
A5: 年次 | B5: 2020 | C5: 2025 | D5: 2030 | E5: 2040 | F5: 2050
A6: 総人口(人) | B6: 8345 | C6: 8161 | D6: 7029 | E6: 5776 | F6: 4525
A7: 65歳以上(人) | B7: 3210 | C7: 3219 | D7: 3149 | E7: 2835 | F7: 2494
A8: 15-64歳(人) | B8: 4381 | C8: 4394 | D8: 3424 | E8: 2605 | F8: 1795
A9: 高齢化率(%) | B9: 38.6 | C9: 38.6 | D9: 44.8 | E9: 49.1 | F9: 55.1
A10: ◆ 高齢者人口ピークは2025年(令和7年)頃。高齢化率は2050年55.1%まで上昇継続(全国37.1%)。
A12: B. 要支援・要介護認定者の推計
A13: 区分 | B13: 2023実績 | C13: R9(2027) | D13: R11(2029) | E13: 2035 | F13: 2040
A14: 認定者数(人) | B14: 578 | C14: 584 | D14: 598 | E14: 605 | F14: 604
A15: 認定率(%) | B15: 17.6 | C15: 18.3 | D15: 18.9 | E15: 20.4 | F15: 21.3
A16: ◆ 高齢者数は減るが後期高齢化・重度化で認定率上昇。認定者は横ばい〜微増、給付費は当面増加圧力。
A18: C. 介護給付費準備基金の確認
A19: 第9期 基金残高(算定時) | B19: 131,700千円 | C19: 第9期計画 保険料算出より
A20: 第9期 予定取崩額 | B20: 78,000千円 | C20: 6,500円実現のため取崩
A21: 第10期開始時 基金残高(計画ベース) | B21: 53,700千円 | C21: 131,700−78,000。R8.6確定値は町確認待ち
A23: D. 第10期 保険料基準額の試算（3パターン・シート06から参照）
B24: 第8期 | C24: 第9期 | D24: 第10期A | E24: 第10期B | F24: 第10期C
A25: 基準月額(円) | B25: 6380 | C25: 6500 | D25: ='06_Step7-8_収納額_基準額'!C18 -> 7632.0192 | E25: ='06_Step7-8_収納額_基準額'!D18 -> 7384.3575 | F25: ='06_Step7-8_収納額_基準額'!E18 -> 7136.6958
A26: 取崩想定 | D26: 取崩なし | E26: 50%取崩 | F26: 全額取崩
A27: ◆ 第9期6,500円は基金131,700千円から78,000千円取崩で実現。第10期は基金枯渇で抑制余地が小さく、
A28: 給付費増(+2.9%)も加わり7,000円台への上昇圧力。6,500円据置では基金が第10期中に枯渇。
A30: 【出典】人口・高齢化率:国立社会保障・人口問題研究所「日本の地域別将来推計人口(令和5年推計)」／川崎町第9期計画。
A31: 給付費・保険料・基金枯渇:前提を置いた参考試算。確定値は町提供データ(基金R8.6・収納率・所得段階別人口)で算定。
