Workbook

Sheet 00_ダッシュボード
A1: 小野町 高齢者保健福祉計画・第10期介護保険事業計画 業務進捗管理表
A2: 基準日：令和8年9月15日
A4: 全体進捗 | B4: ='02_段階サマリ'!H12 | D4: 作業数 | E4: ='02_段階サマリ'!B12 | G4: 完了 | H4: ='02_段階サマリ'!C12
A6: 段階 | B6: 作業数 | C6: 加重進捗率 | D6: 律速要因
A7: ='02_段階サマリ'!A2 | B7: ='02_段階サマリ'!B2 | C7: ='02_段階サマリ'!H2 | D7: ='02_段階サマリ'!K2
A8: ='02_段階サマリ'!A3 | B8: ='02_段階サマリ'!B3 | C8: ='02_段階サマリ'!H3 | D8: ='02_段階サマリ'!K3
A9: ='02_段階サマリ'!A4 | B9: ='02_段階サマリ'!B4 | C9: ='02_段階サマリ'!H4 | D9: ='02_段階サマリ'!K4
A10: ='02_段階サマリ'!A5 | B10: ='02_段階サマリ'!B5 | C10: ='02_段階サマリ'!H5 | D10: ='02_段階サマリ'!K5
A11: ='02_段階サマリ'!A6 | B11: ='02_段階サマリ'!B6 | C11: ='02_段階サマリ'!H6 | D11: ='02_段階サマリ'!K6
A12: ='02_段階サマリ'!A7 | B12: ='02_段階サマリ'!B7 | C12: ='02_段階サマリ'!H7 | D12: ='02_段階サマリ'!K7
A13: ='02_段階サマリ'!A8 | B13: ='02_段階サマリ'!B8 | C13: ='02_段階サマリ'!H8 | D13: ='02_段階サマリ'!K8
A14: ='02_段階サマリ'!A9 | B14: ='02_段階サマリ'!B9 | C14: ='02_段階サマリ'!H9 | D14: ='02_段階サマリ'!K9
A15: ='02_段階サマリ'!A10 | B15: ='02_段階サマリ'!B10 | C15: ='02_段階サマリ'!H10 | D15: ='02_段階サマリ'!K10
A16: ='02_段階サマリ'!A11 | B16: ='02_段階サマリ'!B11 | C16: ='02_段階サマリ'!H11 | D16: ='02_段階サマリ'!K11
A18: ■ 仕様書の業務ブロック別
A19: 仕様書ブロック | B19: 作業数 | C19: 加重進捗率 | D19: 現況・律速
A20: ='10_ブロック別進捗'!A2 | B20: ='10_ブロック別進捗'!C2 | C20: ='10_ブロック別進捗'!I2 | D20: ='10_ブロック別進捗'!J2
A21: ='10_ブロック別進捗'!A3 | B21: ='10_ブロック別進捗'!C3 | C21: ='10_ブロック別進捗'!I3 | D21: ='10_ブロック別進捗'!J3
A22: ='10_ブロック別進捗'!A4 | B22: ='10_ブロック別進捗'!C4 | C22: ='10_ブロック別進捗'!I4 | D22: ='10_ブロック別進捗'!J4
A23: ='10_ブロック別進捗'!A5 | B23: ='10_ブロック別進捗'!C5 | C23: ='10_ブロック別進捗'!I5 | D23: ='10_ブロック別進捗'!J5
A24: ='10_ブロック別進捗'!A6 | B24: ='10_ブロック別進捗'!C6 | C24: ='10_ブロック別進捗'!I6 | D24: ='10_ブロック別進捗'!J6
A25: ='10_ブロック別進捗'!A7 | B25: ='10_ブロック別進捗'!C7 | C25: ='10_ブロック別進捗'!I7 | D25: ='10_ブロック別進捗'!J7
A26: ='10_ブロック別進捗'!A8 | B26: ='10_ブロック別進捗'!C8 | C26: ='10_ブロック別進捗'!I8 | D26: ='10_ブロック別進捗'!J8
A27: ='10_ブロック別進捗'!A9 | B27: ='10_ブロック別進捗'!C9 | C27: ='10_ブロック別進捗'!I9 | D27: ='10_ブロック別進捗'!J9
A28: ='10_ブロック別進捗'!A10 | B28: ='10_ブロック別進捗'!C10 | C28: ='10_ブロック別進捗'!I10 | D28: ='10_ブロック別進捗'!J10
A29: ='10_ブロック別進捗'!A11 | B29: ='10_ブロック別進捗'!C11 | C29: ='10_ブロック別進捗'!I11 | D29: ='10_ブロック別進捗'!J11
A30: ='10_ブロック別進捗'!A12 | B30: ='10_ブロック別進捗'!C12 | C30: ='10_ブロック別進捗'!I12 | D30: ='10_ブロック別進捗'!J12
A32: ■ 現況
A33: 見える化システムによる分析は12分野135ファイルを取り込み、実質的に完了した。認定者数は平成19年3月末〜令和8年3月末の20期分を、要介護度別・年齢階層別・被保険者区分別で確定させた。
A34: 成果品6件のうち3件（①第5版・③第3版・④第2版）が初稿段階に達し、②は算定シートの構築まで進んだ。
A35: **令和8年9月8日、町から介護保険事業状況報告（年報）令和3〜7年度（各47様式）、国保連合会業務統計表（月報）28か月分、第10期将来推計用推計人口を受領した。**これにより依頼35項目の主要部分が一括で解決し、見込量推計・保険料算定に着手できる状態になった。
A36: **最大の律速だった令和8年3月末の認定者数792人は、介護保険事業状況報告（年報）様式1の5で裏付けられた（第1号783＋第2号9）。**さらに国保連月報28か月により、減少が令和7年9月審査分の1か月に集中していること（961人→862人・▲10.3％）と、**同じ月に給付件数がまったく減っていないこと（1,303件→1,365件）**が判明した。減少は要介護2以上に集中し、要支援1はむしろ増えている。死亡171人は平年並みである。
A37: **認定者だけが落ちて給付が落ちていないため、実態の変化ではなく計上の変更とみるのが最も整合的である。**年度でみても、令和7年度は認定者▲16.1％に対し受給者延▲4.6％・給付費▲7.4％で、認定者の減り方は給付の減り方の2倍以上ある。**したがって見込量は認定者数ベースではなく、受給者数と給付費の実績を基礎に組む。**
A38: **あわせて、介護給付費準備基金の保有額が12.0百万円しかないことが判明した。**第9期は基金取崩35.0百万円を見込んでいた。歳入歳出差引残額は144.2百万円あるため、繰越金として滞留している。令和4年度末の基金は120.0百万円で、令和5年度末に1桁減っており、確認を要する。
A39: 令和7年度調査の結果は集計結果・分析報告書として取りまとめ、素案第2版に反映した。**在宅の要介護認定者の42.1％がサービスを利用しておらず、その理由の92.9％が需要側の要因で、供給制約は0.6％であった。**これにより第10期の施策方向を、供給確保から認定運用の確認・利用意向への働きかけ・レスパイトへ組み替えた。
A40: 算定シートには受領した実績を投入した。人口推計（令和9〜11年）、令和7年度の年齢階層別認定率（65〜74歳3.92％／75〜84歳18.72％／85歳以上71.63％）、所得段階別被保険者数13段階と小野町が定める保険料率、収納率99.35％を入力済みである。
A41: **年報 様式2から29のサービス区分について令和3〜7年度の件数・単位数・費用額・給付費を取り出し、サービス別の単価と見込量を試算した。**正規化後の合計は様式2の総計と全年度・介護／予防別に一致しており、取りこぼしも二重計上もない。推計の分母は第1号被保険者数とした。給付件数総計を各分母で割ったときの変動係数が**第1号被保険者数1.63％に対し認定者数5.18％**であり、認定者数は令和7年9月の計上変更で断層があるためである。**令和7年9月審査分の断層は認定者数にだけ現れ、受給者数は連続している（認定者▲11.4％に対し受給者計▲3.9％、利用率＋8.4％）。**見える化の3段連鎖（第1号×認定率×利用率）に組み替えると、断層後にそろえた場合の差は3年計で▲1.0％（月額59円）にとどまる。
A42: **第10期（令和9〜11年度）の総給付費は3年計3,043,066千円、標準給付費は3,280,604千円で、第9期の見込み3,566,486千円の92.0％である。**この見込量に地域支援事業費（年報 様式4 の令和6年度決算・3年計191,749千円）を加えて算式を通すと、保険料基準額は月額6,558円（基金取崩なし）となる。第9期は6,600円であった。**ただし調整交付金・基金取崩額・第1号被保険者負担割合のいずれもが未確定であり、確定値ではない。**
A43: **第9期計画の見込みと実績の対比を確定させた。**標準給付費に対する実績は令和6年度98.6％、令和7年度91.1％（▲106,199千円）。特定入所者介護サービス費は101.8％・95.8％でほぼ計画どおりであり、下振れが施設利用の減少によるものではないことを確認した。
... A46: ■ 警戒事項
A47: # | B47: 内容 | C47: 影響 | D47: 対応
A48: 1 | B48: 第10期の第1号被保険者負担割合と調整交付金が未確定 | C48: **保険料の水準を左右するのは給付費の精度ではなく制度側の2つ。負担割合1ptで月額303円、調整交付金の見込交付割合1ptで295円動く（給付費に直すと5％分に相当）** | D48: **負担割合は3年の計画期間ごとに政令で定まる。第1期17％から3年ごとに1ptずつ上がっており、第10期は24％となる可能性がある。第10期の政令の公布状況を確認する。調整交付金は見える化の係数シート（全国値）で確認する**
A49: 2 | B49: 見える化システムへの入力作業が未着手 | C49: 仕様書4(2)が求める成果（将来推計総括表）が出せない。**総括表がないため、サービス別の対計画比が計画期をまたいで求められず、伸びの偏りの補正（手引き手順7）に進めない** | D49: **アカウントと作業範囲を町と確定する（依頼票C5）。入力時は令和8年度のチェックを外し、伸びは令和6年度→令和7年度を選び、施策反映の画面は編集しない（川崎町の事例）**
A50: 3 | B50: 認定者数の減少は計上の変更の可能性が高い | C50: 認定者数ベースで給付費を推計すると過小になる（令和7年度は認定者▲16.1％に対し給付費▲7.4％） | D50: **令和7年9月審査分の1か月に▲99人が集中し、同月の給付件数は減っていない。令和7年8〜9月の計上方法の変更を町に確認する。見込量は受給者数・給付費の実績を基礎に組む**
A51: 4 | B51: 介護給付費準備基金の保有額が12.0百万円しかない | C51: 第9期が見込んだ基金取崩35.0百万円は実行できない。保険料水準の判断に直結する | D51: **令和4年度末120.0百万円から令和5年度末12.0百万円へ1桁減っている。取崩実績か入力誤りかを町に確認する。繰越金144.2百万円の基金積立も選択肢**
A52: 5 | B52: 高齢者福祉サービス推進協議会の開催回数・時期が未定 | C52: 工程が引けず、パブリックコメント・印刷の日程も確定できない | D52: **仕様書に回数の指定がない。**受託者案（4回）を提示して町と確定する（依頼票C4）
A53: 6 | B53: 通いの場の実態が把握できていない | C53: 第9期の介護予防施策を評価できず、第10期の最重点施策も設計できない | D53: 見える化は0か所、調査は週1回以上5.5％（約190人規模）。町の事業実績で確認する（依頼票H3）
A54: 7 | B54: 印刷工程が確保されていない | C54: 計画書50部・概要版50部が納期に間に合わない | D54: 令和9年2月下旬の校了から逆算し、12月までに印刷業者を押さえる
A55: 8 | B55: 見える化システムへの入力作業が未着手 | C55: 出力の分析だけでは仕様書4(2)を満たさない | D55: アカウント・権限・作業範囲・時期を町と確認する（依頼票C5）
A57: ■ 直近のマイルストーン
A58: 時期 | B58: 内容 | C58: 状態 | D58: 前提
A59: 令和8年9月8日 | B59: **年報5年分・国保連月報28か月・将来推計人口を受領** | C59: 完了 | D59: 認定者数792人を確認。算定シートに実績を投入済み
A60: 令和8年9月中 | B60: **令和7年8〜9月の計上変更の照会／基金残高の確認** | C60: 要対応 | D60: 町への照会
A61: 令和8年9月中 | B61: **サービス別単価の算出と見込量の試算（受給者数ベース）** | C61: 要対応 | D61: 年報 様式2の5年分から算出できる
A62: 令和8年9〜10月 | B62: 協議会 第1回（第9期の評価・調査結果） | C62: 要対応 | D62: **資料は作成済み。開催日が未定**
A63: 令和8年10月 | B63: **認定者数の確定 → 見込量の推計 → 見える化への入力** | C63: 未着手 | D63: 認定者数の確認
A64: 令和8年11月 | B64: 保険料のケース別算定、協議会 第2回 | C64: 未着手 | D64: 見込量の確定
A65: 令和8年12月 | B65: 素案の確定、協議会 第3回 | C65: 未着手 | D65: 保険料の算定
A66: 令和9年1月 | B66: パブリックコメント（1か月） | C66: 未着手 | D66: 素案の確定
A67: 令和9年2月下旬 | B67: **計画書の校了・下版（動かせない期限）** | C67: 未着手 | D67: パブコメ対応
A68: 令和9年3月31日 | B68: 納品（業務期間の末日） | C68: 未着手 | D68: 全成果品の完成

Sheet 01_WBS
A1: 段階 | B1: No | C1: 作業 | D1: 内容 | E1: 仕様書ブロック | F1: 仕様書 条項 | G1: 仕様書の記載内容（原文） | H1: 担当 | I1: 予定開始 | J1: 予定完了 | K1: 状態 | L1: 進捗率 | M1: 重み | N1: 実績・根拠 | O1: 前提条件・ブロッカー
A2: P1 準備・現状把握 | B2: 1-1 | C2: 契約・体制の確立、キックオフ | D2: 実施体制、役割分担、連絡系統 | E2: B10 業務管理・計画の基本的な考え方 | F2: 公告10⑥（技術者の配置） | G2: 【公告10⑥】研究員は「見える化」システムやニーズ調査など各種データから介護給付費の統計分析により将来のサービス量を推計し計画化できる者（公告第1-19号 10⑥） | H2: 受託者 | I2: 2026-06 | J2: 2026-07 | K2: 完了 | L2: 100 | M2: 2 | N2: キックオフ資料・業務計画書（02_キックオフ・業務計画） | O2: ―
A3: P1 準備・現状把握 | B3: 1-2 | C3: 引継ぎ資料の整理 | D3: 前受託者からの引継ぎ資料の棚卸しと索引化 | E3: B10 業務管理・計画の基本的な考え方 | F3: 仕様書全般 | G3: 【全般】委託仕様書及び公告の全体（成果品要件・工程・作業分担の確認） | H3: 受託者 | I3: 2026-07 | J3: 2026-07 | K3: 完了 | L3: 100 | M3: 2 | N3: manifest_全ファイル（207ファイル） | O3: ―
A4: P1 準備・現状把握 | B4: 1-3 | C4: 委託仕様書の確認と適合性チェック | D4: 原典4件（公告・仕様書×2計画）を読み、成果品要件・工程・作業分担を確定 | E4: B10 業務管理・計画の基本的な考え方 | F4: 仕様書全般 | G4: 【全般】委託仕様書及び公告の全体（成果品要件・工程・作業分担の確認） | H4: 受託者 | I4: 2026-08 | J4: 2026-08 | K4: 完了 | L4: 100 | M4: 3 | N4: 仕様書適合性チェック 第2版（00_引継ぎ）。初版8/3、第2版8/13 | O4: ―
A5: P1 準備・現状把握 | B5: 1-4 | C5: 第9期計画本文の確認 | D5: 5章構成・基本理念・3基本目標・14施策、標準給付費3,566,486千円、保険料6,600円の算定根拠 | E5: B1 現状分析（基礎データ・資料の整理分析） | F5: 仕様書4(1) | G5: 【4(1)】基礎的な地域データ及び資料の整理分析（現状分析）。高齢者福祉・介護保険をめぐる施策の動向、小野町の概要及び社会経済的特性、地域福祉資源の整備状況、高齢者の現況動向及びサービスの利用状況等について、小野町が提供するデータをもとに整理分析を行う。（計画策定の検討資料として活用するため、各種事項の将来推計を行う。なお、推計にあたっては、可能な限り細分化する） | H5: 受託者 | I5: 2026-08 | J5: 2026-08 | K5: 完了 | L5: 100 | M5: 3 | N5: 第9期計画本文（13_関連計画）。骨子案第3版・成果品①第5版に反映 | O5: ―
A6: P1 準備・現状把握 | B6: 1-5 | C6: 第3期地域福祉計画との役割分担の整理 | D6: 重複5施策を特定。成年後見は移管、虐待防止・災害対応・支え合いは連携 | E6: B10 業務管理・計画の基本的な考え方 | F6: 仕様書2(2) | G6: 【2(2)】国が示す第10期計画に関する基本的な考え方を踏まえた上で、本町の特性を活かした計画とする。 | H6: 受託者 | I6: 2026-08 | J6: 2026-08 | K6: 完了 | L6: 100 | M6: 2 | N6: 地域福祉計画との整合確認メモ（03_計画素案） | O6: ―
A7: P1 準備・現状把握 | B7: 1-6 | C7: 町への資料依頼票の作成 | D7: 依頼35項目＋確認事項12件。基準日・年度範囲・単位・様式まで指定 | E7: B10 業務管理・計画の基本的な考え方 | F7: 仕様書5(1)（資料は町が貸与） | G7: 【5(1)】本業務の実施に必要な資料等は、小野町が受託者に貸与するものとする。 | H7: 受託者 | I7: 2026-08 | J7: 2026-08 | K7: 完了 | L7: 100 | M7: 2 | N7: 小野町_データ依頼票（16_町データ依頼） | O7: ―
A8: P1 準備・現状把握 | B8: 1-7 | C8: 町データの受領 | D8: 依頼票に基づく資料・データの受領 | E8: B10 業務管理・計画の基本的な考え方 | F8: 仕様書5(1) | G8: 【5(1)】本業務の実施に必要な資料等は、小野町が受託者に貸与するものとする。 | H8: 町 | I8: 2026-08 | J8: 2026-09 | K8: 進行中 | L8: 70 | M8: 4 | N8: **9月8日に介護保険事業状況報告（年報）令和3〜7年度（各47様式）、国保連合会業務統計表（月報）28か月分、第10期将来推計用推計人口を受領。**依頼票のN1・S1〜S5が解決し、S7は令和6年度分のみ解決 | O8: 残るのは地域支援事業費の内訳（S6）、令和7年度決算（S7）、成果指標の現状値17項目（H1〜H17）
A9: P1 準備・現状把握 | B9: 1-8 | C9: 工程・協議会日程の合意と確認事項の照会 | D9: 高齢者計画の仕様書には工程表がないため、業務期間から逆算した工程と協議会の回数・時期を町と合意する。あわせて仕様書の疑義4件を照会する | E9: B10 業務管理・計画の基本的な考え方 | F9: 仕様書5(3) | G9: 【5(3)】本仕様書に定めのない事項及び疑義が生じた場合は、小野町と受託者で協議するものとする。 | H9: 受託者・町 | I9: 2026-08 | J9: 2026-09 | K9: 要対応 | L9: 30 | M9: 2 | N9: **工程変更協議資料と確認事項12件を作成済み（うち高齢者に係るもの8件）** | O9: **町との協議。協議会の回数が決まらないとP6・P8・P9・P10の日程が引けない**
A10: P2 統計分析 | B10: 2-1 | C10: 人口・世帯の分析 | D10: 総人口、高齢化率、前期・後期高齢者、世帯。令和32年まで推計 | E10: B2 統計分析 | F10: 仕様書4(1)①ア | G10: 【4(1)①ア】統計分析（ア）人口 | H10: 受託者 | I10: 2026-07 | J10: 2026-07 | K10: 完了 | L10: 100 | M10: 3 | N10: 基礎数値整理ブック（A系13ファイル） | O10: ―
A11: P2 統計分析 | B11: 2-2 | C11: 第1号被保険者の分析 | D11: 被保険者数の推移と推計 | E11: B2 統計分析 | F11: 仕様書4(1)①ア | G11: 【4(1)①ア】統計分析（ア）人口 | H11: 受託者 | I11: 2026-07 | J11: 2026-07 | K11: 完了 | L11: 100 | M11: 1 | N11: B系4ファイル | O11: ―
A12: P2 統計分析 | B12: 2-3 | C12: 認定者数・認定率の分析 | D12: 平成19年3月末〜令和8年3月末の20期。要介護度別7区分・年齢階層別・被保険者区分別 | E12: B2 統計分析 | F12: 仕様書4(1)①イ | G12: 【4(1)①イ】統計分析（イ）要支援者数、要介護認定者数、認知症高齢者数 | H12: 受託者 | I12: 2026-08 | J12: 2026-08 | K12: 完了 | L12: 100 | M12: 4 | N12: 要支援要介護認定者数の整理（07_見える化整理・10シート）。第1号＋第2号＝全体を20期で検算済み | O12: ―
A13: P2 統計分析 | B13: 2-4 | C13: 認定者数の異常値の検証 | D13: 令和8年3月末の▲152人（▲16.1％）の要因分析。県内59市町村との比較 | E13: B2 統計分析 | F13: 仕様書4(1)①イ | G13: 【4(1)①イ】統計分析（イ）要支援者数、要介護認定者数、認知症高齢者数 | H13: 受託者・町 | I13: 2026-08 | J13: 2026-10 | K13: 進行中 | L13: 85 | M13: 5 | N13: **792人は介護保険事業状況報告（年報）様式1の5で裏付けられた（第1号783＋第2号9）。**国保連月報28か月で、減少が令和7年9月審査分の1か月に集中していること（961→862人）と、同じ月に給付件数が減っていないこと（1,303→1,365件）を確認。減少は要介護2以上に集中し、要支援1は増えている。死亡171人は平年並み | O13: **「令和7年8〜9月に計上方法の変更がなかったか」に論点が絞られた。町外施設入所者の帰属、住所地特例、国保連の集計定義のいずれか**
... A38: P7 推計・算定 | B38: 7-3 | C38: 被保険者数・認定者数の推計 | D38: 人口推計に年齢階層別の認定率を乗じる自然体推計 | E38: B5 事業量推計・保険料算出・介護財政 | F38: 仕様書4(2) | G38: 【4(2)】サービス事業量推計、保険料の算出、介護財政の見通しの検討・調整。「見える化」システムを活用したサービス見込量を推計及び保険料の算出を行うこと。（「見える化」システムへの入力作業を含む。）なお、算定にあたっては、新たに介護施設を整備する場合や制度改正により条件が変わる場合等、様々なケースで勘案する必要があるため、想定されるケースごとに保険料の算定を行うものとする。 | H38: 受託者 | I38: 2026-09 | J38: 2026-10 | K38: 進行中 | L38: 40 | M38: 4 | N38: **算定シートに実績を投入済み。**第10期将来推計用推計人口（令和9〜11年）と、令和7年度の年齢階層別認定率（65〜74歳3.92％／75〜84歳18.72％／85歳以上71.63％）を入力した。85歳以上の認定率は令和6年度82.8％から11.2ポイント下がっている。**認定者数の見込みは令和9年度782人・令和10年度781人・令和11年度780人。見える化ワークシートの849人・850人・841人より8.4％低い。**見える化の基点は令和7年9月の865人（断層の直後）で、その後866人→794人へ減っていく動きを織り込んでいない。計画書には令和8年3月末の実績783人と接続する当方の系列を載せる。**なお見込量そのものへの影響は小さい。**見える化の見込量は第1号被保険者数×認定率×利用率の3段の掛け算で、利用率の分母は認定者数（在宅は認定者数から施設・居住系の利用者数を引いたもの）であり、認定率が高く出れば利用率が同じだけ低く出るため積は変わらない | O38: **認定率をどの水準で置くか（令和7年度実績か、計上変更前の令和6年度水準か）。2-4の確認結果しだいで前提が変わる。**あわせて、認定率の分子に第2号被保険者の認定者を含むかを見える化の画面で確認する（確認事項No.125）
A39: P7 推計・算定 | B39: 7-4 | C39: サービス見込量の推計 | D39: サービス種類別の利用者数・量・給付費 | E39: B5 事業量推計・保険料算出・介護財政 | F39: 仕様書4(2) | G39: 【4(2)】サービス事業量推計、保険料の算出、介護財政の見通しの検討・調整。「見える化」システムを活用したサービス見込量を推計及び保険料の算出を行うこと。（「見える化」システムへの入力作業を含む。）なお、算定にあたっては、新たに介護施設を整備する場合や制度改正により条件が変わる場合等、様々なケースで勘案する必要があるため、想定されるケースごとに保険料の算定を行うものとする。 | H39: 受託者 | I39: 2026-09 | J39: 2026-11 | K39: 完了 | L39: 100 | M39: 5 | N39: **サービス別単価・見込量試算（04_算定・見込量・10シート）を作成し、算定シートの05・06に投入済み。**年報 様式2から29区分の令和3〜7年度の件数・単位数・費用額・給付費を取り出し（正規化後の合計は様式2の総計と全年度一致）、第1号被保険者1人当たりの利用率で令和9〜11年度を試算した。総給付費は3年計3,048,418千円、標準給付費は3,286,398千円（第9期見込の92.1％）。**分母の変動係数は第1号被保険者数1.63％に対し認定者数5.18％で、認定者ベースだと基準期間が断層をまたぐため10.5％低く出る。****9月15日に、量と利用者数の水準を見える化ワークシートの令和7年度実績（給付実績情報の回数・受給者数）に切り替えた。**国保連月報の実日数を回数に読み替えていたため、訪問介護で26％、訪問看護で32％、回数を少なく見ていた。給付費は年報 様式2 のまま（施設サービスは月報・見える化の額に特定入所者介護サービス費が乗っているため採らない）。**サービス見込量（11シート）と算定結果（成果品②の素材）にまとめた** | O39: **基準期間の切替を月報の前年同期比で判定する形に改めた。**①令和7年度の件数が3年平均から5％以上離れ、②令和8年度の前年同期比がその向きを裏づけるサービスだけ令和7年度単年にする。訪問看護・介護予防通所リハビリテーション・介護予防福祉用具貸与・介護予防支援・認知症対応型共同生活介護（介護・予防）の6件が該当。判定は check_base() が月報から再計算し、07_基準期間の判定 に載せている | P39: **9月15日に、推計方法そのものをバックテストで検証した（推計方法のバックテスト・04_算定・見込量）。**令和5年度・令和6年度を起点に1〜2年先を予測し、実績との絶対誤差を給付費で加重して比べた。総給付費の誤差は、当方の方式（利用率・分母＝第1号被保険者数・窓3年）が3.31％で最も小さい。窓2年3.54％、分母を75歳以上とすると4.24％、直近年度の据え置き5.26％、全サービス一律の伸び5.28％、**大雪地区広域連合の手引きの偏り補正（φ0.5・上限±3％）は5.39％で一律に劣る。**同手引きの判定基準「一律より良いことを示せなければ補正しない」により採らない。分母を認定者数とすると6.39％で、起点年度によって2.20％〜9.60％と振れ幅が大きい | Q39: **9月24日に、他町村の手引きの14段階で自己点検した（見込量算定の手引き適合点検・04_算定・見込量）。**済んでいなかった6段階（内的整合・季節性・施策反映・趨勢外の要因・記載事項・自己点検）を埋めた。**新たに分かったことが3つある。**①**単価は報酬改定のない年でも年率＋1.09％伸びており、改定のあった令和6年度の＋1.25％と差がない。**当方は単価を令和7年度で固定しているため、実績の趨勢（年率＋1.13％）で置くと標準給付費が3.43％・保険料が月額211円上がる。固定は過小側の置き方である。②**季節性は、居宅・地域密着型が年度で向きが逆になり再現しない。**施設（冬季が高い）と受給者計（冬季が低い）は再現するが差は2％前後で向きが逆であり相殺される。基準年度が完結年度のため補正は不要。③**施策反映は、当方の式で変数になっているのが第1号被保険者数だけであり、成果指標40件のうち目標値が確定しているものが0件であるため、現時点で反映できるものがない。**歯止めを先に定めた。**自己点検12項目を算定に組み込み、変異試験3件すべてで止まることを確かめた。** | R39: **川崎町の方式（基準年度の要介護度別給付費に要介護度別の認定者数の伸びを乗じる）を小野町のデータで測った。**断層をまたがない令和5年度→令和6年度では誤差▲1.06％と全方式のなかで最も当たる一方、令和7年度を予測先に置く2通りでは▲14.66％・▲13.47％となり、3通りの平均では50設定中49位に落ちる。**令和6年度→令和7年度の認定者数は要介護4が0.755倍・要介護5が0.626倍で、給付費の実績が7.4％しか下がっていないのと合わない。**断層の原因が確認できるまでは採らない。解消すれば要介護度の構成の変化を織り込める点で当方より優れる可能性がある | S39: **9月24日に、地域支援事業の「量」の見込みを追加した（介護保険法117条2項2号。11_地域支援事業の量）。**費用の見込みとは別の必須記載事項であり、第9期計画にもなかった。国保連月報から量を出せるのは介護予防・生活支援サービス事業の3事業だけで、**一般介護予防事業・包括的支援事業・任意事業の13事業は町の事業実績を要する** | T39: **9月16日に、認知症基本法の点検にあわせて必要利用定員総数を追加した（介護保険法117条2項1号。10_必要利用定員総数）。**認知症対応型共同生活介護・地域密着型特定施設入居者生活介護・地域密着型介護老人福祉施設入所者生活介護の3サービスについて各年度の必要利用定員総数を定めることは**努力義務ではなく必須記載事項**であり、第9期計画にも当初の見込量算定にもなかった。**いずれも見込量に対し定員に余力があるため現行定員を維持する案（認知症対応型共同生活介護98人・地域密着型特養58人・地域密着型特定施設0人）** | U39: **9月25日に、令和8年度の置き方を4通りで比べ、国保連月報で裏づけた（12_令和8年度の置き方）。**令和7年度の実績に対する比は、据え置き1.0000／令和6→令和7の動きを1年延長0.9255／当方の現行方式1.0171／**月報3か月の実績0.9598**。**当方の現行方式は実績より6.0％高い。**令和5〜7年度の3年平均が、下がり続けている系列を上に引いているため。**9月25日に、この自然体推計ケースを標準ケースに切り替えた（素案 第5版、見込量の算定結果 令和8年9月25日版）。**令和8年度を月報の実績で置き、そこから人口で延ばす。総給付費の3年計は2,869,936千円（従前の方式から▲5.9％）、標準給付費3,093,948千円、保険料は月額6,048円（100円未満切上げで6,100円。第9期の6,600円から▲500円・▲7.6％）。**見える化システムの自然体推計と総額の置き方が同じであり、システムの出力と素案の数値が突き合う。**従前の方式（3年平均の伸び）によるケースは月額6,402円で、比較のケースとして残した。令和8年度は3か月分しかなく完結年度ではないため、残りの月の実績を見たうえで協議会にお諮りして確定する | V39: **認定者数の見込みを算式に置き換えた。**従前は785／782／781／780とハードコードしていたが、記載の方法（年齢階層別認定率×将来推計人口）で計算すると**787／782／777／772**となり、令和10・11年度で4人・8人ずれていた。**令和6年度→令和7年度の認定率の変化を一定として延ばす置き方は採れない。**65〜74歳▲1.38ポイント・75〜84歳▲1.66ポイント・85歳以上▲11.20ポイントで、毎年加えると令和10年度に65〜74歳の認定率が負になり、令和11年度の認定者数は329人まで落ちる。断層がこの変化に入っているため | W39: **報酬改定率（令和9年度）の確定。**あわせて、訪問介護の基準期間（3年平均だと令和9年度の見込件数が令和7年度実績の1.27倍。令和7年度単年なら月額▲47円）を協議会にお諮りする。**必要利用定員総数は、認知症対応型共同生活介護の定員が令和4年度71人から令和6年度98人へ増えた経緯と町外の方の利用割合を町に確認したうえで確定する。****あわせて、単価を令和7年度で固定していることを協議会にお諮りする（実績の趨勢で置くと月額＋211円）**
A40: P7 推計・算定 | B40: 7-5 | C40: 見える化システムへの入力作業 | D40: 将来推計機能への入力と総括表の出力。出力の分析だけでなく入力が業務に含まれる | E40: B5 事業量推計・保険料算出・介護財政 | F40: 仕様書4(2) | G40: 【4(2)】サービス事業量推計、保険料の算出、介護財政の見通しの検討・調整。「見える化」システムを活用したサービス見込量を推計及び保険料の算出を行うこと。（「見える化」システムへの入力作業を含む。）なお、算定にあたっては、新たに介護施設を整備する場合や制度改正により条件が変わる場合等、様々なケースで勘案する必要があるため、想定されるケースごとに保険料の算定を行うものとする。 | H40: 受託者 | I40: 2026-09 | J40: 2026-10 | K40: 要対応 | L40: 15 | M40: 3 | N40: **川崎町・金ケ崎町の両ブランチを確認し、入力時の設定と落とし穴を整理した（見込量算定の方針と不足資料・04_算定・見込量）。**①介護保険事業状況報告の設定で令和8年度のチェックを外す（外さないと令和8年5月の1か月が年度として扱われる）②伸びは令和6年度→令和7年度（完結年度どうし）③1人1月あたり給付費は令和7年度④**施策反映の3画面は編集せず通過する。**編集するとセルがピンクになり「自然体推計に全て戻す」が押せる状態になる。**この状態のまま総括表を出すと、伸びの窓を変えても見込量が動かない** | O40: **9月24日に、受領したワークシートを1行ずつ読んで入力値を確定した（見える化システム入力値一覧・入力の手順。11_見える化出力依頼）。****入力の前に直す設定が2件ある。**①1人1月あたり給付費の実績値が令和8年度になっている。令和8年度の列は1か月分で、人数・回数・日数の非ゼロ36件のうち31件（86.1％）が整数である（令和6年度は46件中5件、令和7年度は40件中8件で、いずれも12分の1単位の小数）。令和7年度に切り替える。②認定率の伸びが令和6年度→令和7年度になっている。**見える化の認定者数は各年9月末の値で、令和7年度の865人は令和7年9月の断層の直後にあたる。**令和6年度937人は国保連の令和6年10月審査分と一致し、令和7年度865人と令和8年度865人は同値で令和8年度に実績がないことを示す。計上方法の確認が取れるまでこの伸びは使えない。**入力欄は、当方で用意できるものが28欄、町の資料が要るものが26欄。**町の資料が要るのは一般介護予防事業5欄（計5,305千円）、包括的支援事業・任意事業8欄（計29,335千円）、審査支払手数料等2欄（計531千円）、準備基金、令和8年度の当初予算など。**所得段階別加入割合13段階を入れると調整交付金見込交付割合が自動で出るため、当方の算式値（令和9年度6.107％・令和10年度5.548％・令和11年度4.945％）と突き合わせる** | P40: **アカウント・権限・作業範囲・時期の確認（依頼票C5）。これが決まらないと総括表が出せず、対計画比・供給実現性の検証に進めない。****あわせて、令和7年8〜9月の認定者数の計上方法の確認が最優先。これが決まらないと認定率の伸びを置けない**
A41: P7 推計・算定 | B41: 7-6 | C41: 保険料のケース別算定 | D41: ケースC1〜C6ごとの保険料基準額の算定 | E41: B5 事業量推計・保険料算出・介護財政 | F41: 仕様書4(2) | G41: 【4(2)】サービス事業量推計、保険料の算出、介護財政の見通しの検討・調整。「見える化」システムを活用したサービス見込量を推計及び保険料の算出を行うこと。（「見える化」システムへの入力作業を含む。）なお、算定にあたっては、新たに介護施設を整備する場合や制度改正により条件が変わる場合等、様々なケースで勘案する必要があるため、想定されるケースごとに保険料の算定を行うものとする。 | H41: 受託者 | I41: 2026-10 | J41: 2026-11 | K41: 進行中 | L41: 80 | M41: 4 | N41: **所得段階別被保険者数（13段階）、小野町が定める保険料率（第1〜3段階は0.285／0.485／0.685で国の標準より低い）、収納率99.35％、基金保有額12,000千円を投入済み。地域支援事業費は年報 様式4 の令和6年度決算63,916千円（3年計191,749千円）を事業別に割り付けて投入した。総合事業の内訳は国保連月報の総合事業コード（A2・A6・AF）による。****9月25日に標準ケースを自然体推計に切り替え、あわせて所得段階別の割合を軽減前の標準割合に訂正した結果、保険料基準額は月額6,048円（基金取崩なし）、5,997円（保有額12,000千円を全額取崩）、5,808円（第9期と同じ35,000千円を取崩）となった。**第9期は6,600円。負担割合が24％になると6,364円。従前の方式（令和5〜7年度の3年平均の伸び）では6,402円であり、比較のケースとして残している。**9月25日に、保険料基準額の算定に用いる所得段階別の割合を軽減後の賦課割合（0.285／0.485／0.685）から軽減前の標準割合（0.455／0.685／0.690）に訂正した。**軽減相当額は別枠の公費（国1/2・県1/4・町1/4）で補填され、保険料収納必要額から控除されないためである。第9期計画の補正後被保険者数10,136人÷第1号被保険者数10,409人＝0.974も軽減前でしか再現できない（軽減後だと0.93台）。見える化システムの「①標準段階区分・割合」の画面でも0.4550／0.6850／0.6900が固定表示されることを同日の画面で確認した。**あわせて調整交付金の見込交付割合を、第9期からの逆算6.148％から算式（（第1号負担割合＋5％）－第1号負担割合×後期高齢者加入割合補正係数×所得段階別加入割合補正係数）による5.533％に改めた。**2つの訂正は互いに打ち消し合い、保険料基準額は月額115円下がった※ 逆算される調整交付金見込額219,272千円は基数の取り方によらない。見える化システムは標準給付費見込額のみを基数とするため6.148％、総合事業費を含めると5.963％となる（本件は前者にそろえた） | O41: **一般介護予防事業費と包括的支援事業・任意事業費の事業別内訳、令和7年度の決算額（年報が未入力）、調整交付金見込額、第10期の第1号被保険者負担割合。あわせて、第9期が見込んだ基金取崩35,000千円に対し基金保有額が12,000千円しかない点の確認が要る（しかも年報の残高の系列に矛盾がある）**
A42: P7 推計・算定 | B42: 7-7 | C42: サービス見込量推計結果報告書の作成 | D42: 成果品②の本体 | E42: B9 成果品の納品 | F42: 仕様書4 成果品② | G42: 【成果品②】（2）サービス見込量推計結果報告書 ※データ（CD-R）1部、冊子（簡易製本）3部 | H42: 受託者 | I42: 2026-11 | J42: 2026-12 | K42: 進行中 | L42: 60 | M42: 4 | N42: **サービス見込量の算定結果（04_算定・見込量・10章・11表）を作成した。**算定の方法、基準期間の置き方、サービス見込量、給付費と標準給付費、地域支援事業費、供給実現性（定員との突合）、保険料の試算、据え置いた前提と動く幅、町への確認事項までを収めている | O42: **報酬改定率と第1号被保険者負担割合が確定したら数値を差し替える。**あわせて、協議会での議論を踏まえた記述の追加
A43: P7 推計・算定 | B43: 7-8 | C43: 成果品②の製本・納品 | D43: データCD-R1部＋冊子（簡易製本）3部 | E43: B9 成果品の納品 | F43: 仕様書4 成果品② | G43: 【成果品②】（2）サービス見込量推計結果報告書 ※データ（CD-R）1部、冊子（簡易製本）3部 | H43: 受託者 | I43: 2027-03 | J43: 2027-03 | K43: 未着手 | L43: 0 | M43: 1 | N43: ― | O43: 報告書の確定
A44: P8 素案 | B44: 8-1 | C44: 素案の作成 | D44: 骨子案を踏まえた計画素案。12施策の本文 | E44: B6 骨子案・素案の作成 | F44: 仕様書4(3)・成果品④ | G44: 【4(3)】骨子案・素案の作成。これまでの調査結果を踏まえて第10期計画の基本課題や施策方向を整理し、今後の重点課題と施策の目標・体系をとりまとめた計画骨子案、計画素案を作成し、内容の協議を行う。策定にあたっては町総合計画、町地域福祉計画等の既存計画の関連も調整すること。 【成果品④】（4）小野町高齢者保健福祉計画・第10期介護保険事業計画素案 ※データ（CD-R）1部、冊子（簡易製本）3部 | H44: 受託者 | I44: 2026-08 | J44: 2026-12 | K44: 進行中 | L44: 85 | M44: 5 | N44: **第5版（5章＋資料編・74表）。**12施策すべてに現状と課題・施策の方向・主な事業・成果指標を記載。**第2版の未確定158箇所のうち61箇所が解消し97箇所となった。**第2章6（被保険者数・認定者数の見込み）を第10期将来推計用推計人口で確定し、第4章③にサービス見込量・給付費・標準給付費・地域支援事業費の事業別内訳・保険料基準額を入れた。**第5版（9月25日）で令和8年度の置き方を自然体推計に改め、保険料基準額は月額6,402円から6,048円（切上げ6,100円）となった。****9月25日の再検証で、延ばし方を見える化システムの仕様にそろえた**（施設は利用者数一定、居住系・在宅は認定者数で延ばす。月額▲13円）。従前の方式による算定は比較のケースとして残している。**第5章2の進行管理に、保険者機能強化推進交付金等の評価結果を点検項目として加えた**（評価結果を外部の議論の場で検証すること自体が評価指標の要件であるため） | O44: **9月24日に、受託者が算定すべき未確定箇所をすべて解消した。**所得段階別保険料率を13段階すべてについて算定し（乗率・年額・被保険者数・構成比）、必要利用定員総数・地域支援事業の量・認知症高齢者数を加えた。**未確定は158箇所→94箇所となり、【算定後に記載】は0件になった。****あわせて数値の誤りを2件正した。**①所得第2段階の乗率を年報 様式1 所得段階別の令和7年度の値により0.486としたが、**これは誤りで0.485が正しい**（9月25日に再訂正）。第9期計画本文が「基準額×0.485」「年額38,500円」と明記しており、79,200円×0.485＝38,412円の100円未満切上げで38,500円になる。年報の令和6年度は485であり、令和7年度の486が入力誤りである。②所得第1〜3段階の割合を28％としていたが、1,094人÷3,443人で31.8％が正しい。**第2章1の人口（見える化の将来推計・暦年）と第2章6の被保険者数（第10期将来推計用推計人口・年度）が別系列であることを注記した。**従前の注は「保険料算定との整合のため見える化の推計を用いる」と書いていたが、保険料算定は後者を用いており誤りであった | P44: **残る94箇所の内訳は、協議会で設定する目標値39、町データ待ち39、町・国の決定12、見える化出力4。****受託者の算定によるものは残っていない。**町データ待ちの筆頭は成果指標の現状値、一般介護予防事業費・包括的支援事業・任意事業費の事業別内訳、地域支援事業の量（13事業）、認知症対応型共同生活介護の増床の経緯**
A45: P8 素案 | B45: 8-2 | C45: 成果指標の目標値案の作成 | D45: 40指標の目標値案と根拠の型 | E45: B6 骨子案・素案の作成 | F45: 仕様書4(3) | G45: 【4(3)】骨子案・素案の作成。これまでの調査結果を踏まえて第10期計画の基本課題や施策方向を整理し、今後の重点課題と施策の目標・体系をとりまとめた計画骨子案、計画素案を作成し、内容の協議を行う。策定にあたっては町総合計画、町地域福祉計画等の既存計画の関連も調整すること。 | H45: 受託者 | I45: 2026-08 | J45: 2026-08 | K45: 完了 | L45: 100 | M45: 3 | N45: **成果指標目標値案（03_計画素案・40指標）。**現状値が未受領の20指標は算定規則として案を置いた | O45: ―
A46: P8 素案 | B46: 8-3 | C46: 認知症施策推進基本計画の包含方針 | D46: 基本的施策12項目との対応表、包含の形式 | E46: B10 業務管理・計画の基本的な考え方 | F46: 仕様書2(3) | G46: 【2(3)】国の「認知症施策推進基本計画」に基づく市町村計画も包含する計画とする。 | H46: 受託者 | I46: 2026-08 | J46: 2026-08 | K46: 完了 | L46: 100 | M46: 2 | N46: 計画策定業務設計書 第1章（02_キックオフ・業務計画）。分散＋対応表方式を提案。**9月16日に認知症基本法の条文により市町村計画の根拠を第13条第1項（努力義務）、調和規定を第2項、策定手続（意見聴取・公表・評価・5年ごとの検討）を第3項が準用する第12条第3〜7項と確定し、素案に反映した（認知症基本法への対応の点検・03_計画素案）。****施策の柱を認知症施策推進大綱の5本柱から法の基本的施策（第14〜21条）に組み替え、大綱では落ちていた若年性認知症・移動のための交通手段の確保・消費生活被害の防止・孤立の防止を追加した。**北塩原村の法定記載事項チェックと川崎町の骨子案を参照している | O46: **認知症の人及びその家族等の意見をどう聴くか（同法13条3項→12条3項）。記述の追加では埋まらず策定過程に関わるため、協議会の委員構成を確認したうえで家族会・認知症カフェでの意見聴取の機会を設けるかを町と協議する。**あわせて福島県の認知症施策推進計画の策定状況、町の意思決定（方式A／B）
A47: P8 素案 | B47: 8-4 | C47: 見込量・保険料・成果指標の反映 | D47: 素案の未確定156箇所の解消 | E47: B6 骨子案・素案の作成 | F47: 仕様書4(3) | G47: 【4(3)】骨子案・素案の作成。これまでの調査結果を踏まえて第10期計画の基本課題や施策方向を整理し、今後の重点課題と施策の目標・体系をとりまとめた計画骨子案、計画素案を作成し、内容の協議を行う。策定にあたっては町総合計画、町地域福祉計画等の既存計画の関連も調整すること。 | H47: 受託者 | I47: 2026-11 | J47: 2026-12 | K47: 未着手 | L47: 0 | M47: 4 | N47: ― | O47: **P7の完了、町データの受領**
A48: P8 素案 | B48: 8-5 | C48: 素案の協議（協議会） | D48: 素案の内容の合意 | E48: B6 骨子案・素案の作成 | F48: 仕様書4(3)・4(5) | G48: 【4(3)】骨子案・素案の作成。これまでの調査結果を踏まえて第10期計画の基本課題や施策方向を整理し、今後の重点課題と施策の目標・体系をとりまとめた計画骨子案、計画素案を作成し、内容の協議を行う。策定にあたっては町総合計画、町地域福祉計画等の既存計画の関連も調整すること。 【4(5)】高齢者福祉サービス推進協議会、パブリックコメントの支援。小野町高齢者福祉サービス推進協議会の開催及びパブリックコメントの実施について、資料の作成と運営・実施の支援を行うものとする。 | H48: 受託者・町 | I48: 2026-12 | J48: 2026-12 | K48: 未着手 | L48: 0 | M48: 2 | N48: ― | O48: 協議会の開催時期
A49: P8 素案 | B49: 8-6 | C49: 成果品④の製本・納品 | D49: データCD-R1部＋冊子（簡易製本）3部 | E49: B9 成果品の納品 | F49: 仕様書4 成果品④ | G49: 【成果品④】（4）小野町高齢者保健福祉計画・第10期介護保険事業計画素案 ※データ（CD-R）1部、冊子（簡易製本）3部 | H49: 受託者 | I49: 2027-03 | J49: 2027-03 | K49: 未着手 | L49: 0 | M49: 1 | N49: ― | O49: 素案の確定
A50: P9 意見聴取 | B50: 9-1 | C50: 協議会の開催回数・時期の確定 | D50: 小野町高齢者福祉サービス推進協議会 | E50: B8 協議会・パブリックコメントの支援 | F50: 仕様書4(5) | G50: 【4(5)】高齢者福祉サービス推進協議会、パブリックコメントの支援。小野町高齢者福祉サービス推進協議会の開催及びパブリックコメントの実施について、資料の作成と運営・実施の支援を行うものとする。 | H50: 町 | I50: 2026-08 | J50: 2026-08 | K50: 要対応 | L50: 0 | M50: 1 | N50: **仕様書に回数の指定がない。**受託者案は4回 | O50: **町との協議（依頼票C4）。これが決まらないと工程が引けない**
A51: P9 意見聴取 | B51: 9-2 | C51: 協議会 第1回（第9期の評価・調査結果） | D51: 評価と調査結果の報告 | E51: B8 協議会・パブリックコメントの支援 | F51: 仕様書4(5) | G51: 【4(5)】高齢者福祉サービス推進協議会、パブリックコメントの支援。小野町高齢者福祉サービス推進協議会の開催及びパブリックコメントの実施について、資料の作成と運営・実施の支援を行うものとする。 | H51: 受託者・町 | I51: 2026-08 | J51: 2026-09 | K51: 要対応 | L51: 50 | M51: 2 | N51: **資料は作成済み（08_協議会資料・42表）** | O51: **開催日が未定**
A52: P9 意見聴取 | B52: 9-3 | C52: 協議会 第2回（骨子案・見込量・保険料・成果指標） | D52: 計画の骨格の合意 | E52: B8 協議会・パブリックコメントの支援 | F52: 仕様書4(5) | G52: 【4(5)】高齢者福祉サービス推進協議会、パブリックコメントの支援。小野町高齢者福祉サービス推進協議会の開催及びパブリックコメントの実施について、資料の作成と運営・実施の支援を行うものとする。 | H52: 受託者・町 | I52: 2026-11 | J52: 2026-11 | K52: 未着手 | L52: 0 | M52: 2 | N52: 骨子案第3版・成果指標目標値案は作成済み | O52: P7の完了、開催日の確定
A53: P9 意見聴取 | B53: 9-4 | C53: 協議会 第3回（素案） | D53: 素案の合意 | E53: B8 協議会・パブリックコメントの支援 | F53: 仕様書4(5) | G53: 【4(5)】高齢者福祉サービス推進協議会、パブリックコメントの支援。小野町高齢者福祉サービス推進協議会の開催及びパブリックコメントの実施について、資料の作成と運営・実施の支援を行うものとする。 | H53: 受託者・町 | I53: 2026-12 | J53: 2026-12 | K53: 未着手 | L53: 0 | M53: 2 | N53: ― | O53: 素案の確定
A54: P9 意見聴取 | B54: 9-5 | C54: パブリックコメントの様式作成 | D54: 実施要領、意見提出様式、意見と町の考え方の対応表 | E54: B8 協議会・パブリックコメントの支援 | F54: 仕様書4(5) | G54: 【4(5)】高齢者福祉サービス推進協議会、パブリックコメントの支援。小野町高齢者福祉サービス推進協議会の開催及びパブリックコメントの実施について、資料の作成と運営・実施の支援を行うものとする。 | H54: 受託者 | I54: 2026-08 | J54: 2026-08 | K54: 完了 | L54: 100 | M54: 2 | N54: 計画策定業務設計書 第4章（02_キックオフ・業務計画） | O54: ―
A55: P9 意見聴取 | B55: 9-6 | C55: パブリックコメントの実施 | D55: 意見提出期間1か月 | E55: B8 協議会・パブリックコメントの支援 | F55: 仕様書4(5) | G55: 【4(5)】高齢者福祉サービス推進協議会、パブリックコメントの支援。小野町高齢者福祉サービス推進協議会の開催及びパブリックコメントの実施について、資料の作成と運営・実施の支援を行うものとする。 | H55: 町 | I55: 2027-01 | J55: 2027-01 | K55: 未着手 | L55: 0 | M55: 2 | N55: ― | O55: 素案の確定、実施時期の確定（依頼票C6）
A56: P9 意見聴取 | B56: 9-7 | C56: 意見への対応 | D56: 意見の整理、対応案の作成、計画への反映 | E56: B8 協議会・パブリックコメントの支援 | F56: 仕様書4(5) | G56: 【4(5)】高齢者福祉サービス推進協議会、パブリックコメントの支援。小野町高齢者福祉サービス推進協議会の開催及びパブリックコメントの実施について、資料の作成と運営・実施の支援を行うものとする。 | H56: 受託者 | I56: 2027-02 | J56: 2027-02 | K56: 未着手 | L56: 0 | M56: 2 | N56: 対応表の様式は作成済み | O56: パブコメの実施
... A65: P10 完成・納品 | B65: 10-8 | C65: 納品・検収 | D65: 令和9年3月31日まで | E65: B10 業務管理・計画の基本的な考え方 | F65: 仕様書3（業務期間） | G65: 【3】契約締結の日から令和9年3月31日まで | H65: 受託者・町 | I65: 2027-03 | J65: 2027-03 | K65: 未着手 | L65: 0 | M65: 1 | N65: ― | O65: 全成果品の完成

Sheet 02_段階サマリ
A1: 段階 | B1: 作業数 | C1: 完了 | D1: 進行中 | E1: 要対応 | F1: データ待ち | G1: 未着手 | H1: 加重進捗率 | I1: 予定開始 | J1: 予定完了 | K1: 律速要因
A2: P1 準備・現状把握 | B2: =COUNTIF('01_WBS'!$A$2:$A$65,$A2) | C2: =COUNTIFS('01_WBS'!$A$2:$A$65,$A2,'01_WBS'!$K$2:$K$65,"完了") | D2: =COUNTIFS('01_WBS'!$A$2:$A$65,$A2,'01_WBS'!$K$2:$K$65,"進行中") | E2: =COUNTIFS('01_WBS'!$A$2:$A$65,$A2,'01_WBS'!$K$2:$K$65,"要対応") | F2: =COUNTIFS('01_WBS'!$A$2:$A$65,$A2,'01_WBS'!$K$2:$K$65,"データ待ち") | G2: =COUNTIFS('01_WBS'!$A$2:$A$65,$A2,'01_WBS'!$K$2:$K$65,"未着手") | H2: =IF(SUMPRODUCT(('01_WBS'!$A$2:$A$65=$A2)*'01_WBS'!$M$2:$M$65)=0,0,SUMPRODUCT(('01_WBS'!$A$2:$A$65=$A2)*'01_WBS'!$L$2:$L$65*'01_WBS'!$M$2:$M$65)/SUMPRODUCT(('01_WBS'!$A$2:$A$65=$A2)*'01_WBS'!$M$2:$M$65)/100) | I2: 2026-06 | J2: 2026-09 | K2: 町データの受領（依頼35件・受領0件）
A3: P2 統計分析 | B3: =COUNTIF('01_WBS'!$A$2:$A$65,$A3) | C3: =COUNTIFS('01_WBS'!$A$2:$A$65,$A3,'01_WBS'!$K$2:$K$65,"完了") | D3: =COUNTIFS('01_WBS'!$A$2:$A$65,$A3,'01_WBS'!$K$2:$K$65,"進行中") | E3: =COUNTIFS('01_WBS'!$A$2:$A$65,$A3,'01_WBS'!$K$2:$K$65,"要対応") | F3: =COUNTIFS('01_WBS'!$A$2:$A$65,$A3,'01_WBS'!$K$2:$K$65,"データ待ち") | G3: =COUNTIFS('01_WBS'!$A$2:$A$65,$A3,'01_WBS'!$K$2:$K$65,"未着手") | H3: =IF(SUMPRODUCT(('01_WBS'!$A$2:$A$65=$A3)*'01_WBS'!$M$2:$M$65)=0,0,SUMPRODUCT(('01_WBS'!$A$2:$A$65=$A3)*'01_WBS'!$L$2:$L$65*'01_WBS'!$M$2:$M$65)/SUMPRODUCT(('01_WBS'!$A$2:$A$65=$A3)*'01_WBS'!$M$2:$M$65)/100) | I3: 2026-07 | J3: 2026-11 | K3: **令和8年3月末の認定者数の確認。本業務の最大の律速**
A4: P3 給付費等の分析 | B4: =COUNTIF('01_WBS'!$A$2:$A$65,$A4) | C4: =COUNTIFS('01_WBS'!$A$2:$A$65,$A4,'01_WBS'!$K$2:$K$65,"完了") | D4: =COUNTIFS('01_WBS'!$A$2:$A$65,$A4,'01_WBS'!$K$2:$K$65,"進行中") | E4: =COUNTIFS('01_WBS'!$A$2:$A$65,$A4,'01_WBS'!$K$2:$K$65,"要対応") | F4: =COUNTIFS('01_WBS'!$A$2:$A$65,$A4,'01_WBS'!$K$2:$K$65,"データ待ち") | G4: =COUNTIFS('01_WBS'!$A$2:$A$65,$A4,'01_WBS'!$K$2:$K$65,"未着手") | H4: =IF(SUMPRODUCT(('01_WBS'!$A$2:$A$65=$A4)*'01_WBS'!$M$2:$M$65)=0,0,SUMPRODUCT(('01_WBS'!$A$2:$A$65=$A4)*'01_WBS'!$L$2:$L$65*'01_WBS'!$M$2:$M$65)/SUMPRODUCT(('01_WBS'!$A$2:$A$65=$A4)*'01_WBS'!$M$2:$M$65)/100) | I4: 2026-07 | J4: 2027-03 | K4: 町の給付実績（令和3〜7年度）
A5: P4 調査結果の反映 | B5: =COUNTIF('01_WBS'!$A$2:$A$65,$A5) | C5: =COUNTIFS('01_WBS'!$A$2:$A$65,$A5,'01_WBS'!$K$2:$K$65,"完了") | D5: =COUNTIFS('01_WBS'!$A$2:$A$65,$A5,'01_WBS'!$K$2:$K$65,"進行中") | E5: =COUNTIFS('01_WBS'!$A$2:$A$65,$A5,'01_WBS'!$K$2:$K$65,"要対応") | F5: =COUNTIFS('01_WBS'!$A$2:$A$65,$A5,'01_WBS'!$K$2:$K$65,"データ待ち") | G5: =COUNTIFS('01_WBS'!$A$2:$A$65,$A5,'01_WBS'!$K$2:$K$65,"未着手") | H5: =IF(SUMPRODUCT(('01_WBS'!$A$2:$A$65=$A5)*'01_WBS'!$M$2:$M$65)=0,0,SUMPRODUCT(('01_WBS'!$A$2:$A$65=$A5)*'01_WBS'!$L$2:$L$65*'01_WBS'!$M$2:$M$65)/SUMPRODUCT(('01_WBS'!$A$2:$A$65=$A5)*'01_WBS'!$M$2:$M$65)/100) | I5: 2026-08 | J5: 2026-10 | K5: 令和7年度調査の個票データ（クロス集計17件）
A6: P5 第9期の評価 | B6: =COUNTIF('01_WBS'!$A$2:$A$65,$A6) | C6: =COUNTIFS('01_WBS'!$A$2:$A$65,$A6,'01_WBS'!$K$2:$K$65,"完了") | D6: =COUNTIFS('01_WBS'!$A$2:$A$65,$A6,'01_WBS'!$K$2:$K$65,"進行中") | E6: =COUNTIFS('01_WBS'!$A$2:$A$65,$A6,'01_WBS'!$K$2:$K$65,"要対応") | F6: =COUNTIFS('01_WBS'!$A$2:$A$65,$A6,'01_WBS'!$K$2:$K$65,"データ待ち") | G6: =COUNTIFS('01_WBS'!$A$2:$A$65,$A6,'01_WBS'!$K$2:$K$65,"未着手") | H6: =IF(SUMPRODUCT(('01_WBS'!$A$2:$A$65=$A6)*'01_WBS'!$M$2:$M$65)=0,0,SUMPRODUCT(('01_WBS'!$A$2:$A$65=$A6)*'01_WBS'!$L$2:$L$65*'01_WBS'!$M$2:$M$65)/SUMPRODUCT(('01_WBS'!$A$2:$A$65=$A6)*'01_WBS'!$M$2:$M$65)/100) | I6: 2026-08 | J6: 2026-10 | K6: 町の事業実績。とくに総合事業・通いの場
A7: P6 骨子案 | B7: =COUNTIF('01_WBS'!$A$2:$A$65,$A7) | C7: =COUNTIFS('01_WBS'!$A$2:$A$65,$A7,'01_WBS'!$K$2:$K$65,"完了") | D7: =COUNTIFS('01_WBS'!$A$2:$A$65,$A7,'01_WBS'!$K$2:$K$65,"進行中") | E7: =COUNTIFS('01_WBS'!$A$2:$A$65,$A7,'01_WBS'!$K$2:$K$65,"要対応") | F7: =COUNTIFS('01_WBS'!$A$2:$A$65,$A7,'01_WBS'!$K$2:$K$65,"データ待ち") | G7: =COUNTIFS('01_WBS'!$A$2:$A$65,$A7,'01_WBS'!$K$2:$K$65,"未着手") | H7: =IF(SUMPRODUCT(('01_WBS'!$A$2:$A$65=$A7)*'01_WBS'!$M$2:$M$65)=0,0,SUMPRODUCT(('01_WBS'!$A$2:$A$65=$A7)*'01_WBS'!$L$2:$L$65*'01_WBS'!$M$2:$M$65)/SUMPRODUCT(('01_WBS'!$A$2:$A$65=$A7)*'01_WBS'!$M$2:$M$65)/100) | I7: 2026-07 | J7: 2027-03 | K7: 協議会の開催回数・時期が未定
A8: P7 推計・算定 | B8: =COUNTIF('01_WBS'!$A$2:$A$65,$A8) | C8: =COUNTIFS('01_WBS'!$A$2:$A$65,$A8,'01_WBS'!$K$2:$K$65,"完了") | D8: =COUNTIFS('01_WBS'!$A$2:$A$65,$A8,'01_WBS'!$K$2:$K$65,"進行中") | E8: =COUNTIFS('01_WBS'!$A$2:$A$65,$A8,'01_WBS'!$K$2:$K$65,"要対応") | F8: =COUNTIFS('01_WBS'!$A$2:$A$65,$A8,'01_WBS'!$K$2:$K$65,"データ待ち") | G8: =COUNTIFS('01_WBS'!$A$2:$A$65,$A8,'01_WBS'!$K$2:$K$65,"未着手") | H8: =IF(SUMPRODUCT(('01_WBS'!$A$2:$A$65=$A8)*'01_WBS'!$M$2:$M$65)=0,0,SUMPRODUCT(('01_WBS'!$A$2:$A$65=$A8)*'01_WBS'!$L$2:$L$65*'01_WBS'!$M$2:$M$65)/SUMPRODUCT(('01_WBS'!$A$2:$A$65=$A8)*'01_WBS'!$M$2:$M$65)/100) | I8: 2026-08 | J8: 2027-03 | K8: **認定者数の確定。算式は実装済みで、値が入れば通る**
A9: P8 素案 | B9: =COUNTIF('01_WBS'!$A$2:$A$65,$A9) | C9: =COUNTIFS('01_WBS'!$A$2:$A$65,$A9,'01_WBS'!$K$2:$K$65,"完了") | D9: =COUNTIFS('01_WBS'!$A$2:$A$65,$A9,'01_WBS'!$K$2:$K$65,"進行中") | E9: =COUNTIFS('01_WBS'!$A$2:$A$65,$A9,'01_WBS'!$K$2:$K$65,"要対応") | F9: =COUNTIFS('01_WBS'!$A$2:$A$65,$A9,'01_WBS'!$K$2:$K$65,"データ待ち") | G9: =COUNTIFS('01_WBS'!$A$2:$A$65,$A9,'01_WBS'!$K$2:$K$65,"未着手") | H9: =IF(SUMPRODUCT(('01_WBS'!$A$2:$A$65=$A9)*'01_WBS'!$M$2:$M$65)=0,0,SUMPRODUCT(('01_WBS'!$A$2:$A$65=$A9)*'01_WBS'!$L$2:$L$65*'01_WBS'!$M$2:$M$65)/SUMPRODUCT(('01_WBS'!$A$2:$A$65=$A9)*'01_WBS'!$M$2:$M$65)/100) | I9: 2026-08 | J9: 2027-03 | K9: P7の完了と成果指標の現状値
A10: P9 意見聴取 | B10: =COUNTIF('01_WBS'!$A$2:$A$65,$A10) | C10: =COUNTIFS('01_WBS'!$A$2:$A$65,$A10,'01_WBS'!$K$2:$K$65,"完了") | D10: =COUNTIFS('01_WBS'!$A$2:$A$65,$A10,'01_WBS'!$K$2:$K$65,"進行中") | E10: =COUNTIFS('01_WBS'!$A$2:$A$65,$A10,'01_WBS'!$K$2:$K$65,"要対応") | F10: =COUNTIFS('01_WBS'!$A$2:$A$65,$A10,'01_WBS'!$K$2:$K$65,"データ待ち") | G10: =COUNTIFS('01_WBS'!$A$2:$A$65,$A10,'01_WBS'!$K$2:$K$65,"未着手") | H10: =IF(SUMPRODUCT(('01_WBS'!$A$2:$A$65=$A10)*'01_WBS'!$M$2:$M$65)=0,0,SUMPRODUCT(('01_WBS'!$A$2:$A$65=$A10)*'01_WBS'!$L$2:$L$65*'01_WBS'!$M$2:$M$65)/SUMPRODUCT(('01_WBS'!$A$2:$A$65=$A10)*'01_WBS'!$M$2:$M$65)/100) | I10: 2026-08 | J10: 2027-02 | K10: **協議会の開催回数・時期が未定。工程が引けない**
A11: P10 完成・納品 | B11: =COUNTIF('01_WBS'!$A$2:$A$65,$A11) | C11: =COUNTIFS('01_WBS'!$A$2:$A$65,$A11,'01_WBS'!$K$2:$K$65,"完了") | D11: =COUNTIFS('01_WBS'!$A$2:$A$65,$A11,'01_WBS'!$K$2:$K$65,"進行中") | E11: =COUNTIFS('01_WBS'!$A$2:$A$65,$A11,'01_WBS'!$K$2:$K$65,"要対応") | F11: =COUNTIFS('01_WBS'!$A$2:$A$65,$A11,'01_WBS'!$K$2:$K$65,"データ待ち") | G11: =COUNTIFS('01_WBS'!$A$2:$A$65,$A11,'01_WBS'!$K$2:$K$65,"未着手") | H11: =IF(SUMPRODUCT(('01_WBS'!$A$2:$A$65=$A11)*'01_WBS'!$M$2:$M$65)=0,0,SUMPRODUCT(('01_WBS'!$A$2:$A$65=$A11)*'01_WBS'!$L$2:$L$65*'01_WBS'!$M$2:$M$65)/SUMPRODUCT(('01_WBS'!$A$2:$A$65=$A11)*'01_WBS'!$M$2:$M$65)/100) | I11: 2026-08 | J11: 2027-03 | K11: 令和9年2月下旬の校了が動かせない期限
A12: 合計 | B12: =SUM(B2:B11) | C12: =SUM(C2:C11) | D12: =SUM(D2:D11) | E12: =SUM(E2:E11) | F12: =SUM(F2:F11) | G12: =SUM(G2:G11) | H12: =IF(SUM('01_WBS'!$M$2:$M$65)=0,0,SUMPRODUCT('01_WBS'!$L$2:$L$65,'01_WBS'!$M$2:$M$65)/SUM('01_WBS'!$M$2:$M$65)/100) | I12: 2026-06 | J12: 2027-03
A14: ※ 加重進捗率＝Σ（進捗率×重み）÷Σ重み。重みは工数の目安（1〜5）。
A15: ※ 各作業が仕様書のどの条項にあたるかは 01_WBS のE列・F列、条項の網羅状況は 09_仕様書対応表 を参照。
A16: ※ 01_WBS の「状態」「進捗率」を書き換えると、本表とダッシュボードが再計算されます。

Sheet 03_成果品管理
A1: 成果品 | B1: 名称 | C1: 納品仕様 | D1: 版 | E1: 状態 | F1: 進捗率 | G1: 現状 | H1: 確定に必要なもの
A2: ① | B2: 介護保険給付費等分析結果報告書 | C2: データCD-R1部＋冊子（簡易製本）3部 | D2: 第5版 | E2: 進行中 | F2: 70 | G2: 8章・44表・約29,500字 | H2: 町の給付実績、認定者数の確定
A3: ② | B3: サービス見込量推計結果報告書 | C3: データCD-R1部＋冊子（簡易製本）3部 | D3: ― | E3: 進行中 | F3: 20 | G3: 算定シート（11シート・算式実装済み）を構築。報告書本体は未着手 | H3: 認定者数の確定、見える化への入力
A4: ③ | B4: 第10期計画 骨子案 | C4: データCD-R1部＋冊子（簡易製本）3部 | D4: 第3版 | E4: 進行中 | F4: 80 | G4: 13表・9,241字。第9期の5章構成・3基本目標・14施策を反映 | H4: 協議会での合意
A5: ④ | B5: 第10期計画 素案 | C5: データCD-R1部＋冊子（簡易製本）3部 | D5: 第2版 | E5: 進行中 | F5: 65 | G5: 5章＋資料編・67表・約32,000字。未確定156箇所を5区分で明示 | H5: 見込量・保険料、成果指標の現状値、協議会での合意
A6: ⑤ | B6: 第10期計画 | C6: データCD-R1部、印刷50部（A4・4色刷り・80頁程度） | D6: ― | E6: 未着手 | F6: 0 | G6: ― | H6: 素案の確定、パブコメ、印刷工程
A7: ⑥ | B7: 第10期計画 概要版 | C7: データCD-R1部、印刷50部（A4・4色刷り・8頁） | D7: ― | E7: 未着手 | F7: 5 | G7: 構成案（8頁のページ割り）は作成済み | H7: 計画書の確定
A8: ※ 進捗率は目安。納品仕様（製本・印刷）を満たして初めて完了となる。

Sheet 04_工程表
A1: 時期 | B1: 作業 | C1: 担当 | D1: 状態 | E1: 備考
A2: 2026-08 | B2: 町データの照会（依頼票の送付） | C2: 受託者 | D2: 要対応 | E2: **認定者数の確認を含む。最優先**
A3: 2026-08〜09 | B3: 協議会 第1回（第9期の評価・調査結果） | C3: 受託者・町 | D3: 要対応 | E3: 資料は作成済み。**開催日が未定**
A4: 2026-09 | B4: 見える化 優先度C分野の出力 | C4: 受託者 | D4: 未着手 | E4: ―
A5: 2026-10 | B5: 認定者数の確定、見込量の推計、見える化への入力 | C5: 受託者 | D5: 未着手 | E5: **本業務の最大の節目**
A6: 2026-11 | B6: 保険料のケース別算定、協議会 第2回（骨子案・見込量・保険料・成果指標） | C6: 受託者・町 | D6: 未着手 | E6: ―
A7: 2026-12 | B7: 素案の確定、協議会 第3回（素案） | C7: 受託者・町 | D7: 未着手 | E7: ―
A8: 2027-01 | B8: パブリックコメント（1か月） | C8: 町 | D8: 未着手 | E8: ―
A9: 2027-02 | B9: 意見への対応、協議会 第4回（最終案）、**計画書の校了・下版** | C9: 受託者・町 | D9: 未着手 | E9: **2月下旬の校了が動かせない期限**
A10: 2027-03 | B10: 印刷・製本、概要版の作成、納品 | C10: 受託者 | D10: 未着手 | E10: 計画書50部・概要版50部・簡易製本各3部

Sheet 05_資料・データ受領
A1: No | B1: 資料・データ | C1: 提供元 | D1: 状態 | E1: 受領日 | F1: 使途・備考
A2: 町資料 | B2: **介護保険事業状況報告（年報）令和3〜7年度（各47様式）** | C2: 町 | D2: 完了 | E2: 2026-09-08 | F2: **認定者数（様式1の5）・被保険者数（様式1）・受給者数（様式1の6）・サービス別給付費（様式2）・保険料収納状況（様式3）・所得段階別被保険者数・経理状況（様式4）。依頼票N1・S1〜S5を一括で解決した**
A3: 町資料 | B3: **保険者別 国保連合会業務統計表（月報）令和6年5月〜令和8年8月送付分** | C3: 町 | D3: 完了 | E3: 2026-09-08 | F3: **28か月分の月次認定者数と給付件数。令和7年9月審査分の▲99人の断層を特定した**
A4: 町資料 | B4: **第10期将来推計用推計人口（男女別・5歳階級別・令和2〜32年）** | C4: 町 | D4: 完了 | E4: 2026-09-08 | F4: コーホート変化率法。令和9年8,591人→令和11年8,232人。**障がい福祉計画が用いている人口（令和9年8,287人）と300人以上異なり、統一が必要**
A5: 見える化 | B5: 人口・世帯（A系13）／第1号被保険者（B系4）／地域分析（B・D・δ系53） | C5: 見える化システム | D5: 完了 | E5: 2026-07 | F5: 基礎数値・地域分析ブックに取込
A6: 見える化 | B6: 認定者数 年度末基準（B3a〜B3e／5系列） | C6: 見える化システム | D6: 完了 | E6: 2026-08-05 | F6: **平成19年3月末〜令和8年3月末の20期。第1号＋第2号＝全体を検算済み**
A7: 見える化 | B7: 介護保険特別会計経理状況（D47・D48系25） | C7: 見える化システム | D7: 完了 | E7: 2026-08-04 | F7: 財政整理ブックに取込。H26〜R5
A8: 見える化 | B8: 入所定員（D25〜D30）／介護予防・総合事業（F系27）／認知症施策（J16〜18） | C8: 見える化システム | D8: 完了 | E8: 2026-08-04 | F8: 通いの場はR2まで、総合事業はR1・R2のみ
A9: 見える化 | B9: サービス自給率（δ2・δ3系12）／給付分析（D17・D1〜D6・B1・B4-a／29） | C9: 見える化システム | D9: 完了 | E9: 2026-08-04 | F9: 県内59市町村の比較値つき
A10: 見える化 | B10: 在宅医療・介護連携、医療提供体制、リハビリ提供体制、交付金評価指標 | C10: 見える化システム | D10: 未着手 | E10: ― | F10: 優先度C。システムへのアクセスが必要
A11: 町資料 | B11: 第9期高齢者保健福祉計画・介護保険事業計画 本文 | C11: 町 | D11: 完了 | E11: 2026-08-04 | F11: 5章構成・3基本目標・14施策、標準給付費3,566,486千円、保険料6,600円の算定根拠
A12: 町資料 | B12: 第3期地域福祉計画 本文・概要版 | C12: 町 | D12: 完了 | E12: 2026-08-04 | F12: 重複5施策を特定し役割分担を整理
... A19: 町資料 | B19: 成果指標の現状値 17項目（H1〜H17） | C19: 町 | D19: 未着手 | E19: ― | F19: **うちH3（総合事業・通いの場）とH16（調査の個票）が最優先**
A20: ※ 依頼の詳細（粒度・様式・基準日）は 16_町データ依頼/小野町_データ依頼票 を参照。

Sheet 06_会議体・意見聴取
A1: 区分 | B1: 回 | C1: 時期 | D1: 議題 | E1: 資料の状態 | F1: 備考
A2: 高齢者福祉サービス推進協議会 | B2: 第1回 | C2: 令和8年8〜9月 | D2: 第9期計画の評価、令和7年度調査結果の整理 | E2: 完了 | F2: **資料は作成済み（42表・約23,500字）。開催日が未定**
A3: 高齢者福祉サービス推進協議会 | B3: 第2回 | C3: 令和8年11月 | D3: 骨子案、サービス見込量、保険料の考え方、成果指標の目標値 | E3: 進行中 | F3: 骨子案第3版・成果指標目標値案（40指標）は作成済み
A4: 高齢者福祉サービス推進協議会 | B4: 第3回 | C4: 令和8年12月 | D4: 計画素案 | E4: 進行中 | F4: 素案第2版は作成済み。見込量・保険料の反映が必要
A5: 高齢者福祉サービス推進協議会 | B5: 第4回 | C5: 令和9年2月 | D5: パブリックコメントの結果、計画最終案 | E5: 未着手 | F5: ―
A6: パブリックコメント | B6: ― | C6: 令和9年1月 | D6: 計画素案に対する意見の募集 | E6: 完了 | F6: 実施要領・意見提出様式・対応表の様式は作成済み
A7: 町との打合せ | B7: 随時 | C7: 通年 | D7: 工程、データ、協議事項 | E7: 完了 | F7: **仕様書8①により受託者が記録を作成し相互確認する。様式は作成済み**

Sheet 07_課題・リスク
A1: No | B1: 課題・リスク | C1: 内容 | D1: 影響 | E1: 対応 | F1: 状態
A2: 1 | B2: 認定者数の計上方法の変更（旧「認定者数の異常」） | C2: **令和8年3月末の792人は年報 様式1の5で裏付けられ、値そのものは確定した。**国保連月報28か月で、減少が令和7年9月審査分の1か月に集中していること（961→862人・▲10.3％）と、同じ月に給付件数が減っていないこと（1,303→1,365件）が判明した。減少は要介護2以上に集中し要支援1は増えている。死亡171人は平年並み | D2: **実態の変化ではなく計上の変更である可能性が高い。**認定者数ベースで給付費を推計すると過小になる（令和7年度は認定者▲16.1％に対し給付費▲7.4％） | E2: **令和7年8〜9月の計上方法の変更を町に確認する。見込量は認定者数ベースではなく受給者数・給付費の実績を基礎に組む** | F2: 要対応
A3: 2 | B3: 町の実績データの受領状況 | C3: **9月8日に年報5年分・国保連月報28か月・将来推計人口を受領し、依頼35項目のうち主要項目が解決した。**残るのは地域支援事業費の内訳、令和7年度決算、成果指標の現状値17項目。**9月14日に国保連月報のExcel版を受領し、回数・日数が取れるようになった** | D3: 見込量・給付費・保険料の試算は完了した。**計画書の見込量表を回数・日数で書く見通しもついた** | E3: 残項目を再依頼する。とくに地域支援事業費は総合事業・通いの場の評価に必須 | F3: 進行中
A4: 3 | B4: 協議会の開催回数・時期が未定 | C4: 仕様書4(5)は開催支援を定めるが回数の指定がない | D4: 工程が引けず、パブコメ・印刷の日程も確定できない | E4: 受託者案（4回）を提示して町と確定する（依頼票C4） | F4: 要対応
A5: 4 | B5: 介護予防のデータ欠落 | C5: 見える化の通いの場はR2まで、総合事業はR1・R2のみで値もほぼ空。F7〜F14は本町の値が未登録 | D5: 第9期の介護予防施策を評価できない | E5: 町の事業実績（令和3〜7年度）で代替する（依頼票H3） | F5: データ待ち
A6: 5 | B6: 通いの場が実質ゼロ | C6: 見える化では週1回以上が平成28年度以降0か所。一方、調査では週1回以上の参加が5.5％（高齢者人口換算で約190人） | D6: 第10期の最重点施策が設計できない。調整済み軽度認定率は10.6％→15.2％に上昇 | E6: 町の実態を確認したうえで、実態把握と登録を令和9年度の目標に置く | F6: 進行中
A7: 6 | B7: 認定と利用のギャップ | C7: 認定率の地域差指数1.24に対し受給率1.07（比0.86）。在宅の認定者の42.1％が未利用 | D7: 利用に移行した場合に給付費が急増するリスク | E7: 未利用理由の92.9％が需要側（供給制約は0.6％）。供給確保ではなく認定運用の確認・利用意向への働きかけ・レスパイトで対応する | F7: 進行中
A8: 7 | B8: 財政余剰の取扱いと基金残高の不整合 | C8: **年報 様式4で、歳入歳出差引残額は令和6年度末144.2百万円ある一方、介護給付費準備基金の保有額は12.0百万円しかない。**しかも令和4年度末は120.0百万円で、令和5年度末に1桁減っている。第9期は基金取崩35.0百万円を見込んでいた | D8: **基金が12百万円しかなければ35百万円の取崩は実行できない。しかも繰入金（取崩し）は令和3〜6年度とも0円で、残高だけが1桁減っており、年報の系列自体に矛盾がある。**見込量の試算で算式を通すと、保険料基準額は取崩なしで月額6,558円、保有額12百万円を全額取り崩して6,456円、第9期と同じ35百万円で6,259円となる（第9期は6,600円）。**基金の扱いだけで月額300円動く** | E8: 取崩実績か入力誤りかを町に確認したうえで、余剰の還元（据置・引下げ・繰越金の基金積立）をケースC5・C6として算定する | F8: 要対応
A9: 8 | B9: 施設整備方針との不整合 | C9: 第9期は新規施設整備を原則行わない方針だが、認知症対応型共同生活介護の定員が令和4年度71人から令和6年度98人へ27人（38.0％）増加 | D9: 第9期評価の記述に影響 | E9: 整備の経緯を町に確認する（依頼票H15） | F9: 未着手
A10: 9 | B10: 印刷工程の未確保 | C10: 計画書50部（A4・4色刷り・80頁程度）、概要版50部（8頁）、簡易製本各3部が納品仕様 | D10: 納期に間に合わない | E10: **逆算表を作成済み（令和9年2月下旬の校了が期限）。12月までに印刷業者を押さえる** | F10: 進行中
A11: 10 | B11: 見える化システムへの入力作業 | C11: 仕様書4(2)は入力作業を業務に含むと定める | D11: 出力の分析だけでは仕様を満たさない | E11: アカウント・権限・作業範囲・時期を町と確認する（依頼票C5） | F11: 進行中
A12: 13 | B12: **認知症の人及びその家族等の意見聴取の方法が未決** | C12: **認知症基本法13条3項が準用する12条3項は、市町村計画の案の作成にあたり認知症の人及び家族等の意見を聴くよう努めることを求めている** | D12: **記述の追加では埋まらず、策定過程そのものに関わる。協議会の日程から逆算すると、素案の確定前に方針を決める必要がある** | E12: 協議会の委員構成に認知症の人又は家族が含まれるかを確認し、含まれない場合は家族会・認知症カフェでの意見聴取の機会を設けるかを町と協議する | F12: 要対応
A13: 14 | B13: **地域密着型3サービスの必要利用定員総数が第9期計画にない** | C13: 介護保険法117条2項1号は3サービスの各年度の必要利用定員総数を計画に定めることを求めている（必須記載事項） | D13: **第10期では9月16日に追加済み。**ただし認知症対応型共同生活介護の定員が第9期の方針に反して令和4年度71人から令和6年度98人へ27人増えた経緯が確認できていない | E13: 増床の事実関係と町外の方の利用割合を町に確認する | F13: 進行中
... A15: 12 | B15: 成果品欄の「（７）」への参照 | C15: 成果品は（１）〜（６）だが、納品仕様欄に「※（７）のデータ（ＣＤ－Ｒ）１部、概要版印刷50部」との記載がある | D15: 概要版の納品部数の解釈に関わる | E15: 町に確認する（依頼票C2） | F15: 進行中

Sheet 08_変更管理・打合せ記録
A1: No | B1: 区分 | C1: 内容 | D1: 根拠 | E1: 状態 | F1: 記録の有無
A2: 1 | B2: 工程 | C2: 高齢者計画の仕様書には工程表がない（工程が定められているのは障がい計画のみ）。業務期間は令和9年3月31日まで | D2: 仕様書3 | E2: 要対応 | F2: **業務期間から逆算した工程案を作成済み。町との合意が未**
A3: 2 | B3: 協議会 | C3: 開催回数の指定がない。受託者案は4回 | D3: 仕様書4(5) | E3: 要対応 | F3: 未
A4: 3 | B4: 保険料算定 | C4: ケース設定を引継ぎ時点の3ケース（基金の扱いのみ）からC1〜C6に組み直した。仕様書が例示する施設整備・制度改正に対応させた | D4: 仕様書4(2) | E4: 完了 | F4: 受託者の内部判断。町への説明が必要
A5: 4 | B5: 認知症計画 | C5: 包含の形式（独立章方式／分散＋対応表方式） | D5: 仕様書2(3) | E5: 進行中 | F5: **分散＋対応表方式を提案。町の意思決定が未**
A6: 5 | B6: 打合せ記録 | C6: 契約後の打合せ記録が引継ぎ資料に含まれていない | D6: 仕様書8①（受託者が作成し相互確認） | E6: 要対応 | F6: **様式を作成済み。8月の協議から適用する**
A7: ※ 仕様書8①により、打合せ記録は受託者が作成し町と相互に確認する。
A8: ※ 様式は 02_キックオフ・業務計画/小野町_工程変更協議資料 の第5節。

Sheet 09_仕様書対応表
A1: 区分 | B1: 条項 | C1: 仕様書の記載内容（原文） | D1: 対応する作業（01_WBS） | E1: 作業数 | F1: 網羅
A2: 計画の考え方 | B2: 1 | C2: 本業務は、国や福島県の動向、本町の高齢者の状況を的確に把握し、高齢者へのアンケート調査結果及び小野町高齢者保健福祉計画・第9期介護保険事業計画の評価等を行い、本町が取り組むべき課題や高齢者保健福祉施策の方向性、サービスの目標量を定める（第10期計画）とする。 | D2: ― | E2: 0 | F2: 前提条項
A3: 計画の考え方 | B3: 2(1) | C3: 令和9年度から令和11年度までの3年間に実施する取り組みを定める計画とする。 | D3: ― | E3: 0 | F3: 前提条項
A4: 計画の考え方 | B4: 2(2) | C4: 国が示す第10期計画に関する基本的な考え方を踏まえた上で、本町の特性を活かした計画とする。 | D4: 1-5 第3期地域福祉計画との役割分担の整理 | E4: 1 | F4: ○
A5: 計画の考え方 | B5: 2(3) | C5: 国の「認知症施策推進基本計画」に基づく市町村計画も包含する計画とする。 | D5: 2-7 認知症高齢者の分析 8-3 認知症施策推進基本計画の包含方針 | E5: 2 | F5: ○
A6: 計画の考え方 | B6: 3 | C6: 契約締結の日から令和9年3月31日まで | D6: 10-8 納品・検収 | E6: 1 | F6: ○
A7: 業務の内容 | B7: 4(1) | C7: 基礎的な地域データ及び資料の整理分析（現状分析）。高齢者福祉・介護保険をめぐる施策の動向、小野町の概要及び社会経済的特性、地域福祉資源の整備状況、高齢者の現況動向及びサービスの利用状況等について、小野町が提供するデータをもとに整理分析を行う。（計画策定の検討資料として活用するため、各種事項の将来推計を行う。なお、推計にあたっては、可能な限り細分化する） | D7: 1-4 第9期計画本文の確認 | E7: 1 | F7: ○
A8: 業務の内容 | B8: 4(1)①ア | C8: 統計分析（ア）人口 | D8: 2-1 人口・世帯の分析 2-2 第1号被保険者の分析 | E8: 2 | F8: ○
A9: 業務の内容 | B9: 4(1)①イ | C9: 統計分析（イ）要支援者数、要介護認定者数、認知症高齢者数 | D9: 2-3 認定者数・認定率の分析 2-4 認定者数の異常値の検証 2-7 認知症高齢者の分析 | E9: 3 | F9: ○
A10: 業務の内容 | B10: 4(1)①ウ | C10: 統計分析（ウ）居宅サービス・施設サービス・地域密着型サービスの受給者数 | D10: 2-5 サービス受給者数の分析 | E10: 1 | F10: ○
A11: 業務の内容 | B11: 4(1)①エ | C11: 統計分析（エ）介護予防事業対象者数 | D11: 2-6 介護予防事業対象者数の分析 | E11: 1 | F11: ○
A12: 業務の内容 | B12: 4(1)①オ | C12: 統計分析（オ）その他計画策定に必要な推計 | D12: 2-8 サービス自給率の分析 2-10 見える化 優先度C分野の出力 2-11 保険者機能強化推進交付金等の評価結果の整理 | E12: 3 | F12: ○
A13: 業務の内容 | B13: 4(1)② | C13: 介護保険給付費等の分析。介護サービス費目ごとの介護給付費や地域支援事業の利用状況等を分析し、現在の状況や傾向の把握、また、制度改正に伴う影響等を分析し、今後の見通しや具体的施策を検討する。 | D13: 3-1 給付費等分析結果報告書の作成 3-2 町の給付実績との突合 5-1 協議会資料（第9期評価・調査結果）の作成 5-2 成果目標の達成状況の確定 5-3 施設整備方針との不整合の確認 | E13: 5 | F13: ○
... A29: その他 | B29: 公告10⑥ | C29: 研究員は「見える化」システムやニーズ調査など各種データから介護給付費の統計分析により将来のサービス量を推計し計画化できる者（公告第1-19号 10⑥） | D29: 1-1 契約・体制の確立、キックオフ | E29: 1 | F29: ○
A31: ※ 「要確認」は、01_WBS に対応する作業が置かれていない条項です。業務の抜けを疑ってください。
A32: ※ 「前提条項」は、目的・計画期間・個人情報の取扱いなど、作業として分解せず業務全体で担保する条項です。

Sheet 10_ブロック別進捗
A1: 仕様書ブロック | B1: 該当条項 | C1: 作業数 | D1: 完了 | E1: 進行中 | F1: 要対応 | G1: データ待ち | H1: 未着手 | I1: 加重進捗率 | J1: 現況・律速
A2: B1 現状分析（基礎データ・資料の整理分析） | B2: 4(1) | C2: =COUNTIF('01_WBS'!$E$2:$E$65,$A2) | D2: =COUNTIFS('01_WBS'!$E$2:$E$65,$A2,'01_WBS'!$K$2:$K$65,"完了") | E2: =COUNTIFS('01_WBS'!$E$2:$E$65,$A2,'01_WBS'!$K$2:$K$65,"進行中") | F2: =COUNTIFS('01_WBS'!$E$2:$E$65,$A2,'01_WBS'!$K$2:$K$65,"要対応") | G2: =COUNTIFS('01_WBS'!$E$2:$E$65,$A2,'01_WBS'!$K$2:$K$65,"データ待ち") | H2: =COUNTIFS('01_WBS'!$E$2:$E$65,$A2,'01_WBS'!$K$2:$K$65,"未着手") | I2: =IF(SUMPRODUCT(('01_WBS'!$E$2:$E$65=$A2)*'01_WBS'!$M$2:$M$65)=0,"―",SUMPRODUCT(('01_WBS'!$E$2:$E$65=$A2)*'01_WBS'!$L$2:$L$65*'01_WBS'!$M$2:$M$65)/SUMPRODUCT(('01_WBS'!$E$2:$E$65=$A2)*'01_WBS'!$M$2:$M$65)/100) | J2: 第9期計画・第3期地域福祉計画の確認は完了。町からの実績データが未受領
A3: B2 統計分析 | B3: 4(1)①ア、4(1)①イ、4(1)①ウ、4(1)①エ、4(1)①オ | C3: =COUNTIF('01_WBS'!$E$2:$E$65,$A3) | D3: =COUNTIFS('01_WBS'!$E$2:$E$65,$A3,'01_WBS'!$K$2:$K$65,"完了") | E3: =COUNTIFS('01_WBS'!$E$2:$E$65,$A3,'01_WBS'!$K$2:$K$65,"進行中") | F3: =COUNTIFS('01_WBS'!$E$2:$E$65,$A3,'01_WBS'!$K$2:$K$65,"要対応") | G3: =COUNTIFS('01_WBS'!$E$2:$E$65,$A3,'01_WBS'!$K$2:$K$65,"データ待ち") | H3: =COUNTIFS('01_WBS'!$E$2:$E$65,$A3,'01_WBS'!$K$2:$K$65,"未着手") | I3: =IF(SUMPRODUCT(('01_WBS'!$E$2:$E$65=$A3)*'01_WBS'!$M$2:$M$65)=0,"―",SUMPRODUCT(('01_WBS'!$E$2:$E$65=$A3)*'01_WBS'!$L$2:$L$65*'01_WBS'!$M$2:$M$65)/SUMPRODUCT(('01_WBS'!$E$2:$E$65=$A3)*'01_WBS'!$M$2:$M$65)/100) | J3: **認定者数792人は年報で裏付けられた。論点は令和7年8〜9月の計上変更に絞られた。介護予防（総合事業・通いの場）のデータ欠落は残る**
A4: B3 介護保険給付費等の分析 | B4: 4(1)② | C4: =COUNTIF('01_WBS'!$E$2:$E$65,$A4) | D4: =COUNTIFS('01_WBS'!$E$2:$E$65,$A4,'01_WBS'!$K$2:$K$65,"完了") | E4: =COUNTIFS('01_WBS'!$E$2:$E$65,$A4,'01_WBS'!$K$2:$K$65,"進行中") | F4: =COUNTIFS('01_WBS'!$E$2:$E$65,$A4,'01_WBS'!$K$2:$K$65,"要対応") | G4: =COUNTIFS('01_WBS'!$E$2:$E$65,$A4,'01_WBS'!$K$2:$K$65,"データ待ち") | H4: =COUNTIFS('01_WBS'!$E$2:$E$65,$A4,'01_WBS'!$K$2:$K$65,"未着手") | I4: =IF(SUMPRODUCT(('01_WBS'!$E$2:$E$65=$A4)*'01_WBS'!$M$2:$M$65)=0,"―",SUMPRODUCT(('01_WBS'!$E$2:$E$65=$A4)*'01_WBS'!$L$2:$L$65*'01_WBS'!$M$2:$M$65)/SUMPRODUCT(('01_WBS'!$E$2:$E$65=$A4)*'01_WBS'!$M$2:$M$65)/100) | J4: 成果品①は第5版。町の給付実績で数値を確定する段階
A5: B4 令和7年度調査結果の反映 | B5: 4(1)③ | C5: =COUNTIF('01_WBS'!$E$2:$E$65,$A5) | D5: =COUNTIFS('01_WBS'!$E$2:$E$65,$A5,'01_WBS'!$K$2:$K$65,"完了") | E5: =COUNTIFS('01_WBS'!$E$2:$E$65,$A5,'01_WBS'!$K$2:$K$65,"進行中") | F5: =COUNTIFS('01_WBS'!$E$2:$E$65,$A5,'01_WBS'!$K$2:$K$65,"要対応") | G5: =COUNTIFS('01_WBS'!$E$2:$E$65,$A5,'01_WBS'!$K$2:$K$65,"データ待ち") | H5: =COUNTIFS('01_WBS'!$E$2:$E$65,$A5,'01_WBS'!$K$2:$K$65,"未着手") | I5: =IF(SUMPRODUCT(('01_WBS'!$E$2:$E$65=$A5)*'01_WBS'!$M$2:$M$65)=0,"―",SUMPRODUCT(('01_WBS'!$E$2:$E$65=$A5)*'01_WBS'!$L$2:$L$65*'01_WBS'!$M$2:$M$65)/SUMPRODUCT(('01_WBS'!$E$2:$E$65=$A5)*'01_WBS'!$M$2:$M$65)/100) | J5: **単純集計は完了。個票がないとクロス集計17件ができない**
A6: B5 事業量推計・保険料算出・介護財政 | B6: 4(2) | C6: =COUNTIF('01_WBS'!$E$2:$E$65,$A6) | D6: =COUNTIFS('01_WBS'!$E$2:$E$65,$A6,'01_WBS'!$K$2:$K$65,"完了") | E6: =COUNTIFS('01_WBS'!$E$2:$E$65,$A6,'01_WBS'!$K$2:$K$65,"進行中") | F6: =COUNTIFS('01_WBS'!$E$2:$E$65,$A6,'01_WBS'!$K$2:$K$65,"要対応") | G6: =COUNTIFS('01_WBS'!$E$2:$E$65,$A6,'01_WBS'!$K$2:$K$65,"データ待ち") | H6: =COUNTIFS('01_WBS'!$E$2:$E$65,$A6,'01_WBS'!$K$2:$K$65,"未着手") | I6: =IF(SUMPRODUCT(('01_WBS'!$E$2:$E$65=$A6)*'01_WBS'!$M$2:$M$65)=0,"―",SUMPRODUCT(('01_WBS'!$E$2:$E$65=$A6)*'01_WBS'!$L$2:$L$65*'01_WBS'!$M$2:$M$65)/SUMPRODUCT(('01_WBS'!$E$2:$E$65=$A6)*'01_WBS'!$M$2:$M$65)/100) | J6: **年報の受領で実績が揃い、算定シートに投入済み。残るのはサービス別見込量の算定と、地域支援事業費・調整交付金・基金取崩の確定**
A7: B6 骨子案・素案の作成 | B7: 4(3) | C7: =COUNTIF('01_WBS'!$E$2:$E$65,$A7) | D7: =COUNTIFS('01_WBS'!$E$2:$E$65,$A7,'01_WBS'!$K$2:$K$65,"完了") | E7: =COUNTIFS('01_WBS'!$E$2:$E$65,$A7,'01_WBS'!$K$2:$K$65,"進行中") | F7: =COUNTIFS('01_WBS'!$E$2:$E$65,$A7,'01_WBS'!$K$2:$K$65,"要対応") | G7: =COUNTIFS('01_WBS'!$E$2:$E$65,$A7,'01_WBS'!$K$2:$K$65,"データ待ち") | H7: =COUNTIFS('01_WBS'!$E$2:$E$65,$A7,'01_WBS'!$K$2:$K$65,"未着手") | I7: =IF(SUMPRODUCT(('01_WBS'!$E$2:$E$65=$A7)*'01_WBS'!$M$2:$M$65)=0,"―",SUMPRODUCT(('01_WBS'!$E$2:$E$65=$A7)*'01_WBS'!$L$2:$L$65*'01_WBS'!$M$2:$M$65)/SUMPRODUCT(('01_WBS'!$E$2:$E$65=$A7)*'01_WBS'!$M$2:$M$65)/100) | J7: 骨子案第3版・素案第2版・成果指標の目標値案まで到達。見込量と保険料の反映が残る
A8: B7 最終調整及び計画書の作成 | B8: 4(4) | C8: =COUNTIF('01_WBS'!$E$2:$E$65,$A8) | D8: =COUNTIFS('01_WBS'!$E$2:$E$65,$A8,'01_WBS'!$K$2:$K$65,"完了") | E8: =COUNTIFS('01_WBS'!$E$2:$E$65,$A8,'01_WBS'!$K$2:$K$65,"進行中") | F8: =COUNTIFS('01_WBS'!$E$2:$E$65,$A8,'01_WBS'!$K$2:$K$65,"要対応") | G8: =COUNTIFS('01_WBS'!$E$2:$E$65,$A8,'01_WBS'!$K$2:$K$65,"データ待ち") | H8: =COUNTIFS('01_WBS'!$E$2:$E$65,$A8,'01_WBS'!$K$2:$K$65,"未着手") | I8: =IF(SUMPRODUCT(('01_WBS'!$E$2:$E$65=$A8)*'01_WBS'!$M$2:$M$65)=0,"―",SUMPRODUCT(('01_WBS'!$E$2:$E$65=$A8)*'01_WBS'!$L$2:$L$65*'01_WBS'!$M$2:$M$65)/SUMPRODUCT(('01_WBS'!$E$2:$E$65=$A8)*'01_WBS'!$M$2:$M$65)/100) | J8: パブリックコメント後に着手する。時期が来ていない
A9: B8 協議会・パブリックコメントの支援 | B9: 4(5) | C9: =COUNTIF('01_WBS'!$E$2:$E$65,$A9) | D9: =COUNTIFS('01_WBS'!$E$2:$E$65,$A9,'01_WBS'!$K$2:$K$65,"完了") | E9: =COUNTIFS('01_WBS'!$E$2:$E$65,$A9,'01_WBS'!$K$2:$K$65,"進行中") | F9: =COUNTIFS('01_WBS'!$E$2:$E$65,$A9,'01_WBS'!$K$2:$K$65,"要対応") | G9: =COUNTIFS('01_WBS'!$E$2:$E$65,$A9,'01_WBS'!$K$2:$K$65,"データ待ち") | H9: =COUNTIFS('01_WBS'!$E$2:$E$65,$A9,'01_WBS'!$K$2:$K$65,"未着手") | I9: =IF(SUMPRODUCT(('01_WBS'!$E$2:$E$65=$A9)*'01_WBS'!$M$2:$M$65)=0,"―",SUMPRODUCT(('01_WBS'!$E$2:$E$65=$A9)*'01_WBS'!$L$2:$L$65*'01_WBS'!$M$2:$M$65)/SUMPRODUCT(('01_WBS'!$E$2:$E$65=$A9)*'01_WBS'!$M$2:$M$65)/100) | J9: **資料と様式は揃っている。協議会の開催回数・時期が未定で工程が引けない**
A10: B9 成果品の納品 | B10: 成果品①、成果品②、成果品③、成果品④、成果品⑤、成果品⑥ ほか | C10: =COUNTIF('01_WBS'!$E$2:$E$65,$A10) | D10: =COUNTIFS('01_WBS'!$E$2:$E$65,$A10,'01_WBS'!$K$2:$K$65,"完了") | E10: =COUNTIFS('01_WBS'!$E$2:$E$65,$A10,'01_WBS'!$K$2:$K$65,"進行中") | F10: =COUNTIFS('01_WBS'!$E$2:$E$65,$A10,'01_WBS'!$K$2:$K$65,"要対応") | G10: =COUNTIFS('01_WBS'!$E$2:$E$65,$A10,'01_WBS'!$K$2:$K$65,"データ待ち") | H10: =COUNTIFS('01_WBS'!$E$2:$E$65,$A10,'01_WBS'!$K$2:$K$65,"未着手") | I10: =IF(SUMPRODUCT(('01_WBS'!$E$2:$E$65=$A10)*'01_WBS'!$M$2:$M$65)=0,"―",SUMPRODUCT(('01_WBS'!$E$2:$E$65=$A10)*'01_WBS'!$L$2:$L$65*'01_WBS'!$M$2:$M$65)/SUMPRODUCT(('01_WBS'!$E$2:$E$65=$A10)*'01_WBS'!$M$2:$M$65)/100) | J10: **製本・印刷が納品仕様に含まれる。令和9年2月下旬の校了が動かせない期限**
A11: B10 業務管理・計画の基本的な考え方 | B11: 1、2(1)、2(2)、2(3)、3、5(1) ほか | C11: =COUNTIF('01_WBS'!$E$2:$E$65,$A11) | D11: =COUNTIFS('01_WBS'!$E$2:$E$65,$A11,'01_WBS'!$K$2:$K$65,"完了") | E11: =COUNTIFS('01_WBS'!$E$2:$E$65,$A11,'01_WBS'!$K$2:$K$65,"進行中") | F11: =COUNTIFS('01_WBS'!$E$2:$E$65,$A11,'01_WBS'!$K$2:$K$65,"要対応") | G11: =COUNTIFS('01_WBS'!$E$2:$E$65,$A11,'01_WBS'!$K$2:$K$65,"データ待ち") | H11: =COUNTIFS('01_WBS'!$E$2:$E$65,$A11,'01_WBS'!$K$2:$K$65,"未着手") | I11: =IF(SUMPRODUCT(('01_WBS'!$E$2:$E$65=$A11)*'01_WBS'!$M$2:$M$65)=0,"―",SUMPRODUCT(('01_WBS'!$E$2:$E$65=$A11)*'01_WBS'!$L$2:$L$65*'01_WBS'!$M$2:$M$65)/SUMPRODUCT(('01_WBS'!$E$2:$E$65=$A11)*'01_WBS'!$M$2:$M$65)/100) | J11: 仕様書の適合性チェック・データ依頼票は完了。工程と協議会日程の合意が残る
A12: B11 仕様書に定めのない作業 | B12: （該当条項なし） | C12: =COUNTIF('01_WBS'!$E$2:$E$65,$A12) | D12: =COUNTIFS('01_WBS'!$E$2:$E$65,$A12,'01_WBS'!$K$2:$K$65,"完了") | E12: =COUNTIFS('01_WBS'!$E$2:$E$65,$A12,'01_WBS'!$K$2:$K$65,"進行中") | F12: =COUNTIFS('01_WBS'!$E$2:$E$65,$A12,'01_WBS'!$K$2:$K$65,"要対応") | G12: =COUNTIFS('01_WBS'!$E$2:$E$65,$A12,'01_WBS'!$K$2:$K$65,"データ待ち") | H12: =COUNTIFS('01_WBS'!$E$2:$E$65,$A12,'01_WBS'!$K$2:$K$65,"未着手") | I12: =IF(SUMPRODUCT(('01_WBS'!$E$2:$E$65=$A12)*'01_WBS'!$M$2:$M$65)=0,"―",SUMPRODUCT(('01_WBS'!$E$2:$E$65=$A12)*'01_WBS'!$L$2:$L$65*'01_WBS'!$M$2:$M$65)/SUMPRODUCT(('01_WBS'!$E$2:$E$65=$A12)*'01_WBS'!$M$2:$M$65)/100) | J12: 該当なし。仕様書のいずれかの条項に紐づかない作業が発生した場合はここに現れる
A13: 合計 | C13: =SUM(C2:C12) | D13: =SUM(D2:D12) | E13: =SUM(E2:E12) | F13: =SUM(F2:F12) | G13: =SUM(G2:G12) | H13: =SUM(H2:H12) | I13: =IF(SUM('01_WBS'!$M$2:$M$65)=0,0,SUMPRODUCT('01_WBS'!$L$2:$L$65,'01_WBS'!$M$2:$M$65)/SUM('01_WBS'!$M$2:$M$65)/100)
A15: ※ 段階（02_段階サマリ）は業務の進み方の切り口、ブロックは委託契約上の業務単位の切り口です。同じ作業を別の軸で見ています。
A16: ※ 作業が複数の条項にまたがる場合は、先頭の条項が属するブロックに数えています。
A17: ※ 未分類の作業があります：[]
