Workbook
Name 採用・退職: #REF!
Name 所属コード表_新旧対照_: #REF!

Sheet 料金改定率
A1: 女川町水道事業 経営戦略財政シミュレーション結果（法定耐用年数×1.2倍ver）
I2: 【財政シミュレーション結果】
D3: 改定率
C4: 基本料金 | D4: 1.5
C5: 従量料金 | D5: 1
B6: 【料金体系】
B7: 〇基本料金 | C7: 現行 | D7: 他町 | F7: ="現行×"&料金改定率!D4*100&"%" -> 現行×150%
B8: 口径 | C8: 料金 | D8: 料金 | E8: 乖離率 | F8: 料金 | G8: 改定率
B9: 13ミリ | C9: =#REF! -> #REF! | E9: =IFERROR(D9/C9,"") | F9: ='【料金算定－現行×改定率】総括原価'!D9 -> #REF! | G9: =F9/C9 -> #REF!
B10: 20ミリ | C10: =#REF! -> #REF! | E10: =IFERROR(D10/C10,"") | F10: ='【料金算定－現行×改定率】総括原価'!D10 -> #REF! | G10: =F10/C10 -> #REF!
B11: 25ミリ | C11: =#REF! -> #REF! | E11: =IFERROR(D11/C11,"") | F11: ='【料金算定－現行×改定率】総括原価'!D11 -> #REF! | G11: =F11/C11 -> #REF!
B12: 30ミリ | C12: =#REF! -> #REF! | E12: =IFERROR(D12/C12,"") | F12: ='【料金算定－現行×改定率】総括原価'!D12 -> #REF! | G12: =F12/C12 -> #REF!
B13: 40ミリ | C13: =#REF! -> #REF! | E13: =IFERROR(D13/C13,"") | F13: ='【料金算定－現行×改定率】総括原価'!D13 -> #REF! | G13: =F13/C13 -> #REF!
B14: 50ミリ | C14: =#REF! -> #REF! | E14: =IFERROR(D14/C14,"") | F14: ='【料金算定－現行×改定率】総括原価'!D14 -> #REF! | G14: =F14/C14 -> #REF!
B15: 75ミリ | C15: =#REF! -> #REF! | E15: =IFERROR(D15/C15,"") | F15: ='【料金算定－現行×改定率】総括原価'!D15 -> #REF! | G15: =F15/C15 -> #REF!
B16: 100ミリ | C16: =#REF! -> #REF! | E16: =IFERROR(D16/C16,"") | F16: ='【料金算定－現行×改定率】総括原価'!D16 -> #REF! | G16: =F16/C16 -> #REF!
W19: （単位：千円）
B20: 〇水量料金 | C20: 現行 | D20: 他市 | F20: ="現行×"&料金改定率!D5*100&"%" -> 現行×100% | J20: 実績 | L20: 試算
B21: 区分 | C21: 料金 | D21: 料金 | E21: 乖離率 | F21: 料金 | G21: 改定率 | J21: H30 | L21: H31 | N21: R10 | P21: R20 | R21: R30 | T21: R40 | V21: R50
B22: 1～10㎥ | C22: =#REF! -> #REF! | E22: =IFERROR(D22/C22,"") | F22: ='【料金算定－現行×改定率】総括原価'!D18 -> #REF! | G22: =F22/C22 -> #REF! | J22: 収入 | K22: 費用 | L22: 収入 | M22: 費用 | N22: 収入 | O22: 費用 | P22: 収入 | Q22: 費用 | R22: 収入 | S22: 費用 | T22: 収入 | U22: 費用 | V22: 収入 | W22: 費用
B23: 11～20㎥ | C23: =#REF! -> #REF! | E23: =IFERROR(D23/C23,"") | F23: ='【料金算定－現行×改定率】総括原価'!D19 -> #REF! | G23: =F23/C23 -> #REF! | I23: 3条 | J23: =【現行×調整率】財政シミュ!R5 -> #REF! | K23: =【現行×調整率】財政シミュ!R23 -> #REF! | L23: =【現行×調整率】財政シミュ!T5 -> #REF! | M23: =【現行×調整率】財政シミュ!T23 -> #REF! | N23: =【現行×調整率】財政シミュ!AC5 -> #REF! | O23: =【現行×調整率】財政シミュ!AC23 -> #REF! | P23: =【現行×調整率】財政シミュ!AM5 -> #REF! | Q23: =【現行×調整率】財政シミュ!AM23 -> #REF! | R23: =【現行×調整率】財政シミュ!AW5 -> #REF! | S23: =【現行×調整率】財政シミュ!AW23 -> #REF! | T23: =【現行×調整率】財政シミュ!BG5 -> #REF! | U23: =【現行×調整率】財政シミュ!BG23 -> #REF! | V23: =【現行×調整率】財政シミュ!BQ5 -> #REF! | W23: =【現行×調整率】財政シミュ!BQ23 -> #REF!
B24: 21～50㎥ | C24: =#REF! -> #REF! | E24: =IFERROR(D24/C24,"") | F24: ='【料金算定－現行×改定率】総括原価'!D20 -> #REF! | G24: =F24/C24 -> #REF! | I24: 4条 | J24: =【現行×調整率】財政シミュ!R72 -> 9335000 | K24: =【現行×調整率】財政シミュ!R79 -> 280177715 | L24: =【現行×調整率】財政シミュ!T72 -> 150000000000000 | M24: =【現行×調整率】財政シミュ!T79 -> 160000079463153 | N24: =【現行×調整率】財政シミュ!AC72 -> 160000130000000 | O24: =【現行×調整率】財政シミュ!AC79 -> 160000182991959 | P24: =【現行×調整率】財政シミュ!AM72 -> 50000550000000 | Q24: =【現行×調整率】財政シミュ!AM79 -> 50000681474127 | R24: =【現行×調整率】財政シミュ!AW72 -> 50000010000000 | S24: =【現行×調整率】財政シミュ!AW79 -> 50000201631756 | T24: =【現行×調整率】財政シミュ!BG72 -> 50000010000000 | U24: =【現行×調整率】財政シミュ!BG79 -> 50000254808211 | V24: =【現行×調整率】財政シミュ!BQ72 -> 0 | W24: =【現行×調整率】財政シミュ!BQ79 -> 192307993
B25: 51～100㎥ | C25: =#REF! -> #REF! | E25: =IFERROR(D25/C25,"") | F25: ='【料金算定－現行×改定率】総括原価'!D21 -> #REF! | G25: =F25/C25 -> #REF! | I25: 資金残高 | J25: =【現行×調整率】財政シミュ!R113 -> 132458270 | L25: =【現行×調整率】財政シミュ!T113 -> #REF! | N25: =【現行×調整率】財政シミュ!AC113 -> #REF! | P25: =【現行×調整率】財政シミュ!AM113 -> #REF! | R25: =【現行×調整率】財政シミュ!AW113 -> #REF! | T25: =【現行×調整率】財政シミュ!BG113 -> #REF! | V25: =【現行×調整率】財政シミュ!BQ113 -> #REF!
B26: 100㎥超 | C26: =#REF! -> #REF! | E26: =IFERROR(D26/C26,"") | F26: ='【料金算定－現行×改定率】総括原価'!D22 -> #REF! | G26: =F26/C26 -> #REF! | I26: 企業債残高 | J26: =【現行×調整率】財政シミュ!R114 -> 763361128 | L26: =【現行×調整率】財政シミュ!T114 -> 450554111 | N26: =【現行×調整率】財政シミュ!AC114 -> 2822863405 | P26: =【現行×調整率】財政シミュ!AM114 -> 6354190571 | R26: =【現行×調整率】財政シミュ!AW114 -> 5688232449 | T26: =【現行×調整率】財政シミュ!BG114 -> 3988555190 | V26: =【現行×調整率】財政シミュ!BQ114 -> 1904019121

Sheet 【PL】決算数値入力
B1: 収益的収支（税抜き） | F1: この色部分を入れる。
B2: DS:女川町水道事業会計収益費用明細書 | P2: （単位：千円） | R2: 収益的収支（税抜き） | W2: （単位：千円）
B3: 款 | C3: 項 | D3: 目 | E3: 節 | F3: 実績期間 | P3: 平均 | R3: 款 | S3: 項 | T3: 目 | V3: 総括原価の区分 | W3: 実績期間 | AB3: 10年平均値
F4: H26 | G4: H27 | H4: H28 | I4: H29 | J4: H30 | K4: R1 | L4: R2 | M4: R3 | N4: R4 | O4: R5 | W4: R1 | X4: R2 | Y4: R3 | Z4: R4 | AA4: R5
B5: 水道事業収益 | F5: =SUM(F6,F15,F28) -> 140644902 | G5: =SUM(G6,G15,G28) -> 354853084 | H5: =SUM(H6,H15,H28) -> 181202744 | I5: =SUM(I6,I15,I28) -> 225661934 | J5: =SUM(J6,J15,J28) -> 246381566 | K5: =SUM(K6,K15,K28) -> 236084433 | L5: =SUM(L6,L15,L28) -> 471816622 | M5: =SUM(M6,M15,M28) -> 506142175 | ... O5: =SUM(O6,O15,O28) -> 504865980 | P5: =AVERAGE(F5:O5) -> 346115904 | R5: 水道事業収益 | W5: =SUM(W6,W11,W19,W20) -> 236084433 | X5: =SUM(X6,X11,X19,X20) -> 471816622 | Y5: =SUM(Y6,Y11,Y19,Y20) -> 506142175 | Z5: =SUM(Z6,Z11,Z19,Z20) -> 593505600 | AA5: =SUM(AA6,AA11,AA19,AA20) -> 504865980 | AB5: =SUM(AB6,AB11,AB19,AB20) -> 3.4374651e+08
C6: 営業収益 | F6: =SUM(F7,F9,F11) -> 98303392 | G6: =SUM(G7,G9,G11) -> 106482674 | H6: =SUM(H7,H9,H11) -> 108666066 | I6: =SUM(I7,I9,I11) -> 118698260 | J6: =SUM(J7,J9,J11) -> 117662769 | K6: =SUM(K7,K9,K11) -> 115230130 | L6: =SUM(L7,L9,L11) -> 119471832 | M6: =SUM(M7,M9,M11) -> 122357520 | ... O6: =SUM(O7,O9,O11) -> 120750259 | P6: =AVERAGE(F6:O6) -> 1.1474756e+08 | S6: 営業収益 | W6: =SUM(W7:W10) -> 115230130 | X6: =SUM(X7:X10) -> 119471832 | Y6: =SUM(Y7:Y10) -> 122357520 | Z6: =SUM(Z7:Z10) -> 119852700 | AA6: =SUM(AA7:AA10) -> 120750259 | AB6: =SUM(AB7:AB10) -> 112378170
D7: 給水収益 | F7: =F8 -> 90864970 | G7: =G8 -> 96266880 | H7: =H8 -> 101214980 | I7: =I8 -> 117729860 | J7: =J8 -> 117200769 | K7: =K8 -> 114968230 | L7: =L8 -> 119265632 | M7: =M8 -> 122177720 | ... O7: =O8 -> 120553459 | P7: =AVERAGE(F7:O7) -> 111985280 | T7: 給水収益 | W7: =K7 -> 114968230 | X7: =L7 -> 119265632 | Y7: =M7 -> 122177720 | Z7: =N7 -> 119610300 | AA7: =O7 -> 120553459 | AB7: =P7 -> 111985280
E8: 水道使用料 | F8: 90864970 | G8: 96266880 | H8: 101214980 | I8: 117729860 | J8: 117200769 | K8: 114968230 | L8: 119265632 | M8: 122177720 | N8: 119610300 | O8: 120553459 | P8: =AVERAGE(F8:O8) -> 111985280 | T8: 加入金 | AB8: 0
D9: 受託工事収益 | F9: =F10 -> 0 | G9: =G10 -> 0 | H9: =H10 -> 0 | I9: =I10 -> 0 | J9: =J10 -> 0 | K9: =K10 -> 0 | L9: =L10 -> 0 | M9: =M10 -> 0 | ... O9: =O10 -> 0 | P9: =AVERAGE(F9:O9) -> 0 | T9: 受託工事収益 | W9: =K9 -> 0 | X9: =L9 -> 0 | Y9: =M9 -> 0 | Z9: =N9 -> 0 | AA9: =O9 -> 0 | AB9: =P9 -> 0
E10: 受託工事収益 | F10: 0 | G10: 0 | H10: 0 | I10: 0 | J10: 0 | K10: 0 | L10: 0 | M10: 0 | N10: 0 | O10: 0 | P10: =AVERAGE(F10:O10) -> 0 | T10: その他の営業収益 | W10: =K12+K13 -> 261900 | X10: =L12+L13 -> 206200 | Y10: =M12+M13 -> 179800 | Z10: =N12+N13 -> 242400 | AA10: =O12+O13 -> 196800 | AB10: =P12 -> 392890
D11: その他の営業収益 | F11: =SUM(F12:F14) -> 7438422 | G11: =SUM(G12:G14) -> 10215794 | H11: =SUM(H12:H14) -> 7451086 | I11: =SUM(I12:I14) -> 968400 | J11: =SUM(J12:J14) -> 462000 | K11: =SUM(K12:K14) -> 261900 | L11: =SUM(L12:L14) -> 206200 | M11: =SUM(M12:M14) -> 179800 | ... O11: =SUM(O12:O14) -> 196800 | P11: =AVERAGE(F11:O11) -> 2762280.2 | S11: 営業外収益 | W11: =SUM(W12:W16) -> 120854303 | X11: =SUM(X12:X16) -> 352344790 | Y11: =SUM(Y12:Y16) -> 383784655 | Z11: =SUM(Z12:Z16) -> 473652900 | AA11: =SUM(AA12:AA16) -> 384115721 | AB11: =SUM(AB12:AB16) -> 2.3136834e+08
E12: 手数料 | F12: 329800 | G12: 411700 | H12: 669900 | I12: 968400 | J12: 462000 | K12: 261900 | L12: 206200 | M12: 179800 | N12: 242400 | O12: 196800 | P12: =AVERAGE(F12:O12) -> 392890 | T12: 受取利息及び配当金 | W12: =K16 -> 0 | X12: =L16 -> 0 | Y12: =M16 -> 0 | Z12: =N16 -> 0 | AA12: =O16 -> 0 | AB12: =P16 -> 15431.1
E13: 分水収益 | F13: 6961710 | G13: 9706982 | H13: 6730537 | I13: 0 | J13: 0 | K13: 0 | L13: 0 | M13: 0 | N13: 0 | O13: 0 | P13: =AVERAGE(F13:O13) -> 2339922.9 | T13: 他会計補助金 | W13: =K18 -> 23034829 | X13: =L18 -> 61004862 | Y13: =M18 -> 0 | Z13: =N18 -> 25962175 | AA13: =O18 -> 25117004 | AB13: =P18 -> 13834221
E14: 材料売却収益 | F14: 146912 | G14: 97112 | H14: 50649 | I14: 0 | J14: 0 | K14: 0 | L14: 0 | M14: 0 | N14: 0 | O14: 0 | P14: =AVERAGE(F14:O14) -> 29467.3 | T14: 補助金 | W14: =K24 -> 0 | X14: =L24 -> 0 | Y14: =M24 -> 25000000 | Z14: =N24 -> 20000000 | AA14: =O24 -> 20000000 | AB14: =P24 -> 15900000
C15: 営業外収益 | F15: =SUM(F16,F18,F20,F24,F26) -> 42341510 | G15: =SUM(G16,G18,G20,G24,G26) -> 248370410 | H15: =SUM(H16,H18,H20,H24,H26) -> 72536678 | I15: =SUM(I16,I18,I20,I24,I26) -> 106963674 | J15: =SUM(J16,J18,J20,J24,J26) -> 128718797 | K15: =SUM(K16,K18,K20,K24,K26) -> 120854303 | L15: =SUM(L16,L18,L20,L24,L26) -> 352344790 | M15: =SUM(M16,M18,M20,M24,M26) -> 383784655 | ... O15: =SUM(O16,O18,O20,O24,O26) -> 384115721 | P15: =AVERAGE(F15:O15) -> 2.3136834e+08 | T15: 雑収益 | W15: =K20 -> 2684327 | X15: =L20 -> 2450229 | Y15: =M20 -> 22402177 | Z15: =N20 -> 8371047 | AA15: =O20 -> 2589660 | AB15: =P20 -> 4890572.8
D16: 受取利息及び配当金 | F16: =F17 -> 26979 | G16: =G17 -> 19775 | H16: =H17 -> 14752 | I16: =I17 -> 15030 | J16: =J17 -> 77775 | K16: =K17 -> 0 | L16: =L17 -> 0 | M16: =M17 -> 0 | ... O16: =O17 -> 0 | P16: =AVERAGE(F16:O16) -> 15431.1 | T16: 長期前受金戻入益 | W16: =SUM(W17:W18) -> 95135147 | X16: =SUM(X17:X18) -> 288889699 | Y16: =SUM(Y17:Y18) -> 336382478 | Z16: =SUM(Z17:Z18) -> 419319678 | AA16: =SUM(AA17:AA18) -> 336409057 | AB16: =SUM(AB17:AB18) -> 1.9672812e+08
E17: 預金利息 | F17: 26979 | G17: 19775 | H17: 14752 | I17: 15030 | J17: 77775 | K17: 0 | L17: 0 | M17: 0 | N17: 0 | O17: 0 | P17: =AVERAGE(F17:O17) -> 15431.1 | U17: H30末の取得資産 | W17: =K26 -> 95135147 | X17: =L26 -> 288889699 | Y17: =M26 -> 336382478 | Z17: =N26 -> 419319678 | AA17: =O26 -> 336409057 | AB17: =P26 -> 1.9672812e+08
D18: 他会計補助金 | F18: =F19 -> 480000 | G18: =G19 -> 488000 | H18: =H19 -> 1343340 | I18: =I19 -> 576000 | J18: =J19 -> 336000 | K18: =K19 -> 23034829 | L18: =L19 -> 61004862 | M18: =M19 -> 0 | ... O18: =O19 -> 25117004 | P18: =AVERAGE(F18:O18) -> 13834221 | U18: H31以降の取得資産
E19: 他会計補助金 | F19: 480000 | G19: 488000 | H19: 1343340 | I19: 576000 | J19: 336000 | K19: 23034829 | L19: 61004862 | M19: 0 | N19: 25962175 | O19: 25117004 | P19: =AVERAGE(F19:O19) -> 13834221 | S19: 引当金戻入益
D20: 雑収益 | F20: =SUM(F21:F23) -> 1792752 | G20: =SUM(G21:G23) -> 1015811 | H20: =SUM(H21:H23) -> 1702162 | I20: =SUM(I21:I23) -> 1962207 | J20: =SUM(J21:J23) -> 3935356 | K20: =SUM(K21:K23) -> 2684327 | L20: =SUM(L21:L23) -> 2450229 | M20: =SUM(M21:M23) -> 22402177 | ... O20: =SUM(O21:O23) -> 2589660 | P20: =AVERAGE(F20:O20) -> 4890572.8 | S20: 特別利益 | W20: =SUM(W21:W23) -> 0 | X20: =SUM(X21:X23) -> 0 | Y20: =SUM(Y21:Y23) -> 0 | Z20: =SUM(Z21:Z23) -> 0 | AA20: =SUM(AA21:AA23) -> 0 | AB20: =SUM(AB21:AB23) -> 0
E21: その他雑収益 | F21: 1789952 | G21: 1015811 | H21: 1702162 | I21: 1962207 | J21: 2052299 | K21: 2684327 | L21: 2450229 | M21: 22402177 | N21: 8371047 | O21: 2589660 | P21: =AVERAGE(F21:O21) -> 4701987.1 | T21: 固定資産売却益 | W21: =K32 -> 0 | X21: =L32 -> 0 | Y21: =M32 -> 0 | Z21: =N32 -> 0 | AA21: =O32 -> 0 | AB21: =P32 -> 0
E22: 消費税関係雑収益 | F22: 2800 | G22: 0 | H22: 0 | I22: 0 | J22: 1883057 | K22: 0 | L22: 0 | M22: 0 | N22: 0 | O22: 0 | P22: =AVERAGE(F22:O22) -> 188585.7 | T22: 過年度修正益 | W22: =K29 -> 0 | X22: =L29 -> 0 | Y22: =M29 -> 0 | Z22: =N29 -> 0 | AA22: =O29 -> 0 | AB22: =P29 -> 0
E23: 不用品売却収益 | F23: 0 | G23: 0 | H23: 0 | I23: 0 | J23: 0 | K23: 0 | L23: 0 | M23: 0 | N23: 0 | O23: 0 | P23: =AVERAGE(F23:O23) -> 0 | T23: その他特別利益
D24: 補助金 | F24: =F25 -> 14000000 | G24: =G25 -> 15000000 | H24: =H25 -> 11000000 | I24: =I25 -> 27000000 | J24: =J25 -> 27000000 | K24: =K25 -> 0 | L24: =L25 -> 0 | M24: =M25 -> 25000000 | ... O24: =O25 -> 20000000 | P24: =AVERAGE(F24:O24) -> 15900000 | R24: 水道事業費用 | W24: =SUM(W25,W58,W63) -> 390874183 | X24: =SUM(X25,X58,X63) -> 507845824 | Y24: =SUM(Y25,Y58,Y63) -> 543887736 | Z24: =SUM(Z25,Z58,Z63) -> 694576672 | AA24: =SUM(AA25,AA58,AA63) -> 564428515 | AB24: =P35 -> 4.2086899e+08
E25: 国庫補助金 | F25: 14000000 | G25: 15000000 | H25: 11000000 | I25: 27000000 | J25: 27000000 | K25: 0 | L25: 0 | M25: 25000000 | N25: 20000000 | O25: 20000000 | P25: =AVERAGE(F25:O25) -> 15900000 | S25: 営業費用 | W25: =SUM(W26,W34,W43,W52,W55) -> 276187944 | X25: =SUM(X26,X34,X43,X52,X55) -> 493988554 | Y25: =SUM(Y26,Y34,Y43,Y52,Y55) -> 537473069 | Z25: =SUM(Z26,Z34,Z43,Z52,Z55) -> 687804951 | AA25: =SUM(AA26,AA34,AA43,AA52,AA55) -> 548360734 | AB25: =P36 -> 3.5942518e+08
D26: 長期前受金戻入益 | F26: =F27 -> 26041779 | G26: =G27 -> 231846824 | H26: =H27 -> 58476424 | I26: =I27 -> 77410437 | J26: =J27 -> 97369666 | K26: =K27 -> 95135147 | L26: =L27 -> 288889699 | M26: =M27 -> 336382478 | ... O26: =O27 -> 336409057 | P26: =AVERAGE(F26:O26) -> 1.9672812e+08 | T26: 原水及び浄水費 | V26: 原浄水部門費 | W26: =SUM(W27:W33) -> 68125490 | X26: =SUM(X27:X33) -> 86729085 | Y26: =SUM(Y27:Y33) -> 77675517 | Z26: =SUM(Z27:Z33) -> 81124641 | AA26: =SUM(AA27:AA33) -> 85901288 | AB26: =P37 -> 69189921
E27: 長期前受金戻入益 | F27: 26041779 | G27: 231846824 | H27: 58476424 | I27: 77410437 | J27: 97369666 | K27: 95135147 | L27: 288889699 | M27: 336382478 | N27: 419319678 | O27: 336409057 | P27: =AVERAGE(F27:O27) -> 1.9672812e+08 | U27: 人件費 | W27: =K38+K39+K40+K41 -> 6871890 | X27: =L38+L39+L40+L41 -> 6834594 | Y27: =M38+M39+M40+M41 -> 6604994 | Z27: =N38+N39+N40+N41 -> 6808256 | AA27: =O38+O39+O40+O41 -> 6912531 | AB27: =P38+P39+P40+P41 -> 7539318.4
C28: 特別利益 | F28: =SUM(F31,F29) -> 0 | G28: =SUM(G31,G29) -> 0 | H28: =SUM(H31,H29) -> 0 | I28: =SUM(I31,I29) -> 0 | J28: =SUM(J31,J29) -> 0 | K28: =SUM(K31,K29) -> 0 | L28: =SUM(L31,L29) -> 0 | M28: =SUM(M31,M29) -> 0 | ... O28: =SUM(O31,O29) -> 0 | P28: =AVERAGE(F28:O28) -> 0 | U28: 動力費 | W28: =K50 -> 2543653 | X28: =L50 -> 6880183 | Y28: =M50 -> 7599848 | Z28: =N50 -> 9405448 | AA28: =O50 -> 8392602 | AB28: =P50 -> 4481765.6
D29: 過年度損益修正益 | F29: =F30 -> 0 | G29: =G30 -> 0 | H29: =H30 -> 0 | I29: =I30 -> 0 | J29: =J30 -> 0 | K29: =K30 -> 0 | L29: =L30 -> 0 | M29: =M30 -> 0 | ... O29: =O30 -> 0 | P29: =AVERAGE(F29:O29) -> 0 | U29: 薬品費 | W29: =K51 -> 2231130 | X29: =L51 -> 2383550 | Y29: =M51 -> 2505150 | Z29: =N51 -> 2578200 | AA29: =O51 -> 3328640 | AB29: =P51 -> 2232707.9
E30: 過年度損益修正益 | F30: 0 | G30: 0 | H30: 0 | I30: 0 | J30: 0 | K30: 0 | L30: 0 | M30: 0 | N30: 0 | O30: 0 | P30: =AVERAGE(F30:O30) -> 0 | U30: 修繕費 | W30: =K49 -> 4684722 | X30: =L49 -> 8618000 | Y30: =M49 -> 1967420 | Z30: =N49 -> 0 | AA30: =O49 -> 3913900 | AB30: =P49 -> 2660995.2
D31: 固定資産売却益 | F31: =F32 -> 0 | G31: =G32 -> 0 | H31: =H32 -> 0 | I31: =I32 -> 0 | J31: =J32 -> 0 | K31: =K32 -> 0 | L31: =L32 -> 0 | M31: =M32 -> 0 | ... O31: =O32 -> 0 | P31: =AVERAGE(F31:O31) -> 0 | U31: 委託料 | W31: =K46 -> 33900347 | X31: =L46 -> 31437870 | Y31: =M46 -> 37142870 | Z31: =N46 -> 33639873 | AA31: =O46 -> 36092000 | AB31: =P46 -> 30459801
E32: 固定資産売却益 | F32: 0 | G32: 0 | H32: 0 | I32: 0 | J32: 0 | K32: 0 | L32: 0 | M32: 0 | N32: 0 | O32: 0 | P32: =AVERAGE(F32:O32) -> 0 | U32: その他（物価上昇を考慮する） | W32: =K42+K43+K44+K45+K47+K48+K52+K54+K55 -> 7655578 | X32: =L42+L43+L44+L45+L47+L48+L52+L54+L55 -> 9645808 | Y32: =M42+M43+M44+M45+M47+M48+M52+M54+M55 -> 9829369 | Z32: =N42+N43+N44+N45+N47+N48+N52+N54+N55 -> 10153949 | AA32: =O42+O43+O44+O45+O47+O48+O52+O54+O55 -> 9171593 | AB32: =P42+P43+P44+P45+P47+P48+P52+P54+P55 -> 7339389.2
B33: 決算書「水道事業収益」数値 | F33: 140644902 | G33: 354853084 | H33: 181202744 | I33: 225661934 | J33: 246381566 | K33: 236084433 | L33: 471816622 | M33: 506142175 | N33: 593505600 | O33: 504865980 | U33: その他（負担金） | W33: =K53 -> 10238170 | X33: =L53 -> 20929080 | Y33: =M53 -> 12025866 | Z33: =N53 -> 18538915 | AA33: =O53 -> 18090022 | AB33: =P53 -> 14475944
B34: 差異の有無 | F34: =IF(F5=F33,"OK","NG") -> OK | G34: =IF(G5=G33,"OK","NG") -> OK | H34: =IF(H5=H33,"OK","NG") -> OK | I34: =IF(I5=I33,"OK","NG") -> OK | J34: =IF(J5=J33,"OK","NG") -> OK | K34: =IF(K5=K33,"OK","NG") -> OK | L34: =IF(L5=L33,"OK","NG") -> OK | M34: =IF(M5=M33,"OK","NG") -> OK | ... O34: =IF(O5=O33,"OK","NG") -> OK | T34: 配水及び給水費 | V34: 配給水部門費 | W34: =SUM(W35:W41) -> 39566820 | X34: =SUM(X35:X41) -> 36646933 | Y34: =SUM(Y35:Y41) -> 35722581 | Z34: =SUM(Z35:Z41) -> 36936296 | AA34: =SUM(AA35:AA41) -> 32180340 | AB34: =P56 -> 34923211
B35: 水道事業費用 | F35: =SUM(F36,F112,F116) -> 190236030 | G35: =SUM(G36,G112,G116) -> 525072793 | H35: =SUM(H36,H112,H116) -> 228906571 | I35: =SUM(I36,I112,I116) -> 275120413 | J35: =SUM(J36,J112,J116) -> 287741207 | K35: =SUM(K36,K112,K116) -> 390874183 | L35: =SUM(L36,L112,L116) -> 507845824 | M35: =SUM(M36,M112,M116) -> 543887736 | ... O35: =SUM(O36,O112,O116) -> 564428515 | P35: =AVERAGE(F35:O35) -> 4.2086899e+08 | U35: 人件費 | W35: =K57+K58+K59+K60+K61 -> 13528381 | X35: =L57+L58+L59+L60+L61 -> 10517166 | Y35: =M57+M58+M59+M60+M61 -> 10463981 | Z35: =N57+N58+N59+N60+N61 -> 10732216 | AA35: =O57+O58+O59+O60+O61 -> 6777049 | AB35: =P57+P58+P59+P60+P61 -> 12599585
C36: 営業費用 | F36: =SUM(F37,F56,F76,F78,F104,F106,F109) -> 185755422 | G36: =SUM(G37,G56,G76,G78,G104,G106,G109) -> 157078455 | H36: =SUM(H37,H56,H76,H78,H104,H106,H109) -> 157638137 | I36: =SUM(I37,I56,I76,I78,I104,I106,I109) -> 266575866 | J36: =SUM(J37,J56,J76,J78,J104,J106,J109) -> 283388690 | K36: =SUM(K37,K56,K76,K78,K104,K106,K109) -> 276187944 | L36: =SUM(L37,L56,L76,L78,L104,L106,L109) -> 493988554 | M36: =SUM(M37,M56,M76,M78,M104,M106,M109) -> 537473069 | ... O36: =SUM(O37,O56,O76,O78,O104,O106,O109) -> 548360734 | P36: =AVERAGE(F36:O36) -> 3.5942518e+08 | U36: 動力費 | W36: =K72 -> 3189420 | X36: =L72 -> 2083304 | Y36: =M72 -> 2339387 | Z36: =N72 -> 3088131 | AA36: =O72 -> 2470534 | AB36: =P72 -> 2159463.6
D37: 原水及び浄水費 | F37: =SUM(F38:F55) -> 58676576 | G37: =SUM(G38:G55) -> 54090290 | H37: =SUM(H38:H55) -> 45431047 | I37: =SUM(I38:I55) -> 64803015 | J37: =SUM(J38:J55) -> 69342260 | K37: =SUM(K38:K55) -> 68125490 | L37: =SUM(L38:L55) -> 86729085 | M37: =SUM(M38:M55) -> 77675517 | ... O37: =SUM(O38:O55) -> 85901288 | P37: =AVERAGE(F37:O37) -> 69189921 | U37: 薬品費
E38: 給料 | F38: =4689000 -> 4689000 | G38: 4698000 | H38: 4698000 | I38: 3057600 | J38: 3457800 | K38: 3479400 | L38: 3501900 | M38: 3526200 | N38: 3568800 | O38: 3669600 | P38: =AVERAGE(F38:O38) -> 3834630 | U38: 修繕費 | W38: =K70 -> 1577280 | X38: =L70 -> 327448 | Y38: =M70 -> 569069 | Z38: =N70 -> 3745890 | AA38: =O70 -> 3642734 | AB38: =P70 -> 1417521.1
E39: 手当+引当金 | F39: =2534306+603139 -> 3137445 | G39: =1694429+577463 -> 2271892 | H39: =1678889+604723 -> 2283612 | I39: =572069+619295 -> 1191364 | J39: =1263097+460538 -> 1723635 | K39: 1524409 | L39: 1480350 | M39: 1399400 | N39: 1546263 | O39: 1570022 | P39: =AVERAGE(F39:O39) -> 1812839.2 | U39: 委託料 | W39: =K67 -> 17175629 | X39: =L67 -> 18885642 | Y39: =M67 -> 16161047 | Z39: =N67 -> 13583646 | AA39: =O67 -> 13164934 | AB39: =P67 -> 14950335
E40: 法定福利費 | F40: 1580740 | G40: 1545406 | H40: 1419631 | I40: 802571 | J40: 1184413 | K40: 1170458 | L40: 1150209 | M40: 1148697 | N40: 1156088 | O40: 1120349 | P40: =AVERAGE(F40:O40) -> 1227856.2 | U40: その他（物価上昇を考慮する） | W40: =K62+K63+K64+K65+K66+K68+K69+K71+K73+K74+K75 -> 4096110 | X40: =L62+L63+L64+L65+L66+L68+L69+L71+L73+L74+L75 -> 4833373 | Y40: =M62+M63+M64+M65+M66+M68+M69+M71+M73+M74+M75 -> 6189097 | Z40: =N62+N63+N64+N65+N66+N68+N69+N71+N73+N74+N75 -> 5786413 | AA40: =O62+O63+O64+O65+O66+O68+O69+O71+O73+O74+O75 -> 6125089 | AB40: =P62+P63+P64+P65+P66+P68+P69+P71+P73+P74+P75 -> 3796306.5
E41: 退職手当負担金 | F41: 989377 | G41: 972705 | H41: 929859 | I41: 0 | J41: 727869 | K41: 697623 | L41: 702135 | M41: 530697 | N41: 537105 | O41: 552560 | P41: =AVERAGE(F41:O41) -> 663993 | U41: その他（物価上昇を考慮しない）
E42: 備消品費 | F42: 36230 | G42: 16200 | H42: 0 | I42: 60600 | J42: 12000 | K42: 41469 | L42: 0 | M42: 45200 | N42: 102660 | O42: 84896 | P42: =AVERAGE(F42:O42) -> 39925.5 | T42: 受託工事費 | W42: =K76 -> 0 | X42: =L76 -> 0 | Y42: =M76 -> 0 | Z42: =N76 -> 0 | AA42: =O76 -> 0 | AB42: 0
E43: 燃料費 | F43: 8896 | G43: 0 | H43: 0 | I43: 92779 | J43: 77028 | K43: 88370 | L43: 54036 | M43: 57957 | N43: 61255 | O43: 50299 | P43: =AVERAGE(F43:O43) -> 49062 | T43: 総係費 | V43: その他管理業務費 | W43: =SUM(W44:W51) -> 28068995 | X43: =SUM(X44:X51) -> 38902891 | Y43: =SUM(Y44:Y51) -> 34633799 | Z43: =SUM(Z44:Z51) -> 56238492 | AA43: =SUM(AA44:AA51) -> 39372697 | AB43: =SUM(AB44:AB51) -> 31797739
E44: 光熱水費 | F44: 700053 | G44: 670057 | H44: 548910 | I44: 846577 | J44: 776735 | K44: 683820 | L44: 881814 | M44: 1067999 | N44: 1161819 | O44: 940198 | P44: =AVERAGE(F44:O44) -> 827798.2 | U44: 人件費 | W44: =K79+K80+K81+K82+K83 -> 15362936 | X44: =L79+L80+L81+L82+L83 -> 14555234 | Y44: =M79+M80+M81+M82+M83 -> 16036318 | Z44: =N79+N80+N81+N82+N83 -> 33509229 | AA44: =O79+O80+O81+O82+O83 -> 21652038 | AB44: =P79+P80+P81+P82+P83 -> 17988350
E45: 通信運搬費 | F45: 138768 | G45: 137960 | H45: 140377 | I45: 209883 | J45: 226527 | K45: 153892 | L45: 297488 | M45: 392912 | N45: 396880 | O45: 383039 | P45: =AVERAGE(F45:O45) -> 247772.6 | U45: 退職給付費 | W45: 0 | X45: 0 | Y45: 0 | Z45: 0 | AA45: 0 | AB45: 0
E46: 委託料 | F46: 21525180 | G46: 21546970 | H46: 20537602 | I46: 33980932 | J46: 34794366 | K46: 33900347 | L46: 31437870 | M46: 37142870 | N46: 33639873 | O46: 36092000 | P46: =AVERAGE(F46:O46) -> 30459801 | U46: 貸倒引当金繰入額 | W46: 0 | X46: 0 | Y46: 0 | Z46: 0 | AA46: 0 | AB46: 0
E47: 手数料 | F47: 2276000 | G47: 1684500 | H47: 2058500 | I47: 6410600 | J47: 5591900 | K47: 6370940 | L47: 7284500 | M47: 6882600 | N47: 7763964 | O47: 7021650 | P47: =AVERAGE(F47:O47) -> 5334515.4 | U47: 退職給与金 | W47: 0 | X47: 0 | Y47: 0 | Z47: 0 | AA47: 0 | AB47: 0
E48: 使用料及び賃借料 | F48: 0 | G48: 0 | H48: 0 | I48: 0 | J48: 0 | K48: 162000 | L48: 162000 | M48: 194000 | N48: 210000 | O48: 210000 | P48: =AVERAGE(F48:O48) -> 93800 | U48: 修繕費 | W48: =K95 -> 44050 | X48: =L95 -> 0 | Y48: =M95 -> 41350 | Z48: =N95 -> 0 | AA48: =O95 -> 49820 | AB48: =P95 -> 44962
E49: 修繕費 | F49: 2618400 | G49: 0 | H49: 700000 | I49: 2203890 | J49: 1903620 | K49: 4684722 | L49: 8618000 | M49: 1967420 | N49: 0 | O49: 3913900 | P49: =AVERAGE(F49:O49) -> 2660995.2 | U49: 委託料 | W49: =K92 -> 3738298 | X49: =L92 -> 17166788 | Y49: =M92 -> 9892260 | Z49: =N92 -> 14519671 | AA49: =O92 -> 9915945 | AB49: =P92 -> 7403703.5
E50: 動力費 | F50: 2200199 | G50: 1952277 | H50: 1359282 | I50: 2154340 | J50: 2329824 | K50: 2543653 | L50: 6880183 | M50: 7599848 | N50: 9405448 | O50: 8392602 | P50: =AVERAGE(F50:O50) -> 4481765.6 | U50: その他（物価上昇を考慮する） | W50: =K84+K85+K86+K87+K88+K89+K90+K91+K93+K94+K96+K97+K98+K99+K100+K101+K102+K103 -> 8923711 | X50: =L84+L85+L86+L87+L88+L89+L90+L91+L93+L94+L96+L97+L98+L99+L100+L101+L102+L103 -> 7180869 | Y50: =M84+M85+M86+M87+M88+M89+M90+M91+M93+M94+M96+M97+M98+M99+M100+M101+M102+M103 -> 8663871 | Z50: =N84+N85+N86+N87+N88+N89+N90+N91+N93+N94+N96+N97+N98+N99+N100+N101+N102+N103 -> 8209592 | AA50: =O84+O85+O86+O87+O88+O89+O90+O91+O93+O94+O96+O97+O98+O99+O100+O101+O102+O103 -> 7754894 | AB50: =P84+P85+P86+P87+P88+P89+P90+P91+P93+P94+P96+P97+P98+P99+P100+P101+P102+P103 -> 6360723.2
E51: 薬品費 | F51: 1813211 | G51: 1833069 | H51: 1618929 | I51: 2009720 | J51: 2025480 | K51: 2231130 | L51: 2383550 | M51: 2505150 | N51: 2578200 | O51: 3328640 | P51: =AVERAGE(F51:O51) -> 2232707.9 | U51: その他（物価上昇を考慮しない）
E52: 材料費 | F52: 1758080 | G52: 1605000 | H52: 415000 | I52: 0 | J52: 0 | K52: 0 | L52: 705000 | M52: 705000 | N52: 0 | O52: 0 | P52: =AVERAGE(F52:O52) -> 518808 | T52: 減価償却費 | W52: =K104 -> 140426639 | X52: =L104 -> 331709645 | Y52: =M104 -> 389441172 | Z52: =N104 -> 513505522 | AA52: =O104 -> 390906409 | AB52: =P104 -> 2.2341827e+08
E53: 負担金 | F53: 15135758 | G53: 15087015 | H53: 8652106 | I53: 11650515 | J53: 14411989 | K53: 10238170 | L53: 20929080 | M53: 12025866 | N53: 18538915 | O53: 18090022 | P53: =AVERAGE(F53:O53) -> 14475944 | U53: H30末の取得資産 | W53: 140426639 | X53: 331709645 | Y53: 389441172 | Z53: 513505522 | AA53: 390906409 | AB53: =AVERAGE(W53:AA53) -> 3.5319788e+08
E54: 保険料 | F54: 69239 | G54: 69239 | H54: 69239 | I54: 125044 | J54: 99074 | K54: 108887 | L54: 260970 | M54: 477101 | N54: 457371 | O54: 474911 | P54: =AVERAGE(F54:O54) -> 221107.5 | U54: H31以降の取得資産
E55: 雑費 | F55: 0 | G55: 0 | H55: 0 | I55: 6600 | J55: 0 | K55: 46200 | L55: 0 | M55: 6600 | N55: 0 | O55: 6600 | P55: =AVERAGE(F55:O55) -> 6600 | T55: 資産減耗費 | W55: =SUM(W56:W57) -> 0 | X55: =SUM(X56:X57) -> 0 | Y55: =SUM(Y56:Y57) -> 0 | Z55: =SUM(Z56:Z57) -> 0 | AA55: =SUM(AA56:AA57) -> 0 | AB55: 0
D56: 配水及び給水費 | F56: =SUM(F57:F75) -> 28708015 | G56: =SUM(G57:G75) -> 29054607 | H56: =SUM(H57:H75) -> 28651009 | I56: =SUM(I57:I75) -> 42772565 | J56: =SUM(J57:J75) -> 38992946 | K56: =SUM(K57:K75) -> 39566820 | L56: =SUM(L57:L75) -> 36646933 | M56: =SUM(M57:M75) -> 35722581 | ... O56: =SUM(O57:O75) -> 32180340 | P56: =AVERAGE(F56:O56) -> 34923211 | U56: 固定資産除却費
E57: 給料 | F57: 6840000 | G57: 7011300 | H57: 7058700 | I57: 7169100 | J57: 3822600 | K57: 5884200 | L57: 5622900 | M57: 5805000 | N57: 6004500 | O57: 3837000 | P57: =AVERAGE(F57:O57) -> 5905530 | U57: たな卸資産減耗費
E58: 手当+引当金 | F58: =4054523+846141 -> 4900664 | G58: =3418601+865345 -> 4283946 | H58: =3682718+922703 -> 4605421 | I58: =3916703+959961 -> 4876664 | J58: =2731910+798693 -> 3530603 | K58: 3194167 | L58: 2007657 | M58: 1996615 | N58: 2002521 | O58: 1233680 | P58: =AVERAGE(F58:O58) -> 3263193.8 | S58: 営業外費用 | W58: =SUM(W59,W62) -> 39544692 | X58: =SUM(X59,X62) -> 13857270 | Y58: =SUM(Y59,Y62) -> 6414667 | Z58: =SUM(Z59,Z62) -> 6771721 | AA58: =SUM(AA59,AA62) -> 16067781 | AB58: =SUM(AB59,AB62) -> 18069225
E59: 賃金 | F59: 0 | G59: 0 | H59: 0 | I59: 1227520 | J59: 1214368 | K59: 1226424 | L59: 0 | M59: 0 | N59: 0 | O59: 0 | P59: =AVERAGE(F59:O59) -> 366831.2 | T59: 支払利息 | W59: =K114 -> 3322502 | X59: =L114 -> 3316293 | Y59: =M114 -> 3627476 | Z59: =N114 -> 4367904 | AA59: =O114 -> 4944124 | AB59: =P113 -> 10729946
E60: 法定福利費 | F60: 2247701 | G60: 2374680 | H60: 2303626 | I60: 2457210 | J60: 1423691 | K60: 2043807 | L60: 1759221 | M60: 1788715 | N60: 1821518 | O60: 1129185 | P60: =AVERAGE(F60:O60) -> 1934935.4 | U60: R6末の既往債 | W60: =K114 -> 3322502 | X60: =L114 -> 3316293 | Y60: =M114 -> 3627476 | Z60: =N114 -> 4367904 | AA60: =O114 -> 4944124 | AB60: =P114 -> 3390666.4
E61: 退職手当負担金 | F61: 1443245 | G61: 1457688 | H61: 1413820 | I61: 1509093 | J61: 805416 | K61: 1179783 | L61: 1127388 | M61: 873651 | N61: 903677 | O61: 577184 | P61: =AVERAGE(F61:O61) -> 1129094.5 | U61: R7以降の新規債
E62: 備消品費 | F62: 927400 | G62: 174460 | H62: 7490 | I62: 156857 | J62: 218175 | K62: 209910 | L62: 204729 | M62: 438120 | N62: 0 | O62: 450000 | P62: =AVERAGE(F62:O62) -> 278714.1 | T62: 雑支出 | W62: =K115 -> 36222190 | X62: =L115 -> 10540977 | Y62: =M115 -> 2787191 | Z62: =N115 -> 2403817 | AA62: =O115 -> 11123657 | AB62: =P115 -> 7339279.4
E63: 燃料費 | F63: 0 | G63: 0 | H63: 0 | I63: 191371 | J63: 117391 | K63: 124357 | L63: 76433 | M63: 90432 | N63: 55414 | O63: 45436 | P63: =AVERAGE(F63:O63) -> 70083.4 | S63: 特別損失 | W63: =SUM(W64:W67) -> 75141547 | X63: =SUM(X64:X67) -> 0 | Y63: =SUM(Y64:Y67) -> 0 | Z63: =SUM(Z64:Z67) -> 0 | AA63: =SUM(AA64:AA67) -> 0 | AB63: =P78 -> 31797739
E64: 光熱水費 | F64: 38336 | G64: 85574 | H64: 177921 | I64: 886771 | J64: 713231 | K64: 723658 | L64: 739486 | M64: 847360 | N64: 820229 | O64: 687666 | P64: =AVERAGE(F64:O64) -> 572023.2 | T64: 災害臨時損失 | W64: =K118 -> 75141547 | X64: =L118 -> 0 | Y64: =M118 -> 0 | Z64: =N118 -> 0 | AA64: =O118 -> 0 | AB64: =P118 -> 50712200
E65: 印刷製本費 | F65: 0 | G65: 0 | H65: 0 | I65: 0 | J65: 0 | K65: 0 | L65: 0 | M65: 5000 | N65: 0 | O65: 0 | P65: =AVERAGE(F65:O65) -> 500 | T65: その他特別損失 | W65: =K119 -> 0 | X65: =L119 -> 0 | Y65: =M119 -> 0 | Z65: =N119 -> 0 | AA65: =O119 -> 0 | AB65: =P119 -> 1666
E66: 通信運搬費 | F66: 28153 | G66: 27914 | H66: 29059 | I66: 839428 | J66: 864180 | K66: 993512 | L66: 1078816 | M66: 989953 | N66: 1062268 | O66: 1051775 | P66: =AVERAGE(F66:O66) -> 696505.8 | T66: 過年度損益修正損 | W66: =K120 -> 0 | X66: =L120 -> 0 | Y66: =M120 -> 0 | Z66: =N120 -> 0 | AA66: =O120 -> 0 | AB66: =P120 -> 0
E67: 委託料 | F67: 10153814 | G67: 11426491 | H67: 10703946 | I67: 18082032 | J67: 20166170 | K67: 17175629 | L67: 18885642 | M67: 16161047 | N67: 13583646 | O67: 13164934 | P67: =AVERAGE(F67:O67) -> 14950335 | T67: その他特別損失
E68: 手数料 | F68: 0 | G68: 0 | H68: 0 | I68: 107470 | J68: 9700 | K68: 10500 | L68: 15100 | M68: 4100 | N68: 0 | O68: 10200 | P68: =AVERAGE(F68:O68) -> 15707 | R68: 損益 | W68: =W5-W24 -> -154789750 | X68: =X5-X24 -> -36029202 | Y68: =Y5-Y24 -> -37745561 | Z68: =Z5-Z24 -> -101071072 | AA68: =AA5-AA24 -> -59562535 | AB68: =P121 -> -74753090
E69: 使用料及び賃借料 | F69: 3519 | G69: 0 | H69: 6000 | I69: 12478 | J69: 12478 | K69: 174425 | L69: 204600 | M69: 235800 | N69: 251280 | O69: 251280 | P69: =AVERAGE(F69:O69) -> 115186
E70: 修繕費 | F70: 1172000 | G70: 1208000 | H70: 485605 | I70: 125780 | J70: 1321405 | K70: 1577280 | L70: 327448 | M70: 569069 | N70: 3745890 | O70: 3642734 | P70: =AVERAGE(F70:O70) -> 1417521.1
E71: 路面復旧費 | F71: 0 | G71: 3050 | H71: 0 | I71: 0 | J71: 0 | K71: 0 | L71: 0 | M71: 0 | N71: 0 | O71: 0 | P71: =AVERAGE(F71:O71) -> 305
E72: 動力費 | F72: 404888 | G72: 489771 | H72: 1391701 | I72: 3355727 | J72: 2781773 | K72: 3189420 | L72: 2083304 | M72: 2339387 | N72: 3088131 | O72: 2470534 | P72: =AVERAGE(F72:O72) -> 2159463.6
E73: 材料費 | F73: 60748 | G73: 208236 | H73: 164223 | I73: 36960 | J73: 99322 | K73: 0 | L73: 53582 | M73: 153620 | N73: 173180 | O73: 169060 | P73: =AVERAGE(F73:O73) -> 111893.1
E74: 保険料 | F74: 487547 | G74: 303497 | H74: 303497 | I74: 1711004 | J74: 1871943 | K74: 1775248 | L74: 2460627 | M74: 3418112 | N74: 3424042 | O74: 3453072 | P74: =AVERAGE(F74:O74) -> 1920858.9
E75: 雑費 | F75: 0 | G75: 0 | H75: 0 | I75: 27100 | J75: 20500 | K75: 84500 | L75: 0 | M75: 6600 | N75: 0 | O75: 6600 | P75: =AVERAGE(F75:O75) -> 14530
D76: 受託工事費 | F76: =SUM(F77:F77) -> 0 | G76: =SUM(G77:G77) -> 0 | H76: =SUM(H77:H77) -> 0 | I76: =SUM(I77:I77) -> 0 | J76: =SUM(J77:J77) -> 0 | K76: =SUM(K77:K77) -> 0 | L76: =SUM(L77:L77) -> 0 | M76: =SUM(M77:M77) -> 0 | ... O76: =SUM(O77:O77) -> 0 | P76: =AVERAGE(F76:O76) -> 0
E77: 材料費 | F77: 0 | G77: 0 | H77: 0 | I77: 0 | J77: 0 | K77: 0 | L77: 0 | M77: 0 | N77: 0 | O77: 0 | P77: =AVERAGE(F77:O77) -> 0
D78: 総係費 | F78: =SUM(F79:F103) -> 19160695 | G78: =SUM(G79:G103) -> 18223848 | H78: =SUM(H79:H103) -> 24917837 | I78: =SUM(I79:I103) -> 28498527 | J78: =SUM(J79:J103) -> 29959607 | K78: =SUM(K79:K103) -> 28068995 | L78: =SUM(L79:L103) -> 38902891 | M78: =SUM(M79:M103) -> 34633799 | ... O78: =SUM(O79:O103) -> 39372697 | P78: =AVERAGE(F78:O78) -> 31797739
E79: 給料 | F79: 5540400 | G79: 5694300 | H79: 5805000 | I79: 9863400 | J79: 11945400 | K79: 8196300 | L79: 8074574 | M79: 9099300 | N79: 18085718 | O79: 11767500 | P79: =AVERAGE(F79:O79) -> 9407189.2
E80: 手当 | F80: 3489631 | G80: 3052192 | H80: 3979917 | I80: 4435787 | J80: 3895859 | K80: 2877569 | L80: 2354318 | M80: 2852258 | N80: 7094612 | O80: 4407809 | P80: =AVERAGE(F80:O80) -> 3843995.2
E81: 賃金 | F81: 0 | G81: 0 | H81: 0 | I81: 0 | J81: 0 | K81: 0 | L81: 0 | M81: 0 | N81: 0 | O81: 0 | P81: =AVERAGE(F81:O81) -> 0
E82: 法定福利費 | F82: 1829666 | G82: 1910648 | H82: 2062494 | I82: 3428992 | J82: 3714378 | K82: 2645709 | L82: 2402582 | M82: 2715311 | N82: 5602385 | O82: 3705721 | P82: =AVERAGE(F82:O82) -> 3001788.6
E83: 退職手当負担金 | F83: 1169025 | G83: 1188801 | H83: 1163907 | I83: 2076245 | J83: 2521704 | K83: 1643358 | L83: 1723760 | M83: 1369449 | N83: 2726514 | O83: 1771008 | P83: =AVERAGE(F83:O83) -> 1735377.1
E84: 旅費 | F84: 44408 | G84: 0 | H84: 74880 | I84: 12000 | J84: 8000 | K84: 115150 | L84: 67364 | M84: 510918 | N84: 173753 | O84: 145469 | P84: =AVERAGE(F84:O84) -> 115194.2
E85: 報償費 | F85: 0 | G85: 0 | H85: 0 | I85: 0 | J85: 0 | K85: 0 | L85: 0 | M85: 0 | N85: 0 | O85: 0 | P85: =AVERAGE(F85:O85) -> 0
E86: 被服費 | F86: 0 | G86: 0 | H86: 0 | I86: 0 | J86: 0 | K86: 0 | L86: 0 | M86: 0 | N86: 19500 | O86: 0 | P86: =AVERAGE(F86:O86) -> 1950
E87: 備消品費 | F87: 375673 | G87: 268149 | H87: 470466 | I87: 387465 | J87: 388542 | K87: 200844 | L87: 218277 | M87: 258483 | N87: 267688 | O87: 297017 | P87: =AVERAGE(F87:O87) -> 313260.4
E88: 燃料費 | F88: 80313 | G88: 74324 | H88: 75842 | I88: 85058 | J88: 65775 | K88: 55566 | L88: 44656 | M88: 51012 | N88: 44142 | O88: 42453 | P88: =AVERAGE(F88:O88) -> 61914.1
E89: 光熱水費 | F89: 0 | G89: 0 | H89: 0 | I89: 0 | J89: 0 | K89: 0 | L89: 0 | M89: 0 | N89: 0 | O89: 0 | P89: =AVERAGE(F89:O89) -> 0
E90: 印刷製本費 | F90: 220000 | G90: 224750 | H90: 230000 | I90: 247500 | J90: 237200 | K90: 258721 | L90: 605660 | M90: 164360 | N90: 231840 | O90: 374640 | P90: =AVERAGE(F90:O90) -> 279467.1
... E103: その他引当金繰入額 | F103: 691769 | G103: 688346 | H103: 1248443 | I103: 1308107 | J103: 1057098 | K103: 4690921 | L103: 2375544 | M103: 3550618 | N103: 2520591 | O103: 2679255 | P103: =AVERAGE(F103:O103) -> 2081069.2
D104: 減価償却費 | F104: =F105 -> 78879555 | G104: =G105 -> 55521235 | H104: =H105 -> 58556733 | I104: =I105 -> 130141869 | J104: =J105 -> 145093877 | K104: =K105 -> 140426639 | L104: =L105 -> 331709645 | M104: =M105 -> 389441172 | ... O104: =O105 -> 390906409 | P104: =AVERAGE(F104:O104) -> 2.2341827e+08
E105: 有形固定資産減価償却費 | F105: 78879555 | G105: 55521235 | H105: 58556733 | I105: 130141869 | J105: 145093877 | K105: 140426639 | L105: 331709645 | M105: 389441172 | N105: 513505522 | O105: 390906409 | P105: =AVERAGE(F105:O105) -> 2.2341827e+08
D106: 資産減耗費 | F106: =SUM(F107:F108) -> 172601 | G106: =SUM(G107:G108) -> 83900 | H106: =SUM(H107:H108) -> 27300 | I106: =SUM(I107:I108) -> 359890 | J106: =SUM(J107:J108) -> 0 | K106: =SUM(K107:K108) -> 0 | L106: =SUM(L107:L108) -> 0 | M106: =SUM(M107:M108) -> 0 | ... O106: =SUM(O107:O108) -> 0 | P106: =AVERAGE(F106:O106) -> 64369.1
E107: 固定資産除却費 | F107: 172601 | G107: 83900 | H107: 27300 | I107: 359890 | J107: 0 | K107: 0 | L107: 0 | M107: 0 | N107: 0 | O107: 0 | P107: =AVERAGE(F107:O107) -> 64369.1
E108: 棚卸資産減耗費 | F108: 0 | G108: 0 | H108: 0 | I108: 0 | J108: 0 | K108: 0 | L108: 0 | M108: 0 | N108: 0 | O108: 0 | P108: =AVERAGE(F108:O108) -> 0
D109: その他営業費用 | F109: =SUM(F110:F111) -> 157980 | G109: =SUM(G110:G111) -> 104575 | H109: =SUM(H110:H111) -> 54211 | I109: =SUM(I110:I111) -> 0 | J109: =SUM(J110:J111) -> 0 | K109: =SUM(K110:K111) -> 0 | L109: =SUM(L110:L111) -> 0 | M109: =SUM(M110:M111) -> 0 | ... O109: =SUM(O110:O111) -> 0 | P109: =AVERAGE(F109:O109) -> 31676.6
E110: 材料売価原価 | F110: 157980 | G110: 104575 | H110: 54211 | I110: 0 | J110: 0 | K110: 0 | L110: 0 | M110: 0 | N110: 0 | O110: 0 | P110: =AVERAGE(F110:O110) -> 31676.6
F111: 0 | G111: 0 | H111: 0 | I111: 0 | J111: 0 | K111: 0 | L111: 0 | M111: 0 | N111: 0 | O111: 0 | P111: =AVERAGE(F111:O111) -> 0
C112: 営業外費用 | F112: =F113 -> 4463948 | G112: =G113 -> 4510498 | H112: =H113 -> 5038670 | I112: =I113 -> 6277694 | J112: =J113 -> 4352517 | K112: =K113 -> 39544692 | L112: =L113 -> 13857270 | M112: =M113 -> 6414667 | ... O112: =O113 -> 16067781 | P112: =AVERAGE(F112:O112) -> 10729946
...

Sheet 【PL】決算数値入力 (仮保存)
B1: 収益的収支（税抜き） | F1: この色部分を入れる。
B2: DS:女川町水道事業会計収益費用明細書 | P2: （単位：千円） | R2: 収益的収支（税抜き） | W2: （単位：千円）
B3: 款 | C3: 項 | D3: 目 | E3: 節 | F3: 実績期間 | P3: 平均 | R3: 款 | S3: 項 | T3: 目 | V3: 総括原価の区分 | W3: 実績期間 | AB3: 平均値
F4: H26 | G4: H27 | H4: H28 | I4: H29 | J4: H30 | K4: R1 | L4: R2 | M4: R3 | N4: R4 | O4: R5 | W4: R1 | X4: R2 | Y4: R3 | Z4: R4 | AA4: R5
B5: 水道事業収益 | F5: =SUM(F6,F15,F28) -> 0 | G5: =SUM(G6,G15,G28) -> 0 | H5: =SUM(H6,H15,H28) -> 0 | I5: =SUM(I6,I15,I28) -> 0 | J5: =SUM(J6,J15,J28) -> 0 | K5: =SUM(K6,K15,K28) -> 0 | L5: =SUM(L6,L15,L28) -> 0 | M5: =SUM(M6,M15,M28) -> 0 | ... O5: =SUM(O6,O15,O28) -> 504865980 | P5: =AVERAGE(F5:O5) -> 50486598 | R5: 水道事業収益 | W5: =SUM(W6,W11,W18,W19) -> 0 | X5: =SUM(X6,X11,X18,X19) -> 0 | Y5: =SUM(Y6,Y11,Y18,Y19) -> 0 | Z5: =SUM(Z6,Z11,Z18,Z19) -> 0 | AA5: =SUM(AA6,AA11,AA18,AA19) -> 484865980 | AB5: =SUM(AB6,AB11,AB18,AB19) -> 48663718
C6: 営業収益 | F6: =SUM(F7,F9,F11) -> 0 | G6: =SUM(G7,G9,G11) -> 0 | H6: =SUM(H7,H9,H11) -> 0 | I6: =SUM(I7,I9,I11) -> 0 | J6: =SUM(J7,J9,J11) -> 0 | K6: =SUM(K7,K9,K11) -> 0 | L6: =SUM(L7,L9,L11) -> 0 | M6: =SUM(M7,M9,M11) -> 0 | ... O6: =SUM(O7,O9,O11) -> 120750259 | P6: =AVERAGE(F6:O6) -> 12075026 | S6: 営業収益 | W6: =SUM(W7:W10) -> 0 | X6: =SUM(X7:X10) -> 0 | Y6: =SUM(Y7:Y10) -> 0 | Z6: =SUM(Z7:Z10) -> 0 | AA6: =SUM(AA7:AA10) -> 120750259 | AB6: =SUM(AB7:AB10) -> 12252146
D7: 給水収益 | F7: =F8 -> 0 | G7: =G8 -> 0 | H7: =H8 -> 0 | I7: =I8 -> 0 | J7: =J8 -> 0 | K7: =K8 -> 0 | L7: =L8 -> 0 | M7: =M8 -> 0 | ... O7: =O8 -> 120553459 | P7: =AVERAGE(F7:O7) -> 12055346 | T7: 給水収益 | W7: =K7 -> 0 | X7: =L7 -> 0 | Y7: =M7 -> 0 | Z7: =N7 -> 0 | AA7: =O7 -> 120553459 | AB7: =P7 -> 12055346
E8: 水道使用料 | O8: 120553459 | P8: =AVERAGE(F8:O8) -> 120553459 | T8: 加入金 | W8: =K13 -> 0 | X8: =L13 -> 0 | Y8: =M13 -> 0 | Z8: =N13 -> 0 | AA8: =O13 -> 0 | AB8: =P13 -> 0
D9: 受託工事収益 | F9: =F10 -> 0 | G9: =G10 -> 0 | H9: =H10 -> 0 | I9: =I10 -> 0 | J9: =J10 -> 0 | K9: =K10 -> 0 | L9: =L10 -> 0 | M9: =M10 -> 0 | ... O9: =O10 -> 0 | P9: =AVERAGE(F9:O9) -> 0 | T9: 受託工事収益 | W9: =K9 -> 0 | X9: =L9 -> 0 | Y9: =M9 -> 0 | Z9: =N9 -> 0 | AA9: =O9 -> 0 | AB9: =P9 -> 0
E10: 受託工事収益 | O10: 0 | P10: =AVERAGE(F10:O10) -> 0 | T10: その他の営業収益 | W10: =K12 -> 0 | X10: =L12 -> 0 | Y10: =M12 -> 0 | Z10: =N12 -> 0 | AA10: =O12 -> 196800 | AB10: =P12 -> 196800
D11: その他の営業収益 | F11: =SUM(F12:F14) -> 0 | G11: =SUM(G12:G14) -> 0 | H11: =SUM(H12:H14) -> 0 | I11: =SUM(I12:I14) -> 0 | J11: =SUM(J12:J14) -> 0 | K11: =SUM(K12:K14) -> 0 | L11: =SUM(L12:L14) -> 0 | M11: =SUM(M12:M14) -> 0 | ... O11: =SUM(O12:O14) -> 196800 | P11: =AVERAGE(F11:O11) -> 19680 | S11: 営業外収益 | W11: =SUM(W12:W15) -> 0 | X11: =SUM(X12:X15) -> 0 | Y11: =SUM(Y12:Y15) -> 0 | Z11: =SUM(Z12:Z15) -> 0 | AA11: =SUM(AA12:AA15) -> 364115721 | AB11: =SUM(AB12:AB15) -> 36411572
E12: 手数料 | O12: 196800 | P12: =AVERAGE(F12:O12) -> 196800 | T12: 受取利息及び配当金 | W12: =K16 -> 0 | X12: =L16 -> 0 | Y12: =M16 -> 0 | Z12: =N16 -> 0 | AA12: =O16 -> 0 | AB12: =P16 -> 0
E13: 加入金 | O13: 0 | P13: =AVERAGE(F13:O13) -> 0 | T13: 他会計補助金 | W13: =K18 -> 0 | X13: =L18 -> 0 | Y13: =M18 -> 0 | Z13: =N18 -> 0 | AA13: =O18 -> 25117004 | AB13: =P18 -> 2511700.4
E14: 他会計負担金 | O14: 0 | P14: =AVERAGE(F14:O14) -> 0 | T14: 雑収益 | W14: =K20 -> 0 | X14: =L20 -> 0 | Y14: =M20 -> 0 | Z14: =N20 -> 0 | AA14: =O20 -> 2589660 | AB14: =P20 -> 258966
C15: 営業外収益 | F15: =SUM(F16,F18,F20,F24,F26) -> 0 | G15: =SUM(G16,G18,G20,G24,G26) -> 0 | H15: =SUM(H16,H18,H20,H24,H26) -> 0 | I15: =SUM(I16,I18,I20,I24,I26) -> 0 | J15: =SUM(J16,J18,J20,J24,J26) -> 0 | K15: =SUM(K16,K18,K20,K24,K26) -> 0 | L15: =SUM(L16,L18,L20,L24,L26) -> 0 | M15: =SUM(M16,M18,M20,M24,M26) -> 0 | ... O15: =SUM(O16,O18,O20,O24,O26) -> 384115721 | P15: =AVERAGE(F15:O15) -> 38411572 | T15: 長期前受金戻入益 | W15: =SUM(W16:W17) -> 0 | X15: =SUM(X16:X17) -> 0 | Y15: =SUM(Y16:Y17) -> 0 | Z15: =SUM(Z16:Z17) -> 0 | AA15: =SUM(AA16:AA17) -> 336409057 | AB15: =SUM(AB16:AB17) -> 33640906
D16: 受取利息及び配当金 | F16: =F17 -> 0 | G16: =G17 -> 0 | H16: =H17 -> 0 | I16: =I17 -> 0 | J16: =J17 -> 0 | K16: =K17 -> 0 | L16: =L17 -> 0 | M16: =M17 -> 0 | ... O16: =O17 -> 0 | P16: =AVERAGE(F16:O16) -> 0 | U16: H30末の取得資産 | W16: =K26 -> 0 | X16: =L26 -> 0 | Y16: =M26 -> 0 | Z16: =N26 -> 0 | AA16: =O26 -> 336409057 | AB16: =P26 -> 33640906
E17: 預金利息 | O17: 0 | P17: =AVERAGE(F17:O17) -> 0 | U17: H31以降の取得資産
D18: 他会計補助金 | F18: =F19 -> 0 | G18: =G19 -> 0 | H18: =H19 -> 0 | I18: =I19 -> 0 | J18: =J19 -> 0 | K18: =K19 -> 0 | L18: =L19 -> 0 | M18: =M19 -> 0 | ... O18: =O19 -> 25117004 | P18: =AVERAGE(F18:O18) -> 2511700.4 | S18: 引当金戻入益
E19: 他会計補助金 | O19: 25117004 | P19: =AVERAGE(F19:O19) -> 25117004 | S19: 特別利益 | W19: =SUM(W20:W22) -> 0 | X19: =SUM(X20:X22) -> 0 | Y19: =SUM(Y20:Y22) -> 0 | Z19: =SUM(Z20:Z22) -> 0 | AA19: =SUM(AA20:AA22) -> 0 | AB19: =SUM(AB20:AB22) -> 0
D20: 雑収益 | F20: =SUM(F21:F23) -> 0 | G20: =SUM(G21:G23) -> 0 | H20: =SUM(H21:H23) -> 0 | I20: =SUM(I21:I23) -> 0 | J20: =SUM(J21:J23) -> 0 | K20: =SUM(K21:K23) -> 0 | L20: =SUM(L21:L23) -> 0 | M20: =SUM(M21:M23) -> 0 | ... O20: =SUM(O21:O23) -> 2589660 | P20: =AVERAGE(F20:O20) -> 258966 | T20: 固定資産売却益 | W20: =K32 -> 0 | X20: =L32 -> 0 | Y20: =M32 -> 0 | Z20: =N32 -> 0 | AA20: =O32 -> 0 | AB20: =P32 -> 0
E21: その他雑収益 | O21: 2589660 | P21: =AVERAGE(F21:O21) -> 2589660 | T21: 過年度修正益 | W21: =K29 -> 0 | X21: =L29 -> 0 | Y21: =M29 -> 0 | Z21: =N29 -> 0 | AA21: =O29 -> 0 | AB21: =P29 -> 0
E22: 発生品受入益 | O22: 0 | P22: =AVERAGE(F22:O22) -> 0 | T22: その他特別利益
E23: 不用品売却収益 | O23: 0 | P23: =AVERAGE(F23:O23) -> 0 | R23: 水道事業費用 | W23: =SUM(W24,W57,W62) -> 0 | X23: =SUM(X24,X57,X62) -> 0 | Y23: =SUM(Y24,Y57,Y62) -> 0 | Z23: =SUM(Z24,Z57,Z62) -> 0 | AA23: =SUM(AA24,AA57,AA62) -> 0 | AB23: =SUM(AB24,AB57,AB62) -> #DIV/0!
D24: 補助金 | F24: =F25 -> 0 | G24: =G25 -> 0 | H24: =H25 -> 0 | I24: =I25 -> 0 | J24: =J25 -> 0 | K24: =K25 -> 0 | L24: =L25 -> 0 | M24: =M25 -> 0 | ... O24: =O25 -> 20000000 | P24: =AVERAGE(F24:O24) -> 2000000 | S24: 営業費用 | W24: =SUM(W25,W33,W42,W51,W54) -> 0 | X24: =SUM(X25,X33,X42,X51,X54) -> 0 | Y24: =SUM(Y25,Y33,Y42,Y51,Y54) -> 0 | Z24: =SUM(Z25,Z33,Z42,Z51,Z54) -> 0 | AA24: =SUM(AA25,AA33,AA42,AA51,AA54) -> 0 | AB24: =SUM(AB25,AB33,AB42,AB51,AB54) -> #DIV/0!
E25: 国庫補助金 | O25: 20000000 | P25: =AVERAGE(F25:O25) -> 20000000 | T25: 原水及び浄水費 | V25: 原浄水部門費 | W25: =SUM(W26:W32) -> 0 | X25: =SUM(X26:X32) -> 0 | Y25: =SUM(Y26:Y32) -> 0 | Z25: =SUM(Z26:Z32) -> 0 | AA25: =SUM(AA26:AA32) -> 0 | AB25: =SUM(AB26:AB32) -> #DIV/0!
D26: 長期前受金戻入益 | F26: =F27 -> 0 | G26: =G27 -> 0 | H26: =H27 -> 0 | I26: =I27 -> 0 | J26: =J27 -> 0 | K26: =K27 -> 0 | L26: =L27 -> 0 | M26: =M27 -> 0 | ... O26: =O27 -> 336409057 | P26: =AVERAGE(F26:O26) -> 33640906 | U26: 人件費
E27: 長期前受金戻入益 | O27: 336409057 | P27: =AVERAGE(F27:O27) -> 336409057 | U27: 動力費 | W27: =K48 -> 0 | X27: =L48 -> 0 | Y27: =M48 -> 0 | Z27: =N48 -> 0 | AA27: =O48 -> 0 | AB27: =P48 -> #DIV/0!
C28: 特別利益 | F28: =SUM(F31,F29) -> 0 | G28: =SUM(G31,G29) -> 0 | H28: =SUM(H31,H29) -> 0 | I28: =SUM(I31,I29) -> 0 | J28: =SUM(J31,J29) -> 0 | K28: =SUM(K31,K29) -> 0 | L28: =SUM(L31,L29) -> 0 | M28: =SUM(M31,M29) -> 0 | ... O28: =SUM(O31,O29) -> 0 | P28: =AVERAGE(F28:O28) -> 0 | U28: 薬品費 | W28: =K49 -> 0 | X28: =L49 -> 0 | Y28: =M49 -> 0 | Z28: =N49 -> 0 | AA28: =O49 -> 0 | AB28: =P49 -> #DIV/0!
D29: 過年度損益修正益 | F29: =F30 -> 0 | G29: =G30 -> 0 | H29: =H30 -> 0 | I29: =I30 -> 0 | J29: =J30 -> 0 | K29: =K30 -> 0 | L29: =L30 -> 0 | M29: =M30 -> 0 | ... O29: =O30 -> 0 | P29: =AVERAGE(F29:O29) -> 0 | U29: 修繕費 | W29: =K47 -> 0 | X29: =L47 -> 0 | Y29: =M47 -> 0 | Z29: =N47 -> 0 | AA29: =O47 -> 0 | AB29: =P47 -> #DIV/0!
E30: 過年度損益修正益 | O30: 0 | P30: =AVERAGE(F30:O30) -> 0 | U30: 委託料 | W30: =K44 -> 0 | X30: =L44 -> 0 | Y30: =M44 -> 0 | Z30: =N44 -> 0 | AA30: =O44 -> 0 | AB30: =P44 -> #DIV/0!
D31: 固定資産売却益 | F31: =F32 -> 0 | G31: =G32 -> 0 | H31: =H32 -> 0 | I31: =I32 -> 0 | J31: =J32 -> 0 | K31: =K32 -> 0 | L31: =L32 -> 0 | M31: =M32 -> 0 | ... O31: =O32 -> 0 | P31: =AVERAGE(F31:O31) -> 0 | U31: その他（物価上昇を考慮する） | W31: =SUM(K39:K43,K45,K50:K52) -> 0 | X31: =SUM(L39:L43,L45,L50:L52) -> 0 | Y31: =SUM(M39:M43,M45,M50:M52) -> 0 | Z31: =SUM(N39:N43,N45,N50:N52) -> 0 | AA31: =SUM(O39:O43,O45,O50:O52) -> 0 | AB31: =SUM(P39:P43,P45,P50:P52) -> #DIV/0!
E32: 固定資産売却益 | O32: 0 | P32: =AVERAGE(F32:O32) -> 0 | U32: その他（物価上昇を考慮しない） | W32: =K46+K53 -> 0 | X32: =L46+L53 -> 0 | Y32: =M46+M53 -> 0 | Z32: =N46+N53 -> 0 | AA32: =O46+O53 -> 0 | AB32: =P46+P53 -> #DIV/0!
B33: 決算書「水道事業収益」数値 | O33: 504865980 | T33: 配水及び給水費 | V33: 配給水部門費 | W33: =SUM(W34:W40) -> 0 | X33: =SUM(X34:X40) -> 0 | Y33: =SUM(Y34:Y40) -> 0 | Z33: =SUM(Z34:Z40) -> 0 | AA33: =SUM(AA34:AA40) -> 0 | AB33: =SUM(AB34:AB40) -> #DIV/0!
B34: 差異の有無 | F34: =IF(F5=F33,"OK","NG") -> OK | G34: =IF(G5=G33,"OK","NG") -> OK | H34: =IF(H5=H33,"OK","NG") -> OK | I34: =IF(I5=I33,"OK","NG") -> OK | J34: =IF(J5=J33,"OK","NG") -> OK | K34: =IF(K5=K33,"OK","NG") -> OK | L34: =IF(L5=L33,"OK","NG") -> OK | M34: =IF(M5=M33,"OK","NG") -> OK | ... O34: =IF(O5=O33,"OK","NG") -> OK | U34: 人件費
B35: 水道事業費用 | F35: =SUM(F36,F104,F107) -> 0 | G35: =SUM(G36,G104,G107) -> 0 | H35: =SUM(H36,H104,H107) -> 0 | I35: =SUM(I36,I104,I107) -> 0 | J35: =SUM(J36,J104,J107) -> 0 | K35: =SUM(K36,K104,K107) -> 0 | L35: =SUM(L36,L104,L107) -> 0 | M35: =SUM(M36,M104,M107) -> 0 | ... O35: =SUM(O36,O104,O107) -> 0 | P35: =AVERAGE(F35:O35) -> 0 | U35: 動力費 | W35: =K64 -> 0 | X35: =L64 -> 0 | Y35: =M64 -> 0 | Z35: =N64 -> 0 | AA35: =O64 -> 0 | AB35: =P64 -> #DIV/0!
C36: 営業費用 | F36: =SUM(F37,F54,F69,F75,F96,F98,F101) -> 0 | G36: =SUM(G37,G54,G69,G75,G96,G98,G101) -> 0 | H36: =SUM(H37,H54,H69,H75,H96,H98,H101) -> 0 | I36: =SUM(I37,I54,I69,I75,I96,I98,I101) -> 0 | J36: =SUM(J37,J54,J69,J75,J96,J98,J101) -> 0 | K36: =SUM(K37,K54,K69,K75,K96,K98,K101) -> 0 | L36: =SUM(L37,L54,L69,L75,L96,L98,L101) -> 0 | M36: =SUM(M37,M54,M69,M75,M96,M98,M101) -> 0 | ... O36: =SUM(O37,O54,O69,O75,O96,O98,O101) -> 0 | P36: =AVERAGE(F36:O36) -> 0 | U36: 薬品費 | W36: =K65 -> 0 | X36: =L65 -> 0 | Y36: =M65 -> 0 | Z36: =N65 -> 0 | AA36: =O65 -> 0 | AB36: =P65 -> #DIV/0!
D37: 原水及び浄水費 | F37: =SUM(F38:F53) -> 0 | G37: =SUM(G38:G53) -> 0 | H37: =SUM(H38:H53) -> 0 | I37: =SUM(I38:I53) -> 0 | J37: =SUM(J38:J53) -> 0 | K37: =SUM(K38:K53) -> 0 | L37: =SUM(L38:L53) -> 0 | M37: =SUM(M38:M53) -> 0 | ... O37: =SUM(O38:O53) -> 0 | P37: =AVERAGE(F37:O37) -> 0 | U37: 修繕費 | W37: =K63 -> 0 | X37: =L63 -> 0 | Y37: =M63 -> 0 | Z37: =N63 -> 0 | AA37: =O63 -> 0 | AB37: =P63 -> #DIV/0!
E38: 賃金 | P38: =AVERAGE(F38:O38) -> #DIV/0! | U38: 委託料 | W38: =K60 -> 0 | X38: =L60 -> 0 | Y38: =M60 -> 0 | Z38: =N60 -> 0 | AA38: =O60 -> 0 | AB38: =P60 -> #DIV/0!
E39: 備消品費 | P39: =AVERAGE(F39:O39) -> #DIV/0! | U39: その他（物価上昇を考慮する） | W39: =SUM(K55:K59,K61,K66:K67) -> 0 | X39: =SUM(L55:L59,L61,L66:L67) -> 0 | Y39: =SUM(M55:M59,M61,M66:M67) -> 0 | Z39: =SUM(N55:N59,N61,N66:N67) -> 0 | AA39: =SUM(O55:O59,O61,O66:O67) -> 0 | AB39: =SUM(P55:P59,P61,P66:P67) -> #DIV/0!
E40: 燃料費 | P40: =AVERAGE(F40:O40) -> #DIV/0! | U40: その他（物価上昇を考慮しない） | W40: =K62+K68 -> 0 | X40: =L62+L68 -> 0 | Y40: =M62+M68 -> 0 | Z40: =N62+N68 -> 0 | AA40: =O62+O68 -> 0 | AB40: =P62+P68 -> #DIV/0!
E41: 光熱水費 | P41: =AVERAGE(F41:O41) -> #DIV/0! | T41: 受託工事費 | W41: =K69 -> 0 | X41: =L69 -> 0 | Y41: =M69 -> 0 | Z41: =N69 -> 0 | AA41: =O69 -> 0 | AB41: =P69 -> 0
E42: 印刷製本費 | P42: =AVERAGE(F42:O42) -> #DIV/0! | T42: 総係費 | V42: その他管理業務費 | W42: =SUM(W43:W50) -> 0 | X42: =SUM(X43:X50) -> 0 | Y42: =SUM(Y43:Y50) -> 0 | Z42: =SUM(Z43:Z50) -> 0 | AA42: =SUM(AA43:AA50) -> 0 | AB42: =SUM(AB43:AB50) -> #DIV/0!
E43: 通信運搬費 | P43: =AVERAGE(F43:O43) -> #DIV/0! | U43: 人件費 | W43: =SUM(K76:K80) -> 0 | X43: =SUM(L76:L80) -> 0 | Y43: =SUM(M76:M80) -> 0 | Z43: =SUM(N76:N80) -> 0 | AA43: =SUM(O76:O80) -> 0 | AB43: =SUM(P76:P80) -> #DIV/0!
E44: 委託料 | P44: =AVERAGE(F44:O44) -> #DIV/0! | U44: 退職給付費
E45: 手数料 | P45: =AVERAGE(F45:O45) -> #DIV/0! | U45: 貸倒引当金繰入額
E46: 賃借料 | P46: =AVERAGE(F46:O46) -> #DIV/0! | U46: 退職給与金
E47: 修繕費 | P47: =AVERAGE(F47:O47) -> #DIV/0! | U47: 修繕費 | W47: =K90 -> 0 | X47: =L90 -> 0 | Y47: =M90 -> 0 | Z47: =N90 -> 0 | AA47: =O90 -> 0 | AB47: =P90 -> #DIV/0!
E48: 動力費 | P48: =AVERAGE(F48:O48) -> #DIV/0! | U48: 委託料 | W48: =K87 -> 0 | X48: =L87 -> 0 | Y48: =M87 -> 0 | Z48: =N87 -> 0 | AA48: =O87 -> 0 | AB48: =P87 -> #DIV/0!
E49: 薬品費 | P49: =AVERAGE(F49:O49) -> #DIV/0! | U49: その他（物価上昇を考慮する） | W49: =SUM(K81:K86,K88,K91) -> 0 | X49: =SUM(L81:L86,L88,L91) -> 0 | Y49: =SUM(M81:M86,M88,M91) -> 0 | Z49: =SUM(N81:N86,N88,N91) -> 0 | AA49: =SUM(O81:O86,O88,O91) -> 0 | AB49: =SUM(P81:P86,P88,P91) -> #DIV/0!
E50: 材料費 | P50: =AVERAGE(F50:O50) -> #DIV/0! | U50: その他（物価上昇を考慮しない） | W50: =SUM(K89,K92:K95) -> 0 | X50: =SUM(L89,L92:L95) -> 0 | Y50: =SUM(M89,M92:M95) -> 0 | Z50: =SUM(N89,N92:N95) -> 0 | AA50: =SUM(O89,O92:O95) -> 0 | AB50: =SUM(P89,P92:P95) -> #DIV/0!
E51: 受水費 | P51: =AVERAGE(F51:O51) -> #DIV/0! | T51: 減価償却費 | W51: =SUM(W52:W53) -> 0 | X51: =SUM(X52:X53) -> 0 | Y51: =SUM(Y52:Y53) -> 0 | Z51: =SUM(Z52:Z53) -> 0 | AA51: =SUM(AA52:AA53) -> 0 | AB51: =SUM(AB52:AB53) -> 0
E52: 工事請負費 | P52: =AVERAGE(F52:O52) -> #DIV/0! | U52: H30末の取得資産 | W52: =K96 -> 0 | X52: =L96 -> 0 | Y52: =M96 -> 0 | Z52: =N96 -> 0 | AA52: =O96 -> 0 | AB52: =P96 -> 0
E53: 雑費 | P53: =AVERAGE(F53:O53) -> #DIV/0! | U53: H31以降の取得資産
D54: 配水及び給水費 | F54: =SUM(F55:F68) -> 0 | G54: =SUM(G55:G68) -> 0 | H54: =SUM(H55:H68) -> 0 | I54: =SUM(I55:I68) -> 0 | J54: =SUM(J55:J68) -> 0 | K54: =SUM(K55:K68) -> 0 | L54: =SUM(L55:L68) -> 0 | M54: =SUM(M55:M68) -> 0 | ... O54: =SUM(O55:O68) -> 0 | P54: =AVERAGE(F54:O54) -> 0 | T54: 資産減耗費 | W54: =SUM(W55:W56) -> 0 | X54: =SUM(X55:X56) -> 0 | Y54: =SUM(Y55:Y56) -> 0 | Z54: =SUM(Z55:Z56) -> 0 | AA54: =SUM(AA55:AA56) -> 0 | AB54: =SUM(AB55:AB56) -> #DIV/0!
E55: 備消品費 | P55: =AVERAGE(F55:O55) -> #DIV/0! | U55: 固定資産除却費 | W55: =K99 -> 0 | X55: =L99 -> 0 | Y55: =M99 -> 0 | Z55: =N99 -> 0 | AA55: =O99 -> 0 | AB55: =P99 -> #DIV/0!
E56: 燃料費 | P56: =AVERAGE(F56:O56) -> #DIV/0! | U56: たな卸資産減耗費 | W56: =K100 -> 0 | X56: =L100 -> 0 | Y56: =M100 -> 0 | Z56: =N100 -> 0 | AA56: =O100 -> 0 | AB56: =P100 -> #DIV/0!
E57: 光熱水費 | P57: =AVERAGE(F57:O57) -> #DIV/0! | S57: 営業外費用 | W57: =SUM(W58,W61) -> 0 | X57: =SUM(X58,X61) -> 0 | Y57: =SUM(Y58,Y61) -> 0 | Z57: =SUM(Z58,Z61) -> 0 | AA57: =SUM(AA58,AA61) -> 0 | AB57: =SUM(AB58,AB61) -> 0
E58: 印刷製本費 | P58: =AVERAGE(F58:O58) -> #DIV/0! | T58: 支払利息 | W58: =SUM(W59:W60) -> 0 | X58: =SUM(X59:X60) -> 0 | Y58: =SUM(Y59:Y60) -> 0 | Z58: =SUM(Z59:Z60) -> 0 | AA58: =SUM(AA59:AA60) -> 0 | AB58: =SUM(AB59:AB60) -> 0
E59: 通信運搬費 | P59: =AVERAGE(F59:O59) -> #DIV/0! | U59: H30末の既往債 | W59: =K105 -> 0 | X59: =L105 -> 0 | Y59: =M105 -> 0 | Z59: =N105 -> 0 | AA59: =O105 -> 0 | AB59: =P105 -> 0
E60: 委託料 | P60: =AVERAGE(F60:O60) -> #DIV/0! | U60: H31以降の新規債
E61: 手数料 | P61: =AVERAGE(F61:O61) -> #DIV/0! | T61: 雑支出
E62: 賃借料 | P62: =AVERAGE(F62:O62) -> #DIV/0! | S62: 特別損失 | W62: =SUM(W63:W66) -> 0 | X62: =SUM(X63:X66) -> 0 | Y62: =SUM(Y63:Y66) -> 0 | Z62: =SUM(Z63:Z66) -> 0 | AA62: =SUM(AA63:AA66) -> 0 | AB62: =SUM(AB63:AB66) -> 0
E63: 修繕費 | P63: =AVERAGE(F63:O63) -> #DIV/0! | T63: 固定資産売却損
E64: 動力費 | P64: =AVERAGE(F64:O64) -> #DIV/0! | T64: 過年度修正損 | W64: =K108 -> 0 | X64: =L108 -> 0 | Y64: =M108 -> 0 | Z64: =N108 -> 0 | AA64: =O108 -> 0 | AB64: =P108 -> 0
E65: 薬品費 | P65: =AVERAGE(F65:O65) -> #DIV/0! | T65: 臨時損失
E66: 材料費 | P66: =AVERAGE(F66:O66) -> #DIV/0! | T66: その他特別損失
E67: 工事請負費 | P67: =AVERAGE(F67:O67) -> #DIV/0! | R67: 損益 | W67: =W5-W23 -> 0 | X67: =X5-X23 -> 0 | Y67: =Y5-Y23 -> 0 | Z67: =Z5-Z23 -> 0 | AA67: =AA5-AA23 -> 484865980 | AB67: =AB5-AB23 -> #DIV/0!
E68: 雑費 | P68: =AVERAGE(F68:O68) -> #DIV/0!
D69: 受託工事費 | F69: =SUM(F70:F74) -> 0 | G69: =SUM(G70:G74) -> 0 | H69: =SUM(H70:H74) -> 0 | I69: =SUM(I70:I74) -> 0 | J69: =SUM(J70:J74) -> 0 | K69: =SUM(K70:K74) -> 0 | L69: =SUM(L70:L74) -> 0 | M69: =SUM(M70:M74) -> 0 | ... O69: =SUM(O70:O74) -> 0 | P69: =AVERAGE(F69:O69) -> 0
E70: 賃金 | P70: =AVERAGE(F70:O70) -> #DIV/0!
E71: 備消品費 | P71: =AVERAGE(F71:O71) -> #DIV/0!
E72: 委託料 | P72: =AVERAGE(F72:O72) -> #DIV/0!
E73: 材料費 | P73: =AVERAGE(F73:O73) -> #DIV/0!
E74: 工事請負費 | P74: =AVERAGE(F74:O74) -> #DIV/0!
D75: 総係費 | F75: =SUM(F76:F95) -> 0 | G75: =SUM(G76:G95) -> 0 | H75: =SUM(H76:H95) -> 0 | I75: =SUM(I76:I95) -> 0 | J75: =SUM(J76:J95) -> 0 | K75: =SUM(K76:K95) -> 0 | L75: =SUM(L76:L95) -> 0 | M75: =SUM(M76:M95) -> 0 | ... O75: =SUM(O76:O95) -> 0 | P75: =AVERAGE(F75:O75) -> 0
E76: 給料 | P76: =AVERAGE(F76:O76) -> #DIV/0!
E77: 手当 | P77: =AVERAGE(F77:O77) -> #DIV/0!
E78: 賞与等引当金繰入額 | P78: =AVERAGE(F78:O78) -> #DIV/0!
E79: 賃金 | P79: =AVERAGE(F79:O79) -> #DIV/0!
E80: 法定福利費 | P80: =AVERAGE(F80:O80) -> #DIV/0!
E81: 旅費 | P81: =AVERAGE(F81:O81) -> #DIV/0!
E82: 備消品費 | P82: =AVERAGE(F82:O82) -> #DIV/0!
E83: 燃料費 | P83: =AVERAGE(F83:O83) -> #DIV/0!
E84: 光熱水費 | P84: =AVERAGE(F84:O84) -> #DIV/0!
E85: 印刷製本費 | P85: =AVERAGE(F85:O85) -> #DIV/0!
E86: 通信運搬費 | P86: =AVERAGE(F86:O86) -> #DIV/0!
E87: 委託料 | P87: =AVERAGE(F87:O87) -> #DIV/0!
... E95: 雑費 | P95: =AVERAGE(F95:O95) -> #DIV/0!
D96: 減価償却費 | F96: =F97 -> 0 | G96: =G97 -> 0 | H96: =H97 -> 0 | I96: =I97 -> 0 | J96: =J97 -> 0 | K96: =K97 -> 0 | L96: =L97 -> 0 | M96: =M97 -> 0 | ... O96: =O97 -> 0 | P96: =AVERAGE(F96:O96) -> 0
E97: 有形固定資産減価償却費 | P97: =AVERAGE(F97:O97) -> #DIV/0!
D98: 資産減耗費 | F98: =SUM(F99:F100) -> 0 | G98: =SUM(G99:G100) -> 0 | H98: =SUM(H99:H100) -> 0 | I98: =SUM(I99:I100) -> 0 | J98: =SUM(J99:J100) -> 0 | K98: =SUM(K99:K100) -> 0 | L98: =SUM(L99:L100) -> 0 | M98: =SUM(M99:M100) -> 0 | ... O98: =SUM(O99:O100) -> 0 | P98: =AVERAGE(F98:O98) -> 0
E99: 固定資産除却費 | P99: =AVERAGE(F99:O99) -> #DIV/0!
E100: 棚卸資産減耗費 | P100: =AVERAGE(F100:O100) -> #DIV/0!
D101: その他営業費用 | F101: =SUM(F102:F103) -> 0 | G101: =SUM(G102:G103) -> 0 | H101: =SUM(H102:H103) -> 0 | I101: =SUM(I102:I103) -> 0 | J101: =SUM(J102:J103) -> 0 | K101: =SUM(K102:K103) -> 0 | L101: =SUM(L102:L103) -> 0 | M101: =SUM(M102:M103) -> 0 | ... O101: =SUM(O102:O103) -> 0 | P101: =AVERAGE(F101:O101) -> 0
E102: 材料売価原価 | P102: =AVERAGE(F102:O102) -> #DIV/0!
E103: 雑支出 | P103: =AVERAGE(F103:O103) -> #DIV/0!
C104: 営業外費用 | F104: =F105 -> 0 | G104: =G105 -> 0 | H104: =H105 -> 0 | I104: =I105 -> 0 | J104: =J105 -> 0 | K104: =K105 -> 0 | L104: =L105 -> 0 | M104: =M105 -> 0 | ... O104: =O105 -> 0 | P104: =AVERAGE(F104:O104) -> 0
D105: 支払利息及び企業債取扱諸費 | F105: =F106 -> 0 | G105: =G106 -> 0 | H105: =H106 -> 0 | I105: =I106 -> 0 | J105: =J106 -> 0 | K105: =K106 -> 0 | L105: =L106 -> 0 | M105: =M106 -> 0 | ... O105: =O106 -> 0 | P105: =AVERAGE(F105:O105) -> 0
E106: 企業債利息 | P106: =AVERAGE(F106:O106) -> #DIV/0!
C107: 特別損失 | F107: =F108 -> 0 | G107: =G108 -> 0 | H107: =H108 -> 0 | I107: =I108 -> 0 | J107: =J108 -> 0 | K107: =K108 -> 0 | L107: =L108 -> 0 | M107: =M108 -> 0 | ... O107: =O108 -> 0 | P107: =AVERAGE(F107:O107) -> 0
...

Sheet 【BS】決算数値入力
B1: 収益的収支（税抜き）
B2: BS:女川町水道事業会計貸借対照表 | O2: （単位：千円）
B3: 款 | C3: 項 | D3: 目 | E3: 節 | F3: 実績期間
F4: H26 | G4: H27 | H4: H28 | I4: H29 | J4: H30 | K4: R1 | L4: R2 | M4: R3 | N4: R4 | O4: R5
B5: 資産の部 | F5: =F6+F26 -> 2380097996 | G5: =G6+G26 -> 2537722473 | H5: =H6+H26 -> 4801386046 | I5: =I6+I26 -> 12233768878 | J5: =J6+J26 -> 13712547499 | K5: =K6+K26 -> 15321720545 | L5: =L6+L26 -> 13316385816 | M5: =M6+M26 -> 13018106023 | ... O5: =O6+O26 -> 12170791768
C6: 固定資産 | F6: =F7+F22 -> 2147056679 | G6: =G7+G22 -> 1935770531 | H6: =H7+H22 -> 3185400831 | I6: =I7+I22 -> 7267487467 | J6: =J7+J22 -> 10241837798 | K6: =K7+K22 -> 12577603623 | L6: =L7+L22 -> 12376362332 | M6: =M7+M22 -> 12293301793 | ... O6: =O7+O22 -> 11730394419
D7: 有形固定資産 | F7: =SUM(F8,(F9-F10),(F11-F12),(F13-F14),(F15-F16),(F17-F18),(F19-F20),F21) -> 2147007479 | G7: =SUM(G8,(G9-G10),(G11-G12),(G13-G14),(G15-G16),(G17-G18),(G19-G20),G21) -> 1935721331 | H7: =SUM(H8,(H9-H10),(H11-H12),(H13-H14),(H15-H16),(H17-H18),(H19-H20),H21) -> 3185351631 | I7: =SUM(I8,(I9-I10),(I11-I12),(I13-I14),(I15-I16),(I17-I18),(I19-I20),I21) -> 7267438267 | J7: =SUM(J8,(J9-J10),(J11-J12),(J13-J14),(J15-J16),(J17-J18),(J19-J20),J21) -> 10241788598 | K7: =SUM(K8,(K9-K10),(K11-K12),(K13-K14),(K15-K16),(K17-K18),(K19-K20),K21) -> 12577554423 | L7: =SUM(L8,(L9-L10),(L11-L12),(L13-L14),(L15-L16),(L17-L18),(L19-L20),L21) -> 12376313132 | M7: =SUM(M8,(M9-M10),(M11-M12),(M13-M14),(M15-M16),(M17-M18),(M19-M20),M21) -> 12291412593 | ... O7: =SUM(O8,(O9-O10),(O11-O12),(O13-O14),(O15-O16),(O17-O18),(O19-O20),O21) -> 11728505219
E8: 土地 | F8: 45233178 | G8: 45233178 | H8: 45233178 | I8: 46918915 | J8: 46918915 | K8: 46918915 | L8: 46918915 | M8: 46918915 | N8: 46918915 | O8: 46918915
E9: 建物 | F9: 59370402 | G9: 59370402 | H9: 91470402 | I9: 89113320 | J9: 89113320 | K9: 1343128687 | L9: 1343128687 | M9: 826599519 | N9: 826599519 | O9: 826599519
E10: (建)減価償却累計額 | F10: 33818728 | G10: 34777993 | H10: 35737258 | I10: 35628402 | J10: 37580772 | K10: 39396251 | L10: 63693534 | M10: 78177861 | N10: 92652413 | O10: 107126965
E11: 構築物 | F11: 2572383314 | G11: 2268080298 | H11: 2526407046 | I11: 4706136663 | J11: 4706136663 | K11: 5789073943 | L11: 5789073943 | M11: 9380476976 | N11: 9462973196 | O11: 9462973196
E12: (構)減価償却累計額 | F12: 965347881 | G12: 790807786 | H12: 792283372 | I12: 279247134 | J12: 406187489 | K12: 521442915 | L12: 680861584 | M12: 868310357 | N12: 1182092860 | O12: 1375313348
E13: 機械及び装置 | F13: 366676929 | G13: 384212699 | H13: 384597135 | I13: 318156805 | J13: 318156805 | K13: 2592286405 | L13: 2592286405 | M13: 3510077728 | N13: 3510077728 | O13: 3510077728
E14: (機)減価償却累計額 | F14: 221813804 | G14: 235985278 | H14: 246364814 | I14: 166404822 | J14: 182253600 | K14: 196783961 | L14: 343850683 | M14: 530301159 | N14: 714317516 | O14: 896423637
E15: 車両運搬具 | F15: 0 | G15: 0 | H15: 0 | I15: 0 | J15: 0 | K15: 0 | L15: 0 | M15: 0 | N15: 0 | O15: 0
E16: (車)減価償却累計額 | F16: 0 | G16: 0 | H16: 0 | I16: 0 | J16: 0 | K16: 0 | L16: 0 | M16: 0 | N16: 0 | O16: 0
E17: 工具器具及び備品 | F17: 3134000 | G17: 3134000 | H17: 924000 | I17: 924000 | J17: 924000 | K17: 924000 | L17: 924000 | M17: 924000 | N17: 924000 | O17: 924000
E18: (工)減価償却累計額 | F18: 2915700 | G18: 2966100 | H18: 877800 | I18: 877800 | J18: 877800 | K18: 877800 | L18: 877800 | M18: 877800 | N18: 877800 | O18: 877800
E19: 量水器 | F19: 6316071 | G19: 7058898 | H19: 9191977 | I19: 9064993 | J19: 10018309 | K19: 10249740 | L19: 10249740 | M19: 11710950 | N19: 11710950 | O19: 11710950
... E21: 建設仮勘定 | F21: 321704780 | G21: 237428032 | H21: 1207370563 | I21: 2584266044 | J21: 5702756936 | K21: 3559117411 | L21: 3689585765 | M21: 0 | N21: 18025897 | O21: 259008337
D22: 無形固定資産 | F22: =SUM(F23:F25) -> 49200 | G22: =SUM(G23:G25) -> 49200 | H22: =SUM(H23:H25) -> 49200 | I22: =SUM(I23:I25) -> 49200 | J22: =SUM(J23:J25) -> 49200 | K22: =SUM(K23:K25) -> 49200 | L22: =SUM(L23:L25) -> 49200 | M22: =SUM(M23:M25) -> 1889200 | ... O22: =SUM(O23:O25) -> 1889200
E23: 水利権 | F23: 0 | G23: 0 | H23: 0 | I23: 0 | J23: 0 | K23: 0 | L23: 0 | M23: 0 | N23: 0 | O23: 0
E24: 電話加入権 | F24: 49200 | G24: 49200 | H24: 49200 | I24: 49200 | J24: 49200 | K24: 49200 | L24: 49200 | M24: 49200 | N24: 49200 | O24: 49200
E25: その他無形固定資産 | F25: 0 | G25: 0 | H25: 0 | I25: 0 | J25: 0 | K25: 0 | L25: 0 | M25: 1840000 | N25: 1840000 | O25: 1840000
C26: 流動資産 | F26: =SUM(F27:F31) -> 233041317 | G26: =SUM(G27:G31) -> 601951942 | H26: =SUM(H27:H31) -> 1615985215 | I26: =SUM(I27:I31) -> 4966281411 | J26: =SUM(J27:J31) -> 3470709701 | K26: =SUM(K27:K31) -> 2744116922 | L26: =SUM(L27:L31) -> 940023484 | M26: =SUM(M27:M31) -> 724804230 | ... O26: =SUM(O27:O31) -> 440397349
D27: 現金預金 | F27: 111278743 | G27: 387970804 | H27: 541703435 | I27: 2381558496 | J27: 1404969361 | K27: 362817447 | L27: 565026725 | M27: 334744715 | N27: 143864193 | O27: 132458270
D28: 未収金 | F28: 119304242 | G28: 211927898 | H28: 1072286402 | I28: 2430272734 | J28: 1904004223 | K28: 2104310806 | L28: 202810510 | M28: 216699042 | N28: 78306576 | O28: 133778738 | P28: =AVERAGE(F28:O28) -> 8.4737012e+08 | Q28: =ROUND(【BS】決算数値入力!P28/【PL】決算数値入力!P7,3) -> 7.567
D29: 貯蔵品 | F29: 2458332 | G29: 2053240 | H29: 1995378 | I29: 1487206 | J29: 1693453 | K29: 2463653 | L29: 2253062 | M29: 3427286 | N29: 3315927 | O29: 4227154
D30: その他流動資産 | F30: 0 | G30: 0 | H30: 0 | I30: 152962975 | J30: 160042664 | K30: 274525016 | L30: 169933187 | M30: 169933187 | N30: 169933187 | O30: 169933187
D31: 前払金 | F31: 0 | G31: 0 | H31: 0 | I31: 0 | J31: 0 | K31: 0 | L31: 0 | M31: 0 | N31: 0 | O31: 0
B32: 決算書記載の「資産合計」数値 | F32: 2380097996 | G32: 2537722473 | H32: 4801386046 | I32: 12233768878 | J32: 13712547499 | K32: 15321720545 | L32: 13316385816 | M32: 13018106023 | N32: 12275738271
B33: 差異の有無 | F33: =IF(F32=F5,"OK","NG") -> OK | G33: =IF(G32=G5,"OK","NG") -> OK | H33: =IF(H32=H5,"OK","NG") -> OK | I33: =IF(I32=I5,"OK","NG") -> OK | J33: =IF(J32=J5,"OK","NG") -> OK | K33: =IF(K32=K5,"OK","NG") -> OK | L33: =IF(L32=L5,"OK","NG") -> OK | M33: =IF(M32=M5,"OK","NG") -> OK | ... O33: =IF(O32=O5,"OK","NG") -> NG
B35: 負債の部 | F35: =F36+F40+F46 -> 1035293321 | G35: =G36+G40+G46 -> 1176501757 | H35: =H36+H40+H46 -> 2159362638 | I35: =I36+I40+I46 -> 6917884484 | J35: =J36+J40+J46 -> 5272906202 | K35: =K36+K40+K46 -> 7081250998 | L35: =L36+L40+L46 -> 5259514723 | M35: =M36+M40+M46 -> 4998980491 | ... O35: =O36+O40+O46 -> 4312299843
C36: 固定負債 | F36: =SUM(F37:F39) -> 145506374 | G36: =SUM(G37:G39) -> 143734775 | H36: =SUM(H37:H39) -> 157383556 | I36: =SUM(I37:I39) -> 270451036 | J36: =SUM(J37:J39) -> 332135617 | K36: =SUM(K37:K39) -> 353124203 | L36: =SUM(L37:L39) -> 455771228 | M36: =SUM(M37:M39) -> 591530416 | ... O36: =SUM(O37:O39) -> 763361128
D37: 引当金 | F37: 0 | G37: 0 | H37: 0 | I37: 0 | J37: 0 | K37: 0 | L37: 0 | M37: 0 | N37: 0 | O37: 0
D38: 企業債 | F38: 145506374 | G38: 143734775 | H38: 157383556 | I38: 270451036 | J38: 332135617 | K38: 353124203 | L38: 455771228 | M38: 591530416 | N38: 639346881 | O38: 763361128 | P38: 210154111 | Q38: 145371217 | R38: 93398792 | S38: 51146958 | T38: 28589700 | U38: 20827028 | V38: 15575425 | W38: 11249315 | X38: 7472491 | Y38: 3619451 | Z38: 0
D39: 退職給付引当金 | F39: 0 | G39: 0 | H39: 0 | I39: 0 | J39: 0 | K39: 0 | L39: 0 | M39: 0 | N39: 0 | O39: 0
C40: 流動負債 | F40: =SUM(F41:F45) -> 44339482 | G40: =SUM(G41:G45) -> 419166341 | H40: =SUM(H41:H45) -> 1446854865 | I40: =SUM(I41:I45) -> 4707571986 | J40: =SUM(J41:J45) -> 3098278789 | K40: =SUM(K41:K45) -> 2331458110 | L40: =SUM(L41:L45) -> 671046620 | M40: =SUM(M41:M45) -> 442806688 | ... O40: =SUM(O41:O45) -> 217640899
D41: 一時借入金 | F41: 0 | G41: 198000000 | H41: 852000000 | I41: 2830000000 | J41: 3000000000 | K41: 1800000000 | L41: 600000000 | M41: 260000000 | N41: 100000000 | O41: 200000000
D42: 未払金 | F42: 40802389 | G42: 216756487 | H42: 588784896 | I42: 1874217518 | J42: 92927555 | K42: 526300084 | L42: 58138057 | M42: 172474380 | N42: 12616598 | O42: 8058954 | P42: =AVERAGE(F42:O42) -> 3.5910769e+08 | Q42: =ROUND(P42/【PL】決算数値入力!P35,3) -> 0.853
D43: その他流動負債（未払消費税・預り金） | F43: 1396044 | G43: 2278700 | H43: 3294100 | I43: 0 | J43: 2567800 | K43: 0 | L43: 7259000 | M43: 3497000 | N43: 2056000 | O43: 3618000
D44: 企業債 | F44: 0 | G44: 0 | H44: 0 | I44: 0 | J44: 0 | K44: 0 | L44: 0 | M44: 0 | N44: 0 | O44: 0
D45: 引当金 | F45: 2141049 | G45: 2131154 | H45: 2775869 | I45: 3354468 | J45: 2783434 | K45: 5158026 | L45: 5649563 | M45: 6835308 | N45: 5805281 | O45: 5963945
C46: 繰延収益 | F46: =SUM(F47:F48) -> 845447465 | G46: =SUM(G47:G48) -> 613600641 | H46: =SUM(H47:H48) -> 555124217 | I46: =SUM(I47:I48) -> 1939861462 | J46: =SUM(J47:J48) -> 1842491796 | K46: =SUM(K47:K48) -> 4396668685 | L46: =SUM(L47:L48) -> 4132696875 | M46: =SUM(M47:M48) -> 3964643387 | ... O46: =SUM(O47:O48) -> 3331297816
D47: 長期前受金 | F47: 1085431218 | G47: 791254564 | H47: 749529898 | I47: 2505086146 | J47: 2505086146 | K47: 5154398182 | L47: 5179316071 | M47: 5347645061 | N47: 5400180403 | O47: 5464906903
D48: 長期前受金収益化累計額 | F48: -239983753 | G48: -177653923 | H48: -194405681 | I48: -565224684 | J48: -662594350 | K48: -757729497 | L48: -1046619196 | M48: -1383001674 | N48: -1802321352 | O48: -2133609087
B50: 資本の部 | F50: =F51+F58 -> 1344804675 | G50: =G51+G58 -> 1361220716 | H50: =H51+H58 -> 2642023408 | I50: =I51+I58 -> 5315884394 | J50: =J51+J58 -> 8439641297 | K50: =K51+K58 -> 8240469547 | L50: =L51+L58 -> 8056871093 | M50: =M51+M58 -> 8019125532 | ... O50: =O51+O58 -> 7858491925
C51: 資本金 | F51: =F52+F56 -> 1046425750 | G51: =G52+G56 -> 1046425750 | H51: =H52+H56 -> 1046425750 | I51: =I52+I56 -> 1384031753 | J51: =J52+J56 -> 1384031753 | K51: =K52+K56 -> 1384031753 | L51: =L52+L56 -> 1384031753 | M51: =M52+M56 -> 1384031753 | ... O51: =O52+O56 -> 1384031753
D52: 自己資本金 | F52: =SUM(F53:F55) -> 1046425750 | G52: =SUM(G53:G55) -> 1046425750 | H52: =SUM(H53:H55) -> 1046425750 | I52: =SUM(I53:I55) -> 1384031753 | J52: =SUM(J53:J55) -> 1384031753 | K52: =SUM(K53:K55) -> 1384031753 | L52: =SUM(L53:L55) -> 1384031753 | M52: =SUM(M53:M55) -> 1384031753 | ... O52: =SUM(O53:O55) -> 1384031753
E53: 固有資本金 | F53: 50817611 | G53: 50817611 | H53: 50817611 | I53: 388423614 | J53: 388423614 | K53: 388423614 | L53: 388423614 | M53: 388423614 | N53: 388423614 | O53: 388423614
E54: 繰入資本金 | F54: 0 | G54: 0 | H54: 0 | I54: 0 | J54: 0 | K54: 0 | L54: 0 | M54: 0 | N54: 0 | O54: 0
E55: 組入資本金 | F55: 995608139 | G55: 995608139 | H55: 995608139 | I55: 995608139 | J55: 995608139 | K55: 995608139 | L55: 995608139 | M55: 995608139 | N55: 995608139 | O55: 995608139
D56: 借入資本金 | F56: =F57 -> 0 | G56: =G57 -> 0 | H56: =H57 -> 0 | I56: =I57 -> 0 | J56: =J57 -> 0 | K56: =K57 -> 0 | L56: =L57 -> 0 | M56: =M57 -> 0 | ... O56: =O57 -> 0
E57: 企業債 | F57: 0 | G57: 0 | H57: 0 | I57: 0 | J57: 0 | K57: 0 | L57: 0 | M57: 0 | N57: 0 | O57: 0
C58: 剰余金 | F58: =F59+F64 -> 298378925 | G58: =G59+G64 -> 314794966 | H58: =H59+H64 -> 1595597658 | I58: =I59+I64 -> 3931852641 | J58: =J59+J64 -> 7055609544 | K58: =K59+K64 -> 6856437794 | L58: =L59+L64 -> 6672839340 | M58: =M59+M64 -> 6635093779 | ... O58: =O59+O64 -> 6474460172
D59: 資本剰余金 | F59: =SUM(F60:F63) -> 537827284 | G59: =SUM(G60:G63) -> 724463034 | H59: =SUM(H60:H63) -> 2052969553 | I59: =SUM(I60:I63) -> 4438683015 | J59: =SUM(J60:J63) -> 7603799559 | K59: =SUM(K60:K63) -> 7559417559 | L59: =SUM(L60:L63) -> 7559417559 | M59: =SUM(M60:M63) -> 7559417559 | ... O59: =SUM(O60:O63) -> 7559417559
E60: 工事負担金 | F60: 119576484 | G60: 119576484 | H60: 122976484 | I60: 122976484 | J60: 165809665 | K60: 165809665 | L60: 165809665 | M60: 165809665 | N60: 165809665 | O60: 165809665
E61: 他会計補助金 | F61: 0 | G61: 0 | H61: 0 | I61: 0 | J61: 0 | K61: 0 | L61: 0 | M61: 0 | N61: 0 | O61: 0
E62: 国県補助金 | F62: 418250800 | G62: 604886550 | H62: 1929993069 | I62: 4315706531 | J62: 7437989894 | K62: 7393607894 | L62: 7393607894 | M62: 7393607894 | N62: 7393607894 | O62: 7393607894
E63: 受贈財産評価額 | F63: 0 | G63: 0 | H63: 0 | I63: 0 | J63: 0 | K63: 0 | L63: 0 | M63: 0 | N63: 0 | O63: 0
D64: 利益剰余金 | F64: =SUM(F65:F69) -> -239448359 | G64: =SUM(G65:G69) -> -409668068 | H64: =SUM(H65:H69) -> -457371895 | I64: =SUM(I65:I69) -> -506830374 | J64: =SUM(J65:J69) -> -548190015 | K64: =SUM(K65:K69) -> -702979765 | L64: =SUM(L65:L69) -> -886578219 | M64: =SUM(M65:M69) -> -924323780 | ... O64: =SUM(O65:O69) -> -1084957387
E65: 減債積立金 | F65: 0 | G65: 0 | H65: 0 | I65: 0 | J65: 0 | K65: 0 | L65: 0 | M65: 0 | N65: 0 | O65: 0
E66: 利益積立金 | F66: 0 | G66: 0 | H66: 0 | I66: 0 | J66: 0 | K66: 0 | L66: 0 | M66: 0 | N66: 0 | O66: 0
E67: 建設改良積立金 | F67: 0 | G67: 0 | H67: 0 | I67: 0 | J67: 0 | K67: 0 | L67: 0 | M67: 0 | N67: 0 | O67: 0
E68: 過年度収益化利益額 | F68: 0 | G68: 0 | H68: 0 | I68: 0 | J68: 0 | K68: 0 | L68: 0 | M68: 0 | N68: 0 | O68: 0
E69: 当年度未処分利益剰余金 | F69: -239448359 | G69: -409668068 | H69: -457371895 | I69: -506830374 | J69: -548190015 | K69: -702979765 | L69: -886578219 | M69: -924323780 | N69: -1025394852 | O69: -1084957387
B70: 負債・資本合計 | F70: =F35+F50 -> 2380097996 | G70: =G35+G50 -> 2537722473 | H70: =H35+H50 -> 4801386046 | I70: =I35+I50 -> 12233768878 | J70: =J35+J50 -> 13712547499 | K70: =K35+K50 -> 15321720545 | L70: =L35+L50 -> 13316385816 | M70: =M35+M50 -> 13018106023 | ... O70: =O35+O50 -> 12170791768
B71: 決算書記載の「負債資本合計」数値 | F71: 2380097996 | G71: 2537722473 | H71: 4801386046 | I71: 12233768878 | J71: 13712547499 | K71: 15321720545 | L71: 13316385816 | M71: 13018106023 | N71: 12275738271 | O71: 12170791768
B72: 差異の有無 | F72: =IF(F70=F71,"OK","NG") -> OK | G72: =IF(G70=G71,"OK","NG") -> OK | H72: =IF(H70=H71,"OK","NG") -> OK | I72: =IF(I70=I71,"OK","NG") -> OK | J72: =IF(J70=J71,"OK","NG") -> OK | K72: =IF(K70=K71,"OK","NG") -> OK | L72: =IF(L70=L71,"OK","NG") -> OK | M72: =IF(M70=M71,"OK","NG") -> OK | ... O72: =IF(O70=O71,"OK","NG") -> OK
F75: 借入利率算定
E76: 企業債残高 | F76: =F38+F44 -> 145506374 | G76: =G38+G44 -> 143734775 | H76: =H38+H44 -> 157383556 | I76: =I38+I44 -> 270451036 | J76: =J38+J44 -> 332135617 | K76: =K38+K44 -> 353124203 | L76: =L38+L44 -> 455771228 | M76: =M38+M44 -> 591530416 | ... O76: =O38+O44 -> 763361128
E77: 支払利息 | F77: =【PL】決算数値入力!F115 -> 1900238 | G77: =【PL】決算数値入力!G115 -> 1792988 | H77: =【PL】決算数値入力!H115 -> 2378047 | I77: =【PL】決算数値入力!I115 -> 3196288 | J77: =【PL】決算数値入力!J115 -> 1047401 | K77: =【PL】決算数値入力!K115 -> 36222190 | L77: =【PL】決算数値入力!L115 -> 10540977 | M77: =【PL】決算数値入力!M115 -> 2787191 | ... O77: =【PL】決算数値入力!O115 -> 11123657 | P77: 平均値
E78: 利率 | G78: =G77/AVERAGE(F76:G76) -> 0.012397876 | H78: =H77/AVERAGE(G76:H76) -> 0.015794767 | I78: =I77/AVERAGE(H76:I76) -> 0.0149417 | J78: =J77/AVERAGE(I76:J76) -> 0.0034763498 | K78: =K77/AVERAGE(J76:K76) -> 0.10571812 | L78: =L77/AVERAGE(K76:L76) -> 0.026062644 | M78: =M77/AVERAGE(L76:M76) -> 0.0053226136 | N78: =N77/AVERAGE(M76:N76) -> 0.0039058597 | O78: =O77/AVERAGE(N76:O76) -> 0.01586026 | P78: =AVERAGE(G78:O78) -> 0.02260891

Sheet 【統計】水道統計指標
B1: 水道統計（女川町） | I1: ↓女川町の状況を確認して入力
B2: DS：水道用水供給事業調査表 | I2: ※H23資料なし。（H24資料内、前年度数値より入力）
B3: 項目 | C3: 該当箇所 | D3: コード | E3: 該当ページ | F3: 単位 | G3: H26 | H3: H27 | I3: H28 | J3: H29 | K3: H30 | L3: R1 | M3: R2 | N3: R3 | O3: R4 | P3: R5 | Q3: 平均
B4: 人口 行政区域内人口 | C4: （１－６）事業計画と水道普及 水道の普及状況 | D4: 0201 | E4: 2 | F4: 人 | G4: 7012 | H4: 6818 | I4: 6668 | J4: 6575 | K4: 6466 | L4: 6337 | M4: 6211 | N4: 6033 | O4: 5928 | P4: 6263 | Q4: =AVERAGE(G4:P4) -> 6431.1
B5: 人口 給水区域内人口 | C5: （１－６）事業計画と水道普及 水道の普及状況 | D5: 0202 | E5: 2 | F5: 人 | G5: 5621 | H5: 5526 | I5: 5500 | J5: 6575 | K5: 6466 | L5: 6337 | M5: 6209 | N5: 6031 | O5: 5926 | P5: 6263 | Q5: =AVERAGE(G5:P5) -> 6045.4
B6: 人口 計画給水人口 | C6: （１－６）事業計画と水道普及 水道の普及状況 | D6: 0204 | E6: 2 | F6: 人 | G6: 12000 | H6: 12000 | I6: 12000 | J6: 8055 | K6: 8055 | L6: 8055 | M6: 8055 | N6: 8055 | O6: 8055 | P6: 7600 | Q6: =AVERAGE(G6:P6) -> 9193
B7: 人口 現在給水人口 | C7: （１－６）事業計画と水道普及 水道の普及状況 | D7: 0206 | E7: 2 | F7: 人 | G7: 5620 | H7: 5525 | I7: 5499 | J7: 6572 | K7: 6463 | L7: 6335 | M7: 6209 | N7: 6031 | O7: 5926 | P7: 5317 | Q7: =AVERAGE(G7:P7) -> 5949.7
B8: 人口 給水普及率 | C8: （１－６）事業計画と水道普及 水道の普及状況 | D8: 0208 | E8: 2 | F8: ％ | G8: 100 | H8: 100 | I8: 100 | J8: 100 | K8: 100 | L8: 100 | M8: 100 | N8: 100 | O8: 100 | P8: 84.9 | Q8: =AVERAGE(G8:P8) -> 98.49
B9: 世帯数 行政区域内世帯数 | C9: （１－６）事業計画と水道普及 水道の普及状況 | D9: 0209 | E9: 2 | F9: 戸 | G9: 3179 | H9: 3153 | I9: 3137 | K9: 3125 | L9: 3105 | M9: 3074 | N9: 2975 | O9: 3014 | P9: 3045 | Q9: =AVERAGE(G9:P9) -> 3089.6667
B10: 世帯数 給水区域内世帯数 | C10: （１－６）事業計画と水道普及 水道の普及状況 | D10: 0210 | E10: 2 | F10: 戸 | G10: 2578 | H10: 2563 | I10: 2587 | K10: 3125 | L10: 3105 | M10: 3074 | N10: 2975 | O10: 3014 | P10: 3045 | Q10: =AVERAGE(G10:P10) -> 2896.2222
B11: 世帯数 現在給水世帯数 | C11: （１－６）事業計画と水道普及 水道の普及状況 | D11: 0212 | E11: 2 | F11: 戸 | G11: 2577 | H11: 2562 | I11: 2586 | K11: 3122 | L11: 3103 | M11: 3072 | N11: 2973 | O11: 3012 | P11: 3045 | Q11: =AVERAGE(G11:P11) -> 2894.6667
B12: 年間給水量 年間給水量 | C12: （３－２）給水状況 取水量・浄水量・給水量 | D12: 5020 | E12: 11 | F12: 千㎥ | G12: =G13+G16 -> 1035 | H12: =H13+H16 -> 1014 | I12: =I13+I16 -> 0 | J12: =J13+J16 -> 1168 | K12: =K13+K16 -> 1159 | L12: =L13+L16 -> 1112 | M12: =M13+M16 -> 1144 | N12: =N13+N16 -> 1207 | ... P12: =P13+P16 -> 1152 | Q12: =AVERAGE(G12:P12) -> 1018.1
B13: 年間給水量 有効水量 | C13: （３－２）給水状況 取水量・浄水量・給水量 | D13: 5021 | E13: 11 | F13: 千㎥ | G13: =G14+G15 -> 835 | H13: =H14+H15 -> 885 | I13: =I14+I15 -> 0 | J13: =J14+J15 -> 1054 | K13: =K14+K15 -> 1089 | L13: =L14+L15 -> 1077 | M13: =M14+M15 -> 1116 | N13: =N14+N15 -> 1155 | ... P13: =P14+P15 -> 937 | Q13: =AVERAGE(G13:P13) -> 928.5
B14: 年間給水量 内訳 有収水量 | C14: （３－２）給水状況 取水量・浄水量・給水量 | D14: 5022 | E14: 11 | F14: 千㎥ | G14: 791 | H14: 841 | J14: 1004 | K14: 1009 | L14: 986 | M14: 1024 | N14: 1053 | O14: 1028 | P14: 913 | Q14: =AVERAGE(G14:P14) -> 961
B15: 年間給水量 内訳 無収水量 | C15: （３－２）給水状況 取水量・浄水量・給水量 | D15: 5023 | E15: 11 | F15: 千㎥ | G15: 44 | H15: 44 | J15: 50 | K15: 80 | L15: 91 | M15: 92 | N15: 102 | O15: 109 | P15: 24 | Q15: =AVERAGE(G15:P15) -> 70.666667
B16: 年間給水量 無効水量 | C16: （３－２）給水状況 取水量・浄水量・給水量 | D16: 5024 | E16: 11 | F16: 千㎥ | G16: 200 | H16: 129 | J16: 114 | K16: 70 | L16: 35 | M16: 28 | N16: 52 | O16: 53 | P16: 215 | Q16: =AVERAGE(G16:P16) -> 99.555556
B17: 口径別給水契約数 13㎜ | C17: （３－４）給水状況 口径別給水契約数及び年間有収水量 | D17: 5329 | E17: 12 | F17: 件 | G17: 1602 | H17: 1432 | I17: 1027 | J17: 789 | K17: 789 | L17: 745 | M17: 728 | N17: 705 | O17: 698 | P17: 1870 | Q17: =AVERAGE(G17:P17) -> 1038.5
B18: 口径別給水契約数 20㎜ | C18: （３－４）給水状況 口径別給水契約数及び年間有収水量 | D18: 5331 | E18: 12 | F18: 件 | G18: 1124 | H18: 1379 | I18: 1889 | J18: 2062 | K18: 2062 | L18: 2132 | M18: 2133 | N18: 2141 | O18: 2142 | P18: 175 | Q18: =AVERAGE(G18:P18) -> 1723.9
B19: 口径別給水契約数 25㎜ | C19: （３－４）給水状況 口径別給水契約数及び年間有収水量 | D19: 5332 | E19: 12 | F19: 件 | G19: 56 | H19: 71 | I19: 71 | J19: 73 | K19: 73 | L19: 70 | M19: 69 | N19: 69 | O19: 69 | P19: 30 | Q19: =AVERAGE(G19:P19) -> 65.1
B20: 口径別給水契約数 30㎜ | C20: （３－４）給水状況 口径別給水契約数及び年間有収水量 | D20: 5333 | E20: 12 | F20: 件 | G20: 0 | H20: 0 | I20: 0 | J20: 0 | K20: 0 | L20: 0 | M20: 0 | N20: 0 | O20: 0 | P20: 12 | Q20: =AVERAGE(G20:P20) -> 1.2
B21: 口径別給水契約数 40㎜ | C21: （３－４）給水状況 口径別給水契約数及び年間有収水量 | D21: 5334 | E21: 12 | F21: 件 | G21: 45 | H21: 55 | I21: 61 | J21: 57 | K21: 57 | L21: 64 | M21: 72 | N21: 72 | O21: 72 | P21: 9 | Q21: =AVERAGE(G21:P21) -> 56.4
B22: 口径別給水契約数 50㎜ | C22: （３－４）給水状況 口径別給水契約数及び年間有収水量 | D22: 5335 | E22: 12 | F22: 件 | G22: 18 | H22: 23 | I22: 20 | J22: 20 | K22: 20 | L22: 21 | M22: 19 | N22: 21 | O22: 22 | P22: 12 | Q22: =AVERAGE(G22:P22) -> 19.6
B23: 口径別給水契約数 75㎜ | C23: （３－４）給水状況 口径別給水契約数及び年間有収水量 | D23: 5336 | E23: 12 | F23: 件 | G23: 6 | H23: 7 | I23: 5 | J23: 6 | K23: 6 | L23: 6 | M23: 8 | N23: 8 | O23: 8 | P23: 6 | Q23: =AVERAGE(G23:P23) -> 6.6
B24: 口径別給水契約数 100㎜ | C24: （３－４）給水状況 口径別給水契約数及び年間有収水量 | D24: 5337 | E24: 12 | F24: 件 | G24: 5 | H24: 5 | I24: 3 | J24: 4 | K24: 4 | L24: 4 | M24: 3 | N24: 3 | O24: 3 | P24: 1 | Q24: =AVERAGE(G24:P24) -> 3.5
B25: 口径別給水契約数 合計 | C25: （３－４）給水状況 口径別給水契約数及び年間有収水量 | D25: 5342 | E25: 12 | F25: 件 | G25: =SUM(G17:G24) -> 2856 | H25: =SUM(H17:H24) -> 2972 | I25: =SUM(I17:I24) -> 3076 | J25: =SUM(J17:J24) -> 3011 | K25: =SUM(K17:K24) -> 3011 | L25: =SUM(L17:L24) -> 3042 | M25: =SUM(M17:M24) -> 3032 | N25: =SUM(N17:N24) -> 3019 | ... P25: =SUM(P17:P24) -> 2115 | Q25: =AVERAGE(G25:P25) -> 2914.8
B26: 口径別給水有収水量 13㎜ | C26: （３－４）給水状況 口径別給水契約数及び年間有収水量 | D26: 5344 | E26: 12 | F26: 千㎥ | G26: 502 | H26: 463 | I26: 391 | J26: 295 | K26: 125 | L26: 116 | M26: 114 | N26: 108 | O26: 103 | P26: 419 | Q26: =AVERAGE(G26:P26) -> 263.6
B27: 口径別給水有収水量 20㎜ | C27: （３－４）給水状況 口径別給水契約数及び年間有収水量 | D27: 5346 | E27: 12 | F27: 千㎥ | G27: 451 | H27: 504 | I27: 601 | J27: 714 | K27: 382 | L27: 397 | M27: 410 | N27: 396 | O27: 378 | P27: 48 | Q27: =AVERAGE(G27:P27) -> 428.1
B28: 口径別給水有収水量 25㎜ | C28: （３－４）給水状況 口径別給水契約数及び年間有収水量 | D28: 5347 | E28: 12 | F28: 千㎥ | G28: 125 | H28: 150 | I28: 158 | J28: 148 | K28: 67 | L28: 62 | M28: 62 | N28: 65 | O28: 67 | P28: 24 | Q28: =AVERAGE(G28:P28) -> 92.8
B29: 口径別給水有収水量 30㎜ | C29: （３－４）給水状況 口径別給水契約数及び年間有収水量 | D29: 5348 | E29: 12 | F29: 千㎥ | G29: 0 | H29: 0 | I29: 0 | J29: 0 | K29: 0 | L29: 0 | M29: 0 | N29: 0 | O29: 0 | P29: 50 | Q29: =AVERAGE(G29:P29) -> 5
B30: 口径別給水有収水量 40㎜ | C30: （３－４）給水状況 口径別給水契約数及び年間有収水量 | D30: 5349 | E30: 12 | F30: 千㎥ | G30: 307 | H30: 319 | I30: 336 | J30: 342 | K30: 171 | L30: 158 | M30: 165 | N30: 172 | O30: 178 | P30: 58 | Q30: =AVERAGE(G30:P30) -> 220.6
B31: 口径別給水有収水量 50㎜ | C31: （３－４）給水状況 口径別給水契約数及び年間有収水量 | D31: 5350 | E31: 12 | F31: 千㎥ | G31: 263 | H31: 282 | I31: 282 | J31: 278 | K31: 141 | L31: 142 | M31: 145 | N31: 149 | O31: 146 | P31: 85 | Q31: =AVERAGE(G31:P31) -> 191.3
B32: 口径別給水有収水量 75㎜ | C32: （３－４）給水状況 口径別給水契約数及び年間有収水量 | D32: 5351 | E32: 12 | F32: 千㎥ | G32: 138 | H32: 166 | I32: 182 | J32: 197 | K32: 102 | L32: 97 | M32: 122 | N32: 153 | O32: 148 | P32: 222 | Q32: =AVERAGE(G32:P32) -> 152.7
B33: 口径別給水有収水量 100㎜ | C33: （３－４）給水状況 口径別給水契約数及び年間有収水量 | D33: 5352 | E33: 12 | F33: 千㎥ | G33: 41 | H33: 38 | I33: 36 | J33: 33 | K33: 22 | L33: 17 | M33: 15 | N33: 12 | O33: 10 | P33: 7 | Q33: =AVERAGE(G33:P33) -> 23.1
B34: 口径別給水有収水量 合計 | C34: （３－４）給水状況 口径別給水契約数及び年間有収水量 | D34: 5357 | E34: 12 | F34: 千㎥ | G34: =SUM(G26:G33) -> 1827 | H34: =SUM(H26:H33) -> 1922 | I34: =SUM(I26:I33) -> 1986 | J34: =SUM(J26:J33) -> 2007 | K34: =SUM(K26:K33) -> 1010 | L34: =SUM(L26:L33) -> 989 | M34: =SUM(M26:M33) -> 1033 | N34: =SUM(N26:N33) -> 1055 | ... P34: =SUM(P26:P33) -> 913 | Q34: =AVERAGE(G34:P34) -> 1377.2
B36: ※以下、削除予定。（確認の後、削除）
B37: 差異の確認（コード：5342) | G37: =IF(G25=G38,"OK","NG") -> NG | H37: =IF(H25=H38,"OK","NG") -> NG | I37: =IF(I25=I38,"OK","NG") -> NG | J37: =IF(J25=J38,"OK","NG") -> NG | K37: =IF(K25=K38,"OK","NG") -> NG | L37: =IF(L25=L38,"OK","NG") -> NG | M37: =IF(M25=M38,"OK","NG") -> NG | N37: =IF(N25=N38,"OK","NG") -> NG | ... P37: =IF(P25=P38,"OK","NG") -> OK
G38: 1961 | H38: 1978 | I38: 1997 | J38: 2000 | K38: 2016 | L38: 2050 | M38: 2063 | N38: 2080 | O38: 2086 | P38: 2115
B39: 差異の確認（コード：5357) | G39: =IF(G34=G40,"OK","NG") -> NG | H39: =IF(H34=H40,"OK","NG") -> NG | I39: =IF(I34=I40,"OK","NG") -> NG | J39: =IF(J34=J40,"OK","NG") -> NG | K39: =IF(K34=K40,"OK","NG") -> NG | L39: =IF(L34=L40,"OK","NG") -> NG | M39: =IF(M34=M40,"OK","NG") -> NG | N39: =IF(N34=N40,"OK","NG") -> NG | ... P39: =IF(P34=P40,"OK","NG") -> OK
G40: 883 | H40: 928 | I40: 843 | J40: 922 | K40: 909 | L40: 864 | M40: 862 | N40: 859 | O40: 894 | P40: 913

Sheet 【成行】財政シミュ
B2: 収益的収支（税抜き） | N2: （単位：千円） | T2: 1 | U2: 2 | V2: 3 | W2: 4 | X2: 5 | Y2: 6 | Z2: 7 | AA2: 8 | AB2: 9 | AC2: 10 | AD2: 11 | AE2: 12 | AF2: 13 | AG2: 14 | AH2: 15 | AI2: 16 | AJ2: 17 | AK2: 18 | AL2: 19 | AM2: 20 | AN2: 21 | AO2: 22 | AP2: 23 | AQ2: 24 | AR2: 25 | AS2: 26 | AT2: 27 | AU2: 28 | AV2: 29 | AW2: 30 | AX2: 31 | AY2: 32 | AZ2: 33 | BA2: 34 | BB2: 35 | BC2: 36 | BD2: 37 | BE2: 38 | BF2: 39 | BG2: 40 | BH2: 41 | BI2: 42 | BJ2: 43 | BK2: 44 | BL2: 45 | BM2: 46 | BN2: 47 | BO2: 48 | BP2: 49 | BQ2: 50
B3: 款 | C3: 項 | D3: 目 | F3: 総括原価の区分 | J3: 控除 項目 | K3: 将来設定条件 | L3: 物価 | M3: 算出根拠 | N3: 実績期間 | S3: 平均値 | T3: 料金算定期間 | X3: 参考期間
G4: 需要家費 | H4: 固定費 | I4: 変動費 | N4: R1 | O4: R2 | P4: R3 | Q4: R4 | R4: R5 | T4: R6 | U4: R7 | V4: R8 | W4: R9 | X4: R10 | Y4: R11 | Z4: R12 | AA4: R13 | AB4: R14 | AC4: R15 | AD4: R16 | AE4: R17 | AF4: R18 | AG4: R19 | AH4: R20 | AI4: R21 | AJ4: R22 | AK4: R23 | AL4: R24 | AM4: R25 | AN4: R26 | AO4: R27 | AP4: R28 | AQ4: R29 | AR4: R30 | AS4: R31 | AT4: R32 | AU4: R33 | AV4: R34 | AW4: R35 | AX4: R36 | AY4: R37 | AZ4: R38 | BA4: R39 | BB4: R40 | BC4: R41 | BD4: R42 | BE4: R43 | BF4: R44 | BG4: R45 | BH4: R46 | BI4: R47 | BJ4: R48 | BK4: R49 | BL4: R50 | BM4: R51 | BN4: R52 | BO4: R53 | BP4: R54 | BQ4: R55
B5: 水道事業収益 | N5: =【PL】決算数値入力!W5 -> 236084433 | O5: =【PL】決算数値入力!X5 -> 471816622 | P5: =【PL】決算数値入力!Y5 -> 506142175 | Q5: =【PL】決算数値入力!Z5 -> 593505600 | R5: =【PL】決算数値入力!AA5 -> 504865980 | S5: =【PL】決算数値入力!AB5 -> 3.4374651e+08 | T5: =SUM(T6,T11,T19,T20) -> 4.897277e+08 | U5: =SUM(U6,U11,U19,U20) -> 4.9683515e+08 | V5: =SUM(V6,V11,V19,V20) -> 5.5440086e+08 | W5: =SUM(W6,W11,W19,W20) -> 5.8790332e+08 | X5: =SUM(X6,X11,X19,X20) -> 5.8128791e+08 | Y5: =SUM(Y6,Y11,Y19,Y20) -> 5.7556906e+08 | Z5: =SUM(Z6,Z11,Z19,Z20) -> 5.669954e+08 | AA5: =SUM(AA6,AA11,AA19,AA20) -> 5.6319106e+08 | ... BQ5: =SUM(BQ6,BQ11,BQ19,BQ20) -> 1.7133013e+08
C6: 営業収益 | N6: =【PL】決算数値入力!W6 -> 115230130 | O6: =【PL】決算数値入力!X6 -> 119471832 | P6: =【PL】決算数値入力!Y6 -> 122357520 | Q6: =【PL】決算数値入力!Z6 -> 119852700 | R6: =【PL】決算数値入力!AA6 -> 120750259 | S6: =【PL】決算数値入力!AB6 -> 112378170 | T6: =SUM(T7:T10) -> 125118797 | U6: =SUM(U7:U10) -> 123815212 | V6: =SUM(V7:V10) -> 121932198 | W6: =SUM(W7:W10) -> 120296885 | X6: =SUM(X7:X10) -> 118705087 | Y6: =SUM(Y7:Y10) -> 117347425 | Z6: =SUM(Z7:Z10) -> 114527804 | AA6: =SUM(AA7:AA10) -> 113135742 | ... BQ6: =SUM(BQ7:BQ10) -> 72995032
D7: 給水収益 | K7: 【収益】給水収益シート参照 | N7: =【PL】決算数値入力!W7 -> 114968230 | O7: =【PL】決算数値入力!X7 -> 119265632 | P7: =【PL】決算数値入力!Y7 -> 122177720 | Q7: =【PL】決算数値入力!Z7 -> 119610300 | R7: =【PL】決算数値入力!AA7 -> 120553459 | S7: =【PL】決算数値入力!AB7 -> 111985280 | T7: ='【収益－現行】給水収益'!S32 -> 124725907 | U7: ='【収益－現行】給水収益'!T32 -> 123422322 | V7: ='【収益－現行】給水収益'!U32 -> 121539308 | W7: ='【収益－現行】給水収益'!V32 -> 119903995 | X7: ='【収益－現行】給水収益'!W32 -> 118312197 | Y7: ='【収益－現行】給水収益'!X32 -> 116954535 | Z7: ='【収益－現行】給水収益'!Y32 -> 114134914 | AA7: ='【収益－現行】給水収益'!Z32 -> 112742852 | ... BQ7: ='【収益－現行】給水収益'!BP32 -> 72602142
D8: 加入金 | N8: =【PL】決算数値入力!W8 -> 0 | O8: =【PL】決算数値入力!X8 -> 0 | P8: =【PL】決算数値入力!Y8 -> 0 | Q8: =【PL】決算数値入力!Z8 -> 0 | R8: =【PL】決算数値入力!AA8 -> 0 | S8: =【PL】決算数値入力!AB8 -> 0 | T8: =S8 -> 0 | U8: =T8 -> 0 | V8: =U8 -> 0 | W8: =V8 -> 0 | X8: =W8 -> 0 | Y8: =X8 -> 0 | Z8: =Y8 -> 0 | AA8: =Z8 -> 0 | ... BQ8: =BP8 -> 0
D9: 受託工事収益 | K9: 計上しない | N9: =【PL】決算数値入力!W9 -> 0 | O9: =【PL】決算数値入力!X9 -> 0 | P9: =【PL】決算数値入力!Y9 -> 0 | Q9: =【PL】決算数値入力!Z9 -> 0 | R9: =【PL】決算数値入力!AA9 -> 0 | S9: =【PL】決算数値入力!AB9 -> 0 | T9: 0 | U9: 0 | V9: 0 | W9: 0 | X9: 0 | Y9: 0 | Z9: 0 | AA9: 0 | AB9: 0 | AC9: 0 | AD9: 0 | AE9: 0 | AF9: 0 | AG9: 0 | AH9: 0 | AI9: 0 | AJ9: 0 | AK9: 0 | AL9: 0 | AM9: 0 | AN9: 0 | AO9: 0 | AP9: 0 | AQ9: 0 | AR9: 0 | AS9: 0 | AT9: 0 | AU9: 0 | AV9: 0 | AW9: 0 | AX9: 0 | AY9: 0 | AZ9: 0 | BA9: 0 | BB9: 0 | BC9: 0 | BD9: 0 | BE9: 0 | BF9: 0 | BG9: 0 | BH9: 0 | BI9: 0 | BJ9: 0 | BK9: 0 | BL9: 0 | BM9: 0 | BN9: 0 | BO9: 0 | BP9: 0 | BQ9: 0
D10: その他の営業収益 | J10: ● | K10: R1~R5決算の平均値で一定 | N10: =【PL】決算数値入力!W10 -> 261900 | O10: =【PL】決算数値入力!X10 -> 206200 | P10: =【PL】決算数値入力!Y10 -> 179800 | Q10: =【PL】決算数値入力!Z10 -> 242400 | R10: =【PL】決算数値入力!AA10 -> 196800 | S10: =【PL】決算数値入力!AB10 -> 392890 | T10: =S10 -> 392890 | U10: =T10 -> 392890 | V10: =U10 -> 392890 | W10: =V10 -> 392890 | X10: =W10 -> 392890 | Y10: =X10 -> 392890 | Z10: =Y10 -> 392890 | AA10: =Z10 -> 392890 | ... BQ10: =BP10 -> 392890
C11: 営業外収益 | N11: =【PL】決算数値入力!W11 -> 120854303 | O11: =【PL】決算数値入力!X11 -> 352344790 | P11: =【PL】決算数値入力!Y11 -> 383784655 | Q11: =【PL】決算数値入力!Z11 -> 473652900 | R11: =【PL】決算数値入力!AA11 -> 384115721 | S11: =【PL】決算数値入力!AB12 -> 15431.1 | T11: =SUM(T12:T16) -> 3.646089e+08 | U11: =SUM(U12:U16) -> 3.7301994e+08 | V11: =SUM(V12:V16) -> 4.3246866e+08 | W11: =SUM(W12:W16) -> 4.6760643e+08 | X11: =SUM(X12:X16) -> 4.6258282e+08 | Y11: =SUM(Y12:Y16) -> 4.5822163e+08 | Z11: =SUM(Z12:Z16) -> 4.524676e+08 | AA11: =SUM(AA12:AA16) -> 4.5005532e+08 | ... BQ11: =SUM(BQ12:BQ16) -> 98335098
D12: 受取利息及び配当金 | J12: ● | K12: R1~R5決算の平均値で一定 | N12: =【PL】決算数値入力!W12 -> 0 | O12: =【PL】決算数値入力!X12 -> 0 | P12: =【PL】決算数値入力!Y12 -> 0 | Q12: =【PL】決算数値入力!Z12 -> 0 | R12: =【PL】決算数値入力!AA12 -> 0 | S12: =【PL】決算数値入力!AB12 -> 15431.1 | T12: =S12 -> 15431.1 | U12: =T12 -> 15431.1 | V12: =U12 -> 15431.1 | W12: =V12 -> 15431.1 | X12: =W12 -> 15431.1 | Y12: =X12 -> 15431.1 | Z12: =Y12 -> 15431.1 | AA12: =Z12 -> 15431.1 | ... BQ12: =BP12 -> 15431.1
D13: 他会計補助金 | J13: ● | K13: 現状の算定式（＝減価償却費＋人件費＋支払利息）で算定 | N13: =【PL】決算数値入力!W13 -> 23034829 | O13: =【PL】決算数値入力!X13 -> 61004862 | P13: =【PL】決算数値入力!Y13 -> 0 | Q13: =【PL】決算数値入力!Z13 -> 25962175 | R13: =【PL】決算数値入力!AA13 -> 25117004 | S13: =【PL】決算数値入力!AB13 -> 13834221 | T13: =T44+T59 -> 25500721 | U13: =U44+U59 -> 33861477 | V13: =V44+V59 -> 38616631 | W13: =W44+W59 -> 47830328 | X13: =X44+X59 -> 55812079 | Y13: =Y44+Y59 -> 63330098 | Z13: =Z44+Z59 -> 67407860 | AA13: =AA44+AA59 -> 71335475 | ... BQ13: =BQ44+BQ59 -> 75107743
D14: 補助金 | V14: 59000000 | W14: 90000000 | X14: 90000000 | Y14: 90000000 | Z14: 90000000 | AA14: 90000000 | AB14: 90000000 | AC14: 90000000 | AD14: 90000000 | AE14: 90000000
D15: 雑収益 | J15: ● | K15: R1~R5決算の平均値で一定 | N15: =【PL】決算数値入力!W15 -> 2684327 | O15: =【PL】決算数値入力!X15 -> 2450229 | P15: =【PL】決算数値入力!Y15 -> 22402177 | Q15: =【PL】決算数値入力!Z15 -> 8371047 | R15: =【PL】決算数値入力!AA15 -> 2589660 | S15: =【PL】決算数値入力!AB15 -> 4890572.8 | T15: =S15 -> 4890572.8 | U15: =T15 -> 4890572.8 | V15: =U15 -> 4890572.8 | W15: =V15 -> 4890572.8 | X15: =W15 -> 4890572.8 | Y15: =X15 -> 4890572.8 | Z15: =Y15 -> 4890572.8 | AA15: =Z15 -> 4890572.8 | ... BQ15: =BP15 -> 4890572.8
D16: 長期前受金戻入益 | N16: =【PL】決算数値入力!W16 -> 95135147 | O16: =【PL】決算数値入力!X16 -> 288889699 | P16: =【PL】決算数値入力!Y16 -> 336382478 | Q16: =【PL】決算数値入力!Z16 -> 419319678 | R16: =【PL】決算数値入力!AA16 -> 336409057 | S16: =【PL】決算数値入力!AB16 -> 1.9672812e+08 | T16: =SUM(T17:T18) -> 334202174 | U16: =SUM(U17:U18) -> 334252462 | V16: =SUM(V17:V18) -> 329946028 | W16: =SUM(W17:W18) -> 3.248701e+08 | X16: =SUM(X17:X18) -> 3.1186474e+08 | Y16: =SUM(Y17:Y18) -> 2.9998553e+08 | Z16: =SUM(Z17:Z18) -> 2.9015374e+08 | AA16: =SUM(AA17:AA18) -> 2.8381384e+08 | ... BQ16: =SUM(BQ17:BQ18) -> 18321351
E17: R6末の取得資産 | K17: 固定資産台帳データに基づく算定額 | N17: =【PL】決算数値入力!W17 -> 95135147 | O17: =【PL】決算数値入力!X17 -> 288889699 | P17: =【PL】決算数値入力!Y17 -> 336382478 | Q17: =【PL】決算数値入力!Z17 -> 419319678 | R17: =【PL】決算数値入力!AA17 -> 336409057 | S17: =【PL】決算数値入力!AB17 -> 1.9672812e+08 | T17: 334202174 | U17: 334252462 | V17: 329946028 | W17: 323203522 | X17: 308882372 | Y17: 295687375 | Z17: 284539789 | AA17: 276884100 | AB17: 273884174 | AC17: 267903518 | AD17: 261262088 | AE17: 205550308 | AF17: 191542873 | AG17: 184974519 | AH17: 179375298 | AI17: 177581276 | AJ17: 160752472 | AK17: 158769256 | AL17: 156848393 | AM17: 155469435 | AN17: 153891335 | AO17: 152287794 | AP17: 149732486 | AQ17: 148229911 | AR17: 147808454 | AS17: 146754939 | AT17: 145900166 | AU17: 144227410 | AV17: 143083103 | AW17: 141709968 | AX17: 140410450 | AY17: 125972764 | AZ17: 121872042 | BA17: 120244124 | BB17: 115023758 | BC17: 101260785 | BD17: 91443893 | BE17: 57528148 | BF17: 39528004 | BG17: 36969798 | BH17: 36224421 | BI17: 35120010 | BJ17: 34484753 | BK17: 34171874 | BL17: 33895777 | BM17: 32945758 | BN17: 29650024 | BO17: 26441622 | BP17: 21615106 | BQ17: 18321351
E18: R7以降の取得資産 | K18: 償却計算額 | N18: =【PL】決算数値入力!W18 -> 0 | O18: =【PL】決算数値入力!X18 -> 0 | P18: =【PL】決算数値入力!Y18 -> 0 | Q18: =【PL】決算数値入力!Z18 -> 0 | R18: =【PL】決算数値入力!AA18 -> 0 | S18: =【PL】決算数値入力!AB18 -> 0 | T18: =新規取得!I5 -> 0 | U18: =新規取得!J5 -> 0 | V18: =新規取得!P5 -> 0 | W18: =新規取得!Q5 -> 1666578.9 | X18: =新規取得!R5 -> 2982368.4 | Y18: =新規取得!S5 -> 4298157.9 | Z18: =新規取得!T5 -> 5613947.4 | AA18: =新規取得!U5 -> 6929736.8 | AB18: =新規取得!V5 -> 6929736.8 | AC18: =新規取得!W5 -> 6929736.8 | ... BQ18: =新規取得!BK5 -> 0
C19: 引当金戻入益 | J19: ● | K19: 計上しない | N19: =【PL】決算数値入力!W19 -> 0 | O19: =【PL】決算数値入力!X19 -> 0 | P19: =【PL】決算数値入力!Y19 -> 0 | Q19: =【PL】決算数値入力!Z19 -> 0 | R19: =【PL】決算数値入力!AA19 -> 0 | S19: =【PL】決算数値入力!AB19 -> 0 | T19: 0 | U19: 0 | V19: 0 | W19: 0 | X19: 0 | Y19: 0 | Z19: 0 | AA19: 0 | AB19: 0 | AC19: 0 | AD19: 0 | AE19: 0 | AF19: 0 | AG19: 0 | AH19: 0 | AI19: 0 | AJ19: 0 | AK19: 0 | AL19: 0 | AM19: 0 | AN19: 0 | AO19: 0 | AP19: 0 | AQ19: 0 | AR19: 0 | AS19: 0 | AT19: 0 | AU19: 0 | AV19: 0 | AW19: 0 | AX19: 0 | AY19: 0 | AZ19: 0 | BA19: 0 | BB19: 0 | BC19: 0 | BD19: 0 | BE19: 0 | BF19: 0 | BG19: 0 | BH19: 0 | BI19: 0 | BJ19: 0 | BK19: 0 | BL19: 0 | BM19: 0 | BN19: 0 | BO19: 0 | BP19: 0 | BQ19: 0
C20: 特別利益 | N20: =【PL】決算数値入力!W20 -> 0 | O20: =【PL】決算数値入力!X20 -> 0 | P20: =【PL】決算数値入力!Y20 -> 0 | Q20: =【PL】決算数値入力!Z20 -> 0 | R20: =【PL】決算数値入力!AA20 -> 0 | S20: =【PL】決算数値入力!AB20 -> 0 | T20: =SUM(T21:T23) -> 0 | U20: =SUM(U21:U23) -> 0 | V20: =SUM(V21:V23) -> 0 | W20: =SUM(W21:W23) -> 0 | X20: =SUM(X21:X23) -> 0 | Y20: =SUM(Y21:Y23) -> 0 | Z20: =SUM(Z21:Z23) -> 0 | AA20: =SUM(AA21:AA23) -> 0 | ... BQ20: =SUM(BQ21:BQ23) -> 0
D21: 固定資産売却益 | J21: ● | K21: 計上しない | N21: =【PL】決算数値入力!W21 -> 0 | O21: =【PL】決算数値入力!X21 -> 0 | P21: =【PL】決算数値入力!Y21 -> 0 | Q21: =【PL】決算数値入力!Z21 -> 0 | R21: =【PL】決算数値入力!AA21 -> 0 | S21: =【PL】決算数値入力!AB21 -> 0 | T21: 0 | U21: 0 | V21: 0 | W21: 0 | X21: 0 | Y21: 0 | Z21: 0 | AA21: 0 | AB21: 0 | AC21: 0 | AD21: 0 | AE21: 0 | AF21: 0 | AG21: 0 | AH21: 0 | AI21: 0 | AJ21: 0 | AK21: 0 | AL21: 0 | AM21: 0 | AN21: 0 | AO21: 0 | AP21: 0 | AQ21: 0 | AR21: 0 | AS21: 0 | AT21: 0 | AU21: 0 | AV21: 0 | AW21: 0 | AX21: 0 | AY21: 0 | AZ21: 0 | BA21: 0 | BB21: 0 | BC21: 0 | BD21: 0 | BE21: 0 | BF21: 0 | BG21: 0 | BH21: 0 | BI21: 0 | BJ21: 0 | BK21: 0 | BL21: 0 | BM21: 0 | BN21: 0 | BO21: 0 | BP21: 0 | BQ21: 0
D22: 過年度修正益 | J22: ● | K22: 計上しない | N22: =【PL】決算数値入力!W22 -> 0 | O22: =【PL】決算数値入力!X22 -> 0 | P22: =【PL】決算数値入力!Y22 -> 0 | Q22: =【PL】決算数値入力!Z22 -> 0 | R22: =【PL】決算数値入力!AA22 -> 0 | S22: =【PL】決算数値入力!AB22 -> 0 | V22: 0 | W22: 0 | X22: 0 | Y22: 0 | Z22: 0 | AA22: 0 | AB22: 0 | AC22: 0 | AD22: 0 | AE22: 0 | AF22: 0 | AG22: 0 | AH22: 0 | AI22: 0 | AJ22: 0 | AK22: 0 | AL22: 0 | AM22: 0 | AN22: 0 | AO22: 0 | AP22: 0 | AQ22: 0 | AR22: 0 | AS22: 0 | AT22: 0 | AU22: 0 | AV22: 0 | AW22: 0 | AX22: 0 | AY22: 0 | AZ22: 0 | BA22: 0 | BB22: 0 | BC22: 0 | BD22: 0 | BE22: 0 | BF22: 0 | BG22: 0 | BH22: 0 | BI22: 0 | BJ22: 0 | BK22: 0 | BL22: 0 | BM22: 0 | BN22: 0 | BO22: 0 | BP22: 0 | BQ22: 0
D23: その他特別利益 | J23: ● | K23: 計上しない | N23: =【PL】決算数値入力!W23 -> 0 | O23: =【PL】決算数値入力!X23 -> 0 | P23: =【PL】決算数値入力!Y23 -> 0 | Q23: =【PL】決算数値入力!Z23 -> 0 | R23: =【PL】決算数値入力!AA23 -> 0 | S23: =【PL】決算数値入力!AB23 -> 0 | T23: 0 | U23: 0 | V23: 0 | W23: 0 | X23: 0 | Y23: 0 | Z23: 0 | AA23: 0 | AB23: 0 | AC23: 0 | AD23: 0 | AE23: 0 | AF23: 0 | AG23: 0 | AH23: 0 | AI23: 0 | AJ23: 0 | AK23: 0 | AL23: 0 | AM23: 0 | AN23: 0 | AO23: 0 | AP23: 0 | AQ23: 0 | AR23: 0 | AS23: 0 | AT23: 0 | AU23: 0 | AV23: 0 | AW23: 0 | AX23: 0 | AY23: 0 | AZ23: 0 | BA23: 0 | BB23: 0 | BC23: 0 | BD23: 0 | BE23: 0 | BF23: 0 | BG23: 0 | BH23: 0 | BI23: 0 | BJ23: 0 | BK23: 0 | BL23: 0 | BM23: 0 | BN23: 0 | BO23: 0 | BP23: 0 | BQ23: 0
B24: 水道事業費用 | N24: =【PL】決算数値入力!W24 -> 390874183 | O24: =【PL】決算数値入力!X24 -> 507845824 | P24: =【PL】決算数値入力!Y24 -> 543887736 | Q24: =【PL】決算数値入力!Z24 -> 694576672 | R24: =【PL】決算数値入力!AA24 -> 564428515 | S24: =【PL】決算数値入力!AB24 -> 4.2086899e+08 | T24: =SUM(T25,T58,T63) -> 532105330 | U24: =SUM(U25,U58,U63) -> 546680663 | V24: =SUM(V25,V58,V63) -> 554561152 | W24: =SUM(W25,W58,W63) -> 584482252 | X24: =SUM(X25,X58,X63) -> 591468537 | Y24: =SUM(Y25,Y58,Y63) -> 594356181 | Z24: =SUM(Z25,Z58,Z63) -> 594585505 | AA24: =SUM(AA25,AA58,AA63) -> 597174026 | ... BQ24: =SUM(BQ25,BQ58,BQ63) -> 280012115
C25: 営業費用 | N25: =【PL】決算数値入力!W25 -> 276187944 | O25: =【PL】決算数値入力!X25 -> 493988554 | P25: =【PL】決算数値入力!Y25 -> 537473069 | Q25: =【PL】決算数値入力!Z25 -> 687804951 | R25: =【PL】決算数値入力!AA25 -> 548360734 | S25: =【PL】決算数値入力!AB25 -> 3.5942518e+08 | T25: =SUM(T26,T34,T43,T52,T55) -> 5.1745155e+08 | U25: =SUM(U26,U34,U43,U52,U55) -> 5.2386618e+08 | V25: =SUM(V26,V34,V43,V52,V55) -> 5.2719376e+08 | W25: =SUM(W26,W34,W43,W52,W55) -> 5.4810564e+08 | X25: =SUM(X26,X34,X43,X52,X55) -> 5.4731689e+08 | Y25: =SUM(Y26,Y34,Y43,Y52,Y55) -> 5.4289552e+08 | Z25: =SUM(Z26,Z34,Z43,Z52,Z55) -> 5.3925837e+08 | AA25: =SUM(AA26,AA34,AA43,AA52,AA55) -> 5.381329e+08 | ... BQ25: =SUM(BQ26,BQ34,BQ43,BQ52,BQ55) -> 2.2864997e+08
D26: 原水及び浄水費 | F26: 原浄水部門費 | N26: =【PL】決算数値入力!W26 -> 68125490 | O26: =【PL】決算数値入力!X26 -> 86729085 | P26: =【PL】決算数値入力!Y26 -> 77675517 | Q26: =【PL】決算数値入力!Z26 -> 81124641 | R26: =【PL】決算数値入力!AA26 -> 85901288 | S26: =【PL】決算数値入力!AB26 -> 69189921 | T26: =SUM(T27:T33) -> 64166870 | U26: =SUM(U27:U33) -> 64698200 | V26: =SUM(V27:V33) -> 65210913 | W26: =SUM(W27:W33) -> 65733139 | X26: =SUM(X27:X33) -> 66261970 | Y26: =SUM(Y27:Y33) -> 66800191 | Z26: =SUM(Z27:Z33) -> 67324195 | AA26: =SUM(AA27:AA33) -> 67874656 | ... BQ26: =SUM(BQ27:BQ33) -> 97890556
E27: 人件費 | H27: ● | K27: R1~R5決算の平均値に物価上昇率を加味 | L27: ● | N27: =【PL】決算数値入力!W27 -> 6871890 | O27: =【PL】決算数値入力!X27 -> 6834594 | P27: =【PL】決算数値入力!Y27 -> 6604994 | Q27: =【PL】決算数値入力!Z27 -> 6808256 | R27: =【PL】決算数値入力!AA27 -> 6912531 | S27: =【PL】決算数値入力!AB27 -> 7539318.4 | T27: =ROUND(S27*(1+物価上昇率!$H$9),0) -> 7622251 | U27: =ROUND(T27*(1+物価上昇率!$H$9),0) -> 7706096 | V27: =ROUND(U27*(1+物価上昇率!$H$9),0) -> 7790863 | W27: =ROUND(V27*(1+物価上昇率!$H$9),0) -> 7876562 | X27: =ROUND(W27*(1+物価上昇率!$H$9),0) -> 7963204 | Y27: =ROUND(X27*(1+物価上昇率!$H$9),0) -> 8050799 | Z27: =ROUND(Y27*(1+物価上昇率!$H$9),0) -> 8139358 | AA27: =ROUND(Z27*(1+物価上昇率!$H$9),0) -> 8228891 | ... BQ27: =ROUND(BP27*(1+物価上昇率!$H$9),0) -> 13028364
E28: 動力費 | I28: ● | K28: R1~R5有収水量1㎥あたり費用×有収水量（見込） | L28: ● | N28: =【PL】決算数値入力!W28 -> 2543653 | O28: =【PL】決算数値入力!X28 -> 6880183 | P28: =【PL】決算数値入力!Y28 -> 7599848 | Q28: =【PL】決算数値入力!Z28 -> 9405448 | R28: =【PL】決算数値入力!AA28 -> 8392602 | S28: =【PL】決算数値入力!AB28 -> 4481765.6 | T28: =ROUND(SUM(【PL】決算数値入力!$AB$28)/SUM(【収益】水需要予測!$N$19:$W$19),0)*【収益】水需要予測!Y21 -> 924716 | U28: =ROUND(SUM(【PL】決算数値入力!$AB$28)/SUM(【収益】水需要予測!$N$19:$W$19),0)*【収益】水需要予測!Z21 -> 922751 | V28: =ROUND(SUM(【PL】決算数値入力!$AB$28)/SUM(【収益】水需要予測!$N$19:$W$19),0)*【収益】水需要予測!AA21 -> 901322 | W28: =ROUND(SUM(【PL】決算数値入力!$AB$28)/SUM(【収益】水需要予測!$N$19:$W$19),0)*【収益】水需要予測!AB21 -> 882735 | X28: =ROUND(SUM(【PL】決算数値入力!$AB$28)/SUM(【収益】水需要予測!$N$19:$W$19),0)*【収益】水需要予測!AC21 -> 864628 | Y28: =ROUND(SUM(【PL】決算数値入力!$AB$28)/SUM(【収益】水需要予測!$N$19:$W$19),0)*【収益】水需要予測!AD21 -> 849162 | Z28: =ROUND(SUM(【PL】決算数値入力!$AB$28)/SUM(【収益】水需要予測!$N$19:$W$19),0)*【収益】水需要予測!AE21 -> 817519 | AA28: =ROUND(SUM(【PL】決算数値入力!$AB$28)/SUM(【収益】水需要予測!$N$19:$W$19),0)*【収益】水需要予測!AF21 -> 801976 | ... BQ28: =ROUND(SUM(【PL】決算数値入力!$AB$28)/SUM(【収益】水需要予測!$N$19:$W$19),0)*【収益】水需要予測!BV21 -> 372603
E29: 薬品費 | I29: ● | K29: R1~R5有収水量1㎥あたり費用×有収水量（見込） | L29: ● | N29: =【PL】決算数値入力!W29 -> 2231130 | O29: =【PL】決算数値入力!X29 -> 2383550 | P29: =【PL】決算数値入力!Y29 -> 2505150 | Q29: =【PL】決算数値入力!Z29 -> 2578200 | R29: =【PL】決算数値入力!AA29 -> 3328640 | S29: =【PL】決算数値入力!AB29 -> 2232707.9 | T29: =ROUND(SUM(【PL】決算数値入力!$AB$29)/SUM(【収益】水需要予測!$N$19:$W$19)*【収益】水需要予測!Y21,0) -> 238712 | U29: =ROUND(SUM(【PL】決算数値入力!$AB$29)/SUM(【収益】水需要予測!$N$19:$W$19)*【収益】水需要予測!Z21,0) -> 238205 | V29: =ROUND(SUM(【PL】決算数値入力!$AB$29)/SUM(【収益】水需要予測!$N$19:$W$19)*【収益】水需要予測!AA21,0) -> 232673 | W29: =ROUND(SUM(【PL】決算数値入力!$AB$29)/SUM(【収益】水需要予測!$N$19:$W$19)*【収益】水需要予測!AB21,0) -> 227875 | X29: =ROUND(SUM(【PL】決算数値入力!$AB$29)/SUM(【収益】水需要予測!$N$19:$W$19)*【収益】水需要予測!AC21,0) -> 223201 | Y29: =ROUND(SUM(【PL】決算数値入力!$AB$29)/SUM(【収益】水需要予測!$N$19:$W$19)*【収益】水需要予測!AD21,0) -> 219208 | Z29: =ROUND(SUM(【PL】決算数値入力!$AB$29)/SUM(【収益】水需要予測!$N$19:$W$19)*【収益】水需要予測!AE21,0) -> 211040 | AA29: =ROUND(SUM(【PL】決算数値入力!$AB$29)/SUM(【収益】水需要予測!$N$19:$W$19)*【収益】水需要予測!AF21,0) -> 207027 | ... BQ29: =ROUND(SUM(【PL】決算数値入力!$AB$29)/SUM(【収益】水需要予測!$N$19:$W$19)*【収益】水需要予測!BV21,0) -> 96186
E30: 修繕費 | H30: ● | K30: R1~R5決算の平均値に物価上昇率を加味 | L30: ● | N30: =【PL】決算数値入力!W30 -> 4684722 | O30: =【PL】決算数値入力!X30 -> 8618000 | P30: =【PL】決算数値入力!Y30 -> 1967420 | Q30: =【PL】決算数値入力!Z30 -> 0 | R30: =【PL】決算数値入力!AA30 -> 3913900 | S30: =【PL】決算数値入力!AB30 -> 2660995.2 | T30: =ROUND(S30*(1+物価上昇率!$H$9),0) -> 2690266 | U30: =ROUND(T30*(1+物価上昇率!$H$9),0) -> 2719859 | V30: =ROUND(U30*(1+物価上昇率!$H$9),0) -> 2749777 | W30: =ROUND(V30*(1+物価上昇率!$H$9),0) -> 2780025 | X30: =ROUND(W30*(1+物価上昇率!$H$9),0) -> 2810605 | Y30: =ROUND(X30*(1+物価上昇率!$H$9),0) -> 2841522 | Z30: =ROUND(Y30*(1+物価上昇率!$H$9),0) -> 2872779 | AA30: =ROUND(Z30*(1+物価上昇率!$H$9),0) -> 2904380 | ... BQ30: =ROUND(BP30*(1+物価上昇率!$H$9),0) -> 4598352
E31: 委託料 | H31: ● | K31: R1~R5決算の平均値に物価上昇率を加味 | L31: ● | N31: =【PL】決算数値入力!W31 -> 33900347 | O31: =【PL】決算数値入力!X31 -> 31437870 | P31: =【PL】決算数値入力!Y31 -> 37142870 | Q31: =【PL】決算数値入力!Z31 -> 33639873 | R31: =【PL】決算数値入力!AA31 -> 36092000 | S31: =【PL】決算数値入力!AB31 -> 30459801 | T31: =ROUND(S31*(1+物価上昇率!$H$9),0) -> 30794859 | U31: =ROUND(T31*(1+物価上昇率!$H$9),0) -> 31133602 | V31: =ROUND(U31*(1+物価上昇率!$H$9),0) -> 31476072 | W31: =ROUND(V31*(1+物価上昇率!$H$9),0) -> 31822309 | X31: =ROUND(W31*(1+物価上昇率!$H$9),0) -> 32172354 | Y31: =ROUND(X31*(1+物価上昇率!$H$9),0) -> 32526250 | Z31: =ROUND(Y31*(1+物価上昇率!$H$9),0) -> 32884039 | AA31: =ROUND(Z31*(1+物価上昇率!$H$9),0) -> 33245763 | ... BQ31: =ROUND(BP31*(1+物価上昇率!$H$9),0) -> 52636235
E32: その他（物価上昇を考慮する） | H32: ● | K32: R1~R5決算の平均値に物価上昇率を加味 | L32: ● | N32: =【PL】決算数値入力!W32 -> 7655578 | O32: =【PL】決算数値入力!X32 -> 9645808 | P32: =【PL】決算数値入力!Y32 -> 9829369 | Q32: =【PL】決算数値入力!Z32 -> 10153949 | R32: =【PL】決算数値入力!AA32 -> 9171593 | S32: =【PL】決算数値入力!AB32 -> 7339389.2 | T32: =ROUND(S32*(1+物価上昇率!$H$9),0) -> 7420122 | U32: =ROUND(T32*(1+物価上昇率!$H$9),0) -> 7501743 | V32: =ROUND(U32*(1+物価上昇率!$H$9),0) -> 7584262 | W32: =ROUND(V32*(1+物価上昇率!$H$9),0) -> 7667689 | X32: =ROUND(W32*(1+物価上昇率!$H$9),0) -> 7752034 | Y32: =ROUND(X32*(1+物価上昇率!$H$9),0) -> 7837306 | Z32: =ROUND(Y32*(1+物価上昇率!$H$9),0) -> 7923516 | AA32: =ROUND(Z32*(1+物価上昇率!$H$9),0) -> 8010675 | ... BQ32: =ROUND(BP32*(1+物価上昇率!$H$9),0) -> 12682872
E33: その他（物価上昇を考慮しない） | H33: ● | K33: R1~R5決算の平均値で一定 | N33: =【PL】決算数値入力!W33 -> 10238170 | O33: =【PL】決算数値入力!X33 -> 20929080 | P33: =【PL】決算数値入力!Y33 -> 12025866 | Q33: =【PL】決算数値入力!Z33 -> 18538915 | R33: =【PL】決算数値入力!AA33 -> 18090022 | S33: =【PL】決算数値入力!AB33 -> 14475944 | T33: =S33 -> 14475944 | U33: =T33 -> 14475944 | V33: =U33 -> 14475944 | W33: =V33 -> 14475944 | X33: =W33 -> 14475944 | Y33: =X33 -> 14475944 | Z33: =Y33 -> 14475944 | AA33: =Z33 -> 14475944 | ... BQ33: =BP33 -> 14475944
D34: 配水及び給水費 | F34: 配給水部門費 | N34: =【PL】決算数値入力!W34 -> 39566820 | O34: =【PL】決算数値入力!X34 -> 36646933 | P34: =【PL】決算数値入力!Y34 -> 35722581 | Q34: =【PL】決算数値入力!Z34 -> 36936296 | R34: =【PL】決算数値入力!AA34 -> 32180340 | S34: =【PL】決算数値入力!AB34 -> 34923211 | T34: =SUM(T35:T41) -> 33124149 | U34: =SUM(U35:U41) -> 33488515 | V34: =SUM(V35:V41) -> 33856889 | W34: =SUM(W35:W41) -> 34229316 | X34: =SUM(X35:X41) -> 34605838 | Y34: =SUM(Y35:Y41) -> 34986502 | Z34: =SUM(Z35:Z41) -> 35371354 | AA34: =SUM(AA35:AA41) -> 35760439 | ... BQ34: =SUM(BQ35:BQ41) -> 56617592
E35: 人件費 | H35: ● | K35: R1~R5決算の平均値に物価上昇率を加味 | L35: ● | N35: =【PL】決算数値入力!W35 -> 13528381 | O35: =【PL】決算数値入力!X35 -> 10517166 | P35: =【PL】決算数値入力!Y35 -> 10463981 | Q35: =【PL】決算数値入力!Z35 -> 10732216 | R35: =【PL】決算数値入力!AA35 -> 6777049 | S35: =【PL】決算数値入力!AB35 -> 12599585 | T35: =ROUND(S35*(1+物価上昇率!$H$9),0) -> 12738180 | U35: =ROUND(T35*(1+物価上昇率!$H$9),0) -> 12878300 | V35: =ROUND(U35*(1+物価上昇率!$H$9),0) -> 13019961 | W35: =ROUND(V35*(1+物価上昇率!$H$9),0) -> 13163181 | X35: =ROUND(W35*(1+物価上昇率!$H$9),0) -> 13307976 | Y35: =ROUND(X35*(1+物価上昇率!$H$9),0) -> 13454364 | Z35: =ROUND(Y35*(1+物価上昇率!$H$9),0) -> 13602362 | AA35: =ROUND(Z35*(1+物価上昇率!$H$9),0) -> 13751988 | ... BQ35: =ROUND(BP35*(1+物価上昇率!$H$9),0) -> 21772786
E36: 動力費 | I36: ● | K36: R1~R5有収水量1㎥あたり費用×有収水量（見込） | L36: ● | N36: =【PL】決算数値入力!W36 -> 3189420 | O36: =【PL】決算数値入力!X36 -> 2083304 | P36: =【PL】決算数値入力!Y36 -> 2339387 | Q36: =【PL】決算数値入力!Z36 -> 3088131 | R36: =【PL】決算数値入力!AA36 -> 2470534 | S36: =【PL】決算数値入力!AB36 -> 2159463.6 | T36: =ROUND(SUM(【PL】決算数値入力!$AB$36)/SUM(【収益】水需要予測!$N$19:$W$19),0)*【収益】水需要予測!Y21 -> 0 | U36: =ROUND(SUM(【PL】決算数値入力!$AB$36)/SUM(【収益】水需要予測!$N$19:$W$19),0)*【収益】水需要予測!Z21 -> 0 | V36: =ROUND(SUM(【PL】決算数値入力!$AB$36)/SUM(【収益】水需要予測!$N$19:$W$19),0)*【収益】水需要予測!AA21 -> 0 | W36: =ROUND(SUM(【PL】決算数値入力!$AB$36)/SUM(【収益】水需要予測!$N$19:$W$19),0)*【収益】水需要予測!AB21 -> 0 | X36: =ROUND(SUM(【PL】決算数値入力!$AB$36)/SUM(【収益】水需要予測!$N$19:$W$19),0)*【収益】水需要予測!AC21 -> 0 | Y36: =ROUND(SUM(【PL】決算数値入力!$AB$36)/SUM(【収益】水需要予測!$N$19:$W$19),0)*【収益】水需要予測!AD21 -> 0 | Z36: =ROUND(SUM(【PL】決算数値入力!$AB$36)/SUM(【収益】水需要予測!$N$19:$W$19),0)*【収益】水需要予測!AE21 -> 0 | AA36: =ROUND(SUM(【PL】決算数値入力!$AB$36)/SUM(【収益】水需要予測!$N$19:$W$19),0)*【収益】水需要予測!AF21 -> 0 | ... BQ36: =ROUND(SUM(【PL】決算数値入力!$AB$36)/SUM(【収益】水需要予測!$N$19:$W$19),0)*【収益】水需要予測!BV21 -> 0
E37: 薬品費 | I37: ● | K37: R1~R5有収水量1㎥あたり費用×有収水量（見込） | L37: ● | N37: =【PL】決算数値入力!W37 -> 0 | O37: =【PL】決算数値入力!X37 -> 0 | P37: =【PL】決算数値入力!Y37 -> 0 | Q37: =【PL】決算数値入力!Z37 -> 0 | R37: =【PL】決算数値入力!AA37 -> 0 | S37: =【PL】決算数値入力!AB37 -> 0 | T37: =ROUND(SUM(【PL】決算数値入力!AB37)/SUM(【収益】水需要予測!$N$19:$W$19)*【収益】水需要予測!Y21,0) -> 0 | U37: =ROUND(SUM(【PL】決算数値入力!$AB$37)/SUM(【収益】水需要予測!$N$19:$W$19)*【収益】水需要予測!Z21,0) -> 0 | V37: =ROUND(SUM(【PL】決算数値入力!$AB$37)/SUM(【収益】水需要予測!$N$19:$W$19)*【収益】水需要予測!AA21,0) -> 0 | W37: =ROUND(SUM(【PL】決算数値入力!$AB$37)/SUM(【収益】水需要予測!$N$19:$W$19)*【収益】水需要予測!AB21,0) -> 0 | X37: =ROUND(SUM(【PL】決算数値入力!$AB$37)/SUM(【収益】水需要予測!$N$19:$W$19)*【収益】水需要予測!AC21,0) -> 0 | Y37: =ROUND(SUM(【PL】決算数値入力!$AB$37)/SUM(【収益】水需要予測!$N$19:$W$19)*【収益】水需要予測!AD21,0) -> 0 | Z37: =ROUND(SUM(【PL】決算数値入力!$AB$37)/SUM(【収益】水需要予測!$N$19:$W$19)*【収益】水需要予測!AE21,0) -> 0 | AA37: =ROUND(SUM(【PL】決算数値入力!$AB$37)/SUM(【収益】水需要予測!$N$19:$W$19)*【収益】水需要予測!AF21,0) -> 0 | AB37: =ROUND(SUM(【PL】決算数値入力!$AB$37)/SUM(【収益】水需要予測!$N$19:$W$19)*【収益】水需要予測!AG21,0) -> 0 | ... BQ37: =ROUND(SUM(【PL】決算数値入力!$AB$37)/SUM(【収益】水需要予測!$N$19:$W$19)*【収益】水需要予測!BV21,0) -> 0
E38: 修繕費 | H38: ● | K38: R1~R5決算の平均値に物価上昇率を加味 | L38: ● | N38: =【PL】決算数値入力!W38 -> 1577280 | O38: =【PL】決算数値入力!X38 -> 327448 | P38: =【PL】決算数値入力!Y38 -> 569069 | Q38: =【PL】決算数値入力!Z38 -> 3745890 | R38: =【PL】決算数値入力!AA38 -> 3642734 | S38: =【PL】決算数値入力!AB38 -> 1417521.1 | T38: =ROUND(S38*(1+物価上昇率!$H$9),0) -> 1433114 | U38: =ROUND(T38*(1+物価上昇率!$H$9),0) -> 1448878 | V38: =ROUND(U38*(1+物価上昇率!$H$9),0) -> 1464816 | W38: =ROUND(V38*(1+物価上昇率!$H$9),0) -> 1480929 | X38: =ROUND(W38*(1+物価上昇率!$H$9),0) -> 1497219 | Y38: =ROUND(X38*(1+物価上昇率!$H$9),0) -> 1513688 | Z38: =ROUND(Y38*(1+物価上昇率!$H$9),0) -> 1530339 | AA38: =ROUND(Z38*(1+物価上昇率!$H$9),0) -> 1547173 | ... BQ38: =ROUND(BP38*(1+物価上昇率!$H$9),0) -> 2449553
E39: 委託料 | H39: ● | K39: R1~R5決算の平均値に物価上昇率を加味 | L39: ● | N39: =【PL】決算数値入力!W39 -> 17175629 | O39: =【PL】決算数値入力!X39 -> 18885642 | P39: =【PL】決算数値入力!Y39 -> 16161047 | Q39: =【PL】決算数値入力!Z39 -> 13583646 | R39: =【PL】決算数値入力!AA39 -> 13164934 | S39: =【PL】決算数値入力!AB39 -> 14950335 | T39: =ROUND(S39*(1+物価上昇率!$H$9),0) -> 15114789 | U39: =ROUND(T39*(1+物価上昇率!$H$9),0) -> 15281052 | V39: =ROUND(U39*(1+物価上昇率!$H$9),0) -> 15449144 | W39: =ROUND(V39*(1+物価上昇率!$H$9),0) -> 15619085 | X39: =ROUND(W39*(1+物価上昇率!$H$9),0) -> 15790895 | Y39: =ROUND(X39*(1+物価上昇率!$H$9),0) -> 15964595 | Z39: =ROUND(Y39*(1+物価上昇率!$H$9),0) -> 16140206 | AA39: =ROUND(Z39*(1+物価上昇率!$H$9),0) -> 16317748 | ... BQ39: =ROUND(BP39*(1+物価上昇率!$H$9),0) -> 25835021
E40: その他（物価上昇を考慮する） | H40: ● | K40: R1~R5決算の平均値に物価上昇率を加味 | L40: ● | N40: =【PL】決算数値入力!W40 -> 4096110 | O40: =【PL】決算数値入力!X40 -> 4833373 | P40: =【PL】決算数値入力!Y40 -> 6189097 | Q40: =【PL】決算数値入力!Z40 -> 5786413 | R40: =【PL】決算数値入力!AA40 -> 6125089 | S40: =【PL】決算数値入力!AB40 -> 3796306.5 | T40: =ROUND(S40*(1+物価上昇率!$H$9),0) -> 3838066 | U40: =ROUND(T40*(1+物価上昇率!$H$9),0) -> 3880285 | V40: =ROUND(U40*(1+物価上昇率!$H$9),0) -> 3922968 | W40: =ROUND(V40*(1+物価上昇率!$H$9),0) -> 3966121 | X40: =ROUND(W40*(1+物価上昇率!$H$9),0) -> 4009748 | Y40: =ROUND(X40*(1+物価上昇率!$H$9),0) -> 4053855 | Z40: =ROUND(Y40*(1+物価上昇率!$H$9),0) -> 4098447 | AA40: =ROUND(Z40*(1+物価上昇率!$H$9),0) -> 4143530 | ... BQ40: =ROUND(BP40*(1+物価上昇率!$H$9),0) -> 6560232
E41: その他（物価上昇を考慮しない） | H41: ● | K41: R1~R5決算の平均値で一定 | N41: =【PL】決算数値入力!W41 -> 0 | O41: =【PL】決算数値入力!X41 -> 0 | P41: =【PL】決算数値入力!Y41 -> 0 | Q41: =【PL】決算数値入力!Z41 -> 0 | R41: =【PL】決算数値入力!AA41 -> 0 | S41: =【PL】決算数値入力!AB41 -> 0 | T41: =S41 -> 0 | U41: =T41 -> 0 | V41: =U41 -> 0 | W41: =V41 -> 0 | X41: =W41 -> 0 | Y41: =X41 -> 0 | Z41: =Y41 -> 0 | AA41: =Z41 -> 0 | ... BQ41: =BP41 -> 0
D42: 受託工事費 | K42: 計上しない | N42: =【PL】決算数値入力!W42 -> 0 | O42: =【PL】決算数値入力!X42 -> 0 | P42: =【PL】決算数値入力!Y42 -> 0 | Q42: =【PL】決算数値入力!Z42 -> 0 | R42: =【PL】決算数値入力!AA42 -> 0 | S42: =【PL】決算数値入力!AB42 -> 0 | T42: 0 | U42: 0 | V42: 0 | W42: 0 | X42: 0 | Y42: 0 | Z42: 0 | AA42: 0 | AB42: 0 | AC42: 0 | AD42: 0 | AE42: 0 | AF42: 0 | AG42: 0 | AH42: 0 | AI42: 0 | AJ42: 0 | AK42: 0 | AL42: 0 | AM42: 0 | AN42: 0 | AO42: 0 | AP42: 0 | AQ42: 0 | AR42: 0 | AS42: 0 | AT42: 0 | AU42: 0 | AV42: 0 | AW42: 0 | AX42: 0 | AY42: 0 | AZ42: 0 | BA42: 0 | BB42: 0 | BC42: 0 | BD42: 0 | BE42: 0 | BF42: 0 | BG42: 0 | BH42: 0 | BI42: 0 | BJ42: 0 | BK42: 0 | BL42: 0 | BM42: 0 | BN42: 0 | BO42: 0 | BP42: 0 | BQ42: 0
D43: 総係費 | F43: その他管理業務費 | N43: =【PL】決算数値入力!W43 -> 28068995 | O43: =【PL】決算数値入力!X43 -> 38902891 | P43: =【PL】決算数値入力!Y43 -> 34633799 | Q43: =【PL】決算数値入力!Z43 -> 56238492 | R43: =【PL】決算数値入力!AA43 -> 39372697 | S43: =【PL】決算数値入力!AB43 -> 31797739 | T43: =SUM(T44:T51) -> 32147514 | U43: =SUM(U44:U51) -> 32501137 | V43: =SUM(V44:V51) -> 32858650 | W43: =SUM(W44:W51) -> 33220095 | X43: =SUM(X44:X51) -> 33585517 | Y43: =SUM(Y44:Y51) -> 33954958 | Z43: =SUM(Z44:Z51) -> 34328463 | AA43: =SUM(AA44:AA51) -> 34706076 | ... BQ43: =SUM(BQ44:BQ51) -> 54948273
E44: 人件費 | H44: ● | K44: R1~R5決算の平均値に物価上昇率を加味 | L44: ● | N44: =【PL】決算数値入力!W44 -> 15362936 | O44: =【PL】決算数値入力!X44 -> 14555234 | P44: =【PL】決算数値入力!Y44 -> 16036318 | Q44: =【PL】決算数値入力!Z44 -> 33509229 | R44: =【PL】決算数値入力!AA44 -> 21652038 | S44: =【PL】決算数値入力!AB44 -> 17988350 | T44: =ROUND(S44*(1+物価上昇率!$H$9),0) -> 18186222 | U44: =ROUND(T44*(1+物価上昇率!$H$9),0) -> 18386270 | V44: =ROUND(U44*(1+物価上昇率!$H$9),0) -> 18588519 | W44: =ROUND(V44*(1+物価上昇率!$H$9),0) -> 18792993 | X44: =ROUND(W44*(1+物価上昇率!$H$9),0) -> 18999716 | Y44: =ROUND(X44*(1+物価上昇率!$H$9),0) -> 19208713 | Z44: =ROUND(Y44*(1+物価上昇率!$H$9),0) -> 19420009 | AA44: =ROUND(Z44*(1+物価上昇率!$H$9),0) -> 19633629 | ... BQ44: =ROUND(BP44*(1+物価上昇率!$H$9),0) -> 31084873
E45: 退職給付費 | H45: ● | K45: R1~R5決算の平均値に物価上昇率を加味 | L45: ● | N45: =【PL】決算数値入力!W45 -> 0 | O45: =【PL】決算数値入力!X45 -> 0 | P45: =【PL】決算数値入力!Y45 -> 0 | Q45: =【PL】決算数値入力!Z45 -> 0 | R45: =【PL】決算数値入力!AA45 -> 0 | S45: =【PL】決算数値入力!AB45 -> 0 | T45: =ROUND(S45*(1+物価上昇率!$H$9),0) -> 0 | U45: =ROUND(T45*(1+物価上昇率!$H$9),0) -> 0 | V45: =ROUND(U45*(1+物価上昇率!$H$9),0) -> 0 | W45: =ROUND(V45*(1+物価上昇率!$H$9),0) -> 0 | X45: =ROUND(W45*(1+物価上昇率!$H$9),0) -> 0 | Y45: =ROUND(X45*(1+物価上昇率!$H$9),0) -> 0 | Z45: =ROUND(Y45*(1+物価上昇率!$H$9),0) -> 0 | AA45: =ROUND(Z45*(1+物価上昇率!$H$9),0) -> 0 | ... BQ45: =ROUND(BP45*(1+物価上昇率!$H$9),0) -> 0
E46: 貸倒引当金繰入額 | H46: ● | K46: 計上しない | N46: =【PL】決算数値入力!W46 -> 0 | O46: =【PL】決算数値入力!X46 -> 0 | P46: =【PL】決算数値入力!Y46 -> 0 | Q46: =【PL】決算数値入力!Z46 -> 0 | R46: =【PL】決算数値入力!AA46 -> 0 | S46: =【PL】決算数値入力!AB46 -> 0 | T46: 0 | U46: 0 | V46: 0 | W46: 0 | X46: 0 | Y46: 0 | Z46: 0 | AA46: 0 | AB46: 0 | AC46: 0 | AD46: 0 | AE46: 0 | AF46: 0 | AG46: 0 | AH46: 0 | AI46: 0 | AJ46: 0 | AK46: 0 | AL46: 0 | AM46: 0 | AN46: 0 | AO46: 0 | AP46: 0 | AQ46: 0 | AR46: 0 | AS46: 0 | AT46: 0 | AU46: 0 | AV46: 0 | AW46: 0 | AX46: 0 | AY46: 0 | AZ46: 0 | BA46: 0 | BB46: 0 | BC46: 0 | BD46: 0 | BE46: 0 | BF46: 0 | BG46: 0 | BH46: 0 | BI46: 0 | BJ46: 0 | BK46: 0 | BL46: 0 | BM46: 0 | BN46: 0 | BO46: 0 | BP46: 0 | BQ46: 0
E47: 退職給与金 | H47: ● | K47: 計上しない | L47: ● | N47: =【PL】決算数値入力!W47 -> 0 | O47: =【PL】決算数値入力!X47 -> 0 | P47: =【PL】決算数値入力!Y47 -> 0 | Q47: =【PL】決算数値入力!Z47 -> 0 | R47: =【PL】決算数値入力!AA47 -> 0 | S47: =【PL】決算数値入力!AB47 -> 0 | T47: 0 | U47: 0 | V47: 0 | W47: 0 | X47: 0 | Y47: 0 | Z47: 0 | AA47: 0 | AB47: 0 | AC47: 0 | AD47: 0 | AE47: 0 | AF47: 0 | AG47: 0 | AH47: 0 | AI47: 0 | AJ47: 0 | AK47: 0 | AL47: 0 | AM47: 0 | AN47: 0 | AO47: 0 | AP47: 0 | AQ47: 0 | AR47: 0 | AS47: 0 | AT47: 0 | AU47: 0 | AV47: 0 | AW47: 0 | AX47: 0 | AY47: 0 | AZ47: 0 | BA47: 0 | BB47: 0 | BC47: 0 | BD47: 0 | BE47: 0 | BF47: 0 | BG47: 0 | BH47: 0 | BI47: 0 | BJ47: 0 | BK47: 0 | BL47: 0 | BM47: 0 | BN47: 0 | BO47: 0 | BP47: 0 | BQ47: 0
E48: 修繕費 | H48: ● | K48: R1~R5決算の平均値に物価上昇率を加味 | L48: ● | N48: =【PL】決算数値入力!W48 -> 44050 | O48: =【PL】決算数値入力!X48 -> 0 | P48: =【PL】決算数値入力!Y48 -> 41350 | Q48: =【PL】決算数値入力!Z48 -> 0 | R48: =【PL】決算数値入力!AA48 -> 49820 | S48: =【PL】決算数値入力!AB48 -> 44962 | T48: =ROUND(S48*(1+物価上昇率!$H$9),0) -> 45457 | U48: =ROUND(T48*(1+物価上昇率!$H$9),0) -> 45957 | V48: =ROUND(U48*(1+物価上昇率!$H$9),0) -> 46463 | W48: =ROUND(V48*(1+物価上昇率!$H$9),0) -> 46974 | X48: =ROUND(W48*(1+物価上昇率!$H$9),0) -> 47491 | Y48: =ROUND(X48*(1+物価上昇率!$H$9),0) -> 48013 | Z48: =ROUND(Y48*(1+物価上昇率!$H$9),0) -> 48541 | AA48: =ROUND(Z48*(1+物価上昇率!$H$9),0) -> 49075 | ... BQ48: =ROUND(BP48*(1+物価上昇率!$H$9),0) -> 77697
E49: 委託料 | H49: ● | K49: R1~R5決算の平均値に物価上昇率を加味 | L49: ● | N49: =【PL】決算数値入力!W49 -> 3738298 | O49: =【PL】決算数値入力!X49 -> 17166788 | P49: =【PL】決算数値入力!Y49 -> 9892260 | Q49: =【PL】決算数値入力!Z49 -> 14519671 | R49: =【PL】決算数値入力!AA49 -> 9915945 | S49: =【PL】決算数値入力!AB49 -> 7403703.5 | T49: =ROUND(S49*(1+物価上昇率!$H$9),0) -> 7485144 | U49: =ROUND(T49*(1+物価上昇率!$H$9),0) -> 7567481 | V49: =ROUND(U49*(1+物価上昇率!$H$9),0) -> 7650723 | W49: =ROUND(V49*(1+物価上昇率!$H$9),0) -> 7734881 | X49: =ROUND(W49*(1+物価上昇率!$H$9),0) -> 7819965 | Y49: =ROUND(X49*(1+物価上昇率!$H$9),0) -> 7905985 | Z49: =ROUND(Y49*(1+物価上昇率!$H$9),0) -> 7992951 | AA49: =ROUND(Z49*(1+物価上昇率!$H$9),0) -> 8080873 | ... BQ49: =ROUND(BP49*(1+物価上昇率!$H$9),0) -> 12794014
E50: その他（物価上昇を考慮する） | H50: ● | K50: R1~R5決算の平均値に物価上昇率を加味 | L50: ● | N50: =【PL】決算数値入力!W50 -> 8923711 | O50: =【PL】決算数値入力!X50 -> 7180869 | P50: =【PL】決算数値入力!Y50 -> 8663871 | Q50: =【PL】決算数値入力!Z50 -> 8209592 | R50: =【PL】決算数値入力!AA50 -> 7754894 | S50: =【PL】決算数値入力!AB50 -> 6360723.2 | T50: =ROUND(S50*(1+物価上昇率!$H$9),0) -> 6430691 | U50: =ROUND(T50*(1+物価上昇率!$H$9),0) -> 6501429 | V50: =ROUND(U50*(1+物価上昇率!$H$9),0) -> 6572945 | W50: =ROUND(V50*(1+物価上昇率!$H$9),0) -> 6645247 | X50: =ROUND(W50*(1+物価上昇率!$H$9),0) -> 6718345 | Y50: =ROUND(X50*(1+物価上昇率!$H$9),0) -> 6792247 | Z50: =ROUND(Y50*(1+物価上昇率!$H$9),0) -> 6866962 | AA50: =ROUND(Z50*(1+物価上昇率!$H$9),0) -> 6942499 | ... BQ50: =ROUND(BP50*(1+物価上昇率!$H$9),0) -> 10991689
E51: その他（物価上昇を考慮しない） | H51: ● | K51: R1~R5決算の平均値に物価上昇率を加味 | N51: =【PL】決算数値入力!W51 -> 0 | O51: =【PL】決算数値入力!X51 -> 0 | P51: =【PL】決算数値入力!Y51 -> 0 | Q51: =【PL】決算数値入力!Z51 -> 0 | R51: =【PL】決算数値入力!AA51 -> 0 | S51: =【PL】決算数値入力!AB51 -> 0 | T51: =S51 -> 0 | U51: =T51 -> 0 | V51: =U51 -> 0 | W51: =V51 -> 0 | X51: =W51 -> 0 | Y51: =X51 -> 0 | Z51: =Y51 -> 0 | AA51: =Z51 -> 0 | ... BQ51: =BP51 -> 0
D52: 減価償却費 | N52: =【PL】決算数値入力!W52 -> 140426639 | O52: =【PL】決算数値入力!X52 -> 331709645 | P52: =【PL】決算数値入力!Y52 -> 389441172 | Q52: =【PL】決算数値入力!Z52 -> 513505522 | R52: =【PL】決算数値入力!AA52 -> 390906409 | S52: =【PL】決算数値入力!AB52 -> 2.2341827e+08 | T52: =SUM(T53:T54) -> 388013019 | U52: =SUM(U53:U54) -> 393178325 | V52: =SUM(V53:V54) -> 395267309 | W52: =SUM(W53:W54) -> 414923088 | X52: =SUM(X53:X54) -> 412863570 | Y52: =SUM(Y53:Y54) -> 407153866 | Z52: =SUM(Z53:Z54) -> 402234363 | AA52: =SUM(AA53:AA54) -> 399791730 | ... BQ52: =SUM(BQ53:BQ54) -> 19193545
E53: R6末の取得資産 | H53: ● | K53: 固定資産台帳データに基づく算定額 | N53: =【PL】決算数値入力!W53 -> 140426639 | O53: =【PL】決算数値入力!X53 -> 331709645 | P53: =【PL】決算数値入力!Y53 -> 389441172 | Q53: =【PL】決算数値入力!Z53 -> 513505522 | R53: =【PL】決算数値入力!AA53 -> 390906409 | S53: =【PL】決算数値入力!AB53 -> 3.5319788e+08 | T53: 388013019 | U53: 393178325 | V53: 388776204 | W53: 381326720 | X53: 366109307 | Y53: 351189077 | Z53: 335480100 | AA53: 324879572 | AB53: 321264670 | AC53: 314341518 | AD53: 305953416 | AE53: 246393650 | AF53: 230841470 | AG53: 222347054 | AH53: 215076585 | AI53: 211601080 | AJ53: 192017974 | AK53: 188503679 | AL53: 185284373 | AM53: 182918010 | AN53: 180629373 | AO53: 178559629 | AP53: 175597321 | AQ53: 173234257 | AR53: 172061785 | AS53: 170342712 | AT53: 169095180 | AU53: 166861460 | AV53: 165411176 | AW53: 163700204 | AX53: 162176648 | AY53: 146937733 | AZ53: 142336067 | BA53: 140573937 | BB53: 134982359 | BC53: 120272671 | BD53: 109816029 | BE53: 74376754 | BF53: 55573007 | BG53: 52881887 | BH53: 50563684 | BI53: 48483953 | BJ53: 47552392 | BK53: 39957242 | BL53: 36999882 | BM53: 35793597 | BN53: 32191122 | BO53: 27782436 | BP53: 22634774 | BQ53: 19193545
E54: R7以降の取得資産 | H54: ● | K54: 償却計算額 | N54: =【PL】決算数値入力!W54 -> 0 | O54: =【PL】決算数値入力!X54 -> 0 | P54: =【PL】決算数値入力!Y54 -> 0 | Q54: =【PL】決算数値入力!Z54 -> 0 | R54: =【PL】決算数値入力!AA54 -> 0 | S54: =【PL】決算数値入力!AB54 -> 0 | T54: =新規取得!I2 -> 0 | U54: =新規取得!O2 -> 0 | V54: =新規取得!P2 -> 6491105 | W54: =新規取得!Q2 -> 33596368 | X54: =新規取得!R2 -> 46754263 | Y54: =新規取得!S2 -> 55964789 | Z54: =新規取得!T2 -> 66754263 | AA54: =新規取得!U2 -> 74912158 | AB54: =新規取得!V2 -> 84675316 | ... BQ54: =新規取得!BK2 -> 0
D55: 資産減耗費 | N55: =【PL】決算数値入力!W55 -> 0 | O55: =【PL】決算数値入力!X55 -> 0 | P55: =【PL】決算数値入力!Y55 -> 0 | Q55: =【PL】決算数値入力!Z55 -> 0 | R55: =【PL】決算数値入力!AA55 -> 0 | S55: =【PL】決算数値入力!AB55 -> 0 | T55: =SUM(T56:T57) -> 0 | U55: =SUM(U56:U57) -> 0 | V55: =SUM(V56:V57) -> 0 | W55: =SUM(W56:W57) -> 0 | X55: =SUM(X56:X57) -> 0 | Y55: =SUM(Y56:Y57) -> 0 | Z55: =SUM(Z56:Z57) -> 0 | AA55: =SUM(AA56:AA57) -> 0 | ... BQ55: =SUM(BQ56:BQ57) -> 0
E56: 固定資産除却費 | H56: ● | K56: 更新・廃止に伴う除却等の費用を計上 | N56: =【PL】決算数値入力!W56 -> 0 | O56: =【PL】決算数値入力!X56 -> 0 | P56: =【PL】決算数値入力!Y56 -> 0 | Q56: =【PL】決算数値入力!Z56 -> 0 | R56: =【PL】決算数値入力!AA56 -> 0 | S56: =【PL】決算数値入力!AB56 -> 0
E57: たな卸資産減耗費 | H57: ● | K57: 計上しない | N57: =【PL】決算数値入力!W57 -> 0 | O57: =【PL】決算数値入力!X57 -> 0 | P57: =【PL】決算数値入力!Y57 -> 0 | Q57: =【PL】決算数値入力!Z57 -> 0 | R57: =【PL】決算数値入力!AA57 -> 0 | S57: =【PL】決算数値入力!AB57 -> 0 | T57: 0 | U57: 0 | V57: 0 | W57: 0 | X57: 0 | Y57: 0 | Z57: 0 | AA57: 0 | AB57: 0 | AC57: 0 | AD57: 0 | AE57: 0 | AF57: 0 | AG57: 0 | AH57: 0 | AI57: 0 | AJ57: 0 | AK57: 0 | AL57: 0 | AM57: 0 | AN57: 0 | AO57: 0 | AP57: 0 | AQ57: 0 | AR57: 0 | AS57: 0 | AT57: 0 | AU57: 0 | AV57: 0 | AW57: 0 | AX57: 0 | AY57: 0 | AZ57: 0 | BA57: 0 | BB57: 0 | BC57: 0 | BD57: 0 | BE57: 0 | BF57: 0 | BG57: 0 | BH57: 0 | BI57: 0 | BJ57: 0 | BK57: 0 | BL57: 0 | BM57: 0 | BN57: 0 | BO57: 0 | BP57: 0 | BQ57: 0
C58: 営業外費用 | N58: =【PL】決算数値入力!W58 -> 39544692 | O58: =【PL】決算数値入力!X58 -> 13857270 | P58: =【PL】決算数値入力!Y58 -> 6414667 | Q58: =【PL】決算数値入力!Z58 -> 6771721 | R58: =【PL】決算数値入力!AA58 -> 16067781 | S58: =【PL】決算数値入力!AB58 -> 18069225 | T58: =SUM(T59,T62) -> 14653778 | U58: =SUM(U59,U62) -> 22814486 | V58: =SUM(V59,V62) -> 27367391 | W58: =SUM(W59,W62) -> 36376614 | X58: =SUM(X59,X62) -> 44151642 | Y58: =SUM(Y59,Y62) -> 51460664 | Z58: =SUM(Z59,Z62) -> 55327130 | AA58: =SUM(AA59,AA62) -> 59041125 | ... BQ58: =SUM(BQ59,BQ62) -> 51362149
D59: 支払利息 | N59: =【PL】決算数値入力!W59 -> 3322502 | O59: =【PL】決算数値入力!X59 -> 3316293 | P59: =【PL】決算数値入力!Y59 -> 3627476 | Q59: =【PL】決算数値入力!Z59 -> 4367904 | R59: =【PL】決算数値入力!AA59 -> 4944124 | S59: =【PL】決算数値入力!AB59 -> 10729946 | T59: =SUM(T60:T61) -> 7314499 | U59: =SUM(U60:U61) -> 15475207 | V59: =SUM(V60:V61) -> 20028112 | W59: =SUM(W60:W61) -> 29037335 | X59: =SUM(X60:X61) -> 36812363 | Y59: =SUM(Y60:Y61) -> 44121385 | Z59: =SUM(Z60:Z61) -> 47987851 | AA59: =SUM(AA60:AA61) -> 51701846 | ... BQ59: =SUM(BQ60:BQ61) -> 44022870
E60: R6末の既往債 | H60: ● | K60: 既往債の返済スケジュールに基づく利息発生額 | N60: 3267062 | O60: 3316293 | P60: 3571553 | Q60: 4301221 | R60: 4944124 | S60: =【PL】決算数値入力!AB60 -> 3390666.4 | T60: 7314499 | U60: 10426807 | V60: 10790095 | W60: 10529945 | X60: 10171513 | Y60: 9805314 | Z60: 9287703 | AA60: 8710700 | AB60: 8029090 | AC60: 7440621 | AD60: 6856197 | AE60: 6300979 | AF60: 5737430 | AG60: 5165410 | AH60: 4588354 | AI60: 4045880 | AJ60: 3598596 | AK60: 3160696 | AL60: 2719825 | AM60: 2281790 | AN60: 1847085 | AO60: 1412272 | AP60: 1021280 | AQ60: 664686 | AR60: 341080 | AS60: 73217 | AT60: 0 | AU60: 0 | AV60: 0 | AW60: 0 | AX60: 0 | AY60: 0 | AZ60: 0 | BA60: 0 | BB60: 0 | BC60: 0 | BD60: 0 | BE60: 0 | BF60: 0 | BG60: 0 | BH60: 0 | BI60: 0 | BJ60: 0 | BK60: 0 | BL60: 0 | BM60: 0 | BN60: 0 | BO60: 0 | BP60: 0 | BQ60: 0
E61: R7以降の新規債 | H61: ● | K61: 新規債の返済スケジュール×利率の平均値（1.79％） | N61: =【PL】決算数値入力!W61 -> 0 | O61: =【PL】決算数値入力!X61 -> 0 | P61: =【PL】決算数値入力!Y61 -> 0 | Q61: =【PL】決算数値入力!Z61 -> 0 | R61: =【PL】決算数値入力!AA61 -> 0 | S61: =【PL】決算数値入力!AB61 -> 0 | T61: =新規債返済スケジュール!E3 -> 0 | U61: =新規債返済スケジュール!F3 -> 5048400 | V61: =新規債返済スケジュール!G3 -> 9238017 | W61: =新規債返済スケジュール!H3 -> 18507390 | X61: =新規債返済スケジュール!I3 -> 26640850 | Y61: =新規債返済スケジュール!J3 -> 34316071 | Z61: =新規債返済スケジュール!K3 -> 38700148 | AA61: =新規債返済スケジュール!L3 -> 42991146 | ... BQ61: =新規債返済スケジュール!BB3 -> 44022870
D62: 雑支出 | H62: ● | K62: R1~R5決算の平均値で一定 | N62: =【PL】決算数値入力!W62 -> 36222190 | O62: =【PL】決算数値入力!X62 -> 10540977 | P62: =【PL】決算数値入力!Y62 -> 2787191 | Q62: =【PL】決算数値入力!Z62 -> 2403817 | R62: =【PL】決算数値入力!AA62 -> 11123657 | S62: =【PL】決算数値入力!AB62 -> 7339279.4 | T62: =S62 -> 7339279.4 | U62: =T62 -> 7339279.4 | V62: =U62 -> 7339279.4 | W62: =V62 -> 7339279.4 | X62: =W62 -> 7339279.4 | Y62: =X62 -> 7339279.4 | Z62: =Y62 -> 7339279.4 | AA62: =Z62 -> 7339279.4 | ... BQ62: =BP62 -> 7339279.4
C63: 特別損失 | N63: =【PL】決算数値入力!W63 -> 75141547 | O63: =【PL】決算数値入力!X63 -> 0 | P63: =【PL】決算数値入力!Y63 -> 0 | Q63: =【PL】決算数値入力!Z63 -> 0 | R63: =【PL】決算数値入力!AA63 -> 0 | S63: =【PL】決算数値入力!AB63 -> 31797739 | T63: =SUM(T64:T67) -> 0 | U63: =SUM(U64:U67) -> 0 | V63: =SUM(V64:V67) -> 0 | W63: =SUM(W64:W67) -> 0 | X63: =SUM(X64:X67) -> 0 | Y63: =SUM(Y64:Y67) -> 0 | Z63: =SUM(Z64:Z67) -> 0 | AA63: =SUM(AA64:AA67) -> 0 | ... BQ63: =SUM(BQ64:BQ67) -> 0
D64: 固定資産売却損 | H64: ● | K64: 計上しない | N64: =【PL】決算数値入力!W64 -> 75141547 | O64: =【PL】決算数値入力!X64 -> 0 | P64: =【PL】決算数値入力!Y64 -> 0 | Q64: =【PL】決算数値入力!Z64 -> 0 | R64: =【PL】決算数値入力!AA64 -> 0 | S64: =【PL】決算数値入力!AB64 -> 50712200 | T64: 0 | U64: 0 | V64: 0 | W64: 0 | X64: 0 | Y64: 0 | Z64: 0 | AA64: 0 | AB64: 0 | AC64: 0 | AD64: 0 | AE64: 0 | AF64: 0 | AG64: 0 | AH64: 0 | AI64: 0 | AJ64: 0 | AK64: 0 | AL64: 0 | AM64: 0 | AN64: 0 | AO64: 0 | AP64: 0 | AQ64: 0 | AR64: 0 | AS64: 0 | AT64: 0 | AU64: 0 | AV64: 0 | AW64: 0 | AX64: 0 | AY64: 0 | AZ64: 0 | BA64: 0 | BB64: 0 | BC64: 0 | BD64: 0 | BE64: 0 | BF64: 0 | BG64: 0 | BH64: 0 | BI64: 0 | BJ64: 0 | BK64: 0 | BL64: 0 | BM64: 0 | BN64: 0 | BO64: 0 | BP64: 0 | BQ64: 0
D65: 過年度修正損 | H65: ● | K65: 計上しない | N65: =【PL】決算数値入力!W65 -> 0 | O65: =【PL】決算数値入力!X65 -> 0 | P65: =【PL】決算数値入力!Y65 -> 0 | Q65: =【PL】決算数値入力!Z65 -> 0 | R65: =【PL】決算数値入力!AA65 -> 0 | S65: =【PL】決算数値入力!AB65 -> 1666 | V65: 0 | W65: 0 | X65: 0 | Y65: 0 | Z65: 0 | AA65: 0 | AB65: 0 | AC65: 0 | AD65: 0 | AE65: 0 | AF65: 0 | AG65: 0 | AH65: 0 | AI65: 0 | AJ65: 0 | AK65: 0 | AL65: 0 | AM65: 0 | AN65: 0 | AO65: 0 | AP65: 0 | AQ65: 0 | AR65: 0 | AS65: 0 | AT65: 0 | AU65: 0 | AV65: 0 | AW65: 0 | AX65: 0 | AY65: 0 | AZ65: 0 | BA65: 0 | BB65: 0 | BC65: 0 | BD65: 0 | BE65: 0 | BF65: 0 | BG65: 0 | BH65: 0 | BI65: 0 | BJ65: 0 | BK65: 0 | BL65: 0 | BM65: 0 | BN65: 0 | BO65: 0 | BP65: 0 | BQ65: 0
D66: 臨時損失 | H66: ● | K66: 計上しない | N66: =【PL】決算数値入力!W66 -> 0 | O66: =【PL】決算数値入力!X66 -> 0 | P66: =【PL】決算数値入力!Y66 -> 0 | Q66: =【PL】決算数値入力!Z66 -> 0 | R66: =【PL】決算数値入力!AA66 -> 0 | S66: =【PL】決算数値入力!AB66 -> 0 | T66: 0 | U66: 0 | V66: 0 | W66: 0 | X66: 0 | Y66: 0 | Z66: 0 | AA66: 0 | AB66: 0 | AC66: 0 | AD66: 0 | AE66: 0 | AF66: 0 | AG66: 0 | AH66: 0 | AI66: 0 | AJ66: 0 | AK66: 0 | AL66: 0 | AM66: 0 | AN66: 0 | AO66: 0 | AP66: 0 | AQ66: 0 | AR66: 0 | AS66: 0 | AT66: 0 | AU66: 0 | AV66: 0 | AW66: 0 | AX66: 0 | AY66: 0 | AZ66: 0 | BA66: 0 | BB66: 0 | BC66: 0 | BD66: 0 | BE66: 0 | BF66: 0 | BG66: 0 | BH66: 0 | BI66: 0 | BJ66: 0 | BK66: 0 | BL66: 0 | BM66: 0 | BN66: 0 | BO66: 0 | BP66: 0 | BQ66: 0
D67: その他特別損失 | H67: ● | K67: 計上しない | N67: =【PL】決算数値入力!W67 -> 0 | O67: =【PL】決算数値入力!X67 -> 0 | P67: =【PL】決算数値入力!Y67 -> 0 | Q67: =【PL】決算数値入力!Z67 -> 0 | R67: =【PL】決算数値入力!AA67 -> 0 | S67: =【PL】決算数値入力!AB67 -> 0 | T67: 0 | U67: 0 | V67: 0 | W67: 0 | X67: 0 | Y67: 0 | Z67: 0 | AA67: 0 | AB67: 0 | AC67: 0 | AD67: 0 | AE67: 0 | AF67: 0 | AG67: 0 | AH67: 0 | AI67: 0 | AJ67: 0 | AK67: 0 | AL67: 0 | AM67: 0 | AN67: 0 | AO67: 0 | AP67: 0 | AQ67: 0 | AR67: 0 | AS67: 0 | AT67: 0 | AU67: 0 | AV67: 0 | AW67: 0 | AX67: 0 | AY67: 0 | AZ67: 0 | BA67: 0 | BB67: 0 | BC67: 0 | BD67: 0 | BE67: 0 | BF67: 0 | BG67: 0 | BH67: 0 | BI67: 0 | BJ67: 0 | BK67: 0 | BL67: 0 | BM67: 0 | BN67: 0 | BO67: 0 | BP67: 0 | BQ67: 0
B68: 損益 | N68: =【PL】決算数値入力!W68 -> -154789750 | O68: =【PL】決算数値入力!X68 -> -36029202 | P68: =【PL】決算数値入力!Y68 -> -37745561 | Q68: =【PL】決算数値入力!Z68 -> -101071072 | R68: =【PL】決算数値入力!AA68 -> -59562535 | S68: =【PL】決算数値入力!AB68 -> -74753090 | T68: =T5-T24 -> -42377634 | U68: =U5-U24 -> -49845508 | V68: =V5-V24 -> -160291.1 | W68: =W5-W24 -> 3421065.8 | X68: =X5-X24 -> -10180627 | Y68: =Y5-Y24 -> -18787121 | Z68: =Z5-Z24 -> -27590101 | AA68: =AA5-AA24 -> -33982968 | ... BQ68: =BQ5-BQ24 -> -1.0868199e+08
B70: 資本的収支（税込み）
B71: 款 | C71: 項 | D71: 目 | F71: 総括原価の区分 | J71: 控除 項目 | K71: 将来設定条件 | L71: 物価 | M71: 算出根拠 | N71: 実績期間 | S71: 平均値 | T71: 料金算定期間 | X71: 参考期間
G72: 需要家費 | H72: 固定費 | I72: 変動費 | N72: R1 | O72: R2 | P72: R3 | Q72: R4 | R72: R5 | T72: R6 | U72: R7 | V72: R8 | W72: R9 | X72: R10 | Y72: R11 | Z72: R12 | AA72: R13 | AB72: R14 | AC72: R15 | AD72: R16 | AE72: R17 | AF72: R18 | AG72: R19 | AH72: R20 | AI72: R21 | AJ72: R22 | AK72: R23 | AL72: R24 | AM72: R25 | AN72: R26 | AO72: R27 | AP72: R28 | AQ72: R29 | AR72: R30 | AS72: R31 | AT72: R32 | AU72: R33 | AV72: R34 | AW72: R35 | AX72: R36 | AY72: R37 | AZ72: R38 | BA72: R39 | BB72: R40 | BC72: R41 | BD72: R42 | BE72: R43 | BF72: R44 | BG72: R45 | BH72: R46 | BI72: R47 | BJ72: R48 | BK72: R49 | BL72: R50 | BM72: R51 | BN72: R52 | BO72: R53 | BP72: R54 | BQ72: R55
B73: 資本的収入 | N73: =SUM(N74:N79) -> 2676012036 | O73: =SUM(O74:O79) -> 138363434 | P73: =SUM(P74:P79) -> 323524171 | Q73: =SUM(Q74:Q79) -> 110419887 | R73: =SUM(R74:R79) -> 212967818 | S73: =IFERROR(AVERAGE(N73:R73),0) -> 6.9225747e+08 | T73: =SUM(T74:T79) -> 254424733 | U73: =SUM(U74:U79) -> 245418000 | V73: =SUM(V74:V79) -> 1030000000 | W73: =SUM(W74:W79) -> 950000000 | X73: =SUM(X74:X79) -> 500000000 | Y73: =SUM(Y74:Y79) -> 330000000 | Z73: =SUM(Z74:Z79) -> 310000000 | AA73: =SUM(AA74:AA79) -> 310000000 | ... BQ73: =SUM(BQ74:BQ79) -> 0
C74: 企業債 | N74: =【PL】決算数値入力!K129 -> 26700000 | O74: =【PL】決算数値入力!L129 -> 109400000 | P74: =【PL】決算数値入力!M129 -> 143100000 | Q74: =【PL】決算数値入力!N129 -> 57100000 | R74: =【PL】決算数値入力!O129 -> 136400000 | S74: =【PL】決算数値入力!P129 -> 64520000 | T74: 240400000 | U74: 203400000 | V74: =IF((V82+V85+V86+V90-V75-V76-V77-V78)<0,0,(V82+V85+V86+V90-V75-V76-V77-V78)) -> 448670000 | W74: =IF((W82+W85+W86+W90-W75-W76-W77-W78)<0,0,(W82+W85+W86+W90-W75-W76-W77-W78)) -> 402000000 | X74: =IF((X82+X85+X86+X90-X75-X76-X77-X78)<0,0,(X82+X85+X86+X90-X75-X76-X77-X78)) -> 387000000 | Y74: =IF((Y82+Y85+Y86+Y92-Y75-Y76-Y77-Y78)<0,0,(Y82+Y85+Y86+Y92-Y75-Y76-Y77-Y78)) -> 237000000 | Z74: =IF((Z82+Z85+Z86+Z92-Z75-Z76-Z77-Z78)<0,0,(Z82+Z85+Z86+Z92-Z75-Z76-Z77-Z78)) -> 237000000 | AA74: =IF((AA82+AA85+AA86+AA92-AA75-AA76-AA77-AA78)<0,0,(AA82+AA85+AA86+AA92-AA75-AA76-AA77-AA78)) -> 287000000 | AB74: =IF((AB82+AB85+AB86+AB92-AB75-AB76-AB77-AB78)<0,0,(AB82+AB85+AB86+AB92-AB75-AB76-AB77-AB78)) -> 347000000 | AC74: =IF((AC82+AC85+AC86+AC92-AC75-AC76-AC77-AC78)<0,0,(AC82+AC85+AC86+AC92-AC75-AC76-AC77-AC78)) -> 267000000 | AD74: =IF((AD82+AD85+AD86+AD92-AD75-AD76-AD77-AD78)<0,0,(AD82+AD85+AD86+AD92-AD75-AD76-AD77-AD78)) -> 187000000 | AE74: =IF((AE82+AE85+AE86+AE92-AE75-AE76-AE77-AE78)<0,0,(AE82+AE85+AE86+AE92-AE75-AE76-AE77-AE78)) -> 157000000 | AF74: =IF((AF82+AF85+AF86+AF92-AF75-AF76-AF77-AF78)<0,0,(AF82+AF85+AF86+AF92-AF75-AF76-AF77-AF78)) -> 157000000 | ... BQ74: =IF((BQ82+BQ85+BQ86+BQ92-BQ75-BQ76-BQ77-BQ78)<0,0,(BQ82+BQ85+BQ86+BQ92-BQ75-BQ76-BQ77-BQ78)) -> 0
C75: 出資金 | K75: 予定額 | N75: =【PL】決算数値入力!K141 -> 0 | O75: =【PL】決算数値入力!L141 -> 0 | P75: =【PL】決算数値入力!M141 -> 1992527 | Q75: =【PL】決算数値入力!N141 -> 0 | R75: =【PL】決算数値入力!O141 -> 0 | S75: =【PL】決算数値入力!P141 -> 199252.7 | T75: 0 | U75: =16366000 -> 16366000 | V75: =65000000+450000000 -> 515000000 | W75: =45000000+450000000 -> 495000000 | X75: =20000000+40000000 -> 60000000 | Y75: 40000000 | Z75: 20000000 | AA75: 20000000 | AB75: 20000000 | AC75: 20000000 | AD75: 20000000 | AE75: 20000000 | AF75: 20000000 | AG75: 10000000 | AH75: 10000000 | AI75: 10000000 | AJ75: 10000000 | AK75: 10000000 | AL75: 10000000 | AM75: 10000000 | AN75: 10000000 | AO75: 10000000 | AP75: 10000000 | AQ75: 10000000 | AR75: 10000000 | AS75: 10000000 | AT75: 10000000 | AU75: 10000000 | AV75: 10000000 | AW75: 10000000 | AX75: 10000000 | AY75: 10000000 | AZ75: 10000000 | BA75: 10000000 | BB75: 10000000 | BC75: 10000000 | BD75: 10000000 | BE75: 10000000 | BF75: 10000000 | BG75: 10000000 | BH75: 10000000 | BI75: 10000000 | BJ75: 10000000
C76: 他会計補助金 | K76: R6以降はゼロ | N76: =【PL】決算数値入力!K132 -> 733170036 | O76: =【PL】決算数値入力!L132 -> 3283434 | P76: =【PL】決算数値入力!M132 -> 35086328 | Q76: =【PL】決算数値入力!N132 -> 8630000 | R76: =【PL】決算数値入力!O132 -> 11667818 | S76: =【PL】決算数値入力!P132 -> 2.3648396e+08 | T76: 0 | U76: 2686000 | V76: 3000000 | W76: 3000000 | X76: 3000000 | Y76: 3000000 | Z76: 3000000 | AA76: 3000000 | AB76: 3000000 | AC76: 3000000 | AD76: 3000000 | AE76: 3000000 | AF76: 3000000 | AG76: 3000000 | AH76: 3000000 | AI76: 3000000 | AJ76: 3000000 | AK76: 3000000
C77: 国庫補助金 | K77: 予定額 | N77: =【PL】決算数値入力!K135 -> 1916142000 | O77: =【PL】決算数値入力!L135 -> 25680000 | P77: =【PL】決算数値入力!M135 -> 133047000 | Q77: =【PL】決算数値入力!N135 -> 2629187 | R77: =【PL】決算数値入力!O135 -> 64900000 | S77: =【PL】決算数値入力!P135 -> 7.9092982e+08 | T77: 4412733 | U77: 16366000 | V77: 63330000 | W77: 50000000 | X77: 50000000 | Y77: 50000000 | Z77: 50000000
C78: 工事負担金 | K78: 予定額 | N78: =【PL】決算数値入力!K138 -> 0 | O78: =【PL】決算数値入力!L138 -> 0 | P78: =【PL】決算数値入力!M138 -> 10298316 | Q78: =【PL】決算数値入力!N138 -> 42060700 | R78: =【PL】決算数値入力!O138 -> 0 | S78: =【PL】決算数値入力!P138 -> 16075185 | T78: 9612000 | U78: 6600000
C79: 固定資産売却代金 | K79: 計上しない | S79: =IFERROR(AVERAGE(N79:R79),0) -> 0
B80: 資本的支出 | N80: =SUM(N81,N85:N86,N90,N96,N99) -> 2746858038 | O80: =SUM(O81,O85:O86,O90,O96,O99) -> 150071375 | P80: =SUM(P81,P85:P86,P90,P96,P99) -> 345765337 | Q80: =SUM(Q81,Q85:Q86,Q90,Q96,Q99) -> 120983927 | R80: =SUM(R81,R85:R86,R90,R96,R99) -> 280177715 | S80: =SUM(S81,S85:S86,S90,S96,S99) -> 1.1297894e+09 | T80: =SUM(T81,T85:T86,T90,T96,T99) -> 267061936 | U80: =SUM(U81,U85:U86,U90,U96,U99) -> 264833249 | ... BQ80: =SUM(BQ81,BQ85:BQ86,BQ90,BQ96,BQ99) -> 196307993
C81: 建設改良費 | N81: =SUM(N82) -> 0 | O81: =SUM(O82) -> 0 | P81: =SUM(P82) -> 0 | Q81: =SUM(Q82) -> 0 | R81: =SUM(R82) -> 0 | S81: =IFERROR(AVERAGE(N81:R81),0) -> 0 | T81: =SUM(T82) -> 0 | U81: =SUM(U82) -> 0 | V81: =SUM(V82) -> 0 | W81: =SUM(W82) -> 0 | X81: =SUM(X82) -> 0 | Y81: =SUM(Y82) -> 0 | Z81: =SUM(Z82) -> 0 | AA81: =SUM(AA82) -> 0 | ... BQ81: =SUM(BQ82) -> 0
D82: 事務費 | N82: =SUM(N83:N84) -> 0 | O82: =SUM(O83:O84) -> 0 | P82: =SUM(P83:P84) -> 0 | Q82: =SUM(Q83:Q84) -> 0 | R82: =SUM(R83:R84) -> 0 | S82: =IFERROR(AVERAGE(N82:R82),0) -> 0 | T82: =SUM(T83:T84) -> 0 | U82: =SUM(U83:U84) -> 0 | V82: =SUM(V83:V84) -> 0 | W82: =SUM(W83:W84) -> 0 | X82: =SUM(X83:X84) -> 0 | Y82: =SUM(Y83:Y84) -> 0 | Z82: =SUM(Z83:Z84) -> 0 | AA82: =SUM(AA83:AA84) -> 0 | ... BQ82: =SUM(BQ83:BQ84) -> 0
E83: 人件費 | K83: 計上しない | S83: =IFERROR(AVERAGE(N83:R83),0) -> 0
E84: その他（物価上昇を考慮しない） | K84: 計上しない | S84: =IFERROR(AVERAGE(N84:R84),0) -> 0 | T84: 0
C85: 固定資産購入費 | N85: =【PL】決算数値入力!K151 -> 2697464624 | O85: =【PL】決算数値入力!L151 -> 141607400 | P85: =【PL】決算数値入力!M151 -> 338424525 | Q85: =【PL】決算数値入力!N151 -> 111700392 | R85: =【PL】決算数値入力!O151 -> 267791962 | S85: =【PL】決算数値入力!P151 -> 1.1170252e+09 | T85: 252917719
C86: 原水及び浄水施設費 | N86: =SUM(N87:N89) -> 0 | O86: =SUM(O87:O89) -> 0 | P86: =SUM(P87:P89) -> 0 | Q86: =SUM(Q87:Q89) -> 0 | R86: =SUM(R87:R89) -> 0 | S86: =IFERROR(AVERAGE(N86:R86),0) -> 0 | T86: =SUM(T87:T89) -> 0 | U86: =SUM(U87:U89) -> 32732000 | V86: =SUM(V87:V89) -> 750000000 | W86: =SUM(W87:W89) -> 670000000 | X86: =SUM(X87:X89) -> 220000000 | Y86: =SUM(Y87:Y89) -> 70000000 | Z86: =SUM(Z87:Z89) -> 150000000 | AA86: =SUM(AA87:AA89) -> 150000000 | ... BQ86: =SUM(BQ87:BQ89) -> 0
D87: 委託料 | S87: =IFERROR(AVERAGE(N87:R87),0) -> 0 | U87: 32732000
D88: 工事請負費 | K88: 現行計画値 | O88: 0 | P88: 0 | Q88: 0 | R88: 0 | S88: =IFERROR(AVERAGE(N88:R88),0) -> 0 | V88: =V124 -> 750000000 | W88: =W124 -> 670000000 | X88: =X124 -> 220000000 | Y88: =Y124 -> 70000000 | Z88: =Z124 -> 150000000 | AA88: =AA124 -> 150000000 | AB88: =AB124 -> 210000000 | AC88: =AC124 -> 130000000 | ... BQ88: =BQ124 -> 0
D89: 負担金 | S89: =IFERROR(AVERAGE(N89:R89),0) -> 0
C90: 送水及び配水施設費 | N90: =SUM(N91:N95) -> 0 | O90: =SUM(O91:O95) -> 0 | P90: =SUM(P91:P95) -> 0 | Q90: =SUM(Q91:Q95) -> 0 | R90: =SUM(R91:R95) -> 0 | S90: =IFERROR(AVERAGE(N90:R90),0) -> 0 | T90: =SUM(T91:T95) -> 0 | U90: =SUM(U91:U95) -> 213930000 | V90: =SUM(V91:V95) -> 280000000 | W90: =SUM(W91:W95) -> 280000000 | X90: =SUM(X91:X95) -> 280000000 | Y90: =SUM(Y91:Y95) -> 260000000 | Z90: =SUM(Z91:Z95) -> 160000000 | AA90: =SUM(AA91:AA95) -> 161000000 | ... BQ90: =SUM(BQ91:BQ95) -> 4000000
D91: 委託料 | S91: =IFERROR(AVERAGE(N91:R91),0) -> 0
D92: 工事請負費 | K92: 現行計画値 | S92: =IFERROR(AVERAGE(N92:R92),0) -> 0 | U92: 210000000 | V92: =SUM(V120:V121) -> 260000000 | W92: =SUM(W120:W121) -> 260000000 | X92: =SUM(X120:X121) -> 260000000 | Y92: =SUM(Y120:Y121) -> 260000000 | Z92: =SUM(Z120:Z121) -> 160000000 | AA92: =SUM(AA120:AA121) -> 160000000 | AB92: =SUM(AB120:AB121) -> 160000000 | AC92: =SUM(AC120:AC121) -> 160000000 | ... BQ92: =SUM(BQ120:BQ121) -> 0
D93: 量水器費 | S93: =IFERROR(AVERAGE(N93:R93),0) -> 0 | U93: 3930000 | V93: 20000000 | W93: 20000000 | X93: 20000000 | AA93: 1000000 | AB93: 1000000 | AC93: 4000000 | AD93: 20000000 | AE93: 20000000 | AF93: 20000000 | AI93: 1000000 | AJ93: 1000000 | AK93: 4000000 | AL93: 20000000 | AM93: 20000000 | AN93: 20000000 | AQ93: 1000000 | AR93: 1000000 | AS93: 4000000 | AT93: 20000000 | AU93: 20000000 | AV93: 20000000 | AY93: 1000000 | AZ93: 1000000 | BA93: 4000000 | BB93: 20000000 | BC93: 20000000 | BD93: 20000000 | BG93: 1000000 | BH93: 1000000 | BI93: 4000000 | BJ93: 20000000 | BK93: 20000000 | BL93: 20000000 | BO93: 1000000 | BP93: 1000000 | BQ93: 4000000
D94: 負担金 | S94: =IFERROR(AVERAGE(N94:R94),0) -> 0
D95: 補償金 | S95: =IFERROR(AVERAGE(N95:R95),0) -> 0
C96: 企業債償還金 | N96: =SUM(N97:N98) -> 5011414 | O96: =SUM(O97:O98) -> 6752975 | P96: =SUM(P97:P98) -> 7340812 | Q96: =SUM(Q97:Q98) -> 9283535 | R96: =SUM(R97:R98) -> 12385753 | S96: =IFERROR(AVERAGE(N96:R96),0) -> 8154897.8 | T96: =SUM(T97:T98) -> 14144217 | U96: =SUM(U97:U98) -> 18171249 | V96: =SUM(V97:V98) -> 38153082 | W96: =SUM(W97:W98) -> 59344748 | X96: =SUM(X97:X98) -> 60022144 | Y96: =SUM(Y97:Y98) -> 76157864 | Z96: =SUM(Z97:Z98) -> 86244186 | AA96: =SUM(AA97:AA98) -> 108693438 | ... BQ96: =SUM(BQ97:BQ98) -> 192307993
D97: R6末の既往債 | K97: 既往債の返済スケジュールに基づく償還予定額 | N97: =【PL】決算数値入力!K156 -> 5011414 | O97: =【PL】決算数値入力!L156 -> 6752975 | P97: =【PL】決算数値入力!M156 -> 7340812 | Q97: =【PL】決算数値入力!N156 -> 9283535 | R97: =【PL】決算数値入力!O156 -> 12385753 | S97: =IFERROR(AVERAGE(N97:R97),0) -> 8154897.8 | T97: 14144217 | U97: 18171249 | V97: 30881790 | W97: 44652356 | X97: 38508860 | Y97: 47923445 | Z97: 53577472 | AA97: 71501351 | AB97: 53765464 | AC97: 54353929 | AD97: 49366881 | AE97: 49922099 | AF97: 50485648 | AG97: 51057668 | AH97: 50485030 | AI97: 44833168 | AJ97: 43278918 | AK97: 43216900 | AL97: 42121733 | AM97: 40040032 | AN97: 38793244 | AO97: 34916953 | AP97: 28357604 | AQ97: 22391150 | AR97: 18939519 | AS97: 7173448 | AT97: 0 | AU97: 0 | AV97: 0 | AW97: 0 | AX97: 0 | AY97: 0 | AZ97: 0 | BA97: 0 | BB97: 0 | BC97: 0 | BD97: 0 | BE97: 0 | BF97: 0 | BG97: 0 | BH97: 0 | BI97: 0 | BJ97: 0 | BK97: 0 | BL97: 0 | BM97: 0 | BN97: 0 | BO97: 0 | BP97: 0 | BQ97: 0
D98: R7以降の新規債 | K98: 新規債の返済スケジュールに基づく償還予定額 | S98: =IFERROR(AVERAGE(N98:R98),0) -> 0 | T98: =新規債返済スケジュール!E2 -> 0 | U98: 0 | V98: =新規債返済スケジュール!G2 -> 7271292 | W98: =新規債返済スケジュール!H2 -> 14692392 | X98: =新規債返済スケジュール!I2 -> 21513284 | Y98: =新規債返済スケジュール!J2 -> 28234419 | Z98: =新規債返済スケジュール!K2 -> 32666714 | AA98: =新規債返済スケジュール!L2 -> 37192087 | AB98: =新規債返済スケジュール!M2 -> 42622487 | AC98: =新規債返済スケジュール!N2 -> 49138919 | ... BQ98: =新規債返済スケジュール!BB2 -> 192307993
C99: 国庫補助金返還金 | N99: =【PL】決算数値入力!K155 -> 44382000 | O99: =【PL】決算数値入力!L155 -> 1711000 | P99: =【PL】決算数値入力!M155 -> 0 | Q99: =【PL】決算数値入力!N155 -> 0 | R99: =【PL】決算数値入力!O155 -> 0 | S99: =【PL】決算数値入力!P155 -> 4609300
B100: 資本的収支不足額 | N100: =N73-N80 -> -70846002 | O100: =O73-O80 -> -11707941 | P100: =P73-P80 -> -22241166 | Q100: =Q73-Q80 -> -10564040 | R100: =R73-R80 -> -67209897 | S100: =IFERROR(AVERAGE(N100:R100),0) -> -36513809 | T100: =T73-T80 -> -12637203 | U100: =U73-U80 -> -19415249 | V100: =V73-V80 -> -38153082 | W100: =W73-W80 -> -59344748 | X100: =X73-X80 -> -60022144 | Y100: =Y73-Y80 -> -76157864 | Z100: =Z73-Z80 -> -86244186 | AA100: =AA73-AA80 -> -109693438 | ... BQ100: =BQ73-BQ80 -> -196307993
T101: 実績置換 | U101: 予算値
B102: 財政シミュレーション
...

Sheet 【要領】財政シミュ
B2: 収益的収支（税抜き） | N2: （単位：千円） | T2: 1 | U2: 2 | V2: 3 | W2: 4 | X2: 5 | Y2: 6 | Z2: 7 | AA2: 8 | AB2: 9 | AC2: 10 | AD2: 11 | AE2: 12 | AF2: 13 | AG2: 14 | AH2: 15 | AI2: 16 | AJ2: 17 | AK2: 18 | AL2: 19 | AM2: 20 | AN2: 21 | AO2: 22 | AP2: 23 | AQ2: 24 | AR2: 25 | AS2: 26 | AT2: 27 | AU2: 28 | AV2: 29 | AW2: 30 | AX2: 31 | AY2: 32 | AZ2: 33 | BA2: 34 | BB2: 35 | BC2: 36 | BD2: 37 | BE2: 38 | BF2: 39 | BG2: 40 | BH2: 41 | BI2: 42 | BJ2: 43 | BK2: 44 | BL2: 45 | BM2: 46 | BN2: 47 | BO2: 48 | BP2: 49 | BQ2: 50
B3: 款 | C3: 項 | D3: 目 | F3: 総括原価の区分 | J3: 控除 項目 | K3: 将来設定条件 | L3: 物価 | M3: 算出根拠 | N3: 実績期間 | S3: 平均値 | T3: 料金算定期間 | X3: 参考期間
G4: 需要家費 | H4: 固定費 | I4: 変動費 | N4: H26 | O4: H27 | P4: H28 | Q4: H29 | R4: H30 | T4: H31 | U4: R2 | V4: R3 | W4: R4 | X4: R5 | Y4: R6 | Z4: R7 | AA4: R8 | AB4: R9 | AC4: R10 | AD4: R11 | AE4: R12 | AF4: R13 | AG4: R14 | AH4: R15 | AI4: R16 | AJ4: R17 | AK4: R18 | AL4: R19 | AM4: R20 | AN4: R21 | AO4: R22 | AP4: R23 | AQ4: R24 | AR4: R25 | AS4: R26 | AT4: R27 | AU4: R28 | AV4: R29 | AW4: R30 | AX4: R31 | AY4: R32 | AZ4: R33 | BA4: R34 | BB4: R35 | BC4: R36 | BD4: R37 | BE4: R38 | BF4: R39 | BG4: R40 | BH4: R41 | BI4: R42 | BJ4: R43 | BK4: R44 | BL4: R45 | BM4: R46 | BN4: R47 | BO4: R48 | BP4: R49 | BQ4: R50
B5: 水道事業収益 | N5: =【PL】決算数値入力!#REF! -> #REF! | O5: =【PL】決算数値入力!#REF! -> #REF! | P5: =【PL】決算数値入力!#REF! -> #REF! | Q5: =【PL】決算数値入力!#REF! -> #REF! | R5: =【PL】決算数値入力!#REF! -> #REF! | S5: =【PL】決算数値入力!#REF! -> #REF! | T5: =SUM(T6,T11,T18,T19) -> #REF! | U5: =SUM(U6,U11,U18,U19) -> #REF! | V5: =SUM(V6,V11,V18,V19) -> #REF! | W5: =SUM(W6,W11,W18,W19) -> #REF! | X5: =SUM(X6,X11,X18,X19) -> #REF! | Y5: =SUM(Y6,Y11,Y18,Y19) -> #REF! | Z5: =SUM(Z6,Z11,Z18,Z19) -> #REF! | AA5: =SUM(AA6,AA11,AA18,AA19) -> #REF! | ... BQ5: =SUM(BQ6,BQ11,BQ18,BQ19) -> #REF!
C6: 営業収益 | N6: =【PL】決算数値入力!#REF! -> #REF! | O6: =【PL】決算数値入力!#REF! -> #REF! | P6: =【PL】決算数値入力!#REF! -> #REF! | Q6: =【PL】決算数値入力!#REF! -> #REF! | R6: =【PL】決算数値入力!#REF! -> #REF! | S6: =【PL】決算数値入力!#REF! -> #REF! | T6: =SUM(T7:T10) -> #REF! | U6: =SUM(U7:U10) -> #REF! | V6: =SUM(V7:V10) -> #REF! | W6: =SUM(W7:W10) -> #REF! | X6: =SUM(X7:X10) -> #REF! | Y6: =SUM(Y7:Y10) -> #REF! | Z6: =SUM(Z7:Z10) -> #REF! | AA6: =SUM(AA7:AA10) -> #REF! | ... BQ6: =SUM(BQ7:BQ10) -> #REF!
D7: 給水収益 | K7: 【収益】給水収益シート参照 | N7: =【PL】決算数値入力!#REF! -> #REF! | O7: =【PL】決算数値入力!#REF! -> #REF! | P7: =【PL】決算数値入力!#REF! -> #REF! | Q7: =【PL】決算数値入力!#REF! -> #REF! | R7: =【PL】決算数値入力!#REF! -> #REF! | S7: =【PL】決算数値入力!#REF! -> #REF! | T7: ='【収益－要領】給水収益'!S36 -> #REF! | U7: ='【収益－要領】給水収益'!T36 -> #REF! | V7: ='【収益－要領】給水収益'!U36 -> #REF! | W7: ='【収益－要領】給水収益'!V36 -> #REF! | X7: ='【収益－要領】給水収益'!W36 -> #REF! | Y7: ='【収益－要領】給水収益'!X36 -> #REF! | Z7: ='【収益－要領】給水収益'!Y36 -> #REF! | AA7: ='【収益－要領】給水収益'!Z36 -> #REF! | ... BQ7: ='【収益－要領】給水収益'!BP36 -> #REF!
D8: 加入金 | N8: =【PL】決算数値入力!#REF! -> #REF! | O8: =【PL】決算数値入力!#REF! -> #REF! | P8: =【PL】決算数値入力!#REF! -> #REF! | Q8: =【PL】決算数値入力!#REF! -> #REF! | R8: =【PL】決算数値入力!#REF! -> #REF! | S8: =【PL】決算数値入力!#REF! -> #REF! | T8: =S8 -> #REF! | U8: =T8 -> #REF! | V8: =U8 -> #REF! | W8: =V8 -> #REF! | X8: =W8 -> #REF! | Y8: =X8 -> #REF! | Z8: =Y8 -> #REF! | AA8: =Z8 -> #REF! | ... BQ8: =BP8 -> #REF!
D9: 受託工事収益 | K9: 計上しない | N9: =【PL】決算数値入力!#REF! -> #REF! | O9: =【PL】決算数値入力!#REF! -> #REF! | P9: =【PL】決算数値入力!#REF! -> #REF! | Q9: =【PL】決算数値入力!#REF! -> #REF! | R9: =【PL】決算数値入力!#REF! -> #REF! | S9: =【PL】決算数値入力!#REF! -> #REF!
D10: その他の営業収益 | J10: ● | K10: H22~~H30決算の平均値で一定 | N10: =【PL】決算数値入力!#REF! -> #REF! | O10: =【PL】決算数値入力!#REF! -> #REF! | P10: =【PL】決算数値入力!#REF! -> #REF! | Q10: =【PL】決算数値入力!#REF! -> #REF! | R10: =【PL】決算数値入力!#REF! -> #REF! | S10: =【PL】決算数値入力!#REF! -> #REF! | T10: =S10 -> #REF! | U10: =T10 -> #REF! | V10: =U10 -> #REF! | W10: =V10 -> #REF! | X10: =W10 -> #REF! | Y10: =X10 -> #REF! | Z10: =Y10 -> #REF! | AA10: =Z10 -> #REF! | ... BQ10: =BP10 -> #REF!
C11: 営業外収益 | N11: =【PL】決算数値入力!#REF! -> #REF! | O11: =【PL】決算数値入力!#REF! -> #REF! | P11: =【PL】決算数値入力!#REF! -> #REF! | Q11: =【PL】決算数値入力!#REF! -> #REF! | R11: =【PL】決算数値入力!#REF! -> #REF! | S11: =【PL】決算数値入力!#REF! -> #REF! | T11: =SUM(T12:T15) -> #REF! | U11: =SUM(U12:U15) -> #REF! | V11: =SUM(V12:V15) -> #REF! | W11: =SUM(W12:W15) -> #REF! | X11: =SUM(X12:X15) -> #REF! | Y11: =SUM(Y12:Y15) -> #REF! | Z11: =SUM(Z12:Z15) -> #REF! | AA11: =SUM(AA12:AA15) -> #REF! | ... BQ11: =SUM(BQ12:BQ15) -> #REF!
D12: 受取利息及び配当金 | J12: ● | K12: H22~~H30決算の平均値で一定 | N12: =【PL】決算数値入力!#REF! -> #REF! | O12: =【PL】決算数値入力!#REF! -> #REF! | P12: =【PL】決算数値入力!#REF! -> #REF! | Q12: =【PL】決算数値入力!#REF! -> #REF! | R12: =【PL】決算数値入力!#REF! -> #REF! | S12: =【PL】決算数値入力!#REF! -> #REF! | T12: =S12 -> #REF! | U12: =T12 -> #REF! | V12: =U12 -> #REF! | W12: =V12 -> #REF! | X12: =W12 -> #REF! | Y12: =X12 -> #REF! | Z12: =Y12 -> #REF! | AA12: =Z12 -> #REF! | ... BQ12: =BP12 -> #REF!
D13: 他会計補助金 | J13: ● | K13: 予定額 | N13: =【PL】決算数値入力!#REF! -> #REF! | O13: =【PL】決算数値入力!#REF! -> #REF! | P13: =【PL】決算数値入力!#REF! -> #REF! | Q13: =【PL】決算数値入力!#REF! -> #REF! | R13: =【PL】決算数値入力!#REF! -> #REF! | S13: =【PL】決算数値入力!#REF! -> #REF! | T13: =S13 -> #REF! | U13: =T13 -> #REF! | V13: =U13 -> #REF! | W13: =V13 -> #REF! | X13: =W13 -> #REF! | Y13: =X13 -> #REF! | Z13: =Y13 -> #REF! | AA13: =Z13 -> #REF! | ... BQ13: =BP13 -> #REF!
D14: 雑収益 | J14: ● | K14: H22~~H30決算の平均値で一定 | N14: =【PL】決算数値入力!#REF! -> #REF! | O14: =【PL】決算数値入力!#REF! -> #REF! | P14: =【PL】決算数値入力!#REF! -> #REF! | Q14: =【PL】決算数値入力!#REF! -> #REF! | R14: =【PL】決算数値入力!#REF! -> #REF! | S14: =【PL】決算数値入力!#REF! -> #REF! | T14: =S14 -> #REF! | U14: =T14 -> #REF! | V14: =U14 -> #REF! | W14: =V14 -> #REF! | X14: =W14 -> #REF! | Y14: =X14 -> #REF! | Z14: =Y14 -> #REF! | AA14: =Z14 -> #REF! | ... BQ14: =BP14 -> #REF!
D15: 長期前受金戻入益 | N15: =【PL】決算数値入力!#REF! -> #REF! | O15: =【PL】決算数値入力!#REF! -> #REF! | P15: =【PL】決算数値入力!#REF! -> #REF! | Q15: =【PL】決算数値入力!#REF! -> #REF! | R15: =【PL】決算数値入力!#REF! -> #REF! | S15: =【PL】決算数値入力!#REF! -> #REF! | T15: =SUM(T16:T17) -> 4493777 | U15: =SUM(U16:U17) -> 11498029 | V15: =SUM(V16:V17) -> 5367026 | W15: =SUM(W16:W17) -> 5367026 | X15: =SUM(X16:X17) -> 5367026 | Y15: =SUM(Y16:Y17) -> 5367026 | Z15: =SUM(Z16:Z17) -> 5367026 | AA15: =SUM(AA16:AA17) -> 5367026 | ... BQ15: =SUM(BQ16:BQ17) -> 6929736.8
E16: H30末の取得資産 | K16: 固定資産台帳データに基づく算定額 | N16: =【PL】決算数値入力!#REF! -> #REF! | O16: =【PL】決算数値入力!#REF! -> #REF! | P16: =【PL】決算数値入力!#REF! -> #REF! | Q16: =【PL】決算数値入力!#REF! -> #REF! | R16: =【PL】決算数値入力!#REF! -> #REF! | S16: =【PL】決算数値入力!#REF! -> #REF! | T16: 4493777 | U16: 11498029 | V16: 5367026 | W16: 5367026 | X16: 5367026 | Y16: 5367026 | Z16: 5367026 | AA16: 5367026 | AB16: 5367026 | AC16: 5367026 | AD16: 5367026 | AE16: 5367026 | AF16: 5367026 | AG16: 5367026 | AH16: 5332713 | AI16: 3161272 | AJ16: 1216803 | AK16: 956394 | AL16: 777136 | AM16: 709860 | AN16: 709860 | AO16: 709860 | AP16: 709860 | AQ16: 709860 | AR16: 709860 | AS16: 709860 | AT16: 709860 | AU16: 709860 | AV16: 709860 | AW16: 709860 | AX16: 709860 | AY16: 709860 | AZ16: 709860 | BA16: 709860 | BB16: 709860 | BC16: 709860 | BD16: 131539 | BE16: 0 | BF16: 0 | BG16: 0 | BH16: 0 | BI16: 0 | BJ16: 0 | BK16: 0 | BL16: 0 | BM16: 0 | BN16: 0 | BO16: 0 | BP16: 0 | BQ16: 0
E17: H31以降の取得資産 | K17: 償却計算額 | N17: =【PL】決算数値入力!#REF! -> #REF! | O17: =【PL】決算数値入力!#REF! -> #REF! | P17: =【PL】決算数値入力!#REF! -> #REF! | Q17: =【PL】決算数値入力!#REF! -> #REF! | R17: =【PL】決算数値入力!#REF! -> #REF! | S17: =【PL】決算数値入力!#REF! -> #REF! | T17: =新規取得!I5 -> 0 | U17: =新規取得!J5 -> 0 | V17: =新規取得!K5 -> 0 | W17: =新規取得!L5 -> 0 | X17: =新規取得!M5 -> 0 | Y17: =新規取得!N5 -> 0 | Z17: =新規取得!O5 -> 0 | AA17: =新規取得!P5 -> 0 | ... BQ17: =新規取得!BF5 -> 6929736.8
C18: 引当金戻入益 | J18: ● | K18: 計上しない | N18: =【PL】決算数値入力!#REF! -> #REF! | O18: =【PL】決算数値入力!#REF! -> #REF! | P18: =【PL】決算数値入力!#REF! -> #REF! | Q18: =【PL】決算数値入力!#REF! -> #REF! | R18: =【PL】決算数値入力!#REF! -> #REF! | S18: =【PL】決算数値入力!#REF! -> #REF! | T18: 0 | U18: 0 | V18: 0 | W18: 0 | X18: 0 | Y18: 0 | Z18: 0 | AA18: 0 | AB18: 0 | AC18: 0 | AD18: 0 | AE18: 0 | AF18: 0 | AG18: 0 | AH18: 0 | AI18: 0 | AJ18: 0 | AK18: 0 | AL18: 0 | AM18: 0 | AN18: 0 | AO18: 0 | AP18: 0 | AQ18: 0 | AR18: 0 | AS18: 0 | AT18: 0 | AU18: 0 | AV18: 0 | AW18: 0 | AX18: 0 | AY18: 0 | AZ18: 0 | BA18: 0 | BB18: 0 | BC18: 0 | BD18: 0 | BE18: 0 | BF18: 0 | BG18: 0 | BH18: 0 | BI18: 0 | BJ18: 0 | BK18: 0 | BL18: 0 | BM18: 0 | BN18: 0 | BO18: 0 | BP18: 0 | BQ18: 0
C19: 特別利益 | N19: =【PL】決算数値入力!#REF! -> #REF! | O19: =【PL】決算数値入力!#REF! -> #REF! | P19: =【PL】決算数値入力!#REF! -> #REF! | Q19: =【PL】決算数値入力!#REF! -> #REF! | R19: =【PL】決算数値入力!#REF! -> #REF! | S19: =【PL】決算数値入力!#REF! -> #REF! | T19: =SUM(T20:T22) -> 0 | U19: =SUM(U20:U22) -> 0 | V19: =SUM(V20:V22) -> 0 | W19: =SUM(W20:W22) -> 0 | X19: =SUM(X20:X22) -> 0 | Y19: =SUM(Y20:Y22) -> 0 | Z19: =SUM(Z20:Z22) -> 0 | AA19: =SUM(AA20:AA22) -> 0 | ... BQ19: =SUM(BQ20:BQ22) -> 0
D20: 固定資産売却益 | J20: ● | K20: 計上しない | N20: =【PL】決算数値入力!#REF! -> #REF! | O20: =【PL】決算数値入力!#REF! -> #REF! | P20: =【PL】決算数値入力!#REF! -> #REF! | Q20: =【PL】決算数値入力!#REF! -> #REF! | R20: =【PL】決算数値入力!#REF! -> #REF! | S20: =【PL】決算数値入力!#REF! -> #REF! | T20: 0 | U20: 0 | V20: 0 | W20: 0 | X20: 0 | Y20: 0 | Z20: 0 | AA20: 0 | AB20: 0 | AC20: 0 | AD20: 0 | AE20: 0 | AF20: 0 | AG20: 0 | AH20: 0 | AI20: 0 | AJ20: 0 | AK20: 0 | AL20: 0 | AM20: 0 | AN20: 0 | AO20: 0 | AP20: 0 | AQ20: 0 | AR20: 0 | AS20: 0 | AT20: 0 | AU20: 0 | AV20: 0 | AW20: 0 | AX20: 0 | AY20: 0 | AZ20: 0 | BA20: 0 | BB20: 0 | BC20: 0 | BD20: 0 | BE20: 0 | BF20: 0 | BG20: 0 | BH20: 0 | BI20: 0 | BJ20: 0 | BK20: 0 | BL20: 0 | BM20: 0 | BN20: 0 | BO20: 0 | BP20: 0 | BQ20: 0
D21: 過年度修正益 | J21: ● | K21: 計上しない | N21: =【PL】決算数値入力!#REF! -> #REF! | O21: =【PL】決算数値入力!#REF! -> #REF! | P21: =【PL】決算数値入力!#REF! -> #REF! | Q21: =【PL】決算数値入力!#REF! -> #REF! | R21: =【PL】決算数値入力!#REF! -> #REF! | S21: =【PL】決算数値入力!#REF! -> #REF! | T21: 0 | U21: 0 | V21: 0 | W21: 0 | X21: 0 | Y21: 0 | Z21: 0 | AA21: 0 | AB21: 0 | AC21: 0 | AD21: 0 | AE21: 0 | AF21: 0 | AG21: 0 | AH21: 0 | AI21: 0 | AJ21: 0 | AK21: 0 | AL21: 0 | AM21: 0 | AN21: 0 | AO21: 0 | AP21: 0 | AQ21: 0 | AR21: 0 | AS21: 0 | AT21: 0 | AU21: 0 | AV21: 0 | AW21: 0 | AX21: 0 | AY21: 0 | AZ21: 0 | BA21: 0 | BB21: 0 | BC21: 0 | BD21: 0 | BE21: 0 | BF21: 0 | BG21: 0 | BH21: 0 | BI21: 0 | BJ21: 0 | BK21: 0 | BL21: 0 | BM21: 0 | BN21: 0 | BO21: 0 | BP21: 0 | BQ21: 0
D22: その他特別利益 | J22: ● | K22: 計上しない | N22: =【PL】決算数値入力!#REF! -> #REF! | O22: =【PL】決算数値入力!#REF! -> #REF! | P22: =【PL】決算数値入力!#REF! -> #REF! | Q22: =【PL】決算数値入力!#REF! -> #REF! | R22: =【PL】決算数値入力!#REF! -> #REF! | S22: =【PL】決算数値入力!#REF! -> #REF! | T22: 0 | U22: 0 | V22: 0 | W22: 0 | X22: 0 | Y22: 0 | Z22: 0 | AA22: 0 | AB22: 0 | AC22: 0 | AD22: 0 | AE22: 0 | AF22: 0 | AG22: 0 | AH22: 0 | AI22: 0 | AJ22: 0 | AK22: 0 | AL22: 0 | AM22: 0 | AN22: 0 | AO22: 0 | AP22: 0 | AQ22: 0 | AR22: 0 | AS22: 0 | AT22: 0 | AU22: 0 | AV22: 0 | AW22: 0 | AX22: 0 | AY22: 0 | AZ22: 0 | BA22: 0 | BB22: 0 | BC22: 0 | BD22: 0 | BE22: 0 | BF22: 0 | BG22: 0 | BH22: 0 | BI22: 0 | BJ22: 0 | BK22: 0 | BL22: 0 | BM22: 0 | BN22: 0 | BO22: 0 | BP22: 0 | BQ22: 0
B23: 水道事業費用 | N23: =【PL】決算数値入力!#REF! -> #REF! | O23: =【PL】決算数値入力!#REF! -> #REF! | P23: =【PL】決算数値入力!#REF! -> #REF! | Q23: =【PL】決算数値入力!#REF! -> #REF! | R23: =【PL】決算数値入力!#REF! -> #REF! | S23: =【PL】決算数値入力!#REF! -> #REF! | T23: =SUM(T24,T57,T62) -> #REF! | U23: =SUM(U24,U57,U62) -> #REF! | V23: =SUM(V24,V57,V62) -> #REF! | W23: =SUM(W24,W57,W62) -> #REF! | X23: =SUM(X24,X57,X62) -> #REF! | Y23: =SUM(Y24,Y57,Y62) -> #REF! | Z23: =SUM(Z24,Z57,Z62) -> #REF! | AA23: =SUM(AA24,AA57,AA62) -> #REF! | ... BQ23: =SUM(BQ24,BQ57,BQ62) -> #REF!
C24: 営業費用 | N24: =【PL】決算数値入力!#REF! -> #REF! | O24: =【PL】決算数値入力!#REF! -> #REF! | P24: =【PL】決算数値入力!#REF! -> #REF! | Q24: =【PL】決算数値入力!#REF! -> #REF! | R24: =【PL】決算数値入力!#REF! -> #REF! | S24: =【PL】決算数値入力!#REF! -> #REF! | T24: =SUM(T25,T33,T42,T51,T54) -> #REF! | U24: =SUM(U25,U33,U42,U51,U54) -> #REF! | V24: =SUM(V25,V33,V42,V51,V54) -> #REF! | W24: =SUM(W25,W33,W42,W51,W54) -> #REF! | X24: =SUM(X25,X33,X42,X51,X54) -> #REF! | Y24: =SUM(Y25,Y33,Y42,Y51,Y54) -> #REF! | Z24: =SUM(Z25,Z33,Z42,Z51,Z54) -> #REF! | AA24: =SUM(AA25,AA33,AA42,AA51,AA54) -> #REF! | ... BQ24: =SUM(BQ25,BQ33,BQ42,BQ51,BQ54) -> #REF!
D25: 原水及び浄水費 | F25: 原浄水部門費 | N25: =【PL】決算数値入力!#REF! -> #REF! | O25: =【PL】決算数値入力!#REF! -> #REF! | P25: =【PL】決算数値入力!#REF! -> #REF! | Q25: =【PL】決算数値入力!#REF! -> #REF! | R25: =【PL】決算数値入力!#REF! -> #REF! | S25: =【PL】決算数値入力!#REF! -> #REF! | T25: =SUM(T26:T32) -> #REF! | U25: =SUM(U26:U32) -> #REF! | V25: =SUM(V26:V32) -> #REF! | W25: =SUM(W26:W32) -> #REF! | X25: =SUM(X26:X32) -> #REF! | Y25: =SUM(Y26:Y32) -> #REF! | Z25: =SUM(Z26:Z32) -> #REF! | AA25: =SUM(AA26:AA32) -> #REF! | ... BQ25: =SUM(BQ26:BQ32) -> #REF!
E26: 人件費 | H26: ● | K26: H22~~H30決算の平均値に物価上昇率を加味 | L26: ● | N26: =【PL】決算数値入力!#REF! -> #REF! | O26: =【PL】決算数値入力!#REF! -> #REF! | P26: =【PL】決算数値入力!#REF! -> #REF! | Q26: =【PL】決算数値入力!#REF! -> #REF! | R26: =【PL】決算数値入力!#REF! -> #REF! | S26: =【PL】決算数値入力!#REF! -> #REF! | T26: =ROUND(S26*(1+物価上昇率!$G$9),0) -> #REF! | U26: =ROUND(T26*(1+物価上昇率!$G$9),0) -> #REF! | V26: =ROUND(U26*(1+物価上昇率!$G$9),0) -> #REF! | W26: =ROUND(V26*(1+物価上昇率!$G$9),0) -> #REF! | X26: =ROUND(W26*(1+物価上昇率!$G$9),0) -> #REF! | Y26: =ROUND(X26*(1+物価上昇率!$G$9),0) -> #REF! | Z26: =ROUND(Y26*(1+物価上昇率!$G$9),0) -> #REF! | AA26: =ROUND(Z26*(1+物価上昇率!$G$9),0) -> #REF! | ... BQ26: =ROUND(BP26*(1+物価上昇率!$G$9),0) -> #REF!
E27: 動力費 | I27: ● | K27: H22~~H30有収水量1㎥あたり費用×有収水量（見込） | L27: ● | N27: =【PL】決算数値入力!#REF! -> #REF! | O27: =【PL】決算数値入力!#REF! -> #REF! | P27: =【PL】決算数値入力!#REF! -> #REF! | Q27: =【PL】決算数値入力!#REF! -> #REF! | R27: =【PL】決算数値入力!#REF! -> #REF! | S27: =【PL】決算数値入力!#REF! -> #REF! | T27: =ROUND(SUM($N27:$R27)/SUM(【収益】水需要予測!#REF!),0)*【収益】水需要予測!#REF! -> #REF! | U27: =ROUND(SUM($N27:$R27)/SUM(【収益】水需要予測!#REF!),0)*【収益】水需要予測!#REF! -> #REF! | V27: =ROUND(SUM($N27:$R27)/SUM(【収益】水需要予測!#REF!),0)*【収益】水需要予測!#REF! -> #REF! | W27: =ROUND(SUM($N27:$R27)/SUM(【収益】水需要予測!#REF!),0)*【収益】水需要予測!#REF! -> #REF! | X27: =ROUND(SUM($N27:$R27)/SUM(【収益】水需要予測!#REF!),0)*【収益】水需要予測!#REF! -> #REF! | Y27: =ROUND(SUM($N27:$R27)/SUM(【収益】水需要予測!#REF!),0)*【収益】水需要予測!#REF! -> #REF! | Z27: =ROUND(SUM($N27:$R27)/SUM(【収益】水需要予測!#REF!),0)*【収益】水需要予測!#REF! -> #REF! | AA27: =ROUND(SUM($N27:$R27)/SUM(【収益】水需要予測!#REF!),0)*【収益】水需要予測!#REF! -> #REF! | ... BQ27: =ROUND(SUM($N27:$R27)/SUM(【収益】水需要予測!#REF!),0)*【収益】水需要予測!#REF! -> #REF!
E28: 薬品費 | I28: ● | K28: H22~~H30有収水量1㎥あたり費用×有収水量（見込） | L28: ● | N28: =【PL】決算数値入力!#REF! -> #REF! | O28: =【PL】決算数値入力!#REF! -> #REF! | P28: =【PL】決算数値入力!#REF! -> #REF! | Q28: =【PL】決算数値入力!#REF! -> #REF! | R28: =【PL】決算数値入力!#REF! -> #REF! | S28: =【PL】決算数値入力!#REF! -> #REF! | T28: =ROUND(SUM($N28:$R28)/SUM(【収益】水需要予測!#REF!),0)*【収益】水需要予測!#REF! -> #REF! | U28: =ROUND(SUM($N28:$R28)/SUM(【収益】水需要予測!#REF!),0)*【収益】水需要予測!#REF! -> #REF! | V28: =ROUND(SUM($N28:$R28)/SUM(【収益】水需要予測!#REF!),0)*【収益】水需要予測!#REF! -> #REF! | W28: =ROUND(SUM($N28:$R28)/SUM(【収益】水需要予測!#REF!),0)*【収益】水需要予測!#REF! -> #REF! | X28: =ROUND(SUM($N28:$R28)/SUM(【収益】水需要予測!#REF!),0)*【収益】水需要予測!#REF! -> #REF! | Y28: =ROUND(SUM($N28:$R28)/SUM(【収益】水需要予測!#REF!),0)*【収益】水需要予測!#REF! -> #REF! | Z28: =ROUND(SUM($N28:$R28)/SUM(【収益】水需要予測!#REF!),0)*【収益】水需要予測!#REF! -> #REF! | AA28: =ROUND(SUM($N28:$R28)/SUM(【収益】水需要予測!#REF!),0)*【収益】水需要予測!#REF! -> #REF! | ... BQ28: =ROUND(SUM($N28:$R28)/SUM(【収益】水需要予測!#REF!),0)*【収益】水需要予測!#REF! -> #REF!
E29: 修繕費 | H29: ● | K29: H22~~H30決算の平均値に物価上昇率を加味 | L29: ● | N29: =【PL】決算数値入力!#REF! -> #REF! | O29: =【PL】決算数値入力!#REF! -> #REF! | P29: =【PL】決算数値入力!#REF! -> #REF! | Q29: =【PL】決算数値入力!#REF! -> #REF! | R29: =【PL】決算数値入力!#REF! -> #REF! | S29: =【PL】決算数値入力!#REF! -> #REF! | T29: =ROUND(S29*(1+物価上昇率!$G$9),0) -> #REF! | U29: =ROUND(T29*(1+物価上昇率!$G$9),0) -> #REF! | V29: =ROUND(U29*(1+物価上昇率!$G$9),0) -> #REF! | W29: =ROUND(V29*(1+物価上昇率!$G$9),0) -> #REF! | X29: =ROUND(W29*(1+物価上昇率!$G$9),0) -> #REF! | Y29: =ROUND(X29*(1+物価上昇率!$G$9),0) -> #REF! | Z29: =ROUND(Y29*(1+物価上昇率!$G$9),0) -> #REF! | AA29: =ROUND(Z29*(1+物価上昇率!$G$9),0) -> #REF! | ... BQ29: =ROUND(BP29*(1+物価上昇率!$G$9),0) -> #REF!
E30: 委託料 | H30: ● | K30: H22~~H30決算の平均値に物価上昇率を加味 | L30: ● | N30: =【PL】決算数値入力!#REF! -> #REF! | O30: =【PL】決算数値入力!#REF! -> #REF! | P30: =【PL】決算数値入力!#REF! -> #REF! | Q30: =【PL】決算数値入力!#REF! -> #REF! | R30: =【PL】決算数値入力!#REF! -> #REF! | S30: =【PL】決算数値入力!#REF! -> #REF! | T30: =ROUND(S30*(1+物価上昇率!$G$9),0) -> #REF! | U30: =ROUND(T30*(1+物価上昇率!$G$9),0) -> #REF! | V30: =ROUND(U30*(1+物価上昇率!$G$9),0) -> #REF! | W30: =ROUND(V30*(1+物価上昇率!$G$9),0) -> #REF! | X30: =ROUND(W30*(1+物価上昇率!$G$9),0) -> #REF! | Y30: =ROUND(X30*(1+物価上昇率!$G$9),0) -> #REF! | Z30: =ROUND(Y30*(1+物価上昇率!$G$9),0) -> #REF! | AA30: =ROUND(Z30*(1+物価上昇率!$G$9),0) -> #REF! | ... BQ30: =ROUND(BP30*(1+物価上昇率!$G$9),0) -> #REF!
E31: その他（物価上昇を考慮する） | H31: ● | K31: H22~~H30決算の平均値に物価上昇率を加味 | L31: ● | N31: =【PL】決算数値入力!#REF! -> #REF! | O31: =【PL】決算数値入力!#REF! -> #REF! | P31: =【PL】決算数値入力!#REF! -> #REF! | Q31: =【PL】決算数値入力!#REF! -> #REF! | R31: =【PL】決算数値入力!#REF! -> #REF! | S31: =【PL】決算数値入力!#REF! -> #REF! | T31: =ROUND(S31*(1+物価上昇率!$G$9),0) -> #REF! | U31: =ROUND(T31*(1+物価上昇率!$G$9),0) -> #REF! | V31: =ROUND(U31*(1+物価上昇率!$G$9),0) -> #REF! | W31: =ROUND(V31*(1+物価上昇率!$G$9),0) -> #REF! | X31: =ROUND(W31*(1+物価上昇率!$G$9),0) -> #REF! | Y31: =ROUND(X31*(1+物価上昇率!$G$9),0) -> #REF! | Z31: =ROUND(Y31*(1+物価上昇率!$G$9),0) -> #REF! | AA31: =ROUND(Z31*(1+物価上昇率!$G$9),0) -> #REF! | ... BQ31: =ROUND(BP31*(1+物価上昇率!$G$9),0) -> #REF!
E32: その他（物価上昇を考慮しない） | H32: ● | K32: H22~~H30決算の平均値で一定 | N32: =【PL】決算数値入力!#REF! -> #REF! | O32: =【PL】決算数値入力!#REF! -> #REF! | P32: =【PL】決算数値入力!#REF! -> #REF! | Q32: =【PL】決算数値入力!#REF! -> #REF! | R32: =【PL】決算数値入力!#REF! -> #REF! | S32: =【PL】決算数値入力!#REF! -> #REF! | T32: =S32 -> #REF! | U32: =T32 -> #REF! | V32: =U32 -> #REF! | W32: =V32 -> #REF! | X32: =W32 -> #REF! | Y32: =X32 -> #REF! | Z32: =Y32 -> #REF! | AA32: =Z32 -> #REF! | ... BQ32: =BP32 -> #REF!
D33: 配水及び給水費 | F33: 配給水部門費 | N33: =【PL】決算数値入力!#REF! -> #REF! | O33: =【PL】決算数値入力!#REF! -> #REF! | P33: =【PL】決算数値入力!#REF! -> #REF! | Q33: =【PL】決算数値入力!#REF! -> #REF! | R33: =【PL】決算数値入力!#REF! -> #REF! | S33: =【PL】決算数値入力!#REF! -> #REF! | T33: =SUM(T34:T40) -> #REF! | U33: =SUM(U34:U40) -> #REF! | V33: =SUM(V34:V40) -> #REF! | W33: =SUM(W34:W40) -> #REF! | X33: =SUM(X34:X40) -> #REF! | Y33: =SUM(Y34:Y40) -> #REF! | Z33: =SUM(Z34:Z40) -> #REF! | AA33: =SUM(AA34:AA40) -> #REF! | ... BQ33: =SUM(BQ34:BQ40) -> #REF!
E34: 人件費 | H34: ● | K34: H22~~H30決算の平均値に物価上昇率を加味 | L34: ● | N34: =【PL】決算数値入力!#REF! -> #REF! | O34: =【PL】決算数値入力!#REF! -> #REF! | P34: =【PL】決算数値入力!#REF! -> #REF! | Q34: =【PL】決算数値入力!#REF! -> #REF! | R34: =【PL】決算数値入力!#REF! -> #REF! | S34: =【PL】決算数値入力!#REF! -> #REF! | T34: =ROUND(S34*(1+物価上昇率!$G$9),0) -> #REF! | U34: =ROUND(T34*(1+物価上昇率!$G$9),0) -> #REF! | V34: =ROUND(U34*(1+物価上昇率!$G$9),0) -> #REF! | W34: =ROUND(V34*(1+物価上昇率!$G$9),0) -> #REF! | X34: =ROUND(W34*(1+物価上昇率!$G$9),0) -> #REF! | Y34: =ROUND(X34*(1+物価上昇率!$G$9),0) -> #REF! | Z34: =ROUND(Y34*(1+物価上昇率!$G$9),0) -> #REF! | AA34: =ROUND(Z34*(1+物価上昇率!$G$9),0) -> #REF! | ... BQ34: =ROUND(BP34*(1+物価上昇率!$G$9),0) -> #REF!
E35: 動力費 | I35: ● | K35: H22~~H30有収水量1㎥あたり費用×有収水量（見込） | L35: ● | N35: =【PL】決算数値入力!#REF! -> #REF! | O35: =【PL】決算数値入力!#REF! -> #REF! | P35: =【PL】決算数値入力!#REF! -> #REF! | Q35: =【PL】決算数値入力!#REF! -> #REF! | R35: =【PL】決算数値入力!#REF! -> #REF! | S35: =【PL】決算数値入力!#REF! -> #REF! | T35: 0 | U35: 0 | V35: 0 | W35: 0 | X35: 0 | Y35: 0 | Z35: 0 | AA35: 0 | AB35: 0 | AC35: 0 | AD35: 0 | AE35: 0 | AF35: 0 | AG35: 0 | AH35: 0 | AI35: 0 | AJ35: 0 | AK35: 0 | AL35: 0 | AM35: 0 | AN35: 0 | AO35: 0 | AP35: 0 | AQ35: 0 | AR35: 0 | AS35: 0 | AT35: 0 | AU35: 0 | AV35: 0 | AW35: 0 | AX35: 0 | AY35: 0 | AZ35: 0 | BA35: 0 | BB35: 0 | BC35: 0 | BD35: 0 | BE35: 0 | BF35: 0 | BG35: 0 | BH35: 0 | BI35: 0 | BJ35: 0 | BK35: 0 | BL35: 0 | BM35: 0 | BN35: 0 | BO35: 0 | BP35: 0 | BQ35: 0
E36: 薬品費 | I36: ● | K36: H22~~H30有収水量1㎥あたり費用×有収水量（見込） | L36: ● | N36: =【PL】決算数値入力!#REF! -> #REF! | O36: =【PL】決算数値入力!#REF! -> #REF! | P36: =【PL】決算数値入力!#REF! -> #REF! | Q36: =【PL】決算数値入力!#REF! -> #REF! | R36: =【PL】決算数値入力!#REF! -> #REF! | S36: =【PL】決算数値入力!#REF! -> #REF! | T36: 0 | U36: 0 | V36: 0 | W36: 0 | X36: 0 | Y36: 0 | Z36: 0 | AA36: 0 | AB36: 0 | AC36: 0 | AD36: 0 | AE36: 0 | AF36: 0 | AG36: 0 | AH36: 0 | AI36: 0 | AJ36: 0 | AK36: 0 | AL36: 0 | AM36: 0 | AN36: 0 | AO36: 0 | AP36: 0 | AQ36: 0 | AR36: 0 | AS36: 0 | AT36: 0 | AU36: 0 | AV36: 0 | AW36: 0 | AX36: 0 | AY36: 0 | AZ36: 0 | BA36: 0 | BB36: 0 | BC36: 0 | BD36: 0 | BE36: 0 | BF36: 0 | BG36: 0 | BH36: 0 | BI36: 0 | BJ36: 0 | BK36: 0 | BL36: 0 | BM36: 0 | BN36: 0 | BO36: 0 | BP36: 0 | BQ36: 0
E37: 修繕費 | H37: ● | K37: H22~~H30決算の平均値に物価上昇率を加味 | L37: ● | N37: =【PL】決算数値入力!#REF! -> #REF! | O37: =【PL】決算数値入力!#REF! -> #REF! | P37: =【PL】決算数値入力!#REF! -> #REF! | Q37: =【PL】決算数値入力!#REF! -> #REF! | R37: =【PL】決算数値入力!#REF! -> #REF! | S37: =【PL】決算数値入力!#REF! -> #REF! | T37: =ROUND(S37*(1+物価上昇率!$G$9),0) -> #REF! | U37: =ROUND(T37*(1+物価上昇率!$G$9),0) -> #REF! | V37: =ROUND(U37*(1+物価上昇率!$G$9),0) -> #REF! | W37: =ROUND(V37*(1+物価上昇率!$G$9),0) -> #REF! | X37: =ROUND(W37*(1+物価上昇率!$G$9),0) -> #REF! | Y37: =ROUND(X37*(1+物価上昇率!$G$9),0) -> #REF! | Z37: =ROUND(Y37*(1+物価上昇率!$G$9),0) -> #REF! | AA37: =ROUND(Z37*(1+物価上昇率!$G$9),0) -> #REF! | ... BQ37: =ROUND(BP37*(1+物価上昇率!$G$9),0) -> #REF!
E38: 委託料 | H38: ● | K38: H22~~H30決算の平均値に物価上昇率を加味 | L38: ● | N38: =【PL】決算数値入力!#REF! -> #REF! | O38: =【PL】決算数値入力!#REF! -> #REF! | P38: =【PL】決算数値入力!#REF! -> #REF! | Q38: =【PL】決算数値入力!#REF! -> #REF! | R38: =【PL】決算数値入力!#REF! -> #REF! | S38: =【PL】決算数値入力!#REF! -> #REF! | T38: =ROUND(S38*(1+物価上昇率!$G$9),0) -> #REF! | U38: =ROUND(T38*(1+物価上昇率!$G$9),0) -> #REF! | V38: =ROUND(U38*(1+物価上昇率!$G$9),0) -> #REF! | W38: =ROUND(V38*(1+物価上昇率!$G$9),0) -> #REF! | X38: =ROUND(W38*(1+物価上昇率!$G$9),0) -> #REF! | Y38: =ROUND(X38*(1+物価上昇率!$G$9),0) -> #REF! | Z38: =ROUND(Y38*(1+物価上昇率!$G$9),0) -> #REF! | AA38: =ROUND(Z38*(1+物価上昇率!$G$9),0) -> #REF! | ... BQ38: =ROUND(BP38*(1+物価上昇率!$G$9),0) -> #REF!
E39: その他（物価上昇を考慮する） | H39: ● | K39: H22~~H30決算の平均値に物価上昇率を加味 | L39: ● | N39: =【PL】決算数値入力!#REF! -> #REF! | O39: =【PL】決算数値入力!#REF! -> #REF! | P39: =【PL】決算数値入力!#REF! -> #REF! | Q39: =【PL】決算数値入力!#REF! -> #REF! | R39: =【PL】決算数値入力!#REF! -> #REF! | S39: =【PL】決算数値入力!#REF! -> #REF! | T39: =ROUND(S39*(1+物価上昇率!$G$9),0) -> #REF! | U39: =ROUND(T39*(1+物価上昇率!$G$9),0) -> #REF! | V39: =ROUND(U39*(1+物価上昇率!$G$9),0) -> #REF! | W39: =ROUND(V39*(1+物価上昇率!$G$9),0) -> #REF! | X39: =ROUND(W39*(1+物価上昇率!$G$9),0) -> #REF! | Y39: =ROUND(X39*(1+物価上昇率!$G$9),0) -> #REF! | Z39: =ROUND(Y39*(1+物価上昇率!$G$9),0) -> #REF! | AA39: =ROUND(Z39*(1+物価上昇率!$G$9),0) -> #REF! | ... BQ39: =ROUND(BP39*(1+物価上昇率!$G$9),0) -> #REF!
E40: その他（物価上昇を考慮しない） | H40: ● | K40: H22~~H30決算の平均値で一定 | N40: =【PL】決算数値入力!#REF! -> #REF! | O40: =【PL】決算数値入力!#REF! -> #REF! | P40: =【PL】決算数値入力!#REF! -> #REF! | Q40: =【PL】決算数値入力!#REF! -> #REF! | R40: =【PL】決算数値入力!#REF! -> #REF! | S40: =【PL】決算数値入力!#REF! -> #REF! | T40: =S40 -> #REF! | U40: =T40 -> #REF! | V40: =U40 -> #REF! | W40: =V40 -> #REF! | X40: =W40 -> #REF! | Y40: =X40 -> #REF! | Z40: =Y40 -> #REF! | AA40: =Z40 -> #REF! | ... BQ40: =BP40 -> #REF!
D41: 受託工事費 | K41: 計上しない | N41: =【PL】決算数値入力!#REF! -> #REF! | O41: =【PL】決算数値入力!#REF! -> #REF! | P41: =【PL】決算数値入力!#REF! -> #REF! | Q41: =【PL】決算数値入力!#REF! -> #REF! | R41: =【PL】決算数値入力!#REF! -> #REF! | S41: =【PL】決算数値入力!#REF! -> #REF!
D42: 総係費 | F42: その他管理業務費 | N42: =【PL】決算数値入力!#REF! -> #REF! | O42: =【PL】決算数値入力!#REF! -> #REF! | P42: =【PL】決算数値入力!#REF! -> #REF! | Q42: =【PL】決算数値入力!#REF! -> #REF! | R42: =【PL】決算数値入力!#REF! -> #REF! | S42: =【PL】決算数値入力!#REF! -> #REF! | T42: =SUM(T43:T50) -> #REF! | U42: =SUM(U43:U50) -> #REF! | V42: =SUM(V43:V50) -> #REF! | W42: =SUM(W43:W50) -> #REF! | X42: =SUM(X43:X50) -> #REF! | Y42: =SUM(Y43:Y50) -> #REF! | Z42: =SUM(Z43:Z50) -> #REF! | AA42: =SUM(AA43:AA50) -> #REF! | ... BQ42: =SUM(BQ43:BQ50) -> #REF!
E43: 人件費 | H43: ● | K43: H22~~H30決算の平均値に物価上昇率を加味 | L43: ● | N43: =【PL】決算数値入力!#REF! -> #REF! | O43: =【PL】決算数値入力!#REF! -> #REF! | P43: =【PL】決算数値入力!#REF! -> #REF! | Q43: =【PL】決算数値入力!#REF! -> #REF! | R43: =【PL】決算数値入力!#REF! -> #REF! | S43: =【PL】決算数値入力!#REF! -> #REF! | T43: =ROUND(S43*(1+物価上昇率!$G$9),0) -> #REF! | U43: =ROUND(T43*(1+物価上昇率!$G$9),0) -> #REF! | V43: =ROUND(U43*(1+物価上昇率!$G$9),0) -> #REF! | W43: =ROUND(V43*(1+物価上昇率!$G$9),0) -> #REF! | X43: =ROUND(W43*(1+物価上昇率!$G$9),0) -> #REF! | Y43: =ROUND(X43*(1+物価上昇率!$G$9),0) -> #REF! | Z43: =ROUND(Y43*(1+物価上昇率!$G$9),0) -> #REF! | AA43: =ROUND(Z43*(1+物価上昇率!$G$9),0) -> #REF! | ... BQ43: =ROUND(BP43*(1+物価上昇率!$G$9),0) -> #REF!
E44: 退職給付費 | H44: ● | K44: H22~~H30決算の平均値に物価上昇率を加味 | L44: ● | N44: =【PL】決算数値入力!#REF! -> #REF! | O44: =【PL】決算数値入力!#REF! -> #REF! | P44: =【PL】決算数値入力!#REF! -> #REF! | Q44: =【PL】決算数値入力!#REF! -> #REF! | R44: =【PL】決算数値入力!#REF! -> #REF! | S44: =【PL】決算数値入力!#REF! -> #REF! | T44: =ROUND(S44*(1+物価上昇率!$G$9),0) -> #REF! | U44: =ROUND(T44*(1+物価上昇率!$G$9),0) -> #REF! | V44: =ROUND(U44*(1+物価上昇率!$G$9),0) -> #REF! | W44: =ROUND(V44*(1+物価上昇率!$G$9),0) -> #REF! | X44: =ROUND(W44*(1+物価上昇率!$G$9),0) -> #REF! | Y44: =ROUND(X44*(1+物価上昇率!$G$9),0) -> #REF! | Z44: =ROUND(Y44*(1+物価上昇率!$G$9),0) -> #REF! | AA44: =ROUND(Z44*(1+物価上昇率!$G$9),0) -> #REF! | ... BQ44: =ROUND(BP44*(1+物価上昇率!$G$9),0) -> #REF!
E45: 貸倒引当金繰入額 | H45: ● | K45: 計上しない | N45: =【PL】決算数値入力!#REF! -> #REF! | O45: =【PL】決算数値入力!#REF! -> #REF! | P45: =【PL】決算数値入力!#REF! -> #REF! | Q45: =【PL】決算数値入力!#REF! -> #REF! | R45: =【PL】決算数値入力!#REF! -> #REF! | S45: =【PL】決算数値入力!#REF! -> #REF! | T45: 0 | U45: 0 | V45: 0 | W45: 0 | X45: 0 | Y45: 0 | Z45: 0 | AA45: 0 | AB45: 0 | AC45: 0 | AD45: 0 | AE45: 0 | AF45: 0 | AG45: 0 | AH45: 0 | AI45: 0 | AJ45: 0 | AK45: 0 | AL45: 0 | AM45: 0 | AN45: 0 | AO45: 0 | AP45: 0 | AQ45: 0 | AR45: 0 | AS45: 0 | AT45: 0 | AU45: 0 | AV45: 0 | AW45: 0 | AX45: 0 | AY45: 0 | AZ45: 0 | BA45: 0 | BB45: 0 | BC45: 0 | BD45: 0 | BE45: 0 | BF45: 0 | BG45: 0 | BH45: 0 | BI45: 0 | BJ45: 0 | BK45: 0 | BL45: 0 | BM45: 0 | BN45: 0 | BO45: 0 | BP45: 0 | BQ45: 0
E46: 退職給与金 | H46: ● | K46: 計上しない | L46: ● | N46: =【PL】決算数値入力!#REF! -> #REF! | O46: =【PL】決算数値入力!#REF! -> #REF! | P46: =【PL】決算数値入力!#REF! -> #REF! | Q46: =【PL】決算数値入力!#REF! -> #REF! | R46: =【PL】決算数値入力!#REF! -> #REF! | S46: =【PL】決算数値入力!#REF! -> #REF! | T46: 0 | U46: 0 | V46: 0 | W46: 0 | X46: 0 | Y46: 0 | Z46: 0 | AA46: 0 | AB46: 0 | AC46: 0 | AD46: 0 | AE46: 0 | AF46: 0 | AG46: 0 | AH46: 0 | AI46: 0 | AJ46: 0 | AK46: 0 | AL46: 0 | AM46: 0 | AN46: 0 | AO46: 0 | AP46: 0 | AQ46: 0 | AR46: 0 | AS46: 0 | AT46: 0 | AU46: 0 | AV46: 0 | AW46: 0 | AX46: 0 | AY46: 0 | AZ46: 0 | BA46: 0 | BB46: 0 | BC46: 0 | BD46: 0 | BE46: 0 | BF46: 0 | BG46: 0 | BH46: 0 | BI46: 0 | BJ46: 0 | BK46: 0 | BL46: 0 | BM46: 0 | BN46: 0 | BO46: 0 | BP46: 0 | BQ46: 0
E47: 修繕費 | H47: ● | K47: H22~~H30決算の平均値に物価上昇率を加味 | L47: ● | N47: =【PL】決算数値入力!#REF! -> #REF! | O47: =【PL】決算数値入力!#REF! -> #REF! | P47: =【PL】決算数値入力!#REF! -> #REF! | Q47: =【PL】決算数値入力!#REF! -> #REF! | R47: =【PL】決算数値入力!#REF! -> #REF! | S47: =【PL】決算数値入力!#REF! -> #REF! | T47: =ROUND(S47*(1+物価上昇率!$G$9),0) -> #REF! | U47: =ROUND(T47*(1+物価上昇率!$G$9),0) -> #REF! | V47: =ROUND(U47*(1+物価上昇率!$G$9),0) -> #REF! | W47: =ROUND(V47*(1+物価上昇率!$G$9),0) -> #REF! | X47: =ROUND(W47*(1+物価上昇率!$G$9),0) -> #REF! | Y47: =ROUND(X47*(1+物価上昇率!$G$9),0) -> #REF! | Z47: =ROUND(Y47*(1+物価上昇率!$G$9),0) -> #REF! | AA47: =ROUND(Z47*(1+物価上昇率!$G$9),0) -> #REF! | ... BQ47: =ROUND(BP47*(1+物価上昇率!$G$9),0) -> #REF!
E48: 委託料 | H48: ● | K48: H22~~H30決算の平均値に物価上昇率を加味 | L48: ● | N48: =【PL】決算数値入力!#REF! -> #REF! | O48: =【PL】決算数値入力!#REF! -> #REF! | P48: =【PL】決算数値入力!#REF! -> #REF! | Q48: =【PL】決算数値入力!#REF! -> #REF! | R48: =【PL】決算数値入力!#REF! -> #REF! | S48: =【PL】決算数値入力!#REF! -> #REF! | T48: =ROUND(S48*(1+物価上昇率!$G$9),0) -> #REF! | U48: =ROUND(T48*(1+物価上昇率!$G$9),0) -> #REF! | V48: =ROUND(U48*(1+物価上昇率!$G$9),0) -> #REF! | W48: =ROUND(V48*(1+物価上昇率!$G$9),0) -> #REF! | X48: =ROUND(W48*(1+物価上昇率!$G$9),0) -> #REF! | Y48: =ROUND(X48*(1+物価上昇率!$G$9),0) -> #REF! | Z48: =ROUND(Y48*(1+物価上昇率!$G$9),0) -> #REF! | AA48: =ROUND(Z48*(1+物価上昇率!$G$9),0) -> #REF! | ... BQ48: =ROUND(BP48*(1+物価上昇率!$G$9),0) -> #REF!
E49: その他（物価上昇を考慮する） | H49: ● | K49: H22~~H30決算の平均値に物価上昇率を加味 | L49: ● | N49: =【PL】決算数値入力!#REF! -> #REF! | O49: =【PL】決算数値入力!#REF! -> #REF! | P49: =【PL】決算数値入力!#REF! -> #REF! | Q49: =【PL】決算数値入力!#REF! -> #REF! | R49: =【PL】決算数値入力!#REF! -> #REF! | S49: =【PL】決算数値入力!#REF! -> #REF! | T49: =ROUND(S49*(1+物価上昇率!$G$9),0) -> #REF! | U49: =ROUND(T49*(1+物価上昇率!$G$9),0) -> #REF! | V49: =ROUND(U49*(1+物価上昇率!$G$9),0) -> #REF! | W49: =ROUND(V49*(1+物価上昇率!$G$9),0) -> #REF! | X49: =ROUND(W49*(1+物価上昇率!$G$9),0) -> #REF! | Y49: =ROUND(X49*(1+物価上昇率!$G$9),0) -> #REF! | Z49: =ROUND(Y49*(1+物価上昇率!$G$9),0) -> #REF! | AA49: =ROUND(Z49*(1+物価上昇率!$G$9),0) -> #REF! | ... BQ49: =ROUND(BP49*(1+物価上昇率!$G$9),0) -> #REF!
E50: その他（物価上昇を考慮しない） | H50: ● | K50: H22~~H30決算の平均値で一定 | N50: =【PL】決算数値入力!#REF! -> #REF! | O50: =【PL】決算数値入力!#REF! -> #REF! | P50: =【PL】決算数値入力!#REF! -> #REF! | Q50: =【PL】決算数値入力!#REF! -> #REF! | R50: =【PL】決算数値入力!#REF! -> #REF! | S50: =【PL】決算数値入力!#REF! -> #REF! | T50: =S50 -> #REF! | U50: =T50 -> #REF! | V50: =U50 -> #REF! | W50: =V50 -> #REF! | X50: =W50 -> #REF! | Y50: =X50 -> #REF! | Z50: =Y50 -> #REF! | AA50: =Z50 -> #REF! | ... BQ50: =BP50 -> #REF!
D51: 減価償却費 | N51: =【PL】決算数値入力!#REF! -> #REF! | O51: =【PL】決算数値入力!#REF! -> #REF! | P51: =【PL】決算数値入力!#REF! -> #REF! | Q51: =【PL】決算数値入力!#REF! -> #REF! | R51: =【PL】決算数値入力!#REF! -> #REF! | S51: =【PL】決算数値入力!#REF! -> #REF! | T51: =SUM(T52:T53) -> 10539902 | U51: =SUM(U52:U53) -> 17673391 | V51: =SUM(V52:V53) -> 10582885 | W51: =SUM(W52:W53) -> 10582885 | X51: =SUM(X52:X53) -> 10567084 | Y51: =SUM(Y52:Y53) -> 10503880 | Z51: =SUM(Z52:Z53) -> 10445596 | AA51: =SUM(AA52:AA53) -> 16784631 | ... BQ51: =SUM(BQ52:BQ53) -> 208157882
E52: H30末の取得資産 | H52: ● | K52: 固定資産台帳データに基づく算定額 | N52: =【PL】決算数値入力!#REF! -> #REF! | O52: =【PL】決算数値入力!#REF! -> #REF! | P52: =【PL】決算数値入力!#REF! -> #REF! | Q52: =【PL】決算数値入力!#REF! -> #REF! | R52: =【PL】決算数値入力!#REF! -> #REF! | S52: =【PL】決算数値入力!#REF! -> #REF! | T52: 10539902 | U52: 17673391 | V52: 10582885 | W52: 10582885 | X52: 10567084 | Y52: 10503880 | Z52: 10445596 | AA52: 10293526 | AB52: 10293526 | AC52: 10153743 | AD52: 9976836 | AE52: 9976836 | AF52: 9976836 | AG52: 9916300 | AH52: 9816521 | AI52: 5494142 | AJ52: 2075295 | AK52: 1777670 | AL52: 1572802 | AM52: 1495911 | AN52: 1378509 | AO52: 932140 | AP52: 926984 | AQ52: 878994 | AR52: 813129 | AS52: 813129 | AT52: 813129 | AU52: 813129 | AV52: 813129 | AW52: 813129 | AX52: 813129 | AY52: 813129 | AZ52: 813129 | BA52: 812688 | BB52: 811274 | BC52: 811274 | BD52: 150334 | BE52: 0 | BF52: 0 | BG52: 0 | BH52: 0 | BI52: 0 | BJ52: 0 | BK52: 0 | BL52: 0 | BM52: 0 | BN52: 0 | BO52: 0 | BP52: 0 | BQ52: 0
E53: H31以降の取得資産 | H53: ● | K53: 償却計算額 | N53: =【PL】決算数値入力!#REF! -> #REF! | O53: =【PL】決算数値入力!#REF! -> #REF! | P53: =【PL】決算数値入力!#REF! -> #REF! | Q53: =【PL】決算数値入力!#REF! -> #REF! | R53: =【PL】決算数値入力!#REF! -> #REF! | S53: =【PL】決算数値入力!#REF! -> #REF! | T53: =新規取得!I2 -> 0 | U53: =新規取得!J2 -> 0 | V53: =新規取得!K2 -> 0 | W53: =新規取得!L2 -> 0 | X53: =新規取得!M2 -> 0 | Y53: =新規取得!N2 -> 0 | Z53: =新規取得!O2 -> 0 | AA53: =新規取得!P2 -> 6491105 | ... BQ53: =新規取得!BF2 -> 208157882
D54: 資産減耗費 | N54: =【PL】決算数値入力!#REF! -> #REF! | O54: =【PL】決算数値入力!#REF! -> #REF! | P54: =【PL】決算数値入力!#REF! -> #REF! | Q54: =【PL】決算数値入力!#REF! -> #REF! | R54: =【PL】決算数値入力!#REF! -> #REF! | S54: =【PL】決算数値入力!#REF! -> #REF! | T54: =SUM(T55:T56) -> 0 | U54: =SUM(U55:U56) -> 0 | V54: =SUM(V55:V56) -> 0 | W54: =SUM(W55:W56) -> 0 | X54: =SUM(X55:X56) -> 0 | Y54: =SUM(Y55:Y56) -> 0 | Z54: =SUM(Z55:Z56) -> 0 | AA54: =SUM(AA55:AA56) -> 0 | ... BQ54: =SUM(BQ55:BQ56) -> 0
E55: 固定資産除却費 | H55: ● | K55: 更新・廃止に伴う除却等の費用を計上 | N55: =【PL】決算数値入力!#REF! -> #REF! | O55: =【PL】決算数値入力!#REF! -> #REF! | P55: =【PL】決算数値入力!#REF! -> #REF! | Q55: =【PL】決算数値入力!#REF! -> #REF! | R55: =【PL】決算数値入力!#REF! -> #REF! | S55: =【PL】決算数値入力!#REF! -> #REF!
E56: たな卸資産減耗費 | H56: ● | K56: 計上しない | N56: =【PL】決算数値入力!#REF! -> #REF! | O56: =【PL】決算数値入力!#REF! -> #REF! | P56: =【PL】決算数値入力!#REF! -> #REF! | Q56: =【PL】決算数値入力!#REF! -> #REF! | R56: =【PL】決算数値入力!#REF! -> #REF! | S56: =【PL】決算数値入力!#REF! -> #REF! | T56: 0 | U56: 0 | V56: 0 | W56: 0 | X56: 0 | Y56: 0 | Z56: 0 | AA56: 0 | AB56: 0 | AC56: 0 | AD56: 0 | AE56: 0 | AF56: 0 | AG56: 0 | AH56: 0 | AI56: 0 | AJ56: 0 | AK56: 0 | AL56: 0 | AM56: 0 | AN56: 0 | AO56: 0 | AP56: 0 | AQ56: 0 | AR56: 0 | AS56: 0 | AT56: 0 | AU56: 0 | AV56: 0 | AW56: 0 | AX56: 0 | AY56: 0 | AZ56: 0 | BA56: 0 | BB56: 0 | BC56: 0 | BD56: 0 | BE56: 0 | BF56: 0 | BG56: 0 | BH56: 0 | BI56: 0 | BJ56: 0 | BK56: 0 | BL56: 0 | BM56: 0 | BN56: 0 | BO56: 0 | BP56: 0 | BQ56: 0
C57: 営業外費用 | N57: =【PL】決算数値入力!#REF! -> #REF! | O57: =【PL】決算数値入力!#REF! -> #REF! | P57: =【PL】決算数値入力!#REF! -> #REF! | Q57: =【PL】決算数値入力!#REF! -> #REF! | R57: =【PL】決算数値入力!#REF! -> #REF! | S57: =【PL】決算数値入力!#REF! -> #REF! | T57: =SUM(T58,T61) -> #REF! | U57: =SUM(U58,U61) -> #REF! | V57: =SUM(V58,V61) -> #REF! | W57: =SUM(W58,W61) -> #REF! | X57: =SUM(X58,X61) -> #REF! | Y57: =SUM(Y58,Y61) -> #REF! | Z57: =SUM(Z58,Z61) -> #REF! | AA57: =SUM(AA58,AA61) -> #REF! | ... BQ57: =SUM(BQ58,BQ61) -> #REF!
D58: 支払利息 | N58: =【PL】決算数値入力!#REF! -> #REF! | O58: =【PL】決算数値入力!#REF! -> #REF! | P58: =【PL】決算数値入力!#REF! -> #REF! | Q58: =【PL】決算数値入力!#REF! -> #REF! | R58: =【PL】決算数値入力!#REF! -> #REF! | S58: =【PL】決算数値入力!#REF! -> #REF! | T58: =SUM(T59:T60) -> 11610 | U58: =SUM(U59:U60) -> 5059249 | V58: =SUM(V59:V60) -> 9245871 | W58: =SUM(W59:W60) -> 18512235 | X58: =SUM(X59:X60) -> 26642786 | Y58: =SUM(Y59:Y60) -> 34316071 | Z58: =SUM(Z59:Z60) -> 38700148 | AA58: =SUM(AA59:AA60) -> 42991146 | ... BQ58: =SUM(BQ59:BQ60) -> 44022870
E59: H30末の既往債 | H59: ● | K59: 既往債の返済スケジュールに基づく利息発生額 | N59: =【PL】決算数値入力!#REF! -> #REF! | O59: =【PL】決算数値入力!#REF! -> #REF! | P59: =【PL】決算数値入力!#REF! -> #REF! | Q59: =【PL】決算数値入力!#REF! -> #REF! | R59: =【PL】決算数値入力!#REF! -> #REF! | S59: =【PL】決算数値入力!#REF! -> #REF! | T59: 11610 | U59: 10849 | V59: 7854 | W59: 4845 | X59: 1936
E60: H31以降の新規債 | H60: ● | K60: 新規債の返済スケジュール×H22~~H30利率の平均値 | N60: =【PL】決算数値入力!#REF! -> #REF! | O60: =【PL】決算数値入力!#REF! -> #REF! | P60: =【PL】決算数値入力!#REF! -> #REF! | Q60: =【PL】決算数値入力!#REF! -> #REF! | R60: =【PL】決算数値入力!#REF! -> #REF! | S60: =【PL】決算数値入力!#REF! -> #REF! | T60: =新規債返済スケジュール!E3 -> 0 | U60: =新規債返済スケジュール!F3 -> 5048400 | V60: =新規債返済スケジュール!G3 -> 9238017 | W60: =新規債返済スケジュール!H3 -> 18507390 | X60: =新規債返済スケジュール!I3 -> 26640850 | Y60: =新規債返済スケジュール!J3 -> 34316071 | Z60: =新規債返済スケジュール!K3 -> 38700148 | AA60: =新規債返済スケジュール!L3 -> 42991146 | ... BQ60: =新規債返済スケジュール!BB3 -> 44022870
D61: 雑支出 | H61: ● | K61: H22~~H30決算の平均値で一定 | N61: =【PL】決算数値入力!#REF! -> #REF! | O61: =【PL】決算数値入力!#REF! -> #REF! | P61: =【PL】決算数値入力!#REF! -> #REF! | Q61: =【PL】決算数値入力!#REF! -> #REF! | R61: =【PL】決算数値入力!#REF! -> #REF! | S61: =【PL】決算数値入力!#REF! -> #REF! | T61: =S61 -> #REF! | U61: =T61 -> #REF! | V61: =U61 -> #REF! | W61: =V61 -> #REF! | X61: =W61 -> #REF! | Y61: =X61 -> #REF! | Z61: =Y61 -> #REF! | AA61: =Z61 -> #REF! | ... BQ61: =BP61 -> #REF!
C62: 特別損失 | N62: =【PL】決算数値入力!#REF! -> #REF! | O62: =【PL】決算数値入力!#REF! -> #REF! | P62: =【PL】決算数値入力!#REF! -> #REF! | Q62: =【PL】決算数値入力!#REF! -> #REF! | R62: =【PL】決算数値入力!#REF! -> #REF! | S62: =【PL】決算数値入力!#REF! -> #REF! | T62: =SUM(T63:T66) -> 0 | U62: =SUM(U63:U66) -> 0 | V62: =SUM(V63:V66) -> 0 | W62: =SUM(W63:W66) -> 0 | X62: =SUM(X63:X66) -> 0 | Y62: =SUM(Y63:Y66) -> 0 | Z62: =SUM(Z63:Z66) -> 0 | AA62: =SUM(AA63:AA66) -> 0 | ... BQ62: =SUM(BQ63:BQ66) -> 0
D63: 固定資産売却損 | H63: ● | K63: 計上しない | N63: =【PL】決算数値入力!#REF! -> #REF! | O63: =【PL】決算数値入力!#REF! -> #REF! | P63: =【PL】決算数値入力!#REF! -> #REF! | Q63: =【PL】決算数値入力!#REF! -> #REF! | R63: =【PL】決算数値入力!#REF! -> #REF! | S63: =【PL】決算数値入力!#REF! -> #REF! | T63: 0 | U63: 0 | V63: 0 | W63: 0 | X63: 0 | Y63: 0 | Z63: 0 | AA63: 0 | AB63: 0 | AC63: 0 | AD63: 0 | AE63: 0 | AF63: 0 | AG63: 0 | AH63: 0 | AI63: 0 | AJ63: 0 | AK63: 0 | AL63: 0 | AM63: 0 | AN63: 0 | AO63: 0 | AP63: 0 | AQ63: 0 | AR63: 0 | AS63: 0 | AT63: 0 | AU63: 0 | AV63: 0 | AW63: 0 | AX63: 0 | AY63: 0 | AZ63: 0 | BA63: 0 | BB63: 0 | BC63: 0 | BD63: 0 | BE63: 0 | BF63: 0 | BG63: 0 | BH63: 0 | BI63: 0 | BJ63: 0 | BK63: 0 | BL63: 0 | BM63: 0 | BN63: 0 | BO63: 0 | BP63: 0 | BQ63: 0
D64: 過年度修正損 | H64: ● | K64: 計上しない | N64: =【PL】決算数値入力!#REF! -> #REF! | O64: =【PL】決算数値入力!#REF! -> #REF! | P64: =【PL】決算数値入力!#REF! -> #REF! | Q64: =【PL】決算数値入力!#REF! -> #REF! | R64: =【PL】決算数値入力!#REF! -> #REF! | S64: =【PL】決算数値入力!#REF! -> #REF! | T64: 0 | U64: 0 | V64: 0 | W64: 0 | X64: 0 | Y64: 0 | Z64: 0 | AA64: 0 | AB64: 0 | AC64: 0 | AD64: 0 | AE64: 0 | AF64: 0 | AG64: 0 | AH64: 0 | AI64: 0 | AJ64: 0 | AK64: 0 | AL64: 0 | AM64: 0 | AN64: 0 | AO64: 0 | AP64: 0 | AQ64: 0 | AR64: 0 | AS64: 0 | AT64: 0 | AU64: 0 | AV64: 0 | AW64: 0 | AX64: 0 | AY64: 0 | AZ64: 0 | BA64: 0 | BB64: 0 | BC64: 0 | BD64: 0 | BE64: 0 | BF64: 0 | BG64: 0 | BH64: 0 | BI64: 0 | BJ64: 0 | BK64: 0 | BL64: 0 | BM64: 0 | BN64: 0 | BO64: 0 | BP64: 0 | BQ64: 0
D65: 臨時損失 | H65: ● | K65: 計上しない | N65: =【PL】決算数値入力!#REF! -> #REF! | O65: =【PL】決算数値入力!#REF! -> #REF! | P65: =【PL】決算数値入力!#REF! -> #REF! | Q65: =【PL】決算数値入力!#REF! -> #REF! | R65: =【PL】決算数値入力!#REF! -> #REF! | S65: =【PL】決算数値入力!#REF! -> #REF! | T65: 0 | U65: 0 | V65: 0 | W65: 0 | X65: 0 | Y65: 0 | Z65: 0 | AA65: 0 | AB65: 0 | AC65: 0 | AD65: 0 | AE65: 0 | AF65: 0 | AG65: 0 | AH65: 0 | AI65: 0 | AJ65: 0 | AK65: 0 | AL65: 0 | AM65: 0 | AN65: 0 | AO65: 0 | AP65: 0 | AQ65: 0 | AR65: 0 | AS65: 0 | AT65: 0 | AU65: 0 | AV65: 0 | AW65: 0 | AX65: 0 | AY65: 0 | AZ65: 0 | BA65: 0 | BB65: 0 | BC65: 0 | BD65: 0 | BE65: 0 | BF65: 0 | BG65: 0 | BH65: 0 | BI65: 0 | BJ65: 0 | BK65: 0 | BL65: 0 | BM65: 0 | BN65: 0 | BO65: 0 | BP65: 0 | BQ65: 0
D66: その他特別損失 | H66: ● | K66: 計上しない | N66: =【PL】決算数値入力!#REF! -> #REF! | O66: =【PL】決算数値入力!#REF! -> #REF! | P66: =【PL】決算数値入力!#REF! -> #REF! | Q66: =【PL】決算数値入力!#REF! -> #REF! | R66: =【PL】決算数値入力!#REF! -> #REF! | S66: =【PL】決算数値入力!#REF! -> #REF! | T66: 0 | U66: 0 | V66: 0 | W66: 0 | X66: 0 | Y66: 0 | Z66: 0 | AA66: 0 | AB66: 0 | AC66: 0 | AD66: 0 | AE66: 0 | AF66: 0 | AG66: 0 | AH66: 0 | AI66: 0 | AJ66: 0 | AK66: 0 | AL66: 0 | AM66: 0 | AN66: 0 | AO66: 0 | AP66: 0 | AQ66: 0 | AR66: 0 | AS66: 0 | AT66: 0 | AU66: 0 | AV66: 0 | AW66: 0 | AX66: 0 | AY66: 0 | AZ66: 0 | BA66: 0 | BB66: 0 | BC66: 0 | BD66: 0 | BE66: 0 | BF66: 0 | BG66: 0 | BH66: 0 | BI66: 0 | BJ66: 0 | BK66: 0 | BL66: 0 | BM66: 0 | BN66: 0 | BO66: 0 | BP66: 0 | BQ66: 0
B67: 損益 | N67: =【PL】決算数値入力!#REF! -> #REF! | O67: =【PL】決算数値入力!#REF! -> #REF! | P67: =【PL】決算数値入力!#REF! -> #REF! | Q67: =【PL】決算数値入力!#REF! -> #REF! | R67: =【PL】決算数値入力!#REF! -> #REF! | S67: =【PL】決算数値入力!#REF! -> #REF! | T67: =T5-T23 -> #REF! | U67: =U5-U23 -> #REF! | V67: =V5-V23 -> #REF! | W67: =W5-W23 -> #REF! | X67: =X5-X23 -> #REF! | Y67: =Y5-Y23 -> #REF! | Z67: =Z5-Z23 -> #REF! | AA67: =AA5-AA23 -> #REF! | ... BQ67: =BQ5-BQ23 -> #REF!
B69: 資本的収支（税込み）
B70: 款 | C70: 項 | D70: 目 | F70: 総括原価の区分 | J70: 控除 項目 | K70: 将来設定条件 | L70: 物価 | M70: 算出根拠 | N70: 実績期間 | S70: 平均値 | T70: 料金算定期間 | X70: 参考期間
G71: 需要家費 | H71: 固定費 | I71: 変動費 | N71: H26 | O71: H27 | P71: H28 | Q71: H29 | R71: H30 | T71: H31 | U71: R2 | V71: R3 | W71: R4 | X71: R5 | Y71: R6 | Z71: R7 | AA71: R8 | AB71: R9 | AC71: R10 | AD71: R11 | AE71: R12 | AF71: R13 | AG71: R14 | AH71: R15 | AI71: R16 | AJ71: R17 | AK71: R18 | AL71: R19 | AM71: R20 | AN71: R21 | AO71: R22 | AP71: R23 | AQ71: R24 | AR71: R25 | AS71: R26 | AT71: R27 | AU71: R28 | AV71: R29 | AW71: R30 | AX71: R31 | AY71: R32 | AZ71: R33 | BA71: R34 | BB71: R35 | BC71: R36 | BD71: R37 | BE71: R38 | BF71: R39 | BG71: R40 | BH71: R41 | BI71: R42 | BJ71: R43 | BK71: R44 | BL71: R45 | BM71: R46 | BN71: R47 | BO71: R48 | BP71: R49 | BQ71: R50
B72: 資本的収入 | N72: =SUM(N73:N78) -> 0 | O72: =SUM(O73:O78) -> 0 | P72: =SUM(P73:P78) -> 0 | Q72: =SUM(Q73:Q78) -> 0 | R72: =SUM(R73:R78) -> 0 | S72: =IFERROR(AVERAGE(N72:R72),0) -> 0 | T72: =SUM(T73:T78) -> #REF! | U72: =SUM(U73:U78) -> #REF! | V72: =SUM(V73:V78) -> #REF! | W72: =SUM(W73:W78) -> #REF! | X72: =SUM(X73:X78) -> #REF! | Y72: =SUM(Y73:Y78) -> #REF! | Z72: =SUM(Z73:Z78) -> #REF! | AA72: =SUM(AA73:AA78) -> #REF! | ... BQ72: =SUM(BQ73:BQ78) -> 0
C73: 企業債 | S73: =IFERROR(AVERAGE(N73:R73),0) -> 0 | T73: =T84+T87+T91-T76-T77 -> #REF! | U73: =U84+U87+U91-U76-U77 -> #REF! | V73: =V84+V87+V91-V76-V77 -> #REF! | W73: =W84+W87+W91-W76-W77 -> #REF! | X73: =X84+X87+X91-X76-X77 -> #REF! | Y73: =Y84+Y87+Y91-Y76-Y77 -> #REF! | Z73: =Z84+Z87+Z91-Z76-Z77 -> #REF! | AA73: =AA84+AA87+AA91-AA76-AA77 -> #REF! | ... BQ73: =BQ84+BQ87+BQ91-BQ76-BQ77 -> 0
C74: 出資金 | K74: 予定額 | S74: =IFERROR(AVERAGE(N74:R74),0) -> 0
C75: 他会計補助金 | K75: H26~H30決算の平均値で一定 | S75: =IFERROR(AVERAGE(N75:R75),0) -> 0
C76: 国庫補助金 | K76: 予定額 | S76: =IFERROR(AVERAGE(N76:R76),0) -> 0 | T76: =(T87+T91)*0.55 -> #REF! | U76: =(U87+U91)*0.55 -> #REF! | V76: =(V87+V91)*0.55 -> #REF! | W76: =(W87+W91)*0.55 -> #REF! | X76: =(X87+X91)*0.55 -> #REF! | Y76: =(Y87+Y91)*0.55 -> #REF! | Z76: =(Z87+Z91)*0.55 -> #REF! | AA76: =(AA87+AA91)*0.55 -> #REF! | ... BQ76: =(BQ87+BQ91)*0.55 -> 0
C77: 県補助金 | K77: 予定額 | S77: =IFERROR(AVERAGE(N77:R77),0) -> 0 | T77: =(T87+T91)*0.325 -> #REF! | U77: =(U87+U91)*0.325 -> #REF! | V77: =(V87+V91)*0.325 -> #REF! | W77: =(W87+W91)*0.325 -> #REF! | X77: =(X87+X91)*0.325 -> #REF! | Y77: =(Y87+Y91)*0.325 -> #REF! | Z77: =(Z87+Z91)*0.325 -> #REF! | AA77: =(AA87+AA91)*0.325 -> #REF! | ... BQ77: =(BQ87+BQ91)*0.325 -> 0
C78: 固定資産売却代金 | K78: 計上しない | S78: =IFERROR(AVERAGE(N78:R78),0) -> 0
B79: 資本的支出 | N79: =SUM(N80,N84:N85,N89,N95,N98) -> 2139000 | O79: =SUM(O80,O84:O85,O89,O95,O98) -> 74520 | P79: =SUM(P80,P84:P85,P89,P95,P98) -> 0 | Q79: =SUM(Q80,Q84:Q85,Q89,Q95,Q98) -> 0 | R79: =SUM(R80,R84:R85,R89,R95,R98) -> 0 | S79: =IFERROR(AVERAGE(N79:R79),0) -> 442704 | T79: =SUM(T80,T84:T85,T89,T95,T98) -> #REF! | U79: =SUM(U80,U84:U85,U89,U95,U98) -> #REF! | V79: =SUM(V80,V84:V85,V89,V95,V98) -> #REF! | W79: =SUM(W80,W84:W85,W89,W95,W98) -> #REF! | X79: =SUM(X80,X84:X85,X89,X95,X98) -> #REF! | Y79: =SUM(Y80,Y84:Y85,Y89,Y95,Y98) -> #REF! | Z79: =SUM(Z80,Z84:Z85,Z89,Z95,Z98) -> #REF! | AA79: =SUM(AA80,AA84:AA85,AA89,AA95,AA98) -> #REF! | ... BQ79: =SUM(BQ80,BQ84:BQ85,BQ89,BQ95,BQ98) -> 192307993
C80: 建設改良費 | N80: =SUM(N81) -> 0 | O80: =SUM(O81) -> 0 | P80: =SUM(P81) -> 0 | Q80: =SUM(Q81) -> 0 | R80: =SUM(R81) -> 0 | S80: =IFERROR(AVERAGE(N80:R80),0) -> 0 | T80: =SUM(T81) -> 0 | U80: =SUM(U81) -> 0 | V80: =SUM(V81) -> 0 | W80: =SUM(W81) -> 0 | X80: =SUM(X81) -> 0 | Y80: =SUM(Y81) -> 0 | Z80: =SUM(Z81) -> 0 | AA80: =SUM(AA81) -> 0 | ... BQ80: =SUM(BQ81) -> 0
D81: 事務費 | N81: =SUM(N82:N83) -> 0 | O81: =SUM(O82:O83) -> 0 | P81: =SUM(P82:P83) -> 0 | Q81: =SUM(Q82:Q83) -> 0 | R81: =SUM(R82:R83) -> 0 | S81: =IFERROR(AVERAGE(N81:R81),0) -> 0 | T81: =SUM(T82:T83) -> 0 | U81: =SUM(U82:U83) -> 0 | V81: =SUM(V82:V83) -> 0 | W81: =SUM(W82:W83) -> 0 | X81: =SUM(X82:X83) -> 0 | Y81: =SUM(Y82:Y83) -> 0 | Z81: =SUM(Z82:Z83) -> 0 | AA81: =SUM(AA82:AA83) -> 0 | ... BQ81: =SUM(BQ82:BQ83) -> 0
E82: 人件費 | K82: 計上しない | S82: =IFERROR(AVERAGE(N82:R82),0) -> 0
E83: その他（物価上昇を考慮しない） | K83: 計上しない | S83: =IFERROR(AVERAGE(N83:R83),0) -> 0
C84: 固定資産購入費 | S84: =IFERROR(AVERAGE(N84:R84),0) -> 0 | T84: =T126 -> #REF! | U84: =U126 -> #REF! | V84: =V126 -> #REF! | W84: =W126 -> #REF! | X84: =X126 -> #REF! | Y84: =Y126 -> #REF! | Z84: =Z126 -> #REF! | AA84: =AA126 -> #REF! | ... BQ84: =BQ126 -> 0
C85: 原水及び浄水施設費 | N85: =SUM(N86:N88) -> 2139000 | O85: =SUM(O86:O88) -> 0 | P85: =SUM(P86:P88) -> 0 | Q85: =SUM(Q86:Q88) -> 0 | R85: =SUM(R86:R88) -> 0 | S85: =IFERROR(AVERAGE(N85:R85),0) -> 427800 | T85: =SUM(T86:T88) -> #REF! | U85: =SUM(U86:U88) -> #REF! | V85: =SUM(V86:V88) -> #REF! | W85: =SUM(W86:W88) -> #REF! | X85: =SUM(X86:X88) -> #REF! | Y85: =SUM(Y86:Y88) -> #REF! | Z85: =SUM(Z86:Z88) -> #REF! | AA85: =SUM(AA86:AA88) -> #REF! | ... BQ85: =SUM(BQ86:BQ88) -> 0
D86: 委託料 | S86: =IFERROR(AVERAGE(N86:R86),0) -> 0
D87: 工事請負費 | K87: 投資シミュレーション結果 | N87: 2139000 | O87: 0 | P87: 0 | Q87: 0 | R87: 0 | S87: =IFERROR(AVERAGE(N87:R87),0) -> 427800 | T87: =(T121+T122)*1000000 -> #REF! | U87: =(U121+U122)*1000000 -> #REF! | V87: =(V121+V122)*1000000 -> #REF! | W87: =(W121+W122)*1000000 -> #REF! | X87: =(X121+X122)*1000000 -> #REF! | Y87: =(Y121+Y122)*1000000 -> #REF! | Z87: =(Z121+Z122)*1000000 -> #REF! | AA87: =(AA121+AA122)*1000000 -> #REF! | ... BQ87: =(BQ121+BQ122)*1000000 -> 0
D88: 負担金 | S88: =IFERROR(AVERAGE(N88:R88),0) -> 0
C89: 給水及び配水施設費 | N89: =SUM(N90:N94) -> 0 | O89: =SUM(O90:O94) -> 74520 | P89: =SUM(P90:P94) -> 0 | Q89: =SUM(Q90:Q94) -> 0 | R89: =SUM(R90:R94) -> 0 | S89: =IFERROR(AVERAGE(N89:R89),0) -> 14904 | T89: =SUM(T90:T94) -> #REF! | U89: =SUM(U90:U94) -> #REF! | V89: =SUM(V90:V94) -> #REF! | W89: =SUM(W90:W94) -> #REF! | X89: =SUM(X90:X94) -> #REF! | Y89: =SUM(Y90:Y94) -> #REF! | Z89: =SUM(Z90:Z94) -> #REF! | AA89: =SUM(AA90:AA94) -> #REF! | ... BQ89: =SUM(BQ90:BQ94) -> 0
D90: 委託料 | S90: =IFERROR(AVERAGE(N90:R90),0) -> 0
D91: 工事請負費 | K91: 投資シミュレーション結果 | N91: 0 | O91: 74520 | P91: 0 | Q91: 0 | R91: 0 | S91: =IFERROR(AVERAGE(N91:R91),0) -> 14904 | T91: =(T123+T124)*1000000 -> #REF! | U91: =(U123+U124)*1000000 -> #REF! | V91: =(V123+V124)*1000000 -> #REF! | W91: =(W123+W124)*1000000 -> #REF! | X91: =(X123+X124)*1000000 -> #REF! | Y91: =(Y123+Y124)*1000000 -> #REF! | Z91: =(Z123+Z124)*1000000 -> #REF! | AA91: =(AA123+AA124)*1000000 -> #REF! | ... BQ91: =(BQ123+BQ124)*1000000 -> 0
D92: 量水器費 | S92: =IFERROR(AVERAGE(N92:R92),0) -> 0
D93: 負担金 | S93: =IFERROR(AVERAGE(N93:R93),0) -> 0
D94: 補償金 | S94: =IFERROR(AVERAGE(N94:R94),0) -> 0
C95: 企業債償還金 | N95: =SUM(N96:N97) -> 0 | O95: =SUM(O96:O97) -> 0 | P95: =SUM(P96:P97) -> 0 | Q95: =SUM(Q96:Q97) -> 0 | R95: =SUM(R96:R97) -> 0 | S95: =IFERROR(AVERAGE(N95:R95),0) -> 0 | T95: =SUM(T96:T97) -> 106087 | U95: =SUM(U96:U97) -> 4530942 | V95: =SUM(V96:V97) -> 7910777 | W95: =SUM(W96:W97) -> 15334887 | X95: =SUM(X96:X97) -> 22050921 | Y95: =SUM(Y96:Y97) -> 28234419 | Z95: =SUM(Z96:Z97) -> 32666714 | AA95: =SUM(AA96:AA97) -> 37192087 | ... BQ95: =SUM(BQ96:BQ97) -> 192307993
D96: H30末の既往債 | K96: 既往債の返済スケジュールに基づく償還予定額 | S96: =IFERROR(AVERAGE(N96:R96),0) -> 0 | T96: 106087 | U96: 636490 | V96: 639485 | W96: 642495 | X96: 537637
D97: H31以降の新規債 | K97: 新規債の返済スケジュールに基づく償還予定額 | S97: =IFERROR(AVERAGE(N97:R97),0) -> 0 | T97: =新規債返済スケジュール!E2 -> 0 | U97: =新規債返済スケジュール!F2 -> 3894452 | V97: =新規債返済スケジュール!G2 -> 7271292 | W97: =新規債返済スケジュール!H2 -> 14692392 | X97: =新規債返済スケジュール!I2 -> 21513284 | Y97: =新規債返済スケジュール!J2 -> 28234419 | Z97: =新規債返済スケジュール!K2 -> 32666714 | AA97: =新規債返済スケジュール!L2 -> 37192087 | ... BQ97: =新規債返済スケジュール!BB2 -> 192307993
C98: 国庫補助金返還金 | S98: =IFERROR(AVERAGE(N98:R98),0) -> 0
B99: 資本的収支不足額 | N99: =N72-N79 -> -2139000 | O99: =O72-O79 -> -74520 | P99: =P72-P79 -> 0 | Q99: =Q72-Q79 -> 0 | R99: =R72-R79 -> 0 | S99: =IFERROR(AVERAGE(N99:R99),0) -> -442704 | T99: =T72-T79 -> #REF! | U99: =U72-U79 -> #REF! | V99: =V72-V79 -> #REF! | W99: =W72-W79 -> #REF! | X99: =X72-X79 -> #REF! | Y99: =Y72-Y79 -> #REF! | Z99: =Z72-Z79 -> #REF! | AA99: =AA72-AA79 -> #REF! | ... BQ99: =BQ72-BQ79 -> -192307993
B101: 財政シミュレーション
B102: 款 | C102: 項 | D102: 目 | F102: 総括原価の区分 | J102: 控除 項目 | K102: 将来設定条件 | L102: 物価 | M102: 算出根拠 | N102: 実績期間 | S102: 平均値 | T102: 料金算定期間 | X102: 参考期間
G103: 需要家費 | H103: 固定費 | I103: 変動費 | N103: H26 | O103: H27 | P103: H28 | Q103: H29 | R103: H30 | T103: H31 | U103: R2 | V103: R3 | W103: R4 | X103: R5 | Y103: R6 | Z103: R7 | AA103: R8 | AB103: R9 | AC103: R10 | AD103: R11 | AE103: R12 | AF103: R13 | AG103: R14 | AH103: R15 | AI103: R16 | AJ103: R17 | AK103: R18 | AL103: R19 | AM103: R20 | AN103: R21 | AO103: R22 | AP103: R23 | AQ103: R24 | AR103: R25 | AS103: R26 | AT103: R27 | AU103: R28 | AV103: R29 | AW103: R30 | AX103: R31 | AY103: R32 | AZ103: R33 | BA103: R34 | BB103: R35 | BC103: R36 | BD103: R37 | BE103: R38 | BF103: R39 | BG103: R40 | BH103: R41 | BI103: R42 | BJ103: R43 | BK103: R44 | BL103: R45 | BM103: R46 | BN103: R47 | BO103: R48 | BP103: R49 | BQ103: R50
...

Sheet 【現行×調整率】財政シミュ
B2: 収益的収支（税抜き） | N2: （単位：千円） | T2: 1 | U2: 2 | V2: 3 | W2: 4 | X2: 5 | Y2: 6 | Z2: 7 | AA2: 8 | AB2: 9 | AC2: 10 | AD2: 11 | AE2: 12 | AF2: 13 | AG2: 14 | AH2: 15 | AI2: 16 | AJ2: 17 | AK2: 18 | AL2: 19 | AM2: 20 | AN2: 21 | AO2: 22 | AP2: 23 | AQ2: 24 | AR2: 25 | AS2: 26 | AT2: 27 | AU2: 28 | AV2: 29 | AW2: 30 | AX2: 31 | AY2: 32 | AZ2: 33 | BA2: 34 | BB2: 35 | BC2: 36 | BD2: 37 | BE2: 38 | BF2: 39 | BG2: 40 | BH2: 41 | BI2: 42 | BJ2: 43 | BK2: 44 | BL2: 45 | BM2: 46 | BN2: 47 | BO2: 48 | BP2: 49 | BQ2: 50
B3: 款 | C3: 項 | D3: 目 | F3: 総括原価の区分 | J3: 控除 項目 | K3: 将来設定条件 | L3: 物価 | M3: 算出根拠 | N3: 実績期間 | S3: 平均値 | T3: 料金算定期間 | X3: 参考期間
G4: 需要家費 | H4: 固定費 | I4: 変動費 | N4: H22~ | O4: H27 | P4: H28 | Q4: H29 | R4: H30 | T4: H31 | U4: R2 | V4: R3 | W4: R4 | X4: R5 | Y4: R6 | Z4: R7 | AA4: R8 | AB4: R9 | AC4: R10 | AD4: R11 | AE4: R12 | AF4: R13 | AG4: R14 | AH4: R15 | AI4: R16 | AJ4: R17 | AK4: R18 | AL4: R19 | AM4: R20 | AN4: R21 | AO4: R22 | AP4: R23 | AQ4: R24 | AR4: R25 | AS4: R26 | AT4: R27 | AU4: R28 | AV4: R29 | AW4: R30 | AX4: R31 | AY4: R32 | AZ4: R33 | BA4: R34 | BB4: R35 | BC4: R36 | BD4: R37 | BE4: R38 | BF4: R39 | BG4: R40 | BH4: R41 | BI4: R42 | BJ4: R43 | BK4: R44 | BL4: R45 | BM4: R46 | BN4: R47 | BO4: R48 | BP4: R49 | BQ4: R50
B5: 水道事業収益 | N5: =【PL】決算数値入力!#REF! -> #REF! | O5: =【PL】決算数値入力!#REF! -> #REF! | P5: =【PL】決算数値入力!#REF! -> #REF! | Q5: =【PL】決算数値入力!#REF! -> #REF! | R5: =【PL】決算数値入力!#REF! -> #REF! | S5: =【PL】決算数値入力!#REF! -> #REF! | T5: =SUM(T6,T11,T18,T19) -> #REF! | U5: =SUM(U6,U11,U18,U19) -> #REF! | V5: =SUM(V6,V11,V18,V19) -> #REF! | W5: =SUM(W6,W11,W18,W19) -> #REF! | X5: =SUM(X6,X11,X18,X19) -> #REF! | Y5: =SUM(Y6,Y11,Y18,Y19) -> #REF! | Z5: =SUM(Z6,Z11,Z18,Z19) -> #REF! | AA5: =SUM(AA6,AA11,AA18,AA19) -> #REF! | ... BQ5: =SUM(BQ6,BQ11,BQ18,BQ19) -> #REF!
C6: 営業収益 | N6: =【PL】決算数値入力!#REF! -> #REF! | O6: =【PL】決算数値入力!#REF! -> #REF! | P6: =【PL】決算数値入力!#REF! -> #REF! | Q6: =【PL】決算数値入力!#REF! -> #REF! | R6: =【PL】決算数値入力!#REF! -> #REF! | S6: =【PL】決算数値入力!#REF! -> #REF! | T6: =SUM(T7:T10) -> #REF! | U6: =SUM(U7:U10) -> #REF! | V6: =SUM(V7:V10) -> #REF! | W6: =SUM(W7:W10) -> #REF! | X6: =SUM(X7:X10) -> #REF! | Y6: =SUM(Y7:Y10) -> #REF! | Z6: =SUM(Z7:Z10) -> #REF! | AA6: =SUM(AA7:AA10) -> #REF! | ... BQ6: =SUM(BQ7:BQ10) -> #REF!
D7: 給水収益 | K7: 【収益】給水収益シート参照 | N7: =【PL】決算数値入力!#REF! -> #REF! | O7: =【PL】決算数値入力!#REF! -> #REF! | P7: =【PL】決算数値入力!#REF! -> #REF! | Q7: =【PL】決算数値入力!#REF! -> #REF! | R7: =【PL】決算数値入力!#REF! -> #REF! | S7: =【PL】決算数値入力!#REF! -> #REF! | T7: ='【料金算定－現行×改定率】給水収益'!S21 -> #REF! | U7: ='【料金算定－現行×改定率】給水収益'!T21 -> #REF! | V7: ='【料金算定－現行×改定率】給水収益'!U21 -> #REF! | W7: ='【料金算定－現行×改定率】給水収益'!V21 -> #REF! | X7: ='【料金算定－現行×改定率】給水収益'!W21 -> #REF! | Y7: ='【料金算定－現行×改定率】給水収益'!X21 -> #REF! | Z7: ='【料金算定－現行×改定率】給水収益'!Y21 -> #REF! | AA7: ='【料金算定－現行×改定率】給水収益'!Z21 -> #REF! | ... BQ7: ='【料金算定－現行×改定率】給水収益'!BP21 -> #REF!
D8: 加入金 | N8: =【PL】決算数値入力!#REF! -> #REF! | O8: =【PL】決算数値入力!#REF! -> #REF! | P8: =【PL】決算数値入力!#REF! -> #REF! | Q8: =【PL】決算数値入力!#REF! -> #REF! | R8: =【PL】決算数値入力!#REF! -> #REF! | S8: =【PL】決算数値入力!#REF! -> #REF! | T8: =S8 -> #REF! | U8: =T8 -> #REF! | V8: =U8 -> #REF! | W8: =V8 -> #REF! | X8: =W8 -> #REF! | Y8: =X8 -> #REF! | Z8: =Y8 -> #REF! | AA8: =Z8 -> #REF! | ... BQ8: =BP8 -> #REF!
D9: 受託工事収益 | K9: 計上しない | N9: =【PL】決算数値入力!#REF! -> #REF! | O9: =【PL】決算数値入力!#REF! -> #REF! | P9: =【PL】決算数値入力!#REF! -> #REF! | Q9: =【PL】決算数値入力!#REF! -> #REF! | R9: =【PL】決算数値入力!#REF! -> #REF! | S9: =【PL】決算数値入力!#REF! -> #REF! | T9: 0 | U9: 0 | V9: 0 | W9: 0 | X9: 0 | Y9: 0 | Z9: 0 | AA9: 0 | AB9: 0 | AC9: 0 | AD9: 0 | AE9: 0 | AF9: 0 | AG9: 0 | AH9: 0 | AI9: 0 | AJ9: 0 | AK9: 0 | AL9: 0 | AM9: 0 | AN9: 0 | AO9: 0 | AP9: 0 | AQ9: 0 | AR9: 0 | AS9: 0 | AT9: 0 | AU9: 0 | AV9: 0 | AW9: 0 | AX9: 0 | AY9: 0 | AZ9: 0 | BA9: 0 | BB9: 0 | BC9: 0 | BD9: 0 | BE9: 0 | BF9: 0 | BG9: 0 | BH9: 0 | BI9: 0 | BJ9: 0 | BK9: 0 | BL9: 0 | BM9: 0 | BN9: 0 | BO9: 0 | BP9: 0 | BQ9: 0
D10: その他の営業収益 | J10: ● | K10: H22~H30決算の平均値で一定 | N10: =【PL】決算数値入力!#REF! -> #REF! | O10: =【PL】決算数値入力!#REF! -> #REF! | P10: =【PL】決算数値入力!#REF! -> #REF! | Q10: =【PL】決算数値入力!#REF! -> #REF! | R10: =【PL】決算数値入力!#REF! -> #REF! | S10: =【PL】決算数値入力!#REF! -> #REF! | T10: =S10 -> #REF! | U10: =T10 -> #REF! | V10: =U10 -> #REF! | W10: =V10 -> #REF! | X10: =W10 -> #REF! | Y10: =X10 -> #REF! | Z10: =Y10 -> #REF! | AA10: =Z10 -> #REF! | ... BQ10: =BP10 -> #REF!
C11: 営業外収益 | N11: =【PL】決算数値入力!#REF! -> #REF! | O11: =【PL】決算数値入力!#REF! -> #REF! | P11: =【PL】決算数値入力!#REF! -> #REF! | Q11: =【PL】決算数値入力!#REF! -> #REF! | R11: =【PL】決算数値入力!#REF! -> #REF! | S11: =【PL】決算数値入力!#REF! -> #REF! | T11: =SUM(T12:T15) -> #REF! | U11: =SUM(U12:U15) -> #REF! | V11: =SUM(V12:V15) -> #REF! | W11: =SUM(W12:W15) -> #REF! | X11: =SUM(X12:X15) -> #REF! | Y11: =SUM(Y12:Y15) -> #REF! | Z11: =SUM(Z12:Z15) -> #REF! | AA11: =SUM(AA12:AA15) -> #REF! | ... BQ11: =SUM(BQ12:BQ15) -> #REF!
D12: 受取利息及び配当金 | J12: ● | K12: H22~H30決算の平均値で一定 | N12: =【PL】決算数値入力!#REF! -> #REF! | O12: =【PL】決算数値入力!#REF! -> #REF! | P12: =【PL】決算数値入力!#REF! -> #REF! | Q12: =【PL】決算数値入力!#REF! -> #REF! | R12: =【PL】決算数値入力!#REF! -> #REF! | S12: =【PL】決算数値入力!#REF! -> #REF! | T12: =S12 -> #REF! | U12: =T12 -> #REF! | V12: =U12 -> #REF! | W12: =V12 -> #REF! | X12: =W12 -> #REF! | Y12: =X12 -> #REF! | Z12: =Y12 -> #REF! | AA12: =Z12 -> #REF! | ... BQ12: =BP12 -> #REF!
D13: 他会計補助金 | J13: ● | K13: 現状の算定式（＝減価償却費＋人件費＋支払利息）で算定 | N13: =【PL】決算数値入力!#REF! -> #REF! | O13: =【PL】決算数値入力!#REF! -> #REF! | P13: =【PL】決算数値入力!#REF! -> #REF! | Q13: =【PL】決算数値入力!#REF! -> #REF! | R13: =【PL】決算数値入力!#REF! -> #REF! | S13: =【PL】決算数値入力!#REF! -> #REF! | T13: =T43+T51+T58 -> #REF! | U13: =U43+U51+U58 -> #REF! | V13: =V43+V51+V58 -> #REF! | W13: =W43+W51+W58 -> #REF! | X13: =X43+X51+X58 -> #REF! | Y13: =Y43+Y51+Y58 -> #REF! | Z13: =Z43+Z51+Z58 -> #REF! | AA13: =AA43+AA51+AA58 -> #REF! | ... BQ13: =BQ43+BQ51+BQ58 -> #REF!
D14: 雑収益 | J14: ● | K14: H22~H30決算の平均値で一定 | N14: =【PL】決算数値入力!#REF! -> #REF! | O14: =【PL】決算数値入力!#REF! -> #REF! | P14: =【PL】決算数値入力!#REF! -> #REF! | Q14: =【PL】決算数値入力!#REF! -> #REF! | R14: =【PL】決算数値入力!#REF! -> #REF! | S14: =【PL】決算数値入力!#REF! -> #REF! | T14: =S14 -> #REF! | U14: =T14 -> #REF! | V14: =U14 -> #REF! | W14: =V14 -> #REF! | X14: =W14 -> #REF! | Y14: =X14 -> #REF! | Z14: =Y14 -> #REF! | AA14: =Z14 -> #REF! | ... BQ14: =BP14 -> #REF!
D15: 長期前受金戻入益 | N15: =【PL】決算数値入力!#REF! -> #REF! | O15: =【PL】決算数値入力!#REF! -> #REF! | P15: =【PL】決算数値入力!#REF! -> #REF! | Q15: =【PL】決算数値入力!#REF! -> #REF! | R15: =【PL】決算数値入力!#REF! -> #REF! | S15: =【PL】決算数値入力!#REF! -> #REF! | T15: =SUM(T16:T17) -> 7854154 | U15: =SUM(U16:U17) -> 7369181 | V15: =SUM(V16:V17) -> 7145856 | W15: =SUM(W16:W17) -> 6975465 | X15: =SUM(X16:X17) -> 6971670 | Y15: =SUM(Y16:Y17) -> 6791365 | Z15: =SUM(Z16:Z17) -> 6480393 | AA15: =SUM(AA16:AA17) -> 6480393 | ... BQ15: =SUM(BQ16:BQ17) -> 6929736.8
E16: H30末の取得資産 | K16: 固定資産台帳データに基づく算定額 | N16: =【PL】決算数値入力!#REF! -> #REF! | O16: =【PL】決算数値入力!#REF! -> #REF! | P16: =【PL】決算数値入力!#REF! -> #REF! | Q16: =【PL】決算数値入力!#REF! -> #REF! | R16: =【PL】決算数値入力!#REF! -> #REF! | S16: =【PL】決算数値入力!#REF! -> #REF! | T16: 7854154 | U16: 7369181 | V16: 7145856 | W16: 6975465 | X16: 6971670 | Y16: 6791365 | Z16: 6480393 | AA16: 6480393 | AB16: 6480393 | AC16: 6480393 | AD16: 6466335 | AE16: 6307390 | AF16: 6307390 | AG16: 5334454 | AH16: 5334454 | AI16: 4767703 | AJ16: 4767703 | AK16: 4688622 | AL16: 4574099 | AM16: 4574099 | AN16: 4574099 | AO16: 4393098 | AP16: 4393098 | AQ16: 4393098 | AR16: 4393098 | AS16: 4393098 | AT16: 4393098 | AU16: 4344750 | AV16: 4344750 | AW16: 4344750 | AX16: 4344750 | AY16: 3810720 | AZ16: 3810720 | BA16: 3704365 | BB16: 3704365 | BC16: 2810476 | BD16: 2715727 | BE16: 2320665 | BF16: 1635858 | BG16: 1635858 | BH16: 1635858 | BI16: 0 | BJ16: 0 | BK16: 0 | BL16: 0 | BM16: 0 | BN16: 0 | BO16: 0 | BP16: 0 | BQ16: 0
E17: H31以降の取得資産 | K17: 償却計算額 | N17: =【PL】決算数値入力!#REF! -> #REF! | O17: =【PL】決算数値入力!#REF! -> #REF! | P17: =【PL】決算数値入力!#REF! -> #REF! | Q17: =【PL】決算数値入力!#REF! -> #REF! | R17: =【PL】決算数値入力!#REF! -> #REF! | S17: =【PL】決算数値入力!#REF! -> #REF! | T17: =新規取得!I5 -> 0 | U17: =新規取得!J5 -> 0 | V17: =新規取得!K5 -> 0 | W17: =新規取得!L5 -> 0 | X17: =新規取得!M5 -> 0 | Y17: =新規取得!N5 -> 0 | Z17: =新規取得!O5 -> 0 | AA17: =新規取得!P5 -> 0 | ... BQ17: =新規取得!BF5 -> 6929736.8
C18: 引当金戻入益 | J18: ● | K18: 計上しない | N18: =【PL】決算数値入力!#REF! -> #REF! | O18: =【PL】決算数値入力!#REF! -> #REF! | P18: =【PL】決算数値入力!#REF! -> #REF! | Q18: =【PL】決算数値入力!#REF! -> #REF! | R18: =【PL】決算数値入力!#REF! -> #REF! | S18: =【PL】決算数値入力!#REF! -> #REF! | T18: 0 | U18: 0 | V18: 0 | W18: 0 | X18: 0 | Y18: 0 | Z18: 0 | AA18: 0 | AB18: 0 | AC18: 0 | AD18: 0 | AE18: 0 | AF18: 0 | AG18: 0 | AH18: 0 | AI18: 0 | AJ18: 0 | AK18: 0 | AL18: 0 | AM18: 0 | AN18: 0 | AO18: 0 | AP18: 0 | AQ18: 0 | AR18: 0 | AS18: 0 | AT18: 0 | AU18: 0 | AV18: 0 | AW18: 0 | AX18: 0 | AY18: 0 | AZ18: 0 | BA18: 0 | BB18: 0 | BC18: 0 | BD18: 0 | BE18: 0 | BF18: 0 | BG18: 0 | BH18: 0 | BI18: 0 | BJ18: 0 | BK18: 0 | BL18: 0 | BM18: 0 | BN18: 0 | BO18: 0 | BP18: 0 | BQ18: 0
C19: 特別利益 | N19: =【PL】決算数値入力!#REF! -> #REF! | O19: =【PL】決算数値入力!#REF! -> #REF! | P19: =【PL】決算数値入力!#REF! -> #REF! | Q19: =【PL】決算数値入力!#REF! -> #REF! | R19: =【PL】決算数値入力!#REF! -> #REF! | S19: =【PL】決算数値入力!#REF! -> #REF! | T19: =SUM(T20:T22) -> 0 | U19: =SUM(U20:U22) -> 0 | V19: =SUM(V20:V22) -> 0 | W19: =SUM(W20:W22) -> 0 | X19: =SUM(X20:X22) -> 0 | Y19: =SUM(Y20:Y22) -> 0 | Z19: =SUM(Z20:Z22) -> 0 | AA19: =SUM(AA20:AA22) -> 0 | ... BQ19: =SUM(BQ20:BQ22) -> 0
D20: 固定資産売却益 | J20: ● | K20: 計上しない | N20: =【PL】決算数値入力!#REF! -> #REF! | O20: =【PL】決算数値入力!#REF! -> #REF! | P20: =【PL】決算数値入力!#REF! -> #REF! | Q20: =【PL】決算数値入力!#REF! -> #REF! | R20: =【PL】決算数値入力!#REF! -> #REF! | S20: =【PL】決算数値入力!#REF! -> #REF! | T20: 0 | U20: 0 | V20: 0 | W20: 0 | X20: 0 | Y20: 0 | Z20: 0 | AA20: 0 | AB20: 0 | AC20: 0 | AD20: 0 | AE20: 0 | AF20: 0 | AG20: 0 | AH20: 0 | AI20: 0 | AJ20: 0 | AK20: 0 | AL20: 0 | AM20: 0 | AN20: 0 | AO20: 0 | AP20: 0 | AQ20: 0 | AR20: 0 | AS20: 0 | AT20: 0 | AU20: 0 | AV20: 0 | AW20: 0 | AX20: 0 | AY20: 0 | AZ20: 0 | BA20: 0 | BB20: 0 | BC20: 0 | BD20: 0 | BE20: 0 | BF20: 0 | BG20: 0 | BH20: 0 | BI20: 0 | BJ20: 0 | BK20: 0 | BL20: 0 | BM20: 0 | BN20: 0 | BO20: 0 | BP20: 0 | BQ20: 0
D21: 過年度修正益 | J21: ● | K21: 計上しない | N21: =【PL】決算数値入力!#REF! -> #REF! | O21: =【PL】決算数値入力!#REF! -> #REF! | P21: =【PL】決算数値入力!#REF! -> #REF! | Q21: =【PL】決算数値入力!#REF! -> #REF! | R21: =【PL】決算数値入力!#REF! -> #REF! | S21: =【PL】決算数値入力!#REF! -> #REF! | T21: 0 | U21: 0 | V21: 0 | W21: 0 | X21: 0 | Y21: 0 | Z21: 0 | AA21: 0 | AB21: 0 | AC21: 0 | AD21: 0 | AE21: 0 | AF21: 0 | AG21: 0 | AH21: 0 | AI21: 0 | AJ21: 0 | AK21: 0 | AL21: 0 | AM21: 0 | AN21: 0 | AO21: 0 | AP21: 0 | AQ21: 0 | AR21: 0 | AS21: 0 | AT21: 0 | AU21: 0 | AV21: 0 | AW21: 0 | AX21: 0 | AY21: 0 | AZ21: 0 | BA21: 0 | BB21: 0 | BC21: 0 | BD21: 0 | BE21: 0 | BF21: 0 | BG21: 0 | BH21: 0 | BI21: 0 | BJ21: 0 | BK21: 0 | BL21: 0 | BM21: 0 | BN21: 0 | BO21: 0 | BP21: 0 | BQ21: 0
D22: その他特別利益 | J22: ● | K22: 計上しない | N22: =【PL】決算数値入力!#REF! -> #REF! | O22: =【PL】決算数値入力!#REF! -> #REF! | P22: =【PL】決算数値入力!#REF! -> #REF! | Q22: =【PL】決算数値入力!#REF! -> #REF! | R22: =【PL】決算数値入力!#REF! -> #REF! | S22: =【PL】決算数値入力!#REF! -> #REF! | T22: 0 | U22: 0 | V22: 0 | W22: 0 | X22: 0 | Y22: 0 | Z22: 0 | AA22: 0 | AB22: 0 | AC22: 0 | AD22: 0 | AE22: 0 | AF22: 0 | AG22: 0 | AH22: 0 | AI22: 0 | AJ22: 0 | AK22: 0 | AL22: 0 | AM22: 0 | AN22: 0 | AO22: 0 | AP22: 0 | AQ22: 0 | AR22: 0 | AS22: 0 | AT22: 0 | AU22: 0 | AV22: 0 | AW22: 0 | AX22: 0 | AY22: 0 | AZ22: 0 | BA22: 0 | BB22: 0 | BC22: 0 | BD22: 0 | BE22: 0 | BF22: 0 | BG22: 0 | BH22: 0 | BI22: 0 | BJ22: 0 | BK22: 0 | BL22: 0 | BM22: 0 | BN22: 0 | BO22: 0 | BP22: 0 | BQ22: 0
B23: 水道事業費用 | N23: =【PL】決算数値入力!#REF! -> #REF! | O23: =【PL】決算数値入力!#REF! -> #REF! | P23: =【PL】決算数値入力!#REF! -> #REF! | Q23: =【PL】決算数値入力!#REF! -> #REF! | R23: =【PL】決算数値入力!#REF! -> #REF! | S23: =【PL】決算数値入力!#REF! -> #REF! | T23: =SUM(T24,T57,T62) -> #REF! | U23: =SUM(U24,U57,U62) -> #REF! | V23: =SUM(V24,V57,V62) -> #REF! | W23: =SUM(W24,W57,W62) -> #REF! | X23: =SUM(X24,X57,X62) -> #REF! | Y23: =SUM(Y24,Y57,Y62) -> #REF! | Z23: =SUM(Z24,Z57,Z62) -> #REF! | AA23: =SUM(AA24,AA57,AA62) -> #REF! | ... BQ23: =SUM(BQ24,BQ57,BQ62) -> #REF!
C24: 営業費用 | N24: =【PL】決算数値入力!#REF! -> #REF! | O24: =【PL】決算数値入力!#REF! -> #REF! | P24: =【PL】決算数値入力!#REF! -> #REF! | Q24: =【PL】決算数値入力!#REF! -> #REF! | R24: =【PL】決算数値入力!#REF! -> #REF! | S24: =【PL】決算数値入力!#REF! -> #REF! | T24: =SUM(T25,T33,T42,T51,T54) -> #REF! | U24: =SUM(U25,U33,U42,U51,U54) -> #REF! | V24: =SUM(V25,V33,V42,V51,V54) -> #REF! | W24: =SUM(W25,W33,W42,W51,W54) -> #REF! | X24: =SUM(X25,X33,X42,X51,X54) -> #REF! | Y24: =SUM(Y25,Y33,Y42,Y51,Y54) -> #REF! | Z24: =SUM(Z25,Z33,Z42,Z51,Z54) -> #REF! | AA24: =SUM(AA25,AA33,AA42,AA51,AA54) -> #REF! | ... BQ24: =SUM(BQ25,BQ33,BQ42,BQ51,BQ54) -> #REF!
D25: 原水及び浄水費 | F25: 原浄水部門費 | N25: =【PL】決算数値入力!#REF! -> #REF! | O25: =【PL】決算数値入力!#REF! -> #REF! | P25: =【PL】決算数値入力!#REF! -> #REF! | Q25: =【PL】決算数値入力!#REF! -> #REF! | R25: =【PL】決算数値入力!#REF! -> #REF! | S25: =【PL】決算数値入力!#REF! -> #REF! | T25: =SUM(T26:T32) -> #REF! | U25: =SUM(U26:U32) -> #REF! | V25: =SUM(V26:V32) -> #REF! | W25: =SUM(W26:W32) -> #REF! | X25: =SUM(X26:X32) -> #REF! | Y25: =SUM(Y26:Y32) -> #REF! | Z25: =SUM(Z26:Z32) -> #REF! | AA25: =SUM(AA26:AA32) -> #REF! | ... BQ25: =SUM(BQ26:BQ32) -> #REF!
E26: 人件費 | H26: ● | K26: H22~H30決算の平均値に物価上昇率を加味 | L26: ● | N26: =【PL】決算数値入力!#REF! -> #REF! | O26: =【PL】決算数値入力!#REF! -> #REF! | P26: =【PL】決算数値入力!#REF! -> #REF! | Q26: =【PL】決算数値入力!#REF! -> #REF! | R26: =【PL】決算数値入力!#REF! -> #REF! | S26: =【PL】決算数値入力!#REF! -> #REF! | T26: =ROUND(S26*(1+物価上昇率!$G$9),0) -> #REF! | U26: =ROUND(T26*(1+物価上昇率!$G$9),0) -> #REF! | V26: =ROUND(U26*(1+物価上昇率!$G$9),0) -> #REF! | W26: =ROUND(V26*(1+物価上昇率!$G$9),0) -> #REF! | X26: =ROUND(W26*(1+物価上昇率!$G$9),0) -> #REF! | Y26: =ROUND(X26*(1+物価上昇率!$G$9),0) -> #REF! | Z26: =ROUND(Y26*(1+物価上昇率!$G$9),0) -> #REF! | AA26: =ROUND(Z26*(1+物価上昇率!$G$9),0) -> #REF! | ... BQ26: =ROUND(BP26*(1+物価上昇率!$G$9),0) -> #REF!
E27: 動力費 | I27: ● | K27: H22~H30有収水量1㎥あたり費用×有収水量（見込） | L27: ● | N27: =【PL】決算数値入力!#REF! -> #REF! | O27: =【PL】決算数値入力!#REF! -> #REF! | P27: =【PL】決算数値入力!#REF! -> #REF! | Q27: =【PL】決算数値入力!#REF! -> #REF! | R27: =【PL】決算数値入力!#REF! -> #REF! | S27: =【PL】決算数値入力!#REF! -> #REF! | T27: =ROUND(SUM(【PL】決算数値入力!#REF!)/SUM(【収益】水需要予測!$N$19:$W$19),0)*【収益】水需要予測!Y21 -> #REF! | U27: =ROUND(SUM(【PL】決算数値入力!#REF!)/SUM(【収益】水需要予測!$N$19:$W$19),0)*【収益】水需要予測!Z21 -> #REF! | V27: =ROUND(SUM(【PL】決算数値入力!#REF!)/SUM(【収益】水需要予測!$N$19:$W$19),0)*【収益】水需要予測!AA21 -> #REF! | W27: =ROUND(SUM(【PL】決算数値入力!#REF!)/SUM(【収益】水需要予測!$N$19:$W$19),0)*【収益】水需要予測!AB21 -> #REF! | X27: =ROUND(SUM(【PL】決算数値入力!#REF!)/SUM(【収益】水需要予測!$N$19:$W$19),0)*【収益】水需要予測!AC21 -> #REF! | Y27: =ROUND(SUM(【PL】決算数値入力!#REF!)/SUM(【収益】水需要予測!$N$19:$W$19),0)*【収益】水需要予測!AD21 -> #REF! | Z27: =ROUND(SUM(【PL】決算数値入力!#REF!)/SUM(【収益】水需要予測!$N$19:$W$19),0)*【収益】水需要予測!AE21 -> #REF! | AA27: =ROUND(SUM(【PL】決算数値入力!#REF!)/SUM(【収益】水需要予測!$N$19:$W$19),0)*【収益】水需要予測!AF21 -> #REF! | ... BQ27: =ROUND(SUM(【PL】決算数値入力!#REF!)/SUM(【収益】水需要予測!$N$19:$W$19),0)*【収益】水需要予測!BV21 -> #REF!
E28: 薬品費 | I28: ● | K28: H22~H30有収水量1㎥あたり費用×有収水量（見込） | L28: ● | N28: =【PL】決算数値入力!#REF! -> #REF! | O28: =【PL】決算数値入力!#REF! -> #REF! | P28: =【PL】決算数値入力!#REF! -> #REF! | Q28: =【PL】決算数値入力!#REF! -> #REF! | R28: =【PL】決算数値入力!#REF! -> #REF! | S28: =【PL】決算数値入力!#REF! -> #REF! | T28: =ROUND(SUM(【PL】決算数値入力!#REF!)/SUM(【収益】水需要予測!$N$19:$W$19)*【収益】水需要予測!Y21,0) -> #REF! | U28: =ROUND(SUM(【PL】決算数値入力!#REF!)/SUM(【収益】水需要予測!$N$19:$W$19)*【収益】水需要予測!Z21,0) -> #REF! | V28: =ROUND(SUM(【PL】決算数値入力!#REF!)/SUM(【収益】水需要予測!$N$19:$W$19)*【収益】水需要予測!AA21,0) -> #REF! | W28: =ROUND(SUM(【PL】決算数値入力!#REF!)/SUM(【収益】水需要予測!$N$19:$W$19)*【収益】水需要予測!AB21,0) -> #REF! | X28: =ROUND(SUM(【PL】決算数値入力!#REF!)/SUM(【収益】水需要予測!$N$19:$W$19)*【収益】水需要予測!AC21,0) -> #REF! | Y28: =ROUND(SUM(【PL】決算数値入力!#REF!)/SUM(【収益】水需要予測!$N$19:$W$19)*【収益】水需要予測!AD21,0) -> #REF! | Z28: =ROUND(SUM(【PL】決算数値入力!#REF!)/SUM(【収益】水需要予測!$N$19:$W$19)*【収益】水需要予測!AE21,0) -> #REF! | AA28: =ROUND(SUM(【PL】決算数値入力!#REF!)/SUM(【収益】水需要予測!$N$19:$W$19)*【収益】水需要予測!AF21,0) -> #REF! | ... BQ28: =ROUND(SUM(【PL】決算数値入力!#REF!)/SUM(【収益】水需要予測!$N$19:$W$19)*【収益】水需要予測!BV21,0) -> #REF!
E29: 修繕費 | H29: ● | K29: H22~H30決算の平均値に物価上昇率を加味 | L29: ● | N29: =【PL】決算数値入力!#REF! -> #REF! | O29: =【PL】決算数値入力!#REF! -> #REF! | P29: =【PL】決算数値入力!#REF! -> #REF! | Q29: =【PL】決算数値入力!#REF! -> #REF! | R29: =【PL】決算数値入力!#REF! -> #REF! | S29: =【PL】決算数値入力!#REF! -> #REF! | T29: =ROUND(S29*(1+物価上昇率!$G$9),0) -> #REF! | U29: =ROUND(T29*(1+物価上昇率!$G$9),0) -> #REF! | V29: =ROUND(U29*(1+物価上昇率!$G$9),0) -> #REF! | W29: =ROUND(V29*(1+物価上昇率!$G$9),0) -> #REF! | X29: =ROUND(W29*(1+物価上昇率!$G$9),0) -> #REF! | Y29: =ROUND(X29*(1+物価上昇率!$G$9),0) -> #REF! | Z29: =ROUND(Y29*(1+物価上昇率!$G$9),0) -> #REF! | AA29: =ROUND(Z29*(1+物価上昇率!$G$9),0) -> #REF! | ... BQ29: =ROUND(BP29*(1+物価上昇率!$G$9),0) -> #REF!
E30: 委託料 | H30: ● | K30: H22~H30決算の平均値に物価上昇率を加味 | L30: ● | N30: =【PL】決算数値入力!#REF! -> #REF! | O30: =【PL】決算数値入力!#REF! -> #REF! | P30: =【PL】決算数値入力!#REF! -> #REF! | Q30: =【PL】決算数値入力!#REF! -> #REF! | R30: =【PL】決算数値入力!#REF! -> #REF! | S30: =【PL】決算数値入力!#REF! -> #REF! | T30: =ROUND(S30*(1+物価上昇率!$G$9),0) -> #REF! | U30: =ROUND(T30*(1+物価上昇率!$G$9),0) -> #REF! | V30: =ROUND(U30*(1+物価上昇率!$G$9),0) -> #REF! | W30: =ROUND(V30*(1+物価上昇率!$G$9),0) -> #REF! | X30: =ROUND(W30*(1+物価上昇率!$G$9),0) -> #REF! | Y30: =ROUND(X30*(1+物価上昇率!$G$9),0) -> #REF! | Z30: =ROUND(Y30*(1+物価上昇率!$G$9),0) -> #REF! | AA30: =ROUND(Z30*(1+物価上昇率!$G$9),0) -> #REF! | ... BQ30: =ROUND(BP30*(1+物価上昇率!$G$9),0) -> #REF!
E31: その他（物価上昇を考慮する） | H31: ● | K31: H22~H30決算の平均値に物価上昇率を加味 | L31: ● | N31: =【PL】決算数値入力!#REF! -> #REF! | O31: =【PL】決算数値入力!#REF! -> #REF! | P31: =【PL】決算数値入力!#REF! -> #REF! | Q31: =【PL】決算数値入力!#REF! -> #REF! | R31: =【PL】決算数値入力!#REF! -> #REF! | S31: =【PL】決算数値入力!#REF! -> #REF! | T31: =ROUND(S31*(1+物価上昇率!$G$9),0) -> #REF! | U31: =ROUND(T31*(1+物価上昇率!$G$9),0) -> #REF! | V31: =ROUND(U31*(1+物価上昇率!$G$9),0) -> #REF! | W31: =ROUND(V31*(1+物価上昇率!$G$9),0) -> #REF! | X31: =ROUND(W31*(1+物価上昇率!$G$9),0) -> #REF! | Y31: =ROUND(X31*(1+物価上昇率!$G$9),0) -> #REF! | Z31: =ROUND(Y31*(1+物価上昇率!$G$9),0) -> #REF! | AA31: =ROUND(Z31*(1+物価上昇率!$G$9),0) -> #REF! | ... BQ31: =ROUND(BP31*(1+物価上昇率!$G$9),0) -> #REF!
E32: その他（物価上昇を考慮しない） | H32: ● | K32: H22~H30決算の平均値で一定 | N32: =【PL】決算数値入力!#REF! -> #REF! | O32: =【PL】決算数値入力!#REF! -> #REF! | P32: =【PL】決算数値入力!#REF! -> #REF! | Q32: =【PL】決算数値入力!#REF! -> #REF! | R32: =【PL】決算数値入力!#REF! -> #REF! | S32: =【PL】決算数値入力!#REF! -> #REF! | T32: =S32 -> #REF! | U32: =T32 -> #REF! | V32: =U32 -> #REF! | W32: =V32 -> #REF! | X32: =W32 -> #REF! | Y32: =X32 -> #REF! | Z32: =Y32 -> #REF! | AA32: =Z32 -> #REF! | ... BQ32: =BP32 -> #REF!
D33: 配水及び給水費 | F33: 配給水部門費 | N33: =【PL】決算数値入力!#REF! -> #REF! | O33: =【PL】決算数値入力!#REF! -> #REF! | P33: =【PL】決算数値入力!#REF! -> #REF! | Q33: =【PL】決算数値入力!#REF! -> #REF! | R33: =【PL】決算数値入力!#REF! -> #REF! | S33: =【PL】決算数値入力!#REF! -> #REF! | T33: =SUM(T34:T40) -> #REF! | U33: =SUM(U34:U40) -> #REF! | V33: =SUM(V34:V40) -> #REF! | W33: =SUM(W34:W40) -> #REF! | X33: =SUM(X34:X40) -> #REF! | Y33: =SUM(Y34:Y40) -> #REF! | Z33: =SUM(Z34:Z40) -> #REF! | AA33: =SUM(AA34:AA40) -> #REF! | ... BQ33: =SUM(BQ34:BQ40) -> #REF!
E34: 人件費 | H34: ● | K34: H22~H30決算の平均値に物価上昇率を加味 | L34: ● | N34: =【PL】決算数値入力!#REF! -> #REF! | O34: =【PL】決算数値入力!#REF! -> #REF! | P34: =【PL】決算数値入力!#REF! -> #REF! | Q34: =【PL】決算数値入力!#REF! -> #REF! | R34: =【PL】決算数値入力!#REF! -> #REF! | S34: =【PL】決算数値入力!#REF! -> #REF! | T34: =ROUND(S34*(1+物価上昇率!$G$9),0) -> #REF! | U34: =ROUND(T34*(1+物価上昇率!$G$9),0) -> #REF! | V34: =ROUND(U34*(1+物価上昇率!$G$9),0) -> #REF! | W34: =ROUND(V34*(1+物価上昇率!$G$9),0) -> #REF! | X34: =ROUND(W34*(1+物価上昇率!$G$9),0) -> #REF! | Y34: =ROUND(X34*(1+物価上昇率!$G$9),0) -> #REF! | Z34: =ROUND(Y34*(1+物価上昇率!$G$9),0) -> #REF! | AA34: =ROUND(Z34*(1+物価上昇率!$G$9),0) -> #REF! | ... BQ34: =ROUND(BP34*(1+物価上昇率!$G$9),0) -> #REF!
E35: 動力費 | I35: ● | K35: H22~H30有収水量1㎥あたり費用×有収水量（見込） | L35: ● | N35: =【PL】決算数値入力!#REF! -> #REF! | O35: =【PL】決算数値入力!#REF! -> #REF! | P35: =【PL】決算数値入力!#REF! -> #REF! | Q35: =【PL】決算数値入力!#REF! -> #REF! | R35: =【PL】決算数値入力!#REF! -> #REF! | S35: =【PL】決算数値入力!#REF! -> #REF! | T35: =ROUND(SUM(【PL】決算数値入力!#REF!)/SUM(【収益】水需要予測!$N$19:$W$19),0)*【収益】水需要予測!Y21 -> #REF! | U35: =ROUND(SUM(【PL】決算数値入力!#REF!)/SUM(【収益】水需要予測!$N$19:$W$19),0)*【収益】水需要予測!Z21 -> #REF! | V35: =ROUND(SUM(【PL】決算数値入力!#REF!)/SUM(【収益】水需要予測!$N$19:$W$19),0)*【収益】水需要予測!AA21 -> #REF! | W35: =ROUND(SUM(【PL】決算数値入力!#REF!)/SUM(【収益】水需要予測!$N$19:$W$19),0)*【収益】水需要予測!AB21 -> #REF! | X35: =ROUND(SUM(【PL】決算数値入力!#REF!)/SUM(【収益】水需要予測!$N$19:$W$19),0)*【収益】水需要予測!AC21 -> #REF! | Y35: =ROUND(SUM(【PL】決算数値入力!#REF!)/SUM(【収益】水需要予測!$N$19:$W$19),0)*【収益】水需要予測!AD21 -> #REF! | Z35: =ROUND(SUM(【PL】決算数値入力!#REF!)/SUM(【収益】水需要予測!$N$19:$W$19),0)*【収益】水需要予測!AE21 -> #REF! | AA35: =ROUND(SUM(【PL】決算数値入力!#REF!)/SUM(【収益】水需要予測!$N$19:$W$19),0)*【収益】水需要予測!AF21 -> #REF! | ... BQ35: =ROUND(SUM(【PL】決算数値入力!#REF!)/SUM(【収益】水需要予測!$N$19:$W$19),0)*【収益】水需要予測!BV21 -> #REF!
