Workbook

Sheet WBS・進捗管理
A1: 第10期北塩原村高齢者福祉計画・第10期北塩原村介護保険事業計画 策定業務 WBS／進捗管理表
A2: 委託第27号／業務期間：契約締結の日〜令和9年3月31日／計画期間：令和9〜11年度 ｜ 出典：仕様書（8北保福第483号 別紙）を作業レベルに分解（対応は「仕様書対照」シート） ｜ 進捗基準日：令和8年10月13日
A4: No. | B4: 大分類 | C4: 中分類 | D4: 作業項目 | E4: 仕様書該当 | F4: 担当 | G4: 成果物・アウトプット | H4: 前提・依存 | I4: 想定時期 | J4: 予定開始 | K4: 予定完了 | L4: 実績開始 | M4: 実績完了 | N4: 進捗率 | O4: ステータス | P4: 備考
A5: ０-01 | B5: ０ 契約・立上げ | C5: 契約手続 | D5: 見積書の提出 | E5: 通知2 | F5: 受託者 | G5: 見積書 | I5: R8.8 | L5: 46235 | M5: 46254 | N5: 1 | O5: 完了 | P5: 受注決定の連絡を受領。
A6: ０-02 | B6: ０ 契約・立上げ | C6: 契約手続 | D6: 契約締結 | E6: 仕様書3 | F6: 双方 | G6: 委託契約書 | H6: 北塩原村委託契約約款に準拠 | I6: R8.9 | N6: 0.5 | O6: 確認中 | P6: 受注決定は連絡済。契約締結日・契約書の取り交わし状況を要確認。
A7: ０-03 | B7: ０ 契約・立上げ | C7: 立上げ | D7: キックオフ会議の開催 | E7: 仕様書4Ⅲ | F7: 双方 | G7: キックオフ会議資料・議事録 | I7: R8.9上 | L7: 46259 | M7: 46266 | N7: 1 | O7: 完了 | P7: 令和8年9月1日（火）北塩原村役場にて開催。議事録を受領し確認・論点整理を完了（doc22）。優先度S 16件のうち9件が決着。基準日R8.9.1・在宅調査の抽出基準・管理番号の紐付け・発送9/18・ラベル封筒は村が用意・回収は100件ごとの小分け送付。
A8: ０-04 | B8: ０ 契約・立上げ | C8: 立上げ | D8: 連絡体制・資料授受方法の確定 | E8: 仕様書4Ⅲ | F8: 双方 | G8: 連絡体制表 | H8: 所管課（保健福祉課福祉係）の確認 | I8: R8.9上 | L8: 46259 | N8: 0.5 | O8: 着手 | P8: 資料授受は継続中。所管課（住民課→保健福祉課）の確認が未了（doc01確認事項1）。★10/5：村への照会を6通の照会票にまとめた。従来の資料提供確認依頼書（9月8日・調査票の工程）とは別に、計画策定の工程の照会を束ごとに1通とする形にした。
A9: ０-05 | B9: ０ 契約・立上げ | C9: 立上げ | D9: 現行計画・関連計画・実績資料の受領 | E9: 仕様書4Ⅱ(2) | F9: 北塩原村 | G9: 第9期計画書／第5次総合振興計画／第3次健康21ほか | I9: R8.9上 | L9: 46259 | N9: 0.7 | O9: 着手 | P9: 第9期計画書・第9期概要版（表裏）に加え、第四次生涯学習推進計画（全112頁）を受領（doc21）。第五次総合振興計画・第3次健康21・障がい福祉計画が未受領。
A10: ０-06 | B10: ０ 契約・立上げ | C10: 立上げ | D10: 見える化システムのID・パスワードの受領 | E10: 確認 | F10: 北塩原村 | G10: アカウント情報 | I10: R8.9上 | L10: 46259 | N10: 0.9 | O10: 着手 | P10: 見える化の出力を分割して受領（ZIP20本・738冊）。本村の値26,480行を取り出し data/mieruka_batch.csv に収めた（doc52）。ID自体の授受は要確認。
A11: Ⅰ-07 | B11: Ⅰ ニーズ調査 | C11: Ⅰ-1 調査設計 | D11: 調査手法の決定（在宅：手法Ⅰ〜Ⅳ） | E11: 手引き／確認 | F11: 双方 | G11: 調査手法決定メモ | H11: 手法Ⅲは自動集計ソフトなし。仕様書Ⅰ(5)との整合を要確認 | I11: R8.9上 | L11: 46259 | M11: 46274 | N11: 1 | O11: 完了 | P11: ★議事録に記載なし。手法Ⅲか手法Ⅳ（新版 在宅生活改善調査）を加えるかが未決着。9/3の第1稿提出時に併せて提起する（doc22 A-1）。★10/10 村より「高齢者のアンケート発送は全て完了」とのご連絡をいただいた。発送が完了したということは、調査票・依頼状・封筒・宛名ラベル・管理番号がすべて確定して物として出ていったということであり、その前提の工程はいずれも完了している。実績完了日は校了日（令和8年9月9日・doc34）または議事録の発送日（令和8年9月18日）としており、実際の発送日は村にご教示いただいて置き直す。
A12: Ⅰ-08 | B12: Ⅰ ニーズ調査 | C12: Ⅰ-1 調査設計 | D12: 調査対象者の抽出条件の確定 | E12: 仕様書4Ⅰ(1) | F12: 双方 | G12: 抽出条件メモ | H12: ①要支援を含むか②更新・区分変更に限るか③サ高住等を含むか | I12: R8.9上 | L12: 46259 | M12: 46274 | N12: 1 | O12: 完了 | P12: ★在宅介護実態調査は「要支援1・2および要介護1〜5の在宅生活者等」150件で決着（議事録）。基準日は令和8年9月1日。ニーズ調査約850件の抽出基準（要支援を含むか）は未決着。★10/10 村より「高齢者のアンケート発送は全て完了」とのご連絡をいただいた。発送が完了したということは、調査票・依頼状・封筒・宛名ラベル・管理番号がすべて確定して物として出ていったということであり、その前提の工程はいずれも完了している。実績完了日は校了日（令和8年9月9日・doc34）または議事録の発送日（令和8年9月18日）としており、実際の発送日は村にご教示いただいて置き直す。
A13: Ⅰ-09 | B13: Ⅰ ニーズ調査 | C13: Ⅰ-1 調査設計 | D13: 調査票の設計（ニーズ調査） | E13: 仕様書4Ⅰ(2) | F13: 受託者 | G13: 調査票案 | H13: 厚労省令和7年8月版様式を基礎 | I13: R8.9上 | L13: 46269 | M13: 46274 | N13: 1 | O13: 完了 | P13: ★第1稿（0828版）を受領し令和7年8月版との全面突合を完了（doc23）。要修正：選択肢の順序が標準と逆になっている7か所（うち2か所は文字列の誤植）、標準様式の残骸3か所、問7の番号繰り上がり。村独自14問の採否を判定し、削除提案は問3(10)の1問のみ。★9/4：第2稿（0904版）を確認。指摘13件のうち11件が反映。ルビを57→105か所に拡充、通いの場の名称を現行事業名に修正、自由記述欄を新設。未対応は問1(2)①の選択肢順序と問7(7)の採用可否の2件。新たに保険外サービスの選択肢の不統一と個人情報の説明文の後退を検出（doc27）。★9/14：0909校正版（doc34）を確認。問1(2)①の選択肢順序は解消。一方、問1(4)住まいの種類と問4(16)若い人に話しかけるが削除済み、問4(15)病人を見舞うに削除の指示。いずれも見える化の登録対象で、問4(15)(16)が落ちるとR09社会的役割の低下が算出できずR99が10領域→9領域に減る。印刷前の判断を要する。★10/10 村より「高齢者のアンケート発送は全て完了」とのご連絡をいただいた。発送が完了したということは、調査票・依頼状・封筒・宛名ラベル・管理番号がすべて確定して物として出ていったということであり、その前提の工程はいずれも完了している。実績完了日は校了日（令和8年9月9日・doc34）または議事録の発送日（令和8年9月18日）としており、実際の発送日は村にご教示いただいて置き直す。
A14: Ⅰ-10 | B14: Ⅰ ニーズ調査 | C14: Ⅰ-1 調査設計 | D14: 調査票の設計（在宅介護実態調査） | E14: 仕様書4Ⅰ(2) | F14: 受託者 | G14: 調査票案 | H14: 調査手法の決定が前提 | I14: R8.9上 | L14: 46269 | M14: 46274 | N14: 1 | O14: 完了 | P14: ★第1稿を受領し手法Ⅲ標準様式との突合を完了（doc23）。要修正：標準の問13「訪問診療」が削除され問13が欠番、前回指摘2件（介護療養型医療施設の削除・傷病の選択肢13/14の入替）が未反映、基準月が空欄。村独自の問0・問6-1は番号体系を壊さない適切な設計。★9/4：第2稿で介護療養型医療施設の削除・傷病の選択肢13/14・基準月（問8）・訪問診療の復活がすべて反映。ただし訪問診療の番号が問12となり問12が重複・問13が欠番、問9の基準月が未修正、B票の案内文1行が削除された（doc27§3・§5-3）。★9/14：0909校正版（doc34）を確認。問12の重複・問13の欠番と問9の基準月は解消。傷病に「なし」「わからない」が追加され疾病数が算出可能に。サービスは12→9に整理（夜間対応型・定期巡回・看多機を削除。実績0で妥当）。残る印刷前の修正は問7-1の参照先「問6」→「問7」、問10の記号K→H・L→I、A票問15の分岐の食い違い。★10/10 村より「高齢者のアンケート発送は全て完了」とのご連絡をいただいた。発送が完了したということは、調査票・依頼状・封筒・宛名ラベル・管理番号がすべて確定して物として出ていったということであり、その前提の工程はいずれも完了している。実績完了日は校了日（令和8年9月9日・doc34）または議事録の発送日（令和8年9月18日）としており、実際の発送日は村にご教示いただいて置き直す。
A15: Ⅰ-11 | B15: Ⅰ ニーズ調査 | C15: Ⅰ-1 調査設計 | D15: 令和7年8月版 標準様式との逐条突合 | E15: 手引き | F15: 受託者 | G15: 突合ワークシート | H15: 必須項目・オプション項目の充足確認 | I15: R8.9上 | L15: 46261 | M15: 46261 | N15: 1 | O15: 完了 | P15: 122行・全行記入・要確認0件で完了（doc05／突合ワークシートCSV）。
A16: Ⅰ-12 | B16: Ⅰ ニーズ調査 | C16: Ⅰ-1 調査設計 | D16: オプション項目の採否決定 | E16: 仕様書4Ⅰ(2) | F16: 双方 | G16: 採否一覧 | H16: 「問6 就労について」の採否を含む | I16: R8.9上 | L16: 46261 | M16: 46274 | N16: 1 | O16: 完了 | P16: ★第1稿はオプション項目をほぼ全採用。不採用は問7(7)「この1か月間に会った友人・知人の人数」の1問のみだが、番号を繰り上げているため見える化への入力時に対応が崩れる。ICF分析の参加軸に使えるため採用を推奨（doc23§1-2）。★10/10 村より「高齢者のアンケート発送は全て完了」とのご連絡をいただいた。発送が完了したということは、調査票・依頼状・封筒・宛名ラベル・管理番号がすべて確定して物として出ていったということであり、その前提の工程はいずれも完了している。実績完了日は校了日（令和8年9月9日・doc34）または議事録の発送日（令和8年9月18日）としており、実際の発送日は村にご教示いただいて置き直す。
A17: Ⅰ-13 | B17: Ⅰ ニーズ調査 | C17: Ⅰ-1 調査設計 | D17: 村独自設問の設定 | E17: 仕様書4Ⅰ(2) | F17: 双方 | G17: 設問一覧 | H17: 除雪・在宅医療・成年後見・歯科受診・服薬ほか | I17: R8.9上 | L17: 46267 | M17: 46274 | N17: 1 | O17: 完了 | P17: ★第1稿に村独自14問（ニーズ調査）を確認し、1問ずつ採否を判定（doc23§4）。削除提案は問3(10)「1日に何回食事をとりますか」の1問のみで、他13問は施策・交付金の指標と結びつくため残置を推奨。問7(9)の自由記入3欄は入力コストのため簡素化を提案。在宅調査の問0・問6-1は適切。★10/10 村より「高齢者のアンケート発送は全て完了」とのご連絡をいただいた。発送が完了したということは、調査票・依頼状・封筒・宛名ラベル・管理番号がすべて確定して物として出ていったということであり、その前提の工程はいずれも完了している。実績完了日は校了日（令和8年9月9日・doc34）または議事録の発送日（令和8年9月18日）としており、実際の発送日は村にご教示いただいて置き直す。
A18: Ⅰ-14 | B18: Ⅰ ニーズ調査 | C18: Ⅰ-1 調査設計 | D18: 依頼状（表紙）の作成 | E18: 仕様書4Ⅰ(2) | F18: 受託者 | G18: 依頼状 | H18: 村長名・担当課・問合せ先・基準日・回答期限 | I18: R8.9上 | L18: 46274 | M18: 46274 | N18: 1 | O18: 完了 | P18: ★10/10 村より「高齢者のアンケート発送は全て完了」とのご連絡をいただいた。発送が完了したということは、調査票・依頼状・封筒・宛名ラベル・管理番号がすべて確定して物として出ていったということであり、その前提の工程はいずれも完了している。実績完了日は校了日（令和8年9月9日・doc34）または議事録の発送日（令和8年9月18日）としており、実際の発送日は村にご教示いただいて置き直す。実績開始日の記録がないため完了日と同じ日を置いた。実際の開始日は置き直す。
A19: Ⅰ-15 | B19: Ⅰ ニーズ調査 | C19: Ⅰ-1 調査設計 | D19: 調査票の村協議・確定 | E19: 仕様書4Ⅰ(2) | F19: 双方 | G19: 確定版調査票 | H19: 以降の全工程の起点 | I19: R8.9上 | L19: 46269 | M19: 46274 | N19: 1 | O19: 完了 | P19: ★議事録により9/3に第1稿提出、9/9頃に最終校了と確定。未決事項（手法・オプション項目・独自設問・依頼状名義・部数）は選択肢併記で提出する。★9/4：第2稿を受領しレビュー完了（doc27）。校了までの修正リスト11件を優先度付きで整理。必須3件（在宅の問13の番号・問9の基準月・ニーズ問1(2)①の選択肢順序）。★9/14：校了版の校正紙と対象者リスト・返信用封筒の版下を受領（doc34）。印刷前に決着が必要な事項6件を整理し依頼書に追加。返信用封筒の差出有効期間が回収期限と同日（2026年10月16日）で、期限翌日以降の投函が届かないため延長を要請。回収期限は手書きで10月16日（金）に確定。対象者はニーズ882人・在宅118人（在宅は想定150人を32人下回る）。★9/16：発送予定日（9/18）まで2日。印刷前に決着が必要な6件はいずれも未回答であり、本業務で現時点の最大のリスクである。とくに問4(15)(16)の削除は、見える化システムのR09（社会的役割の低下）が算出できなくなり、R99が10領域→9領域となって第9期との比較が成立しなくなる。印刷後は取り返しがつかない。返信用封筒の差出有効期間（2026年10月16日）も回収期限と同日で、期限翌日以降の投函が届かない。村へ至急の判断を要請している（確認事項 優先度S）。★10/10 村より「高齢者のアンケート発送は全て完了」とのご連絡をいただいた。発送が完了したということは、調査票・依頼状・封筒・宛名ラベル・管理番号がすべて確定して物として出ていったということであり、その前提の工程はいずれも完了している。実績完了日は校了日（令和8年9月9日・doc34）または議事録の発送日（令和8年9月18日）としており、実際の発送日は村にご教示いただいて置き直す。
A20: Ⅰ-16 | B20: Ⅰ ニーズ調査 | C20: Ⅰ-1 調査設計 | D20: ウェブ回答フォームの作成 | E20: 仕様書4Ⅰ(2) | F20: 受託者 | G20: ウェブフォーム | H20: 通信の暗号化・公開期間の設定 | I20: R8.9上 | L20: 46267 | M20: 46283 | N20: 1 | O20: 完了 | P20: ★QRコード併用は議事録で決着。実装方法（Googleフォームの可否）が未決着で、不可の場合は代替の構築期間が必要となり9/9校了に影響する（doc22 A-2）。★10/10 村より「高齢者のアンケート発送は全て完了」とのご連絡をいただいた。発送が完了したということは、調査票・依頼状・封筒・宛名ラベル・管理番号がすべて確定して物として出ていったということであり、その前提の工程はいずれも完了している。実績完了日は校了日（令和8年9月9日・doc34）または議事録の発送日（令和8年9月18日）としており、実際の発送日は村にご教示いただいて置き直す。ウェブ回答フォームは、二次元コードを印字した調査票が発送された以上、公開されていなければ回答できないため完了とした。稼働確認の記録の有無を確かめる。
A21: Ⅰ-17 | B21: Ⅰ ニーズ調査 | C21: Ⅰ-1 調査設計 | D21: 二次元コードの作成・調査票／依頼状への印字 | E21: 仕様書4Ⅰ(2) | F21: 受託者 | G21: 二次元コード | H21: URLの確定が前提 | I21: R8.9上 | L21: 46274 | M21: 46274 | N21: 1 | O21: 完了 | P21: ★10/10 村より「高齢者のアンケート発送は全て完了」とのご連絡をいただいた。発送が完了したということは、調査票・依頼状・封筒・宛名ラベル・管理番号がすべて確定して物として出ていったということであり、その前提の工程はいずれも完了している。実績完了日は校了日（令和8年9月9日・doc34）または議事録の発送日（令和8年9月18日）としており、実際の発送日は村にご教示いただいて置き直す。実績開始日の記録がないため完了日と同じ日を置いた。実際の開始日は置き直す。
A22: Ⅰ-18 | B22: Ⅰ ニーズ調査 | C22: Ⅰ-1 調査設計 | D22: 重複回答の管理方法の設計（管理番号） | E22: 仕様書4Ⅰ(2) | F22: 受託者 | G22: 管理番号設計書 | H22: 紙・ウェブの重複を排除 | I22: R8.9上 | L22: 46261 | M22: 46274 | N22: 1 | O22: 完了 | P22: ★議事録で方針決着。氏名は記載せず管理番号を付与し被保険者番号と紐付ける。具体的な番号形式は村のラベル作成仕様と一体で要調整。★10/10 村より「高齢者のアンケート発送は全て完了」とのご連絡をいただいた。発送が完了したということは、調査票・依頼状・封筒・宛名ラベル・管理番号がすべて確定して物として出ていったということであり、その前提の工程はいずれも完了している。実績完了日は校了日（令和8年9月9日・doc34）または議事録の発送日（令和8年9月18日）としており、実際の発送日は村にご教示いただいて置き直す。
A23: Ⅰ-101 | B23: Ⅰ ニーズ調査 | C23: Ⅰ-1 調査設計 | D23: ウェブ回答フォームの公開・稼働確認・受付停止 | E23: 仕様書4Ⅰ(2) | F23: 受託者 | G23: 稼働確認記録 | H23: 二次元コードの印字前に実機で回答→保存まで通す。回収期限の到来で受付を停止し、以後の紙回答との重複を断つ | I23: R8.9中〜10下 | L23: 46283 | N23: 0.7 | O23: 着手 | P23: ★仕様書Ⅰ(2)は「作成し」としか書いていないが、紙とウェブの併用を成り立たせるには公開・稼働確認・受付停止が要る。二次元コードの印字前に実機で回答→保存まで通す必要があり、印刷の校了（Ⅰ-102）と同時期の律速。Webフォームの実装方法が未決のため着手できていない。★10/10 村より「高齢者のアンケート発送は全て完了」とのご連絡をいただいた。発送が完了したということは、調査票・依頼状・封筒・宛名ラベル・管理番号がすべて確定して物として出ていったということであり、その前提の工程はいずれも完了している。実績完了日は校了日（令和8年9月9日・doc34）または議事録の発送日（令和8年9月18日）としており、実際の発送日は村にご教示いただいて置き直す。公開と稼働は発送により確認できる。受付停止は回収期限（令和8年10月16日）の後に行う。
A24: Ⅰ-19 | B24: Ⅰ ニーズ調査 | C24: Ⅰ-1 調査設計 | D24: 被保険者番号と照合可能な管理番号の設計 | E24: 手引き | F24: 双方 | G24: 管理番号設計書 | H24: 第10期の新規要件。村のラベル作成仕様と一体 | I24: R8.9上 | L24: 46261 | M24: 46274 | N24: 1 | O24: 完了 | P24: ★議事録で方針決着（同上）。見える化システムへの登録を見据えた設計とする。★10/10 村より「高齢者のアンケート発送は全て完了」とのご連絡をいただいた。発送が完了したということは、調査票・依頼状・封筒・宛名ラベル・管理番号がすべて確定して物として出ていったということであり、その前提の工程はいずれも完了している。実績完了日は校了日（令和8年9月9日・doc34）または議事録の発送日（令和8年9月18日）としており、実際の発送日は村にご教示いただいて置き直す。
A25: Ⅰ-20 | B25: Ⅰ ニーズ調査 | C25: Ⅰ-2 印刷・発送準備 | D25: 入稿データの作成 | E25: 仕様書4Ⅰ(3) | F25: 受託者 | G25: 入稿データ | H25: 調査票の確定が前提 | I25: R8.9中 | L25: 46279 | M25: 46283 | N25: 1 | O25: 完了 | P25: ★9/9頃の校了・印刷依頼が目標（議事録）。9/3の第1稿提出→修正・確認を経て確定する。★10/10 村より「高齢者のアンケート発送は全て完了」とのご連絡をいただいた。発送が完了したということは、調査票・依頼状・封筒・宛名ラベル・管理番号がすべて確定して物として出ていったということであり、その前提の工程はいずれも完了している。実績完了日は校了日（令和8年9月9日・doc34）または議事録の発送日（令和8年9月18日）としており、実際の発送日は村にご教示いただいて置き直す。
A26: Ⅰ-102 | B26: Ⅰ ニーズ調査 | C26: Ⅰ-2 印刷・発送準備 | D26: 印刷の校正・校了 | E26: 仕様書4Ⅰ(3) | F26: 双方 | G26: 校正紙・校了の記録 | H26: 仕様書(3)の「印刷」には校了の判断が含まれる。印刷後は取り返しがつかない | I26: R8.9中 | L26: 46274 | M26: 46274 | N26: 1 | O26: 完了 | P26: ★0909校正版の校正紙を受領し、印刷前に決着が必要な6件を整理した（doc34）。9/16時点で6件とも未回答で、本業務で現時点の最大のリスク。とくに問4(15)(16)の削除はR09（社会的役割の低下）が算出できなくなり、R99が10領域→9領域となって第9期との比較が成立しない。返信用封筒の差出有効期間が回収期限と同日である点も未決。★10/10 村より「高齢者のアンケート発送は全て完了」とのご連絡をいただいた。発送が完了したということは、調査票・依頼状・封筒・宛名ラベル・管理番号がすべて確定して物として出ていったということであり、その前提の工程はいずれも完了している。実績完了日は校了日（令和8年9月9日・doc34）または議事録の発送日（令和8年9月18日）としており、実際の発送日は村にご教示いただいて置き直す。
A27: Ⅰ-103 | B27: Ⅰ ニーズ調査 | C27: Ⅰ-2 印刷・発送準備 | D27: 印刷部数の確定（予備を含む） | E27: 仕様書4Ⅰ(3) | F27: 双方 | G27: 部数内訳 | H27: 対象者はニーズ882人・在宅118人。仕様書の「約850人／約150人」との差を部数に反映 | I27: R8.9中 | L27: 46279 | M27: 46283 | N27: 1 | O27: 完了 | P27: ★対象者リストによりニーズ882人・在宅118人と判明。★9/24：村の回答により在宅118人で決着（仕様書の「約150人」との差異は解消）。残るのは予備を含めた部数の確定と、回収70〜80件を前提とした集計設計（要介護度3区分を2区分に束ねるか）の判断。★10/10 村より「高齢者のアンケート発送は全て完了」とのご連絡をいただいた。発送が完了したということは、調査票・依頼状・封筒・宛名ラベル・管理番号がすべて確定して物として出ていったということであり、その前提の工程はいずれも完了している。実績完了日は校了日（令和8年9月9日・doc34）または議事録の発送日（令和8年9月18日）としており、実際の発送日は村にご教示いただいて置き直す。
A28: Ⅰ-21 | B28: Ⅰ ニーズ調査 | C28: Ⅰ-2 印刷・発送準備 | D28: 調査票の印刷（ニーズ調査 A4約12頁・黒1色） | E28: 仕様書4Ⅰ(3) | F28: 受託者 | G28: 印刷物 約850部 | H28: 頁数は村と要協議 | I28: R8.9中 | L28: 46283 | M28: 46283 | N28: 1 | O28: 完了 | P28: ★10/10 村より「高齢者のアンケート発送は全て完了」とのご連絡をいただいた。発送が完了したということは、調査票・依頼状・封筒・宛名ラベル・管理番号がすべて確定して物として出ていったということであり、その前提の工程はいずれも完了している。実績完了日は校了日（令和8年9月9日・doc34）または議事録の発送日（令和8年9月18日）としており、実際の発送日は村にご教示いただいて置き直す。実績開始日の記録がないため完了日と同じ日を置いた。実際の開始日は置き直す。
A29: Ⅰ-22 | B29: Ⅰ ニーズ調査 | C29: Ⅰ-2 印刷・発送準備 | D29: 調査票の印刷（在宅調査 A4約8頁・黒1色） | E29: 仕様書4Ⅰ(3) | F29: 受託者 | G29: 印刷物 約150部 | I29: R8.9中 | L29: 46283 | M29: 46283 | N29: 1 | O29: 完了 | P29: ★10/10 村より「高齢者のアンケート発送は全て完了」とのご連絡をいただいた。発送が完了したということは、調査票・依頼状・封筒・宛名ラベル・管理番号がすべて確定して物として出ていったということであり、その前提の工程はいずれも完了している。実績完了日は校了日（令和8年9月9日・doc34）または議事録の発送日（令和8年9月18日）としており、実際の発送日は村にご教示いただいて置き直す。実績開始日の記録がないため完了日と同じ日を置いた。実際の開始日は置き直す。
A30: Ⅰ-23 | B30: Ⅰ ニーズ調査 | C30: Ⅰ-2 印刷・発送準備 | D30: 返信用封筒の印刷 | E30: 仕様書4Ⅰ(3) | F30: 受託者 | G30: 返信用封筒 | I30: R8.9中 | L30: 46274 | M30: 46283 | N30: 1 | O30: 完了 | P30: ★版下を受領済（doc34）。★9/24：配布用封筒は村が用意し費用は村側で請求処理することが決着したため、受託者が印刷するのは返信用（回収用）のみで確定（仕様書4Ⅰ(3)の「封筒（配布用・回収用）」との差異は解消）。差出有効期間が回収期限と同日（2026年10月16日）である点は未決で、期限翌日以降に投函された回答が届かない。★10/10 村より「高齢者のアンケート発送は全て完了」とのご連絡をいただいた。発送が完了したということは、調査票・依頼状・封筒・宛名ラベル・管理番号がすべて確定して物として出ていったということであり、その前提の工程はいずれも完了している。実績完了日は校了日（令和8年9月9日・doc34）または議事録の発送日（令和8年9月18日）としており、実際の発送日は村にご教示いただいて置き直す。
A31: Ⅰ-24 | B31: Ⅰ ニーズ調査 | C31: Ⅰ-2 印刷・発送準備 | D31: 調査対象者の抽出 | E31: 仕様書4Ⅰ(1) | F31: 北塩原村 | G31: 対象者リスト | H31: ニーズ約850人／在宅約150人 | I31: R8.9中 | L31: 46266 | M31: 46293 | N31: 1 | O31: 完了 | P31: ★村が抽出。2026/09/28に対象者名簿2件を受領した。ニーズ調査882人（リスト805＋引き抜き77）、在宅介護実態調査118人（リスト66＋引き抜き52）。個人情報を含むため原本はリポジトリに複製せず、属性の集計値のみを保存（doc16§5-2・§6に従い、年齢・性別・行政区・要介護度のみを読み、該当数10未満は伏せた）。
A32: Ⅰ-25 | B32: Ⅰ ニーズ調査 | C32: Ⅰ-2 印刷・発送準備 | D32: 宛名ラベルシールの作成・提供 | E32: 仕様書4Ⅰ(1) | F32: 北塩原村 | G32: 宛名ラベルシール | H32: 被保険者番号との照合可能な形式 | I32: R8.9中 | L32: 46279 | M32: 46283 | N32: 1 | O32: 完了 | P32: ★名簿の管理番号はニーズ調査が数字のみ、在宅介護実態調査が英字＋数字であることを確認した。調査票の印字見本がどちらも「1」であったことから形式の食い違いを疑い優先度Sで起票したが、印字見本は見本であり実物には名簿の形式のまま管理番号が入ることを村にご確認いただき解決した（doc43§2-4）。管理番号が欠損した場合は氏名でも突合できる。集計プログラムでは管理番号を数値ではなく文字列として扱う（在宅の英字＋数字が壊れるため）。★10/10 村より「高齢者のアンケート発送は全て完了」とのご連絡をいただいた。発送が完了したということは、調査票・依頼状・封筒・宛名ラベル・管理番号がすべて確定して物として出ていったということであり、その前提の工程はいずれも完了している。実績完了日は校了日（令和8年9月9日・doc34）または議事録の発送日（令和8年9月18日）としており、実際の発送日は村にご教示いただいて置き直す。
A33: Ⅰ-26 | B33: Ⅰ ニーズ調査 | C33: Ⅰ-2 印刷・発送準備 | D33: 配布用封筒の提供 | E33: 仕様書4Ⅰ(4) | F33: 北塩原村 | G33: 配布用封筒 | I33: R8.9中 | L33: 46266 | M33: 46283 | N33: 1 | O33: 完了 | P33: ★キックオフ会議で村が用意すると決着。★9/24：費用は村側で請求処理することを確認。提供期限は9/14（9/11への前倒しを要請中）。★10/10 村より「高齢者のアンケート発送は全て完了」とのご連絡をいただいた。発送が完了したということは、調査票・依頼状・封筒・宛名ラベル・管理番号がすべて確定して物として出ていったということであり、その前提の工程はいずれも完了している。実績完了日は校了日（令和8年9月9日・doc34）または議事録の発送日（令和8年9月18日）としており、実際の発送日は村にご教示いただいて置き直す。
A34: Ⅰ-27 | B34: Ⅰ ニーズ調査 | C34: Ⅰ-2 印刷・発送準備 | D34: 宛名ラベルの貼付 | E34: 仕様書4Ⅰ(4) | F34: 受託者 | G34: ― | H34: 村からの提供が前提 | I34: R8.9中 | L34: 46283 | M34: 46283 | N34: 1 | O34: 完了 | P34: ★10/10 村より「高齢者のアンケート発送は全て完了」とのご連絡をいただいた。発送が完了したということは、調査票・依頼状・封筒・宛名ラベル・管理番号がすべて確定して物として出ていったということであり、その前提の工程はいずれも完了している。実績完了日は校了日（令和8年9月9日・doc34）または議事録の発送日（令和8年9月18日）としており、実際の発送日は村にご教示いただいて置き直す。実績開始日の記録がないため完了日と同じ日を置いた。実際の開始日は置き直す。
A35: Ⅰ-28 | B35: Ⅰ ニーズ調査 | C35: Ⅰ-2 印刷・発送準備 | D35: 封入・封緘 | E35: 仕様書4Ⅰ(4) | F35: 受託者 | G35: 発送物 | I35: R8.9中 | L35: 46283 | M35: 46283 | N35: 1 | O35: 完了 | P35: ★10/10 村より「高齢者のアンケート発送は全て完了」とのご連絡をいただいた。発送が完了したということは、調査票・依頼状・封筒・宛名ラベル・管理番号がすべて確定して物として出ていったということであり、その前提の工程はいずれも完了している。実績完了日は校了日（令和8年9月9日・doc34）または議事録の発送日（令和8年9月18日）としており、実際の発送日は村にご教示いただいて置き直す。実績開始日の記録がないため完了日と同じ日を置いた。実際の開始日は置き直す。
A36: Ⅰ-29 | B36: Ⅰ ニーズ調査 | C36: Ⅰ-3 発送・回収 | D36: 発送（郵送費は受託者負担） | E36: 仕様書4Ⅰ(4) | F36: 受託者 | G36: 発送完了報告 | H36: 5連休（9/19〜9/23）の影響を考慮 | I36: R8.9下 | L36: 46283 | M36: 46283 | N36: 1 | O36: 完了 | P36: ★10/10 村より「高齢者のアンケート発送は全て完了」とのご連絡をいただいた。発送が完了したということは、調査票・依頼状・封筒・宛名ラベル・管理番号がすべて確定して物として出ていったということであり、その前提の工程はいずれも完了している。実績完了日は校了日（令和8年9月9日・doc34）または議事録の発送日（令和8年9月18日）としており、実際の発送日は村にご教示いただいて置き直す。対象はニーズ調査882人・在宅介護実態調査118人である。9月18日は金曜で翌日から5連休（敬老の日・国民の休日・秋分の日）であったため、配達が連休明けにずれ込んだ可能性がある（doc22）。実績開始日の記録がないため完了日と同じ日を置いた。実際の開始日は置き直す。
A37: Ⅰ-30 | B37: Ⅰ ニーズ調査 | C37: Ⅰ-3 発送・回収 | D37: 回収状況の管理 | E37: 仕様書4Ⅰ(4) | F37: 双方 | G37: 回収状況表 | H37: ★議事録により、村で100件程度集まるごとに随時受託者へ小分け送付する運用と確定 | I37: R8.9下〜10 | L37: 46283 | N37: 0.4 | O37: 着手 | P37: ★小分け送付の運用に合わせ、村側の送付単位と受託者側の入力進捗を突き合わせる管理表が必要。★10/10 村より「今集計分析を行なっています」とのご連絡をいただき着手を確認した。実績開始日はご連絡をいただいた日としており、実際の着手日は置き直す。回収件数と回収率は村からのご連絡を待って記録する。
A38: Ⅰ-31 | B38: Ⅰ ニーズ調査 | C38: Ⅰ-3 発送・回収 | D38: 督促（リマインド）の実施 | E38: 確認 | F38: 受託者 | G38: 督促文書 | H38: 第9期の在宅調査回収率45.8%を踏まえ実施要否を判断 | I38: R8.10上 | N38: 0 | O38: 未着手
A39: Ⅰ-32 | B39: Ⅰ ニーズ調査 | C39: Ⅰ-3 発送・回収 | D39: 回収期限の管理・締切 | E39: 仕様書4Ⅰ(4) | F39: 受託者 | G39: ― | I39: R8.10 | L39: 46283 | N39: 0.5 | O39: 着手 | P39: ★10/10 村より「今集計分析を行なっています」とのご連絡をいただき着手を確認した。実績開始日はご連絡をいただいた日としており、実際の着手日は置き直す。回収期限は令和8年10月16日（金）である。
A40: Ⅰ-33 | B40: Ⅰ ニーズ調査 | C40: Ⅰ-3 発送・回収 | D40: 開封確認 | E40: 仕様書4Ⅰ(4) | F40: 受託者 | G40: ― | I40: R8.10 | L40: 46305 | N40: 0.4 | O40: 着手 | P40: ★10/10 村より「今集計分析を行なっています」とのご連絡をいただき着手を確認した。実績開始日はご連絡をいただいた日としており、実際の着手日は置き直す。
A41: Ⅰ-94 | B41: Ⅰ ニーズ調査 | C41: Ⅰ-3 発送・回収 | D41: 調査票の受渡し記録の作成・運用 | E41: 確認 | F41: 双方 | G41: 受渡し記録 | H41: ★小分け送付の運用に対応。日付・数量・受渡者・受領者を記録。doc16に追記 | I41: R8.9下〜11 | L41: 46305 | N41: 0.3 | O41: 着手 | P41: ★議事録により村が100件程度ごとに随時送付する運用と確定。個人情報の授受が複数回に分かれるため受渡し記録の様式を用意し doc16 に追記する。★10/10 村より「今集計分析を行なっています」とのご連絡をいただき着手を確認した。実績開始日はご連絡をいただいた日としており、実際の着手日は置き直す。★村で100件程度集まるごとに随時受託者へ小分け送付する運用であり（doc22）、受渡しはすでに起きている。doc74で作ったのは従事者名簿・誓約書・持出簿・廃棄記録簿の4様式で、受渡し記録簿は作っていない。受領日・件数・媒体・引渡者・受領者を記録する様式を作る必要がある。
A42: Ⅰ-34 | B42: Ⅰ ニーズ調査 | C42: Ⅰ-4 データ入力 | D42: 用紙回答のデータ入力 | E42: 仕様書4Ⅰ(5) | F42: 受託者 | G42: 入力データ | H42: 厚労省提示の集計ファイル様式 | I42: R8.10 | L42: 46268 | N42: 0.4 | O42: 着手 | P42: ★doc25§6-2で入力上の留意点6件を確定（複数回答は選択肢ごとに0-1の横持ち／自由記述は原文保持／小分け送付に対応した受付日・ロット番号の記録 ほか）。入力体制は村と要協議（K-93）。★10/10 村より「今集計分析を行なっています」とのご連絡をいただき着手を確認した。実績開始日はご連絡をいただいた日としており、実際の着手日は置き直す。
A43: Ⅰ-35 | B43: Ⅰ ニーズ調査 | C43: Ⅰ-4 データ入力 | D43: ウェブ回答データの取込 | E43: 仕様書4Ⅰ(5) | F43: 受託者 | G43: 入力データ | I43: R8.10 | L43: 46268 | N43: 0.4 | O43: 着手 | P43: ★doc25§6-1でデータレイアウトを確定（管理番号・回答方法・受付日・地区・性別・年齢・認定状況・認定日＋各設問＋派生変数）。紙とWebを同一レイアウトに揃える。Webは必須入力により無回答率が構造的に異なるため回答方法別の集計を必ず1回行う。★9/28：管理番号を文字列として扱うことを明記（ニーズは数字のみ、在宅は英字＋数字のため）。★9/28（第2次）：大雪・金ケ崎の外部レビューで指摘された欠陥の型を踏まえ、基本方針を8→11項目に拡張した（doc44§6）。方針9 分母を設問ごとの有効回答に統一し回収票の総数で割らない、方針10 同じ指標を複数の設問から作らず主・補を明示する、方針11 表ごとに分母とn数を書き時点の異なる値を足さない。クロス表20件すべてに分母の欄を設け、主指標・補足指標の整理5件を新設した（最も注意を要するのは社会参加・通いの場への参加で、村の実績とアンケートで母集団が違う）。集計仕様書の自己点検8件を新設（verify_shukei.py）。★10/10 村より「今集計分析を行なっています」とのご連絡をいただき着手を確認した。実績開始日はご連絡をいただいた日としており、実際の着手日は置き直す。
A44: Ⅰ-36 | B44: Ⅰ ニーズ調査 | C44: Ⅰ-4 データ入力 | D44: 重複回答の排除 | E44: 仕様書4Ⅰ(2) | F44: 受託者 | G44: ― | H44: 管理番号で管理 | I44: R8.10 | L44: 46305 | N44: 0.9 | O44: 着手 | P44: ★10/10 村より「今集計分析を行なっています」とのご連絡をいただき着手を確認した。実績開始日はご連絡をいただいた日としており、実際の着手日は置き直す。管理番号による突合で排除する（Ⅰ-18・Ⅰ-19で設計済み）。★10/10：手順を定め、scripts/shukei_dedupe.py として組んだ。集計仕様書に §8 重複回答の排除 を設け、xlsx の「精度管理」シートにも載せた。要点は「一意に定まること」である。同じ管理番号で2件あったとき、どちらを採るかが実行のたびに変われば回収数も構成比も変わるため、採否の順序を5段で定め、最後の段を回答の中身で決めた。読み込んだ順序を入れ替えても結果が変わらないことを自己試験で確かめている（28件すべて通過）。重複と不備の型を7件（D1 紙が2件／D2 紙とウェブ／D3 ウェブが2件／D4 管理番号が空／D5 形式違い／D6 名簿にない／D7 名簿の番号が正規化で重なる）に整理した。ウェブの管理番号は回答者が手で入れるため、全角・小文字・ハイフン・先頭の0を正規化してから突き合わせる。この正規化は論理チェックのL09と同じ規則にそろえた（規則が分かれると、点検は「重複なし」と言い、排除は1件落とす）。管理番号が空・形式違い・名簿にない回答は捨てず、単純集計には入れ、属性のクロスには入れない件数を記録する形とした。集計本体（shukei_run.py）が必ず排除を通るようにし、点検34でそれを固定した。ダミーデータにわざと重複・不備9件を入れ、管理番号の形式を名簿のとおり（ニーズ＝数字のみ／在宅＝英字＋数字）に直し、回答方法と受付日の列を加えた。★残るのは、2つの名簿に重複する2人の扱い（優先度S・村のご確認）と、実データでの通しである。
A45: Ⅰ-37 | B45: Ⅰ ニーズ調査 | C45: Ⅰ-4 データ入力 | D45: 要介護認定データの受領 | E45: 仕様書4Ⅰ(5) | F45: 北塩原村 | G45: 認定データ | H45: 手法Ⅰ・Ⅱの場合。目的外利用の手続きに留意 | I45: R8.10 | L45: 46293 | N45: 0.3 | O45: 確認中 | P45: ★在宅介護実態調査の対象者118人分については、名簿に要介護度・受給申請日・初回認定日が含まれていた。要介護1が49人・要介護2が30人・要介護3が18人・要介護4が14人・要介護5が7人で、要支援の方は含まれていない。一方ニーズ調査の対象者882人分には要介護度の列がなく、資料3の3-3・3-4・3-6（認定状況と生活機能を重ねる分析）は作成できない。引き続き提供を要請する。
A46: Ⅰ-38 | B46: Ⅰ ニーズ調査 | C46: Ⅰ-4 データ入力 | D46: 認定データとの関連付け（自動プログラム） | E46: 仕様書4Ⅰ(5) | F46: 受託者 | G46: 関連付け済データ | H46: 手法Ⅲでは自動集計ソフトなし | I46: R8.10 | N46: 0 | O46: 未着手
A47: Ⅰ-104 | B47: Ⅰ ニーズ調査 | C47: Ⅰ-4 データ入力 | D47: 入力データの精度管理（論理チェック・ベリファイ） | E47: 仕様書4Ⅰ(5) | F47: 受託者 | G47: チェック結果 | H47: 仕様書(5)の条項名は「入力管理」。単一回答の複数選択・排他条件・分岐の不整合・数値の範囲外を点検する | I47: R8.10〜11 | L47: 46305 | N47: 0.8 | O47: 着手 | P47: 仕様書Ⅰ(5)の条項名は「入力管理」であり、入力そのものだけでなく入力後の精度の確認を含む。集計仕様書（doc25）で派生変数と排他条件を定義済みのため、その定義を論理チェックの規則に転用する。★10/10 村より「今集計分析を行なっています」とのご連絡をいただき着手を確認した。実績開始日はご連絡をいただいた日としており、実際の着手日は置き直す。★10/10：論理チェック12項目（L01〜L12）とコードブックの点検5項目（C01〜C05）を定め、scripts/shukei_check.py として組んだ。集計仕様書に §7 入力データの精度管理 を設け、xlsx にも「精度管理」シートを加えた。表は shukei_check.py から生成しているため、村にお示しした内容と現に走る点検が食い違わない。ベリファイは全件を二重入力するもの（区分が必須の設問・派生変数に使う設問）と10パーセントを抽出するもの（オプション・村独自）とウェブ回答（対象外）に分けた。層の判定（資料3の3-3・3-4・3-6）に効くものを全件とする考え方である。ダミーデータ（ニーズ430件・在宅96件）で動かし、結果が出ることを確かめた。点検そのものの自己試験（--自己試験）を組み、欠陥を入れると19件すべてが鳴ること・正しく答えた1件では何も鳴らないことを確かめた。verify_shukei に点検17〜25を加えた（25件すべて適合）。★残るのは次の2点である。①校了版（令和8年9月9日）の調査票Wordを受領してコードブックを作り直すこと。現在のコードブックは9月4日版から作られており、版が違うと鳴るべきものが鳴らない。shukei_check.py は版を確かめて止まる仕組みとした（--暫定 で続行可）。9月4日版の読み取りの不備も7件残っている（C01 1件・C02 5件・C03 1件）。社内の照会として起票した。②実データでの通し。入力データの受領を待つ。
A48: Ⅰ-39 | B48: Ⅰ ニーズ調査 | C48: Ⅰ-5 集計・分析 | D48: 単純集計 | E48: 仕様書4Ⅰ(6) | F48: 受託者 | G48: 集計表 | I48: R8.10〜11 | L48: 46268 | N48: 0.7 | O48: 着手 | P48: ★doc24でアンケート調査報告書の骨子を確定（全7章＋資料編・約118頁）。第Ⅰ部 単純集計編の掲載方式（全体／地区別／年齢階級別／前回比較／コメントの5点セット）と対象設問を確定。集計仕様書の作成は調査票の校了（9/9）後すぐに着手する。★9/8：集計プログラムを作成し、ダミーデータ430件で単純集計まで通した（doc31／output/10）。回答データが届いたらCSVのパスを指定するだけで集計が出る。
A49: Ⅰ-40 | B49: Ⅰ ニーズ調査 | C49: Ⅰ-5 集計・分析 | D49: 基本属性別クロス集計（地区・性別・年齢） | E49: 仕様書4Ⅰ(6) | F49: 受託者 | G49: 集計表 | I49: R8.10〜11 | L49: 46268 | N49: 0.7 | O49: 着手 | P49: ★doc24で全設問を地区別（北山・大塩・桧原・裏磐梯）・年齢階級別（65〜74／75〜84／85歳以上）で集計する方針を確定。移動手段・外出を控える理由・除雪は地区差が大きいと想定され施策の地区別展開の根拠になる。★9/8：地区・年齢階級・性別・認定状況・生活機能4層の5軸で軸別集計を実装（doc31）。
A50: Ⅰ-41 | B50: Ⅰ ニーズ調査 | C50: Ⅰ-5 集計・分析 | D50: 時系列比較（第8期・第9期との対比） | E50: 仕様書4Ⅰ(6) | F50: 受託者 | G50: 比較表 | H50: 村と協議のうえ範囲を決定 | I50: R8.10〜11 | L50: 46268 | N50: 0.2 | O50: 確認中 | P50: ★令和4年8月版と令和7年8月版で設問文・選択肢が変わった設問は単純比較できない。doc05の逐条突合に基づき比較可能な設問を抽出済。対象範囲は村と協議（doc24 K-86）。
A51: Ⅰ-42 | B51: Ⅰ ニーズ調査 | C51: Ⅰ-5 集計・分析 | D51: 設問間クロス集計 | E51: 仕様書4Ⅰ(6) | F51: 受託者 | G51: 集計表 | H51: 村と協議のうえ設計 | I51: R8.10〜11 | L51: 46268 | N51: 0.65 | O51: 着手 | P51: ★doc25／output/07_集計仕様書.xlsx でクロス表20件を定義（うち★10件が分析編の中核）。X-01疾病数×リスク該当領域数、X-02認定状況×リスク、X-03生活機能4層×参加意向、X-04支え合いの受領×提供、X-15施設入所検討×村内施設、X-16要介護度×就労継続。X-02とX-03は村からの認定データ（K-87）が前提。★9/8：20表のうち軸の定義が確定している9表を実装（X-01・X-02・X-04・X-05・X-06・X-12・X-15・X-16・X-17）。残りは自由記述の分類と複数回答どうしのクロスで、掲載の形を決めてから実装する。★10/7：クロス表を20表から22表に。派生変数Z01（入所の必要性の3区分）・Z02（村内施設の需要の2区分）を定義し、必要利用定員総数の設定（素案5-4(13)）に用いるX-21・X-22を加えた。点検のクロス表の件数のじか書き（20表）を数え上げに改め、表を足しても通るようにした。doc24・doc25の件数も合わせて改めた。
A52: Ⅰ-43 | B52: Ⅰ ニーズ調査 | C52: Ⅰ-5 集計・分析 | D52: リスク判定11種の算出 | E52: 手引き | F52: 受託者 | G52: リスク判定結果 | H52: 運動器・転倒・閉じこもり・低栄養・口腔・認知・うつ・IADL等 | I52: R8.10〜11 | L52: 46268 | N52: 0.7 | O52: 着手 | P52: ★doc24§4-3で判定に用いる設問を確定（運動器・転倒・閉じこもり・低栄養・口腔・認知・IADL・うつ）。判定基準は見える化システムの算出方法に合わせる（独自基準を作ると全国・県との比較ができなくなるため）。★9/8：R01〜R10・R99・D01・P01・S01/S02/S99・L01・B01・U01の20変数を実装（scripts/shukei_derive.py）。判定基準は1か所にまとめてあり、村から算出方法の提供を受けたらそこだけ直せば全集計が連動する。手引きに明記があるのは低栄養のBMI 18.5以下のみで、他9件は暫定。
A53: Ⅰ-44 | B53: Ⅰ ニーズ調査 | C53: Ⅰ-5 集計・分析 | D53: 自由記述の整理 | E53: 仕様書4Ⅰ(6) | F53: 受託者 | G53: 自由意見一覧 | I53: R8.10〜11 | L53: 46268 | N53: 0.1 | O53: 着手 | P53: ★doc24§9で対象設問を確定（問3(9)利用先・問7(9)利用先・問11その他・問4(17)(18)趣味生きがい ほか）。人口2,300人規模では記述から個人が推定され得るため匿名化の方針を村と協議（doc24 K-89）。
A54: Ⅰ-45 | B54: Ⅰ ニーズ調査 | C54: Ⅰ-5 集計・分析 | D54: 在宅調査の要介護度別・介護者就労状況別分析 | E54: 仕様書4Ⅰ(6) | F54: 受託者 | G54: 分析結果 | I54: R8.10〜11 | L54: 46268 | N54: 0.65 | O54: 着手 | P54: ★doc24§5-2で仕様書4Ⅰ(6)が求めるクロスの設計を確定。軸1＝要介護度3区分、軸2＝主な介護者の勤務形態3区分。中核は「要介護度×就労継続の見通し」。村独自の問6-1（村内に施設があれば）と問6のクロスで施設の潜在需要を測る設計も確定。★9/8：X-15（施設入所の検討状況×村内施設があれば）とX-16（要介護度×就労継続の見通し）を実装し、ダミーデータで出力を確認（doc31）。
A55: Ⅰ-46 | B55: Ⅰ ニーズ調査 | C55: Ⅰ-5 集計・分析 | D55: 見える化システム登録用データの作成 | E55: 手引き | F55: 受託者 | G55: 登録用データ | H55: 標準様式の項目順に並べ替えが必要 | I55: R8.11 | L55: 46268 | N55: 0.3 | O55: 着手 | P55: ★doc25§6-3で方針を確定。村独自設問14問を除外し標準様式の設問順に並べ替えた別ファイルとして作成する。並べ替え表は集計プログラムに組み込む。登録作業の分担は村と要協議（K-94）。
A56: Ⅰ-95 | B56: Ⅰ ニーズ調査 | C56: Ⅰ-5 集計・分析 | D56: ICFの構成要素に基づくクロス分析の設計 | E56: 確認 | F56: 受託者 | G56: 分析設計書 | H56: ★議事録で新規要件。単純なリスク分析ではなくICFの健康度指標で「元気な高齢者」×「地域のニーズ」を分析。調査票設計段階で軸の確保が必要 | I56: R8.9上 | L56: 46268 | N56: 0.8 | O56: 着手 | P56: ★doc23§3で設計完了。ICF5領域と標準設問の対応表を作成し、5領域すべてが標準の必須＋オプション項目で埋まること＝分析のための独自設問は不要であることを確定。分析案は3案（B:疾病×生活機能の2軸マトリクス〈主軸〉／A:生活機能ベースの4層区分〈施策設計用〉／C:5領域レーダー〈委員会資料〉）。推奨対応は標準オプション問7(7)の採用1件のみ。★9/3：手引き（令和7年8月版）に「ICFの構成要素間の相互作用の図」による公式の対応表（図表9）が掲載されていることを確認し、doc23の当方作成表を訂正。ICFによる整理は国が公式に推奨する枠組みであることが確定。実装は回収データの受領後。
A57: Ⅰ-47 | B57: Ⅰ ニーズ調査 | C57: Ⅰ-6 報告書 | D57: 設問ごとのグラフ作成 | E57: 仕様書4Ⅰ(7) | F57: 受託者 | G57: グラフ | I57: R8.11 | N57: 0 | O57: 未着手 | P57: ★9/25：案Bの採用により1頁2設問を維持できることとなった（案Aでは1頁3設問に詰める必要があった）。ただし第9期は1頁0.9設問＝実質1設問1頁であり約1.9倍の密度になる。計画書と同じく明度差・線種・ハッチングで識別し、凡例を図の近くに置く。集計結果の確定待ち。
A58: Ⅰ-48 | B58: Ⅰ ニーズ調査 | C58: Ⅰ-6 報告書 | D58: 調査結果報告書の執筆・レイアウト | E58: 仕様書4Ⅰ(7) | F58: 受託者 | G58: 報告書案 | H58: A4両面約100頁 | I58: R8.11 | L58: 46268 | N58: 0.3 | O58: 着手 | P58: ★doc24として骨子案を作成（2部構成・第Ⅰ部 単純集計編／第Ⅱ部 ICF分析編）。★9/24：村の指示により仕様書どおり約100頁に統一することが決着（当初案118頁）。★9/25：圧縮の当て方を案Bで確定。調査票2種・単純集計表・自由記述の全文を電子媒体に移し資料編を25→6頁とし、浮いた頁を集計編に戻して第3章42頁・第4章21頁（計63頁）とした。1頁1.7設問で当初案118頁と同じ密度を100頁の枠内に収めた。第Ⅱ部25頁は計画の施策の根拠のため維持。設問数は削らない（仕様書4Ⅰ(7)が設問ごとのグラフを求めるため）。第9期は1頁0.9設問＝実質1設問1頁であり、採用案でも密度は約1.9倍になるためモノクロ印刷での可読性に注意を要する。本文の執筆は調査の回収・集計待ち。
A59: Ⅰ-49 | B59: Ⅰ ニーズ調査 | C59: Ⅰ-6 報告書 | D59: 報告書の村確認・修正 | E59: 仕様書4Ⅰ(7) | F59: 双方 | G59: 報告書（確定） | I59: R8.11〜12 | N59: 0 | O59: 未着手
A60: Ⅱ-50 | B60: Ⅱ 計画策定 | C60: Ⅱ-1 基礎調査 | D60: 制度改正動向の資料収集・整理 | E60: 仕様書4Ⅱ(1) | F60: 受託者 | G60: 論点整理メモ | I60: R8.9〜11 | L60: 46259 | N60: 0.98 | O60: 着手 | P60: 素案1-8を法律（令和8年法律第51号）と政令・告示等の2本立てに整理。82.65万円・調整交付金の7区分化・令和8年度報酬改定・協力医療機関ほか15事項を掲載。点検41で機械的に確認している。★10/8：第136回社会保障審議会介護保険部会（令和8年9月18日）の資料1〜6および参考資料の提供を受け、原典により確定させた（doc71）。保留していた3件のうち2件が確定した。①補足給付の区分の細分化は令和9年度の当初からの施行である（資料2）。②調整交付金の一定の取組による減額は、年齢区分の精緻化により交付額が増加する保険者について、主要3事業のいずれかの未実施、または1人あたり給付費の外れ値（平均値＋2×標準偏差）に該当した保険者の帳票点検の実施率等が前年度の下半期を下回った場合に、増加額の5%を減額するものである（資料5）。③特定地域サービス・特定地域居宅サービス等事業は本部会の資料に含まれておらず、5-12に残置した。あわせて1-8に「5 引き続き検討することとされた事項」を新設し、原典（資料2）の9事項を影響が及び得る本計画の箇所と対にして掲げた。「一定以上所得」の判断基準は令和8年度中に結論を得るとされており、前のセッションで取り下げた「令和9年度中」が誤りであったことも原典で確かめた。
A61: Ⅱ-51 | B61: Ⅱ 計画策定 | C61: Ⅱ-1 基礎調査 | D61: 第10期国の基本指針の確認・反映 | E61: 仕様書4Ⅱ(1) | F61: 受託者 | G61: 基本指針対応表 | H61: 令和8年内告示予定。遅延時は暫定版で作業 | I61: R8.11〜 | L61: 46293 | N61: 0.85 | O61: 着手 | P61: 別表「確認すべき指標・状況」11事項への対応表を素案 資6として作成（doc49）。一部対応5事項は理由と代替を明記。基本指針そのものは告示前のため案による。★10/2：別表の事項十（医療介護連携に関する加算の算定状況）を、受領済みの見える化 δ1-c に算定率と偏差値が収録されていたため対応に改めた。一部対応は5事項から4事項。事項三（死亡場所別の死亡数）も在宅死亡者数の偏差値を掲げたが、単位の確認が前提。★10/4：事項七・八について見える化に使える系列がないかを当たった。入所率・稼働率・従事者数の系列はない（人員体制は地域包括支援センターのものに限られる）。一方、要介護者等である入居者の状況は特定施設入居者生活介護の給付実績により把握できることが分かり、事項八の対応できていない指標を「施設数・戸数・定員」に絞った。★10/6：資6の一部対応4事項（三・六・七・八）を、受領済みのデータで対応に改められるか確かめた。対応に改められたものはないが、空白を4つとも絞り込めた。事項七は「入所率、入退所の状況、従事者数」から「入退所の状況、従事者数」に。施設・事業所数は見える化のサービス提供事業所数（28サービス・平成24〜令和6年度）で把握でき、入所率・稼働率は定員と受給者数から算定できている（認知症対応型共同生活介護92.6%・通所介護77.8%）。事項八は「施設数・戸数・定員」から「指定を受けない有料老人ホーム・サービス付き高齢者向け住宅の有無」に。指定を受けた特定施設入居者生活介護は平成24年度から令和6年度まで村内0であることを確かめた。残るのは県の所管（老人福祉法29条の届出・高齢者住まい法の登録）であり、県への照会に切り替えた。事項三は出典の表記に住民基本台帳人口が含まれることから人口あたりの率と判明し、確認先が村ではなく国のオープンデータの定義であることを特定した。事項六は第10期調査のB票 問6・問10で把握し、集計の定義は集計仕様書のX-16・X-17に済んでいる。事項七・八について確認事項を2件起票した。★10/12：資6で「一部」とした事項三・七・八について、村・県への照会の文面を整えた（doc85）。照会票は文の単位で170字までしか出ないため、6件とも1文目をお願いに差し替えた。点検69（「一部」の事項に追いかける先があること）を新設した。
A62: Ⅱ-52 | B62: Ⅱ 計画策定 | C62: Ⅱ-1 基礎調査 | D62: 前提条件と基本的課題の明確化 | E62: 仕様書4Ⅱ(1) | F62: 受託者 | G62: 課題整理メモ | I62: R8.11 | L62: 46265 | M62: 46265 | N62: 1 | O62: 完了 | P62: doc11として整理完了。前提条件4区分＋基本的課題5本。国の基本指針は未告示のため告示後に追記。
A63: Ⅱ-53 | B63: Ⅱ 計画策定 | C63: Ⅱ-2 現行計画の評価 | D63: 高齢者福祉事業等の実績資料の受領 | E63: 仕様書4Ⅱ(2)① | F63: 北塩原村 | G63: 実績資料 | H63: R6年度実績、可能であればR7年度 | I63: R8.10〜11 | L63: 46272 | N63: 0.55 | O63: 着手 | P63: 見える化・決算は受領。★9/7：成年後見の実績（利用促進施策の取組状況調査 令和7・8年度、会津権利擁護・成年後見センターの相談件数 令和6・7年度）と合計所得金額分布調査を受領。村単独事業（除雪・緊急通報・生活支援ハウス等）の実績数値は引き続き未受領。
A64: Ⅱ-54 | B64: Ⅱ 計画策定 | C64: Ⅱ-2 現行計画の評価 | D64: 高齢者福祉事業等の実施状況の把握と課題整理 | E64: 仕様書4Ⅱ(2)① | F64: 受託者 | G64: 評価シート | I64: R8.11 | L64: 46267 | N64: 0.88 | O64: 着手 | P64: doc14で第9期施策19本を評価。キックオフ資料により村単独事業名（除雪サービス・緊急通報・生活支援ハウス・はつらつ貯筋教室等）を把握。交付金の指標単位データにより給付適正化の実施状況が判明（doc20§8-2）。実績数値は未受領のため一部保留。進捗管理評価シート27頁の全文読み込みが未了。★10/2：医療と介護の連携の状況を加算の算定率により把握し素案2-5に掲げた。連携が成立しているのは村内の認知症対応型共同生活介護と医療機関の間に限られる。
A65: Ⅱ-55 | B65: Ⅱ 計画策定 | C65: Ⅱ-2 現行計画の評価 | D65: 介護保険給付統計の取りまとめ | E65: 仕様書4Ⅱ(2)② | F65: 受託者 | G65: 統計表 | I65: R8.11 | L65: 46265 | N65: 0.85 | O65: 着手 | P65: D系給付費・K系施設数・D47/D48特別会計決算まで整理済（doc02）。令和6年度決算が未入手。★9/24：介護サービス自給率（δ2・δ2-a〜e）が取得済みでありながら未使用であったため素案2-5に投入した（doc38§A-1）。村外利用の割合を測る最も直接的な指標であり、短期入所系0%は村内に事業所がないことの裏づけになる。
A66: Ⅱ-56 | B66: Ⅱ 計画策定 | C66: Ⅱ-2 現行計画の評価 | D66: 計画数値の評価（計画値と実績の乖離分析） | E66: 仕様書4Ⅱ(2)② | F66: 受託者 | G66: 乖離分析表 | H66: 第9期は第1号被保険者数を過小推計（-5.6〜-6.8%） | I66: R8.11 | L66: 46265 | N66: 0.95 | O66: 着手 | P66: 見える化の地域分析P1〜P4および一括受領738冊と素案の数値を突合し、本村の値の食い違いがないことを確認（doc51・doc52）。費用額の順位の誤り4か所を訂正。
A67: Ⅱ-57 | B67: Ⅱ 計画策定 | C67: Ⅱ-2 現行計画の評価 | D67: 課題の整理 | E67: 仕様書4Ⅱ(2) | F67: 受託者 | G67: 課題一覧 | I67: R8.11 | L67: 46265 | M67: 46265 | N67: 1 | O67: 完了 | P67: doc11で基本的課題5本に集約完了。各課題を交付金評価指標と対応づけ。
A68: Ⅱ-115 | B68: Ⅱ 計画策定 | C68: Ⅱ-2 現行計画の評価 | D68: 見える化システムの収録データの受領と成果品との突合 | E68: 仕様書4Ⅱ(2)② | F68: 双方 | G68: 突合の点検（verify_mieruka.py）・mieruka_batch.csv | H68: 村から見える化の出力を受領。本村の値のみを対象とし他自治体は参照値 | I68: R8.9〜10 | L68: 46294 | N68: 0.98 | O68: 着手 | P68: ZIP20本・738冊を受領し全冊を読み取り。本村の値のみを対象とし他自治体は参照値として扱った。点検52件すべて適合。受領した長形式CSVは期の欄が別の自治体の行の値になっていたため、実物から取り出し直した。交付金W系列210冊のうち本村の値があるのは103冊で、107冊は福島県の列のみ。★10/2：突合を52→63件に広げた。正本21図それぞれに突合の状態を定め、突合済み14図・見える化に相手がない7図を点検32で網羅。新規認定の要支援1の割合（B9）、1人あたり定員（D29・D30）、調整済み認定率（B5-a・B6-a・B6-b）を加えた。★10/4：突合を63→69件に。見える化に相手がないとしていた7図のうち3図（図2-12・図2-16・図2-18）がD6・D47・D48と1点のずれもなく一致した。決算の系列は締めの日で期を呼ぶため1年ずらす必要があった。突合済みは17図、相手がない図は4図。★10/5：居宅・地域密着型・施設の区分別の図2点を、サービス別の系列（D13の27サービス）から組み直した。27サービスの和が7区分の計と一致することを点検40で確かめている。突合は71件。
A69: Ⅱ-58 | B69: Ⅱ 計画策定 | C69: Ⅱ-3 見込量・保険料 | D69: 将来人口の整理（2040年度含む中長期） | E69: 仕様書4Ⅱ(3) | F69: 受託者 | G69: 人口推計表 | H69: 社人研の新推計（2050年まで）に差し替え | I69: R8.11〜12 | L69: 46265 | M69: 46272 | N69: 1 | O69: 完了 | P69: 見える化P1との突合により9点すべて一致を確認（doc51）。
A70: Ⅱ-59 | B70: Ⅱ 計画策定 | C70: Ⅱ-3 見込量・保険料 | D70: 第1号被保険者数の推計 | E70: 仕様書4Ⅱ(3)① | F70: 受託者 | G70: 推計表 | H70: 第9期の過小推計を直近実績で補正 | I70: R8.11〜12 | L70: 46265 | N70: 0.95 | O70: 着手 | P70: doc13で前期・後期別の乖離率補正により令和9〜11年度末を算定（1,002／997／990人）。scripts/estimate_population.pyで再現可能。★9/15：素案5-2・5-3が社人研推計（国勢調査ベース）、5-4以降が厚生労働省配布の推計用人口（住民基本台帳ベース）を用いており2系列が併存していたことが判明。厚生労働省配布の系列（B案・令和7年12月末実績にリベース）に統一し、素案5-1・5-2を全面改訂した（1,004／995／987人）。2つの方法の差は最大3人（0.3%・保険料月額約7円）であり、検証として素案5-2に併記。残るのは補正手法の村合意と国ワークシートによる確定のみ。★10/7：国の推計ワークシート（将来推計総括表・令和8年10月5日出力）を受領した。国の値は令和9年度1,004人・令和10年度1,000人・令和11年度994人で、配布データをそのまま用いるA案（946／939／931）ではなく実績にリベースした系列であり、当方のB案（1,004／995／987）と1〜7人（0.1〜0.7%）の差にとどまる。B案の採用が裏づけられた。一方、前期・後期の内訳は食い違う（国は3区分で前期444／425／405・後期560／575／589、当方は2区分で前期465／444／424・後期538／551／563）。後期高齢者の割合は2.1〜2.2ポイント開く。国の様式は3区分で持つため、当方が提案していた②前期・後期高齢者別は選べない。素案5-2を国の3区分に揃える作業が残る。
A71: Ⅱ-60 | B71: Ⅱ 計画策定 | C71: Ⅱ-3 見込量・保険料 | D71: 要介護者数の推計 | E71: 仕様書4Ⅱ(3)① | F71: 受託者 | G71: 推計表 | H71: 要支援1の急増（39→51人）を反映 | I71: R8.11〜12 | L71: 46265 | N71: 0.95 | O71: 着手 | P71: ★9/7：doc29／scripts/estimate_certified.py として要介護度別の推計を確立。見える化のB4-a（全体）とB4-d（75歳以上）から前期・後期別の要介護度別認定率を分解（前期5.86%／後期34.70%）。B案×令和8年の認定率で基準年が実績と完全一致（211人・要支援1=51・要支援2=29・要介護1=50）。令和9年214人／令和10年217人／令和11年220人。認定率の基準2種×被保険者数2案の4通りを出力し、令和11年度で最大12人・5.8%の幅。★9/15：素案5-3に要介護度別（要支援1〜要介護5）の見込みを掲載し、認定率の置き方3とおりの幅を明示した（令和11年で①3か年平均220人〈採用〉・②直近年度固定224人・③年0.62pt上昇226人、保険料で月額約170円の幅）。国ワークシートの受領で確定する。★10/7：素案5-3を国の推計ワークシートの値に組み替えた（doc67）。令和9年度208人・令和10年度211人・令和11年度210人（第1号被保険者の分）である。当方の算定（214／217／220）は検算として併記し、3か年計で22人（3.5%）高いこと、原因が認定率の置き方であること（当方の認定率を国の内訳に乗じると220／224／228人とさらに高くなる）を本文に書いた。保険料への効きは月額約200円である。要支援1が6人増え要介護2が6人減る動きを本文に起こし、施策1-2・施策3-1へつないだ。doc66の突合で第2号被保険者を含む総数635人と当方の第1号651人を取り違えていた誤りを直した（正しくは629人・▲3.4%）。点検26を組み替え、取り違えが戻れば不適合になるようにした。
A72: Ⅱ-61 | B72: Ⅱ 計画策定 | C72: Ⅱ-3 見込量・保険料 | D72: 各介護保険サービス見込量の推計 | E72: 仕様書4Ⅱ(3)② | F72: 受託者 | G72: 見込量表 | H72: 居宅・施設・地域密着型・総合事業。村外利用を考慮 | I72: R8.12 | L72: 46272 | N72: 0.95 | O72: 着手 | P72: ★9/8：doc30として推計の枠組みを確定。「見える化」システムのデータ定義（受給者数＝年度延べ、D45系の分母＝要介護度別認定者数）を検算のうえ確定し、estimate_services.py により区分別・サービス種類別の見込量を算定。全28サービスのうち令和7年度に実績のある16サービスについて受給者数・利用量・給付費の暫定値を doc18 第5章5-4に投入。施設・居住系の種類別人数は見える化に系列がなく給付費比の按分値のため、村の月報（第2表・第3表）で置き換えが必要。介護給付と予防給付の分離も同じく月報待ち。★9/12：他案件（川崎町・金ケ崎町・大雪）の到達水準と対照し（doc33）、基準年度を令和7年度と確定。見える化の系列別の月数を実測で確認し（D1はR7が11か月、D2/D3/D4は12か月相当）doc30の÷12が正しいことを裏付けて素案5-4に明記。令和9年4月新設4区分の枠と、国の推計ツールのワーニング判定式（閾値＝Q1−2Q〜Q3+2Q）による自己点検の手順を追加。国の推計ツールの出力は未受領で、依頼書18-2として最優先で追加した。★9/15：他案件（大雪・川崎・金ケ崎）の算定の進め方を確認し、本村に適用して第1次概算を実施（doc35）。(1)見込量は需要で置く／地域密着型と総合事業のみ村の供給力が上限、という原則を素案5-4に明記。(2)令和9年4月新設4区分を「―」「要協議」から0に立て直した。(3)夜間対応型訪問介護の令和9年3月末廃止を反映。(4)単価の趨勢を連鎖ラスパイレス指数で実測（R元→R7の年率+1.30%）。3か年平均で固定していることは給付費の5.32%過小＝保険料月額314円に当たる。(5)サービス別の受給者数の年率が▲13.12〜+54.88%と68ポイント開いていることを実測し、伸びをどこまで反映すべきかをバックテストで検証（backtest_growth.py）。φ=0.5・c=5%が最小（WMAPE19.11%）だが一律19.68%に対し改善は2.9%にとどまるため一律を採用すると決定。(6)一律の方法で3年先を予測したときの誤差は絶対値平均11.9%＝保険料月額約700円で、基金取崩24,000千円の効き（702円）と同規模。素案5-4(9)として新設。(7)在宅介護実態調査の施設入所申込みの反映シナリオの枠を素案5-4(3)に新設（+1人／月＝月額75円）。残るのは国の推計ワークシートによる基準年度の置き直しの分解のみ。★9/15（第3次）：推計の系列を統一し、給付費を分離した（doc35§7-3）。(1)素案5-2・5-3が社人研推計（国勢調査ベース）、5-4以降が厚生労働省配布の推計用人口（住民基本台帳ベース）を用いており、令和11年の認定者数が230人と220人で食い違っていた。厚生労働省配布の系列（B案）に統一し5-1・5-2・5-3を全面改訂。5-1に①第1号被保険者数→②認定者数→③受給者数→④利用量→⑤給付費→⑥標準給付費→⑦保険料の連なりを表で明示した。(2)決算（D48-b）の介護サービス等諸費／介護予防サービス等諸費と要介護度別受給者数を突き合わせ、予防給付19,002円・介護給付175,230円の1人あたり給付月額を復元（令和3〜5年度で±1.6%以内の安定）。第10期3か年で介護給付費755,119千円・予防給付費34,344千円に分離し、5-6の空欄を埋めた。(3)見込量の自己点検を実施（check_warning.py）。年度間の変化率は3区分とも4%以内。令和7年度実績→令和9年度見込で±10%超は4件（居宅療養管理指導▲25.3%、短期入所生活介護▲20.8%、訪問入浴介護・地域密着型通所介護は新規計上）。いずれも3か年平均で置くことの副作用であり委員会にお諮りする。(4)地域支援事業費を新系列で置き直し3か年122,737千円（保険料月額+22円）。★9/16：認知症関連を反映（doc36§4）。5-4(7)の必要利用定員総数に認知症高齢者数との対比を追加（自立度Ⅱ以上1人あたりの定員は令和2年0.178人分→令和6年0.168人分。定員は平成28年度以降27人で固定、稼働率93%）。5-5(1)に認知症総合支援事業の6行（初期集中支援推進事業の対象者数・地域支援推進員・認知症カフェ・サポーター養成講座・養成者数・チームオレンジ）を新設。大半が実績未受領のため空欄。村内GHの待機者数と村外GH利用者数が未受領で、定員の増減を委員会に諮れない状態である（優先度A）。★9/24：他案件（大雪・川崎）のブランチを確認し、大雪の点検から5点を採った（doc37）。(1)利用率の分母を実データで検算（verify_bunbo.py）。見える化のサービス利用率の分母は要介護度別認定者数であり本村の算定と整合、直すところはなかった。ただし国の将来推計が在宅の分母を「認定者数−施設・居住系」とする場合要介護1で58.8%→86.1%、要介護2で107.7%（100%超）に変わるため、ワークシート受領時に確認を要する。要介護2の3区分合計が101.5%で、年度途中の在宅→施設の移行による重複1.5%が判明。(2)単価の趨勢と介護報酬改定率の二重計上を防ぐ断りを5-4(10)①に追加。趨勢は改定を含む実測値のため両者は択一。(3)供給の制約（村内定員の到達率）を算定（estimate_supply.py）。GH令和11年度90.7%・通所介護83.6%で超過なし。年報は施設の所在地を問わないため到達率は上限ではないことを明記。5-4(5)として新設。★10/8：居住系サービスの受給者数を、按分の参考値から算出に切り替えた。受給者数＝第1号被保険者1人あたり給付月額（D13）×第1号被保険者数÷受給者1人あたり給付月額（D17）。通所介護で検算すると素案の値（令和5年度37.2・令和6年度42.2・令和7年度38.9人／月）と一致し、居住系2種の和は見える化の居住系受給者数（D1）と令和5・6年度で完全に一致した（令和7年度は0.3人の差。給付費が0のサービスには残差を割り振れないため）。D17系列があるのは15サービスで、施設サービス3種（特養・老健・介護医療院）にはないため按分の参考値のままである。認知症対応型共同生活介護は令和7年度25.0→23.8人／月、到達率92.6→88.1%に改まった。特定施設入居者生活介護は2.4→3.3人／月。見込量は給付費で算定しているため保険料には影響しない。点検72で算出が維持されていることを確かめる。
A73: Ⅱ-105 | B73: Ⅱ 計画策定 | C73: Ⅱ-3 見込量・保険料 | D73: 地域密着型サービスの必要利用定員総数の設定 | E73: 仕様書4Ⅱ(3)② | F73: 受託者 | G73: 定員総数表 | H73: 介護保険法117条2項1号（義務）。本村に関係するのは認知症対応型共同生活介護のみ | I73: R8.12 | L73: 46275 | N73: 0.95 | O73: 着手 | P73: ★介護保険法117条2項1号の義務的記載事項。doc32で欠落を検出し素案5-4(8)に新設した。本村に関係するのは認知症対応型共同生活介護のみで27人を仮置き。稼働率93%・第10期は居住系が増加見込みで村内に余地がないため、増床・村外対応・在宅対応のいずれを取るかは村の判断を要する（確認事項 優先度B）。★10/7：「真に入所が必要と判断される被保険者」を在宅介護実態調査から数える手順を集計仕様書に落とした。派生変数Z01（入所の必要性の3区分）とZ02（村内施設の需要の2区分）を定義し、クロス表X-21（3区分×要介護度）・X-22（3区分×村内施設があれば）を加えた。Z01はA票 問6（入所・入居の検討状況）を基礎に、問12・問14・B票 問10を重ねて①在宅で続けられる方／②支援を強めれば続けられる方／③入所が必要な方に分ける。判定の境目（B票 問10の選択肢の水準と問14の頻度）は調査の結果を見て確定する。回収が50〜60件程度と見込まれるため、該当数が10未満の区分は統合して示す（doc16 §6）。クロス表は20表から22表になり、doc24・doc25の件数も改めた。★10/7：県の施設・居住系サービスの整備量見込みシート（令和8年10月6日提出）を受領した。認知症高齢者グループホームの定員は令和8年度末27人・令和9〜11年度いずれも27人（整備数0）で県に提出済みであり、素案5-4(8)の27人維持の仮置きは村の提出内容と一致する。利用者数は令和8年度26人から令和9〜11年度27人で到達率100%（満床）の見込みである。待機者がいる場合は村外または在宅での対応になるため、待機の状況（人数・待機期間）の照会を起票した。必要利用定員総数の設定そのものは確定した。★10/8：素案5-4の施設・居住系5サービスの見込量を県の整備量見込みシートの値に置き換えた（doc69）。県シートの記入要領は「令和6〜8年度は月平均の実績人数（四捨五入）」としており、本村の被保険者の受給者数である。当方の算出（認知症GH 令和6年度21.0人・令和7年度23.8人、特養14.1人・12.8人、老健15.9人・16.6人、介護医療院1.2人・1.0人、特定施設2.6人・1.9人）は県シートの値と四捨五入の範囲で一致し、按分と算出の両方の方法が裏づけられた。食い違うのは見込みで、認知症GHは当方21.6人に対し県27人（定員27人・到達率100%・満床）である。当方の3か年平均は上がり続けている系列に対して構造的に低く出るため、村が県に提出した値を正とした。到達率は令和6年度77.8%・令和7年度88.9%・令和8年度96.3%・計画期間100%となり、2-5・2-11・施策3-2・資6の88.1%を96.3%・満床に改めた。estimate_supply.py を県シートを正本とする形に替え、年度の名をじか書きしていた欠陥（基準年度の並びを替えたとき、令和8年度の値に令和7年度の名が付いた）も直した。
A74: Ⅱ-106 | B74: Ⅱ 計画策定 | C74: Ⅱ-3 見込量・保険料 | D74: 地域支援事業の量の見込みと事業費の算定 | E74: 仕様書4Ⅱ(3)② | F74: 受託者 | G74: 地域支援事業費表 | H74: 介護保険法117条2項2号（義務）。総合事業・包括的支援事業・任意事業。保険料の構成要素でもある | I74: R8.12 | L74: 46280 | N74: 0.8 | O74: 着手 | P74: ★介護保険法117条2項2号の義務的記載事項。estimate_chiiki_shien.py により第10期3か年122,737千円を算定し素案5-5に投入（保険料月額+22円）。認定者数と第1号被保険者数の両方に連動させる方式。事業別の内訳（総合事業・包括的支援事業・任意事業）は村の実績が未受領のため空欄が残る。
A75: Ⅱ-62 | B75: Ⅱ 計画策定 | C75: Ⅱ-3 見込量・保険料 | D75: 給付費の試算 | E75: 仕様書4Ⅱ(3)③ | F75: 受託者 | G75: 給付費試算表 | H75: R9年度報酬改定は現行単価で仮試算→確定後に精緻化 | I75: R8.12 | L75: 46265 | N75: 0.9 | O75: 着手 | P75: ★9/8：サービス諸費（介護サービス等諸費＋介護予防サービス等諸費）の推計値を算定し doc18 第5章5-6に投入（令和9年度263,470千円／10年度263,505千円／11年度262,488千円）。見える化D48系に令和5年度までの決算が入っていることが判明し、令和3〜5年度の実績（244,097／247,333／258,848千円）と対比。決算の未入手は令和6・7年度の2か年に縮小。補足給付・高額介護サービス費・審査支払手数料は令和5年度決算まで把握済。★9/12：標準給付費見込額（3年計854,014千円）を算定。令和6・7年度決算が未受領のため割増率とその他給付費は令和5年度決算で代用している。★9/15：地域支援事業費を事業の対象別に3分して積み上げた（estimate_chiiki_shien.py）。介護予防・生活支援サービス事業は認定者数の伸び、一般介護予防事業と包括的支援事業・任意事業は第1号被保険者数の伸びによる。3か年計124,788千円で、令和5年度決算×3年の119,658千円を5,130千円上回り、保険料月額+36円に当たる。素案5-5(2)に投入。あわせて感応度表に3行（地域支援事業費+36円／単価の趨勢+314円／推計誤差±約700円）を追加し、据え置き項目31件を素案5-12として一覧化した。★10/7：国の推計ワークシート（将来推計総括表・令和8年10月5日出力）を受領した。突合の結果、3か年計でサービス諸費は当方789,463千円・国858,882千円（＋8.8%）、標準給付費見込額は当方854,014千円・国919,537千円（＋7.7%）であった。内訳の差は特定入所者介護サービス費等▲27.5%、地域支援事業費＋23.4%、高額医療合算介護サービス費等が当方0・国8,519千円、算定対象審査支払手数料＋13.9%である。地域支援事業費は当方が令和5年度決算39,886千円を据え置いていたのに対し、国は47,686／49,218／50,751千円（年3.2%の伸び）で入っていた。国の値を正として5-6を組み替える。★10/8：施設・居住系の見込量が上がったため（doc69）、5-6の給付費も上がる。国の推計ワークシートのサービス諸費（3か年858,882千円）が当方の789,463千円より8.8%高く、その7割は認知症GHの5.4人の差で説明できる。5-6の組み替えは、令和9年度以降も0で入っている6サービスの扱いが決まった時点で行う（影響度1）。
A76: Ⅱ-63 | B76: Ⅱ 計画策定 | C76: Ⅱ-3 見込量・保険料 | D76: 介護保険準備基金の残高・取崩方針の確認 | E76: 確認 | F76: 北塩原村 | G76: 基金残高資料 | H76: 第9期は設定額が必要額を上回る（R6+709円/R7+199円） | I76: R8.12 | L76: 46267 | N76: 0.75 | O76: 着手 | P76: ★議事録に「基金の取り崩し（第9期は800万円程度）」とあり、第9期計画から読み取った24,000,000円との齟齬がある。年額か期間合計かの確認が必要（doc22 K-74）。複数パターンのシミュレーションを受託者で行うことは決着。★10/7：国の推計ワークシート（将来推計総括表・令和8年10月5日出力）を受領した。準備基金の残高（令和8年度末見込）42,128,183円、取崩額40,000,000円（残高の94.9%）、保険料への影響額は月額マイナス1,096.83円と判明した。第9期計画の24,000,000円は期間合計である。残高・取崩額の確認は解消し、残るのは取崩額の水準の判断である。取崩で第11期に余地が残らず第11期の保険料は7,301.29円（＋32.4%）に跳ね上がる見込みであるため、世代間の負担の公平に関わる村の判断事項として起票した。
A77: Ⅱ-64 | B77: Ⅱ 計画策定 | C77: Ⅱ-3 見込量・保険料 | D77: 介護保険料の試算（複数案の比較） | E77: 仕様書4Ⅱ(3)③ | F77: 受託者 | G77: 保険料試算表 | H77: 所得段階・基金活用・上限の設定を反映 | I77: R8.12〜R9.1 | L77: 46272 | N77: 0.96 | O77: 着手 | P77: ★議事録で方針決着：第9期で県内平均を上回ったため急激な負担増を抑えたい意向。基金取崩も視野。令和9年度の介護報酬改定を見据え現行単価で一旦試算し単価確定後に補正。doc18 第5章5-7に様式と所得段階13段階の枠を作成済。★9/8：サービス諸費の推計（doc30）が出たため、残る停止要因は基金残高と令和6・7年度決算の2件に絞られた。★9/12：保険料算定の5式（金ケ崎町で第9期公表値と一致を確認した構造）と調整交付金見込交付割合の式（α+0.05）−α×F×Gを導入し、本村の第9期を0.32%で再現。限界率23.79%・F×G=1.034を復元。感応度9項目（給付費1%＝月額59円、第1号負担割合1pt＝294円、基金24,000千円＝▲702円）と12パターン（5,936〜7,341円・幅1,406円）を算定し素案5-7に投入（scripts/estimate_premium.py）。保険料の幅のうち702円は基金取崩の判断で決まるため、給付費推計の精緻化より基金方針の決定が先。★9/15：中長期（令和17年度・令和22年度）の保険料をαの2案で算定し素案5-11の【要確認】を解消（据え置き23%なら令和22年度6,883円、3年ごと1pt上昇なら8,379円。scripts/estimate_longterm.py）。素案5-6の標準給付費の様式を埋め3か年854,014千円を確定。5-7の感応度に3行（地域支援事業費+22円／単価の趨勢+314円／推計誤差±約700円）を追加した。残るのはα政令・基金残高・令和6-7年度決算の受領。★9/24：年度別の保険料収納必要額を算定し素案5-7に新設（doc37§6）。令和9年度6,704円→令和11年度6,799円で95円上がる。給付費が横ばいで第1号被保険者数が1.7%減るため。3か年平均6,756円との差は令和9年度+596千円（余り）・令和10年度▲109千円・令和11年度▲486千円。第10期末の基金残高を見込むには期首残高が必要（未受領）。年度別の過不足は給付費が1%振れるだけで逆転する程度（年間約680千円）であり、基金の役割は年度間の均衡よりも推計の誤差（絶対値平均11.9%）の吸収にある。★10/7：国の推計ワークシート（将来推計総括表・令和8年10月5日出力）を受領した。第10期の保険料基準額は5,513.72円（第9期6,760.76円比マイナス18.45%）、うち保険料収納必要額6,610.55円・基金取崩の影響マイナス1,096.83円である。当方の算定（取崩なし6,756円）と国（6,611円）の差はマイナス145円・マイナス2.2%であり、5式による復元の筋が合っていたことが確かめられた。下がる理由は総給付費で、第9期計画が実績より過大に見込んでいたことによる（第10期の見込みは令和8年度の実績とほぼ同水準）。確定した係数は第1号被保険者負担割合23%、調整交付金見込交付割合5.36／5.03／4.67%、後期高齢者加入割合補正係数0.9652／0.9790／0.9951、所得段階別加入割合補正係数1.0197／1.0199／1.0193、予定保険料収納率99.50%である。当方が復元していた見込交付割合4.10〜4.32%は1.0ポイント以上低く、出所の確認を起票した。★10/8：素案5-7を国の推計ワークシートの値に組み替えた（doc68）。基準額5,513.72円を節の冒頭に置き、保険料基準額（月額）の内訳（総給付費5,411.96円のうち在宅1,391.37円・居住系1,925.81円・施設2,094.77円、その他給付費382.54円、地域支援事業費931.22円、市町村特別給付費等マイナス115.17円、収納必要額6,610.55円、基金取崩マイナス1,096.83円）を表にした。給付費の61%が施設・居住系であることが国の出力で示せるようになった。確定した係数（α23%、見込交付割合5.36／5.03／4.67%、F 0.9652／0.9790／0.9951、G 1.0197／1.0199／1.0193、収納率99.50%）の表を加えた。当方の5式による算定・感応度・12のパターンは検算として残し、国の値との関係を明記した。基金の節は、残高が分かったため空の注記から第11期への跳ね返りの説明に替えた。★10/9：基金の取崩しの3案を国の推計ワークシートの算定の上に組み直した（doc73）。資料6の3案は当方がワークシートの提供を受ける前に算定したもので、取崩なしの算定上の月額は当方6,756円・国6,610.55円であった。差は145円だが、条例上の基準額は6,800円（＋100円）と6,600円（▲100円）となり、第9期の条例基準額6,700円との向きが逆になる。取崩しをしなくても第9期を下回るため、C案「据置きを優先し基金を最大限取り崩す」は前提が崩れていた。A案 取崩なし 条例6,600円／第11期6,100円、B案 24,000千円 6,000円／6,800円、C案 40,000千円 5,500円／7,200円で組み直し、第10期と第11期が逆の向きに動くことを示した。残高が吸収できる推計の誤差（緩衝力）を3つ目の軸として加えた。C案では月額58円分で、推計の誤差（絶対値の平均11.9%・月額約700円）を吸収できない。第11期は国の中長期シートが令和12年度の単年で立っているため、令和12年度の第1号被保険者数988人×補正係数1.0190×12か月×収納率99.50%で分母を組み、3か年に均した36,063人・月で残高を割った。保険料は期を通じて同一に定めるため、シートの取崩額の欄に残高をそのまま入れた場合（単年の分母で割られ3倍大きく出る）は期の保険料の姿ではない。前回「どちらかを当方が決めない」と報告したのは誤りである。分母の組み方は同じ組み方で第10期の分母を復元して確かめた（ワークシート36,469人・月に対し復元36,499人・月。差＋0.08%）。正本は scripts/estimate_kikin.py に置き、素案5-7と資料6 6-3bが同じ算定を引く。ワークシートの読み取りは1回3〜4秒かかりキャッシュされていないため、結果を覚えておく形にした（組立てが数分かかるようになっていた）。
A78: Ⅱ-107 | B78: Ⅱ 計画策定 | C78: Ⅱ-3 見込量・保険料 | D78: 所得段階の設定（段階数・保険料率・低所得者軽減） | E78: 仕様書4Ⅱ(3)③ | F78: 受託者 | G78: 段階別保険料表 | H78: 第9期は13段階。令和8年度合計所得金額分布調査（13段階・1,015人）を用いる | I78: R8.12〜R9.1 | L78: 46272 | N78: 0.7 | O78: 着手 | P78: ★令和8年度合計所得金額分布調査（13段階・1,015人・10万円刻み）を受領済（doc28§2）。第9期の13段階を踏襲するか区切りを見直すかは未決で、見直す場合の影響試算に同データを用いる。素案5-7に13段階の枠を作成済。★10/7：国の推計ワークシート（将来推計総括表・令和8年10月5日出力）を受領した。「弾力化をした場合の所得段階別加入割合」および「弾力化をした場合の所得段階別被保険者数」の行がすべて0であり、村は標準の段階区分で提出していることが確認された。所得段階別加入割合補正後被保険者数は3か年3,054.34人で入っている。
A79: Ⅱ-108 | B79: Ⅱ 計画策定 | C79: Ⅱ-3 見込量・保険料 | D79: 中長期（令和17・22年度）の保険料見通しの算定 | E79: 仕様書4Ⅱ(3)③ | F79: 受託者 | G79: 中長期見通し表 | H79: 国の基本指針が2040年度・2050年度を見据えた推計を求める | I79: R8.12〜R9.1 | L79: 46280 | M79: 46280 | N79: 1 | O79: 完了 | P79: ★estimate_longterm.py により算定し素案5-11の【要確認】を解消。第1号負担割合αを23%に据え置くと令和22年度6,883円、3年ごとに1ポイント上がると8,379円。補助給付等は令和11年度に令和5年度決算を置きサービス諸費に比例させた。★10/8：素案5-11に国の推計ワークシートの第17期（令和32年度）までの出力を加えた（doc68）。第10期5,513.72円・第11期7,301.29円（＋32.4%）・第12期8,281.46円（＋50.2%）・第14期7,735.73円（＋40.3%）・第16期8,131.97円・第17期9,118.27円（＋65.4%）である。第12期から第14期にかけていったん下がるのは、調整交付金の見込交付割合が5.18%から10.37%へほぼ倍になるためである（Fが0.9753から0.7790へ下がる）。高齢化が進むほど調整交付金が増え、保険料の上がり方が抑えられる方向に働く。当方のαの2案による算定は検算として残した。なおFの復元を試みたところ令和17年度0.8604・令和22年度0.7459となり国の値と一致せず、算出方法の照会を起票した（Fは0.1で月額約250円動く）。
A80: Ⅱ-65 | B80: Ⅱ 計画策定 | C80: Ⅱ-3 見込量・保険料 | D80: 成果目標及び活動指標の設定 | E80: 仕様書4Ⅱ(3)④ | F80: 受託者 | G80: 指標一覧 | H80: 第9期実績との接続。達成可能性の検証を併せて実施 | I80: R8.12〜R9.1 | L80: 46268 | N80: 0.92 | O80: 着手 | P80: 交付金の目標別の得点の推移（令和6〜8年度）を素案2-8と委員会資料2-4に追加（doc53）。活動指標群が38点にとどまることを本文で指摘。★10/2：性・年齢調整済み認定率の図を起こし、交付金の評価が求める分析の空白を3件から2件に減らした。調整済み認定率は19.5→23.0%と上がるが上昇は軽度に集中し、重度（要介護3以上）は6.7→6.6%で横ばい、要介護2以上は10.4→9.0%と低下している。★10/6：交付金の評価が求める分析のうち裏づける図がなかった2件に図を起こし、空白を0件にした。(1) 在宅医療・介護連携の状況＝見える化の地域分析（医療介護連携）の4加算の算定率と偏差値（2-5）。村の給付実績の集計を待たずに描けた。(2) ケアマネジメントの質の分析＝給付適正化の取組別得点の推移（5-8）。ケアプラン点検の実績そのものは村にないが、国の評価における取組別の得点を3か年で示した。ケアプラン点検は令和8年度に4段階のうち2段階（8点）を取得している。あわせて、交付金の後退した項目を数え直した。配点が年度間で変わった項目を除いて数えると3項目15点ではなく5項目22点であった。見落としていたのは「給付適正化の主要な事業の実施と記録」（推進Ⅱ・6点・全国該当率96.9%）で、令和6年度には3つの小項目各2点に分かれていたため集計の単位が違って見落としていた。全国のほぼすべてが取得している項目であり、最も重い。素案2-8・第2回資料・確認事項の3か所を直した。
A81: Ⅱ-109 | B81: Ⅱ 計画策定 | C81: Ⅱ-3 見込量・保険料 | D81: 給付適正化に係る取組内容と目標の設定 | E81: 仕様書4Ⅱ(3)④ | F81: 受託者 | G81: 給付適正化計画 | H81: 介護保険法117条2項3号・4号（義務）。主要3事業（要介護認定の適正化・ケアプラン点検・医療情報との突合） | I81: R8.12〜R9.1 | L81: 46273 | N81: 0.7 | O81: 着手 | P81: ★介護保険法117条2項3号・4号の義務的記載事項（努力義務ではない）。素案を施策3-5（取組内容）と第5章5-8（計画としての目標）の二本立てに整理し、第9期は第5章にのみ置かれ施策体系の中に見えなかった課題（doc17 B-5）を解消した。根拠条項を117条3項5号・6号としていた誤りは訂正済。目標値は村の実績が未受領のため一部空欄。★10/7：交付金の明細から、主要3事業の現状値を村の実績を待たずに置いた。②ケアプラン等の点検は令和8年度に8点／16点（4段階のうち2段階）、令和6・7年度は0点。③医療情報との突合は令和7年度から16点満点（4段階すべて）、縦覧点検は4帳票全件で3年連続満点。①要介護認定の適正化は国の評価指標に単独の項目がなく、村の実績も未受領。②の目標は、件数を置けないため当面は国の評価指標の段階（令和11年度までに4段階すべて）とし、実績の受領後に件数の目標を加える形にした。5-12にその旨を登録した。あわせて、0点の理由の推論を絞った。従来は「①または②のいずれかが未実施」としていたが、②は令和8年度に取得があり③も満点であるため、「①の未実施」か「3事業の実施の記録が国への報告の要件を満たしていない」かのいずれかに絞られる。施策3-5の指標にも、ケアプラン点検と医療情報との突合の評価の段階を加えた。★10/8：介護給付適正化計画の期数が1期ずれていた誤りを原典で直した（doc71）。第6期＝令和6〜8年度／第7期＝令和9〜11年度であり、本計画は第7期に当たる。施策3-5・5-8の3か所を改めた。主要3事業の名称も原典の順（医療情報との突合・縦覧点検）に揃え、点検32の照合先を改めた。5-8に「(5) 帳票を活用した点検の充実と新たな点検手法」を新設した。第7期指針の改訂内容のうち、要介護認定情報の「現在の状況」コードが有料老人ホーム・サービス付き高齢者向け住宅である受給者の給付実績を抽出した帳票が新たに作られることは、5-8(2)に未実施として挙げていた「ケアプラン点検への有料老人ホーム等入居者分の追加」（8点）の方法そのものである。ただし仕組みを構築するとされた段階であり、提供の時期は示されていないためこの帳票を前提とした目標は置かず5-12に登録した。点検対象の事業所の選定に国保連の帳票を積極的に活用する旨を施策3-5に加えた。あわせて6-4に検証項目⑦（1人あたり給付費の外れ値と帳票点検の実施率）を新設し、原典が挙げる3つの管理指標（ケアプラン等の点検件数・医療情報との突合の実施率・縦覧点検の実施率）を上半期・下半期ごとに記録する形にした。
A82: Ⅱ-66 | B82: Ⅱ 計画策定 | C82: Ⅱ-4 高齢者福祉施策 | D82: 現行計画の成果と課題の整理 | E82: 仕様書4Ⅱ(4) | F82: 受託者 | G82: 整理メモ | I82: R8.11〜12 | L82: 46265 | M82: 46265 | N82: 1 | O82: 完了 | P82: doc14として第9期の施策19本を4段階（◎○△✗）で評価完了。
A83: Ⅱ-67 | B83: Ⅱ 計画策定 | C83: Ⅱ-4 高齢者福祉施策 | D83: 次期計画に盛り込む施策の検討 | E83: 仕様書4Ⅱ(4) | F83: 受託者 | G83: 施策案 | H83: 環境整備・支援体制の構築等 | I83: R8.11〜12 | L83: 46265 | N83: 0.85 | O83: 着手 | P83: doc14・doc18として施策案を整理。第4章は26施策。住民ニーズ第1位の除雪を独立施策（2-6）として新設。基本目標5「計画の推進と進捗管理」の新設を提案。国の基本指針で追加・修正の可能性。★9/16：認知症基本法の基本的施策10項目と本計画の施策を対応させたところ、第15条（認知症の人の生活におけるバリアフリー化の推進）を受ける施策がないことが判明。移動・住まい・除雪の各施策が実質的な受け皿になるが、認知症の人に着目した記述はない。外出・買い物・金融機関の利用など介護保険の枠組みの外にある領域であり、庁内の関係部署および事業者との連携の範囲を村と協議する。
A84: Ⅱ-110 | B84: Ⅱ 計画策定 | C84: Ⅱ-4 高齢者福祉施策 | D84: 老人福祉事業の量の目標の設定 | E84: 仕様書4Ⅱ(4) | F84: 受託者 | G84: 量の目標表 | H84: 老人福祉法20条の8第2項（義務）。村単独事業の目標量を年度別に置く | I84: R8.12 | L84: 46275 | N84: 0.7 | O84: 着手 | P84: ★老人福祉法20条の8第2項の義務的記載事項。doc32で欠落を検出し第4章4-6として新設した。村単独事業（除雪サービス・緊急通報・生活支援ハウス・配食等）の年度別目標量を置く枠までを作成。実績数値が未受領のため一部空欄。★10/4：4-6は法的根拠・確保の方策・12事業の枠が揃っており、待っているのは実績値のみであることを確かめた。5-12(1)に掲げていなかったため追加した。あわせて点検51を新設し、空欄の並ぶ表が5-12に掲げられていることを機械で確かめるようにした。5-9の交付金の見込額も掲げ漏れていた。★10/5：4-6(2)の9事業に「確保の方策（該当施策）」の欄を設けた。老人福祉法20条の8第3項第1号が求める量の確保のための方策に当たる。点検53を新設し、12事業すべてに方策があること、方策が指す施策が第4章に実在することを機械で確かめるようにした。
A85: Ⅱ-68 | B85: Ⅱ 計画策定 | C85: Ⅱ-5 成年後見 | D85: 制度の利用実態・考え方の情報提供 | E85: 仕様書4Ⅱ(5) | F85: 北塩原村 | G85: 情報提供資料 | H85: 村長申立の運用、中核機関の状況 | I85: R8.11 | L85: 46272 | N85: 0.7 | O85: 着手 | P85: ★成年後見制度利用促進施策に係る取組状況調査（令和7・8年度）と会津権利擁護・成年後見センターの相談件数（令和6・7年度）を受領し実態が判明（doc28§3）。利用者4人（後見1・保佐2・補助1・任意後見0）、市町村長申立て0件、市民後見人の養成0人（広域中核機関で1人）・登録0人・受任0件、法人後見は圏域内0法人、任意後見の周知は未実施。一方で中核機関・協議会・申立費用助成・報酬助成はいずれも整備済で地域連携ネットワークは26項目中21項目が整備済。市町村計画は第9期と一体で策定済。
A86: Ⅱ-69 | B86: Ⅱ 計画策定 | C86: Ⅱ-5 成年後見 | D86: 利用促進の方向性・計画案の提示 | E86: 仕様書4Ⅱ(5) | F86: 受託者 | G86: 計画案 | H86: 広域調整・関係機関協議は村が実施 | I86: R8.12 | L86: 46272 | N86: 0.4 | O86: 着手 | P86: ★実績判明により方向性を確定。「体制整備」から「利用促進と担い手確保」へ施策4-7の書きぶりを転換することを提案（doc28§3-4）。ニーズ調査 問11（認知度・家族との話し合い・利用意向）と組み合わせて「制度は整っているのに使われていない」原因を住民側の認知度から説明する。
A87: Ⅱ-70 | B87: Ⅱ 計画策定 | C87: Ⅱ-6 計画案の検討 | D87: 第10期の課題の整理 | E87: 仕様書4Ⅱ(6) | F87: 受託者 | G87: 課題整理 | I87: R8.12 | L87: 46265 | M87: 46265 | N87: 1 | O87: 完了 | P87: doc11で基本的課題5本、doc17で第9期計画の課題20件（重大度A 13件）を洗い出し完了。
A88: Ⅱ-71 | B88: Ⅱ 計画策定 | C88: Ⅱ-6 計画案の検討 | D88: 施策体系の整理 | E88: 仕様書4Ⅱ(6) | F88: 受託者 | G88: 施策体系図 | I88: R8.12 | L88: 46269 | N88: 0.95 | O88: 着手 | P88: doc14・doc18で施策体系（基本目標5本・施策28本）を確定。施策3-5「介護給付の適正化」を交付金配点表に基づき全面改訂（主要3事業への再編・縦覧点検4帳票満点の事実を反映）。基本目標5の独立可否は村と要協議。★9/4：資料4として委員会に諮る形に整理（基本目標5本・施策28本、区分別内訳は継続10／継続強化1／強化6／改称1／新規10）。新設10施策の根拠を1件ずつ明示。★9/8：給付適正化を施策3-5（取組内容）と第5章5-8（計画としての目標）の二本立てに整理。第9期は第5章にのみ置かれ施策体系の中に見えなかった課題（doc17 B-5）を解消。★10/5：区分別の内訳を数え直した。継続9／継続・強化2／強化7／改称1／新規5／新設4＝28施策。9月4日の整理（継続10／継続強化1／強化6／改称1／新規10）から動いており、素案3-4の「新規・新設は10施策」がそのまま残っていた。点検57を新設し、本文が述べる基本目標・施策・新規新設の数を構造から数え直して一致を確かめるようにした。あわせて施策2-5と施策4-5の二重取扱いを解いた（生活支援体制整備事業は施策4-5を正本とする）。
A89: Ⅱ-72 | B89: Ⅱ 計画策定 | C89: Ⅱ-6 計画案の検討 | D89: 関連計画との整合確認 | E89: 仕様書4Ⅱ(6) | F89: 受託者 | G89: 整合確認表 | H89: 第5次総合振興計画／第3次健康21・グッドヘルスプラン | I89: R8.12 | L89: 46267 | N89: 0.88 | O89: 着手 | P89: ★議事録で整合対象が確定（障がい福祉計画・地域福祉計画・グッドヘルスプラン・生涯学習計画）。第四次生涯学習推進計画は受領・確認済（doc21）。他は未受領。★10/10：資9（関連計画との対照）を新設し、8計画との重なりと整合のとり方を一覧にした（doc81）。未受領の計画は枠を置き、計画期間を「確認中」として受領後に埋める形とした。★障がい福祉計画については、当方の別業務として同時に策定中であるため素案を確認した。本計画の素案には障がい福祉計画への参照がなかった（「障がい福祉計画」「障害福祉」「共生型」のいずれの語も現れていなかった）。★10/13 訂正：当初「同計画の第7章は3計画を扱っており連携の節は置かれていなかった」と書いたが、これは令和8年10月4日の版を見て書いたもので当たらない。同計画は令和8年10月10日に第7章3として連携の節を新設済みであった（申し送り§2・doc89）。無かったのは本計画の側の独立した節である。本計画の側に1-4（障がい福祉計画との関係）・施策4-1（制度間の移行・世帯単位の支援・用具の移行）・施策3-1（共生型サービスの協議）・資9を加え、障がい福祉計画の側の対応は提案として起票した。あわせて、数で揃える3つの対象（第2号被保険者・65歳到達者・適用除外施設入所者）を照会として起票した。適用除外の該当者がいる場合は第1号被保険者数が減り保険料の分母が動く。★残るのは未受領4計画（総合振興計画・保健医療計画・健康21・地域福祉計画・こども計画）の受領と、村のご確認である。★10/12：障がい福祉計画との突合が互いに古い版で行われていたことが分かった（doc87）。版をコミットのハッシュで記録する仕組みを作り（seigo_han.py・点検70）、相手から受け取った照会Ｋ-1〜Ｋ-8の8件すべてに応答と反映先を付けた。★10/13：障がい福祉計画の側から申し送り（令和8年10月12日付）を受け取った（doc89）。相手はまた1つ古い版（e591fe8）を見ていた。内容のハッシュ（sha256 先頭16桁）で版を照合する仕組みを加え（seigo_han.py --shoumei）、決めた16語で両計画の素案を数えて片側のみの記載を洗い出す仕組みを作った（seigo_go.py・点検74）。受け取った照会はＫ-9まで9件、相手へ渡す事項は7件になった。成年後見制度利用支援事業の条文の誤り（第2項第2号→第3項第3号）を正し、別の事業である旨の注記を施策4-7と資9に置いた（点検73）。
A90: Ⅱ-111 | B90: Ⅱ 計画策定 | C90: Ⅱ-6 計画案の検討 | D90: 計画の名称・計画期間の表記の統一 | E90: 仕様書1 | F90: 双方 | G90: 表記ルール | H90: 委託名は「第10期北塩原村高齢者福祉計画・第10期北塩原村介護保険事業計画」。表紙・奥付・本文・図表で統一する | I90: R8.12 | L90: 46273 | N90: 0.9 | O90: 着手 | P90: 委託名は「第10期北塩原村高齢者福祉計画・第10期北塩原村介護保険事業計画」。素案の表紙・第1章・図表の表記をこれに揃えた。奥付とパブリックコメント・委員名簿は確定後に記入する。★10/4：本則を「第10期北塩原村高齢者福祉計画」「令和9年度から令和11年度まで」「3か年」と定め、点検50で素案・第2回資料・第3回骨子を走査するようにした。「3年間」8件と「令和9年度〜令和11年度」1件を直した。
A91: Ⅱ-73 | B91: Ⅱ 計画策定 | C91: Ⅱ-6 計画案の検討 | D91: 一体的策定の範囲の確認 | E91: 確認 | F91: 双方 | G91: 確認メモ | H91: 成年後見制度利用促進基本計画・認知症施策推進計画の継続可否 | I91: R8.11 | L91: 46267 | N91: 0.6 | O91: 着手 | P91: ★議事録により整合対象が確定：国の基本方針・総合計画・障がい福祉計画・地域福祉計画・グッドヘルスプラン（21計画）・生涯学習計画。生涯学習計画は受領済（doc21）。
A92: Ⅱ-74 | B92: Ⅱ 計画策定 | C92: Ⅱ-7 計画書の作成 | D92: 骨子案の作成 | E92: 仕様書4Ⅱ(7) | F92: 受託者 | G92: 骨子案 | I92: R8.11〜12 | L92: 46265 | M92: 46265 | N92: 1 | O92: 完了 | P92: doc15として全6章の章構成・節構成・想定頁数を確定。素案の作成に移行。
A93: Ⅱ-75 | B93: Ⅱ 計画策定 | C93: Ⅱ-7 計画書の作成 | D93: 素案の作成 | E93: 仕様書4Ⅱ(7) | F93: 受託者 | G93: 素案 | I93: R8.12〜R9.1 | L93: 46267 | N93: 0.98 | O93: 着手 | P93: 記載事項10件を追記し資料編に資6（基本指針の別表11事項への対応）・資7（主な参照資料）・資8（図表番号一覧）を新設（doc49）。図を4点追加し25点とした。図表番号を本文に現れる順に振り直し、画像に焼き込まれた番号との食い違い9図を解消。見える化との突合により費用額の順位の誤り4か所を訂正（doc52）。交付金の目標別の推移を追加（doc53）。反映版との統合を完了し認定の時点を令和8年3月末に確定（doc54）。積算113頁・確定版103頁。【紙面（改頁・表の分割・図の配置）の目視確認は未実施】（変換ができない環境のため）。★10/2：2-3に性・年齢調整済み認定率、2-5に医療と介護の連携の状況を加えた。一元化により2-4の県との差の誤り（▲4,384→▲4,385）を見つけて直した。★10/5：素案を通読し、数値を伏せて一致する文を機械で洗い出した。1,040文のうち7組が重複しており、見込量の原則（4-3と5-4）・入所希望48.5%（2-10と施策3-3）・除雪の第1位（2-11と施策2-6）・通いの場の箇所数（2-6と施策1-1）・包括の職員体制（2-6と施策4-1）・認知症の32点（4-4と施策4-4と4-7）の6か所を、正本を1つに定めて参照に替えた。あわせて2-11の冒頭が「次の5点」のまま課題が6本になっていたのを直した。点検55（同じ文を2か所で述べていないこと）・点検56（「次のN点」の宣言と実際の数が合うこと）を新設して固定した。なお第2章（現状）と第4章（施策）で同じ事実に触れること自体は読み手に必要な繰り返しであり、数値や根拠を残したうえで文の重複だけを解いた。【紙面の目視確認は引き続き未実施】（変換ができない環境のため）。★10/5（第2報）：レビューで見つけた欠陥が他の箇所にも及んでいないかを確かめ、3件を直した。(1) 3-4の「新規・新設は10施策あり」が構造と合っていなかった（実際は新規5＋新設4＝9施策）。(2) 施策2-5（地域支え合い活動の促進）と施策4-5（生活支援体制の整備）が生活支援体制整備事業を二重に扱い、同じ指標「生活支援コーディネーターの地域ケア会議参加割合」に異なる目標値（100%と維持）を置いていた。体制は施策4-5を正本とし、施策2-5は住民の活動（見守り・老人クラブ・ボランティア）に絞って指標を入れ替えた。4-6の老人クラブの確保の方策も合わせて直した。(3) 5-11の1ポイントあたりの額を5-7への参照に替えた。重複の点検のしきい値を実測し直し、30文字では9組のうち5組しか出ないことが分かったため12文字に下げた。★10/10：libreoffice-writer と poppler-utils を入れ、docx を PDF に変換して紙面を実測した（doc83）。【これまで未実施としていた紙面の確認ができるようになった。】実測により推定の前提の誤りが3件見つかった。(1) 表の幅に本文幅（9638）を使っていたが実際は TBLW（9360）で、折り返しを少なく数えていた。(2) 表の1行の下駄は罫線を含めて127 twip（宣言は120）であった。(3) estimate_layout の「頁超」の分岐に死にコードが残っていた。あわせて docx 側の欠陥を2件直した。行送りに lineRule を書いていなかったため Word ではw:line が倍率として読まれ、頁数がフォント次第になっていた（4つの build の15か所に exact を指定）。委員会資料・照会票に既定の書体の宣言がなく、12文字が欧文の明朝で出ていた。前提を直した後の推定は素案135頁・計画書118頁で、実測はそれぞれ137頁・120頁である（差は送りの空白）。計画書は本文120頁＋前付4頁＝124頁となり、削減案A〜Lをすべて行っても111頁で、村が許容する110頁に1頁足りない（点検52が不適合）。足りない1頁の当て方はⅡ-113で詰める。なお游ゴシックは本環境に無く IPAゴシックに置き換えた紙面であるため、Word の紙面そのものではない。★10/6：資6の見直しの過程で、事実の誤りを見つけて直した。「村内で提供されている介護サービスは2種類」と7か所で述べていたが、見える化のサービス提供事業所数では訪問介護が1か所あり、正しくは3種類である（訪問介護・通所介護・認知症対応型共同生活介護）。定員が定められているのが通所介護と認知症対応型共同生活介護の2つであることに引かれ、定員のない訪問介護を数え落としていた。訪問系の自給率が41.1%（0%でない）こととも合わない。2-5の事業所数の表には訪問介護1か所が現に載っており、同じ節の中で食い違っていた。点検57を広げ、本文が述べる村内のサービスの種類数が2-5の表と合うことを確かめるようにした。図を2点加えたため、計画書の見込みは110頁から112頁になった（目安100頁に対し+12頁）。★10/12：紙面を通して確かめた（素案139頁。doc86）。表の孤立行5件と見出しの取り残し1件を直し、枠からのはみ出し・図と題の離れ・小さすぎる字はいずれも0件であることを確かめた。あわせて障がい福祉計画との突合を版ごと組み直し、落ちていた照会4点（介護保険優先原則・受給者証・新高額障害福祉サービス等給付費・計画相談支援）を1-4と資9に書き足した（doc87）。
A94: Ⅱ-112 | B94: Ⅱ 計画策定 | C94: Ⅱ-7 計画書の作成 | D94: 策定委員会の審議意見の反映 | E94: 仕様書4Ⅱ(7) | F94: 受託者 | G94: 対応表 | H94: 仕様書(7)は策定委員会の審議とパブリックコメントの双方の意見の反映を求める。従来はパブコメ側のみ計上していた | I94: R8.11〜R9.2 | N94: 0 | O94: 未着手 | P94: ★仕様書Ⅱ(7)は策定委員会の審議とパブリックコメントの双方の意見の反映を求めるが、従来はパブコメ側のみを作業として計上していた。第2回（11月）の審議結果を素案に反映する工程が必要。第2回の資料は doc26 で構成を確定済。
A95: Ⅱ-76 | B95: Ⅱ 計画策定 | C95: Ⅱ-7 計画書の作成 | D95: パブリックコメントの実施 | E95: 仕様書4Ⅱ(7) | F95: 北塩原村 | G95: パブコメ資料・意見 | H95: ★議事録により第2回委員会（11月）の後に実施と確定。方向性や説明文を追記した上で実施 | I95: R8.11〜12 | N95: 0 | O95: 未着手
A96: Ⅱ-77 | B96: Ⅱ 計画策定 | C96: Ⅱ-7 計画書の作成 | D96: パブリックコメント意見の反映 | E96: 仕様書4Ⅱ(7) | F96: 受託者 | G96: 対応表 | H96: 第3回委員会（1月下旬〜2月上旬）で報告 | I96: R8.12〜R9.1 | N96: 0 | O96: 未着手
A97: Ⅱ-78 | B97: Ⅱ 計画策定 | C97: Ⅱ-7 計画書の作成 | D97: 原案の作成 | E97: 仕様書4Ⅱ(7) | F97: 受託者 | G97: 原案 | I97: R9.1〜2 | N97: 0 | O97: 未着手
A98: Ⅱ-79 | B98: Ⅱ 計画策定 | C98: Ⅱ-7 計画書の作成 | D98: 計画書の最終取りまとめ | E98: 仕様書4Ⅱ(7) | F98: 受託者 | G98: 計画書（確定） | I98: R9.2〜3 | N98: 0 | O98: 未着手
A99: Ⅱ-113 | B99: Ⅱ 計画策定 | C99: Ⅱ-7 計画書の作成 | D99: 計画書のレイアウト・校正 | E99: 仕様書4Ⅱ(7) | F99: 受託者 | G99: 校正紙 | H99: 判型・表紙デザインの踏襲可否は村と要協議。印刷入稿の前提 | I99: R9.2〜3 | L99: 46297 | N99: 0.7 | O99: 着手 | P99: 判型・表紙デザインの踏襲可否は村と要協議（確認事項 優先度C）。当方の環境では docx から PDF への変換ができずレイアウトの目視確認ができないため、校正の工程では村側での確認を前提に組む。★10/2：紙面の点検を機械で代替した（estimate_layout.py）。図3-1が1頁に収まらないことを見つけ、図の高さに上限を設けて直した。表の行に cantSplit、見出しと図に keepNext を入れ、頁の境目で割れないようにした。目視確認は変換ができない環境のため未了。★10/4：表の列幅を宣言どおりに固定し（TableLayoutType.FIXED）、文字の幅を文字の種類で見るようにした。keepNextが表の全体を引き連れるという誤りも直した。計画書としての頁数を出せるようにし、編集注記と5-12を除いて105頁＋前付4頁＝109頁（目安100頁に対し+9頁）。1頁の図版（図3-1）は改頁して頁の頭から置く。点検49で2つの推定が矛盾しないことを確かめる。★10/5：計画書が目安100頁に対し+10頁であることから、分量の削減案を試算した（estimate_sakugen.py）。算定の方法の説明・推計の不確かさ・見込量の自己点検・施策の反映・保険料の算定の過程・交付金の明細の6案で10頁減り、本文96頁＋前付4頁＝100頁に収まる。削るのは当方の検証の記述であり、法定の記載事項には触れない。どこまで削るかは村の判断を仰ぐ（確認事項K-190）。点検52で案が実在する小見出しを指すことを確かめている。目視確認は変換ができない環境のため未了。★10/6：交付金の評価が求める分析の空白を埋める図2点を加えたため、見込みが本文106頁＋前付4頁＝110頁から本文108頁＋前付4頁＝112頁になった。削減案6案をすべて行っても本文100頁＋前付4頁＝104頁で、目安を4頁上回る。目安ちょうどに収めるには用語の解説の絞り込み（案G）もあわせて行う必要がある。この2図は交付金の評価に直接効くため残すことを勧めるが、分量を優先する場合は資料編に移すこともできる旨をK-190に書いた。★10/9：削減案を総当たりで試算した。案G（用語の解説の絞り込み）は0頁で、頁のためには行う意味がない。69語のうち本文に一度も現れないのは8語だが、落としても頁は減らない。一方、10月6日に加えた図2点を資料編に移すと2頁減る（案H）。到達できる最小はA〜F＋Hの101頁で、目安100頁に対し+1頁（★10/8に5-7を組み替えて本文が1頁増えたため102頁・+2頁に改めた）。これ以上は介護保険法117条2項が求める事項か前付（4頁）に手を入れることになるため勧めない。仕様書5①は「約100頁」であり102頁はその範囲と解されるが、どの案を行うかは村の判断としてK-190に書いた。試算に組み合わせの総当たりを組み込み、点検52でG・Hの効果も報告するようにした。★10/12：削減案12案（A〜H・J〜M）の対応表を実測で作った（doc84）。組み合わせごとに計画書を組んでPDFに変換し、何も行わない125頁からA〜Mの109頁までを数えた。村の許容110頁に収まるのはA〜L（110頁）とA〜M（109頁）である。紙面も通して確かめ、表の孤立行5件と見出しの取り残し1件を直した（doc86）。残るのはどの案を行うかの村のご判断である。
A100: Ⅱ-116 | B100: Ⅱ 計画策定 | C100: Ⅱ-7 計画書の作成 | D100: 図表データ管理台帳の作成と図の数値の一元化 | E100: 確認 | F100: 受託者 | G100: 11_図表データ管理台帳.xlsx・data_zuhyo.py | H100: 村が数値を直すと本文の図に反映される仕組み。Ⅱ-75と一体 | I100: R8.9〜10 | L100: 46292 | M100: 46297 | N100: 1 | O100: 完了 | P100: 図20点・53系列の数値の正本を data_zuhyo.py に集約し、作図も台帳もそこから読む形にした。台帳は26シート・自己点検17件。村が数値を直すと作図に反映され、取り込まずに台帳を作り直そうとすると止まる。図と素案の表が同じ数値を持つ24系列を02シートに掲げた。★10/2：図と素案の表が同じ数値を持つ32系列を正本に一元化した。台帳の突合が和暦と西暦を寄せておらず9系列を見落としていたのを直して23→32系列。素案の表10本が data_zuhyo から区分の名で引く形になり、じか書きは0系列。自己点検19件。★10/6：図を26点から28点に。交付金との紐付けの表（03シート）で「ない」としていた2件を「ある」に改め、裏づける図のない分析を0件にした。新しい2図は受領データから直接算定する形（算定による図）とし、じか書きしていない。
A101: Ⅱ-117 | B101: Ⅱ 計画策定 | C101: Ⅱ-7 計画書の作成 | D101: 成果品の自己点検（記載事項の網羅性・制約の走査） | E101: 確認 | F101: 受託者 | G101: 各verifyスクリプト・レッドチーム走査 | H101: 素案・委員会資料・集計仕様書・WBSの数値と記載を機械で点検 | I101: 通期 | L101: 46291 | N101: 0.95 | O101: 着手 | P101: 素案45件・委員会資料20件・集計仕様書16件・WBS・見える化52件・台帳17件。レッドチーム走査6本（日本語でない文字／受託者を主語とする語／禁止表現／個人情報／ヘッダー等／半角全角）は走査自体の自己試験つき。点検スキルを .claude/skills/keikaku-check に整備した。★10/2：点検46（図と図の恒等式35本）・47（摂動試験34系列）・48（紙面が成り立つこと）を新設し48件。verify_wbs は点検15（実績日の整合）・16（納品物の網羅）を加えて16件、verify_mieruka は63件。紙面の目視確認のみ環境制約により未了。★10/5：点検53（確保の方策）・54（正負の記号）・55（同じ文の重複）・56（宣言した数との一致）を新設し素案56件。verify_wbs は点検17（媒体が組み立てられること）・18（成果品を組み直せること）を加えて18件、verify_mieruka は71件。点検54で素案の正号が全角74件・半角31件に混在していたこと、委員会資料の負号が▲とダッシュ類に分かれていたことを検出して揃えた。影響度の一覧が確認事項の並びの位置を鍵にしていたため、1件を解決済みに移すと55件すべてがずれる欠陥があり、鍵を見出しの文字列に改めた。★10/5（第2報）：レビューの結果を受けて点検の範囲を見直した。点検55は素案だけを見ていたのを委員会資料にも広げ、しきい値を実測で30→12文字に下げた（30文字では実在の9組のうち5組しか出なかった）。点検56は確認事項（丸数字で並べているもの）にも広げた。点検19はxlsxとtxtだけだったのをdocxにも広げた（26,991件を走査）。点検57（自分の構造を数えて述べている箇所が構造と合うこと）を新設。点検53の施策の集合に基本目標5の4施策（4-5の表の行）が入っていなかったのを直した。新設・改訂した点検はいずれも、欠陥を戻すと不適合になることを自己試験で確かめた。素案57件。★10/5（第3報）：照会票を組んだところ、確認事項2件に古い数が残っていた。計画書の分量を「本文105頁＋前付4頁＝109頁」、頁数の実測を「本文88頁＋前付4頁＝92頁で約100頁に8頁の余裕がある」と述べており、現在の推定（本文106頁＋前付4頁＝110頁）と合っていなかった。確認事項は照会票として村に渡るため、古い数は村に誤った数を示すことになる。点検57を頁数にも広げ、確認事項に書いた頁数が紙面の推定と一致することを確かめるようにした。WBS19件→20件。★10/7：点検58（素案が指す調査票の設問が集計仕様書と合うこと）を新設。素案58件。資6で「介護者の勤務形態（B票 問6）」と書いていたが、B票 問6は不安に感じる介護で勤務形態はB票 問7であった。設問の番号は調査票の改訂で動くため、番号のすぐ前にある語と設問文を突き合わせる形にした。あわせて点検36の判定の基準を改めた。もとは「95〜105頁」という絶対の幅で判定していたが、目安100頁をどれだけ超えるかはK-190として村の判断を仰いでいる事項であり、点検49と点検57がその数を押さえている。同じ問いを3つの点検が別々の基準で見ると、分量が増えたときに点検36だけが落ち続ける。現にそうなったため、点検36は2つの積算の関係（要素を足すだけの積算が送りを追った推定を上回らないこと）だけを見る形に改めた。集計仕様書の点検も、クロス表の件数のじか書きを数え上げに改めた。★10/8：点検59（確認事項が指す素案の節・図が実在すること）を新設し素案59件。見える化の突合は点検72（居住系の受給者数の算出が見える化と合うこと）を加えて72件。確認事項の「ない」と述べている30件を1件ずつ当たり、2件が現に古くなっていた。(1)「施設・居住系はサービス種類別の受給者数の系列がない」→ 居住系2種は算出できる。(2)「医療介護連携の加算の算定状況が未把握」→ 算定率は見える化で把握済み。優先度をBからCへ。参照の走査では、委員会資料の節番号を素案の節と読み違える書き方が1か所あったため「資料3の3-6」と書き改めた。★10/8：点検61（指し先の実在）を枝番（5-4(8)・1-8の3）に加えて丸数字（6-4⑦）も見る形に拡張した。6-4の検証項目を1つ増やしたとき、施策3-5・5-12から「6-4⑦」と指しても誰も確かめられなかったためである。在庫の数え方を一度しくじった。「節のどこかに文字として現れること」では、⑦の行を落としても「⑦は〜に備えるためのものです」という本文が残るため通ってしまう。表の行頭・箇条書きの頭・小見出しの頭に「見出しとして立っている」ところだけを在庫に数える形に改め、欠陥を戻すと3か所で鳴ることを確かめた。点検56（次のN点）・点検57（自分の数）・WBSの点検9・16・21、委員会資料の点検10も、今回の加筆により不適合となったものを直した。★10/9：点検65（第11期の分母の組み方が第10期で復元できること）を新設し素案65件とした。素案の注記は復元の差を印字するだけなので、差が大きくなっても文面は成り立ってしまう。組み方が通らなくなったことを機械で知るための点検である。復元の差が0.5%以内であること、5-7の基金の節に5つの断りがあること、3案の表が estimate_kikin の算定と一致することを見る。自己試験で3つの欠陥（復元の差を3%にする／注記から「3か年に均した」を落とす／表のA案の第10期を6,700円に書き換える）をそれぞれ戻し、いずれも検出することを確かめた。あわせて点検57（自分の数）の拡張を10月9日に行っている。★10/9：点検60（資5の用語と本文の言い方が合っていること）を新設し素案60件。用語集の見出し語が「総合相談支援業務」で本文の「総合相談支援」と違っており、読み手が引けない状態だったのを直した。本文に現れない用語が削減案Gの候補8語と一致することを確かめる形にしたため、用語を足したのに本文で使っていない場合も捕らえる。
...

Sheet 村への確認事項
A1: 北塩原村への確認事項 一覧（基準日：令和8年10月13日）
A2: 優先度S＝9月3日の調査票第1稿提出・9月9日の校了・9月18日の発送を守るために決着が必要（キックオフ議事録で未決着のもの）／A＝令和8年9月中に確定が必要／B＝第1回策定委員会（11月）まで／C＝第2回以降 ｜ 出所の doc番号は docs/北塩原村_第10期/ 配下の分析資料に対応します
A4: 優先度 | B4: 区分 | C4: 確認事項 | D4: なぜ必要か／影響 | E4: 関連WBS No. | F4: 出所 | G4: 状況 | H4: 回答内容・回答日
A5: S | B5: スケジュール | C5: 対象者抽出・宛名ラベル・配布用封筒の提供時期 | D5: 村作業が遅れると発送が連鎖的に遅れる。9/19〜23が5連休。 | E5: Ⅰ-24,Ⅰ-25,Ⅰ-26 | F5: doc01-4 | G5: 未依頼
A6: S | B6: スケジュール | C6: 宛名ラベル・配布用封筒の提供期限の前倒し可否（9/14→9/11） | D6: ★提供が1日遅れると発送が5連休に食い込む。村作業の遅延に対する余裕がない。 | E6: Ⅰ-25,Ⅰ-26 | F6: doc19 指-2 | G6: 未依頼
A7: S | B7: スケジュール | C7: ★策定委員会 現委員の任期満了（令和8年9月30日）と改選手続きの所要期間 | D7: ★議事録で触れられていない。第2回を11月に開催するには10月中の改選・委嘱が必要。 | E7: Ⅱ-80 | F7: doc22 K-76 | G7: 未依頼
A8: S | B8: スケジュール | C8: ★実際の発送日と回収状況（件数・回収率）、ウェブ回答フォームの稼働確認 | D8: ★10/10 起票：村より「高齢者のアンケート発送は全て完了。今集計分析を行なっています」とのご連絡をいただいた。WBSの実績日は、議事録の発送日（令和8年9月18日）と校了日（令和8年9月9日）で置いている。次の4点をご教示いただきたい。①実際の発送日（9月18日は金曜で翌日から5連休であったため、配達が連休明けにずれ込んだ可能性がある）。②本日時点の回収件数（ニーズ調査・在宅介護実態調査それぞれ。対象は882人・118人）。回収率は督促（Ⅰ-31）の判断に用いる。③ウェブ回答フォームの稼働確認の記録の有無と、ウェブ回答の件数。二次元コードを印字して発送した以上フォームは公開されているはずだが、稼働確認の記録が当方にない（Ⅰ-101）。④これまでの受渡しの回数・日・件数。回収は村で100件程度集まるごとに随時小分け送付する運用であり（doc22）、受渡し記録簿（doc74 §4-2）にさかのぼって記録する必要がある。★回収期限は令和8年10月16日（金）である。 | E8: Ⅰ-29,Ⅰ-30,Ⅰ-101,Ⅰ-94 | F8: doc75 | G8: 未依頼
A9: S | B9: データ | C9: ★返信用封筒の差出有効期間の延長 | D9: ★★印刷前に要対応。版下は「差出有効期間 2026年10月16日まで」で回収期限（10月16日）と同日。期限翌日以降に投函された回答は料金受取人払が効かず届かない。通常は回収期限＋2週間程度。回収率に直結する。 | E9: Ⅰ-23,Ⅰ-102 | F9: doc34§1-2 | G9: 未依頼
A10: S | B10: データ | C10: ★ニーズ調査の対象者882人に対応する要介護認定データ（認定の有無・要介護度） | D10: ★2026/09/28に受領した名簿のうち、要介護度の列があるのは在宅介護実態調査の対象者118人分のみで、ニーズ調査の対象者882人分にはない。資料3の3-3（元気な軽度者）・3-4（生活機能からみた4つの層）・3-6（担い手の可能性）は、ニーズ調査の回答者一人ひとりの認定状況を必要とするため、このままでは作成できない。資料3の3-6は第10期に共助・互助の仕組みをどの規模で構想できるかを示す表であり、合意1・2の根拠でもある。★10/10 優先度をAからSに上げた：村より「高齢者のアンケート発送は全て完了。今集計分析を行なっています」とのご連絡をいただいた。集計が動き出した以上、これが入らないと資料3の3-3・3-4・3-6が作れないまま第2回策定委員会（11月）の資料作成に入ることになる。回答データに後から認定状況を付けることはできるため、集計そのものは止まらないが、クロス集計をやり直す手戻りが生じる。できるだけ早くご提供いただきたい。 | E10: Ⅰ-37,Ⅰ-38 | F10: doc43§1 | G10: 未依頼
A11: S | B11: データ | C11: ★要介護認定データの提供時期と項目（要介護度・認定日・サービス利用状況）および総合事業対象者（基本チェックリスト該当者）の情報 | D11: ★仕様書4Ⅰ(5)。ICF分析の「認定状況×生活機能リスク」表と在宅調査のクロスに必須。目的外利用の手続きの確認を含む。議事録の「元気な軽度者が総合事業を利用している」の検証はこの紐付けでしかできない。★9/28：集計軸の認定状況を「認定なし／事業対象者／要支援1・2／要介護1以上」の4区分に統一したため、要介護認定データだけでは事業対象者を判別できない。総合事業の対象者（基本チェックリスト該当者）の情報もあわせてご提供いただきたい。議事録の「元気な軽度者」は事業対象者と要支援認定者の両方を指すため、これがないと検証の対象が半分になる。★10/10 優先度をAからSに上げた（上記と同じ理由。集計が動き出した）。 | E11: Ⅰ-37 | F11: doc24§12 K-87 | G11: 未依頼
A12: S | B12: 分析 | C12: ★ICFを用いたクロス分析の具体的な期待像（軸・アウトプットのイメージ） | D12: ★議事録の新規要件。「元気な高齢者」×「地域のニーズ」で共助・互助の必要性を示す分析。調査票の設計段階でクロス軸を確保しないと後から分析できない。9/3の第1稿に影響。 | E12: Ⅰ-95 | F12: doc22 K-77 | G12: 未依頼
A13: S | B13: 方針 | C13: ★準備基金の取崩額を40,000,000円（残高の94.9%）とすることの可否（第11期が＋32.4%になる関係） | D13: ★国の推計ワークシートは準備基金の残高42,128,183円のうち40,000,000円を取り崩す前提で、第10期の保険料基準額を5,513.72円（第9期6,760.76円比▲18.45%）としている。一方、第11期は取崩の余地が残らないため7,301.29円（＋1,787.57円・＋32.4%）に跳ね上がる見込みである。第10期を下げるほど第11期の上がり幅が大きくなる関係であり、取崩額の水準は世代間の負担の公平に関わる村の判断事項である。厚生労働省の事務連絡3(3)も、保険料が第9期と比べて大きく増減している場合には推計データ全体の確認を求めている。第2回策定委員会の資料6に、取崩額を変えた場合の第10期・第11期の保険料の対比を示す案で進めてよいかをご確認いただきたい。★10/9 あわせてお願いしたいこと：取崩額を0円・24,000,000円とした場合の第10期・第11期の基準額を、推計ワークシートをご操作のうえ出力いただきたい。当方でも試算できるが、第10期の値が確かめられるのに対し、第11期は中長期シートが令和12年度の単年で立っているため、残高を単年に充てるか3か年に均すかで効きが3倍違う（残高42,128,183円の場合、単年基準では月額3,504円、3か年に均すと1,168円）。ワークシートで再計算いただければこの不確かさがなくなる。なお当方の算定（取崩なし6,756円）と国の算定（同6,610.55円）の差は145円であるが、第9期の条例基準額6,700円との向きが逆になる。当方の算定では取崩なしで条例6,800円（＋100円）、国の算定では条例6,600円（▲100円）であり、取崩しをしなくても第9期を下回る。このため資料6の3案のうちC案「保険料の据置きを優先し、基金を最大限取り崩す」は前提が崩れており、3案を国の算定の上に組み直す。 | E13: Ⅱ-63,Ⅱ-64,Ⅱ-107 | F13: doc66§2-3,doc72 | G13: 未依頼
A14: S | B14: 方針 | C14: ★ニーズ調査 問4(15)(16)（社会的役割）を削除するかどうか | D14: ★★印刷前に要決定。国の手引きは問4(13)〜(16)の4項目すべてが「いいえ」で「社会的役割の低下」と判定する。(16)は削除済み、(15)は0909校正で削除の指示。2項目が欠けるとR09が算出できず、見える化への登録も全国・県との比較も不可。R99が10領域→9領域に減るため第9期調査との比較も成立しない。左余白の「見える化関係」の書き込みは(10)〜(14)を指すとみられるが(15)(16)も登録対象である。 | E14: Ⅰ-15,Ⅰ-102 | F14: doc34§1-1 | G14: 未依頼
A15: S | B15: 方針 | C15: ★第9期計画の第1号被保険者数の推計に用いたデータ（国配布の住基ベース推計か別の推計か） | D15: ★国の事務連絡により、福島県では社人研の市町村別推計が公表されておらず第9期でも住基ベース推計が配布されていたことが判明。当方が示してきた「社人研推計をそのまま用いたため6.6%ずれた」という説明の前提が崩れた。第10期の説明の組み立てに影響する。 | E15: Ⅱ-59 | F15: doc28§1-1 K-105 | G15: 未依頼
A16: S | B16: 疑義 | C16: ★【期限 令和8年10月13日18時】令和9年度以降も0で入っている6サービスを0のままとしてよいか | D16: ★★国の推計ワークシートで、令和6・7年度に実績があるのに令和8年度が0になっているサービスが10件あり、うち6件は令和9年度以降も0のままである（介護予防短期入所生活介護／訪問入浴介護／短期入所療養介護（老健）／特定福祉用具購入費／住宅改修費／地域密着型通所介護）。村の申し送りは「福祉用具購入費や住宅改修費は金額が反映されずゼロ」としており、入力漏れの可能性がある。住宅改修費は令和6年度213.1千円・令和7年度314.5千円、特定福祉用具購入費は令和6年度381.2千円・令和7年度128.3千円の実績がある。厚生労働省の事務連絡は国の集計の提出期間を令和8年9月30日9時から10月13日（火）18時（厳守）としており、都道府県が異常値の確認を保険者に依頼して推計を支援する仕組みがあるため、10月13日18時までは修正の余地がある。0のままとするか修正するかを村にご確認いただき、修正する場合は県にご相談いただきたい。 | E16: Ⅱ-56,Ⅱ-62,Ⅱ-107 | F16: doc66§3-1,§5 | G16: 未依頼
... A211: C | B211: 成果品 | C211: 計画書の判型・レイアウト・表紙デザインの踏襲可否 | D211: 第9期はA4・本文104頁・全6章＋資料編。 | E211: Ⅱ-113,Ⅳ-89 | F211: doc01-10 | G211: 未依頼
A213: ■ 解決済み（記録）
A214: ― | B214: 疑義 | C214: 第1号被保険者数・認定者数の推計に2系列が併存していた（社内・解消済） | D214: ★素案5-2・5-3が社人研推計（国勢調査ベース）、5-4以降が厚生労働省配布の推計用人口（住民基本台帳ベース）を用いており、令和11年の認定者数が230人と220人で食い違っていた。厚生労働省配布の系列（B案）に統一し、5-1・5-2・5-3を全面的に書き改めた。介護保険の第1号被保険者数が住民基本台帳を基礎とすること、国の推計ワークシートが同じ配布データを用いることによる。 | E214: Ⅱ-56,Ⅱ-64 | F214: doc35§7-3(1) | G214: 解決済
A215: ― | B215: データ | C215: 成年後見制度（市民後見人養成含む）の利用実態・実績 | D215: 令和7・8年度の成年後見制度利用促進施策に係る取組状況調査（市町村票）と会津権利擁護・成年後見センターの相談件数の受領により解決。利用者4人、市町村長申立て0件、市民後見人の登録0人・受任0件、中核機関・協議会・申立費用助成・報酬助成はいずれも整備済。 | E215: Ⅱ-68,Ⅱ-69 | F215: doc28§3 | G215: 解決済
A216: ― | B216: 体制 | C216: 所管課・窓口の確認（住民課→保健福祉課の変更の有無、担当者体制） | D216: 成年後見の調査票により解決。報告担当課・主管課とも保健福祉課であることを確認した。担当者名・連絡先は個人情報のため本表には記載しない。調査票の問合せ先表記も裏づけられた。 | E216: ０-04 | F216: doc28§4 | G216: 解決済
A217: ― | B217: データ | C217: 所得段階別の第1号被保険者数 | D217: 令和8年度合計所得金額分布調査の入力済み調査票により解決。13段階・合計1,015人。非課税層60.3%、第1〜3段階だけで346人・34.1%。10万円刻みの分布も入手。 | E217: Ⅱ-64 | F217: doc28§2 | G217: 解決済
A218: ― | B218: データ | C218: 第10期の将来推計人口・第1号被保険者数の推計データ | D218: 厚労省配布の第10期将来推計用人口推計（住基ベース）と補正係数の受領により解決。補正後の第1号被保険者数は令和9年946人／令和10年939人／令和11年931人。ただし直近実績を約6%下回る論点あり（K-106）。 | E218: Ⅱ-59 | F218: doc28§1 | G218: 解決済
A219: ― | B219: 調査設計 | C219: ニーズ調査 選択肢の順序が標準と逆になっている7か所の修正 | D219: 第2稿（0904版）で問7の6か所を修正済。誤植2件（「そのような人はいないその他」「いないその他」）も解消。★問1(2)①の1か所が未修正のため別項目として再掲。 | E219: Ⅰ-09 | F219: doc27§1-1 | G219: 解決済（一部再掲）
A220: ― | B220: 調査設計 | C220: 在宅介護実態調査 前回指摘2件の反映（介護療養型医療施設の削除／傷病の選択肢13・14の入替） | D220: 第2稿（0904版）で両方とも修正済。 | E220: Ⅰ-10 | F220: doc27§1-2 | G220: 解決済
A221: ― | B221: 調査設計 | C221: 在宅介護実態調査 標準の問13「訪問診療」の復活 | D221: 第2稿（0904版）で復活。★ただし番号が問12として付されており問13が欠番。番号の修正を別項目として再掲。 | E221: Ⅰ-10 | F221: doc27§1-2 | G221: 解決済（番号は再掲）
A222: ― | B222: 調査設計 | C222: 調査の基準日（ニーズ調査・在宅介護実態調査） | D222: キックオフ会議（令和8年9月1日）で決着：令和8年9月1日を基準日とする。 | E222: Ⅰ-08,Ⅰ-24 | F222: doc22 §1 | G222: 解決済
A223: ― | B223: 調査設計 | C223: 在宅介護実態調査 約150人の抽出基準 | D223: キックオフ会議で決着：要支援1・2および要介護1〜5の在宅生活者等、150件。 | E223: Ⅰ-08,Ⅰ-24 | F223: doc22 §1 | G223: 解決済
A224: ― | B224: 成果品 | C224: 施策体系図（基本理念→基本目標5→施策28の階層図）の計画書への掲載 | D224: ★2026/09/25 作成して素案3-4と委員会資料4-4に掲載した。第9期が第3章に掲げていた施策体系とSDGsの対応を、体系図（3-4）と対応表（3-5）の2本立てに再構成したもの。3-4にあった同じ内容の平坦な表は図に置き換えて重複を解いた。計画書の推定は97頁で仕様書の約100頁に3頁の余裕がある。 | E224: Ⅱ-113,Ⅱ-71 | F224: doc41§6 | G224: 解決済
A225: ― | B225: データ | C225: 在宅調査票の管理番号の印字形式（N付きか数字のみか） | D225: ★2026/09/28 決着：調査票の印字見本の「1」はあくまで見本であり、実物には対象者ごとの管理番号が入る。名簿の形式（ニーズは数字のみ、在宅は英字＋数字）がそのまま印字される。当方が印字見本を実物と取り違えて優先度Sとしていたもので、問題は生じない。なお回収後の突合は管理番号によるが、万一欠損した場合は氏名で突合できることを村にご確認いただいた。 | E225: Ⅰ-18,Ⅰ-20,Ⅰ-38 | F225: doc34§5-3,doc43§2-4 | G225: 解決済
... A247: ― | B247: データ | C247: 社会保障審議会介護保険部会（令和8年9月18日）の資料の入手 | D247: ★10/8 解決：第136回社会保障審議会介護保険部会（令和8年9月18日）の資料1〜6および参考資料の提供を受けた。入手できていなかったために保留していた3件は、いずれも原典により確定した。①補足給付の区分の細分化の施行の時期は「令和9年度から」（第3段階②の負担限度額の上乗せは令和8年度から）で、年度の当初からの施行である（資料2）。素案1-8の2・5-12を書き改めた。②調整交付金の一定の取組による減額は、年齢区分の精緻化により交付額が増加する保険者について、①主要3事業（要介護認定の適正化／ケアプラン等の点検／医療情報との突合・縦覧点検）のいずれかを実施していない場合、または②令和9年2月から令和10年1月までの1人あたり給付費が外れ値（平均値＋2×標準偏差）に該当した保険者が、国保連の介護給付適正化システムの帳票を活用した点検（ケアプラン等の点検の実施件数・医療情報との突合の実施率・縦覧点検の実施率）について令和10年度下半期の実施率等を令和9年度下半期以上に保てなかった場合に、増加額の5%を減額するものである（資料5）。素案1-8の3・5-8(3)・6-4⑦を新設・改訂した。③特定地域サービス・特定地域居宅サービス等事業の制度の内容は、本部会の資料には含まれていなかった。引き続き省令・通知および介護給付費分科会の検討の結果を待つ（素案5-12(2)に残置）。あわせて、介護給付適正化計画の期数（第6期＝令和6〜8年度／第7期＝令和9〜11年度）、第1号保険料の標準段階・標準乗率の見直しの論点、介護情報基盤の適合基準日と本格運用開始日、ケアプランデータ連携の導入率と統合の時期、都道府県との協定の仕組み、介護経営DBの報告の再開時期、引き続き検討することとされた9事項が原典により確定した。 | E247: Ⅱ-50,Ⅱ-62,Ⅱ-64 | F247: doc70§2,doc71 | G247: 解決済

Sheet 仕様書対照
A1: 仕様書（委託第27号／8北保福第483号 別紙）とWBSの対照
A2: 仕様書の側から「求められていること」を列挙し、WBSのどの作業がそれを担うかを示したもの。状況の「○」は対応する作業がWBSにあること、「村」は村が実施し受託者の作業を伴わないことを表す ｜ 突合は scripts/verify_wbs.py で機械的に行い、漏れがあれば終了コード1を返す
A4: 区分 | B4: 条項 | C4: 仕様書が求めていること | D4: 担当 | E4: 対応WBS No. | F4: 対応する作業項目 | G4: 状況 | H4: 備考
A5: 見積徴取通知 | B5: 通知2-a | C5: 見積書を令和8年8月21日までに保健福祉課へ提出する | D5: 受託者 | E5: ０-01 | F5: 見積書の提出 | G5: ○
A6: 見積徴取通知 | B6: 通知2-b | C6: 契約保証金は免除 | D6: ― | E6: ０-02 | F6: 契約締結 | G6: ○ | H6: 契約手続の条件。作業を伴わない
A7: 1 委託業務名 | B7: 仕様書1-a | C7: 業務名「第10期北塩原村高齢者福祉計画・第10期北塩原村介護保険事業計画策定業務委託」 | D7: 双方 | E7: Ⅱ-111 | F7: 計画の名称・計画期間の表記の統一 | G7: ○ | H7: 計画書の表紙・奥付・本文の名称はこれに合わせる
A8: 2 業務の目的 | B8: 仕様書2-a | C8: 介護保険制度の改正など社会環境の変化を把握する | D8: 受託者 | E8: Ⅱ-50 Ⅱ-51 | F8: 制度改正動向の資料収集・整理 第10期国の基本指針の確認・反映 | G8: ○
A9: 2 業務の目的 | B9: 仕様書2-b | C9: 第9期計画期間（R6〜R8年度）における介護給付実績を評価する | D9: 受託者 | E9: Ⅱ-55 Ⅱ-56 | F9: 介護保険給付統計の取りまとめ 計画数値の評価（計画値と実績の乖離分析） | G9: ○
A10: 2 業務の目的 | B10: 仕様書2-c | C10: 高齢者福祉施策の実施状況を評価する | D10: 受託者 | E10: Ⅱ-53 Ⅱ-54 | F10: 高齢者福祉事業等の実績資料の受領 高齢者福祉事業等の実施状況の把握と課題整理 | G10: ○
A11: 2 業務の目的 | B11: 仕様書2-d | C11: ニーズ調査・在宅介護実態調査の結果を踏まえる | D11: 受託者 | E11: Ⅰ-48 Ⅱ-52 | F11: 調査結果報告書の執筆・レイアウト 前提条件と基本的課題の明確化 | G11: ○
A12: 2 業務の目的 | B12: 仕様書2-e | C12: 第10期計画期間の課題を明らかにした上で計画案を策定する | D12: 受託者 | E12: Ⅱ-70 Ⅱ-75 | F12: 第10期の課題の整理 素案の作成 | G12: ○
A13: 3 業務期間 | B13: 仕様書3-a | C13: 業務期間は契約締結の日から令和9年3月31日まで | D13: 双方 | E13: ０-02 Ⅳ-96 | F13: 契約締結 納品・検収 | G13: ○ | H13: 履行期限。全工程の外枠
A14: 3 業務期間 | B14: 仕様書3-b | C14: 計画期間は令和9年度から令和11年度までの3か年 | D14: 受託者 | E14: Ⅱ-111 | F14: 計画の名称・計画期間の表記の統一 | G14: ○
A15: 4Ⅰ ニーズ調査 | B15: 仕様書4Ⅰ(1)-a | C15: 調査対象区域は全村域 | D15: 双方 | E15: Ⅰ-08 | F15: 調査対象者の抽出条件の確定 | G15: ○
A16: 4Ⅰ ニーズ調査 | B16: 仕様書4Ⅰ(1)-b | C16: 介護予防・日常生活圏域ニーズ調査は約850人（一般高齢者・総合事業対象者・要支援認定者） | D16: 双方 | E16: Ⅰ-08 Ⅰ-24 | F16: 調査対象者の抽出条件の確定 調査対象者の抽出 | G16: ○ | H16: 実際の抽出は882人
A17: 4Ⅰ ニーズ調査 | B17: 仕様書4Ⅰ(1)-c | C17: 在宅介護実態調査は約150人（在宅の要介護認定者） | D17: 双方 | E17: Ⅰ-08 Ⅰ-24 | F17: 調査対象者の抽出条件の確定 調査対象者の抽出 | G17: ○ | H17: 実際の抽出は118人。2026/09/24 村の了解により決着（集計設計上の扱いは当方の判断事項）
A18: 4Ⅰ ニーズ調査 | B18: 仕様書4Ⅰ(1)-d | C18: 対象者の抽出は村が実施し、受託者へ宛名ラベルシールとして提供する | D18: 北塩原村 | E18: Ⅰ-24 Ⅰ-25 | F18: 調査対象者の抽出 宛名ラベルシールの作成・提供 | G18: ○
A19: 4Ⅰ ニーズ調査 | B19: 仕様書4Ⅰ(2)-a | C19: 厚生労働省が示す調査項目を踏まえて調査票を設計する | D19: 受託者 | E19: Ⅰ-09 Ⅰ-10 Ⅰ-11 | F19: 調査票の設計（ニーズ調査） 調査票の設計（在宅介護実態調査） 令和7年8月版 標準様式との逐条突合 | G19: ○ | H19: 令和7年8月版の標準様式
A20: 4Ⅰ ニーズ調査 | B20: 仕様書4Ⅰ(2)-b | C20: 村の過去の調査を踏まえて設計する（時系列比較の確保） | D20: 双方 | E20: Ⅰ-13 Ⅰ-41 | F20: 村独自設問の設定 時系列比較（第8期・第9期との対比） | G20: ○
A21: 4Ⅰ ニーズ調査 | B21: 仕様書4Ⅰ(2)-c | C21: 村と協議の上で調査票を決定する | D21: 双方 | E21: Ⅰ-12 Ⅰ-15 | F21: オプション項目の採否決定 調査票の村協議・確定 | G21: ○
A22: 4Ⅰ ニーズ調査 | B22: 仕様書4Ⅰ(2)-d | C22: 紙とウェブ回答を併用する | D22: 受託者 | E22: Ⅰ-16 Ⅰ-34 Ⅰ-35 | F22: ウェブ回答フォームの作成 用紙回答のデータ入力 ウェブ回答データの取込 | G22: ○
A23: 4Ⅰ ニーズ調査 | B23: 仕様書4Ⅰ(2)-e | C23: 専用のウェブ回答フォームを作成する | D23: 受託者 | E23: Ⅰ-16 Ⅰ-101 | F23: ウェブ回答フォームの作成 ウェブ回答フォームの公開・稼働確認・受付停止 | G23: ○ | H23: 作成のみならず公開・稼働確認・受付停止までが必要
A24: 4Ⅰ ニーズ調査 | B24: 仕様書4Ⅰ(2)-f | C24: 二次元コードを調査票または依頼状に印字する | D24: 受託者 | E24: Ⅰ-14 Ⅰ-17 | F24: 依頼状（表紙）の作成 二次元コードの作成・調査票／依頼状への印字 | G24: ○
A25: 4Ⅰ ニーズ調査 | B25: 仕様書4Ⅰ(2)-g | C25: 紙・ウェブ双方で回答された場合に重複集計されないよう管理番号等で管理する | D25: 受託者 | E25: Ⅰ-18 Ⅰ-36 | F25: 重複回答の管理方法の設計（管理番号） 重複回答の排除 | G25: ○
A26: 4Ⅰ ニーズ調査 | B26: 仕様書4Ⅰ(3)-a | C26: ニーズ調査票を A4判・約12ページ・黒1色で印刷する | D26: 受託者 | E26: Ⅰ-20 Ⅰ-21 | F26: 入稿データの作成 調査票の印刷（ニーズ調査 A4約12頁・黒1色） | G26: ○
A27: 4Ⅰ ニーズ調査 | B27: 仕様書4Ⅰ(3)-b | C27: 在宅介護実態調査票を A4判・約8ページ・黒1色で印刷する | D27: 受託者 | E27: Ⅰ-20 Ⅰ-22 | F27: 入稿データの作成 調査票の印刷（在宅調査 A4約8頁・黒1色） | G27: ○
A28: 4Ⅰ ニーズ調査 | B28: 仕様書4Ⅰ(3)-c | C28: 封筒（配布用・回収用）を各必要部数用意する | D28: 双方 | E28: Ⅰ-23 Ⅰ-26 Ⅰ-103 | F28: 返信用封筒の印刷 配布用封筒の提供 印刷部数の確定（予備を含む） | G28: ○ | H28: 2026/09/24 決着：配布用封筒は村が用意し費用は村側で請求処理。受託者の印刷は返信用（回収用）のみ
A29: 4Ⅰ ニーズ調査 | B29: 仕様書4Ⅰ(3)-d | C29: 印刷にあたり個人情報の取扱いに十分配慮する | D29: 受託者 | E29: Ⅴ-97 | F29: 個人情報の適正管理（アクセス制限・保管ルール） | G29: ○
A30: 4Ⅰ ニーズ調査 | B30: 仕様書4Ⅰ(3)-e | C30: 印刷物の校了を判断する（条項名「印刷」に含まれる） | D30: 双方 | E30: Ⅰ-102 | F30: 印刷の校正・校了 | G30: ○ | H30: 印刷後は修正できないため、本業務で最もリスクが高い判断
A31: 4Ⅰ ニーズ調査 | B31: 仕様書4Ⅰ(4)-a | C31: 村提供の宛名ラベルシールを配布用封筒に貼付する | D31: 受託者 | E31: Ⅰ-26 Ⅰ-27 | F31: 配布用封筒の提供 宛名ラベルの貼付 | G31: ○
A32: 4Ⅰ ニーズ調査 | B32: 仕様書4Ⅰ(4)-b | C32: 調査票と返信用封筒を封入・封緘する | D32: 受託者 | E32: Ⅰ-28 | F32: 封入・封緘 | G32: ○
A33: 4Ⅰ ニーズ調査 | B33: 仕様書4Ⅰ(4)-c | C33: 発送する | D33: 受託者 | E33: Ⅰ-29 | F33: 発送（郵送費は受託者負担） | G33: ○
A34: 4Ⅰ ニーズ調査 | B34: 仕様書4Ⅰ(4)-d | C34: 回収票は受託者が開封確認のうえデータ入力する | D34: 受託者 | E34: Ⅰ-30 Ⅰ-32 Ⅰ-33 Ⅰ-34 | F34: 回収状況の管理 回収期限の管理・締切 開封確認 用紙回答のデータ入力 | G34: ○
A35: 4Ⅰ ニーズ調査 | B35: 仕様書4Ⅰ(4)-e | C35: 発送費用は受託者の負担とする | D35: 受託者 | E35: Ⅰ-29 | F35: 発送（郵送費は受託者負担） | G35: ○ | H35: 往復約1,000通分
A36: 4Ⅰ ニーズ調査 | B36: 仕様書4Ⅰ(5)-a | C36: 厚生労働省が提示する集計ファイル様式を基本として入力する | D36: 受託者 | E36: Ⅰ-34 Ⅰ-35 Ⅰ-46 | F36: 用紙回答のデータ入力 ウェブ回答データの取込 見える化システム登録用データの作成 | G36: ○
A37: 4Ⅰ ニーズ調査 | B37: 仕様書4Ⅰ(5)-b | C37: 在宅介護実態調査は厚生労働省提供の認定データ自動関連付けプログラムを活用できる入力とする | D37: 双方 | E37: Ⅰ-07 Ⅰ-37 Ⅰ-38 | F37: 調査手法の決定（在宅：手法Ⅰ〜Ⅳ） 要介護認定データの受領 認定データとの関連付け（自動プログラム） | G37: ○
A38: 4Ⅰ ニーズ調査 | B38: 仕様書4Ⅰ(5)-c | C38: 入力を管理する（条項名「入力管理」＝入力後の精度の確認） | D38: 受託者 | E38: Ⅰ-104 | F38: 入力データの精度管理（論理チェック・ベリファイ） | G38: ○
A39: 4Ⅰ ニーズ調査 | B39: 仕様書4Ⅰ(6)-a | C39: 単純集計を行う | D39: 受託者 | E39: Ⅰ-39 | F39: 単純集計 | G39: ○
A40: 4Ⅰ ニーズ調査 | B40: 仕様書4Ⅰ(6)-b | C40: 基本属性別のクロス集計を行う | D40: 受託者 | E40: Ⅰ-40 | F40: 基本属性別クロス集計（地区・性別・年齢） | G40: ○
A41: 4Ⅰ ニーズ調査 | B41: 仕様書4Ⅰ(6)-c | C41: 時系列比較・設問間クロス等の詳細は村と協議の上で決定する | D41: 双方 | E41: Ⅰ-41 Ⅰ-42 | F41: 時系列比較（第8期・第9期との対比） 設問間クロス集計 | G41: ○
A42: 4Ⅰ ニーズ調査 | B42: 仕様書4Ⅰ(6)-d | C42: 分析を行う（自由記述・在宅調査の分析を含む） | D42: 受託者 | E42: Ⅰ-44 Ⅰ-45 | F42: 自由記述の整理 在宅調査の要介護度別・介護者就労状況別分析 | G42: ○
A43: 4Ⅰ ニーズ調査 | B43: 仕様書4Ⅰ(7)-a | C43: 設問ごとにグラフを作成する | D43: 受託者 | E43: Ⅰ-47 | F43: 設問ごとのグラフ作成 | G43: ○
A44: 4Ⅰ ニーズ調査 | B44: 仕様書4Ⅰ(7)-b | C44: 分析結果を報告書に取りまとめる | D44: 受託者 | E44: Ⅰ-48 Ⅰ-49 | F44: 調査結果報告書の執筆・レイアウト 報告書の村確認・修正 | G44: ○
A45: 4Ⅱ 計画策定 | B45: 仕様書4Ⅱ(1)-a | C45: 介護保険制度・高齢者の保健／医療／福祉をめぐる制度改正動向の関連資料を収集・整理する | D45: 受託者 | E45: Ⅱ-50 Ⅱ-51 | F45: 制度改正動向の資料収集・整理 第10期国の基本指針の確認・反映 | G45: ○
A46: 4Ⅱ 計画策定 | B46: 仕様書4Ⅱ(1)-b | C46: 次期計画の前提条件を明確化する | D46: 受託者 | E46: Ⅱ-52 | F46: 前提条件と基本的課題の明確化 | G46: ○
A47: 4Ⅱ 計画策定 | B47: 仕様書4Ⅱ(1)-c | C47: 次期計画の基本的課題を明確化する | D47: 受託者 | E47: Ⅱ-52 | F47: 前提条件と基本的課題の明確化 | G47: ○
... A57: 4Ⅱ 計画策定 | B57: 仕様書4Ⅱ(3)②-a | C57: 各介護保険サービスの見込量を推計する | D57: 受託者 | E57: Ⅱ-61 | F57: 各介護保険サービス見込量の推計 | G57: ○
A58: 4Ⅱ 計画策定 | B58: 仕様書4Ⅱ(3)②-b | C58: 地域密着型サービスの必要利用定員総数を定める | D58: 受託者 | E58: Ⅱ-105 | F58: 地域密着型サービスの必要利用定員総数の設定 | G58: ○ | H58: 介護保険法117条2項1号（義務）。仕様書の「各介護保険サービス見込量」に含まれる
A59: 4Ⅱ 計画策定 | B59: 仕様書4Ⅱ(3)②-c | C59: 地域支援事業の量を見込む | D59: 受託者 | E59: Ⅱ-106 | F59: 地域支援事業の量の見込みと事業費の算定 | G59: ○ | H59: 介護保険法117条2項2号（義務）。保険料の構成要素でもある
A60: 4Ⅱ 計画策定 | B60: 仕様書4Ⅱ(3)③-a | C60: 介護保険料を算定する | D60: 受託者 | E60: Ⅱ-62 Ⅱ-64 | F60: 給付費の試算 介護保険料の試算（複数案の比較） | G60: ○
A61: 4Ⅱ 計画策定 | B61: 仕様書4Ⅱ(3)③-b | C61: 介護給付費準備基金の取崩しを織り込む | D61: 双方 | E61: Ⅱ-63 | F61: 介護保険準備基金の残高・取崩方針の確認 | G61: ○
A62: 4Ⅱ 計画策定 | B62: 仕様書4Ⅱ(3)③-c | C62: 所得段階別の保険料を設定する | D62: 受託者 | E62: Ⅱ-107 | F62: 所得段階の設定（段階数・保険料率・低所得者軽減） | G62: ○ | H62: 第9期は13段階
A63: 4Ⅱ 計画策定 | B63: 仕様書4Ⅱ(3)③-d | C63: 中長期（2040年度・2050年度）の保険料水準を見通す | D63: 受託者 | E63: Ⅱ-108 | F63: 中長期（令和17・22年度）の保険料見通しの算定 | G63: ○ | H63: 国の基本指針の要請。仕様書の「介護保険料」に含まれる
A64: 4Ⅱ 計画策定 | B64: 仕様書4Ⅱ(3)④-a | C64: 成果目標を設定する | D64: 受託者 | E64: Ⅱ-65 | F64: 成果目標及び活動指標の設定 | G64: ○
A65: 4Ⅱ 計画策定 | B65: 仕様書4Ⅱ(3)④-b | C65: 活動指標を設定する | D65: 受託者 | E65: Ⅱ-65 | F65: 成果目標及び活動指標の設定 | G65: ○
A66: 4Ⅱ 計画策定 | B66: 仕様書4Ⅱ(3)④-c | C66: 給付適正化に関し取り組むべき施策とその目標を定める | D66: 受託者 | E66: Ⅱ-109 | F66: 給付適正化に係る取組内容と目標の設定 | G66: ○ | H66: 介護保険法117条2項3号・4号（義務）。仕様書の「成果目標及び活動指標」に含まれる
A67: 4Ⅱ 計画策定 | B67: 仕様書4Ⅱ(4)-a | C67: 現行計画の成果と課題を踏まえる | D67: 受託者 | E67: Ⅱ-66 | F67: 現行計画の成果と課題の整理 | G67: ○
A68: 4Ⅱ 計画策定 | B68: 仕様書4Ⅱ(4)-b | C68: 環境整備を検討する | D68: 受託者 | E68: Ⅱ-67 | F68: 次期計画に盛り込む施策の検討 | G68: ○
A69: 4Ⅱ 計画策定 | B69: 仕様書4Ⅱ(4)-c | C69: 支援体制の構築等を検討する | D69: 受託者 | E69: Ⅱ-67 | F69: 次期計画に盛り込む施策の検討 | G69: ○
A70: 4Ⅱ 計画策定 | B70: 仕様書4Ⅱ(4)-d | C70: 老人福祉事業の量の目標を定める | D70: 受託者 | E70: Ⅱ-110 | F70: 老人福祉事業の量の目標の設定 | G70: ○ | H70: 老人福祉法20条の8第2項（義務）。仕様書の「高齢者福祉施策の検討」に含まれる
A71: 4Ⅱ 計画策定 | B71: 仕様書4Ⅱ(5)-a | C71: 村から利用実態・考え方等の情報提供を受ける | D71: 北塩原村 | E71: Ⅱ-68 | F71: 制度の利用実態・考え方の情報提供 | G71: ○
A72: 4Ⅱ 計画策定 | B72: 仕様書4Ⅱ(5)-b | C72: 成年後見制度の利用促進の方向性・計画案を提示する | D72: 受託者 | E72: Ⅱ-69 | F72: 利用促進の方向性・計画案の提示 | G72: ○
A73: 4Ⅱ 計画策定 | B73: 仕様書4Ⅱ(5)-c | C73: 広域調整など関係機関との調整・協議は村が実施する | D73: 北塩原村 | E73: ― | F73: ― | G73: 村 | H73: 受託者の作業ではない。受託者は計画案の提示にとどまる
A74: 4Ⅱ 計画策定 | B74: 仕様書4Ⅱ(6)-a | C74: 課題を整理し、これに対応した計画案を検討・作成する | D74: 受託者 | E74: Ⅱ-70 Ⅱ-71 | F74: 第10期の課題の整理 施策体系の整理 | G74: ○
A75: 4Ⅱ 計画策定 | B75: 仕様書4Ⅱ(6)-b | C75: 国の基本指針との整合を図る | D75: 受託者 | E75: Ⅱ-51 Ⅱ-72 | F75: 第10期国の基本指針の確認・反映 関連計画との整合確認 | G75: ○
A76: 4Ⅱ 計画策定 | B76: 仕様書4Ⅱ(6)-c | C76: 北塩原村第五次総合振興計画との整合を図る | D76: 受託者 | E76: Ⅱ-72 | F76: 関連計画との整合確認 | G76: ○ | H76: ★上位計画が未受領
A77: 4Ⅱ 計画策定 | B77: 仕様書4Ⅱ(6)-d | C77: 第3次健康21・北塩原村グッドヘルスプランとの整合を図る | D77: 受託者 | E77: Ⅱ-72 | F77: 関連計画との整合確認 | G77: ○ | H77: ★未受領
A78: 4Ⅱ 計画策定 | B78: 仕様書4Ⅱ(6)-e | C78: 整合対象の「等」に含まれる計画の範囲を確認する | D78: 双方 | E78: Ⅱ-73 | F78: 一体的策定の範囲の確認 | G78: ○ | H78: 認知症施策推進計画・成年後見制度利用促進基本計画の一体化の継続可否
A79: 4Ⅱ 計画策定 | B79: 仕様書4Ⅱ(7)-a | C79: 策定委員会での審議の意見を反映する | D79: 受託者 | E79: Ⅱ-112 | F79: 策定委員会の審議意見の反映 | G79: ○
A80: 4Ⅱ 計画策定 | B80: 仕様書4Ⅱ(7)-b | C80: パブリックコメントを実施する（村が実施） | D80: 北塩原村 | E80: Ⅱ-76 | F80: パブリックコメントの実施 | G80: ○
A81: 4Ⅱ 計画策定 | B81: 仕様書4Ⅱ(7)-c | C81: パブリックコメントの意見を反映する | D81: 受託者 | E81: Ⅱ-77 | F81: パブリックコメント意見の反映 | G81: ○
A82: 4Ⅱ 計画策定 | B82: 仕様書4Ⅱ(7)-d | C82: 計画書を最終取りまとめする | D82: 受託者 | E82: Ⅱ-74 Ⅱ-75 Ⅱ-78 Ⅱ-79 | F82: 骨子案の作成 素案の作成 原案の作成 計画書の最終取りまとめ | G82: ○
A83: 4Ⅱ 計画策定 | B83: 仕様書4Ⅱ(7)-e | C83: 印刷入稿に足るレイアウト・校正を行う | D83: 受託者 | E83: Ⅱ-113 | F83: 計画書のレイアウト・校正 | G83: ○
A84: 4Ⅱ 計画策定 | B84: 仕様書4Ⅱ(8)-a | C84: 策定委員会の会議資料を作成する | D84: 受託者 | E84: Ⅱ-81 Ⅱ-83 Ⅱ-85 | F84: 第1回 会議資料の作成 第2回 会議資料の作成 第3回 会議資料の作成 | G84: ○
A85: 4Ⅱ 計画策定 | B85: 仕様書4Ⅱ(8)-b | C85: 策定委員会に出席する | D85: 受託者 | E85: Ⅱ-82 Ⅱ-84 Ⅱ-86 | F85: 第1回 会議出席・会議記録（要旨）の作成 第2回 会議出席・会議記録（要旨）の作成 第3回 会議出席・会議記録（要旨）の作成 | G85: ○
A86: 4Ⅱ 計画策定 | B86: 仕様書4Ⅱ(8)-c | C86: 会議記録（要旨）を作成する | D86: 受託者 | E86: Ⅱ-82 Ⅱ-84 Ⅱ-86 | F86: 第1回 会議出席・会議記録（要旨）の作成 第2回 会議出席・会議記録（要旨）の作成 第3回 会議出席・会議記録（要旨）の作成 | G86: ○
A87: 4Ⅱ 計画策定 | B87: 仕様書4Ⅱ(8)-d | C87: 開催回数は3回程度 | D87: 受託者 | E87: Ⅱ-80 | F87: 委員の改選・委嘱 | G87: ○ | H87: 第1回は受託前に開催済み。現委員の任期は令和8年9月30日満了で改選が前提
A88: 4Ⅲ 打合せ等 | B88: 仕様書4Ⅲ-a | C88: 計画策定業務の実施中、必要に応じて打合せを実施する | D88: 双方 | E88: ０-03 Ⅲ-87 | F88: キックオフ会議の開催 定例打合せの実施（電話・オンライン・対面） | G88: ○
A89: 4Ⅲ 打合せ等 | B89: 仕様書4Ⅲ-b | C89: 打合せは電話・面談（オンライン・対面）による | D89: 双方 | E89: Ⅲ-87 | F89: 定例打合せの実施（電話・オンライン・対面） | G89: ○
A90: 4Ⅲ 打合せ等 | B90: 仕様書4Ⅲ-c | C90: 資料の授受を行う | D90: 双方 | E90: ０-04 Ⅲ-88 | F90: 連絡体制・資料授受方法の確定 資料授受の管理 | G90: ○
A91: 5 業務成果品 | B91: 仕様書5①-a | C91: 計画書を A4判・両面約100頁・モノクロで作成する | D91: 受託者 | E91: Ⅳ-89 | F91: 計画書の印刷・製本（A4両面約100頁・くるみ製本） | G91: ○
A92: 5 業務成果品 | B92: 仕様書5①-b | C92: 計画書はコピー／くるみ製本とする | D92: 受託者 | E92: Ⅳ-89 | F92: 計画書の印刷・製本（A4両面約100頁・くるみ製本） | G92: ○
A93: 5 業務成果品 | B93: 仕様書5①-c | C93: 計画書を50部納品する | D93: 受託者 | E93: Ⅳ-89 Ⅳ-96 | F93: 計画書の印刷・製本（A4両面約100頁・くるみ製本） 納品・検収 | G93: ○
A94: 5 業務成果品 | B94: 仕様書5②-a | C94: アンケート調査報告書を A4判・両面約100頁・モノクロ・ホチキス製本で作成する | D94: 受託者 | E94: Ⅳ-90 | F94: アンケート調査報告書の印刷・製本（ホチキス製本） | G94: ○ | H94: 2026/09/24 決着：仕様書どおり約100頁に統一。第Ⅱ部（分析編25頁）は維持し第Ⅰ部・資料編で18頁を圧縮（doc24§1-1）
A95: 5 業務成果品 | B95: 仕様書5②-b | C95: アンケート調査報告書を10部納品する | D95: 受託者 | E95: Ⅳ-90 Ⅳ-96 | F95: アンケート調査報告書の印刷・製本（ホチキス製本） 納品・検収 | G95: ○
A96: 5 業務成果品 | B96: 仕様書5③-a | C96: 成果品及び関連データを収録した電子媒体（Word・Excel・PowerPoint・PDF形式等／CD-R等）を納品する | D96: 受託者 | E96: Ⅳ-91 Ⅳ-96 | F96: 電子媒体の作成（Word/Excel/PowerPoint/PDF） 納品・検収 | G96: ○
A97: 5 業務成果品 | B97: 仕様書5③-b | C97: 電子媒体に収録する「関連データ」の範囲を定める | D97: 双方 | E97: Ⅳ-114 | F97: 納品物に収録する範囲の確定（個人情報の非収録） | G97: ○ | H97: 回答原票・管理番号対応表を含めるかは仕様書6(1)と一体で判断する
A98: 6 その他 | B98: 仕様書6(1)-a | C98: 業務上知り得た個人情報を第三者に開示・漏洩しない | D98: 受託者 | E98: Ⅴ-97 | F98: 個人情報の適正管理（アクセス制限・保管ルール） | G98: ○
A99: 6 その他 | B99: 仕様書6(1)-b | C99: 契約期間終了後・契約解除後も同様とする | D99: 受託者 | E99: Ⅴ-98 | F99: 業務完了後の情報の返還・消去 | G99: ○
A100: 6 その他 | B100: 仕様書6(2)-a | C100: 業務の全部を一括して再委託してはならない | D100: 受託者 | E100: Ⅴ-99 | F100: 再委託の書面承諾の取得 | G100: ○
A101: 6 その他 | B101: 仕様書6(2)-b | C101: 一部を再委託する場合は事前に書面で村の承諾を得る | D101: 双方 | E101: Ⅴ-99 | F101: 再委託の書面承諾の取得 | G101: ○ | H101: 印刷・データ入力・ウェブフォーム構築を外注する場合に該当
A102: 6 その他 | B102: 仕様書6(3)-a | C102: 北塩原村委託契約約款に準拠する | D102: 双方 | E102: ０-02 | F102: 契約締結 | G102: ○
A103: 6 その他 | B103: 仕様書6(4)-a | C103: 疑義が生じたときは村と受託者で協議する | D103: 双方 | E103: Ⅴ-100 | F103: 進捗管理・課題管理 | G103: ○ | H103: 確認事項一覧（本管理表 第2シート）がこの協議の記録を担う
A105: ■ 仕様書に直接の根拠を持たない作業（何に基づき、どの条項の履行を支えるか）
A106: 根拠の種別 | B106: WBS No. | C106: 作業項目 | D106: 担当 | E106: 支える条項 | F106: 位置づけ
A107: 確認 | B107: ０-06 | C107: 見える化システムのID・パスワードの受領 | D107: 北塩原村 | E107: 仕様書4Ⅱ(3) | F107: 見える化システムが人口・認定者・給付費の推計の基礎データである
A108: 手引き／確認 | B108: Ⅰ-07 | C108: 調査手法の決定（在宅：手法Ⅰ〜Ⅳ） | D108: 双方 | E108: 仕様書4Ⅰ(5) | F108: 手引きの手法Ⅰ〜Ⅳのいずれを採るかで認定データ関連付けの可否が決まる
A109: 手引き | B109: Ⅰ-11 | C109: 令和7年8月版 標準様式との逐条突合 | D109: 受託者 | E109: 仕様書4Ⅰ(2) | F109: 「厚生労働省が示す調査項目」の充足を確認する手段
A110: 手引き | B110: Ⅰ-19 | C110: 被保険者番号と照合可能な管理番号の設計 | D110: 双方 | E110: 仕様書4Ⅰ(2) | F110: 重複管理と認定データ関連付けの双方の前提となる管理番号の設計
A111: 確認 | B111: Ⅰ-31 | C111: 督促（リマインド）の実施 | D111: 受託者 | E111: 仕様書4Ⅰ(4) | F111: 回収管理の一環。第9期の在宅調査は回収率45.8%
...

Sheet 受領資料・データ管理
A1: 受領資料・データ管理（基準日：令和8年10月13日）
A2: 仕様書4Ⅲ「資料授受の管理」に対応。★＝未受領で業務進行に影響するもの
A4: 区分 | B4: 資料・データ名 | C4: 内容・数量 | D4: 受領日 | E4: 整理先 | F4: 状況
A5: 仕様書 | B5: 委託第27号 仕様書（8北保福第483号 別紙） | C5: 業務内容・成果品・その他条件 | D5: 46259 | E5: docs/…/01_業務内容整理.md | F5: 受領済
A6: 現行計画 | B6: 第9期北塩原村高齢者福祉計画・介護保険事業計画 | C6: 本文104頁・全6章＋資料編 | D6: 46259 | E6: docs/…/01_業務内容整理.md | F6: 受領済
A7: 現行計画 | B7: 第9期計画 概要版（表・裏の2ページ） | C7: 基本理念・基本目標・数値①〜⑦・施策体系図 | D7: 46265 | E7: docs/…/08_第9期計画概要_計画実績突合.md | F7: 受領済
A8: 現行計画 | B8: ★北塩原村第五次総合振興計画（2017〜2026） | C8: 上位計画。第六次の策定状況も要確認 | D8: ― | E8: ― | F8: 未受領
A9: 現行計画 | B9: ★第3次健康きたしおばら21 | C9: 関連計画 | D9: ― | E9: ― | F9: 未受領
A10: 調査票 | B10: キックオフ資料（0828版・082802版） | C10: 2版をレビュー済 | D10: 46259 | E10: docs/…/03,06 | F10: 受領済
A11: 調査票 | B11: ニーズ調査・在宅介護実態調査 調査票案（資料B・C・C'） | C11: 修正案まで受領 | D11: 46259 | E11: docs/…/03,04 | F11: 受領済
A12: 国様式 | B12: 令和7年8月版 標準調査票（ニーズ調査・在宅介護実態調査） | C12: 逐条突合の基礎。要確認0件で完了 | D12: 46261 | E12: docs/…/05_令和7年8月版との逐条突合.md | F12: 受領済
A13: 見える化 | B13: A系 人口・世帯／B系 認定者 | C13: 第1号被保険者数・認定者数・認定率ほか | D13: 46259 | E13: data/mieruka_tidy.csv | F13: 受領済
A14: 見える化 | B14: C1 保険料／D系 給付費・受給者・利用回数 | C14: 第1号被保険者1人あたり給付月額ほか | D14: 46265 | E14: data/mieruka_tidy.csv | F14: 受領済
A15: 見える化 | B15: K系 施設数／D13系 給付費 | C15: 村内施設ゼロを確認 | D15: 46265 | E15: data/mieruka_tidy.csv | F15: 受領済
A16: 見える化 | B16: D25〜D30 定員／F15〜F25 地域包括支援センター | C16: 定員は平成30年度以降据置 | D16: 46265 | E16: docs/…/02 追記3 | F16: 受領済
A17: 見える化 | B17: F1〜F14・F28〜F40 日常生活支援総合事業 | C17: 17系列が実データなし（＝未実施） | D17: 46265 | E17: docs/…/02 追記3 | F17: 受領済
A18: 見える化 | B18: D47・D48 介護保険特別会計 歳入・歳出 | C18: 平成26〜令和5年度決算 | D18: 46265 | E18: docs/…/02 追記3 | F18: 受領済
A19: 見える化 | B19: W系 保険者機能強化推進交付金 評価指標（77ファイル） | C19: 令和3〜5年度。0点項目21件を抽出 | D19: 46265 | E19: docs/…/07 | F19: 受領済
A20: 見える化 | B20: W138〜W155 アウトプット・アウトカム指標（18ファイル） | C20: 令和5年度 | D20: 46265 | E20: docs/…/07 | F20: 受領済
A21: 見える化 | B21: 地域分析 P1〜P4 | C21: 県平均・全国平均・県内順位・全国順位 | D21: 46265 | E21: docs/…/09 | F21: 受領済
A22: 村データ | B22: ★介護給付費準備基金の現在高 | C22: 令和6年度末実績・令和7年度末見込 | D22: ― | E22: ― | F22: 未受領
A23: 村データ | B23: ★令和6年度決算・令和7年度給付費見込 | C23: 第9期の乖離確定に必要 | D23: ― | E23: ― | F23: 未受領
A24: 村データ | B24: ★通いの場の実数（令和3〜7年度） | C24: 見える化は令和2年度で更新停止。令和6年度分のみ受領 | D24: ― | E24: ― | F24: 一部受領
A25: 村データ | B25: ★高齢者福祉事業（村単独事業）の実績 | C25: 現行計画の評価に必要 | D25: ― | E25: ― | F25: 未受領
A26: 成果物 | B26: 第10期 要介護度別認定者数の推計（doc29／data/…推計.csv） | C26: 前期・後期別の認定率に分解。基準年が実績と完全一致 | D26: 46272 | E26: docs/…/29_要介護認定者数の推計.md | F26: 作成済
A27: 国資料 | B27: 第10期将来推計用人口推計（北塩原村のみ）＋推計の考え方（別紙1・2） | C27: 住基ベース推計と補正係数。令和22年まで。厚労省R8.8.24事務連絡／県R8.8.25通知 | D27: 46272 | E27: docs/…/28_受領資料分析…md §1 | F27: 受領済
A28: 村データ | B28: 令和8年度 合計所得金額分布調査 調査票（入力済） | C28: 所得段階別の第1号被保険者数13段階・合計1,015人。10万円刻みの分布を含む | D28: 46272 | E28: docs/…/28_受領資料分析…md §2 | F28: 受領済
A29: 村データ | B29: 成年後見制度利用促進施策に係る取組状況調査（令和7・8年度 市町村票） | C29: 利用者4人、中核機関整備済、市民後見人0人ほか | D29: 46272 | E29: docs/…/28_受領資料分析…md §3 | F29: 受領済
A30: 村データ | B30: 会津権利擁護・成年後見センター 相談件数（令和6・7年度） | C30: 本村 令和6年度134件／令和7年度76件。圏域13市町村の比較表 | D30: 46272 | E30: docs/…/28_受領資料分析…md §3-3 | F30: 受領済
A31: 調査票 | B31: 調査票 第2稿（0904版） | C31: 指摘13件のうち11件が反映。必須修正3件を新たに検出 | D31: 46269 | E31: docs/…/27_調査票第2稿レビュー.md | F31: 受領済
A32: 成果物 | B32: 第2回策定委員会 資料2・5・6・7（output/08_第2回策定委員会資料.docx） | C32: 26表・A4約30頁。資料2と7は本体完成、資料5と6は骨格 | D32: 46268 | E32: docs/…/26_第2回策定委員会_資料構成.md §11 | F32: 作成済
A33: 成果物 | B33: 集計仕様書（output/07_集計仕様書.xlsx） | C33: 6シート。ニーズ80設問・在宅26設問・派生変数20・クロス表20 | D33: 46268 | E33: docs/…/25_集計仕様書.md | F33: 作成済
A34: 成果物 | B34: 第2回策定委員会 資料構成（doc26） | C34: 資料1〜8・約53頁＋素案別冊。合意事項5点 | D34: 46268 | E34: docs/…/26_第2回策定委員会_資料構成.md | F34: 作成済
A35: 調査票 | B35: 調査票 第1稿（ニーズ調査・在宅介護実態調査） | C35: 0828版。令和7年8月版・手法Ⅲ標準様式と全面突合 | D35: 46267 | E35: docs/…/23_調査票第1稿レビュー_ICF分析設計.md | F35: 受領済
A36: 国資料 | B36: 令和8年度 交付金評価指標（市町村分）配点表 | C36: 全17頁。推進400点・支援400点、目標Ⅰ〜Ⅳ各100点 | D36: 46267 | E36: docs/…/20_交付金評価結果分析.md | F36: 受領済
A37: 国資料 | B37: 令和6年度 該当状況調査票集計表（全国一覧表） | C37: 全国1,741市町村。村は第398行。合計295点 | D37: 46267 | E37: docs/…/20_交付金評価結果分析.md | F37: 受領済
... A46: 村データ | B46: 調査対象者名簿（在宅介護実態調査118人・要介護度を含む） | C46: ★個人情報を含む。要介護1が49人・2が30人・3が18人・4が14人・5が7人 | D46: 46293 | E46: docs/…/43_調査対象者データの確認.md | F46: 受領済
A47: 村データ | B47: ★要介護認定データ（調査票との関連付け用） | C47: 仕様書4Ⅰ(5)。調査回収後に必要 | D47: ― | E47: ― | F47: 未受領
A48: 村データ | B48: 第10期介護保険事業計画 推計ワークシート（将来推計総括表。令和8年10月5日出力） | C48: 県へ10月5日に提出した暫定値。保険料基準額5,513.72円・準備基金残高42,128,183円・取崩額40,000,000円・確定した係数一式。福祉用具購入費・住宅改修費と新サービスは0で入っている | D48: 46302 | E48: docs/…/66_国の推計ワークシートの受領と内容確認.md | F48: 受領済
A49: 村データ | B49: 施設・居住系サービスの整備量見込みシート（令和8年10月6日提出） | C49: 認知症高齢者グループホームの定員27人・整備数0。令和6〜8年度は月平均の実績人数 | D49: 46302 | E49: docs/…/69_施設居住系の見込量を県シートに揃えた.md | F49: 受領済
A50: 村データ | B50: 北塩原村高齢者サービスの手引き（令和8年度版・令和8年4月発行） | C50: ★村単独の高齢者福祉事業の一覧。相談窓口6／生きがい・活動3／教室・イベント4／健康7／お祝い1／福祉サービス12／村内のサービス事業者6事業所。素案4-6の12事業の内容と、2-5の事業所数の裏づけになる。実績値（件数・人数）は載っていない | D50: 46305 | E50: docs/…/76_村受領資料の確認_高齢者サービスの手引きほか.md | F50: 受領済
A51: 社内 | B51: 北塩原村「高齢者福祉・児童福祉・社会福祉」ホームページ整理（令和8年10月10日作成） | C51: ★第8期障がい福祉計画・第4期障がい児福祉計画の検討のために村公式HPを整理したもの。本計画に関わる記述として、生活支援ハウスの名称（シャルムハウス）、除雪サービス登録事業者募集、わたしの思いノート（会津圏域11市町村とセンターの共同作成）、みんなの人権110番、ヘルプマーク等、こども・子育て計画の期間（令和7〜11年度・令和9年度中間見直し）がある。【村HPの二次的な整理であり原典ではない。】当方の環境から村HPを開けないため（proxyが403）、素案には書き込まず確認事項として起票した | D51: 46305 | E51: docs/…/76_村受領資料の確認_高齢者サービスの手引きほか.md | F51: 受領済
A52: 村データ | B52: 緊急連絡カード（様式・2人分） | C52: ★記入欄のみの白紙の様式。住所・固定電話・氏名・性別・血液型・生年月日・持病とお薬・かかりつけ医・緊急連絡先2件・備考。電話機や冷蔵庫の近くに備え付ける運用。施策2-4（見守り）と緊急通報システム事業に関わる | D52: 46305 | E52: 同上 | F52: 受領済
A53: 村データ | B53: 会津権利擁護・成年後見センター 創作劇とトークセッション（令和8年10月23日・24日） | C53: ★北塩原村を含む11市町村とセンターの共催。申込期限は令和8年10月16日。施策4-7（成年後見制度の利用促進）の「制度の周知」の現に行われている取組である | D53: 46305 | E53: 同上 | F53: 受領済
A54: 国資料 | B54: 第136回 社会保障審議会介護保険部会 資料1〜6＋参考資料（令和8年9月18日） | C54: 第10期の計画期間に関わる事項。補足給付の施行時期・調整交付金の5%減額・外れ値の定義・介護給付適正化計画の期数・標準段階の論点・介護情報基盤・ケアプランデータ連携・協定・介護経営DB・継続検討9事項。個人情報の走査は該当なし | D54: 46303 | E54: docs/…/71_部会資料の原典による素案の確定とレビューの反映.md | F54: 受領済

Sheet 凡例・集計
B2: 凡例・入力ルール／進捗集計
B4: ■ 入力する列（ここだけ編集してください）
B5: 予定開始・予定完了 | C5: 日付 | D5: yyyy/mm/dd 形式で入力します。村との協議で工程が固まり次第、入力してください。
B6: 実績開始・実績完了 | C6: 日付 | D6: 着手日・完了日を実績として入力します。
B7: 進捗率 | C7: ％ | D7: 0〜100% を入力します。完了時は 100%。
B8: ステータス | C8: 選択 | D8: 未着手／着手／確認中／完了／保留／対象外 から選択します。
B9: 備考 | C9: 自由 | D9: 課題・懸案・村への確認事項などを記入します。
B11: ■ 行の塗り分け
B12: 薄い緑 | C12: 完了した作業です。
B13: 薄い黄 | C13: 着手中・確認中の作業、または北塩原村が担当する作業です。
B14: 薄い赤 | C14: 「村への確認事項」シートの優先度S・A、および未受領の資料です。
B16: ■ 進捗集計（WBSシートから自動集計されます）
B17: 大分類 | C17: 件数 | D17: 未着手 | E17: 着手 | F17: 確認中 | G17: 完了 | H17: 保留 | I17: 対象外
B18: ０ 契約・立上げ | C18: =COUNTIF('WBS・進捗管理'!$B$5:$B$121,$B18) | D18: =COUNTIFS('WBS・進捗管理'!$B$5:$B$121,$B18,'WBS・進捗管理'!$O$5:$O$121,D$17) | E18: =COUNTIFS('WBS・進捗管理'!$B$5:$B$121,$B18,'WBS・進捗管理'!$O$5:$O$121,E$17) | F18: =COUNTIFS('WBS・進捗管理'!$B$5:$B$121,$B18,'WBS・進捗管理'!$O$5:$O$121,F$17) | G18: =COUNTIFS('WBS・進捗管理'!$B$5:$B$121,$B18,'WBS・進捗管理'!$O$5:$O$121,G$17) | H18: =COUNTIFS('WBS・進捗管理'!$B$5:$B$121,$B18,'WBS・進捗管理'!$O$5:$O$121,H$17) | I18: =COUNTIFS('WBS・進捗管理'!$B$5:$B$121,$B18,'WBS・進捗管理'!$O$5:$O$121,I$17)
B19: Ⅰ ニーズ調査 | C19: =COUNTIF('WBS・進捗管理'!$B$5:$B$121,$B19) | D19: =COUNTIFS('WBS・進捗管理'!$B$5:$B$121,$B19,'WBS・進捗管理'!$O$5:$O$121,D$17) | E19: =COUNTIFS('WBS・進捗管理'!$B$5:$B$121,$B19,'WBS・進捗管理'!$O$5:$O$121,E$17) | F19: =COUNTIFS('WBS・進捗管理'!$B$5:$B$121,$B19,'WBS・進捗管理'!$O$5:$O$121,F$17) | G19: =COUNTIFS('WBS・進捗管理'!$B$5:$B$121,$B19,'WBS・進捗管理'!$O$5:$O$121,G$17) | H19: =COUNTIFS('WBS・進捗管理'!$B$5:$B$121,$B19,'WBS・進捗管理'!$O$5:$O$121,H$17) | I19: =COUNTIFS('WBS・進捗管理'!$B$5:$B$121,$B19,'WBS・進捗管理'!$O$5:$O$121,I$17)
B20: Ⅱ 計画策定 | C20: =COUNTIF('WBS・進捗管理'!$B$5:$B$121,$B20) | D20: =COUNTIFS('WBS・進捗管理'!$B$5:$B$121,$B20,'WBS・進捗管理'!$O$5:$O$121,D$17) | E20: =COUNTIFS('WBS・進捗管理'!$B$5:$B$121,$B20,'WBS・進捗管理'!$O$5:$O$121,E$17) | F20: =COUNTIFS('WBS・進捗管理'!$B$5:$B$121,$B20,'WBS・進捗管理'!$O$5:$O$121,F$17) | G20: =COUNTIFS('WBS・進捗管理'!$B$5:$B$121,$B20,'WBS・進捗管理'!$O$5:$O$121,G$17) | H20: =COUNTIFS('WBS・進捗管理'!$B$5:$B$121,$B20,'WBS・進捗管理'!$O$5:$O$121,H$17) | I20: =COUNTIFS('WBS・進捗管理'!$B$5:$B$121,$B20,'WBS・進捗管理'!$O$5:$O$121,I$17)
B21: Ⅲ 打合せ等 | C21: =COUNTIF('WBS・進捗管理'!$B$5:$B$121,$B21) | D21: =COUNTIFS('WBS・進捗管理'!$B$5:$B$121,$B21,'WBS・進捗管理'!$O$5:$O$121,D$17) | E21: =COUNTIFS('WBS・進捗管理'!$B$5:$B$121,$B21,'WBS・進捗管理'!$O$5:$O$121,E$17) | F21: =COUNTIFS('WBS・進捗管理'!$B$5:$B$121,$B21,'WBS・進捗管理'!$O$5:$O$121,F$17) | G21: =COUNTIFS('WBS・進捗管理'!$B$5:$B$121,$B21,'WBS・進捗管理'!$O$5:$O$121,G$17) | H21: =COUNTIFS('WBS・進捗管理'!$B$5:$B$121,$B21,'WBS・進捗管理'!$O$5:$O$121,H$17) | I21: =COUNTIFS('WBS・進捗管理'!$B$5:$B$121,$B21,'WBS・進捗管理'!$O$5:$O$121,I$17)
B22: Ⅳ 成果品・納品 | C22: =COUNTIF('WBS・進捗管理'!$B$5:$B$121,$B22) | D22: =COUNTIFS('WBS・進捗管理'!$B$5:$B$121,$B22,'WBS・進捗管理'!$O$5:$O$121,D$17) | E22: =COUNTIFS('WBS・進捗管理'!$B$5:$B$121,$B22,'WBS・進捗管理'!$O$5:$O$121,E$17) | F22: =COUNTIFS('WBS・進捗管理'!$B$5:$B$121,$B22,'WBS・進捗管理'!$O$5:$O$121,F$17) | G22: =COUNTIFS('WBS・進捗管理'!$B$5:$B$121,$B22,'WBS・進捗管理'!$O$5:$O$121,G$17) | H22: =COUNTIFS('WBS・進捗管理'!$B$5:$B$121,$B22,'WBS・進捗管理'!$O$5:$O$121,H$17) | I22: =COUNTIFS('WBS・進捗管理'!$B$5:$B$121,$B22,'WBS・進捗管理'!$O$5:$O$121,I$17)
B23: Ⅴ 管理 | C23: =COUNTIF('WBS・進捗管理'!$B$5:$B$121,$B23) | D23: =COUNTIFS('WBS・進捗管理'!$B$5:$B$121,$B23,'WBS・進捗管理'!$O$5:$O$121,D$17) | E23: =COUNTIFS('WBS・進捗管理'!$B$5:$B$121,$B23,'WBS・進捗管理'!$O$5:$O$121,E$17) | F23: =COUNTIFS('WBS・進捗管理'!$B$5:$B$121,$B23,'WBS・進捗管理'!$O$5:$O$121,F$17) | G23: =COUNTIFS('WBS・進捗管理'!$B$5:$B$121,$B23,'WBS・進捗管理'!$O$5:$O$121,G$17) | H23: =COUNTIFS('WBS・進捗管理'!$B$5:$B$121,$B23,'WBS・進捗管理'!$O$5:$O$121,H$17) | I23: =COUNTIFS('WBS・進捗管理'!$B$5:$B$121,$B23,'WBS・進捗管理'!$O$5:$O$121,I$17)
B24: 合計 | C24: =SUM(C18:C23) | D24: =SUM(D18:D23) | E24: =SUM(E18:E23) | F24: =SUM(F18:F23) | G24: =SUM(G18:G23) | H24: =SUM(H18:H23) | I24: =SUM(I18:I23)
B26: ■ 主要指標
B27: 全体進捗率（対象外を除く） | C27: =AVERAGEIF('WBS・進捗管理'!$O$5:$O$121,"<>対象外",'WBS・進捗管理'!$N$5:$N$121)
B28: 作業総数 | C28: =COUNTA('WBS・進捗管理'!$A$5:$A$121)
B29: 完了した作業 | C29: =COUNTIF('WBS・進捗管理'!$O$5:$O$121,"完了")
B30: 着手・確認中の作業 | C30: =COUNTIF('WBS・進捗管理'!$O$5:$O$121,"着手")+COUNTIF('WBS・進捗管理'!$O$5:$O$121,"確認中")
B31: 未着手の作業 | C31: =COUNTIF('WBS・進捗管理'!$O$5:$O$121,"未着手")
B32: 対象外の作業 | C32: =COUNTIF('WBS・進捗管理'!$O$5:$O$121,"対象外")
B33: 村への確認事項（優先度S） | C33: =COUNTIF('村への確認事項'!$A:$A,"S")
B34: 村への確認事項（優先度A） | C34: =COUNTIF('村への確認事項'!$A:$A,"A")
B35: 村への確認事項（未依頼） | C35: =COUNTIF('村への確認事項'!$G:$G,"未依頼")
B36: 未受領の資料・データ | C36: =COUNTIF('受領資料・データ管理'!$F:$F,"未受領")
B38: ■ マイルストーン（令和8年9月1日 キックオフ議事録により確定）
C39: 期日 | D39: 内容 | E39: 留意点
C40: 令和8年9月1日（火） | D40: キックオフ会議 | E40: 完了。議事録を受領（doc22）。S項目16件のうち9件が決着
B41: ★ | C41: 令和8年9月3日（木） | D41: 調査票 第1稿の提出 | E41: ★議事録で確定。未決事項は選択肢併記で提出
B42: ★ | C42: 令和8年9月9日（水）頃 | D42: 調査票の最終校了・印刷依頼 | E42: ★Webフォームの実装方法が未決だと間に合わない恐れ
C43: 令和8年9月14日（月） | D43: 宛名ラベル・配布用封筒の提供 | E43: 村。9/11への前倒しを要請
C44: 令和8年9月16〜17日 | D44: 宛名貼付・封入・封緘 | E44: 受託者
B45: ★ | C45: 令和8年9月18日（金）頃 | D45: アンケート発送 | E45: ★5連休（9/19〜9/23）の直前。9/17前倒しを協議
B46: ★ | C46: 令和8年9月30日（水） | D46: 策定委員会 現委員の任期満了 | E46: ★議事録で触れられず。第2回（11月）には改選が前提
C47: 令和8年10月 | D47: 回収・データ入力 | E47: 村が100件程度集まるごとに随時送付
B48: ★ | C48: 令和8年11月 | D48: 第2回策定委員会 | E48: ★分析結果・効果検証・骨子・体系・見込量・保険料概算・素案（完成度7割）
C49: 令和8年11月〜12月 | D49: パブリックコメント | E49: 第2回委員会の後に実施
C50: 令和9年1月下旬〜2月上旬 | D50: 第3回策定委員会 | E50: パブコメ結果と反映内容を報告。ほぼ完成版の素案で最終合意
C51: 令和9年2月末頃 | D51: 議会全員協議会 | E51: 概要版（A3両面程度）を用いて説明
C52: 令和9年3月31日 | D52: 履行期限（納品・検収）
B54: ※「仕様書該当」欄の凡例：仕様書＝8北保福第483号 別紙／手引き＝厚生労働省の実施の手引き（令和7年8月版）／確認＝本業務での確認事項
B55: ※ No. は行の位置によらない固定値です。作業を追加しても既存の No. は変わりません（追加分は101以降）。確認事項シートの「関連WBS No.」はこの No. を参照します。
B56: ※ 仕様書の要求事項と本WBSの対応は「仕様書対照」シートにあります。漏れと過剰の点検は scripts/verify_wbs.py で機械的に行っています。
B57: ※ 想定時期は仕様書の履行期限（令和9年3月31日）から逆算した目安です。村との協議結果により確定します。
B58: ※ 令和8年9月19日（土）〜23日（水）は5連休（敬老の日9/21・国民の休日9/22・秋分の日9/23）です。発送・回収工程に影響します。
B59: ※ 進捗基準日は令和8年10月13日です。備考欄の doc番号は docs/北塩原村_第10期/ 配下の分析資料に対応します。
B60: ※ マイルストーンの★印は、遅れると後続工程が連鎖的に破綻する項目です。
B61: ※ 第1回策定委員会は受託前に開催済みのため、関連する2作業はステータス「対象外」としています。全体進捗率は対象外を除いて算出しています。

Sheet ペンディング・作業順位
A2: ペンディングの影響度と作業順位（基準日 令和8年10月13日／対象の翌営業日 令和8年10月13日）
A4: ■ 影響度の定義（当方の作業に対する影響）
A5: 影響度 | B5: 呼び方 | C5: 意味
A6: 0 | B6: 社内 | C6: 村の回答を待つものではない。当方で確かめれば解消する。ペンディングとして数えない。
A7: 1 | B7: 停止 | C7: 回答がないと当方の作業が前に進まない。据え置きでは代替できず、回答後の差替えが章節の広い範囲に及ぶ。
A8: 2 | B8: 仮置き | C8: 仮定を置いて進められている。確定時に数値が動くため再算定と差替えが生じる。差替えの範囲は節の単位にとどまる。
A9: 3 | B9: 記載待ち | C9: 記載そのものは済んでいる。回答により文言・施策の内容が変わる。数値は動かない。
A10: 4 | B10: 工程外 | C10: 当方の作業は止まらない。村の内部手続または日程の決定を待つもの。
A11: 5 | B11: 対象外 | C11: 調査工程の項目。調査票は他メンバーが作成しているため当方では作業を進めない。
A13: ■ 未解決の確認事項 187件の内訳（影響度 × 優先度）
A14: 影響度 | B14: 呼び方 | C14: 優先度S | D14: 優先度A | E14: 優先度B | F14: 優先度C | G14: 小計 | H14: 備考
A15: 0 | B15: 社内 | C15: 0 | D15: 2 | E15: 0 | F15: 0 | G15: 2 | H15: 当方で確かめれば解消する。ペンディングとして数えない。
A16: 1 | B16: 停止 | C16: 4 | D16: 2 | E16: 0 | F16: 0 | G16: 6 | H16: 回答がないと成果品の数値が確定しない。最優先で照会する。
A17: 2 | B17: 仮置き | C17: 3 | D17: 28 | E17: 0 | F17: 0 | G17: 31 | H17: 仮定を置いて進めている。確定時に再算定と差替えが生じる。
A18: 3 | B18: 記載待ち | C18: 1 | D18: 35 | E18: 0 | F18: 0 | G18: 36 | H18: 記載は済んでいる。回答により文言・施策の内容が変わる。
A19: 4 | B19: 工程外 | C19: 2 | D19: 8 | E19: 0 | F19: 0 | G19: 10 | H19: 当方の作業は止まらない。村の内部手続または日程の決定を待つ。
A20: 5 | B20: 対象外 | C20: 22 | D20: 5 | E20: 4 | F20: 0 | G20: 31 | H20: 調査票は他メンバーが作成しているため当方では作業しない。
A21: ― | B21: 判定未了 | C21: 0 | D21: 0 | E21: 89 | F21: 2 | G21: 91 | H21: 優先度B・Cのうち計画策定側のもの。第2回策定委員会以降の照会を予定しており影響度は判定していない。ただしこのうち進捗0.90以上のWBSを止めているものは下段の見直し候補に掲げた。
B22: 合計 | C22: 32 | D22: 80 | E22: 93 | F22: 2 | G22: 207
A24: ■ 影響度1（停止）・2（仮置き）の明細 — 村への照会はこの順で起案する
A25: 影響度 | B25: No. | C25: 優先度 | D25: 確認事項 | E25: 止まる対象 | F25: 当方の手当（現時点の扱い） | G25: 回答が必要な時期 | H25: 束
A26: 1 | B26: K-010 | C26: S | D26: ★【期限 令和8年10月13日18時】令和9年度以降も0で入っている6サービスを0のままとしてよいか | E26: 素案 5-4・5-6／Ⅱ-56・Ⅱ-62・Ⅱ-107 | F26: 国の推計ワークシートを正として5-4・5-6を組み替える準備を進めている。6サービス（介護予防短期入所生活介護・訪問入浴介護・短期入所療養介護（老健）・特定福祉用具購入費・住宅改修費・地域密着型通所介護）が0のままでは、実績のあるサービスの見込量を0と掲げることになり、計画として成り立たない。村が修正する場合は当方の算定（素案5-4の現行値）を代替案として示せる。 | G26: 令和8年10月13日（火）18時（国の集計の提出期限。厳守） | H26: 束1
A27: 1 | B27: K-129 | C27: S | D27: ★ニーズ調査の対象者882人に対応する要介護認定データ（認定の有無・要介護度） | E27: 資料3の3-3・3-4・3-6／Ⅰ-37・Ⅰ-38 | F27: 回答データの集計そのものは進むが、認定状況を軸にしたクロス集計は作れない。資料3の3-3（元気な軽度者）・3-4（生活機能からみた4つの層）・3-6（担い手の可能性）がこれに当たる。3-6は第10期に共助・互助の仕組みをどの規模で構想できるかを示す表であり、基本理念・基本目標のご判断の材料になる（資料8-4）。後から認定状況を付けてクロスをやり直すことはできるが手戻りになる。 | G27: 10月中旬（第2回策定委員会の資料作成に入る前） | H27: 束8
A28: 1 | B28: K-133 | C28: S | D28: ★要介護認定データの提供時期と項目（要介護度・認定日・サービス利用状況）および総合事業対象者（基本チェックリスト該当者）の情報 | E28: 資料3の3-3・3-4・3-6／Ⅰ-37 | F28: 上記と一体のもの。集計軸の認定状況は「認定なし／事業対象者／要支援1・2／要介護1以上」の4区分であり、要介護認定データだけでは事業対象者を判別できない。総合事業の対象者（基本チェックリスト該当者）の情報もあわせて要る。 | G28: 10月中旬（同上） | H28: 束8
A29: 1 | B29: K-159 | C29: A | D29: 養護老人ホーム措置・軽費老人ホーム・老人クラブの実績は見える化に系列が一切ない | E29: 素案 4-30・5-4(8)／Ⅱ-53・Ⅱ-54 | F29: 養護老人ホーム措置・軽費老人ホーム・老人クラブは見える化に系列が一切なく、老人福祉事業の量の目標（Ⅱ-110）が立てられない。村提供のみが情報源。★10/12 影響度を2から1に上げた。老人福祉法第20条の8第2項が定めることを求めている量であり、実績がないまま目標の量を置くことはできない。仮定で代替できない。 | G29: 10月下旬 | H29: 束2
A30: 1 | B30: K-202 | C30: A | D30: ★法が定めることを求めている2つの量が空欄である（老人福祉事業の量19事業・地域支援事業の量10事業） | E30: 素案 4-6・5-5・5-12／Ⅱ-53・Ⅱ-110 | F30: 老人福祉法第20条の8第2項の老人福祉事業の量（20事業のうち19事業）と、介護保険法第117条第2項第2号の地域支援事業の量（19事業のうち10事業）が令和9〜11年度とも空欄である。いずれも法が計画に定めることを求めている事項であり、仮定を置いて進めることができない。令和5〜7年度の実績の受領を待つ。 | G30: 10月下旬 | H30: 束2
A31: 1 | B31: K-205 | C31: S | D31: ★令和8年法律第51号により介護保険法第117条に加わった記載事項の第10期計画への適用 | E31: 素案 5-11・5-5・施策4-3・施策4-6・1-6／Ⅱ-72・Ⅱ-110・Ⅱ-113 | F31: 10/15 起票。条文単位の対照（scripts/hotei_kisai.py・点検78）により、令和9年4月1日施行の記載事項7つが本計画に書かれていないことが分かった。うち中長期的な推計と中長期的な観点からの施策の2つは義務であり、書かなければ計画が法の求めを満たさない。要綱により書ける範囲は当方で加えるが、号の番号は新旧対照条文を待つ。加えると紙面が許容110頁を超えるため、削減案を1つ増やすか許容頁数のご判断をいただく必要がある。 | G31: 10月下旬（第2回策定委員会の資料作成前） | H31: 束2
A32: 2 | B32: K-011 | C32: S | D32: ★準備基金の取崩額を40,000,000円（残高の94.9%）とすることの可否（第11期が＋32.4%になる関係） | E32: 素案 5-7・5-11／資料6／Ⅱ-63・Ⅱ-64・Ⅱ-107 | F32: 国の推計ワークシートの前提（取崩40,000千円・保険料5,513.72円）を正として置き、取崩24,000千円・取崩なしを併記する案で資料6を組む。確定すれば併記を1案に絞る。 | G32: 11月上旬（第2回策定委員会資料の確定前） | H32: 束1
A33: 2 | B33: K-012 | C33: A | D33: ★条例上の保険料基準額の百円未満の処理（第9期は切捨てと見られる） | E33: 素案 5-7・図5-2／資料6 6-3b／Ⅱ-64・Ⅱ-107 | F33: 第9期の実例（算定上6,760.76円に対し条例6,700円）に合わせて切捨てで示した。四捨五入とした場合、基金の3案のうちB案（24,000千円取崩）は第10期6,000円・第11期6,800円となり、切捨て（5,900円・6,700円）と100円動く。条例の文言を確かめるまでは切捨てで置き、確認後に確定する。 | G33: 11月上旬（第2回策定委員会まで） | H33: 束1
A34: 2 | B34: K-013 | C34: A | D34: ★第1号被保険者数の前期・後期の内訳が国の様式（3区分）と素案5-2（2区分）で食い違う | E34: 素案 2-2・5-2・5-3／Ⅱ-59・Ⅱ-56 | F34: 10/7 に素案5-2を国の様式（3区分。前期444／425／405、後期560／575／589）に書き換え、2-2の「後期高齢者は令和12年の551人まで増加」を602人に直した。当方のB案の内訳は検算として注記に残した。併記の形でよいかのご確認を待つ。 | G34: 11月上旬（第2回策定委員会まで） | H34: 束1
A35: 2 | B35: K-014 | C35: A | D35: ★認定者数が国の推計（3か年計629人）と当方の算定（651人）で3.4%食い違う | E35: 素案 5-3・5-4／Ⅱ-56・Ⅱ-59 | F35: 10/7 に素案5-3を国の値（208／211／210）に書き換え、当方の算定（214／217／220）を検算として併記した。差の原因は認定率の置き方であることを本文に書いた。併記の形でよいかのご確認を待つ。 | G35: 11月上旬（第2回策定委員会まで） | H35: 束1
A36: 2 | B36: K-015 | C36: A | D36: ★後期高齢者加入割合補正係数（F）の算出方法（当方の復元が国の値と一致しない） | E36: 素案 5-7・5-11／Ⅱ-62・Ⅱ-64・Ⅱ-107 | F36: 国の値を用いて5-7・5-11を記載し、当方の復元が一致しないことを5-11の注記と5-12に明記した。Fは0.1の違いで月額約250円動くため、算出方法が確かめられないと中長期の保険料の形（第12期8,281円・第14期7,736円と上下する）を説明できない。 | G36: 11月上旬（第2回策定委員会まで） | H36: 束1
A37: 2 | B37: K-016 | C37: A | D37: ★調整交付金見込交付割合5.36／5.03／4.67%の出所（県の指示値か村の入力値か） | E37: 素案 5-7(3)・5-9／Ⅱ-62・Ⅱ-64 | F37: 国の値（5.36／5.03／4.67%）を正として5-7を書き換える。当方が復元した4.10〜4.32%との差（1.0ポイント超＝月額約260円）は、出所が分かれば説明できる。 | G37: 10月下旬 | H37: 束1
... A64: 0 | B64: K-199 | C64: A | D64: ★【社内】校了版（令和8年9月9日）の調査票Wordの提供（コードブックの作り直しに必要） | E64: 集計 Ⅰ-104・Ⅰ-35・Ⅰ-36 | F64: 論理チェック（doc25 §7・shukei_check.py）は組み終えており、ダミーデータで結果が出ることと自己試験が通ることを確かめている。ただしコードブックが令和8年9月4日版の調査票から作られているため、版が合うまで結果は暫定である（shukei_check.py は版を確かめて止まる。--暫定 で続行可）。校了版のWordを受領すればコードブックを作り直し、9月4日版の読み取りの不備7件（C01 1件・C02 5件・C03 1件）も同時に解消する。所要は半日。調査票は他メンバーの担当であり、当方では作成しない。お願いするのはWordの提供のみである。受領できないまま入力が進むと、鳴らなかった件が「誤りがない」のか「版違いで鳴らなかった」のか区別できなくなる。 | G64: 入力の開始前（回収期限 令和8年10月16日の前） | H64: 束8
A66: ■ 照会の束 — 1通にまとめて起案する単位（未解決の確認事項を関連WBSで束ねたもの）
A67: 束 | B67: 名称 | C67: 未解決 | D67: うちS | E67: うちA | F67: 止まるWBS | G67: 照会の方法
A68: 束1 | B68: 保険料と推計の確定 | C68: 27 | D68: 3 | E68: 13 | F68: Ⅱ-107、Ⅱ-59、Ⅱ-62、Ⅱ-63、Ⅱ-64 | G68: 国の推計ワークシートの受領（令和8年10月7日）により生じた確認事項を1通にまとめる。令和9年度以降も0で入っている6サービスの扱い（国の集計の提出期限が令和8年10月13日18時）、準備基金の取崩額の水準（第11期が＋32.4%になる関係）、被保険者数と認定者数の内訳の食い違い、調整交付金見込交付割合の出所、条例上の基準額の扱いである。
A69: 束2 | B69: 給付実績・決算と第9期の計画値 | C69: 70 | D69: 1 | E69: 22 | F69: Ⅱ-105、Ⅱ-106、Ⅱ-110、Ⅱ-115、Ⅱ-53、Ⅱ-54、Ⅱ-55、Ⅱ-56、Ⅱ-57、Ⅱ-58、Ⅱ-60、Ⅱ-61 | G69: 令和6・7年度の決算と給付実績、将来推計総括表、第9期計画の本文、見える化に系列のない事業（養護老人ホーム措置・軽費老人ホーム・老人クラブ）を1通にまとめる。
A70: 束3 | B70: 交付金の得点と給付適正化 | C70: 21 | D70: 0 | E70: 13 | F70: Ⅱ-109、Ⅱ-65、Ⅱ-67 | G70: 得点が低下した指標の理由と、未得点項目の取組可否を1通にまとめる。交付金の該当状況調査票の写しにより当方で確かめられるものは照会から除く。
A71: 束4 | B71: 認知症施策と権利擁護 | C71: 12 | D71: 0 | E71: 6 | F71: Ⅱ-68、Ⅱ-69 | G71: 認知症関連事業の実績、意見を聴く方法、権利擁護センターの相談減の要因を1通にまとめる。
A72: 束5 | B72: 計画構成と施策体系 | C72: 17 | D72: 0 | E72: 6 | F72: Ⅱ-113、Ⅱ-70、Ⅱ-71、Ⅱ-72、Ⅱ-73、Ⅱ-75 | G72: 基本理念の変更の有無、関連計画の策定状況、一体的策定の範囲を第2回策定委員会の審議事項として整理する。
A73: 束6 | B73: 日程・体制・成果品 | C73: 12 | D73: 1 | E73: 8 | F73: Ⅱ-76、Ⅱ-77、Ⅱ-80、Ⅱ-81、Ⅱ-83、Ⅱ-93、Ⅳ-114、Ⅳ-90、Ⅳ-92、Ⅴ-97、０-02、０-06 | G73: 委員会の開催日、パブリックコメントの時期、納品物の範囲を工程表とあわせて確認する。
A74: 束7 | B74: 調査票の設計・印刷・発送・回収（他メンバー担当） | C74: 34 | D74: 24 | E74: 5 | F74: Ⅰ-07、Ⅰ-08、Ⅰ-09、Ⅰ-10、Ⅰ-101、Ⅰ-102、Ⅰ-12、Ⅰ-13、Ⅰ-14、Ⅰ-15、Ⅰ-16、Ⅰ-17、Ⅰ-18、Ⅰ-19、Ⅰ-20、Ⅰ-21、Ⅰ-22、Ⅰ-23、Ⅰ-24、Ⅰ-25、Ⅰ-26、Ⅰ-29、Ⅰ-30、Ⅰ-31、Ⅰ-32 | G74: 調査票の設計・印刷・発送・回収は他メンバーが担当しており当方では作業しない。令和8年10月10日時点で発送は完了している。
A75: 束8 | B75: 集計・分析と要介護認定データの突合 | C75: 14 | D75: 3 | E75: 7 | F75: Ⅰ-104、Ⅰ-35、Ⅰ-36、Ⅰ-37、Ⅰ-38、Ⅰ-40、Ⅰ-42、Ⅰ-44、Ⅰ-45、Ⅰ-46、Ⅰ-48、Ⅰ-94、Ⅰ-95 | G75: 入力から集計・分析・報告書までは当方の担当である。村より「今集計分析を行なっています」とのご連絡をいただき着手した。要介護認定データ（Ⅰ-37）が最も急ぐ。これが入らないと資料3の3-3（元気な軽度者）・3-4（生活機能からみた4つの層）・3-6（担い手の可能性）が作れない。
A77: ■ 優先度の見直し候補 — 優先度B・Cのうち、進捗0.90以上のWBSの最後の未確定要素になっているもの 44件
A78: No. | B78: 優先度 | C78: 区分 | D78: 確認事項 | E78: 止めているWBS | F78: 進捗 | G78: 束
A79: K-019 | B79: B | C79: データ | D79: 認知症対応型共同生活介護の待機の状況（定員27人に対し令和9〜11年度の利用者数が27人で到達率100%） | E79: Ⅱ-105 地域密着型サービスの必要利用定員総数の設定 | F79: 0.95 | G79: 束2
A80: K-020 | B80: B | C80: データ | D80: 令和6年度決算および令和7年度の給付費見込 | E80: Ⅱ-56 計画数値の評価（計画値と実績の乖離分析） | F80: 0.95 | G80: 束2
A81: K-021 | B81: B | C81: データ | D81: 通いの場の実数（令和3〜7年度） | E81: Ⅱ-65 成果目標及び活動指標の設定 | F81: 0.92 | G81: 束3
A82: K-024 | B82: B | C82: 方針 | D82: 第1号被保険者数の推計を社人研ベースから補正して用いる方針の可否 | E82: Ⅱ-59 第1号被保険者数の推計 | F82: 0.95 | G82: 束1
A83: K-025 | B83: B | C83: 方針 | D83: 保険料が県・全国を上回る一方で費用額は下位である点の認識と説明方針 | E83: Ⅱ-64 介護保険料の試算（複数案の比較） | F83: 0.96 | G83: 束1
A84: K-026 | B84: B | C84: 方針 | D84: 総合事業のサービスA〜Dを第10期で立ち上げる意向の有無 | E84: Ⅱ-75 素案の作成 | F84: 0.98 | G84: 束3
A85: K-029 | B85: B | C85: 疑義 | D85: 第9期概要版④「地域支援事業費」の集計範囲（任意事業の扱い） | E85: Ⅱ-56 計画数値の評価（計画値と実績の乖離分析） | F85: 0.95 | G85: 束2
A86: K-031 | B86: B | C86: 計画構成 | D86: 認知症施策推進計画・成年後見制度利用促進基本計画の一体化を第10期も踏襲するか | E86: Ⅱ-75 素案の作成 | F86: 0.98 | G86: 束5
A87: K-032 | B87: B | C87: 計画構成 | D87: 定住自立圏（喜多方市・西会津町）／会津権利擁護・成年後見センターとの広域連携の記載方針 | E87: Ⅱ-71 施策体系の整理 | F87: 0.95 | G87: 束5
A88: K-036 | B88: B | C88: データ | D88: 訪問診療・訪問看護の提供実績（村内外の事業所別・令和6〜7年度） | E88: Ⅱ-61 各介護保険サービス見込量の推計 | F88: 0.95 | G88: 束2
A89: K-044 | B89: B | C89: データ | D89: 村内の認知症対応型共同生活介護の入退所の状況（年度ごとの入所者数・退所者数と退所の理由） | E89: Ⅱ-105 地域密着型サービスの必要利用定員総数の設定、Ⅱ-61 各介護保険サービス見込量の推計 | F89: 0.95、0.95 | G89: 束2
... A122: K-204 | B122: B | C122: データ | D122: ★新高額障害福祉サービス等給付費の対象となる介護保険サービスの種類と本村の該当者 | E122: Ⅱ-56 計画数値の評価（計画値と実績の乖離分析） | F122: 0.95 | G122: 束2
A124: ■ 令和8年10月13日の作業順位 — ペンディングがなく進められるもの
A125: 順位 | B125: WBS No. | C125: 作業項目 | D125: 現進捗 | E125: 行うこと | F125: 完了の判定 | G125: 所要
A126: 1 | B126: Ⅳ-91 | C126: 電子媒体の作成（Word/Excel/PowerPoint/PDF） | D126: 0.55 | E126: 電子媒体にPDFを収める。仕様書5③-aは「Word・Excel・PowerPoint・PDF形式等」を求めており、これまで「変換ができない環境のため未作成」としていた（doc83で変換できるようになった）。build_nohin.py に、成果品のdocxからPDFを作って 01_計画書・03_委員会資料 に並べる手順を加える。ただし当方の環境に游ゴシックがなくIPAゴシックに置き換わるため、そのまま納品してはならない。フォントが置き換わったかどうかを確かめ、置き換わっている場合は 00_媒体の構成.txt に「游ゴシックの入った環境で作り直すこと」を申し送る。 | F126: build_nohin.py がPDFを作って並べること。フォントの置換の有無を確かめ、置換があるときは申し送りに現れること。点検17（収録しないと定めたものが紛れていないこと）が通ること。置換のない環境で作り直す手順が doc に書かれていること。 | G126: 3時間
A127: 2 | B127: Ⅴ-100 | C127: 進捗管理・課題管理 | D127: 0.75 | E127: 照会票の優先度S・Aの件について、村にお見せする文の1文目がお願いになっているかを見直す。照会票は「当方の現在の扱い」を文の単位で170字まで出すため、背景から書き始めるとお願いが切れて村に届かない。資6の6件は10月12日に直した（doc85）が、ほかの件は見ていない。見出しだけで何をすればよいか読める件は直さなくてよい。 | F127: 優先度S・Aの件それぞれについて、票に出る文を実際に組み立てて目で見たうえで、直した件と直さなくてよいと判断した件が分かれていること。 | G127: 2時間
A128: 3 | B128: Ⅰ-104 | C128: 入力データの精度管理（論理チェック・ベリファイ） | D128: 0.80 | E128: 【校了版の調査票Wordを受領できた場合のみ】コードブックを校了版から作り直す。在宅調査の設問番号の＋1、問10のサービス12→9（記号A〜I）、問8への「15.なし」「16.わからない」の追加、ニーズ問4(15)の削除、問7(5)(8)(10)の選択肢の順序を反映する。あわせて9月4日版の読み取りの不備7件（C01 1件・C02 5件・C03 1件）を解消し、派生変数S01・S02の参照設問を校了版の番号に直す。校了版を受領したら、施策2-5の指標が頼る問7(11)の選択肢に「地域・近所の見守り、声かけ」があることもあわせて確かめる（doc87 §2-1）。受領できない場合は着手しない（版を推測して直すと、どの版でもない第3の版ができる）。 | F128: shukei_check.py が --暫定 なしで通ること（版の食い違いが解消すること）。コードブックの点検（C01〜C05）が0件になること。verify_shukei 点検21が「版が合っているため断りは不要」に変わること。問7(11)の選択肢の確認の結果が記録されていること。 | G128: 半日
A130: ■ 翌営業日に着手しない未完了のWBSとその理由
A131: WBS No. | B131: 作業項目 | C131: 状況 | D131: 進捗 | E131: 着手しない理由
A132: ０-02 | B132: 契約締結 | C132: 確認中 | D132: 0.50 | E132: 村の内部手続（契約書の取り交わし）を待つ。
A133: ０-04 | B133: 連絡体制・資料授受方法の確定 | C133: 着手 | D133: 0.50 | E133: 所管課の確認を待つ。照会は束6に含める。
A134: ０-05 | B134: 現行計画・関連計画・実績資料の受領 | C134: 着手 | D134: 0.70 | E134: 第五次総合振興計画・第3次健康21・障がい福祉計画の受領を待つ。
A135: ０-06 | B135: 見える化システムのID・パスワードの受領 | C135: 着手 | D135: 0.90 | E135: 受領データで作業は進んでいる。アカウントの授受は体制の整理にとどまる。
A136: Ⅰ-101 | B136: ウェブ回答フォームの公開・稼働確認・受付停止 | C136: 着手 | D136: 0.70 | E136: 調査工程。調査票は他メンバーが作成しているため当方では作業しない。
A137: Ⅰ-30 | B137: 回収状況の管理 | C137: 着手 | D137: 0.40 | E137: 調査工程。調査票は他メンバーが作成しているため当方では作業しない。
A138: Ⅰ-31 | B138: 督促（リマインド）の実施 | C138: 未着手 | D138: 0.00 | E138: 調査工程。調査票は他メンバーが作成しているため当方では作業しない。
A139: Ⅰ-32 | B139: 回収期限の管理・締切 | C139: 着手 | D139: 0.50 | E139: 調査工程。調査票は他メンバーが作成しているため当方では作業しない。
A140: Ⅰ-33 | B140: 開封確認 | C140: 着手 | D140: 0.40 | E140: 調査工程。調査票は他メンバーが作成しているため当方では作業しない。
A141: Ⅰ-94 | B141: 調査票の受渡し記録の作成・運用 | C141: 着手 | D141: 0.30 | E141: 調査工程。調査票は他メンバーが作成しているため当方では作業しない。
A142: Ⅰ-34 | B142: 用紙回答のデータ入力 | C142: 着手 | D142: 0.40 | E142: 調査工程。調査票は他メンバーが作成しているため当方では作業しない。
... A208: Ⅴ-99 | B208: 再委託の書面承諾の取得 | C208: 未着手 | D208: 0.00 | E208: 再委託の予定がない。

Sheet 納品物の構成
A2: 納品物に収録する範囲（仕様書5③-b／WBS Ⅳ-114）
A4: ■ 考え方 — 仕様書は「成果品及び関連データ」とするのみで範囲を定めていない。個人情報は収録しない（doc16 §5-1・§5-2・§6）
A6: ■ 村へ申し送る事項
A7: ・調査票の個人データ（氏名・住所・被保険者番号を含む一切）は電子媒体に収録しません。doc16§5-2により、関連付けの完了後に氏名・被保険者番号を分離し、認定データの原本は村と協議のうえ消去または返還します。
A8: ・管理番号と被保険者番号の対応表は収録しません（doc16§5-1）。業務完了後に消去し、消去の記録を村へ提出します（WBS Ⅴ-98）。
A9: ・集計結果は、該当数10未満のクロス集計の区分を統合または非表示としたうえで収録します（doc16§6）。本村は総人口2,315人・高齢者1,015人と小規模であり、地区×性別×年齢のような多重クロスは特定の恐れがあります。
A10: ・自由記述は、氏名・地区名・事業所名など個人が特定され得る記述を伏字または要約としたうえで収録します（doc16§6）。原文は収録しません。
A11: ・他の県内自治体の数値を含むファイルは収録しません。比較のために参照したものであり、成果品には団体名も数値も掲げていません。
A12: ・業務完了後の個人情報の返還・消去は、別に定める手順により行います。対象の一覧（宛名ラベル・対応表・調査票の原本・ウェブ回答・認定データ・個票・策定委員の連絡先・複写・バックアップ・受領資料の10件）、返還と消去の別、確かめ方、完了報告書の様式を定めています。消去は納品物の検収が済んでから行います。返還と消去の別は村にご確認いただきます。
A13: ・地域包括ケア「見える化」システムの出力そのものは収録しません。村が同じシステムから出力できるためです。計画書に用いた値は図表データ管理台帳に収めており、そこから検算できます。
A15: ■ 成果品 4件
A16: 区分 | B16: ファイル | C16: 媒体での置き場所 | D16: 理由
A17: 成果品 | B17: output/06_北塩原村第10期_計画素案.docx | C17: 01_計画書 | D17: 仕様書5①。確定後に『計画書』として差し替える
A18: 成果品 | B18: output/07_北塩原村第10期_集計仕様書.xlsx | C18: 02_調査報告書 | D18: 仕様書4Ⅰ(5)。集計の定義。報告書の付属
A19: 成果品 | B19: output/08_北塩原村第10期_第2回策定委員会資料.docx | C19: 03_委員会資料 | D19: 策定の経過。仕様書4Ⅱ(8)の会議資料
A20: 成果品 | B20: output/12_北塩原村第10期_第3回策定委員会資料.docx | C20: 03_委員会資料 | D20: 策定の経過。仕様書4Ⅱ(8)の会議資料。現在は骨子であり、第3回の開催前に中身を入れる
A22: ■ 関連 34件
A23: 区分 | B23: ファイル | C23: 媒体での置き場所 | D23: 理由
A24: 関連 | B24: data/集計_コードブック.json | C24: 02_調査報告書 | D24: 集計の変数定義
A25: 関連 | B25: output/11_北塩原村第10期_図表データ管理台帳.xlsx | C25: 04_図表データ | D25: 計画書の図の数値。村が数値を直せば図が変わる。更新の手順を00シートに記す
A26: 関連 | B26: output/figures | C26: 04_図表データ | D26: 計画書に差し込んだ図のPNG。台帳から作り直せる
A27: 関連 | B27: output/05_北塩原村第10期_WBS進捗管理表.xlsx | C27: 05_策定の記録 | D27: 策定の工程と村への確認事項。【氏名・連絡先は記載していない】
A28: 関連 | B28: output/09_北塩原村第10期_資料提供確認依頼書.docx | C28: 05_策定の記録 | D28: 村への照会の記録
A29: 関連 | B29: output/13-1_北塩原村第10期_照会票_束1_保険料と推計の確定.docx | C29: 05_策定の記録 | D29: 村への照会（保険料と推計の確定）。村にご記入いただいて返していただく様式。24件
A30: 関連 | B30: output/13-2_北塩原村第10期_照会票_束2_給付実績・決算と第9期の計画値.docx | C30: 05_策定の記録 | D30: 村への照会（給付実績・決算と第9期の計画値）。村にご記入いただいて返していただく様式。57件
A31: 関連 | B31: output/13-3_北塩原村第10期_照会票_束3_交付金の得点と給付適正化.docx | C31: 05_策定の記録 | D31: 村への照会（交付金の得点と給付適正化）。村にご記入いただいて返していただく様式。20件
A32: 関連 | B32: output/13-4_北塩原村第10期_照会票_束4_認知症施策と権利擁護.docx | C32: 05_策定の記録 | D32: 村への照会（認知症施策と権利擁護）。村にご記入いただいて返していただく様式。10件
A33: 関連 | B33: output/13-5_北塩原村第10期_照会票_束5_計画構成と施策体系.docx | C33: 05_策定の記録 | D33: 村への照会（計画構成と施策体系）。村にご記入いただいて返していただく様式。18件
A34: 関連 | B34: output/13-6_北塩原村第10期_照会票_束6_日程・体制・成果品.docx | C34: 05_策定の記録 | D34: 村への照会（日程・体制・成果品）。村にご記入いただいて返していただく様式。14件
... A57: 関連 | B57: data/第10期_需要に対する供給.csv | C57: 06_算定の根拠 | D57: 5-4(12)
A59: ■ 収録しない 32件
A60: 区分 | B60: ファイル | C60: 媒体での置き場所 | D60: 理由
A61: 収録しない | B61: data/05_令和7年8月版_突合ワークシート.csv | C61: ― | D61: 調査票の突合の作業用。調査は他メンバーの担当
A62: 収録しない | B62: data/dummy_ニーズ.csv | C62: ― | D62: 集計プログラムの検証に用いた架空のデータ。成果品ではない
A63: 収録しない | B63: data/dummy_在宅.csv | C63: ― | D63: 同上
A64: 収録しない | B64: data/mieruka_batch.csv | C64: ― | D64: 見える化の出力から取り出した中間データ。村は同じシステムから出力できる
A65: 収録しない | B65: data/mieruka_inventory.csv | C65: ― | D65: 受領の記録。作業の途中のもの
A66: 収録しない | B66: data/mieruka_inventory_追加分.csv | C66: ― | D66: 同上
A67: 収録しない | B67: data/mieruka_inventory_追加分2.csv | C67: ― | D67: 同上
A68: 収録しない | B68: data/mieruka_inventory_追加分3.csv | C68: ― | D68: 同上
A69: 収録しない | B69: data/mieruka_inventory_追加分4.csv | C69: ― | D69: 同上
A70: 収録しない | B70: data/mieruka_inventory_追加分5.csv | C70: ― | D70: 同上
A71: 収録しない | B71: data/mieruka_inventory_追加分6.csv | C71: ― | D71: 同上
... A92: 収録しない | B92: output/images_basic | C92: ― | D92: 他業務との共通の部品の画像
A94: ■ 納品の時点で作るもの 5件（まだ存在しない）
A95: 区分 | B95: 成果品 | C95: 媒体での置き場所 | D95: 作る時点
A96: 成果品 | B96: 計画書（確定版） | C96: 01_計画書 | D96: 素案の確定後。仕様書5①（50部）
A97: 成果品 | B97: アンケート調査報告書 | C97: 02_調査報告書 | D97: 仕様書5②（10部）
A98: 成果品 | B98: 集計結果（本番データ） | C98: 02_調査報告書 | D98: 調査票の回収・入力の後。該当数10未満の区分を統合または非表示とする（doc16§6）
A99: 成果品 | B99: 概要版 | C99: 01_計画書 | D99: 仕様書の範囲内かを村に確認中（K-109）
A100: 成果品 | B100: パブリックコメントの実施結果 | C100: 05_策定の記録 | D100: 資料編7-4に反映
