Workbook

Sheet 00_業務概要
A1: 音威子府村高齢者福祉計画・第10期介護保険事業計画 策定業務委託 WBS（作業分解構成図）
A2: 本ブックは委託仕様書に基づき作成した業務管理用WBSです。契約締結日・打合せ日程等が確定した時点で日程を更新してください。
A4: 1. 業務の基本情報
A5: 業務名 | B5: 音威子府村高齢者福祉計画・第10期介護保険事業計画 策定業務委託
A6: 発注者 | B6: 音威子府村
A7: 業務目的 | B7: 計画原案の作成等の支援（計画策定に必要となるサービス見込量等の数値の推計を含む）
A8: 委託期間 | B8: 契約締結日 〜 令和9年3月31日
A9: 計画期間 | B9: 第10期＝令和9年度〜令和11年度（3か年）
A10: 人口推計期間 | B10: 令和9年から10年間程度（令和9年度〜令和18年度）
A11: 打合せ回数 | B11: 3回程度（計画策定担当者本人が出席）
A12: 成果品 | B12: 計画（CDデータ）1部／業務データ収録の磁気媒体（CDデータ）1部
A13: 著作権 | B13: 成果品の著作権はすべて音威子府村に帰属
A14: WBS作成日 | B14: =TODAY()
A16: 2. 業務量サマリ（『01_WBS』シートと連動）
A17: 区分 | B17: 値 | C17: 算出方法 | D17: 備考
A18: 作業項目数（レベル3） | B18: =COUNTIF('01_WBS'!$C$5:$C$98,3) | C18: レベル3の行数 | D18: 実作業単位の総数
A19: 総工数（人日） | B19: =SUMIF('01_WBS'!$C$5:$C$98,3,'01_WBS'!$K$5:$K$98) | C19: レベル3の工数合計 | D19: 1人日＝7.5時間想定
A20: 総工数（人月換算） | B20: =ROUND(SUMIF('01_WBS'!$C$5:$C$98,3,'01_WBS'!$K$5:$K$98)/20,1) | C20: 総工数 ÷ 20人日 | D20: 1人月＝20人日換算
A21: 完了件数 | B21: =COUNTIFS('01_WBS'!$C$5:$C$98,3,'01_WBS'!$P$5:$P$98,"完了") | C21: 進捗欄が「完了」の件数 | D21: 進捗欄の入力に応じて自動更新
A22: 進捗率 | B22: =IFERROR(COUNTIFS('01_WBS'!$C$5:$C$98,3,'01_WBS'!$P$5:$P$98,"完了")/COUNTIF('01_WBS'!$C$5:$C$98,3),0) | C22: 完了件数 ÷ 作業項目数 | D22: 0.0%表示
A24: 3. 前提条件（確定次第、各シートの日程・数値を更新）
A25: 項目 | B25: 前提の置き方 | C25: 備考
A26: ★第9期計画 | B26: 未受領。基本理念・基本目標・施策体系・第9期評価は仮置きで執筆している | C26: 素案の該当箇所に『【要差替：第9期計画受領後】』を明記。受領後に一括差替（WBS 2.4.0／リスクR-13）
A27: 契約締結日 | B27: 令和8年9月1日と仮定して日程を設定（未確定） | C27: 確定後にスクリプトの CONTRACT_START を修正
A28: 打合せ日程 | B28: 第1回=R8.9中旬／第2回=R8.12上旬／第3回=R9.2中旬 と仮置き | C28: 村と協議のうえ確定
A29: ニーズ調査 | B29: 令和8年度に村が実施済みの集計データを受領して反映（調査実施は業務範囲外） | C29: 仕様書3(3)による
A30: 国の基本指針 | B30: 第10期の基本指針・介護報酬改定率は策定作業と並行して確定する前提 | C30: 確定遅延時は暫定値で算定→再算定（WBS 4.4.1）
A31: 成果品 | B31: CDデータのみ（印刷・製本は仕様書に記載なし） | C31: 必要な場合は別途協議
A32: パブリックコメント | B32: 実施主体・日程は仕様書に記載なし。村実施を想定し意見反映のみ計上 | C32: 実施支援が必要な場合は協議
A33: 再委託 | B33: 予定なし。必要が生じた場合は事前に村の承諾を得る | C33: 仕様書7 留意事項
A34: 工数単位 | B34: 1人日＝7.5時間、1人月＝20人日で換算 | C34: 見積・要員計画の基礎
A36: 4. シート構成
A37: シート名 | B37: 内容
A38: 01_WBS | B38: 作業分解構成図の本体（レベル1〜3・工数・日程・担当・仕様書対応）
A39: 02_スケジュール | B39: 半月単位のガントチャート（令和8年9月〜令和9年3月）
A40: 03_マイルストーン | B40: 打合せ・提出物等の節目一覧
A41: 04_成果物一覧 | B41: 中間成果物と最終成果品の一覧
A42: 05_推計作業手順 | B42: 人口・認定者数・見込量・保険料の推計手順とデータ・ツール
A43: 06_必要資料リスト | B43: 村から貸与を受ける資料・公表統計の一覧（依頼票）
A44: 07_役割分担 | B44: 受託者／村担当課／関係機関の役割分担（RACI）
A45: 08_リスク管理 | B45: 想定リスクと対応方針
A46: 09_スコープ管理 | B46: 業務範囲に含む／含まない／協議事項の整理
A47: 10_工数集計 | B47: 大分類・中分類別の工数集計

Sheet 01_WBS
A1: WBS（作業分解構成図） ／ 音威子府村高齢者福祉計画・第10期介護保険事業計画 策定業務委託
A2: 委託期間：契約締結日〜令和9年3月31日 ／ 打合せ：3回程度 ／ ★印はマイルストーン ／ レベル1・2行の工数・日程は配下のレベル3から自動集計
A3: 凡例：レベル1＝大分類（濃紺）／レベル2＝中分類（水色）／レベル3＝実作業 進捗欄は「未着手・着手・完了・保留・対象外」から選択
A4: No. | B4: WBS No. | C4: レベル | D4: 大分類 | E4: 中分類 | F4: 作業項目 | G4: 作業内容・実施方法 | H4: 成果物・アウトプット | I4: 主担当 | J4: 村（発注者）の対応 | K4: 工数 (人日) | L4: 開始予定 | M4: 完了予定 | N4: 先行作業 | O4: 仕様書 該当箇所 | P4: 進捗 | Q4: 備考・留意点
B5: 1 | C5: 1 | D5: 業務管理・打合せ | K5: =SUMIF($C$6:$C$21,3,$K$6:$K$21) | L5: 46266 | M5: 46477 | O5: 2 委託期間／4 打合せ
B6: 1.1 | C6: 2 | D6: 業務管理・打合せ | E6: 業務着手準備 | K6: =SUMIF($C$7:$C$10,3,$K$7:$K$10) | L6: 46266 | M6: 46283 | O6: 4 打合せ
A7: 1 | B7: 1.1.1 | C7: 3 | D7: 業務管理・打合せ | E7: 業務着手準備 | F7: 契約締結・業務実施体制の確定 | G7: 契約書・仕様書の内容確認、業務従事者（計画策定担当者）の確定、連絡体制・緊急連絡先の共有 | H7: 業務従事者届／連絡体制表 | I7: 受託者 | J7: 契約手続 | K7: 0.5 | L7: 46266 | M7: 46269 | N7: － | O7: 2 委託期間 | P7: 未着手 | Q7: 打合せには計画策定担当者本人が出席（仕様書4）
A8: 2 | B8: 1.1.2 | C8: 3 | D8: 業務管理・打合せ | E8: 業務着手準備 | F8: 業務実施計画書・詳細工程表の作成 | G8: 本WBSに基づく実施計画書・工程表を作成し、村と協議のうえ確定。以降の変更は都度改訂 | H8: 業務実施計画書／詳細工程表（本WBS） | I8: 受託者 | J8: 内容確認・承認 | K8: 1 | L8: 46266 | M8: 46283 | N8: 1.1.1 | O8: 4 打合せ | P8: 未着手 | Q8: 第1回打合せで協議し確定。スケジュールは以降も適宜協議（仕様書4）
A9: 3 | B9: 1.1.3 | C9: 3 | D9: 業務管理・打合せ | E9: 業務着手準備 | F9: 【第1回打合せ】キックオフ | G9: 業務実施計画・工程の協議、貸与資料の確認、計画の方向性・論点の共有、庁内体制の確認 | H9: 第1回打合せ資料／議事録 | I9: 受託者 | J9: 日程調整・出席・資料準備 | K9: 1 | L9: 46275 | M9: 46275 | N9: 1.1.1 | O9: 4 打合せ（3回程度） | P9: 未着手 | Q9: ★マイルストーン／打合せ1回目
A10: 4 | B10: 1.1.4 | C10: 3 | D10: 業務管理・打合せ | E10: 業務着手準備 | F10: 個人情報・機密情報の取扱手続 | G10: 個人情報保護に関する誓約書の提出、データ授受方法（受渡・保管・返却）の取決め、アクセス権限設定 | H10: 誓約書／情報取扱ルール | I10: 受託者 | J10: 条例に基づく確認 | K10: 0.5 | L10: 46266 | M10: 46276 | N10: 1.1.1 | O10: 7 留意事項（個人情報） | P10: 未着手 | Q10: 音威子府村個人情報保護条例を遵守
B11: 1.2 | C11: 2 | D11: 業務管理・打合せ | E11: 進行管理 | K11: =SUMIF($C$12:$C$15,3,$K$12:$K$15) | L11: 46266 | M11: 46477 | O11: 4 打合せ／5 その他
A12: 5 | B12: 1.2.1 | C12: 3 | D12: 業務管理・打合せ | E12: 進行管理 | F12: 定例連絡・進捗報告 | G12: 月1回程度のメール・電話・Web会議による進捗報告と論点確認（対面打合せ3回を補完） | H12: 進捗報告メモ（月次） | I12: 受託者 | J12: 内容確認・指示 | K12: 2 | L12: 46266 | M12: 46477 | N12: 1.1.1 | O12: 4 打合せ | P12: 未着手 | Q12: 対面3回の制約をWeb会議等で補完
A13: 6 | B13: 1.2.2 | C13: 3 | D13: 業務管理・打合せ | E13: 進行管理 | F13: 【第2回打合せ】現状分析・骨子報告 | G13: 現状分析・現行計画評価の結果報告、課題と施策の方向の協議、計画骨子（章立て）案の提示・確定 | H13: 第2回打合せ資料／議事録 | I13: 受託者 | J13: 日程調整・出席・庁内調整 | K13: 1 | L13: 46366 | M13: 46366 | N13: 2.4.3, 5.2.1 | O13: 4 打合せ（3回程度） | P13: 未着手 | Q13: ★マイルストーン／打合せ2回目
A14: 7 | B14: 1.2.3 | C14: 3 | D14: 業務管理・打合せ | E14: 進行管理 | F14: 【第3回打合せ】計画素案・保険料報告 | G14: サービス見込量・保険料算定結果の報告と協議、計画素案の提示、パブリックコメント等の進め方確認 | H14: 第3回打合せ資料／議事録 | I14: 受託者 | J14: 日程調整・出席・庁内調整 | K14: 1 | L14: 46428 | M14: 46428 | N14: 4.3.4, 5.3.10 | O14: 4 打合せ（3回程度） | P14: 未着手 | Q14: ★マイルストーン／打合せ3回目
A15: 8 | B15: 1.2.4 | C15: 3 | D15: 業務管理・打合せ | E15: 進行管理 | F15: 国の指示・基本指針変更への対応協議 | G15: 国の基本指針・通知・Q&A・介護報酬改定情報を継続的に収集し、仕様変更が必要な場合は村と協議 | H15: 国通知等の整理メモ／協議記録 | I15: 受託者 | J15: 協議・決定 | K15: 0.5 | L15: 46266 | M15: 46477 | N15: 1.1.1 | O15: 5 その他 | P15: 未着手 | Q15: 特別の事情がない限り国の指示を遵守
B16: 1.3 | C16: 2 | D16: 業務管理・打合せ | E16: 資料収集・整理 | K16: =SUMIF($C$17:$C$21,3,$K$17:$K$21) | L16: 46273 | M16: 46310 | O16: 3(1) 現状の評価・分析
A17: 9 | B17: 1.3.1 | C17: 3 | D17: 業務管理・打合せ | E17: 資料収集・整理 | F17: 村提供資料の受領・確認 | G17: 貸与資料リスト（本ブック『06_必要資料リスト』）を提示し、資料を受領。不足・欠測の確認と追加依頼 | H17: 貸与資料リスト（受領チェック済） | I17: 受託者 | J17: 資料抽出・提供 | K17: 0.5 | L17: 46273 | M17: 46295 | N17: 1.1.3 | O17: 7 留意事項（連携・協議） | P17: 未着手 | Q17: 契約後2週間以内にリスト提示
A18: 10 | B18: 1.3.2 | C18: 3 | D18: 業務管理・打合せ | E18: 資料収集・整理 | F18: 公表統計・システムデータの収集 | G18: 国勢調査、住民基本台帳人口、社人研将来推計人口、介護保険事業状況報告、地域包括ケア「見える化」システム等 | H18: 基礎統計データセット | I18: 受託者 | J18: － | K18: 1 | L18: 46273 | M18: 46310 | N18: 1.1.3 | O18: 3(1) 現状の評価・分析 | P18: 未着手 | Q18: 出典・取得日を明記して管理
A19: 11 | B19: 1.3.3 | C19: 3 | D19: 業務管理・打合せ | E19: 資料収集・整理 | F19: 関連計画・関連資料の収集 | G19: 村総合計画、地域福祉計画、健康増進計画、北海道の関連計画等を収集し、記載内容・目標値を整理 | H19: 関連計画整理表 | I19: 受託者 | J19: 計画提供 | K19: 0.5 | L19: 46273 | M19: 46310 | N19: 1.3.1 | O19: 7 留意事項（総合計画等との整合） | P19: 未着手 | Q19: 整合性確認は5.1.3で実施
A20: 12 | B20: 1.3.4 | C20: 3 | D20: 業務管理・打合せ | E20: 資料収集・整理 | F20: 見える化システムデータの棚卸し | G20: ダウンロード済み741ファイルを全件走査し、音威子府村の値の有無・比較群・データ年次を判定して管理表化 | H20: 見える化システムDLデータ棚卸し表 | I20: 受託者 | J20: － | K20: 1 | L20: 46273 | M20: 46283 | N20: － | O20: 3(1) 現状の評価・分析 | P20: 未着手 | Q20: ★実施済み。データは令和8年9月2〜3日出力（データあり521／全欠測130／空DL45／対象外45）
A21: 13 | B21: 1.3.5 | C21: 3 | D21: 業務管理・打合せ | E21: 資料収集・整理 | F21: 未取得データの再取得・代替データの確保 | G21: 比較群が0団体の35ファイルを再出力。L16〜L28（在宅医療のレセプト系）は二次医療圏単位で再取得または代替を確保 | H21: 再取得データ／代替データ整理メモ | I21: 受託者 | J21: － | K21: 1 | L21: 46281 | M21: 46310 | N21: 1.3.4 | O21: 3(1) 現状の評価・分析 | P21: 未着手 | Q21: 認知症・総合事業は村実績で補完（1.3.1で依頼）
B22: 2 | C22: 1 | D22: 現状の評価・分析 | K22: =SUMIF($C$23:$C$40,3,$K$23:$K$40) | L22: 46273 | M22: 46353 | O22: 3(1) 現状の評価・分析
B23: 2.1 | C23: 2 | D23: 現状の評価・分析 | E23: 基礎的資料による現状把握・分析 | K23: =SUMIF($C$24:$C$26,3,$K$24:$K$26) | L23: 46296 | M23: 46325 | O23: 3(1)① 統計資料等
A24: 14 | B24: 2.1.1 | C24: 3 | D24: 現状の評価・分析 | E24: 基礎的資料による現状把握・分析 | F24: 人口・世帯の動向分析 | G24: 総人口・年齢3区分別人口・高齢化率・前期／後期高齢者、高齢者単身世帯・高齢者のみ世帯の推移を分析 | H24: 人口・世帯分析図表 | I24: 受託者 | J24: 住基データ提供 | K24: 1.5 | L24: 46296 | M24: 46318 | N24: 1.3.2 | O24: 3(1)① 統計資料等 | P24: 未着手 | Q24: 直近10年の経年変化で整理
A25: 15 | B25: 2.1.2 | C25: 3 | D25: 現状の評価・分析 | E25: 基礎的資料による現状把握・分析 | F25: 地域資源・社会基盤の整理 | G25: 村内・近隣の介護サービス事業所、医療機関、通所・訪問系資源、住民主体の活動、生活交通の状況を整理 | H25: 地域資源マップ／一覧表 | I25: 受託者 | J25: 事業所情報提供 | K25: 1 | L25: 46296 | M25: 46318 | N25: 1.3.1 | O25: 3(1)① 統計資料等 | P25: 未着手 | Q25: 圏域外（近隣市町村）利用の実態も整理
A26: 16 | B26: 2.1.3 | C26: 3 | D26: 現状の評価・分析 | E26: 基礎的資料による現状把握・分析 | F26: 北海道・全国・類似団体との比較分析 | G26: 高齢化率、認定率、受給率、1人当たり給付費、保険料水準を北海道平均・全国・類似規模団体と比較 | H26: 比較分析図表 | I26: 受託者 | J26: － | K26: 0.5 | L26: 46308 | M26: 46325 | N26: 2.1.1 | O26: 3(1)① 統計資料等 | P26: 未着手 | Q26: 「見える化」システムを活用
B27: 2.2 | C27: 2 | D27: 現状の評価・分析 | E27: 高齢者福祉サービス実績の分析 | K27: =SUMIF($C$28:$C$30,3,$K$28:$K$30) | L27: 46296 | M27: 46326 | O27: 3(1)② 高齢者福祉サービス実績
A28: 17 | B28: 2.2.1 | C28: 3 | D28: 現状の評価・分析 | E28: 高齢者福祉サービス実績の分析 | F28: 高齢者福祉施策（村単独事業）の実績分析 | G28: 配食・除雪・緊急通報・移送・生きがい活動等、村単独の高齢者福祉サービスの利用実績・事業費を分析 | H28: 高齢者福祉サービス実績分析表 | I28: 受託者 | J28: 事業実績提供 | K28: 1 | L28: 46296 | M28: 46326 | N28: 1.3.1 | O28: 3(1)② 高齢者福祉サービス実績 | P28: 未着手 | Q28: 第9期計画の掲載事業と対応づけ
A29: 18 | B29: 2.2.2 | C29: 3 | D29: 現状の評価・分析 | E29: 高齢者福祉サービス実績の分析 | F29: 介護予防・日常生活支援総合事業の実績分析 | G29: 訪問型・通所型サービス、一般介護予防事業（通いの場・住民主体の活動）の実施状況と参加者数を分析 | H29: 総合事業実績分析表 | I29: 受託者 | J29: 事業実績提供 | K29: 1 | L29: 46296 | M29: 46326 | N29: 1.3.1 | O29: 3(1)② 高齢者福祉サービス実績 | P29: 未着手 | Q29: 介護予防の到達点を評価
A30: 19 | B30: 2.2.3 | C30: 3 | D30: 現状の評価・分析 | E30: 高齢者福祉サービス実績の分析 | F30: 包括的支援事業・任意事業の実績分析 | G30: 地域包括支援センター運営、在宅医療・介護連携、認知症施策、生活支援体制整備、権利擁護の実績を分析 | H30: 地域支援事業実績分析表 | I30: 受託者 | J30: 事業実績提供 | K30: 0.5 | L30: 46308 | M30: 46326 | N30: 1.3.1 | O30: 3(1)② 高齢者福祉サービス実績 | P30: 未着手 | Q30: 地域包括ケアの推進状況を評価
B31: 2.3 | C31: 2 | D31: 現状の評価・分析 | E31: 介護保険サービス実績の分析 | K31: =SUMIF($C$32:$C$35,3,$K$32:$K$35) | L31: 46296 | M31: 46346 | O31: 3(1)③ 介護保険サービス実績
A32: 20 | B32: 2.3.1 | C32: 3 | D32: 現状の評価・分析 | E32: 介護保険サービス実績の分析 | F32: 要介護認定者数・認定率の推移分析 | G32: 要支援1〜要介護5別・性別・年齢階級別の認定者数と認定率の推移、認定の重度化傾向を分析 | H32: 認定状況分析図表 | I32: 受託者 | J32: 認定データ提供 | K32: 1.5 | L32: 46296 | M32: 46326 | N32: 1.3.1 | O32: 3(1)③ 介護保険サービス実績 | P32: 未着手 | Q32: 3.2 認定者数推計の基礎データ
A33: 21 | B33: 2.3.2 | C33: 3 | D33: 現状の評価・分析 | E33: 介護保険サービス実績の分析 | F33: サービス種類別給付実績の分析 | G33: 居宅・地域密着型・施設サービスの種類別に、受給者数・利用回数（日数）・給付費の推移を分析 | H33: 給付実績分析図表 | I33: 受託者 | J33: 給付実績提供 | K33: 1.5 | L33: 46301 | M33: 46339 | N33: 1.3.1 | O33: 3(1)③ 介護保険サービス実績 | P33: 未着手 | Q33: 4.1 見込量推計の基礎データ
A34: 22 | B34: 2.3.3 | C34: 3 | D34: 現状の評価・分析 | E34: 介護保険サービス実績の分析 | F34: 受給率・利用率・1人当たり給付費の分析 | G34: 認定者に対する受給率、要介護度別の利用状況、1人当たり給付費（月額）を算出し、傾向と特徴を整理 | H34: 利用状況分析表 | I34: 受託者 | J34: － | K34: 1 | L34: 46315 | M34: 46339 | N34: 2.3.2 | O34: 3(1)③ 介護保険サービス実績 | P34: 未着手 | Q34: 小規模ゆえの年変動に留意
A35: 23 | B35: 2.3.4 | C35: 3 | D35: 現状の評価・分析 | E35: 介護保険サービス実績の分析 | F35: 介護保険財政・保険料収納状況の分析 | G35: 介護保険特別会計の決算推移、第9期の給付費実績と計画対比、介護給付費準備基金残高、収納率を分析 | H35: 介護保険財政分析表 | I35: 受託者 | J35: 決算・基金資料提供 | K35: 1 | L35: 46315 | M35: 46346 | N35: 1.3.1 | O35: 3(1)③ 介護保険サービス実績 | P35: 未着手 | Q35: 4.3 保険料算定の前提となる
B36: 2.4 | C36: 2 | D36: 現状の評価・分析 | E36: 現行計画（第9期）の点検・評価 | K36: =SUMIF($C$37:$C$40,3,$K$37:$K$40) | L36: 46273 | M36: 46353 | O36: 3(1)④ 現行計画の点検・評価
A37: 24 | B37: 2.4.0 | C37: 3 | D37: 現状の評価・分析 | E37: 現行計画（第9期）の点検・評価 | F37: 【前提】第9期計画本体の受領 | G37: 第9期高齢者福祉計画・介護保険事業計画（本編・資料編）および進捗管理資料を村から受領し、基本理念・基本目標・施策体系・目標値を読み取る | H37: 第9期計画 構成整理メモ | I37: 受託者 | J37: 計画の提供 | K37: 0.5 | L37: 46273 | M37: 46297 | N37: 1.1.3 | O37: 3(1)④ 現行計画の点検・評価 | P37: 未着手 | Q37: ★未受領（令和8年9月時点）。2.4.1・5.1.2・5.2.1・5.3.3 の前提となるクリティカルパス
A38: 25 | B38: 2.4.1 | C38: 3 | D38: 現状の評価・分析 | E38: 現行計画（第9期）の点検・評価 | F38: 施策・事業別の進捗評価 | G38: 第9期計画の施策体系に沿って、事業ごとの取組状況・目標値と実績の対比・達成度（3段階等）を評価 | H38: 第9期計画 進捗評価シート | I38: 受託者 | J38: 各事業の実績・自己評価 | K38: 1.5 | L38: 46328 | M38: 46346 | N38: 2.4.0, 2.2.3 | O38: 3(1)④ 現行計画の点検・評価 | P38: 未着手 | Q38: 村担当課への照会により評価を確定。第9期計画の受領が前提
A39: 26 | B39: 2.4.2 | C39: 3 | D39: 現状の評価・分析 | E39: 現行計画（第9期）の点検・評価 | F39: 介護予防・日常生活圏域ニーズ調査結果の整理・分析 | G39: 今年度（令和8年度）村が実施した調査の集計データを整理し、リスク該当者割合・生活実態・意向を分析 | H39: ニーズ調査結果分析資料 | I39: 受託者 | J39: 調査集計データ提供 | K39: 1.5 | L39: 46308 | M39: 46339 | N39: 1.3.1 | O39: 3(3) 見込量（ニーズ調査結果の反映） | P39: 未着手 | Q39: 調査の実施・集計自体は業務範囲外（村実施分を反映）
A40: 27 | B40: 2.4.3 | C40: 3 | D40: 現状の評価・分析 | E40: 現行計画（第9期）の点検・評価 | F40: 現状分析・評価の総括資料作成 | G40: 2.1〜2.4の分析結果を統合し、第2回打合せ用の中間報告資料として取りまとめ | H40: 現状分析・評価 中間報告資料 | I40: 受託者 | J40: 内容確認 | K40: 1 | L40: 46342 | M40: 46353 | N40: 2.4.1, 2.4.2 | O40: 3(1) 現状の評価・分析 | P40: 未着手 | Q40: ★中間成果物／第2回打合せ資料
B41: 3 | C41: 1 | D41: 人口推計・要支援要介護認定者数の推計 | K41: =SUMIF($C$42:$C$51,3,$K$42:$K$51) | L41: 46308 | M41: 46367 | O41: 3(2) 人口推計等
B42: 3.1 | C42: 2 | D42: 人口推計・要支援要介護認定者数の推計 | E42: 人口推計 | K42: =SUMIF($C$43:$C$45,3,$K$43:$K$45) | L42: 46308 | M42: 46346 | O42: 3(2) 人口推計等
A43: 28 | B43: 3.1.1 | C43: 3 | D43: 人口推計・要支援要介護認定者数の推計 | E43: 人口推計 | F43: 推計手法の設定・基準人口の確定 | G43: コーホート要因法を基本とし、基準人口（住民基本台帳／国勢調査）、基準日、推計単位を村と確認 | H43: 推計条件設定書 | I43: 受託者 | J43: 基準人口の確認 | K43: 0.5 | L43: 46308 | M43: 46318 | N43: 2.1.1 | O43: 3(2) 人口推計等 | P43: 未着手 | Q43: 社人研の仮定値を基本に直近実績で補正
A44: 29 | B44: 3.1.2 | C44: 3 | D44: 人口推計・要支援要介護認定者数の推計 | E44: 人口推計 | F44: 将来人口推計（令和9年度から10年間程度） | G44: 生残率・純移動率・出生仮定を設定し、男女5歳階級別に令和9年度〜令和18年度の人口を推計 | H44: 将来人口推計表・グラフ | I44: 受託者 | J44: － | K44: 1.5 | L44: 46321 | M44: 46339 | N44: 3.1.1 | O44: 3(2) 令和9年から10年間程度の将来推計 | P44: 未着手 | Q44: 65-74歳／75歳以上・高齢化率を算出
A45: 30 | B45: 3.1.3 | C45: 3 | D45: 人口推計・要支援要介護認定者数の推計 | E45: 人口推計 | F45: 推計結果の検証・妥当性確認 | G45: 社人研推計・過去トレンドとの比較検証、村の開発・転入出動向を踏まえた妥当性の確認と補正 | H45: 推計検証資料 | I45: 受託者 | J45: 地域事情の情報提供 | K45: 0.5 | L45: 46335 | M45: 46346 | N45: 3.1.2 | O45: 3(2) 人口推計等 | P45: 未着手 | Q45: 国の基本指針が中長期（令和22年度等）を求める場合は対象年次を追加
B46: 3.2 | C46: 2 | D46: 人口推計・要支援要介護認定者数の推計 | E46: 要支援・要介護認定者数の推計 | K46: =SUMIF($C$47:$C$49,3,$K$47:$K$49) | L46: 46335 | M46: 46365 | O46: 3(2) 認定者数の推計
A47: 31 | B47: 3.2.1 | C47: 3 | D47: 人口推計・要支援要介護認定者数の推計 | E47: 要支援・要介護認定者数の推計 | F47: 性・年齢階級別認定率の設定 | G47: 直近実績から第1号・第2号被保険者の性・年齢階級別認定率を算出し、将来の認定率仮定を設定 | H47: 認定率設定表 | I47: 受託者 | J47: 認定データの確認 | K47: 0.5 | L47: 46335 | M47: 46346 | N47: 2.3.1 | O47: 3(2) 認定者数の推計 | P47: 未着手 | Q47: 国の基本指針の考え方に従い設定
A48: 32 | B48: 3.2.2 | C48: 3 | D48: 人口推計・要支援要介護認定者数の推計 | E48: 要支援・要介護認定者数の推計 | F48: 各年度の要支援・要介護認定者数の推計 | G48: 将来人口×認定率により、要支援1〜要介護5別の各年度認定者数を推計（第10期3か年＋中長期） | H48: 認定者数推計表・グラフ | I48: 受託者 | J48: － | K48: 1.5 | L48: 46342 | M48: 46360 | N48: 3.1.2, 3.2.1 | O48: 3(2) 国の基本指針に従い各年度を推計 | P48: 未着手 | Q48: 4.1 見込量推計の前提
A49: 33 | B49: 3.2.3 | C49: 3 | D49: 人口推計・要支援要介護認定者数の推計 | E49: 要支援・要介護認定者数の推計 | F49: 推計結果の検証・村協議 | G49: 認定調査・審査会の運用状況、施設整備の予定等を踏まえて推計値を検証し、村担当課と確認 | H49: 推計検証・協議記録 | I49: 受託者 | J49: 実務状況の確認・確定 | K49: 0.5 | L49: 46357 | M49: 46365 | N49: 3.2.2 | O49: 3(2) 認定者数の推計 | P49: 未着手 | Q49: 確定値を4章以降で使用
B50: 3.3 | C50: 2 | D50: 人口推計・要支援要介護認定者数の推計 | E50: 推計結果の資料化 | K50: =SUMIF($C$51:$C$51,3,$K$51:$K$51) | L50: 46363 | M50: 46367 | O50: 3(2) 人口推計等
A51: 34 | B51: 3.3.1 | C51: 3 | D51: 人口推計・要支援要介護認定者数の推計 | E51: 推計結果の資料化 | F51: 人口・認定者数推計結果の資料化 | G51: 推計手法・仮定条件・結果を計画掲載用の図表に整理し、根拠データを併せて保存 | H51: 人口・認定者数推計 結果資料 | I51: 受託者 | J51: 内容確認 | K51: 1 | L51: 46363 | M51: 46367 | N51: 3.1.3, 3.2.3 | O51: 3(2) 人口推計等 | P51: 未着手 | Q51: ★中間成果物／計画第2章に反映
B52: 4 | C52: 1 | D52: 介護サービス見込量・保険料の推計 | K52: =SUMIF($C$53:$C$67,3,$K$53:$K$67) | L52: 46357 | M52: 46459 | O52: 3(3) 見込量・保険料
B53: 4.1 | C53: 2 | D53: 介護サービス見込量・保険料の推計 | E53: 介護サービス見込量の推計 | K53: =SUMIF($C$54:$C$57,3,$K$54:$K$57) | L53: 46357 | M53: 46402 | O53: 3(3) サービス見込量
A54: 35 | B54: 4.1.1 | C54: 3 | D54: 介護サービス見込量・保険料の推計 | E54: 介護サービス見込量の推計 | F54: 推計ツールの設定・実績データ投入 | G54: 地域包括ケア「見える化」システム等の推計ツールに、人口・認定者数・給付実績データを投入し初期設定 | H54: 推計ツール設定データ | I54: 受託者 | J54: システム利用環境の確認 | K54: 1 | L54: 46357 | M54: 46367 | N54: 3.2.3, 2.3.2 | O54: 3(3) 推計ツール等を用いて | P54: 未着手 | Q54: 国の最新版ツールの公開時期に留意
A55: 36 | B55: 4.1.2 | C55: 3 | D55: 介護サービス見込量・保険料の推計 | E55: 介護サービス見込量の推計 | F55: サービス種類別見込量の推計（令和9〜11年度） | G55: 居宅・地域密着型・施設サービスの種類ごとに、各年度の受給者数・利用回数（日数）の見込量を推計 | H55: サービス見込量推計表 | I55: 受託者 | J55: － | K55: 2 | L55: 46363 | M55: 46381 | N55: 4.1.1 | O55: 3(3) 令和11年度までの各年度・種類ごと | P55: 未着手 | Q55: 第10期＝令和9〜11年度の3か年
A56: 37 | B56: 4.1.3 | C56: 3 | D56: 介護サービス見込量・保険料の推計 | E56: 介護サービス見込量の推計 | F56: ニーズ調査結果・施策方針の反映 | G56: ニーズ調査結果および村の施策方針（介護予防強化、在宅支援等）を見込量に反映し調整 | H56: 見込量調整記録 | I56: 受託者 | J56: 施策方針の提示 | K56: 1 | L56: 46370 | M56: 46395 | N56: 2.4.2, 4.1.2 | O56: 3(3) ニーズ調査結果の反映 | P56: 未着手 | Q56: 国の指示に適宜対応（仕様書3(3)）
A57: 38 | B57: 4.1.4 | C57: 3 | D57: 介護サービス見込量・保険料の推計 | E57: 介護サービス見込量の推計 | F57: 見込量の妥当性検証・村協議 | G57: 過去トレンド・北海道平均との比較、圏域外利用や事業所の供給力を踏まえた実現可能性を検証 | H57: 見込量検証資料 | I57: 受託者 | J57: 供給力の確認・確定 | K57: 0.5 | L57: 46393 | M57: 46402 | N57: 4.1.3 | O57: 3(3) サービス見込量 | P57: 未着手 | Q57: ★見込量の確定（マイルストーン）
B58: 4.2 | C58: 2 | D58: 介護サービス見込量・保険料の推計 | E58: 給付費・地域支援事業費の見込 | K58: =SUMIF($C$59:$C$60,3,$K$59:$K$60) | L58: 46377 | M58: 46409 | O58: 3(3) 見込量・保険料
A59: 39 | B59: 4.2.1 | C59: 3 | D59: 介護サービス見込量・保険料の推計 | E59: 給付費・地域支援事業費の見込 | F59: 介護報酬改定等の国の情報の反映 | G59: 介護報酬改定率、区分支給限度額、負担割合、公費負担割合等の国の決定事項を確認し前提に反映 | H59: 算定前提条件整理メモ | I59: 受託者 | J59: 国通知の共有 | K59: 0.5 | L59: 46377 | M59: 46402 | N59: － | O59: 5 その他（国の指示の遵守） | P59: 未着手 | Q59: 改定率確定が遅れる場合は暫定値で算定→確定後に再算定
A60: 40 | B60: 4.2.2 | C60: 3 | D60: 介護サービス見込量・保険料の推計 | E60: 給付費・地域支援事業費の見込 | F60: 標準給付費・地域支援事業費の算出 | G60: 見込量×単価により標準給付費を算出し、特定入所者介護サービス費・高額介護サービス費等を加算。地域支援事業費も算出 | H60: 給付費見込算出表 | I60: 受託者 | J60: 地域支援事業の方針提示 | K60: 1 | L60: 46393 | M60: 46409 | N60: 4.1.4, 4.2.1 | O60: 3(3) 見込量・保険料 | P60: 未着手 | Q60: 4.3 保険料算定の入力値
B61: 4.3 | C61: 2 | D61: 介護サービス見込量・保険料の推計 | E61: 第10期介護保険料の算定 | K61: =SUMIF($C$62:$C$65,3,$K$62:$K$65) | L61: 46370 | M61: 46428 | O61: 3(3) 第10期の介護保険料を算定
A62: 41 | B62: 4.3.1 | C62: 3 | D62: 介護サービス見込量・保険料の推計 | E62: 第10期介護保険料の算定 | F62: 保険料算定の前提条件整理 | G62: 第1号被保険者負担割合、調整交付金交付割合、予定収納率、所得段階区分・乗率、被保険者数見込を設定 | H62: 保険料算定前提条件表 | I62: 受託者 | J62: 所得段階別被保険者数の提供 | K62: 0.5 | L62: 46370 | M62: 46395 | N62: 2.3.4 | O62: 3(3) 保険料の算定 | P62: 未着手 | Q62: 村独自の多段階設定の要否を協議
A63: 42 | B63: 4.3.2 | C63: 3 | D63: 介護サービス見込量・保険料の推計 | E63: 第10期介護保険料の算定 | F63: 財政シミュレーション（複数パターン） | G63: 介護給付費準備基金の取崩し額を変えた複数パターンで保険料水準を試算し、財政運営上の影響を整理 | H63: 財政シミュレーション表（複数案） | I63: 受託者 | J63: 基金活用方針の検討 | K63: 1.5 | L63: 46399 | M63: 46416 | N63: 4.2.2, 4.3.1 | O63: 3(3) 保険料の算定 | P63: 未着手 | Q63: 3案程度を提示し村が方針決定
A64: 43 | B64: 4.3.3 | C64: 3 | D64: 介護サービス見込量・保険料の推計 | E64: 第10期介護保険料の算定 | F64: 保険料基準額・所得段階別保険料の算定 | G64: 保険料収納必要額から基準額（月額）を算出し、所得段階別の保険料額を設定。第9期との比較も整理 | H64: 第10期介護保険料算定書 | I64: 受託者 | J64: 方針決定 | K64: 1 | L64: 46412 | M64: 46423 | N64: 4.3.2 | O64: 3(3) 第10期の介護保険料を算定 | P64: 未着手 | Q64: ★保険料算定（マイルストーン）
A65: 44 | B65: 4.3.4 | C65: 3 | D65: 介護サービス見込量・保険料の推計 | E65: 第10期介護保険料の算定 | F65: 算定結果の説明資料作成・村協議 | G65: 算定過程・前提条件・保険料水準の根拠を説明資料に整理し、第3回打合せで報告・協議 | H65: 保険料説明資料 | I65: 受託者 | J65: 内容確認・庁内説明 | K65: 1 | L65: 46419 | M65: 46428 | N65: 4.3.3 | O65: 3(3) 保険料の算定 | P65: 未着手 | Q65: 議会・住民説明での活用を想定
B66: 4.4 | C66: 2 | D66: 介護サービス見込量・保険料の推計 | E66: 国の指示等に伴う再算定対応 | K66: =SUMIF($C$67:$C$67,3,$K$67:$K$67) | L66: 46419 | M66: 46459 | O66: 5 その他
A67: 45 | B67: 4.4.1 | C67: 3 | D67: 介護サービス見込量・保険料の推計 | E67: 国の指示等に伴う再算定対応 | F67: 国の確定情報に基づく見込量・保険料の再算定 | G67: 基本指針の告示・報酬改定率の確定等を受け、必要な範囲で見込量・給付費・保険料を再算定し反映 | H67: 再算定結果・修正版算定書 | I67: 受託者 | J67: 協議・確認 | K67: 1 | L67: 46419 | M67: 46459 | N67: 4.3.3 | O67: 5 その他（国の指示により仕様変更） | P67: 未着手 | Q67: 変更が必要な場合は村と協議して決定
B68: 5 | C68: 1 | D68: 計画素案の作成 | K68: =SUMIF($C$69:$C$90,3,$K$69:$K$90) | L68: 46342 | M68: 46459 | O68: 3(4) 計画素案の作成
B69: 5.1 | C69: 2 | D69: 計画素案の作成 | E69: 課題及び施策の方向の整理 | K69: =SUMIF($C$70:$C$72,3,$K$70:$K$72) | L69: 46350 | M69: 46365 | O69: 3(4)① 課題及び施策の方向
A70: 46 | B70: 5.1.1 | C70: 3 | D70: 計画素案の作成 | E70: 課題及び施策の方向の整理 | F70: 現状分析・推計結果からの課題抽出 | G70: 現状分析・第9期評価・ニーズ調査・推計結果を横断的に整理し、村の高齢者施策の課題を抽出・体系化 | H70: 課題整理シート | I70: 受託者 | J70: 課題認識の共有 | K70: 1 | L70: 46350 | M70: 46360 | N70: 2.4.3 | O70: 3(4)① 課題及び施策の方向 | P70: 未着手 | Q70: 第2回打合せで協議
A71: 47 | B71: 5.1.2 | C71: 3 | D71: 計画素案の作成 | E71: 課題及び施策の方向の整理 | F71: 基本理念・基本目標・施策の方向の整理 | G71: 課題に対応する基本理念、基本目標、施策の柱を整理し、施策体系図として提案 | H71: 基本理念・施策体系図（案） | I71: 受託者 | J71: 方針決定 | K71: 1 | L71: 46356 | M71: 46363 | N71: 5.1.1, 2.4.0 | O71: 3(4)① 課題及び施策の方向 | P71: 未着手 | Q71: ★第9期の理念・目標を継承するか刷新するかの判断が必要。未受領の間は仮置きとし受領後に差替
A72: 48 | B72: 5.1.3 | C72: 3 | D72: 計画素案の作成 | E72: 課題及び施策の方向の整理 | F72: 総合計画等 関連計画との整合性確認 | G72: 村総合計画・地域福祉計画・健康増進計画等と理念・目標・施策の整合を確認し、記述を調整 | H72: 関連計画整合性チェック表 | I72: 受託者 | J72: 関連計画の方針確認 | K72: 0.5 | L72: 46356 | M72: 46365 | N72: 1.3.3, 5.1.2 | O72: 7 留意事項（総合計画等との整合） | P72: 未着手 | Q72: 整合しない箇所は協議のうえ調整
B73: 5.2 | C73: 2 | D73: 計画素案の作成 | E73: 計画骨子の提案 | K73: =SUMIF($C$74:$C$76,3,$K$74:$K$76) | L73: 46342 | M73: 46366 | O73: 3(4)② 計画骨子の提案
A74: 49 | B74: 5.2.1 | C74: 3 | D74: 計画素案の作成 | E74: 計画骨子の提案 | F74: 章立て（目次構成）案の作成 | G74: 国の策定指針の記載事項を踏まえた章立て・節構成、ページ配分、掲載図表の案を作成 | H74: 計画骨子（目次構成）案 | I74: 受託者 | J74: 内容確認 | K74: 0.5 | L74: 46358 | M74: 46365 | N74: 5.1.2 | O74: 3(4)② 計画骨子の提案 | P74: 未着手 | Q74: ★中間成果物
A75: 50 | B75: 5.2.2 | C75: 3 | D75: 計画素案の作成 | E75: 計画骨子の提案 | F75: 国の策定指針 記載事項チェックリスト作成 | G75: 基本指針で定める記載事項（任意記載事項を含む）を一覧化し、計画本文との対応を管理 | H75: 記載事項チェックリスト | I75: 受託者 | J75: － | K75: 0.5 | L75: 46342 | M75: 46353 | N75: － | O75: 3(4)※ 国の策定指針に従い記載 | P75: 未着手 | Q75: 記載漏れ防止のため全編で運用
A76: 51 | B76: 5.2.3 | C76: 3 | D76: 計画素案の作成 | E76: 計画骨子の提案 | F76: 骨子案の提示・確定（第2回打合せ） | G76: 骨子案を提示し、構成・記載レベル・分量を協議のうえ確定 | H76: 確定版 計画骨子 | I76: 受託者 | J76: 出席・決定 | K76: 0.5 | L76: 46366 | M76: 46366 | N76: 5.2.1, 5.2.2 | O76: 3(4)② 計画骨子の提案 | P76: 未着手 | Q76: ★マイルストーン
B77: 5.3 | C77: 2 | D77: 計画素案の作成 | E77: 計画素案の執筆 | K77: =SUMIF($C$78:$C$87,3,$K$78:$K$87) | L77: 46370 | M77: 46428 | O77: 3(4)③ 計画素案の作成
A78: 52 | B78: 5.3.1 | C78: 3 | D78: 計画素案の作成 | E78: 計画素案の執筆 | F78: 第1章 計画の策定にあたって | G78: 計画策定の趣旨、法的位置づけ、計画期間（令和9〜11年度）、関連計画との関係、策定体制・経過を執筆 | H78: 第1章 原稿 | I78: 受託者 | J78: 策定体制情報の提供 | K78: 0.5 | L78: 46370 | M78: 46381 | N78: 5.2.3 | O78: 3(4)③ 計画素案の作成 | P78: 未着手
A79: 53 | B79: 5.3.2 | C79: 3 | D79: 計画素案の作成 | E79: 計画素案の執筆 | F79: 第2章 高齢者を取り巻く現状 | G79: 人口・世帯、高齢化の状況、認定者数、給付実績、ニーズ調査結果、将来推計を図表とともに執筆 | H79: 第2章 原稿 | I79: 受託者 | J79: 内容確認 | K79: 2 | L79: 46370 | M79: 46402 | N79: 2.4.3, 3.3.1 | O79: 3(4)③ 計画素案の作成 | P79: 未着手 | Q79: 現状分析・推計結果を反映
A80: 54 | B80: 5.3.3 | C80: 3 | D80: 計画素案の作成 | E80: 計画素案の執筆 | F80: 第3章 第9期計画の評価と課題 | G80: 第9期計画の進捗評価結果、達成状況、残された課題を整理して執筆 | H80: 第3章 原稿 | I80: 受託者 | J80: 評価結果の確認 | K80: 1 | L80: 46370 | M80: 46395 | N80: 2.4.1, 5.1.1 | O80: 3(1)④／3(4)③ | P80: 未着手
A81: 55 | B81: 5.3.4 | C81: 3 | D81: 計画素案の作成 | E81: 計画素案の執筆 | F81: 第4章 計画の基本的な考え方 | G81: 基本理念、基本目標、施策体系図、日常生活圏域の設定、地域包括ケアシステムの考え方を執筆 | H81: 第4章 原稿 | I81: 受託者 | J81: 方針確認 | K81: 1 | L81: 46377 | M81: 46402 | N81: 5.1.2 | O81: 3(4)③ 計画素案の作成 | P81: 未着手
A82: 56 | B82: 5.3.5 | C82: 3 | D82: 計画素案の作成 | E82: 計画素案の執筆 | F82: 第5章 施策の展開 | G82: 介護予防・健康づくり、地域包括ケア、在宅医療・介護連携、認知症施策、生活支援体制整備、権利擁護、住まい、災害・感染症対策、介護人材確保等の施策を執筆 | H82: 第5章 原稿 | I82: 受託者 | J82: 各事業の方針・実施内容確認 | K82: 3 | L82: 46392 | M82: 46423 | N82: 5.1.2, 5.2.3 | O82: 3(4)③ 計画素案の作成 | P82: 未着手 | Q82: 村単独事業と地域支援事業を体系的に記載
A83: 57 | B83: 5.3.6 | C83: 3 | D83: 計画素案の作成 | E83: 計画素案の執筆 | F83: 第6章 介護保険事業の見込みと保険料 | G83: サービス見込量、標準給付費、地域支援事業費、第10期介護保険料（所得段階別）を執筆 | H83: 第6章 原稿 | I83: 受託者 | J83: 保険料方針の決定 | K83: 1.5 | L83: 46412 | M83: 46427 | N83: 4.1.4, 4.3.3 | O83: 3(3)／3(4)③ | P83: 未着手 | Q83: 保険料は村の方針決定後に確定
A84: 58 | B84: 5.3.7 | C84: 3 | D84: 計画素案の作成 | E84: 計画素案の執筆 | F84: 第7章 計画の推進体制 | G84: 推進体制、関係機関との連携、PDCAによる進行管理、評価指標・目標値の設定方法を執筆 | H84: 第7章 原稿 | I84: 受託者 | J84: 推進体制の確認 | K84: 0.5 | L84: 46406 | M84: 46416 | N84: 5.2.3 | O84: 3(4)③ 計画素案の作成 | P84: 未着手 | Q84: 第10期の進捗管理方法を明記
A85: 59 | B85: 5.3.8 | C85: 3 | D85: 計画素案の作成 | E85: 計画素案の執筆 | F85: 資料編の作成 | G85: 策定経過、ニーズ調査結果概要、用語解説、関係法令抜粋、統計資料等を資料編として編集 | H85: 資料編 原稿 | I85: 受託者 | J85: 策定経過情報の提供 | K85: 1 | L85: 46406 | M85: 46423 | N85: 5.3.2 | O85: 3(4)③ 計画素案の作成 | P85: 未着手
A86: 60 | B86: 5.3.9 | C86: 3 | D86: 計画素案の作成 | E86: 計画素案の執筆 | F86: 図表作成・レイアウト・校正 | G86: 図表・グラフの統一デザイン適用、体裁調整、数値・図表番号・用語の整合確認、通読校正 | H86: レイアウト済 素案データ | I86: 受託者 | J86: － | K86: 2 | L86: 46413 | M86: 46427 | N86: 5.3.5, 5.3.6 | O86: 3(4)③ 計画素案の作成 | P86: 未着手 | Q86: 既存のコラム部品ライブラリを活用可
A87: 61 | B87: 5.3.10 | C87: 3 | D87: 計画素案の作成 | E87: 計画素案の執筆 | F87: 計画素案の提出・協議（第3回打合せ） | G87: 計画素案一式を提出し、内容・表現・分量を協議。修正方針を確認 | H87: 計画素案（第1版） | I87: 受託者 | J87: 出席・査読 | K87: 0.5 | L87: 46428 | M87: 46428 | N87: 5.3.9 | O87: 3(4)③ 計画素案の作成 | P87: 未着手 | Q87: ★マイルストーン／中間成果物
B88: 5.4 | C88: 2 | D88: 計画素案の作成 | E88: 素案の修正・反映 | K88: =SUMIF($C$89:$C$90,3,$K$89:$K$90) | L88: 46430 | M88: 46459 | O88: 3(4)③／7 留意事項
A89: 62 | B89: 5.4.1 | C89: 3 | D89: 計画素案の作成 | E89: 素案の修正・反映 | F89: 村意見の反映・修正 | G89: 第3回打合せおよび庁内査読で示された意見を反映し、素案を修正 | H89: 計画素案（修正版） | I89: 受託者 | J89: 意見の取りまとめ | K89: 1.5 | L89: 46430 | M89: 46451 | N89: 5.3.10 | O89: 3(4)③ 計画素案の作成 | P89: 未着手
A90: 63 | B90: 5.4.2 | C90: 3 | D90: 計画素案の作成 | E90: 素案の修正・反映 | F90: パブリックコメント等の意見反映 | G90: 村が実施するパブリックコメント・住民説明等で寄せられた意見への対応案を作成し、計画に反映 | H90: 意見対応表／反映版原稿 | I90: 受託者 | J90: パブコメの実施・意見提供 | K90: 0.5 | L90: 46430 | M90: 46459 | N90: 5.4.1 | O90: 7 留意事項（協議） | P90: 未着手 | Q90: パブコメの実施主体・日程は村と協議（仕様書に明記なし）
B91: 6 | C91: 1 | D91: 成果品の作成・納品 | K91: =SUMIF($C$92:$C$98,3,$K$92:$K$98) | L91: 46454 | M91: 46477 | O91: 6 成果品
B92: 6.1 | C92: 2 | D92: 成果品の作成・納品 | E92: 成果品の作成 | K92: =SUMIF($C$93:$C$95,3,$K$93:$K$95) | L92: 46454 | M92: 46472 | O92: 6 成果品
A93: 64 | B93: 6.1.1 | C93: 3 | D93: 成果品の作成・納品 | E93: 成果品の作成 | F93: 最終原稿の確定・最終校正 | G93: 全編の通し校正（誤字脱字、数値・図表の整合、出典表記、用語統一）を行い最終原稿を確定 | H93: 最終原稿 | I93: 受託者 | J93: 最終確認 | K93: 1 | L93: 46454 | M93: 46465 | N93: 5.4.2 | O93: 6 成果品 | P93: 未着手
A94: 65 | B94: 6.1.2 | C94: 3 | D94: 成果品の作成・納品 | E94: 成果品の作成 | F94: 成果品データの作成（CD-R収録） | G94: 計画本編・資料編の編集可能データ（Word等）およびPDFを作成し、CD-Rに収録・ラベル作成 | H94: 計画（CDデータ）1部 | I94: 受託者 | J94: 検収 | K94: 0.5 | L94: 46463 | M94: 46472 | N94: 6.1.1 | O94: 6 成果品（CDデータ 1部） | P94: 未着手 | Q94: 著作権は音威子府村に帰属
A95: 66 | B95: 6.1.3 | C95: 3 | D95: 成果品の作成・納品 | E95: 成果品の作成 | F95: 業務データの整理・収録 | G95: 推計データ、集計表、図表の元データ、収集統計、算定シート等を整理し磁気媒体（CD-R）に収録 | H95: 業務データ収録媒体（CDデータ）1部 | I95: 受託者 | J95: 検収 | K95: 0.5 | L95: 46463 | M95: 46472 | N95: 6.1.1 | O95: 6 成果品（業務データ CDデータ 1部） | P95: 未着手 | Q95: 村での更新作業を想定した構成とする
B96: 6.2 | C96: 2 | D96: 成果品の作成・納品 | E96: 納品・完了手続 | K96: =SUMIF($C$97:$C$98,3,$K$97:$K$98) | L96: 46475 | M96: 46477 | O96: 2 委託期間／6 成果品
A97: 67 | B97: 6.2.1 | C97: 3 | D97: 成果品の作成・納品 | E97: 納品・完了手続 | F97: 納品・検査対応 | G97: 成果品の納品、業務完了届の提出、検査対応、指摘事項の修正 | H97: 業務完了届／検査調書 | I97: 受託者 | J97: 検査・完了確認 | K97: 0.5 | L97: 46475 | M97: 46477 | N97: 6.1.2, 6.1.3 | O97: 2 委託期間（令和9年3月31日） | P97: 未着手 | Q97: ★マイルストーン／履行期限厳守
A98: 68 | B98: 6.2.2 | C98: 3 | D98: 成果品の作成・納品 | E98: 納品・完了手続 | F98: 貸与資料・個人情報の返却／消去 | G98: 貸与資料の返却、業務上取得した個人情報を含むデータの消去・廃棄と証明書の提出 | H98: 資料返却書／データ消去証明 | I98: 受託者 | J98: 受領確認 | K98: 0.3 | L98: 46475 | M98: 46477 | N98: 6.2.1 | O98: 7 留意事項（個人情報） | P98: 未着手 | Q98: 音威子府村個人情報保護条例を遵守
A99: 合計（レベル3の作業項目） | K99: =SUMIF($C$5:$C$98,3,$K$5:$K$98) | L99: 人日（1人日＝7.5時間／1人月＝20人日換算）

Sheet 02_スケジュール
A1: 実施スケジュール（ガントチャート） ／ 音威子府村高齢者福祉計画・第10期介護保険事業計画 策定業務委託
A2: 期間：契約締結日（令和8年9月1日と仮定）〜令和9年3月31日 半月単位 ／ ■＝作業期間 ◆＝打合せ・提出等のマイルストーン
A3: WBS No. | B3: 作業項目 | C3: 主担当 | D3: 工数 (人日) | E3: 開始予定 | F3: 完了予定 | G3: 9月 | I3: 10月 | K3: 11月 | M3: 12月 | O3: 1月 | Q3: 2月 | S3: 3月
G4: 前半 | H4: 後半 | I4: 前半 | J4: 後半 | K4: 前半 | L4: 後半 | M4: 前半 | N4: 後半 | O4: 前半 | P4: 後半 | Q4: 前半 | R4: 後半 | S4: 前半 | T4: 後半
A5: 1 | B5: 業務管理・打合せ | E5: 46266 | F5: 46477
A6: 1.1 | B6: 業務着手準備 | E6: 46266 | F6: 46283
A7: 1.1.1 | B7: 契約締結・業務実施体制の確定 | C7: 受託者 | D7: 0.5 | E7: 46266 | F7: 46269
A8: 1.1.2 | B8: 業務実施計画書・詳細工程表の作成 | C8: 受託者 | D8: 1 | E8: 46266 | F8: 46283
A9: 1.1.3 | B9: 【第1回打合せ】キックオフ | C9: 受託者 | D9: 1 | E9: 46275 | F9: 46275 | G9: ◆
A10: 1.1.4 | B10: 個人情報・機密情報の取扱手続 | C10: 受託者 | D10: 0.5 | E10: 46266 | F10: 46276
A11: 1.2 | B11: 進行管理 | E11: 46266 | F11: 46477
A12: 1.2.1 | B12: 定例連絡・進捗報告 | C12: 受託者 | D12: 2 | E12: 46266 | F12: 46477
A13: 1.2.2 | B13: 【第2回打合せ】現状分析・骨子報告 | C13: 受託者 | D13: 1 | E13: 46366 | F13: 46366 | M13: ◆
A14: 1.2.3 | B14: 【第3回打合せ】計画素案・保険料報告 | C14: 受託者 | D14: 1 | E14: 46428 | F14: 46428 | Q14: ◆
A15: 1.2.4 | B15: 国の指示・基本指針変更への対応協議 | C15: 受託者 | D15: 0.5 | E15: 46266 | F15: 46477
A16: 1.3 | B16: 資料収集・整理 | E16: 46273 | F16: 46310
A17: 1.3.1 | B17: 村提供資料の受領・確認 | C17: 受託者 | D17: 0.5 | E17: 46273 | F17: 46295
A18: 1.3.2 | B18: 公表統計・システムデータの収集 | C18: 受託者 | D18: 1 | E18: 46273 | F18: 46310
A19: 1.3.3 | B19: 関連計画・関連資料の収集 | C19: 受託者 | D19: 0.5 | E19: 46273 | F19: 46310
A20: 1.3.4 | B20: 見える化システムデータの棚卸し | C20: 受託者 | D20: 1 | E20: 46273 | F20: 46283
A21: 1.3.5 | B21: 未取得データの再取得・代替データの確保 | C21: 受託者 | D21: 1 | E21: 46281 | F21: 46310
A22: 2 | B22: 現状の評価・分析 | E22: 46273 | F22: 46353
A23: 2.1 | B23: 基礎的資料による現状把握・分析 | E23: 46296 | F23: 46325
A24: 2.1.1 | B24: 人口・世帯の動向分析 | C24: 受託者 | D24: 1.5 | E24: 46296 | F24: 46318
A25: 2.1.2 | B25: 地域資源・社会基盤の整理 | C25: 受託者 | D25: 1 | E25: 46296 | F25: 46318
A26: 2.1.3 | B26: 北海道・全国・類似団体との比較分析 | C26: 受託者 | D26: 0.5 | E26: 46308 | F26: 46325
A27: 2.2 | B27: 高齢者福祉サービス実績の分析 | E27: 46296 | F27: 46326
A28: 2.2.1 | B28: 高齢者福祉施策（村単独事業）の実績分析 | C28: 受託者 | D28: 1 | E28: 46296 | F28: 46326
A29: 2.2.2 | B29: 介護予防・日常生活支援総合事業の実績分析 | C29: 受託者 | D29: 1 | E29: 46296 | F29: 46326
A30: 2.2.3 | B30: 包括的支援事業・任意事業の実績分析 | C30: 受託者 | D30: 0.5 | E30: 46308 | F30: 46326
A31: 2.3 | B31: 介護保険サービス実績の分析 | E31: 46296 | F31: 46346
A32: 2.3.1 | B32: 要介護認定者数・認定率の推移分析 | C32: 受託者 | D32: 1.5 | E32: 46296 | F32: 46326
A33: 2.3.2 | B33: サービス種類別給付実績の分析 | C33: 受託者 | D33: 1.5 | E33: 46301 | F33: 46339
A34: 2.3.3 | B34: 受給率・利用率・1人当たり給付費の分析 | C34: 受託者 | D34: 1 | E34: 46315 | F34: 46339
A35: 2.3.4 | B35: 介護保険財政・保険料収納状況の分析 | C35: 受託者 | D35: 1 | E35: 46315 | F35: 46346
A36: 2.4 | B36: 現行計画（第9期）の点検・評価 | E36: 46273 | F36: 46353
A37: 2.4.0 | B37: 【前提】第9期計画本体の受領 | C37: 受託者 | D37: 0.5 | E37: 46273 | F37: 46297
A38: 2.4.1 | B38: 施策・事業別の進捗評価 | C38: 受託者 | D38: 1.5 | E38: 46328 | F38: 46346
A39: 2.4.2 | B39: 介護予防・日常生活圏域ニーズ調査結果の整理・分析 | C39: 受託者 | D39: 1.5 | E39: 46308 | F39: 46339
A40: 2.4.3 | B40: 現状分析・評価の総括資料作成 | C40: 受託者 | D40: 1 | E40: 46342 | F40: 46353
A41: 3 | B41: 人口推計・要支援要介護認定者数の推計 | E41: 46308 | F41: 46367
A42: 3.1 | B42: 人口推計 | E42: 46308 | F42: 46346
A43: 3.1.1 | B43: 推計手法の設定・基準人口の確定 | C43: 受託者 | D43: 0.5 | E43: 46308 | F43: 46318
A44: 3.1.2 | B44: 将来人口推計（令和9年度から10年間程度） | C44: 受託者 | D44: 1.5 | E44: 46321 | F44: 46339
A45: 3.1.3 | B45: 推計結果の検証・妥当性確認 | C45: 受託者 | D45: 0.5 | E45: 46335 | F45: 46346
A46: 3.2 | B46: 要支援・要介護認定者数の推計 | E46: 46335 | F46: 46365
A47: 3.2.1 | B47: 性・年齢階級別認定率の設定 | C47: 受託者 | D47: 0.5 | E47: 46335 | F47: 46346
A48: 3.2.2 | B48: 各年度の要支援・要介護認定者数の推計 | C48: 受託者 | D48: 1.5 | E48: 46342 | F48: 46360
A49: 3.2.3 | B49: 推計結果の検証・村協議 | C49: 受託者 | D49: 0.5 | E49: 46357 | F49: 46365
A50: 3.3 | B50: 推計結果の資料化 | E50: 46363 | F50: 46367
A51: 3.3.1 | B51: 人口・認定者数推計結果の資料化 | C51: 受託者 | D51: 1 | E51: 46363 | F51: 46367
A52: 4 | B52: 介護サービス見込量・保険料の推計 | E52: 46357 | F52: 46459
A53: 4.1 | B53: 介護サービス見込量の推計 | E53: 46357 | F53: 46402
A54: 4.1.1 | B54: 推計ツールの設定・実績データ投入 | C54: 受託者 | D54: 1 | E54: 46357 | F54: 46367
A55: 4.1.2 | B55: サービス種類別見込量の推計（令和9〜11年度） | C55: 受託者 | D55: 2 | E55: 46363 | F55: 46381
A56: 4.1.3 | B56: ニーズ調査結果・施策方針の反映 | C56: 受託者 | D56: 1 | E56: 46370 | F56: 46395
A57: 4.1.4 | B57: 見込量の妥当性検証・村協議 | C57: 受託者 | D57: 0.5 | E57: 46393 | F57: 46402
A58: 4.2 | B58: 給付費・地域支援事業費の見込 | E58: 46377 | F58: 46409
A59: 4.2.1 | B59: 介護報酬改定等の国の情報の反映 | C59: 受託者 | D59: 0.5 | E59: 46377 | F59: 46402
A60: 4.2.2 | B60: 標準給付費・地域支援事業費の算出 | C60: 受託者 | D60: 1 | E60: 46393 | F60: 46409
A61: 4.3 | B61: 第10期介護保険料の算定 | E61: 46370 | F61: 46428
A62: 4.3.1 | B62: 保険料算定の前提条件整理 | C62: 受託者 | D62: 0.5 | E62: 46370 | F62: 46395
A63: 4.3.2 | B63: 財政シミュレーション（複数パターン） | C63: 受託者 | D63: 1.5 | E63: 46399 | F63: 46416
A64: 4.3.3 | B64: 保険料基準額・所得段階別保険料の算定 | C64: 受託者 | D64: 1 | E64: 46412 | F64: 46423
A65: 4.3.4 | B65: 算定結果の説明資料作成・村協議 | C65: 受託者 | D65: 1 | E65: 46419 | F65: 46428
A66: 4.4 | B66: 国の指示等に伴う再算定対応 | E66: 46419 | F66: 46459
A67: 4.4.1 | B67: 国の確定情報に基づく見込量・保険料の再算定 | C67: 受託者 | D67: 1 | E67: 46419 | F67: 46459
A68: 5 | B68: 計画素案の作成 | E68: 46342 | F68: 46459
A69: 5.1 | B69: 課題及び施策の方向の整理 | E69: 46350 | F69: 46365
A70: 5.1.1 | B70: 現状分析・推計結果からの課題抽出 | C70: 受託者 | D70: 1 | E70: 46350 | F70: 46360
A71: 5.1.2 | B71: 基本理念・基本目標・施策の方向の整理 | C71: 受託者 | D71: 1 | E71: 46356 | F71: 46363
A72: 5.1.3 | B72: 総合計画等 関連計画との整合性確認 | C72: 受託者 | D72: 0.5 | E72: 46356 | F72: 46365
A73: 5.2 | B73: 計画骨子の提案 | E73: 46342 | F73: 46366
A74: 5.2.1 | B74: 章立て（目次構成）案の作成 | C74: 受託者 | D74: 0.5 | E74: 46358 | F74: 46365
A75: 5.2.2 | B75: 国の策定指針 記載事項チェックリスト作成 | C75: 受託者 | D75: 0.5 | E75: 46342 | F75: 46353
A76: 5.2.3 | B76: 骨子案の提示・確定（第2回打合せ） | C76: 受託者 | D76: 0.5 | E76: 46366 | F76: 46366 | M76: ◆
A77: 5.3 | B77: 計画素案の執筆 | E77: 46370 | F77: 46428
A78: 5.3.1 | B78: 第1章 計画の策定にあたって | C78: 受託者 | D78: 0.5 | E78: 46370 | F78: 46381
A79: 5.3.2 | B79: 第2章 高齢者を取り巻く現状 | C79: 受託者 | D79: 2 | E79: 46370 | F79: 46402
A80: 5.3.3 | B80: 第3章 第9期計画の評価と課題 | C80: 受託者 | D80: 1 | E80: 46370 | F80: 46395
A81: 5.3.4 | B81: 第4章 計画の基本的な考え方 | C81: 受託者 | D81: 1 | E81: 46377 | F81: 46402
A82: 5.3.5 | B82: 第5章 施策の展開 | C82: 受託者 | D82: 3 | E82: 46392 | F82: 46423
A83: 5.3.6 | B83: 第6章 介護保険事業の見込みと保険料 | C83: 受託者 | D83: 1.5 | E83: 46412 | F83: 46427
A84: 5.3.7 | B84: 第7章 計画の推進体制 | C84: 受託者 | D84: 0.5 | E84: 46406 | F84: 46416
A85: 5.3.8 | B85: 資料編の作成 | C85: 受託者 | D85: 1 | E85: 46406 | F85: 46423
A86: 5.3.9 | B86: 図表作成・レイアウト・校正 | C86: 受託者 | D86: 2 | E86: 46413 | F86: 46427
A87: 5.3.10 | B87: 計画素案の提出・協議（第3回打合せ） | C87: 受託者 | D87: 0.5 | E87: 46428 | F87: 46428 | Q87: ◆
A88: 5.4 | B88: 素案の修正・反映 | E88: 46430 | F88: 46459
A89: 5.4.1 | B89: 村意見の反映・修正 | C89: 受託者 | D89: 1.5 | E89: 46430 | F89: 46451
A90: 5.4.2 | B90: パブリックコメント等の意見反映 | C90: 受託者 | D90: 0.5 | E90: 46430 | F90: 46459
A91: 6 | B91: 成果品の作成・納品 | E91: 46454 | F91: 46477
A92: 6.1 | B92: 成果品の作成 | E92: 46454 | F92: 46472
A93: 6.1.1 | B93: 最終原稿の確定・最終校正 | C93: 受託者 | D93: 1 | E93: 46454 | F93: 46465
A94: 6.1.2 | B94: 成果品データの作成（CD-R収録） | C94: 受託者 | D94: 0.5 | E94: 46463 | F94: 46472
A95: 6.1.3 | B95: 業務データの整理・収録 | C95: 受託者 | D95: 0.5 | E95: 46463 | F95: 46472
A96: 6.2 | B96: 納品・完了手続 | E96: 46475 | F96: 46477
A97: 6.2.1 | B97: 納品・検査対応 | C97: 受託者 | D97: 0.5 | E97: 46475 | F97: 46477
A98: 6.2.2 | B98: 貸与資料・個人情報の返却／消去 | C98: 受託者 | D98: 0.3 | E98: 46475 | F98: 46477
A100: 凡例
B101: 1. 業務管理・打合せ
...

Sheet 03_マイルストーン
A1: マイルストーン・会議体一覧
A2: 打合せは仕様書「4 打合せ」に基づき3回程度。受託者側は計画策定担当者本人が出席する。日程は村と協議のうえ確定。
A4: No. | B4: マイルストーン | C4: 予定時期 | D4: WBS No. | E4: 関係者 | F4: 達成基準・協議内容 | G4: 提出物・成果物
A5: M-01 | B5: 契約締結・業務着手 | C5: 令和8年9月上旬 | D5: 1.1.1 | E5: 受託者・村 | F5: 契約書・仕様書の確認、業務従事者の確定 | G5: －
A6: M-02 | B6: 【第1回打合せ】キックオフ | C6: 令和8年9月中旬 | D6: 1.1.3 | E6: 受託者・村 | F6: 業務実施計画・工程の協議、論点共有、貸与資料の確認 | G6: 第1回打合せ資料／議事録
A7: M-03 | B7: 貸与資料一式の受領完了 | C7: 令和8年9月末 | D7: 1.3.1 | E7: 村 | F7: 分析着手に必要な実績・統計データが揃うこと | G7: 貸与資料リスト（受領済）
A8: M-04 | B8: 現状分析・第9期評価の完了 | C8: 令和8年11月下旬 | D8: 2.4.3 | E8: 受託者 | F8: 現状分析・実績分析・現行計画評価の取りまとめ | G8: 現状分析・評価 中間報告資料
A9: M-05 | B9: 【第2回打合せ】現状分析・骨子報告 | C9: 令和8年12月上旬 | D9: 1.2.2／5.2.3 | E9: 受託者・村 | F9: 課題と施策の方向の協議、計画骨子の確定 | G9: 第2回打合せ資料／確定版計画骨子
A10: M-06 | B10: 人口・要支援要介護認定者数推計の確定 | C10: 令和8年12月中旬 | D10: 3.3.1 | E10: 受託者・村 | F10: 推計手法・仮定条件・結果の村確認 | G10: 人口・認定者数推計 結果資料
A11: M-07 | B11: 介護サービス見込量の確定 | C11: 令和9年1月中旬 | D11: 4.1.4 | E11: 受託者・村 | F11: 令和9〜11年度のサービス種類別見込量の確定 | G11: サービス見込量推計表
A12: M-08 | B12: 第10期介護保険料（第1次案）の算定 | C12: 令和9年2月上旬 | D12: 4.3.3 | E12: 受託者・村 | F12: 基金取崩し方針の決定、保険料基準額の算定 | G12: 第10期介護保険料算定書
A13: M-09 | B13: 【第3回打合せ】計画素案・保険料報告 | C13: 令和9年2月中旬 | D13: 1.2.3 | E13: 受託者・村 | F13: 計画素案および保険料算定結果の報告・協議 | G13: 第3回打合せ資料／議事録
A14: M-10 | B14: 計画素案の提出 | C14: 令和9年2月中旬 | D14: 5.3.10 | E14: 受託者 | F14: 国の策定指針の記載事項を満たした素案の提出 | G14: 計画素案（第1版）
A15: M-11 | B15: 住民意見等の反映完了 | C15: 令和9年3月中旬 | D15: 5.4.2 | E15: 受託者・村 | F15: パブリックコメント等の意見への対応（村実施分） | G15: 意見対応表／反映版原稿
A16: M-12 | B16: 成果品の納品・検査 | C16: 令和9年3月31日 | D16: 6.2.1 | E16: 受託者・村 | F16: 履行期限。計画（CD）1部・業務データ（CD）1部の納品 | G16: 計画CD／業務データCD／業務完了届

Sheet 04_成果物一覧
A1: 成果物・提出物一覧
A2: 仕様書「6 成果品」に定める最終成果品のほか、業務進行上必要となる中間成果物・管理資料を整理したもの。
A4: 区分 | B4: 名称 | C4: 形式 | D4: 部数・数量 | E4: 提出時期 | F4: WBS No. | G4: 備考・根拠
A5: 最終成果品 | B5: 高齢者福祉計画・第10期介護保険事業計画 | C5: CD-R（Word/Excel等の編集可能データ＋PDF） | D5: 1部 | E5: 令和9年3月31日 | F5: 6.1.2 | G5: 仕様書「6 成果品」／著作権は音威子府村に帰属
A6: 最終成果品 | B6: 業務データ収録の磁気媒体 | C6: CD-R（推計データ・集計表・図表元データ等） | D6: 1部 | E6: 令和9年3月31日 | F6: 6.1.3 | G6: 仕様書「6 成果品」／村での更新作業を想定した構成
A7: 中間成果物 | B7: 業務実施計画書・詳細工程表（本WBS） | C7: 電子データ | D7: 1式 | E7: 令和8年9月中旬 | F7: 1.1.2 | G7: 第1回打合せで協議・確定
A8: 中間成果物 | B8: 貸与資料リスト（依頼票） | C8: 電子データ | D8: 1式 | E8: 令和8年9月上旬 | F8: 1.3.1 | G8: 契約後2週間以内に提示
A9: 中間成果物 | B9: 現状分析・評価 中間報告資料 | C9: 電子データ（PowerPoint/PDF等） | D9: 1式 | E9: 令和8年11月下旬 | F9: 2.4.3 | G9: 第2回打合せ資料
A10: 中間成果物 | B10: 人口・要支援要介護認定者数 推計結果資料 | C10: 電子データ（Excel＋図表） | D10: 1式 | E10: 令和8年12月中旬 | F10: 3.3.1 | G10: 推計条件・仮定値を明記
A11: 中間成果物 | B11: 介護サービス見込量 推計表 | C11: 電子データ（Excel） | D11: 1式 | E11: 令和9年1月中旬 | F11: 4.1.2 | G11: サービス種類別・年度別（令和9〜11年度）
A12: 中間成果物 | B12: 第10期介護保険料 算定書・財政シミュレーション | C12: 電子データ（Excel） | D12: 1式 | E12: 令和9年2月上旬 | F12: 4.3.2／4.3.3 | G12: 複数パターンの比較を含む
A13: 中間成果物 | B13: 計画骨子（目次構成）案 | C13: 電子データ | D13: 1式 | E13: 令和8年12月上旬 | F13: 5.2.1 | G13: 国の策定指針の記載事項チェックリストを添付
A14: 中間成果物 | B14: 計画素案（第0版・たたき台） | C14: 電子データ（Word） | D14: 1式 | E14: 令和8年9月 | F14: 5.3 | G14: ★第9期計画未受領のため理念・目標・第3章は仮置き。『【要差替】』箇所あり
A15: 中間成果物 | B15: 計画素案（第1版） | C15: 電子データ（Word/PDF） | D15: 1式 | E15: 令和9年2月中旬 | F15: 5.3.10 | G15: 第3回打合せで提出・協議
... A19: 管理資料 | B19: 個人情報取扱いに関する誓約書・データ消去証明 | C19: 書面／電子データ | D19: 各1式 | E19: 着手時／完了時 | F19: 1.1.4／6.2.2 | G19: 音威子府村個人情報保護条例を遵守

Sheet 05_推計作業手順
A1: 推計作業の手順・使用データ（仕様書 3(2)(3) の詳細展開）
A2: 仕様書に定める「人口推計・要支援要介護認定者数の推計」および「介護サービス見込量、保険料の推計」の作業手順を分解したもの。国の基本指針・推計ツールの公開状況により手順は適宜見直す。
A4: 工程 | B4: No. | C4: 手順 | D4: 使用データ・ツール | E4: 留意点 | F4: WBS No.
A5: Ⅰ. 人口推計 | B5: 1 | C5: 基準人口の設定 | D5: 住民基本台帳人口（各年10月1日現在、男女・5歳階級別）／国勢調査 | E5: 住基と国勢調査の差異を確認し、どちらを基準とするか村と合意する | F5: 3.1.1
B6: 2 | C6: 生残率・純移動率の仮定値設定 | D6: 社人研「日本の地域別将来推計人口」の仮定値／直近の人口動態実績 | E6: 小規模自治体は年変動が大きいため、複数年平均で平滑化する | F6: 3.1.1
B7: 3 | C7: 出生仮定の設定（子ども女性比・0-4歳性比） | D7: 人口動態統計（出生数）／住基 | E7: 出生数が極少の年があるため、実績の単純外挿は避ける | F7: 3.1.1
B8: 4 | C8: コーホート要因法による将来人口推計 | D8: 推計シート（Excel）／社人研仮定値 | E8: 令和9年度〜令和18年度（10年間程度）を男女5歳階級別に推計 | F8: 3.1.2
B9: 5 | C9: 高齢者人口・高齢化率の算出 | D9: 推計結果 | E9: 65〜74歳／75歳以上、高齢化率、後期高齢者割合を年度別に整理 | F9: 3.1.2
B10: 6 | C10: 推計結果の検証 | D10: 社人研推計値／過去10年の実績トレンド | E10: 乖離が大きい場合は仮定値を再設定し、根拠を記録に残す | F10: 3.1.3
A11: Ⅱ. 認定者数推計 | B11: 1 | C11: 認定者数実績の整理 | D11: 介護保険事業状況報告／村の認定データ（要支援1〜要介護5・性・年齢階級別） | E11: 直近5年分。年度末（3月末）現在で統一する | F11: 3.2.1
B12: 2 | C12: 性・年齢階級別認定率の算出 | D12: 認定者数実績 ÷ 該当年齢階級人口 | E12: 第1号（65歳以上）・第2号（40〜64歳）を区分して算出 | F12: 3.2.1
B13: 3 | C13: 将来の認定率仮定の設定 | D13: 国の基本指針／直近実績／北海道平均 | E13: 直近実績固定を基本とし、傾向が明確な場合のみトレンドを反映 | F13: 3.2.1
B14: 4 | C14: 各年度の認定者数の推計 | D14: 将来人口 × 認定率 | E14: 令和9〜11年度（第10期）に加え、中長期年次の要否を国の指針で確認 | F14: 3.2.2
B15: 5 | C15: 推計結果の検証・確定 | D15: 認定調査・審査会の運用状況／施設整備予定 | E15: 村担当課の実務感覚と照合し、必要に応じて補正する | F15: 3.2.3
A16: Ⅲ. サービス見込量推計 | B16: 1 | C16: 推計ツールへのデータ投入 | D16: 地域包括ケア「見える化」システム等の推計ツール | E16: 国の最新版ツールの公開時期を確認。公開前は暫定シートで先行作業 | F16: 4.1.1
B17: 2 | C17: サービス種類別の受給率・利用量の設定 | D17: 給付実績（国保連データ・事業状況報告） | E17: 小規模ゆえ1人の増減で率が大きく振れる。実人数ベースでも確認する | F17: 4.1.2
B18: 3 | C18: 施設・居住系サービスの整備方針の反映 | D18: 村・北海道の整備方針／既存施設の定員 | E18: 圏域外（近隣市町村）の施設利用分を明示的に見込む | F18: 4.1.2
B19: 4 | C19: 総合事業・地域支援事業の見込量設定 | D19: 総合事業実績／地域支援事業実施計画 | E19: 上限額（事業費の枠）との整合を確認する | F19: 4.1.2
B20: 5 | C20: ニーズ調査結果・施策方針の反映 | D20: 介護予防・日常生活圏域ニーズ調査（令和8年度村実施） | E20: 介護予防強化等の施策効果をどこまで見込むか村と合意する | F20: 4.1.3
B21: 6 | C21: 見込量の妥当性検証 | D21: 過去トレンド／北海道平均／事業所の供給力 | E21: 供給力を超える見込みは実現可能性の観点から再検討する | F21: 4.1.4
A22: Ⅳ. 給付費・保険料算定 | B22: 1 | C22: 標準給付費見込額の算出 | D22: 見込量 × 単位数単価 × 介護報酬改定率 | E22: 改定率未確定の段階は暫定値（前提を明記）で算定する | F22: 4.2.2
B23: 2 | C23: 特定入所者介護サービス費等の加算 | D23: 補足給付・高額介護サービス費・審査支払手数料の実績 | E23: 実績ベースで見込み、制度改正の影響を確認する | F23: 4.2.2
B24: 3 | C24: 地域支援事業費の見込 | D24: 総合事業・包括的支援事業・任意事業の事業費 | E24: 上限額の算定式に沿って確認する | F24: 4.2.2
B25: 4 | C25: 算定前提条件の設定 | D25: 第1号被保険者負担割合／調整交付金交付割合／予定収納率／所得段階別被保険者数 | E25: 国の基本指針で示される割合を反映。確定前は暫定値とする | F25: 4.3.1
B26: 5 | C26: 介護給付費準備基金の取崩し方針の検討 | D26: 基金残高推移／第9期の収支実績 | E26: 取崩し額を変えた複数パターン（3案程度）を提示し村が方針決定 | F26: 4.3.2
B27: 6 | C27: 保険料収納必要額・基準額の算出 | D27: 標準給付費＋地域支援事業費 − 各種公費・調整交付金 − 基金取崩し | E27: 第9期基準額との比較・増減要因を必ず整理する | F27: 4.3.3
B28: 7 | C28: 所得段階別保険料額の設定 | D28: 国の標準段階・乗率／村独自段階の要否 | E28: 多段階化の要否は村の被保険者構成を踏まえて協議する | F28: 4.3.3
B29: 8 | C29: 算定結果の説明資料化 | D29: 算定書・比較表・グラフ | E29: 議会・住民説明に耐える根拠の明示（前提条件を必ず併記） | F29: 4.3.4
B30: 9 | C30: 国の確定情報に基づく再算定 | D30: 基本指針の告示／介護報酬改定率の確定値 | E30: 確定が年度末にずれ込む場合、再算定の要否を村と協議（仕様書5） | F30: 4.4.1

Sheet 06_必要資料リスト
A1: 必要資料リスト（貸与依頼票）
A2: 契約後2週間以内に村へ提示し、資料の授受状況を管理する。個人情報を含む資料は原則として個人が特定されない集計値で受領し、音威子府村個人情報保護条例に基づき取り扱う。
A4: 区分 | B4: 資料名 | C4: 対象期間・粒度 | D4: 入手先 | E4: 個人情報の取扱い | F4: 提出期限目安 | G4: 用途（WBS No.） | H4: 受領状況
A5: 計画 | B5: 第9期高齢者福祉計画・介護保険事業計画（本編・資料編） | C5: 現行計画一式 | D5: 村 | E5: なし | F5: 令和8年9月中旬 | G5: 2.4.1／5.2.1 | H5: 未依頼
A6: 計画 | B6: 第9期計画の進捗管理・評価資料（事業別実績、目標値と実績） | C6: 令和6〜8年度 | D6: 村 | E6: なし | F6: 令和8年9月末 | G6: 2.4.1 | H6: 未依頼
A7: 計画 | B7: 村総合計画、地域福祉計画、健康増進計画等の関連計画 | C7: 現行計画一式 | D7: 村 | E7: なし | F7: 令和8年9月末 | G7: 1.3.3／5.1.3 | H7: 未依頼
A8: 人口 | B8: 住民基本台帳人口（男女・5歳階級別、各年10月1日現在） | C8: 直近10年 | D8: 村 | E8: なし（集計値） | F8: 令和8年9月末 | G8: 2.1.1／3.1.1 | H8: 未依頼
A9: 人口 | B9: 人口動態（出生・死亡・転入・転出） | C9: 直近10年 | D9: 村 | E9: なし（集計値） | F9: 令和8年9月末 | G9: 3.1.1 | H9: 未依頼
A10: 人口 | B10: 世帯数、高齢者単身世帯・高齢者のみ世帯の状況 | C10: 直近5年 | D10: 村 | E10: なし（集計値） | F10: 令和8年9月末 | G10: 2.1.1 | H10: 未依頼
A11: 人口 | B11: 国勢調査結果（人口・世帯・就業等） | C11: 直近2回 | D11: 総務省（公表） | E11: なし | F11: － | G11: 2.1.1 | H11: 未依頼
A12: 人口 | B12: 日本の地域別将来推計人口 | C12: 最新版 | D12: 社人研（公表） | E12: なし | F12: － | G12: 3.1.1／3.1.3 | H12: 未依頼
A13: 介護 | B13: 要介護認定者数（要支援1〜要介護5、性・年齢階級別、年度末現在） | C13: 直近5年 | D13: 村 | E13: なし（集計値） | F13: 令和8年9月末 | G13: 2.3.1／3.2.1 | H13: 未依頼
A14: 介護 | B14: 介護給付費実績（サービス種類別・月次／年次、受給者数・回数・給付費） | C14: 直近5年 | D14: 村（国保連データ） | E14: なし（集計値） | F14: 令和8年9月末 | G14: 2.3.2／4.1.1 | H14: 未依頼
A15: 介護 | B15: 介護保険事業状況報告（月報・年報） | C15: 直近5年 | D15: 村／厚労省（公表） | E15: なし | F15: 令和8年9月末 | G15: 2.3.2 | H15: 未依頼
... A29: 国 | B29: 地域包括ケア「見える化」システム データ・推計ツール | C29: 最新版 | D29: 厚生労働省 | E29: なし | F29: － | G29: 2.1.3／4.1.1 | H29: 未依頼

Sheet 07_役割分担
A1: 役割分担表（RACI）
A2: 仕様書「7 留意事項」に基づき、村担当課と緊密な連携を図りながら業務を遂行する。決定を要する事項（施策方針・保険料水準・基金取崩し等）は村が決定し、受託者は根拠と選択肢を提示する。
A4: WBS No. | B4: 作業 | C4: 受託者 | D4: 村担当課 | E4: 村庁内関係課 | F4: 国・北海道／関係機関 | G4: 備考
A5: 1.1.2 | B5: 業務実施計画書・工程表の作成 | C5: R | D5: A | E5: I | F5: － | G5: 村の承認をもって確定
A6: 1.1.3 | B6: 第1回打合せ（キックオフ） | C6: R | D6: A | E6: C | F6: － | G6: 計画策定担当者本人が出席
A7: 1.1.4 | B7: 個人情報の取扱手続 | C7: R | D7: A | E7: I | F7: － | G7: 音威子府村個人情報保護条例に基づく
A8: 1.3.1 | B8: 貸与資料の提供 | C8: C | D8: R/A | E8: C | F8: － | G8: 資料抽出は村、リスト作成は受託者
A9: 1.3.2 | B9: 公表統計・システムデータの収集 | C9: R/A | D9: I | E9: － | F9: C | G9: 見える化システム等
A10: 2.1 | B10: 現状把握・分析 | C10: R/A | D10: C | E10: I | F10: － | G10: 村は地域事情の情報提供
A11: 2.2 | B11: 高齢者福祉サービス実績の分析 | C11: R | D11: A | E11: C | F11: － | G11: 事業実績の確定は村
A12: 2.3 | B12: 介護保険サービス実績の分析 | C12: R | D12: A | E12: C | F12: － | G12: 給付データの提供は村
A13: 2.4.1 | B13: 第9期計画の進捗評価 | C13: R | D13: A | E13: C | F13: － | G13: 各事業の自己評価は村が実施
A14: 2.4.2 | B14: ニーズ調査結果の分析 | C14: R | D14: A | E14: I | F14: － | G14: 調査の実施・集計は村（業務範囲外）
A15: 3.1 | B15: 人口推計 | C15: R/A | D15: C | E15: I | F15: C | G15: 社人研仮定値を参照
... A29: － | B29: 介護保険条例の改正（保険料） | C29: C | D29: R/A | E29: C | F29: I | G29: 業務範囲外（村が実施。算定根拠は受託者が提供）
A31: 凡例
A32: R | B32: Responsible：実行責任者（実際に作業を行う）
A33: A | B33: Accountable：説明責任者（成果を承認・決定する）
A34: C | B34: Consulted：協議先（事前に意見を求める）
A35: I | B35: Informed：報告先（結果を共有する）

Sheet 08_リスク管理
A1: リスク・課題管理表
A2: 業務遂行上想定されるリスクと対応方針。発生時は速やかに村と協議のうえ対応する（仕様書「7 留意事項」）。
A4: No. | B4: 区分 | C4: リスク内容 | D4: 想定される影響 | E4: 発生可能性 | F4: 影響度 | G4: 対応方針 | H4: 主担当 | I4: 監視タイミング
A5: R-01 | B5: スケジュール | C5: 国の基本指針の告示や介護報酬改定率の決定が年度末にずれ込み、保険料が確定できない | D5: 計画素案の第6章が確定せず、納期に影響 | E5: 高 | F5: 大 | G5: 暫定値で算定し、確定後に差し替えられるよう算定シートをパラメータ化。仕様書5に基づき村と協議（WBS 4.4.1） | H5: 受託者 | I5: 毎月／国通知の公表時
A6: R-02 | B6: スケジュール | C6: 村からの貸与資料の提供が遅れ、分析着手が後ろ倒しになる | D6: 現状分析・推計工程が圧迫される | E6: 中 | F6: 大 | G6: 契約後2週間以内に必要資料リストを提示し、提出期限目安を明示。受領状況を『06_必要資料リスト』で管理 | H6: 受託者・村 | I6: 毎月
A7: R-03 | B7: 品質 | C7: 小規模自治体のため給付実績・認定者数の年変動が大きく、推計値が不安定になる | D7: 見込量・保険料が過大／過小になる | E7: 高 | F7: 大 | G7: 複数年平均による平滑化、実人数ベースの併用、複数シナリオ（3案程度）の提示により幅を示す | H7: 受託者 | I7: 推計工程（R8.10〜R9.1）
A8: R-04 | B8: 品質 | C8: 村内のサービス事業所が限られ、近隣市町村の資源に依存している | D8: 見込量が供給力と乖離する | E8: 中 | F8: 中 | G8: 圏域外利用の実績を明示的に分解して推計。近隣市町村・北海道の整備方針を確認して反映 | H8: 受託者・村 | I8: WBS 4.1.2〜4.1.4
A9: R-05 | B9: 品質 | C9: ニーズ調査の回収数が少なく、統計的な信頼性が限られる | D9: 調査結果に基づく施策立案の根拠が弱くなる | E9: 中 | F9: 中 | G9: 経年比較・北海道平均との比較で補完し、自由記述等の定性情報を併用。限界を計画本文に明記 | H9: 受託者 | I9: WBS 2.4.2
A10: R-06 | B10: コミュニケーション | C10: 対面打合せが3回程度に限られ、認識齟齬が生じる | D10: 手戻り・修正工数の増大 | E10: 中 | F10: 中 | G10: 月1回程度のメール・Web会議による中間確認を実施（WBS 1.2.1）。議事録で決定事項を明文化 | H10: 受託者 | I10: 毎月
A11: R-07 | B11: スケジュール | C11: 議会日程・パブリックコメント日程が前倒しとなる | D11: 素案完成が間に合わない | E11: 中 | F11: 大 | G11: 第1回打合せで議会・パブコメ日程を確認し工程に反映。素案は令和9年1月中旬完成を目標に前倒し管理 | H11: 受託者・村 | I11: 第1回打合せ／毎月
A12: R-08 | B12: 情報管理 | C12: 個人情報を含むデータの授受・保管におけるリスク | D12: 条例違反・情報漏えい | E12: 低 | F12: 大 | G12: 個人が特定されない集計値での受領を原則とし、やむを得ない場合は暗号化・持出制限・アクセス権限管理を実施。完了時にデータ消去証明を提出（WBS 1.1.4／6.2.2） | H12: 受託者 | I12: 常時
A13: R-09 | B13: 体制 | C13: 業務従事者の不稼働（傷病等）により進捗が停滞する | D13: 納期遅延 | E13: 低 | F13: 大 | G13: 社内の代替要員・レビュー体制を確保。再委託が必要となる場合は事前に村の承諾を得る（仕様書7） | H13: 受託者 | I13: 常時
A14: R-10 | B14: スケジュール | C14: 冬季の積雪・交通事情により現地打合せが実施できない | D14: 打合せの延期・工程遅延 | E14: 中 | F14: 小 | G14: Web会議の併用を第1回打合せで合意しておく。現地訪問は必要最小限に集約 | H14: 受託者・村 | I14: R8.12〜R9.3
A15: R-11 | B15: スコープ | C15: 国の指針改定により推計対象年次や記載事項が追加される | D15: 作業量の増加 | E15: 中 | F15: 中 | G15: 仕様書5に基づき村と協議して対応方針を決定。原則として国の指示を遵守 | H15: 受託者・村 | I15: 国通知の公表時
... A19: R-12 | B19: 品質 | C19: 関連計画（総合計画等）との整合が取れていない記述が生じる | D19: 計画間の齟齬 | E19: 低 | F19: 中 | G19: 関連計画整合性チェック表により章ごとに確認（WBS 5.1.3）。齟齬は村と協議のうえ調整 | H19: 受託者 | I19: WBS 5.3 執筆時

Sheet 09_スコープ管理
A1: スコープ管理表（業務範囲の整理）
A2: 仕様書の記載から業務範囲を整理したもの。「要協議」の項目は第1回打合せで取扱いを確認する（仕様書「7 留意事項」：仕様書に定めのない事項や疑義が生じた場合は都度協議のうえ決定）。
A4: 区分 | B4: 項目 | C4: 内容 | D4: 仕様書の根拠 | E4: 備考・対応
A5: 含む | B5: 現状の評価・分析 | C5: 統計資料による現状把握・分析、高齢者福祉サービス実績分析、介護保険サービス実績分析、現行計画の点検・評価 | D5: 仕様書 3(1) | E5: WBS 2
A6: 含む | B6: 人口推計 | C6: 令和9年から10年間程度の将来人口推計 | D6: 仕様書 3(2) | E6: WBS 3.1
A7: 含む | B7: 要支援要介護認定者数の推計 | C7: 国の基本指針に従った各年度の認定者数推計 | D7: 仕様書 3(2) | E7: WBS 3.2
A8: 含む | B8: 介護サービス見込量の推計 | C8: 推計ツール等による令和11年度までの各年度・サービス種類ごとの見込量推計 | D8: 仕様書 3(3) | E8: WBS 4.1
A9: 含む | B9: 介護保険料の算定 | C9: 計画期間内の見込量に基づく第10期介護保険料の算定 | D9: 仕様書 3(3) | E9: WBS 4.3
A10: 含む | B10: ニーズ調査結果の反映 | C10: 令和8年度に村が実施した介護予防・日常生活圏域ニーズ調査結果の計画への反映 | D10: 仕様書 3(3) | E10: WBS 2.4.2／4.1.3
A11: 含む | B11: 計画素案の作成 | C11: 課題・施策の方向の整理、計画骨子の提案、計画素案の作成（国の策定指針に従った記載） | D11: 仕様書 3(4) | E11: WBS 5
A12: 含む | B12: 打合せ | C12: 3回程度。受託者側は計画策定担当者本人が出席 | D12: 仕様書 4 | E12: WBS 1.1.3／1.2.2／1.2.3
A13: 含む | B13: 成果品の作成・納品 | C13: 計画（CDデータ）1部、業務データ収録の磁気媒体（CDデータ）1部 | D13: 仕様書 6 | E13: WBS 6
A14: 含む | B14: 関連計画との整合性確保 | C14: 村総合計画等の関連計画との整合を図る | D14: 仕様書 7 | E14: WBS 5.1.3
A15: 含まない | B15: ニーズ調査の実施・集計 | C15: 調査票設計、対象者抽出、発送・回収、データ入力・集計は業務範囲外（令和8年度に村が実施済み） | D15: 仕様書 3(3)「今年度実施した」との記載 | E15: 結果データの提供を受けて反映
... A24: 要協議 | B24: 再委託 | C24: 業務の全部または主要な部分の第三者への再委託 | D24: 仕様書 7 留意事項 | E24: 予定なし。必要が生じた場合は事前に村の承諾を得る

Sheet 10_工数集計
A1: 工数集計（『01_WBS』シートと連動）
A2: 工数はレベル3の作業項目に付した見積値の合計。1人日＝7.5時間、1人月＝20人日で換算。契約・体制の確定後に見直す。
A4: 1. 大分類別工数
A5: 区分 | B5: 大分類 | C5: 対象WBS | D5: 工数(人日) | E5: 構成比 | F5: 人月換算 | G5: 主な内容
A6: 1 | B6: 1. 業務管理・打合せ | C6: 1.1〜 | D6: =SUMPRODUCT(('01_WBS'!$C$5:$C$98=3)*(LEFT('01_WBS'!$B$5:$B$98,1)="1")*'01_WBS'!$K$5:$K$98) | E6: =IFERROR(D6/SUMIF('01_WBS'!$C$5:$C$98,3,'01_WBS'!$K$5:$K$98),0) | F6: =ROUND(D6/20,2) | G6: 業務実施計画、打合せ3回、進行管理、資料収集
A7: 2 | B7: 2. 現状の評価・分析 | C7: 2.1〜 | D7: =SUMPRODUCT(('01_WBS'!$C$5:$C$98=3)*(LEFT('01_WBS'!$B$5:$B$98,1)="2")*'01_WBS'!$K$5:$K$98) | E7: =IFERROR(D7/SUMIF('01_WBS'!$C$5:$C$98,3,'01_WBS'!$K$5:$K$98),0) | F7: =ROUND(D7/20,2) | G7: 現状把握、高齢者福祉・介護保険サービス実績分析、第9期計画の点検評価
A8: 3 | B8: 3. 人口推計・認定者数推計 | C8: 3.1〜 | D8: =SUMPRODUCT(('01_WBS'!$C$5:$C$98=3)*(LEFT('01_WBS'!$B$5:$B$98,1)="3")*'01_WBS'!$K$5:$K$98) | E8: =IFERROR(D8/SUMIF('01_WBS'!$C$5:$C$98,3,'01_WBS'!$K$5:$K$98),0) | F8: =ROUND(D8/20,2) | G8: コーホート要因法による人口推計、要支援要介護認定者数の推計
A9: 4 | B9: 4. サービス見込量・保険料の推計 | C9: 4.1〜 | D9: =SUMPRODUCT(('01_WBS'!$C$5:$C$98=3)*(LEFT('01_WBS'!$B$5:$B$98,1)="4")*'01_WBS'!$K$5:$K$98) | E9: =IFERROR(D9/SUMIF('01_WBS'!$C$5:$C$98,3,'01_WBS'!$K$5:$K$98),0) | F9: =ROUND(D9/20,2) | G9: サービス種類別見込量、標準給付費、第10期介護保険料の算定
A10: 5 | B10: 5. 計画素案の作成 | C10: 5.1〜 | D10: =SUMPRODUCT(('01_WBS'!$C$5:$C$98=3)*(LEFT('01_WBS'!$B$5:$B$98,1)="5")*'01_WBS'!$K$5:$K$98) | E10: =IFERROR(D10/SUMIF('01_WBS'!$C$5:$C$98,3,'01_WBS'!$K$5:$K$98),0) | F10: =ROUND(D10/20,2) | G10: 課題整理、計画骨子、計画素案の執筆・修正
A11: 6 | B11: 6. 成果品の作成・納品 | C11: 6.1〜 | D11: =SUMPRODUCT(('01_WBS'!$C$5:$C$98=3)*(LEFT('01_WBS'!$B$5:$B$98,1)="6")*'01_WBS'!$K$5:$K$98) | E11: =IFERROR(D11/SUMIF('01_WBS'!$C$5:$C$98,3,'01_WBS'!$K$5:$K$98),0) | F11: =ROUND(D11/20,2) | G11: 最終校正、CDデータ作成、納品・検査対応
A12: 合計 | D12: =SUM(D6:D11) | E12: =SUM(E6:E11) | F12: =SUM(F6:F11) | G12: =IF(ROUND(D12-SUMIF('01_WBS'!$C$5:$C$98,3,'01_WBS'!$K$5:$K$98),4)=0,"01_WBS の合計と一致","要確認：01_WBSと不一致")
A14: 2. 中分類別工数
A15: WBS No. | B15: 大分類 | C15: 中分類 | D15: 工数(人日) | E15: 構成比 | F15: 開始予定 | G15: 完了予定
A16: 1.1 | B16: 業務管理・打合せ | C16: 業務着手準備 | D16: ='01_WBS'!$K$6 | E16: =IFERROR(D16/SUMIF('01_WBS'!$C$5:$C$98,3,'01_WBS'!$K$5:$K$98),0) | F16: 46266 | G16: 46283
A17: 1.2 | B17: 業務管理・打合せ | C17: 進行管理 | D17: ='01_WBS'!$K$11 | E17: =IFERROR(D17/SUMIF('01_WBS'!$C$5:$C$98,3,'01_WBS'!$K$5:$K$98),0) | F17: 46266 | G17: 46477
A18: 1.3 | B18: 業務管理・打合せ | C18: 資料収集・整理 | D18: ='01_WBS'!$K$16 | E18: =IFERROR(D18/SUMIF('01_WBS'!$C$5:$C$98,3,'01_WBS'!$K$5:$K$98),0) | F18: 46273 | G18: 46310
A19: 2.1 | B19: 現状の評価・分析 | C19: 基礎的資料による現状把握・分析 | D19: ='01_WBS'!$K$23 | E19: =IFERROR(D19/SUMIF('01_WBS'!$C$5:$C$98,3,'01_WBS'!$K$5:$K$98),0) | F19: 46296 | G19: 46325
A20: 2.2 | B20: 現状の評価・分析 | C20: 高齢者福祉サービス実績の分析 | D20: ='01_WBS'!$K$27 | E20: =IFERROR(D20/SUMIF('01_WBS'!$C$5:$C$98,3,'01_WBS'!$K$5:$K$98),0) | F20: 46296 | G20: 46326
A21: 2.3 | B21: 現状の評価・分析 | C21: 介護保険サービス実績の分析 | D21: ='01_WBS'!$K$31 | E21: =IFERROR(D21/SUMIF('01_WBS'!$C$5:$C$98,3,'01_WBS'!$K$5:$K$98),0) | F21: 46296 | G21: 46346
A22: 2.4 | B22: 現状の評価・分析 | C22: 現行計画（第9期）の点検・評価 | D22: ='01_WBS'!$K$36 | E22: =IFERROR(D22/SUMIF('01_WBS'!$C$5:$C$98,3,'01_WBS'!$K$5:$K$98),0) | F22: 46273 | G22: 46353
A23: 3.1 | B23: 人口推計・要支援要介護認定者数の推計 | C23: 人口推計 | D23: ='01_WBS'!$K$42 | E23: =IFERROR(D23/SUMIF('01_WBS'!$C$5:$C$98,3,'01_WBS'!$K$5:$K$98),0) | F23: 46308 | G23: 46346
A24: 3.2 | B24: 人口推計・要支援要介護認定者数の推計 | C24: 要支援・要介護認定者数の推計 | D24: ='01_WBS'!$K$46 | E24: =IFERROR(D24/SUMIF('01_WBS'!$C$5:$C$98,3,'01_WBS'!$K$5:$K$98),0) | F24: 46335 | G24: 46365
A25: 3.3 | B25: 人口推計・要支援要介護認定者数の推計 | C25: 推計結果の資料化 | D25: ='01_WBS'!$K$50 | E25: =IFERROR(D25/SUMIF('01_WBS'!$C$5:$C$98,3,'01_WBS'!$K$5:$K$98),0) | F25: 46363 | G25: 46367
A26: 4.1 | B26: 介護サービス見込量・保険料の推計 | C26: 介護サービス見込量の推計 | D26: ='01_WBS'!$K$53 | E26: =IFERROR(D26/SUMIF('01_WBS'!$C$5:$C$98,3,'01_WBS'!$K$5:$K$98),0) | F26: 46357 | G26: 46402
A27: 4.2 | B27: 介護サービス見込量・保険料の推計 | C27: 給付費・地域支援事業費の見込 | D27: ='01_WBS'!$K$58 | E27: =IFERROR(D27/SUMIF('01_WBS'!$C$5:$C$98,3,'01_WBS'!$K$5:$K$98),0) | F27: 46377 | G27: 46409
A28: 4.3 | B28: 介護サービス見込量・保険料の推計 | C28: 第10期介護保険料の算定 | D28: ='01_WBS'!$K$61 | E28: =IFERROR(D28/SUMIF('01_WBS'!$C$5:$C$98,3,'01_WBS'!$K$5:$K$98),0) | F28: 46370 | G28: 46428
A29: 4.4 | B29: 介護サービス見込量・保険料の推計 | C29: 国の指示等に伴う再算定対応 | D29: ='01_WBS'!$K$66 | E29: =IFERROR(D29/SUMIF('01_WBS'!$C$5:$C$98,3,'01_WBS'!$K$5:$K$98),0) | F29: 46419 | G29: 46459
A30: 5.1 | B30: 計画素案の作成 | C30: 課題及び施策の方向の整理 | D30: ='01_WBS'!$K$69 | E30: =IFERROR(D30/SUMIF('01_WBS'!$C$5:$C$98,3,'01_WBS'!$K$5:$K$98),0) | F30: 46350 | G30: 46365
A31: 5.2 | B31: 計画素案の作成 | C31: 計画骨子の提案 | D31: ='01_WBS'!$K$73 | E31: =IFERROR(D31/SUMIF('01_WBS'!$C$5:$C$98,3,'01_WBS'!$K$5:$K$98),0) | F31: 46342 | G31: 46366
A32: 5.3 | B32: 計画素案の作成 | C32: 計画素案の執筆 | D32: ='01_WBS'!$K$77 | E32: =IFERROR(D32/SUMIF('01_WBS'!$C$5:$C$98,3,'01_WBS'!$K$5:$K$98),0) | F32: 46370 | G32: 46428
A33: 5.4 | B33: 計画素案の作成 | C33: 素案の修正・反映 | D33: ='01_WBS'!$K$88 | E33: =IFERROR(D33/SUMIF('01_WBS'!$C$5:$C$98,3,'01_WBS'!$K$5:$K$98),0) | F33: 46430 | G33: 46459
A34: 6.1 | B34: 成果品の作成・納品 | C34: 成果品の作成 | D34: ='01_WBS'!$K$92 | E34: =IFERROR(D34/SUMIF('01_WBS'!$C$5:$C$98,3,'01_WBS'!$K$5:$K$98),0) | F34: 46454 | G34: 46472
A35: 6.2 | B35: 成果品の作成・納品 | C35: 納品・完了手続 | D35: ='01_WBS'!$K$96 | E35: =IFERROR(D35/SUMIF('01_WBS'!$C$5:$C$98,3,'01_WBS'!$K$5:$K$98),0) | F35: 46475 | G35: 46477
A37: ※ 工数は仕様書の記載事項から想定した見積値であり、契約金額・要員計画の確定後に実績に合わせて更新すること。
