Workbook

Sheet 00_ダッシュボード
A1: 北塩原村 障がい福祉計画策定業務 進捗ダッシュボード
A2: 委託第24号 第8期北塩原村障がい福祉計画・第4期北塩原村障がい児福祉計画策定業務委託／業務期間：契約締結の日から令和9年3月31日まで／数値は01_仕様書別進捗から自動集計します。
A4: 区分 | B4: 項目数 | C4: 平均進捗率 | D4: 完了・概ね完了 | E4: 作業中 | F4: 未着手等 | G4: 備考
A5: Ⅰ ニーズ調査 | B5: =COUNTIF('01_仕様書別進捗'!$A$6:$A$38,A5) | C5: =IFERROR(AVERAGEIF('01_仕様書別進捗'!$A$6:$A$38,A5,'01_仕様書別進捗'!$F$6:$F$38),0) | D5: =COUNTIFS('01_仕様書別進捗'!$A$6:$A$38,A5,'01_仕様書別進捗'!$E$6:$E$38,"完了")+COUNTIFS('01_仕様書別進捗'!$A$6:$A$38,A5,'01_仕様書別進捗'!$E$6:$E$38,"概ね完了") | E5: =COUNTIFS('01_仕様書別進捗'!$A$6:$A$38,A5,'01_仕様書別進捗'!$E$6:$E$38,"作業中")+COUNTIFS('01_仕様書別進捗'!$A$6:$A$38,A5,'01_仕様書別進捗'!$E$6:$E$38,"継続実施") | F5: =B5-D5-E5 | G5: 調査票の設計はほぼ完了。印刷・発送・集計が未着手
A6: Ⅱ 計画策定業務 | B6: =COUNTIF('01_仕様書別進捗'!$A$6:$A$38,A6) | C6: =IFERROR(AVERAGEIF('01_仕様書別進捗'!$A$6:$A$38,A6,'01_仕様書別進捗'!$F$6:$F$38),0) | D6: =COUNTIFS('01_仕様書別進捗'!$A$6:$A$38,A6,'01_仕様書別進捗'!$E$6:$E$38,"完了")+COUNTIFS('01_仕様書別進捗'!$A$6:$A$38,A6,'01_仕様書別進捗'!$E$6:$E$38,"概ね完了") | E6: =COUNTIFS('01_仕様書別進捗'!$A$6:$A$38,A6,'01_仕様書別進捗'!$E$6:$E$38,"作業中")+COUNTIFS('01_仕様書別進捗'!$A$6:$A$38,A6,'01_仕様書別進捗'!$E$6:$E$38,"継続実施") | F6: =B6-D6-E6 | G6: 様式・受け皿は整備済み。村の実績データ待ちの項目が多い
A7: Ⅲ 打合せ等業務 | B7: =COUNTIF('01_仕様書別進捗'!$A$6:$A$38,A7) | C7: =IFERROR(AVERAGEIF('01_仕様書別進捗'!$A$6:$A$38,A7,'01_仕様書別進捗'!$F$6:$F$38),0) | D7: =COUNTIFS('01_仕様書別進捗'!$A$6:$A$38,A7,'01_仕様書別進捗'!$E$6:$E$38,"完了")+COUNTIFS('01_仕様書別進捗'!$A$6:$A$38,A7,'01_仕様書別進捗'!$E$6:$E$38,"概ね完了") | E7: =COUNTIFS('01_仕様書別進捗'!$A$6:$A$38,A7,'01_仕様書別進捗'!$E$6:$E$38,"作業中")+COUNTIFS('01_仕様書別進捗'!$A$6:$A$38,A7,'01_仕様書別進捗'!$E$6:$E$38,"継続実施") | F7: =B7-D7-E7 | G7: 7月7日実施済み。業務期間を通じて継続
A8: 成果品 | B8: =COUNTIF('01_仕様書別進捗'!$A$6:$A$38,A8) | C8: =IFERROR(AVERAGEIF('01_仕様書別進捗'!$A$6:$A$38,A8,'01_仕様書別進捗'!$F$6:$F$38),0) | D8: =COUNTIFS('01_仕様書別進捗'!$A$6:$A$38,A8,'01_仕様書別進捗'!$E$6:$E$38,"完了")+COUNTIFS('01_仕様書別進捗'!$A$6:$A$38,A8,'01_仕様書別進捗'!$E$6:$E$38,"概ね完了") | E8: =COUNTIFS('01_仕様書別進捗'!$A$6:$A$38,A8,'01_仕様書別進捗'!$E$6:$E$38,"作業中")+COUNTIFS('01_仕様書別進捗'!$A$6:$A$38,A8,'01_仕様書別進捗'!$E$6:$E$38,"継続実施") | F8: =B8-D8-E8 | G8: 計画書は骨子案修正版が原型。報告書は集計後
A9: 契約管理 | B9: =COUNTIF('01_仕様書別進捗'!$A$6:$A$38,A9) | C9: =IFERROR(AVERAGEIF('01_仕様書別進捗'!$A$6:$A$38,A9,'01_仕様書別進捗'!$F$6:$F$38),0) | D9: =COUNTIFS('01_仕様書別進捗'!$A$6:$A$38,A9,'01_仕様書別進捗'!$E$6:$E$38,"完了")+COUNTIFS('01_仕様書別進捗'!$A$6:$A$38,A9,'01_仕様書別進捗'!$E$6:$E$38,"概ね完了") | E9: =COUNTIFS('01_仕様書別進捗'!$A$6:$A$38,A9,'01_仕様書別進捗'!$E$6:$E$38,"作業中")+COUNTIFS('01_仕様書別進捗'!$A$6:$A$38,A9,'01_仕様書別進捗'!$E$6:$E$38,"継続実施") | F9: =B9-D9-E9 | G9: 仕様書との差異が未協議のまま残っている
A10: 全体 | B10: =SUM(B5:B9) | C10: =IFERROR(AVERAGE('01_仕様書別進捗'!$F$6:$F$38),0) | D10: =SUM(D5:D9) | E10: =SUM(E5:E9) | F10: =SUM(F5:F9) | G10: 全体の平均進捗率（項目数による単純平均）
A12: 状態別の件数
A13: 状態 | B13: 件数 | D13: 状態 | E13: 件数
A14: 完了 | B14: =COUNTIF('01_仕様書別進捗'!$E$6:$E$38,A14) | D14: 未着手 | E14: =COUNTIF('01_仕様書別進捗'!$E$6:$E$38,D14)
A15: 概ね完了 | B15: =COUNTIF('01_仕様書別進捗'!$E$6:$E$38,A15) | D15: 村資料待ち | E15: =COUNTIF('01_仕様書別進捗'!$E$6:$E$38,D15)
A16: 作業中 | B16: =COUNTIF('01_仕様書別進捗'!$E$6:$E$38,A16) | D16: 要協議 | E16: =COUNTIF('01_仕様書別進捗'!$E$6:$E$38,D16)
A17: 継続実施 | B17: =COUNTIF('01_仕様書別進捗'!$E$6:$E$38,A17) | D17: 村側作業 | E17: =COUNTIF('01_仕様書別進捗'!$E$6:$E$38,D17)
A19: クリティカルパスと直近の期限
A20: 期限 | B20: 内容 | F20: 状態 | G20: 備考
A21: 2026-08-05 | B21: 印刷仕様の協議・確定（仕様書は約24ページ1種類／実際は2種類・34頁と37頁） | F21: 要協議 | G21: これが決まらないと印刷に入れない
A22: 2026-08-05 | B22: 宛名ラベルシールの受領（仕様書Ⅰ(1)により村が抽出・提供） | F22: 村資料待ち | G22: 発送作業の前提
A23: 2026-08-05 | B23: 対象者数の確定（約190人と156人の差） | F23: 村資料待ち | G23: 回収率の分母・管理番号設計に直結
A24: 2026-08-05 | B24: 郵送費の精算方法の書面確認 | F24: 要協議 | G24: 仕様書と運用が異なる
A25: 2026-08-10 | B25: アンケート発送 | F25: 未着手 | G25: 工程案は8月上旬。回収期間約1か月
A26: 2026-08-31 | B26: 年齢別・サービス別の匿名利用者一覧の受領 | F26: 村資料待ち | G26: 見込量の個別積上げの起点
A27: 2026-09-30 | B27: 令和6・7年度実績、令和8年度見込の受領 | F27: 村資料待ち | G27: 現行計画の評価と見込量の確定
A28: 2026-12-31 | B28: 自立支援協議会（年内1回） | F28: 未着手 | G28: 資料作成・出席・記録作成
A30: 本業務の進捗は、計画本文の作成が工程案より前倒しで進んでいる一方、アンケートの印刷・発送が仕様の協議待ちで止まっている状態です。8月上旬発送を維持するには、印刷仕様・ラベル・対象者数・郵送費の4点を8月5日までに決める必要があります。

Sheet 01_仕様書別進捗
A1: 業務委託仕様書 条項別 進捗管理
A2: 業務委託仕様書（8北保福第366号 別紙）4のⅠ〜Ⅲ、5の成果品、及び令和8年7月7日打合せで生じた契約管理事項を条項単位で管理します。進捗率は手入力で、00_ダッシュボードが区分別に自動集計します。
A5: 区分 | B5: 項番 | C5: 仕様書の要求 | D5: 現在の成果物・根拠 | E5: 状態 | F5: 進捗率 | G5: 主担当 | H5: 期限 | I5: 次の一手・ブロッカー
A6: Ⅰ ニーズ調査 | B6: Ⅰ(1) | C6: 調査対象の抽出（身体約130人・精神約40人・療育約20人＝約190人）。抽出は委託者が行い、受託者にラベルシールとして提供する。 | D6: ―（村側作業） | E6: 村側作業 | F6: 0 | G6: 北塩原村 | H6: 2026-08-05 | I6: 対象者数が確定していない。仕様書の約190人と現行計画の156人（令和5年）の差の理由を確認する。ラベルシールの提供時期を確定する
A7: Ⅰ ニーズ調査 | B7: Ⅰ(2)a | C7: 調査票の設計（厚労省の調査項目及び過去調査を踏まえ、委託者との協議の上決定） | D7: 0825確定版（障がい者版45問・障がい児版44問）／村朱書き修正指示40か所／北塩原村_アンケート調査票_村修正指示_確認結果 | E7: 完了 | F7: 1 | G7: 当社 | H7: 2026-08-25 | I7: 令和8年8月25日版で確定。村の修正指示40か所は反映済み。確定後に国のマニュアル（8月19日事務連絡・県通知8月24日）が発出されたため、標準項目3件（外出の目的・介護保険・強度行動障害の該当有無）と障害支援区分が確定版にない。クロス集計と行政データで代替する（北塩原村_クロス集計設計.xlsx）
A8: Ⅰ ニーズ調査 | B8: Ⅰ(2)b | C8: 文字の大きさ・フォント・表現の工夫、ルビ等の障がい特性に応じた配慮 | D8: 14pt程度・ルビ付与・白黒印刷・専門用語への短い解説（7/7打合せで決定） | E8: 概ね完了 | F8: 0.9 | G8: 当社 | H8: 2026-08-05 | I8: 最終レイアウトでの表示確認
A9: Ⅰ ニーズ調査 | B9: Ⅰ(2)c | C9: ウェブ回答用フォームの作成 | D9: Googleフォーム自動作成 Code（1本統合分岐版・修正版）／設問精査レポート／修正対応メモ | E9: 概ね完了 | F9: 0.85 | G9: 当社 | H9: 2026-08-05 | I9: 枝番設問（障がい者版 問29-1〜3、障がい児版 問32〜34）の選択肢順序を固定する
A10: Ⅰ ニーズ調査 | B10: Ⅰ(2)d | C10: 該当ページの二次元コードを調査票又は依頼状に印字 | D10: ― | E10: 未着手 | F10: 0 | G10: 当社 | H10: 2026-08-05 | I10: フォームURL確定後にQRを生成し、依頼状に配置する
A11: Ⅰ ニーズ調査 | B11: Ⅰ(2)e | C11: 紙とウェブの重複回答が集計されないよう管理番号等で管理 | D11: 管理番号設計（04_紙Web設計確認） | E11: 作業中 | F11: 0.6 | G11: 当社 | H11: 2026-08-05 | I11: 管理番号の付番はラベルシールの提供を受けてから確定する
A12: Ⅰ ニーズ調査 | B12: Ⅰ(3) | C12: 調査票及び封筒（配布用・回収用）の印刷。調査票はA4判・約24ページ・黒1色。 | D12: ― | E12: 要協議 | F12: 0 | G12: 当社／北塩原村 | H12: 2026-08-05 | I12: 仕様は約24ページ1種類だが、実際は障がい者版34ページ・障がい児版37ページの2種類。ページ数・種類数・部数・単価の取扱いを村と協議する。封筒は村の封筒を使用
A13: Ⅰ ニーズ調査 | B13: Ⅰ(4) | C13: 宛名ラベルの貼付、封入・封緘、発送。回収票の開封確認。発送及び回収に係る費用は受託者の負担。 | D13: ― | E13: 未着手 | F13: 0 | G13: 当社／北塩原村 | H13: 2026-08-10 | I13: 7/7打合せにより、村の封筒を使用し差出人・返送先を村役場とする運用に変更。村役場での一括受領・窓口回収。郵便料金は村が立替え後日実費精算（書面確認が必要）
A14: Ⅰ ニーズ調査 | B14: Ⅰ(5) | C14: 厚生労働省が提示する集計ファイル様式を基本としたデータ入力 | D14: ― | E14: 未着手 | F14: 0 | G14: 当社 | H14: 2026-09-10 | I14: 集計様式の入手。回収開始までに入力体制を確定する
A15: Ⅰ ニーズ調査 | B15: Ⅰ(6) | C15: 基本集計及び年齢・障がい種別等によるクロス集計。自由回答の取りまとめ。設問間クロス集計等は委託者と協議の上決定。 | D15: 北塩原村_アンケート集計分析方法_少数母数対応_計画接続メモ／北塩原村_クロス集計設計.xlsx（25件・層6区分・行政データ突合6件） | E15: 作業中 | F15: 0.55 | G15: 当社 | H15: 2026-10-31 | I15: 少数母数の公表基準（n<5の秘匿、地区別・障がい種別クロスの扱い）を村と合意する
A16: Ⅰ ニーズ調査 | B16: Ⅰ(7) | C16: 設問ごとのグラフ作成と分析結果の報告書としての取りまとめ | D16: ― | E16: 未着手 | F16: 0 | G16: 当社 | H16: 2026-11-30 | I16: 集計完了後に着手
A17: Ⅱ 計画策定業務 | B17: Ⅱ(1) | C17: 法制度の改正動向、国の基本指針、福島県障がい福祉計画等の収集・整理 | D17: 骨子案 第1章4（基本指針改正16項目、法定雇用率2.7%）／年齢到達による給付移行 調査報告／現行計画本編 第4章1（第7期の基本指針見直し）／国基準数値 原典照合結果／告示本文・新旧対照表・改正後概要（source/基本指針）／令和8年度報酬改定資料（source/報酬改定） | E17: 概ね完了 | F17: 0.95 | G17: 当社 | H17: 2026-09-30 | I17: 国基準数値11件を告示第4号の本文・別表と照合済み（誤り1件・補足4件・欠落6件を骨子案修正版へ反映）。残るは福島県 第8期計画の公表待ち（別表第四による長期入院患者の基盤整備量、心のサポーター目標）
... A38: 契約管理 | B38: 管理7 | C38: 守秘義務・再委託の禁止・契約約款の遵守 | D38: 仕様書6。個人情報を含む資料は内部管理とし、公表用報告書と分離 | E38: 継続実施 | F38: 0.5 | G38: 当社 | H38: 2027-03-31 | I38: アンケート回収物の受渡し手順、匿名利用者一覧の取扱いを明文化する
A40: 状態の凡例：完了／概ね完了（残作業が確認レベル）／作業中／継続実施（業務期間を通じて実施）／未着手／村資料待ち（当社側の作業は終えており村の資料受領で進む）／要協議（村との協議が必要）／村側作業（仕様書上、村が実施する）。

Sheet 02_成果品管理
A1: 成果品の管理（仕様書5）
A2: 納品する成果品の仕様と進捗です。仕様書5に定める3点に加え、納品時に電子媒体へ収録する関連データを整理します。
A5: 区分 | B5: 成果品 | C5: 仕様 | D5: 部数 | E5: 状態 | F5: 進捗率 | G5: 備考
A6: ① | B6: 障がい福祉計画書 | C6: A4判、両面約60頁、モノクロ印刷、コピー・くるみ製本 | D6: 30部 | E6: 作業中 | F6: 0.4 | G6: 骨子案修正版が原型。全8章＋新設5節。アンケート結果・実績データの反映後に確定
A7: ② | B7: アンケート調査報告書 | C7: A4判、両面約60頁、モノクロ印刷、コピー・ホチキス製本 | D7: 10部 | E7: 未着手 | F7: 0 | G7: 設問ごとのグラフと分析。集計完了後に着手
A8: ③ | B8: 電子媒体 | C8: 上記成果品及び関連データを収録（Word、Excel、PowerPoint、PDF形式等）CD-R等 | D8: 一式 | E8: 作業中 | F8: 0.3 | G8: 収録範囲を村と確認する
A10: 電子媒体への収録候補
A11: 区分 | B11: ファイル | C11: 内容 | E11: 状態 | G11: 備考
A12: 計画書 | B12: 北塩原村_計画素案.docx | C12: 計画書本編のドラフト | E12: 作業中 | G12: 全8章。第2章6・第5章1・第5章2・第5章11を新設済み
A13: 計画書 | B13: 北塩原村_計画素案_概要版.docx | C13: 住民向けの概要版（A4・4頁） | E13: 作業中 | G13: 令和8年9月17日に村の指示により作成。仕様書5の成果品3点には含まれていない
A14: 推計 | B14: 北塩原村_将来推計.xlsx | C14: 人口推計・手帳所持者数の将来推計（8シート） | E14: 作業中 | G14: 方法A・B・中位、不確実性の定量評価、年齢階級別推計（方法C）
A15: 推計 | B15: 北塩原村_サービス見込量.xlsx | C15: サービス見込量の個別積上げ（13シート） | E15: 作業中 | G15: 年齢到達者一覧、65歳移行判定、供給制約、告示別表第一根拠、別表第五判定を含む
A16: 推計 | B16: 北塩原村_活動指標.xlsx | C16: 活動指標の設定（4シート） | E16: 作業中 | G16: 別表第一の83項目。必須33・任意。仕様書4-Ⅱ(3)⑤に対応
A17: 資源 | B17: 北塩原村_圏域サービス資源.xlsx | C17: 圏域の事業所数（5シート） | E17: 完了 | G17: ReMHRAD障害福祉資源18サービス×市町村別、2020→2025
A18: 精神 | B18: 福島県_精神医療指標抽出.xlsx | C18: 福島県の精神医療指標（7シート） | E18: 完了 | G18: 平均生活日数・再入院率・長期入院患者・別表第四の当てはめ・村の在院者
A19: 財源 | B19: 北塩原村_財源構成案.xlsx | C19: 国・県・村の負担内訳（10シート） | E19: 作業中 | G19: 給付実績R2〜R7、財源構成試算、見込量×単価の積上げ
A20: 評価 | B20: 北塩原村_現行計画評価.xlsx | C20: 現行計画の評価（7シート） | E20: 作業中 | G20: 令和3〜5年度の見込量と実績の突合、成果目標・施策目標の評価
A21: 管理 | B21: 北塩原村_業務進捗管理.xlsx | C21: 本ブック | E21: 作業中 | G21: 納品対象とするか村と確認
A22: 調査 | B22: 0728北塩原村_障がい福祉アンケート調査票.docx | C22: 調査票（障がい者版・52問） | E22: 概ね完了 | G22: 最終目視確認が残
... A30: 報告 | B30: 調査結果報告書（未作成） | C30: アンケート集計結果 | E30: 未着手 | G30: 集計後

Sheet 03_スケジュール
A1: 工程管理（案Ａ。令和8年10月14日採用）
A2: 策定委員会（第2回）が令和8年11月にずれ込んだことを受けて引き直した工程です。パブリックコメントを令和9年1月26日から2月9日まで（15日間）に前倒しし、庁議（計画の決定）を2月19日、議会全員協議会を2月下旬に置いて、初校以降を従前のまま令和9年3月31日の納品に収めます。日付は kitashiobara_koutei.py に一本化しており、本シート・03b_納期からの逆算・進捗状況表・概要版はすべてそこから引いています。
A5: 開始 | B5: 終了 | C5: 作業内容 | D5: 主担当 | E5: 状態 | F5: 備考
A6: 2026-08-05 | B6: 2026-08-10 | C6: アンケート印刷・封入・発送準備 | D6: 当社／北塩原村 | E6: 完了 | F6: 印刷仕様の協議、村ラベルの受領、村封筒の手配がすべて前提
A7: 2026-08-31 | B7: 2026-09-25 | C7: アンケート発送・回収、役場での受領保管 | D7: 北塩原村／当社 | E7: 完了 | F7: 返送先は村役場。窓口での現地回収
A8: 2026-10-01 | B8: 2026-10-31 | C8: データ入力、集計、実績・財源・施策評価の整合 | D8: 当社 | E8: 作業中 | F8: 厚労省の集計様式による入力。少数母数の公表基準を事前に合意
A9: 2026-10-01 | B9: 2026-10-31 | C9: 将来見込量・成果目標の算定とすり合わせ | D9: 当社／北塩原村 | E9: 作業中 | F9: 個別積上げ方式。年齢別・サービス別の利用者一覧が前提
A10: 2026-11-01 | B10: 2026-11-18 | C10: 策定委員会（第2回）の資料の作成・修正 | D10: 当社／北塩原村 | E10: 作業中 | F10: 計画素案、前回計画の評価、アンケート分析報告書の3本と、それらを要約した策定委員会資料。方針資料は10月開催としていたが11月にずれ込んだ
A11: 2026-11-19 | B11: 2026-12-31 | C11: 計画素案の修正・庁内調整 | D11: 当社／北塩原村 | E11: 未着手 | F11: 策定委員会の意見の反映。見込量は村の実績データの受領により確定する
A12: 2026-12-01 | B12: 2026-12-16 | C12: ４町村広域の障がい者自立支援協議会（協議） | D12: 北塩原村／当社 | E12: 未着手 | F12: 方針資料・策定委員会資料のいずれにも日程がない工程。広域で確保するサービス（基幹相談支援センター、地域生活支援拠点、医療的ケア児等支援の協議の場）を協議する
A13: 2027-01-04 | B13: 2027-01-15 | C13: 北塩原村障がい者自立支援協議会（計画案の審議） | D13: 北塩原村／当社 | E13: 未着手 | F13: 報告・説明は村。受託者は資料作成・出席・記録作成
A14: 2027-01-26 | B14: 2027-02-09 | C14: パブリックコメントの実施（15日間） | D14: 北塩原村 | E14: 未着手 | F14: 前回計画では2週間実施（令和6年2月9日〜23日）で意見0件。周知の方法を見直す
A15: 2027-02-10 | B15: 2027-02-19 | C15: 結果の整理と計画案の修正、庁議（計画の決定） | D15: 北塩原村／当社 | E15: 未着手 | F15: 庁議は2月19日。ここで本文が確定する
A16: 2027-02-20 | B16: 2027-02-25 | C16: 議会全員協議会（令和9年度主要事業）、目次と頁数の確定 | D16: 北塩原村／当社 | E16: 未着手 | F16: 議会への説明は計画の決定の後に置く。Ｗｏｒｄの目次の更新は当方の環境ではできないため他メンバー又は村に依頼する
... A18: 2027-03-17 | B18: 2027-03-31 | C18: 入稿・印刷・製本・納品 | D18: 当社 | E18: 未着手 | F18: 計画書30部、アンケート報告書10部、電子媒体一式。3月22日は春分の日の振替休日
A20: クリティカルパスは「策定委員会（第2回）→ 素案の修正・庁内調整 → 自立支援協議会 → パブリックコメント → 結果の整理と修正 → 庁議（決定）→ 目次と頁数の確定 → 初校・再校・校了 → 入稿 → 印刷・製本 → 納品」です。ここで最も動かしにくいのは入稿（令和9年3月17日）で、これが動くと納期を超えます。パブリックコメントの開始が1週間後ろへ動くと、最初に削られるのは校正の期間です。4町村広域の障がい者自立支援協議会（12月）と議会全員協議会（2月下旬）は納品までの道筋の上には乗りませんが、村の方針資料に掲げられた工程であるため表に入れています（策定委員会資料のスケジュール表はこの2件を注記に落としていました）。

Sheet 03b_納期からの逆算
A1: 履行期限からの逆算（令和9年3月31日）
A2: 納期から戻して日を置いたものです。案Ａの採用（令和8年10月14日）により、逆算の範囲を策定委員会（第2回）まで遡らせました。所要日数は手で書かず、期限の間の営業日数を数えています（土曜・日曜・祝日・村役場の閉庁日を除く。令和9年3月22日は春分の日の振替休日）。「―（並行）」は納品までの道筋の上に乗らない工程です。所要日数のうち原典があるのは納期と部数・製本の形だけで、印刷・製本の所要日数は当方の想定です（Ｍ-112で確認）。精度「仮」の4件は他者の日程であって出所が月又は旬までしかなく、日は営業日を数えるための仮置きです。対外の文書には月又は旬で書いています（Ｍ-125で照会）。
A5: 順 | B5: 期限 | C5: 工程 | D5: 所要日数 | E5: 誰が | F5: 出所 | G5: 精度
A6: 1 | B6: 2027-03-31 | C6: 成果品の納品（計画書30部・調査報告書10部・電子媒体一式） | D6: ― | E6: 当社 | F6: 仕様書5（原典あり） | G6: 確
A7: 2 | B7: 2027-03-26 | C7: 製本（計画書はくるみ製本、報告書はホチキス製本） | D7: 3営業日 | E7: 印刷業者又は当社 | F7: 当方の想定（Ｍ-112で確認） | G7: 確
A8: 3 | B8: 2027-03-19 | C8: 印刷（Ａ４判両面・モノクロ・コピー） | D8: 4営業日 | E8: 印刷業者又は当社 | F8: 当方の想定（Ｍ-112で確認） | G8: 確
A9: 4 | B9: 2027-03-17 | C9: 入稿（印刷用データの引渡し） | D9: 2営業日 | E9: 当社 | F9: 当方の想定 | G9: 確
A10: 5 | B10: 2027-03-12 | C10: 校了（村の最終確認の完了） | D10: 3営業日 | E10: 北塩原村 | F10: 当方の想定（Ｍ-112で確認） | G10: 確
A11: 6 | B11: 2027-03-05 | C11: 再校（村の指摘の反映と再提出） | D11: 5営業日 | E11: 当社 | F11: 当方の想定 | G11: 確
A12: 7 | B12: 2027-02-26 | C12: 初校（村へ提出し確認を受ける） | D12: 5営業日 | E12: 当社・北塩原村 | F12: 当方の想定 | G12: 確
A13: 8 | B13: 2027-02-25 | C13: 目次と頁数の確定（Ｗｏｒｄの目次の更新） | D13: 1営業日 | E13: 当社又は北塩原村 | F13: 当方の想定 | G13: 確
A14: 9 | B14: 2027-02-24 | C14: 議会全員協議会（令和9年度主要事業の説明） | D14: ―（並行） | E14: 北塩原村 | F14: 案Ａ（令和8年10月14日採用）は旬まで。日は当方の仮置き（Ｍ-125で村に照会） | G14: 仮
A15: 10 | B15: 2027-02-19 | C15: 庁議（計画の決定） | D15: 3営業日 | E15: 北塩原村 | F15: 案Ａ（令和8年10月14日採用）。村に確認（Ｍ-125） | G15: 確
A16: 11 | B16: 2027-02-16 | C16: パブリックコメントの結果の整理と計画案の修正 | D16: 3営業日 | E16: 当社・北塩原村 | F16: 案Ａ（令和8年10月14日採用） | G16: 確
A17: 12 | B17: 2027-02-09 | C17: パブリックコメントの終了 | D17: 4営業日 | E17: 北塩原村 | F17: 案Ａ（令和8年10月14日採用）。村に確認（Ｍ-125） | G17: 確
... A21: 16 | B21: 2026-11-18 | C21: 策定委員会（第2回。計画素案・前回計画の評価・アンケート結果） | D21: 36営業日 | E21: 北塩原村・当社 | F21: 案Ａ（令和8年10月14日採用）は月まで。日は当方の仮置き（Ｍ-125で村に照会） | G21: 仮
A23: この逆算で分かること。①入稿は令和9年3月17日である。これが動くと納期を超える。②入稿に間に合わせるには、校了が3月12日、初校の提出が2月26日になる。③初校を出すには、目次と頁数が2月25日までに確定していなければならない。当方の環境ではWordの目次を更新できないため、この作業を他メンバー又は村に依頼する時期が2月25日までということになる。④計画の決定（庁議）から初校までは3営業日しかない。本文が確定するのはパブリックコメントの結果を反映した2月16日であり、目次の更新はその後に始められる。⑤議会全員協議会は計画の決定の後に置いた。決定前に置くと、未決定の案を議会に説明することになる。⑥印刷・製本の所要日数は当方の想定である。仕様は「コピー・くるみ製本」であり、業者によって所要日数が変わるため確かめる（Ｍ-112）。⑦案Ａの3件（パブリックコメントの1月下旬開始、庁議2月19日、議会全員協議会を決定の後に置くこと）は村の了解を要する（Ｍ-125）。

Sheet 04_村資料受領状況
A1: 村からの資料受領状況（横断管理）
A2: 将来推計・サービス見込量・財源構成案の各ブックに分散していた村確認事項を一本化しました。受領したら「状態」を受領済に変更し、該当ブックへ入力してください。／WBSとの対応（届かないとどの作業が止まるか）は 北塩原村_業務進捗管理表.xlsx 05_村資料・依頼の詳細 に統合しています（同じデータから作成しており、こちらに「関係WBS」列を足したものです）。
A5: 優先度 | B5: 資料 | C5: 内容 | D5: 反映先 | E5: 状態 | F5: 希望期限 | G5: 受領日
A6: 最優先 | B6: 計画値の基礎とする系列（Ｍ-19） | C6: 村が自立支援協議会に報告している実利用者数（人／月）・サービス量を計画値の基礎としてよいか。当方の第1次概算は年間請求件数を基礎にしたため12サービスで村の公表実績と食い違う（計画相談支援 村25人・当方22人、障がい児相談支援 村4人・当方2人ほか）。あわせて令和8年度の実績見込 | D6: 計画素案 第5章3〜7／レビュー対応 02シート | E6: 未受領 | F6: 2026-10-09
A7: 最優先 | B7: 移行管理台帳（Ｍ-18） | C7: 匿名ID・生年月・学年・学校種別・障害支援区分・行動関連項目・医療的ケア・重症心身・現在のサービス・支給決定量・実利用量・利用先と所在地・送迎の可否・冬季の利用可否・卒業予定・65歳到達年度・家族介護の状況。この1枚でＭ-10（継続入所者）・Ｍ-11（保育所等の受入体制）・Ｍ-15（65歳到達者）・Ｍ-21（卒業予定者）が同時に片付く | D7: 計画素案 第5章1・第5章2（第2次算定の入力） | E7: 未受領 | F7: 2026-10-09
A8: 最優先 | B8: 施設入所支援4人の支給決定の内容（Ｍ-13） | C8: 年齢、生活介護との同時支給決定の有無、入所先の施設類型（指定障害者支援施設か）。介護保険法施行法第11条第1項の適用除外に当たると、介護保険の第1号被保険者・認定者から除く | D8: 介護保険事業計画との整合 K-1 | E8: 未受領 | F8: 2026-10-09
A9: 最優先 | B9: 介護保険の第2号被保険者との重なり（Ｍ-14） | C9: 介護保険側が見込む第2号被保険者の認定者（各年度2〜3人）のうち、障がい福祉サービスの受給者証をお持ちの方の人数と利用サービス。重なる場合は介護保険が優先し障がい計画の見込量から減算する | D9: 介護保険事業計画との整合 K-2 | E9: 未受領 | F9: 2026-10-09
A10: 高 | B10: 相談支援の体制（Ｍ-20） | C10: 相談支援専門員の人数、1人当たりの担当件数、新規に受け入れられる件数、主任相談支援専門員の配置。専門員が不足すると受入先があっても移行が進まない | D10: 計画素案 第5章8（確保可能量を決める要素） | E10: 未受領 | F10: 2026-10-09
A11: 最優先 | B11: グループホーム・福祉ホームの設置の予定（Ｍ-37） | C11: 精神・知的障がいの方のグループホーム又は福祉ホームの設置の予定。設置する場合の主体・時期・定員と、条例改正の要否。令和8年10月9日の論点メモに「精神・知的のGHの設置（正式名・福祉ホームだが、条例の改正が必要）」とある。共同生活援助（訓練等給付）と福祉ホーム（地域生活支援事業の任意事業）では根拠も財源も変わる | D11: 計画素案 第5章の居住系の見込量・確保方策・地域生活支援事業 | E11: 未受領 | F11: 2026-10-16
A12: 高 | B12: 物品調達の実績（Ｍ-34） | C12: 障がい者就労施設等からの物品調達の実績（目標3件に対する令和6〜8年度の件数）と、障害者優先調達推進法第9条に基づく調達方針の策定・公表の有無 | D12: 計画素案 第3章5（第4次障がい者計画の目標値の進捗） | E12: 未受領 | F12: 2026-10-31
A13: 高 | B13: 社会福祉法改正への対応（Ｍ-35） | C13: 身寄りのない高齢者への日常生活支援・入院手続・死後事務への対応と、権利擁護の窓口の配置の検討状況。障がい者の親亡き後の支援と同じ課題であり、第6章に書くかを判断する | D13: 計画素案 第6章・第7章 | E13: 未受領 | F13: 2026-10-31
A14: 中 | B14: 防災の取組の状況（Ｍ-36） | C14: 防災無線の設置状況、災害図上訓練（ＤＩＧ）・避難所運営ゲーム（ＨＵＧ）の実施状況、避難訓練の頻度。個別避難計画10件の目標を達成する手順として書く | D14: 計画素案 第3章3（⑥生活環境） | E14: 未受領 | F14: 2026-10-31
A15: 高 | B15: 排泄管理支援用具の増減の理由（Ｍ-38） | C15: 日常生活用具（排泄管理支援用具）の給付件数の直近の増減とその理由。当方は40→68→69→72件と増加傾向と整理したが、論点メモは「死亡により減少」としている。地域生活支援事業の給付件数の大半を占め、事業費にも響く | D15: 計画素案 第5章9／地域生活支援事業 01 | E15: 未受領 | F15: 2026-10-31
A16: 高 | B16: 成年後見の類型別内訳（Ｍ-39） | C16: 成年後見制度の利用者数の類型別内訳（後見・保佐・補助）と、会津権利擁護・成年後見センターにおける本村の位置（相談時間が3番目か、利用者数が3番目か）。民法等改正により後見・保佐が補助に一元化されるため、類型別の把握が要る | D16: 計画素案 第6章 | E16: 未受領 | F16: 2026-10-31
A17: 高 | B17: 指定難病による対象者（Ｍ-32） | C17: 手帳を所持していないが障害者総合支援法の対象疾病に該当してサービスを利用している方、又は利用しうる方の人数。対象疾病は令和7年4月1日から376疾病（厚生労働省の資料で原典確認済み。平成25年4月の施行時は130疾病で、7次にわたり拡大された）。手帳所持者数だけで対象者を数えると、手帳を所持しない方が漏れる | D17: 計画素案 第2章2・第5章1（推計方法） | E17: 未受領 | F17: 2026-10-31
... A74: 中 | B74: 自立支援協議会の委員名簿 | C74: 任期・氏名・所属・役職 | D74: 計画書 資料編 | E74: 未受領 | F74: 2026-12-31
A76: 未受領：53件（うち最優先14件、高27件）、一部受領：7件。未受領の最優先案件が揃わないとサービス見込量の個別積上げと手帳所持者数の年齢階級別推計を確定できません。8月5日期限の3件（対象者数、宛名ラベル、印刷仕様）はアンケート発送のクリティカルパス上にあります。「一部受領」は令和8年8月の調査票朱書きで数値の一部が判明したもので、基準日や内訳の確認が残っています（村提供実績データ 06 参照）。

Sheet 05_課題・リスク
A1: 課題・リスク管理
A2: 業務遂行上の課題とリスクを、区分・重要度・対応方針とあわせて管理します。
A5: No | B5: 区分 | C5: 重要度 | D5: リスク | E5: 内容 | F5: 対応方針 | G5: 状態
A6: R-42 | B6: 工程 | C6: 最高 | D6: 引き直した工程（案Ａ）が村の了解を得られない場合、納期を超える | E6: 策定委員会（第2回）の開催が令和8年11月となり、村の計画策定方針（令和8年5月25日）の工程から1か月後ろへ動いた。策定委員会資料のスケジュール表のまま（パブリックコメント令和9年2月8日〜22日、庁議（計画の決定）3月）進めると、結果の整理に1週間、庁議の後に初校・再校・校了・入稿で3週間を要するため入稿が3月下旬となり、履行期限（令和9年3月31日）を約1週間超える。令和8年10月14日に案Ａ（パブリックコメントを1月26日〜2月9日へ前倒し、庁議2月19日、議会全員協議会2月下旬、初校2月26日以降は従前のまま）が採用され、当方の工程・成果物はすべてこれで組み直した。ただし案Ａは、村のパブリックコメントの開始時期、庁議の開催日、議会全員協議会を計画の決定の後に置くことの3点について村の了解を前提としている。いずれかが動くと、最初に削られるのは校正の期間である | F6: 令和8年10月14日に工程の日付を kitashiobara_koutei.py へ一本化し、進捗管理ブック・進捗状況表・概要版・正本 第1章5（4）がすべて同じ日付を引くようにした。案Ａの3点をＭ-125で照会した（期限 令和8年10月24日）。回答までの間、工程は案Ａを前提に進め、回答により日が動いた場合は kitashiobara_koutei.py の1か所を直して全体を作り直す。パブリックコメントが2月8日開始から動かせない場合は、①校正を初校・校了の2回に減らす②印刷物の納品を4月上旬とすることの可否を履行期限との関係で確かめる、のいずれかとなるため、Ｍ-112（印刷・製本の所要日数）と併せて判断する | G6: 対応中
A7: R-39 | B7: 照会の立て方 | C7: 中 | D7: 高齢者施策への接続について、村が答えられない形で照会していた | E7: 本計画は、65歳に達した後の生活を支える仕組みが介護保険の給付だけではないことを書き、村の高齢者福祉施策・村単独事業・介護保険の地域支援事業への接続を扱っている。当方はこれまで「障がいのある方が対象に含まれるかは事業ごとに異なります」と書き、村に「対象となるか」を照会していた（Ｍ-50・Ｍ-71・Ｍ-81）。国の地域支援事業実施要綱を読んだところ、任意事業の対象者は「被保険者、要介護被保険者を現に介護する者その他個々の事業の対象者として市町村が認める者」とされており、障がいのある方を対象に含めるかどうかは村の要綱の定め方による事項であった。村にとっては、国に決められていることを聞かれているのか自らの定めを聞かれているのかが分からない問いになっていた。あわせて、成年後見制度利用支援事業の条項を第115条の45第2項第2号と取り違えており（正しくは第3項第3号の任意事業。第2項第2号は権利擁護事業）、この誤りが村へ出す照会文Ｍ-97の本文にも入っていた | F7: 令和8年10月11日に、要綱の原典を照合して直した。Ｍ-108（本村が実施している地域支援事業と、その要綱における対象者の定め）を起票し、「対象となるか」から「村の要綱が対象者をどう定めているか」へ聞き方を改めた。第5章5（2）に理由と表5-40（地域支援事業の区分と対象者の定め）を入れた（ＣＳ-1）。Ｍ-97とＫ-9の条項は第3項第3号に直した。照会文は村に渡るものであるため、送る前に直した。以後、照会を立てるときは「国が決めていること」と「村が決めていること」を分けてから書く | G7: 対応済み
A8: R-38 | B8: 制度動向 | C8: 高 | D8: 高次脳機能障害者支援法が令和8年4月1日に施行され、村にも窓口の明確化と実施状況の公表が求められる | E8: 高次脳機能障害者支援法（令和7年法律第96号）は令和7年12月24日に公布され、令和8年4月1日から施行された。施行通知（障精発0415第1号 令和8年4月15日）は「各自治体」として、①相談できる窓口の明確化と周知（法第17条）、②普及啓発（法第18条・第26条・第27条・第28条）、③関係部局間の連携と人材の確保（法第29条）、④実態把握の調査（法第5条）、⑤支援の状況及び施策の実施状況の公表（法第10条第2項）を求めている。通知の宛先は都道府県及び指定都市であるが、都道府県に管内市町村への周知徹底を求めているため、本村も含まれる。とくに⑤は、都道府県が管内市区町村の状況を取りまとめて国へ報告することとされており、本村の実施状況が国へ上がる。さらに施行令（令和8年政令第60号）第1条は、高次脳機能障害から認知症及び発達障害を除いている。窓口が一つしかない本村では、記憶や注意の障がいという見え方が同じでもつなぎ先が分かれるため、この切り分けが相談の入口を決める | F8: 令和8年10月11日に、施行通知と施行令の原典を照合して反映した。第1章4（3）に公布と施行の日を書き（ＫＮ-1）、第5章2（2）に村が行うこと、定義の切り分けの表（表5-17）、及び県が行うことを書いた（ＫＮ-2）。県の支援センターの指定は令和8年度内に行われる見込みであり、指定の状況、地域協議会への参画、及び公表の様式と時期を照会する（Ｍ-107）。手元にないのは法律の条文そのもの、支援事業の実施要綱（障発0407第31号 別紙1）、及び公表等についての通知の別紙様式である。とくに公表の様式は本村が公表する事項に直に関わる | G8: 対応中
A9: R-37 | B9: 資料の読み方 | C9: 高 | D9: 国の予算資料は当初予算と前年度補正予算が同じ資料に載るため、年度を取り違えやすい | E9: 令和8年度障害保健福祉部予算案の概要には、令和8年度当初予算と令和7年度補正予算が同じ資料に載っている。レビューは令和7年度補正の7事業（賃上げ439億円ほか）を令和8年度当初として扱っており、当方はこれを指摘した。ところが当方自身も、令和7年度の資料に【令和6年度補正予算】として載っている中核的人材養成研修事業21百万円を「令和7年度予算にもある」と書いていた。同じ種類の誤りである。あわせて広域的支援人材の配置の開始年度を1年遅く書き（正しくは令和6年度当初予算）、令和8年度の原典にある【新規】の表示を「政策の新設ではない」と言い換えて消していた | F9: 令和8年10月11日に、令和6年度の原典を得て訂正した。build_kitashiobara_yosan_mece.py の自己点検に、①令和7年度の資料についても補正予算の見出しの後ろに並んでいるかを確かめる、②広域的支援人材が令和6年度の原典に「新たに配置」とあることを確かめる、③令和8年度の原典の【新規】表示を確かめる、④訂正前の主張が残っていないこと及び訂正後の記述が入っていることを確かめる、の4点を加えた。いずれも生成のたびに走る。正本の本文（ＹＳ-1・ＹＳ-3）は年度を言わずに書いていたため、本文の訂正は要らなかった。以後、国の施策を本文に書くときは年度を言わず、「進められている」「令和９年度から始められるよう準備が進められている」のように書く | G9: 対応済み
A10: R-36 | B10: 記述の整合 | C10: 高 | D10: 確保の方策の記述が当方の中で食い違っていた（共生型サービス） | E10: 第5章2（4）のＷ-11は、同じ段落の中で「本村には障がい福祉サービスの事業所が３カ所しかありません」と書きながら、末尾で「村内で居宅介護又は生活介護を受けられるようになれば」と書いていた。前者は村内に事業所があると言い、後者はまだ受けられないと言っている。当方の調べ（ReMHRAD障害福祉資源）では令和7年時点で居宅介護１カ所・重度訪問介護１カ所・生活介護１カ所があり、後者が誤りである。外部の資料を見るまでもなく、当方が書いた文の中で矛盾していた。あわせて「共生型サービス又は基準該当サービスの指定を受けることを働きかけます」という書き方も制度用語として誤っていた。基準該当障害福祉サービスは指定を受ける制度ではない | F10: 令和8年10月11日に、国の資料7件を照合したうえでＷ-11を書き直した（build_kitashiobara_juten12.py の側）。村内の３カ所の内訳を明示し、共生型が指定の手続の特例であって事業者の申請が要ることと、一方の指定がもう一方の基準を満たすことを意味しないことを書き足した。第5章5（2）にＫＹ-1（事業所の指定の形と65歳到達後の続け方）を追記した。村内の事業所の指定の形は当方では確かめられないため村に照会する（Ｍ-106）。同種の食い違いを防ぐため、build_kitashiobara_kyoseigata.py の自己点検で直す前の文が正本に残っていないことを生成のたびに確かめる | G10: 対応中
A11: R-35 | B11: 財政 | C11: 高 | D11: 令和8年度の報酬改定（＋1.84％）を見込量の基準年度に織り込んでいない | E11: 本計画の見込量は令和7年度の給付実績を基礎としている。しかし令和8年度の障害福祉サービス等報酬改定は既に決まっており、改定率は＋1.84％である（令和8年度障害保健福祉部予算案の概要）。正本の第1章4（3）は令和9年度の改定（検討中）にしか触れておらず、令和8年度の改定を書いていなかった。利用する方の人数が横ばいでも給付費は増えるため、改定前の単価による見込みのままでは給付費を低く見積もる。国の予算でも障害福祉サービス関係費は令和7年度から令和8年度にかけて9.5％の増である | F11: 令和8年10月10日に、第1章4（3）と第5章7（1）へ書き足した（ＹＳ-1・ＹＳ-7）。令和8年度の給付実績が出そろった段階で、改定後の単価による額を基準に置き直し、第2次算定に用いる。それまでの間、第5章7の給付費は改定前の単価によるものとして読む | G11: 対応中
A12: R-34 | B12: 制度動向 | C12: 中 | D12: 意思決定支援ガイドラインが第2版に改訂され、考え方が変わった | E12: 厚生労働省が令和8年9月に第2版を公表した。「本人の最善の利益」から「本人の意思と選好に基づく最善の解釈」への転換、どのような障害があっても意思決定能力があることを前提とする原則、本人参加の意思決定支援会議、意思決定支援責任者などが第1版から変わっている。周囲が本人にとってよいことを決めるのではなく、本人であれば何を望むのかを読み取るという向きの変更であり、用語の差し替えでは済まない。正本は案の段階から3段階を取り込んでいたが、価値観・最善の解釈・意思決定能力の前提は入っていなかった | F12: 令和8年10月10日に、原典を1件ずつ照合したうえで反映した。移植8（第4章2（7））、移植18（第5章5（1））、Ｙ-5（第6章3）を生成器の側で直し、ＩＫ-1・ＩＫ-2を追記した。新しい数値の指標は作らず、県研修への参加の内数として扱う。残るのは県研修で第2版がいつから扱われるかの確認（Ｓ-12） | G12: 対応中
A13: R-33 | B13: 成果目標 | C13: 中 | D13: 情報公表制度の公表率・更新率100％は、村に達成の手段がほとんどない | E13: 国の基本指針は管内事業所の公表率・更新率100％を成果目標としており、正本も表4-16に置いている。しかし事業者の指定もこの制度の報告先も県であり、村は指定を行う立場にない。国のＱ＆Ａ（問3-1-1）によれば、システムには自治体から事業所へ報告を促す機能も備わっていない。村にできるのは公表・更新の状況を確かめて県と連携した周知を行うことだけであり、100％に届かなかった場合に村の取組み不足とは言えない。さらに、表4-16には公表率・更新率の現状の欄が無く、いまの値を把握できていない | F13: 令和8年10月10日に、目標が何のためのものかと、村にできることの範囲を正本に書いた（ＫＪ-1）。照会Ｍ-104（令和7年度の公表・更新の実績、未報告減算の対象の有無、県から村への情報提供の有無）を第1便に入れた。県から村へ状況の提供がない場合、村は100％かどうかを確かめる手段を持たないため、目標の書き方そのものを見直す | G13: 対応中
A14: R-32 | B14: 広域連携 | C14: 高 | D14: 広域で確保するとした機能が、相手方の計画と同じ単位・同じ数え方になっているか確かめられていない | E14: 本計画は、地域生活支援拠点、基幹相談支援センター、医療的ケア児等支援、インクルージョン推進、強度行動障害支援を猪苗代町・磐梯町・湯川村との広域で確保するとしている。しかし相手方の計画では、医療的ケア児等支援の協議の場を「圏域1カ所」としており、この「圏域」が会津北部4町村か会津障がい保健福祉圏域かが分からない。単位が違えば設置すべき会議体そのものが変わる。医療的ケア児等コーディネーターも、県の養成研修の修了者、本村が数える1人、磐梯町が令和8年4月から制度化した独自配置が混在し、同じ方を双方が数えると4町村の合計が実際より多く見える。本村の計画の中では整っていても、相手方の計画と施設数・コーディネーター数・目標年度・会議体・KPIが食い違えば、広域で確保したことにならない | F14: 令和8年10月10日に会津北部4町村共同確認票（16項目）を作成し、照会Ｍ-98として第6便に入れた（期限 令和8年12月12日）。県への照会8項目はＭ-99。正本には、協議の場の単位とコーディネーターの数え方を書き分ける記述を加えた（ＫＯ-1）。回答が揃うまで、成果目標の「4町村共同」は確定表記にしない | G14: 対応中
A15: R-31 | B15: 推計 | C15: 最高 | D15: 手帳所持者数の将来推計の基礎となる令和8年の値が仮置きである | E15: 当方の将来推計ブックは平成31年〜令和5年の5か年（156人まで減少）を延ばし、令和11年度の中位推計を145人（減少）としている。他メンバー版の正本 第2章2 は令和8年4月を身体127人・療育16人・精神38人の計181人と記述しているが、他メンバー版のワークシートの注記は「総数はR2〜R5が第7期計画（4月1日）、R6〜R8は推計」であり、村の台帳による確定値ではない（網羅性点検に記録済み）。したがって減少という前提が崩れたかどうかを確かめられない。令和8年10月10日の時点で当方は、確認事項「仕様書の約190人と現行計画156人の差」を「約190人は実数であったと考えられる」として解消していたが、その根拠の181人は約190人から作られた値であり循環していた。令和8年10月13日に解消を取り消した。手帳所持者数は所持率法による見込量の検証に用いるため、第2次算定の検証の土台が定まらない | F15: 令和8年10月10日に概要版から令和11年度の推計値を外し、やり直す旨を注記した（計画素案・将来推計ブックにも【要更新】を付した）。令和8年10月13日に、手帳別に別の係数を用いた4通りの試算を行い、令和11年の合計に139人から206人まで67人の幅があることを示した（北塩原村_レビュー対応_第3回.xlsx 02_手帳推計）。同日受領した策定委員会資料2により、療育手帳（令和6年13人・令和7年15人）と精神障害者保健福祉手帳（同33人・36人）の2か年が判明し、6点の回帰で精神＋2.51人／年・療育＋0.57人／年となった（従前は精神＋1.00人／年・療育−0.30人／年）。身体は所持率法（基準年令和8年度5.484％）で124人・122人・119人となり、令和11年の合計は181人、幅は180人から181人へ収束した。残るのは身体障害者手帳の令和6年・令和7年の実数と、策定委員会資料の数値の出所（台帳か推計か）の確認である（Ｍ-124）。身体の127人が確定すれば推計が確定する。それまでの間、令和11年度の推計値は幅（180人から181人）として示し、単一の数値としては計画本文・概要版・委員会資料に載せない | G15: 対応中
A16: R-41 | B16: 記述の整合 | C16: 最高 | D16: 人口の見通しが、正本と当方の他の成果物とで食い違っている | E16: 正本 表2-1 は令和11年度を総人口2,166人・高齢化率45.2％とし、老年人口を998人から978人へ減少させている。「近年の減少（年約50人）を延長」した線形推計である。一方、村のこども・子育て計画（令和7年3月策定）のコーホート変化率法による公式推計は令和11年 総人口2,185人・老年人口1,051人・高齢化率48.1％であり、老年人口の向きが逆（正本は減少、村公式推計は増加）である。当方の成果物は村公式推計の側を用いており、協議会資料3、地域生活支援事業ブック、目次構成_前回対比、クロス集計設計、骨子案修正版 第2章1 がいずれも48.1％と書いている。同じ案件の中で高齢化率が45.2％と48.1％の2通りある状態で、村・委員会の双方が目にする。手帳所持者数の所持率法はこの総人口を分母に用いるため、どちらを用いるかが決まらないと手帳推計も定まらない（R-31） | F16: 令和8年10月10日に当方の網羅性点検（第2章1）へ「どちらを用いるか村と決める。介護保険事業計画の人口基礎とも揃える（K-8）」として起票済み。令和8年10月13日に、手帳推計の試算（レビュー対応_第3回 02_手帳推計）で正本 表2-1 の側に合わせたうえで、人口が定まらないと推計も定まらないことを明記した。正本の数値を動かすかどうかは他メンバーの担当範囲であるため、当方から書き換えず、介護保険事業計画の人口基礎と併せて三者で一度に決める。入稿（令和9年3月17日）までに決めない場合は、当方の成果物の側を正本に合わせて45.2％へ揃える | G16: 対応中
... A44: R-19 | B44: 調査設計 | C44: 低 | D44: 障がい児版の設問番号に誤りがある | E44: 問11の選択肢番号「13」が2つある（「自傷、他害、強いこだわり、パニックなどへの対応」と「特にない」）。問10の選択肢番号は「3」が欠番。いずれも村の朱書きとは別に、通読して気づいたもの | F44: 調査票担当へ申し送り済み。印刷前に番号を振り直す。問10は問8との統合指示があるため、統合時に整理する | G44: 対応中

Sheet 06_打合せ記録
A1: 打合せ・会議の記録（仕様書Ⅲ・Ⅱ(7)）
A2: 仕様書Ⅲの打合せ等業務と、Ⅱ(7)の自立支援協議会の開催記録です。協議会の開催は1回程度を見込みます。
A5: 日付 | B5: 区分 | C5: 場所・形式 | D5: 出席 | E5: 主な決定事項 | F5: 残課題
A6: 2026-07-07 | B6: 打合せ | C6: 北塩原村役場（対面） | D6: 村：保健福祉課ほか3名／当社：3名 | E6: アンケートを障がい者用・障がい児用の2種類に分離。村の封筒を使用し差出人・返送先を村役場に設定。村役場で一括受領し窓口回収。郵便料金は村が立替え後日精算。14pt・ルビ・白黒印刷。重複回答等は集計除外せず報告書欄外に件数を注記。8月上旬発送。 | F6: 郵送費の精算方法の書面化、印刷仕様の確定、ラベル提供時期
B7: 打合せ
B8: 協議会
B9: 打合せ

Sheet 07_更新履歴
A1: 進捗管理の更新履歴
A2: 本ブックの更新と、主要な成果物の版を記録します。
A5: 日付 | B5: 区分 | C5: 内容 | D5: 成果物
A6: 2026-10-07 | B6: アンケート | C6: 前回報告書（概要＋分野別12区分の単純集計の2部のみ）と前回計画本編（報告書を頁単位で5か所引用、第3章は［現状と課題］＋［具体的な取組み］の2段構成）を確認の上、報告書の構成案を作成。ご提案の6区分のうちニーズと計画策定時の注意点の章立てに賛成し、要因分析は統計的分析が成り立たないため村の実績との突合に置き換えて「調査結果の背景」とすることを提案。現行6章に2章を足した8章19節を提示。経年比較を行わない方針を受け、行わない理由を留意事項に書く案を併記。人材確保を設問から外す判断は妥当とし、別表第二 六の項が計画の努力義務であること（計画素案 第5章13で対応済み）を整理 | D6: 北塩原村_アンケート報告書_構成案.xlsx
A7: 2026-10-05 | B7: アンケート | C7: 村から受領した分析報告書（6章・表26・図61）と図表データ集をレビュー。数値整合は良好で、本文の割合521件のうち520件が集計と一致し、クロス表10件の割合は不一致0。指摘19件（重大4・中9・小6）。最大の欠落は経年比較で前回調査との対比が0件、回収率の低下（57.9％→22.1％）にも言及なし。自由記述に個人特定の可能性。当方の計画素案の割合の分母が報告書・前回調査と不一致だったため11項目修正し、見込量MECEチェックに混入していた個票の「計」行を除去 | D7: 北塩原村_アンケート分析報告書_レビュー.xlsx／北塩原村_計画素案.docx／北塩原村_見込量算定_MECEチェック.xlsx
A8: 2026-10-05 | B8: 見込量 | C8: 国の基本指針・通達を確認の上、見込量算定のMECEチェック。別表第一 二〜六の31事項・地域生活支援事業13事業・算定方法6・付加要件8を点検し、指摘17件（重大4・中8・小5）。区分の網羅性は満たすが、告示が「ものとする」とした継続入所者の控除と保育所等の受入体制が算定に入っていないことを検出。マニュアル（参考）のアンケートによる増減判断を実施し増加要素19・減少要素9。条文番号・単位・廃止区分・系列の重複の6件を是正 | D8: 北塩原村_見込量算定_MECEチェック.xlsx／北塩原村_計画素案.docx／北塩原村_地域生活支援事業.xlsx
A9: 2026-10-04 | B9: 品質管理 | C9: 成果物の再現性を点検する仕組みを整備。生成器23本・成果物35点の対応を依存順に明記し、未追跡ファイル・ライブラリの欠落・絶対パスの直書き・外部資料の入手先を7項目で点検。全22本の再実行で34/34点の内容一致を確認。Pillow欠落時に管理表2点の画像シートが警告なく欠ける不具合を発見し手当て | D9: check_reproducibility.py／requirements.txt／北塩原村_成果物の再現性点検と再発防止.md
A10: 2026-10-04 | B10: 計画素案 | C10: アンケート結果と見込量第1次概算を計画素案に反映。第5章3〜7の見込量表を第1次概算（27サービス）に差し替えて基準年度の請求件数の列を追加し、医療型児童発達支援の行を削除。第2章8をアンケート実施結果に書き換え、第3章5の目標値表に本調査の結果と前回との比較可能性の列を追加 | D10: 北塩原村_計画素案.docx
A11: 2026-10-04 | B11: 指標 | C11: 目標・KPIの前回比較可能性を全数洗い出し。第4次計画の施策目標8指標・成果目標8区分・見込量27区分・活動指標33項目・地域生活支援事業15事業・アンケート設問50問の対応を整理。前回計画本編の転記誤り1件（外出の目的28.1％→29.1％）を含む訂正5件を特定 | D11: 北塩原村_目標KPI_前回比較可能性.xlsx
A12: 2026-10-03 | B12: アンケート | C12: アンケート結果報告書（作成中）を点検。個票から集計を再計算し、報告書本文の割合320件を突合して計算誤り0件を確認。分母の取り方・前回調査との比較可能性・障がい児調査の内部矛盾・未記入の11件を洗い出し、村の実績との突合で論点4件を追加 | D12: 北塩原村_アンケート結果報告書_点検結果.xlsx
A13: 2026-09-24 | B13: 見込量 | C13: 大雪地区広域連合・川崎町で確立した算定の手順を障がい福祉計画に移し、サービス見込量の第1次概算を算定。基準年度は令和7年度、採用はパターン3（基準年度据え置き＋成果目標による補正）。3か年給付費172,859,691円。据え置き10件・自己点検12件すべて合 | D13: 北塩原村_サービス見込量算定.xlsx
A14: 2026-09-24 | B14: 計画素案 | C14: レビュー優先度 高の4件を反映。第5章13（人材確保・生産性向上・経営基盤／別表第二 六の項）と第5章14（関係機関との連携／別表第二 五）を新設し、第4章（２）に基盤整備量、第4章（４）に医療的ケア児等の協議の場を追加。第5章の節番号の参照ずれ3か所も修正 | D14: 北塩原村_計画素案.docx
A15: 2026-09-17 | B15: 制度確認 | C15: 村から基本指針の改正2件（社会福祉法等改正 令和8年7月10日、医療的ケア児支援法改正 令和8年8月19日）を受領し、骨子案・計画素案との網羅性を確認。別表第二 六の項の新設と医療的ケア者の新設により、不足14件・確認事項8件を洗い出し | D15: 北塩原村_骨子案レビュー_基本指針網羅性.xlsx
A16: 2026-09-17 | B16: 概要版 | C16: 住民向けの概要版（A4・4頁）を別ファイルで作成。前回の概要版の構成を踏襲しつつ、改定対象外の障がい者計画は「継承する内容」として整理し、ＳＤＧｓの節を国の基本指針の見直しのポイントに差し替え | D16: 北塩原村_計画素案_概要版.docx
... A30: 2026-07-07 | B30: 打合せ | C30: 北塩原村役場にて打合せ。アンケート実施設計を決定 | D30: 議事録

Sheet 08_分量配分計画
A1: 計画書の分量配分計画（成果品①：A4判・両面約60頁）
A2: 村資料が揃ってから分量を考えると組版段階で削る作業が発生するため、章ごとの目標頁数を先に決める。計画素案の頁は目次整理後の推定値（A4・余白2cm・行送り18pt・本文10.5ptで1頁40行として積算。作業用の注記33件を含む）。現行計画は本文57頁（製本63頁は白紙・奥付を含む）。
A5: 章 | B5: 現行計画 （本文57頁） | C5: 計画素案 （推定） | D5: 目標頁 | E5: 増減 | F5: 根拠
A6: 第1章 計画の策定にあたって | B6: 9 | C6: 9 | D6: 9 | E6: 0 | F6: 基本指針の改正16項目とPDCAの推進体制が中心。令和8年9月に障がい福祉サービスの体系（第1章7）を新設し、現行計画と同じ9頁に戻した
A7: 第2章 本村の障がい者の現状 | B7: 5 | C7: 6 | D7: 7 | E7: 1 | F7: 手帳所持者数の将来推計（仕様書4-Ⅱ(3)①）を新設。実績データの受領で図表が埋まる
A8: 第3章 基本理念・基本目標及び施策体系 | B8: 13 | C8: 5 | D8: 5 | E8: 0 | F8: 改定対象外の第4次障がい者計画の再掲。骨格と第8期で加わる視点との対応表に絞る。ＳＤＧｓ対応表は今回は追加しない方針
A9: 第4章 令和11年度に向けた成果目標 | B9: 11 | C9: 9 | D9: 11 | E9: 2 | F9: 7項目→8項目。目標値・考え方の記入で増える
A10: 第5章 サービス等の実績と今後の見込み量 | B10: 16 | C10: 22 | D10: 20 | E10: -2 | F10: 推計方法・年齢到達移行・活動指標・財源構成を新設。本計画の実質的な付加価値。注記の削除で2頁程度減る見込み
A11: 第6章 成年後見制度の利用促進 | B11: 2 | C11: 1 | D11: 2 | E11: 1 | F11: 現行と同水準。中核機関の記述を補う
A12: 第7章 他計画との連携 | B12: ― | C12: 3 | D12: 3 | E12: 0 | F12: 新設章。健康21・総合振興計画・こども子育て計画
A13: 第8章 資料編 | B13: 1 | C13: 3 | D13: 3 | E13: 0 | F13: アンケート集計結果は成果品②（別冊約60頁）に収める。令和8年9月に用語解説（第8章4・30語）を新設
A14: 合計 | B14: =SUM(B6:B13) | C14: =ROUND(SUM(C6:C13),0) | D14: =SUM(D6:D13) | E14: =D14-C14 | F14: 目標60頁。計画素案の推定58頁のうち注記33件を削ると実質53頁前後で、実績データの記入に7頁程度の余地がある
A16: 60頁に収まらない場合の削減順序（上から削る）
A17: 順 | B17: 削減対象 | F17: 理由
A18: 1 | B18: 第3章の施策別の記述 | F18: 改定対象外の再掲であり、詳細は第4次障がい者計画本体を参照すればよい
A19: 2 | B19: 第1章の基本指針改正16項目 | F19: 16項目すべてを列挙せず、本村に関係する項目に絞る
A20: 3 | B20: 第8章の資料編 | F20: 成果品②へ移す
A21: 4 | B21: 第5章の実績値の年次 | F21: 令和2年度からの6年分を令和5年度からの4年分に短縮する
A23: 削ってはならないもの
A24: 項目 | F24: 理由
A25: 第4章の成果目標8項目 | F25: 基本指針が求める必須事項
A26: 第5章のサービス見込量 | F26: 別表第二 三の項の必須記載事項
A27: 第5章の活動指標のうち見込量に相当するもの | F27: 同上（第三 四㈡により見込量以外は任意）
A28: 第5章1の推計方法 | F28: 別表第五の適用判定を含む算定根拠
A30: ※ 本頁換算は文字数からの概算であり、実際の頁数はスタイル（フォントサイズ・行間・余白）で変わる。第1章の原稿が固まった時点で実際の組版にかけ、1頁あたりの文字数を実測して本計画を補正する。
