Workbook

Sheet 01_設定
A1: 女川町水道事業 試算条件切替計算表
A2: 黄色のセルを変えると、02以降のシートがすべて自動で計算し直されます。Excelで開いてご利用ください。
A3: 既定値は中間報告書（改訂版）の採用条件です。総括原価1,175,810千円・必要改定率1.99倍を再現します。
A5: 【投資と減価償却】
B6: 建設改良費の計画 | C6: 建設改良費調査票 | E6: 調査票＝女川町回答（R8〜R17で35.15億円）。量水器費は経営戦略の1.06億円
B7: 耐用年数（管路・構築物） | C7: 38 | E7: 経営戦略の設定は38年
B8: 耐用年数（機械・電気） | C8: 38 | E8: 調査票は4事業とも40年。鷲神高度処理設備は機械・電気設備を含むため要確認
B9: 既存資産の償却費 | C9: 財政シミュに接続 | E9: 接続＝1,855,337千円（R6末1,822,881＋R7取得32,456）。差引方式＝1,814,019千円（41,318千円不足）
B10: 減価償却費の算入方法 | C10: 損益計算書ベース | E10: 台帳ベースを選ぶと長期前受金戻入益の控除は0になります
A11: 【企業債】
B12: 借入利率（％） | C12: 2.1 | E12: 調査票は4事業とも未記入。2.1％は経営戦略の加重平均借入利率
B13: 償還条件 | C13: 経営戦略方式（40年・据置なし）
A14: 【資産維持費】
B15: 資産維持率（％） | C15: 3 | E15: 日本水道協会「水道料金算定要領」の標準値は3％
B16: 対象資産の取り方 | C16: 期首期末平均 | E16: 期首期末平均＝896,312千円 期首＝1,042,625千円。いずれも推計値で未確定
B17: 資産維持費の年数 | C17: 5
A18: 【控除項目】
B19: 長期前受金戻入益 | C19: 経営戦略の実額 | E19: 実額＝1,542,259千円＋新規取得分。推計値＝450,000千円
B20: 他会計補助金等 | C20: 他会計補助金のみ | E20: 他会計補助金272,997千円。繰出基準に基づく区分は町に未確認
B21: その他営業収益・受取利息等 | C21: 控除しない | E21: 控除する場合26,494千円。経営戦略の原価計算表は控除していない
B22: 雑支出 | C22: 算入しない | E22: 算入する場合36,696千円
B23: 動力費・薬品費 | C23: 実績単価に補正 | E23: 経営戦略は1年分の費用を10年間の水量で割っており過小。補正額＋47,167千円
A24: 【水量と収益】
B25: 有収水量 5年計（㎥） | C25: 4316000 | E25: 経営戦略の水需要予測
B26: 給水収益 5年計（千円・税抜） | C26: 590845 | E26: 現行料金による見込額。令和8年4〜6月の基本料金等免除は未反映
A27: 【料金改定の試算】
B28: パターン1の改定率 | E28: 空欄にすると03シートの必要改定率を使います。数値を入れるとその率で試算します
B29: パターン3-Aの水準係数 | C29: 0.976194 | E29: 05シートの「必要な係数の目安」を見ながら調整してください
A31: 算定結果（詳しくは02・03シート）
B32: 総括原価 5年計（千円） | C32: ='02_総括原価'!C14
B33: 給水原価（円/㎥） | C33: ='03_指標と改定率'!C6
B34: 供給単価 R8〜R12・税抜（円/㎥） | C34: ='03_指標と改定率'!C7
B35: 総括原価回収割合 | C35: ='03_指標と改定率'!C8
B36: 年間不足額（千円/年） | C36: ='03_指標と改定率'!C9
B37: 必要改定率（倍） | C37: ='03_指標と改定率'!C10
B38: 赤字半減の改定率（倍） | C38: ='03_指標と改定率'!C13
B39: 標準家庭 20mm・20㎥（円/月・改定後） | C39: ='04_料金への影響'!H19
A41: ※ 数式の計算結果はファイルに保存していません。Excelで開くと計算されます。
A42: ※ 既定値のまま開くと 1,175,810千円 / 272.4円/㎥ / 50.3% / 1.990倍 / 2,809円 になります。
A43: ※ 他会計補助金等を「控除しない」にすると 1,448,807千円 / 2.452倍 になります。

Sheet 02_総括原価
A1: 総括原価の算定（令和8〜12年度 5年計・税抜・千円）
A2: 「01_設定」の選択に基づいて計算しています。
B4: 費目 | C4: 金額 | E4: 内容・変わる条件
A5: Ⅰ | B5: 維持管理費 | C5: =672327+IF('01_設定'!$C$23="実績単価に補正",47167,0) | E5: 動力費・薬品費の補正で＋47,167千円
A6: Ⅱ | B6: 減価償却費 | C6: =IF('01_設定'!$C$10="固定資産台帳ベース",32188*5+INDEX('07_計算用データ'!$E$6:$E$113,MATCH('01_設定'!$C$6&"|"&'01_設定'!$C$10&"|"&'01_設定'!$C$7&"|"&'01_設定'!$C$8,'07_計算用データ'!$G$6:$G$113,0)),IF('01_設定'!$C$9="差引方式",1814019,1855337)+INDEX('07_計算用データ'!$E$6:$E$113,MATCH('01_設定'!$C$6&"|"&'01_設定'!$C$10&"|"&'01_設定'!$C$7&"|"&'01_設定'!$C$8,'07_計算用データ'!$G$6:$G$113,0))) | E6: 既存資産分＋新規分。計画・耐用年数・算入方法・既存分の取り方で変わる
A7: Ⅲ | B7: 支払利息（既往債） | C7: =50585 | E7: 固定
A8: Ⅳ | B8: 支払利息（新規債） | C8: =44630+INDEX('07_計算用データ'!$D$118:$D$183,MATCH('01_設定'!$C$6&"|"&TEXT('01_設定'!$C$12,"0.0")&"|"&'01_設定'!$C$13,'07_計算用データ'!$G$118:$G$183,0)) | E8: 既往計画分44,630千円＋新規分。借入利率と償還条件で変わる
A9: Ⅴ | B9: 雑支出 | C9: =IF('01_設定'!$C$22="算入する",36696,0) | E9: 算入する場合36,696千円
A10: Ⅵ | B10: 資産維持費 | C10: =ROUND(IF('01_設定'!$C$16="期首の帳簿価額",1042625,896312)*'01_設定'!$C$15/100,0)*'01_設定'!$C$17 | E10: 対象資産×資産維持率×年数。対象資産は未確定
A11: Ⅶ | B11: 控除：長期前受金戻入益 | C11: =-IF('01_設定'!$C$10="固定資産台帳ベース",0,IF('01_設定'!$C$19="経営戦略の実額",1542259+INDEX('07_計算用データ'!$F$6:$F$113,MATCH('01_設定'!$C$6&"|"&'01_設定'!$C$10&"|"&'01_設定'!$C$7&"|"&'01_設定'!$C$8,'07_計算用データ'!$G$6:$G$113,0)),IF('01_設定'!$C$19="成果品の推計値",450000,0))) | E11: 補助財源で取得した資産の償却見合い
A12: Ⅷ | B12: 控除：他会計補助金等 | C12: =-IF('01_設定'!$C$20="他会計補助金のみ",272997,IF('01_設定'!$C$20="他会計補助金＋補助金",691997,IF('01_設定'!$C$20="成果品の推計値",15000,0))) | E12: 繰出基準に基づく区分は町に未確認
A13: Ⅸ | B13: 控除：その他営業収益・受取利息等 | C13: =-IF('01_設定'!$C$21="控除する",26494,0) | E13: 控除する場合26,494千円
B14: 総括原価 合計 | C14: =SUM(C5:C13)
A16: 適用中の条件
B17: 建設改良費の計画 | C17: ='01_設定'!$C$6
B18: 耐用年数（管路・構築物） | C18: ='01_設定'!$C$7
B19: 耐用年数（機械・電気） | C19: ='01_設定'!$C$8
B20: 既存資産の償却費 | C20: ='01_設定'!$C$9
B21: 減価償却費の算入方法 | C21: ='01_設定'!$C$10
B22: 借入利率（％） | C22: ='01_設定'!$C$12
B23: 償還条件 | C23: ='01_設定'!$C$13
B24: 資産維持率（％） | C24: ='01_設定'!$C$15
B25: 対象資産の取り方 | C25: ='01_設定'!$C$16
B26: 長期前受金戻入益 | C26: ='01_設定'!$C$19
B27: 他会計補助金等 | C27: ='01_設定'!$C$20
B28: 動力費・薬品費 | C28: ='01_設定'!$C$23

Sheet 03_指標と改定率
A1: 給水原価・総括原価回収割合・必要改定率
A2: 供給単価は税区分と対象年度で3種類ある。同じ指標として比較しないこと。
B4: 指標 | C4: 算定値 | E4: 算定式・注意
B5: 総括原価 5年計（千円） | C5: ='02_総括原価'!C14 | E5: 02シートの合計
B6: 給水原価（円/㎥） | C6: ='02_総括原価'!C14*1000/'01_設定'!$C$25 | E6: 総括原価×1,000÷有収水量
B7: 供給単価 R8〜R12・税抜（円/㎥） | C7: ='01_設定'!$C$26*1000/'01_設定'!$C$25 | E7: 給水収益×1,000÷有収水量
B8: 総括原価回収割合 | C8: =C7/C6 | E8: 供給単価÷給水原価。決算の料金回収率とは分母が異なる
B9: 年間不足額（千円/年） | C9: =('02_総括原価'!C14-'01_設定'!$C$26)/5 | E9: （総括原価−給水収益）÷5年
B10: 必要改定率（倍） | C10: ='02_総括原価'!C14/'01_設定'!$C$26 | E10: 総括原価÷給水収益。★控除条件の前提つきの試算値であり確定水準ではない
B11: 料金不足額 定義③（千円/年） | C11: ='01_設定'!$C$26/5+IF('01_設定'!$C$20="控除しない",0,-('02_総括原価'!C12)/5)-('02_総括原価'!C5/5+'02_総括原価'!C7/5+'02_総括原価'!C8/5+'02_総括原価'!C10/5) | E11: 給水収益＋基準内繰入金−（維持管理費＋支払利息＋資産維持費）÷5年。元金償還・建設改良費を含まない
B12: 半減に必要な増収額（千円/年） | C12: =-C11/2
B13: 赤字半減の改定率（倍） | C13: =1+C12/('01_設定'!$C$26/5) | E13: 定義③の半減
B14: パターン1に適用する改定率（倍） | C14: =IF(ISNUMBER('01_設定'!$C$28),'01_設定'!$C$28,C10) | E14: 01_設定に数値を入れるとその率。空欄なら必要改定率
A16: 参考：段階改定（適用開始は令和9年4月以降）
B17: 段階 | C17: 改定率 | E17: 内容
B18: 第1次（議決 令和9年3月） | C18: =C13 | E18: 定義③の料金不足額の半減
B19: 第2次（令和13〜17年度） | C19: =C10 | E19: 総括原価の回収。その時点の投資計画で再算定
A21: ※ 改定率は通年ベース。令和8年度の料金は現行のままで、増収は令和9年度以降に生じる。

Sheet 04_料金への影響
A1: 利用者への影響（月額・税込）
A2: パターン1は現行料金に改定率を一律に乗じたもの。3-Aは口径別基本料金＋段階逓増。
A3: 件数・月平均水量は代表値による推計であり、原票との照合は未了。
B5: 水量ゾーン | C5: 月平均 水量 | D5: 件数 | E5: 適用 口径 | F5: 現行 | H5: パターン1 改定後 | I5: 現行比 | J5: パターン3-A | K5: 現行比 | M5: 備考
B6: ① 0㎥ | C6: 0 | D6: 297 | E6: 13mm | F6: =IF(C6<=5,990,1210)+IF(C6>10,(MIN(C6,100)-10)*121+MAX(0,C6-100)*110,0)+55 | H6: =ROUND(F6*'03_指標と改定率'!$C$14,0) | I6: =H6/F6 | J6: =ROUND((770+(MIN(C6,10)*91.3+MAX(0,MIN(C6,20)-10)*192.5+MAX(0,MIN(C6,50)-20)*258.5+MAX(0,MIN(C6,100)-50)*280.5+MAX(0,C6-100)*324.5))*'01_設定'!$C$29,0) | K6: =J6/F6
B7: ② 1〜5㎥ | C7: 2.9 | D7: 513 | E7: 13mm | F7: =IF(C7<=5,990,1210)+IF(C7>10,(MIN(C7,100)-10)*121+MAX(0,C7-100)*110,0)+55 | H7: =ROUND(F7*'03_指標と改定率'!$C$14,0) | I7: =H7/F7 | J7: =ROUND((770+(MIN(C7,10)*91.3+MAX(0,MIN(C7,20)-10)*192.5+MAX(0,MIN(C7,50)-20)*258.5+MAX(0,MIN(C7,100)-50)*280.5+MAX(0,C7-100)*324.5))*'01_設定'!$C$29,0) | K7: =J7/F7
B8: ③ 6〜10㎥ | C8: 8 | D8: 590 | E8: 13mm | F8: =IF(C8<=5,990,1210)+IF(C8>10,(MIN(C8,100)-10)*121+MAX(0,C8-100)*110,0)+55 | H8: =ROUND(F8*'03_指標と改定率'!$C$14,0) | I8: =H8/F8 | J8: =ROUND((770+(MIN(C8,10)*91.3+MAX(0,MIN(C8,20)-10)*192.5+MAX(0,MIN(C8,50)-20)*258.5+MAX(0,MIN(C8,100)-50)*280.5+MAX(0,C8-100)*324.5))*'01_設定'!$C$29,0) | K8: =J8/F8
B9: ④ 11〜20㎥ | C9: 14.9 | D9: 856 | E9: 20mm | F9: =IF(C9<=5,990,1210)+IF(C9>10,(MIN(C9,100)-10)*121+MAX(0,C9-100)*110,0)+77 | H9: =ROUND(F9*'03_指標と改定率'!$C$14,0) | I9: =H9/F9 | J9: =ROUND((1430+(MIN(C9,10)*91.3+MAX(0,MIN(C9,20)-10)*192.5+MAX(0,MIN(C9,50)-20)*258.5+MAX(0,MIN(C9,100)-50)*280.5+MAX(0,C9-100)*324.5))*'01_設定'!$C$29,0) | K9: =J9/F9
B10: ⑤ 21〜50㎥ | C10: 28.7 | D10: 672 | E10: 20mm | F10: =IF(C10<=5,990,1210)+IF(C10>10,(MIN(C10,100)-10)*121+MAX(0,C10-100)*110,0)+77 | H10: =ROUND(F10*'03_指標と改定率'!$C$14,0) | I10: =H10/F10 | J10: =ROUND((1430+(MIN(C10,10)*91.3+MAX(0,MIN(C10,20)-10)*192.5+MAX(0,MIN(C10,50)-20)*258.5+MAX(0,MIN(C10,100)-50)*280.5+MAX(0,C10-100)*324.5))*'01_設定'!$C$29,0) | K10: =J10/F10
B11: ⑥ 51〜100㎥ | C11: 71.6 | D11: 55 | E11: 25mm | F11: =IF(C11<=5,990,1210)+IF(C11>10,(MIN(C11,100)-10)*121+MAX(0,C11-100)*110,0)+110 | H11: =ROUND(F11*'03_指標と改定率'!$C$14,0) | I11: =H11/F11 | J11: =ROUND((2310+(MIN(C11,10)*91.3+MAX(0,MIN(C11,20)-10)*192.5+MAX(0,MIN(C11,50)-20)*258.5+MAX(0,MIN(C11,100)-50)*280.5+MAX(0,C11-100)*324.5))*'01_設定'!$C$29,0) | K11: =J11/F11
B12: ⑦ 101〜500㎥ | C12: 197.5 | D12: 55 | E12: 25mm | F12: =IF(C12<=5,990,1210)+IF(C12>10,(MIN(C12,100)-10)*121+MAX(0,C12-100)*110,0)+110 | H12: =ROUND(F12*'03_指標と改定率'!$C$14,0) | I12: =H12/F12 | J12: =ROUND((2310+(MIN(C12,10)*91.3+MAX(0,MIN(C12,20)-10)*192.5+MAX(0,MIN(C12,50)-20)*258.5+MAX(0,MIN(C12,100)-50)*280.5+MAX(0,C12-100)*324.5))*'01_設定'!$C$29,0) | K12: =J12/F12
B13: ⑧ 501㎥超 | C13: 1030.5 | D13: 18 | E13: 50mm | F13: =IF(C13<=5,990,1210)+IF(C13>10,(MIN(C13,100)-10)*121+MAX(0,C13-100)*110,0)+880 | H13: =ROUND(F13*'03_指標と改定率'!$C$14,0) | I13: =H13/F13 | J13: =ROUND((11000+(MIN(C13,10)*91.3+MAX(0,MIN(C13,20)-10)*192.5+MAX(0,MIN(C13,50)-20)*258.5+MAX(0,MIN(C13,100)-50)*280.5+MAX(0,C13-100)*324.5))*'01_設定'!$C$29,0) | K13: =J13/F13
B14: 年間収入（百万円） | D14: =SUM(D6:D13) | F14: =SUMPRODUCT($D$6:$D$13,F6:F13)*12*1.04677/1000000 | H14: =SUMPRODUCT($D$6:$D$13,H6:H13)*12*1.04677/1000000 | J14: =SUMPRODUCT($D$6:$D$13,J6:J13)*12*1.04677/1000000
B15: 総括原価回収割合 | F15: =F14*1000000/('01_設定'!$C$25/5)/'03_指標と改定率'!$C$6 | H15: =H14*1000000/('01_設定'!$C$25/5)/'03_指標と改定率'!$C$6 | J15: =J14*1000000/('01_設定'!$C$25/5)/'03_指標と改定率'!$C$6 | M15: 補正係数1.04677は収入のみの経験補正（中間報告書5-6）
A17: 標準家庭と特殊用途
B18: 区分 | C18: 月使用量 | E18: 口径 | F18: 現行 | H18: パターン1 | I18: 現行比 | J18: パターン3-A | K18: 現行比 | M18: 備考
B19: 標準家庭 | C19: 20 | E19: 20mm | F19: =IF(C19<=5,990,1210)+IF(C19>10,(MIN(C19,100)-10)*121+MAX(0,C19-100)*110,0)+77 | H19: =ROUND(F19*'03_指標と改定率'!$C$14,0) | I19: =H19/F19 | J19: =ROUND((1430+(MIN(C19,10)*91.3+MAX(0,MIN(C19,20)-10)*192.5+MAX(0,MIN(C19,50)-20)*258.5+MAX(0,MIN(C19,100)-50)*280.5+MAX(0,C19-100)*324.5))*'01_設定'!$C$29,0) | K19: =J19/F19 | M19: 中間報告書の標準家庭
B20: 少量使用（13mm・8㎥） | C20: 8 | E20: 13mm | F20: =IF(C20<=5,990,1210)+IF(C20>10,(MIN(C20,100)-10)*121+MAX(0,C20-100)*110,0)+55 | H20: =ROUND(F20*'03_指標と改定率'!$C$14,0) | I20: =H20/F20 | J20: =ROUND((770+(MIN(C20,10)*91.3+MAX(0,MIN(C20,20)-10)*192.5+MAX(0,MIN(C20,50)-20)*258.5+MAX(0,MIN(C20,100)-50)*280.5+MAX(0,C20-100)*324.5))*'01_設定'!$C$29,0) | K20: =J20/F20 | M20: 3-Aでも現行より上がる
B21: 13mm・3㎥ | C21: 3 | E21: 13mm | F21: =IF(C21<=5,990,1210)+IF(C21>10,(MIN(C21,100)-10)*121+MAX(0,C21-100)*110,0)+55 | H21: =ROUND(F21*'03_指標と改定率'!$C$14,0) | I21: =H21/F21 | J21: =ROUND((770+(MIN(C21,10)*91.3+MAX(0,MIN(C21,20)-10)*192.5+MAX(0,MIN(C21,50)-20)*258.5+MAX(0,MIN(C21,100)-50)*280.5+MAX(0,C21-100)*324.5))*'01_設定'!$C$29,0) | K21: =J21/F21 | M21: 3-Aで現行を下回るのはこの付近まで
B22: 中規模事業者 | C22: 1000 | E22: 50mm | F22: =IF(C22<=5,990,1210)+IF(C22>10,(MIN(C22,100)-10)*121+MAX(0,C22-100)*110,0)+880 | H22: =ROUND(F22*'03_指標と改定率'!$C$14,0) | I22: =H22/F22 | J22: =ROUND((11000+(MIN(C22,10)*91.3+MAX(0,MIN(C22,20)-10)*192.5+MAX(0,MIN(C22,50)-20)*258.5+MAX(0,MIN(C22,100)-50)*280.5+MAX(0,C22-100)*324.5))*'01_設定'!$C$29,0) | K22: =J22/F22 | M22: 仮定した事例。実在の事業者ではない
B23: 大規模事業者 | C23: 3000 | E23: 75mm | F23: =IF(C23<=5,990,1210)+IF(C23>10,(MIN(C23,100)-10)*121+MAX(0,C23-100)*110,0)+1100 | H23: =ROUND(F23*'03_指標と改定率'!$C$14,0) | I23: =H23/F23 | J23: =ROUND((22000+(MIN(C23,10)*91.3+MAX(0,MIN(C23,20)-10)*192.5+MAX(0,MIN(C23,50)-20)*258.5+MAX(0,MIN(C23,100)-50)*280.5+MAX(0,C23-100)*324.5))*'01_設定'!$C$29,0) | K23: =J23/F23 | M23: 仮定した事例
A25: ※ 湯屋用・船舶用は用途別の定額設計のため本表に含めていない（中間報告書9-4を参照）。
A26: ※ 現行料金の端数処理は1円未満の切捨て。条例化の際に試算とそろえる。

Sheet 05_口径別料金表
A1: パターン3-A 口径別料金表（税込・円）
A2: 塩竈市の体系比率に「01_設定」の水準係数を乗じたもの。
A3: ★この係数は総括原価と一致するよう逆算した設定値であり、実際の調定データで検証した値ではない。
B5: 口径 | C5: 現行メーター使用料 | D5: 案3-A 基本料金 | F5: 備考
B6: 13mm | C6: 55 | D6: =ROUND(770*'01_設定'!$C$29,0)
B7: 20mm | C7: 77 | D7: =ROUND(1430*'01_設定'!$C$29,0)
B8: 25mm | C8: 110 | D8: =ROUND(2310*'01_設定'!$C$29,0)
B9: 40mm | C9: 220 | D9: =ROUND(5500*'01_設定'!$C$29,0)
B10: 50mm | C10: 880 | D10: =ROUND(11000*'01_設定'!$C$29,0)
B11: 75mm | C11: 1100 | D11: =ROUND(22000*'01_設定'!$C$29,0)
B12: 100mm | C12: 1320 | D12: =ROUND(41800*'01_設定'!$C$29,0)
B14: 水量区分 | C14: 現行（一般用） | D14: 案3-A 従量料金 | F14: 備考
B15: 〜10㎥ | C15: 基本水量 | D15: =91.3*'01_設定'!$C$29
B16: 〜20㎥ | C16: 121円/㎥ | D16: =192.5*'01_設定'!$C$29
B17: 〜50㎥ | C17: 121円/㎥ | D17: =258.5*'01_設定'!$C$29
B18: 〜100㎥ | C18: 121円/㎥ | D18: =280.5*'01_設定'!$C$29
B19: 101㎥超 | C19: 110円/㎥（逓減） | D19: =324.5*'01_設定'!$C$29 | F19: 現行は100㎥超で単価が下がる
A22: 水準係数の調整
B23: 現在の係数 | C23: ='01_設定'!$C$29
B24: 3-Aの年間収入（百万円） | C24: ='04_料金への影響'!J14
B25: 総括原価（年平均・百万円） | C25: ='03_指標と改定率'!C5/5/1000
B26: 必要な係数の目安 | C26: =C23*C25/C24 | F26: この値を「01_設定」の水準係数に入れ直すと、3-Aの収入が総括原価に近づきます。端数処理があるため1〜2回の繰り返しで合います。
A28: ※ 塩竈市の基本料金比率：13mm 770／20mm 1,430／25mm 2,310／40mm 5,500／50mm 11,000／75mm 22,000／100mm 41,800（税込×1.1）
A29: ※ 従量料金の基礎単価：〜10㎥ 91.3／〜20㎥ 192.5／〜50㎥ 258.5／〜100㎥ 280.5／101㎥超 324.5円/㎥

Sheet 06_ケース比較
A1: 主要ケースの比較（01_設定とは独立に計算しています）
A2: 各行はその行の条件だけで計算しており、「01_設定」を変えても動きません。
B4: ケース | C4: 総括原価 5年計（千円） | D4: 給水原価 （円/㎥） | E4: 回収割合 | F4: 必要改定率 （倍） | H4: 内容
B5: ★採用条件（中間報告書の改訂版） | C5: =(672327+IF("実績単価に補正"="実績単価に補正",47167,0))+(IF("損益計算書ベース"="固定資産台帳ベース",32188*5+INDEX('07_計算用データ'!$E$6:$E$113,MATCH("建設改良費調査票"&"|"&"損益計算書ベース"&"|"&38&"|"&38,'07_計算用データ'!$G$6:$G$113,0)),IF("財政シミュに接続"="差引方式",1814019,1855337)+INDEX('07_計算用データ'!$E$6:$E$113,MATCH("建設改良費調査票"&"|"&"損益計算書ベース"&"|"&38&"|"&38,'07_計算用データ'!$G$6:$G$113,0))))+(50585)+(44630+INDEX('07_計算用データ'!$D$118:$D$183,MATCH("建設改良費調査票"&"|"&TEXT(2.1,"0.0")&"|"&"経営戦略方式（40年・据置なし）",'07_計算用データ'!$G$118:$G$183,0)))+(IF("算入しない"="算入する",36696,0))+(ROUND(IF("期首期末平均"="期首の帳簿価額",1042625,896312)*3.0/100,0)*5)+(-IF("損益計算書ベース"="固定資産台帳ベース",0,IF("経営戦略の実額"="経営戦略の実額",1542259+INDEX('07_計算用データ'!$F$6:$F$113,MATCH("建設改良費調査票"&"|"&"損益計算書ベース"&"|"&38&"|"&38,'07_計算用データ'!$G$6:$G$113,0)),IF("経営戦略の実額"="成果品の推計値",450000,0))))+(-IF("他会計補助金のみ"="他会計補助金のみ",272997,IF("他会計補助金のみ"="他会計補助金＋補助金",691997,IF("他会計補助金のみ"="成果品の推計値",15000,0))))+(-IF("控除しない"="控除する",26494,0)) | D5: =C5*1000/'01_設定'!$C$25 | E5: ='01_設定'!$C$26*1000/'01_設定'!$C$25/D5 | F5: =C5/'01_設定'!$C$26 | H5: 基準内繰入金を控除。減価償却費は財政シミュに接続
B6: 繰入金を控除しない | C6: =(672327+IF("実績単価に補正"="実績単価に補正",47167,0))+(IF("損益計算書ベース"="固定資産台帳ベース",32188*5+INDEX('07_計算用データ'!$E$6:$E$113,MATCH("建設改良費調査票"&"|"&"損益計算書ベース"&"|"&38&"|"&38,'07_計算用データ'!$G$6:$G$113,0)),IF("財政シミュに接続"="差引方式",1814019,1855337)+INDEX('07_計算用データ'!$E$6:$E$113,MATCH("建設改良費調査票"&"|"&"損益計算書ベース"&"|"&38&"|"&38,'07_計算用データ'!$G$6:$G$113,0))))+(50585)+(44630+INDEX('07_計算用データ'!$D$118:$D$183,MATCH("建設改良費調査票"&"|"&TEXT(2.1,"0.0")&"|"&"経営戦略方式（40年・据置なし）",'07_計算用データ'!$G$118:$G$183,0)))+(IF("算入しない"="算入する",36696,0))+(ROUND(IF("期首期末平均"="期首の帳簿価額",1042625,896312)*3.0/100,0)*5)+(-IF("損益計算書ベース"="固定資産台帳ベース",0,IF("経営戦略の実額"="経営戦略の実額",1542259+INDEX('07_計算用データ'!$F$6:$F$113,MATCH("建設改良費調査票"&"|"&"損益計算書ベース"&"|"&38&"|"&38,'07_計算用データ'!$G$6:$G$113,0)),IF("経営戦略の実額"="成果品の推計値",450000,0))))+(-IF("控除しない"="他会計補助金のみ",272997,IF("控除しない"="他会計補助金＋補助金",691997,IF("控除しない"="成果品の推計値",15000,0))))+(-IF("控除しない"="控除する",26494,0)) | D6: =C6*1000/'01_設定'!$C$25 | E6: ='01_設定'!$C$26*1000/'01_設定'!$C$25/D6 | F6: =C6/'01_設定'!$C$26 | H6: 控除の根拠が確認できない場合
B7: 他会計補助金＋補助金を控除 | C7: =(672327+IF("実績単価に補正"="実績単価に補正",47167,0))+(IF("損益計算書ベース"="固定資産台帳ベース",32188*5+INDEX('07_計算用データ'!$E$6:$E$113,MATCH("建設改良費調査票"&"|"&"損益計算書ベース"&"|"&38&"|"&38,'07_計算用データ'!$G$6:$G$113,0)),IF("財政シミュに接続"="差引方式",1814019,1855337)+INDEX('07_計算用データ'!$E$6:$E$113,MATCH("建設改良費調査票"&"|"&"損益計算書ベース"&"|"&38&"|"&38,'07_計算用データ'!$G$6:$G$113,0))))+(50585)+(44630+INDEX('07_計算用データ'!$D$118:$D$183,MATCH("建設改良費調査票"&"|"&TEXT(2.1,"0.0")&"|"&"経営戦略方式（40年・据置なし）",'07_計算用データ'!$G$118:$G$183,0)))+(IF("算入しない"="算入する",36696,0))+(ROUND(IF("期首期末平均"="期首の帳簿価額",1042625,896312)*3.0/100,0)*5)+(-IF("損益計算書ベース"="固定資産台帳ベース",0,IF("経営戦略の実額"="経営戦略の実額",1542259+INDEX('07_計算用データ'!$F$6:$F$113,MATCH("建設改良費調査票"&"|"&"損益計算書ベース"&"|"&38&"|"&38,'07_計算用データ'!$G$6:$G$113,0)),IF("経営戦略の実額"="成果品の推計値",450000,0))))+(-IF("他会計補助金＋補助金"="他会計補助金のみ",272997,IF("他会計補助金＋補助金"="他会計補助金＋補助金",691997,IF("他会計補助金＋補助金"="成果品の推計値",15000,0))))+(-IF("控除しない"="控除する",26494,0)) | D7: =C7*1000/'01_設定'!$C$25 | E7: ='01_設定'!$C$26*1000/'01_設定'!$C$25/D7 | F7: =C7/'01_設定'!$C$26 | H7: 補助金419,000千円も控除した場合
B8: 既存資産の償却費を差引方式に戻す | C8: =(672327+IF("実績単価に補正"="実績単価に補正",47167,0))+(IF("損益計算書ベース"="固定資産台帳ベース",32188*5+INDEX('07_計算用データ'!$E$6:$E$113,MATCH("建設改良費調査票"&"|"&"損益計算書ベース"&"|"&38&"|"&38,'07_計算用データ'!$G$6:$G$113,0)),IF("差引方式"="差引方式",1814019,1855337)+INDEX('07_計算用データ'!$E$6:$E$113,MATCH("建設改良費調査票"&"|"&"損益計算書ベース"&"|"&38&"|"&38,'07_計算用データ'!$G$6:$G$113,0))))+(50585)+(44630+INDEX('07_計算用データ'!$D$118:$D$183,MATCH("建設改良費調査票"&"|"&TEXT(2.1,"0.0")&"|"&"経営戦略方式（40年・据置なし）",'07_計算用データ'!$G$118:$G$183,0)))+(IF("算入しない"="算入する",36696,0))+(ROUND(IF("期首期末平均"="期首の帳簿価額",1042625,896312)*3.0/100,0)*5)+(-IF("損益計算書ベース"="固定資産台帳ベース",0,IF("経営戦略の実額"="経営戦略の実額",1542259+INDEX('07_計算用データ'!$F$6:$F$113,MATCH("建設改良費調査票"&"|"&"損益計算書ベース"&"|"&38&"|"&38,'07_計算用データ'!$G$6:$G$113,0)),IF("経営戦略の実額"="成果品の推計値",450000,0))))+(-IF("他会計補助金のみ"="他会計補助金のみ",272997,IF("他会計補助金のみ"="他会計補助金＋補助金",691997,IF("他会計補助金のみ"="成果品の推計値",15000,0))))+(-IF("控除しない"="控除する",26494,0)) | D8: =C8*1000/'01_設定'!$C$25 | E8: ='01_設定'!$C$26*1000/'01_設定'!$C$25/D8 | F8: =C8/'01_設定'!$C$26 | H8: 改訂前の算定。41,318千円不足する
B9: 機械・電気を20年償却 | C9: =(672327+IF("実績単価に補正"="実績単価に補正",47167,0))+(IF("損益計算書ベース"="固定資産台帳ベース",32188*5+INDEX('07_計算用データ'!$E$6:$E$113,MATCH("建設改良費調査票"&"|"&"損益計算書ベース"&"|"&38&"|"&20,'07_計算用データ'!$G$6:$G$113,0)),IF("財政シミュに接続"="差引方式",1814019,1855337)+INDEX('07_計算用データ'!$E$6:$E$113,MATCH("建設改良費調査票"&"|"&"損益計算書ベース"&"|"&38&"|"&20,'07_計算用データ'!$G$6:$G$113,0))))+(50585)+(44630+INDEX('07_計算用データ'!$D$118:$D$183,MATCH("建設改良費調査票"&"|"&TEXT(2.1,"0.0")&"|"&"経営戦略方式（40年・据置なし）",'07_計算用データ'!$G$118:$G$183,0)))+(IF("算入しない"="算入する",36696,0))+(ROUND(IF("期首期末平均"="期首の帳簿価額",1042625,896312)*3.0/100,0)*5)+(-IF("損益計算書ベース"="固定資産台帳ベース",0,IF("経営戦略の実額"="経営戦略の実額",1542259+INDEX('07_計算用データ'!$F$6:$F$113,MATCH("建設改良費調査票"&"|"&"損益計算書ベース"&"|"&38&"|"&20,'07_計算用データ'!$G$6:$G$113,0)),IF("経営戦略の実額"="成果品の推計値",450000,0))))+(-IF("他会計補助金のみ"="他会計補助金のみ",272997,IF("他会計補助金のみ"="他会計補助金＋補助金",691997,IF("他会計補助金のみ"="成果品の推計値",15000,0))))+(-IF("控除しない"="控除する",26494,0)) | D9: =C9*1000/'01_設定'!$C$25 | E9: ='01_設定'!$C$26*1000/'01_設定'!$C$25/D9 | F9: =C9/'01_設定'!$C$26 | H9: 鷲神高度処理設備の区分が確定した場合
B10: 機械・電気を20年＋繰入金を控除しない | C10: =(672327+IF("実績単価に補正"="実績単価に補正",47167,0))+(IF("損益計算書ベース"="固定資産台帳ベース",32188*5+INDEX('07_計算用データ'!$E$6:$E$113,MATCH("建設改良費調査票"&"|"&"損益計算書ベース"&"|"&38&"|"&20,'07_計算用データ'!$G$6:$G$113,0)),IF("財政シミュに接続"="差引方式",1814019,1855337)+INDEX('07_計算用データ'!$E$6:$E$113,MATCH("建設改良費調査票"&"|"&"損益計算書ベース"&"|"&38&"|"&20,'07_計算用データ'!$G$6:$G$113,0))))+(50585)+(44630+INDEX('07_計算用データ'!$D$118:$D$183,MATCH("建設改良費調査票"&"|"&TEXT(2.1,"0.0")&"|"&"経営戦略方式（40年・据置なし）",'07_計算用データ'!$G$118:$G$183,0)))+(IF("算入しない"="算入する",36696,0))+(ROUND(IF("期首期末平均"="期首の帳簿価額",1042625,896312)*3.0/100,0)*5)+(-IF("損益計算書ベース"="固定資産台帳ベース",0,IF("経営戦略の実額"="経営戦略の実額",1542259+INDEX('07_計算用データ'!$F$6:$F$113,MATCH("建設改良費調査票"&"|"&"損益計算書ベース"&"|"&38&"|"&20,'07_計算用データ'!$G$6:$G$113,0)),IF("経営戦略の実額"="成果品の推計値",450000,0))))+(-IF("控除しない"="他会計補助金のみ",272997,IF("控除しない"="他会計補助金＋補助金",691997,IF("控除しない"="成果品の推計値",15000,0))))+(-IF("控除しない"="控除する",26494,0)) | D10: =C10*1000/'01_設定'!$C$25 | E10: ='01_設定'!$C$26*1000/'01_設定'!$C$25/D10 | F10: =C10/'01_設定'!$C$26 | H10: 負担が最も重くなる組合せ
B11: 借入利率2.0％ | C11: =(672327+IF("実績単価に補正"="実績単価に補正",47167,0))+(IF("損益計算書ベース"="固定資産台帳ベース",32188*5+INDEX('07_計算用データ'!$E$6:$E$113,MATCH("建設改良費調査票"&"|"&"損益計算書ベース"&"|"&38&"|"&38,'07_計算用データ'!$G$6:$G$113,0)),IF("財政シミュに接続"="差引方式",1814019,1855337)+INDEX('07_計算用データ'!$E$6:$E$113,MATCH("建設改良費調査票"&"|"&"損益計算書ベース"&"|"&38&"|"&38,'07_計算用データ'!$G$6:$G$113,0))))+(50585)+(44630+INDEX('07_計算用データ'!$D$118:$D$183,MATCH("建設改良費調査票"&"|"&TEXT(2.0,"0.0")&"|"&"経営戦略方式（40年・据置なし）",'07_計算用データ'!$G$118:$G$183,0)))+(IF("算入しない"="算入する",36696,0))+(ROUND(IF("期首期末平均"="期首の帳簿価額",1042625,896312)*3.0/100,0)*5)+(-IF("損益計算書ベース"="固定資産台帳ベース",0,IF("経営戦略の実額"="経営戦略の実額",1542259+INDEX('07_計算用データ'!$F$6:$F$113,MATCH("建設改良費調査票"&"|"&"損益計算書ベース"&"|"&38&"|"&38,'07_計算用データ'!$G$6:$G$113,0)),IF("経営戦略の実額"="成果品の推計値",450000,0))))+(-IF("他会計補助金のみ"="他会計補助金のみ",272997,IF("他会計補助金のみ"="他会計補助金＋補助金",691997,IF("他会計補助金のみ"="成果品の推計値",15000,0))))+(-IF("控除しない"="控除する",26494,0)) | D11: =C11*1000/'01_設定'!$C$25 | E11: ='01_設定'!$C$26*1000/'01_設定'!$C$25/D11 | F11: =C11/'01_設定'!$C$26
B12: 借入利率3.0％ | C12: =(672327+IF("実績単価に補正"="実績単価に補正",47167,0))+(IF("損益計算書ベース"="固定資産台帳ベース",32188*5+INDEX('07_計算用データ'!$E$6:$E$113,MATCH("建設改良費調査票"&"|"&"損益計算書ベース"&"|"&38&"|"&38,'07_計算用データ'!$G$6:$G$113,0)),IF("財政シミュに接続"="差引方式",1814019,1855337)+INDEX('07_計算用データ'!$E$6:$E$113,MATCH("建設改良費調査票"&"|"&"損益計算書ベース"&"|"&38&"|"&38,'07_計算用データ'!$G$6:$G$113,0))))+(50585)+(44630+INDEX('07_計算用データ'!$D$118:$D$183,MATCH("建設改良費調査票"&"|"&TEXT(3.0,"0.0")&"|"&"経営戦略方式（40年・据置なし）",'07_計算用データ'!$G$118:$G$183,0)))+(IF("算入しない"="算入する",36696,0))+(ROUND(IF("期首期末平均"="期首の帳簿価額",1042625,896312)*3.0/100,0)*5)+(-IF("損益計算書ベース"="固定資産台帳ベース",0,IF("経営戦略の実額"="経営戦略の実額",1542259+INDEX('07_計算用データ'!$F$6:$F$113,MATCH("建設改良費調査票"&"|"&"損益計算書ベース"&"|"&38&"|"&38,'07_計算用データ'!$G$6:$G$113,0)),IF("経営戦略の実額"="成果品の推計値",450000,0))))+(-IF("他会計補助金のみ"="他会計補助金のみ",272997,IF("他会計補助金のみ"="他会計補助金＋補助金",691997,IF("他会計補助金のみ"="成果品の推計値",15000,0))))+(-IF("控除しない"="控除する",26494,0)) | D12: =C12*1000/'01_設定'!$C$25 | E12: ='01_設定'!$C$26*1000/'01_設定'!$C$25/D12 | F12: =C12/'01_設定'!$C$26
B13: 資産維持率1.0％ | C13: =(672327+IF("実績単価に補正"="実績単価に補正",47167,0))+(IF("損益計算書ベース"="固定資産台帳ベース",32188*5+INDEX('07_計算用データ'!$E$6:$E$113,MATCH("建設改良費調査票"&"|"&"損益計算書ベース"&"|"&38&"|"&38,'07_計算用データ'!$G$6:$G$113,0)),IF("財政シミュに接続"="差引方式",1814019,1855337)+INDEX('07_計算用データ'!$E$6:$E$113,MATCH("建設改良費調査票"&"|"&"損益計算書ベース"&"|"&38&"|"&38,'07_計算用データ'!$G$6:$G$113,0))))+(50585)+(44630+INDEX('07_計算用データ'!$D$118:$D$183,MATCH("建設改良費調査票"&"|"&TEXT(2.1,"0.0")&"|"&"経営戦略方式（40年・据置なし）",'07_計算用データ'!$G$118:$G$183,0)))+(IF("算入しない"="算入する",36696,0))+(ROUND(IF("期首期末平均"="期首の帳簿価額",1042625,896312)*1.0/100,0)*5)+(-IF("損益計算書ベース"="固定資産台帳ベース",0,IF("経営戦略の実額"="経営戦略の実額",1542259+INDEX('07_計算用データ'!$F$6:$F$113,MATCH("建設改良費調査票"&"|"&"損益計算書ベース"&"|"&38&"|"&38,'07_計算用データ'!$G$6:$G$113,0)),IF("経営戦略の実額"="成果品の推計値",450000,0))))+(-IF("他会計補助金のみ"="他会計補助金のみ",272997,IF("他会計補助金のみ"="他会計補助金＋補助金",691997,IF("他会計補助金のみ"="成果品の推計値",15000,0))))+(-IF("控除しない"="控除する",26494,0)) | D13: =C13*1000/'01_設定'!$C$25 | E13: ='01_設定'!$C$26*1000/'01_設定'!$C$25/D13 | F13: =C13/'01_設定'!$C$26
B14: 資産維持率5.0％ | C14: =(672327+IF("実績単価に補正"="実績単価に補正",47167,0))+(IF("損益計算書ベース"="固定資産台帳ベース",32188*5+INDEX('07_計算用データ'!$E$6:$E$113,MATCH("建設改良費調査票"&"|"&"損益計算書ベース"&"|"&38&"|"&38,'07_計算用データ'!$G$6:$G$113,0)),IF("財政シミュに接続"="差引方式",1814019,1855337)+INDEX('07_計算用データ'!$E$6:$E$113,MATCH("建設改良費調査票"&"|"&"損益計算書ベース"&"|"&38&"|"&38,'07_計算用データ'!$G$6:$G$113,0))))+(50585)+(44630+INDEX('07_計算用データ'!$D$118:$D$183,MATCH("建設改良費調査票"&"|"&TEXT(2.1,"0.0")&"|"&"経営戦略方式（40年・据置なし）",'07_計算用データ'!$G$118:$G$183,0)))+(IF("算入しない"="算入する",36696,0))+(ROUND(IF("期首期末平均"="期首の帳簿価額",1042625,896312)*5.0/100,0)*5)+(-IF("損益計算書ベース"="固定資産台帳ベース",0,IF("経営戦略の実額"="経営戦略の実額",1542259+INDEX('07_計算用データ'!$F$6:$F$113,MATCH("建設改良費調査票"&"|"&"損益計算書ベース"&"|"&38&"|"&38,'07_計算用データ'!$G$6:$G$113,0)),IF("経営戦略の実額"="成果品の推計値",450000,0))))+(-IF("他会計補助金のみ"="他会計補助金のみ",272997,IF("他会計補助金のみ"="他会計補助金＋補助金",691997,IF("他会計補助金のみ"="成果品の推計値",15000,0))))+(-IF("控除しない"="控除する",26494,0)) | D14: =C14*1000/'01_設定'!$C$25 | E14: ='01_設定'!$C$26*1000/'01_設定'!$C$25/D14 | F14: =C14/'01_設定'!$C$26
B15: 対象資産を期首の帳簿価額に | C15: =(672327+IF("実績単価に補正"="実績単価に補正",47167,0))+(IF("損益計算書ベース"="固定資産台帳ベース",32188*5+INDEX('07_計算用データ'!$E$6:$E$113,MATCH("建設改良費調査票"&"|"&"損益計算書ベース"&"|"&38&"|"&38,'07_計算用データ'!$G$6:$G$113,0)),IF("財政シミュに接続"="差引方式",1814019,1855337)+INDEX('07_計算用データ'!$E$6:$E$113,MATCH("建設改良費調査票"&"|"&"損益計算書ベース"&"|"&38&"|"&38,'07_計算用データ'!$G$6:$G$113,0))))+(50585)+(44630+INDEX('07_計算用データ'!$D$118:$D$183,MATCH("建設改良費調査票"&"|"&TEXT(2.1,"0.0")&"|"&"経営戦略方式（40年・据置なし）",'07_計算用データ'!$G$118:$G$183,0)))+(IF("算入しない"="算入する",36696,0))+(ROUND(IF("期首の帳簿価額"="期首の帳簿価額",1042625,896312)*3.0/100,0)*5)+(-IF("損益計算書ベース"="固定資産台帳ベース",0,IF("経営戦略の実額"="経営戦略の実額",1542259+INDEX('07_計算用データ'!$F$6:$F$113,MATCH("建設改良費調査票"&"|"&"損益計算書ベース"&"|"&38&"|"&38,'07_計算用データ'!$G$6:$G$113,0)),IF("経営戦略の実額"="成果品の推計値",450000,0))))+(-IF("他会計補助金のみ"="他会計補助金のみ",272997,IF("他会計補助金のみ"="他会計補助金＋補助金",691997,IF("他会計補助金のみ"="成果品の推計値",15000,0))))+(-IF("控除しない"="控除する",26494,0)) | D15: =C15*1000/'01_設定'!$C$25 | E15: ='01_設定'!$C$26*1000/'01_設定'!$C$25/D15 | F15: =C15/'01_設定'!$C$26 | H15: 1,042,625千円を用いた場合
B16: 量水器費を計上 | C16: =(672327+IF("実績単価に補正"="実績単価に補正",47167,0))+(IF("損益計算書ベース"="固定資産台帳ベース",32188*5+INDEX('07_計算用データ'!$E$6:$E$113,MATCH("調査票＋量水器費"&"|"&"損益計算書ベース"&"|"&38&"|"&38,'07_計算用データ'!$G$6:$G$113,0)),IF("財政シミュに接続"="差引方式",1814019,1855337)+INDEX('07_計算用データ'!$E$6:$E$113,MATCH("調査票＋量水器費"&"|"&"損益計算書ベース"&"|"&38&"|"&38,'07_計算用データ'!$G$6:$G$113,0))))+(50585)+(44630+INDEX('07_計算用データ'!$D$118:$D$183,MATCH("調査票＋量水器費"&"|"&TEXT(2.1,"0.0")&"|"&"経営戦略方式（40年・据置なし）",'07_計算用データ'!$G$118:$G$183,0)))+(IF("算入しない"="算入する",36696,0))+(ROUND(IF("期首期末平均"="期首の帳簿価額",1042625,896312)*3.0/100,0)*5)+(-IF("損益計算書ベース"="固定資産台帳ベース",0,IF("経営戦略の実額"="経営戦略の実額",1542259+INDEX('07_計算用データ'!$F$6:$F$113,MATCH("調査票＋量水器費"&"|"&"損益計算書ベース"&"|"&38&"|"&38,'07_計算用データ'!$G$6:$G$113,0)),IF("経営戦略の実額"="成果品の推計値",450000,0))))+(-IF("他会計補助金のみ"="他会計補助金のみ",272997,IF("他会計補助金のみ"="他会計補助金＋補助金",691997,IF("他会計補助金のみ"="成果品の推計値",15000,0))))+(-IF("控除しない"="控除する",26494,0)) | D16: =C16*1000/'01_設定'!$C$25 | E16: ='01_設定'!$C$26*1000/'01_設定'!$C$25/D16 | F16: =C16/'01_設定'!$C$26 | H16: 経営戦略の1.06億円を戻す
B17: 減価償却を固定資産台帳ベースに | C17: =(672327+IF("実績単価に補正"="実績単価に補正",47167,0))+(IF("固定資産台帳ベース"="固定資産台帳ベース",32188*5+INDEX('07_計算用データ'!$E$6:$E$113,MATCH("建設改良費調査票"&"|"&"固定資産台帳ベース"&"|"&38&"|"&38,'07_計算用データ'!$G$6:$G$113,0)),IF("財政シミュに接続"="差引方式",1814019,1855337)+INDEX('07_計算用データ'!$E$6:$E$113,MATCH("建設改良費調査票"&"|"&"固定資産台帳ベース"&"|"&38&"|"&38,'07_計算用データ'!$G$6:$G$113,0))))+(50585)+(44630+INDEX('07_計算用データ'!$D$118:$D$183,MATCH("建設改良費調査票"&"|"&TEXT(2.1,"0.0")&"|"&"経営戦略方式（40年・据置なし）",'07_計算用データ'!$G$118:$G$183,0)))+(IF("算入しない"="算入する",36696,0))+(ROUND(IF("期首期末平均"="期首の帳簿価額",1042625,896312)*3.0/100,0)*5)+(-IF("固定資産台帳ベース"="固定資産台帳ベース",0,IF("経営戦略の実額"="経営戦略の実額",1542259+INDEX('07_計算用データ'!$F$6:$F$113,MATCH("建設改良費調査票"&"|"&"固定資産台帳ベース"&"|"&38&"|"&38,'07_計算用データ'!$G$6:$G$113,0)),IF("経営戦略の実額"="成果品の推計値",450000,0))))+(-IF("他会計補助金のみ"="他会計補助金のみ",272997,IF("他会計補助金のみ"="他会計補助金＋補助金",691997,IF("他会計補助金のみ"="成果品の推計値",15000,0))))+(-IF("控除しない"="控除する",26494,0)) | D17: =C17*1000/'01_設定'!$C$25 | E17: ='01_設定'!$C$26*1000/'01_設定'!$C$25/D17 | F17: =C17/'01_設定'!$C$26 | H17: 長期前受金の控除は0になる
B18: 長期前受金を成果品の推計値に | C18: =(672327+IF("実績単価に補正"="実績単価に補正",47167,0))+(IF("損益計算書ベース"="固定資産台帳ベース",32188*5+INDEX('07_計算用データ'!$E$6:$E$113,MATCH("建設改良費調査票"&"|"&"損益計算書ベース"&"|"&38&"|"&38,'07_計算用データ'!$G$6:$G$113,0)),IF("財政シミュに接続"="差引方式",1814019,1855337)+INDEX('07_計算用データ'!$E$6:$E$113,MATCH("建設改良費調査票"&"|"&"損益計算書ベース"&"|"&38&"|"&38,'07_計算用データ'!$G$6:$G$113,0))))+(50585)+(44630+INDEX('07_計算用データ'!$D$118:$D$183,MATCH("建設改良費調査票"&"|"&TEXT(2.1,"0.0")&"|"&"経営戦略方式（40年・据置なし）",'07_計算用データ'!$G$118:$G$183,0)))+(IF("算入しない"="算入する",36696,0))+(ROUND(IF("期首期末平均"="期首の帳簿価額",1042625,896312)*3.0/100,0)*5)+(-IF("損益計算書ベース"="固定資産台帳ベース",0,IF("成果品の推計値"="経営戦略の実額",1542259+INDEX('07_計算用データ'!$F$6:$F$113,MATCH("建設改良費調査票"&"|"&"損益計算書ベース"&"|"&38&"|"&38,'07_計算用データ'!$G$6:$G$113,0)),IF("成果品の推計値"="成果品の推計値",450000,0))))+(-IF("他会計補助金のみ"="他会計補助金のみ",272997,IF("他会計補助金のみ"="他会計補助金＋補助金",691997,IF("他会計補助金のみ"="成果品の推計値",15000,0))))+(-IF("控除しない"="控除する",26494,0)) | D18: =C18*1000/'01_設定'!$C$25 | E18: ='01_設定'!$C$26*1000/'01_設定'!$C$25/D18 | F18: =C18/'01_設定'!$C$26 | H18: 450,000千円。改訂前の前提
B19: 動力費・薬品費を補正しない | C19: =(672327+IF("経営戦略のまま"="実績単価に補正",47167,0))+(IF("損益計算書ベース"="固定資産台帳ベース",32188*5+INDEX('07_計算用データ'!$E$6:$E$113,MATCH("建設改良費調査票"&"|"&"損益計算書ベース"&"|"&38&"|"&38,'07_計算用データ'!$G$6:$G$113,0)),IF("財政シミュに接続"="差引方式",1814019,1855337)+INDEX('07_計算用データ'!$E$6:$E$113,MATCH("建設改良費調査票"&"|"&"損益計算書ベース"&"|"&38&"|"&38,'07_計算用データ'!$G$6:$G$113,0))))+(50585)+(44630+INDEX('07_計算用データ'!$D$118:$D$183,MATCH("建設改良費調査票"&"|"&TEXT(2.1,"0.0")&"|"&"経営戦略方式（40年・据置なし）",'07_計算用データ'!$G$118:$G$183,0)))+(IF("算入しない"="算入する",36696,0))+(ROUND(IF("期首期末平均"="期首の帳簿価額",1042625,896312)*3.0/100,0)*5)+(-IF("損益計算書ベース"="固定資産台帳ベース",0,IF("経営戦略の実額"="経営戦略の実額",1542259+INDEX('07_計算用データ'!$F$6:$F$113,MATCH("建設改良費調査票"&"|"&"損益計算書ベース"&"|"&38&"|"&38,'07_計算用データ'!$G$6:$G$113,0)),IF("経営戦略の実額"="成果品の推計値",450000,0))))+(-IF("他会計補助金のみ"="他会計補助金のみ",272997,IF("他会計補助金のみ"="他会計補助金＋補助金",691997,IF("他会計補助金のみ"="成果品の推計値",15000,0))))+(-IF("控除しない"="控除する",26494,0)) | D19: =C19*1000/'01_設定'!$C$25 | E19: ='01_設定'!$C$26*1000/'01_設定'!$C$25/D19 | F19: =C19/'01_設定'!$C$26 | H19: 経営戦略の単価をそのまま使う
B20: その他営業収益等を控除し雑支出を算入 | C20: =(672327+IF("実績単価に補正"="実績単価に補正",47167,0))+(IF("損益計算書ベース"="固定資産台帳ベース",32188*5+INDEX('07_計算用データ'!$E$6:$E$113,MATCH("建設改良費調査票"&"|"&"損益計算書ベース"&"|"&38&"|"&38,'07_計算用データ'!$G$6:$G$113,0)),IF("財政シミュに接続"="差引方式",1814019,1855337)+INDEX('07_計算用データ'!$E$6:$E$113,MATCH("建設改良費調査票"&"|"&"損益計算書ベース"&"|"&38&"|"&38,'07_計算用データ'!$G$6:$G$113,0))))+(50585)+(44630+INDEX('07_計算用データ'!$D$118:$D$183,MATCH("建設改良費調査票"&"|"&TEXT(2.1,"0.0")&"|"&"経営戦略方式（40年・据置なし）",'07_計算用データ'!$G$118:$G$183,0)))+(IF("算入する"="算入する",36696,0))+(ROUND(IF("期首期末平均"="期首の帳簿価額",1042625,896312)*3.0/100,0)*5)+(-IF("損益計算書ベース"="固定資産台帳ベース",0,IF("経営戦略の実額"="経営戦略の実額",1542259+INDEX('07_計算用データ'!$F$6:$F$113,MATCH("建設改良費調査票"&"|"&"損益計算書ベース"&"|"&38&"|"&38,'07_計算用データ'!$G$6:$G$113,0)),IF("経営戦略の実額"="成果品の推計値",450000,0))))+(-IF("他会計補助金のみ"="他会計補助金のみ",272997,IF("他会計補助金のみ"="他会計補助金＋補助金",691997,IF("他会計補助金のみ"="成果品の推計値",15000,0))))+(-IF("控除する"="控除する",26494,0)) | D20: =C20*1000/'01_設定'!$C$25 | E20: ='01_設定'!$C$26*1000/'01_設定'!$C$25/D20 | F20: =C20/'01_設定'!$C$26
A22: ※ 各行は他の条件を採用条件に固定したうえで、記載の条件だけを変えた値である。複数の条件が同時に動く場合は単純な加算にならない。
A23: ※ 必要改定率は給水収益に対する倍率であり、確定した改定水準ではない。

Sheet 07_計算用データ
A1: 計算用データ（参照専用）
A2: 「02_総括原価」「06_ケース比較」が参照します。直接編集しないでください。
A4: 【減価償却費・長期前受金（新規取得分）R8〜R12 5年計・千円】
A5: 計画 | B5: 減価償却費の算入方法 | C5: 管路年数 | D5: 機電年数 | E5: 減価償却費 | F5: 長期前受金(新規) | G5: 照合キー
A6: 経営戦略の計画 | B6: 損益計算書ベース | C6: 35 | D6: 15 | E6: 237143 | F6: 16666 | G6: 経営戦略の計画|損益計算書ベース|35|15
A7: 経営戦略の計画 | B7: 損益計算書ベース | C7: 35 | D7: 20 | E7: 237143 | F7: 16666 | G7: 経営戦略の計画|損益計算書ベース|35|20
A8: 経営戦略の計画 | B8: 損益計算書ベース | C8: 35 | D8: 25 | E8: 237143 | F8: 16666 | G8: 経営戦略の計画|損益計算書ベース|35|25
A9: 経営戦略の計画 | B9: 損益計算書ベース | C9: 35 | D9: 30 | E9: 237143 | F9: 16666 | G9: 経営戦略の計画|損益計算書ベース|35|30
A10: 経営戦略の計画 | B10: 損益計算書ベース | C10: 35 | D10: 38 | E10: 237143 | F10: 16666 | G10: 経営戦略の計画|損益計算書ベース|35|38
A11: 経営戦略の計画 | B11: 損益計算書ベース | C11: 35 | D11: 40 | E11: 237143 | F11: 16666 | G11: 経営戦略の計画|損益計算書ベース|35|40
A12: 経営戦略の計画 | B12: 損益計算書ベース | C12: 38 | D12: 15 | E12: 218421 | F12: 15351 | G12: 経営戦略の計画|損益計算書ベース|38|15
A13: 経営戦略の計画 | B13: 損益計算書ベース | C13: 38 | D13: 20 | E13: 218421 | F13: 15351 | G13: 経営戦略の計画|損益計算書ベース|38|20
A14: 経営戦略の計画 | B14: 損益計算書ベース | C14: 38 | D14: 25 | E14: 218421 | F14: 15351 | G14: 経営戦略の計画|損益計算書ベース|38|25
A15: 経営戦略の計画 | B15: 損益計算書ベース | C15: 38 | D15: 30 | E15: 218421 | F15: 15351 | G15: 経営戦略の計画|損益計算書ベース|38|30
A16: 経営戦略の計画 | B16: 損益計算書ベース | C16: 38 | D16: 38 | E16: 218421 | F16: 15351 | G16: 経営戦略の計画|損益計算書ベース|38|38
A17: 経営戦略の計画 | B17: 損益計算書ベース | C17: 38 | D17: 40 | E17: 218421 | F17: 15351 | G17: 経営戦略の計画|損益計算書ベース|38|40
... A113: 調査票＋量水器費 | B113: 固定資産台帳ベース | C113: 40 | D113: 40 | E113: 122722 | F113: 0 | G113: 調査票＋量水器費|固定資産台帳ベース|40|40
A116: 【支払利息・元金償還（新規債）R8〜R12 5年計・千円】
A117: 計画 | B117: 借入利率(％) | C117: 償還条件 | D117: 支払利息 | E117: 元金償還 | G117: 照合キー
A118: 経営戦略の計画 | B118: 2 | C118: 経営戦略方式（40年・据置なし） | D118: 78800 | E118: 67850 | G118: 経営戦略の計画|2.0|経営戦略方式（40年・据置なし）
A119: 経営戦略の計画 | B119: 2 | C119: 調査票方式（25/40年・据置3年） | D119: 80234 | E119: 7428 | G119: 経営戦略の計画|2.0|調査票方式（25/40年・据置3年）
A120: 経営戦略の計画 | B120: 2.1 | C120: 経営戦略方式（40年・据置なし） | D120: 82772 | E120: 66462 | G120: 経営戦略の計画|2.1|経営戦略方式（40年・据置なし）
A121: 経営戦略の計画 | B121: 2.1 | C121: 調査票方式（25/40年・据置3年） | D121: 84245 | E121: 7268 | G121: 経営戦略の計画|2.1|調査票方式（25/40年・据置3年）
A122: 経営戦略の計画 | B122: 2.2 | C122: 経営戦略方式（40年・据置なし） | D122: 86746 | E122: 65096 | G122: 経営戦略の計画|2.2|経営戦略方式（40年・据置なし）
A123: 経営戦略の計画 | B123: 2.2 | C123: 調査票方式（25/40年・据置3年） | D123: 88257 | E123: 7111 | G123: 経営戦略の計画|2.2|調査票方式（25/40年・据置3年）
A124: 経営戦略の計画 | B124: 2.3 | C124: 経営戦略方式（40年・据置なし） | D124: 90722 | E124: 63752 | G124: 経営戦略の計画|2.3|経営戦略方式（40年・据置なし）
A125: 経営戦略の計画 | B125: 2.3 | C125: 調査票方式（25/40年・据置3年） | D125: 92269 | E125: 6957 | G125: 経営戦略の計画|2.3|調査票方式（25/40年・据置3年）
A126: 経営戦略の計画 | B126: 2.4 | C126: 経営戦略方式（40年・据置なし） | D126: 94701 | E126: 62429 | G126: 経営戦略の計画|2.4|経営戦略方式（40年・据置なし）
A127: 経営戦略の計画 | B127: 2.4 | C127: 調査票方式（25/40年・据置3年） | D127: 96280 | E127: 6806 | G127: 経営戦略の計画|2.4|調査票方式（25/40年・据置3年）
A128: 経営戦略の計画 | B128: 2.5 | C128: 経営戦略方式（40年・据置なし） | D128: 98682 | E128: 61128 | G128: 経営戦略の計画|2.5|経営戦略方式（40年・据置なし）
A129: 経営戦略の計画 | B129: 2.5 | C129: 調査票方式（25/40年・据置3年） | D129: 100292 | E129: 6657 | G129: 経営戦略の計画|2.5|調査票方式（25/40年・据置3年）
... A183: 調査票＋量水器費 | B183: 3 | C183: 調査票方式（25/40年・据置3年） | D183: 95736 | E183: 5550 | G183: 調査票＋量水器費|3.0|調査票方式（25/40年・据置3年）

Sheet 08_参照元
A1: 固定値の出所
B4: 項目 | C4: 値（千円） | E4: 出所・注意
B5: 維持管理費（基礎） | C5: 672327 | E5: 経営戦略の財政シミュレーション
B6: 動力費・薬品費の補正 | C6: 47167 | E6: 1年分の費用を10年間の水量で割る誤りの補正。R8〜R12の5年計
B7: 既存資産の償却費（接続） | C7: 1855337 | E7: R6末取得資産1,822,881＋R7取得資産32,456
B8: 既存資産の償却費（差引方式） | C8: 1814019 | E8: 2,032,440−218,421。改訂前の算定で41,318千円不足
B9: 支払利息（既往債） | C9: 50585 | E9: 経営戦略
B10: 支払利息（新規債の既往計画分） | C10: 44630 | E10: 経営戦略
B11: 長期前受金戻入益（既往分） | C11: 1542259 | E11: 経営戦略の実額
B12: 他会計補助金 | C12: 272997 | E12: ★繰出基準に基づく区分は町に未確認
B13: 補助金 | C13: 419000 | E13: 算定根拠が確認できないため既定では控除しない
B14: その他営業収益・受取利息等 | C14: 26494 | E14: 経営戦略の原価計算表は控除していない
B15: 雑支出 | C15: 36696 | E15: 経営戦略の原価計算表は算入していない
B16: 対象資産（期首期末平均） | C16: 896312 | E16: ★平成31年度末の残高に由来する推計値
... B20: 給水収益 5年計 | C20: 590845 | E20: ★令和8年4〜6月の基本料金等免除は未反映
A22: ★印は未確定。町の資料を受領して確定させる（中間報告書 第5章・第12章）。
A24: この計算表でできないこと
B25: ・使用者別の調定明細による検証。件数・口径分布は代表値による推計のまま
B26: ・産業用特例（3-B）の減収額。対象者の母集団が接続しないため算定していない
B27: ・年次の資金収支。企業債元金償還・建設改良費・期首資金を含む資金残高
B28: ・令和8年4〜6月の基本料金等免除を織り込んだ令和8・9年度の実収入
B29: ・湯屋用・船舶用の影響（中間報告書9-4を参照）
