Workbook
Name _01: #REF!
Name _01: PullDown!$AA$6:$AA$188
Name _02: #REF!
Name _02: PullDown!$AB$6:$AB$45
Name _03: #REF!
Name _03: PullDown!$AC$6:$AC$42
Name _04: #REF!
Name _04: PullDown!$AD$6:$AD$40
Name _05: #REF!
Name _05: PullDown!$AE$6:$AE$32
Name _06: #REF!
Name _06: PullDown!$AF$6:$AF$40
Name _07: #REF!
Name _07: PullDown!$AG$6:$AG$64
Name _08: #REF!
Name _08: PullDown!$AH$6:$AH$49
Name _09: #REF!
Name _09: PullDown!$AI$6:$AI$30
Name _10: #REF!
Name _10: PullDown!$AJ$6:$AJ$40
Name _11: #REF!
Name _11: PullDown!$AK$6:$AK$69
Name _12: #REF!
Name _12: PullDown!$AL$6:$AL$59
Name _13: #REF!
Name _13: PullDown!$AM$6:$AM$67
Name _14: #REF!
Name _14: PullDown!$AN$6:$AN$38
Name _15: #REF!
Name _15: PullDown!$AO$6:$AO$35
Name _16: #REF!
Name _16: PullDown!$AP$6:$AP$23
Name _17: #REF!
Name _17: PullDown!$AQ$6:$AQ$24
Name _18: #REF!
Name _18: PullDown!$AR$6:$AR$23
Name _19: #REF!
Name _19: PullDown!$AS$6:$AS$32
Name _20: #REF!
Name _20: PullDown!$AT$6:$AT$85
Name _21: #REF!
Name _21: PullDown!$AU$6:$AU$50
Name _22: #REF!
Name _22: PullDown!$AV$6:$AV$40
Name _23: #REF!
Name _23: PullDown!$AW$6:$AW$61
Name _24: #REF!
Name _24: PullDown!$AX$6:$AX$37
Name _25: #REF!
Name _25: PullDown!$AY$6:$AY$24
Name _26: #REF!
Name _26: PullDown!$AZ$6:$AZ$31
Name _27: #REF!
Name _27: PullDown!$BA$6:$BA$48
Name _28: #REF!
Name _28: PullDown!$BB$6:$BB$46
Name _29: #REF!
Name _29: PullDown!$BC$6:$BC$44
Name _30: #REF!
Name _30: PullDown!$BD$6:$BD$35

Sheet 所要額データ
A1: 01項番 | B1: 01通し番号 | C1: 01厚生（支）局名 | D1: 01都道府県名 | E1: 01保険者名 | F1: 01保険者番号 | G1: 01市区町村ｺｰﾄﾞ | H1: 01都道府県ｺｰﾄﾞ | I1: 01H27総合事業上限設定 | J1: 01H28総合事業上限設定 | K1: 01H29総合事業上限設定 | L1: 01H30総合事業上限設定 | M1: 01R1総合事業上限設定 | N1: 01R2総合事業上限設定 | O1: 01R3総合事業上限設定 | P1: 01R4総合事業上限設定 | Q1: 01R5総合事業上限設定 | R1: 01R6総合事業上限設定 | S1: 01総合事業移行年 | T1: 01総合事業移行月 | U1: 01総合事業移行日 | V1: 01総合事業移行年月日 | W1: 01総合事業移行年度 | X1: 01総合事業移行前年度 | Y1: 01指定都市 | Z1: 01広域連合等 | AA1: 01上記以外の市町村 | AB1: 01重層実施 | AC1: 01①地域介護予防活動支援事業に要する費用相当額を交付率で除して得た額 | AD1: 01②地域包括支援センターの運営に要する費用相当額を交付率で除して得た額 | AE1: 01③生活支援体制整備事業に要する費用相当額を交付率で除して得た額 | AF1: A1000 | AG1: A1100 | AH1: A1110 | AI1: A1120 | AJ1: A1130 | AK1: A1140 | AL1: A1150 | AM1: A1160 | AN1: A1200 | AO1: A1210 | AP1: A1220 | AQ1: A1230 | AR1: A1240 | AS1: A1250 | AT1: A1300 | AU1: A1310 | AV1: A1320 | AW1: A1330 | AX1: A1340 | AY1: A1400 | AZ1: A1500 | BA1: A1600 | BB1: A1700 | BC1: A1710 | BD1: A1720 | BE1: A1730 | BF1: A1740 | BG1: A1750 | BH1: A2000 | BI1: A2100 | BJ1: A2200 | BK1: A2210 | BL1: A2220 | BM1: A2230 | BN1: A3000 | BO1: A4000 | BP1: A4100 | BQ1: A4200 | BR1: A4210 | BS1: A4220 | BT1: A4230 | BU1: A4240 | BV1: A4300 | BW1: A4310 | BX1: A4320 | BY1: A4330 | BZ1: A4400 | CA1: A5000 | CB1: B1000 | CC1: B1100 | CD1: B1110 | CE1: B1120 | CF1: B1130 | CG1: B1140 | CH1: B1150 | CI1: B1160 | CJ1: B1200 | CK1: B1210 | CL1: B1220 | CM1: B1230 | CN1: B1240 | CO1: B1250 | CP1: B1300 | CQ1: B1310 | CR1: B1320 | CS1: B1330 | CT1: B1340 | CU1: B1400 | CV1: B1500 | CW1: B1600 | CX1: B1700 | CY1: B1710 | CZ1: B1720 | DA1: B1730 | DB1: B1740 | DC1: B1750 | DD1: B2000 | DE1: B2100 | DF1: B2200 | DG1: B2210 | DH1: B2220 | DI1: B2230 | DJ1: B3000 | DK1: B4000 | DL1: B4100 | DM1: B4200 | DN1: B4210 | DO1: B4220 | DP1: B4230 | DQ1: B4240 | DR1: B4300 | DS1: B4310 | DT1: B4320 | DU1: B4330 | DV1: B4400 | DW1: B5000 | DX1: C1000 | DY1: C1100 | DZ1: C1110 | EA1: C1120 | EB1: C1130 | EC1: C1140 | ED1: C1150 | EE1: C1160 | EF1: C1200 | EG1: C1210 | EH1: C1220 | EI1: C1230 | EJ1: C1240 | EK1: C1250 | EL1: C1300 | EM1: C1310 | EN1: C1320 | EO1: C1330 | EP1: C1340 | EQ1: C1400 | ER1: C1500 | ES1: C1600 | ET1: C1700 | EU1: C1710 | EV1: C1720 | EW1: C1730 | EX1: C1740 | EY1: C1750 | EZ1: C2000 | FA1: C2100 | FB1: C2200 | FC1: C2210 | FD1: C2220 | FE1: C2230 | FF1: C3000 | FG1: C4000 | FH1: C4100 | FI1: C4200 | FJ1: C4210 | FK1: C4220 | FL1: C4230 | FM1: C4240 | FN1: C4300 | FO1: C4310 | FP1: C4320 | FQ1: C4330 | FR1: C4400 | FS1: C5000 | FT1: D1000 | FU1: D1100 | FV1: D1110 | FW1: D1120 | FX1: D1130 | FY1: D1140 | FZ1: D1150 | GA1: D1160 | GB1: D1200 | GC1: D1210 | GD1: D1220 | GE1: D1230 | GF1: D1240 | GG1: D1250 | GH1: D1300 | GI1: D1310 | GJ1: D1320 | GK1: D1330 | GL1: D1340 | GM1: D1400 | GN1: D1500 | GO1: D1600 | GP1: D1700 | GQ1: D1710 | GR1: D1720 | GS1: D1730 | GT1: D1740 | GU1: D1750 | GV1: D2000 | GW1: D2100 | GX1: D2200 | GY1: D2210 | GZ1: D2220 | HA1: D2230 | HB1: D3000 | HC1: D4000 | HD1: D4100 | HE1: D4200 | HF1: D4210 | HG1: D4220 | HH1: D4230 | HI1: D4240 | HJ1: D4300 | HK1: D4310 | HL1: D4320 | HM1: D4330 | HN1: D4400 | HO1: D5000 | HP1: E1000 | HQ1: E2000 | HR1: E4000 | HS1: E4100 | HT1: E4200 | HU1: E4210 | HV1: E4220 | HW1: E4230 | HX1: E4240 | HY1: E4300 | HZ1: E4310 | IA1: E4320 | IB1: E4330 | IC1: E4400 | ID1: F1000 | IE1: F2000 | IF1: F3000 | IG1: F4000 | IH1: F5000 | II1: G1000 | IJ1: G2000 | IK1: G3000 | IL1: G4000 | IM1: G5000 | IN1: H1000 | IO1: H2000 | IP1: H3000 | IQ1: H4000 | IR1: H5000 | IS1: I1000 | IT1: I2000 | IU1: I3000 | IV1: I4000 | IW1: I5000 | IX1: J1000 | IY1: J2000 | IZ1: J3000 | JA1: J4000 | JB1: J5000 | JC1: K1000 | JD1: K2000 | JE1: K3000 | JF1: K4000 | JG1: K5000 | JH1: 備考欄1000 | JI1: 備考欄1100 | JJ1: 備考欄1110 | JK1: 備考欄1120 | JL1: 備考欄1130 | JM1: 備考欄1140 | JN1: 備考欄1150 | JO1: 備考欄1160 | JP1: 備考欄1200 | JQ1: 備考欄1210 | JR1: 備考欄1220 | JS1: 備考欄1230 | JT1: 備考欄1240 | JU1: 備考欄1250 | JV1: 備考欄1300 | JW1: 備考欄1310 | JX1: 備考欄1320 | JY1: 備考欄1330 | JZ1: 備考欄1340 | KA1: 備考欄1400 | KB1: 備考欄1500 | KC1: 備考欄1600 | KD1: 備考欄1700 | KE1: 備考欄1710 | KF1: 備考欄1720 | KG1: 備考欄1730 | KH1: 備考欄1740 | KI1: 備考欄1750 | KJ1: 備考欄2000 | KK1: 備考欄2100 | KL1: 備考欄2200 | KM1: 備考欄2210 | KN1: 備考欄2220 | KO1: 備考欄2230 | KP1: 備考欄3000 | KQ1: 備考欄4000 | KR1: 備考欄4100 | KS1: 備考欄4200 | KT1: 備考欄4210 | KU1: 備考欄4220 | KV1: 備考欄4230 | KW1: 備考欄4240 | KX1: 備考欄4300 | KY1: 備考欄4310 | KZ1: 備考欄4320 | LA1: 備考欄4330 | LB1: 備考欄4400 | LC1: 備考欄5000 | LD1: 総合事業の上限額設定状況 | LE1: 包括的支援事業（地域包括支援センターの運営）及び任意事業上限額設定状況 | LF1: 包括的支援事業（社会保障充実分）上限額設定状況 | LG1: 総合事業調整交付金調整基準標準事業費額 | LH1: 総合事業調整交付金所要額 | LI1: 重層的支援体制整備事業の実施有無 | LJ1: 重層的支援体制整備事業に要する費用相当額総額 | LK1: 重層的支援体制整備事業に要する地域介護予防活動支援事業費相当額 | LL1: 重層的支援体制整備事業に要する地域包括支援センターの運営費相当額 | LM1: 重層的支援体制整備事業に要する生活支援体制整備事業費相当額 | LN1: 重層Kセンター運営対象経費基本額（影響額調整後） | LO1: 重層aセンター運営地域支援事業で実施される任意事業に要する費用 | LP1: 重層K'センター運営小計（ K + a ） | LQ1: 重層Lセンター運営基準額 | LR1: 重層bセンター運営K’とLで、いずれか少ない額 | LS1: 重層Mセンター運営交付基本額（ b - a ） | LT1: 重層K'エラーセンター運営 | LU1: 重層bエラーセンター運営 | LV1: 重層Mエラーセンター運営 | LW1: 重層K地域介護予防対象経費基本額（影響額調整後） | LX1: 重層a地域介護予防地域支援事業で実施される介護予防・日常生活支援総合事業に要する費用 | LY1: 重層K'地域介護予防小計（ K + a ） | LZ1: 重層L地域介護予防基準額 | MA1: 重層b地域介護予防K’とLで、いずれか少ない額 | MB1: 重層M地域介護予防交付基本額（ b - a ） | MC1: 重層K'エラー地域介護予防 | MD1: 重層bエラー地域介護予防 | ME1: 重層Mエラー地域介護予防 | MF1: 重層K生活支援体制整備対象経費基本額（影響額調整後） | MG1: 重層a生活支援体制整備地域支援事業で実施される包括的支援事業（社会保障充実分）に要する費用 | MH1: 重層K'生活支援体制整備小計（ K + a ） | MI1: 重層L生活支援体制整備基準額 | MJ1: 重層b生活支援体制整備K’とLで、いずれか少ない額 | MK1: 重層M生活支援体制整備交付基本額（ b - a ） | ML1: 重層K'エラー生活支援体制整備 | MM1: 重層bエラー生活支援体制整備 | MN1: 重層Mエラー生活支援体制整備 | MO1: 02基本の上限額 | MP1: 02介護予防給付全体の伸びを考慮する上限額 | MQ1: 02特例イ | MR1: 02特例ロ | MS1: 02原則の上限額 | MT1: 02予防給付＋介護予防等事業の額 | MU1: 02予防給付の額 | MV1: 02予防給付全体の額（移行前年度） | MW1: 02予防給付全体の額（今年度） | MX1: 0275歳人口(平成２３年１０月１日) | MY1: 0275歳人口(平成２４年１０月１日) | MZ1: 0275歳人口(平成２５年１０月１日) | NA1: 0275歳人口(平成２６年１０月１日) | NB1: 0275歳人口(平成２７年１０月１日) | NC1: 0275歳人口(平成２８年１０月１日) | ND1: 0275歳人口(平成２９年１０月１日) | NE1: 0275歳人口(平成３０年１０月１日) | NF1: 0275歳人口(令和元年１０月１日) | NG1: 0275歳人口(令和２年１０月１日) | NH1: 0275歳人口(令和３年１０月１日) | NI1: 0275歳人口(令和４年１０月１日) | NJ1: 025歳人口(令和５年１０月１日) | NK1: 025歳人口(令和６年１０月１日) | NL1: 0275歳以上高齢者伸び率使用値（基本の上限額を算定するにあたって参照する値） | NM1: 0275歳以上高齢者伸び率使用値（特例イ・ロの額を算定するにあたって参照する値） | NN1: 02平成２９年度の介護予防・日常生活支援総合事業費額 | NO1: 02平成29年度の予防給付費額（介護予防訪問介護・介護予防通所介護・介護予防支援の合計額） | NP1: 02平成２９年度の予防給付費額全体 | NQ1: 02対象経費実支出額（清算書D欄） | NR1: 02実績に基づく上限超過額 | NS1: 02個別協議の要否 | NT1: 02個別協議希望の有無 | NU1: 02事前の個別協議を行わない場合の政令で定める上限額 | NV1: 02前年10月１日人口 | NW1: 02前年10月１日65歳以上人口 | NX1: 02交付申請時における事前の個別協議の承認有無 | NY1: 02事由④の該当性 | NZ1: 02上限超過承認希望額（事由④） | OA1: 02高齢者１人あたり事業費 | OB1: 02「離島等の市町村」への該当性 | OC1: 02事由⑤の該当性 | OD1: 02上限超過承認希望額（事由⑤） | OE1: 0275歳以上被保険者数変動率 | OF1: 02将来における介護予防・日常生活支援総合事業に要する費用の低減に資すると見込まれる事業の実施の有無 | OG1: 02前年度における当該③による個別協議の有無 | OH1: 02前年度における上限超過承認額・・・ア | OI1: 02前年10月１日における75歳以上の人口 | OJ1: 02前年10月１日における75歳以上80歳未満人口 | OK1: 02前年10月１日における80歳以上85歳未満人口 | OL1: 02前年10月１日における85歳以上の人口 | OM1: 02前年度の10月１日における75歳以上80歳未満人口を同日における75歳以上人口で除して得た率・・・X1 | ON1: 02前年度の10月１日における80歳以上85歳未満人口を同日における75歳以上人口で除して得た率・・・Y1 | OO1: 02前年度の10月１日における85歳以上人口を同日における75歳以上人口で除して得た率・・・Z1 | OP1: 令和３年10月１日における75歳以上の人口 | OQ1: 02当該年度の初日の属する年の４年前の４月１日の属する年度の10月１日における75歳以上80歳未満人口 | OR1: 02当該年度の初日の属する年の４年前の４月１日の属する年度の10月１日における80歳以上85歳未満人口 | OS1: 02当該年度の初日の属する年の４年前の４月１日の属する年度の10月１日における85歳以上の人口 | OT1: 02当該年度の初日の属する年の４年前の４月１日の属する年度の10月１日における75歳以上80歳未満人口を同日における75歳以上人口で除して得た率・・・X2 | OU1: 02当該年度の初日の属する年の４年前の４月１日の属する年度の10月１日における80歳以上85歳未満人口を同日における75歳以上人口で除して得た率・・・Y2 | OV1: 02当該年度の初日の属する年の４年前の４月１日の属する年度の10月１日における85歳以上人口を同日における75歳以上人口で除して得た率・・・Z2 | OW1: 02 A×0.9×(X1＋Y1×2＋Z1×3)/(X2＋Y2×2＋Z2×3)＋A×0.1－A・・・イ | OX1: 02事由③の該当性 | OY1: 02上限超過承認希望額（事由③） | OZ1: 02介護予防の効果が高く、かつ、将来における介護予防・日常生活支援総合事業に要する費用の低減に資すると見込まれる新たな事業の開始年度 | PA1: 02事由②の該当性（1年度目） | PB1: 02新たなプログラム等の実施に要する額（１年度目の上限超過承認希望額） | PC1: 02前年度における本事由に係る上限超過承認額（２年度目） | PD1: 02当該年度における新たなプログラム等の実施に要する額 | PE1: 02前年度における個別協議の際に申請した当該見込み額 | PF1: 02事由②の該当性（2年度目） | PG1: 02 ２年度目の上限超過承認希望額 | PH1: 02前年度における本事由に係る上限超過承認額（３年度目） | PI1: 02当該年度年度における新たなプログラム等の実施に要する額 | PJ1: 02事由②の該当性（３年度目） | PK1: 02 ３年度目の上限超過承認希望額 | PL1: 02 事由②による上限超過承認希望額 | PM1: 02従前相当サービス以外の第一号訪問事業の対象経費支出予定額 | PN1: 02従前相当サービス以外の第一号通所事業の対象経費支出予定額 | PO1: 02要介護認定又は要支援認定の状況把握 | PP1: 02数の把握 | PQ1: 02認定率（前々年度末日） | PR1: 02サービス利用率（前々年度末日） | PS1: 02認定率（前前々年度末日） | PT1: 02サービス利用率（前前々年度末日） | PU1: 02前々年度の末日における認定率－前々々年度年度の末日における認定率≦０ | PV1: 02前々年度の末日におけるサービス利用率－前々々年度の末日におけるサービス利用率≦０ | PW1: 02調整済み認定率（前々年度末日） | PX1: 02全国の調整済み認定率の平均（前々年度末日） | PY1: 02全国の調整済みサービス利用率の平均（前々年度末日） | PZ1: 02前々年度の末日における調整済み認定率－前々々年度の末日における全国の調整済み認定率の平均≦０ | QA1: 02前々年度の末日における調整済みサービス利用率－前々々年度の末日における全国の調整済みサービス利用率の平均≦０ | QB1: 02事由⑨の該当性 | QC1: 02前々年度の末日に要介護認定を受けていた第１号被保険者であって、前年度の末日に要支援認定を受けている又は要介護認定及び要支援認定のいずれも受けていない者の数 | QD1: 02前年度の介護予防・日常生活支援総合事業のうち従前相当サービスに要する費用の額として、前年度の交付申請に計上した額 | QE1: 02前年度において、従前相当サービスを利用した者の数 | QF1: 02上限超過承認額（事由⑨） | QG1: 02(4)１、(4)２又は(4)３による個別協議を行う場合の上限超過の承認を希望する額 | QH1: 02(4)１、(4)２又は(4)３による個別協議を行う場合の政令で定める上限額 | QI1: 02(4)４のみによる個別協議を行う場合の上限超過の承認を希望する額 | QJ1: 02(4)４のみによる個別協議を行う場合の政令で定める上限額 | QK1: 02(4)５のみによる個別協議を行う場合の上限超過の承認を希望する額 | QL1: 02(4)５のみによる個別協議を行う場合の政令で定める上限額 | QM1: 02事由４による上限超過の承認を希望する額と事由５による上限超過の承認を希望する額の合計 | QN1: 02事由４による上限超過の承認を希望する額と事由５による上限超過の承認を希望する額の合計ー上限超過額 | QO1: 02149行目が０以下である場合の事由４による上限超過の承認を希望する額 | QP1: 02149行目が０以下である場合の事由５による上限超過の承認を希望する額 | QQ1: 02149行目が０以下である場合の政令で定める上限額 | QR1: 02149行目が０を上回る場合、上限超過額ー事由４による上限超過の承認を希望する額 | QS1: 02153行目と147行目のいずれか少ない方の額 | QT1: 02149行目が０を上回る場合の事由４による上限超過の承認を希望する額 | QU1: 02149行目が０を上回る場合の事由５による上限超過の承認を希望する額 | QV1: 02149行目が０を上回る場合の政令で定める上限額 | QW1: 02事前協議後の上限額（原則の上限額及び①～④のうち最も高い金額） | QX1: 02実際の上限超過額（事前協議後の上限超過額：196行目－192行目） | QY1: 02事後の個別協議の要否 | QZ1: 02事後の個別協議希望の有無 | RA1: 02事後の個別協議を行わない場合の政令で定める上限額 | RB1: 02災害による居宅要支援被保険者等の数の増加有無 | RC1: 02ア～ウのうち該当する項目 | RD1: 02ア・イに該当する場合には災害・感染症の名称、ウに該当する場合には具体的な内容 | RE1: 02事由①の該当性 | RF1: 02ア 災害により増加した居宅要支援被保険者等に対して実施した介護予防・日常生活支援総合事業に要した費用の額 | RG1: 02令和７年４月１日から令和７年９月30日における災害等にかかる令和６年度の介護予防・日常生活支援総合事業特別調整交付金の額 | RH1: 02令和７年10月１日から令和８年３月31日における災害等にかかる令和７年度に交付される予定の介護予防・日常生活支援総合事業特別調整交付金の額 | RI1: 02イ 介護保険法第122条の２第２項に規定する交付金の額の算定に関する省令（平成27年厚生労働省令第58号）第７条各号に定める介護予防・日常 生活支援総合事業特別調整交付金の額 | RJ1: 02上限超過承認希望額（事由①） | RK1: 第一号訪問事業介護職員等処遇改善加算(Ⅰ)a | RL1: 第一号訪問事業介護職員等処遇改善加算(Ⅱ)a | RM1: 第一号訪問事業介護職員等処遇改善加算(Ⅲ)a | RN1: 第一号訪問事業介護職員等処遇改善加算(Ⅳ)a | RO1: 第一号通所事業介護職員等処遇改善加算(Ⅰ)a | RP1: 第一号通所事業介護職員等処遇改善加算(Ⅱ)a | RQ1: 第一号通所事業介護職員等処遇改善加算(Ⅲ)a | RR1: 第一号通所事業介護職員等処遇改善加算(Ⅳ)a | RS1: 第一号訪問事業介護職員等処遇改善加算(Ⅰ)c | RT1: 第一号訪問事業介護職員等処遇改善加算(Ⅱ)c | RU1: 第一号訪問事業介護職員等処遇改善加算(Ⅲ)c | RV1: 第一号訪問事業介護職員等処遇改善加算(Ⅳ)c | RW1: 第一号通所事業介護職員等処遇改善加算(Ⅰ)c | RX1: 第一号通所事業介護職員等処遇改善加算(Ⅱ)c | RY1: 第一号通所事業介護職員等処遇改善加算(Ⅲ)c | RZ1: 第一号通所事業介護職員等処遇改善加算(Ⅳ)c | SA1: 02介護職員等処遇改善加算等の支給に要した費用 | SB1: 02事由⑦の該当性 | SC1: 02上限超過承認希望額（事由⑦） | SD1: 02継続利用要介護者に係る第一号訪問事業の実施に要した額 | SE1: 02継続利用要介護者に係る第一号通所事業の実施に要した額 | SF1: 02継続利用要介護者に係る第一号生活支援事業の実施に要した額 | SG1: 02継続利用要介護者に係る第一号介護予防支援事業の実施に要した額 | SH1: 02事由⑧の該当性 | SI1: 02上限超過承認希望額（事由⑧） | SJ1: 02令和３年度における介護予防支援に係る保険給付に要する費用の額 | SK1: 02令和６年度における介護予防支援に係る保険給付に要する費用の額 | SL1: 02令和７年度の介護予防支援費変動率（（252行目/251行目）+1） | SM1: 02令和７年度の介護予防支援費変動率－75歳以上被保険者数変動率（253行目－250行目） | SN1: 02令和７年度における介護予防支援に係る保険給付に要した費用の額 | SO1: 02イ 令和７年度の当該市町村の被保険者に対する介護予防支援に係る保険給付に要する費用の額に令和７年度の介護予防支援費変動率から令和７年度の75歳以上被保険者数変動率を減じて得た数（当該数が０以下である場合は０とする。）を乗じて得た額（254行目×256行目） | SP1: 02ウ 令和７年度の原則の上限額に、本項に定める事由以外の上限額告示及び本通知に定める事由により増加する当該年度の介護予防・日常生活支援総合事業に要する費用の額を加えた額（192行目+217行目+234行目+244行目） | SQ1: 02事由⑥の該当性 | SR1: 02上限超過承認希望額（事由⑥） | SS1: 02事前の個別協議における上限超過承認額 | ST1: 02事後の個別協議における上限超過承認希望額の合計額 | SU1: 02事後の個別協議における上限超過承認希望額 | SV1: 02事後（または事前・事後両方）の個別協議を行う場合の政令で定める上限額 | SW1: 02（うち事前・事後の個別協議における上限超過承認希望額） | SX1: 02令和７年度実績に基づく政令で定める上限額 | SY1: 低減計画H30事業費 | SZ1: 低減計画H30上限超過額 | TA1: 低減計画R1事業費 | TB1: 低減計画R1上限超過額 | TC1: 低減計画R2事業費 | TD1: 低減計画R2上限超過額 | TE1: 低減計画R3事業費 | TF1: 低減計画R3上限超過額 | TG1: 低減計画R4事業費 | TH1: 低減計画R4上限超過額 | TI1: 低減計画R5事業費 | TJ1: 低減計画R5上限超過額 | TK1: 低減計画R6事業費 | TL1: 低減計画R6上限超過額 | TM1: 03①新たなプログラム | TN1: 03②75歳以上被保険者数変動率1以下 | TO1: 03③1万人未満 | TP1: 03④離島 | TQ1: 03⑤効果的な総合事業 | TR1: 03⑥災害 | TS1: 03⑦介護予防支援の増加率＞75歳以上被保険者数変動率 | TT1: 03⑧処遇改善 | TU1: 03⑨継続利用要介護者 | TV1: 031(1)新たなプログラムの類型 | TW1: 031(2)新たなプログラムの開始年度 | TX1: 031(3)新たなプログラムの開始３年度目の事業費（見込額） | TY1: 031(4)新たなプログラムの開始３年度目の翌年度の事業費（見込額） | TZ1: 031(5)開始２年度目の新たなプログラム等の実施に要する額が開始１年度目の当該額を上回る見込みの有無 | UA1: 03費用低減が見込まれる年度 | UB1: 03費用を低減させる方法 | UC1: 03前々年度認定率 | UD1: 03前々年度調整済み認定率 | UE1: 03前々々年度認定率 | UF1: 03前々年度サービス利用率 | UG1: 03前々々年度サービス利用率 | UH1: 03災害による居宅要支援被保険者等の数の増加有無（有の場合に○） | UI1: 03介護予防支援費変動率 | UJ1: 03介護職員等処遇改善加算等の支給に要した費用 | UK1: 03継続利用要介護者に係る第一号事業の実施に要した額 | UL1: 034(1)30事業費 | UM1: 034(1)30個別 | UN1: 034(1)30超過 | UO1: 034(1)１事業費 | UP1: 034(1)１個別 | UQ1: 034(1)１超過 | UR1: 034(1)2事業費 | US1: 034(1)2個別 | UT1: 034(1)2超過 | UU1: 034(1)3事業費 | UV1: 034(1)3個別 | UW1: 034(1)3超過 | UX1: 034(1)4事業費 | UY1: 034(1)4個別 | UZ1: 034(1)4超過 | VA1: 034(1)5事業費 | VB1: 034(1)5個別 | VC1: 034(1)5超過 | VD1: 034(1)6事業費 | VE1: 034(1)6個別 | VF1: 034(1)6超過 | VG1: 034(1)7事業費 | VH1: 034(1)7個別 | VI1: 034(1)7超過 | VJ1: 03(2)３年度目の翌年度には、介護予防・日常生活支援総合事業に要する費用が令和６年度の原則の上限額以下となるための方策（理由①のみ） | VK1: 03（1(5)が○の場合のみ）新たなプログラムを開始した日が１年度目の途中であること又は２年度目以降に新たなプログラムの実施対象地域の拡大を予定していること等の事情により、予め２年度目の新たなプログラム等の実施に要する額が１年度目の当該額を上回ることが見込まれる場合、上回る理由と上回る額 | VL1: 04通し番号1 | VM1: 04市町村名1 | VN1: 04適用する上限式1 | VO1: 04A1 | VP1: 04B1 | VQ1: 04C1 | VR1: 04D1 | VS1: 40 | VT1: 04F1 | VU1: 04G1 | VV1: 04H1 | VW1: 04I1 | VX1: 04J1 | VY1: 04(a)1 | VZ1: 04K1 | WA1: 04(b)1 | WB1: 04(a)、(b)のいずれか高い方の金額1 | WC1: 04上限式適否1 | WD1: 04通し番号2 | WE1: 04市町村名2 | WF1: 04適用する上限式2 | WG1: 04A2 | WH1: 04B2 | WI1: 04C2 | WJ1: 04D2 | WK1: 400 | WL1: 04F2 | WM1: 04G2 | WN1: 04H2 | WO1: 04I2 | WP1: 04J2 | WQ1: 04(a)2 | WR1: 04K2 | WS1: 04(b)2 | WT1: 04(a)、(b)のいずれか高い方の金額2 | WU1: 04上限式適否2 | WV1: 04通し番号3 | WW1: 04市町村名3 | WX1: 04適用する上限式3 | WY1: 04A3 | WZ1: 04B3 | XA1: 04C3 | XB1: 04D3 | XC1: 4000 | XD1: 04F3 | XE1: 04G3 | XF1: 04H3 | XG1: 04I3 | XH1: 04J3 | XI1: 04(a)3 | XJ1: 04K3 | XK1: 04(b)3 | XL1: 04(a)、(b)のいずれか高い方の金額3 | XM1: 04上限式適否3 | XN1: 04通し番号4 | XO1: 04市町村名4 | XP1: 04適用する上限式4 | XQ1: 04A4 | XR1: 04B4 | XS1: 04C4 | XT1: 04D4 | XU1: 40000 | XV1: 04F4 | XW1: 04G4 | XX1: 04H4 | XY1: 04I4 | XZ1: 04J4 | YA1: 04(a)4 | YB1: 04K4 | YC1: 04(b)4 | YD1: 04(a)、(b)のいずれか高い方の金額4 | YE1: 04上限式適否4 | YF1: 04通し番号5 | YG1: 04市町村名5 | YH1: 04適用する上限式5 | YI1: 04A5 | YJ1: 04B5 | YK1: 04C5 | YL1: 04D5 | YM1: 400000 | YN1: 04F5 | YO1: 04G5 | YP1: 04H5 | YQ1: 04I5 | YR1: 04J5 | YS1: 04(a)5 | YT1: 04K5 | YU1: 04(b)5 | YV1: 04(a)、(b)のいずれか高い方の金額5 | YW1: 04上限式適否5 | YX1: 04通し番号6 | YY1: 04市町村名6 | YZ1: 04適用する上限式6 | ZA1: 04A6 | ZB1: 04B6 | ZC1: 04C6 | ZD1: 04D6 | ZE1: 4000000 | ZF1: 04F6 | ZG1: 04G6 | ZH1: 04H6 | ZI1: 04I6 | ZJ1: 04J6 | ZK1: 04(a)6 | ZL1: 04K6 | ZM1: 04(b)6 | ZN1: 04(a)、(b)のいずれか高い方の金額6 | ZO1: 04上限式適否6 | ZP1: 04通し番号7 | ZQ1: 04市町村名7 | ZR1: 04適用する上限式7 | ZS1: 04A7 | ZT1: 04B7 | ZU1: 04C7 | ZV1: 04D7 | ZW1: 40000000 | ZX1: 04F7 | ZY1: 04G7 | ZZ1: 04H7 | AAA1: 04I7 | AAB1: 04J7 | AAC1: 04(a)7 | AAD1: 04K7 | AAE1: 04(b)7 | AAF1: 04(a)、(b)のいずれか高い方の金額7 | AAG1: 04上限式適否7 | AAH1: 04通し番号8 | AAI1: 04市町村名8 | AAJ1: 04適用する上限式8 | AAK1: 04A8 | AAL1: 04B8 | AAM1: 04C8 | AAN1: 04D8 | AAO1: 400000000 | AAP1: 04F8 | AAQ1: 04G8 | AAR1: 04H8 | AAS1: 04I8 | AAT1: 04J8 | AAU1: 04(a)8 | AAV1: 04K8 | AAW1: 04(b)8 | AAX1: 04(a)、(b)のいずれか高い方の金額8 | AAY1: 04上限式適否8 | AAZ1: 04通し番号9 | ABA1: 04市町村名9 | ABB1: 04適用する上限式9 | ABC1: 04A9 | ABD1: 04B9 | ABE1: 04C9 | ABF1: 04D9 | ABG1: 4000000000 | ABH1: 04F9 | ABI1: 04G9 | ABJ1: 04H9 | ABK1: 04I9 | ABL1: 04J9 | ABM1: 04(a)9 | ABN1: 04K9 | ABO1: 04(b)9 | ABP1: 04(a)、(b)のいずれか高い方の金額9 | ABQ1: 04上限式適否9 | ABR1: 04通し番号10 | ABS1: 04市町村名10 | ABT1: 04適用する上限式10 | ABU1: 04A10 | ABV1: 04B10 | ABW1: 04C10 | ABX1: 04D10 | ABY1: 40000000000 | ABZ1: 04F10 | ACA1: 04G10 | ACB1: 04H10 | ACC1: 04I10 | ACD1: 04J10 | ACE1: 04(a)10 | ACF1: 04K10 | ACG1: 04(b)10 | ACH1: 04(a)、(b)のいずれか高い方の金額10 | ACI1: 04上限式適否10 | ACJ1: 04通し番号11 | ACK1: 04市町村名11 | ACL1: 04適用する上限式11 | ACM1: 04A11 | ACN1: 04B11 | ACO1: 04C11 | ACP1: 04D11 | ACQ1: 400000000000 | ACR1: 04F11 | ACS1: 04G11 | ACT1: 04H11 | ACU1: 04I11 | ACV1: 04J11 | ACW1: 04(a)11 | ACX1: 04K11 | ACY1: 04(b)11 | ACZ1: 04(a)、(b)のいずれか高い方の金額11 | ADA1: 04上限式適否11 | ADB1: 04通し番号12 | ADC1: 04市町村名12 | ADD1: 04適用する上限式12 | ADE1: 04A12 | ADF1: 04B12 | ADG1: 04C12 | ADH1: 04D12 | ADI1: 4000000000000 | ADJ1: 04F12 | ADK1: 04G12 | ADL1: 04H12 | ADM1: 04I12 | ADN1: 04J12 | ADO1: 04(a)12 | ADP1: 04K12 | ADQ1: 04(b)12 | ADR1: 04(a)、(b)のいずれか高い方の金額12 | ADS1: 04上限式適否12 | ADT1: 04通し番号13 | ADU1: 04市町村名13 | ADV1: 04適用する上限式13 | ADW1: 04A13 | ADX1: 04B13 | ADY1: 04C13 | ADZ1: 04D13 | AEA1: 40000000000000 | AEB1: 04F13 | AEC1: 04G13 | AED1: 04H13 | AEE1: 04I13 | AEF1: 04J13 | AEG1: 04(a)13 | AEH1: 04K13 | AEI1: 04(b)13 | AEJ1: 04(a)、(b)のいずれか高い方の金額13 | AEK1: 04上限式適否13 | AEL1: 04通し番号14 | AEM1: 04市町村名14 | AEN1: 04適用する上限式14 | AEO1: 04A14 | AEP1: 04B14 | AEQ1: 04C14 | AER1: 04D14 | AES1: 400000000000000 | AET1: 04F14 | AEU1: 04G14 | AEV1: 04H14 | AEW1: 04I14 | AEX1: 04J14 | AEY1: 04(a)14 | AEZ1: 04K14 | AFA1: 04(b)14 | AFB1: 04(a)、(b)のいずれか高い方の金額14 | AFC1: 04上限式適否14 | AFD1: 04通し番号15 | AFE1: 04市町村名15 | AFF1: 04適用する上限式15 | AFG1: 04A15 | AFH1: 04B15 | AFI1: 04C15 | AFJ1: 04D15 | AFK1: 4e+15 | AFL1: 04F15 | AFM1: 04G15 | AFN1: 04H15 | AFO1: 04I15 | AFP1: 04J15 | AFQ1: 04(a)15 | AFR1: 04K15 | AFS1: 04(b)15 | AFT1: 04(a)、(b)のいずれか高い方の金額15 | AFU1: 04上限式適否15 | AFV1: 04通し番号16 | AFW1: 04市町村名16 | AFX1: 04適用する上限式16 | AFY1: 04A16 | AFZ1: 04B16 | AGA1: 04C16 | AGB1: 04D16 | AGC1: 4e+16 | AGD1: 04F16 | AGE1: 04G16 | AGF1: 04H16 | AGG1: 04I16 | AGH1: 04J16 | AGI1: 04(a)16 | AGJ1: 04K16 | AGK1: 04(b)16 | AGL1: 04(a)、(b)のいずれか高い方の金額16 | AGM1: 04上限式適否16 | AGN1: 04通し番号17 | AGO1: 04市町村名17 | AGP1: 04適用する上限式17 | AGQ1: 04A17 | AGR1: 04B17 | AGS1: 04C17 | AGT1: 04D17 | AGU1: 4e+17 | AGV1: 04F17 | AGW1: 04G17 | AGX1: 04H17 | AGY1: 04I17 | AGZ1: 04J17 | AHA1: 04(a)17 | AHB1: 04K17 | AHC1: 04(b)17 | AHD1: 04(a)、(b)のいずれか高い方の金額17 | AHE1: 04上限式適否17 | AHF1: 04通し番号18 | AHG1: 04市町村名18 | AHH1: 04適用する上限式18 | AHI1: 04A18 | AHJ1: 04B18 | AHK1: 04C18 | AHL1: 04D18 | AHM1: 4e+18 | AHN1: 04F18 | AHO1: 04G18 | AHP1: 04H18 | AHQ1: 04I18 | AHR1: 04J18 | AHS1: 04(a)18 | AHT1: 04K18 | AHU1: 04(b)18 | AHV1: 04(a)、(b)のいずれか高い方の金額18 | AHW1: 04上限式適否18 | AHX1: 04通し番号19 | AHY1: 04市町村名19 | AHZ1: 04適用する上限式19 | AIA1: 04A19 | AIB1: 04B19 | AIC1: 04C19 | AID1: 04D19 | AIE1: 4e+19 | AIF1: 04F19 | AIG1: 04G19 | AIH1: 04H19 | AII1: 04I19 | AIJ1: 04J19 | AIK1: 04(a)19 | AIL1: 04K19 | AIM1: 04(b)19 | AIN1: 04(a)、(b)のいずれか高い方の金額19 | AIO1: 04上限式適否19 | AIP1: 04通し番号20 | AIQ1: 04市町村名20 | AIR1: 04適用する上限式20 | AIS1: 04A20 | AIT1: 04B20 | AIU1: 04C20 | AIV1: 04D20 | AIW1: 4e+20 | AIX1: 04F20 | AIY1: 04G20 | AIZ1: 04H20 | AJA1: 04I20 | AJB1: 04J20 | AJC1: 04(a)20 | AJD1: 04K20 | AJE1: 04(b)20 | AJF1: 04(a)、(b)のいずれか高い方の金額20 | AJG1: 04上限式適否20 | AJH1: 04通し番号21 | AJI1: 04市町村名21 | AJJ1: 04適用する上限式21 | AJK1: 04A21 | AJL1: 04B21 | AJM1: 04C21 | AJN1: 04D21 | AJO1: 4e+21 | AJP1: 04F21 | AJQ1: 04G21 | AJR1: 04H21 | AJS1: 04I21 | AJT1: 04J21 | AJU1: 04(a)21 | AJV1: 04K21 | AJW1: 04(b)21 | AJX1: 04(a)、(b)のいずれか高い方の金額21 | AJY1: 04上限式適否21 | AJZ1: 04通し番号22 | AKA1: 04市町村名22 | AKB1: 04適用する上限式22 | AKC1: 04A22 | AKD1: 04B22 | AKE1: 04C22 | AKF1: 04D22 | AKG1: 4e+22 | AKH1: 04F22 | AKI1: 04G22 | AKJ1: 04H22 | AKK1: 04I22 | AKL1: 04J22 | AKM1: 04(a)22 | AKN1: 04K22 | AKO1: 04(b)22 | AKP1: 04(a)、(b)のいずれか高い方の金額22 | AKQ1: 04上限式適否22 | AKR1: 04通し番号23 | AKS1: 04市町村名23 | AKT1: 04適用する上限式23 | AKU1: 04A23 | AKV1: 04B23 | AKW1: 04C23 | AKX1: 04D23 | AKY1: 4e+23 | AKZ1: 04F23 | ALA1: 04G23 | ALB1: 04H23 | ALC1: 04I23 | ALD1: 04J23 | ALE1: 04(a)23 | ALF1: 04K23 | ALG1: 04(b)23 | ALH1: 04(a)、(b)のいずれか高い方の金額23 | ALI1: 04上限式適否23 | ALJ1: 04通し番号24 | ALK1: 04市町村名24 | ALL1: 04適用する上限式24 | ALM1: 04A24 | ALN1: 04B24 | ALO1: 04C24 | ALP1: 04D24 | ALQ1: 4e+24 | ALR1: 04F24 | ALS1: 04G24 | ALT1: 04H24 | ALU1: 04I24 | ALV1: 04J24 | ALW1: 04(a)24 | ALX1: 04K24 | ALY1: 04(b)24 | ALZ1: 04(a)、(b)のいずれか高い方の金額24 | AMA1: 04上限式適否24 | AMB1: 04通し番号25 | AMC1: 04市町村名25 | AMD1: 04適用する上限式25 | AME1: 04A25 | AMF1: 04B25 | AMG1: 04C25 | AMH1: 04D25 | AMI1: 4e+25 | AMJ1: 04F25 | AMK1: 04G25 | AML1: 04H25 | AMM1: 04I25 | AMN1: 04J25 | AMO1: 04(a)25 | AMP1: 04K25 | AMQ1: 04(b)25 | AMR1: 04(a)、(b)のいずれか高い方の金額25 | AMS1: 04上限式適否25 | AMT1: 04通し番号26 | AMU1: 04市町村名26 | AMV1: 04適用する上限式26 | AMW1: 04A26 | AMX1: 04B26 | AMY1: 04C26 | AMZ1: 04D26 | ANA1: 4e+26 | ANB1: 04F26 | ANC1: 04G26 | AND1: 04H26 | ANE1: 04I26 | ANF1: 04J26 | ANG1: 04(a)26 | ANH1: 04K26 | ANI1: 04(b)26 | ANJ1: 04(a)、(b)のいずれか高い方の金額26 | ANK1: 04上限式適否26 | ANL1: 04通し番号27 | ANM1: 04市町村名27 | ANN1: 04適用する上限式27 | ANO1: 04A27 | ANP1: 04B27 | ANQ1: 04C27 | ANR1: 04D27 | ANS1: 4e+27 | ANT1: 04F27 | ANU1: 04G27 | ANV1: 04H27 | ANW1: 04I27 | ANX1: 04J27 | ANY1: 04(a)27 | ANZ1: 04K27 | AOA1: 04(b)27 | AOB1: 04(a)、(b)のいずれか高い方の金額27 | AOC1: 04上限式適否27 | AOD1: 04通し番号28 | AOE1: 04市町村名28 | AOF1: 04適用する上限式28 | AOG1: 04A28 | AOH1: 04B28 | AOI1: 04C28 | AOJ1: 04D28 | AOK1: 4e+28 | AOL1: 04F28 | AOM1: 04G28 | AON1: 04H28 | AOO1: 04I28 | AOP1: 04J28 | AOQ1: 04(a)28 | AOR1: 04K28 | AOS1: 04(b)28 | AOT1: 04(a)、(b)のいずれか高い方の金額28 | AOU1: 04上限式適否28 | AOV1: 04通し番号29 | AOW1: 04市町村名29 | AOX1: 04適用する上限式29 | AOY1: 04A29 | AOZ1: 04B29 | APA1: 04C29 | APB1: 04D29 | APC1: 4e+29 | APD1: 04F29 | APE1: 04G29 | APF1: 04H29 | APG1: 04I29 | APH1: 04J29 | API1: 04(a)29 | APJ1: 04K29 | APK1: 04(b)29 | APL1: 04(a)、(b)のいずれか高い方の金額29 | APM1: 04上限式適否29 | APN1: 04通し番号30 | APO1: 04市町村名30 | APP1: 04適用する上限式30 | APQ1: 04A30 | APR1: 04B30 | APS1: 04C30 | APT1: 04D30 | APU1: 4e+30 | APV1: 04F30 | APW1: 04G30 | APX1: 04H30 | APY1: 04I30 | APZ1: 04J30 | AQA1: 04(a)30 | AQB1: 04K30 | AQC1: 04(b)30 | AQD1: 04(a)、(b)のいずれか高い方の金額30 | AQE1: 04上限式適否30 | AQF1: 04通し番号31 | AQG1: 04市町村名31 | AQH1: 04適用する上限式31 | AQI1: 04A31 | AQJ1: 04B31 | AQK1: 04C31 | AQL1: 04D31 | AQM1: 4e+31 | AQN1: 04F31 | AQO1: 04G31 | AQP1: 04H31 | AQQ1: 04I31 | AQR1: 04J31 | AQS1: 04(a)31 | AQT1: 04K31 | AQU1: 04(b)31 | AQV1: 04(a)、(b)のいずれか高い方の金額31 | AQW1: 04上限式適否31 | AQX1: 04通し番号32 | AQY1: 04市町村名32 | AQZ1: 04適用する上限式32 | ARA1: 04A32 | ARB1: 04B32 | ARC1: 04C32 | ARD1: 04D32 | ARE1: 4e+32 | ARF1: 04F32 | ARG1: 04G32 | ARH1: 04H32 | ARI1: 04I32 | ARJ1: 04J32 | ARK1: 04(a)32 | ARL1: 04K32 | ARM1: 04(b)32 | ARN1: 04(a)、(b)のいずれか高い方の金額32 | ARO1: 04上限式適否32 | ARP1: 04通し番号33 | ARQ1: 04市町村名33 | ARR1: 04適用する上限式33 | ARS1: 04A33 | ART1: 04B33 | ARU1: 04C33 | ARV1: 04D33 | ARW1: 4e+33 | ARX1: 04F33 | ARY1: 04G33 | ARZ1: 04H33 | ASA1: 04I33 | ASB1: 04J33 | ASC1: 04(a)33 | ASD1: 04K33 | ASE1: 04(b)33 | ASF1: 04(a)、(b)のいずれか高い方の金額33 | ASG1: 04上限式適否33 | ASH1: 04通し番号34 | ASI1: 04市町村名34 | ASJ1: 04適用する上限式34 | ASK1: 04A34 | ASL1: 04B34 | ASM1: 04C34 | ASN1: 04D34 | ASO1: 4e+34 | ASP1: 04F34 | ASQ1: 04G34 | ASR1: 04H34 | ASS1: 04I34 | AST1: 04J34 | ASU1: 04(a)34 | ASV1: 04K34 | ASW1: 04(b)34 | ASX1: 04(a)、(b)のいずれか高い方の金額34 | ASY1: 04上限式適否34 | ASZ1: 05①総事業費 | ATA1: 05②対象経費額（様式１B欄） | ATB1: 05③寄付金その他の収入額 | ATC1: 05④指定介護予防支援等にかかる収入額 | ATD1: 05⑤総合相談支援事業の一部委託にかかる委託費 | ATE1: 05⑥委託費を除いた総事業費 | ATF1: 05⑦様式１A欄 | ATG1: 05⑧様式１C欄 | ATH1: 05⑩様式１D欄 | ATI1: 05設置する地域包括支援センター数 | ATJ1: 06地域包括支援センター数 | ATK1: 06日常生活圏域数 | ATL1: 06専任の認知症地域支援推進員 | ATM1: 06第１層(市町村圏域）の数 | ATN1: 06行政区数 | ATO1: 06構成市町村数 | ATP1: 06（広域）専任の認知症地域支援推進員 | ATQ1: 06在宅医療・介護連携推進事業の実施 | ATR1: 06生活支援コーディネーター・協議体の実施 | ATS1: 06相談支援連携体制構築事業の実施 | ATT1: 06住民参画・官民連携推進事業の実施 | ATU1: 06就労的活動支援コーディネーターの実施 | ATV1: 06認知症初期集中支援事業の実施 | ATW1: 06認知症地域支援・ケア向上事業の実施 | ATX1: 06認知症サポーター活動促進・地域づくり推進事業の実施 | ATY1: 06地域ケア会議推進事業の実施 | ATZ1: 06居住支援連携の実施 | AUA1: 06標準額 | AUB1: 06個別協議額 | AUC1: 06在宅医療・介護連携推進事業標準額 | AUD1: 06生活支援コーディネーター・協議体標準額 | AUE1: 06相談支援連携体制構築事業標準額 | AUF1: 06住民参画・官民連携推進事業標準額 | AUG1: 06就労的活動支援コーディネーター標準額 | AUH1: 06認知症初期集中支援事業標準額 | AUI1: 06認知症地域支援・ケア向上事業標準額 | AUJ1: 06認知症サポーター活動促進・地域づくり推進事業標準額 | AUK1: 06地域ケア会議推進事業標準額 | AUL1: 06（再掲）居住支援加算標準額 | AUM1: 06【令和６年度包括的支援事業（社会保障充実分）上限額設定】 | AUN1: 06エラー | AUO1: 06-1（一般市町村）SCをセンターに配置 | AUP1: 06-1（指定都市）実施行政区数 | AUQ1: 06-1（指定都市）うちSCをセンターに配置している数 | AUR1: 06-1（広域）実施構成市町村数 | AUS1: 06-1（広域）うちSCをセンターに配置している数 | AUT1: 06-1（広域）うち重層実施数 | AUU1: 06-2（指定都市）連携体制構築されている行政区数 | AUV1: 06-2（広域）連携体制構築されている構成市町村数 | AUW1: 07社会保障充実分対象経費額 | AUX1: 07標準額 | AUY1: 07①在宅医療・介護連携推進対象経費額 | AUZ1: 07①ア（イ）等の会議 | AVA1: 07①イ（ア）の相談窓口 | AVB1: 07①イ（ア）のコーディネーター | AVC1: 07①イ（ウ）②多職種研修 | AVD1: 07①イ（ウ）②その他の研修 | AVE1: 07②生活支援体制整備対象経費額 | AVF1: 07②第１層生活支援コーディネーター | AVG1: 07②第２層生活支援コーディネーター | AVH1: 07②住民参画・官民連携推進事業 | AVI1: 07②生活支援コーディネーターを中心とした相談支援連携体制構築事業 | AVJ1: 07②就労的活動支援コーディネーター | AVK1: 07③認知症総合支援対象経費額 | AVL1: 07③認知症初期集中支援チーム設置 | AVM1: 07③認知症地域支援推進員設置 | AVN1: 07③うち専任の認知症地域支援推進員 | AVO1: 07③チームオレンジコーディネーター | AVP1: 07④地域ケア会議推進事業対象経費額 | AVQ1: 07④地域ケア個別会議 | AVR1: 07④居住支援連携 | AVS1: 08①対象経費額 | AVT1: 08①事業内容 | AVU1: 08①効果 | AVV1: 08②対象経費額 | AVW1: 08②事業内容 | AVX1: 08②効果 | AVY1: 08③対象経費額 | AVZ1: 08③事業内容 | AWA1: 08③効果 | AWB1: 08④対象経費額 | AWC1: 08④事業内容 | AWD1: 08④効果 | AWE1: 08⑤対象経費額 | AWF1: 08⑤事業内容 | AWG1: 08⑤効果 | AWH1: 08⑥対象経費額 | AWI1: 08⑥事業内容 | AWJ1: 08⑥効果 | AWK1: 08⑦対象経費額 | AWL1: 08⑦事業内容 | AWM1: 08⑦効果 | AWN1: 08⑧対象経費額 | AWO1: 08⑧事業内容 | AWP1: 08⑧効果 | AWQ1: 08⑨対象経費額 | AWR1: 08⑨事業内容 | AWS1: 08⑨効果 | AWT1: 08⑩対象経費額 | AWU1: 08⑩事業内容 | AWV1: 08⑩効果 | AWW1: 08⑪対象経費額 | AWX1: 08⑪事業内容 | AWY1: 08⑪効果 | AWZ1: 08⑫対象経費額 | AXA1: 08⑫事業内容 | AXB1: 08⑫効果 | AXC1: 08⑬対象経費額 | AXD1: 08⑬事業内容 | AXE1: 08⑬効果 | AXF1: 08⑭対象経費額 | AXG1: 08⑭事業内容 | AXH1: 08⑭効果 | AXI1: 08⑮対象経費額 | AXJ1: 08⑮事業内容 | AXK1: 08⑮効果 | AXL1: 08⑯対象経費額 | AXM1: 08⑯事業内容 | AXN1: 08⑯効果 | AXO1: 08⑰対象経費額 | AXP1: 08⑰事業内容 | AXQ1: 08⑰効果 | AXR1: 08⑱対象経費額 | AXS1: 08⑱事業内容 | AXT1: 08⑱効果 | AXU1: 08⑲対象経費額 | AXV1: 08⑲事業内容 | AXW1: 08⑲効果 | AXX1: 08⑳対象経費額 | AXY1: 08⑳事業内容 | AXZ1: 08⑳効果 | AYA1: 08㉑対象経費額 | AYB1: 08㉑事業内容 | AYC1: 08㉑効果 | AYD1: 08事業名（特区等） | AYE1: 08対象経費額（特区等） | AYF1: 08事業内容（特区等） | AYG1: 08効果（特区等） | AYH1: 08合計 | AYI1: 保険者No | AYJ1: 市町村 | AYK1: 有 | AYL1: (1)R2対象経費支出予定額 | AYM1: (1)R3対象経費支出予定額 | AYN1: (1)R4対象経費支出予定額 | AYO1: (1)R5対象経費支出予定額 | AYP1: (1)R6対象経費支出予定額 | AYQ1: (2)交付上限額 | AYR1: (3)やむを得ない事情の場合の交付上限額 | AYS1: (4)①下方変動 | AYT1: (4)①上方変動 | AYU1: (4)①その他 | AYV1: (4)②その他の内容 | AYW1: 介護用品上限 | AYX1: (5)合計人数 | AYY1: (5)人数（地域支援事業） | AYZ1: (5)人数（市町村特別給付） | AZA1: (5)人数（保健福祉事業） | AZB1: (5)人数（一般財源） | AZC1: (5)合計額 | AZD1: (5)支出予定額（地域支援事業） | AZE1: (5)支出予定額（市町村特別給付） | AZF1: (5)支出予定額（保健福祉事業） | AZG1: (5)支出予定額（一般財源） | AZH1: （６）①支給予定人数計 | AZI1: (6)①第１～３段階（要介護５） | AZJ1: (6)①第４段階（要介護５） | AZK1: (6)①第５段階（要介護５） | AZL1: (6)①第１～３段階（要介護４） | AZM1: (6)①第４段階（要介護４） | AZN1: (6)①第５段階（要介護４） | AZO1: (6)①第１～３段階（要介護３） | AZP1: (6)①第４段階（要介護３） | AZQ1: (6)①第５段階（要介護３） | AZR1: (6)①第１～３段階（要介護１～２） | AZS1: (6)①第４段階（要介護１～２） | AZT1: (6)①第５段階（要介護１～２） | AZU1: (6)①第１～３段階（要支援１～２） | AZV1: (6)①第４段階（要支援１～２） | AZW1: (6)①第５段階（要支援１～２） | AZX1: (6)①第１～３段階（事業対象者） | AZY1: (6)①第４段階（事業対象者） | AZZ1: (6)①第５段階（事業対象者） | BAA1: (6)②一人当たり支給上限額 | BAB1: (6)②詳細 | BAC1: (6)③交付希望額 | BAD1: R6廃止・縮小 | BAE1: R6具体的な取組（縮小） | BAF1: R6廃止後の移行先等 | BAG1: R7廃止・縮小 | BAH1: R7具体的な取組（縮小） | BAI1: R7廃止後の移行先等 | BAJ1: R8廃止・縮小 | BAK1: R8具体的な取組（縮小） | BAL1: R8廃止後の移行先等 | BAM1: （介護用品）任意事業計画書に転記する額 | BAN1: 介護用品上限額 | BAO1: 介護用品やむを得ない場合の上限額 | BAP1: 別紙様式４番号 | BAQ1: 別紙様式２日付 | BAR1: 別紙様式２職氏名
A2: =#REF! -> #REF! | B2: =#REF! -> #REF! | C2: =#REF! -> #REF! | D2: =#REF! -> #REF! | E2: =#REF! -> #REF! | F2: =#REF! -> #REF! | G2: =#REF! -> #REF! | H2: =#REF! -> #REF! | ... VK2: =#REF! -> #REF! | VL2: ='（参考）包括・任意事業の上限額算定の手引き'!$E5 | VM2: ='（参考）包括・任意事業の上限額算定の手引き'!$E6 | VN2: ='（参考）包括・任意事業の上限額算定の手引き'!$E7 -> ①原則の上限額 | VO2: ='（参考）包括・任意事業の上限額算定の手引き'!$E10 -> 24076130 | VP2: ='（参考）包括・任意事業の上限額算定の手引き'!$E11 -> 3464 | VQ2: ='（参考）包括・任意事業の上限額算定の手引き'!$E12 -> 3497 | VR2: ='（参考）包括・任意事業の上限額算定の手引き'!$E13 -> 1.0032 | VS2: ='（参考）包括・任意事業の上限額算定の手引き'!$E14 -> 24153173 | VT2: ='（参考）包括・任意事業の上限額算定の手引き'!$E17 -> 3497 | VU2: ='（参考）包括・任意事業の上限額算定の手引き'!$E18 -> 19427777 | VV2: ='（参考）包括・任意事業の上限額算定の手引き'!$E19 -> 3252210 | VW2: ='（参考）包括・任意事業の上限額算定の手引き'!$E20 -> 22679987 | VX2: ='（参考）包括・任意事業の上限額算定の手引き'!$E25 -> #REF! | VY2: ='（参考）包括・任意事業の上限額算定の手引き'!$E26 -> 3252210 | VZ2: ='（参考）包括・任意事業の上限額算定の手引き'!$E27 -> 0 | WA2: ='（参考）包括・任意事業の上限額算定の手引き'!$E28 -> 0 | WB2: ='（参考）包括・任意事業の上限額算定の手引き'!$E29 -> 3252210 | WC2: ='（参考）包括・任意事業の上限額算定の手引き'!$E30 -> #REF! | WD2: ='（参考）包括・任意事業の上限額算定の手引き'!$G5 | WE2: ='（参考）包括・任意事業の上限額算定の手引き'!$G6 | WF2: ='（参考）包括・任意事業の上限額算定の手引き'!$G7 -> 0 | WG2: ='（参考）包括・任意事業の上限額算定の手引き'!$G10 -> 0 | WH2: ='（参考）包括・任意事業の上限額算定の手引き'!$G11 -> 0 | WI2: ='（参考）包括・任意事業の上限額算定の手引き'!$G12 -> 0 | WJ2: ='（参考）包括・任意事業の上限額算定の手引き'!$G13 | WK2: ='（参考）包括・任意事業の上限額算定の手引き'!$G14 -> 0 | WL2: ='（参考）包括・任意事業の上限額算定の手引き'!$G17 -> 0 | WM2: ='（参考）包括・任意事業の上限額算定の手引き'!$G18 -> 0 | WN2: ='（参考）包括・任意事業の上限額算定の手引き'!$G19 -> 0 | WO2: ='（参考）包括・任意事業の上限額算定の手引き'!$G20 -> 0 | WP2: ='（参考）包括・任意事業の上限額算定の手引き'!$G25 -> 0 | WQ2: ='（参考）包括・任意事業の上限額算定の手引き'!$G26 -> 0 | WR2: ='（参考）包括・任意事業の上限額算定の手引き'!$G27 -> 0 | WS2: ='（参考）包括・任意事業の上限額算定の手引き'!$G28 -> 0 | WT2: ='（参考）包括・任意事業の上限額算定の手引き'!$G29 -> 0 | WU2: ='（参考）包括・任意事業の上限額算定の手引き'!$G30 -> × | WV2: ='（参考）包括・任意事業の上限額算定の手引き'!$I5 | WW2: ='（参考）包括・任意事業の上限額算定の手引き'!$I6 | WX2: ='（参考）包括・任意事業の上限額算定の手引き'!$I7 -> 0 | WY2: ='（参考）包括・任意事業の上限額算定の手引き'!$I10 -> 0 | WZ2: ='（参考）包括・任意事業の上限額算定の手引き'!$I11 -> 0 | XA2: ='（参考）包括・任意事業の上限額算定の手引き'!$I12 -> 0 | XB2: ='（参考）包括・任意事業の上限額算定の手引き'!$I13 | XC2: ='（参考）包括・任意事業の上限額算定の手引き'!$I14 -> 0 | XD2: ='（参考）包括・任意事業の上限額算定の手引き'!$I17 -> 0 | XE2: ='（参考）包括・任意事業の上限額算定の手引き'!$I18 -> 0 | XF2: ='（参考）包括・任意事業の上限額算定の手引き'!$I19 -> 0 | XG2: ='（参考）包括・任意事業の上限額算定の手引き'!$I20 -> 0 | XH2: ='（参考）包括・任意事業の上限額算定の手引き'!$I25 -> 0 | XI2: ='（参考）包括・任意事業の上限額算定の手引き'!$I26 -> 0 | XJ2: ='（参考）包括・任意事業の上限額算定の手引き'!$I27 -> 0 | XK2: ='（参考）包括・任意事業の上限額算定の手引き'!$I28 -> 0 | XL2: ='（参考）包括・任意事業の上限額算定の手引き'!$I29 -> 0 | XM2: ='（参考）包括・任意事業の上限額算定の手引き'!$I30 -> × | XN2: ='（参考）包括・任意事業の上限額算定の手引き'!$K5 | XO2: ='（参考）包括・任意事業の上限額算定の手引き'!$K6 | XP2: ='（参考）包括・任意事業の上限額算定の手引き'!$K7 -> 0 | XQ2: ='（参考）包括・任意事業の上限額算定の手引き'!$K10 -> 0 | XR2: ='（参考）包括・任意事業の上限額算定の手引き'!$K11 -> 0 | XS2: ='（参考）包括・任意事業の上限額算定の手引き'!$K12 -> 0 | XT2: ='（参考）包括・任意事業の上限額算定の手引き'!$K13 | XU2: ='（参考）包括・任意事業の上限額算定の手引き'!$K14 -> 0 | XV2: ='（参考）包括・任意事業の上限額算定の手引き'!$K17 -> 0 | XW2: ='（参考）包括・任意事業の上限額算定の手引き'!$K18 -> 0 | XX2: ='（参考）包括・任意事業の上限額算定の手引き'!$K19 -> 0 | XY2: ='（参考）包括・任意事業の上限額算定の手引き'!$K20 -> 0 | XZ2: ='（参考）包括・任意事業の上限額算定の手引き'!$K25 -> 0 | YA2: ='（参考）包括・任意事業の上限額算定の手引き'!$K26 -> 0 | YB2: ='（参考）包括・任意事業の上限額算定の手引き'!$K27 -> 0 | YC2: ='（参考）包括・任意事業の上限額算定の手引き'!$K28 -> 0 | YD2: ='（参考）包括・任意事業の上限額算定の手引き'!$K29 -> 0 | YE2: ='（参考）包括・任意事業の上限額算定の手引き'!$K30 -> × | YF2: ='（参考）包括・任意事業の上限額算定の手引き'!$M5 | YG2: ='（参考）包括・任意事業の上限額算定の手引き'!$M6 | YH2: ='（参考）包括・任意事業の上限額算定の手引き'!$M7 -> 0 | YI2: ='（参考）包括・任意事業の上限額算定の手引き'!$M10 -> 0 | YJ2: ='（参考）包括・任意事業の上限額算定の手引き'!$M11 -> 0 | YK2: ='（参考）包括・任意事業の上限額算定の手引き'!$M12 -> 0 | YL2: ='（参考）包括・任意事業の上限額算定の手引き'!$M13 | YM2: ='（参考）包括・任意事業の上限額算定の手引き'!$M14 -> 0 | YN2: ='（参考）包括・任意事業の上限額算定の手引き'!$M17 -> 0 | YO2: ='（参考）包括・任意事業の上限額算定の手引き'!$M18 -> 0 | YP2: ='（参考）包括・任意事業の上限額算定の手引き'!$M19 -> 0 | YQ2: ='（参考）包括・任意事業の上限額算定の手引き'!$M20 -> 0 | YR2: ='（参考）包括・任意事業の上限額算定の手引き'!$M25 -> 0 | YS2: ='（参考）包括・任意事業の上限額算定の手引き'!$M26 -> 0 | YT2: ='（参考）包括・任意事業の上限額算定の手引き'!$M27 -> 0 | YU2: ='（参考）包括・任意事業の上限額算定の手引き'!$M28 -> 0 | YV2: ='（参考）包括・任意事業の上限額算定の手引き'!$M29 -> 0 | YW2: ='（参考）包括・任意事業の上限額算定の手引き'!$M30 -> × | YX2: ='（参考）包括・任意事業の上限額算定の手引き'!$O5 | YY2: ='（参考）包括・任意事業の上限額算定の手引き'!$O6 | YZ2: ='（参考）包括・任意事業の上限額算定の手引き'!$O7 -> 0 | ZA2: ='（参考）包括・任意事業の上限額算定の手引き'!$O10 -> 0 | ZB2: ='（参考）包括・任意事業の上限額算定の手引き'!$O11 -> 0 | ZC2: ='（参考）包括・任意事業の上限額算定の手引き'!$O12 -> 0 | ZD2: ='（参考）包括・任意事業の上限額算定の手引き'!$O13 | ZE2: ='（参考）包括・任意事業の上限額算定の手引き'!$O14 -> 0 | ZF2: ='（参考）包括・任意事業の上限額算定の手引き'!$O17 -> 0 | ZG2: ='（参考）包括・任意事業の上限額算定の手引き'!$O18 -> 0 | ZH2: ='（参考）包括・任意事業の上限額算定の手引き'!$O19 -> 0 | ZI2: ='（参考）包括・任意事業の上限額算定の手引き'!$O20 -> 0 | ZJ2: ='（参考）包括・任意事業の上限額算定の手引き'!$O25 -> 0 | ZK2: ='（参考）包括・任意事業の上限額算定の手引き'!$O26 -> 0 | ZL2: ='（参考）包括・任意事業の上限額算定の手引き'!$O27 -> 0 | ZM2: ='（参考）包括・任意事業の上限額算定の手引き'!$O28 -> 0 | ZN2: ='（参考）包括・任意事業の上限額算定の手引き'!$O29 -> 0 | ZO2: ='（参考）包括・任意事業の上限額算定の手引き'!$O30 -> × | ZP2: ='（参考）包括・任意事業の上限額算定の手引き'!$Q5 | ZQ2: ='（参考）包括・任意事業の上限額算定の手引き'!$Q6 | ZR2: ='（参考）包括・任意事業の上限額算定の手引き'!$Q7 -> 0 | ZS2: ='（参考）包括・任意事業の上限額算定の手引き'!$Q10 -> 0 | ZT2: ='（参考）包括・任意事業の上限額算定の手引き'!$Q11 -> 0 | ZU2: ='（参考）包括・任意事業の上限額算定の手引き'!$Q12 -> 0 | ZV2: ='（参考）包括・任意事業の上限額算定の手引き'!$Q13 | ZW2: ='（参考）包括・任意事業の上限額算定の手引き'!$Q14 -> 0 | ZX2: ='（参考）包括・任意事業の上限額算定の手引き'!$Q17 -> 0 | ZY2: ='（参考）包括・任意事業の上限額算定の手引き'!$Q18 -> 0 | ZZ2: ='（参考）包括・任意事業の上限額算定の手引き'!$Q19 -> 0 | AAA2: ='（参考）包括・任意事業の上限額算定の手引き'!$Q20 -> 0 | AAB2: ='（参考）包括・任意事業の上限額算定の手引き'!$Q25 -> 0 | AAC2: ='（参考）包括・任意事業の上限額算定の手引き'!$Q26 -> 0 | AAD2: ='（参考）包括・任意事業の上限額算定の手引き'!$Q27 -> 0 | AAE2: ='（参考）包括・任意事業の上限額算定の手引き'!$Q28 -> 0 | AAF2: ='（参考）包括・任意事業の上限額算定の手引き'!$Q29 -> 0 | AAG2: ='（参考）包括・任意事業の上限額算定の手引き'!$Q30 -> × | AAH2: ='（参考）包括・任意事業の上限額算定の手引き'!$S5 | AAI2: ='（参考）包括・任意事業の上限額算定の手引き'!$S6 | AAJ2: ='（参考）包括・任意事業の上限額算定の手引き'!$S7 -> 0 | AAK2: ='（参考）包括・任意事業の上限額算定の手引き'!$S10 -> 0 | AAL2: ='（参考）包括・任意事業の上限額算定の手引き'!$S11 -> 0 | AAM2: ='（参考）包括・任意事業の上限額算定の手引き'!$S12 -> 0 | AAN2: ='（参考）包括・任意事業の上限額算定の手引き'!$S13 | AAO2: ='（参考）包括・任意事業の上限額算定の手引き'!$S14 -> 0 | AAP2: ='（参考）包括・任意事業の上限額算定の手引き'!$S17 -> 0 | AAQ2: ='（参考）包括・任意事業の上限額算定の手引き'!$S18 -> 0 | AAR2: ='（参考）包括・任意事業の上限額算定の手引き'!$S19 -> 0 | AAS2: ='（参考）包括・任意事業の上限額算定の手引き'!$S20 -> 0 | AAT2: ='（参考）包括・任意事業の上限額算定の手引き'!$S25 -> 0 | AAU2: ='（参考）包括・任意事業の上限額算定の手引き'!$S26 -> 0 | AAV2: ='（参考）包括・任意事業の上限額算定の手引き'!$S27 -> 0 | AAW2: ='（参考）包括・任意事業の上限額算定の手引き'!$S28 -> 0 | AAX2: ='（参考）包括・任意事業の上限額算定の手引き'!$S29 -> 0 | AAY2: ='（参考）包括・任意事業の上限額算定の手引き'!$S30 -> × | AAZ2: ='（参考）包括・任意事業の上限額算定の手引き'!$U5 | ABA2: ='（参考）包括・任意事業の上限額算定の手引き'!$U6 | ABB2: ='（参考）包括・任意事業の上限額算定の手引き'!$U7 -> 0 | ABC2: ='（参考）包括・任意事業の上限額算定の手引き'!$U10 -> 0 | ABD2: ='（参考）包括・任意事業の上限額算定の手引き'!$U11 -> 0 | ABE2: ='（参考）包括・任意事業の上限額算定の手引き'!$U12 -> 0 | ABF2: ='（参考）包括・任意事業の上限額算定の手引き'!$U13 | ABG2: ='（参考）包括・任意事業の上限額算定の手引き'!$U14 -> 0 | ABH2: ='（参考）包括・任意事業の上限額算定の手引き'!$U17 -> 0 | ABI2: ='（参考）包括・任意事業の上限額算定の手引き'!$U18 -> 0 | ABJ2: ='（参考）包括・任意事業の上限額算定の手引き'!$U19 -> 0 | ABK2: ='（参考）包括・任意事業の上限額算定の手引き'!$U20 -> 0 | ABL2: ='（参考）包括・任意事業の上限額算定の手引き'!$U25 -> 0 | ABM2: ='（参考）包括・任意事業の上限額算定の手引き'!$U26 -> 0 | ABN2: ='（参考）包括・任意事業の上限額算定の手引き'!$U27 -> 0 | ABO2: ='（参考）包括・任意事業の上限額算定の手引き'!$U28 -> 0 | ABP2: ='（参考）包括・任意事業の上限額算定の手引き'!$U29 -> 0 | ABQ2: ='（参考）包括・任意事業の上限額算定の手引き'!$U30 -> × | ABR2: ='（参考）包括・任意事業の上限額算定の手引き'!$W5 | ABS2: ='（参考）包括・任意事業の上限額算定の手引き'!$W6 | ABT2: ='（参考）包括・任意事業の上限額算定の手引き'!$W7 -> 0 | ABU2: ='（参考）包括・任意事業の上限額算定の手引き'!$W10 -> 0 | ABV2: ='（参考）包括・任意事業の上限額算定の手引き'!$W11 -> 0 | ABW2: ='（参考）包括・任意事業の上限額算定の手引き'!$W12 -> 0 | ABX2: ='（参考）包括・任意事業の上限額算定の手引き'!$W13 | ABY2: ='（参考）包括・任意事業の上限額算定の手引き'!$W14 -> 0 | ABZ2: ='（参考）包括・任意事業の上限額算定の手引き'!$W17 -> 0 | ACA2: ='（参考）包括・任意事業の上限額算定の手引き'!$W18 -> 0 | ACB2: ='（参考）包括・任意事業の上限額算定の手引き'!$W19 -> 0 | ACC2: ='（参考）包括・任意事業の上限額算定の手引き'!$W20 -> 0 | ACD2: ='（参考）包括・任意事業の上限額算定の手引き'!$W25 -> 0 | ACE2: ='（参考）包括・任意事業の上限額算定の手引き'!$W26 -> 0 | ACF2: ='（参考）包括・任意事業の上限額算定の手引き'!$W27 -> 0 | ACG2: ='（参考）包括・任意事業の上限額算定の手引き'!$W28 -> 0 | ACH2: ='（参考）包括・任意事業の上限額算定の手引き'!$W29 -> 0 | ACI2: ='（参考）包括・任意事業の上限額算定の手引き'!$W30 -> × | ACJ2: ='（参考）包括・任意事業の上限額算定の手引き'!$Y5 | ACK2: ='（参考）包括・任意事業の上限額算定の手引き'!$Y6 | ACL2: ='（参考）包括・任意事業の上限額算定の手引き'!$Y7 -> 0 | ACM2: ='（参考）包括・任意事業の上限額算定の手引き'!$Y10 -> 0 | ACN2: ='（参考）包括・任意事業の上限額算定の手引き'!$Y11 -> 0 | ACO2: ='（参考）包括・任意事業の上限額算定の手引き'!$Y12 -> 0 | ACP2: ='（参考）包括・任意事業の上限額算定の手引き'!$Y13 | ACQ2: ='（参考）包括・任意事業の上限額算定の手引き'!$Y14 -> 0 | ACR2: ='（参考）包括・任意事業の上限額算定の手引き'!$Y17 -> 0 | ACS2: ='（参考）包括・任意事業の上限額算定の手引き'!$Y18 -> 0 | ACT2: ='（参考）包括・任意事業の上限額算定の手引き'!$Y19 -> 0 | ACU2: ='（参考）包括・任意事業の上限額算定の手引き'!$Y20 -> 0 | ACV2: ='（参考）包括・任意事業の上限額算定の手引き'!$Y25 -> 0 | ACW2: ='（参考）包括・任意事業の上限額算定の手引き'!$Y26 -> 0 | ACX2: ='（参考）包括・任意事業の上限額算定の手引き'!$Y27 -> 0 | ACY2: ='（参考）包括・任意事業の上限額算定の手引き'!$Y28 -> 0 | ACZ2: ='（参考）包括・任意事業の上限額算定の手引き'!$Y29 -> 0 | ADA2: ='（参考）包括・任意事業の上限額算定の手引き'!$Y30 -> × | ADB2: ='（参考）包括・任意事業の上限額算定の手引き'!$AA5 | ADC2: ='（参考）包括・任意事業の上限額算定の手引き'!$AA6 | ADD2: ='（参考）包括・任意事業の上限額算定の手引き'!$AA7 -> 0 | ADE2: ='（参考）包括・任意事業の上限額算定の手引き'!$AA10 -> 0 | ADF2: ='（参考）包括・任意事業の上限額算定の手引き'!$AA11 -> 0 | ADG2: ='（参考）包括・任意事業の上限額算定の手引き'!$AA12 -> 0 | ADH2: ='（参考）包括・任意事業の上限額算定の手引き'!$AA13 | ADI2: ='（参考）包括・任意事業の上限額算定の手引き'!$AA14 -> 0 | ADJ2: ='（参考）包括・任意事業の上限額算定の手引き'!$AA17 -> 0 | ADK2: ='（参考）包括・任意事業の上限額算定の手引き'!$AA18 -> 0 | ADL2: ='（参考）包括・任意事業の上限額算定の手引き'!$AA19 -> 0 | ADM2: ='（参考）包括・任意事業の上限額算定の手引き'!$AA20 -> 0 | ADN2: ='（参考）包括・任意事業の上限額算定の手引き'!$AA25 -> 0 | ADO2: ='（参考）包括・任意事業の上限額算定の手引き'!$AA26 -> 0 | ADP2: ='（参考）包括・任意事業の上限額算定の手引き'!$AA27 -> 0 | ADQ2: ='（参考）包括・任意事業の上限額算定の手引き'!$AA28 -> 0 | ADR2: ='（参考）包括・任意事業の上限額算定の手引き'!$AA29 -> 0 | ADS2: ='（参考）包括・任意事業の上限額算定の手引き'!$AA30 -> × | ADT2: ='（参考）包括・任意事業の上限額算定の手引き'!$AC5 | ADU2: ='（参考）包括・任意事業の上限額算定の手引き'!$AC6 | ADV2: ='（参考）包括・任意事業の上限額算定の手引き'!$AC7 -> 0 | ADW2: ='（参考）包括・任意事業の上限額算定の手引き'!$AC10 -> 0 | ADX2: ='（参考）包括・任意事業の上限額算定の手引き'!$AC11 -> 0 | ADY2: ='（参考）包括・任意事業の上限額算定の手引き'!$AC12 -> 0 | ADZ2: ='（参考）包括・任意事業の上限額算定の手引き'!$AC13 | AEA2: ='（参考）包括・任意事業の上限額算定の手引き'!$AC14 -> 0 | AEB2: ='（参考）包括・任意事業の上限額算定の手引き'!$AC17 -> 0 | AEC2: ='（参考）包括・任意事業の上限額算定の手引き'!$AC18 -> 0 | AED2: ='（参考）包括・任意事業の上限額算定の手引き'!$AC19 -> 0 | AEE2: ='（参考）包括・任意事業の上限額算定の手引き'!$AC20 -> 0 | AEF2: ='（参考）包括・任意事業の上限額算定の手引き'!$AC25 -> 0 | AEG2: ='（参考）包括・任意事業の上限額算定の手引き'!$AC26 -> 0 | AEH2: ='（参考）包括・任意事業の上限額算定の手引き'!$AC27 -> 0 | AEI2: ='（参考）包括・任意事業の上限額算定の手引き'!$AC28 -> 0 | AEJ2: ='（参考）包括・任意事業の上限額算定の手引き'!$AC29 -> 0 | AEK2: ='（参考）包括・任意事業の上限額算定の手引き'!$AC30 -> × | AEL2: ='（参考）包括・任意事業の上限額算定の手引き'!$AE5 | AEM2: ='（参考）包括・任意事業の上限額算定の手引き'!$AE6 | AEN2: ='（参考）包括・任意事業の上限額算定の手引き'!$AE7 -> 0 | AEO2: ='（参考）包括・任意事業の上限額算定の手引き'!$AE10 -> 0 | AEP2: ='（参考）包括・任意事業の上限額算定の手引き'!$AE11 -> 0 | AEQ2: ='（参考）包括・任意事業の上限額算定の手引き'!$AE12 -> 0 | AER2: ='（参考）包括・任意事業の上限額算定の手引き'!$AE13 | AES2: ='（参考）包括・任意事業の上限額算定の手引き'!$AE14 -> 0 | AET2: ='（参考）包括・任意事業の上限額算定の手引き'!$AE17 -> 0 | AEU2: ='（参考）包括・任意事業の上限額算定の手引き'!$AE18 -> 0 | AEV2: ='（参考）包括・任意事業の上限額算定の手引き'!$AE19 -> 0 | AEW2: ='（参考）包括・任意事業の上限額算定の手引き'!$AE20 -> 0 | AEX2: ='（参考）包括・任意事業の上限額算定の手引き'!$AE25 -> 0 | AEY2: ='（参考）包括・任意事業の上限額算定の手引き'!$AE26 -> 0 | AEZ2: ='（参考）包括・任意事業の上限額算定の手引き'!$AE27 -> 0 | AFA2: ='（参考）包括・任意事業の上限額算定の手引き'!$AE28 -> 0 | AFB2: ='（参考）包括・任意事業の上限額算定の手引き'!$AE29 -> 0 | AFC2: ='（参考）包括・任意事業の上限額算定の手引き'!$AE30 -> × | AFD2: ='（参考）包括・任意事業の上限額算定の手引き'!$AG5 | AFE2: ='（参考）包括・任意事業の上限額算定の手引き'!$AG6 | AFF2: ='（参考）包括・任意事業の上限額算定の手引き'!$AG7 -> 0 | AFG2: ='（参考）包括・任意事業の上限額算定の手引き'!$AG10 -> 0 | AFH2: ='（参考）包括・任意事業の上限額算定の手引き'!$AG11 -> 0 | AFI2: ='（参考）包括・任意事業の上限額算定の手引き'!$AG12 -> 0 | AFJ2: ='（参考）包括・任意事業の上限額算定の手引き'!$AG13 | AFK2: ='（参考）包括・任意事業の上限額算定の手引き'!$AG14 -> 0 | AFL2: ='（参考）包括・任意事業の上限額算定の手引き'!$AG17 -> 0 | AFM2: ='（参考）包括・任意事業の上限額算定の手引き'!$AG18 -> 0 | AFN2: ='（参考）包括・任意事業の上限額算定の手引き'!$AG19 -> 0 | AFO2: ='（参考）包括・任意事業の上限額算定の手引き'!$AG20 -> 0 | AFP2: ='（参考）包括・任意事業の上限額算定の手引き'!$AG25 -> 0 | AFQ2: ='（参考）包括・任意事業の上限額算定の手引き'!$AG26 -> 0 | AFR2: ='（参考）包括・任意事業の上限額算定の手引き'!$AG27 -> 0 | AFS2: ='（参考）包括・任意事業の上限額算定の手引き'!$AG28 -> 0 | AFT2: ='（参考）包括・任意事業の上限額算定の手引き'!$AG29 -> 0 | AFU2: ='（参考）包括・任意事業の上限額算定の手引き'!$AG30 -> × | AFV2: ='（参考）包括・任意事業の上限額算定の手引き'!$AI5 | AFW2: ='（参考）包括・任意事業の上限額算定の手引き'!$AI6 | AFX2: ='（参考）包括・任意事業の上限額算定の手引き'!$AI7 -> 0 | AFY2: ='（参考）包括・任意事業の上限額算定の手引き'!$AI10 -> 0 | AFZ2: ='（参考）包括・任意事業の上限額算定の手引き'!$AI11 -> 0 | AGA2: ='（参考）包括・任意事業の上限額算定の手引き'!$AI12 -> 0 | AGB2: ='（参考）包括・任意事業の上限額算定の手引き'!$AI13 | AGC2: ='（参考）包括・任意事業の上限額算定の手引き'!$AI14 -> 0 | AGD2: ='（参考）包括・任意事業の上限額算定の手引き'!$AI17 -> 0 | AGE2: ='（参考）包括・任意事業の上限額算定の手引き'!$AI18 -> 0 | AGF2: ='（参考）包括・任意事業の上限額算定の手引き'!$AI19 -> 0 | AGG2: ='（参考）包括・任意事業の上限額算定の手引き'!$AI20 -> 0 | AGH2: ='（参考）包括・任意事業の上限額算定の手引き'!$AI25 -> 0 | AGI2: ='（参考）包括・任意事業の上限額算定の手引き'!$AI26 -> 0 | AGJ2: ='（参考）包括・任意事業の上限額算定の手引き'!$AI27 -> 0 | AGK2: ='（参考）包括・任意事業の上限額算定の手引き'!$AI28 -> 0 | AGL2: ='（参考）包括・任意事業の上限額算定の手引き'!$AI29 -> 0 | AGM2: ='（参考）包括・任意事業の上限額算定の手引き'!$AI30 -> × | AGN2: ='（参考）包括・任意事業の上限額算定の手引き'!$AK5 | AGO2: ='（参考）包括・任意事業の上限額算定の手引き'!$AK6 | AGP2: ='（参考）包括・任意事業の上限額算定の手引き'!$AK7 -> 0 | AGQ2: ='（参考）包括・任意事業の上限額算定の手引き'!$AK10 -> 0 | AGR2: ='（参考）包括・任意事業の上限額算定の手引き'!$AK11 -> 0 | AGS2: ='（参考）包括・任意事業の上限額算定の手引き'!$AK12 -> 0 | AGT2: ='（参考）包括・任意事業の上限額算定の手引き'!$AK13 | AGU2: ='（参考）包括・任意事業の上限額算定の手引き'!$AK14 -> 0 | AGV2: ='（参考）包括・任意事業の上限額算定の手引き'!$AK17 -> 0 | AGW2: ='（参考）包括・任意事業の上限額算定の手引き'!$AK18 -> 0 | AGX2: ='（参考）包括・任意事業の上限額算定の手引き'!$AK19 -> 0 | AGY2: ='（参考）包括・任意事業の上限額算定の手引き'!$AK20 -> 0 | AGZ2: ='（参考）包括・任意事業の上限額算定の手引き'!$AK25 -> 0 | AHA2: ='（参考）包括・任意事業の上限額算定の手引き'!$AK26 -> 0 | AHB2: ='（参考）包括・任意事業の上限額算定の手引き'!$AK27 -> 0 | AHC2: ='（参考）包括・任意事業の上限額算定の手引き'!$AK28 -> 0 | AHD2: ='（参考）包括・任意事業の上限額算定の手引き'!$AK29 -> 0 | AHE2: ='（参考）包括・任意事業の上限額算定の手引き'!$AK30 -> × | AHF2: ='（参考）包括・任意事業の上限額算定の手引き'!$AM5 | AHG2: ='（参考）包括・任意事業の上限額算定の手引き'!$AM6 | AHH2: ='（参考）包括・任意事業の上限額算定の手引き'!$AM7 -> 0 | AHI2: ='（参考）包括・任意事業の上限額算定の手引き'!$AM10 -> 0 | AHJ2: ='（参考）包括・任意事業の上限額算定の手引き'!$AM11 -> 0 | AHK2: ='（参考）包括・任意事業の上限額算定の手引き'!$AM12 -> 0 | AHL2: ='（参考）包括・任意事業の上限額算定の手引き'!$AM13 | AHM2: ='（参考）包括・任意事業の上限額算定の手引き'!$AM14 -> 0 | AHN2: ='（参考）包括・任意事業の上限額算定の手引き'!$AM17 -> 0 | AHO2: ='（参考）包括・任意事業の上限額算定の手引き'!$AM18 -> 0 | AHP2: ='（参考）包括・任意事業の上限額算定の手引き'!$AM19 -> 0 | AHQ2: ='（参考）包括・任意事業の上限額算定の手引き'!$AM20 -> 0 | AHR2: ='（参考）包括・任意事業の上限額算定の手引き'!$AM25 -> 0 | AHS2: ='（参考）包括・任意事業の上限額算定の手引き'!$AM26 -> 0 | AHT2: ='（参考）包括・任意事業の上限額算定の手引き'!$AM27 -> 0 | AHU2: ='（参考）包括・任意事業の上限額算定の手引き'!$AM28 -> 0 | AHV2: ='（参考）包括・任意事業の上限額算定の手引き'!$AM29 -> 0 | AHW2: ='（参考）包括・任意事業の上限額算定の手引き'!$AM30 -> × | AHX2: ='（参考）包括・任意事業の上限額算定の手引き'!$AO5 | AHY2: ='（参考）包括・任意事業の上限額算定の手引き'!$AO6 | AHZ2: ='（参考）包括・任意事業の上限額算定の手引き'!$AO7 -> 0 | AIA2: ='（参考）包括・任意事業の上限額算定の手引き'!$AO10 -> 0 | AIB2: ='（参考）包括・任意事業の上限額算定の手引き'!$AO11 -> 0 | AIC2: ='（参考）包括・任意事業の上限額算定の手引き'!$AO12 -> 0 | AID2: ='（参考）包括・任意事業の上限額算定の手引き'!$AO13 | AIE2: ='（参考）包括・任意事業の上限額算定の手引き'!$AO14 -> 0 | AIF2: ='（参考）包括・任意事業の上限額算定の手引き'!$AO17 -> 0 | AIG2: ='（参考）包括・任意事業の上限額算定の手引き'!$AO18 -> 0 | AIH2: ='（参考）包括・任意事業の上限額算定の手引き'!$AO19 -> 0 | AII2: ='（参考）包括・任意事業の上限額算定の手引き'!$AO20 -> 0 | AIJ2: ='（参考）包括・任意事業の上限額算定の手引き'!$AO25 -> 0 | AIK2: ='（参考）包括・任意事業の上限額算定の手引き'!$AO26 -> 0 | AIL2: ='（参考）包括・任意事業の上限額算定の手引き'!$AO27 -> 0 | AIM2: ='（参考）包括・任意事業の上限額算定の手引き'!$AO28 -> 0 | AIN2: ='（参考）包括・任意事業の上限額算定の手引き'!$AO29 -> 0 | AIO2: ='（参考）包括・任意事業の上限額算定の手引き'!$AO30 -> × | AIP2: ='（参考）包括・任意事業の上限額算定の手引き'!$AQ5 | AIQ2: ='（参考）包括・任意事業の上限額算定の手引き'!$AQ6 | AIR2: ='（参考）包括・任意事業の上限額算定の手引き'!$AQ7 -> 0 | AIS2: ='（参考）包括・任意事業の上限額算定の手引き'!$AQ10 -> 0 | AIT2: ='（参考）包括・任意事業の上限額算定の手引き'!$AQ11 -> 0 | AIU2: ='（参考）包括・任意事業の上限額算定の手引き'!$AQ12 -> 0 | AIV2: ='（参考）包括・任意事業の上限額算定の手引き'!$AQ13 | AIW2: ='（参考）包括・任意事業の上限額算定の手引き'!$AQ14 -> 0 | AIX2: ='（参考）包括・任意事業の上限額算定の手引き'!$AQ17 -> 0 | AIY2: ='（参考）包括・任意事業の上限額算定の手引き'!$AQ18 -> 0 | AIZ2: ='（参考）包括・任意事業の上限額算定の手引き'!$AQ19 -> 0 | AJA2: ='（参考）包括・任意事業の上限額算定の手引き'!$AQ20 -> 0 | AJB2: ='（参考）包括・任意事業の上限額算定の手引き'!$AQ25 -> 0 | AJC2: ='（参考）包括・任意事業の上限額算定の手引き'!$AQ26 -> 0 | AJD2: ='（参考）包括・任意事業の上限額算定の手引き'!$AQ27 -> 0 | AJE2: ='（参考）包括・任意事業の上限額算定の手引き'!$AQ28 -> 0 | AJF2: ='（参考）包括・任意事業の上限額算定の手引き'!$AQ29 -> 0 | AJG2: ='（参考）包括・任意事業の上限額算定の手引き'!$AQ30 -> × | AJH2: ='（参考）包括・任意事業の上限額算定の手引き'!$AS5 | AJI2: ='（参考）包括・任意事業の上限額算定の手引き'!$AS6 | AJJ2: ='（参考）包括・任意事業の上限額算定の手引き'!$AS7 -> 0 | AJK2: ='（参考）包括・任意事業の上限額算定の手引き'!$AS10 -> 0 | AJL2: ='（参考）包括・任意事業の上限額算定の手引き'!$AS11 -> 0 | AJM2: ='（参考）包括・任意事業の上限額算定の手引き'!$AS12 -> 0 | AJN2: ='（参考）包括・任意事業の上限額算定の手引き'!$AS13 | AJO2: ='（参考）包括・任意事業の上限額算定の手引き'!$AS14 -> 0 | AJP2: ='（参考）包括・任意事業の上限額算定の手引き'!$AS17 -> 0 | AJQ2: ='（参考）包括・任意事業の上限額算定の手引き'!$AS18 -> 0 | AJR2: ='（参考）包括・任意事業の上限額算定の手引き'!$AS19 -> 0 | AJS2: ='（参考）包括・任意事業の上限額算定の手引き'!$AS20 -> 0 | AJT2: ='（参考）包括・任意事業の上限額算定の手引き'!$AS25 -> 0 | AJU2: ='（参考）包括・任意事業の上限額算定の手引き'!$AS26 -> 0 | AJV2: ='（参考）包括・任意事業の上限額算定の手引き'!$AS27 -> 0 | AJW2: ='（参考）包括・任意事業の上限額算定の手引き'!$AS28 -> 0 | AJX2: ='（参考）包括・任意事業の上限額算定の手引き'!$AS29 -> 0 | AJY2: ='（参考）包括・任意事業の上限額算定の手引き'!$AS30 -> × | AJZ2: ='（参考）包括・任意事業の上限額算定の手引き'!$AU5 | AKA2: ='（参考）包括・任意事業の上限額算定の手引き'!$AU6 | AKB2: ='（参考）包括・任意事業の上限額算定の手引き'!$AU7 -> 0 | AKC2: ='（参考）包括・任意事業の上限額算定の手引き'!$AU10 -> 0 | AKD2: ='（参考）包括・任意事業の上限額算定の手引き'!$AU11 -> 0 | AKE2: ='（参考）包括・任意事業の上限額算定の手引き'!$AU12 -> 0 | AKF2: ='（参考）包括・任意事業の上限額算定の手引き'!$AU13 | AKG2: ='（参考）包括・任意事業の上限額算定の手引き'!$AU14 -> 0 | AKH2: ='（参考）包括・任意事業の上限額算定の手引き'!$AU17 -> 0 | AKI2: ='（参考）包括・任意事業の上限額算定の手引き'!$AU18 -> 0 | AKJ2: ='（参考）包括・任意事業の上限額算定の手引き'!$AU19 -> 0 | AKK2: ='（参考）包括・任意事業の上限額算定の手引き'!$AU20 -> 0 | AKL2: ='（参考）包括・任意事業の上限額算定の手引き'!$AU25 -> 0 | AKM2: ='（参考）包括・任意事業の上限額算定の手引き'!$AU26 -> 0 | AKN2: ='（参考）包括・任意事業の上限額算定の手引き'!$AU27 -> 0 | AKO2: ='（参考）包括・任意事業の上限額算定の手引き'!$AU28 -> 0 | AKP2: ='（参考）包括・任意事業の上限額算定の手引き'!$AU29 -> 0 | AKQ2: ='（参考）包括・任意事業の上限額算定の手引き'!$AU30 -> × | AKR2: ='（参考）包括・任意事業の上限額算定の手引き'!$AW5 | AKS2: ='（参考）包括・任意事業の上限額算定の手引き'!$AW6 | AKT2: ='（参考）包括・任意事業の上限額算定の手引き'!$AW7 -> 0 | AKU2: ='（参考）包括・任意事業の上限額算定の手引き'!$AW10 -> 0 | AKV2: ='（参考）包括・任意事業の上限額算定の手引き'!$AW11 -> 0 | AKW2: ='（参考）包括・任意事業の上限額算定の手引き'!$AW12 -> 0 | AKX2: ='（参考）包括・任意事業の上限額算定の手引き'!$AW13 | AKY2: ='（参考）包括・任意事業の上限額算定の手引き'!$AW14 -> 0 | AKZ2: ='（参考）包括・任意事業の上限額算定の手引き'!$AW17 -> 0 | ALA2: ='（参考）包括・任意事業の上限額算定の手引き'!$AW18 -> 0 | ALB2: ='（参考）包括・任意事業の上限額算定の手引き'!$AW19 -> 0 | ALC2: ='（参考）包括・任意事業の上限額算定の手引き'!$AW20 -> 0 | ALD2: ='（参考）包括・任意事業の上限額算定の手引き'!$AW25 -> 0 | ALE2: ='（参考）包括・任意事業の上限額算定の手引き'!$AW26 -> 0 | ALF2: ='（参考）包括・任意事業の上限額算定の手引き'!$AW27 -> 0 | ALG2: ='（参考）包括・任意事業の上限額算定の手引き'!$AW28 -> 0 | ALH2: ='（参考）包括・任意事業の上限額算定の手引き'!$AW29 -> 0 | ALI2: ='（参考）包括・任意事業の上限額算定の手引き'!$AW30 -> × | ALJ2: ='（参考）包括・任意事業の上限額算定の手引き'!$AY5 | ALK2: ='（参考）包括・任意事業の上限額算定の手引き'!$AY6 | ALL2: ='（参考）包括・任意事業の上限額算定の手引き'!$AY7 -> 0 | ALM2: ='（参考）包括・任意事業の上限額算定の手引き'!$AY10 -> 0 | ALN2: ='（参考）包括・任意事業の上限額算定の手引き'!$AY11 -> 0 | ALO2: ='（参考）包括・任意事業の上限額算定の手引き'!$AY12 -> 0 | ALP2: ='（参考）包括・任意事業の上限額算定の手引き'!$AY13 | ALQ2: ='（参考）包括・任意事業の上限額算定の手引き'!$AY14 -> 0 | ALR2: ='（参考）包括・任意事業の上限額算定の手引き'!$AY17 -> 0 | ALS2: ='（参考）包括・任意事業の上限額算定の手引き'!$AY18 -> 0 | ALT2: ='（参考）包括・任意事業の上限額算定の手引き'!$AY19 -> 0 | ALU2: ='（参考）包括・任意事業の上限額算定の手引き'!$AY20 -> 0 | ALV2: ='（参考）包括・任意事業の上限額算定の手引き'!$AY25 -> 0 | ALW2: ='（参考）包括・任意事業の上限額算定の手引き'!$AY26 -> 0 | ALX2: ='（参考）包括・任意事業の上限額算定の手引き'!$AY27 -> 0 | ALY2: ='（参考）包括・任意事業の上限額算定の手引き'!$AY28 -> 0 | ALZ2: ='（参考）包括・任意事業の上限額算定の手引き'!$AY29 -> 0 | AMA2: ='（参考）包括・任意事業の上限額算定の手引き'!$AY30 -> × | AMB2: ='（参考）包括・任意事業の上限額算定の手引き'!$BA5 | AMC2: ='（参考）包括・任意事業の上限額算定の手引き'!$BA6 | AMD2: ='（参考）包括・任意事業の上限額算定の手引き'!$BA7 -> 0 | AME2: ='（参考）包括・任意事業の上限額算定の手引き'!$BA10 -> 0 | AMF2: ='（参考）包括・任意事業の上限額算定の手引き'!$BA11 -> 0 | AMG2: ='（参考）包括・任意事業の上限額算定の手引き'!$BA12 -> 0 | AMH2: ='（参考）包括・任意事業の上限額算定の手引き'!$BA13 | AMI2: ='（参考）包括・任意事業の上限額算定の手引き'!$BA14 -> 0 | AMJ2: ='（参考）包括・任意事業の上限額算定の手引き'!$BA17 -> 0 | AMK2: ='（参考）包括・任意事業の上限額算定の手引き'!$BA18 -> 0 | AML2: ='（参考）包括・任意事業の上限額算定の手引き'!$BA19 -> 0 | AMM2: ='（参考）包括・任意事業の上限額算定の手引き'!$BA20 -> 0 | AMN2: ='（参考）包括・任意事業の上限額算定の手引き'!$BA25 -> 0 | AMO2: ='（参考）包括・任意事業の上限額算定の手引き'!$BA26 -> 0 | AMP2: ='（参考）包括・任意事業の上限額算定の手引き'!$BA27 -> 0 | AMQ2: ='（参考）包括・任意事業の上限額算定の手引き'!$BA28 -> 0 | AMR2: ='（参考）包括・任意事業の上限額算定の手引き'!$BA29 -> 0 | AMS2: ='（参考）包括・任意事業の上限額算定の手引き'!$BA30 -> × | AMT2: ='（参考）包括・任意事業の上限額算定の手引き'!$BC5 | AMU2: ='（参考）包括・任意事業の上限額算定の手引き'!$BC6 | AMV2: ='（参考）包括・任意事業の上限額算定の手引き'!$BC7 -> 0 | AMW2: ='（参考）包括・任意事業の上限額算定の手引き'!$BC10 -> 0 | AMX2: ='（参考）包括・任意事業の上限額算定の手引き'!$BC11 -> 0 | AMY2: ='（参考）包括・任意事業の上限額算定の手引き'!$BC12 -> 0 | AMZ2: ='（参考）包括・任意事業の上限額算定の手引き'!$BC13 | ANA2: ='（参考）包括・任意事業の上限額算定の手引き'!$BC14 -> 0 | ANB2: ='（参考）包括・任意事業の上限額算定の手引き'!$BC17 -> 0 | ANC2: ='（参考）包括・任意事業の上限額算定の手引き'!$BC18 -> 0 | AND2: ='（参考）包括・任意事業の上限額算定の手引き'!$BC19 -> 0 | ANE2: ='（参考）包括・任意事業の上限額算定の手引き'!$BC20 -> 0 | ANF2: ='（参考）包括・任意事業の上限額算定の手引き'!$BC25 -> 0 | ANG2: ='（参考）包括・任意事業の上限額算定の手引き'!$BC26 -> 0 | ANH2: ='（参考）包括・任意事業の上限額算定の手引き'!$BC27 -> 0 | ANI2: ='（参考）包括・任意事業の上限額算定の手引き'!$BC28 -> 0 | ANJ2: ='（参考）包括・任意事業の上限額算定の手引き'!$BC29 -> 0 | ANK2: ='（参考）包括・任意事業の上限額算定の手引き'!$BC30 -> × | ANL2: ='（参考）包括・任意事業の上限額算定の手引き'!$BE5 | ANM2: ='（参考）包括・任意事業の上限額算定の手引き'!$BE6 | ANN2: ='（参考）包括・任意事業の上限額算定の手引き'!$BE7 -> 0 | ANO2: ='（参考）包括・任意事業の上限額算定の手引き'!$BE10 -> 0 | ANP2: ='（参考）包括・任意事業の上限額算定の手引き'!$BE11 -> 0 | ANQ2: ='（参考）包括・任意事業の上限額算定の手引き'!$BE12 -> 0 | ANR2: ='（参考）包括・任意事業の上限額算定の手引き'!$BE13 | ANS2: ='（参考）包括・任意事業の上限額算定の手引き'!$BE14 -> 0 | ANT2: ='（参考）包括・任意事業の上限額算定の手引き'!$BE17 -> 0 | ANU2: ='（参考）包括・任意事業の上限額算定の手引き'!$BE18 -> 0 | ANV2: ='（参考）包括・任意事業の上限額算定の手引き'!$BE19 -> 0 | ANW2: ='（参考）包括・任意事業の上限額算定の手引き'!$BE20 -> 0 | ANX2: ='（参考）包括・任意事業の上限額算定の手引き'!$BE25 -> 0 | ANY2: ='（参考）包括・任意事業の上限額算定の手引き'!$BE26 -> 0 | ANZ2: ='（参考）包括・任意事業の上限額算定の手引き'!$BE27 -> 0 | AOA2: ='（参考）包括・任意事業の上限額算定の手引き'!$BE28 -> 0 | AOB2: ='（参考）包括・任意事業の上限額算定の手引き'!$BE29 -> 0 | AOC2: ='（参考）包括・任意事業の上限額算定の手引き'!$BE30 -> × | AOD2: ='（参考）包括・任意事業の上限額算定の手引き'!$BG5 | AOE2: ='（参考）包括・任意事業の上限額算定の手引き'!$BG6 | AOF2: ='（参考）包括・任意事業の上限額算定の手引き'!$BG7 -> 0 | AOG2: ='（参考）包括・任意事業の上限額算定の手引き'!$BG10 -> 0 | AOH2: ='（参考）包括・任意事業の上限額算定の手引き'!$BG11 -> 0 | AOI2: ='（参考）包括・任意事業の上限額算定の手引き'!$BG12 -> 0 | AOJ2: ='（参考）包括・任意事業の上限額算定の手引き'!$BG13 | AOK2: ='（参考）包括・任意事業の上限額算定の手引き'!$BG14 -> 0 | AOL2: ='（参考）包括・任意事業の上限額算定の手引き'!$BG17 -> 0 | AOM2: ='（参考）包括・任意事業の上限額算定の手引き'!$BG18 -> 0 | AON2: ='（参考）包括・任意事業の上限額算定の手引き'!$BG19 -> 0 | AOO2: ='（参考）包括・任意事業の上限額算定の手引き'!$BG20 -> 0 | AOP2: ='（参考）包括・任意事業の上限額算定の手引き'!$BG25 -> 0 | AOQ2: ='（参考）包括・任意事業の上限額算定の手引き'!$BG26 -> 0 | AOR2: ='（参考）包括・任意事業の上限額算定の手引き'!$BG27 -> 0 | AOS2: ='（参考）包括・任意事業の上限額算定の手引き'!$BG28 -> 0 | AOT2: ='（参考）包括・任意事業の上限額算定の手引き'!$BG29 -> 0 | AOU2: ='（参考）包括・任意事業の上限額算定の手引き'!$BG30 -> × | AOV2: ='（参考）包括・任意事業の上限額算定の手引き'!$BI5 | AOW2: ='（参考）包括・任意事業の上限額算定の手引き'!$BI6 | AOX2: ='（参考）包括・任意事業の上限額算定の手引き'!$BI7 -> 0 | AOY2: ='（参考）包括・任意事業の上限額算定の手引き'!$BI10 -> 0 | AOZ2: ='（参考）包括・任意事業の上限額算定の手引き'!$BI11 -> 0 | APA2: ='（参考）包括・任意事業の上限額算定の手引き'!$BI12 -> 0 | APB2: ='（参考）包括・任意事業の上限額算定の手引き'!$BI13 | APC2: ='（参考）包括・任意事業の上限額算定の手引き'!$BI14 -> 0 | APD2: ='（参考）包括・任意事業の上限額算定の手引き'!$BI17 -> 0 | APE2: ='（参考）包括・任意事業の上限額算定の手引き'!$BI18 -> 0 | APF2: ='（参考）包括・任意事業の上限額算定の手引き'!$BI19 -> 0 | APG2: ='（参考）包括・任意事業の上限額算定の手引き'!$BI20 -> 0 | APH2: ='（参考）包括・任意事業の上限額算定の手引き'!$BI25 -> 0 | API2: ='（参考）包括・任意事業の上限額算定の手引き'!$BI26 -> 0 | APJ2: ='（参考）包括・任意事業の上限額算定の手引き'!$BI27 -> 0 | APK2: ='（参考）包括・任意事業の上限額算定の手引き'!$BI28 -> 0 | APL2: ='（参考）包括・任意事業の上限額算定の手引き'!$BI29 -> 0 | APM2: ='（参考）包括・任意事業の上限額算定の手引き'!$BI30 -> × | APN2: ='（参考）包括・任意事業の上限額算定の手引き'!$BK5 | APO2: ='（参考）包括・任意事業の上限額算定の手引き'!$BK6 | APP2: ='（参考）包括・任意事業の上限額算定の手引き'!$BK7 -> 0 | APQ2: ='（参考）包括・任意事業の上限額算定の手引き'!$BK10 -> 0 | APR2: ='（参考）包括・任意事業の上限額算定の手引き'!$BK11 -> 0 | APS2: ='（参考）包括・任意事業の上限額算定の手引き'!$BK12 -> 0 | APT2: ='（参考）包括・任意事業の上限額算定の手引き'!$BK13 | APU2: ='（参考）包括・任意事業の上限額算定の手引き'!$BK14 -> 0 | APV2: ='（参考）包括・任意事業の上限額算定の手引き'!$BK17 -> 0 | APW2: ='（参考）包括・任意事業の上限額算定の手引き'!$BK18 -> 0 | APX2: ='（参考）包括・任意事業の上限額算定の手引き'!$BK19 -> 0 | APY2: ='（参考）包括・任意事業の上限額算定の手引き'!$BK20 -> 0 | APZ2: ='（参考）包括・任意事業の上限額算定の手引き'!$BK25 -> 0 | AQA2: ='（参考）包括・任意事業の上限額算定の手引き'!$BK26 -> 0 | AQB2: ='（参考）包括・任意事業の上限額算定の手引き'!$BK27 -> 0 | AQC2: ='（参考）包括・任意事業の上限額算定の手引き'!$BK28 -> 0 | AQD2: ='（参考）包括・任意事業の上限額算定の手引き'!$BK29 -> 0 | AQE2: ='（参考）包括・任意事業の上限額算定の手引き'!$BK30 -> × | AQF2: ='（参考）包括・任意事業の上限額算定の手引き'!$BM5 | AQG2: ='（参考）包括・任意事業の上限額算定の手引き'!$BM6 | AQH2: ='（参考）包括・任意事業の上限額算定の手引き'!$BM7 -> 0 | AQI2: ='（参考）包括・任意事業の上限額算定の手引き'!$BM10 -> 0 | AQJ2: ='（参考）包括・任意事業の上限額算定の手引き'!$BM11 -> 0 | AQK2: ='（参考）包括・任意事業の上限額算定の手引き'!$BM12 -> 0 | AQL2: ='（参考）包括・任意事業の上限額算定の手引き'!$BM13 | AQM2: ='（参考）包括・任意事業の上限額算定の手引き'!$BM14 -> 0 | AQN2: ='（参考）包括・任意事業の上限額算定の手引き'!$BM17 -> 0 | AQO2: ='（参考）包括・任意事業の上限額算定の手引き'!$BM18 -> 0 | AQP2: ='（参考）包括・任意事業の上限額算定の手引き'!$BM19 -> 0 | AQQ2: ='（参考）包括・任意事業の上限額算定の手引き'!$BM20 -> 0 | AQR2: ='（参考）包括・任意事業の上限額算定の手引き'!$BM25 -> 0 | AQS2: ='（参考）包括・任意事業の上限額算定の手引き'!$BM26 -> 0 | AQT2: ='（参考）包括・任意事業の上限額算定の手引き'!$BM27 -> 0 | AQU2: ='（参考）包括・任意事業の上限額算定の手引き'!$BM28 -> 0 | AQV2: ='（参考）包括・任意事業の上限額算定の手引き'!$BM29 -> 0 | AQW2: ='（参考）包括・任意事業の上限額算定の手引き'!$BM30 -> × | AQX2: ='（参考）包括・任意事業の上限額算定の手引き'!$BO5 | AQY2: ='（参考）包括・任意事業の上限額算定の手引き'!$BO6 | AQZ2: ='（参考）包括・任意事業の上限額算定の手引き'!$BO7 -> 0 | ARA2: ='（参考）包括・任意事業の上限額算定の手引き'!$BO10 -> 0 | ARB2: ='（参考）包括・任意事業の上限額算定の手引き'!$BO11 -> 0 | ARC2: ='（参考）包括・任意事業の上限額算定の手引き'!$BO12 -> 0 | ARD2: ='（参考）包括・任意事業の上限額算定の手引き'!$BO13 | ARE2: ='（参考）包括・任意事業の上限額算定の手引き'!$BO14 -> 0 | ARF2: ='（参考）包括・任意事業の上限額算定の手引き'!$BO17 -> 0 | ARG2: ='（参考）包括・任意事業の上限額算定の手引き'!$BO18 -> 0 | ARH2: ='（参考）包括・任意事業の上限額算定の手引き'!$BO19 -> 0 | ARI2: ='（参考）包括・任意事業の上限額算定の手引き'!$BO20 -> 0 | ARJ2: ='（参考）包括・任意事業の上限額算定の手引き'!$BO25 -> 0 | ARK2: ='（参考）包括・任意事業の上限額算定の手引き'!$BO26 -> 0 | ARL2: ='（参考）包括・任意事業の上限額算定の手引き'!$BO27 -> 0 | ARM2: ='（参考）包括・任意事業の上限額算定の手引き'!$BO28 -> 0 | ARN2: ='（参考）包括・任意事業の上限額算定の手引き'!$BO29 -> 0 | ARO2: ='（参考）包括・任意事業の上限額算定の手引き'!$BO30 -> × | ARP2: ='（参考）包括・任意事業の上限額算定の手引き'!$BQ5 | ARQ2: ='（参考）包括・任意事業の上限額算定の手引き'!$BQ6 | ARR2: ='（参考）包括・任意事業の上限額算定の手引き'!$BQ7 -> 0 | ARS2: ='（参考）包括・任意事業の上限額算定の手引き'!$BQ10 -> 0 | ART2: ='（参考）包括・任意事業の上限額算定の手引き'!$BQ11 -> 0 | ARU2: ='（参考）包括・任意事業の上限額算定の手引き'!$BQ12 -> 0 | ARV2: ='（参考）包括・任意事業の上限額算定の手引き'!$BQ13 | ARW2: ='（参考）包括・任意事業の上限額算定の手引き'!$BQ14 -> 0 | ARX2: ='（参考）包括・任意事業の上限額算定の手引き'!$BQ17 -> 0 | ARY2: ='（参考）包括・任意事業の上限額算定の手引き'!$BQ18 -> 0 | ARZ2: ='（参考）包括・任意事業の上限額算定の手引き'!$BQ19 -> 0 | ASA2: ='（参考）包括・任意事業の上限額算定の手引き'!$BQ20 -> 0 | ASB2: ='（参考）包括・任意事業の上限額算定の手引き'!$BQ25 -> 0 | ASC2: ='（参考）包括・任意事業の上限額算定の手引き'!$BQ26 -> 0 | ASD2: ='（参考）包括・任意事業の上限額算定の手引き'!$BQ27 -> 0 | ASE2: ='（参考）包括・任意事業の上限額算定の手引き'!$BQ28 -> 0 | ASF2: ='（参考）包括・任意事業の上限額算定の手引き'!$BQ29 -> 0 | ASG2: ='（参考）包括・任意事業の上限額算定の手引き'!$BQ30 -> × | ASH2: ='（参考）包括・任意事業の上限額算定の手引き'!$BS5 | ASI2: ='（参考）包括・任意事業の上限額算定の手引き'!$BS6 | ASJ2: ='（参考）包括・任意事業の上限額算定の手引き'!$BS7 -> 0 | ASK2: ='（参考）包括・任意事業の上限額算定の手引き'!$BS10 -> 0 | ASL2: ='（参考）包括・任意事業の上限額算定の手引き'!$BS11 -> 0 | ASM2: ='（参考）包括・任意事業の上限額算定の手引き'!$BS12 -> 0 | ASN2: ='（参考）包括・任意事業の上限額算定の手引き'!$BS13 | ASO2: ='（参考）包括・任意事業の上限額算定の手引き'!$BS14 -> 0 | ASP2: ='（参考）包括・任意事業の上限額算定の手引き'!$BS17 -> 0 | ASQ2: ='（参考）包括・任意事業の上限額算定の手引き'!$BS18 -> 0 | ASR2: ='（参考）包括・任意事業の上限額算定の手引き'!$BS19 -> 0 | ASS2: ='（参考）包括・任意事業の上限額算定の手引き'!$BS20 -> 0 | AST2: ='（参考）包括・任意事業の上限額算定の手引き'!$BS25 -> 0 | ASU2: ='（参考）包括・任意事業の上限額算定の手引き'!$BS26 -> 0 | ASV2: ='（参考）包括・任意事業の上限額算定の手引き'!$BS27 -> 0 | ASW2: ='（参考）包括・任意事業の上限額算定の手引き'!$BS28 -> 0 | ASX2: ='（参考）包括・任意事業の上限額算定の手引き'!$BS29 -> 0 | ASY2: ='（参考）包括・任意事業の上限額算定の手引き'!$BS30 -> × | ASZ2: =#REF! -> #REF! | ATA2: =#REF! -> #REF! | ATB2: =#REF! -> #REF! | ATC2: =#REF! -> #REF! | ATD2: =#REF! -> #REF! | ATE2: =#REF! -> #REF! | ATF2: =#REF! -> #REF! | ATG2: =#REF! -> #REF! | ... AYJ2: =#REF! -> #REF! | AYK2: =IF(SUM(AYL2:AYP2)=0,"","有") -> #REF! | AYL2: =#REF! -> #REF! | AYM2: =#REF! -> #REF! | AYN2: =#REF! -> #REF! | AYO2: =#REF! -> #REF! | AYP2: =#REF! -> #REF! | AYQ2: =#REF! -> #REF! | AYR2: =#REF! -> #REF! | AYS2: =#REF! -> #REF! | ... BAR2: =#REF! -> #REF!
OK5: 令和６年10月１日における85歳以上の人口
OK6: 令和６年度の10月１日における75歳以上80歳未満人口を同日における75歳以上人口で除して得た率・・・X1
OK7: 令和６年度の10月１日における80歳以上85歳未満人口を同日における75歳以上人口で除して得た率・・・Y1
OK8: 令和６年度の10月１日における85歳以上人口を同日における75歳以上人口で除して得た率・・・Z1
OK9: 令和３年10月１日における75歳以上の人口
OK10: 令和３年10月１日における75歳以上80歳未満人口
OK11: 令和３年10月１日における80歳以上85歳未満人口
OK12: 令和３年10月１日における85歳以上の人口
OK13: 令和３年度の10月１日における75歳以上80歳未満人口を同日における75歳以上人口で除して得た率・・・X2
OK14: 令和３年度の10月１日における80歳以上85歳未満人口を同日における75歳以上人口で除して得た率・・・Y2
OK15: 令和３年度の10月１日における85歳以上人口を同日における75歳以上人口で除して得た率・・・Z2
OK16: A×0.9×(X1＋Y1×2＋Z1×3)/(X2＋Y2×2＋Z2×3)＋A×0.1－A・・・イ

Sheet PullDown
A1: 厚生(支)局一覧 | F1: 都道府県一覧 | M1: 地方公共団体一覧 | Z1: 地方公共団体一覧(都道府県別） | BX1: プルダウン一覧
AA4: 北海道 | AB4: 青森県 | AC4: 岩手県 | AD4: 宮城県 | AE4: 秋田県 | AF4: 山形県 | AG4: 福島県 | AH4: 茨城県 | AI4: 栃木県 | AJ4: 群馬県 | AK4: 埼玉県 | AL4: 千葉県 | AM4: 東京都 | AN4: 神奈川県 | AO4: 新潟県 | AP4: 富山県 | AQ4: 石川県 | AR4: 福井県 | AS4: 山梨県 | AT4: 長野県 | AU4: 岐阜県 | AV4: 静岡県 | AW4: 愛知県 | AX4: 三重県 | AY4: 滋賀県 | AZ4: 京都府 | BA4: 大阪府 | BB4: 兵庫県 | BC4: 奈良県 | BD4: 和歌山県 | BE4: 鳥取県 | BF4: 島根県 | BG4: 岡山県 | BH4: 広島県 | BI4: 山口県 | BJ4: 徳島県 | BK4: 香川県 | BL4: 愛媛県 | BM4: 高知県 | BN4: 福岡県 | BO4: 佐賀県 | BP4: 長崎県 | BQ4: 熊本県 | BR4: 大分県 | BS4: 宮崎県 | BT4: 鹿児島県 | BU4: 沖縄県 | BY4: 上限設定状況 | CC4: 実績上限設定状況
B5: 厚生(支)局番号 | C5: 厚生(支)局名 | F5: 地方公共団体コード | G5: 厚生(支)局番号 | H5: 厚生(支)局名 | I5: 都道府県コード | J5: 都道府県名 | N5: 通し番号 | O5: 都道府県番号 | P5: 保険者番号 | Q5: 都道府県コード | R5: 市区町村コード | S5: Ｃ・Ｄ | T5: 団体名 | U5: 厚生(支)局番号 | V5: 厚生(支)局名 | W5: 地方公共団体コード | AA5: 01 | AB5: 02 | AC5: 03 | AD5: 04 | AE5: 05 | AF5: 06 | AG5: 07 | AH5: 08 | AI5: 09 | AJ5: 10 | AK5: 11 | AL5: 12 | AM5: 13 | AN5: 14 | AO5: 15 | AP5: 16 | AQ5: 17 | AR5: 18 | AS5: 19 | AT5: 20 | AU5: 21 | AV5: 22 | AW5: 23 | AX5: 24 | AY5: 25 | AZ5: 26 | BA5: 27 | BB5: 28 | BC5: 29 | BD5: 30 | BE5: 31 | BF5: 32 | BG5: 33 | BH5: 34 | BI5: 35 | BJ5: 36 | BK5: 37 | BL5: 38 | BM5: 39 | BN5: 40 | BO5: 41 | BP5: 42 | BQ5: 43 | BR5: 44 | BS5: 45 | BT5: 46 | BU5: 47 | BY5: ①総合事業上限設定状況 | BZ5: ②センター運営上限設定状況 | CA5: ③社会保障充実上限設定状況 | CC5: ①総合事業実績上限設定状況 | CE5: 移行年度 | CG5: サービス類型 | CJ5: 都道府県名 | CK5: 保険者名 | CM5: 項番
B6: 01 | C6: 北海道厚生局 | F6: 010006 | G6: 01 | H6: 北海道厚生局 | I6: 01 | J6: 北海道 | L6: 0001-1 | M6: 北海道札幌市 | N6: 0001 | O6: 01 | P6: 011007 | Q6: 01 | R6: 100 | S6: 7 | T6: 札幌市 | U6: 01 | V6: 北海道厚生局 | W6: 011002 | X6: 1 | AA6: 札幌市 | AB6: 青森市 | AC6: 盛岡市 | AD6: 仙台市 | AE6: 秋田市 | AF6: 山形市 | AG6: 福島市 | AH6: 水戸市 | AI6: 宇都宮市 | AJ6: 前橋市 | AK6: さいたま市 | AL6: 千葉市 | AM6: 千代田区 | AN6: 横浜市 | AO6: 新潟市 | AP6: 富山市 | AQ6: 金沢市 | AR6: 福井市 | AS6: 甲府市 | AT6: 長野市 | AU6: 岐阜市 | AV6: 静岡市 | AW6: 名古屋市 | AX6: 津市 | AY6: 大津市 | AZ6: 京都市 | BA6: 大阪市 | BB6: 神戸市 | BC6: 奈良市 | BD6: 和歌山市 | BE6: 鳥取市 | BF6: 松江市 | BG6: 岡山市 | BH6: 広島市 | BI6: 下関市 | BJ6: 徳島市 | BK6: 高松市 | BL6: 松山市 | BM6: 高知市 | BN6: 北九州市 | BO6: 唐津市 | BP6: 長崎市 | BQ6: 熊本市 | BR6: 大分市 | BS6: 宮崎市 | BT6: 鹿児島市 | BU6: 那覇市 | BY6: ①基本の上限額 | BZ6: ①原則の上限額 | CA6: ①標準額 | CC6: ①基本の上限額 | CE6: 42095 | CG6: 訪問型サービス・活動A | CI6: 希望する | CJ6: 北海道 | CK6: 札幌市 | CL6: =CJ6&CK6 -> 北海道札幌市 | CM6: 1 | CN6: =VLOOKUP(CL6,$M$6:$N$1784,2,FALSE) -> 0001 | CO6: =CM6&TEXT(CN6,0)&CK6 -> 11札幌市 | CP6: 11札幌市 | CQ6: =CO6=CP6 -> TRUE
B7: 02 | C7: 東北厚生局 | F7: 020001 | G7: 02 | H7: 東北厚生局 | I7: 02 | J7: 青森県 | L7: 0002-1 | M7: 北海道函館市 | N7: 0002 | O7: 01 | P7: 012021 | Q7: 01 | R7: 202 | S7: 1 | T7: 函館市 | U7: 01 | V7: 北海道厚生局 | W7: 012025 | X7: 1 | AA7: 函館市 | AB7: 弘前市 | AC7: 宮古市 | AD7: 石巻市 | AE7: 能代市 | AF7: 米沢市 | AG7: 会津若松市 | AH7: 日立市 | AI7: 足利市 | AJ7: 高崎市 | AK7: 川越市 | AL7: 銚子市 | AM7: 中央区 | AN7: 川崎市 | AO7: 長岡市 | AP7: 高岡市 | AQ7: 七尾市 | AR7: 敦賀市 | AS7: 富士吉田市 | AT7: 松本市 | AU7: 大垣市 | AV7: 浜松市 | AW7: 岡崎市 | AX7: 四日市市 | AY7: 彦根市 | AZ7: 福知山市 | BA7: 堺市 | BB7: 姫路市 | BC7: 大和高田市 | BD7: 海南市 | BE7: 米子市 | BF7: 出雲市 | BG7: 倉敷市 | BH7: 呉市 | BI7: 宇部市 | BJ7: 鳴門市 | BK7: 丸亀市 | BL7: 今治市 | BM7: 室戸市 | BN7: 福岡市 | BO7: 伊万里市 | BP7: 佐世保市 | BQ7: 八代市 | BR7: 別府市 | BS7: 都城市 | BT7: 鹿屋市 | BU7: 宜野湾市 | BY7: ②介護予防給付全体の伸びを考慮する上限額 | BZ7: ②特例の上限額 | CA7: ②個別協議希望 | CC7: ②介護予防給付全体の伸びを考慮する上限額 | CE7: 42461 | CG7: 訪問型サービス・活動B | CI7: 希望しない | CJ7: 北海道 | CK7: 函館市 | CL7: =CJ7&CK7 -> 北海道函館市 | CM7: 2 | CN7: =VLOOKUP(CL7,$M$6:$N$1784,2,FALSE) -> 0002 | CO7: =CM7&TEXT(CN7,0)&CK7 -> 22函館市 | CP7: 22函館市 | CQ7: =CO7=CP7 -> TRUE
B8: 03 | C8: 関東信越厚生局 | F8: 030007 | G8: 02 | H8: 東北厚生局 | I8: 03 | J8: 岩手県 | L8: 0003-1 | M8: 北海道小樽市 | N8: 0003 | O8: 01 | P8: 012039 | Q8: 01 | R8: 203 | S8: 9 | T8: 小樽市 | U8: 01 | V8: 北海道厚生局 | W8: 012033 | X8: 1 | AA8: 小樽市 | AB8: 八戸市 | AC8: 大船渡市 | AD8: 塩竈市 | AE8: 横手市 | AF8: 鶴岡市 | AG8: 郡山市 | AH8: 土浦市 | AI8: 栃木市 | AJ8: 桐生市 | AK8: 川口市 | AL8: 市川市 | AM8: 港区 | AN8: 相模原市 | AO8: 三条市 | AP8: 魚津市 | AQ8: 小松市 | AR8: 小浜市 | AS8: 都留市 | AT8: 上田市 | AU8: 高山市 | AV8: 沼津市 | AW8: 一宮市 | AX8: 伊勢市 | AY8: 長浜市 | AZ8: 舞鶴市 | BA8: 岸和田市 | BB8: 尼崎市 | BC8: 大和郡山市 | BD8: 橋本市 | BE8: 倉吉市 | BF8: 益田市 | BG8: 津山市 | BH8: 竹原市 | BI8: 山口市 | BJ8: 小松島市 | BK8: 坂出市 | BL8: 宇和島市 | BM8: 安芸市 | BN8: 大牟田市 | BO8: 玄海町 | BP8: 諫早市 | BQ8: 人吉市 | BR8: 中津市 | BS8: 延岡市 | BT8: 枕崎市 | BU8: 石垣市 | BY8: ③特例イ | CC8: ③特例イ | CE8: 42826 | CG8: 訪問型サービス・活動C | CJ8: 北海道 | CK8: 小樽市 | CL8: =CJ8&CK8 -> 北海道小樽市 | CM8: 3 | CN8: =VLOOKUP(CL8,$M$6:$N$1784,2,FALSE) -> 0003 | CO8: =CM8&TEXT(CN8,0)&CK8 -> 33小樽市 | CP8: 33小樽市 | CQ8: =CO8=CP8 -> TRUE
B9: 04 | C9: 東海北陸厚生局 | F9: 040002 | G9: 02 | H9: 東北厚生局 | I9: 04 | J9: 宮城県 | L9: 0004-1 | M9: 北海道旭川市 | N9: 0004 | O9: 01 | P9: 012047 | Q9: 01 | R9: 204 | S9: 7 | T9: 旭川市 | U9: 01 | V9: 北海道厚生局 | W9: 012041 | X9: 1 | AA9: 旭川市 | AB9: 黒石市 | AC9: 花巻市 | AD9: 気仙沼市 | AE9: 大館市 | AF9: 酒田市 | AG9: いわき市 | AH9: 古河市 | AI9: 佐野市 | AJ9: 伊勢崎市 | AK9: 行田市 | AL9: 船橋市 | AM9: 新宿区 | AN9: 横須賀市 | AO9: 柏崎市 | AP9: 氷見市 | AQ9: 輪島市 | AR9: 大野市 | AS9: 山梨市 | AT9: 飯田市 | AU9: 多治見市 | AV9: 熱海市 | AW9: 瀬戸市 | AX9: 松阪市 | AY9: 近江八幡市 | AZ9: 綾部市 | BA9: 豊中市 | BB9: 明石市 | BC9: 天理市 | BD9: 有田市 | BE9: 境港市 | BF9: 大田市 | BG9: 玉野市 | BH9: 三原市 | BI9: 萩市 | BJ9: 阿南市 | BK9: 善通寺市 | BL9: 八幡浜市 | BM9: 南国市 | BN9: 久留米市 | BO9: 有田町 | BP9: 大村市 | BQ9: 荒尾市 | BR9: 日田市 | BS9: 日南市 | BT9: 阿久根市 | BU9: 浦添市 | BY9: ④特例ロ | CC9: ④特例ロ | CG9: 訪問型サービス・活動D | CJ9: 北海道 | CK9: 旭川市 | CL9: =CJ9&CK9 -> 北海道旭川市 | CM9: 4 | CN9: =VLOOKUP(CL9,$M$6:$N$1784,2,FALSE) -> 0004 | CO9: =CM9&TEXT(CN9,0)&CK9 -> 44旭川市 | CP9: 44旭川市 | CQ9: =CO9=CP9 -> TRUE
B10: 05 | C10: 近畿厚生局 | F10: 050008 | G10: 02 | H10: 東北厚生局 | I10: 05 | J10: 秋田県 | L10: 0005-1 | M10: 北海道室蘭市 | N10: 0005 | O10: 01 | P10: 012054 | Q10: 01 | R10: 205 | S10: 4 | T10: 室蘭市 | U10: 01 | V10: 北海道厚生局 | W10: 012050 | X10: 1 | AA10: 室蘭市 | AB10: 五所川原市 | AC10: 北上市 | AD10: 白石市 | AE10: 男鹿市 | AF10: 新庄市 | AG10: 白河市 | AH10: 石岡市 | AI10: 鹿沼市 | AJ10: 太田市 | AK10: 秩父市 | AL10: 館山市 | AM10: 文京区 | AN10: 平塚市 | AO10: 新発田市 | AP10: 滑川市 | AQ10: 珠洲市 | AR10: 勝山市 | AS10: 大月市 | AT10: 須坂市 | AU10: 関市 | AV10: 三島市 | AW10: 半田市 | AX10: 桑名市 | AY10: 草津市 | AZ10: 宇治市 | BA10: 池田市 | BB10: 西宮市 | BC10: 橿原市 | BD10: 御坊市 | BE10: 岩美町 | BF10: 安来市 | BG10: 笠岡市 | BH10: 尾道市 | BI10: 防府市 | BJ10: 吉野川市 | BK10: 観音寺市 | BL10: 新居浜市 | BM10: 土佐市 | BN10: 直方市 | BO10: 杵藤地区広域市町村圏組合 | BP10: 平戸市 | BQ10: 水俣市 | BR10: 佐伯市 | BS10: 小林市 | BT10: 出水市 | BU10: 名護市 | BY10: ⑤個別協議希望 | CC10: ⑤個別協議 | CG10: 通所型サービス・活動A | CJ10: 北海道 | CK10: 室蘭市 | CL10: =CJ10&CK10 -> 北海道室蘭市 | CM10: 5 | CN10: =VLOOKUP(CL10,$M$6:$N$1784,2,FALSE) -> 0005 | CO10: =CM10&TEXT(CN10,0)&CK10 -> 55室蘭市 | CP10: 55室蘭市 | CQ10: =CO10=CP10 -> TRUE
B11: 06 | C11: 中国四国厚生局 | F11: 060003 | G11: 02 | H11: 東北厚生局 | I11: 06 | J11: 山形県 | L11: 0006-1 | M11: 北海道釧路市 | N11: 0006 | O11: 01 | P11: 012062 | Q11: 01 | R11: 206 | S11: 2 | T11: 釧路市 | U11: 01 | V11: 北海道厚生局 | W11: 012068 | X11: 1 | AA11: 釧路市 | AB11: 十和田市 | AC11: 遠野市 | AD11: 名取市 | AE11: 湯沢市 | AF11: 寒河江市 | AG11: 須賀川市 | AH11: 結城市 | AI11: 日光市 | AJ11: 沼田市 | AK11: 所沢市 | AL11: 木更津市 | AM11: 台東区 | AN11: 鎌倉市 | AO11: 小千谷市 | AP11: 射水市 | AQ11: 加賀市 | AR11: 鯖江市 | AS11: 韮崎市 | AT11: 小諸市 | AU11: 中津川市 | AV11: 富士宮市 | AW11: 春日井市 | AX11: 名張市 | AY11: 守山市 | AZ11: 宮津市 | BA11: 吹田市 | BB11: 洲本市 | BC11: 桜井市 | BD11: 田辺市 | BE11: 若桜町 | BF11: 津和野町 | BG11: 井原市 | BH11: 福山市 | BI11: 下松市 | BJ11: 阿波市 | BK11: さぬき市 | BL11: 西条市 | BM11: 須崎市 | BN11: 飯塚市 | BO11: 武雄市 | BP11: 松浦市 | BQ11: 玉名市 | BR11: 臼杵市 | BS11: 日向市 | BT11: 指宿市 | BU11: 糸満市 | CC11: ⑥総合事業未実施 | CG11: 通所型サービス・活動B | CJ11: 北海道 | CK11: 釧路市 | CL11: =CJ11&CK11 -> 北海道釧路市 | CM11: 6 | CN11: =VLOOKUP(CL11,$M$6:$N$1784,2,FALSE) -> 0006 | CO11: =CM11&TEXT(CN11,0)&CK11 -> 66釧路市 | CP11: 66釧路市 | CQ11: =CO11=CP11 -> TRUE
B12: 07 | C12: 四国厚生支局 | F12: 070009 | G12: 02 | H12: 東北厚生局 | I12: 07 | J12: 福島県 | L12: 0007-1 | M12: 北海道帯広市 | N12: 0007 | O12: 01 | P12: 012070 | Q12: 01 | R12: 207 | S12: 0 | T12: 帯広市 | U12: 01 | V12: 北海道厚生局 | W12: 012076 | X12: 1 | AA12: 帯広市 | AB12: 三沢市 | AC12: 陸前高田市 | AD12: 角田市 | AE12: 鹿角市 | AF12: 上山市 | AG12: 喜多方市 | AH12: 龍ケ崎市 | AI12: 小山市 | AJ12: 館林市 | AK12: 飯能市 | AL12: 松戸市 | AM12: 墨田区 | AN12: 藤沢市 | AO12: 加茂市 | AP12: 中新川広域行政事務組合 | AQ12: 羽咋市 | AR12: 越前市 | AS12: 南アルプス市 | AT12: 伊那市 | AU12: 美濃市 | AV12: 伊東市 | AW12: 津島市 | AX12: 鳥羽市 | AY12: 甲賀市 | AZ12: 亀岡市 | BA12: 泉大津市 | BB12: 芦屋市 | BC12: 五條市 | BD12: 新宮市 | BE12: 智頭町 | BF12: 吉賀町 | BG12: 総社市 | BH12: 府中市 | BI12: 岩国市 | BJ12: 美馬市 | BK12: 東かがわ市 | BL12: 大洲市 | BM12: 宿毛市 | BN12: 八女市 | BO12: 鹿島市 | BP12: 対馬市 | BQ12: 山鹿市 | BR12: 津久見市 | BS12: 串間市 | BT12: 西之表市 | BU12: 沖縄市 | CG12: 通所型サービス・活動C | CJ12: 北海道 | CK12: 帯広市 | CL12: =CJ12&CK12 -> 北海道帯広市 | CM12: 7 | CN12: =VLOOKUP(CL12,$M$6:$N$1784,2,FALSE) -> 0007 | CO12: =CM12&TEXT(CN12,0)&CK12 -> 77帯広市 | CP12: 77帯広市 | CQ12: =CO12=CP12 -> TRUE
B13: 08 | C13: 九州厚生局 | F13: 080004 | G13: 03 | H13: 関東信越厚生局 | I13: 08 | J13: 茨城県 | L13: 0008-1 | M13: 北海道北見市 | N13: 0008 | O13: 01 | P13: 012088 | Q13: 01 | R13: 208 | S13: 8 | T13: 北見市 | U13: 01 | V13: 北海道厚生局 | W13: 012084 | X13: 1 | AA13: 北見市 | AB13: むつ市 | AC13: 釜石市 | AD13: 多賀城市 | AE13: 潟上市 | AF13: 村山市 | AG13: 相馬市 | AH13: 下妻市 | AI13: 真岡市 | AJ13: 渋川市 | AK13: 加須市 | AL13: 野田市 | AM13: 江東区 | AN13: 小田原市 | AO13: 十日町市 | AP13: 舟橋村 | AQ13: かほく市 | AR13: 永平寺町 | AS13: 北杜市 | AT13: 駒ヶ根市 | AU13: 瑞浪市 | AV13: 島田市 | AW13: 碧南市 | AX13: いなべ市 | AY13: 野洲市 | AZ13: 城陽市 | BA13: 高槻市 | BB13: 伊丹市 | BC13: 御所市 | BD13: 紀の川市 | BE13: 八頭町 | BF13: 邑智郡総合事務組合 | BG13: 高梁市 | BH13: 三次市 | BI13: 光市 | BJ13: 勝浦町 | BK13: 三豊市 | BL13: 伊予市 | BM13: 土佐清水市 | BN13: 筑後市 | BO13: 嬉野市 | BP13: 壱岐市 | BQ13: 菊池市 | BR13: 竹田市 | BS13: 西都市 | BT13: 垂水市 | BU13: うるま市 | CG13: その他生活支援サービス（見守り） | CJ13: 北海道 | CK13: 北見市 | CL13: =CJ13&CK13 -> 北海道北見市 | CM13: 8 | CN13: =VLOOKUP(CL13,$M$6:$N$1784,2,FALSE) -> 0008 | CO13: =CM13&TEXT(CN13,0)&CK13 -> 88北見市 | CP13: 88北見市 | CQ13: =CO13=CP13 -> TRUE
F14: 090000 | G14: 03 | H14: 関東信越厚生局 | I14: 09 | J14: 栃木県 | L14: 0009-1 | M14: 北海道夕張市 | N14: 0009 | O14: 01 | P14: 012096 | Q14: 01 | R14: 209 | S14: 6 | T14: 夕張市 | U14: 01 | V14: 北海道厚生局 | W14: 012092 | X14: 1 | AA14: 夕張市 | AB14: つがる市 | AC14: 奥州市 | AD14: 岩沼市 | AE14: 北秋田市 | AF14: 長井市 | AG14: 二本松市 | AH14: 常総市 | AI14: 大田原市 | AJ14: 藤岡市 | AK14: 本庄市 | AL14: 茂原市 | AM14: 品川区 | AN14: 茅ヶ崎市 | AO14: 見附市 | AP14: 上市町 | AQ14: 白山市 | AR14: 池田町 | AS14: 甲斐市 | AT14: 中野市 | AU14: 羽島市 | AV14: 富士市 | AW14: 刈谷市 | AX14: 志摩市 | AY14: 湖南市 | AZ14: 向日市 | BA14: 貝塚市 | BB14: 相生市 | BC14: 生駒市 | BD14: 岩出市 | BE14: 三朝町 | BF14: 川本町 | BG14: 新見市 | BH14: 庄原市 | BI14: 長門市 | BJ14: 上勝町 | BK14: 土庄町 | BL14: 四国中央市 | BM14: 四万十市 | BN14: 大川市 | BO14: 大町町 | BP14: 五島市 | BQ14: 宇土市 | BR14: 豊後高田市 | BS14: えびの市 | BT14: 薩摩川内市 | BU14: 宮古島市 | CG14: その他生活支援サービス（配食） | CJ14: 北海道 | CK14: 夕張市 | CL14: =CJ14&CK14 -> 北海道夕張市 | CM14: 9 | CN14: =VLOOKUP(CL14,$M$6:$N$1784,2,FALSE) -> 0009 | CO14: =CM14&TEXT(CN14,0)&CK14 -> 99夕張市 | CP14: 99夕張市 | CQ14: =CO14=CP14 -> TRUE
F15: 100005 | G15: 03 | H15: 関東信越厚生局 | I15: 10 | J15: 群馬県 | L15: 0010-1 | M15: 北海道岩見沢市 | N15: 0010 | O15: 01 | P15: 012104 | Q15: 01 | R15: 210 | S15: 4 | T15: 岩見沢市 | U15: 01 | V15: 北海道厚生局 | W15: 012106 | X15: 1 | AA15: 岩見沢市 | AB15: 平川市 | AC15: 滝沢市 | AD15: 登米市 | AE15: 小坂町 | AF15: 天童市 | AG15: 田村市 | AH15: 常陸太田市 | AI15: 矢板市 | AJ15: 富岡市 | AK15: 東松山市 | AL15: 成田市 | AM15: 目黒区 | AN15: 逗子市 | AO15: 村上市 | AP15: 立山町 | AQ15: 能美市 | AR15: 南越前町 | AS15: 笛吹市 | AT15: 飯山市 | AU15: 恵那市 | AV15: 磐田市 | AW15: 豊田市 | AX15: 伊賀市 | AY15: 高島市 | AZ15: 長岡京市 | BA15: 枚方市 | BB15: 豊岡市 | BC15: 香芝市 | BD15: 紀美野町 | BE15: 湯梨浜町 | BF15: 美郷町 | BG15: 備前市 | BH15: 大竹市 | BI15: 柳井市 | BJ15: 佐那河内村 | BK15: 小豆島町 | BL15: 西予市 | BM15: 香南市 | BN15: 行橋市 | BO15: 江北町 | BP15: 西海市 | BQ15: 上天草市 | BR15: 杵築市 | BS15: 三股町 | BT15: 日置市 | BU15: 多良間村 | CG15: その他生活支援サービス（その他） | CJ15: 北海道 | CK15: 岩見沢市 | CL15: =CJ15&CK15 -> 北海道岩見沢市 | CM15: 10 | CN15: =VLOOKUP(CL15,$M$6:$N$1784,2,FALSE) -> 0010 | CO15: =CM15&TEXT(CN15,0)&CK15 -> 1010岩見沢市 | CP15: 1010岩見沢市 | CQ15: =CO15=CP15 -> TRUE
F16: 110001 | G16: 03 | H16: 関東信越厚生局 | I16: 11 | J16: 埼玉県 | L16: 0011-1 | M16: 北海道網走市 | N16: 0011 | O16: 01 | P16: 012112 | Q16: 01 | R16: 211 | S16: 2 | T16: 網走市 | U16: 01 | V16: 北海道厚生局 | W16: 012114 | X16: 1 | AA16: 網走市 | AB16: 平内町 | AC16: 雫石町 | AD16: 栗原市 | AE16: 上小阿仁村 | AF16: 東根市 | AG16: 南相馬市 | AH16: 高萩市 | AI16: 那須塩原市 | AJ16: 安中市 | AK16: 春日部市 | AL16: 佐倉市 | AM16: 大田区 | AN16: 三浦市 | AO16: 燕市 | AP16: 砺波地方介護保険組合 | AQ16: 野々市市 | AR16: 越前町 | AS16: 上野原市 | AT16: 塩尻市 | AU16: 美濃加茂市 | AV16: 焼津市 | AW16: 安城市 | AX16: 木曽岬町 | AY16: 東近江市 | AZ16: 八幡市 | BA16: 茨木市 | BB16: 加古川市 | BC16: 葛城市 | BD16: かつらぎ町 | BE16: 琴浦町 | BF16: 邑南町 | BG16: 瀬戸内市 | BH16: 東広島市 | BI16: 美祢市 | BJ16: 石井町 | BK16: 三木町 | BL16: 東温市 | BM16: 香美市 | BN16: 中間市 | BO16: 白石町 | BP16: 長与町 | BQ16: 宇城市 | BR16: 宇佐市 | BS16: 高原町 | BT16: 曽於市 | BU16: 竹富町 | CG16: 一般介護予防事業 | CJ16: 北海道 | CK16: 網走市 | CL16: =CJ16&CK16 -> 北海道網走市 | CM16: 11 | CN16: =VLOOKUP(CL16,$M$6:$N$1784,2,FALSE) -> 0011 | CO16: =CM16&TEXT(CN16,0)&CK16 -> 1111網走市 | CP16: 1111網走市 | CQ16: =CO16=CP16 -> TRUE
F17: 120006 | G17: 03 | H17: 関東信越厚生局 | I17: 12 | J17: 千葉県 | L17: 0012-1 | M17: 北海道留萌市 | N17: 0012 | O17: 01 | P17: 012120 | Q17: 01 | R17: 212 | S17: 0 | T17: 留萌市 | U17: 01 | V17: 北海道厚生局 | W17: 012122 | X17: 1 | AA17: 留萌市 | AB17: 今別町 | AC17: 紫波町 | AD17: 東松島市 | AE17: 藤里町 | AF17: 尾花沢市 | AG17: 伊達市 | AH17: 北茨城市 | AI17: さくら市 | AJ17: みどり市 | AK17: 狭山市 | AL17: 東金市 | AM17: 世田谷区 | AN17: 秦野市 | AO17: 糸魚川市 | AP17: 砺波市 | AQ17: 川北町 | AR17: 美浜町 | AS17: 甲州市 | AT17: 佐久市 | AU17: 土岐市 | AV17: 掛川市 | AW17: 西尾市 | AX17: 東員町 | AY17: 米原市 | AZ17: 京田辺市 | BA17: 八尾市 | BB17: 赤穂市 | BC17: 宇陀市 | BD17: 九度山町 | BE17: 北栄町 | BF17: 浜田地区広域行政組合 | BG17: 赤磐市 | BH17: 廿日市市 | BI17: 周南市 | BJ17: 神山町 | BK17: 直島町 | BL17: 上島町 | BM17: 東洋町 | BN17: 小郡市 | BO17: 太良町 | BP17: 時津町 | BQ17: 阿蘇市 | BR17: 豊後大野市 | BS17: 国富町 | BT17: 霧島市 | BU17: 与那国町 | CJ17: 北海道 | CK17: 留萌市 | CL17: =CJ17&CK17 -> 北海道留萌市 | CM17: 12 | CN17: =VLOOKUP(CL17,$M$6:$N$1784,2,FALSE) -> 0012 | CO17: =CM17&TEXT(CN17,0)&CK17 -> 1212留萌市 | CP17: 1212留萌市 | CQ17: =CO17=CP17 -> TRUE
F18: 130001 | G18: 03 | H18: 関東信越厚生局 | I18: 13 | J18: 東京都 | L18: 0013-1 | M18: 北海道苫小牧市 | N18: 0013 | O18: 01 | P18: 012138 | Q18: 01 | R18: 213 | S18: 8 | T18: 苫小牧市 | U18: 01 | V18: 北海道厚生局 | W18: 012131 | X18: 1 | AA18: 苫小牧市 | AB18: 蓬田村 | AC18: 矢巾町 | AD18: 大崎市 | AE18: 三種町 | AF18: 南陽市 | AG18: 本宮市 | AH18: 笠間市 | AI18: 那須烏山市 | AJ18: 榛東村 | AK18: 羽生市 | AL18: 旭市 | AM18: 渋谷区 | AN18: 厚木市 | AO18: 妙高市 | AP18: 小矢部市 | AQ18: 津幡町 | AR18: 高浜町 | AS18: 中央市 | AT18: 千曲市 | AU18: 各務原市 | AV18: 藤枝市 | AW18: 犬山市 | AX18: 菰野町 | AY18: 栗東市 | AZ18: 京丹後市 | BA18: 泉佐野市 | BB18: 西脇市 | BC18: 山添村 | BD18: 高野町 | BE18: 大山町 | BF18: 浜田市 | BG18: 真庭市 | BH18: 安芸高田市 | BI18: 山陽小野田市 | BJ18: 那賀町 | BK18: 宇多津町 | BL18: 久万高原町 | BM18: 芸西村 | BN18: 筑紫野市 | BO18: 鳥栖地区広域市町村圏組合 | BP18: 東彼杵町 | BQ18: 天草市 | BR18: 由布市 | BS18: 綾町 | BT18: いちき串木野市 | BU18: 沖縄県介護保険広域連合 | CJ18: 北海道 | CK18: 苫小牧市 | CL18: =CJ18&CK18 -> 北海道苫小牧市 | CM18: 13 | CN18: =VLOOKUP(CL18,$M$6:$N$1784,2,FALSE) -> 0013 | CO18: =CM18&TEXT(CN18,0)&CK18 -> 1313苫小牧市 | CP18: 1313苫小牧市 | CQ18: =CO18=CP18 -> TRUE
F19: 140007 | G19: 03 | H19: 関東信越厚生局 | I19: 14 | J19: 神奈川県 | L19: 0014-1 | M19: 北海道稚内市 | N19: 0014 | O19: 01 | P19: 012146 | Q19: 01 | R19: 214 | S19: 6 | T19: 稚内市 | U19: 01 | V19: 北海道厚生局 | W19: 012149 | X19: 1 | AA19: 稚内市 | AB19: 外ヶ浜町 | AC19: 西和賀町 | AD19: 富谷市 | AE19: 八峰町 | AF19: 山辺町 | AG19: 桑折町 | AH19: 取手市 | AI19: 下野市 | AJ19: 吉岡町 | AK19: 鴻巣市 | AL19: 習志野市 | AM19: 中野区 | AN19: 大和市 | AO19: 五泉市 | AP19: 南砺市 | AQ19: 内灘町 | AR19: おおい町 | AS19: 市川三郷町 | AT19: 東御市 | AU19: 可児市 | AV19: 御殿場市 | AW19: 常滑市 | AX19: 朝日町 | AY19: 日野町 | AZ19: 南丹市 | BA19: 富田林市 | BB19: 宝塚市 | BC19: 平群町 | BD19: 湯浅町 | BE19: 日南町 | BF19: 江津市 | BG19: 美作市 | BH19: 江田島市 | BI19: 周防大島町 | BJ19: 牟岐町 | BK19: 綾川町 | BL19: 松前町 | BM19: 本山町 | BN19: 春日市 | BO19: 鳥栖市 | BP19: 川棚町 | BQ19: 合志市 | BR19: 国東市 | BS19: 高鍋町 | BT19: 南さつま市 | BU19: 豊見城市 | CJ19: 北海道 | CK19: 稚内市 | CL19: =CJ19&CK19 -> 北海道稚内市 | CM19: 14 | CN19: =VLOOKUP(CL19,$M$6:$N$1784,2,FALSE) -> 0014 | CO19: =CM19&TEXT(CN19,0)&CK19 -> 1414稚内市 | CP19: 1414稚内市 | CQ19: =CO19=CP19 -> TRUE
F20: 150002 | G20: 03 | H20: 関東信越厚生局 | I20: 15 | J20: 新潟県 | L20: 0015-1 | M20: 北海道美唄市 | N20: 0015 | O20: 01 | P20: 012153 | Q20: 01 | R20: 215 | S20: 3 | T20: 美唄市 | U20: 01 | V20: 北海道厚生局 | W20: 012157 | X20: 1 | AA20: 美唄市 | AB20: 鰺ヶ沢町 | AC20: 金ケ崎町 | AD20: 蔵王町 | AE20: 五城目町 | AF20: 中山町 | AG20: 国見町 | AH20: 牛久市 | AI20: 上三川町 | AJ20: 上野村 | AK20: 上尾市 | AL20: 柏市 | AM20: 杉並区 | AN20: 伊勢原市 | AO20: 上越市 | AP20: 新川地域介護保険・ケーブルテレビ事業組合 | AQ20: 志賀町 | AR20: 若狭町 | AS20: 早川町 | AT20: 安曇野市 | AU20: 山県市 | AV20: 袋井市 | AW20: 江南市 | AX20: 川越町 | AY20: 竜王町 | AZ20: 木津川市 | BA20: 寝屋川市 | BB20: 三木市 | BC20: 三郷町 | BD20: 広川町 | BE20: 日野町 | BF20: 雲南広域連合 | BG20: 浅口市 | BH20: 府中町 | BI20: 和木町 | BJ20: 美波町 | BK20: 琴平町 | BL20: 砥部町 | BM20: 大豊町 | BN20: 大野城市 | BO20: 基山町 | BP20: 波佐見町 | BQ20: 美里町 | BR20: 姫島村 | BS20: 新富町 | BT20: 志布志市 | BU20: 南城市 | CJ20: 北海道 | CK20: 美唄市 | CL20: =CJ20&CK20 -> 北海道美唄市 | CM20: 15 | CN20: =VLOOKUP(CL20,$M$6:$N$1784,2,FALSE) -> 0015 | CO20: =CM20&TEXT(CN20,0)&CK20 -> 1515美唄市 | CP20: 1515美唄市 | CQ20: =CO20=CP20 -> TRUE
F21: 160008 | G21: 04 | H21: 東海北陸厚生局 | I21: 16 | J21: 富山県 | L21: 0016-1 | M21: 北海道芦別市 | N21: 0016 | O21: 01 | P21: 012161 | Q21: 01 | R21: 216 | S21: 1 | T21: 芦別市 | U21: 01 | V21: 北海道厚生局 | W21: 012165 | X21: 1 | AA21: 芦別市 | AB21: 深浦町 | AC21: 住田町 | AD21: 七ヶ宿町 | AE21: 八郎潟町 | AF21: 河北町 | AG21: 川俣町 | AH21: つくば市 | AI21: 益子町 | AJ21: 神流町 | AK21: 草加市 | AL21: 勝浦市 | AM21: 豊島区 | AN21: 海老名市 | AO21: 阿賀野市 | AP21: 黒部市 | AQ21: 宝達志水町 | AR21: 坂井地区広域連合 | AS21: 身延町 | AT21: 小海町 | AU21: 飛騨市 | AV21: 下田市 | AW21: 小牧市 | AX21: 多気町 | AY21: 愛荘町 | AZ21: 大山崎町 | BA21: 河内長野市 | BB21: 高砂市 | BC21: 斑鳩町 | BD21: 有田川町 | BE21: 江府町 | BF21: 雲南市 | BG21: 和気町 | BH21: 海田町 | BI21: 上関町 | BJ21: 海陽町 | BK21: 多度津町 | BL21: 内子町 | BM21: 土佐町 | BN21: 宗像市 | BO21: みやき町 | BP21: 小値賀町 | BQ21: 玉東町 | BR21: 日出町 | BS21: 西米良村 | BT21: 奄美市 | BU21: 国頭村 | CJ21: 北海道 | CK21: 芦別市 | CL21: =CJ21&CK21 -> 北海道芦別市 | CM21: 16 | CN21: =VLOOKUP(CL21,$M$6:$N$1784,2,FALSE) -> 0016 | CO21: =CM21&TEXT(CN21,0)&CK21 -> 1616芦別市 | CP21: 1616芦別市 | CQ21: =CO21=CP21 -> TRUE
F22: 170003 | G22: 04 | H22: 東海北陸厚生局 | I22: 17 | J22: 石川県 | L22: 0017-1 | M22: 北海道江別市 | N22: 0017 | O22: 01 | P22: 012179 | Q22: 01 | R22: 217 | S22: 9 | T22: 江別市 | U22: 01 | V22: 北海道厚生局 | W22: 012173 | X22: 1 | AA22: 江別市 | AB22: 西目屋村 | AC22: 大槌町 | AD22: 大河原町 | AE22: 井川町 | AF22: 西川町 | AG22: 大玉村 | AH22: ひたちなか市 | AI22: 茂木町 | AJ22: 下仁田町 | AK22: 越谷市 | AL22: 市原市 | AM22: 北区 | AN22: 座間市 | AO22: 佐渡市 | AP22: 入善町 | AQ22: 中能登町 | AR22: あわら市 | AS22: 南部町 | AT22: 川上村 | AU22: 郡上市 | AV22: 裾野市 | AW22: 稲沢市 | AX22: 明和町 | AY22: 豊郷町 | AZ22: 久御山町 | BA22: 松原市 | BB22: 川西市 | BC22: 安堵町 | BD22: 美浜町 | BE22: 南部箕蚊屋広域連合 | BF22: 奥出雲町 | BG22: 早島町 | BH22: 熊野町 | BI22: 田布施町 | BJ22: 松茂町 | BK22: まんのう町 | BL22: 伊方町 | BM22: 大川村 | BN22: 太宰府市 | BO22: 上峰町 | BP22: 佐々町 | BQ22: 南関町 | BR22: 九重町 | BS22: 木城町 | BT22: 南九州市 | BU22: 大宜味村 | CJ22: 北海道 | CK22: 江別市 | CL22: =CJ22&CK22 -> 北海道江別市 | CM22: 17 | CN22: =VLOOKUP(CL22,$M$6:$N$1784,2,FALSE) -> 0017 | CO22: =CM22&TEXT(CN22,0)&CK22 -> 1717江別市 | CP22: 1717江別市 | CQ22: =CO22=CP22 -> TRUE
F23: 180009 | G23: 05 | H23: 近畿厚生局 | I23: 18 | J23: 福井県 | L23: 0018-1 | M23: 北海道赤平市 | N23: 0018 | O23: 01 | P23: 012187 | Q23: 01 | R23: 218 | S23: 7 | T23: 赤平市 | U23: 01 | V23: 北海道厚生局 | W23: 012181 | X23: 1 | AA23: 赤平市 | AB23: 藤崎町 | AC23: 山田町 | AD23: 村田町 | AE23: 大潟村 | AF23: 朝日町 | AG23: 鏡石町 | AH23: 鹿嶋市 | AI23: 市貝町 | AJ23: 南牧村 | AK23: 蕨市 | AL23: 流山市 | AM23: 荒川区 | AN23: 南足柄市 | AO23: 魚沼市 | AP23: 朝日町 | AQ23: 穴水町 | AR23: 坂井市 | AS23: 富士川町 | AT23: 南牧村 | AU23: 下呂市 | AV23: 湖西市 | AW23: 知立市 | AX23: 大台町 | AY23: 甲良町 | AZ23: 井手町 | BA23: 大東市 | BB23: 小野市 | BC23: 川西町 | BD23: 日高町 | BE23: 南部町 | BF23: 飯南町 | BG23: 里庄町 | BH23: 坂町 | BI23: 平生町 | BJ23: 北島町 | BL23: 松野町 | BM23: いの町 | BN23: 古賀市 | BO23: 佐賀中部広域連合 | BP23: 新上五島町 | BQ23: 長洲町 | BR23: 玖珠町 | BS23: 川南町 | BT23: 伊佐市 | BU23: 東村 | CJ23: 北海道 | CK23: 赤平市 | CL23: =CJ23&CK23 -> 北海道赤平市 | CM23: 18 | CN23: =VLOOKUP(CL23,$M$6:$N$1784,2,FALSE) -> 0018 | CO23: =CM23&TEXT(CN23,0)&CK23 -> 1818赤平市 | CP23: 1818赤平市 | CQ23: =CO23=CP23 -> TRUE
F24: 190004 | G24: 03 | H24: 関東信越厚生局 | I24: 19 | J24: 山梨県 | L24: 0019-1 | M24: 北海道紋別市 | N24: 0019 | O24: 01 | P24: 012195 | Q24: 01 | R24: 219 | S24: 5 | T24: 紋別市 | U24: 01 | V24: 北海道厚生局 | W24: 012190 | X24: 1 | AA24: 紋別市 | AB24: 大鰐町 | AC24: 岩泉町 | AD24: 柴田町 | AE24: 羽後町 | AF24: 大江町 | AG24: 天栄村 | AH24: 潮来市 | AI24: 芳賀町 | AJ24: 甘楽町 | AK24: 戸田市 | AL24: 八千代市 | AM24: 板橋区 | AN24: 綾瀬市 | AO24: 南魚沼市 | AQ24: 能登町 | AS24: 昭和町 | AT24: 南相木村 | AU24: 海津市 | AV24: 伊豆市 | AW24: 尾張旭市 | AX24: 玉城町 | AY24: 多賀町 | AZ24: 宇治田原町 | BA24: 和泉市 | BB24: 三田市 | BC24: 三宅町 | BD24: 由良町 | BE24: 伯耆町 | BF24: 隠岐広域連合 | BG24: 矢掛町 | BH24: 安芸太田町 | BI24: 阿武町 | BJ24: 藍住町 | BL24: 鬼北町 | BM24: 仁淀川町 | BN24: 福津市 | BO24: 佐賀市 | BP24: 島原地域広域市町村圏組合 | BQ24: 和水町 | BS24: 都農町 | BT24: 姶良市 | BU24: 今帰仁村 | CJ24: 北海道 | CK24: 紋別市 | CL24: =CJ24&CK24 -> 北海道紋別市 | CM24: 19 | CN24: =VLOOKUP(CL24,$M$6:$N$1784,2,FALSE) -> 0019 | CO24: =CM24&TEXT(CN24,0)&CK24 -> 1919紋別市 | CP24: 1919紋別市 | CQ24: =CO24=CP24 -> TRUE
F25: 200000 | G25: 03 | H25: 関東信越厚生局 | I25: 20 | J25: 長野県 | L25: 0020-1 | M25: 北海道士別市 | N25: 0020 | O25: 01 | P25: 012203 | Q25: 01 | R25: 220 | S25: 3 | T25: 士別市 | U25: 01 | V25: 北海道厚生局 | W25: 012203 | X25: 1 | AA25: 士別市 | AB25: 田舎館村 | AC25: 田野畑村 | AD25: 川崎町 | AE25: 東成瀬村 | AF25: 大石田町 | AG25: 下郷町 | AH25: 守谷市 | AI25: 壬生町 | AJ25: 中之条町 | AK25: 入間市 | AL25: 我孫子市 | AM25: 練馬区 | AN25: 葉山町 | AO25: 胎内市 | AS25: 道志村 | AT25: 北相木村 | AU25: 岐南町 | AV25: 御前崎市 | AW25: 高浜市 | AX25: 度会町 | AZ25: 笠置町 | BA25: 箕面市 | BB25: 加西市 | BC25: 田原本町 | BD25: 印南町 | BE25: 日吉津村 | BF25: 隠岐の島町 | BG25: 新庄村 | BH25: 北広島町 | BJ25: 板野町 | BL25: 愛南町 | BM25: 中土佐町 | BN25: 嘉麻市 | BO25: 多久市 | BP25: 島原市 | BQ25: 大津町 | BS25: 門川町 | BT25: 三島村 | BU25: 本部町 | CJ25: 北海道 | CK25: 士別市 | CL25: =CJ25&CK25 -> 北海道士別市 | CM25: 20 | CN25: =VLOOKUP(CL25,$M$6:$N$1784,2,FALSE) -> 0020 | CO25: =CM25&TEXT(CN25,0)&CK25 -> 2020士別市 | CP25: 2020士別市 | CQ25: =CO25=CP25 -> TRUE
F26: 210005 | G26: 04 | H26: 東海北陸厚生局 | I26: 21 | J26: 岐阜県 | L26: 0021-1 | M26: 北海道名寄市 | N26: 0021 | O26: 01 | P26: 012211 | Q26: 01 | R26: 221 | S26: 1 | T26: 名寄市 | U26: 01 | V26: 北海道厚生局 | W26: 012211 | X26: 1 | AA26: 名寄市 | AB26: 板柳町 | AC26: 二戸地区広域行政事務組合 | AD26: 丸森町 | AE26: 由利本荘市 | AF26: 金山町 | AG26: 檜枝岐村 | AH26: 常陸大宮市 | AI26: 野木町 | AJ26: 長野原町 | AK26: 朝霞市 | AL26: 鴨川市 | AM26: 足立区 | AN26: 寒川町 | AO26: 聖籠町 | AS26: 西桂町 | AT26: 佐久穂町 | AU26: 笠松町 | AV26: 菊川市 | AW26: 岩倉市 | AX26: 大紀町 | AZ26: 和束町 | BA26: 柏原市 | BB26: 丹波篠山市 | BC26: 曽爾村 | BD26: みなべ町 | BF26: 西ノ島町 | BG26: 鏡野町 | BH26: 大崎上島町 | BJ26: 上板町 | BM26: 佐川町 | BN26: 朝倉市 | BO26: 小城市 | BP26: 雲仙市 | BQ26: 菊陽町 | BS26: 諸塚村 | BT26: 十島村 | BU26: 恩納村 | CJ26: 北海道 | CK26: 名寄市 | CL26: =CJ26&CK26 -> 北海道名寄市 | CM26: 21 | CN26: =VLOOKUP(CL26,$M$6:$N$1784,2,FALSE) -> 0021 | CO26: =CM26&TEXT(CN26,0)&CK26 -> 2121名寄市 | CP26: 2121名寄市 | CQ26: =CO26=CP26 -> TRUE
F27: 220001 | G27: 04 | H27: 東海北陸厚生局 | I27: 22 | J27: 静岡県 | L27: 0022-1 | M27: 北海道三笠市 | N27: 0022 | O27: 01 | P27: 012229 | Q27: 01 | R27: 222 | S27: 9 | T27: 三笠市 | U27: 01 | V27: 北海道厚生局 | W27: 012220 | X27: 1 | AA27: 三笠市 | AB27: 鶴田町 | AC27: 二戸市 | AD27: 亘理町 | AE27: にかほ市 | AF27: 最上町 | AG27: 只見町 | AH27: 那珂市 | AI27: 塩谷町 | AJ27: 嬬恋村 | AK27: 志木市 | AL27: 鎌ケ谷市 | AM27: 葛飾区 | AN27: 大磯町 | AO27: 弥彦村 | AS27: 忍野村 | AT27: 軽井沢町 | AU27: 養老町 | AV27: 伊豆の国市 | AW27: 豊明市 | AX27: 南伊勢町 | AZ27: 精華町 | BA27: 羽曳野市 | BB27: 養父市 | BC27: 御杖村 | BD27: 日高川町 | BF27: 海士町 | BG27: 勝央町 | BH27: 世羅町 | BJ27: つるぎ町 | BM27: 越知町 | BN27: みやま市 | BO27: 神埼市 | BP27: 南島原市 | BQ27: 南小国町 | BS27: 椎葉村 | BT27: さつま町 | BU27: 宜野座村 | CJ27: 北海道 | CK27: 三笠市 | CL27: =CJ27&CK27 -> 北海道三笠市 | CM27: 22 | CN27: =VLOOKUP(CL27,$M$6:$N$1784,2,FALSE) -> 0022 | CO27: =CM27&TEXT(CN27,0)&CK27 -> 2222三笠市 | CP27: 2222三笠市 | CQ27: =CO27=CP27 -> TRUE
F28: 230006 | G28: 04 | H28: 東海北陸厚生局 | I28: 23 | J28: 愛知県 | L28: 0023-1 | M28: 北海道根室市 | N28: 0023 | O28: 01 | P28: 012237 | Q28: 01 | R28: 223 | S28: 7 | T28: 根室市 | U28: 01 | V28: 北海道厚生局 | W28: 012238 | X28: 1 | AA28: 根室市 | AB28: 中泊町 | AC28: 一戸町 | AD28: 山元町 | AE28: 大曲仙北広域市町村圏組合 | AF28: 舟形町 | AG28: 南会津町 | AH28: 筑西市 | AI28: 高根沢町 | AJ28: 草津町 | AK28: 和光市 | AL28: 君津市 | AM28: 江戸川区 | AN28: 二宮町 | AO28: 田上町 | AS28: 山中湖村 | AT28: 御代田町 | AU28: 垂井町 | AV28: 牧之原市 | AW28: 日進市 | AX28: 紀北広域連合 | AZ28: 南山城村 | BA28: 摂津市 | BB28: 丹波市 | BC28: 高取町 | BD28: 白浜町 | BF28: 知夫村 | BG28: 奈義町 | BH28: 神石高原町 | BJ28: みよし広域連合 | BM28: 梼原町 | BN28: 糸島市 | BO28: 吉野ヶ里町 | BQ28: 小国町 | BS28: 美郷町 | BT28: 長島町 | BU28: 金武町 | CJ28: 北海道 | CK28: 根室市 | CL28: =CJ28&CK28 -> 北海道根室市 | CM28: 23 | CN28: =VLOOKUP(CL28,$M$6:$N$1784,2,FALSE) -> 0023 | CO28: =CM28&TEXT(CN28,0)&CK28 -> 2323根室市 | CP28: 2323根室市 | CQ28: =CO28=CP28 -> TRUE
F29: 240001 | G29: 04 | H29: 東海北陸厚生局 | I29: 24 | J29: 三重県 | L29: 0024-1 | M29: 北海道千歳市 | N29: 0024 | O29: 01 | P29: 012245 | Q29: 01 | R29: 224 | S29: 5 | T29: 千歳市 | U29: 01 | V29: 北海道厚生局 | W29: 012246 | X29: 1 | AA29: 千歳市 | AB29: 野辺地町 | AC29: 軽米町 | AD29: 松島町 | AE29: 大仙市 | AF29: 真室川町 | AG29: 北塩原村 | AH29: 坂東市 | AI29: 那須町 | AJ29: 高山村 | AK29: 新座市 | AL29: 富津市 | AM29: 八王子市 | AN29: 中井町 | AO29: 阿賀町 | AS29: 鳴沢村 | AT29: 立科町 | AU29: 関ヶ原町 | AV29: 東伊豆町 | AW29: 愛西市 | AX29: 尾鷲市 | AZ29: 京丹波町 | BA29: 高石市 | BB29: 南あわじ市 | BC29: 明日香村 | BD29: 上富田町 | BG29: 西粟倉村 | BJ29: 三好市 | BM29: 日高村 | BN29: 那珂川市 | BQ29: 産山村 | BS29: 高千穂町 | BT29: 湧水町 | BU29: 伊江村 | CJ29: 北海道 | CK29: 千歳市 | CL29: =CJ29&CK29 -> 北海道千歳市 | CM29: 24 | CN29: =VLOOKUP(CL29,$M$6:$N$1784,2,FALSE) -> 0024 | CO29: =CM29&TEXT(CN29,0)&CK29 -> 2424千歳市 | CP29: 2424千歳市 | CQ29: =CO29=CP29 -> TRUE
F30: 250007 | G30: 05 | H30: 近畿厚生局 | I30: 25 | J30: 滋賀県 | L30: 0025-1 | M30: 北海道滝川市 | N30: 0025 | O30: 01 | P30: 012252 | Q30: 01 | R30: 225 | S30: 2 | T30: 滝川市 | U30: 01 | V30: 北海道厚生局 | W30: 012254 | X30: 1 | AA30: 滝川市 | AB30: 七戸町 | AC30: 九戸村 | AD30: 七ヶ浜町 | AE30: 仙北市 | AF30: 大蔵村 | AG30: 西会津町 | AH30: 稲敷市 | AI30: 那珂川町 | AJ30: 東吾妻町 | AK30: 桶川市 | AL30: 浦安市 | AM30: 立川市 | AN30: 大井町 | AO30: 出雲崎町 | AS30: 富士河口湖町 | AT30: 青木村 | AU30: 坂祝町 | AV30: 河津町 | AW30: 清須市 | AX30: 紀北町 | AZ30: 伊根町 | BA30: 藤井寺市 | BB30: 朝来市 | BC30: 上牧町 | BD30: すさみ町 | BG30: 久米南町 | BJ30: 東みよし町 | BM30: 津野町 | BN30: 粕屋町 | BQ30: 高森町 | BS30: 日之影町 | BT30: 大崎町 | BU30: 読谷村 | CJ30: 北海道 | CK30: 滝川市 | CL30: =CJ30&CK30 -> 北海道滝川市 | CM30: 25 | CN30: =VLOOKUP(CL30,$M$6:$N$1784,2,FALSE) -> 0025 | CO30: =CM30&TEXT(CN30,0)&CK30 -> 2525滝川市 | CP30: 2525滝川市 | CQ30: =CO30=CP30 -> TRUE
F31: 260002 | G31: 05 | H31: 近畿厚生局 | I31: 26 | J31: 京都府 | L31: 0026-1 | M31: 北海道砂川市 | N31: 0026 | O31: 01 | P31: 012260 | Q31: 01 | R31: 226 | S31: 0 | T31: 砂川市 | U31: 01 | V31: 北海道厚生局 | W31: 012262 | X31: 1 | AA31: 砂川市 | AB31: 六戸町 | AC31: 盛岡北部行政事務組合 | AD31: 利府町 | AE31: 美郷町 | AF31: 鮭川村 | AG31: 磐梯町 | AH31: かすみがうら市 | AJ31: 片品村 | AK31: 久喜市 | AL31: 四街道市 | AM31: 武蔵野市 | AN31: 松田町 | AO31: 湯沢町 | AS31: 小菅村 | AT31: 長和町 | AU31: 富加町 | AV31: 南伊豆町 | AW31: 北名古屋市 | AX31: 紀南介護保険広域連合 | AZ31: 与謝野町 | BA31: 東大阪市 | BB31: 淡路市 | BC31: 王寺町 | BD31: 那智勝浦町 | BG31: 美咲町 | BM31: 四万十町 | BN31: 苅田町 | BQ31: 西原村 | BS31: 五ヶ瀬町 | BT31: 東串良町 | BU31: 嘉手納町 | CJ31: 北海道 | CK31: 砂川市 | CL31: =CJ31&CK31 -> 北海道砂川市 | CM31: 26 | CN31: =VLOOKUP(CL31,$M$6:$N$1784,2,FALSE) -> 0026 | CO31: =CM31&TEXT(CN31,0)&CK31 -> 2626砂川市 | CP31: 2626砂川市 | CQ31: =CO31=CP31 -> TRUE
F32: 270008 | G32: 05 | H32: 近畿厚生局 | I32: 27 | J32: 大阪府 | L32: 0027-1 | M32: 北海道深川市 | N32: 0027 | O32: 01 | P32: 012286 | Q32: 01 | R32: 228 | S32: 6 | T32: 深川市 | U32: 01 | V32: 北海道厚生局 | W32: 012289 | X32: 1 | AA32: 深川市 | AB32: 横浜町 | AC32: 八幡平市 | AD32: 大和町 | AF32: 戸沢村 | AG32: 猪苗代町 | AH32: 桜川市 | AJ32: 川場村 | AK32: 北本市 | AL32: 袖ケ浦市 | AM32: 三鷹市 | AN32: 山北町 | AO32: 津南町 | AS32: 丹波山村 | AT32: 辰野町 | AU32: 川辺町 | AV32: 松崎町 | AW32: 弥富市 | AX32: 熊野市 | BA32: 泉南市 | BB32: 宍粟市 | BC32: 広陵町 | BD32: 太地町 | BG32: 吉備中央町 | BM32: 大月町 | BN32: みやこ町 | BQ32: 南阿蘇村 | BT32: 錦江町 | BU32: 北谷町 | CJ32: 北海道 | CK32: 深川市 | CL32: =CJ32&CK32 -> 北海道深川市 | CM32: 27 | CN32: =VLOOKUP(CL32,$M$6:$N$1784,2,FALSE) -> 0027 | CO32: =CM32&TEXT(CN32,0)&CK32 -> 2727深川市 | CP32: 2727深川市 | CQ32: =CO32=CP32 -> TRUE
F33: 280003 | G33: 05 | H33: 近畿厚生局 | I33: 28 | J33: 兵庫県 | L33: 0028-1 | M33: 北海道富良野市 | N33: 0028 | O33: 01 | P33: 012294 | Q33: 01 | R33: 229 | S33: 4 | T33: 富良野市 | U33: 01 | V33: 北海道厚生局 | W33: 012297 | X33: 1 | AA33: 富良野市 | AB33: 東北町 | AC33: 岩手町 | AD33: 大郷町 | AF33: 高畠町 | AG33: 会津坂下町 | AH33: 神栖市 | AJ33: 昭和村 | AK33: 八潮市 | AL33: 八街市 | AM33: 青梅市 | AN33: 開成町 | AO33: 刈羽村 | AT33: 箕輪町 | AU33: 七宗町 | AV33: 西伊豆町 | AW33: みよし市 | AX33: 御浜町 | BA33: 交野市 | BB33: 加東市 | BC33: 河合町 | BD33: 古座川町 | BM33: 三原村 | BN33: 福岡県介護保険広域連合 | BQ33: 御船町 | BT33: 南大隅町 | BU33: 北中城村 | CJ33: 北海道 | CK33: 富良野市 | CL33: =CJ33&CK33 -> 北海道富良野市 | CM33: 28 | CN33: =VLOOKUP(CL33,$M$6:$N$1784,2,FALSE) -> 0028 | CO33: =CM33&TEXT(CN33,0)&CK33 -> 2828富良野市 | CP33: 2828富良野市 | CQ33: =CO33=CP33 -> TRUE
F34: 290009 | G34: 05 | H34: 近畿厚生局 | I34: 29 | J34: 奈良県 | L34: 0029-1 | M34: 北海道登別市 | N34: 0029 | O34: 01 | P34: 012302 | Q34: 01 | R34: 230 | S34: 2 | T34: 登別市 | U34: 01 | V34: 北海道厚生局 | W34: 012301 | X34: 1 | AA34: 登別市 | AB34: 六ヶ所村 | AC34: 葛巻町 | AD34: 大衡村 | AF34: 川西町 | AG34: 湯川村 | AH34: 行方市 | AJ34: みなかみ町 | AK34: 富士見市 | AL34: 印西市 | AM34: 府中市 | AN34: 箱根町 | AO34: 関川村 | AT34: 飯島町 | AU34: 八百津町 | AV34: 函南町 | AW34: あま市 | AX34: 紀宝町 | BA34: 大阪狭山市 | BB34: たつの市 | BC34: 吉野町 | BD34: 北山村 | BM34: 黒潮町 | BN34: 田川市 | BQ34: 嘉島町 | BT34: 肝付町 | BU34: 中城村 | CJ34: 北海道 | CK34: 登別市 | CL34: =CJ34&CK34 -> 北海道登別市 | CM34: 29 | CN34: =VLOOKUP(CL34,$M$6:$N$1784,2,FALSE) -> 0029 | CO34: =CM34&TEXT(CN34,0)&CK34 -> 2929登別市 | CP34: 2929登別市 | CQ34: =CO34=CP34 -> TRUE
F35: 300004 | G35: 05 | H35: 近畿厚生局 | I35: 30 | J35: 和歌山県 | L35: 0030-1 | M35: 北海道恵庭市 | N35: 0030 | O35: 01 | P35: 012310 | Q35: 01 | R35: 231 | S35: 0 | T35: 恵庭市 | U35: 01 | V35: 北海道厚生局 | W35: 012319 | X35: 1 | AA35: 恵庭市 | AB35: おいらせ町 | AC35: 久慈広域連合 | AD35: 色麻町 | AF35: 小国町 | AG35: 柳津町 | AH35: 鉾田市 | AJ35: 玉村町 | AK35: 三郷市 | AL35: 南房総市 | AM35: 昭島市 | AN35: 真鶴町 | AO35: 粟島浦村 | AT35: 南箕輪村 | AU35: 白川町 | AV35: 清水町 | AW35: 長久手市 | AX35: 鈴鹿亀山地区広域連合 | BA35: 阪南市 | BB35: 猪名川町 | BC35: 大淀町 | BD35: 串本町 | BM35: 中芸広域連合 | BN35: 柳川市 | BQ35: 益城町 | BT35: 中種子町 | BU35: 西原町 | CJ35: 北海道 | CK35: 恵庭市 | CL35: =CJ35&CK35 -> 北海道恵庭市 | CM35: 30 | CN35: =VLOOKUP(CL35,$M$6:$N$1784,2,FALSE) -> 0030 | CO35: =CM35&TEXT(CN35,0)&CK35 -> 3030恵庭市 | CP35: 3030恵庭市 | CQ35: =CO35=CP35 -> TRUE
F36: 310000 | G36: 06 | H36: 中国四国厚生局 | I36: 31 | J36: 鳥取県 | L36: 0031-1 | M36: 北海道伊達市 | N36: 0031 | O36: 01 | P36: 012336 | Q36: 01 | R36: 233 | S36: 6 | T36: 伊達市 | U36: 01 | V36: 北海道厚生局 | W36: 012335 | X36: 1 | AA36: 伊達市 | AB36: 大間町 | AC36: 久慈市 | AD36: 加美町 | AF36: 白鷹町 | AG36: 三島町 | AH36: つくばみらい市 | AJ36: 板倉町 | AK36: 蓮田市 | AL36: 匝瑳市 | AM36: 調布市 | AN36: 湯河原町 | AT36: 中川村 | AU36: 東白川村 | AV36: 長泉町 | AW36: 東郷町 | AX36: 鈴鹿市 | BA36: 島本町 | BB36: 多可町 | BC36: 下市町 | BM36: 奈半利町 | BN36: 豊前市 | BQ36: 甲佐町 | BT36: 南種子町 | BU36: 与那原町 | CJ36: 北海道 | CK36: 伊達市 | CL36: =CJ36&CK36 -> 北海道伊達市 | CM36: 31 | CN36: =VLOOKUP(CL36,$M$6:$N$1784,2,FALSE) -> 0031 | CO36: =CM36&TEXT(CN36,0)&CK36 -> 3131伊達市 | CP36: 3131伊達市 | CQ36: =CO36=CP36 -> TRUE
F37: 320005 | G37: 06 | H37: 中国四国厚生局 | I37: 32 | J37: 島根県 | L37: 0032-1 | M37: 北海道北広島市 | N37: 0032 | O37: 01 | P37: 012344 | Q37: 01 | R37: 234 | S37: 4 | T37: 北広島市 | U37: 01 | V37: 北海道厚生局 | W37: 012343 | X37: 1 | AA37: 北広島市 | AB37: 東通村 | AC37: 洋野町 | AD37: 涌谷町 | AF37: 飯豊町 | AG37: 金山町 | AH37: 小美玉市 | AJ37: 明和町 | AK37: 坂戸市 | AL37: 香取市 | AM37: 町田市 | AN37: 愛川町 | AT37: 宮田村 | AU37: 御嵩町 | AV37: 小山町 | AW37: 豊山町 | AX37: 亀山市 | BA37: 豊能町 | BB37: 稲美町 | BC37: 黒滝村 | BM37: 田野町 | BN37: うきは市 | BQ37: 山都町 | BT37: 屋久島町 | BU37: 南風原町 | CJ37: 北海道 | CK37: 北広島市 | CL37: =CJ37&CK37 -> 北海道北広島市 | CM37: 32 | CN37: =VLOOKUP(CL37,$M$6:$N$1784,2,FALSE) -> 0032 | CO37: =CM37&TEXT(CN37,0)&CK37 -> 3232北広島市 | CP37: 3232北広島市 | CQ37: =CO37=CP37 -> TRUE
F38: 330001 | G38: 06 | H38: 中国四国厚生局 | I38: 33 | J38: 岡山県 | L38: 0033-1 | M38: 北海道石狩市 | N38: 0033 | O38: 01 | P38: 012351 | Q38: 01 | R38: 235 | S38: 1 | T38: 石狩市 | U38: 01 | V38: 北海道厚生局 | W38: 012351 | X38: 1 | AA38: 石狩市 | AB38: 風間浦村 | AC38: 野田村 | AD38: 美里町 | AF38: 三川町 | AG38: 昭和村 | AH38: 茨城町 | AJ38: 千代田町 | AK38: 幸手市 | AL38: 山武市 | AM38: 小金井市 | AN38: 清川村 | AT38: 松川町 | AU38: 白川村 | AV38: 吉田町 | AW38: 大口町 | BA38: 能勢町 | BB38: 播磨町 | BC38: 天川村 | BM38: 安田町 | BN38: 宮若市 | BQ38: 氷川町 | BT38: 大和村 | BU38: 渡嘉敷村 | CJ38: 北海道 | CK38: 石狩市 | CL38: =CJ38&CK38 -> 北海道石狩市 | CM38: 33 | CN38: =VLOOKUP(CL38,$M$6:$N$1784,2,FALSE) -> 0033 | CO38: =CM38&TEXT(CN38,0)&CK38 -> 3333石狩市 | CP38: 3333石狩市 | CQ38: =CO38=CP38 -> TRUE
F39: 340006 | G39: 06 | H39: 中国四国厚生局 | I39: 34 | J39: 広島県 | L39: 0034-1 | M39: 北海道北斗市 | N39: 0034 | O39: 01 | P39: 012369 | Q39: 01 | R39: 236 | S39: 9 | T39: 北斗市 | U39: 01 | V39: 北海道厚生局 | W39: 012360 | X39: 1 | AA39: 北斗市 | AB39: 佐井村 | AC39: 普代村 | AD39: 女川町 | AF39: 庄内町 | AG39: 会津美里町 | AH39: 大洗町 | AJ39: 大泉町 | AK39: 鶴ヶ島市 | AL39: いすみ市 | AM39: 小平市 | AT39: 高森町 | AU39: 安八郡広域連合 | AV39: 川根本町 | AW39: 扶桑町 | BA39: 忠岡町 | BB39: 市川町 | BC39: 野迫川村 | BM39: 北川村 | BN39: 宇美町 | BQ39: 芦北町 | BT39: 宇検村 | BU39: 座間味村 | CJ39: 北海道 | CK39: 北斗市 | CL39: =CJ39&CK39 -> 北海道北斗市 | CM39: 34 | CN39: =VLOOKUP(CL39,$M$6:$N$1784,2,FALSE) -> 0034 | CO39: =CM39&TEXT(CN39,0)&CK39 -> 3434北斗市 | CP39: 3434北斗市 | CQ39: =CO39=CP39 -> TRUE
F40: 350001 | G40: 06 | H40: 中国四国厚生局 | I40: 35 | J40: 山口県 | L40: 0035-1 | M40: 北海道当別町 | N40: 0035 | O40: 01 | P40: 013037 | Q40: 01 | R40: 303 | S40: 7 | T40: 当別町 | U40: 01 | V40: 北海道厚生局 | W40: 013030 | X40: 1 | AA40: 当別町 | AB40: 三戸町 | AC40: 一関地区広域行政組合 | AD40: 南三陸町 | AF40: 遊佐町 | AG40: 西郷村 | AH40: 城里町 | AJ40: 邑楽町 | AK40: 日高市 | AL40: 大網白里市 | AM40: 日野市 | AT40: 阿南町 | AU40: 神戸町 | AV40: 森町 | AW40: 大治町 | BA40: 熊取町 | BB40: 福崎町 | BC40: 十津川村 | BM40: 馬路村 | BN40: 篠栗町 | BQ40: 津奈木町 | BT40: 瀬戸内町 | BU40: 粟国村 | CJ40: 北海道 | CK40: 当別町 | CL40: =CJ40&CK40 -> 北海道当別町 | CM40: 35 | CN40: =VLOOKUP(CL40,$M$6:$N$1784,2,FALSE) -> 0035 | CO40: =CM40&TEXT(CN40,0)&CK40 -> 3535当別町 | CP40: 3535当別町 | CQ40: =CO40=CP40 -> TRUE
F41: 360007 | G41: 07 | H41: 四国厚生支局 | I41: 36 | J41: 徳島県 | L41: 0036-1 | M41: 北海道新篠津村 | N41: 0036 | O41: 01 | P41: 013045 | Q41: 01 | R41: 304 | S41: 5 | T41: 新篠津村 | U41: 01 | V41: 北海道厚生局 | W41: 013048 | X41: 1 | AA41: 新篠津村 | AB41: 五戸町 | AC41: 一関市 | AG41: 泉崎村 | AH41: 東海村 | AK41: 吉川市 | AL41: 酒々井町 | AM41: 東村山市 | AT41: 阿智村 | AU41: 輪之内町 | AW41: 蟹江町 | BA41: 田尻町 | BB41: 神河町 | BC41: 下北山村 | BN41: 志免町 | BQ41: 錦町 | BT41: 龍郷町 | BU41: 渡名喜村 | CJ41: 北海道 | CK41: 新篠津村 | CL41: =CJ41&CK41 -> 北海道新篠津村 | CM41: 36 | CN41: =VLOOKUP(CL41,$M$6:$N$1784,2,FALSE) -> 0036 | CO41: =CM41&TEXT(CN41,0)&CK41 -> 3636新篠津村 | CP41: 3636新篠津村 | CQ41: =CO41=CP41 -> TRUE
F42: 370002 | G42: 07 | H42: 四国厚生支局 | I42: 37 | J42: 香川県 | L42: 0037-1 | M42: 北海道松前町 | N42: 0037 | O42: 01 | P42: 013318 | Q42: 01 | R42: 331 | S42: 8 | T42: 松前町 | U42: 01 | V42: 北海道厚生局 | W42: 013315 | X42: 1 | AA42: 松前町 | AB42: 田子町 | AC42: 平泉町 | AG42: 中島村 | AH42: 大子町 | AK42: ふじみ野市 | AL42: 富里市 | AM42: 国分寺市 | AT42: 平谷村 | AU42: 安八町 | AW42: 飛島村 | BA42: 岬町 | BB42: 太子町 | BC42: 上北山村 | BN42: 須惠町 | BQ42: 多良木町 | BT42: 喜界町 | BU42: 南大東村 | CJ42: 北海道 | CK42: 松前町 | CL42: =CJ42&CK42 -> 北海道松前町 | CM42: 37 | CN42: =VLOOKUP(CL42,$M$6:$N$1784,2,FALSE) -> 0037 | CO42: =CM42&TEXT(CN42,0)&CK42 -> 3737松前町 | CP42: 3737松前町 | CQ42: =CO42=CP42 -> TRUE
F43: 380008 | G43: 07 | H43: 四国厚生支局 | I43: 38 | J43: 愛媛県 | L43: 0038-1 | M43: 北海道福島町 | N43: 0038 | O43: 01 | P43: 013326 | Q43: 01 | R43: 332 | S43: 6 | T43: 福島町 | U43: 01 | V43: 北海道厚生局 | W43: 013323 | X43: 1 | AA43: 福島町 | AB43: 南部町 | AG43: 矢吹町 | AH43: 美浦村 | AK43: 白岡市 | AL43: 白井市 | AM43: 国立市 | AT43: 根羽村 | AU43: 揖斐広域連合 | AW43: 阿久比町 | BA43: 太子町 | BB43: 上郡町 | BC43: 川上村 | BN43: 新宮町 | BQ43: 湯前町 | BT43: 徳之島町 | BU43: 北大東村 | CJ43: 北海道 | CK43: 福島町 | CL43: =CJ43&CK43 -> 北海道福島町 | CM43: 38 | CN43: =VLOOKUP(CL43,$M$6:$N$1784,2,FALSE) -> 0038 | CO43: =CM43&TEXT(CN43,0)&CK43 -> 3838福島町 | CP43: 3838福島町 | CQ43: =CO43=CP43 -> TRUE
F44: 390003 | G44: 07 | H44: 四国厚生支局 | I44: 39 | J44: 高知県 | L44: 0039-1 | M44: 北海道知内町 | N44: 0039 | O44: 01 | P44: 013334 | Q44: 01 | R44: 333 | S44: 4 | T44: 知内町 | U44: 01 | V44: 北海道厚生局 | W44: 013331 | X44: 1 | AA44: 知内町 | AB44: 階上町 | AG44: 棚倉町 | AH44: 阿見町 | AK44: 伊奈町 | AL44: 栄町 | AM44: 福生市 | AT44: 下條村 | AU44: 揖斐川町 | AW44: 南知多町 | BA44: 河南町 | BB44: 佐用町 | BC44: 東吉野村 | BN44: 久山町 | BQ44: 水上村 | BT44: 天城町 | BU44: 伊平屋村 | CJ44: 北海道 | CK44: 知内町 | CL44: =CJ44&CK44 -> 北海道知内町 | CM44: 39 | CN44: =VLOOKUP(CL44,$M$6:$N$1784,2,FALSE) -> 0039 | CO44: =CM44&TEXT(CN44,0)&CK44 -> 3939知内町 | CP44: 3939知内町 | CQ44: =CO44=CP44 -> TRUE
F45: 400009 | G45: 08 | H45: 九州厚生局 | I45: 40 | J45: 福岡県 | L45: 0040-1 | M45: 北海道木古内町 | N45: 0040 | O45: 01 | P45: 013342 | Q45: 01 | R45: 334 | S45: 2 | T45: 木古内町 | U45: 01 | V45: 北海道厚生局 | W45: 013340 | X45: 1 | AA45: 木古内町 | AB45: 新郷村 | AG45: 矢祭町 | AH45: 河内町 | AK45: 三芳町 | AL45: 神崎町 | AM45: 狛江市 | AT45: 売木村 | AU45: 大野町 | AW45: 美浜町 | BA45: 千早赤阪村 | BB45: 香美町 | BN45: 芦屋町 | BQ45: 相良村 | BT45: 伊仙町 | BU45: 伊是名村 | CJ45: 北海道 | CK45: 木古内町 | CL45: =CJ45&CK45 -> 北海道木古内町 | CM45: 40 | CN45: =VLOOKUP(CL45,$M$6:$N$1784,2,FALSE) -> 0040 | CO45: =CM45&TEXT(CN45,0)&CK45 -> 4040木古内町 | CP45: 4040木古内町 | CQ45: =CO45=CP45 -> TRUE
F46: 410004 | G46: 08 | H46: 九州厚生局 | I46: 41 | J46: 佐賀県 | L46: 0041-1 | M46: 北海道七飯町 | N46: 0041 | O46: 01 | P46: 013375 | Q46: 01 | R46: 337 | S46: 5 | T46: 七飯町 | U46: 01 | V46: 北海道厚生局 | W46: 013374 | X46: 1 | AA46: 七飯町 | AG46: 塙町 | AH46: 八千代町 | AK46: 毛呂山町 | AL46: 多古町 | AM46: 東大和市 | AT46: 天龍村 | AU46: 池田町 | AW46: 武豊町 | BA46: 守口市 | BB46: 新温泉町 | BN46: 水巻町 | BQ46: 五木村 | BT46: 和泊町 | BU46: 久米島町 | CJ46: 北海道 | CK46: 七飯町 | CL46: =CJ46&CK46 -> 北海道七飯町 | CM46: 41 | CN46: =VLOOKUP(CL46,$M$6:$N$1784,2,FALSE) -> 0041 | CO46: =CM46&TEXT(CN46,0)&CK46 -> 4141七飯町 | CP46: 4141七飯町 | CQ46: =CO46=CP46 -> TRUE
F47: 420000 | G47: 08 | H47: 九州厚生局 | I47: 42 | J47: 長崎県 | L47: 0042-1 | M47: 北海道鹿部町 | N47: 0042 | O47: 01 | P47: 013433 | Q47: 01 | R47: 343 | S47: 3 | T47: 鹿部町 | U47: 01 | V47: 北海道厚生局 | W47: 013439 | X47: 1 | AA47: 鹿部町 | AG47: 鮫川村 | AH47: 五霞町 | AK47: 越生町 | AL47: 東庄町 | AM47: 清瀬市 | AT47: 泰阜村 | AU47: もとす広域連合 | AW47: 幸田町 | BA47: 門真市 | BN47: 岡垣町 | BQ47: 山江村 | BT47: 知名町 | BU47: 八重瀬町 | CJ47: 北海道 | CK47: 鹿部町 | CL47: =CJ47&CK47 -> 北海道鹿部町 | CM47: 42 | CN47: =VLOOKUP(CL47,$M$6:$N$1784,2,FALSE) -> 0042 | CO47: =CM47&TEXT(CN47,0)&CK47 -> 4242鹿部町 | CP47: 4242鹿部町 | CQ47: =CO47=CP47 -> TRUE
F48: 430005 | G48: 08 | H48: 九州厚生局 | I48: 43 | J48: 熊本県 | L48: 0043-1 | M48: 北海道森町 | N48: 0043 | O48: 01 | P48: 013458 | Q48: 01 | R48: 345 | S48: 8 | T48: 森町 | U48: 01 | V48: 北海道厚生局 | W48: 013455 | X48: 1 | AA48: 森町 | AG48: 石川町 | AH48: 境町 | AK48: 滑川町 | AL48: 九十九里町 | AM48: 東久留米市 | AT48: 喬木村 | AU48: 瑞穂市 | AW48: 知多北部広域連合 | BA48: 四條畷市 | BN48: 遠賀町 | BQ48: 球磨村 | BT48: 与論町 | CJ48: 北海道 | CK48: 森町 | CL48: =CJ48&CK48 -> 北海道森町 | CM48: 43 | CN48: =VLOOKUP(CL48,$M$6:$N$1784,2,FALSE) -> 0043 | CO48: =CM48&TEXT(CN48,0)&CK48 -> 4343森町 | CP48: 4343森町 | CQ48: =CO48=CP48 -> TRUE
F49: 440001 | G49: 08 | H49: 九州厚生局 | I49: 44 | J49: 大分県 | L49: 0044-1 | M49: 北海道八雲町 | N49: 0044 | O49: 01 | P49: 013466 | Q49: 01 | R49: 346 | S49: 6 | T49: 八雲町 | U49: 01 | V49: 北海道厚生局 | W49: 013463 | X49: 1 | AA49: 八雲町 | AG49: 玉川村 | AH49: 利根町 | AK49: 嵐山町 | AL49: 芝山町 | AM49: 武蔵村山市 | AT49: 豊丘村 | AU49: 本巣市 | AW49: 東海市 | BN49: 小竹町 | BQ49: あさぎり町 | CJ49: 北海道 | CK49: 八雲町 | CL49: =CJ49&CK49 -> 北海道八雲町 | CM49: 44 | CN49: =VLOOKUP(CL49,$M$6:$N$1784,2,FALSE) -> 0044 | CO49: =CM49&TEXT(CN49,0)&CK49 -> 4444八雲町 | CP49: 4444八雲町 | CQ49: =CO49=CP49 -> TRUE
F50: 450006 | G50: 08 | H50: 九州厚生局 | I50: 45 | J50: 宮崎県 | L50: 0045-1 | M50: 北海道長万部町 | N50: 0045 | O50: 01 | P50: 013474 | Q50: 01 | R50: 347 | S50: 4 | T50: 長万部町 | U50: 01 | V50: 北海道厚生局 | W50: 013471 | X50: 1 | AA50: 長万部町 | AG50: 平田村 | AK50: 小川町 | AL50: 横芝光町 | AM50: 多摩市 | AT50: 大鹿村 | AU50: 北方町 | AW50: 大府市 | BN50: 鞍手町 | BQ50: 苓北町 | CJ50: 北海道 | CK50: 長万部町 | CL50: =CJ50&CK50 -> 北海道長万部町 | CM50: 45 | CN50: =VLOOKUP(CL50,$M$6:$N$1784,2,FALSE) -> 0045 | CO50: =CM50&TEXT(CN50,0)&CK50 -> 4545長万部町 | CP50: 4545長万部町 | CQ50: =CO50=CP50 -> TRUE
F51: 460001 | G51: 08 | H51: 九州厚生局 | I51: 46 | J51: 鹿児島県 | L51: 0046-1 | M51: 北海道江差町 | N51: 0046 | O51: 01 | P51: 013615 | Q51: 01 | R51: 361 | S51: 5 | T51: 江差町 | U51: 01 | V51: 北海道厚生局 | W51: 013617 | X51: 1 | AA51: 江差町 | AG51: 浅川町 | AK51: 川島町 | AL51: 一宮町 | AM51: 稲城市 | AT51: 麻績村 | AW51: 知多市 | BN51: 筑前町 | CJ51: 北海道 | CK51: 江差町 | CL51: =CJ51&CK51 -> 北海道江差町 | CM51: 46 | CN51: =VLOOKUP(CL51,$M$6:$N$1784,2,FALSE) -> 0046 | CO51: =CM51&TEXT(CN51,0)&CK51 -> 4646江差町 | CP51: 4646江差町 | CQ51: =CO51=CP51 -> TRUE
F52: 470007 | G52: 08 | H52: 九州厚生局 | I52: 47 | J52: 沖縄県 | L52: 0047-1 | M52: 北海道上ノ国町 | N52: 0047 | O52: 01 | P52: 013623 | Q52: 01 | R52: 362 | S52: 3 | T52: 上ノ国町 | U52: 01 | V52: 北海道厚生局 | W52: 013625 | X52: 1 | AA52: 上ノ国町 | AG52: 古殿町 | AK52: 吉見町 | AL52: 睦沢町 | AM52: 羽村市 | AT52: 生坂村 | AW52: 東浦町 | BN52: 東峰村 | CJ52: 北海道 | CK52: 上ノ国町 | CL52: =CJ52&CK52 -> 北海道上ノ国町 | CM52: 47 | CN52: =VLOOKUP(CL52,$M$6:$N$1784,2,FALSE) -> 0047 | CO52: =CM52&TEXT(CN52,0)&CK52 -> 4747上ノ国町 | CP52: 4747上ノ国町 | CQ52: =CO52=CP52 -> TRUE
L53: 0048-1 | M53: 北海道厚沢部町 | N53: 0048 | O53: 01 | P53: 013631 | Q53: 01 | R53: 363 | S53: 1 | T53: 厚沢部町 | U53: 01 | V53: 北海道厚生局 | W53: 013633 | X53: 1 | AA53: 厚沢部町 | AG53: 三春町 | AK53: 鳩山町 | AL53: 長生村 | AM53: あきる野市 | AT53: 山形村 | AW53: 東三河広域連合 | BN53: 大刀洗町 | CJ53: 北海道 | CK53: 厚沢部町 | CL53: =CJ53&CK53 -> 北海道厚沢部町 | CM53: 48 | CN53: =VLOOKUP(CL53,$M$6:$N$1784,2,FALSE) -> 0048 | CO53: =CM53&TEXT(CN53,0)&CK53 -> 4848厚沢部町 | CP53: 4848厚沢部町 | CQ53: =CO53=CP53 -> TRUE
L54: 0049-1 | M54: 北海道乙部町 | N54: 0049 | O54: 01 | P54: 013649 | Q54: 01 | R54: 364 | S54: 9 | T54: 乙部町 | U54: 01 | V54: 北海道厚生局 | W54: 013641 | X54: 1 | AA54: 乙部町 | AG54: 小野町 | AK54: ときがわ町 | AL54: 白子町 | AM54: 西東京市 | AT54: 朝日村 | AW54: 豊橋市 | BN54: 大木町 | CJ54: 北海道 | CK54: 乙部町 | CL54: =CJ54&CK54 -> 北海道乙部町 | CM54: 49 | CN54: =VLOOKUP(CL54,$M$6:$N$1784,2,FALSE) -> 0049 | CO54: =CM54&TEXT(CN54,0)&CK54 -> 4949乙部町 | CP54: 4949乙部町 | CQ54: =CO54=CP54 -> TRUE
L55: 0050-1 | M55: 北海道奥尻町 | N55: 0050 | O55: 01 | P55: 013672 | Q55: 01 | R55: 367 | S55: 2 | T55: 奥尻町 | U55: 01 | V55: 北海道厚生局 | W55: 013676 | X55: 1 | AA55: 奥尻町 | AG55: 広野町 | AK55: 横瀬町 | AL55: 長柄町 | AM55: 瑞穂町 | AT55: 筑北村 | AW55: 豊川市 | BN55: 広川町 | CJ55: 北海道 | CK55: 奥尻町 | CL55: =CJ55&CK55 -> 北海道奥尻町 | CM55: 50 | CN55: =VLOOKUP(CL55,$M$6:$N$1784,2,FALSE) -> 0050 | CO55: =CM55&TEXT(CN55,0)&CK55 -> 5050奥尻町 | CP55: 5050奥尻町 | CQ55: =CO55=CP55 -> TRUE
L56: 0051-1 | M56: 北海道今金町 | N56: 0051 | O56: 01 | P56: 013706 | Q56: 01 | R56: 370 | S56: 6 | T56: 今金町 | U56: 01 | V56: 北海道厚生局 | W56: 013706 | X56: 1 | AA56: 今金町 | AG56: 楢葉町 | AK56: 皆野町 | AL56: 長南町 | AM56: 日の出町 | AT56: 坂城町 | AW56: 蒲郡市 | BN56: 桂川町 | CJ56: 北海道 | CK56: 今金町 | CL56: =CJ56&CK56 -> 北海道今金町 | CM56: 51 | CN56: =VLOOKUP(CL56,$M$6:$N$1784,2,FALSE) -> 0051 | CO56: =CM56&TEXT(CN56,0)&CK56 -> 5151今金町 | CP56: 5151今金町 | CQ56: =CO56=CP56 -> TRUE
L57: 0052-1 | M57: 北海道せたな町 | N57: 0052 | O57: 01 | P57: 013714 | Q57: 01 | R57: 371 | S57: 4 | T57: せたな町 | U57: 01 | V57: 北海道厚生局 | W57: 013714 | X57: 1 | AA57: せたな町 | AG57: 富岡町 | AK57: 長瀞町 | AL57: 大多喜町 | AM57: 檜原村 | AT57: 小布施町 | AW57: 新城市 | BN57: 香春町 | CJ57: 北海道 | CK57: せたな町 | CL57: =CJ57&CK57 -> 北海道せたな町 | CM57: 52 | CN57: =VLOOKUP(CL57,$M$6:$N$1784,2,FALSE) -> 0052 | CO57: =CM57&TEXT(CN57,0)&CK57 -> 5252せたな町 | CP57: 5252せたな町 | CQ57: =CO57=CP57 -> TRUE
L58: 0053-1 | M58: 北海道寿都町 | N58: 0053 | O58: 01 | P58: 013920 | Q58: 01 | R58: 392 | S58: 0 | T58: 寿都町 | U58: 01 | V58: 北海道厚生局 | W58: 013927 | X58: 1 | AA58: 寿都町 | AG58: 川内村 | AK58: 小鹿野町 | AL58: 御宿町 | AM58: 奥多摩町 | AT58: 高山村 | AW58: 田原市 | BN58: 添田町 | CJ58: 北海道 | CK58: 寿都町 | CL58: =CJ58&CK58 -> 北海道寿都町 | CM58: 53 | CN58: =VLOOKUP(CL58,$M$6:$N$1784,2,FALSE) -> 0053 | CO58: =CM58&TEXT(CN58,0)&CK58 -> 5353寿都町 | CP58: 5353寿都町 | CQ58: =CO58=CP58 -> TRUE
L59: 0054-1 | M59: 北海道岩内町 | N59: 0054 | O59: 01 | P59: 014027 | Q59: 01 | R59: 402 | S59: 7 | T59: 岩内町 | U59: 01 | V59: 北海道厚生局 | W59: 014028 | X59: 1 | AA59: 岩内町 | AG59: 大熊町 | AK59: 東秩父村 | AL59: 鋸南町 | AM59: 大島町 | AT59: 山ノ内町 | AW59: 設楽町 | BN59: 糸田町 | CJ59: 北海道 | CK59: 岩内町 | CL59: =CJ59&CK59 -> 北海道岩内町 | CM59: 54 | CN59: =VLOOKUP(CL59,$M$6:$N$1784,2,FALSE) -> 0054 | CO59: =CM59&TEXT(CN59,0)&CK59 -> 5454岩内町 | CP59: 5454岩内町 | CQ59: =CO59=CP59 -> TRUE
L60: 0055-1 | M60: 北海道余市町 | N60: 0055 | O60: 01 | P60: 014084 | Q60: 01 | R60: 408 | S60: 4 | T60: 余市町 | U60: 01 | V60: 北海道厚生局 | W60: 014087 | X60: 1 | AA60: 余市町 | AG60: 双葉町 | AK60: 美里町 | AM60: 利島村 | AT60: 木島平村 | AW60: 東栄町 | BN60: 川崎町 | CJ60: 北海道 | CK60: 余市町 | CL60: =CJ60&CK60 -> 北海道余市町 | CM60: 55 | CN60: =VLOOKUP(CL60,$M$6:$N$1784,2,FALSE) -> 0055 | CO60: =CM60&TEXT(CN60,0)&CK60 -> 5555余市町 | CP60: 5555余市町 | CQ60: =CO60=CP60 -> TRUE
L61: 0056-1 | M61: 北海道南幌町 | N61: 0056 | O61: 01 | P61: 014233 | Q61: 01 | R61: 423 | S61: 3 | T61: 南幌町 | U61: 01 | V61: 北海道厚生局 | W61: 014231 | X61: 1 | AA61: 南幌町 | AG61: 浪江町 | AK61: 神川町 | AM61: 新島村 | AT61: 野沢温泉村 | AW61: 豊根村 | BN61: 大任町 | CJ61: 北海道 | CK61: 南幌町 | CL61: =CJ61&CK61 -> 北海道南幌町 | CM61: 56 | CN61: =VLOOKUP(CL61,$M$6:$N$1784,2,FALSE) -> 0056 | CO61: =CM61&TEXT(CN61,0)&CK61 -> 5656南幌町 | CP61: 5656南幌町 | CQ61: =CO61=CP61 -> TRUE
L62: 0057-1 | M62: 北海道由仁町 | N62: 0057 | O62: 01 | P62: 014274 | Q62: 01 | R62: 427 | S62: 4 | T62: 由仁町 | U62: 01 | V62: 北海道厚生局 | W62: 014273 | X62: 1 | AA62: 由仁町 | AG62: 葛尾村 | AK62: 上里町 | AM62: 神津島村 | AT62: 信濃町 | BN62: 福智町 | CJ62: 北海道 | CK62: 由仁町 | CL62: =CJ62&CK62 -> 北海道由仁町 | CM62: 57 | CN62: =VLOOKUP(CL62,$M$6:$N$1784,2,FALSE) -> 0057 | CO62: =CM62&TEXT(CN62,0)&CK62 -> 5757由仁町 | CP62: 5757由仁町 | CQ62: =CO62=CP62 -> TRUE
L63: 0058-1 | M63: 北海道長沼町 | N63: 0058 | O63: 01 | P63: 014282 | Q63: 01 | R63: 428 | S63: 2 | T63: 長沼町 | U63: 01 | V63: 北海道厚生局 | W63: 014281 | X63: 1 | AA63: 長沼町 | AG63: 新地町 | AK63: 宮代町 | AM63: 三宅村 | AT63: 小川村 | BN63: 赤村 | CJ63: 北海道 | CK63: 長沼町 | CL63: =CJ63&CK63 -> 北海道長沼町 | CM63: 58 | CN63: =VLOOKUP(CL63,$M$6:$N$1784,2,FALSE) -> 0058 | CO63: =CM63&TEXT(CN63,0)&CK63 -> 5858長沼町 | CP63: 5858長沼町 | CQ63: =CO63=CP63 -> TRUE
L64: 0059-1 | M64: 北海道栗山町 | N64: 0059 | O64: 01 | P64: 014290 | Q64: 01 | R64: 429 | S64: 0 | T64: 栗山町 | U64: 01 | V64: 北海道厚生局 | W64: 014290 | X64: 1 | AA64: 栗山町 | AG64: 飯舘村 | AK64: 杉戸町 | AM64: 御蔵島村 | AT64: 飯綱町 | BN64: 吉富町 | CJ64: 北海道 | CK64: 栗山町 | CL64: =CJ64&CK64 -> 北海道栗山町 | CM64: 59 | CN64: =VLOOKUP(CL64,$M$6:$N$1784,2,FALSE) -> 0059 | CO64: =CM64&TEXT(CN64,0)&CK64 -> 5959栗山町 | CP64: 5959栗山町 | CQ64: =CO64=CP64 -> TRUE
L65: 0060-1 | M65: 北海道月形町 | N65: 0060 | O65: 01 | P65: 014308 | Q65: 01 | R65: 430 | S65: 8 | T65: 月形町 | U65: 01 | V65: 北海道厚生局 | W65: 014303 | X65: 1 | AA65: 月形町 | AK65: 松伏町 | AM65: 八丈町 | AT65: 栄村 | BN65: 上毛町 | CJ65: 北海道 | CK65: 月形町 | CL65: =CJ65&CK65 -> 北海道月形町 | CM65: 60 | CN65: =VLOOKUP(CL65,$M$6:$N$1784,2,FALSE) -> 0060 | CO65: =CM65&TEXT(CN65,0)&CK65 -> 6060月形町 | CP65: 6060月形町 | CQ65: =CO65=CP65 -> TRUE
L66: 0061-1 | M66: 北海道妹背牛町 | N66: 0061 | O66: 01 | P66: 014332 | Q66: 01 | R66: 433 | S66: 2 | T66: 妹背牛町 | U66: 01 | V66: 北海道厚生局 | W66: 014338 | X66: 1 | AA66: 妹背牛町 | AK66: 大里広域市町村圏組合 | AM66: 青ヶ島村 | AT66: 北アルプス広域連合 | BN66: 築上町 | CJ66: 北海道 | CK66: 妹背牛町 | CL66: =CJ66&CK66 -> 北海道妹背牛町 | CM66: 61 | CN66: =VLOOKUP(CL66,$M$6:$N$1784,2,FALSE) -> 0061 | CO66: =CM66&TEXT(CN66,0)&CK66 -> 6161妹背牛町 | CP66: 6161妹背牛町 | CQ66: =CO66=CP66 -> TRUE
L67: 0062-1 | M67: 北海道秩父別町 | N67: 0062 | O67: 01 | P67: 014340 | Q67: 01 | R67: 434 | S67: 0 | T67: 秩父別町 | U67: 01 | V67: 北海道厚生局 | W67: 014346 | X67: 1 | AA67: 秩父別町 | AK67: 熊谷市 | AM67: 小笠原村 | AT67: 大町市 | CJ67: 北海道 | CK67: 秩父別町 | CL67: =CJ67&CK67 -> 北海道秩父別町 | CM67: 62 | CN67: =VLOOKUP(CL67,$M$6:$N$1784,2,FALSE) -> 0062 | CO67: =CM67&TEXT(CN67,0)&CK67 -> 6262秩父別町 | CP67: 6262秩父別町 | CQ67: =CO67=CP67 -> TRUE
L68: 0063-1 | M68: 北海道北竜町 | N68: 0063 | O68: 01 | P68: 014373 | Q68: 01 | R68: 437 | S68: 3 | T68: 北竜町 | U68: 01 | V68: 北海道厚生局 | W68: 014371 | X68: 1 | AA68: 北竜町 | AK68: 深谷市 | AT68: 池田町 | CJ68: 北海道 | CK68: 北竜町 | CL68: =CJ68&CK68 -> 北海道北竜町 | CM68: 63 | CN68: =VLOOKUP(CL68,$M$6:$N$1784,2,FALSE) -> 0063 | CO68: =CM68&TEXT(CN68,0)&CK68 -> 6363北竜町 | CP68: 6363北竜町 | CQ68: =CO68=CP68 -> TRUE
L69: 0064-1 | M69: 北海道沼田町 | N69: 0064 | O69: 01 | P69: 014381 | Q69: 01 | R69: 438 | S69: 1 | T69: 沼田町 | U69: 01 | V69: 北海道厚生局 | W69: 014389 | X69: 1 | AA69: 沼田町 | AK69: 寄居町 | AT69: 松川村 | CJ69: 北海道 | CK69: 沼田町 | CL69: =CJ69&CK69 -> 北海道沼田町 | CM69: 64 | CN69: =VLOOKUP(CL69,$M$6:$N$1784,2,FALSE) -> 0064 | CO69: =CM69&TEXT(CN69,0)&CK69 -> 6464沼田町 | CP69: 6464沼田町 | CQ69: =CO69=CP69 -> TRUE
L70: 0065-1 | M70: 北海道幌加内町 | N70: 0065 | O70: 01 | P70: 014399 | Q70: 01 | R70: 439 | S70: 9 | T70: 幌加内町 | U70: 01 | V70: 北海道厚生局 | W70: 014729 | X70: 1 | AA70: 幌加内町 | AT70: 白馬村 | CJ70: 北海道 | CK70: 幌加内町 | CL70: =CJ70&CK70 -> 北海道幌加内町 | CM70: 65 | CN70: =VLOOKUP(CL70,$M$6:$N$1784,2,FALSE) -> 0065 | CO70: =CM70&TEXT(CN70,0)&CK70 -> 6565幌加内町 | CP70: 6565幌加内町 | CQ70: =CO70=CP70 -> TRUE
L71: 0066-1 | M71: 北海道鷹栖町 | N71: 0066 | O71: 01 | P71: 014522 | Q71: 01 | R71: 452 | S71: 2 | T71: 鷹栖町 | U71: 01 | V71: 北海道厚生局 | W71: 014524 | X71: 1 | AA71: 鷹栖町 | AT71: 小谷村 | CJ71: 北海道 | CK71: 鷹栖町 | CL71: =CJ71&CK71 -> 北海道鷹栖町 | CM71: 66 | CN71: =VLOOKUP(CL71,$M$6:$N$1784,2,FALSE) -> 0066 | CO71: =CM71&TEXT(CN71,0)&CK71 -> 6666鷹栖町 | CP71: 6666鷹栖町 | CQ71: =CO71=CP71 -> TRUE
L72: 0067-1 | M72: 北海道当麻町 | N72: 0067 | O72: 01 | P72: 014548 | Q72: 01 | R72: 454 | S72: 8 | T72: 当麻町 | U72: 01 | V72: 北海道厚生局 | W72: 014541 | X72: 1 | AA72: 当麻町 | AT72: 木曽広域連合 | CJ72: 北海道 | CK72: 当麻町 | CL72: =CJ72&CK72 -> 北海道当麻町 | CM72: 67 | CN72: =VLOOKUP(CL72,$M$6:$N$1784,2,FALSE) -> 0067 | CO72: =CM72&TEXT(CN72,0)&CK72 -> 6767当麻町 | CP72: 6767当麻町 | CQ72: =CO72=CP72 -> TRUE
L73: 0068-1 | M73: 北海道比布町 | N73: 0068 | O73: 01 | P73: 014555 | Q73: 01 | R73: 455 | S73: 5 | T73: 比布町 | U73: 01 | V73: 北海道厚生局 | W73: 014559 | X73: 1 | AA73: 比布町 | AT73: 木曽町 | CJ73: 北海道 | CK73: 比布町 | CL73: =CJ73&CK73 -> 北海道比布町 | CM73: 68 | CN73: =VLOOKUP(CL73,$M$6:$N$1784,2,FALSE) -> 0068 | CO73: =CM73&TEXT(CN73,0)&CK73 -> 6868比布町 | CP73: 6868比布町 | CQ73: =CO73=CP73 -> TRUE
L74: 0069-1 | M74: 北海道愛別町 | N74: 0069 | O74: 01 | P74: 014563 | Q74: 01 | R74: 456 | S74: 3 | T74: 愛別町 | U74: 01 | V74: 北海道厚生局 | W74: 014567 | X74: 1 | AA74: 愛別町 | AT74: 上松町 | CJ74: 北海道 | CK74: 愛別町 | CL74: =CJ74&CK74 -> 北海道愛別町 | CM74: 69 | CN74: =VLOOKUP(CL74,$M$6:$N$1784,2,FALSE) -> 0069 | CO74: =CM74&TEXT(CN74,0)&CK74 -> 6969愛別町 | CP74: 6969愛別町 | CQ74: =CO74=CP74 -> TRUE
L75: 0070-1 | M75: 北海道上川町 | N75: 0070 | O75: 01 | P75: 014571 | Q75: 01 | R75: 457 | S75: 1 | T75: 上川町 | U75: 01 | V75: 北海道厚生局 | W75: 014575 | X75: 1 | AA75: 上川町 | AT75: 南木曽町 | CJ75: 北海道 | CK75: 上川町 | CL75: =CJ75&CK75 -> 北海道上川町 | CM75: 70 | CN75: =VLOOKUP(CL75,$M$6:$N$1784,2,FALSE) -> 0070 | CO75: =CM75&TEXT(CN75,0)&CK75 -> 7070上川町 | CP75: 7070上川町 | CQ75: =CO75=CP75 -> TRUE
L76: 0071-1 | M76: 北海道上富良野町 | N76: 0071 | O76: 01 | P76: 014605 | Q76: 01 | R76: 460 | S76: 5 | T76: 上富良野町 | U76: 01 | V76: 北海道厚生局 | W76: 014605 | X76: 1 | AA76: 上富良野町 | AT76: 木祖村 | CJ76: 北海道 | CK76: 上富良野町 | CL76: =CJ76&CK76 -> 北海道上富良野町 | CM76: 71 | CN76: =VLOOKUP(CL76,$M$6:$N$1784,2,FALSE) -> 0071 | CO76: =CM76&TEXT(CN76,0)&CK76 -> 7171上富良野町 | CP76: 7171上富良野町 | CQ76: =CO76=CP76 -> TRUE
L77: 0072-1 | M77: 北海道中富良野町 | N77: 0072 | O77: 01 | P77: 014613 | Q77: 01 | R77: 461 | S77: 3 | T77: 中富良野町 | U77: 01 | V77: 北海道厚生局 | W77: 014613 | X77: 1 | AA77: 中富良野町 | AT77: 王滝村 | CJ77: 北海道 | CK77: 中富良野町 | CL77: =CJ77&CK77 -> 北海道中富良野町 | CM77: 72 | CN77: =VLOOKUP(CL77,$M$6:$N$1784,2,FALSE) -> 0072 | CO77: =CM77&TEXT(CN77,0)&CK77 -> 7272中富良野町 | CP77: 7272中富良野町 | CQ77: =CO77=CP77 -> TRUE
L78: 0073-1 | M78: 北海道南富良野町 | N78: 0073 | O78: 01 | P78: 014621 | Q78: 01 | R78: 462 | S78: 1 | T78: 南富良野町 | U78: 01 | V78: 北海道厚生局 | W78: 014621 | X78: 1 | AA78: 南富良野町 | AT78: 大桑村 | CJ78: 北海道 | CK78: 南富良野町 | CL78: =CJ78&CK78 -> 北海道南富良野町 | CM78: 73 | CN78: =VLOOKUP(CL78,$M$6:$N$1784,2,FALSE) -> 0073 | CO78: =CM78&TEXT(CN78,0)&CK78 -> 7373南富良野町 | CP78: 7373南富良野町 | CQ78: =CO78=CP78 -> TRUE
L79: 0074-1 | M79: 北海道占冠村 | N79: 0074 | O79: 01 | P79: 014639 | Q79: 01 | R79: 463 | S79: 9 | T79: 占冠村 | U79: 01 | V79: 北海道厚生局 | W79: 014630 | X79: 1 | AA79: 占冠村 | AT79: 諏訪広域連合 | CJ79: 北海道 | CK79: 占冠村 | CL79: =CJ79&CK79 -> 北海道占冠村 | CM79: 74 | CN79: =VLOOKUP(CL79,$M$6:$N$1784,2,FALSE) -> 0074 | CO79: =CM79&TEXT(CN79,0)&CK79 -> 7474占冠村 | CP79: 7474占冠村 | CQ79: =CO79=CP79 -> TRUE
L80: 0075-1 | M80: 北海道和寒町 | N80: 0075 | O80: 01 | P80: 014647 | Q80: 01 | R80: 464 | S80: 7 | T80: 和寒町 | U80: 01 | V80: 北海道厚生局 | W80: 014648 | X80: 1 | AA80: 和寒町 | AT80: 岡谷市 | CJ80: 北海道 | CK80: 和寒町 | CL80: =CJ80&CK80 -> 北海道和寒町 | CM80: 75 | CN80: =VLOOKUP(CL80,$M$6:$N$1784,2,FALSE) -> 0075 | CO80: =CM80&TEXT(CN80,0)&CK80 -> 7575和寒町 | CP80: 7575和寒町 | CQ80: =CO80=CP80 -> TRUE
L81: 0076-1 | M81: 北海道剣淵町 | N81: 0076 | O81: 01 | P81: 014654 | Q81: 01 | R81: 465 | S81: 4 | T81: 剣淵町 | U81: 01 | V81: 北海道厚生局 | W81: 014656 | X81: 1 | AA81: 剣淵町 | AT81: 諏訪市 | CJ81: 北海道 | CK81: 剣淵町 | CL81: =CJ81&CK81 -> 北海道剣淵町 | CM81: 76 | CN81: =VLOOKUP(CL81,$M$6:$N$1784,2,FALSE) -> 0076 | CO81: =CM81&TEXT(CN81,0)&CK81 -> 7676剣淵町 | CP81: 7676剣淵町 | CQ81: =CO81=CP81 -> TRUE
... L85: 0080-1 | M85: 北海道中川町 | N85: 0080 | O85: 01 | P85: 014712 | Q85: 01 | R85: 471 | S85: 2 | T85: 中川町 | U85: 01 | V85: 北海道厚生局 | W85: 014711 | X85: 1 | AA85: 中川町 | AT85: 原村 | CJ85: 北海道 | CK85: 中川町 | CL85: =CJ85&CK85 -> 北海道中川町 | CM85: 80 | CN85: =VLOOKUP(CL85,$M$6:$N$1784,2,FALSE) -> 0080 | CO85: =CM85&TEXT(CN85,0)&CK85 -> 8080中川町 | CP85: 8080中川町 | CQ85: =CO85=CP85 -> TRUE
L86: 0081-1 | M86: 北海道増毛町 | N86: 0081 | O86: 01 | P86: 014811 | Q86: 01 | R86: 481 | S86: 1 | T86: 増毛町 | U86: 01 | V86: 北海道厚生局 | W86: 014818 | X86: 1 | AA86: 増毛町 | CJ86: 北海道 | CK86: 増毛町 | CL86: =CJ86&CK86 -> 北海道増毛町 | CM86: 81 | CN86: =VLOOKUP(CL86,$M$6:$N$1784,2,FALSE) -> 0081 | CO86: =CM86&TEXT(CN86,0)&CK86 -> 8181増毛町 | CP86: 8181増毛町 | CQ86: =CO86=CP86 -> TRUE
L87: 0082-1 | M87: 北海道小平町 | N87: 0082 | O87: 01 | P87: 014829 | Q87: 01 | R87: 482 | S87: 9 | T87: 小平町 | U87: 01 | V87: 北海道厚生局 | W87: 014826 | X87: 1 | AA87: 小平町 | CJ87: 北海道 | CK87: 小平町 | CL87: =CJ87&CK87 -> 北海道小平町 | CM87: 82 | CN87: =VLOOKUP(CL87,$M$6:$N$1784,2,FALSE) -> 0082 | CO87: =CM87&TEXT(CN87,0)&CK87 -> 8282小平町 | CP87: 8282小平町 | CQ87: =CO87=CP87 -> TRUE
L88: 0083-1 | M88: 北海道苫前町 | N88: 0083 | O88: 01 | P88: 014837 | Q88: 01 | R88: 483 | S88: 7 | T88: 苫前町 | U88: 01 | V88: 北海道厚生局 | W88: 014834 | X88: 1 | AA88: 苫前町 | CJ88: 北海道 | CK88: 苫前町 | CL88: =CJ88&CK88 -> 北海道苫前町 | CM88: 83 | CN88: =VLOOKUP(CL88,$M$6:$N$1784,2,FALSE) -> 0083 | CO88: =CM88&TEXT(CN88,0)&CK88 -> 8383苫前町 | CP88: 8383苫前町 | CQ88: =CO88=CP88 -> TRUE
L89: 0084-1 | M89: 北海道羽幌町 | N89: 0084 | O89: 01 | P89: 014845 | Q89: 01 | R89: 484 | S89: 5 | T89: 羽幌町 | U89: 01 | V89: 北海道厚生局 | W89: 014842 | X89: 1 | AA89: 羽幌町 | CJ89: 北海道 | CK89: 羽幌町 | CL89: =CJ89&CK89 -> 北海道羽幌町 | CM89: 84 | CN89: =VLOOKUP(CL89,$M$6:$N$1784,2,FALSE) -> 0084 | CO89: =CM89&TEXT(CN89,0)&CK89 -> 8484羽幌町 | CP89: 8484羽幌町 | CQ89: =CO89=CP89 -> TRUE
L90: 0085-1 | M90: 北海道初山別村 | N90: 0085 | O90: 01 | P90: 014852 | Q90: 01 | R90: 485 | S90: 2 | T90: 初山別村 | U90: 01 | V90: 北海道厚生局 | W90: 014851 | X90: 1 | AA90: 初山別村 | CJ90: 北海道 | CK90: 初山別村 | CL90: =CJ90&CK90 -> 北海道初山別村 | CM90: 85 | CN90: =VLOOKUP(CL90,$M$6:$N$1784,2,FALSE) -> 0085 | CO90: =CM90&TEXT(CN90,0)&CK90 -> 8585初山別村 | CP90: 8585初山別村 | CQ90: =CO90=CP90 -> TRUE
L91: 0086-1 | M91: 北海道遠別町 | N91: 0086 | O91: 01 | P91: 014860 | Q91: 01 | R91: 486 | S91: 0 | T91: 遠別町 | U91: 01 | V91: 北海道厚生局 | W91: 014869 | X91: 1 | AA91: 遠別町 | CJ91: 北海道 | CK91: 遠別町 | CL91: =CJ91&CK91 -> 北海道遠別町 | CM91: 86 | CN91: =VLOOKUP(CL91,$M$6:$N$1784,2,FALSE) -> 0086 | CO91: =CM91&TEXT(CN91,0)&CK91 -> 8686遠別町 | CP91: 8686遠別町 | CQ91: =CO91=CP91 -> TRUE
L92: 0087-1 | M92: 北海道天塩町 | N92: 0087 | O92: 01 | P92: 014878 | Q92: 01 | R92: 487 | S92: 8 | T92: 天塩町 | U92: 01 | V92: 北海道厚生局 | W92: 014877 | X92: 1 | AA92: 天塩町 | CJ92: 北海道 | CK92: 天塩町 | CL92: =CJ92&CK92 -> 北海道天塩町 | CM92: 87 | CN92: =VLOOKUP(CL92,$M$6:$N$1784,2,FALSE) -> 0087 | CO92: =CM92&TEXT(CN92,0)&CK92 -> 8787天塩町 | CP92: 8787天塩町 | CQ92: =CO92=CP92 -> TRUE
L93: 0088-1 | M93: 北海道猿払村 | N93: 0088 | O93: 01 | P93: 015115 | Q93: 01 | R93: 511 | S93: 5 | T93: 猿払村 | U93: 01 | V93: 北海道厚生局 | W93: 015113 | X93: 1 | AA93: 猿払村 | CJ93: 北海道 | CK93: 猿払村 | CL93: =CJ93&CK93 -> 北海道猿払村 | CM93: 88 | CN93: =VLOOKUP(CL93,$M$6:$N$1784,2,FALSE) -> 0088 | CO93: =CM93&TEXT(CN93,0)&CK93 -> 8888猿払村 | CP93: 8888猿払村 | CQ93: =CO93=CP93 -> TRUE
L94: 0089-1 | M94: 北海道浜頓別町 | N94: 0089 | O94: 01 | P94: 015123 | Q94: 01 | R94: 512 | S94: 3 | T94: 浜頓別町 | U94: 01 | V94: 北海道厚生局 | W94: 015121 | X94: 1 | AA94: 浜頓別町 | CJ94: 北海道 | CK94: 浜頓別町 | CL94: =CJ94&CK94 -> 北海道浜頓別町 | CM94: 89 | CN94: =VLOOKUP(CL94,$M$6:$N$1784,2,FALSE) -> 0089 | CO94: =CM94&TEXT(CN94,0)&CK94 -> 8989浜頓別町 | CP94: 8989浜頓別町 | CQ94: =CO94=CP94 -> TRUE
L95: 0090-1 | M95: 北海道中頓別町 | N95: 0090 | O95: 01 | P95: 015131 | Q95: 01 | R95: 513 | S95: 1 | T95: 中頓別町 | U95: 01 | V95: 北海道厚生局 | W95: 015130 | X95: 1 | AA95: 中頓別町 | CJ95: 北海道 | CK95: 中頓別町 | CL95: =CJ95&CK95 -> 北海道中頓別町 | CM95: 90 | CN95: =VLOOKUP(CL95,$M$6:$N$1784,2,FALSE) -> 0090 | CO95: =CM95&TEXT(CN95,0)&CK95 -> 9090中頓別町 | CP95: 9090中頓別町 | CQ95: =CO95=CP95 -> TRUE
L96: 0091-1 | M96: 北海道枝幸町 | N96: 0091 | O96: 01 | P96: 015149 | Q96: 01 | R96: 514 | S96: 9 | T96: 枝幸町 | U96: 01 | V96: 北海道厚生局 | W96: 015148 | X96: 1 | AA96: 枝幸町 | CJ96: 北海道 | CK96: 枝幸町 | CL96: =CJ96&CK96 -> 北海道枝幸町 | CM96: 91 | CN96: =VLOOKUP(CL96,$M$6:$N$1784,2,FALSE) -> 0091 | CO96: =CM96&TEXT(CN96,0)&CK96 -> 9191枝幸町 | CP96: 9191枝幸町 | CQ96: =CO96=CP96 -> TRUE
L97: 0092-1 | M97: 北海道豊富町 | N97: 0092 | O97: 01 | P97: 015164 | Q97: 01 | R97: 516 | S97: 4 | T97: 豊富町 | U97: 01 | V97: 北海道厚生局 | W97: 015164 | X97: 1 | AA97: 豊富町 | CJ97: 北海道 | CK97: 豊富町 | CL97: =CJ97&CK97 -> 北海道豊富町 | CM97: 92 | CN97: =VLOOKUP(CL97,$M$6:$N$1784,2,FALSE) -> 0092 | CO97: =CM97&TEXT(CN97,0)&CK97 -> 9292豊富町 | CP97: 9292豊富町 | CQ97: =CO97=CP97 -> TRUE
... L188: 0180-4 | M188: 北海道東神楽町 | N188: 0183 | O188: 01 | P188: 014530 | Q188: 01 | R188: 453 | S188: 0 | T188: 東神楽町 | U188: 01 | V188: 北海道厚生局 | W188: 014532 | X188: 4 | AA188: 東神楽町 | CJ188: 青森県 | CK188: 横浜町 | CL188: =CJ188&CK188 -> 青森県横浜町 | CM188: 183 | CN188: =VLOOKUP(CL188,$M$6:$N$1784,2,FALSE) -> 0210 | CO188: =CM188&TEXT(CN188,0)&CK188 -> 183210横浜町 | CP188: 183210横浜町 | CQ188: =CO188=CP188 -> TRUE
L189: 0184-1 | M189: 青森県青森市 | N189: 0184 | O189: 02 | P189: 022012 | Q189: 02 | R189: 201 | S189: 2 | T189: 青森市 | U189: 02 | V189: 東北厚生局 | W189: 022012 | X189: 1 | CJ189: 青森県 | CK189: 東北町 | CL189: =CJ189&CK189 -> 青森県東北町 | CM189: 184 | CN189: =VLOOKUP(CL189,$M$6:$N$1784,2,FALSE) -> 0211 | CO189: =CM189&TEXT(CN189,0)&CK189 -> 184211東北町 | CP189: 184211東北町 | CQ189: =CO189=CP189 -> TRUE
L190: 0185-1 | M190: 青森県弘前市 | N190: 0185 | O190: 02 | P190: 022020 | Q190: 02 | R190: 202 | S190: 0 | T190: 弘前市 | U190: 02 | V190: 東北厚生局 | W190: 022021 | X190: 1 | CJ190: 青森県 | CK190: 六ヶ所村 | CL190: =CJ190&CK190 -> 青森県六ヶ所村 | CM190: 185 | CN190: =VLOOKUP(CL190,$M$6:$N$1784,2,FALSE) -> 0212 | CO190: =CM190&TEXT(CN190,0)&CK190 -> 185212六ヶ所村 | CP190: 185212六ヶ所村 | CQ190: =CO190=CP190 -> TRUE
L191: 0186-1 | M191: 青森県八戸市 | N191: 0186 | O191: 02 | P191: 022038 | Q191: 02 | R191: 203 | S191: 8 | T191: 八戸市 | U191: 02 | V191: 東北厚生局 | W191: 022039 | X191: 1 | CJ191: 青森県 | CK191: おいらせ町 | CL191: =CJ191&CK191 -> 青森県おいらせ町 | CM191: 186 | CN191: =VLOOKUP(CL191,$M$6:$N$1784,2,FALSE) -> 0213 | CO191: =CM191&TEXT(CN191,0)&CK191 -> 186213おいらせ町 | CP191: 186213おいらせ町 | CQ191: =CO191=CP191 -> TRUE
L192: 0187-1 | M192: 青森県黒石市 | N192: 0187 | O192: 02 | P192: 022046 | Q192: 02 | R192: 204 | S192: 6 | T192: 黒石市 | U192: 02 | V192: 東北厚生局 | W192: 022047 | X192: 1 | CJ192: 青森県 | CK192: 大間町 | CL192: =CJ192&CK192 -> 青森県大間町 | CM192: 187 | CN192: =VLOOKUP(CL192,$M$6:$N$1784,2,FALSE) -> 0214 | CO192: =CM192&TEXT(CN192,0)&CK192 -> 187214大間町 | CP192: 187214大間町 | CQ192: =CO192=CP192 -> TRUE
L193: 0188-1 | M193: 青森県五所川原市 | N193: 0188 | O193: 02 | P193: 022053 | Q193: 02 | R193: 205 | S193: 3 | T193: 五所川原市 | U193: 02 | V193: 東北厚生局 | W193: 022055 | X193: 1 | CJ193: 青森県 | CK193: 東通村 | CL193: =CJ193&CK193 -> 青森県東通村 | CM193: 188 | CN193: =VLOOKUP(CL193,$M$6:$N$1784,2,FALSE) -> 0215 | CO193: =CM193&TEXT(CN193,0)&CK193 -> 188215東通村 | CP193: 188215東通村 | CQ193: =CO193=CP193 -> TRUE
L194: 0189-1 | M194: 青森県十和田市 | N194: 0189 | O194: 02 | P194: 022061 | Q194: 02 | R194: 206 | S194: 1 | T194: 十和田市 | U194: 02 | V194: 東北厚生局 | W194: 022063 | X194: 1 | CJ194: 青森県 | CK194: 風間浦村 | CL194: =CJ194&CK194 -> 青森県風間浦村 | CM194: 189 | CN194: =VLOOKUP(CL194,$M$6:$N$1784,2,FALSE) -> 0216 | CO194: =CM194&TEXT(CN194,0)&CK194 -> 189216風間浦村 | CP194: 189216風間浦村 | CQ194: =CO194=CP194 -> TRUE
L195: 0190-1 | M195: 青森県三沢市 | N195: 0190 | O195: 02 | P195: 022079 | Q195: 02 | R195: 207 | S195: 9 | T195: 三沢市 | U195: 02 | V195: 東北厚生局 | W195: 022071 | X195: 1 | CJ195: 青森県 | CK195: 佐井村 | CL195: =CJ195&CK195 -> 青森県佐井村 | CM195: 190 | CN195: =VLOOKUP(CL195,$M$6:$N$1784,2,FALSE) -> 0217 | CO195: =CM195&TEXT(CN195,0)&CK195 -> 190217佐井村 | CP195: 190217佐井村 | CQ195: =CO195=CP195 -> TRUE
...

Sheet ←非表示

Sheet 当該年度上限額設定状況
B1: 上限額設定状況 | I1: =IFERROR(#REF!,"")
B3: ○ 保険者にて、入力情報を確認する際に使用してください。入力内容に誤りがあるときは、Ｊ列に示すシートに戻って修正してください。
B4: ○ シート名は変更しないでください。
B6: 項目 | C6: 事項 | I6: 転記元シート
B7: 総合事業 | C7: 開始年月 | D7: 平成 | E7: =#REF! -> #REF! | F7: 年 | G7: =#REF! -> #REF! | H7: 月 | I7: シート「初期設定」
C8: 令和７年度 交付申請時の上限額設定状況 | D8: =IF(#REF!=0,#REF!,PullDown!BY10) -> #REF! | I8: シート「総合事業上限額算定の手引き」
B9: 包括的支援事業 （地域包括支援センターの運営） 及び任意事業 | C9: 令和７年度 交付申請時の上限額設定状況 | D9: =IF('（参考）包括・任意事業の上限額算定の手引き'!E7="","",'（参考）包括・任意事業の上限額算定の手引き'!E7) -> ①原則の上限額 | I9: シート「包括・任意事業の上限額算定の手引き」
B10: 包括的支援事業 （社会保障充実分） | C10: 令和７年度 交付申請時の上限額設定状況 | D10: =IF(#REF!="","",#REF!) -> #REF! | I10: シート「包括的支援事業（社会保障充実分）標準額の手引き」

Sheet シート反映用データ
A1: 項番 | B1: 01通し番号 | C1: 01厚生（支）局名 | D1: 01都道府県名 | E1: 01保険者名 | F1: 01保険者番号 | G1: 01市区町村ｺｰﾄﾞ | H1: 01都道府県ｺｰﾄﾞ | I1: 01H27総合事業上限設定 | J1: 01H28総合事業上限設定 | K1: 01H29総合事業上限設定 | L1: 01H30総合事業上限設定 | M1: 01R1総合事業上限設定 | N1: 01R2総合事業上限設定 | O1: 01R3総合事業上限設定 | P1: 01R4総合事業上限設定 | Q1: 01R5総合事業上限設定 | R1: 01R6総合事業上限設定 | S1: 01総合事業移行年 | T1: 01総合事業移行月 | U1: 01総合事業移行日 | V1: 01総合事業移行年月日 | W1: 01総合事業移行年度 | X1: 01総合事業移行前年度 | Y1: 01指定都市 | Z1: 01広域連合等 | AA1: 01上記以外の市町村 | AB1: 01重層実施 | AC1: 01①地域介護予防活動支援事業に要する費用相当額を交付率で除して得た額 | AD1: 01②地域包括支援センターの運営に要する費用相当額を交付率で除して得た額 | AE1: 01③生活支援体制整備事業に要する費用相当額を交付率で除して得た額 | AF1: A1000 | AG1: A1100 | AH1: A1110 | AI1: A1120 | AJ1: A1130 | AK1: A1140 | AL1: A1150 | AM1: A1160 | AN1: A1200 | AO1: A1210 | AP1: A1220 | AQ1: A1230 | AR1: A1240 | AS1: A1250 | AT1: A1300 | AU1: A1310 | AV1: A1320 | AW1: A1330 | AX1: A1340 | AY1: A1400 | AZ1: A1500 | BA1: A1600 | BB1: A1700 | BC1: A1710 | BD1: A1720 | BE1: A1730 | BF1: A1740 | BG1: A1750 | BH1: A2000 | BI1: A2100 | BJ1: A2200 | BK1: A2210 | BL1: A2220 | BM1: A2230 | BN1: A3000 | BO1: A4000 | BP1: A4100 | BQ1: A4200 | BR1: A4210 | BS1: A4220 | BT1: A4230 | BU1: A4240 | BV1: A4300 | BW1: A4310 | BX1: A4320 | BY1: A4330 | BZ1: A4400 | CA1: A5000 | CB1: B1000 | CC1: B1100 | CD1: B1110 | CE1: B1120 | CF1: B1130 | CG1: B1140 | CH1: B1150 | CI1: B1160 | CJ1: B1200 | CK1: B1210 | CL1: B1220 | CM1: B1230 | CN1: B1240 | CO1: B1250 | CP1: B1300 | CQ1: B1310 | CR1: B1320 | CS1: B1330 | CT1: B1340 | CU1: B1400 | CV1: B1500 | CW1: B1600 | CX1: B1700 | CY1: B1710 | CZ1: B1720 | DA1: B1730 | DB1: B1740 | DC1: B1750 | DD1: B2000 | DE1: B2100 | DF1: B2200 | DG1: B2210 | DH1: B2220 | DI1: B2230 | DJ1: B3000 | DK1: B4000 | DL1: B4100 | DM1: B4200 | DN1: B4210 | DO1: B4220 | DP1: B4230 | DQ1: B4240 | DR1: B4300 | DS1: B4310 | DT1: B4320 | DU1: B4330 | DV1: B4400 | DW1: B5000 | DX1: C1000 | DY1: C1100 | DZ1: C1110 | EA1: C1120 | EB1: C1130 | EC1: C1140 | ED1: C1150 | EE1: C1160 | EF1: C1200 | EG1: C1210 | EH1: C1220 | EI1: C1230 | EJ1: C1240 | EK1: C1250 | EL1: C1300 | EM1: C1310 | EN1: C1320 | EO1: C1330 | EP1: C1340 | EQ1: C1400 | ER1: C1500 | ES1: C1600 | ET1: C1700 | EU1: C1710 | EV1: C1720 | EW1: C1730 | EX1: C1740 | EY1: C1750 | EZ1: C2000 | FA1: C2100 | FB1: C2200 | FC1: C2210 | FD1: C2220 | FE1: C2230 | FF1: C3000 | FG1: C4000 | FH1: C4100 | FI1: C4200 | FJ1: C4210 | FK1: C4220 | FL1: C4230 | FM1: C4240 | FN1: C4300 | FO1: C4310 | FP1: C4320 | FQ1: C4330 | FR1: C4400 | FS1: C5000 | FT1: D1000 | FU1: D1100 | FV1: D1110 | FW1: D1120 | FX1: D1130 | FY1: D1140 | FZ1: D1150 | GA1: D1160 | GB1: D1200 | GC1: D1210 | GD1: D1220 | GE1: D1230 | GF1: D1240 | GG1: D1250 | GH1: D1300 | GI1: D1310 | GJ1: D1320 | GK1: D1330 | GL1: D1340 | GM1: D1400 | GN1: D1500 | GO1: D1600 | GP1: D1700 | GQ1: D1710 | GR1: D1720 | GS1: D1730 | GT1: D1740 | GU1: D1750 | GV1: D2000 | GW1: D2100 | GX1: D2200 | GY1: D2210 | GZ1: D2220 | HA1: D2230 | HB1: D3000 | HC1: D4000 | HD1: D4100 | HE1: D4200 | HF1: D4210 | HG1: D4220 | HH1: D4230 | HI1: D4240 | HJ1: D4300 | HK1: D4310 | HL1: D4320 | HM1: D4330 | HN1: D4400 | HO1: D5000 | HP1: E1000 | HQ1: E2000 | HR1: E4000 | HS1: E4100 | HT1: E4200 | HU1: E4210 | HV1: E4220 | HW1: E4230 | HX1: E4240 | HY1: E4300 | HZ1: E4310 | IA1: E4320 | IB1: E4330 | IC1: E4400 | ID1: F1000 | IE1: F2000 | IF1: F3000 | IG1: F4000 | IH1: F5000 | II1: G1000 | IJ1: G2000 | IK1: G3000 | IL1: G4000 | IM1: G5000 | IN1: H1000 | IO1: H2000 | IP1: H3000 | IQ1: H4000 | IR1: H5000 | IS1: I1000 | IT1: I2000 | IU1: I3000 | IV1: I4000 | IW1: I5000 | IX1: J1000 | IY1: J2000 | IZ1: J3000 | JA1: J4000 | JB1: J5000 | JC1: K1000 | JD1: K2000 | JE1: K3000 | JF1: K4000 | JG1: K5000 | JH1: 備考欄1000 | JI1: 備考欄1100 | JJ1: 備考欄1110 | JK1: 備考欄1120 | JL1: 備考欄1130 | JM1: 備考欄1140 | JN1: 備考欄1150 | JO1: 備考欄1160 | JP1: 備考欄1200 | JQ1: 備考欄1210 | JR1: 備考欄1220 | JS1: 備考欄1230 | JT1: 備考欄1240 | JU1: 備考欄1250 | JV1: 備考欄1300 | JW1: 備考欄1310 | JX1: 備考欄1320 | JY1: 備考欄1330 | JZ1: 備考欄1340 | KA1: 備考欄1400 | KB1: 備考欄1500 | KC1: 備考欄1600 | KD1: 備考欄1700 | KE1: 備考欄1710 | KF1: 備考欄1720 | KG1: 備考欄1730 | KH1: 備考欄1740 | KI1: 備考欄1750 | KJ1: 備考欄2000 | KK1: 備考欄2100 | KL1: 備考欄2200 | KM1: 備考欄2210 | KN1: 備考欄2220 | KO1: 備考欄2230 | KP1: 備考欄3000 | KQ1: 備考欄4000 | KR1: 備考欄4100 | KS1: 備考欄4200 | KT1: 備考欄4210 | KU1: 備考欄4220 | KV1: 備考欄4230 | KW1: 備考欄4240 | KX1: 備考欄4300 | KY1: 備考欄4310 | KZ1: 備考欄4320 | LA1: 備考欄4330 | LB1: 備考欄4400 | LC1: 備考欄5000 | LD1: 総合事業の上限額設定状況 | LE1: 包括的支援事業（地域包括支援センターの運営）及び任意事業上限額設定状況 | LF1: 包括的支援事業（社会保障充実分）上限額設定状況 | LG1: 総合事業調整交付金調整基準標準事業費額 | LH1: 総合事業調整交付金所要額 | LI1: 重層的支援体制整備事業の実施有無 | LJ1: 重層的支援体制整備事業に要する費用相当額総額 | LK1: 重層的支援体制整備事業に要する地域介護予防活動支援事業費相当額 | LL1: 重層的支援体制整備事業に要する地域包括支援センターの運営費相当額 | LM1: 重層的支援体制整備事業に要する生活支援体制整備事業費相当額 | LN1: 重層Kセンター運営対象経費基本額（影響額調整後） | LO1: 重層aセンター運営地域支援事業で実施される任意事業に要する費用 | LP1: 重層K'センター運営小計（ K + a ） | LQ1: 重層Lセンター運営基準額 | LR1: 重層bセンター運営K’とLで、いずれか少ない額 | LS1: 重層Mセンター運営交付基本額（ b - a ） | LT1: 重層K'エラーセンター運営 | LU1: 重層Mエラーセンター運営 | LV1: 重層K地域介護予防対象経費基本額（影響額調整後） | LW1: 重層a地域介護予防地域支援事業で実施される介護予防・日常生活支援総合事業に要する費用 | LX1: 重層K'地域介護予防小計（ K + a ） | LY1: 重層L地域介護予防基準額 | LZ1: 重層b地域介護予防K’とLで、いずれか少ない額 | MA1: 重層M地域介護予防交付基本額（ b - a ） | MB1: 重層K'エラー地域介護予防 | MC1: 重層Mエラー地域介護予防 | MD1: 重層K生活支援体制整備対象経費基本額（影響額調整後） | ME1: 重層a生活支援体制整備地域支援事業で実施される包括的支援事業（社会保障充実分）に要する費用 | MF1: 重層K'生活支援体制整備小計（ K + a ） | MG1: 重層L生活支援体制整備基準額 | MH1: 重層b生活支援体制整備K’とLで、いずれか少ない額 | MI1: 重層M生活支援体制整備交付基本額（ b - a ） | MJ1: 重層K'エラー生活支援体制整備 | MK1: 重層Mエラー生活支援体制整備 | ML1: 02基本の上限額 | MM1: 02介護予防給付全体の伸びを考慮する上限額 | MN1: 02特例イ | MO1: 02特例ロ | MP1: 02原則の上限額 | MQ1: 02予防給付＋介護予防等事業の額 | MR1: 02予防給付の額 | MS1: 02予防給付全体の額（移行前年度） | MT1: 02予防給付全体の額（今年度） | MU1: 0275歳人口(平成２３年１０月１日) | MV1: 0275歳人口(平成２４年１０月１日) | MW1: 0275歳人口(平成２５年１０月１日) | MX1: 0275歳人口(平成２６年１０月１日) | MY1: 0275歳人口(平成２７年１０月１日) | MZ1: 0275歳人口(平成２８年１０月１日) | NA1: 0275歳人口(平成２９年１０月１日) | NB1: 0275歳人口(平成３０年１０月１日) | NC1: 0275歳人口(令和元年１０月１日) | ND1: 0275歳人口(令和２年１０月１日) | NE1: 0275歳人口(令和３年１０月１日) | NF1: 0275歳人口(令和４年１０月１日) | NG1: 025歳人口(令和５年１０月１日) | NH1: 025歳人口(令和６年１０月１日) | NI1: 0275歳以上高齢者伸び率使用値（基本の上限額を算定するにあたって参照する値） | NJ1: 0275歳以上高齢者伸び率使用値（特例イ・ロの額を算定するにあたって参照する値） | NK1: 02平成２９年度の介護予防・日常生活支援総合事業費額 | NL1: 02平成29年度の予防給付費額（介護予防訪問介護・介護予防通所介護・介護予防支援の合計額） | NM1: 02平成２９年度の予防給付費額全体 | NN1: 02対象経費支出予定額（清算書D欄） | NO1: 02実績に基づく上限超過額 | NP1: 02個別協議の要否 | NQ1: 02個別協議希望の有無 | NR1: 02事前の個別協議を行わない場合の政令で定める上限額 | NS1: 02前年10月１日人口 | NT1: 02前年10月１日65歳以上人口 | NU1: 02交付申請時における事前の個別協議の承認有無 | NV1: 02事由④の該当性 | NW1: 02上限超過承認希望額（事由④） | NX1: 02高齢者１人あたり事業費 | NY1: 02「離島等の市町村」への該当性 | NZ1: 02事由⑤の該当性 | OA1: 02上限超過承認希望額（事由⑤） | OB1: 0275歳以上被保険者数変動率 | OC1: 02将来における介護予防・日常生活支援総合事業に要する費用の低減に資すると見込まれる事業の実施の有無 | OD1: 02前年度における当該③による個別協議の有無 | OE1: 02前年度における上限超過承認額・・・ア | OF1: 02前年10月１日における75歳以上の人口 | OG1: 02前年10月１日における75歳以上80歳未満人口 | OH1: 02前年10月１日における80歳以上85歳未満人口 | OI1: 02前年10月１日における85歳以上の人口 | OJ1: 02前年度の10月１日における75歳以上80歳未満人口を同日における75歳以上人口で除して得た率・・・X1 | OK1: 02前年度の10月１日における80歳以上85歳未満人口を同日における75歳以上人口で除して得た率・・・Y1 | OL1: 02前年度の10月１日における85歳以上人口を同日における75歳以上人口で除して得た率・・・Z1 | OM1: 令和３年10月１日における75歳以上の人口 | ON1: 02当該年度の初日の属する年の４年前の４月１日の属する年度の10月１日における75歳以上80歳未満人口 | OO1: 02当該年度の初日の属する年の４年前の４月１日の属する年度の10月１日における80歳以上85歳未満人口 | OP1: 02当該年度の初日の属する年の４年前の４月１日の属する年度の10月１日における85歳以上の人口 | OQ1: 02当該年度の初日の属する年の４年前の４月１日の属する年度の10月１日における75歳以上80歳未満人口を同日における75歳以上人口で除して得た率・・・X2 | OR1: 02当該年度の初日の属する年の４年前の４月１日の属する年度の10月１日における80歳以上85歳未満人口を同日における75歳以上人口で除して得た率・・・Y2 | OS1: 02当該年度の初日の属する年の４年前の４月１日の属する年度の10月１日における85歳以上人口を同日における75歳以上人口で除して得た率・・・Z2 | OT1: 02 A×0.9×(X1＋Y1×2＋Z1×3)/(X2＋Y2×2＋Z2×3)＋A×0.1－A・・・イ | OU1: 02事由③の該当性 | OV1: 02上限超過承認希望額（事由③） | OW1: 02介護予防の効果が高く、かつ、将来における介護予防・日常生活支援総合事業に要する費用の低減に資すると見込まれる新たな事業の開始年度 | OX1: 02事由②の該当性（1年度目） | OY1: 02新たなプログラム等の実施に要する額（１年度目の上限超過承認希望額） | OZ1: 02前年度における本事由に係る上限超過承認額（２年度目） | PA1: 02当該年度における新たなプログラム等の実施に要する額 | PB1: 02前年度における個別協議の際に申請した当該見込み額 | PC1: 02事由②の該当性（2年度目） | PD1: 02 ２年度目の上限超過承認希望額 | PE1: 02前年度における本事由に係る上限超過承認額（３年度目） | PF1: 02当該年度年度における新たなプログラム等の実施に要する額 | PG1: 02事由②の該当性（３年度目） | PH1: 02 ３年度目の上限超過承認希望額 | PI1: 02 事由②による上限超過承認希望額 | PJ1: 02従前相当サービス以外の第一号訪問事業の対象経費支出予定額 | PK1: 02従前相当サービス以外の第一号通所事業の対象経費支出予定額 | PL1: 02要介護認定又は要支援認定の状況把握 | PM1: 02数の把握 | PN1: 02認定率（前々年度末日） | PO1: 02サービス利用率（前々年度末日） | PP1: 02認定率（前前々年度末日） | PQ1: 02サービス利用率（前前々年度末日） | PR1: 02前々年度の末日における認定率－前々々年度年度の末日における認定率≦０ | PS1: 02前々年度の末日におけるサービス利用率－前々々年度の末日におけるサービス利用率≦０ | PT1: 02調整済み認定率（前々年度末日） | PU1: 02全国の調整済み認定率の平均（前々年度末日） | PV1: 02全国の調整済みサービス利用率の平均（前々年度末日） | PW1: 02前々年度の末日における調整済み認定率－前々々年度の末日における全国の調整済み認定率の平均≦０ | PX1: 02前々年度の末日における調整済みサービス利用率－前々々年度の末日における全国の調整済みサービス利用率の平均≦０ | PY1: 02事由⑨の該当性 | PZ1: 02前々年度の末日に要介護認定を受けていた第１号被保険者であって、前年度の末日に要支援認定を受けている又は要介護認定及び要支援認定のいずれも受けていない者の数 | QA1: 02前年度の介護予防・日常生活支援総合事業のうち従前相当サービスに要する費用の額として、前年度の交付申請に計上した額 | QB1: 02前年度において、従前相当サービスを利用した者の数 | QC1: 02上限超過承認額（事由⑨） | QD1: 02(4)１、(4)２又は(4)３による個別協議を行う場合の上限超過の承認を希望する額 | QE1: 02(4)１、(4)２又は(4)３による個別協議を行う場合の政令で定める上限額 | QF1: 02(4)４のみによる個別協議を行う場合の上限超過の承認を希望する額 | QG1: 02(4)４のみによる個別協議を行う場合の政令で定める上限額 | QH1: 02(4)５のみによる個別協議を行う場合の上限超過の承認を希望する額 | QI1: 02(4)５のみによる個別協議を行う場合の政令で定める上限額 | QJ1: 02事由４による上限超過の承認を希望する額と事由５による上限超過の承認を希望する額の合計 | QK1: 02事由４による上限超過の承認を希望する額と事由５による上限超過の承認を希望する額の合計ー上限超過額 | QL1: 02149行目が０以下である場合の事由４による上限超過の承認を希望する額 | QM1: 02149行目が０以下である場合の事由５による上限超過の承認を希望する額 | QN1: 02149行目が０以下である場合の政令で定める上限額 | QO1: 02149行目が０を上回る場合、上限超過額ー事由４による上限超過の承認を希望する額 | QP1: 02153行目と147行目のいずれか少ない方の額 | QQ1: 02149行目が０を上回る場合の事由４による上限超過の承認を希望する額 | QR1: 02149行目が０を上回る場合の事由５による上限超過の承認を希望する額 | QS1: 02149行目が０を上回る場合の政令で定める上限額 | QT1: 02事前協議後の上限額（原則の上限額及び①～④のうち最も高い金額） | QU1: 02実際の上限超過額（事前協議後の上限超過額：163行目－159行目） | QV1: 02事後の個別協議の要否 | QW1: 02事後の個別協議希望の有無 | QX1: 02事後の個別協議を行わない場合の政令で定める上限額 | QY1: 02災害による居宅要支援被保険者等の数の増加有無 | QZ1: 02ア～ウのうち該当する項目 | RA1: 02ア・イに該当する場合には災害・感染症の名称、ウに該当する場合には具体的な内容 | RB1: 02事由①の該当性 | RC1: 02ア 災害により増加した居宅要支援被保険者等に対して実施した介護予防・日常生活支援総合事業に要した費用の額 | RD1: 02令和６年４月１日から令和６年９月30日における災害等にかかる令和６年度の介護予防・日常生活支援総合事業特別調整交付金の額 | RE1: 02令和６年10月１日から令和７年３月31日における災害等にかかる令和７年度に交付される予定の介護予防・日常生活支援総合事業特別調整交付金の額 | RF1: 02イ 介護保険法第122条の２第２項に規定する交付金の額の算定に関する省令（平成27年厚生労働省令第58号）第７条各号に定める介護予防・日常 生活支援総合事業特別調整交付金の額 | RG1: 02上限超過承認希望額（事由①） | RH1: 第一号訪問事業介護職員等ベースアップ等支援加算a | RI1: 第一号通所事業介護職員等ベースアップ等支援加算a | RJ1: 第一号訪問事業介護職員等処遇改善加算(Ⅰ)a | RK1: 第一号訪問事業介護職員等処遇改善加算(Ⅱ)a | RL1: 第一号訪問事業介護職員等処遇改善加算(Ⅲ)a | RM1: 第一号訪問事業介護職員等処遇改善加算(Ⅳ)a | RN1: 第一号訪問事業介護職員等処遇改善加算(Ⅴ)(1)a | RO1: 第一号訪問事業介護職員等処遇改善加算(Ⅴ)(2)a | RP1: 第一号訪問事業介護職員等処遇改善加算(Ⅴ)(3)a | RQ1: 第一号訪問事業介護職員等処遇改善加算(Ⅴ)(4)a | RR1: 第一号訪問事業介護職員等処遇改善加算(Ⅴ)(5)a | RS1: 第一号訪問事業介護職員等処遇改善加算(Ⅴ)(6)a | RT1: 第一号訪問事業介護職員等処遇改善加算(Ⅴ)(7)a | RU1: 第一号訪問事業介護職員等処遇改善加算(Ⅴ)(8)a | RV1: 第一号訪問事業介護職員等処遇改善加算(Ⅴ)(9)a | RW1: 第一号訪問事業介護職員等処遇改善加算(Ⅴ)(10)a | RX1: 第一号訪問事業介護職員等処遇改善加算(Ⅴ)(11)a | RY1: 第一号訪問事業介護職員等処遇改善加算(Ⅴ)(12)a | RZ1: 第一号訪問事業介護職員等処遇改善加算(Ⅴ)(13)a | SA1: 第一号訪問事業介護職員等処遇改善加算(Ⅴ)(14)a | SB1: 第一号通所事業介護職員等処遇改善加算(Ⅰ)a | SC1: 第一号通所事業介護職員等処遇改善加算(Ⅱ)a | SD1: 第一号通所事業介護職員等処遇改善加算(Ⅲ)a | SE1: 第一号通所事業介護職員等処遇改善加算(Ⅳ)a | SF1: 第一号通所事業介護職員等処遇改善加算(Ⅴ)(1)a | SG1: 第一号通所事業介護職員等処遇改善加算(Ⅴ)(2)a | SH1: 第一号通所事業介護職員等処遇改善加算(Ⅴ)(3)a | SI1: 第一号通所事業介護職員等処遇改善加算(Ⅴ)(4)a | SJ1: 第一号通所事業介護職員等処遇改善加算(Ⅴ)(5)a | SK1: 第一号通所事業介護職員等処遇改善加算(Ⅴ)(6)a | SL1: 第一号通所事業介護職員等処遇改善加算(Ⅴ)(7)a | SM1: 第一号通所事業介護職員等処遇改善加算(Ⅴ)(8)a | SN1: 第一号通所事業介護職員等処遇改善加算(Ⅴ)(9)a | SO1: 第一号通所事業介護職員等処遇改善加算(Ⅴ)(10)a | SP1: 第一号通所事業介護職員等処遇改善加算(Ⅴ)(11)a | SQ1: 第一号通所事業介護職員等処遇改善加算(Ⅴ)(12)a | SR1: 第一号通所事業介護職員等処遇改善加算(Ⅴ)(13)a | SS1: 第一号通所事業介護職員等処遇改善加算(Ⅴ)(14)a | ST1: 第一号訪問事業介護職員等ベースアップ等支援加算c | SU1: 第一号通所事業介護職員等ベースアップ等支援加算c | SV1: 第一号訪問事業介護職員等処遇改善加算(Ⅰ)c | SW1: 第一号訪問事業介護職員等処遇改善加算(Ⅱ)c | SX1: 第一号訪問事業介護職員等処遇改善加算(Ⅲ)c | SY1: 第一号訪問事業介護職員等処遇改善加算(Ⅳ)c | SZ1: 第一号訪問事業介護職員等処遇改善加算(Ⅴ)(1)c | TA1: 第一号訪問事業介護職員等処遇改善加算(Ⅴ)(2)c | TB1: 第一号訪問事業介護職員等処遇改善加算(Ⅴ)(3)c | TC1: 第一号訪問事業介護職員等処遇改善加算(Ⅴ)(4)c | TD1: 第一号訪問事業介護職員等処遇改善加算(Ⅴ)(5)c | TE1: 第一号訪問事業介護職員等処遇改善加算(Ⅴ)(6)c | TF1: 第一号訪問事業介護職員等処遇改善加算(Ⅴ)(7)c | TG1: 第一号訪問事業介護職員等処遇改善加算(Ⅴ)(8)c | TH1: 第一号訪問事業介護職員等処遇改善加算(Ⅴ)(9)c | TI1: 第一号訪問事業介護職員等処遇改善加算(Ⅴ)(10)c | TJ1: 第一号訪問事業介護職員等処遇改善加算(Ⅴ)(11)c | TK1: 第一号訪問事業介護職員等処遇改善加算(Ⅴ)(12)c | TL1: 第一号訪問事業介護職員等処遇改善加算(Ⅴ)(13)c | TM1: 第一号訪問事業介護職員等処遇改善加算(Ⅴ)(14)c | TN1: 第一号通所事業介護職員等処遇改善加算(Ⅰ)c | TO1: 第一号通所事業介護職員等処遇改善加算(Ⅱ)c | TP1: 第一号通所事業介護職員等処遇改善加算(Ⅲ)c | TQ1: 第一号通所事業介護職員等処遇改善加算(Ⅳ)c | TR1: 第一号通所事業介護職員等処遇改善加算(Ⅴ)(1)c | TS1: 第一号通所事業介護職員等処遇改善加算(Ⅴ)(2)c | TT1: 第一号通所事業介護職員等処遇改善加算(Ⅴ)(3)c | TU1: 第一号通所事業介護職員等処遇改善加算(Ⅴ)(4)c | TV1: 第一号通所事業介護職員等処遇改善加算(Ⅴ)(5)c | TW1: 第一号通所事業介護職員等処遇改善加算(Ⅴ)(6)c | TX1: 第一号通所事業介護職員等処遇改善加算(Ⅴ)(7)c | TY1: 第一号通所事業介護職員等処遇改善加算(Ⅴ)(8)c | TZ1: 第一号通所事業介護職員等処遇改善加算(Ⅴ)(9)c | UA1: 第一号通所事業介護職員等処遇改善加算(Ⅴ)(10)c | UB1: 第一号通所事業介護職員等処遇改善加算(Ⅴ)(11)c | UC1: 第一号通所事業介護職員等処遇改善加算(Ⅴ)(12)c | UD1: 第一号通所事業介護職員等処遇改善加算(Ⅴ)(13)c | UE1: 第一号通所事業介護職員等処遇改善加算(Ⅴ)(14)c | UF1: 02介護職員等処遇改善加算等の支給に要した費用 | UG1: 02事由⑦の該当性 | UH1: 02上限超過承認希望額（事由⑦） | UI1: 02継続利用要介護者に係る第一号訪問事業の実施に要した額 | UJ1: 02継続利用要介護者に係る第一号通所事業の実施に要した額 | UK1: 02継続利用要介護者に係る第一号生活支援事業の実施に要した額 | UL1: 02継続利用要介護者に係る第一号介護予防支援事業の実施に要した額 | UM1: 02事由⑧の該当性 | UN1: 02上限超過承認希望額（事由⑧） | UO1: 02令和２年度における介護予防支援に係る保険給付に要する費用の額 | UP1: 02令和５年度における介護予防支援に係る保険給付に要する費用の額 | UQ1: 02令和６年度の介護予防支援費変動率（（250行目/249行目）+1） | UR1: 02令和６年度の介護予防支援費変動率－75歳以上被保険者数変動率（251行目－248行目） | US1: 02令和６年度における介護予防支援に係る保険給付に要した費用の額 | UT1: 02イ 令和６年度の当該市町村の被保険者に対する介護予防支援に係る保険給付に要する費用の額に令和６年度の介護予防支援費変動率から令和６年度の75歳以上被保険者数変動率を減じて得た数（当該数が０以下である場合は０とする。）を乗じて得た額（252行目×254行目） | UU1: 02ウ 令和６年度の原則の上限額に、本項に定める事由以外の上限額告示及び本通知に定める事由により増加する当該年度の介護予防・日常生活支援総合事業に要する費用の額を加えた額（159行目+184行目+232行目+242行目） | UV1: 02事由⑥の該当性 | UW1: 02上限超過承認希望額（事由⑥） | UX1: 02事前の個別協議における上限超過承認額 | UY1: 02事後の個別協議における上限超過承認希望額の合計額 | UZ1: 02事後の個別協議における上限超過承認希望額 | VA1: 02事後（または事前・事後両方）の個別協議を行う場合の政令で定める上限額 | VB1: 02（うち事前・事後の個別協議における上限超過承認希望額） | VC1: 02令和６年度実績に基づく政令で定める上限額 | VD1: 低減計画H30事業費 | VE1: 低減計画H30上限超過額 | VF1: 低減計画R1事業費 | VG1: 低減計画R1上限超過額 | VH1: 低減計画R2事業費 | VI1: 低減計画R2上限超過額 | VJ1: 低減計画R3事業費 | VK1: 低減計画R3上限超過額 | VL1: 低減計画R4事業費 | VM1: 低減計画R4上限超過額 | VN1: 低減計画R5事業費 | VO1: 低減計画R5上限超過額 | VP1: 低減計画R6事業費 | VQ1: 低減計画R6上限超過額 | VR1: 03①新たなプログラム | VS1: 03②75歳以上被保険者数変動率1以下 | VT1: 03③1万人未満 | VU1: 03④離島 | VV1: 03⑤効果的な総合事業 | VW1: 03⑥災害 | VX1: 03⑦介護予防支援の増加率＞75歳以上被保険者数変動率 | VY1: 03⑧処遇改善 | VZ1: 03⑨継続利用要介護者 | WA1: 031(1)新たなプログラムの類型 | WB1: 031(2)新たなプログラムの開始年度 | WC1: 031(3)新たなプログラムの開始３年度目の事業費（見込額） | WD1: 031(4)新たなプログラムの開始３年度目の翌年度の事業費（見込額） | WE1: 031(5)開始２年度目の新たなプログラム等の実施に要する額が開始１年度目の当該額を上回る見込みの有無 | WF1: 03費用低減が見込まれる年度 | WG1: 03費用を低減させる方法 | WH1: 03前々年度認定率 | WI1: 03前々年度調整済み認定率 | WJ1: 03前々々年度認定率 | WK1: 03前々年度サービス利用率 | WL1: 03前々々年度サービス利用率 | WM1: 03災害による居宅要支援被保険者等の数の増加有無（有の場合に○） | WN1: 03介護予防支援費変動率 | WO1: 03介護職員等処遇改善加算等の支給に要した費用 | WP1: 03継続利用要介護者に係る第一号事業の実施に要した額 | WQ1: 034(1)30事業費 | WR1: 034(1)30個別 | WS1: 034(1)30超過 | WT1: 034(1)１事業費 | WU1: 034(1)１個別 | WV1: 034(1)１超過 | WW1: 034(1)2事業費 | WX1: 034(1)2個別 | WY1: 034(1)2超過 | WZ1: 034(1)3事業費 | XA1: 034(1)3個別 | XB1: 034(1)3超過 | XC1: 034(1)4事業費 | XD1: 034(1)4個別 | XE1: 034(1)4超過 | XF1: 034(1)5事業費 | XG1: 034(1)5個別 | XH1: 034(1)5超過 | XI1: 034(1)6事業費 | XJ1: 034(1)6個別 | XK1: 034(1)6超過 | XL1: 034(1)7事業費 | XM1: 034(1)7個別 | XN1: 034(1)7超過 | XO1: 03(2)３年度目の翌年度には、介護予防・日常生活支援総合事業に要する費用が令和６年度の原則の上限額以下となるための方策（理由①のみ） | XP1: 03（1(5)が○の場合のみ）新たなプログラムを開始した日が１年度目の途中であること又は２年度目以降に新たなプログラムの実施対象地域の拡大を予定していること等の事情により、予め２年度目の新たなプログラム等の実施に要する額が１年度目の当該額を上回ることが見込まれる場合、上回る理由と上回る額 | XQ1: 04通し番号1 | XR1: 04市町村名1 | XS1: 04適用する上限式1 | XT1: 04A1 | XU1: 04B1 | XV1: 04C1 | XW1: 04D1 | XX1: 40 | XY1: 04F1 | XZ1: 04G1 | YA1: 04H1 | YB1: 04I1 | YC1: 04J1 | YD1: 04(a)1 | YE1: 04K1 | YF1: 04(b)1 | YG1: 04(a)、(b)のいずれか高い方の金額1 | YH1: 04上限式適否1 | YI1: 04通し番号2 | YJ1: 04市町村名2 | YK1: 04適用する上限式2 | YL1: 04A2 | YM1: 04B2 | YN1: 04C2 | YO1: 04D2 | YP1: 400 | YQ1: 04F2 | YR1: 04G2 | YS1: 04H2 | YT1: 04I2 | YU1: 04J2 | YV1: 04(a)2 | YW1: 04K2 | YX1: 04(b)2 | YY1: 04(a)、(b)のいずれか高い方の金額2 | YZ1: 04上限式適否2 | ZA1: 04通し番号3 | ZB1: 04市町村名3 | ZC1: 04適用する上限式3 | ZD1: 04A3 | ZE1: 04B3 | ZF1: 04C3 | ZG1: 04D3 | ZH1: 4000 | ZI1: 04F3 | ZJ1: 04G3 | ZK1: 04H3 | ZL1: 04I3 | ZM1: 04J3 | ZN1: 04(a)3 | ZO1: 04K3 | ZP1: 04(b)3 | ZQ1: 04(a)、(b)のいずれか高い方の金額3 | ZR1: 04上限式適否3 | ZS1: 04通し番号4 | ZT1: 04市町村名4 | ZU1: 04適用する上限式4 | ZV1: 04A4 | ZW1: 04B4 | ZX1: 04C4 | ZY1: 04D4 | ZZ1: 40000 | AAA1: 04F4 | AAB1: 04G4 | AAC1: 04H4 | AAD1: 04I4 | AAE1: 04J4 | AAF1: 04(a)4 | AAG1: 04K4 | AAH1: 04(b)4 | AAI1: 04(a)、(b)のいずれか高い方の金額4 | AAJ1: 04上限式適否4 | AAK1: 04通し番号5 | AAL1: 04市町村名5 | AAM1: 04適用する上限式5 | AAN1: 04A5 | AAO1: 04B5 | AAP1: 04C5 | AAQ1: 04D5 | AAR1: 400000 | AAS1: 04F5 | AAT1: 04G5 | AAU1: 04H5 | AAV1: 04I5 | AAW1: 04J5 | AAX1: 04(a)5 | AAY1: 04K5 | AAZ1: 04(b)5 | ABA1: 04(a)、(b)のいずれか高い方の金額5 | ABB1: 04上限式適否5 | ABC1: 04通し番号6 | ABD1: 04市町村名6 | ABE1: 04適用する上限式6 | ABF1: 04A6 | ABG1: 04B6 | ABH1: 04C6 | ABI1: 04D6 | ABJ1: 4000000 | ABK1: 04F6 | ABL1: 04G6 | ABM1: 04H6 | ABN1: 04I6 | ABO1: 04J6 | ABP1: 04(a)6 | ABQ1: 04K6 | ABR1: 04(b)6 | ABS1: 04(a)、(b)のいずれか高い方の金額6 | ABT1: 04上限式適否6 | ABU1: 04通し番号7 | ABV1: 04市町村名7 | ABW1: 04適用する上限式7 | ABX1: 04A7 | ABY1: 04B7 | ABZ1: 04C7 | ACA1: 04D7 | ACB1: 40000000 | ACC1: 04F7 | ACD1: 04G7 | ACE1: 04H7 | ACF1: 04I7 | ACG1: 04J7 | ACH1: 04(a)7 | ACI1: 04K7 | ACJ1: 04(b)7 | ACK1: 04(a)、(b)のいずれか高い方の金額7 | ACL1: 04上限式適否7 | ACM1: 04通し番号8 | ACN1: 04市町村名8 | ACO1: 04適用する上限式8 | ACP1: 04A8 | ACQ1: 04B8 | ACR1: 04C8 | ACS1: 04D8 | ACT1: 400000000 | ACU1: 04F8 | ACV1: 04G8 | ACW1: 04H8 | ACX1: 04I8 | ACY1: 04J8 | ACZ1: 04(a)8 | ADA1: 04K8 | ADB1: 04(b)8 | ADC1: 04(a)、(b)のいずれか高い方の金額8 | ADD1: 04上限式適否8 | ADE1: 04通し番号9 | ADF1: 04市町村名9 | ADG1: 04適用する上限式9 | ADH1: 04A9 | ADI1: 04B9 | ADJ1: 04C9 | ADK1: 04D9 | ADL1: 4000000000 | ADM1: 04F9 | ADN1: 04G9 | ADO1: 04H9 | ADP1: 04I9 | ADQ1: 04J9 | ADR1: 04(a)9 | ADS1: 04K9 | ADT1: 04(b)9 | ADU1: 04(a)、(b)のいずれか高い方の金額9 | ADV1: 04上限式適否9 | ADW1: 04通し番号10 | ADX1: 04市町村名10 | ADY1: 04適用する上限式10 | ADZ1: 04A10 | AEA1: 04B10 | AEB1: 04C10 | AEC1: 04D10 | AED1: 40000000000 | AEE1: 04F10 | AEF1: 04G10 | AEG1: 04H10 | AEH1: 04I10 | AEI1: 04J10 | AEJ1: 04(a)10 | AEK1: 04K10 | AEL1: 04(b)10 | AEM1: 04(a)、(b)のいずれか高い方の金額10 | AEN1: 04上限式適否10 | AEO1: 04通し番号11 | AEP1: 04市町村名11 | AEQ1: 04適用する上限式11 | AER1: 04A11 | AES1: 04B11 | AET1: 04C11 | AEU1: 04D11 | AEV1: 400000000000 | AEW1: 04F11 | AEX1: 04G11 | AEY1: 04H11 | AEZ1: 04I11 | AFA1: 04J11 | AFB1: 04(a)11 | AFC1: 04K11 | AFD1: 04(b)11 | AFE1: 04(a)、(b)のいずれか高い方の金額11 | AFF1: 04上限式適否11 | AFG1: 04通し番号12 | AFH1: 04市町村名12 | AFI1: 04適用する上限式12 | AFJ1: 04A12 | AFK1: 04B12 | AFL1: 04C12 | AFM1: 04D12 | AFN1: 4000000000000 | AFO1: 04F12 | AFP1: 04G12 | AFQ1: 04H12 | AFR1: 04I12 | AFS1: 04J12 | AFT1: 04(a)12 | AFU1: 04K12 | AFV1: 04(b)12 | AFW1: 04(a)、(b)のいずれか高い方の金額12 | AFX1: 04上限式適否12 | AFY1: 04通し番号13 | AFZ1: 04市町村名13 | AGA1: 04適用する上限式13 | AGB1: 04A13 | AGC1: 04B13 | AGD1: 04C13 | AGE1: 04D13 | AGF1: 40000000000000 | AGG1: 04F13 | AGH1: 04G13 | AGI1: 04H13 | AGJ1: 04I13 | AGK1: 04J13 | AGL1: 04(a)13 | AGM1: 04K13 | AGN1: 04(b)13 | AGO1: 04(a)、(b)のいずれか高い方の金額13 | AGP1: 04上限式適否13 | AGQ1: 04通し番号14 | AGR1: 04市町村名14 | AGS1: 04適用する上限式14 | AGT1: 04A14 | AGU1: 04B14 | AGV1: 04C14 | AGW1: 04D14 | AGX1: 400000000000000 | AGY1: 04F14 | AGZ1: 04G14 | AHA1: 04H14 | AHB1: 04I14 | AHC1: 04J14 | AHD1: 04(a)14 | AHE1: 04K14 | AHF1: 04(b)14 | AHG1: 04(a)、(b)のいずれか高い方の金額14 | AHH1: 04上限式適否14 | AHI1: 04通し番号15 | AHJ1: 04市町村名15 | AHK1: 04適用する上限式15 | AHL1: 04A15 | AHM1: 04B15 | AHN1: 04C15 | AHO1: 04D15 | AHP1: 4e+15 | AHQ1: 04F15 | AHR1: 04G15 | AHS1: 04H15 | AHT1: 04I15 | AHU1: 04J15 | AHV1: 04(a)15 | AHW1: 04K15 | AHX1: 04(b)15 | AHY1: 04(a)、(b)のいずれか高い方の金額15 | AHZ1: 04上限式適否15 | AIA1: 04通し番号16 | AIB1: 04市町村名16 | AIC1: 04適用する上限式16 | AID1: 04A16 | AIE1: 04B16 | AIF1: 04C16 | AIG1: 04D16 | AIH1: 4e+16 | AII1: 04F16 | AIJ1: 04G16 | AIK1: 04H16 | AIL1: 04I16 | AIM1: 04J16 | AIN1: 04(a)16 | AIO1: 04K16 | AIP1: 04(b)16 | AIQ1: 04(a)、(b)のいずれか高い方の金額16 | AIR1: 04上限式適否16 | AIS1: 04通し番号17 | AIT1: 04市町村名17 | AIU1: 04適用する上限式17 | AIV1: 04A17 | AIW1: 04B17 | AIX1: 04C17 | AIY1: 04D17 | AIZ1: 4e+17 | AJA1: 04F17 | AJB1: 04G17 | AJC1: 04H17 | AJD1: 04I17 | AJE1: 04J17 | AJF1: 04(a)17 | AJG1: 04K17 | AJH1: 04(b)17 | AJI1: 04(a)、(b)のいずれか高い方の金額17 | AJJ1: 04上限式適否17 | AJK1: 04通し番号18 | AJL1: 04市町村名18 | AJM1: 04適用する上限式18 | AJN1: 04A18 | AJO1: 04B18 | AJP1: 04C18 | AJQ1: 04D18 | AJR1: 4e+18 | AJS1: 04F18 | AJT1: 04G18 | AJU1: 04H18 | AJV1: 04I18 | AJW1: 04J18 | AJX1: 04(a)18 | AJY1: 04K18 | AJZ1: 04(b)18 | AKA1: 04(a)、(b)のいずれか高い方の金額18 | AKB1: 04上限式適否18 | AKC1: 04通し番号19 | AKD1: 04市町村名19 | AKE1: 04適用する上限式19 | AKF1: 04A19 | AKG1: 04B19 | AKH1: 04C19 | AKI1: 04D19 | AKJ1: 4e+19 | AKK1: 04F19 | AKL1: 04G19 | AKM1: 04H19 | AKN1: 04I19 | AKO1: 04J19 | AKP1: 04(a)19 | AKQ1: 04K19 | AKR1: 04(b)19 | AKS1: 04(a)、(b)のいずれか高い方の金額19 | AKT1: 04上限式適否19 | AKU1: 04通し番号20 | AKV1: 04市町村名20 | AKW1: 04適用する上限式20 | AKX1: 04A20 | AKY1: 04B20 | AKZ1: 04C20 | ALA1: 04D20 | ALB1: 4e+20 | ALC1: 04F20 | ALD1: 04G20 | ALE1: 04H20 | ALF1: 04I20 | ALG1: 04J20 | ALH1: 04(a)20 | ALI1: 04K20 | ALJ1: 04(b)20 | ALK1: 04(a)、(b)のいずれか高い方の金額20 | ALL1: 04上限式適否20 | ALM1: 04通し番号21 | ALN1: 04市町村名21 | ALO1: 04適用する上限式21 | ALP1: 04A21 | ALQ1: 04B21 | ALR1: 04C21 | ALS1: 04D21 | ALT1: 4e+21 | ALU1: 04F21 | ALV1: 04G21 | ALW1: 04H21 | ALX1: 04I21 | ALY1: 04J21 | ALZ1: 04(a)21 | AMA1: 04K21 | AMB1: 04(b)21 | AMC1: 04(a)、(b)のいずれか高い方の金額21 | AMD1: 04上限式適否21 | AME1: 04通し番号22 | AMF1: 04市町村名22 | AMG1: 04適用する上限式22 | AMH1: 04A22 | AMI1: 04B22 | AMJ1: 04C22 | AMK1: 04D22 | AML1: 4e+22 | AMM1: 04F22 | AMN1: 04G22 | AMO1: 04H22 | AMP1: 04I22 | AMQ1: 04J22 | AMR1: 04(a)22 | AMS1: 04K22 | AMT1: 04(b)22 | AMU1: 04(a)、(b)のいずれか高い方の金額22 | AMV1: 04上限式適否22 | AMW1: 04通し番号23 | AMX1: 04市町村名23 | AMY1: 04適用する上限式23 | AMZ1: 04A23 | ANA1: 04B23 | ANB1: 04C23 | ANC1: 04D23 | AND1: 4e+23 | ANE1: 04F23 | ANF1: 04G23 | ANG1: 04H23 | ANH1: 04I23 | ANI1: 04J23 | ANJ1: 04(a)23 | ANK1: 04K23 | ANL1: 04(b)23 | ANM1: 04(a)、(b)のいずれか高い方の金額23 | ANN1: 04上限式適否23 | ANO1: 04通し番号24 | ANP1: 04市町村名24 | ANQ1: 04適用する上限式24 | ANR1: 04A24 | ANS1: 04B24 | ANT1: 04C24 | ANU1: 04D24 | ANV1: 4e+24 | ANW1: 04F24 | ANX1: 04G24 | ANY1: 04H24 | ANZ1: 04I24 | AOA1: 04J24 | AOB1: 04(a)24 | AOC1: 04K24 | AOD1: 04(b)24 | AOE1: 04(a)、(b)のいずれか高い方の金額24 | AOF1: 04上限式適否24 | AOG1: 04通し番号25 | AOH1: 04市町村名25 | AOI1: 04適用する上限式25 | AOJ1: 04A25 | AOK1: 04B25 | AOL1: 04C25 | AOM1: 04D25 | AON1: 4e+25 | AOO1: 04F25 | AOP1: 04G25 | AOQ1: 04H25 | AOR1: 04I25 | AOS1: 04J25 | AOT1: 04(a)25 | AOU1: 04K25 | AOV1: 04(b)25 | AOW1: 04(a)、(b)のいずれか高い方の金額25 | AOX1: 04上限式適否25 | AOY1: 04通し番号26 | AOZ1: 04市町村名26 | APA1: 04適用する上限式26 | APB1: 04A26 | APC1: 04B26 | APD1: 04C26 | APE1: 04D26 | APF1: 4e+26 | APG1: 04F26 | APH1: 04G26 | API1: 04H26 | APJ1: 04I26 | APK1: 04J26 | APL1: 04(a)26 | APM1: 04K26 | APN1: 04(b)26 | APO1: 04(a)、(b)のいずれか高い方の金額26 | APP1: 04上限式適否26 | APQ1: 04通し番号27 | APR1: 04市町村名27 | APS1: 04適用する上限式27 | APT1: 04A27 | APU1: 04B27 | APV1: 04C27 | APW1: 04D27 | APX1: 4e+27 | APY1: 04F27 | APZ1: 04G27 | AQA1: 04H27 | AQB1: 04I27 | AQC1: 04J27 | AQD1: 04(a)27 | AQE1: 04K27 | AQF1: 04(b)27 | AQG1: 04(a)、(b)のいずれか高い方の金額27 | AQH1: 04上限式適否27 | AQI1: 04通し番号28 | AQJ1: 04市町村名28 | AQK1: 04適用する上限式28 | AQL1: 04A28 | AQM1: 04B28 | AQN1: 04C28 | AQO1: 04D28 | AQP1: 4e+28 | AQQ1: 04F28 | AQR1: 04G28 | AQS1: 04H28 | AQT1: 04I28 | AQU1: 04J28 | AQV1: 04(a)28 | AQW1: 04K28 | AQX1: 04(b)28 | AQY1: 04(a)、(b)のいずれか高い方の金額28 | AQZ1: 04上限式適否28 | ARA1: 04通し番号29 | ARB1: 04市町村名29 | ARC1: 04適用する上限式29 | ARD1: 04A29 | ARE1: 04B29 | ARF1: 04C29 | ARG1: 04D29 | ARH1: 4e+29 | ARI1: 04F29 | ARJ1: 04G29 | ARK1: 04H29 | ARL1: 04I29 | ARM1: 04J29 | ARN1: 04(a)29 | ARO1: 04K29 | ARP1: 04(b)29 | ARQ1: 04(a)、(b)のいずれか高い方の金額29 | ARR1: 04上限式適否29 | ARS1: 04通し番号30 | ART1: 04市町村名30 | ARU1: 04適用する上限式30 | ARV1: 04A30 | ARW1: 04B30 | ARX1: 04C30 | ARY1: 04D30 | ARZ1: 4e+30 | ASA1: 04F30 | ASB1: 04G30 | ASC1: 04H30 | ASD1: 04I30 | ASE1: 04J30 | ASF1: 04(a)30 | ASG1: 04K30 | ASH1: 04(b)30 | ASI1: 04(a)、(b)のいずれか高い方の金額30 | ASJ1: 04上限式適否30 | ASK1: 04通し番号31 | ASL1: 04市町村名31 | ASM1: 04適用する上限式31 | ASN1: 04A31 | ASO1: 04B31 | ASP1: 04C31 | ASQ1: 04D31 | ASR1: 4e+31 | ASS1: 04F31 | AST1: 04G31 | ASU1: 04H31 | ASV1: 04I31 | ASW1: 04J31 | ASX1: 04(a)31 | ASY1: 04K31 | ASZ1: 04(b)31 | ATA1: 04(a)、(b)のいずれか高い方の金額31 | ATB1: 04上限式適否31 | ATC1: 04通し番号32 | ATD1: 04市町村名32 | ATE1: 04適用する上限式32 | ATF1: 04A32 | ATG1: 04B32 | ATH1: 04C32 | ATI1: 04D32 | ATJ1: 4e+32 | ATK1: 04F32 | ATL1: 04G32 | ATM1: 04H32 | ATN1: 04I32 | ATO1: 04J32 | ATP1: 04(a)32 | ATQ1: 04K32 | ATR1: 04(b)32 | ATS1: 04(a)、(b)のいずれか高い方の金額32 | ATT1: 04上限式適否32 | ATU1: 04通し番号33 | ATV1: 04市町村名33 | ATW1: 04適用する上限式33 | ATX1: 04A33 | ATY1: 04B33 | ATZ1: 04C33 | AUA1: 04D33 | AUB1: 4e+33 | AUC1: 04F33 | AUD1: 04G33 | AUE1: 04H33 | AUF1: 04I33 | AUG1: 04J33 | AUH1: 04(a)33 | AUI1: 04K33 | AUJ1: 04(b)33 | AUK1: 04(a)、(b)のいずれか高い方の金額33 | AUL1: 04上限式適否33 | AUM1: 04通し番号34 | AUN1: 04市町村名34 | AUO1: 04適用する上限式34 | AUP1: 04A34 | AUQ1: 04B34 | AUR1: 04C34 | AUS1: 04D34 | AUT1: 4e+34 | AUU1: 04F34 | AUV1: 04G34 | AUW1: 04H34 | AUX1: 04I34 | AUY1: 04J34 | AUZ1: 04(a)34 | AVA1: 04K34 | AVB1: 04(b)34 | AVC1: 04(a)、(b)のいずれか高い方の金額34 | AVD1: 04上限式適否34 | AVE1: 05①総事業費 | AVF1: 05②対象経費額（様式１B欄） | AVG1: 05③寄付金その他の収入額 | AVH1: 05④指定介護予防支援等にかかる収入額 | AVI1: 05⑤総合相談支援事業の一部委託にかかる委託費 | AVJ1: 05⑥委託費を除いた総事業費 | AVK1: 05⑦様式１A欄 | AVL1: 05⑧様式１C欄 | AVM1: 05⑩様式１D欄 | AVN1: 05設置する地域包括支援センター数 | AVO1: 06地域包括支援センター数 | AVP1: 06日常生活圏域数 | AVQ1: 06専任の認知症地域支援推進員 | AVR1: 06第１層(市町村圏域）の数 | AVS1: 06行政区数 | AVT1: 06構成市町村数 | AVU1: 06（広域）専任の認知症地域支援推進員 | AVV1: 06在宅医療・介護連携推進事業の実施 | AVW1: 06生活支援コーディネーター・協議体の実施 | AVX1: 06相談支援連携体制構築事業の実施 | AVY1: 06住民参画・官民連携推進事業の実施 | AVZ1: 06就労的活動支援コーディネーターの実施 | AWA1: 06認知症初期集中支援事業の実施 | AWB1: 06認知症地域支援・ケア向上事業の実施 | AWC1: 06認知症サポーター活動促進・地域づくり推進事業の実施 | AWD1: 06地域ケア会議推進事業の実施 | AWE1: 06居住支援連携の実施 | AWF1: 06標準額 | AWG1: 06個別協議額 | AWH1: 06在宅医療・介護連携推進事業標準額 | AWI1: 06生活支援コーディネーター・協議体標準額 | AWJ1: 06相談支援連携体制構築事業標準額 | AWK1: 06住民参画・官民連携推進事業標準額 | AWL1: 06就労的活動支援コーディネーター標準額 | AWM1: 06認知症初期集中支援事業標準額 | AWN1: 06認知症地域支援・ケア向上事業標準額 | AWO1: 06認知症サポーター活動促進・地域づくり推進事業標準額 | AWP1: 06地域ケア会議推進事業標準額 | AWQ1: 06（再掲）居住支援加算標準額 | AWR1: 06【令和６年度包括的支援事業（社会保障充実分）上限額設定】 | AWS1: 06エラー | AWT1: 06-1（一般市町村）SCをセンターに配置 | AWU1: 06-1（指定都市）実施行政区数 | AWV1: 06-1（指定都市）うちSCをセンターに配置している数 | AWW1: 06-1（広域）実施構成市町村数 | AWX1: 06-1（広域）うちSCをセンターに配置している数 | AWY1: 06-1（広域）うち重層実施数 | AWZ1: 06-2（指定都市）連携体制構築されている行政区数 | AXA1: 06-2（広域）連携体制構築されている構成市町村数 | AXB1: 07社会保障充実分対象経費額 | AXC1: 07標準額 | AXD1: 07①在宅医療・介護連携推進対象経費額 | AXE1: 07①ア（イ）等の会議 | AXF1: 07①イ（ア）の相談窓口 | AXG1: 07①イ（ア）のコーディネーター | AXH1: 07①イ（ウ）②多職種研修 | AXI1: 07①イ（ウ）②その他の研修 | AXJ1: 07②生活支援体制整備対象経費額 | AXK1: 07②第１層生活支援コーディネーター | AXL1: 07②第２層生活支援コーディネーター | AXM1: 07②住民参画・官民連携推進事業 | AXN1: 07②就労的活動支援コーディネーター | AXO1: 07③認知症総合支援対象経費額 | AXP1: 07③認知症初期集中支援チーム設置 | AXQ1: 07③認知症地域支援推進員設置 | AXR1: 07③うち専任の認知症地域支援推進員 | AXS1: 07③チームオレンジコーディネーター | AXT1: 07④地域ケア会議推進事業対象経費額 | AXU1: 07④地域ケア個別会議 | AXV1: 07④居住支援連携 | AXW1: 07主な理由 | AXX1: 08①対象経費額 | AXY1: 08①事業内容 | AXZ1: 08①効果 | AYA1: 08②対象経費額 | AYB1: 08②事業内容 | AYC1: 08②効果 | AYD1: 08③対象経費額 | AYE1: 08③事業内容 | AYF1: 08③効果 | AYG1: 08④対象経費額 | AYH1: 08④事業内容 | AYI1: 08④効果 | AYJ1: 08⑤対象経費額 | AYK1: 08⑤事業内容 | AYL1: 08⑤効果 | AYM1: 08⑥対象経費額 | AYN1: 08⑥事業内容 | AYO1: 08⑥効果 | AYP1: 08⑦対象経費額 | AYQ1: 08⑦事業内容 | AYR1: 08⑦効果 | AYS1: 08⑧対象経費額 | AYT1: 08⑧事業内容 | AYU1: 08⑧効果 | AYV1: 08⑨対象経費額 | AYW1: 08⑨事業内容 | AYX1: 08⑨効果 | AYY1: 08⑩対象経費額 | AYZ1: 08⑩事業内容 | AZA1: 08⑩効果 | AZB1: 08⑪対象経費額 | AZC1: 08⑪事業内容 | AZD1: 08⑪効果 | AZE1: 08⑫対象経費額 | AZF1: 08⑫事業内容 | AZG1: 08⑫効果 | AZH1: 08⑬対象経費額 | AZI1: 08⑬事業内容 | AZJ1: 08⑬効果 | AZK1: 08⑭対象経費額 | AZL1: 08⑭事業内容 | AZM1: 08⑭効果 | AZN1: 08⑮対象経費額 | AZO1: 08⑮事業内容 | AZP1: 08⑮効果 | AZQ1: 08⑯対象経費額 | AZR1: 08⑯事業内容 | AZS1: 08⑯効果 | AZT1: 08⑰対象経費額 | AZU1: 08⑰事業内容 | AZV1: 08⑰効果 | AZW1: 08⑱対象経費額 | AZX1: 08⑱事業内容 | AZY1: 08⑱効果 | AZZ1: 08⑲対象経費額 | BAA1: 08⑲事業内容 | BAB1: 08⑲効果 | BAC1: 08⑳対象経費額 | BAD1: 08⑳事業内容 | BAE1: 08⑳効果 | BAF1: 08㉑対象経費額 | BAG1: 08㉑事業内容 | BAH1: 08㉑効果 | BAI1: 08事業名（特区等） | BAJ1: 08対象経費額（特区等） | BAK1: 08事業内容（特区等） | BAL1: 08効果（特区等） | BAM1: 08合計 | BAN1: 保険者No | BAO1: 市町村 | BAP1: 有 | BAQ1: (1)R2対象経費支出予定額 | BAR1: (1)R3対象経費支出予定額 | BAS1: (1)R4対象経費支出予定額 | BAT1: (1)R5対象経費支出予定額 | BAU1: (1)R6対象経費支出予定額 | BAV1: (2)交付上限額 | BAW1: (3)やむを得ない事情の場合の交付上限額 | BAX1: (4)①下方変動 | BAY1: (4)①上方変動 | BAZ1: (4)①その他 | BBA1: (4)②その他の内容 | BBB1: (5)合計人数 | BBC1: (5)人数（地域支援事業） | BBD1: (5)人数（市町村特別給付） | BBE1: (5)人数（保健福祉事業） | BBF1: (5)人数（一般財源） | BBG1: (5)合計額 | BBH1: (5)支出予定額（地域支援事業） | BBI1: (5)支出予定額（市町村特別給付） | BBJ1: (5)支出予定額（保健福祉事業） | BBK1: (5)支出予定額（一般財源） | BBL1: (6)①第１～３段階（要介護５） | BBM1: (6)①第４段階（要介護５） | BBN1: (6)①第５段階（要介護５） | BBO1: (6)①第１～３段階（要介護４） | BBP1: (6)①第４段階（要介護４） | BBQ1: (6)①第５段階（要介護４） | BBR1: (6)①第１～３段階（要介護３） | BBS1: (6)①第４段階（要介護３） | BBT1: (6)①第５段階（要介護３） | BBU1: (6)①第１～３段階（要介護１～２） | BBV1: (6)①第４段階（要介護１～２） | BBW1: (6)①第５段階（要介護１～２） | BBX1: (6)①第１～３段階（要支援１～２） | BBY1: (6)①第４段階（要支援１～２） | BBZ1: (6)①第５段階（要支援１～２） | BCA1: (6)①第１～３段階（事業対象者） | BCB1: (6)①第４段階（事業対象者） | BCC1: (6)①第５段階（事業対象者） | BCD1: (6)②一人当たり支給上限額 | BCE1: (6)②詳細 | BCF1: (6)③交付希望額 | BCG1: R6廃止・縮小 | BCH1: R6具体的な取組（縮小） | BCI1: R6廃止後の移行先等 | BCJ1: R7廃止・縮小 | BCK1: R7具体的な取組（縮小） | BCL1: R7廃止後の移行先等 | BCM1: R8廃止・縮小 | BCN1: R8具体的な取組（縮小） | BCO1: R8廃止後の移行先等 | BCP1: 10文書番号 | BCQ1: 10提出年月日 | BCR1: 比較A介護予防・日常生活支援総合事業 | BCS1: 比較A包括的支援事業（地域包括支援センターの運営）及び任意事業 | BCT1: 比較A在宅医療・介護連携推進事業 | BCU1: 比較A生活支援コーディネーター・協議体 | BCV1: 比較A住民参画・官民連携推進事業 | BCW1: 比較A就労的活動支援コーディネーター | BCX1: 比較A認知症初期集中支援推進事業 | BCY1: 比較A認知症地域支援・ケア向上事業 | BCZ1: 比較A認知症サポーター活動促進・地域づくり推進事業 | BDA1: 比較A地域ケア会議推進事業 | BDB1: 比較A合計 | BDC1: 比較B介護予防・日常生活支援総合事業 | BDD1: 比較B包括的支援事業（地域包括支援センターの運営）及び任意事業 | BDE1: 比較B在宅医療・介護連携推進事業 | BDF1: 比較B生活支援コーディネーター・協議体 | BDG1: 比較B住民参画・官民連携推進事業 | BDH1: 比較B就労的活動支援コーディネーター | BDI1: 比較B認知症初期集中支援推進事業 | BDJ1: 比較B認知症地域支援・ケア向上事業 | BDK1: 比較B認知症サポーター活動促進・地域づくり推進事業 | BDL1: 比較B地域ケア会議推進事業 | BDM1: 比較B合計 | BDN1: 比較C介護予防・日常生活支援総合事業 | BDO1: 比較C包括的支援事業（地域包括支援センターの運営）及び任意事業 | BDP1: 比較C在宅医療・介護連携推進事業 | BDQ1: 比較C生活支援コーディネーター・協議体 | BDR1: 比較C住民参画・官民連携推進事業 | BDS1: 比較C就労的活動支援コーディネーター | BDT1: 比較C認知症初期集中支援推進事業 | BDU1: 比較C認知症地域支援・ケア向上事業 | BDV1: 比較C認知症サポーター活動促進・地域づくり推進事業 | BDW1: 比較C地域ケア会議推進事業 | BDX1: 比較C合計 | BDY1: 比較D介護予防・日常生活支援総合事業 | BDZ1: 比較D包括的支援事業（地域包括支援センターの運営）及び任意事業 | BEA1: 比較D在宅医療・介護連携推進事業 | BEB1: 比較D生活支援コーディネーター・協議体 | BEC1: 比較D住民参画・官民連携推進事業 | BED1: 比較D就労的活動支援コーディネーター | BEE1: 比較D認知症初期集中支援推進事業 | BEF1: 比較D認知症地域支援・ケア向上事業 | BEG1: 比較D認知症サポーター活動促進・地域づくり推進事業 | BEH1: 比較D地域ケア会議推進事業 | BEI1: 比較D合計 | BEJ1: 比較E総合事業 | BEK1: 比較E包括・任意 | BEL1: 比較E社補充 | BEM1: 比較F総合事業 | BEN1: 比較F包括・任意 | BEO1: 比較F社補充 | BEP1: 比較F合計 | BEQ1: 比較G総合事業 | BER1: 比較G包括・任意 | BES1: 比較G社補充 | BET1: 比較G合計 | BEU1: 比較H調整基準標準事業費額 | BEV1: 比較I総合事業調整交付金所要額 | BEW1: 比較J上限設定の選択（総合事業） | BEX1: 比較J上限設定の選択（包括・任意） | BEY1: 比較J上限設定の選択（社補充） | BEZ1: 比較K個別協議の有無（総合事業） | BFA1: 比較K個別協議の有無（社補充） | BFB1: 比較重層実施の有無 | BFC1: 比較重層全体 | BFD1: 比較重層①地域介護予防活動支援事業費相当額 | BFE1: 比較重層② 地域包括支援センターの運営費相当額 | BFF1: 比較重層③ 生活支援体制整備事業費相当額 | BFG1: 重層bエラーセンター運営 | BFH1: 重層bエラー地域介護予防 | BFI1: 重層bエラー生活支援体制整備 | BFJ1: 事前協議書番号 | BFK1: 事前協議書日付 | BFL1: 事前協議書職氏名 | BFM1: 事前協議書協議額 | BFN1: 事前協議書総合事業 | BFO1: 事前協議書包括任意 | BFP1: 事前協議書社保充 | BFQ1: 別紙様式２番号 | BFR1: 別紙様式２日付 | BFS1: 別紙様式２職氏名 | BFT1: 別紙様式２職申請額 | BFU1: 別紙様式２総合事業 | BFV1: 別紙様式２包括任意 | BFW1: 別紙様式２社保充 | BFX1: 社保充計画書②生活支援コーディネーターを中心とした相談支援連携体制構築事業 | BFY1: 介護用品計画書（６）①支給予定人数計 | BFZ1: 変更の有無 | BGB1: 交付決定通知 | BGC1: 交付決定総合事業 | BGD1: 交付決定包括任意 | BGE1: 交付決定社保充
A2: 362 | B2: 405 | C2: 東北厚生局 | D2: 福島県 | E2: 小野町 | F2: 75226 | G2: 522 | H2: 7 | I2: ①基本の上限額 | J2: ①基本の上限額 | K2: ①基本の上限額 | L2: ⑤個別協議 | M2: ⑤個別協議 | N2: ⑤個別協議 | O2: ⑤個別協議 | P2: ⑤個別協議 | Q2: ⑤個別協議 | R2: ⑤個別協議 | S2: 27 | T2: 4 | U2: 1 | V2: 42095 | W2: 42095 | X2: 41730 | Y2: 0 | Z2: 0 | AA2: ○ | AB2: ②未実施 | AC2: 0 | AD2: 0 | AE2: 0 | AF2: 39809000 | AG2: 5627000 | AH2: 5627000 | AI2: 0 | AJ2: 0 | AK2: 0 | AL2: 0 | AM2: 0 | AN2: 25006000 | AO2: 25006000 | AP2: 0 | AQ2: 0 | AR2: 0 | AS2: 0 | AT2: 0 | AU2: 0 | AV2: 0 | AW2: 0 | AX2: 0 | AY2: 2929000 | AZ2: 121000 | BA2: 120000 | BB2: 6006000 | BC2: 0 | BD2: 0 | BE2: 6006000 | BF2: 0 | BG2: 0 | BH2: 20703000 | BI2: 17484000 | BJ2: 3219000 | BK2: 638000 | BL2: 1350000 | BM2: 1231000 | BN2: 60512000 | BO2: 10963000 | BP2: 2890000 | BQ2: 3249000 | BR2: 3249000 | BS2: 0 | BT2: 0 | BU2: 0 | BV2: 3883000 | BW2: 0 | BX2: 0 | BY2: 3883000 | BZ2: 941000 | CA2: 71475000 | CB2: 0 | CC2: 0 | CD2: 0 | CE2: 0 | CF2: 0 | CG2: 0 | CH2: 0 | CI2: 0 | CJ2: 0 | CK2: 0 | CL2: 0 | CM2: 0 | CN2: 0 | CO2: 0 | CP2: 0 | CQ2: 0 | CR2: 0 | CS2: 0 | CT2: 0 | CU2: 0 | CV2: 0 | CW2: 0 | CX2: 0 | CY2: 0 | CZ2: 0 | DA2: 0 | DB2: 0 | DC2: 0 | DD2: 0 | DE2: 0 | DF2: 0 | DG2: 0 | DH2: 0 | DI2: 0 | DJ2: 0 | DK2: 0 | DL2: 0 | DM2: 0 | DN2: 0 | DO2: 0 | DP2: 0 | DQ2: 0 | DR2: 0 | DS2: 0 | DT2: 0 | DU2: 0 | DV2: 0 | DW2: 0 | DX2: 39809000 | DY2: 5627000 | DZ2: 5627000 | EA2: 0 | EB2: 0 | EC2: 0 | ED2: 0 | EE2: 0 | EF2: 25006000 | EG2: 25006000 | EH2: 0 | EI2: 0 | EJ2: 0 | EK2: 0 | EL2: 0 | EM2: 0 | EN2: 0 | EO2: 0 | EP2: 0 | EQ2: 2929000 | ER2: 121000 | ES2: 120000 | ET2: 6006000 | EU2: 0 | EV2: 0 | EW2: 6006000 | EX2: 0 | EY2: 0 | EZ2: 20703000 | FA2: 17484000 | FB2: 3219000 | FC2: 638000 | FD2: 1350000 | FE2: 1231000 | FF2: 60512000 | FG2: 10963000 | FH2: 2890000 | FI2: 3249000 | FJ2: 3249000 | FK2: 0 | FL2: 0 | FM2: 0 | FN2: 3883000 | FO2: 0 | FP2: 0 | FQ2: 3883000 | FR2: 941000 | FS2: 71475000 | FT2: 39809000 | FU2: 5627000 | FV2: 5627000 | FW2: 0 | FX2: 0 | FY2: 0 | FZ2: 0 | GA2: 0 | GB2: 25006000 | GC2: 25006000 | GD2: 0 | GE2: 0 | GF2: 0 | GG2: 0 | GH2: 0 | GI2: 0 | GJ2: 0 | GK2: 0 | GL2: 0 | GM2: 2929000 | GN2: 121000 | GO2: 120000 | GP2: 6006000 | GQ2: 0 | GR2: 0 | GS2: 6006000 | GT2: 0 | GU2: 0 | GV2: 20703000 | GW2: 17484000 | GX2: 3219000 | GY2: 638000 | GZ2: 1350000 | HA2: 1231000 | HB2: 60512000 | HC2: 10963000 | HD2: 2890000 | HE2: 3249000 | HF2: 3249000 | HG2: 0 | HH2: 0 | HI2: 0 | HJ2: 3883000 | HK2: 0 | HL2: 0 | HM2: 3883000 | HN2: 941000 | HO2: 71475000 | HP2: 39809000 | HQ2: 24153173 | HR2: 28886000 | HS2: 4819000 | HT2: 8000000 | HU2: 8000000 | HV2: 0 | HW2: 0 | HX2: 0 | HY2: 14795000 | HZ2: 10266000 | IA2: 0 | IB2: 4529000 | IC2: 1272000 | ID2: 39809000 | IE2: 20703000 | IF2: 60512000 | IG2: 10963000 | IH2: 71475000 | II2: 7961800 | IJ2: 7970655 | IK2: 15932455 | IL2: 4220755 | IM2: 20153210 | IN2: 0 | IO2: 0 | IP2: 0 | IQ2: 0 | IR2: 0 | IS2: 0 | IT2: 0 | IU2: 0 | IV2: 0 | IW2: 0 | IX2: 0 | IY2: 0 | IZ2: 0 | JA2: 0 | JB2: 0 | JC2: -7961800 | JD2: -7970655 | JE2: -15932455 | JF2: -4220755 | JG2: -20153210 | JH2: 7961800 | JI2: 0 | JJ2: 0 | JK2: 0 | JL2: 0 | JM2: 0 | JN2: 0 | JO2: 0 | JP2: 0 | JQ2: 0 | JR2: 0 | JS2: 0 | JT2: 0 | JU2: 0 | JV2: 0 | JW2: 0 | JX2: 0 | JY2: 0 | JZ2: 0 | KA2: 0 | KB2: 0 | KC2: 0 | KD2: 0 | KE2: 0 | KF2: 0 | KG2: 0 | KH2: 0 | KI2: 0 | KJ2: 7970655 | KK2: 0 | KL2: 0 | KM2: 0 | KN2: 0 | KO2: 0 | KP2: 15932455 | KQ2: 4220755 | KR2: 0 | KS2: 0 | KT2: 0 | KU2: 0 | KV2: 0 | KW2: 0 | KX2: 0 | KY2: 0 | KZ2: 0 | LA2: 0 | LB2: 0 | LC2: 20153210 | LD2: ⑤個別協議希望 | LE2: ①原則の上限額 | LF2: ①標準額 | LG2: 34833023 | LH2: 2575000 | LI2: ②未実施 | LJ2: 0 | LK2: 0 | LL2: 0 | LM2: 0 | LN2: 0 | LO2: 0 | LP2: 0 | LQ2: 0 | LR2: 0 | LS2: 0 | LT2: 金額が一致しません | LU2: 初期設定シートと一致しません | LV2: 6006000 | LW2: 33803000 | LX2: 39809000 | LY2: 39809000 | LZ2: 39809000 | MA2: 6006000 | MB2: OK | MC2: 初期設定シートと一致しません | MD2: 0 | ME2: 0 | MF2: 0 | MG2: 0 | MH2: 0 | MI2: 0 | MJ2: 金額が一致しません | MK2: 初期設定シートと一致しません | ML2: 5847848 | MM2: -13136791 | MN2: 0 | MO2: 0 | MP2: 5847848 | MQ2: 26788377 | MR2: 18979000 | MS2: 36936839 | MT2: 47369000 | MU2: 1921 | MV2: 1955 | MW2: 1965 | MX2: 1981 | MY2: 1978 | MZ2: 1930 | NA2: 1920 | NB2: 1881 | NC2: 1872 | ND2: 1841 | NE2: 1801 | NF2: 1792 | NG2: 1802 | NH2: 1812 | NI2: 0.92677689 | NJ2: 0 | NK2: 0 | NL2: 0 | NM2: 0 | NN2: 39809000 | NO2: 33961152 | NP2: 要 | NQ2: 有 | NR2: 5847848 | NS2: 8916 | NT2: 3497 | NU2: 0 | NV2: ○ | NW2: 33961152 | NX2: 11383.758 | NY2: 0 | NZ2: × | OA2: 0 | OB2: 1.002 | OC2: 0 | OD2: 0 | OE2: 0 | OF2: 1812 | OG2: 0 | OH2: 0 | OI2: 1812 | OJ2: 0 | OK2: 0 | OL2: 1 | OM2: 1801 | ON2: 0 | OO2: 0 | OP2: 1801 | OQ2: 0 | OR2: 0 | OS2: 1 | OT2: 0 | OU2: × | OV2: 0 | OW2: 0 | OX2: × | OY2: 0 | OZ2: 0 | PA2: 0 | PB2: 0 | PC2: × | PD2: 0 | PE2: 0 | PF2: 0 | PG2: × | PH2: 0 | PI2: 0 | PJ2: 0 | PK2: 0 | PL2: 0 | PM2: 0 | PN2: 0 | PO2: 0 | PP2: 0 | PQ2: 0 | PR2: 0 | PS2: 0 | PT2: 0 | PU2: 0.19418786 | PV2: 0.76158993 | PW2: -0.19418786 | PX2: -0.76158993 | PY2: × | PZ2: 0 | QA2: 0 | QB2: 0 | QC2: 0 | QD2: 33961152 | QE2: 39809000 | QF2: 0 | QG2: 5847848 | QH2: 0 | QI2: 5847848 | QJ2: 0 | QK2: -33961152 | QL2: 0 | QM2: 0 | QN2: 5847848 | QO2: 0 | QP2: 0 | QQ2: 0 | QR2: 0 | QS2: 0 | QT2: 39809000 | QU2: 0 | QV2: 不要 | QW2: 0 | QX2: 39809000 | QY2: 0 | QZ2: 0 | RA2: 0 | RB2: × | RC2: 0 | RD2: 0 | RE2: 0 | RF2: 0 | RG2: 0 | RH2: 0 | RI2: 0 | RJ2: 0 | RK2: 0 | RL2: 0 | RM2: 0 | RN2: 0 | RO2: 0 | RP2: 0 | RQ2: 0 | RR2: 0 | RS2: 0 | RT2: 0 | RU2: 0 | RV2: 0 | RW2: 0 | RX2: 0 | RY2: 0 | RZ2: 0 | SA2: 0 | SB2: 0 | SC2: 0 | SD2: 0 | SE2: 0 | SF2: 0 | SG2: 0 | SH2: 0 | SI2: 0 | SJ2: 0 | SK2: 0 | SL2: 0 | SM2: 0 | SN2: 0 | SO2: 0 | SP2: 0 | SQ2: 0 | SR2: 0 | SS2: 0 | ST2: 0 | SU2: 0 | SV2: 0 | SW2: 0 | SX2: 0 | SY2: 0 | SZ2: 0 | TA2: 0 | TB2: 0 | TC2: 0 | TD2: 0 | TE2: 0 | TF2: 0 | TG2: 0 | TH2: 0 | TI2: 0 | TJ2: 0 | TK2: 0 | TL2: 0 | TM2: 0 | TN2: 0 | TO2: 0 | TP2: 0 | TQ2: 0 | TR2: 0 | TS2: 0 | TT2: 0 | TU2: 0 | TV2: 0 | TW2: 0 | TX2: 0 | TY2: 0 | TZ2: 0 | UA2: 0 | UB2: 0 | UC2: 0 | UD2: 0 | UE2: 0 | UF2: 0 | UG2: × | UH2: 0 | UI2: 0 | UJ2: 0 | UK2: 0 | UL2: 0 | UM2: × | UN2: 0 | UO2: 0 | UQ2: 0 | UR2: -1.002 | US2: 0 | UT2: 0 | UU2: 39809000 | UV2: × | UW2: 0 | UX2: 33961152 | UY2: 0 | UZ2: 0 | VA2: 39809000 | VB2: 33961152 | VC2: 5847848 | VD2: 0 | VE2: 0 | VF2: 0 | VG2: 0 | VH2: 0 | VI2: 0 | VJ2: 0 | VK2: 0 | VL2: 0 | VM2: 0 | VN2: 0 | VO2: 0 | VP2: 0 | VQ2: 0 | VR2: × | VS2: × | VT2: ○ | VU2: × | VV2: × | VW2: × | VX2: × | VY2: × | VZ2: × | WA2: 0 | WB2: 0 | WC2: 0 | WD2: 0 | WE2: 0 | WF2: 0 | WG2: 0 | WH2: 0 | WI2: 0 | WJ2: 0 | WK2: 0 | WL2: 0 | WM2: 0 | WN2: 0 | WO2: 0 | WP2: 0 | WQ2: 0 | WR2: ● | WS2: 0 | WT2: 0 | WU2: ● | WV2: 0 | WW2: 0 | WX2: ● | WY2: 0 | WZ2: 0 | XA2: ● | XB2: 0 | XC2: 0 | XD2: ● | XE2: 0 | XF2: 0 | XG2: ● | XH2: 0 | XI2: 0 | XJ2: ● | XK2: 0 | XL2: 39809 | XM2: ● | XN2: 33961.152 | XO2: 0 | XP2: 0 | XQ2: 405 | XR2: 小野町 | XS2: ①原則の上限額 | XT2: 24076130 | XU2: 3464 | XV2: 3497 | XW2: 1.0032 | XX2: 24153173 | XY2: 3497 | XZ2: 19427777 | YA2: 3252210 | YB2: 22679987 | YC2: 3219000 | YD2: 3252210 | YE2: 0 | YF2: 0 | YG2: 3252210 | YH2: ○ | YI2: 0 | YJ2: 0 | YK2: 0 | YL2: 0 | YM2: 0 | YN2: 0 | YP2: 0 | YQ2: 0 | YR2: 0 | YS2: 0 | YT2: 0 | YU2: 0 | YV2: 0 | YW2: 0 | YX2: 0 | YY2: 0 | YZ2: × | ZA2: 0 | ZB2: 0 | ZC2: 0 | ZD2: 0 | ZE2: 0 | ZF2: 0 | ZH2: 0 | ZI2: 0 | ZJ2: 0 | ZK2: 0 | ZL2: 0 | ZM2: 0 | ZN2: 0 | ZO2: 0 | ZP2: 0 | ZQ2: 0 | ZR2: × | ZS2: 0 | ZT2: 0 | ZU2: 0 | ZV2: 0 | ZW2: 0 | ZX2: 0 | ZZ2: 0 | AAA2: 0 | AAB2: 0 | AAC2: 0 | AAD2: 0 | AAE2: 0 | AAF2: 0 | AAG2: 0 | AAH2: 0 | AAI2: 0 | AAJ2: × | AAK2: 0 | AAL2: 0 | AAM2: 0 | AAN2: 0 | AAO2: 0 | AAP2: 0 | AAR2: 0 | AAS2: 0 | AAT2: 0 | AAU2: 0 | AAV2: 0 | AAW2: 0 | AAX2: 0 | AAY2: 0 | AAZ2: 0 | ABA2: 0 | ABB2: × | ABC2: 0 | ABD2: 0 | ABE2: 0 | ABF2: 0 | ABG2: 0 | ABH2: 0 | ABJ2: 0 | ABK2: 0 | ABL2: 0 | ABM2: 0 | ABN2: 0 | ABO2: 0 | ABP2: 0 | ABQ2: 0 | ABR2: 0 | ABS2: 0 | ABT2: × | ABU2: 0 | ABV2: 0 | ABW2: 0 | ABX2: 0 | ABY2: 0 | ABZ2: 0 | ACB2: 0 | ACC2: 0 | ACD2: 0 | ACE2: 0 | ACF2: 0 | ACG2: 0 | ACH2: 0 | ACI2: 0 | ACJ2: 0 | ACK2: 0 | ACL2: × | ACM2: 0 | ACN2: 0 | ACO2: 0 | ACP2: 0 | ACQ2: 0 | ACR2: 0 | ACT2: 0 | ACU2: 0 | ACV2: 0 | ACW2: 0 | ACX2: 0 | ACY2: 0 | ACZ2: 0 | ADA2: 0 | ADB2: 0 | ADC2: 0 | ADD2: × | ADE2: 0 | ADF2: 0 | ADG2: 0 | ADH2: 0 | ADI2: 0 | ADJ2: 0 | ADL2: 0 | ADM2: 0 | ADN2: 0 | ADO2: 0 | ADP2: 0 | ADQ2: 0 | ADR2: 0 | ADS2: 0 | ADT2: 0 | ADU2: 0 | ADV2: × | ADW2: 0 | ADX2: 0 | ADY2: 0 | ADZ2: 0 | AEA2: 0 | AEB2: 0 | AED2: 0 | AEE2: 0 | AEF2: 0 | AEG2: 0 | AEH2: 0 | AEI2: 0 | AEJ2: 0 | AEK2: 0 | AEL2: 0 | AEM2: 0 | AEN2: × | AEO2: 0 | AEP2: 0 | AEQ2: 0 | AER2: 0 | AES2: 0 | AET2: 0 | AEV2: 0 | AEW2: 0 | AEX2: 0 | AEY2: 0 | AEZ2: 0 | AFA2: 0 | AFB2: 0 | AFC2: 0 | AFD2: 0 | AFE2: 0 | AFF2: × | AFG2: 0 | AFH2: 0 | AFI2: 0 | AFJ2: 0 | AFK2: 0 | AFL2: 0 | AFN2: 0 | AFO2: 0 | AFP2: 0 | AFQ2: 0 | AFR2: 0 | AFS2: 0 | AFT2: 0 | AFU2: 0 | AFV2: 0 | AFW2: 0 | AFX2: × | AFY2: 0 | AFZ2: 0 | AGA2: 0 | AGB2: 0 | AGC2: 0 | AGD2: 0 | AGF2: 0 | AGG2: 0 | AGH2: 0 | AGI2: 0 | AGJ2: 0 | AGK2: 0 | AGL2: 0 | AGM2: 0 | AGN2: 0 | AGO2: 0 | AGP2: × | AGQ2: 0 | AGR2: 0 | AGS2: 0 | AGT2: 0 | AGU2: 0 | AGV2: 0 | AGX2: 0 | AGY2: 0 | AGZ2: 0 | AHA2: 0 | AHB2: 0 | AHC2: 0 | AHD2: 0 | AHE2: 0 | AHF2: 0 | AHG2: 0 | AHH2: × | AHI2: 0 | AHJ2: 0 | AHK2: 0 | AHL2: 0 | AHM2: 0 | AHN2: 0 | AHP2: 0 | AHQ2: 0 | AHR2: 0 | AHS2: 0 | AHT2: 0 | AHU2: 0 | AHV2: 0 | AHW2: 0 | AHX2: 0 | AHY2: 0 | AHZ2: × | AIA2: 0 | AIB2: 0 | AIC2: 0 | AID2: 0 | AIE2: 0 | AIF2: 0 | AIH2: 0 | AII2: 0 | AIJ2: 0 | AIK2: 0 | AIL2: 0 | AIM2: 0 | AIN2: 0 | AIO2: 0 | AIP2: 0 | AIQ2: 0 | AIR2: × | AIS2: 0 | AIT2: 0 | AIU2: 0 | AIV2: 0 | AIW2: 0 | AIX2: 0 | AIZ2: 0 | AJA2: 0 | AJB2: 0 | AJC2: 0 | AJD2: 0 | AJE2: 0 | AJF2: 0 | AJG2: 0 | AJH2: 0 | AJI2: 0 | AJJ2: × | AJK2: 0 | AJL2: 0 | AJM2: 0 | AJN2: 0 | AJO2: 0 | AJP2: 0 | AJR2: 0 | AJS2: 0 | AJT2: 0 | AJU2: 0 | AJV2: 0 | AJW2: 0 | AJX2: 0 | AJY2: 0 | AJZ2: 0 | AKA2: 0 | AKB2: × | AKC2: 0 | AKD2: 0 | AKE2: 0 | AKF2: 0 | AKG2: 0 | AKH2: 0 | AKJ2: 0 | AKK2: 0 | AKL2: 0 | AKM2: 0 | AKN2: 0 | AKO2: 0 | AKP2: 0 | AKQ2: 0 | AKR2: 0 | AKS2: 0 | AKT2: × | AKU2: 0 | AKV2: 0 | AKW2: 0 | AKX2: 0 | AKY2: 0 | AKZ2: 0 | ALB2: 0 | ALC2: 0 | ALD2: 0 | ALE2: 0 | ALF2: 0 | ALG2: 0 | ALH2: 0 | ALI2: 0 | ALJ2: 0 | ALK2: 0 | ALL2: × | ALM2: 0 | ALN2: 0 | ALO2: 0 | ALP2: 0 | ALQ2: 0 | ALR2: 0 | ALT2: 0 | ALU2: 0 | ALV2: 0 | ALW2: 0 | ALX2: 0 | ALY2: 0 | ALZ2: 0 | AMA2: 0 | AMB2: 0 | AMC2: 0 | AMD2: × | AME2: 0 | AMF2: 0 | AMG2: 0 | AMH2: 0 | AMI2: 0 | AMJ2: 0 | AML2: 0 | AMM2: 0 | AMN2: 0 | AMO2: 0 | AMP2: 0 | AMQ2: 0 | AMR2: 0 | AMS2: 0 | AMT2: 0 | AMU2: 0 | AMV2: × | AMW2: 0 | AMX2: 0 | AMY2: 0 | AMZ2: 0 | ANA2: 0 | ANB2: 0 | AND2: 0 | ANE2: 0 | ANF2: 0 | ANG2: 0 | ANH2: 0 | ANI2: 0 | ANJ2: 0 | ANK2: 0 | ANL2: 0 | ANM2: 0 | ANN2: × | ANO2: 0 | ANP2: 0 | ANQ2: 0 | ANR2: 0 | ANS2: 0 | ANT2: 0 | ANV2: 0 | ANW2: 0 | ANX2: 0 | ANY2: 0 | ANZ2: 0 | AOA2: 0 | AOB2: 0 | AOC2: 0 | AOD2: 0 | AOE2: 0 | AOF2: × | AOG2: 0 | AOH2: 0 | AOI2: 0 | AOJ2: 0 | AOK2: 0 | AOL2: 0 | AON2: 0 | AOO2: 0 | AOP2: 0 | AOQ2: 0 | AOR2: 0 | AOS2: 0 | AOT2: 0 | AOU2: 0 | AOV2: 0 | AOW2: 0 | AOX2: × | AOY2: 0 | AOZ2: 0 | APA2: 0 | APB2: 0 | APC2: 0 | APD2: 0 | APF2: 0 | APG2: 0 | APH2: 0 | API2: 0 | APJ2: 0 | APK2: 0 | APL2: 0 | APM2: 0 | APN2: 0 | APO2: 0 | APP2: × | APQ2: 0 | APR2: 0 | APS2: 0 | APT2: 0 | APU2: 0 | APV2: 0 | APX2: 0 | APY2: 0 | APZ2: 0 | AQA2: 0 | AQB2: 0 | AQC2: 0 | AQD2: 0 | AQE2: 0 | AQF2: 0 | AQG2: 0 | AQH2: × | AQI2: 0 | AQJ2: 0 | AQK2: 0 | AQL2: 0 | AQM2: 0 | AQN2: 0 | AQP2: 0 | AQQ2: 0 | AQR2: 0 | AQS2: 0 | AQT2: 0 | AQU2: 0 | AQV2: 0 | AQW2: 0 | AQX2: 0 | AQY2: 0 | AQZ2: × | ARA2: 0 | ARB2: 0 | ARC2: 0 | ARD2: 0 | ARE2: 0 | ARF2: 0 | ARH2: 0 | ARI2: 0 | ARJ2: 0 | ARK2: 0 | ARL2: 0 | ARM2: 0 | ARN2: 0 | ARO2: 0 | ARP2: 0 | ARQ2: 0 | ARR2: × | ARS2: 0 | ART2: 0 | ARU2: 0 | ARV2: 0 | ARW2: 0 | ARX2: 0 | ARZ2: 0 | ASA2: 0 | ASB2: 0 | ASC2: 0 | ASD2: 0 | ASE2: 0 | ASF2: 0 | ASG2: 0 | ASH2: 0 | ASI2: 0 | ASJ2: × | ASK2: 0 | ASL2: 0 | ASM2: 0 | ASN2: 0 | ASO2: 0 | ASP2: 0 | ASR2: 0 | ASS2: 0 | AST2: 0 | ASU2: 0 | ASV2: 0 | ASW2: 0 | ASX2: 0 | ASY2: 0 | ASZ2: 0 | ATA2: 0 | ATB2: × | ATC2: 0 | ATD2: 0 | ATE2: 0 | ATF2: 0 | ATG2: 0 | ATH2: 0 | ATJ2: 0 | ATK2: 0 | ATL2: 0 | ATM2: 0 | ATN2: 0 | ATO2: 0 | ATP2: 0 | ATQ2: 0 | ATR2: 0 | ATS2: 0 | ATT2: × | ATU2: 0 | ATV2: 0 | ATW2: 0 | ATX2: 0 | ATY2: 0 | ATZ2: 0 | AUB2: 0 | AUC2: 0 | AUD2: 0 | AUE2: 0 | AUF2: 0 | AUG2: 0 | AUH2: 0 | AUI2: 0 | AUJ2: 0 | AUK2: 0 | AUL2: × | AUM2: 0 | AUN2: 0 | AUO2: 0 | AUP2: 0 | AUQ2: 0 | AUR2: 0 | AUT2: 0 | AUU2: 0 | AUV2: 0 | AUW2: 0 | AUX2: 0 | AUY2: 0 | AUZ2: 0 | AVA2: 0 | AVB2: 0 | AVC2: 0 | AVD2: × | AVE2: 23484000 | AVF2: 23484000 | AVG2: 0 | AVH2: 6000000 | AVI2: 0 | AVJ2: 23484000 | AVK2: 17484000 | AVL2: 17484000 | AVM2: 17484000 | AVN2: 1 | AVO2: 1 | AVP2: 1 | AVQ2: 0 | AVR2: 1 | AVS2: 0 | AVT2: 0 | AVU2: 0 | AVV2: 実施予定あり | AVW2: 実施予定あり | AVX2: 実施予定なし | AVY2: 実施予定なし | AVZ2: 実施予定なし | AWA2: 実施予定あり | AWB2: 実施予定なし | AWC2: 実施予定あり | AWD2: 実施予定あり | AWE2: 加算予定なし | AWF2: 28886000 | AWG2: 個別協議不要 | AWH2: 4819000 | AWI2: 8000000 | AWJ2: 0 | AWK2: 0 | AWL2: 0 | AWM2: 10266000 | AWN2: 0 | AWO2: 4529000 | AWP2: 1272000 | AWQ2: 0 | AWR2: ①標準額 | AWS2: 0 | AWT2: 非該当 | AWU2: 0 | AWV2: 0 | AWW2: 0 | AWX2: 0 | AWY2: 0 | AWZ2: 0 | AXA2: 0 | AXB2: 10963000 | AXC2: 28886000 | AXD2: 2890000 | AXE2: 2 | AXF2: 1 | AXG2: 2 | AXH2: 2 | AXI2: 2 | AXJ2: 3249000 | AXK2: 有 | AXL2: 日常生活圏域が１つ | AXM2: 無 | AXN2: 無 | AXO2: 3883000 | AXP2: 1 | AXQ2: 1 | AXR2: 0 | AXS2: 3 | AXT2: 941000 | AXU2: 有 | AXV2: 無 | AXW2: 0 | AXX2: 0 | AXY2: 0 | AXZ2: 0 | AYA2: 638000 | AYB2: 令和7年度よりｹｱﾌﾟﾗﾝ点検業務を国保連合会に委託する。厚生労働省が開発した点検ﾂｰﾙを使用し介護支援専門員が点検を行うことで、従来の町職員の点検と比較して専門性が向上する。 | AYC2: 町内全居宅事業所からｹｱﾌﾟﾗﾝの提出を求め点検を行い、うち２事業所で実地指導を行う。 委託事業は初年度であるが、点検したケアプランの5%程度で指摘事項があることを目標とする。 | AYD2: 0 | AYE2: 0 | AYF2: 0 | AYG2: 0 | AYH2: 0 | AYI2: 0 | AYJ2: 0 | AYK2: 0 | AYL2: 0 | AYM2: 0 | AYN2: 0 | AYO2: 0 | AYP2: 0 | AYQ2: 0 | AYR2: 0 | AYS2: 0 | AYT2: 0 | AYU2: 0 | AYV2: 0 | AYW2: 0 | AYX2: 0 | AYY2: 0 | AYZ2: 0 | AZA2: 0 | AZB2: 0 | AZC2: 0 | AZD2: 0 | AZE2: 1350000 | AZF2: 要介護3以上の認定を受け、民生委員若しくは担当ケアマネージャーが常時おむつの使用が必要と認めた高齢者（認定調査で排尿、排便でに介助、見守りがある）を介護する場合、その家族の負担軽減のため、紙おむつや清拭剤等の介護用品と引き換えることができる給付券を介護者に交付する。 【課税対象者及び新規申込者を交付金の対象者に含めない】 | AZG2: 給付券（月額3,500円）により介護者の経済的な負担軽減による在宅介護の継続を図る。施設介護ではなく在宅介護を継続するため、交付金対象外者を含めた利用者数は前年実績程度を維持したい。 | AZH2: 1231000 | AZI2: 成年後見制度の普及啓発を行うため、令和5年度に権利擁護センターを設置し、業務を社会福祉協議会に委託している。委託料を障害者分（一般会計）と高齢者（介護分）を対象者数で按分する。 | AZJ2: 令和6年度実績が１件で、令和7年度も昨年度からの継続事案が１件あるなど、事業委託の効果が表れており、更なる理解促進と権利擁護思想の普及を図る。広報啓発活動の充実により、要介護者分の申立て件数2件の実績を目標としたい | AZK2: 0 | AZL2: 0 | AZM2: 0 | AZN2: 0 | AZO2: 0 | AZP2: 0 | AZQ2: 0 | AZR2: 0 | AZS2: 0 | AZT2: 0 | AZU2: 0 | AZV2: 0 | AZW2: 0 | AZX2: 0 | AZY2: 0 | AZZ2: 0 | BAA2: 0 | BAB2: 0 | BAC2: 0 | BAD2: 0 | BAE2: 0 | BAF2: 0 | BAG2: 0 | BAH2: 0 | BAI2: 0 | BAJ2: 0 | BAK2: 0 | BAL2: 0 | BAM2: 3219000 | BAN2: 75226 | BAO2: 小野町 | BAP2: 有 | BAQ2: 2540000 | BAR2: 3290000 | BAS2: 3290000 | BAT2: 3220000 | BAU2: 2940000 | BAV2: 1239700 | BAW2: 1330198.1 | BAX2: 0 | BAY2: 0 | BAZ2: 0 | BBA2: 0 | BBB2: 86 | BBC2: 36 | BBD2: 50 | BBE2: 0 | BBF2: 0 | BBG2: 2550000 | BBH2: 1350000 | BBI2: 1200000 | BBJ2: 0 | BBK2: 0 | BBL2: 0 | BBM2: 0 | BBN2: 1 | BBO2: 7 | BBP2: 3 | BBQ2: 0 | BBR2: 14 | BBS2: 7 | BBT2: 4 | BBU2: 0 | BBV2: 0 | BBW2: 0 | BBX2: 0 | BBY2: 0 | BBZ2: 0 | BCA2: 0 | BCB2: 0 | BCC2: 0 | BCD2: 42000 | BCE2: 0 | BCF2: 519750 | BCG2: 縮小 | BCH2: 令和6年10月1日以降の新規申込者は、別事業（一般会計負担）に移行した。 | BCI2: 0 | BCJ2: 縮小 | BCK2: 新規申込者は別事業（一般会計負担）から支出する。 | BCL2: 0 | BCM2: 縮小 | BCN2: 新規申込者は別事業（一般会計負担）から支出し、令和9年度の全面移行に備える。 | BCO2: 0 | BCP2: 0 | BCQ2: 0 | BCR2: 0 | BCS2: 0 | BCT2: 0 | BCU2: 0 | BCV2: 0 | BCW2: 0 | BCX2: 0 | BCY2: 0 | BCZ2: 0 | BDA2: 0 | BDB2: 0 | BDC2: 0 | BDD2: 0 | BDE2: 0 | BDF2: 0 | BDG2: 0 | BDH2: 0 | BDI2: 0 | BDJ2: 0 | BDK2: 0 | BDL2: 0 | BDM2: 0 | BDN2: 0 | BDO2: 0 | BDP2: 0 | BDQ2: 0 | BDR2: 0 | BDS2: 0 | BDT2: 0 | BDU2: 0 | BDV2: 0 | BDW2: 0 | BDX2: 0 | BDY2: 0 | BDZ2: 0 | BEA2: 0 | BEB2: 0 | BEC2: 0 | BED2: 0 | BEE2: 0 | BEF2: 0 | BEG2: 0 | BEH2: 0 | BEI2: 0 | BEJ2: 0 | BEK2: 0 | BEL2: 0 | BEM2: 0 | BEN2: 0 | BEO2: 0 | BEP2: 0 | BEQ2: 0 | BER2: 0 | BES2: 0 | BET2: 0 | BEU2: 0 | BEV2: 0 | BEW2: 0 | BEX2: 0 | BEY2: 0 | BEZ2: 0 | BFA2: 0 | BFB2: 0 | BFC2: 0 | BFD2: 0 | BFE2: 0 | BFF2: 0 | BFG2: 金額が一致しません | BFH2: OK | BFI2: 金額が一致しません | BFJ2: 0 | BFK2: 0 | BFL2: 0 | BFM2: 0 | BFN2: 0 | BFO2: 0 | BFP2: 0 | BFQ2: 7小健第３７２２号 | BFR2: 46057 | BFS2: 小野町長 村上 昭正 | BFT2: 22728210 | BFU2: 10536800 | BFV2: 7970655 | BFW2: 4220755 | BFX2: 無 | BFY2: 36 | BFZ2: 無 | BGA2: 0 | BGB2: 令和８年３月５日東北厚発0305第21号 | BGC2: 7961800 | BGD2: 7970655 | BGE2: 4220755

Sheet R１実績
A1: 別紙様式第４様式１
A2: 令和元年度地域支援事業交付金精算書
A4: 区 分 | E4: 総事業費 | F4: 寄付金その他 の収入額 | G4: 差引額 | H4: 対象経費 実支出額 | I4: 基準額 | J4: 交付基本額 | K4: 交付金所要額 | L4: 交付金 交付決定額 | M4: 交付金 受入済額 | N4: 差引過不足額 Ｉ－Ｇ | P4: 備 考 | Q4: 事業を実施しているか
E5: Ａ | F5: B | G5: Ｃ（Ａ－Ｂ） | H5: D | I5: Ｅ | J5: Ｆ | K5: Ｇ | L5: Ｈ | M5: Ｉ | N5: 超過額 Ｊ | O5: 不足額 Ｋ
E6: 円 | F6: 円 | G6: 円 | H6: 円 | I6: 円 | J6: 円 | K6: 円 | L6: 円 | M6: 円 | N6: 円 | O6: 円 | Q6: 円
A7: １ 介護予防・日常生活支援総合事業 | E7: =E8+E15+E21+E26+E27+E28+E29 -> 25442100 | F7: =F8+F15+F21+F26+F27+F28+F29 -> 0 | G7: =G8+G15+G21+G26+G27+G28+G29 -> 25442100 | H7: =H8+H15+H21+H26+H27+H28+H29 -> 25442100 | I7: 26846000 | J7: =MIN(G7,H7,I7) -> 25442100 | K7: =ROUNDDOWN(J7*0.2,0) -> 5088420 | L7: 5369200 | M7: 5369200 | N7: =IF(M7-K7>0,M7-K7,0) -> 280780 | O7: =IF(M7-K7<0,M7-K7,0) -> 0 | Q7: =SUM(#REF!) -> #REF!
B8: （１） | C8: 訪問型サービス（第１号訪問事業） | E8: =SUM(E9:E14) -> 3924570 | F8: =SUM(F9:F14) -> 0 | G8: =E8-F8 -> 3924570 | H8: =SUM(H9:H14) -> 3924570 | Q8: =SUM(#REF!) -> #REF!
C9: ア | D9: 訪問介護相当サービス | E9: 2870070 | G9: =E9-F9 -> 2870070 | H9: 2870070 | Q9: =SUM(#REF!) -> #REF!
C10: イ | D10: 訪問型サービスＡ（緩和した基準によるサービス） | G10: =E10-F10 -> 0 | Q10: =SUM(#REF!) -> #REF!
C11: ウ | D11: 訪問型サービスＢ（住民主体による支援） | E11: 1054500 | G11: =E11-F11 -> 1054500 | H11: 1054500 | Q11: =SUM(#REF!) -> #REF!
C12: エ | D12: 訪問型サービスＣ（短期集中予防サービス） | G12: =E12-F12 -> 0
C13: オ | D13: 訪問型サービスＤ（移動支援） | G13: =E13-F13 -> 0
C14: カ | D14: その他 | G14: =E14-F14 -> 0
B15: （２） | C15: 通所型サービス（第１号通所事業） | E15: =SUM(E16:E20) -> 17528358 | F15: =SUM(F16:F20) -> 0 | G15: =E15-F15 -> 17528358 | H15: =SUM(H16:H20) -> 17528358 | Q15: =SUM(#REF!) -> #REF!
C16: ア | D16: 通所介護相当サービス | E16: 15657258 | G16: =E16-F16 -> 15657258 | H16: 15657258 | Q16: =SUM(#REF!) -> #REF!
C17: イ | D17: 通所型サービスＡ（緩和した基準によるサービス） | G17: =E17-F17 -> 0 | Q17: =SUM(#REF!) -> #REF!
C18: ウ | D18: 通所型サービスＢ（住民主体による支援） | E18: 1871100 | G18: =E18-F18 -> 1871100 | H18: 1871100 | Q18: =SUM(#REF!) -> #REF!
C19: エ | D19: 通所型サービスＣ（短期集中予防サービス） | G19: =E19-F19 -> 0 | Q19: =SUM(#REF!) -> #REF!
C20: オ | D20: その他 | G20: =E20-F20 -> 0 | Q20: =SUM(#REF!) -> #REF!
B21: （３） | C21: その他生活支援サービス（第１号生活支援事業） | E21: =SUM(E22:E25) -> 0 | F21: =SUM(F22:F25) -> 0 | G21: =E21-F21 -> 0 | H21: =SUM(H22:H25) -> 0 | Q21: =SUM(#REF!) -> #REF!
C22: ア | D22: 栄養改善を目的とした配食 | G22: =E22-F22 -> 0 | Q22: =SUM(#REF!) -> #REF!
C23: イ | D23: 定期的な安否確認及び緊急時の対応 | G23: =E23-F23 -> 0 | Q23: =SUM(#REF!) -> #REF!
C24: ウ | D24: 訪問型サービス・通所型サービスの一体的提供等 | G24: =E24-F24 -> 0 | Q24: =SUM(#REF!) -> #REF!
C25: エ | D25: その他 | G25: =E25-F25 -> 0 | Q25: =SUM(#REF!) -> #REF!
B26: （４） | C26: 介護予防ケアマネジメント（第１号介護予防支援事業） | E26: 2503120 | G26: =E26-F26 -> 2503120 | H26: 2503120 | Q26: =SUM(#REF!) -> #REF!
B27: （５）審査支払手数料 | E27: 73080 | G27: =E27-F27 -> 73080 | H27: 73080 | Q27: =COUNTIF(H27,">0") -> 1
B28: （６）高額介護予防サービス費相当事業等 | E28: 14001 | G28: =E28-F28 -> 14001 | H28: 14001
B29: （７） | C29: 一般介護予防事業 | E29: =SUM(E30:E34) -> 1398971 | F29: =SUM(F30:F34) -> 0 | G29: =E29-F29 -> 1398971 | H29: =SUM(H30:H34) -> 1398971 | Q29: =SUM(#REF!) -> #REF!
C30: ア | D30: 介護予防把握事業 | G30: =E30-F30 -> 0 | Q30: =SUM(#REF!) -> #REF!
C31: イ | D31: 介護予防普及啓発事業 | G31: =E31-F31 -> 0 | Q31: =SUM(#REF!) -> #REF!
C32: ウ | D32: 地域介護予防活動支援事業 | E32: 1398971 | G32: =E32-F32 -> 1398971 | H32: 1398971 | Q32: =SUM(#REF!) -> #REF!
C33: エ | D33: 一般介護予防事業評価事業 | G33: =E33-F33 -> 0 | Q33: =SUM(#REF!) -> #REF!
C34: オ | D34: 地域リハビリテーション活動支援事業 | G34: =E34-F34 -> 0 | Q34: =SUM(#REF!) -> #REF!
A35: ２ 包括的支援事業（地域包括支援センターの運営）及び任意事業 | E35: =E36+E37 -> 16898292 | F35: =SUM(F36:F37) -> 4023620 | G35: =E35-F35 -> 12874672 | H35: =H36+H37 -> 12874672 | I35: 22946479 | J35: =MIN(G35,H35,I35) -> 12874672 | K35: =ROUNDDOWN(J35*0.385,0) -> 4956748 | L35: 6179250 | M35: 6179250 | N35: =IF(M35-K35>0,M35-K35,0) -> 1222502 | O35: =IF(M35-K35<0,M35-K35,0) -> 0 | Q35: =SUM(#REF!) -> #REF!
B36: （１）包括的支援事業（地域包括支援センターの運営） | E36: 13634653 | F36: 4023620 | G36: =E36-F36 -> 9611033 | H36: 9611033 | Q36: =SUM(#REF!) -> #REF!
B37: （２）任意事業 | E37: =SUM(E38:E40) -> 3263639 | F37: =SUM(F38:F40) -> 0 | G37: =E37-F37 -> 3263639 | H37: =SUM(H38:H40) -> 3263639 | Q37: =SUM(#REF!) -> #REF!
C38: ア 介護給付等費用適正化事業 | G38: =E38-F38 -> 0 | Q38: =SUM(#REF!) -> #REF!
C39: イ 家族介護支援事業 | E39: 3263639 | G39: =E39-F39 -> 3263639 | H39: 3263639 | Q39: =SUM(#REF!) -> #REF!
C40: ウ その他の事業 | E40: =SUM(E41:E46) -> 0 | F40: =SUM(F41:F46) -> 0 | G40: =E40-F40 -> 0 | H40: =SUM(H41:H46) -> 0 | Q40: =SUM(#REF!) -> #REF!
D41: （ア）成年後見制度利用支援事業 | G41: =E41-F41 -> 0 | Q41: =SUM(#REF!) -> #REF!
D42: （イ）福祉用具・住宅改修支援事業 | G42: =E42-F42 -> 0 | Q42: =SUM(#REF!) -> #REF!
D43: （ウ）認知症対応型共同生活介護事業所の家賃等助成事業 | G43: =E43-F43 -> 0 | Q43: =SUM(#REF!) -> #REF!
D44: （エ）認知症サポーター等養成事業 | G44: =E44-F44 -> 0 | Q44: =SUM(#REF!) -> #REF!
D45: （オ）重度のＡＬＳ患者の入院におけるコミュニケーション支援事業 | G45: =E45-F45 -> 0 | Q45: =SUM(#REF!) -> #REF!
D46: （カ）地域自立生活支援事業 | G46: =E46-F46 -> 0 | Q46: =SUM(#REF!) -> #REF!
A47: ３ 小 計（１＋２） | E47: =E7+E35 -> 42340392 | F47: =F7+F35 -> 4023620 | G47: =E47-F47 -> 38316772 | H47: =H7+H35 -> 38316772 | J47: =J7+J35 -> 38316772 | K47: =K7+K35 -> 10045168 | L47: =L7+L35 -> 11548450 | M47: =M7+M35 -> 11548450 | Q47: =SUM(#REF!) -> #REF!
A48: ４ 包括的支援事業（社会保障充実分） | E48: =SUM(E49:E53) -> 7058103 | F48: =SUM(F49:F53) -> 0 | G48: =E48-F48 -> 7058103 | H48: =SUM(H49:H53) -> 7058103 | I48: 35659000 | J48: =MIN(G48,H48,I48) -> 7058103 | K48: =ROUNDDOWN(J48*0.385,0) -> 2717369 | L48: 3619000 | M48: 3619000 | N48: =IF(M48-K48>0,M48-K48,0) -> 901631 | O48: =IF(M48-K48<0,M48-K48,0) -> 0 | Q48: =SUM(#REF!) -> #REF!
B49: （１）在宅医療・介護連携推進事業 | E49: 1066224 | G49: =E49-F49 -> 1066224 | H49: 1066224 | Q49: =SUM(#REF!) -> #REF!
B50: （２）生活支援体制整備事業 | E50: 2132448 | G50: =E50-F50 -> 2132448 | H50: 2132448 | Q50: =SUM(#REF!) -> #REF!
B51: （３）認知症初期集中支援推進事業 | E51: 3363862 | G51: =E51-F51 -> 3363862 | H51: 3363862
B52: （４）認知症地域支援・ケア向上事業 | G52: =E52-F52 -> 0 | Q52: =SUM(#REF!) -> #REF!
B53: （５）地域ケア会議推進事業 | E53: 495569 | G53: =E53-F53 -> 495569 | H53: 495569 | Q53: =SUM(#REF!) -> #REF!
A54: ５ 合 計（３＋４） | E54: =E47+E48 -> 49398495 | F54: =F47+F48 -> 4023620 | G54: =G47+G48 -> 45374875 | H54: =H47+H48 -> 45374875 | J54: =J47+J48 -> 45374875 | K54: =K47+K48 -> 12762537 | L54: =L47+L48 -> 15167450 | M54: =M47+M48 -> 15167450 | N54: =IF(M54-K54>0,M54-K54,0) -> 2404913 | O54: =IF(M54-K54<0,M54-K54,0) -> 0 | Q54: =SUM(#REF!) -> #REF!
A56: （注） | C56: １ Ａ欄のうち、地域包括支援センターの運営については、交付要綱４にいう総事業費（指定介護予防支援等の業務にかかる経費を含む。また、指定介護予防支援等の業務を | K56: 個別協議の有無
C57: 指定居宅介護支援事業所へ委託を行っている場合における委託費を含む。）を記入すること。 | K57: ①総合事業の個別協議の有無
C58: ２ Ｂ欄には、交付要綱４にいう寄付金その他の収入額（地域包括支援センターの運営については、指定介護予防支援等にかかる収入額）を記入すること。 | K58: ○
C59: ３ Ｄ欄のうち、地域包括支援センターの運営については、指定介護予防支援等の業務にかかる経費（指定介護予防支援等の業務を指定居宅介護支援事業所へ委託を行って | K59: ②包括的支援事業（地域包括支援センターの運営）の個別協議の有無
C60: いる場合における委託費を含む。）を含む地域包括支援センターの総経費から、指定介護予防支援等にかかる収入額を控除した後の経費における対象経費の実支出（予定） | K60: ×
C61: 額を記入すること。 | K61: ③包括的支援事業（社会保障充実分）の個別協議の有無 | O61: 保 険 者 名 | P61: 小野町
C62: ４ Ｅ欄には、交付要綱４に定める基準額を記入すること。 | K62: × | O62: 都道府県ｺｰﾄﾞ | P62: 7
C63: ５ Ｆ欄には、Ｃ欄、Ｄ欄及びＥ欄を比較して最も少ない額を記入すること。 | O63: 市区町村ｺｰﾄﾞ | P63: 522
C64: ６ Ｇ欄には、Ｆ欄の額に交付要綱４の第４欄に定める交付率を乗じて得た額（１円未満の端数が生じた場合には、これを切り捨てること。）を記入すること。 | K64: 総合事業調整交付金 | O64: Ｃ・Ｄ | P64: 6
K65: ④調整基準標準事業費額
K66: 24851044
K67: ⑤総合事業調整交付金所要額
K68: 2154000

Sheet R２実績
A1: 別紙様式第４様式１
A2: 令和２年度地域支援事業交付金精算書
A4: 区 分 | E4: 総事業費 | F4: 寄付金その他 の収入額 | G4: 差引額 | H4: 対象経費 実支出額 | I4: 基準額 | J4: 交付基本額 | K4: 交付金所要額 | L4: 交付金 交付決定額 | M4: 交付金 受入済額 | N4: 差引過不足額 Ｉ－Ｇ | P4: 備 考 | Q4: 事業を実施しているか
E5: Ａ | F5: B | G5: Ｃ（Ａ－Ｂ） | H5: D | I5: Ｅ | J5: Ｆ | K5: Ｇ | L5: Ｈ | M5: Ｉ | N5: 超過額 Ｊ | O5: 不足額 Ｋ
E6: 円 | F6: 円 | G6: 円 | H6: 円 | I6: 円 | J6: 円 | K6: 円 | L6: 円 | M6: 円 | N6: 円 | O6: 円 | Q6: 円
A7: １ 介護予防・日常生活支援総合事業 | E7: 26788952 | F7: 0 | G7: 26788952 | H7: 26788952 | I7: 26788952 | J7: 26788952 | K7: 5357790 | L7: 5607600 | M7: 5607600 | N7: 249810 | O7: 0 | Q7: =SUM(#REF!) -> #REF!
B8: （１） | C8: 訪問型サービス（第１号訪問事業） | E8: 4313145 | F8: 0 | G8: 4313145 | H8: 4313145 | Q8: =SUM(#REF!) -> #REF!
C9: ア | D9: 訪問介護相当サービス | E9: 2736645 | G9: 2736645 | H9: 2736645 | Q9: =SUM(#REF!) -> #REF!
C10: イ | D10: 訪問型サービスＡ（緩和した基準によるサービス） | G10: 0 | Q10: =SUM(#REF!) -> #REF!
C11: ウ | D11: 訪問型サービスＢ（住民主体による支援） | E11: 1576500 | G11: 1576500 | H11: 1576500 | Q11: =SUM(#REF!) -> #REF!
C12: エ | D12: 訪問型サービスＣ（短期集中予防サービス） | G12: 0
C13: オ | D13: 訪問型サービスＤ（移動支援） | G13: 0
C14: カ | D14: その他 | G14: 0
B15: （２） | C15: 通所型サービス（第１号通所事業） | E15: 18622360 | F15: 0 | G15: 18622360 | H15: 18622360 | Q15: =SUM(#REF!) -> #REF!
C16: ア | D16: 通所介護相当サービス | E16: 17099560 | G16: 17099560 | H16: 17099560 | Q16: =SUM(#REF!) -> #REF!
C17: イ | D17: 通所型サービスＡ（緩和した基準によるサービス） | G17: 0 | Q17: =SUM(#REF!) -> #REF!
C18: ウ | D18: 通所型サービスＢ（住民主体による支援） | E18: 1522800 | G18: 1522800 | H18: 1522800 | Q18: =SUM(#REF!) -> #REF!
C19: エ | D19: 通所型サービスＣ（短期集中予防サービス） | G19: 0 | Q19: =SUM(#REF!) -> #REF!
C20: オ | D20: その他 | G20: 0 | Q20: =SUM(#REF!) -> #REF!
B21: （３） | C21: その他生活支援サービス（第１号生活支援事業） | E21: 0 | F21: 0 | G21: 0 | H21: 0 | Q21: =SUM(#REF!) -> #REF!
C22: ア | D22: 栄養改善を目的とした配食 | G22: 0 | Q22: =SUM(#REF!) -> #REF!
C23: イ | D23: 定期的な安否確認及び緊急時の対応 | G23: 0 | Q23: =SUM(#REF!) -> #REF!
C24: ウ | D24: 訪問型サービス・通所型サービスの一体的提供等 | G24: 0 | Q24: =SUM(#REF!) -> #REF!
C25: エ | D25: その他 | G25: 0 | Q25: =SUM(#REF!) -> #REF!
B26: （４） | C26: 介護予防ケアマネジメント（第１号介護予防支援事業） | E26: 2401640 | G26: 2401640 | H26: 2401640 | Q26: =SUM(#REF!) -> #REF!
B27: （５）審査支払手数料 | E27: 72500 | G27: 72500 | H27: 72500 | Q27: =COUNTIF(H27,">0") -> 1
B28: （６）高額介護予防サービス費相当事業等 | E28: 5326 | G28: 5326 | H28: 5326
B29: （７） | C29: 一般介護予防事業 | E29: 1373981 | F29: 0 | G29: 1373981 | H29: 1373981 | Q29: =SUM(#REF!) -> #REF!
C30: ア | D30: 介護予防把握事業 | G30: 0 | Q30: =SUM(#REF!) -> #REF!
C31: イ | D31: 介護予防普及啓発事業 | G31: 0 | Q31: =SUM(#REF!) -> #REF!
C32: ウ | D32: 地域介護予防活動支援事業 | E32: 1373981 | G32: 1373981 | H32: 1373981 | Q32: =SUM(#REF!) -> #REF!
C33: エ | D33: 一般介護予防事業評価事業 | G33: 0 | Q33: =SUM(#REF!) -> #REF!
C34: オ | D34: 地域リハビリテーション活動支援事業 | G34: 0 | Q34: =SUM(#REF!) -> #REF!
A35: ２ 包括的支援事業（地域包括支援センターの運営）及び任意事業 | E35: 23311883 | F35: 4844770 | G35: 18467113 | H35: 13622343 | I35: 23139229 | J35: 13622343 | K35: 5244602 | L35: 8389150 | M35: 8389150 | N35: 3144548 | O35: 0 | Q35: =SUM(#REF!) -> #REF!
B36: （１）包括的支援事業（地域包括支援センターの運営） | E36: 20022503 | F36: 4844770 | G36: 15177733 | H36: 10332963 | Q36: =SUM(#REF!) -> #REF!
B37: （２）任意事業 | E37: 3289380 | F37: 0 | G37: 3289380 | H37: 3289380 | Q37: =SUM(#REF!) -> #REF!
C38: ア 介護給付等費用適正化事業 | G38: 0 | Q38: =SUM(#REF!) -> #REF!
C39: イ 家族介護支援事業 | E39: 3289380 | G39: 3289380 | H39: 3289380 | Q39: =SUM(#REF!) -> #REF!
C40: ウ その他の事業 | E40: 0 | F40: 0 | G40: 0 | H40: 0 | Q40: =SUM(#REF!) -> #REF!
D41: （ア）成年後見制度利用支援事業 | G41: 0 | Q41: =SUM(#REF!) -> #REF!
D42: （イ）福祉用具・住宅改修支援事業 | G42: 0 | Q42: =SUM(#REF!) -> #REF!
D43: （ウ）認知症対応型共同生活介護事業所の家賃等助成事業 | G43: 0 | Q43: =SUM(#REF!) -> #REF!
D44: （エ）認知症サポーター等養成事業 | G44: 0 | Q44: =SUM(#REF!) -> #REF!
D45: （オ）重度のＡＬＳ患者の入院におけるコミュニケーション支援事業 | G45: 0 | Q45: =SUM(#REF!) -> #REF!
D46: （カ）地域自立生活支援事業 | G46: 0 | Q46: =SUM(#REF!) -> #REF!
A47: ３ 小 計（１＋２） | E47: 50100835 | F47: 4844770 | G47: 45256065 | H47: 40411295 | J47: 40411295 | K47: 10602392 | L47: 13996750 | M47: 13996750 | Q47: =SUM(#REF!) -> #REF!
A48: ４ 包括的支援事業（社会保障充実分） | E48: 2587904 | F48: 0 | G48: 2587904 | H48: 2587904 | I48: 40188000 | J48: 2587904 | K48: 996343 | L48: 1627010 | M48: 1627010 | N48: 630667 | O48: 0 | Q48: =SUM(#REF!) -> #REF!
B49: （１）在宅医療・介護連携推進事業 | E49: 431068 | G49: 431068 | H49: 431068 | Q49: =SUM(#REF!) -> #REF!
B50: （２）生活支援体制整備事業 | E50: 798828 | F50: 0 | G50: 798828 | H50: 798828 | Q50: =SUM(#REF!) -> #REF!
C51: ア 生活支援コーディネーター・協議体 | E51: 798828 | G51: 798828 | H51: 798828
C52: イ 就労的活動支援コーディネーター | G52: 0
B53: （３）認知症初期集中支援推進事業 | E53: 287579 | G53: 287579 | H53: 287579
B54: （４）認知症地域支援・ケア向上事業 | E54: 671015 | G54: 671015 | H54: 671015 | Q54: =SUM(#REF!) -> #REF!
B55: （５）認知症サポーター活動促進・地域づくり推進事業 | G55: 0
B56: （６）地域ケア会議推進事業 | E56: 399414 | G56: 399414 | H56: 399414 | Q56: =SUM(#REF!) -> #REF!
A57: ５ 合 計（３＋４） | E57: 52688739 | F57: 4844770 | G57: 47843969 | H57: 42999199 | J57: 42999199 | K57: 11598735 | L57: 15623760 | M57: 15623760 | N57: 4025025 | O57: 0 | Q57: =SUM(#REF!) -> #REF!
A59: （注） | C59: １ Ａ欄のうち、地域包括支援センターの運営については、交付要綱４にいう総事業費（指定介護予防支援等の業務にかかる経費を含む。 | J59: 上限設定の選択 | L59: 個別協議の有無
C60: また、指定介護予防支援等の業務を指定居宅介護支援事業所へ委託を行っている場合における委託費を含む。）を記入すること。 | J60: ① 総合事業 | L60: ① 総合事業
C61: ２ Ｂ欄には、交付要綱４にいう寄付金その他の収入額（地域包括支援センターの運営については、指定介護予防支援等にかかる収入額）を記入すること。 | J61: ⑤個別協議 | L61: ○
C62: ３ Ｄ欄のうち、地域包括支援センターの運営については、指定介護予防支援等の業務にかかる経費（指定介護予防支援等の業務を指定居宅介護支援事業所 | J62: ② 包括的支援事業（地域包括支援センターの運営）・任意事業 | L62: ② 包括的支援事業（地域包括支援センターの運営）
C63: へ委託を行っている場合における委託費を含む。）を含む地域包括支援センターの総経費から、指定介護予防支援等にかかる収入額を控除した後の経費における | J63: ①原則の上限式 | L63: ×
C64: 対象経費の実支出（予定）額を記入すること。 | J64: ③ 包括的支援事業（社会保障充実分） | L64: ③ 包括的支援事業（社会保障充実分） | O64: 保 険 者 名 | P64: 小野町
C65: ４ Ｅ欄には、交付要綱４に定める基準額を記入すること。 | J65: ①標準額 | L65: × | O65: 都道府県ｺｰﾄﾞ | P65: 7
C66: ５ Ｆ欄には、Ｃ欄、Ｄ欄及びＥ欄を比較して最も少ない額を記入すること。 | O66: 市区町村ｺｰﾄﾞ | P66: 522
C67: ６ Ｇ欄には、Ｆ欄の額に交付要綱４の第４欄に定める交付率を乗じて得た額（１円未満の端数が生じた場合には、これを切り捨てること。）を記入すること。 | L67: 総合事業調整交付金 | O67: Ｃ・Ｄ | P67: 6
L68: ④ 調整基準標準事業費額
L69: 25555269 | M69: 円
L70: ⑤ 総合事業調整交付金所要額
L71: 2085000 | M71: 円

Sheet R３実績
B1: 別紙様式第４様式１
B3: 令和３年度地域支援事業交付金精算書
B5: 区 分 | F5: 総事業費 | G5: 寄付金その他 の収入額 | H5: 差引額 | I5: 対象経費 実支出額 | J5: 基準額 | K5: 交付基本額 | L5: 交付金所要額 | M5: 交付金 交付決定額 | N5: 交付金 受入済額 | O5: 差引過不足額 Ｉ－Ｇ | Q5: 備 考
F6: Ａ | G6: B | H6: Ｃ（Ａ－Ｂ） | I6: D | J6: Ｅ | K6: Ｆ | L6: Ｇ | M6: Ｈ | N6: Ｉ | O6: 超過額 Ｊ | P6: 不足額 Ｋ
F7: 円 | G7: 円 | H7: 円 | I7: 円 | J7: 円 | K7: 円 | L7: 円 | M7: 円 | N7: 円 | O7: 円 | P7: 円
B8: １ 介護予防・日常生活支援総合事業 | F8: 32312660 | G8: 0 | H8: 32312660 | I8: 32312660 | J8: 32312660 | K8: 32312660 | L8: 6462532 | M8: 5737800 | N8: 5737800 | O8: 0 | P8: -724732
C9: （１） | D9: 訪問型サービス（第１号訪問事業） | F9: 4917222 | G9: 0 | H9: 4917222 | I9: 4917222
D10: ア | E10: 訪問介護相当サービス | F10: 3315222 | G10: 0 | H10: 3315222 | I10: 3315222
D11: イ | E11: 訪問型サービスＡ（緩和した基準によるサービス） | F11: 0 | G11: 0 | H11: 0 | I11: 0
D12: ウ | E12: 訪問型サービスＢ（住民主体による支援） | F12: 1602000 | G12: 0 | H12: 1602000 | I12: 1602000
D13: エ | E13: 訪問型サービスＣ（短期集中予防サービス） | F13: 0 | G13: 0 | H13: 0 | I13: 0
D14: オ | E14: 訪問型サービスＤ（移動支援） | F14: 0 | G14: 0 | H14: 0 | I14: 0
D15: カ | E15: その他 | F15: 0 | G15: 0 | H15: 0 | I15: 0
C16: （２） | D16: 通所型サービス（第１号通所事業） | F16: 23267684 | G16: 0 | H16: 23267684 | I16: 23267684
D17: ア | E17: 通所介護相当サービス | F17: 21847484 | G17: 0 | H17: 21847484 | I17: 21847484
D18: イ | E18: 通所型サービスＡ（緩和した基準によるサービス） | F18: 0 | G18: 0 | H18: 0 | I18: 0
D19: ウ | E19: 通所型サービスＢ（住民主体による支援） | F19: 1420200 | G19: 0 | H19: 1420200 | I19: 1420200
D20: エ | E20: 通所型サービスＣ（短期集中予防サービス） | F20: 0 | G20: 0 | H20: 0 | I20: 0
D21: オ | E21: その他 | F21: 0 | G21: 0 | H21: 0 | I21: 0
C22: （３） | D22: その他生活支援サービス（第１号生活支援事業） | F22: 0 | G22: 0 | H22: 0 | I22: 0
D23: ア | E23: 栄養改善を目的とした配食 | F23: 0 | G23: 0 | H23: 0 | I23: 0
D24: イ | E24: 定期的な安否確認及び緊急時の対応 | F24: 0 | G24: 0 | H24: 0 | I24: 0
D25: ウ | E25: 訪問型サービス・通所型サービスの一体的提供等 | F25: 0 | G25: 0 | H25: 0 | I25: 0
D26: エ | E26: その他 | F26: 0 | G26: 0 | H26: 0 | I26: 0
C27: （４） | D27: 介護予防ケアマネジメント（第１号介護予防支援事業） | F27: 2827450 | G27: 0 | H27: 2827450 | I27: 2827450
C28: （５）審査支払手数料 | F28: 93933 | G28: 0 | H28: 93933 | I28: 93933
C29: （６）高額介護予防サービス費相当事業等 | F29: 617 | G29: 0 | H29: 617 | I29: 617
C30: （７） | D30: 一般介護予防事業 | F30: 1205754 | G30: 0 | H30: 1205754 | I30: 1205754
D31: ア | E31: 介護予防把握事業 | F31: 0 | G31: 0 | H31: 0 | I31: 0
D32: イ | E32: 介護予防普及啓発事業 | F32: 0 | G32: 0 | H32: 0 | I32: 0
D33: ウ | E33: 地域介護予防活動支援事業 | F33: 1205754 | G33: 0 | H33: 1205754 | I33: 1205754
D34: エ | E34: 一般介護予防事業評価事業 | F34: 0 | G34: 0 | H34: 0 | I34: 0
D35: オ | E35: 地域リハビリテーション活動支援事業 | F35: 0 | G35: 0 | H35: 0 | I35: 0
B36: ２ 包括的支援事業（地域包括支援センターの運営）及び任意事業 | F36: 26212935 | G36: 5366120 | H36: 20846815 | I36: 20846815 | J36: 23345168 | K36: 20846815 | L36: 8026023 | M36: 8752975 | N36: 8752975 | O36: 726952 | P36: 0
C37: （１）包括的支援事業（地域包括支援センターの運営） | F37: 22953323 | G37: 5366120 | H37: 17587203 | I37: 17587203
C38: （２）任意事業 | F38: 3259612 | G38: 0 | H38: 3259612 | I38: 3259612
D39: ア 介護給付等費用適正化事業 | F39: 0 | G39: 0 | H39: 0 | I39: 0
D40: イ 家族介護支援事業 | F40: 3259612 | G40: 0 | H40: 3259612 | I40: 3259612
D41: ウ その他の事業 | F41: 0 | G41: 0 | H41: 0 | I41: 0
E42: （ア）成年後見制度利用支援事業 | F42: 0 | G42: 0 | H42: 0 | I42: 0
E43: （イ）福祉用具・住宅改修支援事業 | F43: 0 | G43: 0 | H43: 0 | I43: 0
E44: （ウ）認知症対応型共同生活介護事業所の家賃等助成事業 | F44: 0 | G44: 0 | H44: 0 | I44: 0
E45: （エ）認知症サポーター等養成事業 | F45: 0 | G45: 0 | H45: 0 | I45: 0
E46: （オ）重度のＡＬＳ患者の入院におけるコミュニケーション支援事業 | F46: 0 | G46: 0 | H46: 0 | I46: 0
E47: （カ）地域自立生活支援事業 | F47: 0 | G47: 0 | H47: 0 | I47: 0
B48: ３ 小 計（１＋２） | F48: 58525595 | G48: 5366120 | H48: 53159475 | I48: 53159475 | K48: 53159475 | L48: 14488555 | M48: 14490775 | N48: 14490775
B49: ４ 包括的支援事業（社会保障充実分） | F49: 2463748 | G49: 0 | H49: 2463748 | I49: 2463748 | J49: 40188000 | K49: 2463748 | L49: 948542 | M49: 1439515 | N49: 1439515 | O49: 490973 | P49: 0
C50: （１）在宅医療・介護連携推進事業 | F50: 856960 | G50: 0 | H50: 856960 | I50: 856960
C51: （２）生活支援体制整備事業 | F51: 576061 | G51: 0 | H51: 576061 | I51: 576061
D52: ア 生活支援コーディネーター・協議体 | F52: 576061 | G52: 0 | H52: 576061 | I52: 576061
D53: イ 就労的活動支援コーディネーター | F53: 0 | G53: 0 | H53: 0 | I53: 0
C54: （３）認知症初期集中支援推進事業 | F54: 0 | G54: 0 | H54: 0 | I54: 0
C55: （４）認知症地域支援・ケア向上事業 | F55: 0 | G55: 0 | H55: 0 | I55: 0
C56: （５）認知症サポーター活動促進・地域づくり推進事業 | F56: 659002 | G56: 0 | H56: 659002 | I56: 659002
C57: （６）地域ケア会議推進事業 | F57: 371725 | G57: 0 | H57: 371725 | I57: 371725
B58: ５ 合 計（３＋４） | F58: 60989343 | G58: 5366120 | H58: 55623223 | I58: 55623223 | K58: 55623223 | L58: 15437097 | M58: 15930290 | N58: 15930290 | O58: 493193 | P58: 0
B60: （注） | D60: １ Ａ欄のうち、地域包括支援センターの運営については、交付要綱４にいう総事業費（指定介護予防支援等の業務にかかる経費を含む。 | K60: 上限設定の選択 | M60: 個別協議の有無 | P60: 保 険 者 名 | Q60: =[1]初期設定!B8 -> 小野町
D61: また、指定介護予防支援等の業務を指定居宅介護支援事業所へ委託を行っている場合における委託費を含む。）を記入すること。 | K61: ① 総合事業 | M61: ① 総合事業 | P61: 都道府県ｺｰﾄﾞ | Q61: =[1]初期設定!B12 -> 07
D62: ２ Ｂ欄には、交付要綱４にいう寄付金その他の収入額（地域包括支援センターの運営については、指定介護予防支援等にかかる収入額）を記入すること。 | K62: =[1]初期設定!B37 -> ⑤個別協議 | M62: =IF(COUNTIF([1]初期設定!B37,"*個別*")>0,"○","×") -> #VALUE! | P62: 市区町村ｺｰﾄﾞ | Q62: =[1]初期設定!B11 -> 522
D63: ３ Ｄ欄のうち、地域包括支援センターの運営については、指定介護予防支援等の業務にかかる経費（指定介護予防支援等の業務を指定居宅介護支援 | K63: ② 包括的支援事業（地域包括支援センターの運営）・任意事業 | M63: ② 包括的支援事業（社会保障充実分） | P63: Ｃ・Ｄ | Q63: =[1]初期設定!B13 -> 6
D64: 事業所へ委託を行っている場合における委託費を含む。）を含む地域包括支援センターの総経費から、指定介護予防支援等にかかる収入額を | K64: =[1]初期設定!B53 -> ①原則の上限額 | M64: =IF(COUNTIF([1]初期設定!B59,"*個別*")>0,"○","×") -> #VALUE!
D65: 控除した後の経費における対象経費の実支出（予定）額を記入すること。 | K65: ③ 包括的支援事業（社会保障充実分） | P65: 重層的支援体制整備事業に要する費用相当額
D66: ４ Ｅ欄には、交付要綱４に定める基準額を記入すること。 | K66: =[1]初期設定!B59 -> ①標準額 | P66: 総額（①＋②＋③）
D67: ５ Ｆ欄には、Ｃ欄、Ｄ欄及びＥ欄を比較して最も少ない額から、重層的支援体制整備事業に要する費用相当額を控除した額を記入すること。 | P67: =SUM(P69,P71,P73) -> 0 | Q67: 円
D68: ６ Ｇ欄には、Ｆ欄の額に交付要綱４の第４欄に定める交付率を乗じて得た額（１円未満の端数が生じた場合には、これを切り捨てること。）を記入すること。 | M68: 総合事業調整交付金 | P68: ① 地域介護予防活動支援事業費相当額
D69: ７ H欄及びI欄には、重層的支援体制整備事業に要する費用相当額を含めない。 | M69: ④ 調整基準標準事業費額 | P69: =[1]初期設定!B46 -> 0 | Q69: 円
M70: =[1]初期設定!B40 -> 21897654 | N70: 円 | P70: ② 地域包括支援センターの運営費相当額
M71: ⑤ 総合事業調整交付金所要額 | P71: =[1]初期設定!B47 -> 0 | Q71: 円
M72: =[1]初期設定!B41 -> 2650000 | N72: 円 | P72: ③ 生活支援体制整備事業費相当額
P73: =SUM(P75,P77) -> 0 | Q73: 円
P74: ア 生活支援コーディネーター・協議体
M75: 重層的支援体制整備事業の実施有無 | P75: =[1]初期設定!B49 -> 0 | Q75: 円
M76: =[1]初期設定!B45 -> ②未実施 | P76: イ 就労的活動支援コーディネーター
P77: =[1]初期設定!B50 -> 0 | Q77: 円

Sheet R４実績
B1: 別紙様式第４様式１
B3: 令和４年度地域支援事業交付金精算書
B5: 区 分 | F5: 総事業費 | G5: 寄付金その他 の収入額 | H5: 差引額 | I5: 対象経費 実支出額 | J5: 基準額 | K5: 交付基本額 | L5: 交付金所要額 | M5: 交付金 交付決定額 | N5: 交付金 受入済額 | O5: 差引過不足額 Ｉ－Ｇ | Q5: 備 考
F6: Ａ | G6: B | H6: Ｃ（Ａ－Ｂ） | I6: D | J6: Ｅ | K6: Ｆ | L6: Ｇ | M6: Ｈ | N6: Ｉ | O6: 超過額 Ｊ | P6: 不足額 Ｋ
F7: 円 | G7: 円 | H7: 円 | I7: 円 | J7: 円 | K7: 円 | L7: 円 | M7: 円 | N7: 円 | O7: 円 | P7: 円
B8: １ 介護予防・日常生活支援総合事業 | F8: 32537465 | G8: 0 | H8: 32537465 | I8: 32537465 | J8: 32537465 | K8: 32537465 | L8: 6507493 | M8: 7737000 | N8: 7737000 | O8: 1229507 | P8: 0
C9: （１） | D9: 訪問型サービス（第１号訪問事業） | F9: 6259143 | G9: 0 | H9: 6259143 | I9: 6259143
D10: ア | E10: 訪問介護相当サービス | F10: 4647393 | G10: 0 | H10: 4647393 | I10: 4647393
D11: イ | E11: 訪問型サービスＡ（緩和した基準によるサービス） | F11: 0 | G11: 0 | H11: 0 | I11: 0
D12: ウ | E12: 訪問型サービスＢ（住民主体による支援） | F12: 1611750 | G12: 0 | H12: 1611750 | I12: 1611750
D13: エ | E13: 訪問型サービスＣ（短期集中予防サービス） | F13: 0 | G13: 0 | H13: 0 | I13: 0
D14: オ | E14: 訪問型サービスＤ（移動支援） | F14: 0 | G14: 0 | H14: 0 | I14: 0
D15: カ | E15: その他 | F15: 0 | G15: 0 | H15: 0 | I15: 0
C16: （２） | D16: 通所型サービス（第１号通所事業） | F16: 22522622 | G16: 0 | H16: 22522622 | I16: 22522622
D17: ア | E17: 通所介護相当サービス | F17: 20578622 | G17: 0 | H17: 20578622 | I17: 20578622
D18: イ | E18: 通所型サービスＡ（緩和した基準によるサービス） | F18: 0 | G18: 0 | H18: 0 | I18: 0
D19: ウ | E19: 通所型サービスＢ（住民主体による支援） | F19: 1944000 | G19: 0 | H19: 1944000 | I19: 1944000
D20: エ | E20: 通所型サービスＣ（短期集中予防サービス） | F20: 0 | G20: 0 | H20: 0 | I20: 0
D21: オ | E21: その他 | F21: 0 | G21: 0 | H21: 0 | I21: 0
C22: （３） | D22: その他生活支援サービス（第１号生活支援事業） | F22: 0 | G22: 0 | H22: 0 | I22: 0
D23: ア | E23: 栄養改善を目的とした配食 | F23: 0 | G23: 0 | H23: 0 | I23: 0
D24: イ | E24: 定期的な安否確認及び緊急時の対応 | F24: 0 | G24: 0 | H24: 0 | I24: 0
D25: ウ | E25: 訪問型サービス・通所型サービスの一体的提供等 | F25: 0 | G25: 0 | H25: 0 | I25: 0
D26: エ | E26: その他 | F26: 0 | G26: 0 | H26: 0 | I26: 0
C27: （４） | D27: 介護予防ケアマネジメント（第１号介護予防支援事業） | F27: 2639820 | G27: 0 | H27: 2639820 | I27: 2639820
C28: （５）審査支払手数料 | F28: 91980 | G28: 0 | H28: 91980 | I28: 91980
C29: （６）高額介護予防サービス費相当事業等 | F29: 2540 | G29: 0 | H29: 2540 | I29: 2540
C30: （７） | D30: 一般介護予防事業 | F30: 1021360 | G30: 0 | H30: 1021360 | I30: 1021360
D31: ア | E31: 介護予防把握事業 | F31: 0 | G31: 0 | H31: 0 | I31: 0
D32: イ | E32: 介護予防普及啓発事業 | F32: 0 | G32: 0 | H32: 0 | I32: 0
D33: ウ | E33: 地域介護予防活動支援事業 | F33: 1021360 | G33: 0 | H33: 1021360 | I33: 1021360
D34: エ | E34: 一般介護予防事業評価事業 | F34: 0 | G34: 0 | H34: 0 | I34: 0
D35: オ | E35: 地域リハビリテーション活動支援事業 | F35: 0 | G35: 0 | H35: 0 | I35: 0
B36: ２ 包括的支援事業（地域包括支援センターの運営）及び任意事業 | F36: 27822673 | G36: 5676840 | H36: 22145833 | I36: 21921293 | J36: 23641651 | K36: 21921293 | L36: 8439697 | M36: 9095625 | N36: 9095625 | O36: 655928 | P36: 0
C37: （１）包括的支援事業（地域包括支援センターの運営） | F37: 24735064 | G37: 5676840 | H37: 19058224 | I37: 19058224
C38: （２）任意事業 | F38: 3087609 | G38: 0 | H38: 3087609 | I38: 2863069
D39: ア 介護給付等費用適正化事業 | F39: 0 | G39: 0 | H39: 0 | I39: 0
D40: イ 家族介護支援事業 | F40: 3087609 | G40: 0 | H40: 3087609 | I40: 2863069
D41: ウ その他の事業 | F41: 0 | G41: 0 | H41: 0 | I41: 0
E42: （ア）成年後見制度利用支援事業 | F42: 0 | G42: 0 | H42: 0 | I42: 0
E43: （イ）福祉用具・住宅改修支援事業 | F43: 0 | G43: 0 | H43: 0 | I43: 0
E44: （ウ）認知症対応型共同生活介護事業所の家賃等助成事業 | F44: 0 | G44: 0 | H44: 0 | I44: 0
E45: （エ）認知症サポーター等養成事業 | F45: 0 | G45: 0 | H45: 0 | I45: 0
E46: （オ）重度のＡＬＳ患者の入院におけるコミュニケーション支援事業 | F46: 0 | G46: 0 | H46: 0 | I46: 0
E47: （カ）地域自立生活支援事業 | F47: 0 | G47: 0 | H47: 0 | I47: 0
B48: ３ 小 計（１＋２） | F48: 60360138 | G48: 5676840 | H48: 54683298 | I48: 54458758 | K48: 54458758 | L48: 14947190 | M48: 16832625 | N48: 16832625
B49: ４ 包括的支援事業（社会保障充実分） | F49: 2686840 | G49: 0 | H49: 2686840 | I49: 2686840 | J49: 18620000 | K49: 2686840 | L49: 1034433 | M49: 1292830 | N49: 1292830 | O49: 258397 | P49: 0
C50: （１）在宅医療・介護連携推進事業 | F50: 891258 | G50: 0 | H50: 891258 | I50: 891258
C51: （２）生活支援体制整備事業 | F51: 624244 | G51: 0 | H51: 624244 | I51: 624244
D52: ア 生活支援コーディネーター・協議体 | F52: 624244 | G52: 0 | H52: 624244 | I52: 624244
D53: イ 就労的活動支援コーディネーター | F53: 0 | G53: 0 | H53: 0 | I53: 0
C54: （３）認知症初期集中支援推進事業 | F54: 0 | G54: 0 | H54: 0 | I54: 0
C55: （４）認知症地域支援・ケア向上事業 | F55: 0 | G55: 0 | H55: 0 | I55: 0
C56: （５）認知症サポーター活動促進・地域づくり推進事業 | F56: 714122 | G56: 0 | H56: 714122 | I56: 714122
C57: （６）地域ケア会議推進事業 | F57: 457216 | G57: 0 | H57: 457216 | I57: 457216
B58: ５ 合 計（３＋４） | F58: 63046978 | G58: 5676840 | H58: 57370138 | I58: 57145598 | K58: 57145598 | L58: 15981623 | M58: 18125455 | N58: 18125455 | O58: 2143832 | P58: 0
B60: （注） | D60: １ Ａ欄のうち、地域包括支援センターの運営については、交付要綱４にいう総事業費（指定介護予防支援等の業務にかかる経費を含む。 | K60: 上限設定の選択 | M60: 個別協議の有無 | P60: 保 険 者 名 | Q60: =[2]初期設定!B7 -> 小野町
D61: また、指定介護予防支援等の業務を指定居宅介護支援事業所へ委託を行っている場合における委託費を含む。）を記入すること。 | K61: ① 総合事業 | M61: ① 総合事業 | P61: 都道府県ｺｰﾄﾞ | Q61: =[2]初期設定!B11 -> 07
D62: ２ Ｂ欄には、交付要綱４にいう寄付金その他の収入額（地域包括支援センターの運営については、指定介護予防支援等にかかる収入額）を記入すること。 | K62: =IF('[2]総合事業上限額算定の手引き（事前の個別協議なし）'!C59="",'[2]総合事業上限額算定の手引き（事前の個別協議あり）'!E55,'[2]総合事業上限額算定の手引き（事前の個別協議なし）'!C59) -> ⑤個別協議希望 | M62: ○ | P62: 市区町村ｺｰﾄﾞ | Q62: =[2]初期設定!B10 -> 522
D63: ３ Ｄ欄のうち、地域包括支援センターの運営については、指定介護予防支援等の業務にかかる経費（指定介護予防支援等の業務を指定居宅介護支援 | K63: ② 包括的支援事業（地域包括支援センターの運営）・任意事業 | M63: ② 包括的支援事業（社会保障充実分） | P63: Ｃ・Ｄ | Q63: =[2]初期設定!B12 -> 6
D64: 事業所へ委託を行っている場合における委託費を含む。）を含む地域包括支援センターの総経費から、指定介護予防支援等にかかる収入額を | K64: =[2]初期設定!B51 -> ①原則の上限額 | M64: =IF(COUNTIF('[2]包括的支援事業(社会保障充実分) 標準額の手引き'!H13,"*個別*")>0,"○","×") -> #VALUE!
D65: 控除した後の経費における対象経費の実支出（予定）額を記入すること。 | K65: ③ 包括的支援事業（社会保障充実分） | P65: 重層的支援体制整備事業に要する費用相当額
D66: ４ Ｅ欄には、交付要綱４に定める基準額を記入すること。 | K66: =IF('[2]包括的支援事業(社会保障充実分) 標準額の手引き'!H13="","未設定",'[2]包括的支援事業(社会保障充実分) 標準額の手引き'!H13) -> ①標準額 | P66: 総額（①＋②＋③）
D67: ５ Ｆ欄には、Ｃ欄、Ｄ欄及びＥ欄を比較して最も少ない額から、重層的支援体制整備事業に要する費用相当額を控除した額を記入すること。 | P67: =SUM(P69,P71,P73) -> 0
D68: ６ Ｇ欄には、Ｆ欄の額に交付要綱４の第４欄に定める交付率を乗じて得た額（１円未満の端数が生じた場合には、これを切り捨てること。）を記入すること。 | M68: 総合事業調整交付金 | P68: ① 地域介護予防活動支援事業費相当額
D69: ７ H欄及びI欄には、重層的支援体制整備事業に要する費用相当額を含めない。 | M69: ④ 調整基準標準事業費額 | P69: =[2]初期設定!B39 -> 0
M70: =[2]初期設定!B46 -> 33303297 | N70: 円 | P70: ② 地域包括支援センターの運営費相当額
M71: ⑤ 総合事業調整交付金所要額 | P71: =[2]初期設定!B40 -> 0
M72: =[2]初期設定!B47 -> 2843000 | N72: 円 | P72: ③ 生活支援体制整備事業費相当額
P73: =[2]初期設定!B41 -> 0
P74: ア 生活支援コーディネーター・協議体
M75: 重層的支援体制整備事業の実施有無 | P75: =[2]初期設定!B42 -> 0
M76: =[2]初期設定!B38 -> ②未実施 | P76: イ 就労的活動支援コーディネーター
P77: =[2]初期設定!B43 -> 0

Sheet R５実績
B1: 別紙様式第４様式１
B3: 令和５年度地域支援事業交付金精算書
B5: 区 分 | F5: 総事業費 | G5: 寄付金その他 の収入額 | H5: 差引額 | I5: 対象経費 実支出額 | J5: 基準額 | K5: 交付基本額 | L5: 交付金所要額 | M5: 交付金 交付決定額 | N5: 交付金 受入済額 | O5: 差引過不足額 Ｉ－Ｇ | Q5: 備 考
F6: Ａ | G6: B | H6: Ｃ（Ａ－Ｂ） | I6: D | J6: Ｅ | K6: Ｆ | L6: Ｇ | M6: Ｈ | N6: Ｉ | O6: 超過額 Ｊ | P6: 不足額 Ｋ
F7: 円 | G7: 円 | H7: 円 | I7: 円 | J7: 円 | K7: 円 | L7: 円 | M7: 円 | N7: 円 | O7: 円 | P7: 円
B8: １ 介護予防・日常生活支援総合事業 | F8: 35770401 | G8: 0 | H8: 35770401 | I8: 35770401 | J8: 35770401 | K8: 35770401 | L8: 7154080 | M8: 7249800 | N8: 7249800 | O8: 95720 | P8: 0
C9: （１） | D9: 訪問型サービス（第１号訪問事業） | F9: 7480665 | G9: 0 | H9: 7480665 | I9: 7480665
D10: ア | E10: 訪問介護相当サービス | F10: 6006465 | G10: 0 | H10: 6006465 | I10: 6006465
D11: イ | E11: 訪問型サービスＡ（緩和した基準によるサービス） | F11: 0 | G11: 0 | H11: 0 | I11: 0
D12: ウ | E12: 訪問型サービスＢ（住民主体による支援） | F12: 1474200 | G12: 0 | H12: 1474200 | I12: 1474200
D13: エ | E13: 訪問型サービスＣ（短期集中予防サービス） | F13: 0 | G13: 0 | H13: 0 | I13: 0
D14: オ | E14: 訪問型サービスＤ（移動支援） | F14: 0 | G14: 0 | H14: 0 | I14: 0
D15: カ | E15: その他 | F15: 0 | G15: 0 | H15: 0 | I15: 0
C16: （２） | D16: 通所型サービス（第１号通所事業） | F16: 24427941 | G16: 0 | H16: 24427941 | I16: 24427941
D17: ア | E17: 通所介護相当サービス | F17: 22760141 | G17: 0 | H17: 22760141 | I17: 22760141
D18: イ | E18: 通所型サービスＡ（緩和した基準によるサービス） | F18: 0 | G18: 0 | H18: 0 | I18: 0
D19: ウ | E19: 通所型サービスＢ（住民主体による支援） | F19: 1667800 | G19: 0 | H19: 1667800 | I19: 1667800
D20: エ | E20: 通所型サービスＣ（短期集中予防サービス） | F20: 0 | G20: 0 | H20: 0 | I20: 0
D21: オ | E21: その他 | F21: 0 | G21: 0 | H21: 0 | I21: 0
C22: （３） | D22: その他生活支援サービス（第１号生活支援事業） | F22: 0 | G22: 0 | H22: 0 | I22: 0
D23: ア | E23: 栄養改善を目的とした配食 | F23: 0 | G23: 0 | H23: 0 | I23: 0
D24: イ | E24: 定期的な安否確認及び緊急時の対応 | F24: 0 | G24: 0 | H24: 0 | I24: 0
D25: ウ | E25: 訪問型サービス・通所型サービスの一体的提供等 | F25: 0 | G25: 0 | H25: 0 | I25: 0
D26: エ | E26: その他 | F26: 0 | G26: 0 | H26: 0 | I26: 0
C27: （４） | D27: 介護予防ケアマネジメント（第１号介護予防支援事業） | F27: 2743560 | G27: 0 | H27: 2743560 | I27: 2743560
C28: （５）審査支払手数料 | F28: 99981 | G28: 0 | H28: 99981 | I28: 99981
C29: （６）高額介護予防サービス費相当事業等 | F29: 24552 | G29: 0 | H29: 24552 | I29: 24552
C30: （７） | D30: 一般介護予防事業 | F30: 993702 | G30: 0 | H30: 993702 | I30: 993702
D31: ア | E31: 介護予防把握事業 | F31: 0 | G31: 0 | H31: 0 | I31: 0
D32: イ | E32: 介護予防普及啓発事業 | F32: 0 | G32: 0 | H32: 0 | I32: 0
D33: ウ | E33: 地域介護予防活動支援事業 | F33: 993702 | G33: 0 | H33: 993702 | I33: 993702
D34: エ | E34: 一般介護予防事業評価事業 | F34: 0 | G34: 0 | H34: 0 | I34: 0
D35: オ | E35: 地域リハビリテーション活動支援事業 | F35: 0 | G35: 0 | H35: 0 | I35: 0
B36: ２ 包括的支援事業（地域包括支援センターの運営）及び任意事業 | F36: 30888451 | G36: 6340080 | H36: 24548371 | I36: 24548371 | J36: 23915894 | K36: 23915894 | L36: 9207619 | M36: 9207619 | N36: 9207619 | O36: 0 | P36: 0
C37: （１）包括的支援事業（地域包括支援センターの運営） | F37: 25943303 | G37: 6340080 | H37: 19603223 | I37: 19603223
C38: （２）任意事業 | F38: 4945148 | G38: 0 | H38: 4945148 | I38: 4945148
D39: ア 介護給付等費用適正化事業 | F39: 0 | G39: 0 | H39: 0 | I39: 0
D40: イ 家族介護支援事業 | F40: 2586720 | G40: 0 | H40: 2586720 | I40: 2586720
D41: ウ その他の事業 | F41: 2358428 | G41: 0 | H41: 2358428 | I41: 2358428
E42: （ア）成年後見制度利用支援事業 | F42: 2358428 | G42: 0 | H42: 2358428 | I42: 2358428
E43: （イ）福祉用具・住宅改修支援事業 | F43: 0 | G43: 0 | H43: 0 | I43: 0
E44: （ウ）認知症対応型共同生活介護事業所の家賃等助成事業 | F44: 0 | G44: 0 | H44: 0 | I44: 0
E45: （エ）認知症サポーター等養成事業 | F45: 0 | G45: 0 | H45: 0 | I45: 0
E46: （オ）重度のＡＬＳ患者の入院におけるコミュニケーション支援事業 | F46: 0 | G46: 0 | H46: 0 | I46: 0
E47: （カ）地域自立生活支援事業 | F47: 0 | G47: 0 | H47: 0 | I47: 0
B48: ３ 小 計（１＋２） | F48: 66658852 | G48: 6340080 | H48: 60318772 | I48: 60318772 | K48: 59686295 | L48: 16361699 | M48: 16457419 | N48: 16457419
B49: ４ 包括的支援事業（社会保障充実分） | F49: 3046087 | G49: 0 | H49: 3046087 | I49: 3046087 | J49: 18620000 | K49: 3046087 | L49: 1172743 | M49: 1262415 | N49: 1262415 | O49: 89672 | P49: 0
C50: （１）在宅医療・介護連携推進事業 | F50: 689088 | G50: 0 | H50: 689088 | I50: 689088
C51: （２）生活支援体制整備事業 | F51: 765533 | G51: 0 | H51: 765533 | I51: 765533
D52: ア 生活支援コーディネーター・協議体 | F52: 765533 | G52: 0 | H52: 765533 | I52: 765533
D53: イ 就労的活動支援コーディネーター | F53: 0 | G53: 0 | H53: 0 | I53: 0
C54: （３）認知症初期集中支援推進事業 | F54: 0 | G54: 0 | H54: 0 | I54: 0
C55: （４）認知症地域支援・ケア向上事業 | F55: 0 | G55: 0 | H55: 0 | I55: 0
C56: （５）認知症サポーター活動促進・地域づくり推進事業 | F56: 1020711 | G56: 0 | H56: 1020711 | I56: 1020711
C57: （６）地域ケア会議推進事業 | F57: 570755 | G57: 0 | H57: 570755 | I57: 570755
B58: ５ 合 計（３＋４） | F58: 69704939 | G58: 6340080 | H58: 63364859 | I58: 63364859 | K58: 62732382 | L58: 17534442 | M58: 17719834 | N58: 17719834 | O58: 185392 | P58: 0
P60: =[3]初期設定!B45 -> 0

Sheet R６実績 
F1: 項目タイトル | H1: 項目タイトル | J1: 項目タイトル | L1: 項目タイトル | N1: 項目タイトル | P1: 項目タイトル | R1: 項目タイトル | T1: 項目タイトル | V1: 項目タイトル | X1: 項目タイトル | Z1: 項目タイトル | AB1: 項目タイトル
A2: 別紙様式第４様式１
B3: 令和６年度地域支援事業交付金所精算書
B6: 区 分 | G6: 総事業費 | I6: 寄付金その他 の収入額 | K6: 差引額 | M6: 対象経費 実支出額 | O6: 基準額 | Q6: 交付基本額 | S6: 交付金所要額 | U6: 交付金 交付決定額 | W6: 交付金 受入済額 | Y6: 差引過不足額 Ｉ－Ｇ | AC6: 備 考
G7: Ａ | I7: B | K7: Ｃ（Ａ－Ｂ） | M7: D | O7: Ｅ | Q7: Ｆ | S7: Ｇ | U7: Ｈ | W7: Ｉ | Y7: 超過額 Ｊ | AA7: 不足額 Ｋ
G8: 円 | I8: 円 | K8: 円 | M8: 円 | O8: 円 | Q8: 円 | S8: 円 | U8: 円 | W8: 円 | Y8: 円 | AA8: 円 | AC8: 円
B9: １ 介護予防・日常生活支援総合事業 | F9: A1000 | G9: 34677442 | H9: B1000 | I9: 0 | J9: C1000 | K9: 34677442 | L9: D1000 | M9: 34030529 | N9: E1000 | O9: 34030529 | P9: F1000 | Q9: 34030529 | R9: G1000 | S9: 6806105 | T9: H1000 | U9: 8011400 | V9: I1000 | W9: 8011400 | X9: J1000 | Y9: 1205295 | Z9: K1000 | AA9: 0 | AB9: 備考欄1000
C10: （１） | D10: 訪問型サービス（第１号訪問事業） | F10: A1100 | G10: 5135587 | H10: B1100 | I10: 0 | J10: C1100 | K10: 5135587 | L10: D1100 | M10: 5135587 | AB10: 備考欄1100 | AE10: 上限設定の選択
D11: ア | E11: 従前相当サービス | F11: A1110 | G11: 4782787 | H11: B1110 | I11: 0 | J11: C1110 | K11: 4782787 | L11: D1110 | M11: 4782787 | AB11: 備考欄1110 | AE11: ① 総合事業
D12: イ | E12: サービス・活動A | F12: A1120 | G12: 0 | H12: B1120 | I12: 0 | J12: C1120 | K12: 0 | L12: D1120 | M12: 0 | AB12: 備考欄1120 | AE12: =IF(当該年度上限額設定状況!D8="","未設定",当該年度上限額設定状況!D8) -> #REF!
D13: ウ | E13: サービス・活動B | F13: A1130 | G13: 352800 | H13: B1130 | I13: 0 | J13: C1130 | K13: 352800 | L13: D1130 | M13: 352800 | AB13: 備考欄1130 | AE13: ② 包括的支援事業（地域包括支援センターの運営）・任意事業
D14: エ | E14: サービス・活動C | F14: A1140 | G14: 0 | H14: B1140 | I14: 0 | J14: C1140 | K14: 0 | L14: D1140 | M14: 0 | AB14: 備考欄1140 | AE14: =IF(当該年度上限額設定状況!D9="","未設定",当該年度上限額設定状況!D9) -> ①原則の上限額
D15: オ | E15: サービス・活動D | F15: A1150 | G15: 0 | H15: B1150 | I15: 0 | J15: C1150 | K15: 0 | L15: D1150 | M15: 0 | AB15: 備考欄1150 | AE15: ③ 包括的支援事業（社会保障充実分）
D16: カ | E16: その他 | F16: A1160 | G16: 0 | H16: B1160 | I16: 0 | J16: C1160 | K16: 0 | L16: D1160 | M16: 0 | AB16: 備考欄1160 | AE16: =IF(当該年度上限額設定状況!D10="","未設定",当該年度上限額設定状況!D10) -> #REF!
C17: （２） | D17: 通所型サービス（第１号通所事業） | F17: A1200 | G17: 21535628 | H17: B1200 | I17: 0 | J17: C1200 | K17: 21535628 | L17: D1200 | M17: 21535628 | AB17: 備考欄1200
D18: ア | E18: 従前相当サービス | F18: A1210 | G18: 21396128 | H18: B1210 | I18: 0 | J18: C1210 | K18: 21396128 | L18: D1210 | M18: 21396128 | AB18: 備考欄1210 | AE18: 個別協議の有無
D19: イ | E19: サービス・活動A | F19: A1220 | G19: 0 | H19: B1220 | I19: 0 | J19: C1220 | K19: 0 | L19: D1220 | M19: 0 | AB19: 備考欄1220 | AE19: ① 総合事業
D20: ウ | E20: サービス・活動B | F20: A1230 | G20: 139500 | H20: B1230 | I20: 0 | J20: C1230 | K20: 139500 | L20: D1230 | M20: 139500 | AB20: 備考欄1230 | AE20: =IF(COUNTIF(AE12,"*個別*")>0,"○","×") -> ×
D21: エ | E21: サービス・活動C | F21: A1240 | G21: 0 | H21: B1240 | I21: 0 | J21: C1240 | K21: 0 | L21: D1240 | M21: 0 | AB21: 備考欄1240 | AE21: ② 包括的支援事業（社会保障充実分）
D22: オ | E22: その他 | F22: A1250 | G22: 0 | H22: B1250 | I22: 0 | J22: C1250 | K22: 0 | L22: D1250 | M22: 0 | AB22: 備考欄1250 | AE22: =IF(COUNTIF(AE16,"*個別*")>0,"○","×") -> ×
C23: （３） | D23: その他生活支援サービス（第１号生活支援事業） | F23: A1300 | G23: 0 | H23: B1300 | I23: 0 | J23: C1300 | K23: 0 | L23: D1300 | M23: 0 | AB23: 備考欄1300
D24: ア | E24: 栄養改善を目的とした配食 | F24: A1310 | G24: 0 | H24: B1310 | I24: 0 | J24: C1310 | K24: 0 | L24: D1310 | M24: 0 | AB24: 備考欄1310
D25: イ | E25: 定期的な安否確認及び緊急時の対応 | F25: A1320 | G25: 0 | H25: B1320 | I25: 0 | J25: C1320 | K25: 0 | L25: D1320 | M25: 0 | AB25: 備考欄1320
D26: ウ | E26: 訪問型サービスと通所型サービスを複合的に行う事業 | F26: A1330 | G26: 0 | H26: B1330 | I26: 0 | J26: C1330 | K26: 0 | L26: D1330 | M26: 0 | AB26: 備考欄1330 | AE26: 総合事業調整交付金
D27: エ | E27: その他 | F27: A1340 | G27: 0 | H27: B1340 | I27: 0 | J27: C1340 | K27: 0 | L27: D1340 | M27: 0 | AB27: 備考欄1340 | AE27: ④ 調整基準標準事業費額
C28: （４） | D28: 介護予防ケアマネジメント（第１号介護予防支援事業） | F28: A1400 | G28: 2564140 | H28: B1400 | I28: 0 | J28: C1400 | K28: 2564140 | L28: D1400 | M28: 2564140 | AB28: 備考欄1400 | AF28: 円
C29: （５） | D29: 審査支払手数料 | F29: A1500 | G29: 96395 | H29: B1500 | I29: 0 | J29: C1500 | K29: 96395 | L29: D1500 | M29: 96395 | AB29: 備考欄1500 | AE29: ⑤ 総合事業調整交付金所要額
C30: （６） | D30: 高額介護予防サービス費相当事業等 | F30: A1600 | G30: 40966 | H30: B1600 | I30: 0 | J30: C1600 | K30: 40966 | L30: D1600 | M30: 40966 | AB30: 備考欄1600 | AF30: 円
C31: （７） | D31: 一般介護予防事業 | F31: A1700 | G31: 5304726 | H31: B1700 | I31: 0 | J31: C1700 | K31: 5304726 | L31: D1700 | M31: 4657813 | AB31: 備考欄1700
D32: ア | E32: 介護予防把握事業 | F32: A1710 | G32: 0 | H32: B1710 | I32: 0 | J32: C1710 | K32: 0 | L32: D1710 | M32: 0 | AB32: 備考欄1710
D33: イ | E33: 介護予防普及啓発事業 | F33: A1720 | G33: 0 | H33: B1720 | I33: 0 | J33: C1720 | K33: 0 | L33: D1720 | M33: 0 | AB33: 備考欄1720
D34: ウ | E34: 地域介護予防活動支援事業 | F34: A1730 | G34: 5304726 | H34: B1730 | I34: 0 | J34: C1730 | K34: 5304726 | L34: D1730 | M34: 4657813 | AB34: 備考欄1730 | AE34: 重層的支援体制整備事業の実施有無
D35: エ | E35: 一般介護予防事業評価事業 | F35: A1740 | G35: 0 | H35: B1740 | I35: 0 | J35: C1740 | K35: 0 | L35: D1740 | M35: 0 | AB35: 備考欄1740 | AE35: =#REF! -> #REF!
D36: オ | E36: 地域リハビリテーション活動支援事業 | F36: A1750 | G36: 0 | H36: B1750 | I36: 0 | J36: C1750 | K36: 0 | L36: D1750 | M36: 0 | AB36: 備考欄1750
B37: ２ 包括的支援事業（地域包括支援センターの運営）及び任意事業 | F37: A2000 | G37: 22347005 | H37: B2000 | I37: 0 | J37: C2000 | K37: 22347005 | L37: D2000 | M37: 22347005 | N37: E2000 | O37: 24076130 | P37: F2000 | Q37: 22347005 | R37: G2000 | S37: 8603596 | T37: H2000 | U37: 8908900 | V37: I2000 | W37: 8908900 | X37: J2000 | Y37: 305304 | Z37: K2000 | AA37: 0 | AB37: 備考欄2000 | AE37: 重層的支援体制整備事業に要する費用相当額
C38: （１） | D38: 包括的支援事業（地域包括支援センターの運営） | F38: A2100 | G38: 19140546 | H38: B2100 | I38: 0 | J38: C2100 | K38: 19140546 | L38: D2100 | M38: 19140546 | AB38: 備考欄2100 | AE38: 総額（①＋②＋③）
C39: （２） | D39: 任意事業 | F39: A2200 | G39: 3206459 | H39: B2200 | I39: 0 | J39: C2200 | K39: 3206459 | L39: D2200 | M39: 3206459 | AB39: 備考欄2200 | AE39: =AE41+AE43+AE45 -> #REF! | AF39: 円
D40: ア | E40: 介護給付等費用適正化事業 | F40: A2210 | G40: 0 | H40: B2210 | I40: 0 | J40: C2210 | K40: 0 | L40: D2210 | M40: 0 | AB40: 備考欄2210 | AE40: ① 地域介護予防活動支援事業費相当額
D41: イ | E41: 家族介護支援事業 | F41: A2220 | G41: 2170991 | H41: B2220 | I41: 0 | J41: C2220 | K41: 2170991 | L41: D2220 | M41: 2170991 | AB41: 備考欄2220 | AE41: =#REF! -> #REF! | AF41: 円
