Workbook
Name _: #REF!
Name __: #REF!
Name _1Q_H12国調結果地区別年齢別_5歳毎: #REF!
Name _END1: #REF!
Name _N1: #REF!
Name _PNO1: #REF!
Name _PNO2: #REF!
Name _PNO3: #REF!
Name _PNO4: #REF!
Name _YH1: #REF!
Name _YH2: #REF!
Name \0: #REF!
Name \a: #REF!
Name \b: #REF!
Name \c: #REF!
Name \d: #REF!
Name \e: #REF!
Name \p: #REF!
Name \s: #REF!
Name aa: #REF!
Name BC: #REF!
Name BGH: #REF!
Name BH: #REF!
Name BOR: #REF!
Name CODE: #REF!
Name Data: [2]H17国勢調査!#REF!
Name DataEnd: [2]H17国勢調査!#REF!
Name F: #REF!
Name H6ﾃﾞｰﾀ: #REF!
Name H7ﾃﾞｰﾀ: #REF!
Name HEAD2: #REF!
Name Hyousoku: [2]H17国勢調査!#REF!
Name HyousokuArea: [2]H17国勢調査!#REF!
Name HyousokuEnd: [2]H17国勢調査!#REF!
Name Hyoutou: [2]H17国勢調査!#REF!
Name kei: #REF!
Name KES: #REF!
Name ｎ: #N/A
Name №１: #REF!
Name №１００: #REF!
Name №１５０: #REF!
Name №２００: #REF!
Name №２５０: #REF!
Name №３００: #REF!
Name №３２５: #REF!
Name №348: #REF!
Name №３５０: #REF!
Name №５０: #REF!
Name P: #N/A
Name ppp: '[3]10(000)'!#REF!
Name PRIN1: #REF!
Name PRINT: #REF!
Name Rangai0: [2]H17国勢調査!#REF!
Name RECORD: #REF!
Name RR: #REF!
Name START: #REF!
Name tanjyuu: #REF!
Name Title: [2]H17国勢調査!#REF!
Name TitleEnglish: [2]H17国勢調査!#REF!
Name UNDK_KF010H: #REF!

Sheet 計画改訂スケジュール水道
A5: 年度 | B5: 2025 | C5: 2026 | D5: 2027 | E5: 2028 | F5: 2029 | G5: 2030 | H5: 2031 | I5: 2032 | J5: 2033 | K5: 2034
B6: (令和7) | C6: (令和8) | D6: (令和9) | E6: (令和10) | F6: (令和11) | G6: (令和12) | H6: (令和13) | I6: (令和14) | J6: (令和15) | K6: (令和16)
A7: 瀬戸市汚水適正処理構想 | B7: 【愛知県】 全県域汚水適正処理構想の 見直し・改定までに実施
A10: 瀬戸市公共下水道事業基本計画 | E10: 見直し 改定 | J10: 見直し 改定
A13: 瀬戸市下水道ストックマネジメント計画 【管路施設】 | E13: 見直し 改定 | J13: 見直し 改定
A16: 瀬戸市下水道ストックマネジメント計画 【処理場施設】 | B16: 見直し 改定
A19: 年度 | B19: 令和7 | C19: 令和8 | D19: 令和9 | E19: 令和10 | F19: 令和11 | G19: 令和12 | H19: 令和13 | I19: 令和14 | J19: 令和15 | K19: 令和16 | L19: 令和17
B20: 2025 | C20: 2026 | D20: 2027 | E20: 2028 | F20: 2029 | G20: 2030 | H20: 2031 | I20: 2032 | J20: 2033 | K20: 2034 | L20: 2035
A21: 経営戦略 | B21: 改定 | F21: 検証 見直し | G21: 改定 | K21: 検証 見直し | L21: 改定
A24: 料金 | C24: 改定必要性の検証 | H24: 改定必要性の検証

Sheet 計画改訂スケジュール 下水道
A5: 年度 | B5: 2025 | C5: 2026 | D5: 2027 | E5: 2028 | F5: 2029 | G5: 2030 | H5: 2031 | I5: 2032 | J5: 2033 | K5: 2034
B6: (令和7) | C6: (令和8) | D6: (令和9) | E6: (令和10) | F6: (令和11) | G6: (令和12) | H6: (令和13) | I6: (令和14) | J6: (令和15) | K6: (令和16)
A7: 瀬戸市汚水適正処理構想 | B7: 【愛知県】 全県域汚水適正処理構想の 見直し・改定までに実施
A10: 瀬戸市公共下水道事業基本計画 | E10: 見直し 改定 | J10: 見直し 改定
A13: 瀬戸市下水道ストックマネジメント計画 【管路施設】 | E13: 見直し 改定 | J13: 見直し 改定
A16: 瀬戸市下水道ストックマネジメント計画 【処理場施設】 | B16: 見直し 改定
A19: 年度 | B19: 令和7 | C19: 令和8 | D19: 令和9 | E19: 令和10 | F19: 令和11 | G19: 令和12 | H19: 令和13 | I19: 令和14 | J19: 令和15 | K19: 令和16 | L19: 令和17
B20: 2025 | C20: 2026 | D20: 2027 | E20: 2028 | F20: 2029 | G20: 2030 | H20: 2031 | I20: 2032 | J20: 2033 | K20: 2034 | L20: 2035
A21: 経営戦略 | B21: 改定 | F21: 検証 見直し | G21: 改定 | K21: 検証 見直し | L21: 改定
A24: 使用料 | C24: 改定必要性の検証 | D24: 改定（※） | H24: 改定必要性の検証

Sheet Sheet2
B2: 和暦 | C2: 西暦
B3: S45 | C3: 1970
B4: S46 | C4: 1971
B5: S47 | C5: 1972
B6: S48 | C6: 1973
B7: S49 | C7: 1974
B8: S50 | C8: 1975
B9: S51 | C9: 1976
B10: S52 | C10: 1977
B11: S53 | C11: 1978
B12: S54 | C12: 1979
B13: S55 | C13: 1980
B14: S56 | C14: 1981
... B63: R5 | C63: 2023

Sheet Sheet3
B1: 取得価額 | C1: 資産名称 | D1: 取得価額 | E1: 耐用年数 | F1: 取得年度 | G1: 年度２ | H1: デフレーター | I1: 区分 | J1: 係数 | K1: 限界耐用年数 | L1: 限界年度 | X1: s | Y1: d | Z1: f | AB1: s | AC1: d | AD1: f
B2: 21817 | C2: 非常通報装置 | D2: =ROUND(B2*H2,0) -> 31786 | E2: 9 | F2: H18 | G2: =VLOOKUP(F2,Sheet2!$B$2:$C$70,2,FALSE) -> 2006 | H2: =VLOOKUP(G2,$AB$1:$AD$51,3,FALSE) -> 1.4569536 | I2: 配水・給水設備 | K2: =ROUND(E2*1.5,0) -> 14 | L2: =G2+K2 -> 2020 | N2: 2026 | O2: 2027 | P2: 2028 | Q2: 2029 | R2: 2030 | S2: 2031 | T2: 2032 | U2: 2033 | V2: 2034 | W2: 2035 | X2: 1985 | Y2: 77.7 | Z2: =$Y$32/Y2 -> 1.2870013 | AB2: 1975 | AC2: 77.7 | AD2: =$AC$51/AC2 -> 1.6988417
B3: 863776 | C3: 加圧ポンプ | D3: =ROUND(B3*H3,0) -> 1258482 | E3: 15 | F3: H18 | G3: =VLOOKUP(F3,Sheet2!$B$2:$C$70,2,FALSE) -> 2006 | H3: =VLOOKUP(G3,$AB$1:$AD$51,3,FALSE) -> 1.4569536 | I3: 配水・給水設備 | K3: =ROUND(E3*1.5,0) -> 23 | L3: =G3+K3 -> 2029 | M3: 取水・浄水施設 | N3: =SUMIFS($D$1:$D$203,$L$1:$L$203,N$2,$I$1:$I$203,$M3) -> 0 | O3: =SUMIFS($D$1:$D$203,$L$1:$L$203,O$2,$I$1:$I$203,$M3) -> 0 | P3: =SUMIFS($D$1:$D$203,$L$1:$L$203,P$2,$I$1:$I$203,$M3) -> 0 | Q3: =SUMIFS($D$1:$D$203,$L$1:$L$203,Q$2,$I$1:$I$203,$M3) -> 0 | R3: =SUMIFS($D$1:$D$203,$L$1:$L$203,R$2,$I$1:$I$203,$M3) -> 0 | S3: =SUMIFS($D$1:$D$203,$L$1:$L$203,S$2,$I$1:$I$203,$M3) -> 4143468 | T3: =SUMIFS($D$1:$D$203,$L$1:$L$203,T$2,$I$1:$I$203,$M3) -> 0 | U3: =SUMIFS($D$1:$D$203,$L$1:$L$203,U$2,$I$1:$I$203,$M3) -> 0 | ... W3: =SUMIFS($D$1:$D$203,$L$1:$L$203,W$2,$I$1:$I$203,$M3) -> 0 | X3: 1986 | Y3: 76.8 | Z3: =$Y$32/Y3 -> 1.3020833 | AB3: 1976 | AC3: 77.7 | AD3: =$AC$51/AC3 -> 1.6988417
B4: 755516 | C4: 薬品注入ポンプ（NKW-20VL-CIH） | D4: =ROUND(B4*H4,0) -> 1060937 | E4: 15 | F4: H21 | G4: =VLOOKUP(F4,Sheet2!$B$2:$C$70,2,FALSE) -> 2009 | H4: =VLOOKUP(G4,$AB$1:$AD$51,3,FALSE) -> 1.4042553 | I4: 配水・給水設備 | K4: =ROUND(E4*1.5,0) -> 23 | L4: =G4+K4 -> 2032 | M4: 配水・給水施設 | N4: =SUMIFS($D$1:$D$203,$L$1:$L$203,N$2,$I$1:$I$203,$M4) -> 0 | O4: =SUMIFS($D$1:$D$203,$L$1:$L$203,O$2,$I$1:$I$203,$M4) -> 0 | P4: =SUMIFS($D$1:$D$203,$L$1:$L$203,P$2,$I$1:$I$203,$M4) -> 0 | Q4: =SUMIFS($D$1:$D$203,$L$1:$L$203,Q$2,$I$1:$I$203,$M4) -> 0 | R4: =SUMIFS($D$1:$D$203,$L$1:$L$203,R$2,$I$1:$I$203,$M4) -> 0 | S4: =SUMIFS($D$1:$D$203,$L$1:$L$203,S$2,$I$1:$I$203,$M4) -> 3351730 | T4: =SUMIFS($D$1:$D$203,$L$1:$L$203,T$2,$I$1:$I$203,$M4) -> 0 | U4: =SUMIFS($D$1:$D$203,$L$1:$L$203,U$2,$I$1:$I$203,$M4) -> 0 | ... W4: =SUMIFS($D$1:$D$203,$L$1:$L$203,W$2,$I$1:$I$203,$M4) -> 0 | X4: 1987 | Y4: 77.3 | Z4: =$Y$32/Y4 -> 1.2936611 | AB4: 1977 | AC4: 77.7 | AD4: =$AC$51/AC4 -> 1.6988417
B5: 693900 | C5: 水位計 | D5: =ROUND(B5*H5,0) -> 973377 | E5: 10 | F5: H22 | G5: =VLOOKUP(F5,Sheet2!$B$2:$C$70,2,FALSE) -> 2010 | H5: =VLOOKUP(G5,$AB$1:$AD$51,3,FALSE) -> 1.402763 | I5: 配水・給水設備 | K5: =ROUND(E5*1.5,0) -> 15 | L5: =G5+K5 -> 2025 | M5: 取水・浄水設備 | N5: =SUMIFS($D$1:$D$203,$L$1:$L$203,N$2,$I$1:$I$203,$M5) -> 0 | O5: =SUMIFS($D$1:$D$203,$L$1:$L$203,O$2,$I$1:$I$203,$M5) -> 0 | P5: =SUMIFS($D$1:$D$203,$L$1:$L$203,P$2,$I$1:$I$203,$M5) -> 0 | Q5: =SUMIFS($D$1:$D$203,$L$1:$L$203,Q$2,$I$1:$I$203,$M5) -> 0 | R5: =SUMIFS($D$1:$D$203,$L$1:$L$203,R$2,$I$1:$I$203,$M5) -> 0 | S5: =SUMIFS($D$1:$D$203,$L$1:$L$203,S$2,$I$1:$I$203,$M5) -> 0 | T5: =SUMIFS($D$1:$D$203,$L$1:$L$203,T$2,$I$1:$I$203,$M5) -> 0 | U5: =SUMIFS($D$1:$D$203,$L$1:$L$203,U$2,$I$1:$I$203,$M5) -> 0 | ... W5: =SUMIFS($D$1:$D$203,$L$1:$L$203,W$2,$I$1:$I$203,$M5) -> 0 | X5: 1988 | Y5: 78.7 | Z5: =$Y$32/Y5 -> 1.270648 | AB5: 1978 | AC5: 77.7 | AD5: =$AC$51/AC5 -> 1.6988417
B6: 615009 | C6: 排水設備 | D6: =ROUND(B6*H6,0) -> 862712 | E6: 20 | F6: H22 | G6: =VLOOKUP(F6,Sheet2!$B$2:$C$70,2,FALSE) -> 2010 | H6: =VLOOKUP(G6,$AB$1:$AD$51,3,FALSE) -> 1.402763 | I6: 配水・給水設備 | K6: =ROUND(E6*1.5,0) -> 30 | L6: =G6+K6 -> 2040 | M6: 配水・給水設備 | N6: =SUMIFS($D$1:$D$203,$L$1:$L$203,N$2,$I$1:$I$203,$M6) -> 5213139 | O6: =SUMIFS($D$1:$D$203,$L$1:$L$203,O$2,$I$1:$I$203,$M6) -> 0 | P6: =SUMIFS($D$1:$D$203,$L$1:$L$203,P$2,$I$1:$I$203,$M6) -> 24757302 | Q6: =SUMIFS($D$1:$D$203,$L$1:$L$203,Q$2,$I$1:$I$203,$M6) -> 1258482 | R6: =SUMIFS($D$1:$D$203,$L$1:$L$203,R$2,$I$1:$I$203,$M6) -> 74777679 | S6: =SUMIFS($D$1:$D$203,$L$1:$L$203,S$2,$I$1:$I$203,$M6) -> 6794350 | T6: =SUMIFS($D$1:$D$203,$L$1:$L$203,T$2,$I$1:$I$203,$M6) -> 20517734 | U6: =SUMIFS($D$1:$D$203,$L$1:$L$203,U$2,$I$1:$I$203,$M6) -> 19106249 | ... W6: =SUMIFS($D$1:$D$203,$L$1:$L$203,W$2,$I$1:$I$203,$M6) -> 0 | X6: 1989 | Y6: 82.4 | Z6: =$Y$32/Y6 -> 1.2135922 | AB6: 1979 | AC6: 77.7 | AD6: =$AC$51/AC6 -> 1.6988417
B7: 321730 | C7: 無試薬形遊離塩素計 | D7: =ROUND(B7*H7,0) -> 401402 | E7: 10 | F7: H30 | G7: =VLOOKUP(F7,Sheet2!$B$2:$C$70,2,FALSE) -> 2018 | H7: =VLOOKUP(G7,$AB$1:$AD$51,3,FALSE) -> 1.2476371 | I7: 配水・給水設備 | K7: =ROUND(E7*1.5,0) -> 15 | L7: =G7+K7 -> 2033 | M7: 管路 | N7: =SUMIFS($D$1:$D$203,$L$1:$L$203,N$2,$I$1:$I$203,$M7) -> 0 | O7: =SUMIFS($D$1:$D$203,$L$1:$L$203,O$2,$I$1:$I$203,$M7) -> 0 | P7: =SUMIFS($D$1:$D$203,$L$1:$L$203,P$2,$I$1:$I$203,$M7) -> 0 | Q7: =SUMIFS($D$1:$D$203,$L$1:$L$203,Q$2,$I$1:$I$203,$M7) -> 0 | R7: =SUMIFS($D$1:$D$203,$L$1:$L$203,R$2,$I$1:$I$203,$M7) -> 0 | S7: =SUMIFS($D$1:$D$203,$L$1:$L$203,S$2,$I$1:$I$203,$M7) -> 20864978 | T7: =SUMIFS($D$1:$D$203,$L$1:$L$203,T$2,$I$1:$I$203,$M7) -> 0 | U7: =SUMIFS($D$1:$D$203,$L$1:$L$203,U$2,$I$1:$I$203,$M7) -> 0 | ... W7: =SUMIFS($D$1:$D$203,$L$1:$L$203,W$2,$I$1:$I$203,$M7) -> 0 | X7: 1990 | Y7: 85.3 | Z7: =$Y$32/Y7 -> 1.1723329 | AB7: 1980 | AC7: 77.7 | AD7: =$AC$51/AC7 -> 1.6988417
B8: 6069467 | C8: 増圧ポンプ | D8: =ROUND(B8*H8,0) -> 7572492 | E8: 15 | F8: H30 | G8: =VLOOKUP(F8,Sheet2!$B$2:$C$70,2,FALSE) -> 2018 | H8: =VLOOKUP(G8,$AB$1:$AD$51,3,FALSE) -> 1.2476371 | I8: 配水・給水設備 | K8: =ROUND(E8*1.5,0) -> 23 | L8: =G8+K8 -> 2041 | X8: 1991 | Y8: 87.6 | Z8: =$Y$32/Y8 -> 1.1415525 | AB8: 1981 | AC8: 77.7 | AD8: =$AC$51/AC8 -> 1.6988417
B9: 3339935 | C9: 遠方通報装置 | D9: =ROUND(B9*H9,0) -> 4167027 | E9: 9 | F9: H30 | G9: =VLOOKUP(F9,Sheet2!$B$2:$C$70,2,FALSE) -> 2018 | H9: =VLOOKUP(G9,$AB$1:$AD$51,3,FALSE) -> 1.2476371 | I9: 配水・給水設備 | K9: =ROUND(E9*1.5,0) -> 14 | L9: =G9+K9 -> 2032 | N9: 2026 | O9: 2027 | P9: 2028 | Q9: 2029 | R9: 2030 | S9: 2031 | T9: 2032 | U9: 2033 | V9: 2034 | W9: 2035 | X9: 1992 | Y9: 88.6 | Z9: =$Y$32/Y9 -> 1.1286682 | AB9: 1982 | AC9: 77.7 | AD9: =$AC$51/AC9 -> 1.6988417
B10: 2130648 | C10: 増圧ポンプ | D10: =ROUND(B10*H10,0) -> 2582604 | E10: 15 | F10: R2 | G10: =VLOOKUP(F10,Sheet2!$B$2:$C$70,2,FALSE) -> 2020 | H10: =VLOOKUP(G10,$AB$1:$AD$51,3,FALSE) -> 1.2121212 | I10: 配水・給水設備 | K10: =ROUND(E10*1.5,0) -> 23 | L10: =G10+K10 -> 2043 | M10: 取水・浄水施設 | N10: =ROUND(N3/1000,0) -> 0 | O10: =ROUND(O3/1000,0) -> 0 | P10: =ROUND(P3/1000,0) -> 0 | Q10: =ROUND(Q3/1000,0) -> 0 | R10: =ROUND(R3/1000,0) -> 0 | S10: =ROUND(S3/1000,0) -> 4143 | T10: =ROUND(T3/1000,0) -> 0 | U10: =ROUND(U3/1000,0) -> 0 | ... W10: =ROUND(W3/1000,0) -> 0 | X10: 1993 | Y10: 88.4 | Z10: =$Y$32/Y10 -> 1.1312217 | AB10: 1983 | AC10: 77.7 | AD10: =$AC$51/AC10 -> 1.6988417
B11: 3685445 | C11: 配水管 | D11: =ROUND(B11*H11,0) -> 4467206 | E11: 40 | F11: R2 | G11: =VLOOKUP(F11,Sheet2!$B$2:$C$70,2,FALSE) -> 2020 | H11: =VLOOKUP(G11,$AB$1:$AD$51,3,FALSE) -> 1.2121212 | I11: 管路 | K11: =ROUND(E11*1.5,0) -> 60 | L11: =G11+K11 -> 2080 | M11: 配水・給水施設 | N11: =ROUND(N4/1000,0) -> 0 | O11: =ROUND(O4/1000,0) -> 0 | P11: =ROUND(P4/1000,0) -> 0 | Q11: =ROUND(Q4/1000,0) -> 0 | R11: =ROUND(R4/1000,0) -> 0 | S11: =ROUND(S4/1000,0) -> 3352 | T11: =ROUND(T4/1000,0) -> 0 | U11: =ROUND(U4/1000,0) -> 0 | ... W11: =ROUND(W4/1000,0) -> 0 | X11: 1994 | Y11: 88.6 | Z11: =$Y$32/Y11 -> 1.1286682 | AB11: 1984 | AC11: 77.7 | AD11: =$AC$51/AC11 -> 1.6988417
B12: 2303403 | C12: フェンス | D12: =ROUND(B12*H12,0) -> 3190443 | E12: 60 | F12: H23 | G12: =VLOOKUP(F12,Sheet2!$B$2:$C$70,2,FALSE) -> 2011 | H12: =VLOOKUP(G12,$AB$1:$AD$51,3,FALSE) -> 1.3850997 | I12: 配水・給水設備 | K12: =ROUND(E12*1.5,0) -> 90 | L12: =G12+K12 -> 2101 | M12: 取水・浄水設備 | N12: =ROUND(N5/1000,0) -> 0 | O12: =ROUND(O5/1000,0) -> 0 | P12: =ROUND(P5/1000,0) -> 0 | Q12: =ROUND(Q5/1000,0) -> 0 | R12: =ROUND(R5/1000,0) -> 0 | S12: =ROUND(S5/1000,0) -> 0 | T12: =ROUND(T5/1000,0) -> 0 | U12: =ROUND(U5/1000,0) -> 0 | ... W12: =ROUND(W5/1000,0) -> 0 | X12: 1995 | Y12: 88.8 | Z12: =$Y$32/Y12 -> 1.1261261 | AB12: 1985 | AC12: 77.7 | AD12: =$AC$51/AC12 -> 1.6988417
B13: 3800615 | C13: 管路一式 | D13: =ROUND(B13*H13,0) -> 5042022 | E13: 40 | F13: H26 | G13: =VLOOKUP(F13,Sheet2!$B$2:$C$70,2,FALSE) -> 2014 | H13: =VLOOKUP(G13,$AB$1:$AD$51,3,FALSE) -> 1.3266332 | I13: 管路 | K13: =ROUND(E13*1.5,0) -> 60 | L13: =G13+K13 -> 2074 | M13: 配水・給水設備 | N13: =ROUND(N6/1000,0) -> 5213 | O13: =ROUND(O6/1000,0) -> 0 | P13: =ROUND(P6/1000,0) -> 24757 | Q13: =ROUND(Q6/1000,0) -> 1258 | R13: =ROUND(R6/1000,0) -> 74778 | S13: =ROUND(S6/1000,0) -> 6794 | T13: =ROUND(T6/1000,0) -> 20518 | U13: =ROUND(U6/1000,0) -> 19106 | ... W13: =ROUND(W6/1000,0) -> 0 | X13: 1996 | Y13: 88.5 | Z13: =$Y$32/Y13 -> 1.1299435 | AB13: 1986 | AC13: 76.8 | AD13: =$AC$51/AC13 -> 1.71875
B14: 1071082 | C14: 次亜塩注入器 | D14: =ROUND(B14*H14,0) -> 1298281 | E14: 10 | F14: R1 | G14: =VLOOKUP(F14,Sheet2!$B$2:$C$70,2,FALSE) -> 2019 | H14: =VLOOKUP(G14,$AB$1:$AD$51,3,FALSE) -> 1.2121212 | I14: 配水・給水設備 | K14: =ROUND(E14*1.5,0) -> 15 | L14: =G14+K14 -> 2034 | M14: 管路 | N14: =ROUND(N7/1000,0) -> 0 | O14: =ROUND(O7/1000,0) -> 0 | P14: =ROUND(P7/1000,0) -> 0 | Q14: =ROUND(Q7/1000,0) -> 0 | R14: =ROUND(R7/1000,0) -> 0 | S14: =ROUND(S7/1000,0) -> 20865 | T14: =ROUND(T7/1000,0) -> 0 | U14: =ROUND(U7/1000,0) -> 0 | ... W14: =ROUND(W7/1000,0) -> 0 | X14: 1997 | Y14: 89.4 | Z14: =$Y$32/Y14 -> 1.1185682 | AB14: 1987 | AC14: 77.3 | AD14: =$AC$51/AC14 -> 1.7076326
B15: 345510 | C15: 配水管 | D15: =ROUND(B15*H15,0) -> 586967 | E15: 40 | F15: S59 | G15: =VLOOKUP(F15,Sheet2!$B$2:$C$70,2,FALSE) -> 1984 | H15: =VLOOKUP(G15,$AB$1:$AD$51,3,FALSE) -> 1.6988417 | I15: 管路 | K15: =ROUND(E15*1.5,0) -> 60 | L15: =G15+K15 -> 2044 | X15: 1998 | Y15: 88 | Z15: =$Y$32/Y15 -> 1.1363636 | AB15: 1988 | AC15: 78.7 | AD15: =$AC$51/AC15 -> 1.6772554
B16: 1900308 | C16: 湧水井戸 | D16: =ROUND(B16*H16,0) -> 3228322 | E16: 40 | F16: S60 | G16: =VLOOKUP(F16,Sheet2!$B$2:$C$70,2,FALSE) -> 1985 | H16: =VLOOKUP(G16,$AB$1:$AD$51,3,FALSE) -> 1.6988417 | I16: 取水・浄水施設 | K16: =ROUND(E16*1.5,0) -> 60 | L16: =G16+K16 -> 2045 | X16: 1999 | Y16: 87 | Z16: =$Y$32/Y16 -> 1.1494253 | AB16: 1989 | AC16: 82.4 | AD16: =$AC$51/AC16 -> 1.6019417
B17: 493504 | C17: 砕石 | D17: =ROUND(B17*H17,0) -> 748765 | E17: 40 | F17: H11 | G17: =VLOOKUP(F17,Sheet2!$B$2:$C$70,2,FALSE) -> 1999 | H17: =VLOOKUP(G17,$AB$1:$AD$51,3,FALSE) -> 1.5172414 | I17: 取水・浄水施設 | K17: =ROUND(E17*1.5,0) -> 60 | L17: =G17+K17 -> 2059 | X17: 2000 | Y17: 87.2 | Z17: =$Y$32/Y17 -> 1.146789 | AB17: 1990 | AC17: 85.3 | AD17: =$AC$51/AC17 -> 1.5474795
B18: 341988 | C18: 水源地施設 | D18: =ROUND(B18*H18,0) -> 517688 | E18: 40 | F18: H12 | G18: =VLOOKUP(F18,Sheet2!$B$2:$C$70,2,FALSE) -> 2000 | H18: =VLOOKUP(G18,$AB$1:$AD$51,3,FALSE) -> 1.5137615 | I18: 取水・浄水施設 | K18: =ROUND(E18*1.5,0) -> 60 | L18: =G18+K18 -> 2060 | X18: 2001 | Y18: 85.6 | Z18: =$Y$32/Y18 -> 1.1682243 | AB18: 1991 | AC18: 87.6 | AD18: =$AC$51/AC18 -> 1.5068493
B19: 1471331 | C19: 管路一式 | D19: =ROUND(B19*H19,0) -> 2227244 | E19: 40 | F19: H12 | G19: =VLOOKUP(F19,Sheet2!$B$2:$C$70,2,FALSE) -> 2000 | H19: =VLOOKUP(G19,$AB$1:$AD$51,3,FALSE) -> 1.5137615 | I19: 管路 | K19: =ROUND(E19*1.5,0) -> 60 | L19: =G19+K19 -> 2060 | X19: 2002 | Y19: 85 | Z19: =$Y$32/Y19 -> 1.1764706 | AB19: 1992 | AC19: 88.6 | AD19: =$AC$51/AC19 -> 1.489842
B20: 13431685 | C20: 建屋 | D20: =ROUND(B20*H20,0) -> 20332367 | E20: 50 | F20: H12 | G20: =VLOOKUP(F20,Sheet2!$B$2:$C$70,2,FALSE) -> 2000 | H20: =VLOOKUP(G20,$AB$1:$AD$51,3,FALSE) -> 1.5137615 | I20: 取水・浄水施設 | K20: =ROUND(E20*1.5,0) -> 75 | L20: =G20+K20 -> 2075 | X20: 2003 | Y20: 86 | Z20: =$Y$32/Y20 -> 1.1627907 | AB20: 1993 | AC20: 88.4 | AD20: =$AC$51/AC20 -> 1.4932127
B21: 5752823 | C21: 浄水施設 配水池 | D21: =ROUND(B21*H21,0) -> 8708402 | E21: 60 | F21: H12 | G21: =VLOOKUP(F21,Sheet2!$B$2:$C$70,2,FALSE) -> 2000 | H21: =VLOOKUP(G21,$AB$1:$AD$51,3,FALSE) -> 1.5137615 | I21: 取水・浄水施設 | K21: =ROUND(E21*1.5,0) -> 90 | L21: =G21+K21 -> 2090 | X21: 2004 | Y21: 87.5 | Z21: =$Y$32/Y21 -> 1.1428571 | AB21: 1994 | AC21: 88.6 | AD21: =$AC$51/AC21 -> 1.489842
B22: 35619073 | C22: 機械設備 | D22: =ROUND(B22*H22,0) -> 53918780 | E22: 20 | F22: H12 | G22: =VLOOKUP(F22,Sheet2!$B$2:$C$70,2,FALSE) -> 2000 | H22: =VLOOKUP(G22,$AB$1:$AD$51,3,FALSE) -> 1.5137615 | I22: 配水・給水設備 | K22: =ROUND(E22*1.5,0) -> 30 | L22: =G22+K22 -> 2030 | X22: 2005 | Y22: 89 | Z22: =$Y$32/Y22 -> 1.1235955 | AB22: 1995 | AC22: 88.8 | AD22: =$AC$51/AC22 -> 1.4864865
B23: 20711870 | C23: 電気計装設備 | D23: =ROUND(B23*H23,0) -> 31352831 | E23: 10 | F23: H12 | G23: =VLOOKUP(F23,Sheet2!$B$2:$C$70,2,FALSE) -> 2000 | H23: =VLOOKUP(G23,$AB$1:$AD$51,3,FALSE) -> 1.5137615 | I23: 配水・給水設備 | K23: =ROUND(E23*1.5,0) -> 15 | L23: =G23+K23 -> 2015 | X23: 2006 | Y23: 90.6 | Z23: =$Y$32/Y23 -> 1.1037528 | AB23: 1996 | AC23: 88.5 | AD23: =$AC$51/AC23 -> 1.4915254
B24: 529783 | C24: 緊急警報装置 | D24: =ROUND(B24*H24,0) -> 738451 | E24: 9 | F24: H24 | G24: =VLOOKUP(F24,Sheet2!$B$2:$C$70,2,FALSE) -> 2012 | H24: =VLOOKUP(G24,$AB$1:$AD$51,3,FALSE) -> 1.3938754 | I24: 配水・給水設備 | K24: =ROUND(E24*1.5,0) -> 14 | L24: =G24+K24 -> 2026 | X24: 2007 | Y24: 93.5 | Z24: =$Y$32/Y24 -> 1.0695187 | AB24: 1997 | AC24: 89.4 | AD24: =$AC$51/AC24 -> 1.4765101
B25: 5308193 | C25: 制水弁設置工事 | D25: =ROUND(B25*H25,0) -> 7253431 | E25: 20 | F25: H25 | G25: =VLOOKUP(F25,Sheet2!$B$2:$C$70,2,FALSE) -> 2013 | H25: =VLOOKUP(G25,$AB$1:$AD$51,3,FALSE) -> 1.3664596 | I25: 配水・給水設備 | K25: =ROUND(E25*1.5,0) -> 30 | L25: =G25+K25 -> 2043 | X25: 2008 | Y25: 98.8 | Z25: =$Y$32/Y25 -> 1.0121457 | AB25: 1998 | AC25: 88 | AD25: =$AC$51/AC25 -> 1.5
B26: 3535724 | C26: 減圧弁 | D26: =ROUND(B26*H26,0) -> 4575643 | E26: 20 | F26: H29 | G26: =VLOOKUP(F26,Sheet2!$B$2:$C$70,2,FALSE) -> 2017 | H26: =VLOOKUP(G26,$AB$1:$AD$51,3,FALSE) -> 1.2941176 | I26: 配水・給水設備 | K26: =ROUND(E26*1.5,0) -> 30 | L26: =G26+K26 -> 2047 | X26: 2009 | Y26: 94 | Z26: =$Y$32/Y26 -> 1.0638298 | AB26: 1999 | AC26: 87 | AD26: =$AC$51/AC26 -> 1.5172414
... B29: 2084580 | C29: 浄水UF膜 | D29: =ROUND(B29*H29,0) -> 2420093 | E29: 20 | F29: R3 | G29: =VLOOKUP(F29,Sheet2!$B$2:$C$70,2,FALSE) -> 2021 | H29: =VLOOKUP(G29,$AB$1:$AD$51,3,FALSE) -> 1.1609499 | I29: 配水・給水設備 | K29: =ROUND(E29*1.5,0) -> 30 | L29: =G29+K29 -> 2051 | X29: 2012 | Y29: 94.7 | Z29: =$Y$32/Y29 -> 1.0559662 | AB29: 2002 | AC29: 85 | AD29: =$AC$51/AC29 -> 1.5529412
B30: 915296 | C30: 水源施設 第1取水 | D30: =ROUND(B30*H30,0) -> 1554943 | E30: 40 | F30: S46 | G30: =VLOOKUP(F30,Sheet2!$B$2:$C$70,2,FALSE) -> 1971 | H30: 1.6988417 | I30: 取水・浄水施設 | K30: =ROUND(E30*1.5,0) -> 60 | L30: =G30+K30 -> 2031 | X30: 2013 | Y30: 96.6 | Z30: =$Y$32/Y30 -> 1.0351967 | AB30: 2003 | AC30: 86 | AD30: =$AC$51/AC30 -> 1.5348837
B31: 1523700 | C31: 水源施設 第2取水 | D31: =ROUND(B31*H31,0) -> 2588525 | E31: 40 | F31: S46 | G31: =VLOOKUP(F31,Sheet2!$B$2:$C$70,2,FALSE) -> 1971 | H31: 1.6988417 | I31: 取水・浄水施設 | K31: =ROUND(E31*1.5,0) -> 60 | L31: =G31+K31 -> 2031 | X31: 2014 | Y31: 99.5 | Z31: =$Y$32/Y31 -> 1.0050251 | AB31: 2004 | AC31: 87.5 | AD31: =$AC$51/AC31 -> 1.5085714
B32: 12183990 | C32: 管路一式 | D32: =ROUND(B32*H32,0) -> 20698670 | E32: 40 | F32: S46 | G32: =VLOOKUP(F32,Sheet2!$B$2:$C$70,2,FALSE) -> 1971 | H32: 1.6988417 | I32: 管路 | K32: =ROUND(E32*1.5,0) -> 60 | L32: =G32+K32 -> 2031 | X32: 2015 | Y32: 100 | Z32: =$Y$32/Y32 -> 1 | AB32: 2005 | AC32: 89 | AD32: =$AC$51/AC32 -> 1.4831461
B33: 508511 | C33: 送水施設 減圧槽 | D33: =ROUND(B33*H33,0) -> 863880 | E33: 60 | F33: S46 | G33: =VLOOKUP(F33,Sheet2!$B$2:$C$70,2,FALSE) -> 1971 | H33: 1.6988417 | I33: 配水・給水施設 | K33: =ROUND(E33*1.5,0) -> 90 | L33: =G33+K33 -> 2061 | X33: 2016 | Y33: 100.1 | Z33: =$Y$32/Y33 -> 0.999001 | AB33: 2006 | AC33: 90.6 | AD33: =$AC$51/AC33 -> 1.4569536
B34: 970654 | C34: 浄水施設 滅菌設備棟 | D34: =ROUND(B34*H34,0) -> 1648987 | E34: 50 | F34: S46 | G34: =VLOOKUP(F34,Sheet2!$B$2:$C$70,2,FALSE) -> 1971 | H34: 1.6988417 | I34: 取水・浄水施設 | K34: =ROUND(E34*1.5,0) -> 75 | L34: =G34+K34 -> 2046 | X34: 2017 | Y34: 102 | Z34: =$Y$32/Y34 -> 0.98039216 | AB34: 2007 | AC34: 93.5 | AD34: =$AC$51/AC34 -> 1.4117647
B35: 731578 | C35: 浄水施設 着水井 | D35: =ROUND(B35*H35,0) -> 1242835 | E35: 60 | F35: S46 | G35: =VLOOKUP(F35,Sheet2!$B$2:$C$70,2,FALSE) -> 1971 | H35: 1.6988417 | I35: 取水・浄水施設 | K35: =ROUND(E35*1.5,0) -> 90 | L35: =G35+K35 -> 2061 | X35: 2018 | Y35: 105.8 | Z35: =$Y$32/Y35 -> 0.94517958 | AB35: 2008 | AC35: 98.8 | AD35: =$AC$51/AC35 -> 1.3360324
B36: 687236 | C36: 浄水施設 滅菌設備 | D36: =ROUND(B36*H36,0) -> 1167505 | E36: 10 | F36: S46 | G36: =VLOOKUP(F36,Sheet2!$B$2:$C$70,2,FALSE) -> 1971 | H36: 1.6988417 | I36: 取水・浄水施設 | K36: =ROUND(E36*1.5,0) -> 15 | L36: =G36+K36 -> 1986 | X36: 2019 | Y36: 108.9 | Z36: =$Y$32/Y36 -> 0.91827365 | AB36: 2009 | AC36: 94 | AD36: =$AC$51/AC36 -> 1.4042553
B37: 2849736 | C37: 配水施設 配水池 | D37: =ROUND(B37*H37,0) -> 4841250 | E37: 60 | F37: S46 | G37: =VLOOKUP(F37,Sheet2!$B$2:$C$70,2,FALSE) -> 1971 | H37: 1.6988417 | I37: 配水・給水施設 | K37: =ROUND(E37*1.5,0) -> 90 | L37: =G37+K37 -> 2061 | X37: 2020 | Y37: 108.9 | Z37: =$Y$32/Y37 -> 0.91827365 | AB37: 2010 | AC37: 94.1 | AD37: =$AC$51/AC37 -> 1.402763
B38: 539105 | C38: 配水施設 減圧槽 | D38: =ROUND(B38*H38,0) -> 915854 | E38: 60 | F38: S46 | G38: =VLOOKUP(F38,Sheet2!$B$2:$C$70,2,FALSE) -> 1971 | H38: 1.6988417 | I38: 配水・給水施設 | K38: =ROUND(E38*1.5,0) -> 90 | L38: =G38+K38 -> 2061 | X38: 2021 | Y38: 113.7 | Z38: =$Y$32/Y38 -> 0.87950748 | AB38: 2011 | AC38: 95.3 | AD38: =$AC$51/AC38 -> 1.3850997
B39: 279129 | C39: 水深及浄水場内柵 | D39: =ROUND(B39*H39,0) -> 474196 | E39: 60 | F39: S46 | G39: =VLOOKUP(F39,Sheet2!$B$2:$C$70,2,FALSE) -> 1971 | H39: 1.6988417 | I39: 配水・給水施設 | K39: =ROUND(E39*1.5,0) -> 90 | L39: =G39+K39 -> 2061 | X39: 2022 | Y39: 122.8 | Z39: =$Y$32/Y39 -> 0.81433225 | AB39: 2012 | AC39: 94.7 | AD39: =$AC$51/AC39 -> 1.3938754
B40: 647538 | C40: 量水器ボックス | D40: =ROUND(B40*H40,0) -> 1100065 | E40: 60 | F40: S46 | G40: =VLOOKUP(F40,Sheet2!$B$2:$C$70,2,FALSE) -> 1971 | H40: 1.6988417 | I40: 配水・給水施設 | K40: =ROUND(E40*1.5,0) -> 90 | L40: =G40+K40 -> 2061 | X40: 2023 | Y40: 127.1 | Z40: =$Y$32/Y40 -> 0.78678206 | AB40: 2013 | AC40: 96.6 | AD40: =$AC$51/AC40 -> 1.3664596 | AG40: 100 | AH40: 132 | AI40: =AG40*AJ40/AH40 -> 75.757576 | AJ40: 100
B41: 97895 | C41: 配水池排泥管 | D41: =ROUND(B41*H41,0) -> 166308 | E41: 40 | F41: S46 | G41: =VLOOKUP(F41,Sheet2!$B$2:$C$70,2,FALSE) -> 1971 | H41: 1.6988417 | I41: 管路 | K41: =ROUND(E41*1.5,0) -> 60 | L41: =G41+K41 -> 2031 | X41: 2024 | Y41: 132 | Z41: =$Y$32/Y41 -> 0.75757576 | AB41: 2014 | AC41: 99.5 | AD41: =$AC$51/AC41 -> 1.3266332
B42: 1972950 | C42: 給水装置 | D42: =ROUND(B42*H42,0) -> 3351730 | E42: 40 | F42: S46 | G42: =VLOOKUP(F42,Sheet2!$B$2:$C$70,2,FALSE) -> 1971 | H42: 1.6988417 | I42: 配水・給水施設 | K42: =ROUND(E42*1.5,0) -> 60 | L42: =G42+K42 -> 2031 | AB42: 2015 | AC42: 100 | AD42: =$AC$51/AC42 -> 1.32
B43: 165845 | C43: 量水器 | D43: =ROUND(B43*H43,0) -> 281744 | E43: 10 | F43: S46 | G43: =VLOOKUP(F43,Sheet2!$B$2:$C$70,2,FALSE) -> 1971 | H43: 1.6988417 | I43: 配水・給水設備 | K43: =ROUND(E43*1.5,0) -> 15 | L43: =G43+K43 -> 1986 | AB43: 2016 | AC43: 100.1 | AD43: =$AC$51/AC43 -> 1.3186813
B44: 403096 | C44: 水源 | D44: =ROUND(B44*H44,0) -> 684796 | E44: 40 | F44: S53 | G44: =VLOOKUP(F44,Sheet2!$B$2:$C$70,2,FALSE) -> 1978 | H44: =VLOOKUP(G44,$AB$1:$AD$51,3,FALSE) -> 1.6988417 | I44: 配水・給水施設 | K44: =ROUND(E44*1.5,0) -> 60 | L44: =G44+K44 -> 2038 | AB44: 2017 | AC44: 102 | AD44: =$AC$51/AC44 -> 1.2941176
B45: 724420 | C45: 小規模水道井戸ポンプ | D45: =ROUND(B45*H45,0) -> 1245097 | E45: 15 | F45: S61 | G45: =VLOOKUP(F45,Sheet2!$B$2:$C$70,2,FALSE) -> 1986 | H45: =VLOOKUP(G45,$AB$1:$AD$51,3,FALSE) -> 1.71875 | I45: 配水・給水設備 | K45: =ROUND(E45*1.5,0) -> 23 | L45: =G45+K45 -> 2009 | AB45: 2018 | AC45: 105.8 | AD45: =$AC$51/AC45 -> 1.2476371
B46: 76781 | C46: 電柱電線 | D46: =ROUND(B46*H46,0) -> 116228 | E46: 20 | F46: H12 | G46: =VLOOKUP(F46,Sheet2!$B$2:$C$70,2,FALSE) -> 2000 | H46: =VLOOKUP(G46,$AB$1:$AD$51,3,FALSE) -> 1.5137615 | I46: 配水・給水設備 | K46: =ROUND(E46*1.5,0) -> 30 | L46: =G46+K46 -> 2030 | AB46: 2019 | AC46: 108.9 | AD46: =$AC$51/AC46 -> 1.2121212
B47: 2861074 | C47: フェンス | D47: =ROUND(B47*H47,0) -> 3467968 | E47: 60 | F47: R2 | G47: =VLOOKUP(F47,Sheet2!$B$2:$C$70,2,FALSE) -> 2020 | H47: =VLOOKUP(G47,$AB$1:$AD$51,3,FALSE) -> 1.2121212 | I47: 配水・給水施設 | K47: =ROUND(E47*1.5,0) -> 90 | L47: =G47+K47 -> 2110 | AB47: 2020 | AC47: 108.9 | AD47: =$AC$51/AC47 -> 1.2121212
B48: 1327912 | C48: 減圧弁 | D48: =ROUND(B48*H48,0) -> 1814538 | E48: 20 | F48: H25 | G48: =VLOOKUP(F48,Sheet2!$B$2:$C$70,2,FALSE) -> 2013 | H48: =VLOOKUP(G48,$AB$1:$AD$51,3,FALSE) -> 1.3664596 | I48: 配水・給水設備 | K48: =ROUND(E48*1.5,0) -> 30 | L48: =G48+K48 -> 2043 | AB48: 2021 | AC48: 113.7 | AD48: =$AC$51/AC48 -> 1.1609499
B49: 2280369 | C49: 流量計 | D49: =ROUND(B49*H49,0) -> 2951066 | E49: 10 | F49: H29 | G49: =VLOOKUP(F49,Sheet2!$B$2:$C$70,2,FALSE) -> 2017 | H49: =VLOOKUP(G49,$AB$1:$AD$51,3,FALSE) -> 1.2941176 | I49: 配水・給水設備 | K49: =ROUND(E49*1.5,0) -> 15 | L49: =G49+K49 -> 2032 | AB49: 2022 | AC49: 122.8 | AD49: =$AC$51/AC49 -> 1.0749186
B50: 5528168 | C50: 監視通報装置 | D50: =ROUND(B50*H50,0) -> 6700810 | E50: 9 | F50: R1 | G50: =VLOOKUP(F50,Sheet2!$B$2:$C$70,2,FALSE) -> 2019 | H50: =VLOOKUP(G50,$AB$1:$AD$51,3,FALSE) -> 1.2121212 | I50: 配水・給水設備 | K50: =ROUND(E50*1.5,0) -> 14 | L50: =G50+K50 -> 2033 | AB50: 2023 | AC50: 127.1 | AD50: =$AC$51/AC50 -> 1.0385523
B51: 1312940 | C51: 減圧弁 | D51: =ROUND(B51*H51,0) -> 1524258 | E51: 20 | F51: R3 | G51: =VLOOKUP(F51,Sheet2!$B$2:$C$70,2,FALSE) -> 2021 | H51: =VLOOKUP(G51,$AB$1:$AD$51,3,FALSE) -> 1.1609499 | I51: 配水・給水設備 | K51: =ROUND(E51*1.5,0) -> 30 | L51: =G51+K51 -> 2051 | AB51: 2024 | AC51: 132 | AD51: =$AC$51/AC51 -> 1
B52: 1106975 | C52: 水道管 | D52: =ROUND(B52*H52,0) -> 1668045 | E52: 40 | F52: H3 | G52: =VLOOKUP(F52,Sheet2!$B$2:$C$70,2,FALSE) -> 1991 | H52: =VLOOKUP(G52,$AB$1:$AD$51,3,FALSE) -> 1.5068493 | I52: 管路 | K52: =ROUND(E52*1.5,0) -> 60 | L52: =G52+K52 -> 2051
B53: 1066391 | C53: 管路一式 | D53: =ROUND(B53*H53,0) -> 1380035 | E53: 40 | F53: H29 | G53: =VLOOKUP(F53,Sheet2!$B$2:$C$70,2,FALSE) -> 2017 | H53: =VLOOKUP(G53,$AB$1:$AD$51,3,FALSE) -> 1.2941176 | I53: 管路 | K53: =ROUND(E53*1.5,0) -> 60 | L53: =G53+K53 -> 2077
B54: 28000000 | C54: 深井戸 | D54: =ROUND(B54*H54,0) -> 42000000 | E54: 40 | F54: H10 | G54: =VLOOKUP(F54,Sheet2!$B$2:$C$70,2,FALSE) -> 1998 | H54: =VLOOKUP(G54,$AB$1:$AD$51,3,FALSE) -> 1.5 | I54: 取水・浄水施設 | K54: =ROUND(E54*1.5,0) -> 60 | L54: =G54+K54 -> 2058
B55: 37950000 | C55: 管路一式 | D55: =ROUND(B55*H55,0) -> 56925000 | E55: 40 | F55: H10 | G55: =VLOOKUP(F55,Sheet2!$B$2:$C$70,2,FALSE) -> 1998 | H55: =VLOOKUP(G55,$AB$1:$AD$51,3,FALSE) -> 1.5 | I55: 管路 | K55: =ROUND(E55*1.5,0) -> 60 | L55: =G55+K55 -> 2058
B56: 36850000 | C56: 管路一式 | D56: =ROUND(B56*H56,0) -> 55275000 | E56: 40 | F56: H10 | G56: =VLOOKUP(F56,Sheet2!$B$2:$C$70,2,FALSE) -> 1998 | H56: =VLOOKUP(G56,$AB$1:$AD$51,3,FALSE) -> 1.5 | I56: 管路 | K56: =ROUND(E56*1.5,0) -> 60 | L56: =G56+K56 -> 2058
B57: 47890000 | C57: 管路一式 | D57: =ROUND(B57*H57,0) -> 71835000 | E57: 40 | F57: H10 | G57: =VLOOKUP(F57,Sheet2!$B$2:$C$70,2,FALSE) -> 1998 | H57: =VLOOKUP(G57,$AB$1:$AD$51,3,FALSE) -> 1.5 | I57: 管路 | K57: =ROUND(E57*1.5,0) -> 60 | L57: =G57+K57 -> 2058
B58: 33350000 | C58: 管路一式 | D58: =ROUND(B58*H58,0) -> 50025000 | E58: 40 | F58: H10 | G58: =VLOOKUP(F58,Sheet2!$B$2:$C$70,2,FALSE) -> 1998 | H58: =VLOOKUP(G58,$AB$1:$AD$51,3,FALSE) -> 1.5 | I58: 管路 | K58: =ROUND(E58*1.5,0) -> 60 | L58: =G58+K58 -> 2058
B59: 39450000 | C59: 管路一式 | D59: =ROUND(B59*H59,0) -> 59175000 | E59: 40 | F59: H10 | G59: =VLOOKUP(F59,Sheet2!$B$2:$C$70,2,FALSE) -> 1998 | H59: =VLOOKUP(G59,$AB$1:$AD$51,3,FALSE) -> 1.5 | I59: 管路 | K59: =ROUND(E59*1.5,0) -> 60 | L59: =G59+K59 -> 2058
B60: 34680000 | C60: 管路一式 | D60: =ROUND(B60*H60,0) -> 52020000 | E60: 40 | F60: H10 | G60: =VLOOKUP(F60,Sheet2!$B$2:$C$70,2,FALSE) -> 1998 | H60: =VLOOKUP(G60,$AB$1:$AD$51,3,FALSE) -> 1.5 | I60: 管路 | K60: =ROUND(E60*1.5,0) -> 60 | L60: =G60+K60 -> 2058
B61: 37740000 | C61: 管路一式 | D61: =ROUND(B61*H61,0) -> 56610000 | E61: 40 | F61: H10 | G61: =VLOOKUP(F61,Sheet2!$B$2:$C$70,2,FALSE) -> 1998 | H61: =VLOOKUP(G61,$AB$1:$AD$51,3,FALSE) -> 1.5 | I61: 管路 | K61: =ROUND(E61*1.5,0) -> 60 | L61: =G61+K61 -> 2058
B62: 48649829 | C62: 配水池 | D62: =ROUND(B62*H62,0) -> 72974744 | E62: 60 | F62: H10 | G62: =VLOOKUP(F62,Sheet2!$B$2:$C$70,2,FALSE) -> 1998 | H62: =VLOOKUP(G62,$AB$1:$AD$51,3,FALSE) -> 1.5 | I62: 配水・送水施設 | K62: =ROUND(E62*1.5,0) -> 90 | L62: =G62+K62 -> 2088
B63: 954171 | C63: 浄水場 | D63: =ROUND(B63*H63,0) -> 1431257 | E63: 60 | F63: H10 | G63: =VLOOKUP(F63,Sheet2!$B$2:$C$70,2,FALSE) -> 1998 | H63: =VLOOKUP(G63,$AB$1:$AD$51,3,FALSE) -> 1.5 | I63: 取水・浄水施設 | K63: =ROUND(E63*1.5,0) -> 90 | L63: =G63+K63 -> 2088
... B100: 12108 | C100: 薬注室排水管 | D100: =ROUND(B100*H100,0) -> 17094 | E100: 40 | F100: H19 | G100: =VLOOKUP(F100,Sheet2!$B$2:$C$70,2,FALSE) -> 2007 | H100: =VLOOKUP(G100,$AB$1:$AD$51,3,FALSE) -> 1.4117647 | I100: 管路 | K100: =ROUND(E100*1.5,0) -> 60 | L100: =G100+K100 -> 2067
B101: 66094 | C101: 手洗い器給水設備 | D101: =ROUND(B101*H101,0) -> 80114 | E101: 40 | F101: H19 | G101: =VLOOKUP(F11,Sheet2!$B$2:$C$70,2,FALSE) -> 2020 | H101: =VLOOKUP(G101,$AB$1:$AD$51,3,FALSE) -> 1.2121212 | I101: 配水・給水施設 | K101: =ROUND(E101*1.5,0) -> 60 | L101: =G101+K101 -> 2080
B102: 18520 | C102: 手洗い器排水設備 | D102: =ROUND(B102*H102,0) -> 26146 | E102: 40 | F102: H19 | G102: =VLOOKUP(F102,Sheet2!$B$2:$C$70,2,FALSE) -> 2007 | H102: =VLOOKUP(G102,$AB$1:$AD$51,3,FALSE) -> 1.4117647 | I102: 配水・給水施設 | K102: =ROUND(E102*1.5,0) -> 60 | L102: =G102+K102 -> 2067
B103: 68094 | C103: 足洗い給水設備 | D103: =ROUND(B103*H103,0) -> 96133 | E103: 40 | F103: H19 | G103: =VLOOKUP(F103,Sheet2!$B$2:$C$70,2,FALSE) -> 2007 | H103: =VLOOKUP(G103,$AB$1:$AD$51,3,FALSE) -> 1.4117647 | I103: 配水・給水施設 | K103: =ROUND(E103*1.5,0) -> 60 | L103: =G103+K103 -> 2067
B104: 23481 | C104: 足洗い排水設備 | D104: =ROUND(B104*H104,0) -> 33150 | E104: 40 | F104: H19 | G104: =VLOOKUP(F104,Sheet2!$B$2:$C$70,2,FALSE) -> 2007 | H104: =VLOOKUP(G104,$AB$1:$AD$51,3,FALSE) -> 1.4117647 | I104: 配水・給水施設 | K104: =ROUND(E104*1.5,0) -> 60 | L104: =G104+K104 -> 2067
B105: 25760000 | C105: 浄水処理施設配水池 | D105: =ROUND(B105*H105,0) -> 36367059 | E105: 60 | F105: H19 | G105: =VLOOKUP(F105,Sheet2!$B$2:$C$70,2,FALSE) -> 2007 | H105: =VLOOKUP(G105,$AB$1:$AD$51,3,FALSE) -> 1.4117647 | I105: 取水・浄水施設 | K105: =ROUND(E105*1.5,0) -> 90 | L105: =G105+K105 -> 2097
B106: 2159055 | C106: 取水ポンプ設備 | D106: =ROUND(B106*H106,0) -> 3048078 | E106: 15 | F106: H19 | G106: =VLOOKUP(F106,Sheet2!$B$2:$C$70,2,FALSE) -> 2007 | H106: =VLOOKUP(G106,$AB$1:$AD$51,3,FALSE) -> 1.4117647 | I106: 配水・給水設備 | K106: =ROUND(E106*1.5,0) -> 23 | L106: =G106+K106 -> 2030
B107: 263402 | C107: ドレンポンプ設備 | D107: =ROUND(B107*H107,0) -> 371862 | E107: 15 | F107: H19 | G107: =VLOOKUP(F107,Sheet2!$B$2:$C$70,2,FALSE) -> 2007 | H107: =VLOOKUP(G107,$AB$1:$AD$51,3,FALSE) -> 1.4117647 | I107: 配水・給水設備 | K107: =ROUND(E107*1.5,0) -> 23 | L107: =G107+K107 -> 2030
B108: 34910558 | C108: 浄水機械設備 | D108: =ROUND(B108*H108,0) -> 49285494 | E108: 20 | F108: H19 | G108: =VLOOKUP(F108,Sheet2!$B$2:$C$70,2,FALSE) -> 2007 | H108: =VLOOKUP(G108,$AB$1:$AD$51,3,FALSE) -> 1.4117647 | I108: 配水・給水設備 | K108: =ROUND(E108*1.5,0) -> 30 | L108: =G108+K108 -> 2037
B109: 1604230 | C109: 表洗設備 | D109: =ROUND(B109*H109,0) -> 2264795 | E109: 20 | F109: H19 | G109: =VLOOKUP(F109,Sheet2!$B$2:$C$70,2,FALSE) -> 2007 | H109: =VLOOKUP(G109,$AB$1:$AD$51,3,FALSE) -> 1.4117647 | I109: 配水・給水設備 | K109: =ROUND(E109*1.5,0) -> 30 | L109: =G109+K109 -> 2037
B110: 2495313 | C110: 逆流ポンプ設備 | D110: =ROUND(B110*H110,0) -> 3522795 | E110: 15 | F110: H19 | G110: =VLOOKUP(F110,Sheet2!$B$2:$C$70,2,FALSE) -> 2007 | H110: =VLOOKUP(G110,$AB$1:$AD$51,3,FALSE) -> 1.4117647 | I110: 配水・給水設備 | K110: =ROUND(E110*1.5,0) -> 23 | L110: =G110+K110 -> 2030
B111: 898088 | C111: 浄水サンプリングポンプ設備 | D111: =ROUND(B111*H111,0) -> 1267889 | E111: 15 | F111: H19 | G111: =VLOOKUP(F111,Sheet2!$B$2:$C$70,2,FALSE) -> 2007 | H111: =VLOOKUP(G111,$AB$1:$AD$51,3,FALSE) -> 1.4117647 | I111: 配水・給水設備 | K111: =ROUND(E111*1.5,0) -> 23 | L111: =G111+K111 -> 2030
B112: 3202855 | C112: 次亜塩注入装置 | D112: =ROUND(B112*H112,0) -> 4521678 | E112: 10 | F112: H19 | G112: =VLOOKUP(F112,Sheet2!$B$2:$C$70,2,FALSE) -> 2007 | H112: =VLOOKUP(G112,$AB$1:$AD$51,3,FALSE) -> 1.4117647 | I112: 配水・給水設備 | K112: =ROUND(E112*1.5,0) -> 15 | L112: =G112+K112 -> 2022
B113: 2928244 | C113: PAC注入装置 | D113: =ROUND(B113*H113,0) -> 4133992 | E113: 15 | F113: H19 | G113: =VLOOKUP(F113,Sheet2!$B$2:$C$70,2,FALSE) -> 2007 | H113: =VLOOKUP(G113,$AB$1:$AD$51,3,FALSE) -> 1.4117647 | I113: 配水・給水設備 | K113: =ROUND(E113*1.5,0) -> 23 | L113: =G113+K113 -> 2030
... B200: 553317 | C200: 急速ろ過設備_流量計 | D200: =ROUND(B200*H200,0) -> 849277 | E200: 10 | F200: H15 | G200: =VLOOKUP(F200,Sheet2!$B$2:$C$70,2,FALSE) -> 2003 | H200: =VLOOKUP(G200,$AB$1:$AD$51,3,FALSE) -> 1.5348837 | I200: 配水・給水設備 | K200: =ROUND(E200*1.5,0) -> 15 | L200: =G200+K200 -> 2018
B201: 2348623 | C201: 前次亜注入機 | D201: =ROUND(B201*H201,0) -> 3555255 | E201: 10 | F201: H15 | G201: =VLOOKUP(F21,Sheet2!$B$2:$C$70,2,FALSE) -> 2000 | H201: =VLOOKUP(G201,$AB$1:$AD$51,3,FALSE) -> 1.5137615 | I201: 配水・給水設備 | K201: =ROUND(E201*1.5,0) -> 15 | L201: =G201+K201 -> 2015
B202: 2497365 | C202: 後次亜注入機 | D202: =ROUND(B202*H202,0) -> 3833165 | E202: 10 | F202: H15 | G202: =VLOOKUP(F202,Sheet2!$B$2:$C$70,2,FALSE) -> 2003 | H202: =VLOOKUP(G202,$AB$1:$AD$51,3,FALSE) -> 1.5348837 | I202: 配水・給水設備 | K202: =ROUND(E202*1.5,0) -> 15 | L202: =G202+K202 -> 2018
B203: 2348623 | C203: PAC注入機 | D203: =ROUND(B203*H203,0) -> 3604863 | E203: 15 | F203: H15 | G203: =VLOOKUP(F203,Sheet2!$B$2:$C$70,2,FALSE) -> 2003 | H203: =VLOOKUP(G203,$AB$1:$AD$51,3,FALSE) -> 1.5348837 | I203: 配水・給水設備 | K203: =ROUND(E203*1.5,0) -> 23 | L203: =G203+K203 -> 2026
B204: 1418991 | C204: 硫酸注入機 | D204: =ROUND(B204*H204,0) -> 2177986 | E204: 15 | F204: H15 | G204: =VLOOKUP(F204,Sheet2!$B$2:$C$70,2,FALSE) -> 2003 | H204: =VLOOKUP(G204,$AB$1:$AD$51,3,FALSE) -> 1.5348837 | I204: 配水・給水設備 | K204: =ROUND(E204*1.5,0) -> 23 | L204: =G204+K204 -> 2026
B205: 1652515 | C205: 減圧施設 | D205: =ROUND(B205*H205,0) -> 2536418 | E205: 20 | F205: H15 | G205: =VLOOKUP(F205,Sheet2!$B$2:$C$70,2,FALSE) -> 2003 | H205: =VLOOKUP(G205,$AB$1:$AD$51,3,FALSE) -> 1.5348837 | I205: 配水・給水設備 | K205: =ROUND(E205*1.5,0) -> 30 | L205: =G205+K205 -> 2033
B206: 15141853 | C206: 電気計装制御盤類 | D206: =ROUND(B206*H206,0) -> 23240984 | E206: 20 | F206: H15 | G206: =VLOOKUP(F206,Sheet2!$B$2:$C$70,2,FALSE) -> 2003 | H206: =VLOOKUP(G206,$AB$1:$AD$51,3,FALSE) -> 1.5348837 | I206: 配水・給水設備 | K206: =ROUND(E206*1.5,0) -> 30 | L206: =G206+K206 -> 2033
B207: 29358535 | C207: 電気計装機器 | D207: =ROUND(B207*H207,0) -> 45061937 | E207: 10 | F207: H15 | G207: =VLOOKUP(F207,Sheet2!$B$2:$C$70,2,FALSE) -> 2003 | H207: =VLOOKUP(G207,$AB$1:$AD$51,3,FALSE) -> 1.5348837 | I207: 配水・給水設備 | K207: =ROUND(E207*1.5,0) -> 15 | L207: =G207+K207 -> 2018
B208: 8240261 | C208: 非常用発電機 | D208: =ROUND(B208*H208,0) -> 12647842 | E208: 15 | F208: H15 | G208: =VLOOKUP(F208,Sheet2!$B$2:$C$70,2,FALSE) -> 2003 | H208: =VLOOKUP(G208,$AB$1:$AD$51,3,FALSE) -> 1.5348837 | I208: 配水・給水設備 | K208: =ROUND(E208*1.5,0) -> 23 | L208: =G208+K208 -> 2026
B209: 22590000 | C209: 管路一式 | D209: =ROUND(B209*H209,0) -> 29818800 | E209: 40 | F209: H27 | G209: =VLOOKUP(F209,Sheet2!$B$2:$C$70,2,FALSE) -> 2015 | H209: =VLOOKUP(G209,$AB$1:$AD$51,3,FALSE) -> 1.32 | I209: 管路 | K209: =ROUND(E209*1.5,0) -> 60 | L209: =G209+K209 -> 2075
B210: 21530000 | C210: 管路一式 | D210: =ROUND(B210*H210,0) -> 28419600 | E210: 40 | F210: H27 | G210: =VLOOKUP(F210,Sheet2!$B$2:$C$70,2,FALSE) -> 2015 | H210: =VLOOKUP(G210,$AB$1:$AD$51,3,FALSE) -> 1.32 | I210: 管路 | K210: =ROUND(E210*1.5,0) -> 60 | L210: =G210+K210 -> 2075
B211: 19700000 | C211: 管路一式 | D211: =ROUND(B211*H211,0) -> 26004000 | E211: 40 | F211: H27 | G211: =VLOOKUP(F211,Sheet2!$B$2:$C$70,2,FALSE) -> 2015 | H211: =VLOOKUP(G211,$AB$1:$AD$51,3,FALSE) -> 1.32 | I211: 管路 | K211: =ROUND(E211*1.5,0) -> 60 | L211: =G211+K211 -> 2075
B212: 21220000 | C212: 管路一式 | D212: =ROUND(B212*H212,0) -> 28010400 | E212: 40 | F212: H27 | G212: =VLOOKUP(F212,Sheet2!$B$2:$C$70,2,FALSE) -> 2015 | H212: =VLOOKUP(G212,$AB$1:$AD$51,3,FALSE) -> 1.32 | I212: 管路 | K212: =ROUND(E212*1.5,0) -> 60 | L212: =G212+K212 -> 2075
B213: 19688482 | C213: 管路一式 | D213: =ROUND(B213*H213,0) -> 25988796 | E213: 40 | F213: H27 | G213: =VLOOKUP(F213,Sheet2!$B$2:$C$70,2,FALSE) -> 2015 | H213: =VLOOKUP(G213,$AB$1:$AD$51,3,FALSE) -> 1.32 | I213: 管路 | K213: =ROUND(E213*1.5,0) -> 60 | L213: =G213+K213 -> 2075
... B280: 43944545 | C280: 膜ろ過設備一式 | D280: =ROUND(B280*H280,0) -> 45638709 | E280: 20 | F280: R5 | G280: =VLOOKUP(F280,Sheet2!$B$2:$C$70,2,FALSE) -> 2023 | H280: =VLOOKUP(G280,$AB$1:$AD$51,3,FALSE) -> 1.0385523 | I280: 配水・給水設備 | K280: =ROUND(E280*1.5,0) -> 30 | L280: =G280+K280 -> 2053

Sheet Sheet1
C1: 資産名称 | D1: 取得価額 | E1: 耐用年数 | F1: 取得年度 | H1: コード | I1: 区分 | J1: 係数 | K1: 限界耐用年数 | L1: 限界年度
C2: 流入ポンプ棟_土木躯体 | D2: 95930106 | E2: 50 | F2: H17 | G2: =VLOOKUP(F2,Sheet2!$B$2:$C$90,2,FALSE) -> 2005 | H2: 610104001000 | I2: 建物 | J2: 1.5 | K2: =ROUND(E2*J2,0) -> 75 | L2: =G2+K2 -> 2080 | N2: 2026 | O2: 2027 | P2: 2028 | Q2: 2029 | R2: 2030 | S2: 2031 | T2: 2032 | U2: 2033 | V2: 2034 | W2: 2035
C3: オキシデーションディッチ_土木躯体 | D3: 127211158 | E3: 50 | F3: H17 | G3: =VLOOKUP(F3,Sheet2!$B$2:$C$90,2,FALSE) -> 2005 | H3: 610104001000 | I3: 建物 | J3: 1.5 | K3: =ROUND(E3*J3,0) -> 75 | L3: =G3+K3 -> 2080 | M3: 建物 | N3: =SUMIFS($D$1:$D$203,$L$1:$L$203,N$2,$I$1:$I$203,$M3) -> 0 | O3: =SUMIFS($D$1:$D$203,$L$1:$L$203,O$2,$I$1:$I$203,$M3) -> 0 | P3: =SUMIFS($D$1:$D$203,$L$1:$L$203,P$2,$I$1:$I$203,$M3) -> 0 | Q3: =SUMIFS($D$1:$D$203,$L$1:$L$203,Q$2,$I$1:$I$203,$M3) -> 0 | R3: =SUMIFS($D$1:$D$203,$L$1:$L$203,R$2,$I$1:$I$203,$M3) -> 0 | S3: =SUMIFS($D$1:$D$203,$L$1:$L$203,S$2,$I$1:$I$203,$M3) -> 0 | T3: =SUMIFS($D$1:$D$203,$L$1:$L$203,T$2,$I$1:$I$203,$M3) -> 0 | U3: =SUMIFS($D$1:$D$203,$L$1:$L$203,U$2,$I$1:$I$203,$M3) -> 0 | ... W3: =SUMIFS($D$1:$D$203,$L$1:$L$203,W$2,$I$1:$I$203,$M3) -> 0
C4: 最終沈殿池_土木躯体 | D4: 63704898 | E4: 50 | F4: H17 | G4: =VLOOKUP(F4,Sheet2!$B$2:$C$90,2,FALSE) -> 2005 | H4: 610104001000 | I4: 建物 | J4: 1.5 | K4: =ROUND(E4*J4,0) -> 75 | L4: =G4+K4 -> 2080 | M4: 処理場設備 | N4: =SUMIFS($D$1:$D$203,$L$1:$L$203,N$2,$I$1:$I$203,$M4) -> 0 | O4: =SUMIFS($D$1:$D$203,$L$1:$L$203,O$2,$I$1:$I$203,$M4) -> 0 | P4: =SUMIFS($D$1:$D$203,$L$1:$L$203,P$2,$I$1:$I$203,$M4) -> 154940800 | Q4: =SUMIFS($D$1:$D$203,$L$1:$L$203,Q$2,$I$1:$I$203,$M4) -> 0 | R4: =SUMIFS($D$1:$D$203,$L$1:$L$203,R$2,$I$1:$I$203,$M4) -> 0 | S4: =SUMIFS($D$1:$D$203,$L$1:$L$203,S$2,$I$1:$I$203,$M4) -> 0 | T4: =SUMIFS($D$1:$D$203,$L$1:$L$203,T$2,$I$1:$I$203,$M4) -> 0 | U4: =SUMIFS($D$1:$D$203,$L$1:$L$203,U$2,$I$1:$I$203,$M4) -> 0 | ... W4: =SUMIFS($D$1:$D$203,$L$1:$L$203,W$2,$I$1:$I$203,$M4) -> 0
C5: 滅菌池_土木躯体 | D5: 21113153 | E5: 50 | F5: H17 | G5: =VLOOKUP(F5,Sheet2!$B$2:$C$90,2,FALSE) -> 2005 | H5: 610104001000 | I5: 建物 | J5: 1.5 | K5: =ROUND(E5*J5,0) -> 75 | L5: =G5+K5 -> 2080 | M5: 処理場機械 | N5: =SUMIFS($D$1:$D$203,$L$1:$L$203,N$2,$I$1:$I$203,$M5) -> 0 | O5: =SUMIFS($D$1:$D$203,$L$1:$L$203,O$2,$I$1:$I$203,$M5) -> 0 | P5: =SUMIFS($D$1:$D$203,$L$1:$L$203,P$2,$I$1:$I$203,$M5) -> 0 | Q5: =SUMIFS($D$1:$D$203,$L$1:$L$203,Q$2,$I$1:$I$203,$M5) -> 0 | R5: =SUMIFS($D$1:$D$203,$L$1:$L$203,R$2,$I$1:$I$203,$M5) -> 0 | S5: =SUMIFS($D$1:$D$203,$L$1:$L$203,S$2,$I$1:$I$203,$M5) -> 0 | T5: =SUMIFS($D$1:$D$203,$L$1:$L$203,T$2,$I$1:$I$203,$M5) -> 0 | U5: =SUMIFS($D$1:$D$203,$L$1:$L$203,U$2,$I$1:$I$203,$M5) -> 0 | ... W5: =SUMIFS($D$1:$D$203,$L$1:$L$203,W$2,$I$1:$I$203,$M5) -> 0
C6: ブロワ室・汚泥ポンプ_土木躯体 | D6: 2552415 | E6: 50 | F6: H17 | G6: =VLOOKUP(F6,Sheet2!$B$2:$C$90,2,FALSE) -> 2005 | H6: 610104001000 | I6: 建物 | J6: 1.5 | K6: =ROUND(E6*J6,0) -> 75 | L6: =G6+K6 -> 2080 | M6: 管渠 | N6: =SUMIFS($D$1:$D$203,$L$1:$L$203,N$2,$I$1:$I$203,$M6) -> 0 | O6: =SUMIFS($D$1:$D$203,$L$1:$L$203,O$2,$I$1:$I$203,$M6) -> 0 | P6: =SUMIFS($D$1:$D$203,$L$1:$L$203,P$2,$I$1:$I$203,$M6) -> 0 | Q6: =SUMIFS($D$1:$D$203,$L$1:$L$203,Q$2,$I$1:$I$203,$M6) -> 0 | R6: =SUMIFS($D$1:$D$203,$L$1:$L$203,R$2,$I$1:$I$203,$M6) -> 0 | S6: =SUMIFS($D$1:$D$203,$L$1:$L$203,S$2,$I$1:$I$203,$M6) -> 0 | T6: =SUMIFS($D$1:$D$203,$L$1:$L$203,T$2,$I$1:$I$203,$M6) -> 0 | U6: =SUMIFS($D$1:$D$203,$L$1:$L$203,U$2,$I$1:$I$203,$M6) -> 0 | ... W6: =SUMIFS($D$1:$D$203,$L$1:$L$203,W$2,$I$1:$I$203,$M6) -> 0
B7: 管理棟 | C7: 管理汚泥棟_土木躯体 | D7: 17729272 | E7: 50 | F7: H17 | G7: =VLOOKUP(F7,Sheet2!$B$2:$C$90,2,FALSE) -> 2005 | H7: 610104001000 | I7: 建物 | J7: 1.5 | K7: =ROUND(E7*J7,0) -> 75 | L7: =G7+K7 -> 2080 | M7: MP | N7: =SUMIFS($D$1:$D$203,$L$1:$L$203,N$2,$I$1:$I$203,$M7) -> 0 | O7: =SUMIFS($D$1:$D$203,$L$1:$L$203,O$2,$I$1:$I$203,$M7) -> 0 | P7: =SUMIFS($D$1:$D$203,$L$1:$L$203,P$2,$I$1:$I$203,$M7) -> 196139904 | Q7: =SUMIFS($D$1:$D$203,$L$1:$L$203,Q$2,$I$1:$I$203,$M7) -> 19468200 | R7: =SUMIFS($D$1:$D$203,$L$1:$L$203,R$2,$I$1:$I$203,$M7) -> 9383952 | S7: =SUMIFS($D$1:$D$203,$L$1:$L$203,S$2,$I$1:$I$203,$M7) -> 12591303 | T7: =SUMIFS($D$1:$D$203,$L$1:$L$203,T$2,$I$1:$I$203,$M7) -> 0 | U7: =SUMIFS($D$1:$D$203,$L$1:$L$203,U$2,$I$1:$I$203,$M7) -> 0 | ... W7: =SUMIFS($D$1:$D$203,$L$1:$L$203,W$2,$I$1:$I$203,$M7) -> 18434564
B8: 管理棟 | C8: 管理汚泥棟_建築躯体 | D8: 281475173 | E8: 50 | F8: H17 | G8: =VLOOKUP(F8,Sheet2!$B$2:$C$90,2,FALSE) -> 2005 | H8: 610102001000 | I8: 建物 | J8: 1.5 | K8: =ROUND(E8*J8,0) -> 75 | L8: =G8+K8 -> 2080
B9: 管理棟 | C9: 管理汚泥等_照明設備 | D9: 21251387 | E9: 15 | F9: H17 | G9: =VLOOKUP(F9,Sheet2!$B$2:$C$90,2,FALSE) -> 2005 | H9: 610102001000 | I9: 処理場設備 | J9: 1.5 | K9: =ROUND(E9*J9,0) -> 23 | L9: =G9+K9 -> 2028 | N9: 2026 | O9: 2027 | P9: 2028 | Q9: 2029 | R9: 2030 | S9: 2031 | T9: 2032 | U9: 2033 | V9: 2034 | W9: 2035
B10: 管理棟 | C10: 管理汚泥等_コンセント設備 | D10: 4368779 | E10: 15 | F10: H17 | G10: =VLOOKUP(F10,Sheet2!$B$2:$C$90,2,FALSE) -> 2005 | H10: 610102001000 | I10: 処理場設備 | J10: 1.5 | K10: =ROUND(E10*J10,0) -> 23 | L10: =G10+K10 -> 2028 | M10: 建物 | N10: =ROUND(N3/1000,0) -> 0 | O10: =ROUND(O3/1000,0) -> 0 | P10: =ROUND(P3/1000,0) -> 0 | Q10: =ROUND(Q3/1000,0) -> 0 | R10: =ROUND(R3/1000,0) -> 0 | S10: =ROUND(S3/1000,0) -> 0 | T10: =ROUND(T3/1000,0) -> 0 | U10: =ROUND(U3/1000,0) -> 0 | ... W10: =ROUND(W3/1000,0) -> 0
B11: 管理棟 | C11: 管理汚泥等_動力設備 | D11: 17233413 | E11: 15 | F11: H17 | G11: =VLOOKUP(F11,Sheet2!$B$2:$C$90,2,FALSE) -> 2005 | H11: 610102001000 | I11: 処理場設備 | J11: 1.5 | K11: =ROUND(E11*J11,0) -> 23 | L11: =G11+K11 -> 2028 | M11: 処理場設備 | N11: =ROUND(N4/1000,0) -> 0 | O11: =ROUND(O4/1000,0) -> 0 | P11: =ROUND(P4/1000,0) -> 154941 | Q11: =ROUND(Q4/1000,0) -> 0 | R11: =ROUND(R4/1000,0) -> 0 | S11: =ROUND(S4/1000,0) -> 0 | T11: =ROUND(T4/1000,0) -> 0 | U11: =ROUND(U4/1000,0) -> 0 | ... W11: =ROUND(W4/1000,0) -> 0
B12: 管理棟 | C12: 管理汚泥等_電話設備 | D12: 1887014 | E12: 15 | F12: H17 | G12: =VLOOKUP(F12,Sheet2!$B$2:$C$90,2,FALSE) -> 2005 | H12: 610102001000 | I12: 処理場設備 | J12: 1.5 | K12: =ROUND(E12*J12,0) -> 23 | L12: =G12+K12 -> 2028 | M12: 処理場機械 | N12: =ROUND(N5/1000,0) -> 0 | O12: =ROUND(O5/1000,0) -> 0 | P12: =ROUND(P5/1000,0) -> 0 | Q12: =ROUND(Q5/1000,0) -> 0 | R12: =ROUND(R5/1000,0) -> 0 | S12: =ROUND(S5/1000,0) -> 0 | T12: =ROUND(T5/1000,0) -> 0 | U12: =ROUND(U5/1000,0) -> 0 | ... W12: =ROUND(W5/1000,0) -> 0
B13: 管理棟 | C13: 管理汚泥等_インターホン設備 | D13: 49953 | E13: 15 | F13: H17 | G13: =VLOOKUP(F13,Sheet2!$B$2:$C$90,2,FALSE) -> 2005 | H13: 610102001000 | I13: 処理場設備 | J13: 1.5 | K13: =ROUND(E13*J13,0) -> 23 | L13: =G13+K13 -> 2028 | M13: 管渠 | N13: =ROUND(N6/1000,0) -> 0 | O13: =ROUND(O6/1000,0) -> 0 | P13: =ROUND(P6/1000,0) -> 0 | Q13: =ROUND(Q6/1000,0) -> 0 | R13: =ROUND(R6/1000,0) -> 0 | S13: =ROUND(S6/1000,0) -> 0 | T13: =ROUND(T6/1000,0) -> 0 | U13: =ROUND(U6/1000,0) -> 0 | ... W13: =ROUND(W6/1000,0) -> 0
B14: 管理棟 | C14: 管理汚泥等_呼出設備 | D14: 345234 | E14: 15 | F14: H17 | G14: =VLOOKUP(F14,Sheet2!$B$2:$C$90,2,FALSE) -> 2005 | H14: 610102001000 | I14: 処理場設備 | J14: 1.5 | K14: =ROUND(E14*J14,0) -> 23 | L14: =G14+K14 -> 2028 | M14: MP | N14: =ROUND(N7/1000,0) -> 0 | O14: =ROUND(O7/1000,0) -> 0 | P14: =ROUND(P7/1000,0) -> 196140 | Q14: =ROUND(Q7/1000,0) -> 19468 | R14: =ROUND(R7/1000,0) -> 9384 | S14: =ROUND(S7/1000,0) -> 12591 | T14: =ROUND(T7/1000,0) -> 0 | U14: =ROUND(U7/1000,0) -> 0 | ... W14: =ROUND(W7/1000,0) -> 18435
B15: 管理棟 | C15: 管理汚泥等_テレビ共同受信設備 | D15: 288940 | E15: 15 | F15: H17 | G15: =VLOOKUP(F15,Sheet2!$B$2:$C$90,2,FALSE) -> 2005 | H15: 610102001000 | I15: 処理場設備 | J15: 1.5 | K15: =ROUND(E15*J15,0) -> 23 | L15: =G15+K15 -> 2028
B16: 管理棟 | C16: 管理汚泥等_防犯設備 | D16: 387964 | E16: 15 | F16: H17 | G16: =VLOOKUP(F16,Sheet2!$B$2:$C$90,2,FALSE) -> 2005 | H16: 610102001000 | I16: 処理場設備 | J16: 1.5 | K16: =ROUND(E16*J16,0) -> 23 | L16: =G16+K16 -> 2028
B17: 管理棟 | C17: 管理汚泥等_火災報知設備 | D17: 8836787 | E17: 15 | F17: H17 | G17: =VLOOKUP(F17,Sheet2!$B$2:$C$90,2,FALSE) -> 2005 | H17: 610102001000 | I17: 処理場設備 | J17: 1.5 | K17: =ROUND(E17*J17,0) -> 23 | L17: =G17+K17 -> 2028
B18: 管理棟 | C18: 管理汚泥等_空調機器設備 | D18: 10724570 | E18: 15 | F18: H17 | G18: =VLOOKUP(F18,Sheet2!$B$2:$C$90,2,FALSE) -> 2005 | H18: 610102001000 | I18: 処理場設備 | J18: 1.5 | K18: =ROUND(E18*J18,0) -> 23 | L18: =G18+K18 -> 2028
B19: 管理棟 | C19: 管理汚泥等_冷媒配管設備 | D19: 551161 | E19: 15 | F19: H17 | G19: =VLOOKUP(F19,Sheet2!$B$2:$C$90,2,FALSE) -> 2005 | H19: 610102001000 | I19: 処理場設備 | J19: 1.5 | K19: =ROUND(E19*J19,0) -> 23 | L19: =G19+K19 -> 2028
B20: 管理棟 | C20: 管理汚泥等_ドレン配管設備 | D20: 598578 | E20: 15 | F20: H17 | G20: =VLOOKUP(F20,Sheet2!$B$2:$C$90,2,FALSE) -> 2005 | H20: 610102001000 | I20: 処理場設備 | J20: 1.5 | K20: =ROUND(E20*J20,0) -> 23 | L20: =G20+K20 -> 2028
B21: 管理棟 | C21: 管理汚泥等_換気機器設備 | D21: 9305431 | E21: 15 | F21: H17 | G21: =VLOOKUP(F21,Sheet2!$B$2:$C$90,2,FALSE) -> 2005 | H21: 610102001000 | I21: 処理場設備 | J21: 1.5 | K21: =ROUND(E21*J21,0) -> 23 | L21: =G21+K21 -> 2028
B22: 管理棟 | C22: 管理汚泥等_換気ダクト設備 | D22: 20457729 | E22: 15 | F22: H17 | G22: =VLOOKUP(F22,Sheet2!$B$2:$C$90,2,FALSE) -> 2005 | H22: 610102001000 | I22: 処理場設備 | J22: 1.5 | K22: =ROUND(E22*J22,0) -> 23 | L22: =G22+K22 -> 2028
B23: 管理棟 | C23: 管理汚泥等_衛生器具設備 | D23: 3125315 | E23: 15 | F23: H17 | G23: =VLOOKUP(F23,Sheet2!$B$2:$C$90,2,FALSE) -> 2005 | H23: 610102001000 | I23: 処理場設備 | J23: 1.5 | K23: =ROUND(E23*J23,0) -> 23 | L23: =G23+K23 -> 2028
B24: 管理棟 | C24: 管理汚泥等_給水設備 | D24: 3008244 | E24: 15 | F24: H17 | G24: =VLOOKUP(F24,Sheet2!$B$2:$C$90,2,FALSE) -> 2005 | H24: 610102001000 | I24: 処理場設備 | J24: 1.5 | K24: =ROUND(E24*J24,0) -> 23 | L24: =G24+K24 -> 2028
B25: 管理棟 | C25: 管理汚泥等_排水設備 | D25: 2494220 | E25: 15 | F25: H17 | G25: =VLOOKUP(F25,Sheet2!$B$2:$C$90,2,FALSE) -> 2005 | H25: 610102001000 | I25: 処理場設備 | J25: 1.5 | K25: =ROUND(E25*J25,0) -> 23 | L25: =G25+K25 -> 2028
B26: 管理棟 | C26: 管理汚泥等_給湯設備 | D26: 1785863 | E26: 15 | F26: H17 | G26: =VLOOKUP(F26,Sheet2!$B$2:$C$90,2,FALSE) -> 2005 | H26: 610102001000 | I26: 処理場設備 | J26: 1.5 | K26: =ROUND(E26*J26,0) -> 23 | L26: =G26+K26 -> 2028
... B68: その他 | C68: 排水設備 | D68: 1795689 | E68: 15 | F68: H17 | G68: =VLOOKUP(F68,Sheet2!$B$2:$C$90,2,FALSE) -> 2005 | H68: 610102001000 | I68: 処理場設備 | J68: 1.5 | K68: =ROUND(E68*J68,0) -> 23 | L68: =G68+K68 -> 2028
C69: 汚水ポンプ | D69: 21647911 | E69: 20 | F69: H17 | G69: =VLOOKUP(F69,Sheet2!$B$2:$C$90,2,FALSE) -> 2005 | H69: 610106002000 | I69: 処理場機械 | J69: 1 | K69: =ROUND(E69*J69,0) -> 20 | L69: =G69+K69 -> 2025
C70: 汚水ポンプ吊上機 | D70: 457414 | E70: 20 | F70: H17 | G70: =VLOOKUP(F70,Sheet2!$B$2:$C$90,2,FALSE) -> 2005 | H70: 610106007000 | I70: 処理場機械 | J70: 1 | K70: =ROUND(E70*J70,0) -> 20 | L70: =G70+K70 -> 2025
C71: スクリーンユニット | D71: 67253448 | E71: 20 | F71: H17 | G71: =VLOOKUP(F71,Sheet2!$B$2:$C$90,2,FALSE) -> 2005 | H71: 610106007000 | I71: 処理場機械 | J71: 1 | K71: =ROUND(E71*J71,0) -> 20 | L71: =G71+K71 -> 2025
C72: 汚水切り替え弁（Φ400） | D72: 2581445 | E72: 20 | F72: H17 | G72: =VLOOKUP(F72,Sheet2!$B$2:$C$90,2,FALSE) -> 2005 | H72: 610106007000 | I72: 処理場機械 | J72: 1 | K72: =ROUND(E72*J72,0) -> 20 | L72: =G72+K72 -> 2025
C73: 分配可動堰 | D73: 4325054 | E73: 20 | F73: H17 | G73: =VLOOKUP(F73,Sheet2!$B$2:$C$90,2,FALSE) -> 2005 | H73: 610106007000 | I73: 処理場機械 | J73: 1 | K73: =ROUND(E73*J73,0) -> 20 | L73: =G73+K73 -> 2025
C74: 汚水切替弁（Φ250） | D74: 1050693 | E74: 20 | F74: H17 | G74: =VLOOKUP(F74,Sheet2!$B$2:$C$90,2,FALSE) -> 2005 | H74: 610106007000 | I74: 処理場機械 | J74: 1 | K74: =ROUND(E74*J74,0) -> 20 | L74: =G74+K74 -> 2025
C75: ディッチ曝気装置 | D75: 126807848 | E75: 20 | F75: H17 | G75: =VLOOKUP(F75,Sheet2!$B$2:$C$90,2,FALSE) -> 2005 | H75: 610106007000 | I75: 処理場機械 | J75: 1 | K75: =ROUND(E75*J75,0) -> 20 | L75: =G75+K75 -> 2025
C76: 送風機吊上機 | D76: 523082 | E76: 20 | F76: H17 | G76: =VLOOKUP(F76,Sheet2!$B$2:$C$90,2,FALSE) -> 2005 | H76: 610106007000 | I76: 処理場機械 | J76: 1 | K76: =ROUND(E76*J76,0) -> 20 | L76: =G76+K76 -> 2025
C77: ディッチ流出可動堰 | D77: 4098611 | E77: 20 | F77: H17 | G77: =VLOOKUP(F77,Sheet2!$B$2:$C$90,2,FALSE) -> 2005 | H77: 610106007000 | I77: 処理場機械 | J77: 1 | K77: =ROUND(E77*J77,0) -> 20 | L77: =G77+K77 -> 2025
C78: ディッチ流出ゲート | D78: 2694666 | E78: 20 | F78: H17 | G78: =VLOOKUP(F78,Sheet2!$B$2:$C$90,2,FALSE) -> 2005 | H78: 610106007000 | I78: 処理場機械 | J78: 1 | K78: =ROUND(E78*J78,0) -> 20 | L78: =G78+K78 -> 2025
C79: ディッチ連絡ゲート | D79: 2694666 | E79: 20 | F79: H17 | G79: =VLOOKUP(F79,Sheet2!$B$2:$C$90,2,FALSE) -> 2005 | H79: 610106007000 | I79: 処理場機械 | J79: 1 | K79: =ROUND(E79*J79,0) -> 20 | L79: =G79+K79 -> 2025
C80: 終沈汚泥掻寄機 | D80: 57742860 | E80: 20 | F80: H17 | G80: =VLOOKUP(F80,Sheet2!$B$2:$C$90,2,FALSE) -> 2005 | H80: 610106007000 | I80: 処理場機械 | J80: 1 | K80: =ROUND(E80*J80,0) -> 20 | L80: =G80+K80 -> 2025
... C203: 管渠一式 | D203: 3120514 | E203: 50 | F203: R3 | G203: =VLOOKUP(F203,Sheet2!$B$2:$C$90,2,FALSE) -> 2021 | H203: 610104002000 | I203: 管渠 | J203: 1.5 | K203: =ROUND(E203*J203,0) -> 75 | L203: =G203+K203 -> 2096
C204: パソコン機器 | D204: 1297965 | E204: 20 | F204: R3 | G204: =VLOOKUP(F204,Sheet2!$B$2:$C$90,2,FALSE) -> 2021 | H204: 610106001000
C205: ソフトウェア | D205: 5015895 | E205: 20 | F205: R3 | G205: =VLOOKUP(F205,Sheet2!$B$2:$C$90,2,FALSE) -> 2021 | H205: 610106001000
C206: 電動ビュレット | D206: 273000 | E206: 15 | F206: H23 | G206: =VLOOKUP(F206,Sheet2!$B$2:$C$90,2,FALSE) -> 2011 | H206: 610110001000
C207: デジタルパックテスト | D207: 173250 | E207: 15 | F207: H23 | G207: =VLOOKUP(F207,Sheet2!$B$2:$C$90,2,FALSE) -> 2011 | H207: 610110001000
C208: 赤外線水分計 | D208: 266700 | E208: 15 | F208: H23 | G208: =VLOOKUP(F208,Sheet2!$B$2:$C$90,2,FALSE) -> 2011 | H208: 610110001000
C209: 発電機 | D209: 115500 | E209: 20 | F209: H25 | G209: =VLOOKUP(F209,Sheet2!$B$2:$C$90,2,FALSE) -> 2013 | H209: 610110001000
C210: ホイキャリア | D210: 165900 | E210: 17 | F210: H25 | G210: =VLOOKUP(F210,Sheet2!$B$2:$C$90,2,FALSE) -> 2013 | H210: 610110001000
C211: 受益者負担金システム | D211: 1467510 | E211: 5 | F211: R3 | G211: =VLOOKUP(F211,Sheet2!$B$2:$C$90,2,FALSE) -> 2021 | H211: 610201000000

Sheet 予測
A1: コード | B1: 市などの別 | C1: 都道府県 | D1: 市区町村 | E1: 総人口（人） | L1: 令和2（2020）年の総人口を100としたときの総人口の指数
E2: 2020年 | F2: 2025年 | G2: 2030年 | H2: 2035年 | I2: 2040年 | J2: 2045年 | K2: 2050年 | L2: 2020年 | M2: 2025年 | N2: 2030年 | O2: 2035年 | P2: 2040年 | Q2: 2045年 | R2: 2050年
A3: 2441 | B3: 3 | C3: 青森県 | D3: 三戸町 | E3: 9082 | F3: 8122 | G3: 7226 | H3: 6371 | I3: 5563 | J3: 4824 | K3: 4143 | L3: 100 | M3: 89.429641 | N3: 79.563973 | O3: 70.149747 | P3: 61.253028 | Q3: 53.116054 | R3: 45.617705
G4: =G3/F3 -> 0.88968234 | H4: =H3/G3 -> 0.88167728
F6: 2025
F7: 8598
F9: 1 | G9: =F9-G4 -> 0.11031766 | H9: =G9/5 -> 0.022063531
F10: 1 | G10: =F10-H4 -> 0.11832272 | H10: =G10/5 -> 0.023664545
F11: 令和7 （2025） | G11: 令和8 （2026） | H11: 令和9 （2027） | I11: 令和10 （2028） | J11: 令和11 （2029） | K11: 令和12 （2030） | L11: 令和13 （2031） | M11: 令和14 （2032） | N11: 令和15 （2033） | O11: 令和16 （2034） | P11: 令和17 （2035）
E12: 総人口(人） | F12: 3846 | G12: 3835 | H12: 3825 | I12: 3814 | J12: 3803 | K12: 3771 | L12: 3757 | M12: 3742 | N12: 3728 | O12: 3713 | P12: 3670
E13: 処理区域人口(人） | F13: 2727 | G13: 2719 | H13: 2712 | I13: 2704 | J13: 2696 | K13: 2674 | L13: 2664 | M13: 2653 | N13: 2643 | O13: 2633 | P13: 2602
E14: 水洗化人口(人） | F14: =ROUND(F13*98.5%,0) -> 2686 | G14: =ROUND(G13*98.5%,0) -> 2678 | H14: =ROUND(H13*98.5%,0) -> 2671 | I14: =ROUND(I13*98.5%,0) -> 2663 | J14: =ROUND(J13*98.5%,0) -> 2656 | K14: =ROUND(K13*98.5%,0) -> 2634 | L14: =ROUND(L13*98.5%,0) -> 2624 | M14: =ROUND(M13*98.5%,0) -> 2613 | ... P14: =ROUND(P13*98.5%,0) -> 2563
F18: 令和7 （2025） | G18: 令和8 （2026） | H18: 令和9 （2027） | I18: 令和10 （2028） | J18: 令和11 （2029） | K18: 令和12 （2030） | L18: 令和13 （2031） | M18: 令和14 （2032） | N18: 令和15 （2033） | O18: 令和16 （2034） | P18: 令和17 （2035）
E19: 一般家庭等 | F19: =ROUND(F14*91.1,0) -> 244695 | G19: =ROUND(G14*91.1,0) -> 243966 | H19: =ROUND(H14*91.1,0) -> 243328 | I19: =ROUND(I14*91.1,0) -> 242599 | J19: =ROUND(J14*91.1,0) -> 241962 | K19: =ROUND(K14*91.1,0) -> 239957 | L19: =ROUND(L14*91.1,0) -> 239046 | M19: =ROUND(M14*91.1,0) -> 238044 | ... P19: =ROUND(P14*91.1,0) -> 233489
E20: 工場排水 | F20: 117600 | G20: 117600 | H20: 117600 | I20: 117600 | J20: 117600 | K20: 117600 | L20: 117600 | M20: 117600 | N20: 117600 | O20: 117600 | P20: 117600
E21: 有収水量（㎥） | F21: =SUM(F19:F20) -> 362295 | G21: =SUM(G19:G20) -> 361566 | H21: =SUM(H19:H20) -> 360928 | I21: =SUM(I19:I20) -> 360199 | J21: =SUM(J19:J20) -> 359562 | K21: =SUM(K19:K20) -> 357557 | L21: =SUM(L19:L20) -> 356646 | M21: =SUM(M19:M20) -> 355644 | ... P21: =SUM(P19:P20) -> 351089
F22: 令和7 （2025） | G22: 令和8 （2026） | H22: 令和9 （2027） | I22: 令和10 （2028） | J22: 令和11 （2029） | K22: 令和12 （2030） | L22: 令和13 （2031） | M22: 令和14 （2032） | N22: 令和15 （2033） | O22: 令和16 （2034） | P22: 令和17 （2035）
E23: 一般家庭等 | F23: =ROUND(F19*170.5/1000,0) -> 41720 | G23: =ROUND(G19*170.5/1000,0) -> 41596 | H23: =ROUND(H19*170.5/1000,0) -> 41487 | I23: =ROUND(I19*170.5/1000,0) -> 41363 | J23: =ROUND(J19*170.5/1000,0) -> 41255 | K23: =ROUND(K19*170.5/1000,0) -> 40913 | L23: =ROUND(L19*170.5/1000,0) -> 40757 | M23: =ROUND(M19*170.5/1000,0) -> 40587 | ... P23: =ROUND(P19*170.5/1000,0) -> 39810
E24: 工場利用 | F24: =ROUND(F20*170.5/1000,0) -> 20051 | G24: =ROUND(G20*170.5/1000,0) -> 20051 | H24: =ROUND(H20*170.5/1000,0) -> 20051 | I24: =ROUND(I20*170.5/1000,0) -> 20051 | J24: =ROUND(J20*170.5/1000,0) -> 20051 | K24: =ROUND(K20*170.5/1000,0) -> 20051 | L24: =ROUND(L20*170.5/1000,0) -> 20051 | M24: =ROUND(M20*170.5/1000,0) -> 20051 | ... P24: =ROUND(P20*170.5/1000,0) -> 20051
E25: 料金収入 | F25: =SUM(F23:F24) -> 61771 | G25: =SUM(G23:G24) -> 61647 | H25: =SUM(H23:H24) -> 61538 | I25: =SUM(I23:I24) -> 61414 | J25: =SUM(J23:J24) -> 61306 | K25: =SUM(K23:K24) -> 60964 | L25: =SUM(L23:L24) -> 60808 | M25: =SUM(M23:M24) -> 60638 | ... P25: =SUM(P23:P24) -> 59861
F29: 令和7 （2025） | G29: 令和8 （2026） | H29: 令和9 （2027） | I29: 令和10 （2028） | J29: 令和11 （2029） | K29: 令和12 （2030） | L29: 令和13 （2031） | M29: 令和14 （2032） | N29: 令和15 （2033） | O29: 令和16 （2034） | P29: 令和17 （2035）
E30: 総人口(人） | F30: =F12 -> 3846 | G30: =G12 -> 3835 | H30: =H12 -> 3825 | I30: =I12 -> 3814 | J30: =J12 -> 3803 | K30: =K12 -> 3771 | L30: =L12 -> 3757 | M30: =M12 -> 3742 | ... O30: =O12 -> 3713
E31: 給水人口（人） | F31: 3803 | G31: 3798 | H31: 3794 | I31: 3790 | J31: 3786 | K31: 3783 | L31: 3779 | M31: 3776 | N31: 3773 | O31: 3771
F35: 令和7 （2025） | G35: 令和8 （2026） | H35: 令和9 （2027） | I35: 令和10 （2028） | J35: 令和11 （2029） | K35: 令和12 （2030） | L35: 令和13 （2031） | M35: 令和14 （2032） | N35: 令和15 （2033） | O35: 令和16 （2034） | P35: 令和17 （2035）
E36: 有収水量（㎥） | F36: =F45*1000 -> 741320 | G36: =G45*1000 -> 740950 | H36: =H45*1000 -> 742610 | I36: =I45*1000 -> 740590 | J36: =J45*1000 -> 740220 | K36: =K45*1000 -> 740220 | L36: =L45*1000 -> 741880 | M36: =M45*1000 -> 739490 | ... O36: =O45*1000 -> 739490
G37: =F36-G36 -> 370 | H37: =G36-H36 -> -1660 | I37: =H36-I36 -> 2020 | J37: =I36-J36 -> 370 | K37: =J36-K36 -> 0 | L37: =K36-L36 -> -1660 | M37: =L36-M36 -> 2390 | N37: =M36-N36 -> 0 | O37: =N36-O36 -> 0
F40: 令和7 （2025） | G40: 令和8 （2026） | H40: 令和9 （2027） | I40: 令和10 （2028） | J40: 令和11 （2029） | K40: 令和12 （2030） | L40: 令和13 （2031） | M40: 令和14 （2032） | N40: 令和15 （2033） | O40: 令和16 （2034） | P40: 令和17 （2035）
E41: 料金収入（千円） | F41: 83606 | G41: 83564 | H41: 83752 | I41: 83524 | J41: 83482 | K41: 83482 | L41: 83669 | M41: 83400 | N41: 83400 | O41: 83400
F45: 741.32 | G45: 740.95 | H45: 742.61 | I45: 740.59 | J45: 740.22 | K45: 740.22 | L45: 741.88 | M45: 739.49 | N45: 739.49 | O45: 739.49

Sheet 下水過去
B2: 平成26年度 (2014) | C2: 平成27年度 (2015) | D2: 平成28年度 (2016) | E2: 平成29年度 (2017) | F2: 平成30年度 (2018) | G2: 令和元年度 （2019） | H2: 令和2年度 （2020） | I2: 令和3年度 （2021） | J2: 令和4年度 （2022） | K2: 令和5年度 （2023） | L2: 令和6年度 （2024） | M2: R7 | N2: R8 | O2: R9 | P2: R10 | Q2: R11 | R2: R12 | S2: R13 | T2: R14 | U2: R15 | V2: R16 | W2: R17 | X2: R18 | Y2: R19
A3: 行政区域内人口 | B3: 11023 | C3: 10763 | D3: 10517 | E3: 10236 | F3: 10027 | G3: 9814 | H3: 9596 | I3: 9353 | J3: 9114 | K3: 8954 | L3: 8699
A4: 処理区域内人口 | B4: 2487 | C4: 2540 | D4: 2601 | E4: 2573 | F4: 2619 | G4: 2581 | H4: 2557 | I4: 2512 | J4: 2453 | K4: 2428 | L4: 2375
A5: 水洗便所設置人口（水洗化人口） | B5: 908 | C5: 949 | D5: 1010 | E5: 1046 | F5: 1128 | G5: 1180 | H5: 1196 | I5: 1201 | J5: 1230 | K5: 1218 | L5: 1236
A6: 年間総処理水量 | B6: 92397 | C6: 92397 | D6: 115147 | E6: 126057 | F6: 123822 | G6: 132480 | H6: 141455 | I6: 139716 | J6: 133569 | K6: 136601 | L6: 143484
A7: 有収水量 | B7: 92397 | C7: 92397 | D7: 109901 | E7: 116363 | F7: 121416 | G7: 129752 | H7: 134144 | I7: 140013 | J7: 131918 | K7: 137673 | L7: 141103
A8: 使用料収入 | B8: 16335000 | C8: 18571000 | D8: 19404000 | E8: 20438000 | F8: 21301000 | G8: 23039000 | H8: 24134000 | I8: 25187000 | J8: 23963000 | K8: 24015000 | L8: 23660000
A9: 有収水量 | B9: 92397 | C9: 92397 | D9: 109901 | E9: 116363 | F9: 121416 | G9: 129752 | H9: 134144 | I9: 140013 | J9: 131918 | K9: 137673 | L9: 141103
A10: 汚水処理費 | B10: 105578000 | C10: 114501000 | D10: 123604000 | E10: 98219000 | F10: 84617000 | G10: 94520000 | H10: 92010000 | I10: 91414000 | J10: 103443000 | K10: 98181000 | L10: 64460000
G12: =G4/G3 -> 0.26299164 | H12: =H4/H3 -> 0.26646519 | I12: =I4/I3 -> 0.26857693 | J12: =J4/J3 -> 0.26914637 | K12: =K4/K3 -> 0.27116373 | L12: =L4/L3 -> 0.27301989 | M12: =L12+$L$14 -> 0.27450087 | N12: =M12+$L$14 -> 0.27598186 | O12: =N12+$L$14 -> 0.27746285 | P12: =O12+$L$14 -> 0.27894383 | Q12: =P12+$L$14 -> 0.28042482 | R12: =Q12+$L$14 -> 0.28190581 | S12: =R12+$L$14 -> 0.28338679 | T12: =S12+$L$14 -> 0.28486778 | ... Z12: =Y12+$L$14 -> 0.2937537
H13: =H5/H4 -> 0.46773563 | I13: =I12-H12 -> 0.0021117334 | J13: =J12-I12 -> 0.00056944104 | K13: =K12-J12 -> 0.0020173575 | L13: =L12-K12 -> 0.0018561616
L14: =AVERAGE(J13:L13) -> 0.0014809867
G16: =G5/G4 -> 0.45718714 | H16: =H5/H4 -> 0.46773563 | I16: =I5/I4 -> 0.4781051 | J16: =J5/J4 -> 0.50142682 | K16: =K5/K4 -> 0.50164745 | L16: =L5/L4 -> 0.52042105 | M16: =L16+$L$18 -> 0.53452637 | N16: =M16+$L$18 -> 0.54863169 | O16: =N16+$L$18 -> 0.56273701 | P16: =O16+$L$18 -> 0.57684233 | Q16: =P16+$L$18 -> 0.59094765 | R16: =Q16+$L$18 -> 0.60505297 | S16: =R16+$L$18 -> 0.61915829 | T16: =S16+$L$18 -> 0.6332636 | ... Y16: =X16+$L$18 -> 0.7037902
H17: =H9/H8 -> 0.0055582995 | I17: =I16-H16 -> 0.010369468 | J17: =J16-I16 -> 0.023321729 | K17: =K16-J16 -> 0.00022062216 | L17: =L16-K16 -> 0.018773606
L18: =AVERAGE(J17:L17) -> 0.014105319
G20: =G7/G5 -> 109.95932 | H20: =H7/H5 -> 112.16054 | I20: =I7/I5 -> 116.58035 | J20: =J7/J5 -> 107.25041 | K20: =K7/K5 -> 113.03202 | L20: =L7/L5 -> 114.161
L21: =AVERAGE(K20:L20) -> 113.59651
L23: =L8/L7 -> 167.67893

Sheet 簡水過去
B1: 平成26年度 (2014) | C1: 平成27年度 (2015) | D1: 平成28年度 (2016) | E1: 平成29年度 (2017) | F1: 平成30年度 (2018) | G1: 令和元年度 （2019） | H1: 令和2年度 （2020） | I1: 令和3年度 （2021） | J1: 令和4年度 （2022） | K1: 令和5年度 （2023） | L1: 令和6年度 （2024）
A2: 行政区域内人口 | B2: 11023 | C2: 10763 | D2: 10517 | E2: 10235 | F2: 10027 | G2: 9814 | H2: 9596 | I2: 9353 | J2: 9114 | K2: 8954 | L2: 8699
A3: 給水人口(人） | B3: 1214 | C3: 1111 | D3: 1101 | E3: 1068 | F3: 1064 | G3: 983 | H3: 1018 | I3: 954 | J3: 959 | K3: 954 | L3: 867
A4: 給水戸数(戸） | G4: 386 | H4: 388 | I4: 384 | J4: 384 | K4: 382 | L4: 380
A5: 年間総配水量 | B5: 101297 | C5: 81334 | D5: 73493 | E5: 76114 | F5: 71592 | G5: 76669 | H5: 74134 | I5: 76664 | J5: 83492 | K5: 66584 | L5: 52420
A6: 有収水量（㎥） | B6: 61696 | C6: 63548 | D6: 57682 | E6: 56577 | F6: 56676 | G6: 58604 | H6: 56491 | I6: 56936 | J6: 54363 | K6: 54695 | L6: 51540
A7: 料金収入 | B7: 13986000 | C7: 14450000 | D7: 13728000 | E7: 13054000 | F7: 13668000 | G7: 14030000 | H7: 14568000 | I7: 13861000 | J7: 13202000 | K7: 12705000 | L7: 11841000
B8: =B3/B2 -> 0.11013336 | C8: =C3/C2 -> 0.10322401 | D8: =D3/D2 -> 0.10468765 | E8: =E3/E2 -> 0.10434783 | F8: =F3/F2 -> 0.10611349 | G8: =G3/G2 -> 0.10016303 | H8: =H3/H2 -> 0.10608587 | I8: =I3/I2 -> 0.10199936 | ... L8: =L3/L2 -> 0.099666628
C12: =B3-C3 -> 103 | D12: =C3-D3 -> 10 | E12: =D3-E3 -> 33 | F12: =E3-F3 -> 4 | G12: =F3-G3 -> 81 | H12: =G3-H3 -> -35 | I12: =H3-I3 -> 64 | J12: =I3-J3 -> -5 | ... L12: =K3-L3 -> 87
C14: =C6*1000/C3 -> 57198.92 | D14: =D6*1000/D3 -> 52390.554 | E14: =E6*1000/E3 -> 52974.719 | F14: =F6*1000/F3 -> 53266.917 | G14: =G6*1000/G3 -> 59617.497 | H14: =H6*1000/H3 -> 55492.141 | I14: =I6*1000/I3 -> 59681.342 | J14: =J6*1000/J3 -> 56687.174 | ... L14: =L6*1000/L3 -> 59446.367 | N14: 51.54 | O14: =N14*1000 -> 51540
L15: =AVERAGE(J14:L14) -> 57821.942
L17: =L7/L6 -> 229.74389

Sheet 【下水道】建設改良費の年度別事業費 (2)
N2: （単位：千円）
E3: 計画年次❶ | F3: ❷ | G3: ❸ | H3: ❹ | I3: ❺ | J3: ❻ | K3: ❼ | L3: ❽ | M3: ❾ | N3: ➓
A4: 内容 年度 | C4: 2023 (令和5) | D4: 2024 (令和6) | E4: 令和7 (2025) | F4: 令和8 (2026) | G4: 令和9 (2027) | H4: 令和10 (2028) | I4: 令和11 (2029) | J4: 令和12 (2030) | K4: 令和13 (2031) | L4: 令和14 (2032) | M4: 令和15 (2033) | N4: 令和16 (2034) | O4: 令和17 (2035) | S4: 令和8 (2026) | T4: 令和9 (2027) | U4: 令和10 (2028) | V4: 令和11 (2029) | W4: 令和12 (2030) | X4: 令和13 (2031) | Y4: 令和14 (2032) | Z4: 令和15 (2033) | AA4: 令和16 (2034) | AB4: 令和17 (2035)
A5: ❶管渠更新 | R5: 事業計画 | T5: 10000
A6: 金額 | E6: 12500 | F6: 0 | G6: 0 | H6: 0 | I6: 11000 | J6: 0 | K6: 0 | L6: 0 | M6: 0 | N6: 11000 | R6: ストマネ計画策て | T6: 16000
A7: ❷マンホールポンプ更新 | R7: 事業計画 | T7: 10000
C8: 18000 | D8: 18000 | R8: ストマネ計画策て | T8: 16000
A9: ❸管路施設・設備長寿命化
A10: 金額
A11: ❷処理場設備等更新
A12: 金額 | C12: 18000 | D12: 18000 | E12: 80600 | F12: 146000 | G12: 749000 | H12: 50000 | I12: 88426 | J12: 50000 | K12: 50000 | L12: 50000 | M12: 50000 | N12: 58426
A13: 内容 年度 | C13: 2023 (令和5) | D13: 2024 (令和6) | E13: 令和7 (2025) | F13: 令和8 (2026) | G13: 令和9 (2027) | H13: 令和10 (2028) | I13: 令和11 (2029) | J13: 令和12 (2030) | K13: 令和13 (2031) | L13: 令和14 (2032) | M13: 令和15 (2033) | N13: 令和16 (2034)
A14: 事業費合計 | C14: =#REF!+#REF!+C12+#REF!+#REF!+#REF!+#REF!+C10+#REF!+C8+C6 -> #REF! | D14: =#REF!+#REF!+D12+#REF!+#REF!+#REF!+#REF!+D10+#REF!+D8+D6 -> #REF! | E14: =E6+E8+E10+E12 -> 93100 | F14: =F6+F8+F10+F12 -> 146000 | G14: =G6+G8+G10+G12 -> 749000 | H14: =H6+H8+H10+H12 -> 50000 | I14: =I6+I8+I10+I12 -> 99426 | J14: =J6+J8+J10+J12 -> 50000 | K14: =K6+K8+K10+K12 -> 50000 | L14: =L6+L8+L10+L12 -> 50000 | ... N14: =N6+N8+N10+N12 -> 69426
A15: 財源内訳
A16: ①国庫補助金
A17: 金額 | E17: =ROUND((E14-E6)*50%,0) -> 40300 | F17: =ROUND((F14-F6)*50%,0) -> 73000 | G17: =ROUND((G14-G6)*50%,0) -> 374500 | H17: =ROUND((H14-H6)*50%,0) -> 25000 | I17: =ROUND((I14-I6)*50%,0) -> 44213 | J17: =ROUND((J14-J6)*50%,0) -> 25000 | K17: =ROUND((K14-K6)*50%,0) -> 25000 | L17: =ROUND((L14-L6)*50%,0) -> 25000 | ... N17: =ROUND((N14-N6)*50%,0) -> 29213
A18: ②受益者負担金
A19: 金額
A20: ②企業債
A21: 金額 | E21: 46550 | F21: 73000 | G21: 374500 | H21: 25000 | I21: 49713 | J21: 25000 | K21: 25000 | L21: 25000 | M21: 25000 | N21: 34713
A22: ③自己財源
A23: 金額 | E23: =E14-E17-E19-E21 -> 6250 | F23: =F14-F17-F19-F21 -> 0 | G23: =G14-G17-G19-G21 -> 0 | H23: =H14-H17-H19-H21 -> 0 | I23: =I14-I17-I19-I21 -> 5500 | J23: =J14-J17-J19-J21 -> 0 | K23: =K14-K17-K19-K21 -> 0 | L23: =L14-L17-L19-L21 -> 0 | ... N23: =N14-N17-N19-N21 -> 5500
A25: 差額 | E25: =E14-E17-E19-E21-E23 -> 0 | F25: =F14-F17-F19-F21-F23 -> 0 | G25: =G14-G17-G19-G21-G23 -> 0 | H25: =H14-H17-H19-H21-H23 -> 0 | I25: =I14-I17-I19-I21-I23 -> 0 | J25: =J14-J17-J19-J21-J23 -> 0 | K25: =K14-K17-K19-K21-K23 -> 0 | L25: =L14-L17-L19-L21-L23 -> 0 | ... N25: =N14-N17-N19-N21-N23 -> 0
A26: [注]
C29: =SUM(C17:C23) -> 0 | D29: =SUM(D17:D23) -> 0 | E29: =SUM(E17:E23) -> 93100 | F29: =SUM(F17:F23) -> 146000 | G29: =SUM(G17:G23) -> 749000 | H29: =SUM(H17:H23) -> 50000 | I29: =SUM(I17:I23) -> 99426 | J29: =SUM(J17:J23) -> 50000 | ... N29: =SUM(N17:N23) -> 69426
C31: =C14-C29 -> #REF! | D31: =D14-D29 -> #REF! | E31: =E14-E29 -> 0 | F31: =F14-F29 -> 0 | G31: =G14-G29 -> 0 | H31: =H14-H29 -> 0 | I31: =I14-I29 -> 0 | J31: =J14-J29 -> 0 | ... N31: =N14-N29 -> 0
C33: =SUM(C17,C19,C23) -> 0 | D33: =SUM(D17,D19,D23) -> 0 | E33: =SUM(E17,E19,E23) -> 46550 | F33: =SUM(F17,F19,F23) -> 73000 | G33: =SUM(G17,G19,G23) -> 374500 | H33: =SUM(H17,H19,H23) -> 25000 | I33: =SUM(I17,I19,I23) -> 49713 | J33: =SUM(J17,J19,J23) -> 25000 | ... N33: =SUM(N17,N19,N23) -> 34713
E37: =#REF!+#REF! -> #REF! | F37: =#REF!+#REF! -> #REF! | G37: =#REF!+#REF! -> #REF! | H37: =#REF!+#REF! -> #REF! | I37: =#REF!+#REF! -> #REF! | J37: =#REF!+#REF! -> #REF! | K37: =#REF!+#REF! -> #REF! | L37: =#REF!+#REF! -> #REF! | ... N37: =#REF!+#REF! -> #REF!
E38: =E14-E37 -> #REF! | F38: =F14-F37 -> #REF! | G38: =G14-G37 -> #REF! | H38: =H14-H37 -> #REF! | I38: =I14-I37 -> #REF! | J38: =J14-J37 -> #REF! | K38: =K14-K37 -> #REF! | L38: =L14-L37 -> #REF! | ... N38: =N14-N37 -> #REF!
F39: 200 | G39: 0.4 | H39: =F39/G39 -> 500
G40: 0.6 | H40: =F39/G40 -> 333.33333
E42: 投資３億円で調整
E46: =ROUND((E6+E8+E10+#REF!+#REF!)*45%,0) -> #REF! | F46: =ROUND((F6+F8+F10+#REF!+#REF!)*45%,0) -> #REF! | G46: =ROUND((G6+G8+G10+#REF!+#REF!)*45%,0) -> #REF! | H46: =ROUND((H6+H8+H10+#REF!+#REF!)*45%,0) -> #REF! | I46: =ROUND((I6+I8+I10+#REF!+#REF!)*45%,0) -> #REF! | J46: =ROUND((J6+J8+J10+#REF!+#REF!)*45%,0) -> #REF! | K46: =ROUND((K6+K8+K10+#REF!+#REF!)*45%,0) -> #REF! | L46: =ROUND((L6+L8+L10+#REF!+#REF!)*45%,0) -> #REF! | ... N46: =ROUND((N6+N8+N10+#REF!+#REF!)*45%,0) -> #REF!

Sheet 下水道現況予測
A1: 3事業合算 | P1: 令和7年度 | Q1: 令和8年度 | R1: 令和9年度 | S1: 令和10年度 | T1: 令和11年度 | U1: 令和12年度 | V1: 令和13年度 | W1: 令和14年度 | X1: 令和15年度 | Y1: 令和16年度 | Z1: 令和17年度 | AA1: 令和18年度 | AB1: 令和19年度 | AC1: 令和20年度 | AD1: 令和21年度 | AE1: 令和22年度 | AF1: 令和23年度 | AG1: 令和24年度 | AH1: 令和25年度 | AI1: 令和26年度 | AJ1: 令和27年度 | AK1: 令和28年度 | AL1: 令和29年度 | AM1: 令和30年度 | AN1: 令和31年度 | AO1: 令和32年度 | AP1: 令和33年度 | AQ1: 令和34年度 | AR1: 令和35年度
P2: 2025 | Q2: 2026 | R2: 2027 | S2: 2028 | T2: 2029 | U2: 2030 | V2: 2031 | W2: 2032 | X2: 2033 | Y2: 2034 | Z2: 2035 | AA2: 2036 | AB2: 2037 | AC2: 2038 | AD2: 2039 | AE2: 2040 | AF2: 2041 | AG2: 2042 | AH2: 2043 | AI2: 2044 | AJ2: 2045 | AK2: 2046 | AL2: 2047 | AM2: 2048 | AN2: 2049 | AO2: 2050 | AP2: 2051 | AQ2: 2052 | AR2: 2053 | AS2: 2055
D3: 普及率 | J3: 10(000)_行政区域内人口 | AT3: =[12]公共下水道事業!AY3 -> 75263
D4: 水洗化率 | J4: 10(000)_処理区域内人口
D5: 有収水量 | J5: 10(000)_水洗化人口
J6: 10(000)_現在処理区域面積
J7: 10(000)_年間総処理水量
J8: 10(000)_年間有収水量
J10: 人口一人当たりの有収水量
J11: 人口一人当たりの使用料（使用料収入÷水洗化人口）
J12: 20㎥あたりの使用料（使用料収入÷年間有収水量×20）
J13: 普及率 | P13: =P5/P3 -> #DIV/0! | Q13: =Q5/Q3 -> #DIV/0! | R13: =R5/R3 -> #DIV/0! | S13: =S5/S3 -> #DIV/0! | T13: =T5/T3 -> #DIV/0! | U13: =U5/U3 -> #DIV/0! | V13: =V5/V3 -> #DIV/0! | W13: =W5/W3 -> #DIV/0! | ... AR13: =AR5/AR3 -> #DIV/0!
J14: 水洗化率 | P14: =AVERAGE($K$14:$M$14) -> #DIV/0! | Q14: =AVERAGE($K$14:$M$14) -> #DIV/0! | R14: =AVERAGE($K$14:$M$14) -> #DIV/0! | S14: =AVERAGE($K$14:$M$14) -> #DIV/0! | T14: =AVERAGE($K$14:$M$14) -> #DIV/0! | U14: =AVERAGE($K$14:$M$14) -> #DIV/0! | V14: =AVERAGE($K$14:$M$14) -> #DIV/0! | W14: =AVERAGE($K$14:$M$14) -> #DIV/0! | ... AR14: =AVERAGE($K$14:$M$14) -> #DIV/0!
J16: 汚水処理費（A） | P16: =ROUND(P53*$AT$21,0) -> 109223 | Q16: =ROUND(Q53*$AT$21,0) -> 109886 | R16: =ROUND(R53*$AT$21,0) -> 111329 | S16: =ROUND(S53*$AT$21,0)-15000 -> 117988 | T16: =ROUND(T53*$AT$21,0)-16000 -> 117748 | U16: =ROUND(U53*$AT$21,0)-17000 -> 118784 | V16: =ROUND(V53*$AT$21,0)-18000 -> 119166 | W16: =ROUND(W53*$AT$21,0)-19000 -> 119595 | X16: =ROUND(X53*$AT$21,0)-20000 -> 119785 | Y16: =ROUND(Y53*$AT$21,0)-21000 -> 118804 | Z16: =[12]公共下水道事業!AE16+#REF!+[12]農業集落排水事業!AE16 -> #REF! | AA16: =[12]公共下水道事業!AF16+#REF!+[12]農業集落排水事業!AF16 -> #REF! | AB16: =[12]公共下水道事業!AG16+#REF!+[12]農業集落排水事業!AG16 -> #REF! | AC16: =[12]公共下水道事業!AH16+#REF!+[12]農業集落排水事業!AH16 -> #REF! | AD16: =[12]公共下水道事業!AI16+#REF!+[12]農業集落排水事業!AI16 -> #REF! | AE16: =[12]公共下水道事業!AJ16+#REF!+[12]農業集落排水事業!AJ16 -> #REF! | AF16: =[12]公共下水道事業!AK16+#REF!+[12]農業集落排水事業!AK16 -> #REF! | AG16: =[12]公共下水道事業!AL16+#REF!+[12]農業集落排水事業!AL16 -> #REF! | ... AR16: =[12]公共下水道事業!AW16+#REF!+[12]農業集落排水事業!AW16 -> #REF!
J17: 使用料収入（B） | P17: =P28 -> 61771 | Q17: =Q28 -> 61647 | R17: =R28 -> 61538 | S17: =S28 -> 61414 | T17: =T28 -> 61306 | U17: =U28 -> 60964 | V17: =V28 -> 60808 | W17: =W28 -> 60638 | ... Y17: =Y28 -> 60342 | Z17: =[12]公共下水道事業!AE19+#REF!+[12]農業集落排水事業!AE19 -> #REF! | AA17: =[12]公共下水道事業!AF19+#REF!+[12]農業集落排水事業!AF19 -> #REF! | AB17: =[12]公共下水道事業!AG19+#REF!+[12]農業集落排水事業!AG19 -> #REF! | AC17: =[12]公共下水道事業!AH19+#REF!+[12]農業集落排水事業!AH19 -> #REF! | AD17: =[12]公共下水道事業!AI19+#REF!+[12]農業集落排水事業!AI19 -> #REF! | AE17: =[12]公共下水道事業!AJ19+#REF!+[12]農業集落排水事業!AJ19 -> #REF! | AF17: =[12]公共下水道事業!AK19+#REF!+[12]農業集落排水事業!AK19 -> #REF! | AG17: =[12]公共下水道事業!AL19+#REF!+[12]農業集落排水事業!AL19 -> #REF! | ... AR17: =[12]公共下水道事業!AW19+#REF!+[12]農業集落排水事業!AW19 -> #REF!
J18: 経費回収率（B÷A） | P18: =P17/P16 -> 0.56554938 | Q18: =Q17/Q16 -> 0.56100868 | R18: =R17/R16 -> 0.55275804 | S18: =S17/S16 -> 0.52051056 | T18: =T17/T16 -> 0.52065428 | U18: =U17/U16 -> 0.51323411 | V18: =V17/V16 -> 0.51027978 | W18: =W17/W16 -> 0.50702789 | ... AR18: =AR17/AR16 -> #REF!
J19: 有収水量（C） | P19: =予測!F21 -> 362295 | Q19: =予測!G21 -> 361566 | R19: =予測!H21 -> 360928 | S19: =予測!I21 -> 360199 | T19: =予測!J21 -> 359562 | U19: =予測!K21 -> 357557 | V19: =予測!L21 -> 356646 | W19: =予測!M21 -> 355644 | ... Y19: =予測!O21 -> 353913 | Z19: =Z8 -> 0 | AA19: =AA8 -> 0 | AB19: =AB8 -> 0 | AC19: =AC8 -> 0 | AD19: =AD8 -> 0 | AE19: =AE8 -> 0 | AF19: =AF8 -> 0 | AG19: =AG8 -> 0 | ... AR19: =AR8 -> 0 | AT19: 109686
J20: 汚水処理原価（A÷C） | P20: =P16/P19*1000 -> 301.47532 | Q20: =Q16/Q19*1000 -> 303.91685 | R20: =R16/R19*1000 -> 308.4521 | S20: =S16/S19*1000 -> 327.56337 | T20: =T16/T19*1000 -> 327.47621 | U20: =U16/U19*1000 -> 332.20997 | V20: =V16/V19*1000 -> 334.12964 | W20: =W16/W19*1000 -> 336.27729 | ... AR20: =AR16/AR19*1000 -> #REF! | AT20: 175739
J21: 経常収支比率 | P21: =P37/P53 -> 1.0950931 | Q21: =Q37/Q53 -> 1.0762415 | R21: =R37/R53 -> 1.0577672 | S21: =S37/S53 -> 1.0340306 | T21: =T37/T53 -> 1.0200102 | U21: =U37/U53 -> 1.0053412 | V21: =V37/V53 -> 0.99220542 | W21: =W37/W53 -> 0.97954579 | ... AR21: =AR37/AR53 -> #REF! | AT21: =AT19/AT20 -> 0.62414148
P23: =P49-P35+P51 -> 47112 | Q23: =Q49-Q35+Q51 -> 44631 | R23: =R49-R35+R51 -> 41592 | S23: =S49-S35+S51 -> 60280 | T23: =T49-T35+T51 -> 58152 | U23: =U49-U35+U51 -> 59445 | V23: =V49-V35+V51 -> 60068 | W23: =W49-W35+W51 -> 60745 | ... Y23: =Y49-Y35+Y51 -> 60864
J24: 3条
I25: 年 度 | P25: 令和7年度 | Q25: 令和8年度 | R25: 令和9年度 | S25: 令和10年度 | T25: 令和11年度 | U25: 令和12年度 | V25: 令和13年度 | W25: 令和14年度 | X25: 令和15年度 | Y25: 令和16年度 | Z25: 令和17年度 | AA25: 令和18年度 | AB25: 令和19年度 | AC25: 令和20年度 | AD25: 令和21年度 | AE25: 令和22年度 | AF25: 令和23年度 | AG25: 令和24年度 | AH25: 令和25年度 | AI25: 令和26年度 | AJ25: 令和27年度 | AK25: 令和28年度 | AL25: 令和29年度 | AM25: 令和30年度 | AN25: 令和31年度 | AO25: 令和32年度 | AP25: 令和33年度 | AQ25: 令和34年度 | AR25: 令和35年度
C26: 区 分 | P26: 2025 | Q26: 2026 | R26: 2027 | S26: 2028 | T26: 2029 | U26: 2030 | V26: 2031 | W26: 2032 | X26: 2033 | Y26: 2034 | Z26: 2035 | AA26: 2036 | AB26: 2037 | AC26: 2038 | AD26: 2039 | AE26: 2040 | AF26: 2041 | AG26: 2042 | AH26: 2043 | AI26: 2044 | AJ26: 2045 | AK26: 2046 | AL26: 2047 | AM26: 2048 | AN26: 2049 | AO26: 2050 | AP26: 2051 | AQ26: 2052 | AR26: 2053
B27: 収益的収支 | C27: 収益的収入 | D27: １． | E27: 営業収益 | J27: (A) | P27: =SUM(P28:P30) -> 61841 | Q27: =SUM(Q28:Q30) -> 61717 | R27: =SUM(R28:R30) -> 61608 | S27: =SUM(S28:S30) -> 61484 | T27: =SUM(T28:T30) -> 61376 | U27: =SUM(U28:U30) -> 61034 | V27: =SUM(V28:V30) -> 60878 | W27: =SUM(W28:W30) -> 60708 | ... AR27: =SUM(AR28:AR30) -> #REF!
D28: (1) | F28: 使用料収入 | P28: =予測!F25 -> 61771 | Q28: =予測!G25 -> 61647 | R28: =予測!H25 -> 61538 | S28: =予測!I25 -> 61414 | T28: =予測!J25 -> 61306 | U28: =予測!K25 -> 60964 | V28: =予測!L25 -> 60808 | W28: =予測!M25 -> 60638 | ... Y28: =予測!O25 -> 60342 | Z28: =[12]公共下水道事業!AE30+#REF!+[12]農業集落排水事業!AE30 -> #REF! | AA28: =[12]公共下水道事業!AF30+#REF!+[12]農業集落排水事業!AF30 -> #REF! | AB28: =[12]公共下水道事業!AG30+#REF!+[12]農業集落排水事業!AG30 -> #REF! | AC28: =[12]公共下水道事業!AH30+#REF!+[12]農業集落排水事業!AH30 -> #REF! | AD28: =[12]公共下水道事業!AI30+#REF!+[12]農業集落排水事業!AI30 -> #REF! | AE28: =[12]公共下水道事業!AJ30+#REF!+[12]農業集落排水事業!AJ30 -> #REF! | AF28: =[12]公共下水道事業!AK30+#REF!+[12]農業集落排水事業!AK30 -> #REF! | AG28: =[12]公共下水道事業!AL30+#REF!+[12]農業集落排水事業!AL30 -> #REF! | ... AR28: =[12]公共下水道事業!AW30+#REF!+[12]農業集落排水事業!AW30 -> #REF!
D29: (2) | F29: 雨水処理負担金 | P29: 0 | Q29: 0 | R29: 0 | S29: 0 | T29: 0 | U29: 0 | V29: 0 | W29: 0 | X29: 0 | Y29: 0 | Z29: =[12]公共下水道事業!AE31+#REF!+[12]農業集落排水事業!AE31 -> #REF! | AA29: =[12]公共下水道事業!AF31+#REF!+[12]農業集落排水事業!AF31 -> #REF! | AB29: =[12]公共下水道事業!AG31+#REF!+[12]農業集落排水事業!AG31 -> #REF! | AC29: =[12]公共下水道事業!AH31+#REF!+[12]農業集落排水事業!AH31 -> #REF! | AD29: =[12]公共下水道事業!AI31+#REF!+[12]農業集落排水事業!AI31 -> #REF! | AE29: =[12]公共下水道事業!AJ31+#REF!+[12]農業集落排水事業!AJ31 -> #REF! | AF29: =[12]公共下水道事業!AK31+#REF!+[12]農業集落排水事業!AK31 -> #REF! | AG29: =[12]公共下水道事業!AL31+#REF!+[12]農業集落排水事業!AL31 -> #REF! | ... AR29: =[12]公共下水道事業!AW31+#REF!+[12]農業集落排水事業!AW31 -> #REF!
D30: (3) | F30: その他 | P30: 70 | Q30: =P30 -> 70 | R30: =Q30 -> 70 | S30: =R30 -> 70 | T30: =S30 -> 70 | U30: =T30 -> 70 | V30: =U30 -> 70 | W30: =V30 -> 70 | X30: =W30 -> 70 | Y30: =X30 -> 70 | Z30: =[12]公共下水道事業!AE32+#REF!+[12]農業集落排水事業!AE32 -> #REF! | AA30: =[12]公共下水道事業!AF32+#REF!+[12]農業集落排水事業!AF32 -> #REF! | AB30: =[12]公共下水道事業!AG32+#REF!+[12]農業集落排水事業!AG32 -> #REF! | AC30: =[12]公共下水道事業!AH32+#REF!+[12]農業集落排水事業!AH32 -> #REF! | AD30: =[12]公共下水道事業!AI32+#REF!+[12]農業集落排水事業!AI32 -> #REF! | AE30: =[12]公共下水道事業!AJ32+#REF!+[12]農業集落排水事業!AJ32 -> #REF! | AF30: =[12]公共下水道事業!AK32+#REF!+[12]農業集落排水事業!AK32 -> #REF! | AG30: =[12]公共下水道事業!AL32+#REF!+[12]農業集落排水事業!AL32 -> #REF! | ... AR30: =[12]公共下水道事業!AW32+#REF!+[12]農業集落排水事業!AW32 -> #REF!
D31: ２． | E31: 営業外収益 | P31: =P32+P35+P36 -> 129797 | Q31: =Q32+Q35+Q36 -> 127765 | R31: =R32+R35+R36 -> 127067 | S31: =S32+S35+S36 -> 158840 | T31: =T32+T35+T36 -> 157203 | U31: =U32+U35+U36 -> 157681 | V31: =V32+V35+V36 -> 157177 | W31: =W32+W35+W36 -> 156807 | ... Y31: =Y32+Y35+Y36 -> 153591 | Z31: =[12]公共下水道事業!AE33+#REF!+[12]農業集落排水事業!AE33 -> #REF! | AA31: =[12]公共下水道事業!AF33+#REF!+[12]農業集落排水事業!AF33 -> #REF! | AB31: =[12]公共下水道事業!AG33+#REF!+[12]農業集落排水事業!AG33 -> #REF! | AC31: =[12]公共下水道事業!AH33+#REF!+[12]農業集落排水事業!AH33 -> #REF! | AD31: =[12]公共下水道事業!AI33+#REF!+[12]農業集落排水事業!AI33 -> #REF! | AE31: =[12]公共下水道事業!AJ33+#REF!+[12]農業集落排水事業!AJ33 -> #REF! | AF31: =[12]公共下水道事業!AK33+#REF!+[12]農業集落排水事業!AK33 -> #REF! | AG31: =[12]公共下水道事業!AL33+#REF!+[12]農業集落排水事業!AL33 -> #REF! | ... AR31: =[12]公共下水道事業!AW33+#REF!+[12]農業集落排水事業!AW33 -> #REF!
D32: (1) | F32: 補助金 | P32: =P33+P34 -> 88514 | Q32: =Q33+Q34 -> 83963 | R32: =R33+R34 -> 78957 | S32: =S33+S34 -> 95777 | T32: =T33+T34 -> 91874 | U32: =U33+U34 -> 91481 | V32: =V33+V34 -> 90502 | W32: =W33+W34 -> 89657 | ... Y32: =Y33+Y34 -> 86957 | Z32: =[12]公共下水道事業!AE34+#REF!+[12]農業集落排水事業!AE34 -> #REF! | AA32: =[12]公共下水道事業!AF34+#REF!+[12]農業集落排水事業!AF34 -> #REF! | AB32: =[12]公共下水道事業!AG34+#REF!+[12]農業集落排水事業!AG34 -> #REF! | AC32: =[12]公共下水道事業!AH34+#REF!+[12]農業集落排水事業!AH34 -> #REF! | AD32: =[12]公共下水道事業!AI34+#REF!+[12]農業集落排水事業!AI34 -> #REF! | AE32: =[12]公共下水道事業!AJ34+#REF!+[12]農業集落排水事業!AJ34 -> #REF! | AF32: =[12]公共下水道事業!AK34+#REF!+[12]農業集落排水事業!AK34 -> #REF! | AG32: =[12]公共下水道事業!AL34+#REF!+[12]農業集落排水事業!AL34 -> #REF! | ... AR32: =[12]公共下水道事業!AW34+#REF!+[12]農業集落排水事業!AW34 -> #REF!
G33: 他会計補助金 | P33: 88514 | Q33: =Q101 -> 83963 | R33: =R101 -> 78957 | S33: =S101 -> 95777 | T33: =T101 -> 91874 | U33: =U101 -> 91481 | V33: =V101 -> 90502 | W33: =W101 -> 89657 | X33: =X101 -> 88778 | Y33: =Y101 -> 86957 | Z33: =[12]公共下水道事業!AE35+#REF!+[12]農業集落排水事業!AE35 -> #REF! | AA33: =[12]公共下水道事業!AF35+#REF!+[12]農業集落排水事業!AF35 -> #REF! | AB33: =[12]公共下水道事業!AG35+#REF!+[12]農業集落排水事業!AG35 -> #REF! | AC33: =[12]公共下水道事業!AH35+#REF!+[12]農業集落排水事業!AH35 -> #REF! | AD33: =[12]公共下水道事業!AI35+#REF!+[12]農業集落排水事業!AI35 -> #REF! | AE33: =[12]公共下水道事業!AJ35+#REF!+[12]農業集落排水事業!AJ35 -> #REF! | AF33: =[12]公共下水道事業!AK35+#REF!+[12]農業集落排水事業!AK35 -> #REF! | AG33: =[12]公共下水道事業!AL35+#REF!+[12]農業集落排水事業!AL35 -> #REF! | ... AR33: =[12]公共下水道事業!AW35+#REF!+[12]農業集落排水事業!AW35 -> #REF!
G34: その他補助金 | Z34: =[12]公共下水道事業!AE36+#REF!+[12]農業集落排水事業!AE36 -> #REF! | AA34: =[12]公共下水道事業!AF36+#REF!+[12]農業集落排水事業!AF36 -> #REF! | AB34: =[12]公共下水道事業!AG36+#REF!+[12]農業集落排水事業!AG36 -> #REF! | AC34: =[12]公共下水道事業!AH36+#REF!+[12]農業集落排水事業!AH36 -> #REF! | AD34: =[12]公共下水道事業!AI36+#REF!+[12]農業集落排水事業!AI36 -> #REF! | AE34: =[12]公共下水道事業!AJ36+#REF!+[12]農業集落排水事業!AJ36 -> #REF! | AF34: =[12]公共下水道事業!AK36+#REF!+[12]農業集落排水事業!AK36 -> #REF! | AG34: =[12]公共下水道事業!AL36+#REF!+[12]農業集落排水事業!AL36 -> #REF! | ... AR34: =[12]公共下水道事業!AW36+#REF!+[12]農業集落排水事業!AW36 -> #REF!
D35: (2) | F35: 長期前受金戻入 | P35: 41283 | Q35: 43802 | R35: 48110 | S35: 63063 | T35: 65329 | U35: 66200 | V35: 66675 | W35: 67150 | X35: 67333 | Y35: 66634 | Z35: =[12]公共下水道事業!AE37+#REF!+[12]農業集落排水事業!AE37 -> #REF! | AA35: =[12]公共下水道事業!AF37+#REF!+[12]農業集落排水事業!AF37 -> #REF! | AB35: =[12]公共下水道事業!AG37+#REF!+[12]農業集落排水事業!AG37 -> #REF! | AC35: =[12]公共下水道事業!AH37+#REF!+[12]農業集落排水事業!AH37 -> #REF! | AD35: =[12]公共下水道事業!AI37+#REF!+[12]農業集落排水事業!AI37 -> #REF! | AE35: =[12]公共下水道事業!AJ37+#REF!+[12]農業集落排水事業!AJ37 -> #REF! | AF35: =[12]公共下水道事業!AK37+#REF!+[12]農業集落排水事業!AK37 -> #REF! | AG35: =[12]公共下水道事業!AL37+#REF!+[12]農業集落排水事業!AL37 -> #REF! | ... AR35: =[12]公共下水道事業!AW37+#REF!+[12]農業集落排水事業!AW37 -> #REF!
D36: (3) | F36: その他 | Z36: =[12]公共下水道事業!AE38+#REF!+[12]農業集落排水事業!AE38 -> #REF! | AA36: =[12]公共下水道事業!AF38+#REF!+[12]農業集落排水事業!AF38 -> #REF! | AB36: =[12]公共下水道事業!AG38+#REF!+[12]農業集落排水事業!AG38 -> #REF! | AC36: =[12]公共下水道事業!AH38+#REF!+[12]農業集落排水事業!AH38 -> #REF! | AD36: =[12]公共下水道事業!AI38+#REF!+[12]農業集落排水事業!AI38 -> #REF! | AE36: =[12]公共下水道事業!AJ38+#REF!+[12]農業集落排水事業!AJ38 -> #REF! | AF36: =[12]公共下水道事業!AK38+#REF!+[12]農業集落排水事業!AK38 -> #REF! | AG36: =[12]公共下水道事業!AL38+#REF!+[12]農業集落排水事業!AL38 -> #REF! | ... AR36: =[12]公共下水道事業!AW38+#REF!+[12]農業集落排水事業!AW38 -> #REF! | AU36: 3141
D37: 収入計 | J37: (C) | P37: =P27+P31 -> 191638 | Q37: =Q27+Q31 -> 189482 | R37: =R27+R31 -> 188675 | S37: =S27+S31 -> 220324 | T37: =T27+T31 -> 218579 | U37: =U27+U31 -> 218715 | V37: =V27+V31 -> 218055 | W37: =W27+W31 -> 217515 | ... AR37: =AR27+AR31 -> #REF! | AU37: 1470
C38: 収益的支出 | D38: １． | E38: 営業費用 | P38: =P39+P43+P49+P48 -> 168673 | Q38: =Q39+Q43+Q49+Q48 -> 172354 | R38: =R39+R43+R49+R48 -> 173423 | S38: =S39+S43+S49+S48 -> 200775 | T38: =T39+T43+T49+T48 -> 201841 | U38: =U39+U43+U49+U48 -> 204321 | V38: =V39+V43+V49+V48 -> 206266 | W38: =W39+W43+W49+W48 -> 208243 | ... Y38: =Y39+Y43+Y49+Y48 -> 209822 | Z38: =Z39+Z43+Z49 -> #REF! | AA38: =AA39+AA43+AA49 -> #REF! | AB38: =AB39+AB43+AB49 -> #REF! | AC38: =AC39+AC43+AC49 -> #REF! | AD38: =AD39+AD43+AD49 -> #REF! | AE38: =AE39+AE43+AE49 -> #REF! | AF38: =AF39+AF43+AF49 -> #REF! | AG38: =AG39+AG43+AG49 -> #REF! | ... AR38: =AR39+AR43+AR49 -> #REF! | AU38: =SUM(AU36:AU37) -> 4611
D39: (1) | F39: 職員給与費 | P39: =SUM(P40:P42) -> 9533 | Q39: =SUM(Q40:Q42) -> 9819 | R39: =SUM(R40:R42) -> 10114 | S39: =SUM(S40:S42) -> 10417 | T39: =SUM(T40:T42) -> 10730 | U39: =SUM(U40:U42) -> 11052 | V39: =SUM(V40:V42) -> 11383 | W39: =SUM(W40:W42) -> 11724 | ... AR39: =SUM(AR40:AR42) -> #REF!
G40: 基本給 | P40: =ROUND(4645*1.03,0) -> 4784 | Q40: =ROUND(P40*1.03,0) -> 4928 | R40: =ROUND(Q40*1.03,0) -> 5076 | S40: =ROUND(R40*1.03,0) -> 5228 | T40: =ROUND(S40*1.03,0) -> 5385 | U40: =ROUND(T40*1.03,0) -> 5547 | V40: =ROUND(U40*1.03,0) -> 5713 | W40: =ROUND(V40*1.03,0) -> 5884 | X40: =ROUND(W40*1.03,0) -> 6061 | Y40: =ROUND(X40*1.03,0) -> 6243 | Z40: =[12]公共下水道事業!AE42+#REF!+[12]農業集落排水事業!AE42 -> #REF! | AA40: =[12]公共下水道事業!AF42+#REF!+[12]農業集落排水事業!AF42 -> #REF! | AB40: =[12]公共下水道事業!AG42+#REF!+[12]農業集落排水事業!AG42 -> #REF! | AC40: =[12]公共下水道事業!AH42+#REF!+[12]農業集落排水事業!AH42 -> #REF! | AD40: =[12]公共下水道事業!AI42+#REF!+[12]農業集落排水事業!AI42 -> #REF! | AE40: =[12]公共下水道事業!AJ42+#REF!+[12]農業集落排水事業!AJ42 -> #REF! | AF40: =[12]公共下水道事業!AK42+#REF!+[12]農業集落排水事業!AK42 -> #REF! | AG40: =[12]公共下水道事業!AL42+#REF!+[12]農業集落排水事業!AL42 -> #REF! | ... AR40: =[12]公共下水道事業!AW42+#REF!+[12]農業集落排水事業!AW42 -> #REF!
G41: 退職給付費 | Z41: =[12]公共下水道事業!AE43+#REF!+[12]農業集落排水事業!AE43 -> #REF! | AA41: =[12]公共下水道事業!AF43+#REF!+[12]農業集落排水事業!AF43 -> #REF! | AB41: =[12]公共下水道事業!AG43+#REF!+[12]農業集落排水事業!AG43 -> #REF! | AC41: =[12]公共下水道事業!AH43+#REF!+[12]農業集落排水事業!AH43 -> #REF! | AD41: =[12]公共下水道事業!AI43+#REF!+[12]農業集落排水事業!AI43 -> #REF! | AE41: =[12]公共下水道事業!AJ43+#REF!+[12]農業集落排水事業!AJ43 -> #REF! | AF41: =[12]公共下水道事業!AK43+#REF!+[12]農業集落排水事業!AK43 -> #REF! | AG41: =[12]公共下水道事業!AL43+#REF!+[12]農業集落排水事業!AL43 -> #REF! | ... AR41: =[12]公共下水道事業!AW43+#REF!+[12]農業集落排水事業!AW43 -> #REF!
G42: その他 | P42: =ROUND(4611*1.03,0) -> 4749 | Q42: =ROUND(P42*1.03,0) -> 4891 | R42: =ROUND(Q42*1.03,0) -> 5038 | S42: =ROUND(R42*1.03,0) -> 5189 | T42: =ROUND(S42*1.03,0) -> 5345 | U42: =ROUND(T42*1.03,0) -> 5505 | V42: =ROUND(U42*1.03,0) -> 5670 | W42: =ROUND(V42*1.03,0) -> 5840 | X42: =ROUND(W42*1.03,0) -> 6015 | Y42: =ROUND(X42*1.03,0) -> 6195 | Z42: =[12]公共下水道事業!AE44+#REF!+[12]農業集落排水事業!AE44 -> #REF! | AA42: =[12]公共下水道事業!AF44+#REF!+[12]農業集落排水事業!AF44 -> #REF! | AB42: =[12]公共下水道事業!AG44+#REF!+[12]農業集落排水事業!AG44 -> #REF! | AC42: =[12]公共下水道事業!AH44+#REF!+[12]農業集落排水事業!AH44 -> #REF! | AD42: =[12]公共下水道事業!AI44+#REF!+[12]農業集落排水事業!AI44 -> #REF! | AE42: =[12]公共下水道事業!AJ44+#REF!+[12]農業集落排水事業!AJ44 -> #REF! | AF42: =[12]公共下水道事業!AK44+#REF!+[12]農業集落排水事業!AK44 -> #REF! | AG42: =[12]公共下水道事業!AL44+#REF!+[12]農業集落排水事業!AL44 -> #REF! | ... AR42: =[12]公共下水道事業!AW44+#REF!+[12]農業集落排水事業!AW44 -> #REF! | AU42: 0.02
D43: (2) | F43: 経費 | P43: =SUM(P44:P47) -> 76391 | Q43: =SUM(Q44:Q47) -> 77129 | R43: =SUM(R44:R47) -> 77877 | S43: =SUM(S44:S47) -> 78635 | T43: =SUM(T44:T47) -> 79402 | U43: =SUM(U44:U47) -> 80178 | V43: =SUM(V44:V47) -> 80964 | W43: =SUM(W44:W47) -> 81760 | ... AR43: =SUM(AR44:AR47) -> #REF! | AU43: 0/%
G44: 動力費 | P44: =ROUND(AS44*(1+AU44),0) -> 11470 | Q44: =ROUND(P44*(1+$AU44),0) -> 11504 | R44: =ROUND(Q44*(1+$AU44),0) -> 11539 | S44: =ROUND(R44*(1+$AU44),0) -> 11574 | T44: =ROUND(S44*(1+$AU44),0) -> 11609 | U44: =ROUND(T44*(1+$AU44),0) -> 11644 | V44: =ROUND(U44*(1+$AU44),0) -> 11679 | W44: =ROUND(V44*(1+$AU44),0) -> 11714 | X44: =ROUND(W44*(1+$AU44),0) -> 11749 | Y44: =ROUND(X44*(1+$AU44),0) -> 11784 | Z44: =[12]公共下水道事業!AE46+#REF!+[12]農業集落排水事業!AE46 -> #REF! | AA44: =[12]公共下水道事業!AF46+#REF!+[12]農業集落排水事業!AF46 -> #REF! | AB44: =[12]公共下水道事業!AG46+#REF!+[12]農業集落排水事業!AG46 -> #REF! | AC44: =[12]公共下水道事業!AH46+#REF!+[12]農業集落排水事業!AH46 -> #REF! | AD44: =[12]公共下水道事業!AI46+#REF!+[12]農業集落排水事業!AI46 -> #REF! | AE44: =[12]公共下水道事業!AJ46+#REF!+[12]農業集落排水事業!AJ46 -> #REF! | AF44: =[12]公共下水道事業!AK46+#REF!+[12]農業集落排水事業!AK46 -> #REF! | AG44: =[12]公共下水道事業!AL46+#REF!+[12]農業集落排水事業!AL46 -> #REF! | ... AR44: =[12]公共下水道事業!AW46+#REF!+[12]農業集落排水事業!AW46 -> #REF! | AS44: 11436 | AT44: =ROUND(AS44/$AS$48,4) -> 0.1511 | AU44: =ROUND($AU$42*AT44,4) -> 0.003 | AY44: 245208
G45: 修繕費 | P45: =ROUND(AS45*(1+AU45),0) -> 6600 | Q45: =ROUND(P45*(1+$AU45),0) -> 6611 | R45: =ROUND(Q45*(1+$AU45),0) -> 6622 | S45: =ROUND(R45*(1+$AU45),0) -> 6633 | T45: =ROUND(S45*(1+$AU45),0) -> 6644 | U45: =ROUND(T45*(1+$AU45),0) -> 6655 | V45: =ROUND(U45*(1+$AU45),0) -> 6666 | W45: =ROUND(V45*(1+$AU45),0) -> 6677 | X45: =ROUND(W45*(1+$AU45),0) -> 6688 | Y45: =ROUND(X45*(1+$AU45),0) -> 6699 | Z45: =[12]公共下水道事業!AE47+#REF!+[12]農業集落排水事業!AE47 -> #REF! | AA45: =[12]公共下水道事業!AF47+#REF!+[12]農業集落排水事業!AF47 -> #REF! | AB45: =[12]公共下水道事業!AG47+#REF!+[12]農業集落排水事業!AG47 -> #REF! | AC45: =[12]公共下水道事業!AH47+#REF!+[12]農業集落排水事業!AH47 -> #REF! | AD45: =[12]公共下水道事業!AI47+#REF!+[12]農業集落排水事業!AI47 -> #REF! | AE45: =[12]公共下水道事業!AJ47+#REF!+[12]農業集落排水事業!AJ47 -> #REF! | AF45: =[12]公共下水道事業!AK47+#REF!+[12]農業集落排水事業!AK47 -> #REF! | AG45: =[12]公共下水道事業!AL47+#REF!+[12]農業集落排水事業!AL47 -> #REF! | ... AR45: =[12]公共下水道事業!AW47+#REF!+[12]農業集落排水事業!AW47 -> #REF! | AS45: 6589 | AT45: =ROUND(AS45/$AS$48,4) -> 0.0871 | AU45: =ROUND($AU$42*AT45,4) -> 0.0017 | AY45: 4710
G46: 材料費 | P46: =ROUND(AS46*(1+AU46),0) -> 7234 | Q46: =ROUND(P46*(1+$AU46),0) -> 7248 | R46: =ROUND(Q46*(1+$AU46),0) -> 7262 | S46: =ROUND(R46*(1+$AU46),0) -> 7276 | T46: =ROUND(S46*(1+$AU46),0) -> 7290 | U46: =ROUND(T46*(1+$AU46),0) -> 7304 | V46: =ROUND(U46*(1+$AU46),0) -> 7318 | W46: =ROUND(V46*(1+$AU46),0) -> 7332 | X46: =ROUND(W46*(1+$AU46),0) -> 7346 | Y46: =ROUND(X46*(1+$AU46),0) -> 7360 | Z46: =[12]公共下水道事業!AE48+#REF!+[12]農業集落排水事業!AE48 -> #REF! | AA46: =[12]公共下水道事業!AF48+#REF!+[12]農業集落排水事業!AF48 -> #REF! | AB46: =[12]公共下水道事業!AG48+#REF!+[12]農業集落排水事業!AG48 -> #REF! | AC46: =[12]公共下水道事業!AH48+#REF!+[12]農業集落排水事業!AH48 -> #REF! | AD46: =[12]公共下水道事業!AI48+#REF!+[12]農業集落排水事業!AI48 -> #REF! | AE46: =[12]公共下水道事業!AJ48+#REF!+[12]農業集落排水事業!AJ48 -> #REF! | AF46: =[12]公共下水道事業!AK48+#REF!+[12]農業集落排水事業!AK48 -> #REF! | AG46: =[12]公共下水道事業!AL48+#REF!+[12]農業集落排水事業!AL48 -> #REF! | ... AR46: =[12]公共下水道事業!AW48+#REF!+[12]農業集落排水事業!AW48 -> #REF! | AS46: 7220 | AT46: =ROUND(AS46/$AS$48,4) -> 0.0954 | AU46: =ROUND($AU$42*AT46,4) -> 0.0019 | AY46: 22513
G47: その他 | P47: =ROUND(AS47*(1+AU47),0) -> 51087 | Q47: =ROUND(P47*(1+$AU47),0) -> 51766 | R47: =ROUND(Q47*(1+$AU47),0) -> 52454 | S47: =ROUND(R47*(1+$AU47),0) -> 53152 | T47: =ROUND(S47*(1+$AU47),0) -> 53859 | U47: =ROUND(T47*(1+$AU47),0) -> 54575 | V47: =ROUND(U47*(1+$AU47),0) -> 55301 | W47: =ROUND(V47*(1+$AU47),0) -> 56037 | X47: =ROUND(W47*(1+$AU47),0) -> 56782 | Y47: =ROUND(X47*(1+$AU47),0) -> 57537 | Z47: =[12]公共下水道事業!AE49+#REF!+[12]農業集落排水事業!AE49 -> #REF! | AA47: =[12]公共下水道事業!AF49+#REF!+[12]農業集落排水事業!AF49 -> #REF! | AB47: =[12]公共下水道事業!AG49+#REF!+[12]農業集落排水事業!AG49 -> #REF! | AC47: =[12]公共下水道事業!AH49+#REF!+[12]農業集落排水事業!AH49 -> #REF! | AD47: =[12]公共下水道事業!AI49+#REF!+[12]農業集落排水事業!AI49 -> #REF! | AE47: =[12]公共下水道事業!AJ49+#REF!+[12]農業集落排水事業!AJ49 -> #REF! | AF47: =[12]公共下水道事業!AK49+#REF!+[12]農業集落排水事業!AK49 -> #REF! | AG47: =[12]公共下水道事業!AL49+#REF!+[12]農業集落排水事業!AL49 -> #REF! | ... AR47: =[12]公共下水道事業!AW49+#REF!+[12]農業集落排水事業!AW49 -> #REF! | AS47: =40175+10102+139 -> 50416 | AT47: =ROUND(AS47/$AS$48,4) -> 0.6663 | AU47: =ROUND($AU$42*AT47,4) -> 0.0133 | AY47: 169845
D48: (3) | F48: 流域下水道負担金 | AS48: =SUM(AS44:AS47) -> 75661 | AY48: 6793
D49: (4) | F49: 減価償却費 | P49: 82749 | Q49: 85406 | R49: 85432 | S49: 111723 | T49: 111709 | U49: 113091 | V49: 113919 | W49: 114759 | X49: 115218 | Y49: 114004 | Z49: 123504 | AA49: =[12]公共下水道事業!AF50+#REF!+[12]農業集落排水事業!AF50 -> #REF! | AB49: =[12]公共下水道事業!AG50+#REF!+[12]農業集落排水事業!AG50 -> #REF! | AC49: =[12]公共下水道事業!AH50+#REF!+[12]農業集落排水事業!AH50 -> #REF! | AD49: =[12]公共下水道事業!AI50+#REF!+[12]農業集落排水事業!AI50 -> #REF! | AE49: =[12]公共下水道事業!AJ50+#REF!+[12]農業集落排水事業!AJ50 -> #REF! | AF49: =[12]公共下水道事業!AK50+#REF!+[12]農業集落排水事業!AK50 -> #REF! | AG49: =[12]公共下水道事業!AL50+#REF!+[12]農業集落排水事業!AL50 -> #REF! | AH49: =[12]公共下水道事業!AM50+#REF!+[12]農業集落排水事業!AM50 -> #REF! | ... AR49: =[12]公共下水道事業!AW50+#REF!+[12]農業集落排水事業!AW50 -> #REF! | AY49: 250
D50: ２． | E50: 営業外費用 | P50: =P51+P52 -> 6324 | Q50: =Q51+Q52 -> 3705 | R50: =R51+R52 -> 4948 | S50: =S51+S52 -> 12298 | T50: =T51+T52 -> 12450 | U50: =U51+U52 -> 13232 | V50: =V51+V52 -> 13502 | W50: =W51+W52 -> 13814 | ... AR50: =AR51+AR52 -> #REF! | AY50: 169
D51: (1) | F51: 支払利息 | P51: 5646 | Q51: 3027 | R51: 4270 | S51: 11620 | T51: 11772 | U51: 12554 | V51: 12824 | W51: 13136 | X51: 13427 | Y51: 13494 | Z51: =[12]公共下水道事業!AE52+#REF!+[12]農業集落排水事業!AE52 -> #REF! | AA51: =[12]公共下水道事業!AF52+#REF!+[12]農業集落排水事業!AF52 -> #REF! | AB51: =[12]公共下水道事業!AG52+#REF!+[12]農業集落排水事業!AG52 -> #REF! | AC51: =[12]公共下水道事業!AH52+#REF!+[12]農業集落排水事業!AH52 -> #REF! | AD51: =[12]公共下水道事業!AI52+#REF!+[12]農業集落排水事業!AI52 -> #REF! | AE51: =[12]公共下水道事業!AJ52+#REF!+[12]農業集落排水事業!AJ52 -> #REF! | AF51: =[12]公共下水道事業!AK52+#REF!+[12]農業集落排水事業!AK52 -> #REF! | AG51: =[12]公共下水道事業!AL52+#REF!+[12]農業集落排水事業!AL52 -> #REF! | ... AR51: =[12]公共下水道事業!AW52+#REF!+[12]農業集落排水事業!AW52 -> #REF! | AY51: =SUM(AY45:AY50) -> 204280
D52: (2) | F52: その他 | P52: 678 | Q52: 678 | R52: 678 | S52: 678 | T52: 678 | U52: 678 | V52: 678 | W52: 678 | X52: 678 | Y52: 678 | Z52: =[12]公共下水道事業!AE53+#REF!+[12]農業集落排水事業!AE53 -> #REF! | AA52: =[12]公共下水道事業!AF53+#REF!+[12]農業集落排水事業!AF53 -> #REF! | AB52: =[12]公共下水道事業!AG53+#REF!+[12]農業集落排水事業!AG53 -> #REF! | AC52: =[12]公共下水道事業!AH53+#REF!+[12]農業集落排水事業!AH53 -> #REF! | AD52: =[12]公共下水道事業!AI53+#REF!+[12]農業集落排水事業!AI53 -> #REF! | AE52: =[12]公共下水道事業!AJ53+#REF!+[12]農業集落排水事業!AJ53 -> #REF! | AF52: =[12]公共下水道事業!AK53+#REF!+[12]農業集落排水事業!AK53 -> #REF! | AG52: =[12]公共下水道事業!AL53+#REF!+[12]農業集落排水事業!AL53 -> #REF! | ... AR52: =[12]公共下水道事業!AW53+#REF!+[12]農業集落排水事業!AW53 -> #REF! | AY52: =AY44-AY51 -> 40928
D53: 支出計 | J53: (D) | P53: =P38+P50 -> 174997 | Q53: =Q38+Q50 -> 176059 | R53: =R38+R50 -> 178371 | S53: =S38+S50 -> 213073 | T53: =T38+T50 -> 214291 | U53: =U38+U50 -> 217553 | V53: =V38+V50 -> 219768 | W53: =W38+W50 -> 222057 | ... AR53: =AR38+AR50 -> #REF!
C54: 経常損益 | H54: (C)-(D) | J54: (E) | P54: =P37-P53 -> 16641 | Q54: =Q37-Q53 -> 13423 | R54: =R37-R53-R90 -> 10304 | S54: =S37-S53 -> 7251 | T54: =T37-T53 -> 4288 | U54: =U37-U53 -> 1162 | V54: =V37-V53 -> -1713 | W54: =W37-W53 -> -4542 | X54: =X37-X53 -> -7301 | Y54: =Y37-Y53 -> -9991 | Z54: =Z37-Z53 -> #REF! | ... AR54: =AR37-AR53 -> #REF!
B55: 特別利益 | J55: (F) | Z55: =[12]公共下水道事業!AE56+#REF!+[12]農業集落排水事業!AE56 -> #REF! | AA55: =[12]公共下水道事業!AF56+#REF!+[12]農業集落排水事業!AF56 -> #REF! | AB55: =[12]公共下水道事業!AG56+#REF!+[12]農業集落排水事業!AG56 -> #REF! | AC55: =[12]公共下水道事業!AH56+#REF!+[12]農業集落排水事業!AH56 -> #REF! | AD55: =[12]公共下水道事業!AI56+#REF!+[12]農業集落排水事業!AI56 -> #REF! | AE55: =[12]公共下水道事業!AJ56+#REF!+[12]農業集落排水事業!AJ56 -> #REF! | AF55: =[12]公共下水道事業!AK56+#REF!+[12]農業集落排水事業!AK56 -> #REF! | AG55: =[12]公共下水道事業!AL56+#REF!+[12]農業集落排水事業!AL56 -> #REF! | ... AR55: =[12]公共下水道事業!AW56+#REF!+[12]農業集落排水事業!AW56 -> #REF!
B56: 特別損失 | J56: (G) | Z56: =[12]公共下水道事業!AE57+#REF!+[12]農業集落排水事業!AE57 -> #REF! | AA56: =[12]公共下水道事業!AF57+#REF!+[12]農業集落排水事業!AF57 -> #REF! | AB56: =[12]公共下水道事業!AG57+#REF!+[12]農業集落排水事業!AG57 -> #REF! | AC56: =[12]公共下水道事業!AH57+#REF!+[12]農業集落排水事業!AH57 -> #REF! | AD56: =[12]公共下水道事業!AI57+#REF!+[12]農業集落排水事業!AI57 -> #REF! | AE56: =[12]公共下水道事業!AJ57+#REF!+[12]農業集落排水事業!AJ57 -> #REF! | AF56: =[12]公共下水道事業!AK57+#REF!+[12]農業集落排水事業!AK57 -> #REF! | AG56: =[12]公共下水道事業!AL57+#REF!+[12]農業集落排水事業!AL57 -> #REF! | ... AR56: =[12]公共下水道事業!AW57+#REF!+[12]農業集落排水事業!AW57 -> #REF!
B57: 特別損益 | H57: (F)-(G) | J57: (H) | P57: =P55-P56 -> 0 | Q57: =Q55-Q56 -> 0 | R57: =R55-R56 -> 0 | S57: =S55-S56 -> 0 | T57: =T55-T56 -> 0 | U57: =U55-U56 -> 0 | V57: =V55-V56 -> 0 | W57: =W55-W56 -> 0 | ... AR57: =AR55-AR56 -> #REF!
B58: 当年度純利益（又は純損失） | I58: (E)+(H) | P58: =P54+P57 -> 16641 | Q58: =Q54+Q57 -> 13423 | R58: =R54+R57 -> 10304 | S58: =S54+S57 -> 7251 | T58: =T54+T57 -> 4288 | U58: =U54+U57 -> 1162 | V58: =V54+V57 -> -1713 | W58: =W54+W57 -> -4542 | ... AR58: =AR54+AR57 -> #REF!
B59: 繰越利益剰余金 | P59: =P58 -> 16641 | Q59: =Q58+P59-Q90 -> 30064 | R59: =R58+Q59-R90 -> 40368 | S59: =S58+R59-S90 -> 47619 | T59: =T58+S59-T90 -> 51907 | U59: =U58+T59-U90 -> 53069 | V59: =V58+U59-V90 -> 51356 | W59: =W58+V59-W90 -> 46814 | X59: =X58+W59-X90 -> 39513 | Y59: =Y58+X59-Y90 -> 29522
B61: 経常収支比率 | P61: =P21 -> 1.0950931 | Q61: =Q21 -> 1.0762415 | R61: =R21 -> 1.0577672 | S61: =S21 -> 1.0340306 | T61: =T21 -> 1.0200102 | U61: =U21 -> 1.0053412 | V61: =V21 -> 0.99220542 | W61: =W21 -> 0.97954579 | ... Y61: =Y21 -> 0.95539613
B62: 経費回収率 | P62: =P18 -> 0.56554938 | Q62: =Q18 -> 0.56100868 | R62: =R18 -> 0.55275804 | S62: =S18 -> 0.52051056 | T62: =T18 -> 0.52065428 | U62: =U18 -> 0.51323411 | V62: =V18 -> 0.51027978 | W62: =W18 -> 0.50702789 | ... Y62: =Y18 -> 0.50791219
B63: 総括原価率 | P63: =P28/(P53-P35) -> 0.46196359 | Q63: =Q28/(Q53-Q35) -> 0.46611522 | R63: =R28/(R53-R35) -> 0.47242076 | S63: =S28/(S53-S35) -> 0.40939937 | T63: =T28/(T53-T35) -> 0.41155462 | U63: =U28/(U53-U35) -> 0.40279347 | V63: =V28/(V53-V35) -> 0.39719648 | W63: =W28/(W53-W35) -> 0.39144777 | ... Y63: =Y28/(Y53-Y35) -> 0.38346467
J65: 4条
I66: 年 度 | P66: 令和7年度 | Q66: 令和8年度 | R66: 令和9年度 | S66: 令和10年度 | T66: 令和11年度 | U66: 令和12年度 | V66: 令和13年度 | W66: 令和14年度 | X66: 令和15年度 | Y66: 令和16年度 | Z66: 令和17年度 | AA66: 令和18年度 | AB66: 令和19年度 | AC66: 令和20年度 | AD66: 令和21年度 | AE66: 令和22年度 | AF66: 令和23年度 | AG66: 令和24年度 | AH66: 令和25年度 | AI66: 令和26年度 | AJ66: 令和27年度 | AK66: 令和28年度 | AL66: 令和29年度 | AM66: 令和30年度 | AN66: 令和31年度 | AO66: 令和32年度 | AP66: 令和33年度 | AQ66: 令和34年度 | AR66: 令和35年度
E67: 区 分 | P67: 2025 | Q67: 2026 | R67: 2027 | S67: 2028 | T67: 2029 | U67: 2030 | V67: 2031 | W67: 2032 | X67: 2033 | Y67: 2034 | Z67: 2035 | AA67: 2036 | AB67: 2037 | AC67: 2038 | AD67: 2039 | AE67: 2040 | AF67: 2041 | AG67: 2042 | AH67: 2043 | AI67: 2044 | AJ67: 2045 | AK67: 2046 | AL67: 2047 | AM67: 2048 | AN67: 2049 | AO67: 2050 | AP67: 2051 | AQ67: 2052 | AR67: 2053
C68: 資本的収支 | D68: 資本的収入 | E68: １． | F68: 企業債 | P68: 13900 | Q68: ='【下水道】建設改良費の年度別事業費 (2)'!F21 -> 73000 | R68: ='【下水道】建設改良費の年度別事業費 (2)'!G21 -> 374500 | S68: ='【下水道】建設改良費の年度別事業費 (2)'!H21 -> 25000 | T68: ='【下水道】建設改良費の年度別事業費 (2)'!I21 -> 49713 | U68: ='【下水道】建設改良費の年度別事業費 (2)'!J21 -> 25000 | V68: ='【下水道】建設改良費の年度別事業費 (2)'!K21 -> 25000 | W68: ='【下水道】建設改良費の年度別事業費 (2)'!L21 -> 25000 | X68: ='【下水道】建設改良費の年度別事業費 (2)'!M21 -> 25000 | Y68: ='【下水道】建設改良費の年度別事業費 (2)'!N21 -> 34713 | Z68: =[12]公共下水道事業!AE73+#REF!+[12]農業集落排水事業!AE64 -> #REF! | AA68: =[12]公共下水道事業!AF73+#REF!+[12]農業集落排水事業!AF64 -> #REF! | AB68: =[12]公共下水道事業!AG73+#REF!+[12]農業集落排水事業!AG64 -> #REF! | AC68: =[12]公共下水道事業!AH73+#REF!+[12]農業集落排水事業!AH64 -> #REF! | AD68: =[12]公共下水道事業!AI73+#REF!+[12]農業集落排水事業!AI64 -> #REF! | AE68: =[12]公共下水道事業!AJ73+#REF!+[12]農業集落排水事業!AJ64 -> #REF! | AF68: =[12]公共下水道事業!AK73+#REF!+[12]農業集落排水事業!AK64 -> #REF! | AG68: =[12]公共下水道事業!AL73+#REF!+[12]農業集落排水事業!AL64 -> #REF! | ... AR68: =[12]公共下水道事業!AW73+#REF!+[12]農業集落排水事業!AW64 -> #REF!
F69: うち資本費平準化債 | P69: 0 | Q69: 0 | R69: 0 | S69: 0 | T69: 0 | U69: 0 | V69: 0 | W69: 0 | X69: 0 | Y69: 0 | Z69: =[12]公共下水道事業!AE74+#REF!+[12]農業集落排水事業!AE65 -> #REF! | AA69: =[12]公共下水道事業!AF74+#REF!+[12]農業集落排水事業!AF65 -> #REF! | AB69: =[12]公共下水道事業!AG74+#REF!+[12]農業集落排水事業!AG65 -> #REF! | AC69: =[12]公共下水道事業!AH74+#REF!+[12]農業集落排水事業!AH65 -> #REF! | AD69: =[12]公共下水道事業!AI74+#REF!+[12]農業集落排水事業!AI65 -> #REF! | AE69: =[12]公共下水道事業!AJ74+#REF!+[12]農業集落排水事業!AJ65 -> #REF! | AF69: =[12]公共下水道事業!AK74+#REF!+[12]農業集落排水事業!AK65 -> #REF! | AG69: =[12]公共下水道事業!AL74+#REF!+[12]農業集落排水事業!AL65 -> #REF! | ... AR69: =[12]公共下水道事業!AW74+#REF!+[12]農業集落排水事業!AW65 -> #REF!
E70: ２． | F70: 他会計出資金 | P70: 50013 | Q70: 46082 | R70: 37403 | S70: 30426 | T70: 24755 | U70: 20752 | V70: 15296 | W70: 7604 | X70: 7167 | Y70: 1407 | Z70: =[12]公共下水道事業!AE75+#REF!+[12]農業集落排水事業!AE66 -> #REF! | AA70: =[12]公共下水道事業!AF75+#REF!+[12]農業集落排水事業!AF66 -> #REF! | AB70: =[12]公共下水道事業!AG75+#REF!+[12]農業集落排水事業!AG66 -> #REF! | AC70: =[12]公共下水道事業!AH75+#REF!+[12]農業集落排水事業!AH66 -> #REF! | AD70: =[12]公共下水道事業!AI75+#REF!+[12]農業集落排水事業!AI66 -> #REF! | AE70: =[12]公共下水道事業!AJ75+#REF!+[12]農業集落排水事業!AJ66 -> #REF! | AF70: =[12]公共下水道事業!AK75+#REF!+[12]農業集落排水事業!AK66 -> #REF! | AG70: =[12]公共下水道事業!AL75+#REF!+[12]農業集落排水事業!AL66 -> #REF! | ... AR70: =[12]公共下水道事業!AW75+#REF!+[12]農業集落排水事業!AW66 -> #REF!
E71: ３． | F71: 他会計補助金 | Z71: =[12]公共下水道事業!AE76+#REF!+[12]農業集落排水事業!AE67 -> #REF! | AA71: =[12]公共下水道事業!AF76+#REF!+[12]農業集落排水事業!AF67 -> #REF! | AB71: =[12]公共下水道事業!AG76+#REF!+[12]農業集落排水事業!AG67 -> #REF! | AC71: =[12]公共下水道事業!AH76+#REF!+[12]農業集落排水事業!AH67 -> #REF! | AD71: =[12]公共下水道事業!AI76+#REF!+[12]農業集落排水事業!AI67 -> #REF! | AE71: =[12]公共下水道事業!AJ76+#REF!+[12]農業集落排水事業!AJ67 -> #REF! | AF71: =[12]公共下水道事業!AK76+#REF!+[12]農業集落排水事業!AK67 -> #REF! | AG71: =[12]公共下水道事業!AL76+#REF!+[12]農業集落排水事業!AL67 -> #REF! | ... AR71: =[12]公共下水道事業!AW76+#REF!+[12]農業集落排水事業!AW67 -> #REF!
E72: ４． | F72: 他会計負担金 | Z72: =[12]公共下水道事業!AE77+#REF!+[12]農業集落排水事業!AE68 -> #REF! | AA72: =[12]公共下水道事業!AF77+#REF!+[12]農業集落排水事業!AF68 -> #REF! | AB72: =[12]公共下水道事業!AG77+#REF!+[12]農業集落排水事業!AG68 -> #REF! | AC72: =[12]公共下水道事業!AH77+#REF!+[12]農業集落排水事業!AH68 -> #REF! | AD72: =[12]公共下水道事業!AI77+#REF!+[12]農業集落排水事業!AI68 -> #REF! | AE72: =[12]公共下水道事業!AJ77+#REF!+[12]農業集落排水事業!AJ68 -> #REF! | AF72: =[12]公共下水道事業!AK77+#REF!+[12]農業集落排水事業!AK68 -> #REF! | AG72: =[12]公共下水道事業!AL77+#REF!+[12]農業集落排水事業!AL68 -> #REF! | ... AR72: =[12]公共下水道事業!AW77+#REF!+[12]農業集落排水事業!AW68 -> #REF!
E73: ５． | F73: 他会計借入金 | Z73: =[12]公共下水道事業!AE78+#REF!+[12]農業集落排水事業!AE69 -> #REF! | AA73: =[12]公共下水道事業!AF78+#REF!+[12]農業集落排水事業!AF69 -> #REF! | AB73: =[12]公共下水道事業!AG78+#REF!+[12]農業集落排水事業!AG69 -> #REF! | AC73: =[12]公共下水道事業!AH78+#REF!+[12]農業集落排水事業!AH69 -> #REF! | AD73: =[12]公共下水道事業!AI78+#REF!+[12]農業集落排水事業!AI69 -> #REF! | AE73: =[12]公共下水道事業!AJ78+#REF!+[12]農業集落排水事業!AJ69 -> #REF! | AF73: =[12]公共下水道事業!AK78+#REF!+[12]農業集落排水事業!AK69 -> #REF! | AG73: =[12]公共下水道事業!AL78+#REF!+[12]農業集落排水事業!AL69 -> #REF! | ... AR73: =[12]公共下水道事業!AW78+#REF!+[12]農業集落排水事業!AW69 -> #REF!
E74: ６． | F74: 国（都道府県）補助金 | P74: ='【下水道】建設改良費の年度別事業費 (2)'!E17 -> 40300 | Q74: ='【下水道】建設改良費の年度別事業費 (2)'!F17 -> 73000 | R74: ='【下水道】建設改良費の年度別事業費 (2)'!G17 -> 374500 | S74: ='【下水道】建設改良費の年度別事業費 (2)'!H17 -> 25000 | T74: ='【下水道】建設改良費の年度別事業費 (2)'!I17 -> 44213 | U74: ='【下水道】建設改良費の年度別事業費 (2)'!J17 -> 25000 | V74: ='【下水道】建設改良費の年度別事業費 (2)'!K17 -> 25000 | W74: ='【下水道】建設改良費の年度別事業費 (2)'!L17 -> 25000 | ... Y74: ='【下水道】建設改良費の年度別事業費 (2)'!N17 -> 29213 | Z74: =[12]公共下水道事業!AE79+#REF!+[12]農業集落排水事業!AE70 -> #REF! | AA74: =[12]公共下水道事業!AF79+#REF!+[12]農業集落排水事業!AF70 -> #REF! | AB74: =[12]公共下水道事業!AG79+#REF!+[12]農業集落排水事業!AG70 -> #REF! | AC74: =[12]公共下水道事業!AH79+#REF!+[12]農業集落排水事業!AH70 -> #REF! | AD74: =[12]公共下水道事業!AI79+#REF!+[12]農業集落排水事業!AI70 -> #REF! | AE74: =[12]公共下水道事業!AJ79+#REF!+[12]農業集落排水事業!AJ70 -> #REF! | AF74: =[12]公共下水道事業!AK79+#REF!+[12]農業集落排水事業!AK70 -> #REF! | AG74: =[12]公共下水道事業!AL79+#REF!+[12]農業集落排水事業!AL70 -> #REF! | ... AR74: =[12]公共下水道事業!AW79+#REF!+[12]農業集落排水事業!AW70 -> #REF!
E75: ７． | F75: 固定資産売却代金 | Z75: =[12]公共下水道事業!AE80+#REF!+[12]農業集落排水事業!AE71 -> #REF! | AA75: =[12]公共下水道事業!AF80+#REF!+[12]農業集落排水事業!AF71 -> #REF! | AB75: =[12]公共下水道事業!AG80+#REF!+[12]農業集落排水事業!AG71 -> #REF! | AC75: =[12]公共下水道事業!AH80+#REF!+[12]農業集落排水事業!AH71 -> #REF! | AD75: =[12]公共下水道事業!AI80+#REF!+[12]農業集落排水事業!AI71 -> #REF! | AE75: =[12]公共下水道事業!AJ80+#REF!+[12]農業集落排水事業!AJ71 -> #REF! | AF75: =[12]公共下水道事業!AK80+#REF!+[12]農業集落排水事業!AK71 -> #REF! | AG75: =[12]公共下水道事業!AL80+#REF!+[12]農業集落排水事業!AL71 -> #REF! | ... AR75: =[12]公共下水道事業!AW80+#REF!+[12]農業集落排水事業!AW71 -> #REF!
E76: ８． | F76: 工事負担金 | P76: 1428 | Q76: 1428 | R76: 1428 | S76: 1428 | T76: 1428 | U76: 1428 | V76: 1428 | W76: 1428 | X76: 1428 | Y76: 1428 | Z76: =[12]公共下水道事業!AE81+#REF!+[12]農業集落排水事業!AE72 -> #REF! | AA76: =[12]公共下水道事業!AF81+#REF!+[12]農業集落排水事業!AF72 -> #REF! | AB76: =[12]公共下水道事業!AG81+#REF!+[12]農業集落排水事業!AG72 -> #REF! | AC76: =[12]公共下水道事業!AH81+#REF!+[12]農業集落排水事業!AH72 -> #REF! | AD76: =[12]公共下水道事業!AI81+#REF!+[12]農業集落排水事業!AI72 -> #REF! | AE76: =[12]公共下水道事業!AJ81+#REF!+[12]農業集落排水事業!AJ72 -> #REF! | AF76: =[12]公共下水道事業!AK81+#REF!+[12]農業集落排水事業!AK72 -> #REF! | AG76: =[12]公共下水道事業!AL81+#REF!+[12]農業集落排水事業!AL72 -> #REF! | ... AR76: =[12]公共下水道事業!AW81+#REF!+[12]農業集落排水事業!AW72 -> #REF!
E77: ９． | F77: その他 | Z77: =[12]公共下水道事業!AE82+#REF!+[12]農業集落排水事業!AE73 -> #REF! | AA77: =[12]公共下水道事業!AF82+#REF!+[12]農業集落排水事業!AF73 -> #REF! | AB77: =[12]公共下水道事業!AG82+#REF!+[12]農業集落排水事業!AG73 -> #REF! | AC77: =[12]公共下水道事業!AH82+#REF!+[12]農業集落排水事業!AH73 -> #REF! | AD77: =[12]公共下水道事業!AI82+#REF!+[12]農業集落排水事業!AI73 -> #REF! | AE77: =[12]公共下水道事業!AJ82+#REF!+[12]農業集落排水事業!AJ73 -> #REF! | AF77: =[12]公共下水道事業!AK82+#REF!+[12]農業集落排水事業!AK73 -> #REF! | AG77: =[12]公共下水道事業!AL82+#REF!+[12]農業集落排水事業!AL73 -> #REF! | ... AR77: =[12]公共下水道事業!AW82+#REF!+[12]農業集落排水事業!AW73 -> #REF!
E78: 計 | J78: (A) | P78: =SUM(P68,P70:P77) -> 105641 | Q78: =SUM(Q68,Q70:Q77) -> 193510 | R78: =SUM(R68,R70:R77) -> 787831 | S78: =SUM(S68,S70:S77) -> 81854 | T78: =SUM(T68,T70:T77) -> 120109 | U78: =SUM(U68,U70:U77) -> 72180 | V78: =SUM(V68,V70:V77) -> 66724 | W78: =SUM(W68,W70:W77) -> 59032 | ... Y78: =SUM(Y68,Y70:Y77) -> 66761 | Z78: =SUM(Z68:Z77) -> #REF! | AA78: =SUM(AA68:AA77) -> #REF! | AB78: =SUM(AB68:AB77) -> #REF! | AC78: =SUM(AC68:AC77) -> #REF! | AD78: =SUM(AD68:AD77) -> #REF! | AE78: =SUM(AE68:AE77) -> #REF! | AF78: =SUM(AF68:AF77) -> #REF! | AG78: =SUM(AG68:AG77) -> #REF! | ... AR78: =SUM(AR68:AR77) -> #REF!
E79: (A)のうち翌年度へ繰り越される支出の財源充当額 | J79: (B) | P79: 0 | Q79: =P79 -> 0 | R79: =Q79 -> 0 | S79: =R79 -> 0 | T79: =S79 -> 0 | U79: =T79 -> 0 | V79: =U79 -> 0 | W79: =V79 -> 0 | X79: =W79 -> 0 | Y79: =X79 -> 0 | Z79: =[12]公共下水道事業!AE84+#REF!+[12]農業集落排水事業!AE75 -> #REF! | AA79: =[12]公共下水道事業!AF84+#REF!+[12]農業集落排水事業!AF75 -> #REF! | AB79: =[12]公共下水道事業!AG84+#REF!+[12]農業集落排水事業!AG75 -> #REF! | AC79: =[12]公共下水道事業!AH84+#REF!+[12]農業集落排水事業!AH75 -> #REF! | AD79: =[12]公共下水道事業!AI84+#REF!+[12]農業集落排水事業!AI75 -> #REF! | AE79: =[12]公共下水道事業!AJ84+#REF!+[12]農業集落排水事業!AJ75 -> #REF! | AF79: =[12]公共下水道事業!AK84+#REF!+[12]農業集落排水事業!AK75 -> #REF! | AG79: =[12]公共下水道事業!AL84+#REF!+[12]農業集落排水事業!AL75 -> #REF! | ... AR79: =[12]公共下水道事業!AW84+#REF!+[12]農業集落排水事業!AW75 -> #REF!
F80: 純計 | H80: (A)-(B) | J80: (C) | P80: =P78-P79 -> 105641 | Q80: =Q78-Q79 -> 193510 | R80: =R78-R79 -> 787831 | S80: =S78-S79 -> 81854 | T80: =T78-T79 -> 120109 | U80: =U78-U79 -> 72180 | V80: =V78-V79 -> 66724 | W80: =W78-W79 -> 59032 | ... AR80: =AR78-AR79 -> #REF!
D81: 資本的支出 | E81: １． | F81: 建設改良費 | P81: ='【下水道】建設改良費の年度別事業費 (2)'!E14 -> 93100 | Q81: ='【下水道】建設改良費の年度別事業費 (2)'!F14 -> 146000 | R81: ='【下水道】建設改良費の年度別事業費 (2)'!G14 -> 749000 | S81: ='【下水道】建設改良費の年度別事業費 (2)'!H14 -> 50000 | T81: ='【下水道】建設改良費の年度別事業費 (2)'!I14 -> 99426 | U81: ='【下水道】建設改良費の年度別事業費 (2)'!J14 -> 50000 | V81: ='【下水道】建設改良費の年度別事業費 (2)'!K14 -> 50000 | W81: ='【下水道】建設改良費の年度別事業費 (2)'!L14 -> 50000 | ... Y81: ='【下水道】建設改良費の年度別事業費 (2)'!N14 -> 69426 | Z81: =[12]公共下水道事業!AE86+#REF!+[12]農業集落排水事業!AE77 -> #REF! | AA81: =[12]公共下水道事業!AF86+#REF!+[12]農業集落排水事業!AF77 -> #REF! | AB81: =[12]公共下水道事業!AG86+#REF!+[12]農業集落排水事業!AG77 -> #REF! | AC81: =[12]公共下水道事業!AH86+#REF!+[12]農業集落排水事業!AH77 -> #REF! | AD81: =[12]公共下水道事業!AI86+#REF!+[12]農業集落排水事業!AI77 -> #REF! | AE81: =[12]公共下水道事業!AJ86+#REF!+[12]農業集落排水事業!AJ77 -> #REF! | AF81: =[12]公共下水道事業!AK86+#REF!+[12]農業集落排水事業!AK77 -> #REF! | AG81: =[12]公共下水道事業!AL86+#REF!+[12]農業集落排水事業!AL77 -> #REF! | ... AR81: =[12]公共下水道事業!AW86+#REF!+[12]農業集落排水事業!AW77 -> #REF!
F82: うち職員給与費 | Z82: =[12]公共下水道事業!AE87+#REF!+[12]農業集落排水事業!AE78 -> #REF! | AA82: =[12]公共下水道事業!AF87+#REF!+[12]農業集落排水事業!AF78 -> #REF! | AB82: =[12]公共下水道事業!AG87+#REF!+[12]農業集落排水事業!AG78 -> #REF! | AC82: =[12]公共下水道事業!AH87+#REF!+[12]農業集落排水事業!AH78 -> #REF! | AD82: =[12]公共下水道事業!AI87+#REF!+[12]農業集落排水事業!AI78 -> #REF! | AE82: =[12]公共下水道事業!AJ87+#REF!+[12]農業集落排水事業!AJ78 -> #REF! | AF82: =[12]公共下水道事業!AK87+#REF!+[12]農業集落排水事業!AK78 -> #REF! | AG82: =[12]公共下水道事業!AL87+#REF!+[12]農業集落排水事業!AL78 -> #REF! | ... AR82: =[12]公共下水道事業!AW87+#REF!+[12]農業集落排水事業!AW78 -> #REF!
E83: ２． | F83: 企業債償還金 | P83: 89306 | Q83: 73368 | R83: 60040 | S83: 50231 | T83: 46498 | U83: 40209 | V83: 31963 | W83: 22551 | X83: 33547 | Y83: 25540 | Z83: 154903 | AA83: =[12]公共下水道事業!AF88+#REF!+[12]農業集落排水事業!AF79 -> #REF! | AB83: =[12]公共下水道事業!AG88+#REF!+[12]農業集落排水事業!AG79 -> #REF! | AC83: =[12]公共下水道事業!AH88+#REF!+[12]農業集落排水事業!AH79 -> #REF! | AD83: =[12]公共下水道事業!AI88+#REF!+[12]農業集落排水事業!AI79 -> #REF! | AE83: =[12]公共下水道事業!AJ88+#REF!+[12]農業集落排水事業!AJ79 -> #REF! | AF83: =[12]公共下水道事業!AK88+#REF!+[12]農業集落排水事業!AK79 -> #REF! | AG83: =[12]公共下水道事業!AL88+#REF!+[12]農業集落排水事業!AL79 -> #REF! | AH83: =[12]公共下水道事業!AM88+#REF!+[12]農業集落排水事業!AM79 -> #REF! | ... AR83: =[12]公共下水道事業!AW88+#REF!+[12]農業集落排水事業!AW79 -> #REF!
E84: ３． | F84: 他会計長期借入返還金 | Z84: =[12]公共下水道事業!AE89+#REF!+[12]農業集落排水事業!AE80 -> #REF! | AA84: =[12]公共下水道事業!AF89+#REF!+[12]農業集落排水事業!AF80 -> #REF! | AB84: =[12]公共下水道事業!AG89+#REF!+[12]農業集落排水事業!AG80 -> #REF! | AC84: =[12]公共下水道事業!AH89+#REF!+[12]農業集落排水事業!AH80 -> #REF! | AD84: =[12]公共下水道事業!AI89+#REF!+[12]農業集落排水事業!AI80 -> #REF! | AE84: =[12]公共下水道事業!AJ89+#REF!+[12]農業集落排水事業!AJ80 -> #REF! | AF84: =[12]公共下水道事業!AK89+#REF!+[12]農業集落排水事業!AK80 -> #REF! | AG84: =[12]公共下水道事業!AL89+#REF!+[12]農業集落排水事業!AL80 -> #REF! | ... AR84: =[12]公共下水道事業!AW89+#REF!+[12]農業集落排水事業!AW80 -> #REF!
E85: ４． | F85: 他会計への支出金 | Z85: =[12]公共下水道事業!AE90+#REF!+[12]農業集落排水事業!AE81 -> #REF! | AA85: =[12]公共下水道事業!AF90+#REF!+[12]農業集落排水事業!AF81 -> #REF! | AB85: =[12]公共下水道事業!AG90+#REF!+[12]農業集落排水事業!AG81 -> #REF! | AC85: =[12]公共下水道事業!AH90+#REF!+[12]農業集落排水事業!AH81 -> #REF! | AD85: =[12]公共下水道事業!AI90+#REF!+[12]農業集落排水事業!AI81 -> #REF! | AE85: =[12]公共下水道事業!AJ90+#REF!+[12]農業集落排水事業!AJ81 -> #REF! | AF85: =[12]公共下水道事業!AK90+#REF!+[12]農業集落排水事業!AK81 -> #REF! | AG85: =[12]公共下水道事業!AL90+#REF!+[12]農業集落排水事業!AL81 -> #REF! | ... AR85: =[12]公共下水道事業!AW90+#REF!+[12]農業集落排水事業!AW81 -> #REF!
E86: ５． | F86: その他 | Z86: =[12]公共下水道事業!AE91+#REF!+[12]農業集落排水事業!AE82 -> #REF! | AA86: =[12]公共下水道事業!AF91+#REF!+[12]農業集落排水事業!AF82 -> #REF! | AB86: =[12]公共下水道事業!AG91+#REF!+[12]農業集落排水事業!AG82 -> #REF! | AC86: =[12]公共下水道事業!AH91+#REF!+[12]農業集落排水事業!AH82 -> #REF! | AD86: =[12]公共下水道事業!AI91+#REF!+[12]農業集落排水事業!AI82 -> #REF! | AE86: =[12]公共下水道事業!AJ91+#REF!+[12]農業集落排水事業!AJ82 -> #REF! | AF86: =[12]公共下水道事業!AK91+#REF!+[12]農業集落排水事業!AK82 -> #REF! | AG86: =[12]公共下水道事業!AL91+#REF!+[12]農業集落排水事業!AL82 -> #REF! | ... AR86: =[12]公共下水道事業!AW91+#REF!+[12]農業集落排水事業!AW82 -> #REF!
E87: 計 | J87: (D) | P87: =SUM(P83:P86)+P81 -> 182406 | Q87: =SUM(Q83:Q86)+Q81 -> 219368 | R87: =SUM(R83:R86)+R81 -> 809040 | S87: =SUM(S83:S86)+S81 -> 100231 | T87: =SUM(T83:T86)+T81 -> 145924 | U87: =SUM(U83:U86)+U81 -> 90209 | V87: =SUM(V83:V86)+V81 -> 81963 | W87: =SUM(W83:W86)+W81 -> 72551 | ... AR87: =SUM(AR83:AR86)+AR81 -> #REF!
C88: 資本的収入額が資本的支出額に不足する額 (D)-(C) | J88: (E) | P88: =P87-P80 -> 76765 | Q88: =Q87-Q80 -> 25858 | R88: =R87-R80 -> 21209 | S88: =S87-S80 -> 18377 | T88: =T87-T80 -> 25815 | U88: =U87-U80 -> 18029 | V88: =V87-V80 -> 15239 | W88: =W87-W80 -> 13519 | ... AR88: =AR87-AR80 -> #REF!
C89: 補塡財源 | E89: １． | F89: 損益勘定留保資金 | P89: 40935 | Q89: 11258 | S89: 13377 | T89: 15872 | U89: 13029 | V89: 10239 | W89: 8519 | X89: 19952 | Y89: 21262 | Z89: =[12]公共下水道事業!AE94+#REF!+[12]農業集落排水事業!AE85 -> #REF! | AA89: =[12]公共下水道事業!AF94+#REF!+[12]農業集落排水事業!AF85 -> #REF! | AB89: =[12]公共下水道事業!AG94+#REF!+[12]農業集落排水事業!AG85 -> #REF! | AC89: =[12]公共下水道事業!AH94+#REF!+[12]農業集落排水事業!AH85 -> #REF! | AD89: =[12]公共下水道事業!AI94+#REF!+[12]農業集落排水事業!AI85 -> #REF! | AE89: =[12]公共下水道事業!AJ94+#REF!+[12]農業集落排水事業!AJ85 -> #REF! | AF89: =[12]公共下水道事業!AK94+#REF!+[12]農業集落排水事業!AK85 -> #REF! | AG89: =[12]公共下水道事業!AL94+#REF!+[12]農業集落排水事業!AL85 -> #REF! | ... AR89: =[12]公共下水道事業!AW94+#REF!+[12]農業集落排水事業!AW85 -> #REF!
E90: ２． | F90: 利益剰余金処分額 | Z90: =[12]公共下水道事業!AE95+#REF!+[12]農業集落排水事業!AE86 -> #REF! | AA90: =[12]公共下水道事業!AF95+#REF!+[12]農業集落排水事業!AF86 -> #REF! | AB90: =[12]公共下水道事業!AG95+#REF!+[12]農業集落排水事業!AG86 -> #REF! | AC90: =[12]公共下水道事業!AH95+#REF!+[12]農業集落排水事業!AH86 -> #REF! | AD90: =[12]公共下水道事業!AI95+#REF!+[12]農業集落排水事業!AI86 -> #REF! | AE90: =[12]公共下水道事業!AJ95+#REF!+[12]農業集落排水事業!AJ86 -> #REF! | AF90: =[12]公共下水道事業!AK95+#REF!+[12]農業集落排水事業!AK86 -> #REF! | AG90: =[12]公共下水道事業!AL95+#REF!+[12]農業集落排水事業!AL86 -> #REF! | ... AR90: =[12]公共下水道事業!AW95+#REF!+[12]農業集落排水事業!AW86 -> #REF!
E91: ３． | F91: 繰越工事資金 | Z91: =[12]公共下水道事業!AE96+#REF!+[12]農業集落排水事業!AE87 -> #REF! | AA91: =[12]公共下水道事業!AF96+#REF!+[12]農業集落排水事業!AF87 -> #REF! | AB91: =[12]公共下水道事業!AG96+#REF!+[12]農業集落排水事業!AG87 -> #REF! | AC91: =[12]公共下水道事業!AH96+#REF!+[12]農業集落排水事業!AH87 -> #REF! | AD91: =[12]公共下水道事業!AI96+#REF!+[12]農業集落排水事業!AI87 -> #REF! | AE91: =[12]公共下水道事業!AJ96+#REF!+[12]農業集落排水事業!AJ87 -> #REF! | AF91: =[12]公共下水道事業!AK96+#REF!+[12]農業集落排水事業!AK87 -> #REF! | AG91: =[12]公共下水道事業!AL96+#REF!+[12]農業集落排水事業!AL87 -> #REF! | ... AR91: =[12]公共下水道事業!AW96+#REF!+[12]農業集落排水事業!AW87 -> #REF!
E92: ４． | F92: その他 | P92: =ROUND(P81*10%,0) -> 9310 | Q92: =ROUND(Q81*10%,0) -> 14600 | R92: 21209 | S92: =ROUND(S81*10%,0) -> 5000 | T92: =ROUND(T81*10%,0) -> 9943 | U92: =ROUND(U81*10%,0) -> 5000 | V92: =ROUND(V81*10%,0) -> 5000 | W92: =ROUND(W81*10%,0) -> 5000 | X92: =ROUND(X81*10%,0) -> 5000 | Y92: =ROUND(Y81*10%,0) -> 6943 | Z92: =[12]公共下水道事業!AE97+#REF!+[12]農業集落排水事業!AE88 -> #REF! | AA92: =[12]公共下水道事業!AF97+#REF!+[12]農業集落排水事業!AF88 -> #REF! | AB92: =[12]公共下水道事業!AG97+#REF!+[12]農業集落排水事業!AG88 -> #REF! | AC92: =[12]公共下水道事業!AH97+#REF!+[12]農業集落排水事業!AH88 -> #REF! | AD92: =[12]公共下水道事業!AI97+#REF!+[12]農業集落排水事業!AI88 -> #REF! | AE92: =[12]公共下水道事業!AJ97+#REF!+[12]農業集落排水事業!AJ88 -> #REF! | AF92: =[12]公共下水道事業!AK97+#REF!+[12]農業集落排水事業!AK88 -> #REF! | AG92: =[12]公共下水道事業!AL97+#REF!+[12]農業集落排水事業!AL88 -> #REF! | ... AR92: =[12]公共下水道事業!AW97+#REF!+[12]農業集落排水事業!AW88 -> #REF!
E93: 計 | J93: (F) | P93: =SUM(P89:P92) -> 50245 | Q93: =SUM(Q89:Q92) -> 25858 | R93: =SUM(R89:R92) -> 21209 | S93: =SUM(S89:S92) -> 18377 | T93: =SUM(T89:T92) -> 25815 | U93: =SUM(U89:U92) -> 18029 | V93: =SUM(V89:V92) -> 15239 | W93: =SUM(W89:W92) -> 13519 | ... AR93: =SUM(AR89:AR92) -> #REF!
C94: 補塡財源不足額 | I94: (E)-(F) | P94: =P88-P93 -> 26520 | Q94: =Q88-Q93 -> 0 | R94: =R88-R93 -> 0 | S94: =S88-S93 -> 0 | T94: =T88-T93 -> 0 | U94: =U88-U93 -> 0 | V94: =V88-V93 -> 0 | W94: =W88-W93 -> 0 | ... AR94: =AR88-AR93 -> #REF!
C95: 他会計借入金残高 | J95: (G) | P95: =[12]公共下水道事業!U100+[12]農業集落排水事業!U91 -> 0 | Q95: =[12]公共下水道事業!V100+[12]農業集落排水事業!V91 -> 0 | R95: =[12]公共下水道事業!W100+[12]農業集落排水事業!W91 -> 0 | S95: =[12]公共下水道事業!X100+[12]農業集落排水事業!X91 -> 0 | T95: =[12]公共下水道事業!Y100+[12]農業集落排水事業!Y91 -> 0 | U95: =[12]公共下水道事業!Z100+[12]農業集落排水事業!Z91 -> 0 | V95: =[12]公共下水道事業!AA100+[12]農業集落排水事業!AA91 -> 0 | W95: =[12]公共下水道事業!AB100+[12]農業集落排水事業!AB91 -> 0 | ... Y95: =[12]公共下水道事業!AD100+[12]農業集落排水事業!AD91 -> 0 | Z95: =[12]公共下水道事業!AE100+#REF!+[12]農業集落排水事業!AE91 -> #REF! | AA95: =[12]公共下水道事業!AF100+#REF!+[12]農業集落排水事業!AF91 -> #REF! | AB95: =[12]公共下水道事業!AG100+#REF!+[12]農業集落排水事業!AG91 -> #REF! | AC95: =[12]公共下水道事業!AH100+#REF!+[12]農業集落排水事業!AH91 -> #REF! | AD95: =[12]公共下水道事業!AI100+#REF!+[12]農業集落排水事業!AI91 -> #REF! | AE95: =[12]公共下水道事業!AJ100+#REF!+[12]農業集落排水事業!AJ91 -> #REF! | AF95: =[12]公共下水道事業!AK100+#REF!+[12]農業集落排水事業!AK91 -> #REF! | AG95: =[12]公共下水道事業!AL100+#REF!+[12]農業集落排水事業!AL91 -> #REF! | ... AR95: =[12]公共下水道事業!AW100+#REF!+[12]農業集落排水事業!AW91 -> #REF!
C96: 企業債残高 | J96: (H) | P96: =P135+P68-P83 -> 395712 | Q96: =P96+Q68-Q83 -> 395344 | R96: =Q96+R68-R83 -> 709804 | S96: =R96+S68-S83 -> 684573 | T96: =S96+T68-T83 -> 687788 | U96: =T96+U68-U83 -> 672579 | V96: =U96+V68-V83 -> 665616 | W96: =V96+W68-W83 -> 668065 | X96: =W96+X68-X83 -> 659518 | Y96: =X96+Y68-Y83 -> 668691 | Z96: =[12]公共下水道事業!AE101+#REF!+[12]農業集落排水事業!AE92 -> #REF! | AA96: =[12]公共下水道事業!AF101+#REF!+[12]農業集落排水事業!AF92 -> #REF! | AB96: =[12]公共下水道事業!AG101+#REF!+[12]農業集落排水事業!AG92 -> #REF! | AC96: =[12]公共下水道事業!AH101+#REF!+[12]農業集落排水事業!AH92 -> #REF! | AD96: =[12]公共下水道事業!AI101+#REF!+[12]農業集落排水事業!AI92 -> #REF! | AE96: =[12]公共下水道事業!AJ101+#REF!+[12]農業集落排水事業!AJ92 -> #REF! | AF96: =[12]公共下水道事業!AK101+#REF!+[12]農業集落排水事業!AK92 -> #REF! | AG96: =[12]公共下水道事業!AL101+#REF!+[12]農業集落排水事業!AL92 -> #REF! | ... AR96: =[12]公共下水道事業!AW101+#REF!+[12]農業集落排水事業!AW92 -> #REF! | AT96: =P96-Y96 -> -272979
C98: ○他会計繰入金 | AT98: 1240550 | AU98: 28130 | AV98: =AT98+AU98 -> 1268680
I99: 年 度 | P99: 令和7年度 | Q99: 令和8年度 | R99: 令和9年度 | S99: 令和10年度 | T99: 令和11年度 | U99: 令和12年度 | V99: 令和13年度 | W99: 令和14年度 | X99: 令和15年度 | Y99: 令和16年度 | Z99: 令和17年度 | AA99: 令和18年度 | AB99: 令和19年度 | AC99: 令和20年度 | AD99: 令和21年度 | AE99: 令和22年度 | AF99: 令和23年度 | AG99: 令和24年度 | AH99: 令和25年度 | AI99: 令和26年度 | AJ99: 令和27年度 | AK99: 令和28年度 | AL99: 令和29年度 | AM99: 令和30年度 | AN99: 令和31年度 | AO99: 令和32年度 | AP99: 令和33年度 | AQ99: 令和34年度 | AR99: 令和35年度
E100: 区 分 | P100: 2025 | Q100: 2026 | R100: 2027 | S100: 2028 | T100: 2029 | U100: 2030 | V100: 2031 | W100: 2032 | X100: 2033 | Y100: 2034 | Z100: 2035 | AA100: 2036 | AB100: 2037 | AC100: 2038 | AD100: 2039 | AE100: 2040 | AF100: 2041 | AG100: 2042 | AH100: 2043 | AI100: 2044 | AJ100: 2045 | AK100: 2046 | AL100: 2047 | AM100: 2048 | AN100: 2049 | AO100: 2050 | AP100: 2051 | AQ100: 2052 | AR100: 2053
C101: 収益的収支分 | P101: =P102+P103 -> 88514 | Q101: =Q102+Q103 -> 83963 | R101: =R102+R103 -> 78957 | S101: =S102+S103 -> 95777 | T101: =T102+T103 -> 91874 | U101: =U102+U103 -> 91481 | V101: =V102+V103 -> 90502 | W101: =W102+W103 -> 89657 | ... AR101: =AR102+AR103 -> #REF! | AT101: 114000 | AU101: 76000 | AV101: =SUM(AT101:AU101) -> 190000
F102: うち基準内繰入金 | P102: =P23 -> 47112 | Q102: =Q23 -> 44631 | R102: =R23 -> 41592 | S102: =S23 -> 60280 | T102: =T23 -> 58152 | U102: =U23 -> 59445 | V102: =V23 -> 60068 | W102: =W23 -> 60745 | ... Y102: =Y23 -> 60864 | Z102: =[12]公共下水道事業!AE107+#REF!+[12]農業集落排水事業!AE98 -> #REF! | AA102: =[12]公共下水道事業!AF107+#REF!+[12]農業集落排水事業!AF98 -> #REF! | AB102: =[12]公共下水道事業!AG107+#REF!+[12]農業集落排水事業!AG98 -> #REF! | AC102: =[12]公共下水道事業!AH107+#REF!+[12]農業集落排水事業!AH98 -> #REF! | AD102: =[12]公共下水道事業!AI107+#REF!+[12]農業集落排水事業!AI98 -> #REF! | AE102: =[12]公共下水道事業!AJ107+#REF!+[12]農業集落排水事業!AJ98 -> #REF! | AF102: =[12]公共下水道事業!AK107+#REF!+[12]農業集落排水事業!AK98 -> #REF! | AG102: =[12]公共下水道事業!AL107+#REF!+[12]農業集落排水事業!AL98 -> #REF! | ... AR102: =[12]公共下水道事業!AW107+#REF!+[12]農業集落排水事業!AW98 -> #REF! | AT102: 19019 | AU102: 6469 | AV102: =SUM(AT102:AU102) -> 25488
F103: うち基準外繰入金 | P103: =P33-P102 -> 41402 | Q103: =ROUND(P103*95%,0) -> 39332 | R103: =ROUND(Q103*95%,0) -> 37365 | S103: =ROUND(R103*95%,0) -> 35497 | T103: =ROUND(S103*95%,0) -> 33722 | U103: =ROUND(T103*95%,0) -> 32036 | V103: =ROUND(U103*95%,0) -> 30434 | W103: =ROUND(V103*95%,0) -> 28912 | X103: =ROUND(W103*95%,0) -> 27466 | Y103: =ROUND(X103*95%,0) -> 26093 | Z103: =[12]公共下水道事業!AE108+#REF!+[12]農業集落排水事業!AE99 -> #REF! | AA103: =[12]公共下水道事業!AF108+#REF!+[12]農業集落排水事業!AF99 -> #REF! | AB103: =[12]公共下水道事業!AG108+#REF!+[12]農業集落排水事業!AG99 -> #REF! | AC103: =[12]公共下水道事業!AH108+#REF!+[12]農業集落排水事業!AH99 -> #REF! | AD103: =[12]公共下水道事業!AI108+#REF!+[12]農業集落排水事業!AI99 -> #REF! | AE103: =[12]公共下水道事業!AJ108+#REF!+[12]農業集落排水事業!AJ99 -> #REF! | AF103: =[12]公共下水道事業!AK108+#REF!+[12]農業集落排水事業!AK99 -> #REF! | AG103: =[12]公共下水道事業!AL108+#REF!+[12]農業集落排水事業!AL99 -> #REF! | ... AR103: =[12]公共下水道事業!AW108+#REF!+[12]農業集落排水事業!AW99 -> #REF! | AV103: =AV102/AV101 -> 0.13414737
C104: 資本的収支分 | P104: =P105+P106 -> 50013 | Q104: =Q105+Q106 -> 46082 | R104: =R105+R106 -> 37403 | S104: =S105+S106 -> 30426 | T104: =T105+T106 -> 24755 | U104: =U105+U106 -> 20752 | V104: =V105+V106 -> 15296 | W104: =W105+W106 -> 7604 | ... AR104: =AR105+AR106 -> #REF!
F105: うち基準内繰入金 | Z105: =[12]公共下水道事業!AE110+#REF!+[12]農業集落排水事業!AE101 -> #REF! | AA105: =[12]公共下水道事業!AF110+#REF!+[12]農業集落排水事業!AF101 -> #REF! | AB105: =[12]公共下水道事業!AG110+#REF!+[12]農業集落排水事業!AG101 -> #REF! | AC105: =[12]公共下水道事業!AH110+#REF!+[12]農業集落排水事業!AH101 -> #REF! | AD105: =[12]公共下水道事業!AI110+#REF!+[12]農業集落排水事業!AI101 -> #REF! | AE105: =[12]公共下水道事業!AJ110+#REF!+[12]農業集落排水事業!AJ101 -> #REF! | AF105: =[12]公共下水道事業!AK110+#REF!+[12]農業集落排水事業!AK101 -> #REF! | AG105: =[12]公共下水道事業!AL110+#REF!+[12]農業集落排水事業!AL101 -> #REF! | ... AR105: =[12]公共下水道事業!AW110+#REF!+[12]農業集落排水事業!AW101 -> #REF!
F106: うち基準外繰入金 | P106: =P70 -> 50013 | Q106: =Q70 -> 46082 | R106: =R70 -> 37403 | S106: =S70 -> 30426 | T106: =T70 -> 24755 | U106: =U70 -> 20752 | V106: =V70 -> 15296 | W106: =W70 -> 7604 | ... Y106: =Y70 -> 1407 | Z106: =[12]公共下水道事業!AE111+#REF!+[12]農業集落排水事業!AE102 -> #REF! | AA106: =[12]公共下水道事業!AF111+#REF!+[12]農業集落排水事業!AF102 -> #REF! | AB106: =[12]公共下水道事業!AG111+#REF!+[12]農業集落排水事業!AG102 -> #REF! | AC106: =[12]公共下水道事業!AH111+#REF!+[12]農業集落排水事業!AH102 -> #REF! | AD106: =[12]公共下水道事業!AI111+#REF!+[12]農業集落排水事業!AI102 -> #REF! | AE106: =[12]公共下水道事業!AJ111+#REF!+[12]農業集落排水事業!AJ102 -> #REF! | AF106: =[12]公共下水道事業!AK111+#REF!+[12]農業集落排水事業!AK102 -> #REF! | AG106: =[12]公共下水道事業!AL111+#REF!+[12]農業集落排水事業!AL102 -> #REF! | ... AR106: =[12]公共下水道事業!AW111+#REF!+[12]農業集落排水事業!AW102 -> #REF!
...

Sheet 【簡易水道】建設改良費の年度別事業費 
N2: （単位：千円）
E3: 計画年次❶ | F3: ❷ | G3: ❸ | H3: ❹ | I3: ❺ | J3: ❻ | K3: ❼ | L3: ❽ | M3: ❾ | N3: ➓
A4: 内容 年度 | C4: 2023 (令和5) | D4: 2024 (令和6) | E4: 令和7 (2025) | F4: 令和8 (2026) | G4: 令和9 (2027) | H4: 令和10 (2028) | I4: 令和11 (2029) | J4: 令和12 (2030) | K4: 令和13 (2031) | L4: 令和14 (2032) | M4: 令和15 (2033) | N4: 令和16 (2034) | S4: 令和8 (2026) | T4: 令和9 (2027) | U4: 令和10 (2028) | V4: 令和11 (2029) | W4: 令和12 (2030) | X4: 令和13 (2031) | Y4: 令和14 (2032) | Z4: 令和15 (2033) | AA4: 令和16 (2034) | AB4: 令和17 (2035)
A5: ❶構築物改良費 | R5: 事業計画 | T5: 10000
A6: 金額 | E6: 38000 | F6: 10000 | G6: 25000 | H6: 110000 | I6: 110000 | J6: 70000 | K6: 60000 | L6: 55000 | M6: 83300 | N6: 121470 | P6: =ROUND(J6/$J$16,4) -> 0.9957 | Q6: =ROUND(P6*$J$19,0) -> 13442 | R6: ストマネ計画策て | T6: 16000
A7: ❷計装設備改良費 | R7: 事業計画 | T7: 10000
A8: 金額 | E8: 12550 | F8: 115300 | G8: 300 | H8: 300 | I8: 300 | J8: 300 | K8: 300 | L8: 300 | M8: 300 | N8: 300 | P8: =ROUND(J8/$J$16,4) -> 0.0043 | Q8: =ROUND(P8*$J$19,0) -> 58 | R8: ストマネ計画策て | T8: 16000
A9: ❸取水・浄水設備 | R9: 事業計画 | T9: 10000
A10: 金額 | C10: 18000 | D10: 18000 | E10: =Sheet3!N12 -> 0 | F10: =Sheet3!O12 -> 0 | G10: =Sheet3!P12 -> 0 | H10: =Sheet3!Q12 -> 0 | I10: =Sheet3!R12 -> 0 | J10: =Sheet3!S12 -> 0 | K10: =Sheet3!T12 -> 0 | L10: =Sheet3!U12 -> 0 | ... N10: =Sheet3!W12 -> 0 | P10: =ROUND(J10/$J$16,4) -> 0 | R10: ストマネ計画策て | T10: 16000
A11: ❹配水・給水設備
A12: 金額 | P12: =ROUND(J12/$J$16,4) -> 0 | Q12: =ROUND(P12*$J$19,0) -> 0
A13: ❺管路
A14: 金額 | C14: 18000 | D14: 18000 | E14: =Sheet3!N14 -> 0 | F14: =Sheet3!O14 -> 0 | G14: =Sheet3!P14 -> 0 | H14: =Sheet3!Q14 -> 0 | I14: =Sheet3!R14 -> 0 | K14: =Sheet3!T14 -> 0 | L14: =Sheet3!U14 -> 0 | M14: =Sheet3!V14 -> 0 | N14: =Sheet3!W14 -> 0 | P14: =ROUND(J14/$J$16,4) -> 0 | Q14: =ROUND(P14*$J$19,0) -> 0
A15: 内容 年度 | C15: 2023 (令和5) | D15: 2024 (令和6) | E15: 令和7 (2025) | F15: 令和8 (2026) | G15: 令和9 (2027) | H15: 令和10 (2028) | I15: 令和11 (2029) | J15: 令和12 (2030) | K15: 令和13 (2031) | L15: 令和14 (2032) | M15: 令和15 (2033) | N15: 令和16 (2034)
A16: 事業費合計 | C16: =#REF!+#REF!+C14+#REF!+#REF!+#REF!+#REF!+C12+#REF!+C10+C6 -> #REF! | D16: =#REF!+#REF!+D14+#REF!+#REF!+#REF!+#REF!+D12+#REF!+D10+D6 -> #REF! | E16: =E6+E10+E12+E14+E8 -> 50550 | F16: =F6+F10+F12+F14+F8 -> 125300 | G16: =G6+G10+G12+G14+G8 -> 25300 | H16: =H6+H10+H12+H14+H8 -> 110300 | I16: =I6+I10+I12+I14+I8 -> 110300 | J16: =J6+J10+J12+J14+J8 -> 70300 | K16: =K6+K10+K12+K14+K8 -> 60300 | L16: =L6+L10+L12+L14+L8 -> 55300 | ... N16: =N6+N10+N12+N14+N8 -> 121770
A17: 財源内訳
A18: ①国庫補助金
A19: 金額 | E19: 3700 | F19: 34500 | G19: 0 | H19: 30000 | I19: 30000 | J19: 13500 | K19: 15000 | L19: 13500 | M19: 13500 | N19: 13500
A20: ②受益者負担金
A21: 金額
A22: ②企業債
A23: 金額 | E23: 32300 | F23: 80100 | G23: 16100 | H23: 70500 | I23: 70500 | J23: 44900 | K23: 38500 | L23: 35300 | M23: 53400 | N23: 77800
A24: ③工事負担金
A25: 金額 | E25: 3033 | F25: 7518 | G25: 1518 | H25: 6618 | I25: 6618 | J25: 4218 | K25: 3618 | L25: 3318 | M25: 5016 | N25: 7306
A26: ④自己財源
A27: 金額 | E27: =E16-E19-E23-E25 -> 11517 | F27: =F16-F19-F23-F25 -> 3182 | G27: =G16-G19-G23-G25 -> 7682 | H27: =H16-H19-H23-H25 -> 3182 | I27: =I16-I19-I23-I25 -> 3182 | J27: =J16-J19-J23-J25 -> 7682 | K27: =K16-K19-K23-K25 -> 3182 | L27: =L16-L19-L23-L25 -> 3182 | ... N27: =N16-N19-N23-N25 -> 23164
A29: 差額 | E29: =E16-E19-E21-E23-E25 -> 11517 | F29: =F16-F19-F21-F23-F25 -> 3182 | G29: =G16-G19-G21-G23-G25 -> 7682 | H29: =H16-H19-H21-H23-H25 -> 3182 | I29: =I16-I19-I21-I23-I25 -> 3182 | J29: =J16-J19-J21-J23-J25 -> 7682 | K29: =K16-K19-K21-K23-K25 -> 3182 | L29: =L16-L19-L21-L23-L25 -> 3182 | ... N29: =N16-N19-N21-N23-N25 -> 23164
A30: [注]
C33: =SUM(C19:C25) -> 0 | D33: =SUM(D19:D25) -> 0 | E33: =SUM(E19:E25) -> 39033 | F33: =SUM(F19:F25) -> 122118 | G33: =SUM(G19:G25) -> 17618 | H33: =SUM(H19:H25) -> 107118 | I33: =SUM(I19:I25) -> 107118 | J33: =SUM(J19:J25) -> 62618 | ... N33: =SUM(N19:N25) -> 98606
C35: =C16-C33 -> #REF! | D35: =D16-D33 -> #REF! | E35: =E16-E33 -> 11517 | F35: =F16-F33 -> 3182 | G35: =G16-G33 -> 7682 | H35: =H16-H33 -> 3182 | I35: =I16-I33 -> 3182 | J35: =J16-J33 -> 7682 | ... N35: =N16-N33 -> 23164
C37: =SUM(C19,C21,C25) -> 0 | D37: =SUM(D19,D21,D25) -> 0 | E37: =SUM(E19,E21,E25) -> 6733 | F37: =SUM(F19,F21,F25) -> 42018 | G37: =SUM(G19,G21,G25) -> 1518 | H37: =SUM(H19,H21,H25) -> 36618 | I37: =SUM(I19,I21,I25) -> 36618 | J37: =SUM(J19,J21,J25) -> 17718 | ... N37: =SUM(N19,N21,N25) -> 20806
E41: =#REF!+#REF! -> #REF! | F41: =#REF!+#REF! -> #REF! | G41: =#REF!+#REF! -> #REF! | H41: =#REF!+#REF! -> #REF! | I41: =#REF!+#REF! -> #REF! | J41: =#REF!+#REF! -> #REF! | K41: =#REF!+#REF! -> #REF! | L41: =#REF!+#REF! -> #REF! | ... N41: =#REF!+#REF! -> #REF!
E42: =E16-E41 -> #REF! | F42: =F16-F41 -> #REF! | G42: =G16-G41 -> #REF! | H42: =H16-H41 -> #REF! | I42: =I16-I41 -> #REF! | J42: =J16-J41 -> #REF! | K42: =K16-K41 -> #REF! | L42: =L16-L41 -> #REF! | ... N42: =N16-N41 -> #REF!
F43: 200 | G43: 0.4 | H43: =F43/G43 -> 500
G44: 0.6 | H44: =F43/G44 -> 333.33333
E46: 投資３億円で調整
E50: =ROUND((E6+E10+E12+#REF!+#REF!)*45%,0) -> #REF! | F50: =ROUND((F6+F10+F12+#REF!+#REF!)*45%,0) -> #REF! | G50: =ROUND((G6+G10+G12+#REF!+#REF!)*45%,0) -> #REF! | H50: =ROUND((H6+H10+H12+#REF!+#REF!)*45%,0) -> #REF! | I50: =ROUND((I6+I10+I12+#REF!+#REF!)*45%,0) -> #REF! | J50: =ROUND((J6+J10+J12+#REF!+#REF!)*45%,0) -> #REF! | K50: =ROUND((K6+K10+K12+#REF!+#REF!)*45%,0) -> #REF! | L50: =ROUND((L6+L10+L12+#REF!+#REF!)*45%,0) -> #REF! | ... N50: =ROUND((N6+N10+N12+#REF!+#REF!)*45%,0) -> #REF!

Sheet 簡水現況予測
A1: 3事業合算 | P1: 令和7年度 | Q1: 令和8年度 | R1: 令和9年度 | S1: 令和10年度 | T1: 令和11年度 | U1: 令和12年度 | V1: 令和13年度 | W1: 令和14年度 | X1: 令和15年度 | Y1: 令和16年度 | Z1: 令和17年度 | AA1: 令和18年度 | AB1: 令和19年度 | AC1: 令和20年度 | AD1: 令和21年度 | AE1: 令和22年度 | AF1: 令和23年度 | AG1: 令和24年度 | AH1: 令和25年度 | AI1: 令和26年度 | AJ1: 令和27年度 | AK1: 令和28年度 | AL1: 令和29年度 | AM1: 令和30年度 | AN1: 令和31年度 | AO1: 令和32年度 | AP1: 令和33年度 | AQ1: 令和34年度 | AR1: 令和35年度
P2: 2025 | Q2: 2026 | R2: 2027 | S2: 2028 | T2: 2029 | U2: 2030 | V2: 2031 | W2: 2032 | X2: 2033 | Y2: 2034 | Z2: 2035 | AA2: 2036 | AB2: 2037 | AC2: 2038 | AD2: 2039 | AE2: 2040 | AF2: 2041 | AG2: 2042 | AH2: 2043 | AI2: 2044 | AJ2: 2045 | AK2: 2046 | AL2: 2047 | AM2: 2048 | AN2: 2049 | AO2: 2050 | AP2: 2051 | AQ2: 2052 | AR2: 2053 | AS2: 2055
D3: 普及率 | J3: 10(000)_行政区域内人口 | AT3: =[12]公共下水道事業!AY3 -> 75263
D4: 水洗化率 | J4: 10(000)_処理区域内人口
D5: 有収水量 | J5: 10(000)_水洗化人口
J6: 10(000)_現在処理区域面積
J7: 10(000)_年間総処理水量
J8: 10(000)_年間有収水量
J10: 人口一人当たりの有収水量
J11: 人口一人当たりの使用料（使用料収入÷水洗化人口）
J12: 20㎥あたりの使用料（使用料収入÷年間有収水量×20）
J13: 普及率 | P13: =P5/P3 -> #DIV/0! | Q13: =Q5/Q3 -> #DIV/0! | R13: =R5/R3 -> #DIV/0! | S13: =S5/S3 -> #DIV/0! | T13: =T5/T3 -> #DIV/0! | U13: =U5/U3 -> #DIV/0! | V13: =V5/V3 -> #DIV/0! | W13: =W5/W3 -> #DIV/0! | ... AR13: =AR5/AR3 -> #DIV/0!
J14: 水洗化率 | P14: =AVERAGE($K$14:$M$14) -> #DIV/0! | Q14: =AVERAGE($K$14:$M$14) -> #DIV/0! | R14: =AVERAGE($K$14:$M$14) -> #DIV/0! | S14: =AVERAGE($K$14:$M$14) -> #DIV/0! | T14: =AVERAGE($K$14:$M$14) -> #DIV/0! | U14: =AVERAGE($K$14:$M$14) -> #DIV/0! | V14: =AVERAGE($K$14:$M$14) -> #DIV/0! | W14: =AVERAGE($K$14:$M$14) -> #DIV/0! | ... AR14: =AVERAGE($K$14:$M$14) -> #DIV/0!
J16: 汚水処理費（A） | P16: =P53-P35-P103-P30 -> 72463 | Q16: =Q53-Q35-Q103-Q30 -> 73868 | R16: =R53-R35-R103-R30 -> 78891 | S16: =S53-S35-S103-S30 -> 78669 | T16: =T53-T35-T103-T30 -> 81007 | U16: =U53-U35-U103-U30 -> 83584 | V16: =V53-V35-V103-V30 -> 84428 | W16: =W53-W35-W103-W30 -> 82474 | ... Y16: =Y53-Y35-Y103-Y30 -> 79306 | Z16: =[12]公共下水道事業!AE16+#REF!+[12]農業集落排水事業!AE16 -> #REF! | AA16: =[12]公共下水道事業!AF16+#REF!+[12]農業集落排水事業!AF16 -> #REF! | AB16: =[12]公共下水道事業!AG16+#REF!+[12]農業集落排水事業!AG16 -> #REF! | AC16: =[12]公共下水道事業!AH16+#REF!+[12]農業集落排水事業!AH16 -> #REF! | AD16: =[12]公共下水道事業!AI16+#REF!+[12]農業集落排水事業!AI16 -> #REF! | AE16: =[12]公共下水道事業!AJ16+#REF!+[12]農業集落排水事業!AJ16 -> #REF! | AF16: =[12]公共下水道事業!AK16+#REF!+[12]農業集落排水事業!AK16 -> #REF! | AG16: =[12]公共下水道事業!AL16+#REF!+[12]農業集落排水事業!AL16 -> #REF! | ... AR16: =[12]公共下水道事業!AW16+#REF!+[12]農業集落排水事業!AW16 -> #REF!
J17: 使用料収入（B） | P17: =P28 -> 83606 | Q17: =Q28 -> 83564 | R17: =R28 -> 83752 | S17: =S28 -> 83524 | T17: =T28 -> 83482 | U17: =U28 -> 83482 | V17: =V28 -> 83669 | W17: =W28 -> 83400 | ... Y17: =Y28 -> 83400 | Z17: =[12]公共下水道事業!AE19+#REF!+[12]農業集落排水事業!AE19 -> #REF! | AA17: =[12]公共下水道事業!AF19+#REF!+[12]農業集落排水事業!AF19 -> #REF! | AB17: =[12]公共下水道事業!AG19+#REF!+[12]農業集落排水事業!AG19 -> #REF! | AC17: =[12]公共下水道事業!AH19+#REF!+[12]農業集落排水事業!AH19 -> #REF! | AD17: =[12]公共下水道事業!AI19+#REF!+[12]農業集落排水事業!AI19 -> #REF! | AE17: =[12]公共下水道事業!AJ19+#REF!+[12]農業集落排水事業!AJ19 -> #REF! | AF17: =[12]公共下水道事業!AK19+#REF!+[12]農業集落排水事業!AK19 -> #REF! | AG17: =[12]公共下水道事業!AL19+#REF!+[12]農業集落排水事業!AL19 -> #REF! | ... AR17: =[12]公共下水道事業!AW19+#REF!+[12]農業集落排水事業!AW19 -> #REF!
J18: 経費回収率（B÷A） | P18: =P17/P16 -> 1.153775 | Q18: =Q17/Q16 -> 1.1312612 | R18: =R17/R16 -> 1.0616167 | S18: =S17/S16 -> 1.0617143 | T18: =T17/T16 -> 1.0305529 | U18: =U17/U16 -> 0.99877967 | V18: =V17/V16 -> 0.99101009 | W18: =W17/W16 -> 1.0112278 | ... AR18: =AR17/AR16 -> #REF!
J19: 有収水量（C） | P19: =予測!F36 -> 741320 | Q19: =予測!G36 -> 740950 | R19: =予測!H36 -> 742610 | S19: =予測!I36 -> 740590 | T19: =予測!J36 -> 740220 | U19: =予測!K36 -> 740220 | V19: =予測!L36 -> 741880 | W19: =予測!M36 -> 739490 | ... Y19: =予測!O36 -> 739490 | Z19: =Z8 -> 0 | AA19: =AA8 -> 0 | AB19: =AB8 -> 0 | AC19: =AC8 -> 0 | AD19: =AD8 -> 0 | AE19: =AE8 -> 0 | AF19: =AF8 -> 0 | AG19: =AG8 -> 0 | ... AR19: =AR8 -> 0
J20: 汚水処理原価（A÷C） | P20: =P16/P19*1000 -> 97.748611 | Q20: =Q16/Q19*1000 -> 99.693637 | R20: =R16/R19*1000 -> 106.23477 | S20: =S16/S19*1000 -> 106.22477 | T20: =T16/T19*1000 -> 109.43638 | U20: =U16/U19*1000 -> 112.91778 | V20: =V16/V19*1000 -> 113.80277 | W20: =W16/W19*1000 -> 111.52822 | ... AR20: =AR16/AR19*1000 -> #REF!
J21: 経常収支比率 | P21: =P37/P53 -> 1.102176 | Q21: =Q37/Q53 -> 1.0916274 | R21: =R37/R53 -> 1.0571733 | S21: =S37/S53 -> 1.0584482 | T21: =T37/T53 -> 1.0424948 | U21: =U37/U53 -> 1.0257771 | V21: =V37/V53 -> 1.0215803 | W21: =W37/W53 -> 1.0321522 | ... AR21: =AR37/AR53 -> #REF!
J24: 3条
I25: 年 度 | P25: 令和7年度 | Q25: 令和8年度 | R25: 令和9年度 | S25: 令和10年度 | T25: 令和11年度 | U25: 令和12年度 | V25: 令和13年度 | W25: 令和14年度 | X25: 令和15年度 | Y25: 令和16年度 | Z25: 令和17年度 | AA25: 令和18年度 | AB25: 令和19年度 | AC25: 令和20年度 | AD25: 令和21年度 | AE25: 令和22年度 | AF25: 令和23年度 | AG25: 令和24年度 | AH25: 令和25年度 | AI25: 令和26年度 | AJ25: 令和27年度 | AK25: 令和28年度 | AL25: 令和29年度 | AM25: 令和30年度 | AN25: 令和31年度 | AO25: 令和32年度 | AP25: 令和33年度 | AQ25: 令和34年度 | AR25: 令和35年度
C26: 区 分 | P26: 2025 | Q26: 2026 | R26: 2027 | S26: 2028 | T26: 2029 | U26: 2030 | V26: 2031 | W26: 2032 | X26: 2033 | Y26: 2034 | Z26: 2035 | AA26: 2036 | AB26: 2037 | AC26: 2038 | AD26: 2039 | AE26: 2040 | AF26: 2041 | AG26: 2042 | AH26: 2043 | AI26: 2044 | AJ26: 2045 | AK26: 2046 | AL26: 2047 | AM26: 2048 | AN26: 2049 | AO26: 2050 | AP26: 2051 | AQ26: 2052 | AR26: 2053
B27: 収益的収支 | C27: 収益的収入 | D27: １． | E27: 営業収益 | J27: (A) | P27: =SUM(P28:P30) -> 137386 | Q27: =SUM(Q28:Q30) -> 137344 | R27: =SUM(R28:R30) -> 137532 | S27: =SUM(S28:S30) -> 137304 | T27: =SUM(T28:T30) -> 137262 | U27: =SUM(U28:U30) -> 137262 | V27: =SUM(V28:V30) -> 137449 | W27: =SUM(W28:W30) -> 137180 | ... AR27: =SUM(AR28:AR30) -> #REF!
D28: (1) | F28: 料金収入 | P28: =予測!F41 -> 83606 | Q28: =予測!G41 -> 83564 | R28: =予測!H41 -> 83752 | S28: =予測!I41 -> 83524 | T28: =予測!J41 -> 83482 | U28: =予測!K41 -> 83482 | V28: =予測!L41 -> 83669 | W28: =予測!M41 -> 83400 | ... Y28: =予測!O41 -> 83400 | Z28: =[12]公共下水道事業!AE30+#REF!+[12]農業集落排水事業!AE30 -> #REF! | AA28: =[12]公共下水道事業!AF30+#REF!+[12]農業集落排水事業!AF30 -> #REF! | AB28: =[12]公共下水道事業!AG30+#REF!+[12]農業集落排水事業!AG30 -> #REF! | AC28: =[12]公共下水道事業!AH30+#REF!+[12]農業集落排水事業!AH30 -> #REF! | AD28: =[12]公共下水道事業!AI30+#REF!+[12]農業集落排水事業!AI30 -> #REF! | AE28: =[12]公共下水道事業!AJ30+#REF!+[12]農業集落排水事業!AJ30 -> #REF! | AF28: =[12]公共下水道事業!AK30+#REF!+[12]農業集落排水事業!AK30 -> #REF! | AG28: =[12]公共下水道事業!AL30+#REF!+[12]農業集落排水事業!AL30 -> #REF! | ... AR28: =[12]公共下水道事業!AW30+#REF!+[12]農業集落排水事業!AW30 -> #REF!
D29: (2) | F29: 受託工事 | P29: 0 | Q29: 0 | R29: 0 | S29: 0 | T29: 0 | U29: 0 | V29: 0 | W29: 0 | X29: 0 | Y29: 0 | Z29: =[12]公共下水道事業!AE31+#REF!+[12]農業集落排水事業!AE31 -> #REF! | AA29: =[12]公共下水道事業!AF31+#REF!+[12]農業集落排水事業!AF31 -> #REF! | AB29: =[12]公共下水道事業!AG31+#REF!+[12]農業集落排水事業!AG31 -> #REF! | AC29: =[12]公共下水道事業!AH31+#REF!+[12]農業集落排水事業!AH31 -> #REF! | AD29: =[12]公共下水道事業!AI31+#REF!+[12]農業集落排水事業!AI31 -> #REF! | AE29: =[12]公共下水道事業!AJ31+#REF!+[12]農業集落排水事業!AJ31 -> #REF! | AF29: =[12]公共下水道事業!AK31+#REF!+[12]農業集落排水事業!AK31 -> #REF! | AG29: =[12]公共下水道事業!AL31+#REF!+[12]農業集落排水事業!AL31 -> #REF! | ... AR29: =[12]公共下水道事業!AW31+#REF!+[12]農業集落排水事業!AW31 -> #REF!
D30: (3) | F30: その他 | P30: 53780 | Q30: 53780 | R30: 53780 | S30: 53780 | T30: 53780 | U30: 53780 | V30: 53780 | W30: 53780 | X30: 53780 | Y30: 53780 | Z30: =[12]公共下水道事業!AE32+#REF!+[12]農業集落排水事業!AE32 -> #REF! | AA30: =[12]公共下水道事業!AF32+#REF!+[12]農業集落排水事業!AF32 -> #REF! | AB30: =[12]公共下水道事業!AG32+#REF!+[12]農業集落排水事業!AG32 -> #REF! | AC30: =[12]公共下水道事業!AH32+#REF!+[12]農業集落排水事業!AH32 -> #REF! | AD30: =[12]公共下水道事業!AI32+#REF!+[12]農業集落排水事業!AI32 -> #REF! | AE30: =[12]公共下水道事業!AJ32+#REF!+[12]農業集落排水事業!AJ32 -> #REF! | AF30: =[12]公共下水道事業!AK32+#REF!+[12]農業集落排水事業!AK32 -> #REF! | AG30: =[12]公共下水道事業!AL32+#REF!+[12]農業集落排水事業!AL32 -> #REF! | ... AR30: =[12]公共下水道事業!AW32+#REF!+[12]農業集落排水事業!AW32 -> #REF!
D31: ２． | E31: 営業外収益 | P31: =P32+P35+P36 -> 29457 | Q31: =Q32+Q35+Q36 -> 29687 | R31: =R32+R35+R36 -> 32305 | S31: =S32+S35+S36 -> 28920 | T31: =T32+T35+T36 -> 29533 | U31: =U32+U35+U36 -> 30749 | V31: =V32+V35+V36 -> 31313 | W31: =W32+W35+W36 -> 31356 | ... Y31: =Y32+Y35+Y36 -> 28737 | Z31: =[12]公共下水道事業!AE33+#REF!+[12]農業集落排水事業!AE33 -> #REF! | AA31: =[12]公共下水道事業!AF33+#REF!+[12]農業集落排水事業!AF33 -> #REF! | AB31: =[12]公共下水道事業!AG33+#REF!+[12]農業集落排水事業!AG33 -> #REF! | AC31: =[12]公共下水道事業!AH33+#REF!+[12]農業集落排水事業!AH33 -> #REF! | AD31: =[12]公共下水道事業!AI33+#REF!+[12]農業集落排水事業!AI33 -> #REF! | AE31: =[12]公共下水道事業!AJ33+#REF!+[12]農業集落排水事業!AJ33 -> #REF! | AF31: =[12]公共下水道事業!AK33+#REF!+[12]農業集落排水事業!AK33 -> #REF! | AG31: =[12]公共下水道事業!AL33+#REF!+[12]農業集落排水事業!AL33 -> #REF! | ... AR31: =[12]公共下水道事業!AW33+#REF!+[12]農業集落排水事業!AW33 -> #REF!
D32: (1) | F32: 補助金 | P32: =P33+P34 -> 5720 | Q32: =Q33+Q34 -> 5955 | R32: =R33+R34 -> 6412 | S32: =S33+S34 -> 6531 | T32: =T33+T34 -> 7190 | U32: =U33+U34 -> 7795 | V32: =V33+V34 -> 8129 | W32: =W33+W34 -> 8392 | ... Y32: =Y33+Y34 -> 9033 | Z32: =[12]公共下水道事業!AE34+#REF!+[12]農業集落排水事業!AE34 -> #REF! | AA32: =[12]公共下水道事業!AF34+#REF!+[12]農業集落排水事業!AF34 -> #REF! | AB32: =[12]公共下水道事業!AG34+#REF!+[12]農業集落排水事業!AG34 -> #REF! | AC32: =[12]公共下水道事業!AH34+#REF!+[12]農業集落排水事業!AH34 -> #REF! | AD32: =[12]公共下水道事業!AI34+#REF!+[12]農業集落排水事業!AI34 -> #REF! | AE32: =[12]公共下水道事業!AJ34+#REF!+[12]農業集落排水事業!AJ34 -> #REF! | AF32: =[12]公共下水道事業!AK34+#REF!+[12]農業集落排水事業!AK34 -> #REF! | AG32: =[12]公共下水道事業!AL34+#REF!+[12]農業集落排水事業!AL34 -> #REF! | ... AR32: =[12]公共下水道事業!AW34+#REF!+[12]農業集落排水事業!AW34 -> #REF!
G33: 他会計補助金 | P33: 5720 | Q33: 5955 | R33: 6412 | S33: 6531 | T33: 7190 | U33: 7795 | V33: 8129 | W33: 8392 | X33: 8626 | Y33: 9033 | Z33: =[12]公共下水道事業!AE35+#REF!+[12]農業集落排水事業!AE35 -> #REF! | AA33: =[12]公共下水道事業!AF35+#REF!+[12]農業集落排水事業!AF35 -> #REF! | AB33: =[12]公共下水道事業!AG35+#REF!+[12]農業集落排水事業!AG35 -> #REF! | AC33: =[12]公共下水道事業!AH35+#REF!+[12]農業集落排水事業!AH35 -> #REF! | AD33: =[12]公共下水道事業!AI35+#REF!+[12]農業集落排水事業!AI35 -> #REF! | AE33: =[12]公共下水道事業!AJ35+#REF!+[12]農業集落排水事業!AJ35 -> #REF! | AF33: =[12]公共下水道事業!AK35+#REF!+[12]農業集落排水事業!AK35 -> #REF! | AG33: =[12]公共下水道事業!AL35+#REF!+[12]農業集落排水事業!AL35 -> #REF! | ... AR33: =[12]公共下水道事業!AW35+#REF!+[12]農業集落排水事業!AW35 -> #REF!
G34: その他補助金 | Z34: =[12]公共下水道事業!AE36+#REF!+[12]農業集落排水事業!AE36 -> #REF! | AA34: =[12]公共下水道事業!AF36+#REF!+[12]農業集落排水事業!AF36 -> #REF! | AB34: =[12]公共下水道事業!AG36+#REF!+[12]農業集落排水事業!AG36 -> #REF! | AC34: =[12]公共下水道事業!AH36+#REF!+[12]農業集落排水事業!AH36 -> #REF! | AD34: =[12]公共下水道事業!AI36+#REF!+[12]農業集落排水事業!AI36 -> #REF! | AE34: =[12]公共下水道事業!AJ36+#REF!+[12]農業集落排水事業!AJ36 -> #REF! | AF34: =[12]公共下水道事業!AK36+#REF!+[12]農業集落排水事業!AK36 -> #REF! | AG34: =[12]公共下水道事業!AL36+#REF!+[12]農業集落排水事業!AL36 -> #REF! | ... AR34: =[12]公共下水道事業!AW36+#REF!+[12]農業集落排水事業!AW36 -> #REF!
D35: (2) | F35: 長期前受金戻入 | P35: 23704 | Q35: 23699 | R35: 25860 | S35: 22356 | T35: 22310 | U35: 22921 | V35: 23151 | W35: 22931 | X35: 22427 | Y35: 19671 | Z35: =[12]公共下水道事業!AE37+#REF!+[12]農業集落排水事業!AE37 -> #REF! | AA35: =[12]公共下水道事業!AF37+#REF!+[12]農業集落排水事業!AF37 -> #REF! | AB35: =[12]公共下水道事業!AG37+#REF!+[12]農業集落排水事業!AG37 -> #REF! | AC35: =[12]公共下水道事業!AH37+#REF!+[12]農業集落排水事業!AH37 -> #REF! | AD35: =[12]公共下水道事業!AI37+#REF!+[12]農業集落排水事業!AI37 -> #REF! | AE35: =[12]公共下水道事業!AJ37+#REF!+[12]農業集落排水事業!AJ37 -> #REF! | AF35: =[12]公共下水道事業!AK37+#REF!+[12]農業集落排水事業!AK37 -> #REF! | AG35: =[12]公共下水道事業!AL37+#REF!+[12]農業集落排水事業!AL37 -> #REF! | ... AR35: =[12]公共下水道事業!AW37+#REF!+[12]農業集落排水事業!AW37 -> #REF!
D36: (3) | F36: その他 | P36: 33 | Q36: 33 | R36: 33 | S36: 33 | T36: 33 | U36: 33 | V36: 33 | W36: 33 | X36: 33 | Y36: 33 | Z36: =[12]公共下水道事業!AE38+#REF!+[12]農業集落排水事業!AE38 -> #REF! | AA36: =[12]公共下水道事業!AF38+#REF!+[12]農業集落排水事業!AF38 -> #REF! | AB36: =[12]公共下水道事業!AG38+#REF!+[12]農業集落排水事業!AG38 -> #REF! | AC36: =[12]公共下水道事業!AH38+#REF!+[12]農業集落排水事業!AH38 -> #REF! | AD36: =[12]公共下水道事業!AI38+#REF!+[12]農業集落排水事業!AI38 -> #REF! | AE36: =[12]公共下水道事業!AJ38+#REF!+[12]農業集落排水事業!AJ38 -> #REF! | AF36: =[12]公共下水道事業!AK38+#REF!+[12]農業集落排水事業!AK38 -> #REF! | AG36: =[12]公共下水道事業!AL38+#REF!+[12]農業集落排水事業!AL38 -> #REF! | ... AR36: =[12]公共下水道事業!AW38+#REF!+[12]農業集落排水事業!AW38 -> #REF!
D37: 収入計 | J37: (C) | P37: =P27+P31 -> 166843 | Q37: =Q27+Q31 -> 167031 | R37: =R27+R31 -> 169837 | S37: =S27+S31 -> 166224 | T37: =T27+T31 -> 166795 | U37: =U27+U31 -> 168011 | V37: =V27+V31 -> 168762 | W37: =W27+W31 -> 168536 | ... AR37: =AR27+AR31 -> #REF!
C38: 収益的支出 | D38: １． | E38: 営業費用 | P38: =P39+P43+P49+P48 -> 148259 | Q38: =Q39+Q43+Q49+Q48 -> 149424 | R38: =R39+R43+R49+R48 -> 156151 | S38: =S39+S43+S49+S48 -> 152306 | T38: =T39+T43+T49+T48 -> 153938 | U38: =U39+U43+U49+U48 -> 156522 | V38: =V39+V43+V49+V48 -> 157262 | W38: =W39+W43+W49+W48 -> 154825 | ... Y38: =Y39+Y43+Y49+Y48 -> 147755 | Z38: =Z39+Z43+Z49 -> #REF! | AA38: =AA39+AA43+AA49 -> #REF! | AB38: =AB39+AB43+AB49 -> #REF! | AC38: =AC39+AC43+AC49 -> #REF! | AD38: =AD39+AD43+AD49 -> #REF! | AE38: =AE39+AE43+AE49 -> #REF! | AF38: =AF39+AF43+AF49 -> #REF! | AG38: =AG39+AG43+AG49 -> #REF! | ... AR38: =AR39+AR43+AR49 -> #REF!
D39: (1) | F39: 職員給与費 | P39: =SUM(P40:P42) -> 22733 | Q39: =SUM(Q40:Q42) -> 22812 | R39: =SUM(R40:R42) -> 22891 | S39: =SUM(S40:S42) -> 22970 | T39: =SUM(T40:T42) -> 23049 | U39: =SUM(U40:U42) -> 23128 | V39: =SUM(V40:V42) -> 23207 | W39: =SUM(W40:W42) -> 23286 | ... AR39: =SUM(AR40:AR42) -> #REF!
G40: 基本給 | P40: 9380 | Q40: 9418 | R40: 9456 | S40: 9494 | T40: 9532 | U40: 9570 | V40: 9608 | W40: 9646 | X40: 9684 | Y40: 9722 | Z40: =[12]公共下水道事業!AE42+#REF!+[12]農業集落排水事業!AE42 -> #REF! | AA40: =[12]公共下水道事業!AF42+#REF!+[12]農業集落排水事業!AF42 -> #REF! | AB40: =[12]公共下水道事業!AG42+#REF!+[12]農業集落排水事業!AG42 -> #REF! | AC40: =[12]公共下水道事業!AH42+#REF!+[12]農業集落排水事業!AH42 -> #REF! | AD40: =[12]公共下水道事業!AI42+#REF!+[12]農業集落排水事業!AI42 -> #REF! | AE40: =[12]公共下水道事業!AJ42+#REF!+[12]農業集落排水事業!AJ42 -> #REF! | AF40: =[12]公共下水道事業!AK42+#REF!+[12]農業集落排水事業!AK42 -> #REF! | AG40: =[12]公共下水道事業!AL42+#REF!+[12]農業集落排水事業!AL42 -> #REF! | ... AR40: =[12]公共下水道事業!AW42+#REF!+[12]農業集落排水事業!AW42 -> #REF!
G41: 退職給付費 | Z41: =[12]公共下水道事業!AE43+#REF!+[12]農業集落排水事業!AE43 -> #REF! | AA41: =[12]公共下水道事業!AF43+#REF!+[12]農業集落排水事業!AF43 -> #REF! | AB41: =[12]公共下水道事業!AG43+#REF!+[12]農業集落排水事業!AG43 -> #REF! | AC41: =[12]公共下水道事業!AH43+#REF!+[12]農業集落排水事業!AH43 -> #REF! | AD41: =[12]公共下水道事業!AI43+#REF!+[12]農業集落排水事業!AI43 -> #REF! | AE41: =[12]公共下水道事業!AJ43+#REF!+[12]農業集落排水事業!AJ43 -> #REF! | AF41: =[12]公共下水道事業!AK43+#REF!+[12]農業集落排水事業!AK43 -> #REF! | AG41: =[12]公共下水道事業!AL43+#REF!+[12]農業集落排水事業!AL43 -> #REF! | ... AR41: =[12]公共下水道事業!AW43+#REF!+[12]農業集落排水事業!AW43 -> #REF!
G42: その他 | P42: 13353 | Q42: 13394 | R42: 13435 | S42: 13476 | T42: 13517 | U42: 13558 | V42: 13599 | W42: 13640 | X42: 13681 | Y42: 13722 | Z42: =[12]公共下水道事業!AE44+#REF!+[12]農業集落排水事業!AE44 -> #REF! | AA42: =[12]公共下水道事業!AF44+#REF!+[12]農業集落排水事業!AF44 -> #REF! | AB42: =[12]公共下水道事業!AG44+#REF!+[12]農業集落排水事業!AG44 -> #REF! | AC42: =[12]公共下水道事業!AH44+#REF!+[12]農業集落排水事業!AH44 -> #REF! | AD42: =[12]公共下水道事業!AI44+#REF!+[12]農業集落排水事業!AI44 -> #REF! | AE42: =[12]公共下水道事業!AJ44+#REF!+[12]農業集落排水事業!AJ44 -> #REF! | AF42: =[12]公共下水道事業!AK44+#REF!+[12]農業集落排水事業!AK44 -> #REF! | AG42: =[12]公共下水道事業!AL44+#REF!+[12]農業集落排水事業!AL44 -> #REF! | ... AR42: =[12]公共下水道事業!AW44+#REF!+[12]農業集落排水事業!AW44 -> #REF! | AU42: 0.02
D43: (2) | F43: 経費 | P43: =SUM(P44:P47) -> 77116 | Q43: =SUM(Q44:Q47) -> 77576 | R43: =SUM(R44:R47) -> 78061 | S43: =SUM(S44:S47) -> 78520 | T43: =SUM(T44:T47) -> 79003 | U43: =SUM(U44:U47) -> 79388 | V43: =SUM(V44:V47) -> 79794 | W43: =SUM(W44:W47) -> 80158 | ... AR43: =SUM(AR44:AR47) -> #REF! | AU43: 0/%
G44: 動力費 | P44: 5132 | Q44: 5199 | R44: 5280 | S44: 5342 | T44: 5417 | U44: 5478 | V44: 5552 | W44: 5593 | X44: 5654 | Y44: 5715 | Z44: =[12]公共下水道事業!AE46+#REF!+[12]農業集落排水事業!AE46 -> #REF! | AA44: =[12]公共下水道事業!AF46+#REF!+[12]農業集落排水事業!AF46 -> #REF! | AB44: =[12]公共下水道事業!AG46+#REF!+[12]農業集落排水事業!AG46 -> #REF! | AC44: =[12]公共下水道事業!AH46+#REF!+[12]農業集落排水事業!AH46 -> #REF! | AD44: =[12]公共下水道事業!AI46+#REF!+[12]農業集落排水事業!AI46 -> #REF! | AE44: =[12]公共下水道事業!AJ46+#REF!+[12]農業集落排水事業!AJ46 -> #REF! | AF44: =[12]公共下水道事業!AK46+#REF!+[12]農業集落排水事業!AK46 -> #REF! | AG44: =[12]公共下水道事業!AL46+#REF!+[12]農業集落排水事業!AL46 -> #REF! | ... AR44: =[12]公共下水道事業!AW46+#REF!+[12]農業集落排水事業!AW46 -> #REF! | AS44: 4112 | AT44: =ROUND(AS44/$AS$48,4) -> 0.1375 | AU44: =ROUND($AU$42*AT44,4) -> 0.0028 | AY44: 245208
G45: 修繕費 | P45: 7436 | Q45: 7540 | R45: 7646 | S45: 7753 | T45: 7862 | U45: 7948 | V45: 8035 | W45: 8123 | X45: 8212 | Y45: 8302 | Z45: =[12]公共下水道事業!AE47+#REF!+[12]農業集落排水事業!AE47 -> #REF! | AA45: =[12]公共下水道事業!AF47+#REF!+[12]農業集落排水事業!AF47 -> #REF! | AB45: =[12]公共下水道事業!AG47+#REF!+[12]農業集落排水事業!AG47 -> #REF! | AC45: =[12]公共下水道事業!AH47+#REF!+[12]農業集落排水事業!AH47 -> #REF! | AD45: =[12]公共下水道事業!AI47+#REF!+[12]農業集落排水事業!AI47 -> #REF! | AE45: =[12]公共下水道事業!AJ47+#REF!+[12]農業集落排水事業!AJ47 -> #REF! | AF45: =[12]公共下水道事業!AK47+#REF!+[12]農業集落排水事業!AK47 -> #REF! | AG45: =[12]公共下水道事業!AL47+#REF!+[12]農業集落排水事業!AL47 -> #REF! | ... AR45: =[12]公共下水道事業!AW47+#REF!+[12]農業集落排水事業!AW47 -> #REF! | AS45: 8879 | AT45: =ROUND(AS45/$AS$48,4) -> 0.2968 | AU45: =ROUND($AU$42*AT45,4) -> 0.0059 | AY45: 4710
G46: 材料費 | P46: 101 | Q46: 102 | R46: 103 | S46: 104 | T46: 105 | U46: 106 | V46: 107 | W46: 108 | X46: 109 | Y46: 110 | Z46: =[12]公共下水道事業!AE48+#REF!+[12]農業集落排水事業!AE48 -> #REF! | AA46: =[12]公共下水道事業!AF48+#REF!+[12]農業集落排水事業!AF48 -> #REF! | AB46: =[12]公共下水道事業!AG48+#REF!+[12]農業集落排水事業!AG48 -> #REF! | AC46: =[12]公共下水道事業!AH48+#REF!+[12]農業集落排水事業!AH48 -> #REF! | AD46: =[12]公共下水道事業!AI48+#REF!+[12]農業集落排水事業!AI48 -> #REF! | AE46: =[12]公共下水道事業!AJ48+#REF!+[12]農業集落排水事業!AJ48 -> #REF! | AF46: =[12]公共下水道事業!AK48+#REF!+[12]農業集落排水事業!AK48 -> #REF! | AG46: =[12]公共下水道事業!AL48+#REF!+[12]農業集落排水事業!AL48 -> #REF! | ... AR46: =[12]公共下水道事業!AW48+#REF!+[12]農業集落排水事業!AW48 -> #REF! | AS46: 168 | AT46: =ROUND(AS46/$AS$48,4) -> 0.0056 | AU46: =ROUND($AU$42*AT46,4) -> 0.0001 | AY46: 22513
G47: その他 | P47: 64447 | Q47: 64735 | R47: 65032 | S47: 65321 | T47: 65619 | U47: 65856 | V47: 66100 | W47: 66334 | X47: 66577 | Y47: 66823 | Z47: =[12]公共下水道事業!AE49+#REF!+[12]農業集落排水事業!AE49 -> #REF! | AA47: =[12]公共下水道事業!AF49+#REF!+[12]農業集落排水事業!AF49 -> #REF! | AB47: =[12]公共下水道事業!AG49+#REF!+[12]農業集落排水事業!AG49 -> #REF! | AC47: =[12]公共下水道事業!AH49+#REF!+[12]農業集落排水事業!AH49 -> #REF! | AD47: =[12]公共下水道事業!AI49+#REF!+[12]農業集落排水事業!AI49 -> #REF! | AE47: =[12]公共下水道事業!AJ49+#REF!+[12]農業集落排水事業!AJ49 -> #REF! | AF47: =[12]公共下水道事業!AK49+#REF!+[12]農業集落排水事業!AK49 -> #REF! | AG47: =[12]公共下水道事業!AL49+#REF!+[12]農業集落排水事業!AL49 -> #REF! | ... AR47: =[12]公共下水道事業!AW49+#REF!+[12]農業集落排水事業!AW49 -> #REF! | AS47: 16757 | AT47: =ROUND(AS47/$AS$48,4) -> 0.5601 | AU47: =ROUND($AU$42*AT47,4) -> 0.0112 | AY47: 169845
D48: (3) | F48: 流域下水道負担金 | AS48: =SUM(AS44:AS47) -> 29916 | AX48: 99450 | AY48: 6793
D49: (3) | F49: 減価償却費 | P49: 48410 | Q49: 49036 | R49: 55199 | S49: 50816 | T49: 51886 | U49: 54006 | V49: 54261 | W49: 51381 | X49: 48534 | Y49: 43361 | Z49: =[12]公共下水道事業!AE50+#REF!+[12]農業集落排水事業!AE50 -> #REF! | AA49: =[12]公共下水道事業!AF50+#REF!+[12]農業集落排水事業!AF50 -> #REF! | AB49: =[12]公共下水道事業!AG50+#REF!+[12]農業集落排水事業!AG50 -> #REF! | AC49: =[12]公共下水道事業!AH50+#REF!+[12]農業集落排水事業!AH50 -> #REF! | AD49: =[12]公共下水道事業!AI50+#REF!+[12]農業集落排水事業!AI50 -> #REF! | AE49: =[12]公共下水道事業!AJ50+#REF!+[12]農業集落排水事業!AJ50 -> #REF! | AF49: =[12]公共下水道事業!AK50+#REF!+[12]農業集落排水事業!AK50 -> #REF! | AG49: =[12]公共下水道事業!AL50+#REF!+[12]農業集落排水事業!AL50 -> #REF! | ... AR49: =[12]公共下水道事業!AW50+#REF!+[12]農業集落排水事業!AW50 -> #REF! | AX49: 1325 | AY49: 250
D50: ２． | E50: 営業外費用 | P50: =P51+P52 -> 3117 | Q50: =Q51+Q52 -> 3587 | R50: =R51+R52 -> 4501 | S50: =S51+S52 -> 4739 | T50: =T51+T52 -> 6058 | U50: =U51+U52 -> 7267 | V50: =V51+V52 -> 7935 | W50: =W51+W52 -> 8461 | ... AR50: =AR51+AR52 -> #REF! | AX50: =SUM(AX48:AX49) -> 100775 | AY50: 169
D51: (1) | F51: 支払利息 | P51: 2857 | Q51: 3327 | R51: 4241 | S51: 4479 | T51: 5798 | U51: 7007 | V51: 7675 | W51: 8201 | X51: 8669 | Y51: 9484 | Z51: =[12]公共下水道事業!AE52+#REF!+[12]農業集落排水事業!AE52 -> #REF! | AA51: =[12]公共下水道事業!AF52+#REF!+[12]農業集落排水事業!AF52 -> #REF! | AB51: =[12]公共下水道事業!AG52+#REF!+[12]農業集落排水事業!AG52 -> #REF! | AC51: =[12]公共下水道事業!AH52+#REF!+[12]農業集落排水事業!AH52 -> #REF! | AD51: =[12]公共下水道事業!AI52+#REF!+[12]農業集落排水事業!AI52 -> #REF! | AE51: =[12]公共下水道事業!AJ52+#REF!+[12]農業集落排水事業!AJ52 -> #REF! | AF51: =[12]公共下水道事業!AK52+#REF!+[12]農業集落排水事業!AK52 -> #REF! | AG51: =[12]公共下水道事業!AL52+#REF!+[12]農業集落排水事業!AL52 -> #REF! | ... AR51: =[12]公共下水道事業!AW52+#REF!+[12]農業集落排水事業!AW52 -> #REF! | AX51: =AX50-SUM(AS44:AS47,AX49) -> 69534 | AY51: =SUM(AY45:AY50) -> 204280
D52: (2) | F52: その他 | P52: 260 | Q52: 260 | R52: 260 | S52: 260 | T52: 260 | U52: 260 | V52: 260 | W52: 260 | X52: 260 | Y52: 260 | Z52: =[12]公共下水道事業!AE53+#REF!+[12]農業集落排水事業!AE53 -> #REF! | AA52: =[12]公共下水道事業!AF53+#REF!+[12]農業集落排水事業!AF53 -> #REF! | AB52: =[12]公共下水道事業!AG53+#REF!+[12]農業集落排水事業!AG53 -> #REF! | AC52: =[12]公共下水道事業!AH53+#REF!+[12]農業集落排水事業!AH53 -> #REF! | AD52: =[12]公共下水道事業!AI53+#REF!+[12]農業集落排水事業!AI53 -> #REF! | AE52: =[12]公共下水道事業!AJ53+#REF!+[12]農業集落排水事業!AJ53 -> #REF! | AF52: =[12]公共下水道事業!AK53+#REF!+[12]農業集落排水事業!AK53 -> #REF! | AG52: =[12]公共下水道事業!AL53+#REF!+[12]農業集落排水事業!AL53 -> #REF! | ... AR52: =[12]公共下水道事業!AW53+#REF!+[12]農業集落排水事業!AW53 -> #REF! | AY52: =AY44-AY51 -> 40928
D53: 支出計 | J53: (D) | P53: =P38+P50 -> 151376 | Q53: =Q38+Q50 -> 153011 | R53: =R38+R50 -> 160652 | S53: =S38+S50 -> 157045 | T53: =T38+T50 -> 159996 | U53: =U38+U50 -> 163789 | V53: =V38+V50 -> 165197 | W53: =W38+W50 -> 163286 | ... AR53: =AR38+AR50 -> #REF!
C54: 経常損益 | H54: (C)-(D) | J54: (E) | P54: =P37-P53 -> 15467 | Q54: =Q37-Q53 -> 14020 | R54: =R37-R53 -> 9185 | S54: =S37-S53 -> 9179 | T54: =T37-T53 -> 6799 | U54: =U37-U53 -> 4222 | V54: =V37-V53 -> 3565 | W54: =W37-W53 -> 5250 | ... AR54: =AR37-AR53 -> #REF!
B55: 特別利益 | J55: (F) | Z55: =[12]公共下水道事業!AE56+#REF!+[12]農業集落排水事業!AE56 -> #REF! | AA55: =[12]公共下水道事業!AF56+#REF!+[12]農業集落排水事業!AF56 -> #REF! | AB55: =[12]公共下水道事業!AG56+#REF!+[12]農業集落排水事業!AG56 -> #REF! | AC55: =[12]公共下水道事業!AH56+#REF!+[12]農業集落排水事業!AH56 -> #REF! | AD55: =[12]公共下水道事業!AI56+#REF!+[12]農業集落排水事業!AI56 -> #REF! | AE55: =[12]公共下水道事業!AJ56+#REF!+[12]農業集落排水事業!AJ56 -> #REF! | AF55: =[12]公共下水道事業!AK56+#REF!+[12]農業集落排水事業!AK56 -> #REF! | AG55: =[12]公共下水道事業!AL56+#REF!+[12]農業集落排水事業!AL56 -> #REF! | ... AR55: =[12]公共下水道事業!AW56+#REF!+[12]農業集落排水事業!AW56 -> #REF!
B56: 特別損失 | J56: (G) | Z56: =[12]公共下水道事業!AE57+#REF!+[12]農業集落排水事業!AE57 -> #REF! | AA56: =[12]公共下水道事業!AF57+#REF!+[12]農業集落排水事業!AF57 -> #REF! | AB56: =[12]公共下水道事業!AG57+#REF!+[12]農業集落排水事業!AG57 -> #REF! | AC56: =[12]公共下水道事業!AH57+#REF!+[12]農業集落排水事業!AH57 -> #REF! | AD56: =[12]公共下水道事業!AI57+#REF!+[12]農業集落排水事業!AI57 -> #REF! | AE56: =[12]公共下水道事業!AJ57+#REF!+[12]農業集落排水事業!AJ57 -> #REF! | AF56: =[12]公共下水道事業!AK57+#REF!+[12]農業集落排水事業!AK57 -> #REF! | AG56: =[12]公共下水道事業!AL57+#REF!+[12]農業集落排水事業!AL57 -> #REF! | ... AR56: =[12]公共下水道事業!AW57+#REF!+[12]農業集落排水事業!AW57 -> #REF!
B57: 特別損益 | H57: (F)-(G) | J57: (H) | P57: =P55-P56 -> 0 | Q57: =Q55-Q56 -> 0 | R57: =R55-R56 -> 0 | S57: =S55-S56 -> 0 | T57: =T55-T56 -> 0 | U57: =U55-U56 -> 0 | V57: =V55-V56 -> 0 | W57: =W55-W56 -> 0 | ... AR57: =AR55-AR56 -> #REF!
B58: 当年度純利益（又は純損失） | I58: (E)+(H) | P58: =P54+P57 -> 15467 | Q58: =Q54+Q57 -> 14020 | R58: =R54+R57 -> 9185 | S58: =S54+S57 -> 9179 | T58: =T54+T57 -> 6799 | U58: =U54+U57 -> 4222 | V58: =V54+V57 -> 3565 | W58: =W54+W57 -> 5250 | ... AR58: =AR54+AR57 -> #REF!
B59: 繰越利益剰余金 | P59: =P58-P91 -> 15467 | Q59: =Q58+P59-Q91 -> 29487 | R59: =R58+Q59-R91 -> 38672 | S59: =S58+R59-S91 -> 47851 | T59: =T58+S59-T91 -> 54650 | U59: =U58+T59-U91 -> 58872 | V59: =V58+U59-V91 -> 62437 | W59: =W58+V59-W91 -> 67687 | X59: =X58+W59-X91 -> 74573 | Y59: =Y58+X59-Y91 -> 82991
B61: 経常収支比率 | P61: =P21 -> 1.102176 | Q61: =Q21 -> 1.0916274 | R61: =R21 -> 1.0571733 | S61: =S21 -> 1.0584482 | T61: =T21 -> 1.0424948 | U61: =U21 -> 1.0257771 | V61: =V21 -> 1.0215803 | W61: =W21 -> 1.0321522 | ... Y61: =Y21 -> 1.053448
B62: 料金回収率 | P62: =ROUND(P63/P64,4) -> 0.6717 | Q62: =ROUND(Q63/Q64,4) -> 0.668 | R62: =ROUND(R63/R64,4) -> 0.6506 | S62: =ROUND(S63/S64,4) -> 0.6675 | T62: =ROUND(T63/T64,4) -> 0.6569 | U62: =ROUND(U63/U64,4) -> 0.6478 | V62: =ROUND(V63/V64,4) -> 0.6422 | W62: =ROUND(W63/W64,4) -> 0.6497 | ... Y62: =ROUND(Y63/Y64,4) -> 0.6803
B63: 給水原価 | P63: =ROUND(P28*1000/予測!F36,1) -> 112.8 | Q63: =ROUND(Q28*1000/予測!G36,1) -> 112.8 | R63: =ROUND(R28*1000/予測!H36,1) -> 112.8 | S63: =ROUND(S28*1000/予測!I36,1) -> 112.8 | T63: =ROUND(T28*1000/予測!J36,1) -> 112.8 | U63: =ROUND(U28*1000/予測!K36,1) -> 112.8 | V63: =ROUND(V28*1000/予測!L36,1) -> 112.8 | W63: =ROUND(W28*1000/予測!M36,1) -> 112.8 | ... Y63: =ROUND(Y28*1000/予測!O36,1) -> 112.8
B64: 供給原価 | P64: =ROUND((P53-P30/2)*1000/予測!F36,2) -> 167.92 | Q64: =ROUND((Q53-Q30/2-1000)*1000/予測!G36,2) -> 168.87 | R64: =ROUND((R53-R30/2-5000)*1000/予測!H36,2) -> 173.39 | S64: =ROUND((S53-S30/2-5000)*1000/予測!I36,2) -> 168.99 | T64: =ROUND((T53-T30/2-6000)*1000/予測!J36,2) -> 171.71 | U64: =ROUND((U53-U30/2-8000)*1000/予測!K36,2) -> 174.14 | V64: =ROUND((V53-V30/2-8000)*1000/予測!L36,2) -> 175.64 | W64: =ROUND((W53-W30/2-8000)*1000/予測!M36,2) -> 173.63 | X64: =ROUND((X53-X30/2-8000)*1000/予測!N36,2) -> 171.05 | Y64: =ROUND((Y53-Y30/2-8000)*1000/予測!O36,2) -> 165.8
J66: 4条
I67: 年 度 | P67: 令和7年度 | Q67: 令和8年度 | R67: 令和9年度 | S67: 令和10年度 | T67: 令和11年度 | U67: 令和12年度 | V67: 令和13年度 | W67: 令和14年度 | X67: 令和15年度 | Y67: 令和16年度 | Z67: 令和17年度 | AA67: 令和18年度 | AB67: 令和19年度 | AC67: 令和20年度 | AD67: 令和21年度 | AE67: 令和22年度 | AF67: 令和23年度 | AG67: 令和24年度 | AH67: 令和25年度 | AI67: 令和26年度 | AJ67: 令和27年度 | AK67: 令和28年度 | AL67: 令和29年度 | AM67: 令和30年度 | AN67: 令和31年度 | AO67: 令和32年度 | AP67: 令和33年度 | AQ67: 令和34年度 | AR67: 令和35年度
E68: 区 分 | P68: 2025 | Q68: 2026 | R68: 2027 | S68: 2028 | T68: 2029 | U68: 2030 | V68: 2031 | W68: 2032 | X68: 2033 | Y68: 2034 | Z68: 2035 | AA68: 2036 | AB68: 2037 | AC68: 2038 | AD68: 2039 | AE68: 2040 | AF68: 2041 | AG68: 2042 | AH68: 2043 | AI68: 2044 | AJ68: 2045 | AK68: 2046 | AL68: 2047 | AM68: 2048 | AN68: 2049 | AO68: 2050 | AP68: 2051 | AQ68: 2052 | AR68: 2053
C69: 資本的収支 | D69: 資本的収入 | E69: １． | F69: 企業債 | P69: ='【簡易水道】建設改良費の年度別事業費 '!E23 -> 32300 | Q69: ='【簡易水道】建設改良費の年度別事業費 '!F23 -> 80100 | R69: ='【簡易水道】建設改良費の年度別事業費 '!G23 -> 16100 | S69: ='【簡易水道】建設改良費の年度別事業費 '!H23 -> 70500 | T69: ='【簡易水道】建設改良費の年度別事業費 '!I23 -> 70500 | U69: ='【簡易水道】建設改良費の年度別事業費 '!J23 -> 44900 | V69: ='【簡易水道】建設改良費の年度別事業費 '!K23 -> 38500 | W69: ='【簡易水道】建設改良費の年度別事業費 '!L23 -> 35300 | ... Y69: ='【簡易水道】建設改良費の年度別事業費 '!N23 -> 77800 | Z69: =[12]公共下水道事業!AE73+#REF!+[12]農業集落排水事業!AE64 -> #REF! | AA69: =[12]公共下水道事業!AF73+#REF!+[12]農業集落排水事業!AF64 -> #REF! | AB69: =[12]公共下水道事業!AG73+#REF!+[12]農業集落排水事業!AG64 -> #REF! | AC69: =[12]公共下水道事業!AH73+#REF!+[12]農業集落排水事業!AH64 -> #REF! | AD69: =[12]公共下水道事業!AI73+#REF!+[12]農業集落排水事業!AI64 -> #REF! | AE69: =[12]公共下水道事業!AJ73+#REF!+[12]農業集落排水事業!AJ64 -> #REF! | AF69: =[12]公共下水道事業!AK73+#REF!+[12]農業集落排水事業!AK64 -> #REF! | AG69: =[12]公共下水道事業!AL73+#REF!+[12]農業集落排水事業!AL64 -> #REF! | ... AR69: =[12]公共下水道事業!AW73+#REF!+[12]農業集落排水事業!AW64 -> #REF!
F70: うち資本費平準化債 | Z70: =[12]公共下水道事業!AE74+#REF!+[12]農業集落排水事業!AE65 -> #REF! | AA70: =[12]公共下水道事業!AF74+#REF!+[12]農業集落排水事業!AF65 -> #REF! | AB70: =[12]公共下水道事業!AG74+#REF!+[12]農業集落排水事業!AG65 -> #REF! | AC70: =[12]公共下水道事業!AH74+#REF!+[12]農業集落排水事業!AH65 -> #REF! | AD70: =[12]公共下水道事業!AI74+#REF!+[12]農業集落排水事業!AI65 -> #REF! | AE70: =[12]公共下水道事業!AJ74+#REF!+[12]農業集落排水事業!AJ65 -> #REF! | AF70: =[12]公共下水道事業!AK74+#REF!+[12]農業集落排水事業!AK65 -> #REF! | AG70: =[12]公共下水道事業!AL74+#REF!+[12]農業集落排水事業!AL65 -> #REF! | ... AR70: =[12]公共下水道事業!AW74+#REF!+[12]農業集落排水事業!AW65 -> #REF!
E71: ２． | F71: 他会計出資金 | Z71: =[12]公共下水道事業!AE75+#REF!+[12]農業集落排水事業!AE66 -> #REF! | AA71: =[12]公共下水道事業!AF75+#REF!+[12]農業集落排水事業!AF66 -> #REF! | AB71: =[12]公共下水道事業!AG75+#REF!+[12]農業集落排水事業!AG66 -> #REF! | AC71: =[12]公共下水道事業!AH75+#REF!+[12]農業集落排水事業!AH66 -> #REF! | AD71: =[12]公共下水道事業!AI75+#REF!+[12]農業集落排水事業!AI66 -> #REF! | AE71: =[12]公共下水道事業!AJ75+#REF!+[12]農業集落排水事業!AJ66 -> #REF! | AF71: =[12]公共下水道事業!AK75+#REF!+[12]農業集落排水事業!AK66 -> #REF! | AG71: =[12]公共下水道事業!AL75+#REF!+[12]農業集落排水事業!AL66 -> #REF! | ... AR71: =[12]公共下水道事業!AW75+#REF!+[12]農業集落排水事業!AW66 -> #REF!
E72: ３． | F72: 他会計補助金 | Z72: =[12]公共下水道事業!AE76+#REF!+[12]農業集落排水事業!AE67 -> #REF! | AA72: =[12]公共下水道事業!AF76+#REF!+[12]農業集落排水事業!AF67 -> #REF! | AB72: =[12]公共下水道事業!AG76+#REF!+[12]農業集落排水事業!AG67 -> #REF! | AC72: =[12]公共下水道事業!AH76+#REF!+[12]農業集落排水事業!AH67 -> #REF! | AD72: =[12]公共下水道事業!AI76+#REF!+[12]農業集落排水事業!AI67 -> #REF! | AE72: =[12]公共下水道事業!AJ76+#REF!+[12]農業集落排水事業!AJ67 -> #REF! | AF72: =[12]公共下水道事業!AK76+#REF!+[12]農業集落排水事業!AK67 -> #REF! | AG72: =[12]公共下水道事業!AL76+#REF!+[12]農業集落排水事業!AL67 -> #REF! | ... AR72: =[12]公共下水道事業!AW76+#REF!+[12]農業集落排水事業!AW67 -> #REF!
E73: ４． | F73: 他会計負担金 | P73: 7940 | Q73: 7940 | R73: 7940 | S73: 7940 | T73: 7940 | U73: 7940 | V73: 7940 | W73: 7940 | X73: 7940 | Y73: 7940 | Z73: =[12]公共下水道事業!AE77+#REF!+[12]農業集落排水事業!AE68 -> #REF! | AA73: =[12]公共下水道事業!AF77+#REF!+[12]農業集落排水事業!AF68 -> #REF! | AB73: =[12]公共下水道事業!AG77+#REF!+[12]農業集落排水事業!AG68 -> #REF! | AC73: =[12]公共下水道事業!AH77+#REF!+[12]農業集落排水事業!AH68 -> #REF! | AD73: =[12]公共下水道事業!AI77+#REF!+[12]農業集落排水事業!AI68 -> #REF! | AE73: =[12]公共下水道事業!AJ77+#REF!+[12]農業集落排水事業!AJ68 -> #REF! | AF73: =[12]公共下水道事業!AK77+#REF!+[12]農業集落排水事業!AK68 -> #REF! | AG73: =[12]公共下水道事業!AL77+#REF!+[12]農業集落排水事業!AL68 -> #REF! | ... AR73: =[12]公共下水道事業!AW77+#REF!+[12]農業集落排水事業!AW68 -> #REF!
E74: ５． | F74: 他会計借入金 | Z74: =[12]公共下水道事業!AE78+#REF!+[12]農業集落排水事業!AE69 -> #REF! | AA74: =[12]公共下水道事業!AF78+#REF!+[12]農業集落排水事業!AF69 -> #REF! | AB74: =[12]公共下水道事業!AG78+#REF!+[12]農業集落排水事業!AG69 -> #REF! | AC74: =[12]公共下水道事業!AH78+#REF!+[12]農業集落排水事業!AH69 -> #REF! | AD74: =[12]公共下水道事業!AI78+#REF!+[12]農業集落排水事業!AI69 -> #REF! | AE74: =[12]公共下水道事業!AJ78+#REF!+[12]農業集落排水事業!AJ69 -> #REF! | AF74: =[12]公共下水道事業!AK78+#REF!+[12]農業集落排水事業!AK69 -> #REF! | AG74: =[12]公共下水道事業!AL78+#REF!+[12]農業集落排水事業!AL69 -> #REF! | ... AR74: =[12]公共下水道事業!AW78+#REF!+[12]農業集落排水事業!AW69 -> #REF!
E75: ６． | F75: 国（都道府県）補助金 | P75: ='【簡易水道】建設改良費の年度別事業費 '!E19 -> 3700 | Q75: ='【簡易水道】建設改良費の年度別事業費 '!F19 -> 34500 | R75: ='【簡易水道】建設改良費の年度別事業費 '!G19 -> 0 | S75: ='【簡易水道】建設改良費の年度別事業費 '!H19 -> 30000 | T75: ='【簡易水道】建設改良費の年度別事業費 '!I19 -> 30000 | U75: ='【簡易水道】建設改良費の年度別事業費 '!J19 -> 13500 | V75: ='【簡易水道】建設改良費の年度別事業費 '!K19 -> 15000 | W75: ='【簡易水道】建設改良費の年度別事業費 '!L19 -> 13500 | ... Y75: ='【簡易水道】建設改良費の年度別事業費 '!N19 -> 13500 | Z75: =[12]公共下水道事業!AE79+#REF!+[12]農業集落排水事業!AE70 -> #REF! | AA75: =[12]公共下水道事業!AF79+#REF!+[12]農業集落排水事業!AF70 -> #REF! | AB75: =[12]公共下水道事業!AG79+#REF!+[12]農業集落排水事業!AG70 -> #REF! | AC75: =[12]公共下水道事業!AH79+#REF!+[12]農業集落排水事業!AH70 -> #REF! | AD75: =[12]公共下水道事業!AI79+#REF!+[12]農業集落排水事業!AI70 -> #REF! | AE75: =[12]公共下水道事業!AJ79+#REF!+[12]農業集落排水事業!AJ70 -> #REF! | AF75: =[12]公共下水道事業!AK79+#REF!+[12]農業集落排水事業!AK70 -> #REF! | AG75: =[12]公共下水道事業!AL79+#REF!+[12]農業集落排水事業!AL70 -> #REF! | ... AR75: =[12]公共下水道事業!AW79+#REF!+[12]農業集落排水事業!AW70 -> #REF!
E76: ７． | F76: 固定資産売却代金 | Z76: =[12]公共下水道事業!AE80+#REF!+[12]農業集落排水事業!AE71 -> #REF! | AA76: =[12]公共下水道事業!AF80+#REF!+[12]農業集落排水事業!AF71 -> #REF! | AB76: =[12]公共下水道事業!AG80+#REF!+[12]農業集落排水事業!AG71 -> #REF! | AC76: =[12]公共下水道事業!AH80+#REF!+[12]農業集落排水事業!AH71 -> #REF! | AD76: =[12]公共下水道事業!AI80+#REF!+[12]農業集落排水事業!AI71 -> #REF! | AE76: =[12]公共下水道事業!AJ80+#REF!+[12]農業集落排水事業!AJ71 -> #REF! | AF76: =[12]公共下水道事業!AK80+#REF!+[12]農業集落排水事業!AK71 -> #REF! | AG76: =[12]公共下水道事業!AL80+#REF!+[12]農業集落排水事業!AL71 -> #REF! | ... AR76: =[12]公共下水道事業!AW80+#REF!+[12]農業集落排水事業!AW71 -> #REF!
E77: ８． | F77: 工事負担金 | P77: ='【簡易水道】建設改良費の年度別事業費 '!E25 -> 3033 | Q77: ='【簡易水道】建設改良費の年度別事業費 '!F25 -> 7518 | R77: ='【簡易水道】建設改良費の年度別事業費 '!G25 -> 1518 | S77: ='【簡易水道】建設改良費の年度別事業費 '!H25 -> 6618 | T77: ='【簡易水道】建設改良費の年度別事業費 '!I25 -> 6618 | U77: ='【簡易水道】建設改良費の年度別事業費 '!J25 -> 4218 | V77: ='【簡易水道】建設改良費の年度別事業費 '!K25 -> 3618 | W77: ='【簡易水道】建設改良費の年度別事業費 '!L25 -> 3318 | ... Y77: ='【簡易水道】建設改良費の年度別事業費 '!N25 -> 7306 | Z77: =[12]公共下水道事業!AE81+#REF!+[12]農業集落排水事業!AE72 -> #REF! | AA77: =[12]公共下水道事業!AF81+#REF!+[12]農業集落排水事業!AF72 -> #REF! | AB77: =[12]公共下水道事業!AG81+#REF!+[12]農業集落排水事業!AG72 -> #REF! | AC77: =[12]公共下水道事業!AH81+#REF!+[12]農業集落排水事業!AH72 -> #REF! | AD77: =[12]公共下水道事業!AI81+#REF!+[12]農業集落排水事業!AI72 -> #REF! | AE77: =[12]公共下水道事業!AJ81+#REF!+[12]農業集落排水事業!AJ72 -> #REF! | AF77: =[12]公共下水道事業!AK81+#REF!+[12]農業集落排水事業!AK72 -> #REF! | AG77: =[12]公共下水道事業!AL81+#REF!+[12]農業集落排水事業!AL72 -> #REF! | ... AR77: =[12]公共下水道事業!AW81+#REF!+[12]農業集落排水事業!AW72 -> #REF!
E78: ９． | F78: その他 | Z78: =[12]公共下水道事業!AE82+#REF!+[12]農業集落排水事業!AE73 -> #REF! | AA78: =[12]公共下水道事業!AF82+#REF!+[12]農業集落排水事業!AF73 -> #REF! | AB78: =[12]公共下水道事業!AG82+#REF!+[12]農業集落排水事業!AG73 -> #REF! | AC78: =[12]公共下水道事業!AH82+#REF!+[12]農業集落排水事業!AH73 -> #REF! | AD78: =[12]公共下水道事業!AI82+#REF!+[12]農業集落排水事業!AI73 -> #REF! | AE78: =[12]公共下水道事業!AJ82+#REF!+[12]農業集落排水事業!AJ73 -> #REF! | AF78: =[12]公共下水道事業!AK82+#REF!+[12]農業集落排水事業!AK73 -> #REF! | AG78: =[12]公共下水道事業!AL82+#REF!+[12]農業集落排水事業!AL73 -> #REF! | ... AR78: =[12]公共下水道事業!AW82+#REF!+[12]農業集落排水事業!AW73 -> #REF!
E79: 計 | J79: (A) | P79: =SUM(P69,P71:P78) -> 46973 | Q79: =SUM(Q69,Q71:Q78) -> 130058 | R79: =SUM(R69,R71:R78) -> 25558 | S79: =SUM(S69,S71:S78) -> 115058 | T79: =SUM(T69,T71:T78) -> 115058 | U79: =SUM(U69,U71:U78) -> 70558 | V79: =SUM(V69,V71:V78) -> 65058 | W79: =SUM(W69,W71:W78) -> 60058 | ... Y79: =SUM(Y69,Y71:Y78) -> 106546 | Z79: =SUM(Z69:Z78) -> #REF! | AA79: =SUM(AA69:AA78) -> #REF! | AB79: =SUM(AB69:AB78) -> #REF! | AC79: =SUM(AC69:AC78) -> #REF! | AD79: =SUM(AD69:AD78) -> #REF! | AE79: =SUM(AE69:AE78) -> #REF! | AF79: =SUM(AF69:AF78) -> #REF! | AG79: =SUM(AG69:AG78) -> #REF! | ... AR79: =SUM(AR69:AR78) -> #REF!
E80: (A)のうち翌年度へ繰り越される支出の財源充当額 | J80: (B) | P80: =[12]公共下水道事業!U84+[12]農業集落排水事業!U75 -> 0 | Q80: =[12]公共下水道事業!V84+[12]農業集落排水事業!V75 -> 0 | R80: =[12]公共下水道事業!W84+[12]農業集落排水事業!W75 -> 0 | S80: =[12]公共下水道事業!X84+[12]農業集落排水事業!X75 -> 0 | T80: =[12]公共下水道事業!Y84+[12]農業集落排水事業!Y75 -> 0 | U80: =[12]公共下水道事業!Z84+[12]農業集落排水事業!Z75 -> 0 | V80: =[12]公共下水道事業!AA84+[12]農業集落排水事業!AA75 -> 0 | W80: =[12]公共下水道事業!AB84+[12]農業集落排水事業!AB75 -> 0 | ... Y80: =[12]公共下水道事業!AD84+[12]農業集落排水事業!AD75 -> 0 | Z80: =[12]公共下水道事業!AE84+#REF!+[12]農業集落排水事業!AE75 -> #REF! | AA80: =[12]公共下水道事業!AF84+#REF!+[12]農業集落排水事業!AF75 -> #REF! | AB80: =[12]公共下水道事業!AG84+#REF!+[12]農業集落排水事業!AG75 -> #REF! | AC80: =[12]公共下水道事業!AH84+#REF!+[12]農業集落排水事業!AH75 -> #REF! | AD80: =[12]公共下水道事業!AI84+#REF!+[12]農業集落排水事業!AI75 -> #REF! | AE80: =[12]公共下水道事業!AJ84+#REF!+[12]農業集落排水事業!AJ75 -> #REF! | AF80: =[12]公共下水道事業!AK84+#REF!+[12]農業集落排水事業!AK75 -> #REF! | AG80: =[12]公共下水道事業!AL84+#REF!+[12]農業集落排水事業!AL75 -> #REF! | ... AR80: =[12]公共下水道事業!AW84+#REF!+[12]農業集落排水事業!AW75 -> #REF!
F81: 純計 | H81: (A)-(B) | J81: (C) | P81: =P79-P80 -> 46973 | Q81: =Q79-Q80 -> 130058 | R81: =R79-R80 -> 25558 | S81: =S79-S80 -> 115058 | T81: =T79-T80 -> 115058 | U81: =U79-U80 -> 70558 | V81: =V79-V80 -> 65058 | W81: =W79-W80 -> 60058 | ... AR81: =AR79-AR80 -> #REF!
D82: 資本的支出 | E82: １． | F82: 建設改良費 | P82: ='【簡易水道】建設改良費の年度別事業費 '!E6+'【簡易水道】建設改良費の年度別事業費 '!E8 -> 50550 | Q82: ='【簡易水道】建設改良費の年度別事業費 '!F6+'【簡易水道】建設改良費の年度別事業費 '!F8 -> 125300 | R82: ='【簡易水道】建設改良費の年度別事業費 '!G6+'【簡易水道】建設改良費の年度別事業費 '!G8 -> 25300 | S82: ='【簡易水道】建設改良費の年度別事業費 '!H6+'【簡易水道】建設改良費の年度別事業費 '!H8 -> 110300 | T82: ='【簡易水道】建設改良費の年度別事業費 '!I6+'【簡易水道】建設改良費の年度別事業費 '!I8 -> 110300 | U82: ='【簡易水道】建設改良費の年度別事業費 '!J6+'【簡易水道】建設改良費の年度別事業費 '!J8 -> 70300 | V82: ='【簡易水道】建設改良費の年度別事業費 '!K6+'【簡易水道】建設改良費の年度別事業費 '!K8 -> 60300 | W82: ='【簡易水道】建設改良費の年度別事業費 '!L6+'【簡易水道】建設改良費の年度別事業費 '!L8 -> 55300 | ... Y82: ='【簡易水道】建設改良費の年度別事業費 '!N6+'【簡易水道】建設改良費の年度別事業費 '!N8 -> 121770 | Z82: =[12]公共下水道事業!AE86+#REF!+[12]農業集落排水事業!AE77 -> #REF! | AA82: =[12]公共下水道事業!AF86+#REF!+[12]農業集落排水事業!AF77 -> #REF! | AB82: =[12]公共下水道事業!AG86+#REF!+[12]農業集落排水事業!AG77 -> #REF! | AC82: =[12]公共下水道事業!AH86+#REF!+[12]農業集落排水事業!AH77 -> #REF! | AD82: =[12]公共下水道事業!AI86+#REF!+[12]農業集落排水事業!AI77 -> #REF! | AE82: =[12]公共下水道事業!AJ86+#REF!+[12]農業集落排水事業!AJ77 -> #REF! | AF82: =[12]公共下水道事業!AK86+#REF!+[12]農業集落排水事業!AK77 -> #REF! | AG82: =[12]公共下水道事業!AL86+#REF!+[12]農業集落排水事業!AL77 -> #REF! | ... AR82: =[12]公共下水道事業!AW86+#REF!+[12]農業集落排水事業!AW77 -> #REF!
F83: うち職員給与費 | Z83: =[12]公共下水道事業!AE87+#REF!+[12]農業集落排水事業!AE78 -> #REF! | AA83: =[12]公共下水道事業!AF87+#REF!+[12]農業集落排水事業!AF78 -> #REF! | AB83: =[12]公共下水道事業!AG87+#REF!+[12]農業集落排水事業!AG78 -> #REF! | AC83: =[12]公共下水道事業!AH87+#REF!+[12]農業集落排水事業!AH78 -> #REF! | AD83: =[12]公共下水道事業!AI87+#REF!+[12]農業集落排水事業!AI78 -> #REF! | AE83: =[12]公共下水道事業!AJ87+#REF!+[12]農業集落排水事業!AJ78 -> #REF! | AF83: =[12]公共下水道事業!AK87+#REF!+[12]農業集落排水事業!AK78 -> #REF! | AG83: =[12]公共下水道事業!AL87+#REF!+[12]農業集落排水事業!AL78 -> #REF! | ... AR83: =[12]公共下水道事業!AW87+#REF!+[12]農業集落排水事業!AW78 -> #REF!
E84: ２． | F84: 企業債償還金 | P84: 12859 | Q84: 12659 | R84: 12753 | S84: 15521 | T84: 26914 | U84: 22908 | V84: 22851 | W84: 20847 | X84: 21521 | Y84: 27593 | Z84: 8703 | AA84: =[12]公共下水道事業!AF88+#REF!+[12]農業集落排水事業!AF79 -> #REF! | AB84: =[12]公共下水道事業!AG88+#REF!+[12]農業集落排水事業!AG79 -> #REF! | AC84: =[12]公共下水道事業!AH88+#REF!+[12]農業集落排水事業!AH79 -> #REF! | AD84: =[12]公共下水道事業!AI88+#REF!+[12]農業集落排水事業!AI79 -> #REF! | AE84: =[12]公共下水道事業!AJ88+#REF!+[12]農業集落排水事業!AJ79 -> #REF! | AF84: =[12]公共下水道事業!AK88+#REF!+[12]農業集落排水事業!AK79 -> #REF! | AG84: =[12]公共下水道事業!AL88+#REF!+[12]農業集落排水事業!AL79 -> #REF! | AH84: =[12]公共下水道事業!AM88+#REF!+[12]農業集落排水事業!AM79 -> #REF! | ... AR84: =[12]公共下水道事業!AW88+#REF!+[12]農業集落排水事業!AW79 -> #REF!
E85: ３． | F85: 他会計長期借入返還金 | Z85: =[12]公共下水道事業!AE89+#REF!+[12]農業集落排水事業!AE80 -> #REF! | AA85: =[12]公共下水道事業!AF89+#REF!+[12]農業集落排水事業!AF80 -> #REF! | AB85: =[12]公共下水道事業!AG89+#REF!+[12]農業集落排水事業!AG80 -> #REF! | AC85: =[12]公共下水道事業!AH89+#REF!+[12]農業集落排水事業!AH80 -> #REF! | AD85: =[12]公共下水道事業!AI89+#REF!+[12]農業集落排水事業!AI80 -> #REF! | AE85: =[12]公共下水道事業!AJ89+#REF!+[12]農業集落排水事業!AJ80 -> #REF! | AF85: =[12]公共下水道事業!AK89+#REF!+[12]農業集落排水事業!AK80 -> #REF! | AG85: =[12]公共下水道事業!AL89+#REF!+[12]農業集落排水事業!AL80 -> #REF! | ... AR85: =[12]公共下水道事業!AW89+#REF!+[12]農業集落排水事業!AW80 -> #REF!
E86: ４． | F86: 他会計への支出金 | Z86: =[12]公共下水道事業!AE90+#REF!+[12]農業集落排水事業!AE81 -> #REF! | AA86: =[12]公共下水道事業!AF90+#REF!+[12]農業集落排水事業!AF81 -> #REF! | AB86: =[12]公共下水道事業!AG90+#REF!+[12]農業集落排水事業!AG81 -> #REF! | AC86: =[12]公共下水道事業!AH90+#REF!+[12]農業集落排水事業!AH81 -> #REF! | AD86: =[12]公共下水道事業!AI90+#REF!+[12]農業集落排水事業!AI81 -> #REF! | AE86: =[12]公共下水道事業!AJ90+#REF!+[12]農業集落排水事業!AJ81 -> #REF! | AF86: =[12]公共下水道事業!AK90+#REF!+[12]農業集落排水事業!AK81 -> #REF! | AG86: =[12]公共下水道事業!AL90+#REF!+[12]農業集落排水事業!AL81 -> #REF! | ... AR86: =[12]公共下水道事業!AW90+#REF!+[12]農業集落排水事業!AW81 -> #REF!
E87: ５． | F87: その他 | Z87: =[12]公共下水道事業!AE91+#REF!+[12]農業集落排水事業!AE82 -> #REF! | AA87: =[12]公共下水道事業!AF91+#REF!+[12]農業集落排水事業!AF82 -> #REF! | AB87: =[12]公共下水道事業!AG91+#REF!+[12]農業集落排水事業!AG82 -> #REF! | AC87: =[12]公共下水道事業!AH91+#REF!+[12]農業集落排水事業!AH82 -> #REF! | AD87: =[12]公共下水道事業!AI91+#REF!+[12]農業集落排水事業!AI82 -> #REF! | AE87: =[12]公共下水道事業!AJ91+#REF!+[12]農業集落排水事業!AJ82 -> #REF! | AF87: =[12]公共下水道事業!AK91+#REF!+[12]農業集落排水事業!AK82 -> #REF! | AG87: =[12]公共下水道事業!AL91+#REF!+[12]農業集落排水事業!AL82 -> #REF! | ... AR87: =[12]公共下水道事業!AW91+#REF!+[12]農業集落排水事業!AW82 -> #REF!
E88: 計 | J88: (D) | P88: =SUM(P84:P87)+P82 -> 63409 | Q88: =SUM(Q84:Q87)+Q82 -> 137959 | R88: =SUM(R84:R87)+R82 -> 38053 | S88: =SUM(S84:S87)+S82 -> 125821 | T88: =SUM(T84:T87)+T82 -> 137214 | U88: =SUM(U84:U87)+U82 -> 93208 | V88: =SUM(V84:V87)+V82 -> 83151 | W88: =SUM(W84:W87)+W82 -> 76147 | ... AR88: =SUM(AR84:AR87)+AR82 -> #REF!
C89: 資本的収入額が資本的支出額に不足する額 (D)-(C) | J89: (E) | P89: =P88-P81 -> 16436 | Q89: =Q88-Q81 -> 7901 | R89: =R88-R81 -> 12495 | S89: =S88-S81 -> 10763 | T89: =T88-T81 -> 22156 | U89: =U88-U81 -> 22650 | V89: =V88-V81 -> 18093 | W89: =W88-W81 -> 16089 | ... AR89: =AR88-AR81 -> #REF!
C90: 補塡財源 | E90: １． | F90: 損益勘定留保資金 | P90: 11381 | Q90: 7901 | R90: 9965 | S90: 10763 | T90: 15196 | U90: 15620 | V90: 12063 | W90: 10559 | X90: 16905 | Y90: 30640 | Z90: =[12]公共下水道事業!AE94+#REF!+[12]農業集落排水事業!AE85 -> #REF! | AA90: =[12]公共下水道事業!AF94+#REF!+[12]農業集落排水事業!AF85 -> #REF! | AB90: =[12]公共下水道事業!AG94+#REF!+[12]農業集落排水事業!AG85 -> #REF! | AC90: =[12]公共下水道事業!AH94+#REF!+[12]農業集落排水事業!AH85 -> #REF! | AD90: =[12]公共下水道事業!AI94+#REF!+[12]農業集落排水事業!AI85 -> #REF! | AE90: =[12]公共下水道事業!AJ94+#REF!+[12]農業集落排水事業!AJ85 -> #REF! | AF90: =[12]公共下水道事業!AK94+#REF!+[12]農業集落排水事業!AK85 -> #REF! | AG90: =[12]公共下水道事業!AL94+#REF!+[12]農業集落排水事業!AL85 -> #REF! | ... AR90: =[12]公共下水道事業!AW94+#REF!+[12]農業集落排水事業!AW85 -> #REF!
E91: ２． | F91: 利益剰余金処分額 | Z91: =[12]公共下水道事業!AE95+#REF!+[12]農業集落排水事業!AE86 -> #REF! | AA91: =[12]公共下水道事業!AF95+#REF!+[12]農業集落排水事業!AF86 -> #REF! | AB91: =[12]公共下水道事業!AG95+#REF!+[12]農業集落排水事業!AG86 -> #REF! | AC91: =[12]公共下水道事業!AH95+#REF!+[12]農業集落排水事業!AH86 -> #REF! | AD91: =[12]公共下水道事業!AI95+#REF!+[12]農業集落排水事業!AI86 -> #REF! | AE91: =[12]公共下水道事業!AJ95+#REF!+[12]農業集落排水事業!AJ86 -> #REF! | AF91: =[12]公共下水道事業!AK95+#REF!+[12]農業集落排水事業!AK86 -> #REF! | AG91: =[12]公共下水道事業!AL95+#REF!+[12]農業集落排水事業!AL86 -> #REF! | ... AR91: =[12]公共下水道事業!AW95+#REF!+[12]農業集落排水事業!AW86 -> #REF!
E92: ３． | F92: 繰越工事資金 | Z92: =[12]公共下水道事業!AE96+#REF!+[12]農業集落排水事業!AE87 -> #REF! | AA92: =[12]公共下水道事業!AF96+#REF!+[12]農業集落排水事業!AF87 -> #REF! | AB92: =[12]公共下水道事業!AG96+#REF!+[12]農業集落排水事業!AG87 -> #REF! | AC92: =[12]公共下水道事業!AH96+#REF!+[12]農業集落排水事業!AH87 -> #REF! | AD92: =[12]公共下水道事業!AI96+#REF!+[12]農業集落排水事業!AI87 -> #REF! | AE92: =[12]公共下水道事業!AJ96+#REF!+[12]農業集落排水事業!AJ87 -> #REF! | AF92: =[12]公共下水道事業!AK96+#REF!+[12]農業集落排水事業!AK87 -> #REF! | AG92: =[12]公共下水道事業!AL96+#REF!+[12]農業集落排水事業!AL87 -> #REF! | ... AR92: =[12]公共下水道事業!AW96+#REF!+[12]農業集落排水事業!AW87 -> #REF!
E93: ４． | F93: その他 | P93: =ROUND(P82*10%,0) -> 5055 | R93: =ROUND(R82*10%,0) -> 2530 | T93: 6960 | U93: =ROUND(U82*10%,0) -> 7030 | V93: =ROUND(V82*10%,0) -> 6030 | W93: =ROUND(W82*10%,0) -> 5530 | X93: =ROUND(X82*10%,0) -> 8360 | Y93: =ROUND(Y82*10%,0) -> 12177 | Z93: =[12]公共下水道事業!AE97+#REF!+[12]農業集落排水事業!AE88 -> #REF! | AA93: =[12]公共下水道事業!AF97+#REF!+[12]農業集落排水事業!AF88 -> #REF! | AB93: =[12]公共下水道事業!AG97+#REF!+[12]農業集落排水事業!AG88 -> #REF! | AC93: =[12]公共下水道事業!AH97+#REF!+[12]農業集落排水事業!AH88 -> #REF! | AD93: =[12]公共下水道事業!AI97+#REF!+[12]農業集落排水事業!AI88 -> #REF! | AE93: =[12]公共下水道事業!AJ97+#REF!+[12]農業集落排水事業!AJ88 -> #REF! | AF93: =[12]公共下水道事業!AK97+#REF!+[12]農業集落排水事業!AK88 -> #REF! | AG93: =[12]公共下水道事業!AL97+#REF!+[12]農業集落排水事業!AL88 -> #REF! | ... AR93: =[12]公共下水道事業!AW97+#REF!+[12]農業集落排水事業!AW88 -> #REF!
E94: 計 | J94: (F) | P94: =SUM(P90:P93) -> 16436 | Q94: =SUM(Q90:Q93) -> 7901 | R94: =SUM(R90:R93) -> 12495 | S94: =SUM(S90:S93) -> 10763 | T94: =SUM(T90:T93) -> 22156 | U94: =SUM(U90:U93) -> 22650 | V94: =SUM(V90:V93) -> 18093 | W94: =SUM(W90:W93) -> 16089 | ... AR94: =SUM(AR90:AR93) -> #REF!
C95: 補塡財源不足額 | I95: (E)-(F) | P95: =P89-P94 -> 0 | Q95: =Q89-Q94 -> 0 | R95: =R89-R94 -> 0 | S95: =S89-S94 -> 0 | T95: =T89-T94 -> 0 | U95: =U89-U94 -> 0 | V95: =V89-V94 -> 0 | W95: =W89-W94 -> 0 | ... AR95: =AR89-AR94 -> #REF!
C96: 他会計借入金残高 | J96: (G) | P96: 0 | Q96: 0 | R96: 0 | S96: 0 | T96: 0 | U96: 0 | V96: 0 | W96: 0 | X96: 0 | Y96: 0 | Z96: =[12]公共下水道事業!AE100+#REF!+[12]農業集落排水事業!AE91 -> #REF! | AA96: =[12]公共下水道事業!AF100+#REF!+[12]農業集落排水事業!AF91 -> #REF! | AB96: =[12]公共下水道事業!AG100+#REF!+[12]農業集落排水事業!AG91 -> #REF! | AC96: =[12]公共下水道事業!AH100+#REF!+[12]農業集落排水事業!AH91 -> #REF! | AD96: =[12]公共下水道事業!AI100+#REF!+[12]農業集落排水事業!AI91 -> #REF! | AE96: =[12]公共下水道事業!AJ100+#REF!+[12]農業集落排水事業!AJ91 -> #REF! | AF96: =[12]公共下水道事業!AK100+#REF!+[12]農業集落排水事業!AK91 -> #REF! | AG96: =[12]公共下水道事業!AL100+#REF!+[12]農業集落排水事業!AL91 -> #REF! | ... AR96: =[12]公共下水道事業!AW100+#REF!+[12]農業集落排水事業!AW91 -> #REF!
C97: 企業債残高 | J97: (H) | P97: 262323 | Q97: 329764 | R97: 333111 | S97: 388090 | T97: 431676 | U97: 453668 | V97: 469317 | W97: 483770 | X97: 515649 | Y97: 565856 | Z97: =[12]公共下水道事業!AE101+#REF!+[12]農業集落排水事業!AE92 -> #REF! | AA97: =[12]公共下水道事業!AF101+#REF!+[12]農業集落排水事業!AF92 -> #REF! | AB97: =[12]公共下水道事業!AG101+#REF!+[12]農業集落排水事業!AG92 -> #REF! | AC97: =[12]公共下水道事業!AH101+#REF!+[12]農業集落排水事業!AH92 -> #REF! | AD97: =[12]公共下水道事業!AI101+#REF!+[12]農業集落排水事業!AI92 -> #REF! | AE97: =[12]公共下水道事業!AJ101+#REF!+[12]農業集落排水事業!AJ92 -> #REF! | AF97: =[12]公共下水道事業!AK101+#REF!+[12]農業集落排水事業!AK92 -> #REF! | AG97: =[12]公共下水道事業!AL101+#REF!+[12]農業集落排水事業!AL92 -> #REF! | ... AR97: =[12]公共下水道事業!AW101+#REF!+[12]農業集落排水事業!AW92 -> #REF! | AT97: =P97-Y97 -> -303533
C99: ○他会計繰入金 | AT99: 1240550 | AU99: 28130 | AV99: =AT99+AU99 -> 1268680
I100: 年 度 | P100: 令和7年度 | Q100: 令和8年度 | R100: 令和9年度 | S100: 令和10年度 | T100: 令和11年度 | U100: 令和12年度 | V100: 令和13年度 | W100: 令和14年度 | X100: 令和15年度 | Y100: 令和16年度 | Z100: 令和17年度 | AA100: 令和18年度 | AB100: 令和19年度 | AC100: 令和20年度 | AD100: 令和21年度 | AE100: 令和22年度 | AF100: 令和23年度 | AG100: 令和24年度 | AH100: 令和25年度 | AI100: 令和26年度 | AJ100: 令和27年度 | AK100: 令和28年度 | AL100: 令和29年度 | AM100: 令和30年度 | AN100: 令和31年度 | AO100: 令和32年度 | AP100: 令和33年度 | AQ100: 令和34年度 | AR100: 令和35年度
E101: 区 分 | P101: 2025 | Q101: 2026 | R101: 2027 | S101: 2028 | T101: 2029 | U101: 2030 | V101: 2031 | W101: 2032 | X101: 2033 | Y101: 2034 | Z101: 2035 | AA101: 2036 | AB101: 2037 | AC101: 2038 | AD101: 2039 | AE101: 2040 | AF101: 2041 | AG101: 2042 | AH101: 2043 | AI101: 2044 | AJ101: 2045 | AK101: 2046 | AL101: 2047 | AM101: 2048 | AN101: 2049 | AO101: 2050 | AP101: 2051 | AQ101: 2052 | AR101: 2053
C102: 収益的収支分 | P102: =P103+P104 -> 5720 | Q102: =Q103+Q104 -> 5955 | R102: =R103+R104 -> 6412 | S102: =S103+S104 -> 6531 | T102: =T103+T104 -> 7190 | U102: =U103+U104 -> 7795 | V102: =V103+V104 -> 8129 | W102: =W103+W104 -> 8392 | ... AR102: =AR103+AR104 -> #REF! | AT102: 114000 | AU102: 76000 | AV102: =SUM(AT102:AU102) -> 190000
F103: うち基準内繰入金 | P103: 1429 | Q103: 1664 | R103: 2121 | S103: 2240 | T103: 2899 | U103: 3504 | V103: 3838 | W103: 4101 | X103: 4335 | Y103: 4742 | Z103: =[12]公共下水道事業!AE107+#REF!+[12]農業集落排水事業!AE98 -> #REF! | AA103: =[12]公共下水道事業!AF107+#REF!+[12]農業集落排水事業!AF98 -> #REF! | AB103: =[12]公共下水道事業!AG107+#REF!+[12]農業集落排水事業!AG98 -> #REF! | AC103: =[12]公共下水道事業!AH107+#REF!+[12]農業集落排水事業!AH98 -> #REF! | AD103: =[12]公共下水道事業!AI107+#REF!+[12]農業集落排水事業!AI98 -> #REF! | AE103: =[12]公共下水道事業!AJ107+#REF!+[12]農業集落排水事業!AJ98 -> #REF! | AF103: =[12]公共下水道事業!AK107+#REF!+[12]農業集落排水事業!AK98 -> #REF! | AG103: =[12]公共下水道事業!AL107+#REF!+[12]農業集落排水事業!AL98 -> #REF! | ... AR103: =[12]公共下水道事業!AW107+#REF!+[12]農業集落排水事業!AW98 -> #REF! | AT103: 19019 | AU103: 6469 | AV103: =SUM(AT103:AU103) -> 25488
F104: うち基準外繰入金 | P104: 4291 | Q104: 4291 | R104: 4291 | S104: 4291 | T104: 4291 | U104: 4291 | V104: 4291 | W104: 4291 | X104: 4291 | Y104: 4291 | Z104: =[12]公共下水道事業!AE108+#REF!+[12]農業集落排水事業!AE99 -> #REF! | AA104: =[12]公共下水道事業!AF108+#REF!+[12]農業集落排水事業!AF99 -> #REF! | AB104: =[12]公共下水道事業!AG108+#REF!+[12]農業集落排水事業!AG99 -> #REF! | AC104: =[12]公共下水道事業!AH108+#REF!+[12]農業集落排水事業!AH99 -> #REF! | AD104: =[12]公共下水道事業!AI108+#REF!+[12]農業集落排水事業!AI99 -> #REF! | AE104: =[12]公共下水道事業!AJ108+#REF!+[12]農業集落排水事業!AJ99 -> #REF! | AF104: =[12]公共下水道事業!AK108+#REF!+[12]農業集落排水事業!AK99 -> #REF! | AG104: =[12]公共下水道事業!AL108+#REF!+[12]農業集落排水事業!AL99 -> #REF! | ... AR104: =[12]公共下水道事業!AW108+#REF!+[12]農業集落排水事業!AW99 -> #REF! | AV104: =AV103/AV102 -> 0.13414737
C105: 資本的収支分 | P105: =P106+P107 -> 7940 | Q105: =Q106+Q107 -> 7940 | R105: =R106+R107 -> 7940 | S105: =S106+S107 -> 7940 | T105: =T106+T107 -> 7940 | U105: =U106+U107 -> 7940 | V105: =V106+V107 -> 7940 | W105: =W106+W107 -> 7940 | ... AR105: =AR106+AR107 -> #REF!
F106: うち基準内繰入金 | P106: =P73 -> 7940 | Q106: =Q73 -> 7940 | R106: =R73 -> 7940 | S106: =S73 -> 7940 | T106: =T73 -> 7940 | U106: =U73 -> 7940 | V106: =V73 -> 7940 | W106: =W73 -> 7940 | ... Y106: =Y73 -> 7940 | Z106: =[12]公共下水道事業!AE110+#REF!+[12]農業集落排水事業!AE101 -> #REF! | AA106: =[12]公共下水道事業!AF110+#REF!+[12]農業集落排水事業!AF101 -> #REF! | AB106: =[12]公共下水道事業!AG110+#REF!+[12]農業集落排水事業!AG101 -> #REF! | AC106: =[12]公共下水道事業!AH110+#REF!+[12]農業集落排水事業!AH101 -> #REF! | AD106: =[12]公共下水道事業!AI110+#REF!+[12]農業集落排水事業!AI101 -> #REF! | AE106: =[12]公共下水道事業!AJ110+#REF!+[12]農業集落排水事業!AJ101 -> #REF! | AF106: =[12]公共下水道事業!AK110+#REF!+[12]農業集落排水事業!AK101 -> #REF! | AG106: =[12]公共下水道事業!AL110+#REF!+[12]農業集落排水事業!AL101 -> #REF! | ... AR106: =[12]公共下水道事業!AW110+#REF!+[12]農業集落排水事業!AW101 -> #REF!
F107: うち基準外繰入金 | P107: =P71 -> 0 | Q107: =Q71 -> 0 | R107: =R71 -> 0 | S107: =S71 -> 0 | T107: =T71 -> 0 | U107: =U71 -> 0 | V107: =V71 -> 0 | W107: =W71 -> 0 | ... Y107: =Y71 -> 0 | Z107: =[12]公共下水道事業!AE111+#REF!+[12]農業集落排水事業!AE102 -> #REF! | AA107: =[12]公共下水道事業!AF111+#REF!+[12]農業集落排水事業!AF102 -> #REF! | AB107: =[12]公共下水道事業!AG111+#REF!+[12]農業集落排水事業!AG102 -> #REF! | AC107: =[12]公共下水道事業!AH111+#REF!+[12]農業集落排水事業!AH102 -> #REF! | AD107: =[12]公共下水道事業!AI111+#REF!+[12]農業集落排水事業!AI102 -> #REF! | AE107: =[12]公共下水道事業!AJ111+#REF!+[12]農業集落排水事業!AJ102 -> #REF! | AF107: =[12]公共下水道事業!AK111+#REF!+[12]農業集落排水事業!AK102 -> #REF! | AG107: =[12]公共下水道事業!AL111+#REF!+[12]農業集落排水事業!AL102 -> #REF! | ... AR107: =[12]公共下水道事業!AW111+#REF!+[12]農業集落排水事業!AW102 -> #REF!
...

Sheet 予測 (2)P1-10%
A1: コード | B1: 市などの別 | C1: 都道府県 | D1: 市区町村 | E1: 総人口（人） | L1: 令和2（2020）年の総人口を100としたときの総人口の指数
E2: 2020年 | F2: 2025年 | G2: 2030年 | H2: 2035年 | I2: 2040年 | J2: 2045年 | K2: 2050年 | L2: 2020年 | M2: 2025年 | N2: 2030年 | O2: 2035年 | P2: 2040年 | Q2: 2045年 | R2: 2050年
A3: 2441 | B3: 3 | C3: 青森県 | D3: 三戸町 | E3: 9082 | F3: 8122 | G3: 7226 | H3: 6371 | I3: 5563 | J3: 4824 | K3: 4143 | L3: 100 | M3: 89.429641 | N3: 79.563973 | O3: 70.149747 | P3: 61.253028 | Q3: 53.116054 | R3: 45.617705
G4: =G3/F3 -> 0.88968234 | H4: =H3/G3 -> 0.88167728
F6: 2025
F7: 8598
F9: 1 | G9: =F9-G4 -> 0.11031766 | H9: =G9/5 -> 0.022063531
F10: 1 | G10: =F10-H4 -> 0.11832272 | H10: =G10/5 -> 0.023664545
F11: 令和7 （2025） | G11: 令和8 （2026） | H11: 令和9 （2027） | I11: 令和10 （2028） | J11: 令和11 （2029） | K11: 令和12 （2030） | L11: 令和13 （2031） | M11: 令和14 （2032） | N11: 令和15 （2033） | O11: 令和16 （2034） | P11: 令和17 （2035）
E12: 総人口(人） | F12: 3846 | G12: 3835 | H12: 3825 | I12: 3814 | J12: 3803 | K12: 3771 | L12: 3757 | M12: 3742 | N12: 3728 | O12: 3713 | P12: 3670
E13: 処理区域人口(人） | F13: 2727 | G13: 2719 | H13: 2712 | I13: 2704 | J13: 2696 | K13: 2674 | L13: 2664 | M13: 2653 | N13: 2643 | O13: 2633 | P13: 2602
E14: 水洗化人口(人） | F14: =ROUND(F13*98.5%,0) -> 2686 | G14: =ROUND(G13*98.5%,0) -> 2678 | H14: =ROUND(H13*98.5%,0) -> 2671 | I14: =ROUND(I13*98.5%,0) -> 2663 | J14: =ROUND(J13*98.5%,0) -> 2656 | K14: =ROUND(K13*98.5%,0) -> 2634 | L14: =ROUND(L13*98.5%,0) -> 2624 | M14: =ROUND(M13*98.5%,0) -> 2613 | ... P14: =ROUND(P13*98.5%,0) -> 2563
F18: 令和7 （2025） | G18: 令和8 （2026） | H18: 令和9 （2027） | I18: 令和10 （2028） | J18: 令和11 （2029） | K18: 令和12 （2030） | L18: 令和13 （2031） | M18: 令和14 （2032） | N18: 令和15 （2033） | O18: 令和16 （2034） | P18: 令和17 （2035）
E19: 一般家庭等 | F19: =ROUND(F14*91.1,0) -> 244695 | G19: =ROUND(G14*91.1,0) -> 243966 | H19: =ROUND(H14*91.1,0) -> 243328 | I19: =ROUND(I14*91.1,0) -> 242599 | J19: =ROUND(J14*91.1,0) -> 241962 | K19: =ROUND(K14*91.1,0) -> 239957 | L19: =ROUND(L14*91.1,0) -> 239046 | M19: =ROUND(M14*91.1,0) -> 238044 | ... P19: =ROUND(P14*91.1,0) -> 233489
E20: 工場排水 | F20: 117600 | G20: 117600 | H20: 117600 | I20: 117600 | J20: 117600 | K20: 117600 | L20: 117600 | M20: 117600 | N20: 117600 | O20: 117600 | P20: 117600
F22: 令和7 （2025） | G22: 令和8 （2026） | H22: 令和9 （2027） | I22: 令和10 （2028） | J22: 令和11 （2029） | K22: 令和12 （2030） | L22: 令和13 （2031） | M22: 令和14 （2032） | N22: 令和15 （2033） | O22: 令和16 （2034） | P22: 令和17 （2035）
E23: 一般家庭等 | F23: =ROUND(F19*170.5/1000,0) -> 41720 | G23: =ROUND(G19*170.5/1000,0) -> 41596 | H23: =ROUND(H19*(170.5*110%)/1000,0) -> 45636 | I23: =ROUND(I19*(170.5*110%)/1000,0) -> 45499 | J23: =ROUND(J19*(170.5*110%)/1000,0) -> 45380 | K23: =ROUND(K19*(170.5*110%)/1000,0) -> 45004 | L23: =ROUND(L19*(170.5*110%)/1000,0) -> 44833 | M23: =ROUND(M19*(170.5*110%)/1000,0) -> 44645 | N23: =ROUND(N19*(170.5*110%)/1000,0) -> 44474 | O23: =ROUND(O19*(170.5*110%)/1000,0) -> 44321 | P23: =ROUND(P19*(170.5*110%)/1000,0) -> 43791
E24: 工場排水 | F24: =ROUND(F20*170.5/1000,0) -> 20051 | G24: =ROUND(G20*170.5/1000,0) -> 20051 | H24: =ROUND(H20*(170.5*110%)/1000,0) -> 22056 | I24: =ROUND(I20*(170.5*110%)/1000,0) -> 22056 | J24: =ROUND(J20*(170.5*110%)/1000,0) -> 22056 | K24: =ROUND(K20*(170.5*110%)/1000,0) -> 22056 | L24: =ROUND(L20*(170.5*110%)/1000,0) -> 22056 | M24: =ROUND(M20*(170.5*110%)/1000,0) -> 22056 | N24: =ROUND(N20*(170.5*110%)/1000,0) -> 22056 | O24: =ROUND(O20*(170.5*110%)/1000,0) -> 22056 | P24: =ROUND(P20*(170.5*110%)/1000,0) -> 22056
E25: 計 | F25: =SUM(F23:F24) -> 61771 | G25: =SUM(G23:G24) -> 61647 | H25: =SUM(H23:H24) -> 67692 | I25: =SUM(I23:I24) -> 67555 | J25: =SUM(J23:J24) -> 67436 | K25: =SUM(K23:K24) -> 67060 | L25: =SUM(L23:L24) -> 66889 | M25: =SUM(M23:M24) -> 66701 | ... P25: =SUM(P23:P24) -> 65847
H26: 170.5 | I26: =H26*110% -> 187.55
F29: 令和8 （2026） | G29: 令和9 （2027） | H29: 令和10 （2028） | I29: 令和11 （2029） | J29: 令和12 （2030） | K29: 令和13 （2031） | L29: 令和14 （2032） | M29: 令和15 （2033） | N29: 令和16 （2034） | O29: 令和17 （2035）
E30: 総人口(人） | F30: =F12 -> 3846 | G30: =G12 -> 3835 | H30: =H12 -> 3825 | I30: =I12 -> 3814 | J30: =J12 -> 3803 | K30: =K12 -> 3771 | L30: =L12 -> 3757 | M30: =M12 -> 3742 | ... O30: =O12 -> 3713
E31: 給水人口（人） | F31: =ROUND(F30*簡水過去!$L$8,0) -> 383 | G31: =ROUND(G30*簡水過去!$L$8,0) -> 382 | H31: =ROUND(H30*簡水過去!$L$8,0) -> 381 | I31: =ROUND(I30*簡水過去!$L$8,0) -> 380 | J31: =ROUND(J30*簡水過去!$L$8,0) -> 379 | K31: =ROUND(K30*簡水過去!$L$8,0) -> 376 | L31: =ROUND(L30*簡水過去!$L$8,0) -> 374 | M31: =ROUND(M30*簡水過去!$L$8,0) -> 373 | ... O31: =ROUND(O30*簡水過去!$L$8,0) -> 370
F35: 令和8 （2026） | G35: 令和9 （2027） | H35: 令和10 （2028） | I35: 令和11 （2029） | J35: 令和12 （2030） | K35: 令和13 （2031） | L35: 令和14 （2032） | M35: 令和15 （2033） | N35: 令和16 （2034） | O35: 令和17 （2035）
E36: 有収水量（㎥） | F36: =ROUND(F31*簡水過去!$L$15/1000,) -> 22146 | G36: =ROUND(G31*簡水過去!$L$15/1000,) -> 22088 | H36: =ROUND(H31*簡水過去!$L$15/1000,) -> 22030 | I36: =ROUND(I31*簡水過去!$L$15/1000,) -> 21972 | J36: =ROUND(J31*簡水過去!$L$15/1000,) -> 21915 | K36: =ROUND(K31*簡水過去!$L$15/1000,) -> 21741 | L36: =ROUND(L31*簡水過去!$L$15/1000,) -> 21625 | M36: =ROUND(M31*簡水過去!$L$15/1000,) -> 21568 | ... O36: =ROUND(O31*簡水過去!$L$15/1000,) -> 21394
G37: =F36-G36 -> 58 | H37: =G36-H36 -> 58 | I37: =H36-I36 -> 58 | J37: =I36-J36 -> 57 | K37: =J36-K36 -> 174 | L37: =K36-L36 -> 116 | M37: =L36-M36 -> 57 | N37: =M36-N36 -> 58 | O37: =N36-O36 -> 116
F40: 令和8 （2026） | G40: 令和9 （2027） | H40: 令和10 （2028） | I40: 令和11 （2029） | J40: 令和12 （2030） | K40: 令和13 （2031） | L40: 令和14 （2032） | M40: 令和15 （2033） | N40: 令和16 （2034） | O40: 令和17 （2035）
E41: 料金収入（千円） | F41: =ROUND(F36*簡水過去!$L$17/1000,0) -> 5088 | G41: =ROUND(G36*簡水過去!$L$17/1000,0) -> 5075 | H41: =ROUND(H36*簡水過去!$L$17/1000,0) -> 5061 | I41: =ROUND(I36*簡水過去!$L$17/1000,0) -> 5048 | J41: =ROUND(J36*簡水過去!$L$17/1000,0) -> 5035 | K41: =ROUND(K36*簡水過去!$L$17/1000,0) -> 4995 | L41: =ROUND(L36*簡水過去!$L$17/1000,0) -> 4968 | M41: =ROUND(M36*簡水過去!$L$17/1000,0) -> 4955 | ... O41: =ROUND(O36*簡水過去!$L$17/1000,0) -> 4915

Sheet 下水道現況予測 P1-10%
A1: 3事業合算 | P1: 令和7年度 | Q1: 令和8年度 | R1: 令和9年度 | S1: 令和10年度 | T1: 令和11年度 | U1: 令和12年度 | V1: 令和13年度 | W1: 令和14年度 | X1: 令和15年度 | Y1: 令和16年度 | Z1: 令和17年度 | AA1: 令和18年度 | AB1: 令和19年度 | AC1: 令和20年度 | AD1: 令和21年度 | AE1: 令和22年度 | AF1: 令和23年度 | AG1: 令和24年度 | AH1: 令和25年度 | AI1: 令和26年度 | AJ1: 令和27年度 | AK1: 令和28年度 | AL1: 令和29年度 | AM1: 令和30年度 | AN1: 令和31年度 | AO1: 令和32年度 | AP1: 令和33年度 | AQ1: 令和34年度 | AR1: 令和35年度
P2: 2025 | Q2: 2026 | R2: 2027 | S2: 2028 | T2: 2029 | U2: 2030 | V2: 2031 | W2: 2032 | X2: 2033 | Y2: 2034 | Z2: 2035 | AA2: 2036 | AB2: 2037 | AC2: 2038 | AD2: 2039 | AE2: 2040 | AF2: 2041 | AG2: 2042 | AH2: 2043 | AI2: 2044 | AJ2: 2045 | AK2: 2046 | AL2: 2047 | AM2: 2048 | AN2: 2049 | AO2: 2050 | AP2: 2051 | AQ2: 2052 | AR2: 2053 | AS2: 2055
D3: 普及率 | J3: 10(000)_行政区域内人口 | AT3: =[12]公共下水道事業!AY3 -> 75263
D4: 水洗化率 | J4: 10(000)_処理区域内人口
D5: 有収水量 | J5: 10(000)_水洗化人口
J6: 10(000)_現在処理区域面積
J7: 10(000)_年間総処理水量
J8: 10(000)_年間有収水量
J10: 人口一人当たりの有収水量
J11: 人口一人当たりの使用料（使用料収入÷水洗化人口）
J12: 20㎥あたりの使用料（使用料収入÷年間有収水量×20）
J13: 普及率 | P13: =P5/P3 -> #DIV/0! | Q13: =Q5/Q3 -> #DIV/0! | R13: =R5/R3 -> #DIV/0! | S13: =S5/S3 -> #DIV/0! | T13: =T5/T3 -> #DIV/0! | U13: =U5/U3 -> #DIV/0! | V13: =V5/V3 -> #DIV/0! | W13: =W5/W3 -> #DIV/0! | ... AR13: =AR5/AR3 -> #DIV/0!
J14: 水洗化率 | P14: =AVERAGE($K$14:$M$14) -> #DIV/0! | Q14: =AVERAGE($K$14:$M$14) -> #DIV/0! | R14: =AVERAGE($K$14:$M$14) -> #DIV/0! | S14: =AVERAGE($K$14:$M$14) -> #DIV/0! | T14: =AVERAGE($K$14:$M$14) -> #DIV/0! | U14: =AVERAGE($K$14:$M$14) -> #DIV/0! | V14: =AVERAGE($K$14:$M$14) -> #DIV/0! | W14: =AVERAGE($K$14:$M$14) -> #DIV/0! | ... AR14: =AVERAGE($K$14:$M$14) -> #DIV/0!
J16: 汚水処理費（A） | P16: =下水道現況予測!P16 -> 109223 | Q16: =下水道現況予測!Q16 -> 109886 | R16: =下水道現況予測!R16 -> 111329 | S16: =下水道現況予測!S16 -> 117988 | T16: =下水道現況予測!T16 -> 117748 | U16: =下水道現況予測!U16 -> 118784 | V16: =下水道現況予測!V16 -> 119166 | W16: =下水道現況予測!W16 -> 119595 | ... Y16: =下水道現況予測!Y16 -> 118804 | Z16: =[12]公共下水道事業!AE16+#REF!+[12]農業集落排水事業!AE16 -> #REF! | AA16: =[12]公共下水道事業!AF16+#REF!+[12]農業集落排水事業!AF16 -> #REF! | AB16: =[12]公共下水道事業!AG16+#REF!+[12]農業集落排水事業!AG16 -> #REF! | AC16: =[12]公共下水道事業!AH16+#REF!+[12]農業集落排水事業!AH16 -> #REF! | AD16: =[12]公共下水道事業!AI16+#REF!+[12]農業集落排水事業!AI16 -> #REF! | AE16: =[12]公共下水道事業!AJ16+#REF!+[12]農業集落排水事業!AJ16 -> #REF! | AF16: =[12]公共下水道事業!AK16+#REF!+[12]農業集落排水事業!AK16 -> #REF! | AG16: =[12]公共下水道事業!AL16+#REF!+[12]農業集落排水事業!AL16 -> #REF! | ... AR16: =[12]公共下水道事業!AW16+#REF!+[12]農業集落排水事業!AW16 -> #REF!
J17: 使用料収入（B） | P17: =P28 -> 61771 | Q17: =Q28 -> 61647 | R17: =R28 -> 67692 | S17: =S28 -> 67555 | T17: =T28 -> 67436 | U17: =U28 -> 67060 | V17: =V28 -> 66889 | W17: =W28 -> 66701 | ... Y17: =Y28 -> 66377 | Z17: =[12]公共下水道事業!AE19+#REF!+[12]農業集落排水事業!AE19 -> #REF! | AA17: =[12]公共下水道事業!AF19+#REF!+[12]農業集落排水事業!AF19 -> #REF! | AB17: =[12]公共下水道事業!AG19+#REF!+[12]農業集落排水事業!AG19 -> #REF! | AC17: =[12]公共下水道事業!AH19+#REF!+[12]農業集落排水事業!AH19 -> #REF! | AD17: =[12]公共下水道事業!AI19+#REF!+[12]農業集落排水事業!AI19 -> #REF! | AE17: =[12]公共下水道事業!AJ19+#REF!+[12]農業集落排水事業!AJ19 -> #REF! | AF17: =[12]公共下水道事業!AK19+#REF!+[12]農業集落排水事業!AK19 -> #REF! | AG17: =[12]公共下水道事業!AL19+#REF!+[12]農業集落排水事業!AL19 -> #REF! | ... AR17: =[12]公共下水道事業!AW19+#REF!+[12]農業集落排水事業!AW19 -> #REF!
J18: 経費回収率（B÷A） | P18: =P17/P16 -> 0.56554938 | Q18: =Q17/Q16 -> 0.56100868 | R18: =R17/R16 -> 0.60803564 | S18: =S17/S16 -> 0.57255823 | T18: =T17/T16 -> 0.57271461 | U18: =U17/U16 -> 0.56455415 | V18: =V17/V16 -> 0.56130943 | W18: =W17/W16 -> 0.55772399 | ... AR18: =AR17/AR16 -> #REF!
J19: 有収水量（C） | P19: ='予測 (2)P1-10%'!F19+'予測 (2)P1-10%'!F20 -> 362295 | Q19: ='予測 (2)P1-10%'!G19+'予測 (2)P1-10%'!G20 -> 361566 | R19: ='予測 (2)P1-10%'!H19+'予測 (2)P1-10%'!H20 -> 360928 | S19: ='予測 (2)P1-10%'!I19+'予測 (2)P1-10%'!I20 -> 360199 | T19: ='予測 (2)P1-10%'!J19+'予測 (2)P1-10%'!J20 -> 359562 | U19: ='予測 (2)P1-10%'!K19+'予測 (2)P1-10%'!K20 -> 357557 | V19: ='予測 (2)P1-10%'!L19+'予測 (2)P1-10%'!L20 -> 356646 | W19: ='予測 (2)P1-10%'!M19+'予測 (2)P1-10%'!M20 -> 355644 | ... Y19: ='予測 (2)P1-10%'!O19+'予測 (2)P1-10%'!O20 -> 353913 | Z19: =Z8 -> 0 | AA19: =AA8 -> 0 | AB19: =AB8 -> 0 | AC19: =AC8 -> 0 | AD19: =AD8 -> 0 | AE19: =AE8 -> 0 | AF19: =AF8 -> 0 | AG19: =AG8 -> 0 | ... AR19: =AR8 -> 0
J20: 汚水処理原価（A÷C） | P20: =P16/P19*1000 -> 301.47532 | Q20: =Q16/Q19*1000 -> 303.91685 | R20: =R16/R19*1000 -> 308.4521 | S20: =S16/S19*1000 -> 327.56337 | T20: =T16/T19*1000 -> 327.47621 | U20: =U16/U19*1000 -> 332.20997 | V20: =V16/V19*1000 -> 334.12964 | W20: =W16/W19*1000 -> 336.27729 | ... AR20: =AR16/AR19*1000 -> #REF!
J21: 経常収支比率 | P21: =P37/P53 -> 1.0950931 | Q21: =Q37/Q53 -> 1.0762415 | R21: =R37/R53 -> 1.0922684 | S21: =S37/S53 -> 1.0628517 | T21: =T37/T53 -> 1.0486161 | U21: =U37/U53 -> 1.033362 | V21: =V37/V53 -> 1.0198755 | W21: =W37/W53 -> 1.0068496 | ... AR21: =AR37/AR53 -> #REF!
J24: 3条
I25: 年 度 | P25: 令和7年度 | Q25: 令和8年度 | R25: 令和9年度 | S25: 令和10年度 | T25: 令和11年度 | U25: 令和12年度 | V25: 令和13年度 | W25: 令和14年度 | X25: 令和15年度 | Y25: 令和16年度 | Z25: 令和17年度 | AA25: 令和18年度 | AB25: 令和19年度 | AC25: 令和20年度 | AD25: 令和21年度 | AE25: 令和22年度 | AF25: 令和23年度 | AG25: 令和24年度 | AH25: 令和25年度 | AI25: 令和26年度 | AJ25: 令和27年度 | AK25: 令和28年度 | AL25: 令和29年度 | AM25: 令和30年度 | AN25: 令和31年度 | AO25: 令和32年度 | AP25: 令和33年度 | AQ25: 令和34年度 | AR25: 令和35年度
C26: 区 分 | P26: 2025 | Q26: 2026 | R26: 2027 | S26: 2028 | T26: 2029 | U26: 2030 | V26: 2031 | W26: 2032 | X26: 2033 | Y26: 2034 | Z26: 2035 | AA26: 2036 | AB26: 2037 | AC26: 2038 | AD26: 2039 | AE26: 2040 | AF26: 2041 | AG26: 2042 | AH26: 2043 | AI26: 2044 | AJ26: 2045 | AK26: 2046 | AL26: 2047 | AM26: 2048 | AN26: 2049 | AO26: 2050 | AP26: 2051 | AQ26: 2052 | AR26: 2053
B27: 収益的収支 | C27: 収益的収入 | D27: １． | E27: 営業収益 | J27: (A) | P27: =SUM(P28:P30) -> 61841 | Q27: =SUM(Q28:Q30) -> 61717 | R27: =SUM(R28:R30) -> 67762 | S27: =SUM(S28:S30) -> 67625 | T27: =SUM(T28:T30) -> 67506 | U27: =SUM(U28:U30) -> 67130 | V27: =SUM(V28:V30) -> 66959 | W27: =SUM(W28:W30) -> 66771 | ... AR27: =SUM(AR28:AR30) -> #REF!
D28: (1) | F28: 使用料収入 | P28: ='予測 (2)P1-10%'!F25 -> 61771 | Q28: ='予測 (2)P1-10%'!G25 -> 61647 | R28: ='予測 (2)P1-10%'!H25 -> 67692 | S28: ='予測 (2)P1-10%'!I25 -> 67555 | T28: ='予測 (2)P1-10%'!J25 -> 67436 | U28: ='予測 (2)P1-10%'!K25 -> 67060 | V28: ='予測 (2)P1-10%'!L25 -> 66889 | W28: ='予測 (2)P1-10%'!M25 -> 66701 | ... Y28: ='予測 (2)P1-10%'!O25 -> 66377 | Z28: =[12]公共下水道事業!AE30+#REF!+[12]農業集落排水事業!AE30 -> #REF! | AA28: =[12]公共下水道事業!AF30+#REF!+[12]農業集落排水事業!AF30 -> #REF! | AB28: =[12]公共下水道事業!AG30+#REF!+[12]農業集落排水事業!AG30 -> #REF! | AC28: =[12]公共下水道事業!AH30+#REF!+[12]農業集落排水事業!AH30 -> #REF! | AD28: =[12]公共下水道事業!AI30+#REF!+[12]農業集落排水事業!AI30 -> #REF! | AE28: =[12]公共下水道事業!AJ30+#REF!+[12]農業集落排水事業!AJ30 -> #REF! | AF28: =[12]公共下水道事業!AK30+#REF!+[12]農業集落排水事業!AK30 -> #REF! | AG28: =[12]公共下水道事業!AL30+#REF!+[12]農業集落排水事業!AL30 -> #REF! | ... AR28: =[12]公共下水道事業!AW30+#REF!+[12]農業集落排水事業!AW30 -> #REF!
D29: (2) | F29: 雨水処理負担金 | P29: 0 | Q29: 0 | R29: 0 | S29: 0 | T29: 0 | U29: 0 | V29: 0 | W29: 0 | X29: 0 | Y29: 0 | Z29: =[12]公共下水道事業!AE31+#REF!+[12]農業集落排水事業!AE31 -> #REF! | AA29: =[12]公共下水道事業!AF31+#REF!+[12]農業集落排水事業!AF31 -> #REF! | AB29: =[12]公共下水道事業!AG31+#REF!+[12]農業集落排水事業!AG31 -> #REF! | AC29: =[12]公共下水道事業!AH31+#REF!+[12]農業集落排水事業!AH31 -> #REF! | AD29: =[12]公共下水道事業!AI31+#REF!+[12]農業集落排水事業!AI31 -> #REF! | AE29: =[12]公共下水道事業!AJ31+#REF!+[12]農業集落排水事業!AJ31 -> #REF! | AF29: =[12]公共下水道事業!AK31+#REF!+[12]農業集落排水事業!AK31 -> #REF! | AG29: =[12]公共下水道事業!AL31+#REF!+[12]農業集落排水事業!AL31 -> #REF! | ... AR29: =[12]公共下水道事業!AW31+#REF!+[12]農業集落排水事業!AW31 -> #REF!
D30: (3) | F30: その他 | P30: 70 | Q30: =P30 -> 70 | R30: =Q30 -> 70 | S30: =R30 -> 70 | T30: =S30 -> 70 | U30: =T30 -> 70 | V30: =U30 -> 70 | W30: =V30 -> 70 | X30: =W30 -> 70 | Y30: =X30 -> 70 | Z30: =[12]公共下水道事業!AE32+#REF!+[12]農業集落排水事業!AE32 -> #REF! | AA30: =[12]公共下水道事業!AF32+#REF!+[12]農業集落排水事業!AF32 -> #REF! | AB30: =[12]公共下水道事業!AG32+#REF!+[12]農業集落排水事業!AG32 -> #REF! | AC30: =[12]公共下水道事業!AH32+#REF!+[12]農業集落排水事業!AH32 -> #REF! | AD30: =[12]公共下水道事業!AI32+#REF!+[12]農業集落排水事業!AI32 -> #REF! | AE30: =[12]公共下水道事業!AJ32+#REF!+[12]農業集落排水事業!AJ32 -> #REF! | AF30: =[12]公共下水道事業!AK32+#REF!+[12]農業集落排水事業!AK32 -> #REF! | AG30: =[12]公共下水道事業!AL32+#REF!+[12]農業集落排水事業!AL32 -> #REF! | ... AR30: =[12]公共下水道事業!AW32+#REF!+[12]農業集落排水事業!AW32 -> #REF!
D31: ２． | E31: 営業外収益 | P31: =P32+P35+P36 -> 129797 | Q31: =Q32+Q35+Q36 -> 127765 | R31: =R32+R35+R36 -> 127067 | S31: =S32+S35+S36 -> 158840 | T31: =T32+T35+T36 -> 157203 | U31: =U32+U35+U36 -> 157681 | V31: =V32+V35+V36 -> 157177 | W31: =W32+W35+W36 -> 156807 | ... Y31: =Y32+Y35+Y36 -> 153591 | Z31: =[12]公共下水道事業!AE33+#REF!+[12]農業集落排水事業!AE33 -> #REF! | AA31: =[12]公共下水道事業!AF33+#REF!+[12]農業集落排水事業!AF33 -> #REF! | AB31: =[12]公共下水道事業!AG33+#REF!+[12]農業集落排水事業!AG33 -> #REF! | AC31: =[12]公共下水道事業!AH33+#REF!+[12]農業集落排水事業!AH33 -> #REF! | AD31: =[12]公共下水道事業!AI33+#REF!+[12]農業集落排水事業!AI33 -> #REF! | AE31: =[12]公共下水道事業!AJ33+#REF!+[12]農業集落排水事業!AJ33 -> #REF! | AF31: =[12]公共下水道事業!AK33+#REF!+[12]農業集落排水事業!AK33 -> #REF! | AG31: =[12]公共下水道事業!AL33+#REF!+[12]農業集落排水事業!AL33 -> #REF! | ... AR31: =[12]公共下水道事業!AW33+#REF!+[12]農業集落排水事業!AW33 -> #REF!
D32: (1) | F32: 補助金 | P32: =P33+P34 -> 88514 | Q32: =Q33+Q34 -> 83963 | R32: =R33+R34 -> 78957 | S32: =S33+S34 -> 95777 | T32: =T33+T34 -> 91874 | U32: =U33+U34 -> 91481 | V32: =V33+V34 -> 90502 | W32: =W33+W34 -> 89657 | ... Y32: =Y33+Y34 -> 86957 | Z32: =[12]公共下水道事業!AE34+#REF!+[12]農業集落排水事業!AE34 -> #REF! | AA32: =[12]公共下水道事業!AF34+#REF!+[12]農業集落排水事業!AF34 -> #REF! | AB32: =[12]公共下水道事業!AG34+#REF!+[12]農業集落排水事業!AG34 -> #REF! | AC32: =[12]公共下水道事業!AH34+#REF!+[12]農業集落排水事業!AH34 -> #REF! | AD32: =[12]公共下水道事業!AI34+#REF!+[12]農業集落排水事業!AI34 -> #REF! | AE32: =[12]公共下水道事業!AJ34+#REF!+[12]農業集落排水事業!AJ34 -> #REF! | AF32: =[12]公共下水道事業!AK34+#REF!+[12]農業集落排水事業!AK34 -> #REF! | AG32: =[12]公共下水道事業!AL34+#REF!+[12]農業集落排水事業!AL34 -> #REF! | ... AR32: =[12]公共下水道事業!AW34+#REF!+[12]農業集落排水事業!AW34 -> #REF!
G33: 他会計補助金 | P33: =下水道現況予測!P33 -> 88514 | Q33: =下水道現況予測!Q33 -> 83963 | R33: =下水道現況予測!R33 -> 78957 | S33: =下水道現況予測!S33 -> 95777 | T33: =下水道現況予測!T33 -> 91874 | U33: =下水道現況予測!U33 -> 91481 | V33: =下水道現況予測!V33 -> 90502 | W33: =下水道現況予測!W33 -> 89657 | ... Y33: =下水道現況予測!Y33 -> 86957 | Z33: =[12]公共下水道事業!AE35+#REF!+[12]農業集落排水事業!AE35 -> #REF! | AA33: =[12]公共下水道事業!AF35+#REF!+[12]農業集落排水事業!AF35 -> #REF! | AB33: =[12]公共下水道事業!AG35+#REF!+[12]農業集落排水事業!AG35 -> #REF! | AC33: =[12]公共下水道事業!AH35+#REF!+[12]農業集落排水事業!AH35 -> #REF! | AD33: =[12]公共下水道事業!AI35+#REF!+[12]農業集落排水事業!AI35 -> #REF! | AE33: =[12]公共下水道事業!AJ35+#REF!+[12]農業集落排水事業!AJ35 -> #REF! | AF33: =[12]公共下水道事業!AK35+#REF!+[12]農業集落排水事業!AK35 -> #REF! | AG33: =[12]公共下水道事業!AL35+#REF!+[12]農業集落排水事業!AL35 -> #REF! | ... AR33: =[12]公共下水道事業!AW35+#REF!+[12]農業集落排水事業!AW35 -> #REF!
G34: その他補助金 | Z34: =[12]公共下水道事業!AE36+#REF!+[12]農業集落排水事業!AE36 -> #REF! | AA34: =[12]公共下水道事業!AF36+#REF!+[12]農業集落排水事業!AF36 -> #REF! | AB34: =[12]公共下水道事業!AG36+#REF!+[12]農業集落排水事業!AG36 -> #REF! | AC34: =[12]公共下水道事業!AH36+#REF!+[12]農業集落排水事業!AH36 -> #REF! | AD34: =[12]公共下水道事業!AI36+#REF!+[12]農業集落排水事業!AI36 -> #REF! | AE34: =[12]公共下水道事業!AJ36+#REF!+[12]農業集落排水事業!AJ36 -> #REF! | AF34: =[12]公共下水道事業!AK36+#REF!+[12]農業集落排水事業!AK36 -> #REF! | AG34: =[12]公共下水道事業!AL36+#REF!+[12]農業集落排水事業!AL36 -> #REF! | ... AR34: =[12]公共下水道事業!AW36+#REF!+[12]農業集落排水事業!AW36 -> #REF!
D35: (2) | F35: 長期前受金戻入 | P35: =下水道現況予測!P35 -> 41283 | Q35: =下水道現況予測!Q35 -> 43802 | R35: =下水道現況予測!R35 -> 48110 | S35: =下水道現況予測!S35 -> 63063 | T35: =下水道現況予測!T35 -> 65329 | U35: =下水道現況予測!U35 -> 66200 | V35: =下水道現況予測!V35 -> 66675 | W35: =下水道現況予測!W35 -> 67150 | ... Y35: =下水道現況予測!Y35 -> 66634 | Z35: =[12]公共下水道事業!AE37+#REF!+[12]農業集落排水事業!AE37 -> #REF! | AA35: =[12]公共下水道事業!AF37+#REF!+[12]農業集落排水事業!AF37 -> #REF! | AB35: =[12]公共下水道事業!AG37+#REF!+[12]農業集落排水事業!AG37 -> #REF! | AC35: =[12]公共下水道事業!AH37+#REF!+[12]農業集落排水事業!AH37 -> #REF! | AD35: =[12]公共下水道事業!AI37+#REF!+[12]農業集落排水事業!AI37 -> #REF! | AE35: =[12]公共下水道事業!AJ37+#REF!+[12]農業集落排水事業!AJ37 -> #REF! | AF35: =[12]公共下水道事業!AK37+#REF!+[12]農業集落排水事業!AK37 -> #REF! | AG35: =[12]公共下水道事業!AL37+#REF!+[12]農業集落排水事業!AL37 -> #REF! | ... AR35: =[12]公共下水道事業!AW37+#REF!+[12]農業集落排水事業!AW37 -> #REF!
D36: (3) | F36: その他 | Z36: =[12]公共下水道事業!AE38+#REF!+[12]農業集落排水事業!AE38 -> #REF! | AA36: =[12]公共下水道事業!AF38+#REF!+[12]農業集落排水事業!AF38 -> #REF! | AB36: =[12]公共下水道事業!AG38+#REF!+[12]農業集落排水事業!AG38 -> #REF! | AC36: =[12]公共下水道事業!AH38+#REF!+[12]農業集落排水事業!AH38 -> #REF! | AD36: =[12]公共下水道事業!AI38+#REF!+[12]農業集落排水事業!AI38 -> #REF! | AE36: =[12]公共下水道事業!AJ38+#REF!+[12]農業集落排水事業!AJ38 -> #REF! | AF36: =[12]公共下水道事業!AK38+#REF!+[12]農業集落排水事業!AK38 -> #REF! | AG36: =[12]公共下水道事業!AL38+#REF!+[12]農業集落排水事業!AL38 -> #REF! | ... AR36: =[12]公共下水道事業!AW38+#REF!+[12]農業集落排水事業!AW38 -> #REF! | AU36: 3141
D37: 収入計 | J37: (C) | P37: =P27+P31 -> 191638 | Q37: =Q27+Q31 -> 189482 | R37: =R27+R31 -> 194829 | S37: =S27+S31 -> 226465 | T37: =T27+T31 -> 224709 | U37: =U27+U31 -> 224811 | V37: =V27+V31 -> 224136 | W37: =W27+W31 -> 223578 | ... AR37: =AR27+AR31 -> #REF! | AU37: 1470
C38: 収益的支出 | D38: １． | E38: 営業費用 | P38: =P39+P43+P49+P48 -> 168673 | Q38: =Q39+Q43+Q49+Q48 -> 172354 | R38: =R39+R43+R49+R48 -> 173423 | S38: =S39+S43+S49+S48 -> 200775 | T38: =T39+T43+T49+T48 -> 201841 | U38: =U39+U43+U49+U48 -> 204321 | V38: =V39+V43+V49+V48 -> 206266 | W38: =W39+W43+W49+W48 -> 208243 | ... Y38: =Y39+Y43+Y49+Y48 -> 209822 | Z38: =Z39+Z43+Z49 -> #REF! | AA38: =AA39+AA43+AA49 -> #REF! | AB38: =AB39+AB43+AB49 -> #REF! | AC38: =AC39+AC43+AC49 -> #REF! | AD38: =AD39+AD43+AD49 -> #REF! | AE38: =AE39+AE43+AE49 -> #REF! | AF38: =AF39+AF43+AF49 -> #REF! | AG38: =AG39+AG43+AG49 -> #REF! | ... AR38: =AR39+AR43+AR49 -> #REF! | AU38: =SUM(AU36:AU37) -> 4611
D39: (1) | F39: 職員給与費 | P39: =SUM(P40:P42) -> 9533 | Q39: =SUM(Q40:Q42) -> 9819 | R39: =SUM(R40:R42) -> 10114 | S39: =SUM(S40:S42) -> 10417 | T39: =SUM(T40:T42) -> 10730 | U39: =SUM(U40:U42) -> 11052 | V39: =SUM(V40:V42) -> 11383 | W39: =SUM(W40:W42) -> 11724 | ... AR39: =SUM(AR40:AR42) -> #REF!
G40: 基本給 | P40: =ROUND(4645*1.03,0) -> 4784 | Q40: =ROUND(P40*1.03,0) -> 4928 | R40: =ROUND(Q40*1.03,0) -> 5076 | S40: =ROUND(R40*1.03,0) -> 5228 | T40: =ROUND(S40*1.03,0) -> 5385 | U40: =ROUND(T40*1.03,0) -> 5547 | V40: =ROUND(U40*1.03,0) -> 5713 | W40: =ROUND(V40*1.03,0) -> 5884 | X40: =ROUND(W40*1.03,0) -> 6061 | Y40: =ROUND(X40*1.03,0) -> 6243 | Z40: =[12]公共下水道事業!AE42+#REF!+[12]農業集落排水事業!AE42 -> #REF! | AA40: =[12]公共下水道事業!AF42+#REF!+[12]農業集落排水事業!AF42 -> #REF! | AB40: =[12]公共下水道事業!AG42+#REF!+[12]農業集落排水事業!AG42 -> #REF! | AC40: =[12]公共下水道事業!AH42+#REF!+[12]農業集落排水事業!AH42 -> #REF! | AD40: =[12]公共下水道事業!AI42+#REF!+[12]農業集落排水事業!AI42 -> #REF! | AE40: =[12]公共下水道事業!AJ42+#REF!+[12]農業集落排水事業!AJ42 -> #REF! | AF40: =[12]公共下水道事業!AK42+#REF!+[12]農業集落排水事業!AK42 -> #REF! | AG40: =[12]公共下水道事業!AL42+#REF!+[12]農業集落排水事業!AL42 -> #REF! | ... AR40: =[12]公共下水道事業!AW42+#REF!+[12]農業集落排水事業!AW42 -> #REF!
G41: 退職給付費 | Z41: =[12]公共下水道事業!AE43+#REF!+[12]農業集落排水事業!AE43 -> #REF! | AA41: =[12]公共下水道事業!AF43+#REF!+[12]農業集落排水事業!AF43 -> #REF! | AB41: =[12]公共下水道事業!AG43+#REF!+[12]農業集落排水事業!AG43 -> #REF! | AC41: =[12]公共下水道事業!AH43+#REF!+[12]農業集落排水事業!AH43 -> #REF! | AD41: =[12]公共下水道事業!AI43+#REF!+[12]農業集落排水事業!AI43 -> #REF! | AE41: =[12]公共下水道事業!AJ43+#REF!+[12]農業集落排水事業!AJ43 -> #REF! | AF41: =[12]公共下水道事業!AK43+#REF!+[12]農業集落排水事業!AK43 -> #REF! | AG41: =[12]公共下水道事業!AL43+#REF!+[12]農業集落排水事業!AL43 -> #REF! | ... AR41: =[12]公共下水道事業!AW43+#REF!+[12]農業集落排水事業!AW43 -> #REF!
G42: その他 | P42: =ROUND(4611*1.03,0) -> 4749 | Q42: =ROUND(P42*1.03,0) -> 4891 | R42: =ROUND(Q42*1.03,0) -> 5038 | S42: =ROUND(R42*1.03,0) -> 5189 | T42: =ROUND(S42*1.03,0) -> 5345 | U42: =ROUND(T42*1.03,0) -> 5505 | V42: =ROUND(U42*1.03,0) -> 5670 | W42: =ROUND(V42*1.03,0) -> 5840 | X42: =ROUND(W42*1.03,0) -> 6015 | Y42: =ROUND(X42*1.03,0) -> 6195 | Z42: =[12]公共下水道事業!AE44+#REF!+[12]農業集落排水事業!AE44 -> #REF! | AA42: =[12]公共下水道事業!AF44+#REF!+[12]農業集落排水事業!AF44 -> #REF! | AB42: =[12]公共下水道事業!AG44+#REF!+[12]農業集落排水事業!AG44 -> #REF! | AC42: =[12]公共下水道事業!AH44+#REF!+[12]農業集落排水事業!AH44 -> #REF! | AD42: =[12]公共下水道事業!AI44+#REF!+[12]農業集落排水事業!AI44 -> #REF! | AE42: =[12]公共下水道事業!AJ44+#REF!+[12]農業集落排水事業!AJ44 -> #REF! | AF42: =[12]公共下水道事業!AK44+#REF!+[12]農業集落排水事業!AK44 -> #REF! | AG42: =[12]公共下水道事業!AL44+#REF!+[12]農業集落排水事業!AL44 -> #REF! | ... AR42: =[12]公共下水道事業!AW44+#REF!+[12]農業集落排水事業!AW44 -> #REF! | AU42: 0.02
D43: (2) | F43: 経費 | P43: =SUM(P44:P47) -> 76391 | Q43: =SUM(Q44:Q47) -> 77129 | R43: =SUM(R44:R47) -> 77877 | S43: =SUM(S44:S47) -> 78635 | T43: =SUM(T44:T47) -> 79402 | U43: =SUM(U44:U47) -> 80178 | V43: =SUM(V44:V47) -> 80964 | W43: =SUM(W44:W47) -> 81760 | ... AR43: =SUM(AR44:AR47) -> #REF! | AU43: 0/%
G44: 動力費 | P44: =ROUND(AS44*(1+AU44),0) -> 11470 | Q44: =ROUND(P44*(1+$AU44),0) -> 11504 | R44: =ROUND(Q44*(1+$AU44),0) -> 11539 | S44: =ROUND(R44*(1+$AU44),0) -> 11574 | T44: =ROUND(S44*(1+$AU44),0) -> 11609 | U44: =ROUND(T44*(1+$AU44),0) -> 11644 | V44: =ROUND(U44*(1+$AU44),0) -> 11679 | W44: =ROUND(V44*(1+$AU44),0) -> 11714 | X44: =ROUND(W44*(1+$AU44),0) -> 11749 | Y44: =ROUND(X44*(1+$AU44),0) -> 11784 | Z44: =[12]公共下水道事業!AE46+#REF!+[12]農業集落排水事業!AE46 -> #REF! | AA44: =[12]公共下水道事業!AF46+#REF!+[12]農業集落排水事業!AF46 -> #REF! | AB44: =[12]公共下水道事業!AG46+#REF!+[12]農業集落排水事業!AG46 -> #REF! | AC44: =[12]公共下水道事業!AH46+#REF!+[12]農業集落排水事業!AH46 -> #REF! | AD44: =[12]公共下水道事業!AI46+#REF!+[12]農業集落排水事業!AI46 -> #REF! | AE44: =[12]公共下水道事業!AJ46+#REF!+[12]農業集落排水事業!AJ46 -> #REF! | AF44: =[12]公共下水道事業!AK46+#REF!+[12]農業集落排水事業!AK46 -> #REF! | AG44: =[12]公共下水道事業!AL46+#REF!+[12]農業集落排水事業!AL46 -> #REF! | ... AR44: =[12]公共下水道事業!AW46+#REF!+[12]農業集落排水事業!AW46 -> #REF! | AS44: 11436 | AT44: =ROUND(AS44/$AS$48,4) -> 0.1511 | AU44: =ROUND($AU$42*AT44,4) -> 0.003 | AY44: 245208
G45: 修繕費 | P45: =ROUND(AS45*(1+AU45),0) -> 6600 | Q45: =ROUND(P45*(1+$AU45),0) -> 6611 | R45: =ROUND(Q45*(1+$AU45),0) -> 6622 | S45: =ROUND(R45*(1+$AU45),0) -> 6633 | T45: =ROUND(S45*(1+$AU45),0) -> 6644 | U45: =ROUND(T45*(1+$AU45),0) -> 6655 | V45: =ROUND(U45*(1+$AU45),0) -> 6666 | W45: =ROUND(V45*(1+$AU45),0) -> 6677 | X45: =ROUND(W45*(1+$AU45),0) -> 6688 | Y45: =ROUND(X45*(1+$AU45),0) -> 6699 | Z45: =[12]公共下水道事業!AE47+#REF!+[12]農業集落排水事業!AE47 -> #REF! | AA45: =[12]公共下水道事業!AF47+#REF!+[12]農業集落排水事業!AF47 -> #REF! | AB45: =[12]公共下水道事業!AG47+#REF!+[12]農業集落排水事業!AG47 -> #REF! | AC45: =[12]公共下水道事業!AH47+#REF!+[12]農業集落排水事業!AH47 -> #REF! | AD45: =[12]公共下水道事業!AI47+#REF!+[12]農業集落排水事業!AI47 -> #REF! | AE45: =[12]公共下水道事業!AJ47+#REF!+[12]農業集落排水事業!AJ47 -> #REF! | AF45: =[12]公共下水道事業!AK47+#REF!+[12]農業集落排水事業!AK47 -> #REF! | AG45: =[12]公共下水道事業!AL47+#REF!+[12]農業集落排水事業!AL47 -> #REF! | ... AR45: =[12]公共下水道事業!AW47+#REF!+[12]農業集落排水事業!AW47 -> #REF! | AS45: 6589 | AT45: =ROUND(AS45/$AS$48,4) -> 0.0871 | AU45: =ROUND($AU$42*AT45,4) -> 0.0017 | AY45: 4710
G46: 材料費 | P46: =ROUND(AS46*(1+AU46),0) -> 7234 | Q46: =ROUND(P46*(1+$AU46),0) -> 7248 | R46: =ROUND(Q46*(1+$AU46),0) -> 7262 | S46: =ROUND(R46*(1+$AU46),0) -> 7276 | T46: =ROUND(S46*(1+$AU46),0) -> 7290 | U46: =ROUND(T46*(1+$AU46),0) -> 7304 | V46: =ROUND(U46*(1+$AU46),0) -> 7318 | W46: =ROUND(V46*(1+$AU46),0) -> 7332 | X46: =ROUND(W46*(1+$AU46),0) -> 7346 | Y46: =ROUND(X46*(1+$AU46),0) -> 7360 | Z46: =[12]公共下水道事業!AE48+#REF!+[12]農業集落排水事業!AE48 -> #REF! | AA46: =[12]公共下水道事業!AF48+#REF!+[12]農業集落排水事業!AF48 -> #REF! | AB46: =[12]公共下水道事業!AG48+#REF!+[12]農業集落排水事業!AG48 -> #REF! | AC46: =[12]公共下水道事業!AH48+#REF!+[12]農業集落排水事業!AH48 -> #REF! | AD46: =[12]公共下水道事業!AI48+#REF!+[12]農業集落排水事業!AI48 -> #REF! | AE46: =[12]公共下水道事業!AJ48+#REF!+[12]農業集落排水事業!AJ48 -> #REF! | AF46: =[12]公共下水道事業!AK48+#REF!+[12]農業集落排水事業!AK48 -> #REF! | AG46: =[12]公共下水道事業!AL48+#REF!+[12]農業集落排水事業!AL48 -> #REF! | ... AR46: =[12]公共下水道事業!AW48+#REF!+[12]農業集落排水事業!AW48 -> #REF! | AS46: 7220 | AT46: =ROUND(AS46/$AS$48,4) -> 0.0954 | AU46: =ROUND($AU$42*AT46,4) -> 0.0019 | AY46: 22513
G47: その他 | P47: =ROUND(AS47*(1+AU47),0) -> 51087 | Q47: =ROUND(P47*(1+$AU47),0) -> 51766 | R47: =ROUND(Q47*(1+$AU47),0) -> 52454 | S47: =ROUND(R47*(1+$AU47),0) -> 53152 | T47: =ROUND(S47*(1+$AU47),0) -> 53859 | U47: =ROUND(T47*(1+$AU47),0) -> 54575 | V47: =ROUND(U47*(1+$AU47),0) -> 55301 | W47: =ROUND(V47*(1+$AU47),0) -> 56037 | X47: =ROUND(W47*(1+$AU47),0) -> 56782 | Y47: =ROUND(X47*(1+$AU47),0) -> 57537 | Z47: =[12]公共下水道事業!AE49+#REF!+[12]農業集落排水事業!AE49 -> #REF! | AA47: =[12]公共下水道事業!AF49+#REF!+[12]農業集落排水事業!AF49 -> #REF! | AB47: =[12]公共下水道事業!AG49+#REF!+[12]農業集落排水事業!AG49 -> #REF! | AC47: =[12]公共下水道事業!AH49+#REF!+[12]農業集落排水事業!AH49 -> #REF! | AD47: =[12]公共下水道事業!AI49+#REF!+[12]農業集落排水事業!AI49 -> #REF! | AE47: =[12]公共下水道事業!AJ49+#REF!+[12]農業集落排水事業!AJ49 -> #REF! | AF47: =[12]公共下水道事業!AK49+#REF!+[12]農業集落排水事業!AK49 -> #REF! | AG47: =[12]公共下水道事業!AL49+#REF!+[12]農業集落排水事業!AL49 -> #REF! | ... AR47: =[12]公共下水道事業!AW49+#REF!+[12]農業集落排水事業!AW49 -> #REF! | AS47: =40175+10102+139 -> 50416 | AT47: =ROUND(AS47/$AS$48,4) -> 0.6663 | AU47: =ROUND($AU$42*AT47,4) -> 0.0133 | AY47: 169845
D48: (3) | F48: 流域下水道負担金 | AS48: =SUM(AS44:AS47) -> 75661 | AY48: 6793
D49: (4) | F49: 減価償却費 | P49: =下水道現況予測!P49 -> 82749 | Q49: =下水道現況予測!Q49 -> 85406 | R49: =下水道現況予測!R49 -> 85432 | S49: =下水道現況予測!S49 -> 111723 | T49: =下水道現況予測!T49 -> 111709 | U49: =下水道現況予測!U49 -> 113091 | V49: =下水道現況予測!V49 -> 113919 | W49: =下水道現況予測!W49 -> 114759 | ... Y49: =下水道現況予測!Y49 -> 114004 | Z49: 114004 | AA49: =[12]公共下水道事業!AF50+#REF!+[12]農業集落排水事業!AF50 -> #REF! | AB49: =[12]公共下水道事業!AG50+#REF!+[12]農業集落排水事業!AG50 -> #REF! | AC49: =[12]公共下水道事業!AH50+#REF!+[12]農業集落排水事業!AH50 -> #REF! | AD49: =[12]公共下水道事業!AI50+#REF!+[12]農業集落排水事業!AI50 -> #REF! | AE49: =[12]公共下水道事業!AJ50+#REF!+[12]農業集落排水事業!AJ50 -> #REF! | AF49: =[12]公共下水道事業!AK50+#REF!+[12]農業集落排水事業!AK50 -> #REF! | AG49: =[12]公共下水道事業!AL50+#REF!+[12]農業集落排水事業!AL50 -> #REF! | AH49: =[12]公共下水道事業!AM50+#REF!+[12]農業集落排水事業!AM50 -> #REF! | ... AR49: =[12]公共下水道事業!AW50+#REF!+[12]農業集落排水事業!AW50 -> #REF! | AY49: 250
D50: ２． | E50: 営業外費用 | P50: =P51+P52 -> 6324 | Q50: =Q51+Q52 -> 3705 | R50: =R51+R52 -> 4948 | S50: =S51+S52 -> 12298 | T50: =T51+T52 -> 12450 | U50: =U51+U52 -> 13232 | V50: =V51+V52 -> 13502 | W50: =W51+W52 -> 13814 | ... AR50: =AR51+AR52 -> #REF! | AY50: 169
D51: (1) | F51: 支払利息 | P51: 5646 | Q51: 3027 | R51: 4270 | S51: 11620 | T51: 11772 | U51: 12554 | V51: 12824 | W51: 13136 | X51: 13427 | Y51: 13494 | Z51: =[12]公共下水道事業!AE52+#REF!+[12]農業集落排水事業!AE52 -> #REF! | AA51: =[12]公共下水道事業!AF52+#REF!+[12]農業集落排水事業!AF52 -> #REF! | AB51: =[12]公共下水道事業!AG52+#REF!+[12]農業集落排水事業!AG52 -> #REF! | AC51: =[12]公共下水道事業!AH52+#REF!+[12]農業集落排水事業!AH52 -> #REF! | AD51: =[12]公共下水道事業!AI52+#REF!+[12]農業集落排水事業!AI52 -> #REF! | AE51: =[12]公共下水道事業!AJ52+#REF!+[12]農業集落排水事業!AJ52 -> #REF! | AF51: =[12]公共下水道事業!AK52+#REF!+[12]農業集落排水事業!AK52 -> #REF! | AG51: =[12]公共下水道事業!AL52+#REF!+[12]農業集落排水事業!AL52 -> #REF! | ... AR51: =[12]公共下水道事業!AW52+#REF!+[12]農業集落排水事業!AW52 -> #REF! | AY51: =SUM(AY45:AY50) -> 204280
D52: (2) | F52: その他 | P52: 678 | Q52: 678 | R52: 678 | S52: 678 | T52: 678 | U52: 678 | V52: 678 | W52: 678 | X52: 678 | Y52: 678 | Z52: =[12]公共下水道事業!AE53+#REF!+[12]農業集落排水事業!AE53 -> #REF! | AA52: =[12]公共下水道事業!AF53+#REF!+[12]農業集落排水事業!AF53 -> #REF! | AB52: =[12]公共下水道事業!AG53+#REF!+[12]農業集落排水事業!AG53 -> #REF! | AC52: =[12]公共下水道事業!AH53+#REF!+[12]農業集落排水事業!AH53 -> #REF! | AD52: =[12]公共下水道事業!AI53+#REF!+[12]農業集落排水事業!AI53 -> #REF! | AE52: =[12]公共下水道事業!AJ53+#REF!+[12]農業集落排水事業!AJ53 -> #REF! | AF52: =[12]公共下水道事業!AK53+#REF!+[12]農業集落排水事業!AK53 -> #REF! | AG52: =[12]公共下水道事業!AL53+#REF!+[12]農業集落排水事業!AL53 -> #REF! | ... AR52: =[12]公共下水道事業!AW53+#REF!+[12]農業集落排水事業!AW53 -> #REF! | AY52: =AY44-AY51 -> 40928
D53: 支出計 | J53: (D) | P53: =P38+P50 -> 174997 | Q53: =Q38+Q50 -> 176059 | R53: =R38+R50 -> 178371 | S53: =S38+S50 -> 213073 | T53: =T38+T50 -> 214291 | U53: =U38+U50 -> 217553 | V53: =V38+V50 -> 219768 | W53: =W38+W50 -> 222057 | ... AR53: =AR38+AR50 -> #REF!
C54: 経常損益 | H54: (C)-(D) | J54: (E) | P54: =P37-P53 -> 16641 | Q54: =Q37-Q53 -> 13423 | R54: =R37-R53-R90 -> 16458 | S54: =S37-S53 -> 13392 | T54: =T37-T53 -> 10418 | U54: =U37-U53 -> 7258 | V54: =V37-V53 -> 4368 | W54: =W37-W53 -> 1521 | X54: =X37-X53 -> -1253 | Y54: =Y37-Y53 -> -3956 | Z54: =Z37-Z53 -> #REF! | ... AR54: =AR37-AR53 -> #REF!
B55: 特別利益 | J55: (F) | Z55: =[12]公共下水道事業!AE56+#REF!+[12]農業集落排水事業!AE56 -> #REF! | AA55: =[12]公共下水道事業!AF56+#REF!+[12]農業集落排水事業!AF56 -> #REF! | AB55: =[12]公共下水道事業!AG56+#REF!+[12]農業集落排水事業!AG56 -> #REF! | AC55: =[12]公共下水道事業!AH56+#REF!+[12]農業集落排水事業!AH56 -> #REF! | AD55: =[12]公共下水道事業!AI56+#REF!+[12]農業集落排水事業!AI56 -> #REF! | AE55: =[12]公共下水道事業!AJ56+#REF!+[12]農業集落排水事業!AJ56 -> #REF! | AF55: =[12]公共下水道事業!AK56+#REF!+[12]農業集落排水事業!AK56 -> #REF! | AG55: =[12]公共下水道事業!AL56+#REF!+[12]農業集落排水事業!AL56 -> #REF! | ... AR55: =[12]公共下水道事業!AW56+#REF!+[12]農業集落排水事業!AW56 -> #REF!
B56: 特別損失 | J56: (G) | Z56: =[12]公共下水道事業!AE57+#REF!+[12]農業集落排水事業!AE57 -> #REF! | AA56: =[12]公共下水道事業!AF57+#REF!+[12]農業集落排水事業!AF57 -> #REF! | AB56: =[12]公共下水道事業!AG57+#REF!+[12]農業集落排水事業!AG57 -> #REF! | AC56: =[12]公共下水道事業!AH57+#REF!+[12]農業集落排水事業!AH57 -> #REF! | AD56: =[12]公共下水道事業!AI57+#REF!+[12]農業集落排水事業!AI57 -> #REF! | AE56: =[12]公共下水道事業!AJ57+#REF!+[12]農業集落排水事業!AJ57 -> #REF! | AF56: =[12]公共下水道事業!AK57+#REF!+[12]農業集落排水事業!AK57 -> #REF! | AG56: =[12]公共下水道事業!AL57+#REF!+[12]農業集落排水事業!AL57 -> #REF! | ... AR56: =[12]公共下水道事業!AW57+#REF!+[12]農業集落排水事業!AW57 -> #REF!
B57: 特別損益 | H57: (F)-(G) | J57: (H) | P57: =P55-P56 -> 0 | Q57: =Q55-Q56 -> 0 | R57: =R55-R56 -> 0 | S57: =S55-S56 -> 0 | T57: =T55-T56 -> 0 | U57: =U55-U56 -> 0 | V57: =V55-V56 -> 0 | W57: =W55-W56 -> 0 | ... AR57: =AR55-AR56 -> #REF!
