Workbook

Sheet 00_使い方
A1: 第10期 サービス見込量・給付費推計ワークブック
A2: 委託仕様書（保介第41号）6（5）が求める「要介護認定者数の推計」及び「サービス事業量の推計」に対応し、給付費を『認定者数 × 利用率 × 単価』に分解して積み上げる。黄色セルが入力項目。値を変更すると下流のシートと保険料が自動で再計算される。
A4: シート | B4: 内容 | C4: 入力の要否
A5: 01_実績データ | B5: 第9期計画書による認定者数・受給者数・給付費の実績（R2〜R5） | C5: 入力不要（実績・固定）
A6: 02_認定者数の推計 | B6: 高齢者人口 × 認定率 により第10期の認定者数を推計 | C6: 黄色：認定率
A7: 03_利用率の設定 | B7: 認定者数に対するサービス区分別の受給者割合 | C7: 黄色：第10期の利用率
A8: 04_単価の設定 | B8: 受給者1人あたり月額給付費。介護報酬改定率を乗じる | C8: 黄色：報酬改定率
A9: 05_見込量・給付費 | B9: 受給者数と給付費の年度別見込み（02×03×04） | C9: 入力不要（自動計算）
A10: 06_施設シナリオ | B10: 施設入所申込47人の反映度合いによる3シナリオ | C10: 黄色：入所増加人数
A11: 07_保険料への反映 | B11: 標準給付費を保険料8ステップに接続し基準額を算定 | C11: 黄色：他パラメータ
A12: 08_必要資料 | B12: 推計の精度を上げるために提供を要する資料の一覧 | C12: ─
A14: 【推計の考え方】給付費 ＝ Σ（サービス区分別 受給者数 × 1人あたり月額単価 × 12か月） 受給者数 ＝ 認定者数 × サービス区分別利用率 認定者数 ＝ 第1号被保険者数（高齢者人口）× 認定率 従来の「総給付額を一律の伸び率で延伸する方法」と異なり、人口・認定率・利用率・単価のどれが給付費を動かしているかが分解して見える。委員会での説明と政策判断に用いる。
A15: 【実績の出典】認定者数・認定率・要介護度別内訳：第9期計画書 p.12（介護保険事業状況報告、各年9月末） 受給者数（居宅・地域密着型・施設）：同 p.13（介護保険事業報告年報、各年度1か月平均） サービス種類別給付費：同 p.14（各年度介護状況報告年報）
A16: 【現時点の限界】国の推計ガイドは「年齢階級別・性別の人口 × 年齢階級別・性別の認定率」による推計を求めているが、年齢階級別の認定者数が未入手のため、本ワークブックは全体の認定率による簡便法を用いている。また利用率・単価はサービス3区分の粗い単位であり、仕様書6（5）が求めるサービス種類別（訪問介護・通所介護等）の事業量推計には08シートの資料が必要である。

Sheet 01_実績データ
A1: 01 実績データ（第9期計画書より）
A2: 第9期計画書に掲載された実績。入力不要。02〜04シートの設定はこの実績を出発点とする。
A4: A. 要支援・要介護認定者数と認定率（各年9月末）
A5: 区分 | B5: R2(2020) | C5: R3(2021) | D5: R4(2022) | E5: R5(2023) | F5: 出典・備考
A6: 高齢者人口（人） | B6: 3207 | C6: 3250 | D6: 3273 | E6: 3286 | F6: 第9期計画 p.11
A7: 認定者数（人） | B7: 599 | C7: 568 | D7: 575 | E7: 578 | F7: 第9期計画 p.11・p.12
A8: 認定率 | B8: =B7/B6 | C8: =C7/C6 | D8: =D7/D6 | E8: =E7/E6 | F8: ＝認定者数÷高齢者人口
A10: B. サービス区分別 受給者数（各年度1か月平均）
A11: サービス区分 | B11: R2年度 | C11: R3年度 | D11: R4年度 | E11: （R4を基準） | F11: 出典・備考
A12: 居宅サービス | B12: 281 | C12: 279 | D12: 278 | E12: ◀ 基準年 | F12: 第9期計画 p.13
A13: 地域密着型サービス | B13: 46 | C13: 47 | D13: 46 | E13: ◀ 基準年 | F13: 第9期計画 p.13
A14: 施設サービス | B14: 130 | C14: 124 | D14: 131 | E14: ◀ 基準年 | F14: 第9期計画 p.13
A15: 受給者 計 | B15: =SUM(B12:B14) | C15: =SUM(C12:C14) | D15: =SUM(D12:D14) | F15: ※延べではなく区分別の実人数
A17: C. サービス区分別 給付費（千円）
A18: サービス区分 | B18: R2年度 | C18: R3年度 | D18: R4年度 | E18: （R4を基準） | F18: 出典・備考
A19: 居宅サービス | B19: 367393 | C19: 366043 | D19: 339473 | E19: ◀ 基準年 | F19: 第9期計画 p.14
A20: 地域密着型サービス | B20: 149355 | C20: 152764 | D20: 153142 | E20: ◀ 基準年 | F20: 第9期計画 p.14
A21: 施設サービス | B21: 443089 | C21: 441677 | D21: 469181 | E21: ◀ 基準年 | F21: 第9期計画 p.14
A22: 総給付費 計 | B22: =SUM(B19:B21) | C22: =SUM(C19:C21) | D22: =SUM(D19:D21) | F22: 計画表の総給付費と一致
A24: 注）R4年度を推計の基準年とする。R5〜R8年度の年報実績は未入手であり、受領後は基準年をR7年度に更新することが望ましい（08シート No.1）。

Sheet 02_認定者数の推計
A1: 02 認定者数の推計（人口 × 認定率）
A2: 第1号被保険者数に認定率を乗じて認定者数を推計する。認定率（黄色）が入力項目。第9期計画の認定率実績は R3=17.5% R4=17.6% R5=17.5%、見える化による推計は R6=17.7% R7=17.6% R8=18.1%。高齢者数は減少するが後期高齢者の増加により認定率は上昇する。
A4: 区分 | B4: R9(2027) | C4: R10(2028) | D4: R11(2029) | E4: 3年計 | F4: 備考
A5: 第1号被保険者数（人） | B5: 3187 | C5: 3160 | D5: 3133 | E5: =SUM(B5:D5) | F5: 第9期計画の推計をR7年度末実績3,240人（同計画推計比−2.29%）で補正した値
A6: 認定率 | B6: 0.176 | C6: 0.18 | D6: 0.184 | E6: 【入力】 | F6: R7年度末実績17.31%（561人÷3,240人）からの上昇。年齢階級別認定率は65-74歳3.87%／75-84歳13.22%／85歳以上58.67%
A7: 認定者数（人） | B7: =ROUND(B5*B6,0) | C7: =ROUND(C5*C6,0) | D7: =ROUND(D5*D6,0) | E7: =SUM(B7:D7) | F7: ＝第1号被保険者数×認定率
A9: （参考）要介護度別の構成比（第9期計画 p.12 のR8推計）
A10: 要介護度 | B10: 構成比 | C10: R9見込（人） | D10: R10見込（人） | E10: R11見込（人） | F10: 備考
A11: 要支援1 | B11: 0.057 | C11: =ROUND(B7*$B11,0) | D11: =ROUND(C7*$B11,0) | E11: =ROUND(D7*$B11,0) | F11: 第9期計画R8推計の構成比を据置
A12: 要支援2 | B12: 0.158 | C12: =ROUND(B7*$B12,0) | D12: =ROUND(C7*$B12,0) | E12: =ROUND(D7*$B12,0) | F12: 第9期計画R8推計の構成比を据置
A13: 要介護1 | B13: 0.104 | C13: =ROUND(B7*$B13,0) | D13: =ROUND(C7*$B13,0) | E13: =ROUND(D7*$B13,0) | F13: 第9期計画R8推計の構成比を据置
A14: 要介護2 | B14: 0.241 | C14: =ROUND(B7*$B14,0) | D14: =ROUND(C7*$B14,0) | E14: =ROUND(D7*$B14,0) | F14: 第9期計画R8推計の構成比を据置
A15: 要介護3 | B15: 0.152 | C15: =ROUND(B7*$B15,0) | D15: =ROUND(C7*$B15,0) | E15: =ROUND(D7*$B15,0) | F15: 第9期計画R8推計の構成比を据置
A16: 要介護4 | B16: 0.177 | C16: =ROUND(B7*$B16,0) | D16: =ROUND(C7*$B16,0) | E16: =ROUND(D7*$B16,0) | F16: 第9期計画R8推計の構成比を据置
A17: 要介護5 | B17: 0.111 | C17: =ROUND(B7*$B17,0) | D17: =ROUND(C7*$B17,0) | E17: =ROUND(D7*$B17,0) | F17: 第9期計画R8推計の構成比を据置
A18: 計 | B18: =SUM(B11:B17) | C18: =SUM(C11:C17) | D18: =SUM(D11:D17) | E18: =SUM(E11:E17)
A20: 注）要介護3以上は第10期計画期間で約44%。特別養護老人ホームの入所要件を満たす層であり、06シートの施設シナリオの基礎となる。

Sheet 03_利用率の設定
A1: 03 利用率の設定（受給者数 ÷ 認定者数）
A2: 認定者数に対するサービス区分別の受給者の割合。R4年度実績を基準とし、第10期の設定値（黄色）を入力する。利用率を据え置けば現状維持、引き上げれば在宅・施設サービスの利用促進を織り込むことになる。
A4: サービス区分 | B4: R2年度 | C4: R3年度 | D4: R4年度 | E4: 第10期設定 | F4: 設定の考え方
A5: 居宅サービス | B5: 0.46911519 | C5: 0.49119718 | D5: 0.48347826 | E5: 0.48347826 | F5: R4実績を据置。在宅生活継続の施策効果は当面見込まない
A6: 地域密着型サービス | B6: 0.076794658 | C6: 0.082746479 | D6: 0.08 | E6: 0.08 | F6: R4実績を据置。定員に空きがなく大幅な増は見込みにくい
A7: 施設サービス | B7: 0.21702838 | C7: 0.21830986 | D7: 0.22782609 | E7: 0.22782609 | F7: R4実績を据置。入所申込47人の反映は06シートで別途検討
A8: 受給率（合計） | B8: =SUM(B5:B7) | C8: =SUM(C5:C7) | D8: =SUM(D5:D7) | E8: =SUM(E5:E7) | F8: 第9期計画 p.13 の受給率（R4=79.0%）と一致
A10: 注1）利用率は認定者数に対する割合であり、1人が複数区分を利用する場合は重複する。第9期計画 p.13 の受給実人数（R4=454人）とは概念が異なる。
A11: 注2）在宅介護実態調査では、在宅の認定者142人のうち介護保険サービス利用ありは41.3%にとどまる。居宅利用率48.3%との差は要確認（08シート No.5）。

Sheet 04_単価の設定
A1: 04 単価の設定（受給者1人あたり月額給付費）
A2: 給付費 ÷ 受給者数 ÷ 12 により1人あたり月額単価を算出する。第10期は令和9年度の介護報酬改定が見込まれるため、改定率（黄色）を乗じて設定する。
A4: サービス区分 | B4: R2年度 | C4: R3年度 | D4: R4年度 | E4: 報酬改定率 | F4: 第10期単価（千円/月）
A5: 居宅サービス | B5: 108.95403 | C5: 109.33184 | D5: 101.76049 | E5: 1 | F5: =D5*E5
A6: 地域密着型サービス | B6: 270.57065 | C6: 270.85816 | D6: 277.43116 | E6: 1 | F6: =D6*E6
A7: 施設サービス | B7: 284.03141 | C7: 296.82594 | D7: 298.4612 | E7: 1 | F7: =D7*E7
A9: 注1）報酬改定率は現在1.000（改定なし）で仮置きしている。令和9年度の介護報酬改定率が示された段階で入力する。改定率1%につき標準給付費は約1%、保険料基準額は約1%動く。
A10: 注2）単価は区分内のサービス構成が一定であることを前提とする。施設サービスは特別養護老人ホームと介護老人保健施設の構成比により単価が変動する。

Sheet 05_見込量・給付費
A1: 05 サービス見込量と給付費の見込み
A2: 02（認定者数）×03（利用率）＝受給者数、受給者数×04（単価）×12＝給付費。すべて自動計算。
A4: A. 受給者数の見込み（人）＝ 認定者数 × 利用率
A5: サービス区分 | B5: R9(2027) | C5: R10(2028) | D5: R11(2029) | E5: 3年計 | F5: 備考
A6: 居宅サービス | B6: =ROUND('02_認定者数の推計'!B7*'03_利用率の設定'!$E$5,0) | C6: =ROUND('02_認定者数の推計'!C7*'03_利用率の設定'!$E$5,0) | D6: =ROUND('02_認定者数の推計'!D7*'03_利用率の設定'!$E$5,0) | E6: =SUM(B6:D6) | F6: 02×03
A7: 地域密着型サービス | B7: =ROUND('02_認定者数の推計'!B7*'03_利用率の設定'!$E$6,0) | C7: =ROUND('02_認定者数の推計'!C7*'03_利用率の設定'!$E$6,0) | D7: =ROUND('02_認定者数の推計'!D7*'03_利用率の設定'!$E$6,0) | E7: =SUM(B7:D7) | F7: 02×03
A8: 施設サービス | B8: =ROUND('02_認定者数の推計'!B7*'03_利用率の設定'!$E$7,0) | C8: =ROUND('02_認定者数の推計'!C7*'03_利用率の設定'!$E$7,0) | D8: =ROUND('02_認定者数の推計'!D7*'03_利用率の設定'!$E$7,0) | E8: =SUM(B8:D8) | F8: 02×03
A9: 計 | B9: =SUM(B6:B8) | C9: =SUM(C6:C8) | D9: =SUM(D6:D8) | E9: =SUM(E6:E8)
A11: B. 給付費の見込み（千円）＝ 受給者数 × 単価 × 12か月
A12: サービス区分 | B12: R9(2027) | C12: R10(2028) | D12: R11(2029) | E12: 3年計 | F12: 備考
A13: 居宅サービス | B13: =ROUND(B6*'04_単価の設定'!$F$5*12,0) | C13: =ROUND(C6*'04_単価の設定'!$F$5*12,0) | D13: =ROUND(D6*'04_単価の設定'!$F$5*12,0) | E13: =SUM(B13:D13) | F13: 受給者数×単価×12
A14: 地域密着型サービス | B14: =ROUND(B7*'04_単価の設定'!$F$6*12,0) | C14: =ROUND(C7*'04_単価の設定'!$F$6*12,0) | D14: =ROUND(D7*'04_単価の設定'!$F$6*12,0) | E14: =SUM(B14:D14) | F14: 受給者数×単価×12
A15: 施設サービス | B15: =ROUND(B8*'04_単価の設定'!$F$7*12,0) | C15: =ROUND(C8*'04_単価の設定'!$F$7*12,0) | D15: =ROUND(D8*'04_単価の設定'!$F$7*12,0) | E15: =SUM(B15:D15) | F15: 受給者数×単価×12
A16: 総給付額 計 | B16: =SUM(B13:B15) | C16: =SUM(C13:C15) | D16: =SUM(D13:D15) | E16: =SUM(E13:E15)
A17: 補完項目 | B17: 88451 | C17: 89512 | D17: 90586 | E17: =SUM(B17:D17) | F17: 特定入所者・高額介護・高額医療合算・審査手数料
A18: 標準給付費見込額 | B18: =B16+B17 | C18: =C16+C17 | D18: =D16+D17 | E18: =E16+E17 | F18: 07シートで保険料に接続
A20: 注）補完項目は現行の保険料試算ワークブック 02シートの値をそのまま用いている。特定入所者介護サービス費は施設・短期入所の利用量に連動するため、本来は施設受給者数に比例させるべきである（08シート No.4）。

Sheet 06_施設シナリオ
A1: 06 施設入所申込の反映シナリオ
A2: 在宅介護実態調査（n=139）では、施設等への入所・入居を『すでに申し込み』33.8%（142件換算で約47人）、『検討している』14.4%（約20人）であった。要介護3以上は58.3%を占める。この需要をどこまで見込量に反映するかは委員会の政策判断事項であり、保険料に直結する。
A4: シナリオ | B4: 施設受給者の増 | C4: 施設受給者数(R11) | D4: 標準給付費3年計(千円) | E4: 保険料基準額A(円) | F4: 考え方
A5: ① 現状維持（利用率据置） | B5: 0 | C5: =ROUND('02_認定者数の推計'!D7*'03_利用率の設定'!$E$7,0)+B5 | D5: ='05_見込量・給付費'!E18+B5*'04_単価の設定'!$F$7*12*3 | E5: =ROUND((D5*(1+'07_保険料への反映'!$B$8)*0.23+D5*'07_保険料への反映'!$B$9-D5*'07_保険料への反映'!$B$10-'07_保険料への反映'!$B$11)*1000/('07_保険料への反映'!$B$12*12*'07_保険料への反映'!$B$13*'07_保険料への反映'!$B$14),0) | F5: 町内定員を増やさず、待機は解消しない
A6: ② 一部反映（申込の2割） | B6: 10 | C6: =ROUND('02_認定者数の推計'!D7*'03_利用率の設定'!$E$7,0)+B6 | D6: ='05_見込量・給付費'!E18+B6*'04_単価の設定'!$F$7*12*3 | E6: =ROUND((D6*(1+'07_保険料への反映'!$B$8)*0.23+D6*'07_保険料への反映'!$B$9-D6*'07_保険料への反映'!$B$10-'07_保険料への反映'!$B$11)*1000/('07_保険料への反映'!$B$12*12*'07_保険料への反映'!$B$13*'07_保険料への反映'!$B$14),0) | F6: 町外施設の活用等により段階的に対応
A7: ③ 相当程度の反映（申込の4割） | B7: 20 | C7: =ROUND('02_認定者数の推計'!D7*'03_利用率の設定'!$E$7,0)+B7 | D7: ='05_見込量・給付費'!E18+B7*'04_単価の設定'!$F$7*12*3 | E7: =ROUND((D7*(1+'07_保険料への反映'!$B$8)*0.23+D7*'07_保険料への反映'!$B$9-D7*'07_保険料への反映'!$B$10-'07_保険料への反映'!$B$11)*1000/('07_保険料への反映'!$B$12*12*'07_保険料への反映'!$B$13*'07_保険料への反映'!$B$14),0) | F7: 地域密着型の整備等を伴う
A8: ④ 大幅反映（申込の6割） | B8: 30 | C8: =ROUND('02_認定者数の推計'!D7*'03_利用率の設定'!$E$7,0)+B8 | D8: ='05_見込量・給付費'!E18+B8*'04_単価の設定'!$F$7*12*3 | E8: =ROUND((D8*(1+'07_保険料への反映'!$B$8)*0.23+D8*'07_保険料への反映'!$B$9-D8*'07_保険料への反映'!$B$10-'07_保険料への反映'!$B$11)*1000/('07_保険料への反映'!$B$12*12*'07_保険料への反映'!$B$13*'07_保険料への反映'!$B$14),0) | F8: 施設整備を要し、供給側の制約が課題
A10: 注1）保険料基準額は基金取崩なし（パターンA）で算定している。基金を取り崩す場合はこの額から下がる。
A11: 注2）施設サービスは介護保険法上、計画に定める定員が都道府県の指定に係る協議の基礎となる。シナリオ②以降を採る場合は、計画本文に整備方針と定員を明記する必要がある。

Sheet 07_保険料への反映
A1: 07 保険料への反映（8ステップへの接続）
A2: 05シートの標準給付費を保険料算定の8ステップに接続し、基準額を算定する。現行の保険料試算ワークブック（一律1.2%/年で延伸）との差も示す。
A4: A. 算定パラメータ
A5: 項目 | B5: 値 | F5: 備考
A6: 標準給付費（3年計・千円） | B6: ='05_見込量・給付費'!E18 | F6: 05シートから自動参照
A7: 地域支援事業費／標準給付費 | B7: 0.027004166 | F7: 第1号負担分の算定基礎に加算する比率
A8: 調整交付金相当額率 | B8: 0.05 | F8: 国基準5%
A9: 調整交付金見込率 | B9: 0.039 | F9: 第9期実績3.9%。標準5%との乖離は要確認（R7年度の交付実績で確定）
A10: 保険者機能強化交付金（千円） | B10: 10800 | F10: 第9期実績
A11: 第1号被保険者数 3年計（人） | B11: ='02_認定者数の推計'!E5 | F11: 02シートから自動参照
A12: 予定収納率 | B12: 0.967 | F12: R7年度実績の総合収納率（様式3：244,747,850÷253,091,271）
A13: 補正係数（所得段階別加重平均料率） | B13: 1.0137 | F13: R7年度末の所得段階別被保険者数（13段階・3,240人）×保険者の定める割合で実算定（年報 様式1）
A15: B. 保険料基準額の算定
A16: 項目 | B16: パターンA | C16: パターンB | D16: パターンC | F16: 備考
A17: 基金取崩額（千円） | B17: 0 | C17: 39154 | D17: 78308 | F17: 取崩なし／50%／全額（残高78,308千円＝131,700−第9期取崩予算53,392）
A18: 保険料収納必要額（千円） | B18: =$B$6*(1+$B$7)*0.23+$B$6*$B$8-$B$6*$B$9-$B$10-B17 | C18: =$B$6*(1+$B$7)*0.23+$B$6*$B$8-$B$6*$B$9-$B$10-C17 | D18: =$B$6*(1+$B$7)*0.23+$B$6*$B$8-$B$6*$B$9-$B$10-D17 | F18: 第1号負担分＋調整交付金相当額−見込額−機能強化−基金取崩
A19: 保険料基準額（月額・円） | B19: =ROUND(B18*1000/($B$11*12*$B$12*$B$13),0) | C19: =ROUND(C18*1000/($B$11*12*$B$12*$B$13),0) | D19: =ROUND(D18*1000/($B$11*12*$B$12*$B$13),0) | F19: 第9期は6,508円（年額78,000円）
A20: 第9期比 | B20: =B19/6508-1 | C20: =C19/6508-1 | D20: =D19/6508-1
A22: C. 現行の保険料試算ワークブックとの比較
A23: 推計方法 | B23: 標準給付費3年計 | C23: 基準額A | D23: 差 | F23: 備考
A24: 本ワークブック（認定者数×利用率×単価） | B24: =$B$6 | C24: =B19 | D24: ─ | F24: 仕様書6（5）に対応
A25: 現行（総給付額を一律1.2%/年で延伸） | B25: 3390699 | C25: 7632 | D25: =C25-C24 | F25: 保険料試算ワークブックの現行値
A27: 注）差は、現行が総給付額の実績横引きであるのに対し、本ワークブックが人口減少（第1号被保険者数の減）と認定率上昇を分けて織り込んだことによる。

Sheet 08_必要資料
A1: 08 推計の精度を上げるために提供を要する資料
A2: 本ワークブックは第9期計画書に掲載された実績のみで構成している。以下の資料により、簡便法から国の推計ガイドに沿った方法へ移行できる。
A4: No | B4: 資料 | C4: 内容 | D4: これにより可能になること | E4: 優先度 | F4: 入手先
A5: 1 | B5: 介護保険事業状況報告 年報（R5〜R7年度） | C5: サービス種類別・要介護度別の受給者数と給付費。第9期計画はR4年度までしか掲載していない。 | D5: 推計の基準年をR4からR7に更新できる。3年古いデータで推計している現状を解消 | E5: 最高 | F5: 発注者
A6: 2 | B6: 年齢階級別・性別の認定者数（R4〜R8年度） | C6: 5歳階級別（65-69、70-74、75-79、80-84、85-89、90以上）の認定者数。性別内訳を含む。 | D6: 国の推計ガイドが求める「年齢階級別・性別の認定率×人口」による推計に移行できる。後期高齢者の増加が認定者数に与える影響を分離できる | E6: 最高 | F6: 発注者
A7: 3 | B7: サービス種類別の給付実績（R5〜R7年度） | C7: 訪問介護・通所介護・短期入所・地域密着型各種・施設種別ごとの件数と給付費。 | D7: 仕様書6（5）が求めるサービス種類別の事業量推計ができる。現在の3区分（居宅・地密・施設）の粗い推計を細分化できる | E7: 高 | F7: 発注者・国保連
A8: 4 | B8: 特定入所者介護サービス費等の実績（R4〜R7年度） | C8: 特定入所者介護サービス費・高額介護サービス費・高額医療合算・審査支払手数料の年度別実績。 | D8: 補完項目を施設利用量に連動させられる。現在は固定値で置いている | E8: 高 | F8: 発注者
A9: 5 | B9: 介護保険サービス未利用の認定者の状況 | C9: 認定を受けながらサービスを利用していない者の数と要介護度別内訳。 | D9: 在宅介護実態調査の「サービス利用あり41.3%」と居宅利用率48.3%の差を説明できる。利用率の設定根拠が確かになる | E9: 高 | F9: 発注者
A10: 6 | B10: 町内事業所・施設の定員と稼働状況 | C10: 特別養護老人ホーム・介護老人保健施設・地域密着型各事業所の定員、利用者数、待機者数。 | D10: 06シートの施設シナリオを供給側の制約と突き合わせられる。計画に定員を記載するための基礎となる | E10: 高 | F10: 発注者・3事業所
A11: 7 | B11: 所得段階別被保険者数（R7またはR8時点・13段階） | C11: 第9期の13段階区分による段階別人数。手元にあるのはR3年度末の9段階（第8期区分）のみ。 | D11: 補正係数を最新分布で確定できる。現在はR3の分布から0.9734を算定して用いている | E11: 高 | F11: 発注者（賦課台帳）
A12: 8 | B12: 住所地特例者の状況（R4〜R7年度） | C12: 町外施設利用者24人の施設種別・所在自治体・要介護度の内訳。 | D12: 施設サービスの給付費のうち町外分を分離でき、町内定員の議論と切り分けられる | E12: 中 | F12: 発注者
A13: 9 | B13: 介護報酬改定率（令和9年度） | C13: 国が示す改定率。サービス種類別の改定内容を含む。 | D13: 04シートの単価に反映できる。改定率1%につき保険料基準額は約1%動く | E13: 中 | F13: 国の情報
A14: 10 | B14: 日常生活圏域別の認定者数・受給者数 | C14: 圏域別（または行政区別）の認定者数、サービス受給者数、事業所所在地。 | D14: 施設の地域偏在という論点を数値で示せる。ニーズ調査に圏域IDがないため現在は検証できない | E14: 中 | F14: 発注者
A16: 注）No.1・No.2があれば、本ワークブックは国の推計ガイドに沿った方法へ移行できる。この2点が最優先である。
