Workbook

Sheet 00_使い方
A1: 川崎町第10期 保険料試算ワークブック
A2: ── 8ステップ準拠・3パターン(A/B/C)試算・9段階/13段階比較 ──
A4: 1．本ワークブックの目的
A5: 国基本指針に準拠した8ステップで川崎町第10期介護保険料(第1号被保険者基準月額)を試算します。基金取崩額により3パターン(A:取崩なし/B:50%取崩/C:全額取崩)を並列計算し、9段階と13段階区分の比較も実施。第3回策定委員会(R9.1中旬)で確定値を提示するための作業用シートです。
A7: 2．シート構成
A8: シート | B8: 内容 | F8: 対応ステップ
A9: 01_入力_基礎データ | B9: 人口・認定者・収納率・基金残高等の基礎数値 | F9: 全Step共通
A10: 02_Step1-2_標準給付費 | B10: サービス見込量と単価から3年間の標準給付費を算定 | F10: Step1-2
A11: 03_Step3-4_地域支援等 | B11: 地域支援事業費と第1号負担分相当額(23%)を算定 | F11: Step3-4
A12: 04_Step5_調整交付金 | B12: 国の調整交付金(5%基本+変動)を算定 | F12: Step5
A13: 05_Step6_基金3パターン | B13: 基金取崩額の3パターン設定(A/B/C) | F13: Step6
A14: 06_Step7-8_収納額・基準額 | B14: 保険料収納必要額と基準額(月額)の算定 | F14: Step7-8
A15: 07_所得段階_9段階版 | B15: 現行9段階区分での所得段階別保険料 | F15: Step8拡張
A16: 08_所得段階_13段階版 | B16: 13段階区分での所得段階別保険料(協議事項5) | F16: Step8拡張
A17: 09_比較分析 | B17: 3パターン×9/13段階のクロス比較・近隣比較 | F17: 総合
A19: 3．セルの色分け凡例
A20: 入力欄(黄色) | B20: 町担当課・弊社で入力する数値。基礎データ・基金残高等
A21: 既知数値(緑) | B21: 確定済の数値。R3給付実績・R7.6人口等
A22: 計算結果(青) | B22: 数式により自動算出される数値。手入力不要
A23: 重要結果(赤) | B23: 保険料基準額等の最重要算定結果
A25: 4．保険料算定の8ステップ全体像
A26: Step | B26: 内容 | E26: 数式・元データ | G26: シート
A27: Step1 | B27: サービス見込量×単価=標準給付費(年度別) | E27: 見込量(第7章7-1) × サービス単価 | G27: 02
A28: Step2 | B28: 標準給付費3年間総額 | E28: Step1の3年分(R9-R11)を合計 | G28: 02
A29: Step3 | B29: 地域支援事業費(包括的・任意事業) | E29: Step1の3〜4%相当(国基準) | G29: 03
A30: Step4 | B30: 第1号負担分相当額 | E30: (Step2+Step3)×23%(第1号負担割合) | G30: 03
A31: Step5 | B31: 調整交付金額 | E31: Step4×(調整交付金率5%-実績)補正 | G31: 04
A32: Step6 | B32: 基金取崩額の設定(3パターン) | E32: A:0/B:基金×50%/C:基金×100% | G32: 05
A33: Step7 | B33: 保険料収納必要額 | E33: Step4-Step5+Step6 | G33: 06
A34: Step8 | B34: 保険料基準月額 | E34: Step7÷(被保険者数×12×収納率×補正) | G34: 06
A36: 5．運用上の注意事項
A37: ※ 本ワークブックは作業用です。確定値は介護給付費準備基金残高(R8.6時点)の入手後にシート01で入力してください。
A38: ※ サービス見込量(Step1)は計画素案v1.5第7章7-1の暫定値を使用。Phase 2でアンケート補正後に更新します。
A39: ※ 見える化システムの仙南圏域他自治体保険料との比較は、町担当課が見える化システム登録完了後に実施します。
A40: ※ 13段階区分(シート08)は国推奨基準率に基づく試算。確定段階率は委員会協議事項5で確定します。
A41: ※ 3パターン試算の結果を第3回策定委員会(R9.1中旬)で提示し、委員協議の上、第10期保険料パターンを決定します。

Sheet 01_入力_基礎データ
A1: 01 基礎データ入力シート
A2: ── 8ステップ算定の前提となる基礎数値を入力 ──
A4: A. 第1号被保険者数の推計（Step8で使用）
A5: 年度 | B5: 65歳以上人口(人) | D5: 備考 | F5: 出典
A6: R7(2025) | B6: 3244 | D6: 実績(R7.6時点) | F6: 町保険者データ
A7: R8(2026) | B7: [入力] | D7: 推計値(町担当課入力) | F7: 町推計
A8: R9(2027) | B8: [入力] | D8: 第10期初年度推計 | F8: 社人研推計+補正
A9: R10(2028) | B9: [入力] | D9: 第10期中年度推計 | F9: 社人研推計+補正
A10: R11(2029) | B10: [入力] | D10: 第10期最終年度推計 | F10: 社人研推計+補正
A11: 3年合計 | B11: =SUM(B8:B10) -> 0 | D11: R9-R11の合計(Step8で使用) | F11: 計算
A13: B. 介護給付費準備基金（Step6で使用）
A14: 項目 | B14: 金額(千円) | D14: 備考・時点
A15: 基金残高(R8.6時点) | B15: [町担当課入力] | D15: R8.6確定時点の残高(町担当課に依頼中)
A16: 計画期間中の予定取崩額 | B16: [3パターン算定] | D16: シート05_Step6で算定
A18: C. 保険料収納率の過去5年実績（Step8で使用）
A19: 年度 | B19: 総合収納率(%) | D19: 現年度分(%) | F19: 出典
A20: R3 | B20: 96.3 | D20: 99 | F20: 実績(MECEデータ既知)
A21: R4 | B21: [入力] | D21: [入力] | F21: 町担当課入力
A22: R5 | B22: [入力] | D22: [入力] | F22: 町担当課入力
A23: R6 | B23: [入力] | D23: [入力] | F23: 町担当課入力
A24: R7 | B24: [入力] | D24: [入力] | F24: 町担当課入力(R7.3末)
A25: 5年平均 | B25: =AVERAGE(B19:B23) -> 96.3 | D25: =AVERAGE(D19:D23) -> 99 | F25: 予定収納率(Step8で使用)
A27: D. 第10期の制度パラメータ（国基準値）
A28: パラメータ | B28: 値 | D28: 備考
A29: 第1号被保険者負担割合 | B29: 23% | D29: Step4で使用。第10期も第9期と同じ23%(国基準)
A30: 第2号被保険者負担割合 | B30: 27% | D30: 参考。Step4対象外
A31: 公費負担割合(国) | B31: 25% | D31: 参考。調整交付金5%含む
A32: 公費負担割合(都道府県) | B32: 12.5% | D32: 参考
A33: 公費負担割合(市町村) | B33: 12.5% | D33: 参考
A34: 標準調整交付金率 | B34: 5% | D34: Step5で使用。実際は補正あり
A35: 地域支援事業費率(対給付費) | B35: 3〜4% | D35: Step3で使用。上限額管理あり

Sheet 02_Step1-2_標準給付費
A1: 02 Step1-2 標準給付費の算定
A2: ── サービス見込量×単価で年度別給付費を算定 ──
A4: Step1：サービス区分別の3年間給付費見込み（千円）
A5: サービス区分 | B5: R3実績(参考) | C5: R9見込み | D5: R10見込み | E5: R11見込み | F5: 3年合計 | G5: 備考
A6: 居宅サービス | B6: 365000 | F6: =SUM(C6:E6) -> 0 | G6: R3実績9.6億×38.1%(参考)
A7: 地域密着型サービス | B7: 152000 | F7: =SUM(C7:E7) -> 0 | G7: R3実績9.6億×15.9%
A8: 施設サービス | B8: 441000 | F8: =SUM(C8:E8) -> 0 | G8: R3実績9.6億×46.0%(特養68・老健66)
A9: 住宅改修・福祉用具 | B9: 2857 | F9: =SUM(C9:E9) -> 0 | G9: R3実績(参考値)
A10: Step2: 標準給付費合計 | B10: =SUM(B6:B9) -> 960857 | C10: =SUM(C6:C9) -> 0 | D10: =SUM(D6:D9) -> 0 | E10: =SUM(E6:E9) -> 0 | F10: =SUM(F6:F9) -> 0 | G10: Step3で使用
A12: ※ R3実績は参考値です。R9-R11の見込み値は計画素案v1.5 第7章7-1のサービス見込量(6ステップ算定)に基づき入力します。
A13: ※ 住宅改修・福祉用具は便宜上1区分にまとめています。詳細区分が必要な場合は別途展開します。
A14: ※ 見込量はR8.7末アンケート結果による補正後の値を入力してください(Phase 2のW8-W9で実施)。

Sheet 03_Step3-4_地域支援等
A1: 03 Step3-4 地域支援事業費と第1号負担分相当額
A2: ── 地域支援事業費(Step3)と第1号負担分23%(Step4)を算定 ──
A4: Step3：地域支援事業費（千円）
A5: 区分 | B5: R3実績 | C5: R9見込み | D5: R10見込み | E5: R11見込み | F5: 3年合計
A6: 総合事業(介護予防・生活支援) | B6: 5650 | F6: =SUM(C6:E6) -> 0
A7: 一般介護予防事業 | B7: 1950 | F7: =SUM(C7:E7) -> 0
A8: 包括的支援事業・任意事業 | B8: 24471 | F8: =SUM(C8:E8) -> 0
A9: Step3 合計 | B9: =SUM(B6:B8) -> 32071 | C9: =SUM(C6:C8) -> 0 | D9: =SUM(D6:D8) -> 0 | E9: =SUM(E6:E8) -> 0 | F9: =SUM(F6:F8) -> 0
A11: Step4：第1号被保険者負担分相当額（千円・国基準23%）
A12: 計算式：(Step2:標準給付費合計 + Step3:地域支援事業費合計) × 23%
A13: 項目 | B13: 金額(千円・3年合計) | D13: 備考
A14: Step2 標準給付費合計 | B14: ='02_Step1-2_標準給付費'!F10 -> 0 | D14: シート02から自動参照
A15: Step3 地域支援事業費合計 | B15: =F9 -> 0 | D15: 本シート上部から自動参照
A16: 保険給付費等合計 | B16: =B14+B15 -> 0 | D16: Step2 + Step3
A17: Step4 第1号負担分相当額 | B17: =B16*0.23 -> 0 | D17: × 23%(第1号負担割合)= Step5で使用

Sheet 04_Step5_調整交付金
A1: 04 Step5 調整交付金
A2: ── 国の調整交付金(基準5%+変動)を算定 ──
A4: Step5：調整交付金額の算定（千円）
A5: 解説：調整交付金は標準調整交付金率5%を基本に、後期高齢者割合・所得段階分布等で町別に補正されます。実際の交付金率は5%±αで、町の状況により4-6%程度になります。
A6: 項目 | B6: 値 | D6: 備考
A7: 標準調整交付金率 | B7: 5.0% | D7: 国基準値
A8: 川崎町の交付金率(暫定) | B8: 5.0% | D8: 町担当課で国通知に基づき調整(暫定値5.0%)
A9: 標準給付費合計(Step2) | B9: ='02_Step1-2_標準給付費'!F10 -> 0 | D9: シート02から参照(千円)
A10: Step5 調整交付金額 | B10: =B9*B8 -> 0 | D10: 標準給付費×交付金率(千円)。Step7で減算
A12: ■ 標準5%との差額(調整交付金不足額)
A13: 標準5%額 | B13: =B8*0.05 -> 0.0025 | D13: 標準給付費×5%(国標準額)
A14: 差額(町実額-標準5%額) | B14: =B9-B13 -> -0.0025 | D14: 差額がプラス→保険料軽減効果あり、マイナス→保険料追加負担

Sheet 05_Step6_基金3パターン
A1: 05 Step6 介護給付費準備基金取崩額の3パターン設定
A2: ── A:取崩なし / B:50%取崩 / C:全額取崩 ──
A4: ■ 基金残高（シート01から自動参照）
A5: 基金残高(R8.6時点・千円) | B5: =01_入力_基礎データ!B15 -> [町担当課入力] | D5: シート01のB15から自動参照
A7: ■ 3パターン基金取崩額設定
A8: パターン | B8: 取崩割合 | C8: 取崩額(千円) | D8: 残高(千円) | E8: 効果・想定
A9: A 取崩なし | B9: 0 | C9: =$B$5*B9 -> #VALUE! | D9: =$B$5-C9 -> #VALUE! | E9: 基金温存・第11期負担緩和・給付費増を保険料に直接反映(最高水準)
A10: B 50%取崩 | B10: 0.5 | C10: =$B$5*B10 -> #VALUE! | D10: =$B$5-C10 -> #VALUE! | E10: 給付費増を一部相殺・次期負担との均衡(中位水準)
A11: C 全額取崩 | B11: 1 | C11: =$B$5*B11 -> #VALUE! | D11: =$B$5-C11 -> #VALUE! | E11: 住民負担最小化・第11期負担増のリスクあり(最低水準)
A13: ※ 基金残高(B5)はシート01の確定値を参照しています。基金残高未確定の場合は本シートも未確定となります。
A14: ※ パターンBの50%は標準的な選択肢ですが、25%/75%等の中間値も検討可能です(シート05_2を別途作成可)。
A15: ※ 基金取崩は計画期間(3年)の累計額です。年度別配分は別途検討します。
A16: ※ 国は基金残高の概ね半分以下を取崩水準として推奨しているため、パターンBが標準的とされます。

Sheet 06_Step7-8_収納額_基準額
A1: 06 Step7-8 保険料収納必要額と基準月額の算定
A2: ── 3パターン(A/B/C)で保険料基準月額を算定 ──
A4: Step7：保険料収納必要額（3パターン・千円）
A5: 計算式：Step4(第1号負担分) - Step5(調整交付金) - Step6(基金取崩額)
A6: 項目 | B6: 共通値 | C6: パターンA | D6: パターンB | E6: パターンC | F6: 備考
A7: Step4 第1号負担分 | B7: ='03_Step3-4_地域支援等'!B17 -> 0 | C7: =$B$8 -> 0 | D7: =$B$8 -> 0 | E7: =$B$8 -> 0 | F7: 3パターン共通
A8: Step5 調整交付金(減算) | B8: =04_Step5_調整交付金!B9 -> 0 | C8: =$B$9 -> (パターン別) | D8: =$B$9 -> (パターン別) | E8: =$B$9 -> (パターン別) | F8: 3パターン共通
A9: Step6 基金取崩額(減算) | B9: (パターン別) | C9: =05_Step6_基金3パターン!C9 -> #VALUE! | D9: =05_Step6_基金3パターン!C10 -> #VALUE! | E9: =05_Step6_基金3パターン!C11 -> #VALUE! | F9: シート05から参照
A10: Step7 保険料収納必要額 | B10: (計算式) | C10: =C8-C9-C10 -> #VALUE! | D10: =D8-D9-D10 -> #VALUE! | E10: =E8-E9-E10 -> #VALUE! | F10: Step4-Step5-Step6
A12: Step8：保険料基準月額の算定（円）
A13: 計算式：Step7 ÷ (第1号被保険者数3年合計 × 12ヶ月 × 予定収納率 × 補正係数1.0)
A14: 第1号被保険者数 3年合計 | B14: =01_入力_基礎データ!B11 -> 0 | D14: シート01から自動参照
A15: 予定収納率(5年平均) | B15: =01_入力_基礎データ!B24/100 -> #VALUE! | D15: シート01から自動参照(%→比率変換)
A16: 補正係数(所得段階分布) | B16: 1.0 | D16: 9段階・13段階の平均係数。後で精緻化
A18: Step8 保険料基準月額(円) | B18: 計算結果 | C18: =IFERROR(C11*1000/($B$15*12*$B$16*$B$17),"町データ入力後算定") -> 町データ入力後算定 | D18: =IFERROR(D11*1000/($B$15*12*$B$16*$B$17),"町データ入力後算定") -> 町データ入力後算定 | E18: =IFERROR(E11*1000/($B$15*12*$B$16*$B$17),"町データ入力後算定") -> 町データ入力後算定 | F18: 第10期基準月額
A20: ■ 第9期との比較
A21: 比較項目 | B21: 第8期 | C21: 第9期 | D21: 第10期A | E21: 第10期B | F21: 第10期C
A22: 月額(円) | B22: 6380 | C22: 6500 | D22: =IFERROR(C18,"未算定") -> 町データ入力後算定 | E22: =IFERROR(D18,"未算定") -> 町データ入力後算定 | F22: =IFERROR(E18,"未算定") -> 町データ入力後算定
A23: 第9期比増減率(%) | D23: =IFERROR((D22/$C$22-1)*100,"未算定") -> 未算定 | E23: =IFERROR((E22/$C$22-1)*100,"未算定") -> 未算定 | F23: =IFERROR((F22/$C$22-1)*100,"未算定") -> 未算定

Sheet 07_所得段階_9段階
A1: 07 所得段階別保険料（9段階版・現行）
A2: ── 現行9段階区分での所得段階別年間保険料(月額×12) ──
A4: 段階 | B4: 対象 | C4: 係数 | D4: 月額A(円) | E4: 月額B(円) | F4: 月額C(円) | G4: 該当人数
A5: 第1段階 | B5: 生活保護・老齢福祉年金受給者・市町村民税非課税世帯+本人非課税 | C5: 0.3 | D5: =IFERROR('06_Step7-8_収納額_基準額'!C18*$C5,"未算定") -> 未算定 | E5: =IFERROR('06_Step7-8_収納額_基準額'!D18*$C5,"未算定") -> 未算定 | F5: =IFERROR('06_Step7-8_収納額_基準額'!E18*$C5,"未算定") -> 未算定
A6: 第2段階 | B6: 市町村民税非課税世帯+本人非課税(年金収入80万円超120万円以下) | C6: 0.5 | D6: =IFERROR('06_Step7-8_収納額_基準額'!C18*$C6,"未算定") -> 未算定 | E6: =IFERROR('06_Step7-8_収納額_基準額'!D18*$C6,"未算定") -> 未算定 | F6: =IFERROR('06_Step7-8_収納額_基準額'!E18*$C6,"未算定") -> 未算定
A7: 第3段階 | B7: 市町村民税非課税世帯+本人非課税(年金収入120万円超) | C7: 0.7 | D7: =IFERROR('06_Step7-8_収納額_基準額'!C18*$C7,"未算定") -> 未算定 | E7: =IFERROR('06_Step7-8_収納額_基準額'!D18*$C7,"未算定") -> 未算定 | F7: =IFERROR('06_Step7-8_収納額_基準額'!E18*$C7,"未算定") -> 未算定
A8: 第4段階 | B8: 本人市町村民税非課税(世帯課税)・課税年金収入80万円以下 | C8: 0.9 | D8: =IFERROR('06_Step7-8_収納額_基準額'!C18*$C8,"未算定") -> 未算定 | E8: =IFERROR('06_Step7-8_収納額_基準額'!D18*$C8,"未算定") -> 未算定 | F8: =IFERROR('06_Step7-8_収納額_基準額'!E18*$C8,"未算定") -> 未算定
A9: 第5段階(基準) | B9: 本人市町村民税非課税(世帯課税)・課税年金収入80万円超 | C9: 1 | D9: =IFERROR('06_Step7-8_収納額_基準額'!C18*$C9,"未算定") -> 未算定 | E9: =IFERROR('06_Step7-8_収納額_基準額'!D18*$C9,"未算定") -> 未算定 | F9: =IFERROR('06_Step7-8_収納額_基準額'!E18*$C9,"未算定") -> 未算定
A10: 第6段階 | B10: 本人市町村民税課税・合計所得120万円未満 | C10: 1.2 | D10: =IFERROR('06_Step7-8_収納額_基準額'!C18*$C10,"未算定") -> 未算定 | E10: =IFERROR('06_Step7-8_収納額_基準額'!D18*$C10,"未算定") -> 未算定 | F10: =IFERROR('06_Step7-8_収納額_基準額'!E18*$C10,"未算定") -> 未算定
A11: 第7段階 | B11: 本人市町村民税課税・合計所得120万円以上210万円未満 | C11: 1.3 | D11: =IFERROR('06_Step7-8_収納額_基準額'!C18*$C11,"未算定") -> 未算定 | E11: =IFERROR('06_Step7-8_収納額_基準額'!D18*$C11,"未算定") -> 未算定 | F11: =IFERROR('06_Step7-8_収納額_基準額'!E18*$C11,"未算定") -> 未算定
A12: 第8段階 | B12: 本人市町村民税課税・合計所得210万円以上320万円未満 | C12: 1.5 | D12: =IFERROR('06_Step7-8_収納額_基準額'!C18*$C12,"未算定") -> 未算定 | E12: =IFERROR('06_Step7-8_収納額_基準額'!D18*$C12,"未算定") -> 未算定 | F12: =IFERROR('06_Step7-8_収納額_基準額'!E18*$C12,"未算定") -> 未算定
A13: 第9段階 | B13: 本人市町村民税課税・合計所得320万円以上 | C13: 1.7 | D13: =IFERROR('06_Step7-8_収納額_基準額'!C18*$C13,"未算定") -> 未算定 | E13: =IFERROR('06_Step7-8_収納額_基準額'!D18*$C13,"未算定") -> 未算定 | F13: =IFERROR('06_Step7-8_収納額_基準額'!E18*$C13,"未算定") -> 未算定
A15: ※ 係数は国基準値です。市町村は条例により調整可能(±10%程度)。
A16: ※ 該当人数の合計は所得段階別R3末3,255人(第5基準697人)が参考値です。R7時点の確定値を入力してください。
A17: ※ 本シートはステップ8の算定結果を所得段階別に展開した参考表です。条例改正案作成の元データとなります。

Sheet 08_所得段階_13段階
A1: 08 所得段階別保険料（13段階版・協議事項5）
A2: ── 国推奨13段階区分での所得段階別保険料 ──
A4: 段階 | B4: 対象 | C4: 係数 | D4: 月額A(円) | E4: 月額B(円) | F4: 月額C(円) | G4: 該当人数
A5: 第1段階 | B5: 生活保護受給者・老齢福祉年金受給者・住民税非課税世帯本人収入80万円以下 | C5: 0.285 | D5: =IFERROR('06_Step7-8_収納額_基準額'!C18*$C5,"未算定") -> 未算定 | E5: =IFERROR('06_Step7-8_収納額_基準額'!D18*$C5,"未算定") -> 未算定 | F5: =IFERROR('06_Step7-8_収納額_基準額'!E18*$C5,"未算定") -> 未算定
A6: 第2段階 | B6: 住民税非課税世帯+本人収入80万円超120万円以下 | C6: 0.485 | D6: =IFERROR('06_Step7-8_収納額_基準額'!C18*$C6,"未算定") -> 未算定 | E6: =IFERROR('06_Step7-8_収納額_基準額'!D18*$C6,"未算定") -> 未算定 | F6: =IFERROR('06_Step7-8_収納額_基準額'!E18*$C6,"未算定") -> 未算定
A7: 第3段階 | B7: 住民税非課税世帯+本人収入120万円超 | C7: 0.685 | D7: =IFERROR('06_Step7-8_収納額_基準額'!C18*$C7,"未算定") -> 未算定 | E7: =IFERROR('06_Step7-8_収納額_基準額'!D18*$C7,"未算定") -> 未算定 | F7: =IFERROR('06_Step7-8_収納額_基準額'!E18*$C7,"未算定") -> 未算定
A8: 第4段階 | B8: 本人非課税(世帯課税)+課税年金収入80万円以下 | C8: 0.88 | D8: =IFERROR('06_Step7-8_収納額_基準額'!C18*$C8,"未算定") -> 未算定 | E8: =IFERROR('06_Step7-8_収納額_基準額'!D18*$C8,"未算定") -> 未算定 | F8: =IFERROR('06_Step7-8_収納額_基準額'!E18*$C8,"未算定") -> 未算定
A9: 第5段階(基準) | B9: 本人非課税(世帯課税)+課税年金収入80万円超 | C9: 1 | D9: =IFERROR('06_Step7-8_収納額_基準額'!C18*$C9,"未算定") -> 未算定 | E9: =IFERROR('06_Step7-8_収納額_基準額'!D18*$C9,"未算定") -> 未算定 | F9: =IFERROR('06_Step7-8_収納額_基準額'!E18*$C9,"未算定") -> 未算定
A10: 第6段階 | B10: 本人課税・合計所得120万円未満 | C10: 1.2 | D10: =IFERROR('06_Step7-8_収納額_基準額'!C18*$C10,"未算定") -> 未算定 | E10: =IFERROR('06_Step7-8_収納額_基準額'!D18*$C10,"未算定") -> 未算定 | F10: =IFERROR('06_Step7-8_収納額_基準額'!E18*$C10,"未算定") -> 未算定
A11: 第7段階 | B11: 本人課税・合計所得120万円以上210万円未満 | C11: 1.3 | D11: =IFERROR('06_Step7-8_収納額_基準額'!C18*$C11,"未算定") -> 未算定 | E11: =IFERROR('06_Step7-8_収納額_基準額'!D18*$C11,"未算定") -> 未算定 | F11: =IFERROR('06_Step7-8_収納額_基準額'!E18*$C11,"未算定") -> 未算定
A12: 第8段階 | B12: 本人課税・合計所得210万円以上320万円未満 | C12: 1.5 | D12: =IFERROR('06_Step7-8_収納額_基準額'!C18*$C12,"未算定") -> 未算定 | E12: =IFERROR('06_Step7-8_収納額_基準額'!D18*$C12,"未算定") -> 未算定 | F12: =IFERROR('06_Step7-8_収納額_基準額'!E18*$C12,"未算定") -> 未算定
A13: 第9段階 | B13: 本人課税・合計所得320万円以上420万円未満 | C13: 1.7 | D13: =IFERROR('06_Step7-8_収納額_基準額'!C18*$C13,"未算定") -> 未算定 | E13: =IFERROR('06_Step7-8_収納額_基準額'!D18*$C13,"未算定") -> 未算定 | F13: =IFERROR('06_Step7-8_収納額_基準額'!E18*$C13,"未算定") -> 未算定
A14: 第10段階(新) | B14: 本人課税・合計所得420万円以上520万円未満 | C14: 1.9 | D14: =IFERROR('06_Step7-8_収納額_基準額'!C18*$C14,"未算定") -> 未算定 | E14: =IFERROR('06_Step7-8_収納額_基準額'!D18*$C14,"未算定") -> 未算定 | F14: =IFERROR('06_Step7-8_収納額_基準額'!E18*$C14,"未算定") -> 未算定
A15: 第11段階(新) | B15: 本人課税・合計所得520万円以上620万円未満 | C15: 2.1 | D15: =IFERROR('06_Step7-8_収納額_基準額'!C18*$C15,"未算定") -> 未算定 | E15: =IFERROR('06_Step7-8_収納額_基準額'!D18*$C15,"未算定") -> 未算定 | F15: =IFERROR('06_Step7-8_収納額_基準額'!E18*$C15,"未算定") -> 未算定
A16: 第12段階(新) | B16: 本人課税・合計所得620万円以上720万円未満 | C16: 2.3 | D16: =IFERROR('06_Step7-8_収納額_基準額'!C18*$C16,"未算定") -> 未算定 | E16: =IFERROR('06_Step7-8_収納額_基準額'!D18*$C16,"未算定") -> 未算定 | F16: =IFERROR('06_Step7-8_収納額_基準額'!E18*$C16,"未算定") -> 未算定
A17: 第13段階(新) | B17: 本人課税・合計所得720万円以上 | C17: 2.4 | D17: =IFERROR('06_Step7-8_収納額_基準額'!C18*$C17,"未算定") -> 未算定 | E17: =IFERROR('06_Step7-8_収納額_基準額'!D18*$C17,"未算定") -> 未算定 | F17: =IFERROR('06_Step7-8_収納額_基準額'!E18*$C17,"未算定") -> 未算定
A19: ※ (新)マークは9段階版にはなかった新設段階(第10〜13段階)です。高所得層への応分負担で全体最適化。
A20: ※ 係数は国推奨値ですが、市町村は条例で調整可能。委員会協議で確定値を決定します。
A21: ※ 13段階への移行は、低所得層(1〜3段階・約30%)の負担軽減と、高所得層への応分負担拡大の効果を狙います。
A22: ※ 該当人数のR7時点確定値は町担当課入力後に9段階版と13段階版で再分布を計算します。

Sheet 09_比較分析
A1: 09 3パターン×9/13段階 比較分析
A2: ── 委員会協議に向けた総合比較表・推奨パターンの検討材料 ──
A4: ■ 第10期基準月額の3パターン比較
A5: パターン | B5: 月額 | C5: 第9期比 | D5: 基金活用 | E5: 推奨度・特徴
A6: A 取崩なし | B6: =IFERROR('06_Step7-8_収納額_基準額'!C18,"未算定") -> 町データ入力後算定 | C6: 高 | D6: なし | E6: 基金温存・第11期負担緩和の安定性
A7: B 50%取崩 | B7: =IFERROR('06_Step7-8_収納額_基準額'!D18,"未算定") -> 町データ入力後算定 | C7: 中 | D7: 50% | E7: 中庸選択・住民負担と次期均衡(国推奨水準)
A8: C 全額取崩 | B8: =IFERROR('06_Step7-8_収納額_基準額'!E18,"未算定") -> 町データ入力後算定 | C8: 低 | D8: 100% | E8: 住民負担最小化・次期負担増リスク
A10: ■ 仙南圏域・宮城県との比較(見える化システム参考値)
A11: 自治体 | B11: 第9期月額 | C11: 第10期月額 | D11: 高齢化率 | E11: 備考
A12: 川崎町(本町) | B12: 6500 | C12: （試算） | D12: 41.4 | E12: 本町
A13: 柴田町 | B13: [入力] | C13: [入力] | D13: [入力] | E13: 見える化システムから入力
A14: 大河原町 | B14: [入力] | C14: [入力] | D14: [入力] | E14: 見える化システムから入力
A15: 村田町 | B15: [入力] | C15: [入力] | D15: [入力] | E15: 見える化システムから入力
A16: 蔵王町 | B16: [入力] | C16: [入力] | D16: [入力] | E16: 見える化システムから入力
A17: 仙南圏域平均 | B17: [入力] | C17: [入力] | D17: [入力] | E17: 見える化システムから入力
A18: 宮城県平均 | B18: [入力] | C18: [入力] | D18: 28.5 | E18: 宮城県計画から入力
A19: 全国平均 | B19: 6225 | C19: [入力] | D19: 29.1 | E19: 全国平均(第9期)
A21: ■ 第3回策定委員会向け 委員協議のポイント
A22: ①住民負担vs持続可能性のバランス：基金温存(A)か、住民負担軽減(C)か、中庸(B)か。
A23: ②国推奨水準との比較：国はパターンB(50%取崩)を標準的水準として推奨。
A24: ③仙南圏域・宮城県平均との水準感：本町は宮城県平均より若干上の水準で推移する見込み。
A25: ④第11期(R12〜)の予測：給付費上昇傾向の中で、第11期負担増のリスクを勘案。
A26: ⑤所得段階区分(9→13段階)の影響：低所得層負担軽減と高所得層応分負担のバランス。
A27: ⑥委員会では各委員にA/B/Cの選好を伺い、論点整理→次回再協議の流れを推奨。
