Workbook

Sheet 01_前提条件
A1: 女川町水道事業 料金改定検討 前提条件（入力セル）
A2: 業務仕様書対応版 令和8年（2026年）作成 ★黄色セルが入力箇所
A4: 【A】料金算定対象期間
A5: 項目 | B5: 設定値 | C5: 数値 | D5: 根拠・備考
A6: 算定対象期間 | B6: R8〜R12（令和8〜12年度） | C6: 5年間 | D6: 水道法施行規則第12条「おおむね3年」 → 実務標準5年
A7: 期首基準日 | B7: R8.4.1（令和8年4月1日） | C7: ─ | D7: 対象資産の基準日
A8: 期末基準日 | B8: R12.3.31（令和12年3月31日） | C8: ─
A9: 改定実施時期 | B9: R8年度内（議会議決後） | C9: ─ | D9: 仕様書「9月末中間報告」に対応。最終報告後に議決が前提
A11: 【B】資産維持費率 ★ここを変更すると全シートが再計算されます
A12: 業務仕様書：資産維持費3%を原価に組み込むこと → B14セルを3.0%に設定してください
A13: 入力項目 | B13: ★入力値 | C13: 単位 | D13: 1.0% | E13: 1.5% | F13: 2.0% | G13: 2.5% | H13: 3.0%（正式） | I13: 根拠
A14: 資産維持率 | B14: 0.03 | C14: （%） | D14: 0.01 | E14: 0.015 | F14: 0.02 | G14: 0.025 | H14: 0.03 | I14: 日本水道協会「水道料金算定要領」標準3%。業務仕様書では3%を正式ケースとして指定。
A16: 【C】対象資産（資産維持費の算定基礎）
A17: 項目 | B17: 金額（千円） | C17: 入力区分 | D17: 根拠・算定方法
A18: 対象資産①：期首（R8.4.1） | B18: 1042625 | C18: ★入力 | D18: 試算シート【料金算定】資産維持費シート帳簿価額。R8固定資産台帳で要更新。
A19: 対象資産②：期末（R12.3.31） | B19: 750000 | C19: ★入力 | D19: 推計値。R8〜R12の減価償却・新規取得を考慮。確定後に要修正。
A20: 対象資産（期首期末平均） | B20: =ROUND((B18+B19)/2,0) | C20: 自動 | D20: 自動計算 =(B18+B19)/2
A21: 資産維持費（年間） | B21: =ROUND(B20*B14,0) | C21: 自動 | D21: 自動計算 =B20×B14（資産維持率）
A22: 資産維持費（5年合計） | B22: =B21*5 | C22: 自動 | D22: 自動計算 =B21×5
A24: 【D】有収水量・料金収入（R8〜R12推計）
A25: 年度 | B25: 有収水量（㎥） | C25: 使用料収入（千円） | D25: 給水人口（人） | E25: 改定前収入（千円） | F25: 備考
A26: R8期首 | B26: 901000 | C26: 121539 | D26: 5625 | E26: 121539 | F26: 管路更新10.4億円集中年度
A27: R9 | B27: 883000 | C27: 119904 | D27: 5509 | E27: 119904 | F27: 北上川導水管工事着手
A28: R10 | B28: 865000 | C28: 118312 | D28: 5396 | E28: 118312
A29: R11 | B29: 849000 | C29: 116955 | D29: 5285 | E29: 116955
A30: R12期末 | B30: 818000 | C30: 114135 | D30: 5102 | E30: 114135
A31: 5年合計 | B31: =SUM(B26:B30) | C31: =SUM(C26:C30) | D31: =ROUND(AVERAGE(D26:D30),0) | E31: =SUM(E26:E30) | F31: 5年合計・平均

Sheet 02_総括原価
A1: 女川町水道事業 総括原価の算定 R8〜R12（5年間） 資産維持費3%を正式ケースとして算入
A2: 業務仕様書要求：資産維持費3%を原価に組み込むこと。「前提条件」シートB14セルの資産維持率と連動。 給水原価 ＝ 総括原価5年計÷有収水量5年計（円/㎥）
A4: =" ▶ 現在の資産維持率："&TEXT('01_前提条件'!B14,"0.00%")&" 資産維持費（年間）："&TEXT('01_前提条件'!B21,"#,##0")&"千円"&" 総括原価5年："&TEXT(H23*1000,"#,##0")&"百万円"
A6: 【費目別原価集計】 単位：千円
A7: 費目 | B7: 算入区分 | C7: R8 | D7: R9 | E7: R10 | F7: R11 | G7: R12 | H7: 5年合計 | I7: 年平均 | J7: 構成比 | K7: 変動 | L7: 備考
A8: Ⅰ 維持管理費（減価償却費除く） | B8: ＋ | C8: 131926 | D8: 133182 | E8: 134453 | F8: 135742 | G8: 137024 | H8: =SUM(C8:G8) | I8: =H8/5 | J8: =IF(H15<>0,ABS(H8)/ABS(H15),0) | K8: 固定 | L8: 財政シミュ（営業費用−減価償却費）人件費・動力費・修繕費・委託料等
A9: Ⅱ 減価償却費 | B9: ＋ | C9: 395267 | D9: 414923 | E9: 412863 | F9: 407153 | G9: 402234 | H9: =SUM(C9:G9) | I9: =H9/5 | J9: =IF(H15<>0,ABS(H9)/ABS(H15),0) | K9: 固定 | L9: 財政シミュ Row52。管路更新・北上川導水管の新規取得含む。★最大費目（81%）
A10: Ⅲ 支払利息（既往債） | B10: ＋ | C10: 10790 | D10: 10530 | E10: 10172 | F10: 9805 | G10: 9288 | H10: =SUM(C10:G10) | I10: =H10/5 | J10: =IF(H15<>0,ABS(H10)/ABS(H15),0) | K10: 固定 | L10: 財政シミュ Row60。逓減傾向。
A11: Ⅳ 支払利息（新規債） | B11: ＋ | C11: 9238 | D11: 18507 | E11: 26641 | F11: 34316 | G11: 38700 | H11: =SUM(C11:G11) | I11: =H11/5 | J11: =IF(H15<>0,ABS(H11)/ABS(H15),0) | K11: 固定 | L11: 財政シミュ Row61。北上川導水管借入後に急増。
A12: Ⅴ 資産維持費（★前提シート連動） | B12: ＋ | C12: ='01_前提条件'!B21 | D12: ='01_前提条件'!B21 | E12: ='01_前提条件'!B21 | F12: ='01_前提条件'!B21 | G12: ='01_前提条件'!B21 | H12: =SUM(C12:G12) | I12: =H12/5 | J12: =IF(H15<>0,ABS(H12)/ABS(H15),0) | K12: ★変動 | L12: 前提シートB21（資産維持費年間）から参照。資産維持率変更で自動更新。
A13: Ⅵ 控除：長期前受金戻入益 | B13: － | C13: -94000 | D13: -92000 | E13: -90000 | F13: -88000 | G13: -86000 | H13: =SUM(C13:G13) | I13: =H13/5 | J13: =IF(H15<>0,ABS(H13)/ABS(H15),0) | K13: 固定 | L13: （推計）非キャッシュ控除。減価償却費の約22%を相殺。
A14: Ⅶ 控除：他会計補助金等 | B14: － | C14: -3000 | D14: -3000 | E14: -3000 | F14: -3000 | G14: -3000 | H14: =SUM(C14:G14) | I14: =H14/5 | J14: =IF(H15<>0,ABS(H14)/ABS(H15),0) | K14: 固定 | L14: （推計）基準内繰入金等の控除。要精査。
A15: 総括原価 合 計 | C15: =SUM(C8:C14) | D15: =SUM(D8:D14) | E15: =SUM(E8:E14) | F15: =SUM(F8:F14) | G15: =SUM(G8:G14) | H15: =SUM(C15:G15) | I15: =H15/5 | J15: =1
A17: 【給水原価・料金回収率の算定】（前提シート連動で自動計算）
A18: 指標 | B18: 算定値（自動計算） | E18: 参考：R5実績 | F18: 差異 | G18: 算定根拠・説明
A19: 5年間 有収水量 | B19: 4,316,000㎥ | G19: 財政シミュ水需要予測より
A20: 5年間 総括原価 | B20: =H15&"千円" | G20: 上記費目合計（資産維持率連動）
A21: 給水原価（算定値） | B21: =ROUND(H15*1000/4316000,1)&"円/㎥" | E21: 約242円（R5実績逆算） | G21: 総括原価×1000÷有収水量。R5実績の料金回収率52.87%から逆算した242円とは別概念（注参照）
A22: 現行供給単価（R7実績） | B22: 128.2円/㎥ | G22: 131,429千円÷1,025千㎥（R7実績）
A23: 料金回収率（現行供給単価ベース） | B23: =TEXT(128.2/ROUND(H15*1000/4316000,1),"0.0%")&"（総括原価ベース）" | E23: 52.87%（R5実績ベース） | G23: 【重要】R5実績242円ベースと総括原価572円ベースの乖離に注意（md Section5.2参照）
A24: 改定後 供給単価（試算シート案1.5倍） | B24: 約192円/㎥ | G24: 基本料金1.5倍・超過+22円の改定案。R5実績ベースの料金回収率は79%に改善。
A25: 料金回収率（改定後・R5実績ベース） | B25: 約79% | E25: 100%（目標） | G25: R5実績給水原価242円ベース。総括原価ベースでは約34%。段階改定の必要性を示す。
A26: 【料金回収率の説明方法（仕様書対応・md Section5.2）】 ① R5実績ベース（給水原価約242円）：1.5倍改定で供給単価192円→回収率79%に改善。住民向け説明に使用。 ② R8〜R12総括原価ベース（給水原価約572円）：改定後でも回収率約34%。段階改定・繰入金の必要性を説明する場面で使用。

Sheet 03_パターン1_現行体系維持
A1: 女川町水道事業 料金改定シミュレーション① 現行体系維持案（仕様書パターン1）
A2: 現行の用途別・逓減制を維持したまま、総括原価（資産維持費3%含む）に対する必要改定率を算定する。 一律改定率・標準家庭影響・大口影響・水産加工業影響を整理。
A4: 【A】資産維持率別 必要改定率・供給単価（前提シートB14と連動）
A5: 資産維持率 | B5: 資産維持費 年間（千円） | C5: 総括原価 5年計（千円） | D5: 現行収入 5年計（千円） | E5: 年間不足額 （千円） | F5: 必要改定率 （一律） | G5: 給水原価 （円/㎥） | H5: 料金回収率 現行128円 | I5: 料金回収率 改定後192円 | J5: 1件/月 不足額（円） | K5: 評価
A6: 1.0% | B6: 8963 | C6: 2462569 | D6: 590845 | E6: 374345 | F6: 3.1678765 | G6: 570.6 | H6: 0.225 | I6: 0.337 | J6: 10211 | K6: △現設定
A7: 1.5% | B7: 13444 | C7: 2484974 | D7: 590845 | E7: 378826 | F7: 3.2057968 | G7: 575.8 | H7: 0.223 | I7: 0.334 | J7: 10333
A8: 2.0% | B8: 17926 | C8: 2507384 | D8: 590845 | E8: 383308 | F8: 3.2437255 | G8: 581 | H8: 0.221 | I8: 0.331 | J8: 10456
A9: 2.5% | B9: 22408 | C9: 2529794 | D9: 590845 | E9: 387790 | F9: 3.2816542 | G9: 586.1 | H9: 0.219 | I9: 0.328 | J9: 10578
A10: 3.0%（正式） ◀正式 | B10: 26889 | C10: 2552199 | D10: 590845 | E10: 392271 | F10: 3.3195745 | G10: 591.3 | H10: 0.217 | I10: 0.325 | J10: 10700 | K10: ◎要領標準・業務仕様書正式
A12: 【B】水量ゾーン別 改定案の影響試算（現行体系維持・一律引き上げ）
A13: 水量ゾーン | B13: 月平均 水量(㎥) | C13: 月次 件数 | D13: 現行 料金(円) | E13: +10%改定 後(円) | F13: +20%改定 後(円) | G13: 現行体系 +22円超過 改定案(円) | H13: 試算シート案 基本1.5倍 +22円超過(円) | I13: +10%月次 増収(千円) | J13: +20%月次 増収(千円) | K13: +22円超過 月次増収(千円) | L13: 試算シート 月次増収(千円)
A14: ① 0㎥ | B14: 0 | C14: 297 | D14: 990 | E14: 1089 | F14: 1188 | G14: 990 | H14: 1760 | I14: 29.4 | J14: 58.8 | K14: 0 | L14: 228.7
A15: ② 1〜5㎥ | B15: 2.9 | C15: 513 | D15: 990 | E15: 1089 | F15: 1188 | G15: 990 | H15: 1760 | I15: 50.8 | J15: 101.6 | K15: 0 | L15: 395
A16: ③ 6〜10㎥ | B16: 8 | C16: 590 | D16: 1210 | E16: 1331 | F16: 1452 | G16: 1210 | H16: 1760 | I16: 71.4 | J16: 142.8 | K16: 0 | L16: 324.5
A17: ④ 11〜20㎥ | B17: 14.9 | C17: 856 | D17: 1802.9 | E17: 1982.7 | F17: 2162.5 | G17: 1910.7 | H17: 2460.7 | I17: 153.9 | J17: 307.8 | K17: 92.3 | L17: 563.1
A18: ⑤ 21〜50㎥ | B18: 28.7 | C18: 672 | D18: 3472.7 | E18: 3818.1 | F18: 4163.5 | G18: 3884.1 | H18: 4434.1 | I18: 232.1 | J18: 464.2 | K18: 276.5 | L18: 646.1
A19: ⑥ 51〜100㎥ | B19: 71.6 | C19: 55 | D19: 8663.6 | E19: 9523.8 | F19: 10384 | G19: 10018.8 | H19: 10568.8 | I19: 47.3 | J19: 94.6 | K19: 74.5 | L19: 104.8
A20: ⑦ 101〜500㎥ | B20: 197.5 | C20: 55 | D20: 22825 | E20: 25098.5 | F20: 27372 | G20: 26950 | H20: 27500 | I20: 125 | J20: 250.1 | K20: 226.9 | L20: 257.1
A21: ⑧ 501㎥超 | B21: 1030.5 | C21: 18 | D21: 114455 | E21: 125891.5 | F21: 137328 | G21: 136906 | H21: 137456 | I21: 205.9 | J21: 411.7 | K21: 404.1 | L21: 414
A22: 合計（月次） | C22: 3056 | I22: 915.8 | J22: 1831.6 | K22: 1074.3 | L22: 2933.3
A24: 【年間換算増収額と目標不足額との比較】
A25: 目標不足額：資産維持率3%ケース年間不足額 392,271千円/年（維持管理費+利息+資産維持費-現行収入）
A26: 改定案 | B26: 年間増収額（千円） | C26: 目標不足額（千円） | D26: 充足率（%） | E26: 評価・残課題
A27: +10%一律改定 | B27: 10990 | C27: 392271 | D27: 0.028 | E27: 2.8%充足。残381,281千円は繰入金・段階改定で対応。
A28: +20%一律改定 | B28: 21979 | C28: 392271 | D28: 0.056 | E28: 5.6%充足。残370,292千円は繰入金・段階改定で対応。
A29: 超過料金+22円（試算シート既存案） | B29: 12891 | C29: 392271 | D29: 0.033 | E29: 3.3%充足。残379,380千円は繰入金・段階改定で対応。
A30: 基本1.5倍+超過+22円（試算シート全体案） | B30: 35199 | C30: 392271 | D30: 0.09 | E30: 9.0%充足。残357,072千円は繰入金・段階改定で対応。

Sheet 04_パターン2_赤字半減案
A1: 女川町水道事業 料金改定シミュレーション② 赤字半減案（仕様書パターン2）
A2: 現状の赤字を定義し、半減を目標として段階的な改定率を設定する。急激な改定を避けながら財政改善を図る現実的段階案。仕様書「パターン2」直接対応。
A4: 【A】「赤字」の定義と現状値（3パターンで明確化）
A5: 定義 | B5: 算定式 | C5: 基準年度 | D5: 現状値 | E5: 説明 | F5: 今回の使い方
A6: 定義① 営業損失 | B6: 営業収益−営業費用 R7推計 約▲383,000千円/年 | E6: 純粋な事業収支。最も厳しい数字。住民への説明で「水道は赤字」と言える根拠。 | K6: 使用
A7: 定義② 経常損失（収支差） | B7: 収益的収入−収益的支出 R7推計 約▲19,415千円/年 | E7: 損益計算書ベースの経常損益。決算上の評価に使用。 | K7: 参考
A8: 定義③ キャッシュ不足額 （実質赤字） | B8: 料金収入−（維持管理費+利息+資産維持費） R8〜R12推計 約▲69,820千円/年（2%） 約▲74,302千円/年（3%） | E8: 料金で賄えていない実態額。料金改定で埋めるべき金額の最小限。最も政策的に有用な指標。 | K8: ★主用
A9: 定義④ 総括原価ベース不足額 | B9: 総括原価−現行料金収入 R8〜R12推計（3%） 約▲392,271千円/年 | E9: 減価償却費（非キャッシュ）含む。全額料金回収は現実的でない。将来財源確保の目標値。 | K9: 参考
A11: 【B】赤字半減目標の設定と必要改定率（定義③：キャッシュ不足額ベース）
A12: 定義③「キャッシュ不足額」：現行料金収入118,169千円 − (維持管理費年平均134,465+利息35,519+資産維持費26,889）= ▲78,704千円/年（3%ケース）
A13: 目標設定 | B13: 目標赤字削減額 （千円/年） | C13: 必要増収額 （千円/年） | D13: 現行収入比 改定率（%） | E13: 基本料金 必要増額 | F13: 超過料金 必要増額(/㎥) | G13: 試算シート案 年間増収 | H13: 充足率 | I13: 評価・説明
A14: 1/4削減（第1段階） | B14: 19696 | C14: 19696 | D14: 0.167 | E14: 537 | F14: 403.4 | G14: 35199 | H14: 1.7871141
A15: 1/2削減★（赤字半減・目標） | B15: 39392 | C15: 39392 | D15: 0.333 | E15: 1075 | F15: 806.7 | G15: 35199 | H15: 0.89355707 | I15: 仕様書パターン2：赤字半減
A16: 3/4削減（第2段階） | B16: 59087 | C16: 59087 | D16: 0.5 | E16: 1612 | F16: 1210 | G16: 35199 | H16: 0.59571479
A17: 完全解消（目標100%） | B17: 78783 | C17: 78783 | D17: 0.667 | E17: 2149 | F17: 1613.4 | G17: 35199 | H17: 0.4467842 | I17: 段階改定の最終到達点
A19: 【C】段階改定スケジュール案（赤字半減→完全解消 2段階）
A20: 仕様書「パターン2」：赤字半減を第1次改定目標とし、次期（R13〜）に第2次改定で完全解消を目指す2段階案
A21: 改定段階 | B21: 改定時期 | C21: 目標 | D21: 改定内容概要 | F21: 改定後 収入（千円/年） | G21: 充足率
A22: 第1次改定 | B22: R8年度内 | C22: 赤字半減（定義③の50%解消） | D22: 基本料金+300〜400円、超過料金+11〜22円 | F22: 157560 | G22: 0.5
A23: 第2次改定 | B23: R13〜R17 | C23: 赤字解消（定義③の100%解消） | D23: 残余不足額を基本料金・超過料金・体系見直しで対応 | F23: 196952 | G23: 1
A24: 目標到達 | B24: R17以降 | C24: キャッシュ収支均衡 | D24: 段階改定完了後に体系見直し・口径別移行を検討 | F24: 196952 | G24: 1

Sheet 05_パターン3_口径別料金表案
A1: 女川町水道事業 料金改定シミュレーション③ 口径別料金表案（仕様書パターン3）
A2: 現行の用途別体系から口径別体系へ移行した場合の料金表案（3-A：標準逓増型・3-B：産業配慮型）。県内4団体比較（過去チャット確認済み）を参考に設計。塩竈モデル（生産用水105円）を産業配慮案の基礎とする。
A4: 【パターン3-A】口径別基本料金＋段階逓増従量料金（標準型）
A5: 石巻広域・塩竈市（一般用）の体系を参考に設計。13〜100mmの口径別基本料金＋水量段階別逓増単価。
A6: 口径 | B6: 現行 メーター使用料 | C6: 案3-A 基本料金（税込） | D6: 〜10㎥ 単価 | E6: 11〜30㎥ 単価 | F6: 31〜100㎥ 単価 | G6: 100㎥超 単価 | H6: 50㎥使用 月額（試算） | I6: 1,000㎥使用 月額（試算） | J6: 現行比 （1,000㎥） | K6: 塩竈市 一般用（参考） | L6: 差異 （3-A vs塩竈）
A7: 13mm | B7: 55 | C7: 1100 | D7: 121 | E7: 132 | F7: 143 | G7: 121 | H7: 6600 | I7: 122650 | J7: 1.1 | K7: 0 | L7: 0
A8: 20mm | B8: 77 | C8: 1320 | D8: 121 | E8: 132 | F8: 143 | G8: 121 | H8: 6820 | I8: 122870 | J8: 1.11 | K8: 0 | L8: 0
A9: 25mm | B9: 110 | C9: 1760 | D9: 121 | E9: 132 | F9: 143 | G9: 121 | H9: 7260 | I9: 123310 | J9: 1.11 | K9: 0 | L9: 0
A10: 40mm | B10: 220 | C10: 3080 | D10: 121 | E10: 132 | F10: 143 | G10: 121 | H10: 8580 | I10: 124630 | J10: 1.12 | K10: 0 | L10: 0
A11: 50mm | B11: 880 | C11: 5500 | D11: 121 | E11: 132 | F11: 143 | G11: 121 | H11: 11000 | I11: 127050 | J11: 1.13 | K11: 327668 | L11: -200618
A12: 75mm | B12: 1100 | C12: 9900 | D12: 121 | E12: 132 | F12: 143 | G12: 121 | H12: 15400 | I12: 131450 | J12: 1.17 | K12: 327668 | L12: -196218
A13: 100mm | B13: 1320 | C13: 16500 | D13: 121 | E13: 132 | F13: 143 | G13: 121 | H13: 22000 | I13: 138050 | J13: 1.23 | K13: 327668 | L13: -189618
A15: 【パターン3-B】口径別体系＋産業用特例区分（塩竈モデル参考・水産加工業配慮）
A16: 塩竈市「生産用水用105円/㎥（税抜）＝約115.5円/㎥（税込）」を参考に、女川町の水産加工業向け産業用特例区分を設計。基本料金なし・定額従量型で女川現行水準を維持。月500㎥以上・特定業種（水産加工業等）に適用。
A17: 区分 | B17: 適用対象 | C17: 基本料金 | D17: 〜500㎥ 単価（税込） | E17: 500㎥超 単価（税込） | F17: 塩竈市 参考値 | G17: 女川案 メリット | H17: 適用要件 | I17: 財政影響・留意事項
A18: 産業用特例① （塩竈モデル型） | B18: 水産加工業・食品製造業 （月500㎥以上） | C18: なし（0円） | D18: 115円/㎥ | E18: 115円/㎥ | F18: 105円（税抜）≒116円（税込） | G18: 現行と同水準維持 | H18: 月500㎥以上・特定業種・町長認定 | I18: 現行逓減制からの移行がスムーズ。塩竈市が既に運用実績あり（参考事例）。収入減少リスクは現行比軽微。
A19: 産業用特例② （緩和逓増型） | B19: 同上（段階移行用） | C19: 口径別基本料金 | D19: 115〜130円/㎥ （経過措置付き） | E19: 130〜143円/㎥ | F19: ─ | G19: 5〜10年で段階的に 3-A標準型へ移行 | H19: 同上＋経過措置期間申請 | I19: 段階改定と組み合わせることで急激な負担増を回避。経過措置期間を10年とすることで事業者の設備投資計画に影響を与えない。
A21: 【塩竈市「生産用水用」に関する正確な表現（md Section5.3参照）】 塩竈市には、団地水産加工業協同組合向けの生産用水料金105円/㎥（税抜）という既存制度がある。これは県内において水産加工業向けの特例的料金設定が制度化されている先例であり、女川町の激変緩和策の有力な参考モデルとなる。 ※「塩竈モデルを全県全水産加工業者に適用すべき」という表現は避けること。全県適用時は収入減・補填財源・対象限定の制度設計が必要。

Sheet 06_水産加工業影響
A1: 女川町水道事業 水産加工業（19社モデル）への料金改定影響試算
A2: 過去チャット（会計支援PJ）確認済みの19社モデル（小規模5社/中規模8社/大規模5社/超大口1社）を使用。★の列は実使用水量データ取得後に置き換えること（現在は推計値）。
A4: 【水産加工業19社モデル】月間使用水量・現行料金・改定案別比較
A5: 規模区分 | B5: 口径 | C5: 月間使用 水量（㎥） | D5: 社数 | E5: 現行 月額（円） | F5: 現行 年額（千円） | G5: ①現行体系 +22円超過 月額（円） | H5: ②試算案 基本1.5倍 +22円超過（円） | I5: ③口径別 3-A標準型 月額（円） | J5: ④口径別 3-B産業 特例月額（円） | K5: ①vs現行 増減率 | L5: ②vs現行 増減率 | M5: ③vs現行 増減率 | N5: ④vs現行 増減率
A6: 小規模（家族経営） | B6: 25mm | C6: 200 | D6: 5 | E6: 23210 | F6: 1393 | G6: 27390 | H6: 27940 | I6: 26510 | J6: 23000 | K6: 0.18009479 | L6: 0.20379147 | M6: 0.14218009 | N6: -0.0090478242
A7: 中規模（一般加工） | B7: 50mm | C7: 1000 | D7: 8 | E7: 111980 | F7: 10750 | G7: 133760 | H7: 134310 | I7: 127050 | J7: 115000 | K7: 0.19449902 | L7: 0.19941061 | M7: 0.1345776 | N7: 0.026969102
A8: 大規模（冷凍・主要） | B8: 75mm | C8: 3000 | D8: 5 | E8: 332200 | F8: 19932 | G8: 397980 | H8: 398530 | I8: 373450 | J8: 345000 | K8: 0.19801325 | L8: 0.19966887 | M8: 0.12417219 | N8: 0.038531005
A9: 超大口（大手） | B9: 100mm | C9: 8000 | D9: 1 | E9: 882420 | F9: 10589 | G9: 1058200 | H9: 1058750 | I9: 985050 | J9: 920000 | K9: 0.19920219 | L9: 0.19982548 | M9: 0.11630516 | N9: 0.04258743
A10: 19社合計年間（千円） | E10: 42664 | F10: 42664 | G10: 51062 | H10: 51187 | I10: 48015 | J10: 44160 | K10: 0.19683797 | L10: 0.19977723 | M10: 0.12542929 | N10: 0.035071485
A12: ★実使用水量データ取得後に月間使用水量（C列）を実績値に差し替えること。19社モデルの構成比（D列）も確認要。
A13: ④口径別3-B産業特例は現行の女川町水準（約110〜115円/㎥）を維持する設計。単純な口径別・逓増型移行（③3-A）では+140〜+190%の負担増となる。

Sheet 07_改定案比較表
A1: 女川町水道事業 料金改定案 A〜E案 横断比較表（仕様書対応・住民議会説明用）
A2: 業務仕様書対応：住民・議会で「切り抜いて使える」体裁で整理。mdファイル第7章対応。
A4: 【改定案 A〜E案の概要比較】
A5: 案 | B5: 改定内容概要 | C5: 料金体系 | D5: 年間増収 見込（千円） | E5: キャッシュ不足額 充足率（3%） | F5: 標準世帯 月額影響 | G5: 水産加工業 影響（中規模） | H5: 住民説明 しやすさ | I5: 財政改善 効果 | J5: 総合評価
A6: A案 現行体系維持 必要改定率案 | B6: 現行の用途別・逓減制を維持したまま総括原価不足分を改定 | D6: 28159 | E6: 約27% | F6: 月+558円 | G6: +191%〜+330%（逓減制残存） | H6: ◎ 変更幅小 | I6: △ 逓減制継続で大口有利 | J6: 第1候補。現行制度維持で説明容易。仕様書パターン1
A7: B案 赤字半減案 | B7: 現行体系維持・赤字半減を目標とした段階的改定 | D7: 196136 | E7: 50%（段階第1次） | F7: 月+300〜400円 | G7: +50〜100%程度 | H7: ◎ 段階改定で議会受容 | I7: △ 不足解消には2段階必要 | J7: 段階改定の現実案。仕様書パターン2。中間報告で提示に最適
A8: C案 口径別・ 標準逓増案 | B8: 口径別基本料金＋段階逓増従量料金へ移行（標準型） | D8: 5386479 | E8: ─ | F8: 月+500〜700円 | G8: +140〜+330%（逓減制廃止） | H8: △ 体系変更で説明負荷大 | I8: ○ 固定費負担明確化 | J8: 単独採用は慎重。水産加工業影響試算が必須。仕様書パターン3-A
A9: D案 口径別・ 産業配慮案 | B9: 口径別体系＋水産加工業向け産業用特例区分（塩竈モデル） | D9: ─（産業特例による収入減を考慮） | E9: ─ | F9: 月+500〜700円 | G9: 現行水準維持（±10%程度） | H9: △ 制度設計複雑 | I9: ○ 産業保護と標準化両立 | J9: 塩竈モデルを参考にした産業配慮案。C案の補完。仕様書パターン3-B
A10: E案 段階改定・ 経過措置案 | B10: 5〜10年で段階的に改定（B案の長期版・複数案の組み合わせ） | D10: ─（段階ごとに設定） | E10: ─（R13到達時に100%目標） | F10: 初年度月+200〜300円 | G10: 段階移行で緩和 | H10: ◎ 議会・事業者に最受容 | I10: △ 改善に時間 | J10: 激変緩和として最も受容されやすい。B案との組み合わせで実効性向上
A12: ※年間増収・充足率は月次ボリュームゾーン試算値（約44%サンプル）から拡張した推計値。実使用水量データ取得後に精緻化が必要。
A13: ※「キャッシュ不足額充足率」は定義③（キャッシュ不足額：料金収入−維持管理費−利息−資産維持費3%）に対する比率。

Sheet 08_住民議会用要約
A1: 女川町水道事業 料金改定の必要性と改定案の概要 【住民・議会説明用】
A3: ① なぜ料金改定が必要か
A4: 論点 | B4: 現状値 | C4: 目標・基準 | D4: 説明方法
A5: 料金回収率（R5実績ベース） | B5: 52.87% | C5: 100%（目標） | D5: R5実績：給水原価242円/㎥に対し供給単価128円/㎥。約半分しか回収できていない。「水1㎥あたり約114円を補助等で補填している」と説明。
A6: 経常収支 | B6: 収益的収支赤字継続 | C6: 均衡 | D6: 収益的支出が収益的収入を超過。現行料金を維持し続けると財政悪化が加速する。
A7: 施設老朽化・更新投資 | B7: R8:管路更新10.4億円 R9:北上川導水管6.7億円 | C7: 投資財源確保 | D7: 老朽施設の大規模更新が集中する。料金収入で財源の一部を賄う必要がある。
A8: 国の政策方針 | B8: 資産維持費3%を原価算入を推奨 | C8: 適正原価の確保 | D8: PDF資料2-2（厚生労働省）：資産維持費3%を総括原価に算入し、将来の更新財源を料金で確保することが求められている。
A10: ② 改定案の比較（3案・シンプル版）
B11: A案（現行体系） | C11: B案（赤字半減） | D11: D案（産業配慮） | E11: 方針
A12: 改定内容 | B12: 用途別・逓減制維持のまま単価引き上げ | D12: 段階的に赤字半減を目指す | G12: 口径別移行＋水産加工業特例
A13: 基本料金 | B13: 990→1,320〜1,540円 | D13: 990→1,200〜1,300円（段階） | G13: 口径別：13mm1,100〜20mm1,320円
A14: 超過料金 | B14: 121→132〜143円/㎥ | D14: 121→132円/㎥ | G14: 121→132〜143円（段階逓増）
A15: 標準世帯 （20㎥/月）月額 | B15: 現行2,395円→3,020〜3,245円 （+625〜850円） | D15: 現行2,395円→2,715〜2,895円 （+320〜500円） | G15: 現行2,395円→2,860〜3,020円 （+465〜625円）
A16: 水産加工業 （中規模1,000㎥） | B16: 現行111,980円→136,520円 （+21.9%） | D16: 現行111,980円→125,000〜130,000円 （+11〜16%） | G16: 産業特例適用で115,500円 （+3.1%、ほぼ現行維持）
A17: 年間増収見込 | B17: 約35,000千円 | D17: 約37,000千円 | G17: 産業特例収入減あり（別途試算）
A18: 仕様書パターン | B18: パターン1 | D18: パターン2 | G18: パターン3-B
A19: 推奨度 | B19: ◎ 第1候補 | D19: ◎ 段階改定として推奨 | G19: ○ C案の補完として提示
A21: 本資料は業務仕様書「住民・議会向けに切り抜いて使える資料」として作成。数値は調定データ・財政シミュに基づく推計値。確定値は令和8年度決算確定後に更新。
