Workbook

Sheet 前提条件（入力）
A1: 女川町上水道事業 料金算定前提条件・パラメータ入力シート
A2: ★ 黄色セルに数値を入力してください。総括原価シートの計算結果が自動更新されます。
A4: 【A】資産維持率（最重要パラメータ）
A5: 資産維持率を下のセル（B7）に直接入力してください。1.0〜3.0%の範囲で設定可能です。
A6: 入力項目 | B6: 入力値 | C6: 単位 | D6: 参考：最小値 （1.0%） | E6: 参考：標準値 （2.0%） | F6: 参考：標準値 （3.0%） | G6: 入力ガイド・根拠
A7: 資産維持率 | B7: 0.01 | C7: （%） | D7: 0.01 | E7: 0.02 | F7: 0.03 | G7: 日本水道協会「水道料金算定要領」標準3%。女川町試算シート現設定1%。1〜3%の範囲で設定。
A9: 【B】資産維持費の算定基礎データ（対象資産）
A10: 項目 | B10: 入力値 （千円） | C10: 入力 区分 | D10: 根拠・算定方法
A11: 対象資産①：期首（R8.4.1）帳簿価額 | B11: 1042625 | C11: ★入力 | D11: 試算シート【料金算定】資産維持費シートのH31末帳簿価額。R8年度の固定資産台帳で要確認・更新。
A12: 対象資産②：期末（R12.3.31）帳簿価額 | B12: 750000 | C12: ★入力 | D12: 推計値。R8〜R12の減価償却（年平均約406,000千円）と管路更新等新規取得を考慮。要精算。
A13: 対象資産（期首期末平均） | B13: =ROUND((B11+B12)/2,0) -> 896313 | C13: 自動計算 | D13: （期首＋期末）÷2 日本水道協会料金算定要領の算定方式
A14: 資産維持費（年間） | B14: =ROUND(B13*B7,0) -> 8963 | C14: 千円/年 | D14: 対象資産（期首期末平均）×資産維持率（B7セル）で自動計算。資産維持率を変更するとここが更新されます。
A15: 資産維持費（5年合計） | B15: =B14*5 -> 44815 | C15: 千円 | D15: 年間資産維持費×5年間
A17: 【C】費用項目（財政シミュレーション確定値） 単位：千円
A18: 費目 | B18: R8 | C18: R9 | D18: R10 | E18: R11 | F18: R12 | G18: 5年合計 | H18: 年平均 | I18: 出所・備考
A19: Ⅰ 維持管理費（減価償却費除く） | B19: 131926 | C19: 133182 | D19: 134453 | E19: 135742 | F19: 137024 | G19: =SUM(B19:F19) -> 672327 | H19: =G19/5 -> 134465.4 | I19: 財政シミュ 営業費用ー減価償却費。人件費・動力費・修繕費・委託料等
A20: Ⅱ 減価償却費 | B20: 395267 | C20: 414923 | D20: 412863 | E20: 407153 | F20: 402234 | G20: =SUM(B20:F20) -> 2032440 | H20: =G20/5 -> 406488 | I20: 財政シミュ Row52。既存資産＋管路更新・北上川導水管の新規取得資産を含む。
A21: Ⅲ 支払利息（既往債） | B21: 10790 | C21: 10530 | D21: 10172 | E21: 9805 | F21: 9288 | G21: =SUM(B21:F21) -> 50585 | H21: =G21/5 -> 10117 | I21: 財政シミュ Row60。逓減傾向。
A22: Ⅳ 支払利息（新規債） | B22: 9238 | C22: 18507 | D22: 26641 | E22: 34316 | F22: 38700 | G22: =SUM(B22:F22) -> 127402 | H22: =G22/5 -> 25480.4 | I22: 財政シミュ Row61。北上川導水管借入後に急増。
A23: Ⅵ 控除：長期前受金戻入益 | B23: -94000 | C23: -92000 | D23: -90000 | E23: -88000 | F23: -86000 | G23: =SUM(B23:F23) -> -450000 | H23: =G23/5 -> -90000 | I23: （推計値）△表示。財政シミュR6〜R7平均から推計。要精査。
A24: Ⅶ 控除：他会計補助金等 | B24: -3000 | C24: -3000 | D24: -3000 | E24: -3000 | F24: -3000 | G24: =SUM(B24:F24) -> -15000 | H24: =G24/5 -> -3000 | I24: （推計値）国定基準内繰入金等の控除。要精査。
A25: Ⅴ 資産維持費（★可変） | B25: =$B$14 -> 8963 | C25: =$B$14 -> 8963 | D25: =$B$14 -> 8963 | E25: =$B$14 -> 8963 | F25: =$B$14 -> 8963 | G25: =B14*5 -> 44815 | H25: =B14 -> 8963 | I25: ★B7セルの資産維持率に連動して自動計算。ここを変えるにはB7セルを変更してください。

Sheet 総括原価シミュレーション
A1: 女川町上水道事業 総括原価シミュレーション R8〜R12（5年間）
A2: 「前提条件（入力）」シートのB7セル（資産維持率）を変更すると、このシートの全計算が自動更新されます。 黄色セル＝パラメータ連動。青色セル＝固定値。
A4: =" 現在の資産維持率："&TEXT('前提条件（入力）'!B7,"0.00%")&" 資産維持費（年間）："&TEXT('前提条件（入力）'!B14,"#,##0")&"千円"&" 資産維持費（5年合計）："&TEXT('前提条件（入力）'!B15,"#,##0")&"千円" -> 現在の資産維持率：1.00% 資産維持費（年間）：8,963千円 資産維持費（5年合計）：44,815千円
A6: 【A】年度別・費目別 原価集計表（千円） ※資産維持率変更で自動再計算
A7: 費目 | B7: 算入 区分 | C7: R8 | D7: R9 | E7: R10 | F7: R11 | G7: R12 | H7: 5年合計 | I7: 年平均 | J7: 総括原価 構成比 | K7: 変動 有無 | L7: 出所・根拠
A8: Ⅰ 維持管理費（減価償却費除く） | B8: ＋固定費 ・変動費 | C8: ='前提条件（入力）'!B19 -> 131926 | D8: ='前提条件（入力）'!C19 -> 133182 | E8: ='前提条件（入力）'!D19 -> 134453 | F8: ='前提条件（入力）'!E19 -> 135742 | G8: ='前提条件（入力）'!F19 -> 137024 | H8: =SUM(C8:G8) -> 672327 | I8: =H8/5 -> 134465.4 | J8: =IF(H15<>0,ABS(H8)/ABS(H15),0) -> 0.092380743 | K8: 固定 | L8: 財政シミュ（営業費用-減価償却費）
A9: Ⅱ 減価償却費 | B9: ＋固定費 | C9: ='前提条件（入力）'!B20 -> 395267 | D9: ='前提条件（入力）'!C20 -> 414923 | E9: ='前提条件（入力）'!D20 -> 412863 | F9: ='前提条件（入力）'!E20 -> 407153 | G9: ='前提条件（入力）'!F20 -> 402234 | H9: =SUM(C9:G9) -> 2032440 | I9: =H9/5 -> 406488 | J9: =IF(H15<>0,ABS(H9)/ABS(H15),0) -> 0.27926636 | K9: 固定 | L9: 財政シミュ Row52
A10: Ⅲ 支払利息（既往債） | B10: ＋固定費 | C10: ='前提条件（入力）'!B21 -> 10790 | D10: ='前提条件（入力）'!C21 -> 10530 | E10: ='前提条件（入力）'!D21 -> 10172 | F10: ='前提条件（入力）'!E21 -> 9805 | G10: ='前提条件（入力）'!F21 -> 9288 | H10: =SUM(C10:G10) -> 50585 | I10: =H10/5 -> 10117 | J10: =IF(H15<>0,ABS(H10)/ABS(H15),0) -> 0.0069506057 | K10: 固定 | L10: 財政シミュ Row60
A11: Ⅳ 支払利息（新規債） | B11: ＋固定費 | C11: ='前提条件（入力）'!B22 -> 9238 | D11: ='前提条件（入力）'!C22 -> 18507 | E11: ='前提条件（入力）'!D22 -> 26641 | F11: ='前提条件（入力）'!E22 -> 34316 | G11: ='前提条件（入力）'!F22 -> 38700 | H11: =SUM(C11:G11) -> 127402 | I11: =H11/5 -> 25480.4 | J11: =IF(H15<>0,ABS(H11)/ABS(H15),0) -> 0.017505606 | K11: 固定 | L11: 財政シミュ Row61
A12: Ⅴ 資産維持費（★可変） | B12: ＋固定費 | C12: ='前提条件（入力）'!B25 -> 8963 | D12: ='前提条件（入力）'!C25 -> 8963 | E12: ='前提条件（入力）'!D25 -> 8963 | F12: ='前提条件（入力）'!E25 -> 8963 | G12: ='前提条件（入力）'!F25 -> 8963 | H12: =SUM(C12:G12) -> 44815 | I12: =H12/5 -> 8963 | J12: =IF(H15<>0,ABS(H12)/ABS(H15),0) -> 0.0061577818 | K12: ★変動 | L12: 前提シートB7×対象資産平均で自動計算
A13: Ⅵ 控除：長期前受金戻入益 | B13: －控除 | C13: ='前提条件（入力）'!B23 -> -94000 | D13: ='前提条件（入力）'!C23 -> -92000 | E13: ='前提条件（入力）'!D23 -> -90000 | F13: ='前提条件（入力）'!E23 -> -88000 | G13: ='前提条件（入力）'!F23 -> -86000 | H13: =SUM(C13:G13) -> -450000 | I13: =H13/5 -> -90000 | J13: =IF(H15<>0,ABS(H13)/ABS(H15),0) -> 0.061832017 | K13: 固定 | L13: （推計）△控除項目
A14: Ⅶ 控除：他会計補助金等 | B14: －控除 | C14: ='前提条件（入力）'!B24 -> -3000 | D14: ='前提条件（入力）'!C24 -> -3000 | E14: ='前提条件（入力）'!D24 -> -3000 | F14: ='前提条件（入力）'!E24 -> -3000 | G14: ='前提条件（入力）'!F24 -> -3000 | H14: =SUM(C14:G14) -> -15000 | I14: =H14/5 -> -3000 | J14: =IF(H15<>0,ABS(H14)/ABS(H15),0) -> 0.0020610672 | K14: 固定 | L14: （推計）△控除項目
A15: 総括原価 合 計 | C15: =SUM(C8:C14) -> 459184 | D15: =SUM(C8:D14) -> 950289 | E15: =SUM(C8:E14) -> 1450381 | F15: =SUM(C8:F14) -> 1955360 | G15: =SUM(C8:G14) -> 2462569 | H15: =SUM(C15:G15) -> 7277783 | I15: =H15/5 -> 1455556.6
A17: 【B】供給単価・料金回収率 自動算定
A18: 指標 | B18: 算定値（自動） | E18: 参考：現行 （R7実績） | F18: 差異 （改善幅） | G18: 算定式・根拠
A19: 5年間 有収水量 | B19: 4,316,000㎥（4,316千㎥） | G19: 財政シミュ 水需要予測。R8:901→R12:818千㎥の合計。
A20: 5年間 総括原価 | B20: =H15 -> 7277783 | G20: 上記Ⅰ〜Ⅶの合計（千円）。資産維持率変更で自動更新。
A21: 給水原価（算定） | B21: =ROUND(H15*1000/4316000,1) -> 1686.2 | E21: 128.2 | F21: =ROUND(H15*1000/4316000,1)-128.2 -> 1558 | G21: 総括原価（千円）×1,000÷有収水量（㎥）。[円/㎥]
A22: 現行供給単価（R7実績） | B22: 128.2 | E22: 128.2 | G22: 使用料収入131,429千円÷有収水量1,024千㎥（R7実績）
A23: 料金回収率（現行） | B23: =128.2/ROUND(H15*1000/4316000,1) -> 0.076028941 | E23: 0.5287 | G23: 現行供給単価÷算定給水原価。100%が目標。
A24: 改定後 供給単価（基本1.5倍・超過+22円） | B24: 192.3 | E24: 192.3 | G24: 基本料金1.5倍・超過料金+22円の改定案適用時の概算（別途試算）
A25: 料金回収率（改定後） | B25: =192.3/ROUND(H15*1000/4316000,1) -> 0.11404341 | G25: 改定後供給単価÷算定給水原価。100%目標に対する達成度。
A26: 不足額（1件あたり月額換算） | B26: =ROUND((ROUND(H15*1000/4316000,1)-128.2)/12,0) -> 130 | G26: （算定給水原価 - 現行供給単価）÷12ヶ月。追加で必要な月額収入の目安。
A28: 【C】資産維持率 感度分析 （1.0%〜3.0% のシナリオ比較）
A29: 下記は各資産維持率における総括原価・給水原価・料金回収率の試算値。強調行が現在の設定値（前提シートB7と連動）。
A30: 資産維持率 | B30: 資産維持費 （年間・千円） | C30: 資産維持費 （5年計・千円） | D30: 総括原価 （5年計・千円） | E30: 給水原価 （円/㎥） | F30: 料金回収率 （現行128円） | G30: 料金回収率 （改定後192円） | H30: 日本水道 協会要領 | I30: 評価・コメント
A31: =IF(ABS('前提条件（入力）'!$B$7-0.01)<0.0001,"▶ 1.0%（現設定）","1.0%（現設定）") -> ▶ 1.0%（現設定） | B31: =ROUND('前提条件（入力）'!$B$13*0.01,0) -> 8963 | C31: =ROUND('前提条件（入力）'!$B$13*0.01,0)*5 -> 44815 | D31: =2417754+ROUND('前提条件（入力）'!$B$13*0.01,0)*5 -> 2462569 | E31: =ROUND((2417754+ROUND('前提条件（入力）'!$B$13*0.01,0)*5)*1000/4316000,1) -> 570.6 | F31: =IF(E31<>0,128.2/E31,0) -> 0.22467578 | G31: =IF(E31<>0,192.3/E31,0) -> 0.33701367 | H31: △現設定 | I31: 試算シート現設定。資金不足のリスクが高い。
A32: =IF(ABS('前提条件（入力）'!$B$7-0.013)<0.0001,"▶ 1.3%","1.3%") -> 1.3% | B32: =ROUND('前提条件（入力）'!$B$13*0.013,0) -> 11652 | C32: =ROUND('前提条件（入力）'!$B$13*0.013,0)*5 -> 58260 | D32: =2417754+ROUND('前提条件（入力）'!$B$13*0.013,0)*5 -> 2476014 | E32: =ROUND((2417754+ROUND('前提条件（入力）'!$B$13*0.013,0)*5)*1000/4316000,1) -> 573.7 | F32: =IF(E32<>0,128.2/E32,0) -> 0.22346174 | G32: =IF(E32<>0,192.3/E32,0) -> 0.33519261 | I32: 現設定より僅かな上乗せ。
A33: =IF(ABS('前提条件（入力）'!$B$7-0.015)<0.0001,"▶ 1.5%","1.5%") -> 1.5% | B33: =ROUND('前提条件（入力）'!$B$13*0.015,0) -> 13445 | C33: =ROUND('前提条件（入力）'!$B$13*0.015,0)*5 -> 67225 | D33: =2417754+ROUND('前提条件（入力）'!$B$13*0.015,0)*5 -> 2484979 | E33: =ROUND((2417754+ROUND('前提条件（入力）'!$B$13*0.015,0)*5)*1000/4316000,1) -> 575.8 | F33: =IF(E33<>0,128.2/E33,0) -> 0.22264675 | G33: =IF(E33<>0,192.3/E33,0) -> 0.33397013 | I33: 小規模改定での現実的な下限水準。
A34: =IF(ABS('前提条件（入力）'!$B$7-0.017)<0.0001,"▶ 1.7%","1.7%") -> 1.7% | B34: =ROUND('前提条件（入力）'!$B$13*0.017,0) -> 15237 | C34: =ROUND('前提条件（入力）'!$B$13*0.017,0)*5 -> 76185 | D34: =2417754+ROUND('前提条件（入力）'!$B$13*0.017,0)*5 -> 2493939 | E34: =ROUND((2417754+ROUND('前提条件（入力）'!$B$13*0.017,0)*5)*1000/4316000,1) -> 577.8 | F34: =IF(E34<>0,128.2/E34,0) -> 0.22187608 | G34: =IF(E34<>0,192.3/E34,0) -> 0.33281412 | I34: 段階的引き上げの中間値。
A35: =IF(ABS('前提条件（入力）'!$B$7-0.02)<0.0001,"▶ 2.0%（推奨下限）","2.0%（推奨下限）") -> 2.0%（推奨下限） | B35: =ROUND('前提条件（入力）'!$B$13*0.02,0) -> 17926 | C35: =ROUND('前提条件（入力）'!$B$13*0.02,0)*5 -> 89630 | D35: =2417754+ROUND('前提条件（入力）'!$B$13*0.02,0)*5 -> 2507384 | E35: =ROUND((2417754+ROUND('前提条件（入力）'!$B$13*0.02,0)*5)*1000/4316000,1) -> 581 | F35: =IF(E35<>0,128.2/E35,0) -> 0.22065404 | G35: =IF(E35<>0,192.3/E35,0) -> 0.33098107 | H35: ○推奨 | I35: 女川町規模での推奨水準（最低ライン）。
A36: =IF(ABS('前提条件（入力）'!$B$7-0.023)<0.0001,"▶ 2.3%（松山市）","2.3%（松山市）") -> 2.3%（松山市） | B36: =ROUND('前提条件（入力）'!$B$13*0.023,0) -> 20615 | C36: =ROUND('前提条件（入力）'!$B$13*0.023,0)*5 -> 103075 | D36: =2417754+ROUND('前提条件（入力）'!$B$13*0.023,0)*5 -> 2520829 | E36: =ROUND((2417754+ROUND('前提条件（入力）'!$B$13*0.023,0)*5)*1000/4316000,1) -> 584.1 | F36: =IF(E36<>0,128.2/E36,0) -> 0.21948297 | G36: =IF(E36<>0,192.3/E36,0) -> 0.32922445 | I36: 松山市事例（PDF P11）と同水準。
A37: =IF(ABS('前提条件（入力）'!$B$7-0.025)<0.0001,"▶ 2.5%","2.5%") -> 2.5% | B37: =ROUND('前提条件（入力）'!$B$13*0.025,0) -> 22408 | C37: =ROUND('前提条件（入力）'!$B$13*0.025,0)*5 -> 112040 | D37: =2417754+ROUND('前提条件（入力）'!$B$13*0.025,0)*5 -> 2529794 | E37: =ROUND((2417754+ROUND('前提条件（入力）'!$B$13*0.025,0)*5)*1000/4316000,1) -> 586.1 | F37: =IF(E37<>0,128.2/E37,0) -> 0.218734 | G37: =IF(E37<>0,192.3/E37,0) -> 0.32810101 | H37: ○推奨 | I37: 2.0〜3.0%の中間。
A38: =IF(ABS('前提条件（入力）'!$B$7-0.027)<0.0001,"▶ 2.7%","2.7%") -> 2.7% | B38: =ROUND('前提条件（入力）'!$B$13*0.027,0) -> 24200 | C38: =ROUND('前提条件（入力）'!$B$13*0.027,0)*5 -> 121000 | D38: =2417754+ROUND('前提条件（入力）'!$B$13*0.027,0)*5 -> 2538754 | E38: =ROUND((2417754+ROUND('前提条件（入力）'!$B$13*0.027,0)*5)*1000/4316000,1) -> 588.2 | F38: =IF(E38<>0,128.2/E38,0) -> 0.21795308 | G38: =IF(E38<>0,192.3/E38,0) -> 0.32692962 | I38: 標準3%に近い水準。
A39: =IF(ABS('前提条件（入力）'!$B$7-0.03)<0.0001,"▶ 3.0%（要領標準）","3.0%（要領標準）") -> 3.0%（要領標準） | B39: =ROUND('前提条件（入力）'!$B$13*0.03,0) -> 26889 | C39: =ROUND('前提条件（入力）'!$B$13*0.03,0)*5 -> 134445 | D39: =2417754+ROUND('前提条件（入力）'!$B$13*0.03,0)*5 -> 2552199 | E39: =ROUND((2417754+ROUND('前提条件（入力）'!$B$13*0.03,0)*5)*1000/4316000,1) -> 591.3 | F39: =IF(E39<>0,128.2/E39,0) -> 0.21681042 | G39: =IF(E39<>0,192.3/E39,0) -> 0.32521563 | H39: ◎標準 | I39: 日本水道協会要領の標準。最大の財源確保。
A40: ※「▶」マークが現在の設定値（前提シートB7）と一致する行を示します。資産維持率を変更すると▶が移動します。

Sheet 感度分析グラフ用データ
A1: 女川町上水道事業 資産維持率 感度分析データ（グラフ作成用）
A2: 前提条件シートのB7（資産維持率）・B13（対象資産平均）に連動して自動更新。グラフ化に使用してください。
A4: 感度分析：資産維持率 1.0%〜3.0% のシナリオ別試算値
A5: 資産維持率 | B5: 資産維持費 年間（千円） | C5: 資産維持費 5年計（千円） | D5: 総括原価 5年計（千円） | E5: 給水原価 （円/㎥） | F5: 料金回収率 現行128円 | G5: 料金回収率 改定後192円 | H5: ★現在値 （★印）
A6: 0.01 | B6: =ROUND('前提条件（入力）'!$B$13*0.01,0) -> 8963 | C6: =ROUND('前提条件（入力）'!$B$13*0.01,0)*5 -> 44815 | D6: =2417754+ROUND('前提条件（入力）'!$B$13*0.01,0)*5 -> 2462569 | E6: =ROUND((2417754+ROUND('前提条件（入力）'!$B$13*0.01,0)*5)*1000/4316000,1) -> 570.6 | F6: =IF(E6<>0,128.2/E6,0) -> 0.22467578 | G6: =IF(E6<>0,192.3/E6,0) -> 0.33701367 | H6: =IF(ABS('前提条件（入力）'!$B$7-0.01)<0.0001,"★現在値","") -> ★現在値
A7: 0.013 | B7: =ROUND('前提条件（入力）'!$B$13*0.013,0) -> 11652 | C7: =ROUND('前提条件（入力）'!$B$13*0.013,0)*5 -> 58260 | D7: =2417754+ROUND('前提条件（入力）'!$B$13*0.013,0)*5 -> 2476014 | E7: =ROUND((2417754+ROUND('前提条件（入力）'!$B$13*0.013,0)*5)*1000/4316000,1) -> 573.7 | F7: =IF(E7<>0,128.2/E7,0) -> 0.22346174 | G7: =IF(E7<>0,192.3/E7,0) -> 0.33519261 | H7: =IF(ABS('前提条件（入力）'!$B$7-0.013)<0.0001,"★現在値","")
A8: 0.015 | B8: =ROUND('前提条件（入力）'!$B$13*0.015,0) -> 13445 | C8: =ROUND('前提条件（入力）'!$B$13*0.015,0)*5 -> 67225 | D8: =2417754+ROUND('前提条件（入力）'!$B$13*0.015,0)*5 -> 2484979 | E8: =ROUND((2417754+ROUND('前提条件（入力）'!$B$13*0.015,0)*5)*1000/4316000,1) -> 575.8 | F8: =IF(E8<>0,128.2/E8,0) -> 0.22264675 | G8: =IF(E8<>0,192.3/E8,0) -> 0.33397013 | H8: =IF(ABS('前提条件（入力）'!$B$7-0.015)<0.0001,"★現在値","")
A9: 0.017 | B9: =ROUND('前提条件（入力）'!$B$13*0.017,0) -> 15237 | C9: =ROUND('前提条件（入力）'!$B$13*0.017,0)*5 -> 76185 | D9: =2417754+ROUND('前提条件（入力）'!$B$13*0.017,0)*5 -> 2493939 | E9: =ROUND((2417754+ROUND('前提条件（入力）'!$B$13*0.017,0)*5)*1000/4316000,1) -> 577.8 | F9: =IF(E9<>0,128.2/E9,0) -> 0.22187608 | G9: =IF(E9<>0,192.3/E9,0) -> 0.33281412 | H9: =IF(ABS('前提条件（入力）'!$B$7-0.017)<0.0001,"★現在値","")
A10: 0.02 | B10: =ROUND('前提条件（入力）'!$B$13*0.02,0) -> 17926 | C10: =ROUND('前提条件（入力）'!$B$13*0.02,0)*5 -> 89630 | D10: =2417754+ROUND('前提条件（入力）'!$B$13*0.02,0)*5 -> 2507384 | E10: =ROUND((2417754+ROUND('前提条件（入力）'!$B$13*0.02,0)*5)*1000/4316000,1) -> 581 | F10: =IF(E10<>0,128.2/E10,0) -> 0.22065404 | G10: =IF(E10<>0,192.3/E10,0) -> 0.33098107 | H10: =IF(ABS('前提条件（入力）'!$B$7-0.02)<0.0001,"★現在値","")
A11: 0.023 | B11: =ROUND('前提条件（入力）'!$B$13*0.023,0) -> 20615 | C11: =ROUND('前提条件（入力）'!$B$13*0.023,0)*5 -> 103075 | D11: =2417754+ROUND('前提条件（入力）'!$B$13*0.023,0)*5 -> 2520829 | E11: =ROUND((2417754+ROUND('前提条件（入力）'!$B$13*0.023,0)*5)*1000/4316000,1) -> 584.1 | F11: =IF(E11<>0,128.2/E11,0) -> 0.21948297 | G11: =IF(E11<>0,192.3/E11,0) -> 0.32922445 | H11: =IF(ABS('前提条件（入力）'!$B$7-0.023)<0.0001,"★現在値","")
A12: 0.025 | B12: =ROUND('前提条件（入力）'!$B$13*0.025,0) -> 22408 | C12: =ROUND('前提条件（入力）'!$B$13*0.025,0)*5 -> 112040 | D12: =2417754+ROUND('前提条件（入力）'!$B$13*0.025,0)*5 -> 2529794 | E12: =ROUND((2417754+ROUND('前提条件（入力）'!$B$13*0.025,0)*5)*1000/4316000,1) -> 586.1 | F12: =IF(E12<>0,128.2/E12,0) -> 0.218734 | G12: =IF(E12<>0,192.3/E12,0) -> 0.32810101 | H12: =IF(ABS('前提条件（入力）'!$B$7-0.025)<0.0001,"★現在値","")
A13: 0.027 | B13: =ROUND('前提条件（入力）'!$B$13*0.027,0) -> 24200 | C13: =ROUND('前提条件（入力）'!$B$13*0.027,0)*5 -> 121000 | D13: =2417754+ROUND('前提条件（入力）'!$B$13*0.027,0)*5 -> 2538754 | E13: =ROUND((2417754+ROUND('前提条件（入力）'!$B$13*0.027,0)*5)*1000/4316000,1) -> 588.2 | F13: =IF(E13<>0,128.2/E13,0) -> 0.21795308 | G13: =IF(E13<>0,192.3/E13,0) -> 0.32692962 | H13: =IF(ABS('前提条件（入力）'!$B$7-0.027)<0.0001,"★現在値","")
A14: 0.03 | B14: =ROUND('前提条件（入力）'!$B$13*0.03,0) -> 26889 | C14: =ROUND('前提条件（入力）'!$B$13*0.03,0)*5 -> 134445 | D14: =2417754+ROUND('前提条件（入力）'!$B$13*0.03,0)*5 -> 2552199 | E14: =ROUND((2417754+ROUND('前提条件（入力）'!$B$13*0.03,0)*5)*1000/4316000,1) -> 591.3 | F14: =IF(E14<>0,128.2/E14,0) -> 0.21681042 | G14: =IF(E14<>0,192.3/E14,0) -> 0.32521563 | H14: =IF(ABS('前提条件（入力）'!$B$7-0.03)<0.0001,"★現在値","")
