Workbook

Sheet 00_前提・検証
A1: 項目 | B1: 値 | C1: 単位 | D1: 内容 | F1: Red Team検証 | G1: 結果 | H1: 対象範囲 | I1: 判定式 | J1: 備考
A2: 資産維持費対象資産 | B2: 16455364 | C2: 千円 | D2: R7末償却対象資産相当。資産維持費=対象資産×率。 | F2: 資産維持費込料金回収率の大小 | G2: 03_SIM比較!I4:I11 | H2: 全SIM | I2: 資産維持費込 <= 通常 | J2: 全てOKであればロジック整合
A3: 料金改定開始年度 | B3: 令和11年度 | D3: SIMではR11以降に料金改定率を適用。
A4: 算定期間開始 | B4: 令和11年度 | D4: 料金改定率はR11〜R15の5か年で総括原価を回収する水準。
A5: 算定期間終了 | B5: 令和15年度 | D5: 総括原価=営業費用+営業外費用-長期前受金戻入-その他営業収益-繰入金・負担金等+資産維持費。
A6: R7末現預金（推計開始残高） | B6: 242588 | C6: 千円 | D6: R7末現金預金を推計開始残高として使用。
A7: 最低現金目安 | B7: 300000 | C7: 千円 | D7: 便宜的な資金安全ライン。
A8: 検証ルール | B8: 資産維持費込料金回収率 <= 料金回収率 | D8: 同一分子で分母に資産維持費を加算するため。
A9: 主な修正点 | B9: 資産維持費込料金回収率の分母修正 | D9: 分子は改定後給水収益、分母は通常給水原価対象費用＋資産維持費。
A10: R8予算反映 | B10: R8収入・資本的収入はR8当初予算書を採用。投資は将来年次計画の調整後事業費計を採用。
A11: Red Team確認 | B11: 資産維持費込料金回収率が通常料金回収率を上回らないこと、R8予算値が04シートと一致することを確認。
A12: 営業費用の修正 | B12: 修繕・動力・薬品・委託・資産減耗・その他営業費用は物件費の内数（993作成資料）。従来SIMは約512百万円/年を二重計上しており、必要改定率が約44ポイント過大だった。本版で解消。
A13: 追加精緻化項目 | B13: 値 | C13: 単位 | D13: 内容
A14: 建設仮勘定対象事業合計 | B14: =05_建設仮勘定・企業債!B27 -> 465568277 | C14: 円 | D14: 05_建設仮勘定・企業債で算定
A15: 長期前受金等合計 | B15: =05_建設仮勘定・企業債!B28 -> 346184893 | C15: 円 | D15: 工事負担金・県補償金等
A16: 令和10年度以降 年額減価償却費 | B16: =05_建設仮勘定・企業債!E40 -> 11639 | C16: 千円 | D16: 40年定額、千円丸め
A17: 令和10年度以降 年額長期前受金戻入 | B17: =05_建設仮勘定・企業債!E41 -> 8655 | C17: 千円 | D17: 40年定額、千円丸め
A18: 追加企業債対象額 | B18: =05_建設仮勘定・企業債!B29 -> 119383384 | C18: 円 | D18: 国費・負担金等控除後の純額
A19: 利率の扱い | B19: 区分別入力 | D19: 一律3%固定ではなく、05シートG27:G28で区分別に置換可能
A20: 企業債充当率100% | B20: R8〜R16企業債＝建設改良費−国庫補助金−工事負担金。R9に過年度建設仮勘定純額12,066千円を追加借入。利率3%・40年元金均等・翌年度償還開始（Δモデル、02シート55〜59行）。
A21: 補填財源残高 | B21: R7末183,463千円（0708修正版補てん財源経過表）を起点にSIM72行目で簡便推計。現預金残高（59行）と区分表示。
A22: 建設仮勘定統合 | B22: R10以降の減価償却費+11,639千円・長期前受金戻入+8,655千円を02シート本体へ統合。総括原価・必要改定率へ反映済み。

Sheet 01_ビジョン原計画
A1: ビジョン上の投資財政計画（R7〜R16）
A2: 収益・費用・4条収入は見直後財政計画を基礎。建設改良費はビジョン/既存計画の額を使用。単位：千円。 【修正】修繕費・動力費・薬品費・委託料・資産減耗費・その他営業費用は993作成資料上「物件費」の内数のため、営業費用の合計から除外（従来は二重計上）。R8予算年度のみ資産減耗費12,000を別掲加算。
A3: 区分 | B3: 令和7年度 | C3: 令和8年度 | D3: 令和9年度 | E3: 令和10年度 | F3: 令和11年度 | G3: 令和12年度 | H3: 令和13年度 | I3: 令和14年度 | J3: 令和15年度 | K3: 令和16年度
A4: 【収益的収入】
A5: 水道事業収益 | B5: =SUM(B6,B9,B14) -> 1619060 | C5: =SUM(C6,C9,C14) -> 1604473 | D5: =SUM(D6,D9,D14) -> 1586060 | E5: =SUM(E6,E9,E14) -> 1568503 | F5: =SUM(F6,F9,F14) -> 1550232 | G5: =SUM(G6,G9,G14) -> 1544775 | H5: =SUM(H6,H9,H14) -> 1532660 | I5: =SUM(I6,I9,I14) -> 1511152 | ... K5: =SUM(K6,K9,K14) -> 1463657
A6: 営業収益 | B6: =SUM(B7:B8) -> 1261575 | C6: =SUM(C7:C8) -> 1249336 | D6: =SUM(D7:D8) -> 1237293 | E6: =SUM(E7:E8) -> 1225373 | F6: =SUM(F7:F8) -> 1213574 | G6: =SUM(G7:G8) -> 1201896 | H6: =SUM(H7:H8) -> 1190336 | I6: =SUM(I7:I8) -> 1178894 | ... K6: =SUM(K7:K8) -> 1156360
A7: 給水収益 | B7: 1231181 | C7: 1218869 | D7: 1206680 | E7: 1194613 | F7: 1182666 | G7: 1170839 | H7: 1159130 | I7: 1147538 | J7: 1136062 | K7: 1124701
A8: その他営業収益 | B8: 30394 | C8: 30467 | D8: 30613 | E8: 30760 | F8: 30908 | G8: 31057 | H8: 31206 | I8: 31356 | J8: 31507 | K8: 31659
A9: 営業外収益 | B9: =SUM(B10:B13) -> 354909 | C9: =SUM(C10:C13) -> 355137 | D9: =SUM(D10:D13) -> 348767 | E9: =SUM(E10:E13) -> 343130 | F9: =SUM(F10:F13) -> 336658 | G9: =SUM(G10:G13) -> 342879 | H9: =SUM(H10:H13) -> 342324 | I9: =SUM(I10:I13) -> 332258 | ... K9: =SUM(K10:K13) -> 307297
A10: 受取利息 | B10: 1 | C10: 1 | D10: 0 | E10: 0 | F10: 0 | G10: 0 | H10: 0 | I10: 0 | J10: 0 | K10: 0
A11: 繰入金・負担金等 | B11: 73283 | C11: 71157 | D11: 68955 | E11: 66740 | F11: 64490 | G11: 62175 | H11: 59946 | I11: 57892 | J11: 56062 | K11: 54385
A12: 長期前受金戻入 | B12: 281625 | C12: 283979 | D12: 279812 | E12: 276390 | F12: 272168 | G12: 272926 | H12: 274600 | I12: 266588 | J12: 250287 | K12: 245134
A13: その他営業外収益 | B13: 0 | C13: 0 | D13: 0 | E13: 0 | F13: 0 | G13: 7778 | H13: 7778 | I13: 7778 | J13: 7778 | K13: 7778
A14: 特別利益 | B14: 2576 | C14: 0 | D14: 0 | E14: 0 | F14: 0 | G14: 0 | H14: 0 | I14: 0 | J14: 0 | K14: 0
A16: 【収益的支出】
A17: 水道事業費用 | B17: =SUM(B18,B28,B31) -> 1608275 | C17: =SUM(C18,C28,C31) -> 1597336 | D17: =SUM(D18,D28,D31) -> 1591913 | E17: =SUM(E18,E28,E31) -> 1586945 | F17: =SUM(F18,F28,F31) -> 1585772 | G17: =SUM(G18,G28,G31) -> 1588017 | H17: =SUM(H18,H28,H31) -> 1595258 | I17: =SUM(I18,I28,I31) -> 1591786 | ... K17: =SUM(K18,K28,K31) -> 1575072
A18: 営業費用 | B18: =SUM(B19,B20,B25,B26,B27) -> 1479507 | C18: =SUM(C19,C20,C25,C26,C27) -> 1476545 | D18: =SUM(D19,D20,D25,D26,D27) -> 1474501 | E18: =SUM(E19,E20,E25,E26,E27) -> 1471288 | F18: =SUM(F19,F20,F25,F26,F27) -> 1471712 | G18: =SUM(G19,G20,G25,G26,G27) -> 1476923 | H18: =SUM(H19,H20,H25,H26,H27) -> 1486420 | I18: =SUM(I19,I20,I25,I26,I27) -> 1484101 | ... K18: =SUM(K19,K20,K25,K26,K27) -> 1469682
A19: 人件費 | B19: 176462 | C19: 176462 | D19: 176462 | E19: 176462 | F19: 176462 | G19: 176462 | H19: 176462 | I19: 176462 | J19: 176462 | K19: 176462
A20: 物件費 | B20: 547263 | C20: 545340 | D20: 545648 | E20: 545957 | F20: 546267 | G20: 546577 | H20: 546888 | I20: 547200 | J20: 547513 | K20: 547827
A21: 修繕費（物件費の内数・参考） | B21: 65247 | C21: 65000 | D21: 65000 | E21: 65000 | F21: 65000 | G21: 65000 | H21: 65000 | I21: 65000 | J21: 65000 | K21: 65000
A22: 動力費（物件費の内数・参考） | B22: 102261 | C22: 102568 | D22: 102876 | E22: 103185 | F22: 103495 | G22: 103805 | H22: 104116 | I22: 104428 | J22: 104741 | K22: 105055
A23: 薬品費（物件費の内数・参考） | B23: 15316 | C23: 15000 | D23: 15000 | E23: 15000 | F23: 15000 | G23: 15000 | H23: 15000 | I23: 15000 | J23: 15000 | K23: 15000
A24: 委託料（物件費の内数・参考） | B24: 304419 | C24: 304000 | D24: 304000 | E24: 304000 | F24: 304000 | G24: 304000 | H24: 304000 | I24: 304000 | J24: 304000 | K24: 304000
A25: 減価償却費 | B25: 755782 | C25: 754743 | D25: 752391 | E25: 748869 | F25: 748983 | G25: 753884 | H25: 763070 | I25: 760439 | J25: 744482 | K25: 745393
A26: 資産減耗・除却費（R8予算のみ別掲、他年度は物件費内数のため0） | B26: 0 | C26: 0 | D26: 0 | E26: 0 | F26: 0 | G26: 0 | H26: 0 | I26: 0 | J26: 0 | K26: 0
A27: その他営業費用（物件費内数のため0） | B27: 0 | C27: 0 | D27: 0 | E27: 0 | F27: 0 | G27: 0 | H27: 0 | I27: 0 | J27: 0 | K27: 0
A28: 営業外費用 | B28: =SUM(B29:B30) -> 128495 | C28: =SUM(C29:C30) -> 120518 | D28: =SUM(D29:D30) -> 117139 | E28: =SUM(E29:E30) -> 115384 | F28: =SUM(F29:F30) -> 113787 | G28: =SUM(G29:G30) -> 110821 | H28: =SUM(H29:H30) -> 108565 | I28: =SUM(I29:I30) -> 107412 | ... K28: =SUM(K29:K30) -> 105117
A29: 支払利息 | B29: 118910 | C29: 111872 | D29: 108458 | E29: 106668 | F29: 105071 | G29: 102070 | H29: 99779 | I29: 98626 | J29: 98322 | K29: 96331
A30: 雑支出 | B30: 9585 | C30: 8646 | D30: 8681 | E30: 8716 | F30: 8716 | G30: 8751 | H30: 8786 | I30: 8786 | J30: 8786 | K30: 8786
A31: 特別損失 | B31: 273 | C31: 273 | D31: 273 | E31: 273 | F31: 273 | G31: 273 | H31: 273 | I31: 273 | J31: 273 | K31: 273
A33: 【資本的収入】
A34: 資本的収入 | B34: 698941 | C34: 664331 | D34: 636408 | E34: 715698 | F34: 627649 | G34: 570213 | H34: 571338 | I34: 536592 | J34: 406734 | K34: 365000
A35: 企業債 | B35: 329000 | C35: 435000 | D35: 399000 | E35: 400000 | F35: 232000 | G35: 283000 | H35: 286000 | I35: 368000 | J35: 251000 | K35: 230000
A36: 一般会計負担金 | B36: 169041 | C36: 164831 | D36: 162408 | E36: 167998 | F36: 173649 | G36: 182213 | H36: 180338 | I36: 168592 | J36: 155734 | K36: 135000
A37: 一般会計出資金 | B37: 0 | C37: 0 | D37: 0 | E37: 0 | F37: 0 | G37: 0 | H37: 0 | I37: 0 | J37: 0 | K37: 0
A38: 国庫補助金 | B38: 0 | C38: 64500 | D38: 75000 | E38: 147700 | F38: 222000 | G38: 105000 | H38: 105000 | I38: 0 | J38: 0 | K38: 0
A39: 固定資産売却代金 | B39: 0 | C39: 0 | D39: 0 | E39: 0 | F39: 0 | G39: 0 | H39: 0 | I39: 0 | J39: 0 | K39: 0
A40: 工事負担金 | B40: 200900 | C40: 0 | D40: 0 | E40: 0 | F40: 0 | G40: 0 | H40: 0 | I40: 0 | J40: 0 | K40: 0
A41: その他・調整 | B41: =B34-SUM(B35:B40) -> 0 | C41: =C34-SUM(C35:C40) -> 0 | D41: =D34-SUM(D35:D40) -> 0 | E41: =E34-SUM(E35:E40) -> 0 | F41: =F34-SUM(F35:F40) -> 0 | G41: =G34-SUM(G35:G40) -> 0 | H41: =H34-SUM(H35:H40) -> 0 | I41: =I34-SUM(I35:I40) -> 0 | ... K41: =K34-SUM(K35:K40) -> 0
A43: 【資本的支出】
A44: 資本的支出 | B44: =SUM(B45:B47) -> 1412922 | C44: =SUM(C45:C47) -> 1320955 | D44: =SUM(D45:D47) -> 1228308 | E44: =SUM(E45:E47) -> 1249449 | F44: =SUM(F45:F47) -> 1123446 | G44: =SUM(G45:G47) -> 992222 | H44: =SUM(H45:H47) -> 982061 | I44: =SUM(I45:I47) -> 942741 | ... K44: =SUM(K45:K47) -> 789992
A45: 建設改良費 | B45: 557893 | C45: 525014 | D45: 500489 | E45: 576808 | F45: 484835 | G45: 415935 | H45: 419465 | I45: 395135 | J45: 279155 | K45: 257135
A46: 企業債償還金 | B46: 855029 | C46: 795941 | D46: 727819 | E46: 672641 | F46: 638611 | G46: 576287 | H46: 562596 | I46: 547606 | J46: 546246 | K46: 532857
A47: その他資本的支出 | B47: 0 | C47: 0 | D47: 0 | E47: 0 | F47: 0 | G47: 0 | H47: 0 | I47: 0 | J47: 0 | K47: 0
A48: 資本的収支不足額（収入－支出） | B48: =B34-B44 -> -713981 | C48: =C34-C44 -> -656624 | D48: =D34-D44 -> -591900 | E48: =E34-E44 -> -533751 | F48: =F34-F44 -> -495797 | G48: =G34-G44 -> -422009 | H48: =H34-H44 -> -410723 | I48: =I34-I44 -> -406149 | ... K48: =K34-K44 -> -424992

Sheet 02_将来年次投資置換
A1: 将来年次計画の投資に置換した投資財政計画（R7〜R16）
A2: 収益・費用・4条収入は見直後財政計画を基礎。建設改良費のみ将来年次計画2025.12.2（2026.3.1シート）の調整後事業費へ置換。単位：千円。 【修正】修繕費・動力費・薬品費・委託料・資産減耗費・その他営業費用は993作成資料上「物件費」の内数のため、営業費用の合計から除外（従来は二重計上）。R8予算年度のみ資産減耗費12,000を別掲加算。
A3: 区分 | B3: 令和7年度 | C3: 令和8年度 | D3: 令和9年度 | E3: 令和10年度 | F3: 令和11年度 | G3: 令和12年度 | H3: 令和13年度 | I3: 令和14年度 | J3: 令和15年度 | K3: 令和16年度
A4: 【収益的収入】
A5: 水道事業収益 | B5: =SUM(B6,B9,B14) -> 1619060 | C5: =SUM(C6,C9,C14) -> 1604473 | D5: =SUM(D6,D9,D14) -> 1586060 | E5: =SUM(E6,E9,E14) -> 1568503 | F5: =SUM(F6,F9,F14) -> 1550232 | G5: =SUM(G6,G9,G14) -> 1544775 | H5: =SUM(H6,H9,H14) -> 1532660 | I5: =SUM(I6,I9,I14) -> 1511152 | ... K5: =SUM(K6,K9,K14) -> 1463657
A6: 営業収益 | B6: =SUM(B7:B8) -> 1261575 | C6: =SUM(C7:C8) -> 1249336 | D6: =SUM(D7:D8) -> 1237293 | E6: =SUM(E7:E8) -> 1225373 | F6: =SUM(F7:F8) -> 1213574 | G6: =SUM(G7:G8) -> 1201896 | H6: =SUM(H7:H8) -> 1190336 | I6: =SUM(I7:I8) -> 1178894 | ... K6: =SUM(K7:K8) -> 1156360
A7: 給水収益 | B7: 1231181 | C7: 1218869 | D7: 1206680 | E7: 1194613 | F7: 1182666 | G7: 1170839 | H7: 1159130 | I7: 1147538 | J7: 1136062 | K7: 1124701
A8: その他営業収益 | B8: 30394 | C8: 30467 | D8: 30613 | E8: 30760 | F8: 30908 | G8: 31057 | H8: 31206 | I8: 31356 | J8: 31507 | K8: 31659
A9: 営業外収益 | B9: =SUM(B10:B13) -> 354909 | C9: =SUM(C10:C13) -> 355137 | D9: =SUM(D10:D13) -> 348767 | E9: =SUM(E10:E13) -> 343130 | F9: =SUM(F10:F13) -> 336658 | G9: =SUM(G10:G13) -> 342879 | H9: =SUM(H10:H13) -> 342324 | I9: =SUM(I10:I13) -> 332258 | ... K9: =SUM(K10:K13) -> 307297
A10: 受取利息 | B10: 1 | C10: 1 | D10: 0 | E10: 0 | F10: 0 | G10: 0 | H10: 0 | I10: 0 | J10: 0 | K10: 0
A11: 繰入金・負担金等 | B11: 73283 | C11: 71157 | D11: 68955 | E11: 66740 | F11: 64490 | G11: 62175 | H11: 59946 | I11: 57892 | J11: 56062 | K11: 54385
A12: 長期前受金戻入 | B12: 281625 | C12: 283979 | D12: 279812 | E12: 276390 | F12: 272168 | G12: 272926 | H12: 274600 | I12: 266588 | J12: 250287 | K12: 245134
A13: その他営業外収益 | B13: 0 | C13: 0 | D13: 0 | E13: 0 | F13: 0 | G13: 7778 | H13: 7778 | I13: 7778 | J13: 7778 | K13: 7778
A14: 特別利益 | B14: 2576 | C14: 0 | D14: 0 | E14: 0 | F14: 0 | G14: 0 | H14: 0 | I14: 0 | J14: 0 | K14: 0
A16: 【収益的支出】
A17: 水道事業費用 | B17: =SUM(B18,B28,B31) -> 1608275 | C17: =SUM(C18,C28,C31) -> 1597336 | D17: =SUM(D18,D28,D31) -> 1591913 | E17: =SUM(E18,E28,E31) -> 1586945 | F17: =SUM(F18,F28,F31) -> 1585772 | G17: =SUM(G18,G28,G31) -> 1588017 | H17: =SUM(H18,H28,H31) -> 1595258 | I17: =SUM(I18,I28,I31) -> 1591786 | ... K17: =SUM(K18,K28,K31) -> 1575072
A18: 営業費用 | B18: =SUM(B19,B20,B25,B26,B27) -> 1479507 | C18: =SUM(C19,C20,C25,C26,C27) -> 1476545 | D18: =SUM(D19,D20,D25,D26,D27) -> 1474501 | E18: =SUM(E19,E20,E25,E26,E27) -> 1471288 | F18: =SUM(F19,F20,F25,F26,F27) -> 1471712 | G18: =SUM(G19,G20,G25,G26,G27) -> 1476923 | H18: =SUM(H19,H20,H25,H26,H27) -> 1486420 | I18: =SUM(I19,I20,I25,I26,I27) -> 1484101 | ... K18: =SUM(K19,K20,K25,K26,K27) -> 1469682
A19: 人件費 | B19: 176462 | C19: 176462 | D19: 176462 | E19: 176462 | F19: 176462 | G19: 176462 | H19: 176462 | I19: 176462 | J19: 176462 | K19: 176462
A20: 物件費 | B20: 547263 | C20: 545340 | D20: 545648 | E20: 545957 | F20: 546267 | G20: 546577 | H20: 546888 | I20: 547200 | J20: 547513 | K20: 547827
A21: 修繕費（物件費の内数・参考） | B21: 65247 | C21: 65000 | D21: 65000 | E21: 65000 | F21: 65000 | G21: 65000 | H21: 65000 | I21: 65000 | J21: 65000 | K21: 65000
A22: 動力費（物件費の内数・参考） | B22: 102261 | C22: 102568 | D22: 102876 | E22: 103185 | F22: 103495 | G22: 103805 | H22: 104116 | I22: 104428 | J22: 104741 | K22: 105055
A23: 薬品費（物件費の内数・参考） | B23: 15316 | C23: 15000 | D23: 15000 | E23: 15000 | F23: 15000 | G23: 15000 | H23: 15000 | I23: 15000 | J23: 15000 | K23: 15000
A24: 委託料（物件費の内数・参考） | B24: 304419 | C24: 304000 | D24: 304000 | E24: 304000 | F24: 304000 | G24: 304000 | H24: 304000 | I24: 304000 | J24: 304000 | K24: 304000
A25: 減価償却費 | B25: 755782 | C25: 754743 | D25: 752391 | E25: 748869 | F25: 748983 | G25: 753884 | H25: 763070 | I25: 760439 | J25: 744482 | K25: 745393
A26: 資産減耗・除却費（R8予算のみ別掲、他年度は物件費内数のため0） | B26: 0 | C26: 0 | D26: 0 | E26: 0 | F26: 0 | G26: 0 | H26: 0 | I26: 0 | J26: 0 | K26: 0
A27: その他営業費用（物件費内数のため0） | B27: 0 | C27: 0 | D27: 0 | E27: 0 | F27: 0 | G27: 0 | H27: 0 | I27: 0 | J27: 0 | K27: 0
A28: 営業外費用 | B28: =SUM(B29:B30) -> 128495 | C28: =SUM(C29:C30) -> 120518 | D28: =SUM(D29:D30) -> 117139 | E28: =SUM(E29:E30) -> 115384 | F28: =SUM(F29:F30) -> 113787 | G28: =SUM(G29:G30) -> 110821 | H28: =SUM(H29:H30) -> 108565 | I28: =SUM(I29:I30) -> 107412 | ... K28: =SUM(K29:K30) -> 105117
A29: 支払利息 | B29: 118910 | C29: 111872 | D29: 108458 | E29: 106668 | F29: 105071 | G29: 102070 | H29: 99779 | I29: 98626 | J29: 98322 | K29: 96331
A30: 雑支出 | B30: 9585 | C30: 8646 | D30: 8681 | E30: 8716 | F30: 8716 | G30: 8751 | H30: 8786 | I30: 8786 | J30: 8786 | K30: 8786
A31: 特別損失 | B31: 273 | C31: 273 | D31: 273 | E31: 273 | F31: 273 | G31: 273 | H31: 273 | I31: 273 | J31: 273 | K31: 273
A33: 【資本的収入】
A34: 資本的収入 | B34: 698941 | C34: 664331 | D34: 636408 | E34: 715698 | F34: 627649 | G34: 570213 | H34: 571338 | I34: 536592 | J34: 406734 | K34: 365000
A35: 企業債 | B35: 329000 | C35: 435000 | D35: 399000 | E35: 400000 | F35: 232000 | G35: 283000 | H35: 286000 | I35: 368000 | J35: 251000 | K35: 230000
A36: 一般会計負担金 | B36: 169041 | C36: 164831 | D36: 162408 | E36: 167998 | F36: 173649 | G36: 182213 | H36: 180338 | I36: 168592 | J36: 155734 | K36: 135000
A37: 一般会計出資金 | B37: 0 | C37: 0 | D37: 0 | E37: 0 | F37: 0 | G37: 0 | H37: 0 | I37: 0 | J37: 0 | K37: 0
A38: 国庫補助金 | B38: 0 | C38: 64500 | D38: 75000 | E38: 147700 | F38: 222000 | G38: 105000 | H38: 105000 | I38: 0 | J38: 0 | K38: 0
A39: 固定資産売却代金 | B39: 0 | C39: 0 | D39: 0 | E39: 0 | F39: 0 | G39: 0 | H39: 0 | I39: 0 | J39: 0 | K39: 0
A40: 工事負担金 | B40: 200900 | C40: 0 | D40: 0 | E40: 0 | F40: 0 | G40: 0 | H40: 0 | I40: 0 | J40: 0 | K40: 0
A41: その他・調整 | B41: =B34-SUM(B35:B40) -> 0 | C41: =C34-SUM(C35:C40) -> 0 | D41: =D34-SUM(D35:D40) -> 0 | E41: =E34-SUM(E35:E40) -> 0 | F41: =F34-SUM(F35:F40) -> 0 | G41: =G34-SUM(G35:G40) -> 0 | H41: =H34-SUM(H35:H40) -> 0 | I41: =I34-SUM(I35:I40) -> 0 | ... K41: =K34-SUM(K35:K40) -> 0
A43: 【資本的支出】
A44: 資本的支出 | B44: =SUM(B45:B47) -> 1123770 | C44: =SUM(C45:C47) -> 1684483 | D44: =SUM(D45:D47) -> 1131274 | E44: =SUM(E45:E47) -> 1433926 | F44: =SUM(F45:F47) -> 1196811 | G44: =SUM(G45:G47) -> 965587 | H44: =SUM(H45:H47) -> 945526 | I44: =SUM(I45:I47) -> 916106 | ... K44: =SUM(K45:K47) -> 763357
A45: 建設改良費 | B45: 268741 | C45: 888542 | D45: 403455 | E45: 761285 | F45: 558200 | G45: 389300 | H45: 382930 | I45: 368500 | J45: 265720 | K45: 230500
A46: 企業債償還金 | B46: 855029 | C46: 795941 | D46: 727819 | E46: 672641 | F46: 638611 | G46: 576287 | H46: 562596 | I46: 547606 | J46: 546246 | K46: 532857
A47: その他資本的支出 | B47: 0 | C47: 0 | D47: 0 | E47: 0 | F47: 0 | G47: 0 | H47: 0 | I47: 0 | J47: 0 | K47: 0
A48: 資本的収支不足額（収入－支出） | B48: =B34-B44 -> -424829 | C48: =C34-C44 -> -1020152 | D48: =D34-D44 -> -494866 | E48: =E34-E44 -> -718228 | F48: =F34-F44 -> -569162 | G48: =G34-G44 -> -395374 | H48: =H34-H44 -> -374188 | I48: =I34-I44 -> -379514 | ... K48: =K34-K44 -> -398357

Sheet 03_SIM比較_R8予算反映
A1: SIM比較（R8予算収入・将来年次投資置換／資産維持費0〜3%）
A2: R8は予算ベース、建設改良費は将来年次計画へ置換。資産維持費込料金回収率は「給水収益÷（通常給水原価対象費用＋資産維持費）」で検証。
A3: 計画区分 | B3: 資産維持費率 | C3: 必要改定率 | D3: R11経常収支比率 | E3: R11料金回収率 | F3: R11資産維持費込料金回収率 | G3: R16年度末現預金 | H3: R7-R16累計4条不足額 | I3: 検証 | J3: R16現預金（精緻化後） | K3: 精緻化後最低現金差額
A4: R8予算・年次投資置換 | B4: ='SIM_R8予算置換_0%'!$B$4 -> 0 | C4: ='SIM_R8予算置換_0%'!$B$6 -> 0.072639394 | D4: ='SIM_R8予算置換_0%'!F31 -> 107.67319 | E4: ='SIM_R8予算置換_0%'!F32 -> 95.630009 | F4: ='SIM_R8予算置換_0%'!F33 -> 95.630009 | G4: ='SIM_R8予算置換_0%'!K59 -> 941905.2 | H4: =SUM('SIM_R8予算置換_0%'!B54:K54) -> -4594154 | I4: =IF(F4<=E4,"OK","要確認") -> OK | J4: ='SIM_R8予算置換_0%'!K70 -> 941905.2 | K4: =J4-00_前提・検証!$B$7 -> 641905.2
A5: R8予算・年次投資置換 | B5: ='SIM_R8予算置換_1%'!$B$4 -> 0.01 | C5: ='SIM_R8予算置換_1%'!$B$6 -> 0.21458812 | D5: ='SIM_R8予算置換_1%'!F31 -> 128.56175 | E5: ='SIM_R8予算置換_1%'!F32 -> 108.28529 | F5: ='SIM_R8予算置換_1%'!F33 -> 96.335212 | G5: ='SIM_R8予算置換_1%'!K59 -> 2906741.4 | H5: =SUM('SIM_R8予算置換_1%'!B54:K54) -> -4594154 | I5: =IF(F5<=E5,"OK","要確認") -> OK | J5: ='SIM_R8予算置換_1%'!K70 -> 2906741.4 | K5: =J5-00_前提・検証!$B$7 -> 2606741.4
A6: R8予算・年次投資置換 | B6: ='SIM_R8予算置換_2%'!$B$4 -> 0.02 | C6: ='SIM_R8予算置換_2%'!$B$6 -> 0.35653686 | D6: ='SIM_R8予算置換_2%'!F31 -> 149.45031 | E6: ='SIM_R8予算置換_2%'!F32 -> 120.94058 | F6: ='SIM_R8予算置換_2%'!F33 -> 96.900237 | G6: ='SIM_R8予算置換_2%'!K59 -> 4871577.5 | H6: =SUM('SIM_R8予算置換_2%'!B54:K54) -> -4594154 | I6: =IF(F6<=E6,"OK","要確認") -> OK | J6: ='SIM_R8予算置換_2%'!K70 -> 4871577.5 | K6: =J6-00_前提・検証!$B$7 -> 4571577.5
A7: R8予算・年次投資置換 | B7: ='SIM_R8予算置換_3%'!$B$4 -> 0.03 | C7: ='SIM_R8予算置換_3%'!$B$6 -> 0.49848559 | D7: ='SIM_R8予算置換_3%'!F31 -> 170.33888 | E7: ='SIM_R8予算置換_3%'!F32 -> 133.59587 | F7: ='SIM_R8予算置換_3%'!F33 -> 97.363101 | G7: ='SIM_R8予算置換_3%'!K59 -> 6836413.7 | H7: =SUM('SIM_R8予算置換_3%'!B54:K54) -> -4594154 | I7: =IF(F7<=E7,"OK","要確認") -> OK | J7: ='SIM_R8予算置換_3%'!K70 -> 6836413.7 | K7: =J7-00_前提・検証!$B$7 -> 6536413.7

Sheet 03_SIM比較
A1: SIM比較（ビジョン原計画・将来年次投資置換／資産維持費0〜3%）
A2: 資産維持費込料金回収率は、同一の改定後給水収益を分子とし、給水原価対象費用＋資産維持費を分母にするため、通常料金回収率以下になるよう修正。
A3: 計画区分 | B3: 資産維持費率 | C3: 必要改定率 | D3: R11経常収支比率 | E3: R11料金回収率 | F3: R11資産維持費込料金回収率 | G3: R16年度末現預金 | H3: R7-R16累計4条不足額 | I3: 検証
A4: ビジョン原計画 | B4: ='SIM_ビジョン_0%'!$B$4 -> 0 | C4: ='SIM_ビジョン_0%'!$B$6 -> 0.059677187 | D4: ='SIM_ビジョン_0%'!F31 -> 106.67861 | E4: ='SIM_ビジョン_0%'!F32 -> 95.424853 | F4: ='SIM_ビジョン_0%'!F33 -> 95.424853 | G4: ='SIM_ビジョン_0%'!K59 -> 613660.98 | H4: =SUM('SIM_ビジョン_0%'!B54:K54) -> -5074593 | I4: =IF(F4<=E4,"OK","要確認") -> OK
A5: ビジョン原計画 | B5: ='SIM_ビジョン_1%'!$B$4 -> 0.01 | C5: ='SIM_ビジョン_1%'!$B$6 -> 0.20162592 | D5: ='SIM_ビジョン_1%'!F31 -> 127.85528 | E5: ='SIM_ビジョン_1%'!F32 -> 108.20746 | F5: ='SIM_ビジョン_1%'!F33 -> 96.159205 | G5: ='SIM_ビジョン_1%'!K59 -> 2578497.1 | H5: =SUM('SIM_ビジョン_1%'!B54:K54) -> -5074593 | I5: =IF(F5<=E5,"OK","要確認") -> OK
A6: ビジョン原計画 | B6: ='SIM_ビジョン_2%'!$B$4 -> 0.02 | C6: ='SIM_ビジョン_2%'!$B$6 -> 0.34357465 | D6: ='SIM_ビジョン_2%'!F31 -> 149.03195 | E6: ='SIM_ビジョン_2%'!F32 -> 120.99007 | F6: ='SIM_ビジョン_2%'!F33 -> 96.746409 | G6: ='SIM_ビジョン_2%'!K59 -> 4543333.3 | H6: =SUM('SIM_ビジョン_2%'!B54:K54) -> -5074593 | I6: =IF(F6<=E6,"OK","要確認") -> OK
A7: ビジョン原計画 | B7: ='SIM_ビジョン_3%'!$B$4 -> 0.03 | C7: ='SIM_ビジョン_3%'!$B$6 -> 0.48552338 | D7: ='SIM_ビジョン_3%'!F31 -> 170.20862 | E7: ='SIM_ビジョン_3%'!F32 -> 133.77267 | F7: ='SIM_ビジョン_3%'!F33 -> 97.226666 | G7: ='SIM_ビジョン_3%'!K59 -> 6508169.5 | H7: =SUM('SIM_ビジョン_3%'!B54:K54) -> -5074593 | I7: =IF(F7<=E7,"OK","要確認") -> OK
A8: 将来年次投資置換 | B8: ='SIM_置換後_0%'!$B$4 -> 0 | C8: ='SIM_置換後_0%'!$B$6 -> 0.059677187 | D8: ='SIM_置換後_0%'!F31 -> 106.67861 | E8: ='SIM_置換後_0%'!F32 -> 95.424853 | F8: ='SIM_置換後_0%'!F33 -> 95.424853 | G8: ='SIM_置換後_0%'!K59 -> 219199.98 | H8: =SUM('SIM_置換後_0%'!B54:K54) -> -5179902 | I8: =IF(F8<=E8,"OK","要確認") -> OK
A9: 将来年次投資置換 | B9: ='SIM_置換後_1%'!$B$4 -> 0.01 | C9: ='SIM_置換後_1%'!$B$6 -> 0.20162592 | D9: ='SIM_置換後_1%'!F31 -> 127.85528 | E9: ='SIM_置換後_1%'!F32 -> 108.20746 | F9: ='SIM_置換後_1%'!F33 -> 96.159205 | G9: ='SIM_置換後_1%'!K59 -> 2184036.1 | H9: =SUM('SIM_置換後_1%'!B54:K54) -> -5179902 | I9: =IF(F9<=E9,"OK","要確認") -> OK
A10: 将来年次投資置換 | B10: ='SIM_置換後_2%'!$B$4 -> 0.02 | C10: ='SIM_置換後_2%'!$B$6 -> 0.34357465 | D10: ='SIM_置換後_2%'!F31 -> 149.03195 | E10: ='SIM_置換後_2%'!F32 -> 120.99007 | F10: ='SIM_置換後_2%'!F33 -> 96.746409 | G10: ='SIM_置換後_2%'!K59 -> 4148872.3 | H10: =SUM('SIM_置換後_2%'!B54:K54) -> -5179902 | I10: =IF(F10<=E10,"OK","要確認") -> OK
A11: 将来年次投資置換 | B11: ='SIM_置換後_3%'!$B$4 -> 0.03 | C11: ='SIM_置換後_3%'!$B$6 -> 0.48552338 | D11: ='SIM_置換後_3%'!F31 -> 170.20862 | E11: ='SIM_置換後_3%'!F32 -> 133.77267 | F11: ='SIM_置換後_3%'!F33 -> 97.226666 | G11: ='SIM_置換後_3%'!K59 -> 6113708.5 | H11: =SUM('SIM_置換後_3%'!B54:K54) -> -5179902 | I11: =IF(F11<=E11,"OK","要確認") -> OK

Sheet 04_R8予算・投資確認
A1: 項目 | B1: R8当初予算 | C1: 中間改定/作成資料ベース | D1: 将来年次計画 | E1: 採用値 | F1: 確認結果・備考 | G1: 差額（採用-予算）
A2: 収益的収入：水道事業収益 | B2: 1747782 | C2: =02_将来年次投資置換!C5 -> 1604473 | E2: =02_R8予算_年次計画置換!C5 -> 1747782 | F2: R8は予算ベースへ修正 | G2: =E2-B2 -> 0
A3: 収益的収入：給水収益 | B3: 1331944 | C3: =02_将来年次投資置換!C7 -> 1218869 | E3: =02_R8予算_年次計画置換!C7 -> 1331944 | F3: R8は予算ベースへ修正 | G3: =E3-B3 -> 0
A4: 収益的支出：水道事業費用 | B4: 1710280 | C4: =02_将来年次投資置換!C17 -> 1597336 | E4: =02_R8予算_年次計画置換!C17 -> 1710280 | F4: R8は予算ベースへ修正 | G4: =E4-B4 -> 0
A5: 資本的収入：合計 | B5: 861283 | C5: =02_将来年次投資置換!C34 -> 664331 | E5: =02_R8予算_年次計画置換!C34 -> 1055380 | F5: R8は予算ベースへ修正 | G5: =E5-B5 -> 194097
A6: 資本的収入：企業債 | B6: 519900 | C6: =02_将来年次投資置換!C35 -> 435000 | E6: =02_R8予算_年次計画置換!C35 -> 713997 | F6: R8は予算ベースへ修正 | G6: =E6-B6 -> 194097
A7: 資本的収入：一般会計負担金 | B7: 166838 | C7: =02_将来年次投資置換!C36 -> 164831 | E7: =02_R8予算_年次計画置換!C36 -> 166838 | F7: R8は予算ベースへ修正 | G7: =E7-B7 -> 0
A8: 資本的収入：国庫補助金 | B8: 2000 | C8: =02_将来年次投資置換!C38 -> 64500 | E8: =02_R8予算_年次計画置換!C38 -> 2000 | F8: R8は予算ベースへ修正 | G8: =E8-B8 -> 0
A9: 資本的収入：工事負担金 | B9: 172545 | C9: =02_将来年次投資置換!C40 -> 0 | E9: =02_R8予算_年次計画置換!C40 -> 172545 | F9: R8は予算ベースへ修正 | G9: =E9-B9 -> 0
A10: 建設改良費 | B10: 714032 | C10: =01_ビジョン原計画!C45 -> 525014 | D10: 888542 | E10: =02_R8予算_年次計画置換!C45 -> 888542 | F10: 投資は将来年次計画へ置換（予算との差額を確認） | G10: =E10-B10 -> 174510
A11: 企業債償還金 | B11: 795933 | C11: =02_将来年次投資置換!C46 -> 795941 | E11: =02_R8予算_年次計画置換!C46 -> 795933 | F11: R8は予算ベースへ修正 | G11: =E11-B11 -> 0

Sheet SIM_ビジョン_0%
A1: SIM_ビジョン_0%
A2: 単位：千円、比率は％。料金改定率はR11〜R15の総括原価回収を基礎に算定し、R11以降の給水収益へ反映。
A3: 区分 | B3: 令和7年度 | C3: 令和8年度 | D3: 令和9年度 | E3: 令和10年度 | F3: 令和11年度 | G3: 令和12年度 | H3: 令和13年度 | I3: 令和14年度 | J3: 令和15年度 | K3: 令和16年度
A4: 資産維持費率 | B4: 0
A5: 年額資産維持費（千円） | B5: =00_前提・検証!$B$2*$B$4 -> 0
A6: 料金改定率（R11以降・試算） | B6: =MAX(0,(SUMPRODUCT((01_ビジョン原計画!F18:J18+01_ビジョン原計画!F28:J28-01_ビジョン原計画!F12:J12-01_ビジョン原計画!F8:J8-01_ビジョン原計画!F11:J11+$B$5)-01_ビジョン原計画!F7:J7)/SUM(01_ビジョン原計画!F7:J7))) -> 0.059677187
A8: 【収益的収入】
A9: 営業収益 | B9: =SUM(B10:B12) -> 1261575 | C9: =SUM(C10:C12) -> 1249336 | D9: =SUM(D10:D12) -> 1237293 | E9: =SUM(E10:E12) -> 1225373 | F9: =SUM(F10:F12) -> 1354730.4 | G9: =SUM(G10:G12) -> 1341640.8 | H9: =SUM(H10:H12) -> 1328683.2 | I9: =SUM(I10:I12) -> 1315857.7 | ... K9: =SUM(K10:K12) -> 1290598
A10: 給水収益（改定反映後） | B10: =01_ビジョン原計画!B7*IF(7>=11,1+$B$6,1) -> 1231181 | C10: =01_ビジョン原計画!C7*IF(8>=11,1+$B$6,1) -> 1218869 | D10: =01_ビジョン原計画!D7*IF(9>=11,1+$B$6,1) -> 1206680 | E10: =01_ビジョン原計画!E7*IF(10>=11,1+$B$6,1) -> 1194613 | F10: =01_ビジョン原計画!F7*IF(11>=11,1+$B$6,1) -> 1253244.2 | G10: =01_ビジョン原計画!G7*IF(12>=11,1+$B$6,1) -> 1240711.4 | H10: =01_ビジョン原計画!H7*IF(13>=11,1+$B$6,1) -> 1228303.6 | I10: =01_ビジョン原計画!I7*IF(14>=11,1+$B$6,1) -> 1216019.8 | J10: =01_ビジョン原計画!J7*IF(15>=11,1+$B$6,1) -> 1203859 | K10: =01_ビジョン原計画!K7*IF(16>=11,1+$B$6,1) -> 1191820
A11: うち料金改定増収 | B11: =B10-01_ビジョン原計画!B7 -> 0 | C11: =C10-01_ビジョン原計画!C7 -> 0 | D11: =D10-01_ビジョン原計画!D7 -> 0 | E11: =E10-01_ビジョン原計画!E7 -> 0 | F11: =F10-01_ビジョン原計画!F7 -> 70578.18 | G11: =G10-01_ビジョン原計画!G7 -> 69872.378 | H11: =H10-01_ビジョン原計画!H7 -> 69173.618 | I11: =I10-01_ビジョン原計画!I7 -> 68481.84 | ... K11: =K10-01_ビジョン原計画!K7 -> 67118.992
A12: その他営業収益 | B12: =01_ビジョン原計画!B8 -> 30394 | C12: =01_ビジョン原計画!C8 -> 30467 | D12: =01_ビジョン原計画!D8 -> 30613 | E12: =01_ビジョン原計画!E8 -> 30760 | F12: =01_ビジョン原計画!F8 -> 30908 | G12: =01_ビジョン原計画!G8 -> 31057 | H12: =01_ビジョン原計画!H8 -> 31206 | I12: =01_ビジョン原計画!I8 -> 31356 | ... K12: =01_ビジョン原計画!K8 -> 31659
A13: 営業外収益 | B13: =01_ビジョン原計画!B9 -> 354909 | C13: =01_ビジョン原計画!C9 -> 355137 | D13: =01_ビジョン原計画!D9 -> 348767 | E13: =01_ビジョン原計画!E9 -> 343130 | F13: =01_ビジョン原計画!F9 -> 336658 | G13: =01_ビジョン原計画!G9 -> 342879 | H13: =01_ビジョン原計画!H9 -> 342324 | I13: =01_ビジョン原計画!I9 -> 332258 | ... K13: =01_ビジョン原計画!K9 -> 307297
A14: 長期前受金戻入 | B14: =01_ビジョン原計画!B12 -> 281625 | C14: =01_ビジョン原計画!C12 -> 283979 | D14: =01_ビジョン原計画!D12 -> 279812 | E14: =01_ビジョン原計画!E12 -> 276390 | F14: =01_ビジョン原計画!F12 -> 272168 | G14: =01_ビジョン原計画!G12 -> 272926 | H14: =01_ビジョン原計画!H12 -> 274600 | I14: =01_ビジョン原計画!I12 -> 266588 | ... K14: =01_ビジョン原計画!K12 -> 245134
A15: 繰入金・負担金等 | B15: =01_ビジョン原計画!B11 -> 73283 | C15: =01_ビジョン原計画!C11 -> 71157 | D15: =01_ビジョン原計画!D11 -> 68955 | E15: =01_ビジョン原計画!E11 -> 66740 | F15: =01_ビジョン原計画!F11 -> 64490 | G15: =01_ビジョン原計画!G11 -> 62175 | H15: =01_ビジョン原計画!H11 -> 59946 | I15: =01_ビジョン原計画!I11 -> 57892 | ... K15: =01_ビジョン原計画!K11 -> 54385
A16: 特別利益 | B16: =01_ビジョン原計画!B14 -> 2576 | C16: =01_ビジョン原計画!C14 -> 0 | D16: =01_ビジョン原計画!D14 -> 0 | E16: =01_ビジョン原計画!E14 -> 0 | F16: =01_ビジョン原計画!F14 -> 0 | G16: =01_ビジョン原計画!G14 -> 0 | H16: =01_ビジョン原計画!H14 -> 0 | I16: =01_ビジョン原計画!I14 -> 0 | ... K16: =01_ビジョン原計画!K14 -> 0
A17: 収益的収入合計 | B17: =SUM(B9,B13,B16) -> 1619060 | C17: =SUM(C9,C13,C16) -> 1604473 | D17: =SUM(D9,D13,D16) -> 1586060 | E17: =SUM(E9,E13,E16) -> 1568503 | F17: =SUM(F9,F13,F16) -> 1691388.4 | G17: =SUM(G9,G13,G16) -> 1684519.8 | H17: =SUM(H9,H13,H16) -> 1671007.2 | I17: =SUM(I9,I13,I16) -> 1648115.7 | ... K17: =SUM(K9,K13,K16) -> 1597895
A19: 【収益的支出】
A20: 営業費用 | B20: =01_ビジョン原計画!B18 -> 1479507 | C20: =01_ビジョン原計画!C18 -> 1476545 | D20: =01_ビジョン原計画!D18 -> 1474501 | E20: =01_ビジョン原計画!E18 -> 1471288 | F20: =01_ビジョン原計画!F18 -> 1471712 | G20: =01_ビジョン原計画!G18 -> 1476923 | H20: =01_ビジョン原計画!H18 -> 1486420 | I20: =01_ビジョン原計画!I18 -> 1484101 | ... K20: =01_ビジョン原計画!K18 -> 1469682
A21: 減価償却費 | B21: =01_ビジョン原計画!B25 -> 755782 | C21: =01_ビジョン原計画!C25 -> 754743 | D21: =01_ビジョン原計画!D25 -> 752391 | E21: =01_ビジョン原計画!E25 -> 748869 | F21: =01_ビジョン原計画!F25 -> 748983 | G21: =01_ビジョン原計画!G25 -> 753884 | H21: =01_ビジョン原計画!H25 -> 763070 | I21: =01_ビジョン原計画!I25 -> 760439 | ... K21: =01_ビジョン原計画!K25 -> 745393
A22: 資産減耗・除却費 | B22: =01_ビジョン原計画!B26 -> 0 | C22: =01_ビジョン原計画!C26 -> 0 | D22: =01_ビジョン原計画!D26 -> 0 | E22: =01_ビジョン原計画!E26 -> 0 | F22: =01_ビジョン原計画!F26 -> 0 | G22: =01_ビジョン原計画!G26 -> 0 | H22: =01_ビジョン原計画!H26 -> 0 | I22: =01_ビジョン原計画!I26 -> 0 | ... K22: =01_ビジョン原計画!K26 -> 0
A23: 営業外費用 | B23: =01_ビジョン原計画!B28 -> 128495 | C23: =01_ビジョン原計画!C28 -> 120518 | D23: =01_ビジョン原計画!D28 -> 117139 | E23: =01_ビジョン原計画!E28 -> 115384 | F23: =01_ビジョン原計画!F28 -> 113787 | G23: =01_ビジョン原計画!G28 -> 110821 | H23: =01_ビジョン原計画!H28 -> 108565 | I23: =01_ビジョン原計画!I28 -> 107412 | ... K23: =01_ビジョン原計画!K28 -> 105117
A24: 支払利息 | B24: =01_ビジョン原計画!B29 -> 118910 | C24: =01_ビジョン原計画!C29 -> 111872 | D24: =01_ビジョン原計画!D29 -> 108458 | E24: =01_ビジョン原計画!E29 -> 106668 | F24: =01_ビジョン原計画!F29 -> 105071 | G24: =01_ビジョン原計画!G29 -> 102070 | H24: =01_ビジョン原計画!H29 -> 99779 | I24: =01_ビジョン原計画!I29 -> 98626 | ... K24: =01_ビジョン原計画!K29 -> 96331
A25: 特別損失 | B25: =01_ビジョン原計画!B31 -> 273 | C25: =01_ビジョン原計画!C31 -> 273 | D25: =01_ビジョン原計画!D31 -> 273 | E25: =01_ビジョン原計画!E31 -> 273 | F25: =01_ビジョン原計画!F31 -> 273 | G25: =01_ビジョン原計画!G31 -> 273 | H25: =01_ビジョン原計画!H31 -> 273 | I25: =01_ビジョン原計画!I31 -> 273 | ... K25: =01_ビジョン原計画!K31 -> 273
A26: 収益的支出合計 | B26: =SUM(B20,B23,B25) -> 1608275 | C26: =SUM(C20,C23,C25) -> 1597336 | D26: =SUM(D20,D23,D25) -> 1591913 | E26: =SUM(E20,E23,E25) -> 1586945 | F26: =SUM(F20,F23,F25) -> 1585772 | G26: =SUM(G20,G23,G25) -> 1588017 | H26: =SUM(H20,H23,H25) -> 1595258 | I26: =SUM(I20,I23,I25) -> 1591786 | ... K26: =SUM(K20,K23,K25) -> 1575072
A27: 経常損益 | B27: =SUM(B9,B13)-SUM(B20,B23) -> 8482 | C27: =SUM(C9,C13)-SUM(C20,C23) -> 7410 | D27: =SUM(D9,D13)-SUM(D20,D23) -> -5580 | E27: =SUM(E9,E13)-SUM(E20,E23) -> -18169 | F27: =SUM(F9,F13)-SUM(F20,F23) -> 105889.36 | G27: =SUM(G9,G13)-SUM(G20,G23) -> 96775.756 | H27: =SUM(H9,H13)-SUM(H20,H23) -> 76022.236 | I27: =SUM(I9,I13)-SUM(I20,I23) -> 56602.68 | ... K27: =SUM(K9,K13)-SUM(K20,K23) -> 23095.984
A28: 純損益 | B28: =B27+B16-B25 -> 10785 | C28: =C27+C16-C25 -> 7137 | D28: =D27+D16-D25 -> -5853 | E28: =E27+E16-E25 -> -18442 | F28: =F27+F16-F25 -> 105616.36 | G28: =G27+G16-G25 -> 96502.756 | H28: =H27+H16-H25 -> 75749.236 | I28: =I27+I16-I25 -> 56329.68 | ... K28: =K27+K16-K25 -> 22822.984
A30: 【経営指標】
A31: 経常収支比率 | B31: =IFERROR((SUM(B9,B13)/SUM(B20,B23))*100,0) -> 100.52749 | C31: =IFERROR((SUM(C9,C13)/SUM(C20,C23))*100,0) -> 100.46398 | D31: =IFERROR((SUM(D9,D13)/SUM(D20,D23))*100,0) -> 99.649418 | E31: =IFERROR((SUM(E9,E13)/SUM(E20,E23))*100,0) -> 98.854899 | F31: =IFERROR((SUM(F9,F13)/SUM(F20,F23))*100,0) -> 106.67861 | G31: =IFERROR((SUM(G9,G13)/SUM(G20,G23))*100,0) -> 106.09517 | H31: =IFERROR((SUM(H9,H13)/SUM(H20,H23))*100,0) -> 104.76633 | I31: =IFERROR((SUM(I9,I13)/SUM(I20,I23))*100,0) -> 103.55653 | ... K31: =IFERROR((SUM(K9,K13)/SUM(K20,K23))*100,0) -> 101.4666
A32: 料金回収率（通常） | B32: =IFERROR(B10/B34*100,0) -> 92.822855 | C32: =IFERROR(C10/C34*100,0) -> 92.824907 | D32: =IFERROR(D10/D34*100,0) -> 91.98462 | E32: =IFERROR(E10/E34*100,0) -> 91.172206 | F32: =IFERROR(F10/F34*100,0) -> 95.424853 | G32: =IFERROR(G10/G34*100,0) -> 94.363735 | H32: =IFERROR(H10/H34*100,0) -> 93.026172 | I32: =IFERROR(I10/I34*100,0) -> 91.780277 | ... K32: =IFERROR(K10/K34*100,0) -> 89.633102
A33: 資産維持費込料金回収率 | B33: =IFERROR(B10/B35*100,0) -> 92.822855 | C33: =IFERROR(C10/C35*100,0) -> 92.824907 | D33: =IFERROR(D10/D35*100,0) -> 91.98462 | E33: =IFERROR(E10/E35*100,0) -> 91.172206 | F33: =IFERROR(F10/F35*100,0) -> 95.424853 | G33: =IFERROR(G10/G35*100,0) -> 94.363735 | H33: =IFERROR(H10/H35*100,0) -> 93.026172 | I33: =IFERROR(I10/I35*100,0) -> 91.780277 | ... K33: =IFERROR(K10/K35*100,0) -> 89.633102
A34: 給水原価対象費用 | B34: =SUM(B20,B23)-B14 -> 1326377 | C34: =SUM(C20,C23)-C14 -> 1313084 | D34: =SUM(D20,D23)-D14 -> 1311828 | E34: =SUM(E20,E23)-E14 -> 1310282 | F34: =SUM(F20,F23)-F14 -> 1313331 | G34: =SUM(G20,G23)-G14 -> 1314818 | H34: =SUM(H20,H23)-H14 -> 1320385 | I34: =SUM(I20,I23)-I14 -> 1324925 | ... K34: =SUM(K20,K23)-K14 -> 1329665
A35: 給水原価対象費用＋資産維持費 | B35: =B34+$B$5 -> 1326377 | C35: =C34+$B$5 -> 1313084 | D35: =D34+$B$5 -> 1311828 | E35: =E34+$B$5 -> 1310282 | F35: =F34+$B$5 -> 1313331 | G35: =G34+$B$5 -> 1314818 | H35: =H34+$B$5 -> 1320385 | I35: =I34+$B$5 -> 1324925 | ... K35: =K34+$B$5 -> 1329665
A36: 総括原価回収率（参考） | B36: =IFERROR(B10/(B20+B23-B14-B12-B15+$B$5)*100,0) -> 100.69363 | C36: =IFERROR(C10/(C20+C23-C14-C12-C15+$B$5)*100,0) -> 100.61158 | D36: =IFERROR(D10/(D20+D23-D14-D12-D15+$B$5)*100,0) -> 99.539703 | E36: =IFERROR(E10/(E20+E23-E14-E12-E15+$B$5)*100,0) -> 98.501874 | F36: =IFERROR(F10/(F20+F23-F14-F12-F15+$B$5)*100,0) -> 102.89927 | G36: =IFERROR(G10/(G20+G23-G14-G12-G15+$B$5)*100,0) -> 101.56562 | H36: =IFERROR(H10/(H20+H23-H14-H12-H15+$B$5)*100,0) -> 99.924393 | I36: =IFERROR(I10/(I20+I23-I14-I12-I15+$B$5)*100,0) -> 98.409199 | ... K36: =IFERROR(K10/(K20+K23-K14-K12-K15+$B$5)*100,0) -> 95.834663
A37: 検証：資産維持費込<=通常 | B37: =IF(B33<=B32,"OK","要確認") -> OK | C37: =IF(C33<=C32,"OK","要確認") -> OK | D37: =IF(D33<=D32,"OK","要確認") -> OK | E37: =IF(E33<=E32,"OK","要確認") -> OK | F37: =IF(F33<=F32,"OK","要確認") -> OK | G37: =IF(G33<=G32,"OK","要確認") -> OK | H37: =IF(H33<=H32,"OK","要確認") -> OK | I37: =IF(I33<=I32,"OK","要確認") -> OK | ... K37: =IF(K33<=K32,"OK","要確認") -> OK
A39: 【資本的収入】
A40: 資本的収入 | B40: =01_ビジョン原計画!B34 -> 698941 | C40: =01_ビジョン原計画!C34 -> 664331 | D40: =01_ビジョン原計画!D34 -> 636408 | E40: =01_ビジョン原計画!E34 -> 715698 | F40: =01_ビジョン原計画!F34 -> 627649 | G40: =01_ビジョン原計画!G34 -> 570213 | H40: =01_ビジョン原計画!H34 -> 571338 | I40: =01_ビジョン原計画!I34 -> 536592 | ... K40: =01_ビジョン原計画!K34 -> 365000
A41: 企業債 | B41: =01_ビジョン原計画!B35 -> 329000 | C41: =01_ビジョン原計画!C35 -> 435000 | D41: =01_ビジョン原計画!D35 -> 399000 | E41: =01_ビジョン原計画!E35 -> 400000 | F41: =01_ビジョン原計画!F35 -> 232000 | G41: =01_ビジョン原計画!G35 -> 283000 | H41: =01_ビジョン原計画!H35 -> 286000 | I41: =01_ビジョン原計画!I35 -> 368000 | ... K41: =01_ビジョン原計画!K35 -> 230000
A42: 一般会計負担金 | B42: =01_ビジョン原計画!B36 -> 169041 | C42: =01_ビジョン原計画!C36 -> 164831 | D42: =01_ビジョン原計画!D36 -> 162408 | E42: =01_ビジョン原計画!E36 -> 167998 | F42: =01_ビジョン原計画!F36 -> 173649 | G42: =01_ビジョン原計画!G36 -> 182213 | H42: =01_ビジョン原計画!H36 -> 180338 | I42: =01_ビジョン原計画!I36 -> 168592 | ... K42: =01_ビジョン原計画!K36 -> 135000
A43: 一般会計出資金 | B43: =01_ビジョン原計画!B37 -> 0 | C43: =01_ビジョン原計画!C37 -> 0 | D43: =01_ビジョン原計画!D37 -> 0 | E43: =01_ビジョン原計画!E37 -> 0 | F43: =01_ビジョン原計画!F37 -> 0 | G43: =01_ビジョン原計画!G37 -> 0 | H43: =01_ビジョン原計画!H37 -> 0 | I43: =01_ビジョン原計画!I37 -> 0 | ... K43: =01_ビジョン原計画!K37 -> 0
A44: 国庫補助金 | B44: =01_ビジョン原計画!B38 -> 0 | C44: =01_ビジョン原計画!C38 -> 64500 | D44: =01_ビジョン原計画!D38 -> 75000 | E44: =01_ビジョン原計画!E38 -> 147700 | F44: =01_ビジョン原計画!F38 -> 222000 | G44: =01_ビジョン原計画!G38 -> 105000 | H44: =01_ビジョン原計画!H38 -> 105000 | I44: =01_ビジョン原計画!I38 -> 0 | ... K44: =01_ビジョン原計画!K38 -> 0
A45: 固定資産売却代金 | B45: =01_ビジョン原計画!B39 -> 0 | C45: =01_ビジョン原計画!C39 -> 0 | D45: =01_ビジョン原計画!D39 -> 0 | E45: =01_ビジョン原計画!E39 -> 0 | F45: =01_ビジョン原計画!F39 -> 0 | G45: =01_ビジョン原計画!G39 -> 0 | H45: =01_ビジョン原計画!H39 -> 0 | I45: =01_ビジョン原計画!I39 -> 0 | ... K45: =01_ビジョン原計画!K39 -> 0
A46: 工事負担金 | B46: =01_ビジョン原計画!B40 -> 200900 | C46: =01_ビジョン原計画!C40 -> 0 | D46: =01_ビジョン原計画!D40 -> 0 | E46: =01_ビジョン原計画!E40 -> 0 | F46: =01_ビジョン原計画!F40 -> 0 | G46: =01_ビジョン原計画!G40 -> 0 | H46: =01_ビジョン原計画!H40 -> 0 | I46: =01_ビジョン原計画!I40 -> 0 | ... K46: =01_ビジョン原計画!K40 -> 0
A47: その他・調整 | B47: =01_ビジョン原計画!B41 -> 0 | C47: =01_ビジョン原計画!C41 -> 0 | D47: =01_ビジョン原計画!D41 -> 0 | E47: =01_ビジョン原計画!E41 -> 0 | F47: =01_ビジョン原計画!F41 -> 0 | G47: =01_ビジョン原計画!G41 -> 0 | H47: =01_ビジョン原計画!H41 -> 0 | I47: =01_ビジョン原計画!I41 -> 0 | ... K47: =01_ビジョン原計画!K41 -> 0
A49: 【資本的支出】
A50: 資本的支出 | B50: =01_ビジョン原計画!B44 -> 1412922 | C50: =01_ビジョン原計画!C44 -> 1320955 | D50: =01_ビジョン原計画!D44 -> 1228308 | E50: =01_ビジョン原計画!E44 -> 1249449 | F50: =01_ビジョン原計画!F44 -> 1123446 | G50: =01_ビジョン原計画!G44 -> 992222 | H50: =01_ビジョン原計画!H44 -> 982061 | I50: =01_ビジョン原計画!I44 -> 942741 | ... K50: =01_ビジョン原計画!K44 -> 789992
A51: 建設改良費 | B51: =01_ビジョン原計画!B45 -> 557893 | C51: =01_ビジョン原計画!C45 -> 525014 | D51: =01_ビジョン原計画!D45 -> 500489 | E51: =01_ビジョン原計画!E45 -> 576808 | F51: =01_ビジョン原計画!F45 -> 484835 | G51: =01_ビジョン原計画!G45 -> 415935 | H51: =01_ビジョン原計画!H45 -> 419465 | I51: =01_ビジョン原計画!I45 -> 395135 | ... K51: =01_ビジョン原計画!K45 -> 257135
A52: 企業債償還金 | B52: =01_ビジョン原計画!B46 -> 855029 | C52: =01_ビジョン原計画!C46 -> 795941 | D52: =01_ビジョン原計画!D46 -> 727819 | E52: =01_ビジョン原計画!E46 -> 672641 | F52: =01_ビジョン原計画!F46 -> 638611 | G52: =01_ビジョン原計画!G46 -> 576287 | H52: =01_ビジョン原計画!H46 -> 562596 | I52: =01_ビジョン原計画!I46 -> 547606 | ... K52: =01_ビジョン原計画!K46 -> 532857
A53: その他資本的支出 | B53: =01_ビジョン原計画!B47 -> 0 | C53: =01_ビジョン原計画!C47 -> 0 | D53: =01_ビジョン原計画!D47 -> 0 | E53: =01_ビジョン原計画!E47 -> 0 | F53: =01_ビジョン原計画!F47 -> 0 | G53: =01_ビジョン原計画!G47 -> 0 | H53: =01_ビジョン原計画!H47 -> 0 | I53: =01_ビジョン原計画!I47 -> 0 | ... K53: =01_ビジョン原計画!K47 -> 0
A54: 資本的収支不足額（収入－支出） | B54: =B40-B50 -> -713981 | C54: =C40-C50 -> -656624 | D54: =D40-D50 -> -591900 | E54: =E40-E50 -> -533751 | F54: =F40-F50 -> -495797 | G54: =G40-G50 -> -422009 | H54: =H40-H50 -> -410723 | I54: =I40-I50 -> -406149 | ... K54: =K40-K50 -> -424992
A56: 【現預金・4条財源】
A57: 補てん可能財源相当（簡便CF） | B57: =B28+B21+B22-B14 -> 484942 | C57: =C28+C21+C22-C14 -> 477901 | D57: =D28+D21+D22-D14 -> 466726 | E57: =E28+E21+E22-E14 -> 454037 | F57: =F28+F21+F22-F14 -> 582431.36 | G57: =G28+G21+G22-G14 -> 577460.76 | H57: =H28+H21+H22-H14 -> 564219.24 | I57: =I28+I21+I22-I14 -> 550180.68 | ... K57: =K28+K21+K22-K14 -> 523081.98
A58: 資本的収支不足額（再掲） | B58: =B54 -> -713981 | C58: =C54 -> -656624 | D58: =D54 -> -591900 | E58: =E54 -> -533751 | F58: =F54 -> -495797 | G58: =G54 -> -422009 | H58: =H54 -> -410723 | I58: =I54 -> -406149 | ... K58: =K54 -> -424992
A59: 年度末現預金残高 | B59: =00_前提・検証!$B$6 -> 242588 | C59: =B59+C57+C58 -> 63865 | D59: =C59+D57+D58 -> -61309 | E59: =D59+E57+E58 -> -141023 | F59: =E59+F57+F58 -> -54388.64 | G59: =F59+G57+G58 -> 101063.12 | H59: =G59+H57+H58 -> 254559.35 | I59: =H59+I57+I58 -> 398591.03 | J59: =I59+J57+J58 -> 515571 | K59: =J59+K57+K58 -> 613660.98
A60: 最低現金目安との差額 | B60: =B59-00_前提・検証!$B$7 -> -57412 | C60: =C59-00_前提・検証!$B$7 -> -236135 | D60: =D59-00_前提・検証!$B$7 -> -361309 | E60: =E59-00_前提・検証!$B$7 -> -441023 | F60: =F59-00_前提・検証!$B$7 -> -354388.64 | G60: =G59-00_前提・検証!$B$7 -> -198936.88 | H60: =H59-00_前提・検証!$B$7 -> -45440.648 | I60: =I59-00_前提・検証!$B$7 -> 98591.031 | ... K60: =K59-00_前提・検証!$B$7 -> 313660.98

Sheet SIM_ビジョン_1%
A1: SIM_ビジョン_1%
A2: 単位：千円、比率は％。料金改定率はR11〜R15の総括原価回収を基礎に算定し、R11以降の給水収益へ反映。
A3: 区分 | B3: 令和7年度 | C3: 令和8年度 | D3: 令和9年度 | E3: 令和10年度 | F3: 令和11年度 | G3: 令和12年度 | H3: 令和13年度 | I3: 令和14年度 | J3: 令和15年度 | K3: 令和16年度
A4: 資産維持費率 | B4: 0.01
A5: 年額資産維持費（千円） | B5: =00_前提・検証!$B$2*$B$4 -> 164553.64
A6: 料金改定率（R11以降・試算） | B6: =MAX(0,(SUMPRODUCT((01_ビジョン原計画!F18:J18+01_ビジョン原計画!F28:J28-01_ビジョン原計画!F12:J12-01_ビジョン原計画!F8:J8-01_ビジョン原計画!F11:J11+$B$5)-01_ビジョン原計画!F7:J7)/SUM(01_ビジョン原計画!F7:J7))) -> 0.20162592
A8: 【収益的収入】
A9: 営業収益 | B9: =SUM(B10:B12) -> 1261575 | C9: =SUM(C10:C12) -> 1249336 | D9: =SUM(D10:D12) -> 1237293 | E9: =SUM(E10:E12) -> 1225373 | F9: =SUM(F10:F12) -> 1690486.2 | G9: =SUM(G10:G12) -> 1674039 | H9: =SUM(H10:H12) -> 1657757.3 | I9: =SUM(I10:I12) -> 1641640.8 | ... K9: =SUM(K10:K12) -> 1609897.7
A10: 給水収益（改定反映後） | B10: =01_ビジョン原計画!B7*IF(7>=11,1+$B$6,1) -> 1231181 | C10: =01_ビジョン原計画!C7*IF(8>=11,1+$B$6,1) -> 1218869 | D10: =01_ビジョン原計画!D7*IF(9>=11,1+$B$6,1) -> 1206680 | E10: =01_ビジョン原計画!E7*IF(10>=11,1+$B$6,1) -> 1194613 | F10: =01_ビジョン原計画!F7*IF(11>=11,1+$B$6,1) -> 1421122.1 | G10: =01_ビジョン原計画!G7*IF(12>=11,1+$B$6,1) -> 1406910.5 | H10: =01_ビジョン原計画!H7*IF(13>=11,1+$B$6,1) -> 1392840.6 | I10: =01_ビジョン原計画!I7*IF(14>=11,1+$B$6,1) -> 1378911.4 | J10: =01_ビジョン原計画!J7*IF(15>=11,1+$B$6,1) -> 1365121.5 | K10: =01_ビジョン原計画!K7*IF(16>=11,1+$B$6,1) -> 1351469.9
A11: うち料金改定増収 | B11: =B10-01_ビジョン原計画!B7 -> 0 | C11: =C10-01_ビジョン原計画!C7 -> 0 | D11: =D10-01_ビジョン原計画!D7 -> 0 | E11: =E10-01_ビジョン原計画!E7 -> 0 | F11: =F10-01_ビジョン原計画!F7 -> 238456.12 | G11: =G10-01_ビジョン原計画!G7 -> 236071.49 | H11: =H10-01_ビジョン原計画!H7 -> 233710.65 | I11: =I10-01_ビジョン原計画!I7 -> 231373.4 | ... K11: =K10-01_ビジョン原計画!K7 -> 226768.87
A12: その他営業収益 | B12: =01_ビジョン原計画!B8 -> 30394 | C12: =01_ビジョン原計画!C8 -> 30467 | D12: =01_ビジョン原計画!D8 -> 30613 | E12: =01_ビジョン原計画!E8 -> 30760 | F12: =01_ビジョン原計画!F8 -> 30908 | G12: =01_ビジョン原計画!G8 -> 31057 | H12: =01_ビジョン原計画!H8 -> 31206 | I12: =01_ビジョン原計画!I8 -> 31356 | ... K12: =01_ビジョン原計画!K8 -> 31659
A13: 営業外収益 | B13: =01_ビジョン原計画!B9 -> 354909 | C13: =01_ビジョン原計画!C9 -> 355137 | D13: =01_ビジョン原計画!D9 -> 348767 | E13: =01_ビジョン原計画!E9 -> 343130 | F13: =01_ビジョン原計画!F9 -> 336658 | G13: =01_ビジョン原計画!G9 -> 342879 | H13: =01_ビジョン原計画!H9 -> 342324 | I13: =01_ビジョン原計画!I9 -> 332258 | ... K13: =01_ビジョン原計画!K9 -> 307297
A14: 長期前受金戻入 | B14: =01_ビジョン原計画!B12 -> 281625 | C14: =01_ビジョン原計画!C12 -> 283979 | D14: =01_ビジョン原計画!D12 -> 279812 | E14: =01_ビジョン原計画!E12 -> 276390 | F14: =01_ビジョン原計画!F12 -> 272168 | G14: =01_ビジョン原計画!G12 -> 272926 | H14: =01_ビジョン原計画!H12 -> 274600 | I14: =01_ビジョン原計画!I12 -> 266588 | ... K14: =01_ビジョン原計画!K12 -> 245134
A15: 繰入金・負担金等 | B15: =01_ビジョン原計画!B11 -> 73283 | C15: =01_ビジョン原計画!C11 -> 71157 | D15: =01_ビジョン原計画!D11 -> 68955 | E15: =01_ビジョン原計画!E11 -> 66740 | F15: =01_ビジョン原計画!F11 -> 64490 | G15: =01_ビジョン原計画!G11 -> 62175 | H15: =01_ビジョン原計画!H11 -> 59946 | I15: =01_ビジョン原計画!I11 -> 57892 | ... K15: =01_ビジョン原計画!K11 -> 54385
A16: 特別利益 | B16: =01_ビジョン原計画!B14 -> 2576 | C16: =01_ビジョン原計画!C14 -> 0 | D16: =01_ビジョン原計画!D14 -> 0 | E16: =01_ビジョン原計画!E14 -> 0 | F16: =01_ビジョン原計画!F14 -> 0 | G16: =01_ビジョン原計画!G14 -> 0 | H16: =01_ビジョン原計画!H14 -> 0 | I16: =01_ビジョン原計画!I14 -> 0 | ... K16: =01_ビジョン原計画!K14 -> 0
A17: 収益的収入合計 | B17: =SUM(B9,B13,B16) -> 1619060 | C17: =SUM(C9,C13,C16) -> 1604473 | D17: =SUM(D9,D13,D16) -> 1586060 | E17: =SUM(E9,E13,E16) -> 1568503 | F17: =SUM(F9,F13,F16) -> 2027144.2 | G17: =SUM(G9,G13,G16) -> 2016918 | H17: =SUM(H9,H13,H16) -> 2000081.3 | I17: =SUM(I9,I13,I16) -> 1973898.8 | ... K17: =SUM(K9,K13,K16) -> 1917194.7
A19: 【収益的支出】
A20: 営業費用 | B20: =01_ビジョン原計画!B18 -> 1479507 | C20: =01_ビジョン原計画!C18 -> 1476545 | D20: =01_ビジョン原計画!D18 -> 1474501 | E20: =01_ビジョン原計画!E18 -> 1471288 | F20: =01_ビジョン原計画!F18 -> 1471712 | G20: =01_ビジョン原計画!G18 -> 1476923 | H20: =01_ビジョン原計画!H18 -> 1486420 | I20: =01_ビジョン原計画!I18 -> 1484101 | ... K20: =01_ビジョン原計画!K18 -> 1469682
A21: 減価償却費 | B21: =01_ビジョン原計画!B25 -> 755782 | C21: =01_ビジョン原計画!C25 -> 754743 | D21: =01_ビジョン原計画!D25 -> 752391 | E21: =01_ビジョン原計画!E25 -> 748869 | F21: =01_ビジョン原計画!F25 -> 748983 | G21: =01_ビジョン原計画!G25 -> 753884 | H21: =01_ビジョン原計画!H25 -> 763070 | I21: =01_ビジョン原計画!I25 -> 760439 | ... K21: =01_ビジョン原計画!K25 -> 745393
A22: 資産減耗・除却費 | B22: =01_ビジョン原計画!B26 -> 0 | C22: =01_ビジョン原計画!C26 -> 0 | D22: =01_ビジョン原計画!D26 -> 0 | E22: =01_ビジョン原計画!E26 -> 0 | F22: =01_ビジョン原計画!F26 -> 0 | G22: =01_ビジョン原計画!G26 -> 0 | H22: =01_ビジョン原計画!H26 -> 0 | I22: =01_ビジョン原計画!I26 -> 0 | ... K22: =01_ビジョン原計画!K26 -> 0
A23: 営業外費用 | B23: =01_ビジョン原計画!B28 -> 128495 | C23: =01_ビジョン原計画!C28 -> 120518 | D23: =01_ビジョン原計画!D28 -> 117139 | E23: =01_ビジョン原計画!E28 -> 115384 | F23: =01_ビジョン原計画!F28 -> 113787 | G23: =01_ビジョン原計画!G28 -> 110821 | H23: =01_ビジョン原計画!H28 -> 108565 | I23: =01_ビジョン原計画!I28 -> 107412 | ... K23: =01_ビジョン原計画!K28 -> 105117
A24: 支払利息 | B24: =01_ビジョン原計画!B29 -> 118910 | C24: =01_ビジョン原計画!C29 -> 111872 | D24: =01_ビジョン原計画!D29 -> 108458 | E24: =01_ビジョン原計画!E29 -> 106668 | F24: =01_ビジョン原計画!F29 -> 105071 | G24: =01_ビジョン原計画!G29 -> 102070 | H24: =01_ビジョン原計画!H29 -> 99779 | I24: =01_ビジョン原計画!I29 -> 98626 | ... K24: =01_ビジョン原計画!K29 -> 96331
A25: 特別損失 | B25: =01_ビジョン原計画!B31 -> 273 | C25: =01_ビジョン原計画!C31 -> 273 | D25: =01_ビジョン原計画!D31 -> 273 | E25: =01_ビジョン原計画!E31 -> 273 | F25: =01_ビジョン原計画!F31 -> 273 | G25: =01_ビジョン原計画!G31 -> 273 | H25: =01_ビジョン原計画!H31 -> 273 | I25: =01_ビジョン原計画!I31 -> 273 | ... K25: =01_ビジョン原計画!K31 -> 273
A26: 収益的支出合計 | B26: =SUM(B20,B23,B25) -> 1608275 | C26: =SUM(C20,C23,C25) -> 1597336 | D26: =SUM(D20,D23,D25) -> 1591913 | E26: =SUM(E20,E23,E25) -> 1586945 | F26: =SUM(F20,F23,F25) -> 1585772 | G26: =SUM(G20,G23,G25) -> 1588017 | H26: =SUM(H20,H23,H25) -> 1595258 | I26: =SUM(I20,I23,I25) -> 1591786 | ... K26: =SUM(K20,K23,K25) -> 1575072
A27: 経常損益 | B27: =SUM(B9,B13)-SUM(B20,B23) -> 8482 | C27: =SUM(C9,C13)-SUM(C20,C23) -> 7410 | D27: =SUM(D9,D13)-SUM(D20,D23) -> -5580 | E27: =SUM(E9,E13)-SUM(E20,E23) -> -18169 | F27: =SUM(F9,F13)-SUM(F20,F23) -> 441645.23 | G27: =SUM(G9,G13)-SUM(G20,G23) -> 429173.98 | H27: =SUM(H9,H13)-SUM(H20,H23) -> 405096.3 | I27: =SUM(I9,I13)-SUM(I20,I23) -> 382385.8 | ... K27: =SUM(K9,K13)-SUM(K20,K23) -> 342395.74
A28: 純損益 | B28: =B27+B16-B25 -> 10785 | C28: =C27+C16-C25 -> 7137 | D28: =D27+D16-D25 -> -5853 | E28: =E27+E16-E25 -> -18442 | F28: =F27+F16-F25 -> 441372.23 | G28: =G27+G16-G25 -> 428900.98 | H28: =H27+H16-H25 -> 404823.3 | I28: =I27+I16-I25 -> 382112.8 | ... K28: =K27+K16-K25 -> 342122.74
A30: 【経営指標】
A31: 経常収支比率 | B31: =IFERROR((SUM(B9,B13)/SUM(B20,B23))*100,0) -> 100.52749 | C31: =IFERROR((SUM(C9,C13)/SUM(C20,C23))*100,0) -> 100.46398 | D31: =IFERROR((SUM(D9,D13)/SUM(D20,D23))*100,0) -> 99.649418 | E31: =IFERROR((SUM(E9,E13)/SUM(E20,E23))*100,0) -> 98.854899 | F31: =IFERROR((SUM(F9,F13)/SUM(F20,F23))*100,0) -> 127.85528 | G31: =IFERROR((SUM(G9,G13)/SUM(G20,G23))*100,0) -> 127.03043 | H31: =IFERROR((SUM(H9,H13)/SUM(H20,H23))*100,0) -> 125.39813 | I31: =IFERROR((SUM(I9,I13)/SUM(I20,I23))*100,0) -> 124.02656 | ... K31: =IFERROR((SUM(K9,K13)/SUM(K20,K23))*100,0) -> 121.74219
A32: 料金回収率（通常） | B32: =IFERROR(B10/B34*100,0) -> 92.822855 | C32: =IFERROR(C10/C34*100,0) -> 92.824907 | D32: =IFERROR(D10/D34*100,0) -> 91.98462 | E32: =IFERROR(E10/E34*100,0) -> 91.172206 | F32: =IFERROR(F10/F34*100,0) -> 108.20746 | G32: =IFERROR(G10/G34*100,0) -> 107.0042 | H32: =IFERROR(H10/H34*100,0) -> 105.48746 | I32: =IFERROR(I10/I34*100,0) -> 104.07468 | ... K32: =IFERROR(K10/K34*100,0) -> 101.63988
A33: 資産維持費込料金回収率 | B33: =IFERROR(B10/B35*100,0) -> 82.57802 | C33: =IFERROR(C10/C35*100,0) -> 82.487679 | D33: =IFERROR(D10/D35*100,0) -> 81.732255 | E33: =IFERROR(E10/E35*100,0) -> 80.999738 | F33: =IFERROR(F10/F35*100,0) -> 96.159205 | G33: =IFERROR(G10/G35*100,0) -> 95.101897 | H33: =IFERROR(H10/H35*100,0) -> 93.797859 | I33: =IFERROR(I10/I35*100,0) -> 92.576783 | ... K33: =IFERROR(K10/K35*100,0) -> 90.446594
A34: 給水原価対象費用 | B34: =SUM(B20,B23)-B14 -> 1326377 | C34: =SUM(C20,C23)-C14 -> 1313084 | D34: =SUM(D20,D23)-D14 -> 1311828 | E34: =SUM(E20,E23)-E14 -> 1310282 | F34: =SUM(F20,F23)-F14 -> 1313331 | G34: =SUM(G20,G23)-G14 -> 1314818 | H34: =SUM(H20,H23)-H14 -> 1320385 | I34: =SUM(I20,I23)-I14 -> 1324925 | ... K34: =SUM(K20,K23)-K14 -> 1329665
A35: 給水原価対象費用＋資産維持費 | B35: =B34+$B$5 -> 1490930.6 | C35: =C34+$B$5 -> 1477637.6 | D35: =D34+$B$5 -> 1476381.6 | E35: =E34+$B$5 -> 1474835.6 | F35: =F34+$B$5 -> 1477884.6 | G35: =G34+$B$5 -> 1479371.6 | H35: =H34+$B$5 -> 1484938.6 | I35: =I34+$B$5 -> 1489478.6 | ... K35: =K34+$B$5 -> 1494218.6
A36: 総括原価回収率（参考） | B36: =IFERROR(B10/(B20+B23-B14-B12-B15+$B$5)*100,0) -> 88.749524 | C36: =IFERROR(C10/(C20+C23-C14-C12-C15+$B$5)*100,0) -> 88.579718 | D36: =IFERROR(D10/(D20+D23-D14-D12-D15+$B$5)*100,0) -> 87.642943 | E36: =IFERROR(E10/(E20+E23-E14-E12-E15+$B$5)*100,0) -> 86.733616 | F36: =IFERROR(F10/(F20+F23-F14-F12-F15+$B$5)*100,0) -> 102.79464 | G36: =IFERROR(G10/(G20+G23-G14-G12-G15+$B$5)*100,0) -> 101.49847 | H36: =IFERROR(H10/(H20+H23-H14-H12-H15+$B$5)*100,0) -> 99.932128 | I36: =IFERROR(I10/(I20+I23-I14-I12-I15+$B$5)*100,0) -> 98.477448 | ... K36: =IFERROR(K10/(K20+K23-K14-K12-K15+$B$5)*100,0) -> 95.973172
A37: 検証：資産維持費込<=通常 | B37: =IF(B33<=B32,"OK","要確認") -> OK | C37: =IF(C33<=C32,"OK","要確認") -> OK | D37: =IF(D33<=D32,"OK","要確認") -> OK | E37: =IF(E33<=E32,"OK","要確認") -> OK | F37: =IF(F33<=F32,"OK","要確認") -> OK | G37: =IF(G33<=G32,"OK","要確認") -> OK | H37: =IF(H33<=H32,"OK","要確認") -> OK | I37: =IF(I33<=I32,"OK","要確認") -> OK | ... K37: =IF(K33<=K32,"OK","要確認") -> OK
A39: 【資本的収入】
A40: 資本的収入 | B40: =01_ビジョン原計画!B34 -> 698941 | C40: =01_ビジョン原計画!C34 -> 664331 | D40: =01_ビジョン原計画!D34 -> 636408 | E40: =01_ビジョン原計画!E34 -> 715698 | F40: =01_ビジョン原計画!F34 -> 627649 | G40: =01_ビジョン原計画!G34 -> 570213 | H40: =01_ビジョン原計画!H34 -> 571338 | I40: =01_ビジョン原計画!I34 -> 536592 | ... K40: =01_ビジョン原計画!K34 -> 365000
A41: 企業債 | B41: =01_ビジョン原計画!B35 -> 329000 | C41: =01_ビジョン原計画!C35 -> 435000 | D41: =01_ビジョン原計画!D35 -> 399000 | E41: =01_ビジョン原計画!E35 -> 400000 | F41: =01_ビジョン原計画!F35 -> 232000 | G41: =01_ビジョン原計画!G35 -> 283000 | H41: =01_ビジョン原計画!H35 -> 286000 | I41: =01_ビジョン原計画!I35 -> 368000 | ... K41: =01_ビジョン原計画!K35 -> 230000
A42: 一般会計負担金 | B42: =01_ビジョン原計画!B36 -> 169041 | C42: =01_ビジョン原計画!C36 -> 164831 | D42: =01_ビジョン原計画!D36 -> 162408 | E42: =01_ビジョン原計画!E36 -> 167998 | F42: =01_ビジョン原計画!F36 -> 173649 | G42: =01_ビジョン原計画!G36 -> 182213 | H42: =01_ビジョン原計画!H36 -> 180338 | I42: =01_ビジョン原計画!I36 -> 168592 | ... K42: =01_ビジョン原計画!K36 -> 135000
A43: 一般会計出資金 | B43: =01_ビジョン原計画!B37 -> 0 | C43: =01_ビジョン原計画!C37 -> 0 | D43: =01_ビジョン原計画!D37 -> 0 | E43: =01_ビジョン原計画!E37 -> 0 | F43: =01_ビジョン原計画!F37 -> 0 | G43: =01_ビジョン原計画!G37 -> 0 | H43: =01_ビジョン原計画!H37 -> 0 | I43: =01_ビジョン原計画!I37 -> 0 | ... K43: =01_ビジョン原計画!K37 -> 0
A44: 国庫補助金 | B44: =01_ビジョン原計画!B38 -> 0 | C44: =01_ビジョン原計画!C38 -> 64500 | D44: =01_ビジョン原計画!D38 -> 75000 | E44: =01_ビジョン原計画!E38 -> 147700 | F44: =01_ビジョン原計画!F38 -> 222000 | G44: =01_ビジョン原計画!G38 -> 105000 | H44: =01_ビジョン原計画!H38 -> 105000 | I44: =01_ビジョン原計画!I38 -> 0 | ... K44: =01_ビジョン原計画!K38 -> 0
A45: 固定資産売却代金 | B45: =01_ビジョン原計画!B39 -> 0 | C45: =01_ビジョン原計画!C39 -> 0 | D45: =01_ビジョン原計画!D39 -> 0 | E45: =01_ビジョン原計画!E39 -> 0 | F45: =01_ビジョン原計画!F39 -> 0 | G45: =01_ビジョン原計画!G39 -> 0 | H45: =01_ビジョン原計画!H39 -> 0 | I45: =01_ビジョン原計画!I39 -> 0 | ... K45: =01_ビジョン原計画!K39 -> 0
A46: 工事負担金 | B46: =01_ビジョン原計画!B40 -> 200900 | C46: =01_ビジョン原計画!C40 -> 0 | D46: =01_ビジョン原計画!D40 -> 0 | E46: =01_ビジョン原計画!E40 -> 0 | F46: =01_ビジョン原計画!F40 -> 0 | G46: =01_ビジョン原計画!G40 -> 0 | H46: =01_ビジョン原計画!H40 -> 0 | I46: =01_ビジョン原計画!I40 -> 0 | ... K46: =01_ビジョン原計画!K40 -> 0
A47: その他・調整 | B47: =01_ビジョン原計画!B41 -> 0 | C47: =01_ビジョン原計画!C41 -> 0 | D47: =01_ビジョン原計画!D41 -> 0 | E47: =01_ビジョン原計画!E41 -> 0 | F47: =01_ビジョン原計画!F41 -> 0 | G47: =01_ビジョン原計画!G41 -> 0 | H47: =01_ビジョン原計画!H41 -> 0 | I47: =01_ビジョン原計画!I41 -> 0 | ... K47: =01_ビジョン原計画!K41 -> 0
A49: 【資本的支出】
A50: 資本的支出 | B50: =01_ビジョン原計画!B44 -> 1412922 | C50: =01_ビジョン原計画!C44 -> 1320955 | D50: =01_ビジョン原計画!D44 -> 1228308 | E50: =01_ビジョン原計画!E44 -> 1249449 | F50: =01_ビジョン原計画!F44 -> 1123446 | G50: =01_ビジョン原計画!G44 -> 992222 | H50: =01_ビジョン原計画!H44 -> 982061 | I50: =01_ビジョン原計画!I44 -> 942741 | ... K50: =01_ビジョン原計画!K44 -> 789992
A51: 建設改良費 | B51: =01_ビジョン原計画!B45 -> 557893 | C51: =01_ビジョン原計画!C45 -> 525014 | D51: =01_ビジョン原計画!D45 -> 500489 | E51: =01_ビジョン原計画!E45 -> 576808 | F51: =01_ビジョン原計画!F45 -> 484835 | G51: =01_ビジョン原計画!G45 -> 415935 | H51: =01_ビジョン原計画!H45 -> 419465 | I51: =01_ビジョン原計画!I45 -> 395135 | ... K51: =01_ビジョン原計画!K45 -> 257135
A52: 企業債償還金 | B52: =01_ビジョン原計画!B46 -> 855029 | C52: =01_ビジョン原計画!C46 -> 795941 | D52: =01_ビジョン原計画!D46 -> 727819 | E52: =01_ビジョン原計画!E46 -> 672641 | F52: =01_ビジョン原計画!F46 -> 638611 | G52: =01_ビジョン原計画!G46 -> 576287 | H52: =01_ビジョン原計画!H46 -> 562596 | I52: =01_ビジョン原計画!I46 -> 547606 | ... K52: =01_ビジョン原計画!K46 -> 532857
A53: その他資本的支出 | B53: =01_ビジョン原計画!B47 -> 0 | C53: =01_ビジョン原計画!C47 -> 0 | D53: =01_ビジョン原計画!D47 -> 0 | E53: =01_ビジョン原計画!E47 -> 0 | F53: =01_ビジョン原計画!F47 -> 0 | G53: =01_ビジョン原計画!G47 -> 0 | H53: =01_ビジョン原計画!H47 -> 0 | I53: =01_ビジョン原計画!I47 -> 0 | ... K53: =01_ビジョン原計画!K47 -> 0
A54: 資本的収支不足額（収入－支出） | B54: =B40-B50 -> -713981 | C54: =C40-C50 -> -656624 | D54: =D40-D50 -> -591900 | E54: =E40-E50 -> -533751 | F54: =F40-F50 -> -495797 | G54: =G40-G50 -> -422009 | H54: =H40-H50 -> -410723 | I54: =I40-I50 -> -406149 | ... K54: =K40-K50 -> -424992
A56: 【現預金・4条財源】
A57: 補てん可能財源相当（簡便CF） | B57: =B28+B21+B22-B14 -> 484942 | C57: =C28+C21+C22-C14 -> 477901 | D57: =D28+D21+D22-D14 -> 466726 | E57: =E28+E21+E22-E14 -> 454037 | F57: =F28+F21+F22-F14 -> 918187.23 | G57: =G28+G21+G22-G14 -> 909858.98 | H57: =H28+H21+H22-H14 -> 893293.3 | I57: =I28+I21+I22-I14 -> 875963.8 | ... K57: =K28+K21+K22-K14 -> 842381.74
A58: 資本的収支不足額（再掲） | B58: =B54 -> -713981 | C58: =C54 -> -656624 | D58: =D54 -> -591900 | E58: =E54 -> -533751 | F58: =F54 -> -495797 | G58: =G54 -> -422009 | H58: =H54 -> -410723 | I58: =I54 -> -406149 | ... K58: =K54 -> -424992
A59: 年度末現預金残高 | B59: =00_前提・検証!$B$6 -> 242588 | C59: =B59+C57+C58 -> 63865 | D59: =C59+D57+D58 -> -61309 | E59: =D59+E57+E58 -> -141023 | F59: =E59+F57+F58 -> 281367.23 | G59: =F59+G57+G58 -> 769217.21 | H59: =G59+H57+H58 -> 1251787.5 | I59: =H59+I57+I58 -> 1721602.3 | J59: =I59+J57+J58 -> 2161107.4 | K59: =J59+K57+K58 -> 2578497.1
A60: 最低現金目安との差額 | B60: =B59-00_前提・検証!$B$7 -> -57412 | C60: =C59-00_前提・検証!$B$7 -> -236135 | D60: =D59-00_前提・検証!$B$7 -> -361309 | E60: =E59-00_前提・検証!$B$7 -> -441023 | F60: =F59-00_前提・検証!$B$7 -> -18632.765 | G60: =G59-00_前提・検証!$B$7 -> 469217.21 | H60: =H59-00_前提・検証!$B$7 -> 951787.51 | I60: =I59-00_前提・検証!$B$7 -> 1421602.3 | ... K60: =K59-00_前提・検証!$B$7 -> 2278497.1

Sheet SIM_ビジョン_2%
A1: SIM_ビジョン_2%
A2: 単位：千円、比率は％。料金改定率はR11〜R15の総括原価回収を基礎に算定し、R11以降の給水収益へ反映。
A3: 区分 | B3: 令和7年度 | C3: 令和8年度 | D3: 令和9年度 | E3: 令和10年度 | F3: 令和11年度 | G3: 令和12年度 | H3: 令和13年度 | I3: 令和14年度 | J3: 令和15年度 | K3: 令和16年度
A4: 資産維持費率 | B4: 0.02
A5: 年額資産維持費（千円） | B5: =00_前提・検証!$B$2*$B$4 -> 329107.28
A6: 料金改定率（R11以降・試算） | B6: =MAX(0,(SUMPRODUCT((01_ビジョン原計画!F18:J18+01_ビジョン原計画!F28:J28-01_ビジョン原計画!F12:J12-01_ビジョン原計画!F8:J8-01_ビジョン原計画!F11:J11+$B$5)-01_ビジョン原計画!F7:J7)/SUM(01_ビジョン原計画!F7:J7))) -> 0.34357465
A8: 【収益的収入】
A9: 営業収益 | B9: =SUM(B10:B12) -> 1261575 | C9: =SUM(C10:C12) -> 1249336 | D9: =SUM(D10:D12) -> 1237293 | E9: =SUM(E10:E12) -> 1225373 | F9: =SUM(F10:F12) -> 2026242.1 | G9: =SUM(G10:G12) -> 2006437.2 | H9: =SUM(H10:H12) -> 1986831.4 | I9: =SUM(I10:I12) -> 1967423.9 | ... K9: =SUM(K10:K12) -> 1929197.5
A10: 給水収益（改定反映後） | B10: =01_ビジョン原計画!B7*IF(7>=11,1+$B$6,1) -> 1231181 | C10: =01_ビジョン原計画!C7*IF(8>=11,1+$B$6,1) -> 1218869 | D10: =01_ビジョン原計画!D7*IF(9>=11,1+$B$6,1) -> 1206680 | E10: =01_ビジョン原計画!E7*IF(10>=11,1+$B$6,1) -> 1194613 | F10: =01_ビジョン原計画!F7*IF(11>=11,1+$B$6,1) -> 1589000.1 | G10: =01_ビジョン原計画!G7*IF(12>=11,1+$B$6,1) -> 1573109.6 | H10: =01_ビジョン原計画!H7*IF(13>=11,1+$B$6,1) -> 1557377.7 | I10: =01_ビジョン原計画!I7*IF(14>=11,1+$B$6,1) -> 1541803 | J10: =01_ビジョン原計画!J7*IF(15>=11,1+$B$6,1) -> 1526384.1 | K10: =01_ビジョン原計画!K7*IF(16>=11,1+$B$6,1) -> 1511119.8
A11: うち料金改定増収 | B11: =B10-01_ビジョン原計画!B7 -> 0 | C11: =C10-01_ビジョン原計画!C7 -> 0 | D11: =D10-01_ビジョン原計画!D7 -> 0 | E11: =E10-01_ビジョン原計画!E7 -> 0 | F11: =F10-01_ビジョン原計画!F7 -> 406334.05 | G11: =G10-01_ビジョン原計画!G7 -> 402270.6 | H11: =H10-01_ビジョン原計画!H7 -> 398247.68 | I11: =I10-01_ビジョン原計画!I7 -> 394264.96 | ... K11: =K10-01_ビジョン原計画!K7 -> 386418.75
A12: その他営業収益 | B12: =01_ビジョン原計画!B8 -> 30394 | C12: =01_ビジョン原計画!C8 -> 30467 | D12: =01_ビジョン原計画!D8 -> 30613 | E12: =01_ビジョン原計画!E8 -> 30760 | F12: =01_ビジョン原計画!F8 -> 30908 | G12: =01_ビジョン原計画!G8 -> 31057 | H12: =01_ビジョン原計画!H8 -> 31206 | I12: =01_ビジョン原計画!I8 -> 31356 | ... K12: =01_ビジョン原計画!K8 -> 31659
A13: 営業外収益 | B13: =01_ビジョン原計画!B9 -> 354909 | C13: =01_ビジョン原計画!C9 -> 355137 | D13: =01_ビジョン原計画!D9 -> 348767 | E13: =01_ビジョン原計画!E9 -> 343130 | F13: =01_ビジョン原計画!F9 -> 336658 | G13: =01_ビジョン原計画!G9 -> 342879 | H13: =01_ビジョン原計画!H9 -> 342324 | I13: =01_ビジョン原計画!I9 -> 332258 | ... K13: =01_ビジョン原計画!K9 -> 307297
A14: 長期前受金戻入 | B14: =01_ビジョン原計画!B12 -> 281625 | C14: =01_ビジョン原計画!C12 -> 283979 | D14: =01_ビジョン原計画!D12 -> 279812 | E14: =01_ビジョン原計画!E12 -> 276390 | F14: =01_ビジョン原計画!F12 -> 272168 | G14: =01_ビジョン原計画!G12 -> 272926 | H14: =01_ビジョン原計画!H12 -> 274600 | I14: =01_ビジョン原計画!I12 -> 266588 | ... K14: =01_ビジョン原計画!K12 -> 245134
A15: 繰入金・負担金等 | B15: =01_ビジョン原計画!B11 -> 73283 | C15: =01_ビジョン原計画!C11 -> 71157 | D15: =01_ビジョン原計画!D11 -> 68955 | E15: =01_ビジョン原計画!E11 -> 66740 | F15: =01_ビジョン原計画!F11 -> 64490 | G15: =01_ビジョン原計画!G11 -> 62175 | H15: =01_ビジョン原計画!H11 -> 59946 | I15: =01_ビジョン原計画!I11 -> 57892 | ... K15: =01_ビジョン原計画!K11 -> 54385
A16: 特別利益 | B16: =01_ビジョン原計画!B14 -> 2576 | C16: =01_ビジョン原計画!C14 -> 0 | D16: =01_ビジョン原計画!D14 -> 0 | E16: =01_ビジョン原計画!E14 -> 0 | F16: =01_ビジョン原計画!F14 -> 0 | G16: =01_ビジョン原計画!G14 -> 0 | H16: =01_ビジョン原計画!H14 -> 0 | I16: =01_ビジョン原計画!I14 -> 0 | ... K16: =01_ビジョン原計画!K14 -> 0
A17: 収益的収入合計 | B17: =SUM(B9,B13,B16) -> 1619060 | C17: =SUM(C9,C13,C16) -> 1604473 | D17: =SUM(D9,D13,D16) -> 1586060 | E17: =SUM(E9,E13,E16) -> 1568503 | F17: =SUM(F9,F13,F16) -> 2362900.1 | G17: =SUM(G9,G13,G16) -> 2349316.2 | H17: =SUM(H9,H13,H16) -> 2329155.4 | I17: =SUM(I9,I13,I16) -> 2299681.9 | ... K17: =SUM(K9,K13,K16) -> 2236494.5
A19: 【収益的支出】
A20: 営業費用 | B20: =01_ビジョン原計画!B18 -> 1479507 | C20: =01_ビジョン原計画!C18 -> 1476545 | D20: =01_ビジョン原計画!D18 -> 1474501 | E20: =01_ビジョン原計画!E18 -> 1471288 | F20: =01_ビジョン原計画!F18 -> 1471712 | G20: =01_ビジョン原計画!G18 -> 1476923 | H20: =01_ビジョン原計画!H18 -> 1486420 | I20: =01_ビジョン原計画!I18 -> 1484101 | ... K20: =01_ビジョン原計画!K18 -> 1469682
A21: 減価償却費 | B21: =01_ビジョン原計画!B25 -> 755782 | C21: =01_ビジョン原計画!C25 -> 754743 | D21: =01_ビジョン原計画!D25 -> 752391 | E21: =01_ビジョン原計画!E25 -> 748869 | F21: =01_ビジョン原計画!F25 -> 748983 | G21: =01_ビジョン原計画!G25 -> 753884 | H21: =01_ビジョン原計画!H25 -> 763070 | I21: =01_ビジョン原計画!I25 -> 760439 | ... K21: =01_ビジョン原計画!K25 -> 745393
A22: 資産減耗・除却費 | B22: =01_ビジョン原計画!B26 -> 0 | C22: =01_ビジョン原計画!C26 -> 0 | D22: =01_ビジョン原計画!D26 -> 0 | E22: =01_ビジョン原計画!E26 -> 0 | F22: =01_ビジョン原計画!F26 -> 0 | G22: =01_ビジョン原計画!G26 -> 0 | H22: =01_ビジョン原計画!H26 -> 0 | I22: =01_ビジョン原計画!I26 -> 0 | ... K22: =01_ビジョン原計画!K26 -> 0
A23: 営業外費用 | B23: =01_ビジョン原計画!B28 -> 128495 | C23: =01_ビジョン原計画!C28 -> 120518 | D23: =01_ビジョン原計画!D28 -> 117139 | E23: =01_ビジョン原計画!E28 -> 115384 | F23: =01_ビジョン原計画!F28 -> 113787 | G23: =01_ビジョン原計画!G28 -> 110821 | H23: =01_ビジョン原計画!H28 -> 108565 | I23: =01_ビジョン原計画!I28 -> 107412 | ... K23: =01_ビジョン原計画!K28 -> 105117
A24: 支払利息 | B24: =01_ビジョン原計画!B29 -> 118910 | C24: =01_ビジョン原計画!C29 -> 111872 | D24: =01_ビジョン原計画!D29 -> 108458 | E24: =01_ビジョン原計画!E29 -> 106668 | F24: =01_ビジョン原計画!F29 -> 105071 | G24: =01_ビジョン原計画!G29 -> 102070 | H24: =01_ビジョン原計画!H29 -> 99779 | I24: =01_ビジョン原計画!I29 -> 98626 | ... K24: =01_ビジョン原計画!K29 -> 96331
A25: 特別損失 | B25: =01_ビジョン原計画!B31 -> 273 | C25: =01_ビジョン原計画!C31 -> 273 | D25: =01_ビジョン原計画!D31 -> 273 | E25: =01_ビジョン原計画!E31 -> 273 | F25: =01_ビジョン原計画!F31 -> 273 | G25: =01_ビジョン原計画!G31 -> 273 | H25: =01_ビジョン原計画!H31 -> 273 | I25: =01_ビジョン原計画!I31 -> 273 | ... K25: =01_ビジョン原計画!K31 -> 273
A26: 収益的支出合計 | B26: =SUM(B20,B23,B25) -> 1608275 | C26: =SUM(C20,C23,C25) -> 1597336 | D26: =SUM(D20,D23,D25) -> 1591913 | E26: =SUM(E20,E23,E25) -> 1586945 | F26: =SUM(F20,F23,F25) -> 1585772 | G26: =SUM(G20,G23,G25) -> 1588017 | H26: =SUM(H20,H23,H25) -> 1595258 | I26: =SUM(I20,I23,I25) -> 1591786 | ... K26: =SUM(K20,K23,K25) -> 1575072
A27: 経常損益 | B27: =SUM(B9,B13)-SUM(B20,B23) -> 8482 | C27: =SUM(C9,C13)-SUM(C20,C23) -> 7410 | D27: =SUM(D9,D13)-SUM(D20,D23) -> -5580 | E27: =SUM(E9,E13)-SUM(E20,E23) -> -18169 | F27: =SUM(F9,F13)-SUM(F20,F23) -> 777401.11 | G27: =SUM(G9,G13)-SUM(G20,G23) -> 761572.19 | H27: =SUM(H9,H13)-SUM(H20,H23) -> 734170.36 | I27: =SUM(I9,I13)-SUM(I20,I23) -> 708168.93 | ... K27: =SUM(K9,K13)-SUM(K20,K23) -> 661695.5
A28: 純損益 | B28: =B27+B16-B25 -> 10785 | C28: =C27+C16-C25 -> 7137 | D28: =D27+D16-D25 -> -5853 | E28: =E27+E16-E25 -> -18442 | F28: =F27+F16-F25 -> 777128.11 | G28: =G27+G16-G25 -> 761299.19 | H28: =H27+H16-H25 -> 733897.36 | I28: =I27+I16-I25 -> 707895.93 | ... K28: =K27+K16-K25 -> 661422.5
A30: 【経営指標】
A31: 経常収支比率 | B31: =IFERROR((SUM(B9,B13)/SUM(B20,B23))*100,0) -> 100.52749 | C31: =IFERROR((SUM(C9,C13)/SUM(C20,C23))*100,0) -> 100.46398 | D31: =IFERROR((SUM(D9,D13)/SUM(D20,D23))*100,0) -> 99.649418 | E31: =IFERROR((SUM(E9,E13)/SUM(E20,E23))*100,0) -> 98.854899 | F31: =IFERROR((SUM(F9,F13)/SUM(F20,F23))*100,0) -> 149.03195 | G31: =IFERROR((SUM(G9,G13)/SUM(G20,G23))*100,0) -> 147.96568 | H31: =IFERROR((SUM(H9,H13)/SUM(H20,H23))*100,0) -> 146.02992 | I31: =IFERROR((SUM(I9,I13)/SUM(I20,I23))*100,0) -> 144.49658 | ... K31: =IFERROR((SUM(K9,K13)/SUM(K20,K23))*100,0) -> 142.01777
A32: 料金回収率（通常） | B32: =IFERROR(B10/B34*100,0) -> 92.822855 | C32: =IFERROR(C10/C34*100,0) -> 92.824907 | D32: =IFERROR(D10/D34*100,0) -> 91.98462 | E32: =IFERROR(E10/E34*100,0) -> 91.172206 | F32: =IFERROR(F10/F34*100,0) -> 120.99007 | G32: =IFERROR(G10/G34*100,0) -> 119.64467 | H32: =IFERROR(H10/H34*100,0) -> 117.94876 | I32: =IFERROR(I10/I34*100,0) -> 116.36907 | ... K32: =IFERROR(K10/K34*100,0) -> 113.64665
A33: 資産維持費込料金回収率 | B33: =IFERROR(B10/B35*100,0) -> 74.369839 | C33: =IFERROR(C10/C35*100,0) -> 74.222109 | D33: =IFERROR(D10/D35*100,0) -> 73.536112 | E33: =IFERROR(E10/E35*100,0) -> 72.869392 | F33: =IFERROR(F10/F35*100,0) -> 96.746409 | G33: =IFERROR(G10/G35*100,0) -> 95.692281 | H33: =IFERROR(H10/H35*100,0) -> 94.415579 | I33: =IFERROR(I10/I35*100,0) -> 93.214805 | ... K33: =IFERROR(K10/K35*100,0) -> 91.098686
A34: 給水原価対象費用 | B34: =SUM(B20,B23)-B14 -> 1326377 | C34: =SUM(C20,C23)-C14 -> 1313084 | D34: =SUM(D20,D23)-D14 -> 1311828 | E34: =SUM(E20,E23)-E14 -> 1310282 | F34: =SUM(F20,F23)-F14 -> 1313331 | G34: =SUM(G20,G23)-G14 -> 1314818 | H34: =SUM(H20,H23)-H14 -> 1320385 | I34: =SUM(I20,I23)-I14 -> 1324925 | ... K34: =SUM(K20,K23)-K14 -> 1329665
A35: 給水原価対象費用＋資産維持費 | B35: =B34+$B$5 -> 1655484.3 | C35: =C34+$B$5 -> 1642191.3 | D35: =D34+$B$5 -> 1640935.3 | E35: =E34+$B$5 -> 1639389.3 | F35: =F34+$B$5 -> 1642438.3 | G35: =G34+$B$5 -> 1643925.3 | H35: =H34+$B$5 -> 1649492.3 | I35: =I34+$B$5 -> 1654032.3 | ... K35: =K34+$B$5 -> 1658772.3
A36: 総括原価回収率（参考） | B36: =IFERROR(B10/(B20+B23-B14-B12-B15+$B$5)*100,0) -> 79.338525 | C36: =IFERROR(C10/(C20+C23-C14-C12-C15+$B$5)*100,0) -> 79.118193 | D36: =IFERROR(D10/(D20+D23-D14-D12-D15+$B$5)*100,0) -> 78.286338 | E36: =IFERROR(E10/(E20+E23-E14-E12-E15+$B$5)*100,0) -> 77.477223 | F36: =IFERROR(F10/(F20+F23-F14-F12-F15+$B$5)*100,0) -> 102.71226 | G36: =IFERROR(G10/(G20+G23-G14-G12-G15+$B$5)*100,0) -> 101.44557 | H36: =IFERROR(H10/(H20+H23-H14-H12-H15+$B$5)*100,0) -> 99.938229 | I36: =IFERROR(I10/(I20+I23-I14-I12-I15+$B$5)*100,0) -> 98.531343 | ... K36: =IFERROR(K10/(K20+K23-K14-K12-K15+$B$5)*100,0) -> 96.082697
A37: 検証：資産維持費込<=通常 | B37: =IF(B33<=B32,"OK","要確認") -> OK | C37: =IF(C33<=C32,"OK","要確認") -> OK | D37: =IF(D33<=D32,"OK","要確認") -> OK | E37: =IF(E33<=E32,"OK","要確認") -> OK | F37: =IF(F33<=F32,"OK","要確認") -> OK | G37: =IF(G33<=G32,"OK","要確認") -> OK | H37: =IF(H33<=H32,"OK","要確認") -> OK | I37: =IF(I33<=I32,"OK","要確認") -> OK | ... K37: =IF(K33<=K32,"OK","要確認") -> OK
A39: 【資本的収入】
A40: 資本的収入 | B40: =01_ビジョン原計画!B34 -> 698941 | C40: =01_ビジョン原計画!C34 -> 664331 | D40: =01_ビジョン原計画!D34 -> 636408 | E40: =01_ビジョン原計画!E34 -> 715698 | F40: =01_ビジョン原計画!F34 -> 627649 | G40: =01_ビジョン原計画!G34 -> 570213 | H40: =01_ビジョン原計画!H34 -> 571338 | I40: =01_ビジョン原計画!I34 -> 536592 | ... K40: =01_ビジョン原計画!K34 -> 365000
A41: 企業債 | B41: =01_ビジョン原計画!B35 -> 329000 | C41: =01_ビジョン原計画!C35 -> 435000 | D41: =01_ビジョン原計画!D35 -> 399000 | E41: =01_ビジョン原計画!E35 -> 400000 | F41: =01_ビジョン原計画!F35 -> 232000 | G41: =01_ビジョン原計画!G35 -> 283000 | H41: =01_ビジョン原計画!H35 -> 286000 | I41: =01_ビジョン原計画!I35 -> 368000 | ... K41: =01_ビジョン原計画!K35 -> 230000
A42: 一般会計負担金 | B42: =01_ビジョン原計画!B36 -> 169041 | C42: =01_ビジョン原計画!C36 -> 164831 | D42: =01_ビジョン原計画!D36 -> 162408 | E42: =01_ビジョン原計画!E36 -> 167998 | F42: =01_ビジョン原計画!F36 -> 173649 | G42: =01_ビジョン原計画!G36 -> 182213 | H42: =01_ビジョン原計画!H36 -> 180338 | I42: =01_ビジョン原計画!I36 -> 168592 | ... K42: =01_ビジョン原計画!K36 -> 135000
A43: 一般会計出資金 | B43: =01_ビジョン原計画!B37 -> 0 | C43: =01_ビジョン原計画!C37 -> 0 | D43: =01_ビジョン原計画!D37 -> 0 | E43: =01_ビジョン原計画!E37 -> 0 | F43: =01_ビジョン原計画!F37 -> 0 | G43: =01_ビジョン原計画!G37 -> 0 | H43: =01_ビジョン原計画!H37 -> 0 | I43: =01_ビジョン原計画!I37 -> 0 | ... K43: =01_ビジョン原計画!K37 -> 0
A44: 国庫補助金 | B44: =01_ビジョン原計画!B38 -> 0 | C44: =01_ビジョン原計画!C38 -> 64500 | D44: =01_ビジョン原計画!D38 -> 75000 | E44: =01_ビジョン原計画!E38 -> 147700 | F44: =01_ビジョン原計画!F38 -> 222000 | G44: =01_ビジョン原計画!G38 -> 105000 | H44: =01_ビジョン原計画!H38 -> 105000 | I44: =01_ビジョン原計画!I38 -> 0 | ... K44: =01_ビジョン原計画!K38 -> 0
A45: 固定資産売却代金 | B45: =01_ビジョン原計画!B39 -> 0 | C45: =01_ビジョン原計画!C39 -> 0 | D45: =01_ビジョン原計画!D39 -> 0 | E45: =01_ビジョン原計画!E39 -> 0 | F45: =01_ビジョン原計画!F39 -> 0 | G45: =01_ビジョン原計画!G39 -> 0 | H45: =01_ビジョン原計画!H39 -> 0 | I45: =01_ビジョン原計画!I39 -> 0 | ... K45: =01_ビジョン原計画!K39 -> 0
A46: 工事負担金 | B46: =01_ビジョン原計画!B40 -> 200900 | C46: =01_ビジョン原計画!C40 -> 0 | D46: =01_ビジョン原計画!D40 -> 0 | E46: =01_ビジョン原計画!E40 -> 0 | F46: =01_ビジョン原計画!F40 -> 0 | G46: =01_ビジョン原計画!G40 -> 0 | H46: =01_ビジョン原計画!H40 -> 0 | I46: =01_ビジョン原計画!I40 -> 0 | ... K46: =01_ビジョン原計画!K40 -> 0
A47: その他・調整 | B47: =01_ビジョン原計画!B41 -> 0 | C47: =01_ビジョン原計画!C41 -> 0 | D47: =01_ビジョン原計画!D41 -> 0 | E47: =01_ビジョン原計画!E41 -> 0 | F47: =01_ビジョン原計画!F41 -> 0 | G47: =01_ビジョン原計画!G41 -> 0 | H47: =01_ビジョン原計画!H41 -> 0 | I47: =01_ビジョン原計画!I41 -> 0 | ... K47: =01_ビジョン原計画!K41 -> 0
A49: 【資本的支出】
A50: 資本的支出 | B50: =01_ビジョン原計画!B44 -> 1412922 | C50: =01_ビジョン原計画!C44 -> 1320955 | D50: =01_ビジョン原計画!D44 -> 1228308 | E50: =01_ビジョン原計画!E44 -> 1249449 | F50: =01_ビジョン原計画!F44 -> 1123446 | G50: =01_ビジョン原計画!G44 -> 992222 | H50: =01_ビジョン原計画!H44 -> 982061 | I50: =01_ビジョン原計画!I44 -> 942741 | ... K50: =01_ビジョン原計画!K44 -> 789992
A51: 建設改良費 | B51: =01_ビジョン原計画!B45 -> 557893 | C51: =01_ビジョン原計画!C45 -> 525014 | D51: =01_ビジョン原計画!D45 -> 500489 | E51: =01_ビジョン原計画!E45 -> 576808 | F51: =01_ビジョン原計画!F45 -> 484835 | G51: =01_ビジョン原計画!G45 -> 415935 | H51: =01_ビジョン原計画!H45 -> 419465 | I51: =01_ビジョン原計画!I45 -> 395135 | ... K51: =01_ビジョン原計画!K45 -> 257135
A52: 企業債償還金 | B52: =01_ビジョン原計画!B46 -> 855029 | C52: =01_ビジョン原計画!C46 -> 795941 | D52: =01_ビジョン原計画!D46 -> 727819 | E52: =01_ビジョン原計画!E46 -> 672641 | F52: =01_ビジョン原計画!F46 -> 638611 | G52: =01_ビジョン原計画!G46 -> 576287 | H52: =01_ビジョン原計画!H46 -> 562596 | I52: =01_ビジョン原計画!I46 -> 547606 | ... K52: =01_ビジョン原計画!K46 -> 532857
A53: その他資本的支出 | B53: =01_ビジョン原計画!B47 -> 0 | C53: =01_ビジョン原計画!C47 -> 0 | D53: =01_ビジョン原計画!D47 -> 0 | E53: =01_ビジョン原計画!E47 -> 0 | F53: =01_ビジョン原計画!F47 -> 0 | G53: =01_ビジョン原計画!G47 -> 0 | H53: =01_ビジョン原計画!H47 -> 0 | I53: =01_ビジョン原計画!I47 -> 0 | ... K53: =01_ビジョン原計画!K47 -> 0
A54: 資本的収支不足額（収入－支出） | B54: =B40-B50 -> -713981 | C54: =C40-C50 -> -656624 | D54: =D40-D50 -> -591900 | E54: =E40-E50 -> -533751 | F54: =F40-F50 -> -495797 | G54: =G40-G50 -> -422009 | H54: =H40-H50 -> -410723 | I54: =I40-I50 -> -406149 | ... K54: =K40-K50 -> -424992
A56: 【現預金・4条財源】
A57: 補てん可能財源相当（簡便CF） | B57: =B28+B21+B22-B14 -> 484942 | C57: =C28+C21+C22-C14 -> 477901 | D57: =D28+D21+D22-D14 -> 466726 | E57: =E28+E21+E22-E14 -> 454037 | F57: =F28+F21+F22-F14 -> 1253943.1 | G57: =G28+G21+G22-G14 -> 1242257.2 | H57: =H28+H21+H22-H14 -> 1222367.4 | I57: =I28+I21+I22-I14 -> 1201746.9 | ... K57: =K28+K21+K22-K14 -> 1161681.5
A58: 資本的収支不足額（再掲） | B58: =B54 -> -713981 | C58: =C54 -> -656624 | D58: =D54 -> -591900 | E58: =E54 -> -533751 | F58: =F54 -> -495797 | G58: =G54 -> -422009 | H58: =H54 -> -410723 | I58: =I54 -> -406149 | ... K58: =K54 -> -424992
A59: 年度末現預金残高 | B59: =00_前提・検証!$B$6 -> 242588 | C59: =B59+C57+C58 -> 63865 | D59: =C59+D57+D58 -> -61309 | E59: =D59+E57+E58 -> -141023 | F59: =E59+F57+F58 -> 617123.11 | G59: =F59+G57+G58 -> 1437371.3 | H59: =G59+H57+H58 -> 2249015.7 | I59: =H59+I57+I58 -> 3044613.6 | J59: =I59+J57+J58 -> 3806643.8 | K59: =J59+K57+K58 -> 4543333.3
A60: 最低現金目安との差額 | B60: =B59-00_前提・検証!$B$7 -> -57412 | C60: =C59-00_前提・検証!$B$7 -> -236135 | D60: =D59-00_前提・検証!$B$7 -> -361309 | E60: =E59-00_前提・検証!$B$7 -> -441023 | F60: =F59-00_前提・検証!$B$7 -> 317123.11 | G60: =G59-00_前提・検証!$B$7 -> 1137371.3 | H60: =H59-00_前提・検証!$B$7 -> 1949015.7 | I60: =I59-00_前提・検証!$B$7 -> 2744613.6 | ... K60: =K59-00_前提・検証!$B$7 -> 4243333.3

Sheet SIM_ビジョン_3%
A1: SIM_ビジョン_3%
A2: 単位：千円、比率は％。料金改定率はR11〜R15の総括原価回収を基礎に算定し、R11以降の給水収益へ反映。
A3: 区分 | B3: 令和7年度 | C3: 令和8年度 | D3: 令和9年度 | E3: 令和10年度 | F3: 令和11年度 | G3: 令和12年度 | H3: 令和13年度 | I3: 令和14年度 | J3: 令和15年度 | K3: 令和16年度
A4: 資産維持費率 | B4: 0.03
A5: 年額資産維持費（千円） | B5: =00_前提・検証!$B$2*$B$4 -> 493660.92
A6: 料金改定率（R11以降・試算） | B6: =MAX(0,(SUMPRODUCT((01_ビジョン原計画!F18:J18+01_ビジョン原計画!F28:J28-01_ビジョン原計画!F12:J12-01_ビジョン原計画!F8:J8-01_ビジョン原計画!F11:J11+$B$5)-01_ビジョン原計画!F7:J7)/SUM(01_ビジョン原計画!F7:J7))) -> 0.48552338
A8: 【収益的収入】
A9: 営業収益 | B9: =SUM(B10:B12) -> 1261575 | C9: =SUM(C10:C12) -> 1249336 | D9: =SUM(D10:D12) -> 1237293 | E9: =SUM(E10:E12) -> 1225373 | F9: =SUM(F10:F12) -> 2361998 | G9: =SUM(G10:G12) -> 2338835.4 | H9: =SUM(H10:H12) -> 2315905.4 | I9: =SUM(I10:I12) -> 2293207.1 | ... K9: =SUM(K10:K12) -> 2248497.3
A10: 給水収益（改定反映後） | B10: =01_ビジョン原計画!B7*IF(7>=11,1+$B$6,1) -> 1231181 | C10: =01_ビジョン原計画!C7*IF(8>=11,1+$B$6,1) -> 1218869 | D10: =01_ビジョン原計画!D7*IF(9>=11,1+$B$6,1) -> 1206680 | E10: =01_ビジョン原計画!E7*IF(10>=11,1+$B$6,1) -> 1194613 | F10: =01_ビジョン原計画!F7*IF(11>=11,1+$B$6,1) -> 1756878 | G10: =01_ビジョン原計画!G7*IF(12>=11,1+$B$6,1) -> 1739308.7 | H10: =01_ビジョン原計画!H7*IF(13>=11,1+$B$6,1) -> 1721914.7 | I10: =01_ビジョン原計画!I7*IF(14>=11,1+$B$6,1) -> 1704694.5 | J10: =01_ビジョン原計画!J7*IF(15>=11,1+$B$6,1) -> 1687646.7 | K10: =01_ビジョン原計画!K7*IF(16>=11,1+$B$6,1) -> 1670769.6
A11: うち料金改定増収 | B11: =B10-01_ビジョン原計画!B7 -> 0 | C11: =C10-01_ビジョン原計画!C7 -> 0 | D11: =D10-01_ビジョン原計画!D7 -> 0 | E11: =E10-01_ビジョン原計画!E7 -> 0 | F11: =F10-01_ビジョン原計画!F7 -> 574211.99 | G11: =G10-01_ビジョン原計画!G7 -> 568469.71 | H11: =H10-01_ビジョン原計画!H7 -> 562784.71 | I11: =I10-01_ビジョン原計画!I7 -> 557156.53 | ... K11: =K10-01_ビジョン原計画!K7 -> 546068.63
A12: その他営業収益 | B12: =01_ビジョン原計画!B8 -> 30394 | C12: =01_ビジョン原計画!C8 -> 30467 | D12: =01_ビジョン原計画!D8 -> 30613 | E12: =01_ビジョン原計画!E8 -> 30760 | F12: =01_ビジョン原計画!F8 -> 30908 | G12: =01_ビジョン原計画!G8 -> 31057 | H12: =01_ビジョン原計画!H8 -> 31206 | I12: =01_ビジョン原計画!I8 -> 31356 | ... K12: =01_ビジョン原計画!K8 -> 31659
A13: 営業外収益 | B13: =01_ビジョン原計画!B9 -> 354909 | C13: =01_ビジョン原計画!C9 -> 355137 | D13: =01_ビジョン原計画!D9 -> 348767 | E13: =01_ビジョン原計画!E9 -> 343130 | F13: =01_ビジョン原計画!F9 -> 336658 | G13: =01_ビジョン原計画!G9 -> 342879 | H13: =01_ビジョン原計画!H9 -> 342324 | I13: =01_ビジョン原計画!I9 -> 332258 | ... K13: =01_ビジョン原計画!K9 -> 307297
A14: 長期前受金戻入 | B14: =01_ビジョン原計画!B12 -> 281625 | C14: =01_ビジョン原計画!C12 -> 283979 | D14: =01_ビジョン原計画!D12 -> 279812 | E14: =01_ビジョン原計画!E12 -> 276390 | F14: =01_ビジョン原計画!F12 -> 272168 | G14: =01_ビジョン原計画!G12 -> 272926 | H14: =01_ビジョン原計画!H12 -> 274600 | I14: =01_ビジョン原計画!I12 -> 266588 | ... K14: =01_ビジョン原計画!K12 -> 245134
A15: 繰入金・負担金等 | B15: =01_ビジョン原計画!B11 -> 73283 | C15: =01_ビジョン原計画!C11 -> 71157 | D15: =01_ビジョン原計画!D11 -> 68955 | E15: =01_ビジョン原計画!E11 -> 66740 | F15: =01_ビジョン原計画!F11 -> 64490 | G15: =01_ビジョン原計画!G11 -> 62175 | H15: =01_ビジョン原計画!H11 -> 59946 | I15: =01_ビジョン原計画!I11 -> 57892 | ... K15: =01_ビジョン原計画!K11 -> 54385
A16: 特別利益 | B16: =01_ビジョン原計画!B14 -> 2576 | C16: =01_ビジョン原計画!C14 -> 0 | D16: =01_ビジョン原計画!D14 -> 0 | E16: =01_ビジョン原計画!E14 -> 0 | F16: =01_ビジョン原計画!F14 -> 0 | G16: =01_ビジョン原計画!G14 -> 0 | H16: =01_ビジョン原計画!H14 -> 0 | I16: =01_ビジョン原計画!I14 -> 0 | ... K16: =01_ビジョン原計画!K14 -> 0
A17: 収益的収入合計 | B17: =SUM(B9,B13,B16) -> 1619060 | C17: =SUM(C9,C13,C16) -> 1604473 | D17: =SUM(D9,D13,D16) -> 1586060 | E17: =SUM(E9,E13,E16) -> 1568503 | F17: =SUM(F9,F13,F16) -> 2698656 | G17: =SUM(G9,G13,G16) -> 2681714.4 | H17: =SUM(H9,H13,H16) -> 2658229.4 | I17: =SUM(I9,I13,I16) -> 2625465.1 | ... K17: =SUM(K9,K13,K16) -> 2555794.3
A19: 【収益的支出】
A20: 営業費用 | B20: =01_ビジョン原計画!B18 -> 1479507 | C20: =01_ビジョン原計画!C18 -> 1476545 | D20: =01_ビジョン原計画!D18 -> 1474501 | E20: =01_ビジョン原計画!E18 -> 1471288 | F20: =01_ビジョン原計画!F18 -> 1471712 | G20: =01_ビジョン原計画!G18 -> 1476923 | H20: =01_ビジョン原計画!H18 -> 1486420 | I20: =01_ビジョン原計画!I18 -> 1484101 | ... K20: =01_ビジョン原計画!K18 -> 1469682
A21: 減価償却費 | B21: =01_ビジョン原計画!B25 -> 755782 | C21: =01_ビジョン原計画!C25 -> 754743 | D21: =01_ビジョン原計画!D25 -> 752391 | E21: =01_ビジョン原計画!E25 -> 748869 | F21: =01_ビジョン原計画!F25 -> 748983 | G21: =01_ビジョン原計画!G25 -> 753884 | H21: =01_ビジョン原計画!H25 -> 763070 | I21: =01_ビジョン原計画!I25 -> 760439 | ... K21: =01_ビジョン原計画!K25 -> 745393
A22: 資産減耗・除却費 | B22: =01_ビジョン原計画!B26 -> 0 | C22: =01_ビジョン原計画!C26 -> 0 | D22: =01_ビジョン原計画!D26 -> 0 | E22: =01_ビジョン原計画!E26 -> 0 | F22: =01_ビジョン原計画!F26 -> 0 | G22: =01_ビジョン原計画!G26 -> 0 | H22: =01_ビジョン原計画!H26 -> 0 | I22: =01_ビジョン原計画!I26 -> 0 | ... K22: =01_ビジョン原計画!K26 -> 0
A23: 営業外費用 | B23: =01_ビジョン原計画!B28 -> 128495 | C23: =01_ビジョン原計画!C28 -> 120518 | D23: =01_ビジョン原計画!D28 -> 117139 | E23: =01_ビジョン原計画!E28 -> 115384 | F23: =01_ビジョン原計画!F28 -> 113787 | G23: =01_ビジョン原計画!G28 -> 110821 | H23: =01_ビジョン原計画!H28 -> 108565 | I23: =01_ビジョン原計画!I28 -> 107412 | ... K23: =01_ビジョン原計画!K28 -> 105117
A24: 支払利息 | B24: =01_ビジョン原計画!B29 -> 118910 | C24: =01_ビジョン原計画!C29 -> 111872 | D24: =01_ビジョン原計画!D29 -> 108458 | E24: =01_ビジョン原計画!E29 -> 106668 | F24: =01_ビジョン原計画!F29 -> 105071 | G24: =01_ビジョン原計画!G29 -> 102070 | H24: =01_ビジョン原計画!H29 -> 99779 | I24: =01_ビジョン原計画!I29 -> 98626 | ... K24: =01_ビジョン原計画!K29 -> 96331
A25: 特別損失 | B25: =01_ビジョン原計画!B31 -> 273 | C25: =01_ビジョン原計画!C31 -> 273 | D25: =01_ビジョン原計画!D31 -> 273 | E25: =01_ビジョン原計画!E31 -> 273 | F25: =01_ビジョン原計画!F31 -> 273 | G25: =01_ビジョン原計画!G31 -> 273 | H25: =01_ビジョン原計画!H31 -> 273 | I25: =01_ビジョン原計画!I31 -> 273 | ... K25: =01_ビジョン原計画!K31 -> 273
A26: 収益的支出合計 | B26: =SUM(B20,B23,B25) -> 1608275 | C26: =SUM(C20,C23,C25) -> 1597336 | D26: =SUM(D20,D23,D25) -> 1591913 | E26: =SUM(E20,E23,E25) -> 1586945 | F26: =SUM(F20,F23,F25) -> 1585772 | G26: =SUM(G20,G23,G25) -> 1588017 | H26: =SUM(H20,H23,H25) -> 1595258 | I26: =SUM(I20,I23,I25) -> 1591786 | ... K26: =SUM(K20,K23,K25) -> 1575072
A27: 経常損益 | B27: =SUM(B9,B13)-SUM(B20,B23) -> 8482 | C27: =SUM(C9,C13)-SUM(C20,C23) -> 7410 | D27: =SUM(D9,D13)-SUM(D20,D23) -> -5580 | E27: =SUM(E9,E13)-SUM(E20,E23) -> -18169 | F27: =SUM(F9,F13)-SUM(F20,F23) -> 1113157 | G27: =SUM(G9,G13)-SUM(G20,G23) -> 1093970.4 | H27: =SUM(H9,H13)-SUM(H20,H23) -> 1063244.4 | I27: =SUM(I9,I13)-SUM(I20,I23) -> 1033952.1 | ... K27: =SUM(K9,K13)-SUM(K20,K23) -> 980995.26
A28: 純損益 | B28: =B27+B16-B25 -> 10785 | C28: =C27+C16-C25 -> 7137 | D28: =D27+D16-D25 -> -5853 | E28: =E27+E16-E25 -> -18442 | F28: =F27+F16-F25 -> 1112884 | G28: =G27+G16-G25 -> 1093697.4 | H28: =H27+H16-H25 -> 1062971.4 | I28: =I27+I16-I25 -> 1033679.1 | ... K28: =K27+K16-K25 -> 980722.26
A30: 【経営指標】
A31: 経常収支比率 | B31: =IFERROR((SUM(B9,B13)/SUM(B20,B23))*100,0) -> 100.52749 | C31: =IFERROR((SUM(C9,C13)/SUM(C20,C23))*100,0) -> 100.46398 | D31: =IFERROR((SUM(D9,D13)/SUM(D20,D23))*100,0) -> 99.649418 | E31: =IFERROR((SUM(E9,E13)/SUM(E20,E23))*100,0) -> 98.854899 | F31: =IFERROR((SUM(F9,F13)/SUM(F20,F23))*100,0) -> 170.20862 | G31: =IFERROR((SUM(G9,G13)/SUM(G20,G23))*100,0) -> 168.90093 | H31: =IFERROR((SUM(H9,H13)/SUM(H20,H23))*100,0) -> 166.66172 | I31: =IFERROR((SUM(I9,I13)/SUM(I20,I23))*100,0) -> 164.96661 | ... K31: =IFERROR((SUM(K9,K13)/SUM(K20,K23))*100,0) -> 162.29336
A32: 料金回収率（通常） | B32: =IFERROR(B10/B34*100,0) -> 92.822855 | C32: =IFERROR(C10/C34*100,0) -> 92.824907 | D32: =IFERROR(D10/D34*100,0) -> 91.98462 | E32: =IFERROR(E10/E34*100,0) -> 91.172206 | F32: =IFERROR(F10/F34*100,0) -> 133.77267 | G32: =IFERROR(G10/G34*100,0) -> 132.28513 | H32: =IFERROR(H10/H34*100,0) -> 130.41005 | I32: =IFERROR(I10/I34*100,0) -> 128.66347 | ... K32: =IFERROR(K10/K34*100,0) -> 125.65343
A33: 資産維持費込料金回収率 | B33: =IFERROR(B10/B35*100,0) -> 67.645898 | C33: =IFERROR(C10/C35*100,0) -> 67.462152 | D33: =IFERROR(D10/D35*100,0) -> 66.833974 | E33: =IFERROR(E10/E35*100,0) -> 66.222328 | F33: =IFERROR(F10/F35*100,0) -> 97.226666 | G33: =IFERROR(G10/G35*100,0) -> 96.175227 | H33: =IFERROR(H10/H35*100,0) -> 94.921231 | I33: =IFERROR(I10/I35*100,0) -> 93.737365 | ... K33: =IFERROR(K10/K35*100,0) -> 91.633076
A34: 給水原価対象費用 | B34: =SUM(B20,B23)-B14 -> 1326377 | C34: =SUM(C20,C23)-C14 -> 1313084 | D34: =SUM(D20,D23)-D14 -> 1311828 | E34: =SUM(E20,E23)-E14 -> 1310282 | F34: =SUM(F20,F23)-F14 -> 1313331 | G34: =SUM(G20,G23)-G14 -> 1314818 | H34: =SUM(H20,H23)-H14 -> 1320385 | I34: =SUM(I20,I23)-I14 -> 1324925 | ... K34: =SUM(K20,K23)-K14 -> 1329665
A35: 給水原価対象費用＋資産維持費 | B35: =B34+$B$5 -> 1820037.9 | C35: =C34+$B$5 -> 1806744.9 | D35: =D34+$B$5 -> 1805488.9 | E35: =E34+$B$5 -> 1803942.9 | F35: =F34+$B$5 -> 1806991.9 | G35: =G34+$B$5 -> 1808478.9 | H35: =H34+$B$5 -> 1814045.9 | I35: =I34+$B$5 -> 1818585.9 | ... K35: =K34+$B$5 -> 1823325.9
A36: 総括原価回収率（参考） | B36: =IFERROR(B10/(B20+B23-B14-B12-B15+$B$5)*100,0) -> 71.732057 | C36: =IFERROR(C10/(C20+C23-C14-C12-C15+$B$5)*100,0) -> 71.482848 | D36: =IFERROR(D10/(D20+D23-D14-D12-D15+$B$5)*100,0) -> 70.734815 | E36: =IFERROR(E10/(E20+E23-E14-E12-E15+$B$5)*100,0) -> 70.006033 | F36: =IFERROR(F10/(F20+F23-F14-F12-F15+$B$5)*100,0) -> 102.64573 | G36: =IFERROR(G10/(G20+G23-G14-G12-G15+$B$5)*100,0) -> 101.40282 | H36: =IFERROR(H10/(H20+H23-H14-H12-H15+$B$5)*100,0) -> 99.943165 | I36: =IFERROR(I10/(I20+I23-I14-I12-I15+$B$5)*100,0) -> 98.574981 | ... K36: =IFERROR(K10/(K20+K23-K14-K12-K15+$B$5)*100,0) -> 96.171474
A37: 検証：資産維持費込<=通常 | B37: =IF(B33<=B32,"OK","要確認") -> OK | C37: =IF(C33<=C32,"OK","要確認") -> OK | D37: =IF(D33<=D32,"OK","要確認") -> OK | E37: =IF(E33<=E32,"OK","要確認") -> OK | F37: =IF(F33<=F32,"OK","要確認") -> OK | G37: =IF(G33<=G32,"OK","要確認") -> OK | H37: =IF(H33<=H32,"OK","要確認") -> OK | I37: =IF(I33<=I32,"OK","要確認") -> OK | ... K37: =IF(K33<=K32,"OK","要確認") -> OK
A39: 【資本的収入】
A40: 資本的収入 | B40: =01_ビジョン原計画!B34 -> 698941 | C40: =01_ビジョン原計画!C34 -> 664331 | D40: =01_ビジョン原計画!D34 -> 636408 | E40: =01_ビジョン原計画!E34 -> 715698 | F40: =01_ビジョン原計画!F34 -> 627649 | G40: =01_ビジョン原計画!G34 -> 570213 | H40: =01_ビジョン原計画!H34 -> 571338 | I40: =01_ビジョン原計画!I34 -> 536592 | ... K40: =01_ビジョン原計画!K34 -> 365000
A41: 企業債 | B41: =01_ビジョン原計画!B35 -> 329000 | C41: =01_ビジョン原計画!C35 -> 435000 | D41: =01_ビジョン原計画!D35 -> 399000 | E41: =01_ビジョン原計画!E35 -> 400000 | F41: =01_ビジョン原計画!F35 -> 232000 | G41: =01_ビジョン原計画!G35 -> 283000 | H41: =01_ビジョン原計画!H35 -> 286000 | I41: =01_ビジョン原計画!I35 -> 368000 | ... K41: =01_ビジョン原計画!K35 -> 230000
A42: 一般会計負担金 | B42: =01_ビジョン原計画!B36 -> 169041 | C42: =01_ビジョン原計画!C36 -> 164831 | D42: =01_ビジョン原計画!D36 -> 162408 | E42: =01_ビジョン原計画!E36 -> 167998 | F42: =01_ビジョン原計画!F36 -> 173649 | G42: =01_ビジョン原計画!G36 -> 182213 | H42: =01_ビジョン原計画!H36 -> 180338 | I42: =01_ビジョン原計画!I36 -> 168592 | ... K42: =01_ビジョン原計画!K36 -> 135000
A43: 一般会計出資金 | B43: =01_ビジョン原計画!B37 -> 0 | C43: =01_ビジョン原計画!C37 -> 0 | D43: =01_ビジョン原計画!D37 -> 0 | E43: =01_ビジョン原計画!E37 -> 0 | F43: =01_ビジョン原計画!F37 -> 0 | G43: =01_ビジョン原計画!G37 -> 0 | H43: =01_ビジョン原計画!H37 -> 0 | I43: =01_ビジョン原計画!I37 -> 0 | ... K43: =01_ビジョン原計画!K37 -> 0
A44: 国庫補助金 | B44: =01_ビジョン原計画!B38 -> 0 | C44: =01_ビジョン原計画!C38 -> 64500 | D44: =01_ビジョン原計画!D38 -> 75000 | E44: =01_ビジョン原計画!E38 -> 147700 | F44: =01_ビジョン原計画!F38 -> 222000 | G44: =01_ビジョン原計画!G38 -> 105000 | H44: =01_ビジョン原計画!H38 -> 105000 | I44: =01_ビジョン原計画!I38 -> 0 | ... K44: =01_ビジョン原計画!K38 -> 0
A45: 固定資産売却代金 | B45: =01_ビジョン原計画!B39 -> 0 | C45: =01_ビジョン原計画!C39 -> 0 | D45: =01_ビジョン原計画!D39 -> 0 | E45: =01_ビジョン原計画!E39 -> 0 | F45: =01_ビジョン原計画!F39 -> 0 | G45: =01_ビジョン原計画!G39 -> 0 | H45: =01_ビジョン原計画!H39 -> 0 | I45: =01_ビジョン原計画!I39 -> 0 | ... K45: =01_ビジョン原計画!K39 -> 0
A46: 工事負担金 | B46: =01_ビジョン原計画!B40 -> 200900 | C46: =01_ビジョン原計画!C40 -> 0 | D46: =01_ビジョン原計画!D40 -> 0 | E46: =01_ビジョン原計画!E40 -> 0 | F46: =01_ビジョン原計画!F40 -> 0 | G46: =01_ビジョン原計画!G40 -> 0 | H46: =01_ビジョン原計画!H40 -> 0 | I46: =01_ビジョン原計画!I40 -> 0 | ... K46: =01_ビジョン原計画!K40 -> 0
A47: その他・調整 | B47: =01_ビジョン原計画!B41 -> 0 | C47: =01_ビジョン原計画!C41 -> 0 | D47: =01_ビジョン原計画!D41 -> 0 | E47: =01_ビジョン原計画!E41 -> 0 | F47: =01_ビジョン原計画!F41 -> 0 | G47: =01_ビジョン原計画!G41 -> 0 | H47: =01_ビジョン原計画!H41 -> 0 | I47: =01_ビジョン原計画!I41 -> 0 | ... K47: =01_ビジョン原計画!K41 -> 0
A49: 【資本的支出】
A50: 資本的支出 | B50: =01_ビジョン原計画!B44 -> 1412922 | C50: =01_ビジョン原計画!C44 -> 1320955 | D50: =01_ビジョン原計画!D44 -> 1228308 | E50: =01_ビジョン原計画!E44 -> 1249449 | F50: =01_ビジョン原計画!F44 -> 1123446 | G50: =01_ビジョン原計画!G44 -> 992222 | H50: =01_ビジョン原計画!H44 -> 982061 | I50: =01_ビジョン原計画!I44 -> 942741 | ... K50: =01_ビジョン原計画!K44 -> 789992
A51: 建設改良費 | B51: =01_ビジョン原計画!B45 -> 557893 | C51: =01_ビジョン原計画!C45 -> 525014 | D51: =01_ビジョン原計画!D45 -> 500489 | E51: =01_ビジョン原計画!E45 -> 576808 | F51: =01_ビジョン原計画!F45 -> 484835 | G51: =01_ビジョン原計画!G45 -> 415935 | H51: =01_ビジョン原計画!H45 -> 419465 | I51: =01_ビジョン原計画!I45 -> 395135 | ... K51: =01_ビジョン原計画!K45 -> 257135
A52: 企業債償還金 | B52: =01_ビジョン原計画!B46 -> 855029 | C52: =01_ビジョン原計画!C46 -> 795941 | D52: =01_ビジョン原計画!D46 -> 727819 | E52: =01_ビジョン原計画!E46 -> 672641 | F52: =01_ビジョン原計画!F46 -> 638611 | G52: =01_ビジョン原計画!G46 -> 576287 | H52: =01_ビジョン原計画!H46 -> 562596 | I52: =01_ビジョン原計画!I46 -> 547606 | ... K52: =01_ビジョン原計画!K46 -> 532857
A53: その他資本的支出 | B53: =01_ビジョン原計画!B47 -> 0 | C53: =01_ビジョン原計画!C47 -> 0 | D53: =01_ビジョン原計画!D47 -> 0 | E53: =01_ビジョン原計画!E47 -> 0 | F53: =01_ビジョン原計画!F47 -> 0 | G53: =01_ビジョン原計画!G47 -> 0 | H53: =01_ビジョン原計画!H47 -> 0 | I53: =01_ビジョン原計画!I47 -> 0 | ... K53: =01_ビジョン原計画!K47 -> 0
A54: 資本的収支不足額（収入－支出） | B54: =B40-B50 -> -713981 | C54: =C40-C50 -> -656624 | D54: =D40-D50 -> -591900 | E54: =E40-E50 -> -533751 | F54: =F40-F50 -> -495797 | G54: =G40-G50 -> -422009 | H54: =H40-H50 -> -410723 | I54: =I40-I50 -> -406149 | ... K54: =K40-K50 -> -424992
A56: 【現預金・4条財源】
A57: 補てん可能財源相当（簡便CF） | B57: =B28+B21+B22-B14 -> 484942 | C57: =C28+C21+C22-C14 -> 477901 | D57: =D28+D21+D22-D14 -> 466726 | E57: =E28+E21+E22-E14 -> 454037 | F57: =F28+F21+F22-F14 -> 1589699 | G57: =G28+G21+G22-G14 -> 1574655.4 | H57: =H28+H21+H22-H14 -> 1551441.4 | I57: =I28+I21+I22-I14 -> 1527530.1 | ... K57: =K28+K21+K22-K14 -> 1480981.3
A58: 資本的収支不足額（再掲） | B58: =B54 -> -713981 | C58: =C54 -> -656624 | D58: =D54 -> -591900 | E58: =E54 -> -533751 | F58: =F54 -> -495797 | G58: =G54 -> -422009 | H58: =H54 -> -410723 | I58: =I54 -> -406149 | ... K58: =K54 -> -424992
A59: 年度末現預金残高 | B59: =00_前提・検証!$B$6 -> 242588 | C59: =B59+C57+C58 -> 63865 | D59: =C59+D57+D58 -> -61309 | E59: =D59+E57+E58 -> -141023 | F59: =E59+F57+F58 -> 952878.98 | G59: =F59+G57+G58 -> 2105525.4 | H59: =G59+H57+H58 -> 3246243.8 | I59: =H59+I57+I58 -> 4367624.9 | J59: =I59+J57+J58 -> 5452180.2 | K59: =J59+K57+K58 -> 6508169.5
A60: 最低現金目安との差額 | B60: =B59-00_前提・検証!$B$7 -> -57412 | C60: =C59-00_前提・検証!$B$7 -> -236135 | D60: =D59-00_前提・検証!$B$7 -> -361309 | E60: =E59-00_前提・検証!$B$7 -> -441023 | F60: =F59-00_前提・検証!$B$7 -> 652878.98 | G60: =G59-00_前提・検証!$B$7 -> 1805525.4 | H60: =H59-00_前提・検証!$B$7 -> 2946243.8 | I60: =I59-00_前提・検証!$B$7 -> 4067624.9 | ... K60: =K59-00_前提・検証!$B$7 -> 6208169.5

Sheet SIM_置換後_0%
A1: SIM_置換後_0%
A2: 単位：千円、比率は％。料金改定率はR11〜R15の総括原価回収を基礎に算定し、R11以降の給水収益へ反映。
A3: 区分 | B3: 令和7年度 | C3: 令和8年度 | D3: 令和9年度 | E3: 令和10年度 | F3: 令和11年度 | G3: 令和12年度 | H3: 令和13年度 | I3: 令和14年度 | J3: 令和15年度 | K3: 令和16年度
A4: 資産維持費率 | B4: 0
A5: 年額資産維持費（千円） | B5: =00_前提・検証!$B$2*$B$4 -> 0
A6: 料金改定率（R11以降・試算） | B6: =MAX(0,(SUMPRODUCT((02_将来年次投資置換!F18:J18+02_将来年次投資置換!F28:J28-02_将来年次投資置換!F12:J12-02_将来年次投資置換!F8:J8-02_将来年次投資置換!F11:J11+$B$5)-02_将来年次投資置換!F7:J7)/SUM(02_将来年次投資置換!F7:J7))) -> 0.059677187
A8: 【収益的収入】
A9: 営業収益 | B9: =SUM(B10:B12) -> 1261575 | C9: =SUM(C10:C12) -> 1249336 | D9: =SUM(D10:D12) -> 1237293 | E9: =SUM(E10:E12) -> 1225373 | F9: =SUM(F10:F12) -> 1354730.4 | G9: =SUM(G10:G12) -> 1341640.8 | H9: =SUM(H10:H12) -> 1328683.2 | I9: =SUM(I10:I12) -> 1315857.7 | ... K9: =SUM(K10:K12) -> 1290598
A10: 給水収益（改定反映後） | B10: =02_将来年次投資置換!B7*IF(7>=11,1+$B$6,1) -> 1231181 | C10: =02_将来年次投資置換!C7*IF(8>=11,1+$B$6,1) -> 1218869 | D10: =02_将来年次投資置換!D7*IF(9>=11,1+$B$6,1) -> 1206680 | E10: =02_将来年次投資置換!E7*IF(10>=11,1+$B$6,1) -> 1194613 | F10: =02_将来年次投資置換!F7*IF(11>=11,1+$B$6,1) -> 1253244.2 | G10: =02_将来年次投資置換!G7*IF(12>=11,1+$B$6,1) -> 1240711.4 | H10: =02_将来年次投資置換!H7*IF(13>=11,1+$B$6,1) -> 1228303.6 | I10: =02_将来年次投資置換!I7*IF(14>=11,1+$B$6,1) -> 1216019.8 | J10: =02_将来年次投資置換!J7*IF(15>=11,1+$B$6,1) -> 1203859 | K10: =02_将来年次投資置換!K7*IF(16>=11,1+$B$6,1) -> 1191820
A11: うち料金改定増収 | B11: =B10-02_将来年次投資置換!B7 -> 0 | C11: =C10-02_将来年次投資置換!C7 -> 0 | D11: =D10-02_将来年次投資置換!D7 -> 0 | E11: =E10-02_将来年次投資置換!E7 -> 0 | F11: =F10-02_将来年次投資置換!F7 -> 70578.18 | G11: =G10-02_将来年次投資置換!G7 -> 69872.378 | H11: =H10-02_将来年次投資置換!H7 -> 69173.618 | I11: =I10-02_将来年次投資置換!I7 -> 68481.84 | ... K11: =K10-02_将来年次投資置換!K7 -> 67118.992
A12: その他営業収益 | B12: =02_将来年次投資置換!B8 -> 30394 | C12: =02_将来年次投資置換!C8 -> 30467 | D12: =02_将来年次投資置換!D8 -> 30613 | E12: =02_将来年次投資置換!E8 -> 30760 | F12: =02_将来年次投資置換!F8 -> 30908 | G12: =02_将来年次投資置換!G8 -> 31057 | H12: =02_将来年次投資置換!H8 -> 31206 | I12: =02_将来年次投資置換!I8 -> 31356 | ... K12: =02_将来年次投資置換!K8 -> 31659
A13: 営業外収益 | B13: =02_将来年次投資置換!B9 -> 354909 | C13: =02_将来年次投資置換!C9 -> 355137 | D13: =02_将来年次投資置換!D9 -> 348767 | E13: =02_将来年次投資置換!E9 -> 343130 | F13: =02_将来年次投資置換!F9 -> 336658 | G13: =02_将来年次投資置換!G9 -> 342879 | H13: =02_将来年次投資置換!H9 -> 342324 | I13: =02_将来年次投資置換!I9 -> 332258 | ... K13: =02_将来年次投資置換!K9 -> 307297
A14: 長期前受金戻入 | B14: =02_将来年次投資置換!B12 -> 281625 | C14: =02_将来年次投資置換!C12 -> 283979 | D14: =02_将来年次投資置換!D12 -> 279812 | E14: =02_将来年次投資置換!E12 -> 276390 | F14: =02_将来年次投資置換!F12 -> 272168 | G14: =02_将来年次投資置換!G12 -> 272926 | H14: =02_将来年次投資置換!H12 -> 274600 | I14: =02_将来年次投資置換!I12 -> 266588 | ... K14: =02_将来年次投資置換!K12 -> 245134
A15: 繰入金・負担金等 | B15: =02_将来年次投資置換!B11 -> 73283 | C15: =02_将来年次投資置換!C11 -> 71157 | D15: =02_将来年次投資置換!D11 -> 68955 | E15: =02_将来年次投資置換!E11 -> 66740 | F15: =02_将来年次投資置換!F11 -> 64490 | G15: =02_将来年次投資置換!G11 -> 62175 | H15: =02_将来年次投資置換!H11 -> 59946 | I15: =02_将来年次投資置換!I11 -> 57892 | ... K15: =02_将来年次投資置換!K11 -> 54385
A16: 特別利益 | B16: =02_将来年次投資置換!B14 -> 2576 | C16: =02_将来年次投資置換!C14 -> 0 | D16: =02_将来年次投資置換!D14 -> 0 | E16: =02_将来年次投資置換!E14 -> 0 | F16: =02_将来年次投資置換!F14 -> 0 | G16: =02_将来年次投資置換!G14 -> 0 | H16: =02_将来年次投資置換!H14 -> 0 | I16: =02_将来年次投資置換!I14 -> 0 | ... K16: =02_将来年次投資置換!K14 -> 0
A17: 収益的収入合計 | B17: =SUM(B9,B13,B16) -> 1619060 | C17: =SUM(C9,C13,C16) -> 1604473 | D17: =SUM(D9,D13,D16) -> 1586060 | E17: =SUM(E9,E13,E16) -> 1568503 | F17: =SUM(F9,F13,F16) -> 1691388.4 | G17: =SUM(G9,G13,G16) -> 1684519.8 | H17: =SUM(H9,H13,H16) -> 1671007.2 | I17: =SUM(I9,I13,I16) -> 1648115.7 | ... K17: =SUM(K9,K13,K16) -> 1597895
A19: 【収益的支出】
A20: 営業費用 | B20: =02_将来年次投資置換!B18 -> 1479507 | C20: =02_将来年次投資置換!C18 -> 1476545 | D20: =02_将来年次投資置換!D18 -> 1474501 | E20: =02_将来年次投資置換!E18 -> 1471288 | F20: =02_将来年次投資置換!F18 -> 1471712 | G20: =02_将来年次投資置換!G18 -> 1476923 | H20: =02_将来年次投資置換!H18 -> 1486420 | I20: =02_将来年次投資置換!I18 -> 1484101 | ... K20: =02_将来年次投資置換!K18 -> 1469682
A21: 減価償却費 | B21: =02_将来年次投資置換!B25 -> 755782 | C21: =02_将来年次投資置換!C25 -> 754743 | D21: =02_将来年次投資置換!D25 -> 752391 | E21: =02_将来年次投資置換!E25 -> 748869 | F21: =02_将来年次投資置換!F25 -> 748983 | G21: =02_将来年次投資置換!G25 -> 753884 | H21: =02_将来年次投資置換!H25 -> 763070 | I21: =02_将来年次投資置換!I25 -> 760439 | ... K21: =02_将来年次投資置換!K25 -> 745393
A22: 資産減耗・除却費 | B22: =02_将来年次投資置換!B26 -> 0 | C22: =02_将来年次投資置換!C26 -> 0 | D22: =02_将来年次投資置換!D26 -> 0 | E22: =02_将来年次投資置換!E26 -> 0 | F22: =02_将来年次投資置換!F26 -> 0 | G22: =02_将来年次投資置換!G26 -> 0 | H22: =02_将来年次投資置換!H26 -> 0 | I22: =02_将来年次投資置換!I26 -> 0 | ... K22: =02_将来年次投資置換!K26 -> 0
A23: 営業外費用 | B23: =02_将来年次投資置換!B28 -> 128495 | C23: =02_将来年次投資置換!C28 -> 120518 | D23: =02_将来年次投資置換!D28 -> 117139 | E23: =02_将来年次投資置換!E28 -> 115384 | F23: =02_将来年次投資置換!F28 -> 113787 | G23: =02_将来年次投資置換!G28 -> 110821 | H23: =02_将来年次投資置換!H28 -> 108565 | I23: =02_将来年次投資置換!I28 -> 107412 | ... K23: =02_将来年次投資置換!K28 -> 105117
A24: 支払利息 | B24: =02_将来年次投資置換!B29 -> 118910 | C24: =02_将来年次投資置換!C29 -> 111872 | D24: =02_将来年次投資置換!D29 -> 108458 | E24: =02_将来年次投資置換!E29 -> 106668 | F24: =02_将来年次投資置換!F29 -> 105071 | G24: =02_将来年次投資置換!G29 -> 102070 | H24: =02_将来年次投資置換!H29 -> 99779 | I24: =02_将来年次投資置換!I29 -> 98626 | ... K24: =02_将来年次投資置換!K29 -> 96331
A25: 特別損失 | B25: =02_将来年次投資置換!B31 -> 273 | C25: =02_将来年次投資置換!C31 -> 273 | D25: =02_将来年次投資置換!D31 -> 273 | E25: =02_将来年次投資置換!E31 -> 273 | F25: =02_将来年次投資置換!F31 -> 273 | G25: =02_将来年次投資置換!G31 -> 273 | H25: =02_将来年次投資置換!H31 -> 273 | I25: =02_将来年次投資置換!I31 -> 273 | ... K25: =02_将来年次投資置換!K31 -> 273
A26: 収益的支出合計 | B26: =SUM(B20,B23,B25) -> 1608275 | C26: =SUM(C20,C23,C25) -> 1597336 | D26: =SUM(D20,D23,D25) -> 1591913 | E26: =SUM(E20,E23,E25) -> 1586945 | F26: =SUM(F20,F23,F25) -> 1585772 | G26: =SUM(G20,G23,G25) -> 1588017 | H26: =SUM(H20,H23,H25) -> 1595258 | I26: =SUM(I20,I23,I25) -> 1591786 | ... K26: =SUM(K20,K23,K25) -> 1575072
A27: 経常損益 | B27: =SUM(B9,B13)-SUM(B20,B23) -> 8482 | C27: =SUM(C9,C13)-SUM(C20,C23) -> 7410 | D27: =SUM(D9,D13)-SUM(D20,D23) -> -5580 | E27: =SUM(E9,E13)-SUM(E20,E23) -> -18169 | F27: =SUM(F9,F13)-SUM(F20,F23) -> 105889.36 | G27: =SUM(G9,G13)-SUM(G20,G23) -> 96775.756 | H27: =SUM(H9,H13)-SUM(H20,H23) -> 76022.236 | I27: =SUM(I9,I13)-SUM(I20,I23) -> 56602.68 | ... K27: =SUM(K9,K13)-SUM(K20,K23) -> 23095.984
A28: 純損益 | B28: =B27+B16-B25 -> 10785 | C28: =C27+C16-C25 -> 7137 | D28: =D27+D16-D25 -> -5853 | E28: =E27+E16-E25 -> -18442 | F28: =F27+F16-F25 -> 105616.36 | G28: =G27+G16-G25 -> 96502.756 | H28: =H27+H16-H25 -> 75749.236 | I28: =I27+I16-I25 -> 56329.68 | ... K28: =K27+K16-K25 -> 22822.984
A30: 【経営指標】
A31: 経常収支比率 | B31: =IFERROR((SUM(B9,B13)/SUM(B20,B23))*100,0) -> 100.52749 | C31: =IFERROR((SUM(C9,C13)/SUM(C20,C23))*100,0) -> 100.46398 | D31: =IFERROR((SUM(D9,D13)/SUM(D20,D23))*100,0) -> 99.649418 | E31: =IFERROR((SUM(E9,E13)/SUM(E20,E23))*100,0) -> 98.854899 | F31: =IFERROR((SUM(F9,F13)/SUM(F20,F23))*100,0) -> 106.67861 | G31: =IFERROR((SUM(G9,G13)/SUM(G20,G23))*100,0) -> 106.09517 | H31: =IFERROR((SUM(H9,H13)/SUM(H20,H23))*100,0) -> 104.76633 | I31: =IFERROR((SUM(I9,I13)/SUM(I20,I23))*100,0) -> 103.55653 | ... K31: =IFERROR((SUM(K9,K13)/SUM(K20,K23))*100,0) -> 101.4666
A32: 料金回収率（通常） | B32: =IFERROR(B10/B34*100,0) -> 92.822855 | C32: =IFERROR(C10/C34*100,0) -> 92.824907 | D32: =IFERROR(D10/D34*100,0) -> 91.98462 | E32: =IFERROR(E10/E34*100,0) -> 91.172206 | F32: =IFERROR(F10/F34*100,0) -> 95.424853 | G32: =IFERROR(G10/G34*100,0) -> 94.363735 | H32: =IFERROR(H10/H34*100,0) -> 93.026172 | I32: =IFERROR(I10/I34*100,0) -> 91.780277 | ... K32: =IFERROR(K10/K34*100,0) -> 89.633102
A33: 資産維持費込料金回収率 | B33: =IFERROR(B10/B35*100,0) -> 92.822855 | C33: =IFERROR(C10/C35*100,0) -> 92.824907 | D33: =IFERROR(D10/D35*100,0) -> 91.98462 | E33: =IFERROR(E10/E35*100,0) -> 91.172206 | F33: =IFERROR(F10/F35*100,0) -> 95.424853 | G33: =IFERROR(G10/G35*100,0) -> 94.363735 | H33: =IFERROR(H10/H35*100,0) -> 93.026172 | I33: =IFERROR(I10/I35*100,0) -> 91.780277 | ... K33: =IFERROR(K10/K35*100,0) -> 89.633102
A34: 給水原価対象費用 | B34: =SUM(B20,B23)-B14 -> 1326377 | C34: =SUM(C20,C23)-C14 -> 1313084 | D34: =SUM(D20,D23)-D14 -> 1311828 | E34: =SUM(E20,E23)-E14 -> 1310282 | F34: =SUM(F20,F23)-F14 -> 1313331 | G34: =SUM(G20,G23)-G14 -> 1314818 | H34: =SUM(H20,H23)-H14 -> 1320385 | I34: =SUM(I20,I23)-I14 -> 1324925 | ... K34: =SUM(K20,K23)-K14 -> 1329665
A35: 給水原価対象費用＋資産維持費 | B35: =B34+$B$5 -> 1326377 | C35: =C34+$B$5 -> 1313084 | D35: =D34+$B$5 -> 1311828 | E35: =E34+$B$5 -> 1310282 | F35: =F34+$B$5 -> 1313331 | G35: =G34+$B$5 -> 1314818 | H35: =H34+$B$5 -> 1320385 | I35: =I34+$B$5 -> 1324925 | ... K35: =K34+$B$5 -> 1329665
A36: 総括原価回収率（参考） | B36: =IFERROR(B10/(B20+B23-B14-B12-B15+$B$5)*100,0) -> 100.69363 | C36: =IFERROR(C10/(C20+C23-C14-C12-C15+$B$5)*100,0) -> 100.61158 | D36: =IFERROR(D10/(D20+D23-D14-D12-D15+$B$5)*100,0) -> 99.539703 | E36: =IFERROR(E10/(E20+E23-E14-E12-E15+$B$5)*100,0) -> 98.501874 | F36: =IFERROR(F10/(F20+F23-F14-F12-F15+$B$5)*100,0) -> 102.89927 | G36: =IFERROR(G10/(G20+G23-G14-G12-G15+$B$5)*100,0) -> 101.56562 | H36: =IFERROR(H10/(H20+H23-H14-H12-H15+$B$5)*100,0) -> 99.924393 | I36: =IFERROR(I10/(I20+I23-I14-I12-I15+$B$5)*100,0) -> 98.409199 | ... K36: =IFERROR(K10/(K20+K23-K14-K12-K15+$B$5)*100,0) -> 95.834663
A37: 検証：資産維持費込<=通常 | B37: =IF(B33<=B32,"OK","要確認") -> OK | C37: =IF(C33<=C32,"OK","要確認") -> OK | D37: =IF(D33<=D32,"OK","要確認") -> OK | E37: =IF(E33<=E32,"OK","要確認") -> OK | F37: =IF(F33<=F32,"OK","要確認") -> OK | G37: =IF(G33<=G32,"OK","要確認") -> OK | H37: =IF(H33<=H32,"OK","要確認") -> OK | I37: =IF(I33<=I32,"OK","要確認") -> OK | ... K37: =IF(K33<=K32,"OK","要確認") -> OK
A39: 【資本的収入】
A40: 資本的収入 | B40: =02_将来年次投資置換!B34 -> 698941 | C40: =02_将来年次投資置換!C34 -> 664331 | D40: =02_将来年次投資置換!D34 -> 636408 | E40: =02_将来年次投資置換!E34 -> 715698 | F40: =02_将来年次投資置換!F34 -> 627649 | G40: =02_将来年次投資置換!G34 -> 570213 | H40: =02_将来年次投資置換!H34 -> 571338 | I40: =02_将来年次投資置換!I34 -> 536592 | ... K40: =02_将来年次投資置換!K34 -> 365000
A41: 企業債 | B41: =02_将来年次投資置換!B35 -> 329000 | C41: =02_将来年次投資置換!C35 -> 435000 | D41: =02_将来年次投資置換!D35 -> 399000 | E41: =02_将来年次投資置換!E35 -> 400000 | F41: =02_将来年次投資置換!F35 -> 232000 | G41: =02_将来年次投資置換!G35 -> 283000 | H41: =02_将来年次投資置換!H35 -> 286000 | I41: =02_将来年次投資置換!I35 -> 368000 | ... K41: =02_将来年次投資置換!K35 -> 230000
A42: 一般会計負担金 | B42: =02_将来年次投資置換!B36 -> 169041 | C42: =02_将来年次投資置換!C36 -> 164831 | D42: =02_将来年次投資置換!D36 -> 162408 | E42: =02_将来年次投資置換!E36 -> 167998 | F42: =02_将来年次投資置換!F36 -> 173649 | G42: =02_将来年次投資置換!G36 -> 182213 | H42: =02_将来年次投資置換!H36 -> 180338 | I42: =02_将来年次投資置換!I36 -> 168592 | ... K42: =02_将来年次投資置換!K36 -> 135000
A43: 一般会計出資金 | B43: =02_将来年次投資置換!B37 -> 0 | C43: =02_将来年次投資置換!C37 -> 0 | D43: =02_将来年次投資置換!D37 -> 0 | E43: =02_将来年次投資置換!E37 -> 0 | F43: =02_将来年次投資置換!F37 -> 0 | G43: =02_将来年次投資置換!G37 -> 0 | H43: =02_将来年次投資置換!H37 -> 0 | I43: =02_将来年次投資置換!I37 -> 0 | ... K43: =02_将来年次投資置換!K37 -> 0
A44: 国庫補助金 | B44: =02_将来年次投資置換!B38 -> 0 | C44: =02_将来年次投資置換!C38 -> 64500 | D44: =02_将来年次投資置換!D38 -> 75000 | E44: =02_将来年次投資置換!E38 -> 147700 | F44: =02_将来年次投資置換!F38 -> 222000 | G44: =02_将来年次投資置換!G38 -> 105000 | H44: =02_将来年次投資置換!H38 -> 105000 | I44: =02_将来年次投資置換!I38 -> 0 | ... K44: =02_将来年次投資置換!K38 -> 0
A45: 固定資産売却代金 | B45: =02_将来年次投資置換!B39 -> 0 | C45: =02_将来年次投資置換!C39 -> 0 | D45: =02_将来年次投資置換!D39 -> 0 | E45: =02_将来年次投資置換!E39 -> 0 | F45: =02_将来年次投資置換!F39 -> 0 | G45: =02_将来年次投資置換!G39 -> 0 | H45: =02_将来年次投資置換!H39 -> 0 | I45: =02_将来年次投資置換!I39 -> 0 | ... K45: =02_将来年次投資置換!K39 -> 0
A46: 工事負担金 | B46: =02_将来年次投資置換!B40 -> 200900 | C46: =02_将来年次投資置換!C40 -> 0 | D46: =02_将来年次投資置換!D40 -> 0 | E46: =02_将来年次投資置換!E40 -> 0 | F46: =02_将来年次投資置換!F40 -> 0 | G46: =02_将来年次投資置換!G40 -> 0 | H46: =02_将来年次投資置換!H40 -> 0 | I46: =02_将来年次投資置換!I40 -> 0 | ... K46: =02_将来年次投資置換!K40 -> 0
A47: その他・調整 | B47: =02_将来年次投資置換!B41 -> 0 | C47: =02_将来年次投資置換!C41 -> 0 | D47: =02_将来年次投資置換!D41 -> 0 | E47: =02_将来年次投資置換!E41 -> 0 | F47: =02_将来年次投資置換!F41 -> 0 | G47: =02_将来年次投資置換!G41 -> 0 | H47: =02_将来年次投資置換!H41 -> 0 | I47: =02_将来年次投資置換!I41 -> 0 | ... K47: =02_将来年次投資置換!K41 -> 0
A49: 【資本的支出】
A50: 資本的支出 | B50: =02_将来年次投資置換!B44 -> 1123770 | C50: =02_将来年次投資置換!C44 -> 1684483 | D50: =02_将来年次投資置換!D44 -> 1131274 | E50: =02_将来年次投資置換!E44 -> 1433926 | F50: =02_将来年次投資置換!F44 -> 1196811 | G50: =02_将来年次投資置換!G44 -> 965587 | H50: =02_将来年次投資置換!H44 -> 945526 | I50: =02_将来年次投資置換!I44 -> 916106 | ... K50: =02_将来年次投資置換!K44 -> 763357
A51: 建設改良費 | B51: =02_将来年次投資置換!B45 -> 268741 | C51: =02_将来年次投資置換!C45 -> 888542 | D51: =02_将来年次投資置換!D45 -> 403455 | E51: =02_将来年次投資置換!E45 -> 761285 | F51: =02_将来年次投資置換!F45 -> 558200 | G51: =02_将来年次投資置換!G45 -> 389300 | H51: =02_将来年次投資置換!H45 -> 382930 | I51: =02_将来年次投資置換!I45 -> 368500 | ... K51: =02_将来年次投資置換!K45 -> 230500
A52: 企業債償還金 | B52: =02_将来年次投資置換!B46 -> 855029 | C52: =02_将来年次投資置換!C46 -> 795941 | D52: =02_将来年次投資置換!D46 -> 727819 | E52: =02_将来年次投資置換!E46 -> 672641 | F52: =02_将来年次投資置換!F46 -> 638611 | G52: =02_将来年次投資置換!G46 -> 576287 | H52: =02_将来年次投資置換!H46 -> 562596 | I52: =02_将来年次投資置換!I46 -> 547606 | ... K52: =02_将来年次投資置換!K46 -> 532857
A53: その他資本的支出 | B53: =02_将来年次投資置換!B47 -> 0 | C53: =02_将来年次投資置換!C47 -> 0 | D53: =02_将来年次投資置換!D47 -> 0 | E53: =02_将来年次投資置換!E47 -> 0 | F53: =02_将来年次投資置換!F47 -> 0 | G53: =02_将来年次投資置換!G47 -> 0 | H53: =02_将来年次投資置換!H47 -> 0 | I53: =02_将来年次投資置換!I47 -> 0 | ... K53: =02_将来年次投資置換!K47 -> 0
A54: 資本的収支不足額（収入－支出） | B54: =B40-B50 -> -424829 | C54: =C40-C50 -> -1020152 | D54: =D40-D50 -> -494866 | E54: =E40-E50 -> -718228 | F54: =F40-F50 -> -569162 | G54: =G40-G50 -> -395374 | H54: =H40-H50 -> -374188 | I54: =I40-I50 -> -379514 | ... K54: =K40-K50 -> -398357
A56: 【現預金・4条財源】
A57: 補てん可能財源相当（簡便CF） | B57: =B28+B21+B22-B14 -> 484942 | C57: =C28+C21+C22-C14 -> 477901 | D57: =D28+D21+D22-D14 -> 466726 | E57: =E28+E21+E22-E14 -> 454037 | F57: =F28+F21+F22-F14 -> 582431.36 | G57: =G28+G21+G22-G14 -> 577460.76 | H57: =H28+H21+H22-H14 -> 564219.24 | I57: =I28+I21+I22-I14 -> 550180.68 | ... K57: =K28+K21+K22-K14 -> 523081.98
A58: 資本的収支不足額（再掲） | B58: =B54 -> -424829 | C58: =C54 -> -1020152 | D58: =D54 -> -494866 | E58: =E54 -> -718228 | F58: =F54 -> -569162 | G58: =G54 -> -395374 | H58: =H54 -> -374188 | I58: =I54 -> -379514 | ... K58: =K54 -> -398357
A59: 年度末現預金残高 | B59: =00_前提・検証!$B$6 -> 242588 | C59: =B59+C57+C58 -> -299663 | D59: =C59+D57+D58 -> -327803 | E59: =D59+E57+E58 -> -591994 | F59: =E59+F57+F58 -> -578724.64 | G59: =F59+G57+G58 -> -396637.88 | H59: =G59+H57+H58 -> -206606.65 | I59: =H59+I57+I58 -> -35939.969 | J59: =I59+J57+J58 -> 94475 | K59: =J59+K57+K58 -> 219199.98
A60: 最低現金目安との差額 | B60: =B59-00_前提・検証!$B$7 -> -57412 | C60: =C59-00_前提・検証!$B$7 -> -599663 | D60: =D59-00_前提・検証!$B$7 -> -627803 | E60: =E59-00_前提・検証!$B$7 -> -891994 | F60: =F59-00_前提・検証!$B$7 -> -878724.64 | G60: =G59-00_前提・検証!$B$7 -> -696637.88 | H60: =H59-00_前提・検証!$B$7 -> -506606.65 | I60: =I59-00_前提・検証!$B$7 -> -335939.97 | ... K60: =K59-00_前提・検証!$B$7 -> -80800.016

Sheet SIM_置換後_1%
A1: SIM_置換後_1%
A2: 単位：千円、比率は％。料金改定率はR11〜R15の総括原価回収を基礎に算定し、R11以降の給水収益へ反映。
A3: 区分 | B3: 令和7年度 | C3: 令和8年度 | D3: 令和9年度 | E3: 令和10年度 | F3: 令和11年度 | G3: 令和12年度 | H3: 令和13年度 | I3: 令和14年度 | J3: 令和15年度 | K3: 令和16年度
A4: 資産維持費率 | B4: 0.01
A5: 年額資産維持費（千円） | B5: =00_前提・検証!$B$2*$B$4 -> 164553.64
A6: 料金改定率（R11以降・試算） | B6: =MAX(0,(SUMPRODUCT((02_将来年次投資置換!F18:J18+02_将来年次投資置換!F28:J28-02_将来年次投資置換!F12:J12-02_将来年次投資置換!F8:J8-02_将来年次投資置換!F11:J11+$B$5)-02_将来年次投資置換!F7:J7)/SUM(02_将来年次投資置換!F7:J7))) -> 0.20162592
A8: 【収益的収入】
A9: 営業収益 | B9: =SUM(B10:B12) -> 1261575 | C9: =SUM(C10:C12) -> 1249336 | D9: =SUM(D10:D12) -> 1237293 | E9: =SUM(E10:E12) -> 1225373 | F9: =SUM(F10:F12) -> 1690486.2 | G9: =SUM(G10:G12) -> 1674039 | H9: =SUM(H10:H12) -> 1657757.3 | I9: =SUM(I10:I12) -> 1641640.8 | ... K9: =SUM(K10:K12) -> 1609897.7
A10: 給水収益（改定反映後） | B10: =02_将来年次投資置換!B7*IF(7>=11,1+$B$6,1) -> 1231181 | C10: =02_将来年次投資置換!C7*IF(8>=11,1+$B$6,1) -> 1218869 | D10: =02_将来年次投資置換!D7*IF(9>=11,1+$B$6,1) -> 1206680 | E10: =02_将来年次投資置換!E7*IF(10>=11,1+$B$6,1) -> 1194613 | F10: =02_将来年次投資置換!F7*IF(11>=11,1+$B$6,1) -> 1421122.1 | G10: =02_将来年次投資置換!G7*IF(12>=11,1+$B$6,1) -> 1406910.5 | H10: =02_将来年次投資置換!H7*IF(13>=11,1+$B$6,1) -> 1392840.6 | I10: =02_将来年次投資置換!I7*IF(14>=11,1+$B$6,1) -> 1378911.4 | J10: =02_将来年次投資置換!J7*IF(15>=11,1+$B$6,1) -> 1365121.5 | K10: =02_将来年次投資置換!K7*IF(16>=11,1+$B$6,1) -> 1351469.9
A11: うち料金改定増収 | B11: =B10-02_将来年次投資置換!B7 -> 0 | C11: =C10-02_将来年次投資置換!C7 -> 0 | D11: =D10-02_将来年次投資置換!D7 -> 0 | E11: =E10-02_将来年次投資置換!E7 -> 0 | F11: =F10-02_将来年次投資置換!F7 -> 238456.12 | G11: =G10-02_将来年次投資置換!G7 -> 236071.49 | H11: =H10-02_将来年次投資置換!H7 -> 233710.65 | I11: =I10-02_将来年次投資置換!I7 -> 231373.4 | ... K11: =K10-02_将来年次投資置換!K7 -> 226768.87
A12: その他営業収益 | B12: =02_将来年次投資置換!B8 -> 30394 | C12: =02_将来年次投資置換!C8 -> 30467 | D12: =02_将来年次投資置換!D8 -> 30613 | E12: =02_将来年次投資置換!E8 -> 30760 | F12: =02_将来年次投資置換!F8 -> 30908 | G12: =02_将来年次投資置換!G8 -> 31057 | H12: =02_将来年次投資置換!H8 -> 31206 | I12: =02_将来年次投資置換!I8 -> 31356 | ... K12: =02_将来年次投資置換!K8 -> 31659
A13: 営業外収益 | B13: =02_将来年次投資置換!B9 -> 354909 | C13: =02_将来年次投資置換!C9 -> 355137 | D13: =02_将来年次投資置換!D9 -> 348767 | E13: =02_将来年次投資置換!E9 -> 343130 | F13: =02_将来年次投資置換!F9 -> 336658 | G13: =02_将来年次投資置換!G9 -> 342879 | H13: =02_将来年次投資置換!H9 -> 342324 | I13: =02_将来年次投資置換!I9 -> 332258 | ... K13: =02_将来年次投資置換!K9 -> 307297
A14: 長期前受金戻入 | B14: =02_将来年次投資置換!B12 -> 281625 | C14: =02_将来年次投資置換!C12 -> 283979 | D14: =02_将来年次投資置換!D12 -> 279812 | E14: =02_将来年次投資置換!E12 -> 276390 | F14: =02_将来年次投資置換!F12 -> 272168 | G14: =02_将来年次投資置換!G12 -> 272926 | H14: =02_将来年次投資置換!H12 -> 274600 | I14: =02_将来年次投資置換!I12 -> 266588 | ... K14: =02_将来年次投資置換!K12 -> 245134
A15: 繰入金・負担金等 | B15: =02_将来年次投資置換!B11 -> 73283 | C15: =02_将来年次投資置換!C11 -> 71157 | D15: =02_将来年次投資置換!D11 -> 68955 | E15: =02_将来年次投資置換!E11 -> 66740 | F15: =02_将来年次投資置換!F11 -> 64490 | G15: =02_将来年次投資置換!G11 -> 62175 | H15: =02_将来年次投資置換!H11 -> 59946 | I15: =02_将来年次投資置換!I11 -> 57892 | ... K15: =02_将来年次投資置換!K11 -> 54385
A16: 特別利益 | B16: =02_将来年次投資置換!B14 -> 2576 | C16: =02_将来年次投資置換!C14 -> 0 | D16: =02_将来年次投資置換!D14 -> 0 | E16: =02_将来年次投資置換!E14 -> 0 | F16: =02_将来年次投資置換!F14 -> 0 | G16: =02_将来年次投資置換!G14 -> 0 | H16: =02_将来年次投資置換!H14 -> 0 | I16: =02_将来年次投資置換!I14 -> 0 | ... K16: =02_将来年次投資置換!K14 -> 0
A17: 収益的収入合計 | B17: =SUM(B9,B13,B16) -> 1619060 | C17: =SUM(C9,C13,C16) -> 1604473 | D17: =SUM(D9,D13,D16) -> 1586060 | E17: =SUM(E9,E13,E16) -> 1568503 | F17: =SUM(F9,F13,F16) -> 2027144.2 | G17: =SUM(G9,G13,G16) -> 2016918 | H17: =SUM(H9,H13,H16) -> 2000081.3 | I17: =SUM(I9,I13,I16) -> 1973898.8 | ... K17: =SUM(K9,K13,K16) -> 1917194.7
A19: 【収益的支出】
A20: 営業費用 | B20: =02_将来年次投資置換!B18 -> 1479507 | C20: =02_将来年次投資置換!C18 -> 1476545 | D20: =02_将来年次投資置換!D18 -> 1474501 | E20: =02_将来年次投資置換!E18 -> 1471288 | F20: =02_将来年次投資置換!F18 -> 1471712 | G20: =02_将来年次投資置換!G18 -> 1476923 | H20: =02_将来年次投資置換!H18 -> 1486420 | I20: =02_将来年次投資置換!I18 -> 1484101 | ... K20: =02_将来年次投資置換!K18 -> 1469682
A21: 減価償却費 | B21: =02_将来年次投資置換!B25 -> 755782 | C21: =02_将来年次投資置換!C25 -> 754743 | D21: =02_将来年次投資置換!D25 -> 752391 | E21: =02_将来年次投資置換!E25 -> 748869 | F21: =02_将来年次投資置換!F25 -> 748983 | G21: =02_将来年次投資置換!G25 -> 753884 | H21: =02_将来年次投資置換!H25 -> 763070 | I21: =02_将来年次投資置換!I25 -> 760439 | ... K21: =02_将来年次投資置換!K25 -> 745393
A22: 資産減耗・除却費 | B22: =02_将来年次投資置換!B26 -> 0 | C22: =02_将来年次投資置換!C26 -> 0 | D22: =02_将来年次投資置換!D26 -> 0 | E22: =02_将来年次投資置換!E26 -> 0 | F22: =02_将来年次投資置換!F26 -> 0 | G22: =02_将来年次投資置換!G26 -> 0 | H22: =02_将来年次投資置換!H26 -> 0 | I22: =02_将来年次投資置換!I26 -> 0 | ... K22: =02_将来年次投資置換!K26 -> 0
A23: 営業外費用 | B23: =02_将来年次投資置換!B28 -> 128495 | C23: =02_将来年次投資置換!C28 -> 120518 | D23: =02_将来年次投資置換!D28 -> 117139 | E23: =02_将来年次投資置換!E28 -> 115384 | F23: =02_将来年次投資置換!F28 -> 113787 | G23: =02_将来年次投資置換!G28 -> 110821 | H23: =02_将来年次投資置換!H28 -> 108565 | I23: =02_将来年次投資置換!I28 -> 107412 | ... K23: =02_将来年次投資置換!K28 -> 105117
A24: 支払利息 | B24: =02_将来年次投資置換!B29 -> 118910 | C24: =02_将来年次投資置換!C29 -> 111872 | D24: =02_将来年次投資置換!D29 -> 108458 | E24: =02_将来年次投資置換!E29 -> 106668 | F24: =02_将来年次投資置換!F29 -> 105071 | G24: =02_将来年次投資置換!G29 -> 102070 | H24: =02_将来年次投資置換!H29 -> 99779 | I24: =02_将来年次投資置換!I29 -> 98626 | ... K24: =02_将来年次投資置換!K29 -> 96331
A25: 特別損失 | B25: =02_将来年次投資置換!B31 -> 273 | C25: =02_将来年次投資置換!C31 -> 273 | D25: =02_将来年次投資置換!D31 -> 273 | E25: =02_将来年次投資置換!E31 -> 273 | F25: =02_将来年次投資置換!F31 -> 273 | G25: =02_将来年次投資置換!G31 -> 273 | H25: =02_将来年次投資置換!H31 -> 273 | I25: =02_将来年次投資置換!I31 -> 273 | ... K25: =02_将来年次投資置換!K31 -> 273
A26: 収益的支出合計 | B26: =SUM(B20,B23,B25) -> 1608275 | C26: =SUM(C20,C23,C25) -> 1597336 | D26: =SUM(D20,D23,D25) -> 1591913 | E26: =SUM(E20,E23,E25) -> 1586945 | F26: =SUM(F20,F23,F25) -> 1585772 | G26: =SUM(G20,G23,G25) -> 1588017 | H26: =SUM(H20,H23,H25) -> 1595258 | I26: =SUM(I20,I23,I25) -> 1591786 | ... K26: =SUM(K20,K23,K25) -> 1575072
A27: 経常損益 | B27: =SUM(B9,B13)-SUM(B20,B23) -> 8482 | C27: =SUM(C9,C13)-SUM(C20,C23) -> 7410 | D27: =SUM(D9,D13)-SUM(D20,D23) -> -5580 | E27: =SUM(E9,E13)-SUM(E20,E23) -> -18169 | F27: =SUM(F9,F13)-SUM(F20,F23) -> 441645.23 | G27: =SUM(G9,G13)-SUM(G20,G23) -> 429173.98 | H27: =SUM(H9,H13)-SUM(H20,H23) -> 405096.3 | I27: =SUM(I9,I13)-SUM(I20,I23) -> 382385.8 | ... K27: =SUM(K9,K13)-SUM(K20,K23) -> 342395.74
A28: 純損益 | B28: =B27+B16-B25 -> 10785 | C28: =C27+C16-C25 -> 7137 | D28: =D27+D16-D25 -> -5853 | E28: =E27+E16-E25 -> -18442 | F28: =F27+F16-F25 -> 441372.23 | G28: =G27+G16-G25 -> 428900.98 | H28: =H27+H16-H25 -> 404823.3 | I28: =I27+I16-I25 -> 382112.8 | ... K28: =K27+K16-K25 -> 342122.74
A30: 【経営指標】
A31: 経常収支比率 | B31: =IFERROR((SUM(B9,B13)/SUM(B20,B23))*100,0) -> 100.52749 | C31: =IFERROR((SUM(C9,C13)/SUM(C20,C23))*100,0) -> 100.46398 | D31: =IFERROR((SUM(D9,D13)/SUM(D20,D23))*100,0) -> 99.649418 | E31: =IFERROR((SUM(E9,E13)/SUM(E20,E23))*100,0) -> 98.854899 | F31: =IFERROR((SUM(F9,F13)/SUM(F20,F23))*100,0) -> 127.85528 | G31: =IFERROR((SUM(G9,G13)/SUM(G20,G23))*100,0) -> 127.03043 | H31: =IFERROR((SUM(H9,H13)/SUM(H20,H23))*100,0) -> 125.39813 | I31: =IFERROR((SUM(I9,I13)/SUM(I20,I23))*100,0) -> 124.02656 | ... K31: =IFERROR((SUM(K9,K13)/SUM(K20,K23))*100,0) -> 121.74219
A32: 料金回収率（通常） | B32: =IFERROR(B10/B34*100,0) -> 92.822855 | C32: =IFERROR(C10/C34*100,0) -> 92.824907 | D32: =IFERROR(D10/D34*100,0) -> 91.98462 | E32: =IFERROR(E10/E34*100,0) -> 91.172206 | F32: =IFERROR(F10/F34*100,0) -> 108.20746 | G32: =IFERROR(G10/G34*100,0) -> 107.0042 | H32: =IFERROR(H10/H34*100,0) -> 105.48746 | I32: =IFERROR(I10/I34*100,0) -> 104.07468 | ... K32: =IFERROR(K10/K34*100,0) -> 101.63988
A33: 資産維持費込料金回収率 | B33: =IFERROR(B10/B35*100,0) -> 82.57802 | C33: =IFERROR(C10/C35*100,0) -> 82.487679 | D33: =IFERROR(D10/D35*100,0) -> 81.732255 | E33: =IFERROR(E10/E35*100,0) -> 80.999738 | F33: =IFERROR(F10/F35*100,0) -> 96.159205 | G33: =IFERROR(G10/G35*100,0) -> 95.101897 | H33: =IFERROR(H10/H35*100,0) -> 93.797859 | I33: =IFERROR(I10/I35*100,0) -> 92.576783 | ... K33: =IFERROR(K10/K35*100,0) -> 90.446594
A34: 給水原価対象費用 | B34: =SUM(B20,B23)-B14 -> 1326377 | C34: =SUM(C20,C23)-C14 -> 1313084 | D34: =SUM(D20,D23)-D14 -> 1311828 | E34: =SUM(E20,E23)-E14 -> 1310282 | F34: =SUM(F20,F23)-F14 -> 1313331 | G34: =SUM(G20,G23)-G14 -> 1314818 | H34: =SUM(H20,H23)-H14 -> 1320385 | I34: =SUM(I20,I23)-I14 -> 1324925 | ... K34: =SUM(K20,K23)-K14 -> 1329665
A35: 給水原価対象費用＋資産維持費 | B35: =B34+$B$5 -> 1490930.6 | C35: =C34+$B$5 -> 1477637.6 | D35: =D34+$B$5 -> 1476381.6 | E35: =E34+$B$5 -> 1474835.6 | F35: =F34+$B$5 -> 1477884.6 | G35: =G34+$B$5 -> 1479371.6 | H35: =H34+$B$5 -> 1484938.6 | I35: =I34+$B$5 -> 1489478.6 | ... K35: =K34+$B$5 -> 1494218.6
A36: 総括原価回収率（参考） | B36: =IFERROR(B10/(B20+B23-B14-B12-B15+$B$5)*100,0) -> 88.749524 | C36: =IFERROR(C10/(C20+C23-C14-C12-C15+$B$5)*100,0) -> 88.579718 | D36: =IFERROR(D10/(D20+D23-D14-D12-D15+$B$5)*100,0) -> 87.642943 | E36: =IFERROR(E10/(E20+E23-E14-E12-E15+$B$5)*100,0) -> 86.733616 | F36: =IFERROR(F10/(F20+F23-F14-F12-F15+$B$5)*100,0) -> 102.79464 | G36: =IFERROR(G10/(G20+G23-G14-G12-G15+$B$5)*100,0) -> 101.49847 | H36: =IFERROR(H10/(H20+H23-H14-H12-H15+$B$5)*100,0) -> 99.932128 | I36: =IFERROR(I10/(I20+I23-I14-I12-I15+$B$5)*100,0) -> 98.477448 | ... K36: =IFERROR(K10/(K20+K23-K14-K12-K15+$B$5)*100,0) -> 95.973172
A37: 検証：資産維持費込<=通常 | B37: =IF(B33<=B32,"OK","要確認") -> OK | C37: =IF(C33<=C32,"OK","要確認") -> OK | D37: =IF(D33<=D32,"OK","要確認") -> OK | E37: =IF(E33<=E32,"OK","要確認") -> OK | F37: =IF(F33<=F32,"OK","要確認") -> OK | G37: =IF(G33<=G32,"OK","要確認") -> OK | H37: =IF(H33<=H32,"OK","要確認") -> OK | I37: =IF(I33<=I32,"OK","要確認") -> OK | ... K37: =IF(K33<=K32,"OK","要確認") -> OK
A39: 【資本的収入】
A40: 資本的収入 | B40: =02_将来年次投資置換!B34 -> 698941 | C40: =02_将来年次投資置換!C34 -> 664331 | D40: =02_将来年次投資置換!D34 -> 636408 | E40: =02_将来年次投資置換!E34 -> 715698 | F40: =02_将来年次投資置換!F34 -> 627649 | G40: =02_将来年次投資置換!G34 -> 570213 | H40: =02_将来年次投資置換!H34 -> 571338 | I40: =02_将来年次投資置換!I34 -> 536592 | ... K40: =02_将来年次投資置換!K34 -> 365000
A41: 企業債 | B41: =02_将来年次投資置換!B35 -> 329000 | C41: =02_将来年次投資置換!C35 -> 435000 | D41: =02_将来年次投資置換!D35 -> 399000 | E41: =02_将来年次投資置換!E35 -> 400000 | F41: =02_将来年次投資置換!F35 -> 232000 | G41: =02_将来年次投資置換!G35 -> 283000 | H41: =02_将来年次投資置換!H35 -> 286000 | I41: =02_将来年次投資置換!I35 -> 368000 | ... K41: =02_将来年次投資置換!K35 -> 230000
A42: 一般会計負担金 | B42: =02_将来年次投資置換!B36 -> 169041 | C42: =02_将来年次投資置換!C36 -> 164831 | D42: =02_将来年次投資置換!D36 -> 162408 | E42: =02_将来年次投資置換!E36 -> 167998 | F42: =02_将来年次投資置換!F36 -> 173649 | G42: =02_将来年次投資置換!G36 -> 182213 | H42: =02_将来年次投資置換!H36 -> 180338 | I42: =02_将来年次投資置換!I36 -> 168592 | ... K42: =02_将来年次投資置換!K36 -> 135000
A43: 一般会計出資金 | B43: =02_将来年次投資置換!B37 -> 0 | C43: =02_将来年次投資置換!C37 -> 0 | D43: =02_将来年次投資置換!D37 -> 0 | E43: =02_将来年次投資置換!E37 -> 0 | F43: =02_将来年次投資置換!F37 -> 0 | G43: =02_将来年次投資置換!G37 -> 0 | H43: =02_将来年次投資置換!H37 -> 0 | I43: =02_将来年次投資置換!I37 -> 0 | ... K43: =02_将来年次投資置換!K37 -> 0
A44: 国庫補助金 | B44: =02_将来年次投資置換!B38 -> 0 | C44: =02_将来年次投資置換!C38 -> 64500 | D44: =02_将来年次投資置換!D38 -> 75000 | E44: =02_将来年次投資置換!E38 -> 147700 | F44: =02_将来年次投資置換!F38 -> 222000 | G44: =02_将来年次投資置換!G38 -> 105000 | H44: =02_将来年次投資置換!H38 -> 105000 | I44: =02_将来年次投資置換!I38 -> 0 | ... K44: =02_将来年次投資置換!K38 -> 0
A45: 固定資産売却代金 | B45: =02_将来年次投資置換!B39 -> 0 | C45: =02_将来年次投資置換!C39 -> 0 | D45: =02_将来年次投資置換!D39 -> 0 | E45: =02_将来年次投資置換!E39 -> 0 | F45: =02_将来年次投資置換!F39 -> 0 | G45: =02_将来年次投資置換!G39 -> 0 | H45: =02_将来年次投資置換!H39 -> 0 | I45: =02_将来年次投資置換!I39 -> 0 | ... K45: =02_将来年次投資置換!K39 -> 0
A46: 工事負担金 | B46: =02_将来年次投資置換!B40 -> 200900 | C46: =02_将来年次投資置換!C40 -> 0 | D46: =02_将来年次投資置換!D40 -> 0 | E46: =02_将来年次投資置換!E40 -> 0 | F46: =02_将来年次投資置換!F40 -> 0 | G46: =02_将来年次投資置換!G40 -> 0 | H46: =02_将来年次投資置換!H40 -> 0 | I46: =02_将来年次投資置換!I40 -> 0 | ... K46: =02_将来年次投資置換!K40 -> 0
A47: その他・調整 | B47: =02_将来年次投資置換!B41 -> 0 | C47: =02_将来年次投資置換!C41 -> 0 | D47: =02_将来年次投資置換!D41 -> 0 | E47: =02_将来年次投資置換!E41 -> 0 | F47: =02_将来年次投資置換!F41 -> 0 | G47: =02_将来年次投資置換!G41 -> 0 | H47: =02_将来年次投資置換!H41 -> 0 | I47: =02_将来年次投資置換!I41 -> 0 | ... K47: =02_将来年次投資置換!K41 -> 0
A49: 【資本的支出】
A50: 資本的支出 | B50: =02_将来年次投資置換!B44 -> 1123770 | C50: =02_将来年次投資置換!C44 -> 1684483 | D50: =02_将来年次投資置換!D44 -> 1131274 | E50: =02_将来年次投資置換!E44 -> 1433926 | F50: =02_将来年次投資置換!F44 -> 1196811 | G50: =02_将来年次投資置換!G44 -> 965587 | H50: =02_将来年次投資置換!H44 -> 945526 | I50: =02_将来年次投資置換!I44 -> 916106 | ... K50: =02_将来年次投資置換!K44 -> 763357
A51: 建設改良費 | B51: =02_将来年次投資置換!B45 -> 268741 | C51: =02_将来年次投資置換!C45 -> 888542 | D51: =02_将来年次投資置換!D45 -> 403455 | E51: =02_将来年次投資置換!E45 -> 761285 | F51: =02_将来年次投資置換!F45 -> 558200 | G51: =02_将来年次投資置換!G45 -> 389300 | H51: =02_将来年次投資置換!H45 -> 382930 | I51: =02_将来年次投資置換!I45 -> 368500 | ... K51: =02_将来年次投資置換!K45 -> 230500
A52: 企業債償還金 | B52: =02_将来年次投資置換!B46 -> 855029 | C52: =02_将来年次投資置換!C46 -> 795941 | D52: =02_将来年次投資置換!D46 -> 727819 | E52: =02_将来年次投資置換!E46 -> 672641 | F52: =02_将来年次投資置換!F46 -> 638611 | G52: =02_将来年次投資置換!G46 -> 576287 | H52: =02_将来年次投資置換!H46 -> 562596 | I52: =02_将来年次投資置換!I46 -> 547606 | ... K52: =02_将来年次投資置換!K46 -> 532857
A53: その他資本的支出 | B53: =02_将来年次投資置換!B47 -> 0 | C53: =02_将来年次投資置換!C47 -> 0 | D53: =02_将来年次投資置換!D47 -> 0 | E53: =02_将来年次投資置換!E47 -> 0 | F53: =02_将来年次投資置換!F47 -> 0 | G53: =02_将来年次投資置換!G47 -> 0 | H53: =02_将来年次投資置換!H47 -> 0 | I53: =02_将来年次投資置換!I47 -> 0 | ... K53: =02_将来年次投資置換!K47 -> 0
A54: 資本的収支不足額（収入－支出） | B54: =B40-B50 -> -424829 | C54: =C40-C50 -> -1020152 | D54: =D40-D50 -> -494866 | E54: =E40-E50 -> -718228 | F54: =F40-F50 -> -569162 | G54: =G40-G50 -> -395374 | H54: =H40-H50 -> -374188 | I54: =I40-I50 -> -379514 | ... K54: =K40-K50 -> -398357
A56: 【現預金・4条財源】
A57: 補てん可能財源相当（簡便CF） | B57: =B28+B21+B22-B14 -> 484942 | C57: =C28+C21+C22-C14 -> 477901 | D57: =D28+D21+D22-D14 -> 466726 | E57: =E28+E21+E22-E14 -> 454037 | F57: =F28+F21+F22-F14 -> 918187.23 | G57: =G28+G21+G22-G14 -> 909858.98 | H57: =H28+H21+H22-H14 -> 893293.3 | I57: =I28+I21+I22-I14 -> 875963.8 | ... K57: =K28+K21+K22-K14 -> 842381.74
A58: 資本的収支不足額（再掲） | B58: =B54 -> -424829 | C58: =C54 -> -1020152 | D58: =D54 -> -494866 | E58: =E54 -> -718228 | F58: =F54 -> -569162 | G58: =G54 -> -395374 | H58: =H54 -> -374188 | I58: =I54 -> -379514 | ... K58: =K54 -> -398357
A59: 年度末現預金残高 | B59: =00_前提・検証!$B$6 -> 242588 | C59: =B59+C57+C58 -> -299663 | D59: =C59+D57+D58 -> -327803 | E59: =D59+E57+E58 -> -591994 | F59: =E59+F57+F58 -> -242968.77 | G59: =F59+G57+G58 -> 271516.21 | H59: =G59+H57+H58 -> 790621.51 | I59: =H59+I57+I58 -> 1287071.3 | J59: =I59+J57+J58 -> 1740011.4 | K59: =J59+K57+K58 -> 2184036.1
A60: 最低現金目安との差額 | B60: =B59-00_前提・検証!$B$7 -> -57412 | C60: =C59-00_前提・検証!$B$7 -> -599663 | D60: =D59-00_前提・検証!$B$7 -> -627803 | E60: =E59-00_前提・検証!$B$7 -> -891994 | F60: =F59-00_前提・検証!$B$7 -> -542968.77 | G60: =G59-00_前提・検証!$B$7 -> -28483.79 | H60: =H59-00_前提・検証!$B$7 -> 490621.51 | I60: =I59-00_前提・検証!$B$7 -> 987071.31 | ... K60: =K59-00_前提・検証!$B$7 -> 1884036.1

Sheet SIM_置換後_2%
A1: SIM_置換後_2%
A2: 単位：千円、比率は％。料金改定率はR11〜R15の総括原価回収を基礎に算定し、R11以降の給水収益へ反映。
A3: 区分 | B3: 令和7年度 | C3: 令和8年度 | D3: 令和9年度 | E3: 令和10年度 | F3: 令和11年度 | G3: 令和12年度 | H3: 令和13年度 | I3: 令和14年度 | J3: 令和15年度 | K3: 令和16年度
A4: 資産維持費率 | B4: 0.02
A5: 年額資産維持費（千円） | B5: =00_前提・検証!$B$2*$B$4 -> 329107.28
A6: 料金改定率（R11以降・試算） | B6: =MAX(0,(SUMPRODUCT((02_将来年次投資置換!F18:J18+02_将来年次投資置換!F28:J28-02_将来年次投資置換!F12:J12-02_将来年次投資置換!F8:J8-02_将来年次投資置換!F11:J11+$B$5)-02_将来年次投資置換!F7:J7)/SUM(02_将来年次投資置換!F7:J7))) -> 0.34357465
A8: 【収益的収入】
A9: 営業収益 | B9: =SUM(B10:B12) -> 1261575 | C9: =SUM(C10:C12) -> 1249336 | D9: =SUM(D10:D12) -> 1237293 | E9: =SUM(E10:E12) -> 1225373 | F9: =SUM(F10:F12) -> 2026242.1 | G9: =SUM(G10:G12) -> 2006437.2 | H9: =SUM(H10:H12) -> 1986831.4 | I9: =SUM(I10:I12) -> 1967423.9 | ... K9: =SUM(K10:K12) -> 1929197.5
A10: 給水収益（改定反映後） | B10: =02_将来年次投資置換!B7*IF(7>=11,1+$B$6,1) -> 1231181 | C10: =02_将来年次投資置換!C7*IF(8>=11,1+$B$6,1) -> 1218869 | D10: =02_将来年次投資置換!D7*IF(9>=11,1+$B$6,1) -> 1206680 | E10: =02_将来年次投資置換!E7*IF(10>=11,1+$B$6,1) -> 1194613 | F10: =02_将来年次投資置換!F7*IF(11>=11,1+$B$6,1) -> 1589000.1 | G10: =02_将来年次投資置換!G7*IF(12>=11,1+$B$6,1) -> 1573109.6 | H10: =02_将来年次投資置換!H7*IF(13>=11,1+$B$6,1) -> 1557377.7 | I10: =02_将来年次投資置換!I7*IF(14>=11,1+$B$6,1) -> 1541803 | J10: =02_将来年次投資置換!J7*IF(15>=11,1+$B$6,1) -> 1526384.1 | K10: =02_将来年次投資置換!K7*IF(16>=11,1+$B$6,1) -> 1511119.8
A11: うち料金改定増収 | B11: =B10-02_将来年次投資置換!B7 -> 0 | C11: =C10-02_将来年次投資置換!C7 -> 0 | D11: =D10-02_将来年次投資置換!D7 -> 0 | E11: =E10-02_将来年次投資置換!E7 -> 0 | F11: =F10-02_将来年次投資置換!F7 -> 406334.05 | G11: =G10-02_将来年次投資置換!G7 -> 402270.6 | H11: =H10-02_将来年次投資置換!H7 -> 398247.68 | I11: =I10-02_将来年次投資置換!I7 -> 394264.96 | ... K11: =K10-02_将来年次投資置換!K7 -> 386418.75
A12: その他営業収益 | B12: =02_将来年次投資置換!B8 -> 30394 | C12: =02_将来年次投資置換!C8 -> 30467 | D12: =02_将来年次投資置換!D8 -> 30613 | E12: =02_将来年次投資置換!E8 -> 30760 | F12: =02_将来年次投資置換!F8 -> 30908 | G12: =02_将来年次投資置換!G8 -> 31057 | H12: =02_将来年次投資置換!H8 -> 31206 | I12: =02_将来年次投資置換!I8 -> 31356 | ... K12: =02_将来年次投資置換!K8 -> 31659
A13: 営業外収益 | B13: =02_将来年次投資置換!B9 -> 354909 | C13: =02_将来年次投資置換!C9 -> 355137 | D13: =02_将来年次投資置換!D9 -> 348767 | E13: =02_将来年次投資置換!E9 -> 343130 | F13: =02_将来年次投資置換!F9 -> 336658 | G13: =02_将来年次投資置換!G9 -> 342879 | H13: =02_将来年次投資置換!H9 -> 342324 | I13: =02_将来年次投資置換!I9 -> 332258 | ... K13: =02_将来年次投資置換!K9 -> 307297
A14: 長期前受金戻入 | B14: =02_将来年次投資置換!B12 -> 281625 | C14: =02_将来年次投資置換!C12 -> 283979 | D14: =02_将来年次投資置換!D12 -> 279812 | E14: =02_将来年次投資置換!E12 -> 276390 | F14: =02_将来年次投資置換!F12 -> 272168 | G14: =02_将来年次投資置換!G12 -> 272926 | H14: =02_将来年次投資置換!H12 -> 274600 | I14: =02_将来年次投資置換!I12 -> 266588 | ... K14: =02_将来年次投資置換!K12 -> 245134
A15: 繰入金・負担金等 | B15: =02_将来年次投資置換!B11 -> 73283 | C15: =02_将来年次投資置換!C11 -> 71157 | D15: =02_将来年次投資置換!D11 -> 68955 | E15: =02_将来年次投資置換!E11 -> 66740 | F15: =02_将来年次投資置換!F11 -> 64490 | G15: =02_将来年次投資置換!G11 -> 62175 | H15: =02_将来年次投資置換!H11 -> 59946 | I15: =02_将来年次投資置換!I11 -> 57892 | ... K15: =02_将来年次投資置換!K11 -> 54385
A16: 特別利益 | B16: =02_将来年次投資置換!B14 -> 2576 | C16: =02_将来年次投資置換!C14 -> 0 | D16: =02_将来年次投資置換!D14 -> 0 | E16: =02_将来年次投資置換!E14 -> 0 | F16: =02_将来年次投資置換!F14 -> 0 | G16: =02_将来年次投資置換!G14 -> 0 | H16: =02_将来年次投資置換!H14 -> 0 | I16: =02_将来年次投資置換!I14 -> 0 | ... K16: =02_将来年次投資置換!K14 -> 0
A17: 収益的収入合計 | B17: =SUM(B9,B13,B16) -> 1619060 | C17: =SUM(C9,C13,C16) -> 1604473 | D17: =SUM(D9,D13,D16) -> 1586060 | E17: =SUM(E9,E13,E16) -> 1568503 | F17: =SUM(F9,F13,F16) -> 2362900.1 | G17: =SUM(G9,G13,G16) -> 2349316.2 | H17: =SUM(H9,H13,H16) -> 2329155.4 | I17: =SUM(I9,I13,I16) -> 2299681.9 | ... K17: =SUM(K9,K13,K16) -> 2236494.5
A19: 【収益的支出】
A20: 営業費用 | B20: =02_将来年次投資置換!B18 -> 1479507 | C20: =02_将来年次投資置換!C18 -> 1476545 | D20: =02_将来年次投資置換!D18 -> 1474501 | E20: =02_将来年次投資置換!E18 -> 1471288 | F20: =02_将来年次投資置換!F18 -> 1471712 | G20: =02_将来年次投資置換!G18 -> 1476923 | H20: =02_将来年次投資置換!H18 -> 1486420 | I20: =02_将来年次投資置換!I18 -> 1484101 | ... K20: =02_将来年次投資置換!K18 -> 1469682
A21: 減価償却費 | B21: =02_将来年次投資置換!B25 -> 755782 | C21: =02_将来年次投資置換!C25 -> 754743 | D21: =02_将来年次投資置換!D25 -> 752391 | E21: =02_将来年次投資置換!E25 -> 748869 | F21: =02_将来年次投資置換!F25 -> 748983 | G21: =02_将来年次投資置換!G25 -> 753884 | H21: =02_将来年次投資置換!H25 -> 763070 | I21: =02_将来年次投資置換!I25 -> 760439 | ... K21: =02_将来年次投資置換!K25 -> 745393
A22: 資産減耗・除却費 | B22: =02_将来年次投資置換!B26 -> 0 | C22: =02_将来年次投資置換!C26 -> 0 | D22: =02_将来年次投資置換!D26 -> 0 | E22: =02_将来年次投資置換!E26 -> 0 | F22: =02_将来年次投資置換!F26 -> 0 | G22: =02_将来年次投資置換!G26 -> 0 | H22: =02_将来年次投資置換!H26 -> 0 | I22: =02_将来年次投資置換!I26 -> 0 | ... K22: =02_将来年次投資置換!K26 -> 0
A23: 営業外費用 | B23: =02_将来年次投資置換!B28 -> 128495 | C23: =02_将来年次投資置換!C28 -> 120518 | D23: =02_将来年次投資置換!D28 -> 117139 | E23: =02_将来年次投資置換!E28 -> 115384 | F23: =02_将来年次投資置換!F28 -> 113787 | G23: =02_将来年次投資置換!G28 -> 110821 | H23: =02_将来年次投資置換!H28 -> 108565 | I23: =02_将来年次投資置換!I28 -> 107412 | ... K23: =02_将来年次投資置換!K28 -> 105117
A24: 支払利息 | B24: =02_将来年次投資置換!B29 -> 118910 | C24: =02_将来年次投資置換!C29 -> 111872 | D24: =02_将来年次投資置換!D29 -> 108458 | E24: =02_将来年次投資置換!E29 -> 106668 | F24: =02_将来年次投資置換!F29 -> 105071 | G24: =02_将来年次投資置換!G29 -> 102070 | H24: =02_将来年次投資置換!H29 -> 99779 | I24: =02_将来年次投資置換!I29 -> 98626 | ... K24: =02_将来年次投資置換!K29 -> 96331
A25: 特別損失 | B25: =02_将来年次投資置換!B31 -> 273 | C25: =02_将来年次投資置換!C31 -> 273 | D25: =02_将来年次投資置換!D31 -> 273 | E25: =02_将来年次投資置換!E31 -> 273 | F25: =02_将来年次投資置換!F31 -> 273 | G25: =02_将来年次投資置換!G31 -> 273 | H25: =02_将来年次投資置換!H31 -> 273 | I25: =02_将来年次投資置換!I31 -> 273 | ... K25: =02_将来年次投資置換!K31 -> 273
A26: 収益的支出合計 | B26: =SUM(B20,B23,B25) -> 1608275 | C26: =SUM(C20,C23,C25) -> 1597336 | D26: =SUM(D20,D23,D25) -> 1591913 | E26: =SUM(E20,E23,E25) -> 1586945 | F26: =SUM(F20,F23,F25) -> 1585772 | G26: =SUM(G20,G23,G25) -> 1588017 | H26: =SUM(H20,H23,H25) -> 1595258 | I26: =SUM(I20,I23,I25) -> 1591786 | ... K26: =SUM(K20,K23,K25) -> 1575072
A27: 経常損益 | B27: =SUM(B9,B13)-SUM(B20,B23) -> 8482 | C27: =SUM(C9,C13)-SUM(C20,C23) -> 7410 | D27: =SUM(D9,D13)-SUM(D20,D23) -> -5580 | E27: =SUM(E9,E13)-SUM(E20,E23) -> -18169 | F27: =SUM(F9,F13)-SUM(F20,F23) -> 777401.11 | G27: =SUM(G9,G13)-SUM(G20,G23) -> 761572.19 | H27: =SUM(H9,H13)-SUM(H20,H23) -> 734170.36 | I27: =SUM(I9,I13)-SUM(I20,I23) -> 708168.93 | ... K27: =SUM(K9,K13)-SUM(K20,K23) -> 661695.5
A28: 純損益 | B28: =B27+B16-B25 -> 10785 | C28: =C27+C16-C25 -> 7137 | D28: =D27+D16-D25 -> -5853 | E28: =E27+E16-E25 -> -18442 | F28: =F27+F16-F25 -> 777128.11 | G28: =G27+G16-G25 -> 761299.19 | H28: =H27+H16-H25 -> 733897.36 | I28: =I27+I16-I25 -> 707895.93 | ... K28: =K27+K16-K25 -> 661422.5
A30: 【経営指標】
A31: 経常収支比率 | B31: =IFERROR((SUM(B9,B13)/SUM(B20,B23))*100,0) -> 100.52749 | C31: =IFERROR((SUM(C9,C13)/SUM(C20,C23))*100,0) -> 100.46398 | D31: =IFERROR((SUM(D9,D13)/SUM(D20,D23))*100,0) -> 99.649418 | E31: =IFERROR((SUM(E9,E13)/SUM(E20,E23))*100,0) -> 98.854899 | F31: =IFERROR((SUM(F9,F13)/SUM(F20,F23))*100,0) -> 149.03195 | G31: =IFERROR((SUM(G9,G13)/SUM(G20,G23))*100,0) -> 147.96568 | H31: =IFERROR((SUM(H9,H13)/SUM(H20,H23))*100,0) -> 146.02992 | I31: =IFERROR((SUM(I9,I13)/SUM(I20,I23))*100,0) -> 144.49658 | ... K31: =IFERROR((SUM(K9,K13)/SUM(K20,K23))*100,0) -> 142.01777
A32: 料金回収率（通常） | B32: =IFERROR(B10/B34*100,0) -> 92.822855 | C32: =IFERROR(C10/C34*100,0) -> 92.824907 | D32: =IFERROR(D10/D34*100,0) -> 91.98462 | E32: =IFERROR(E10/E34*100,0) -> 91.172206 | F32: =IFERROR(F10/F34*100,0) -> 120.99007 | G32: =IFERROR(G10/G34*100,0) -> 119.64467 | H32: =IFERROR(H10/H34*100,0) -> 117.94876 | I32: =IFERROR(I10/I34*100,0) -> 116.36907 | ... K32: =IFERROR(K10/K34*100,0) -> 113.64665
A33: 資産維持費込料金回収率 | B33: =IFERROR(B10/B35*100,0) -> 74.369839 | C33: =IFERROR(C10/C35*100,0) -> 74.222109 | D33: =IFERROR(D10/D35*100,0) -> 73.536112 | E33: =IFERROR(E10/E35*100,0) -> 72.869392 | F33: =IFERROR(F10/F35*100,0) -> 96.746409 | G33: =IFERROR(G10/G35*100,0) -> 95.692281 | H33: =IFERROR(H10/H35*100,0) -> 94.415579 | I33: =IFERROR(I10/I35*100,0) -> 93.214805 | ... K33: =IFERROR(K10/K35*100,0) -> 91.098686
A34: 給水原価対象費用 | B34: =SUM(B20,B23)-B14 -> 1326377 | C34: =SUM(C20,C23)-C14 -> 1313084 | D34: =SUM(D20,D23)-D14 -> 1311828 | E34: =SUM(E20,E23)-E14 -> 1310282 | F34: =SUM(F20,F23)-F14 -> 1313331 | G34: =SUM(G20,G23)-G14 -> 1314818 | H34: =SUM(H20,H23)-H14 -> 1320385 | I34: =SUM(I20,I23)-I14 -> 1324925 | ... K34: =SUM(K20,K23)-K14 -> 1329665
A35: 給水原価対象費用＋資産維持費 | B35: =B34+$B$5 -> 1655484.3 | C35: =C34+$B$5 -> 1642191.3 | D35: =D34+$B$5 -> 1640935.3 | E35: =E34+$B$5 -> 1639389.3 | F35: =F34+$B$5 -> 1642438.3 | G35: =G34+$B$5 -> 1643925.3 | H35: =H34+$B$5 -> 1649492.3 | I35: =I34+$B$5 -> 1654032.3 | ... K35: =K34+$B$5 -> 1658772.3
A36: 総括原価回収率（参考） | B36: =IFERROR(B10/(B20+B23-B14-B12-B15+$B$5)*100,0) -> 79.338525 | C36: =IFERROR(C10/(C20+C23-C14-C12-C15+$B$5)*100,0) -> 79.118193 | D36: =IFERROR(D10/(D20+D23-D14-D12-D15+$B$5)*100,0) -> 78.286338 | E36: =IFERROR(E10/(E20+E23-E14-E12-E15+$B$5)*100,0) -> 77.477223 | F36: =IFERROR(F10/(F20+F23-F14-F12-F15+$B$5)*100,0) -> 102.71226 | G36: =IFERROR(G10/(G20+G23-G14-G12-G15+$B$5)*100,0) -> 101.44557 | H36: =IFERROR(H10/(H20+H23-H14-H12-H15+$B$5)*100,0) -> 99.938229 | I36: =IFERROR(I10/(I20+I23-I14-I12-I15+$B$5)*100,0) -> 98.531343 | ... K36: =IFERROR(K10/(K20+K23-K14-K12-K15+$B$5)*100,0) -> 96.082697
A37: 検証：資産維持費込<=通常 | B37: =IF(B33<=B32,"OK","要確認") -> OK | C37: =IF(C33<=C32,"OK","要確認") -> OK | D37: =IF(D33<=D32,"OK","要確認") -> OK | E37: =IF(E33<=E32,"OK","要確認") -> OK | F37: =IF(F33<=F32,"OK","要確認") -> OK | G37: =IF(G33<=G32,"OK","要確認") -> OK | H37: =IF(H33<=H32,"OK","要確認") -> OK | I37: =IF(I33<=I32,"OK","要確認") -> OK | ... K37: =IF(K33<=K32,"OK","要確認") -> OK
A39: 【資本的収入】
A40: 資本的収入 | B40: =02_将来年次投資置換!B34 -> 698941 | C40: =02_将来年次投資置換!C34 -> 664331 | D40: =02_将来年次投資置換!D34 -> 636408 | E40: =02_将来年次投資置換!E34 -> 715698 | F40: =02_将来年次投資置換!F34 -> 627649 | G40: =02_将来年次投資置換!G34 -> 570213 | H40: =02_将来年次投資置換!H34 -> 571338 | I40: =02_将来年次投資置換!I34 -> 536592 | ... K40: =02_将来年次投資置換!K34 -> 365000
A41: 企業債 | B41: =02_将来年次投資置換!B35 -> 329000 | C41: =02_将来年次投資置換!C35 -> 435000 | D41: =02_将来年次投資置換!D35 -> 399000 | E41: =02_将来年次投資置換!E35 -> 400000 | F41: =02_将来年次投資置換!F35 -> 232000 | G41: =02_将来年次投資置換!G35 -> 283000 | H41: =02_将来年次投資置換!H35 -> 286000 | I41: =02_将来年次投資置換!I35 -> 368000 | ... K41: =02_将来年次投資置換!K35 -> 230000
A42: 一般会計負担金 | B42: =02_将来年次投資置換!B36 -> 169041 | C42: =02_将来年次投資置換!C36 -> 164831 | D42: =02_将来年次投資置換!D36 -> 162408 | E42: =02_将来年次投資置換!E36 -> 167998 | F42: =02_将来年次投資置換!F36 -> 173649 | G42: =02_将来年次投資置換!G36 -> 182213 | H42: =02_将来年次投資置換!H36 -> 180338 | I42: =02_将来年次投資置換!I36 -> 168592 | ... K42: =02_将来年次投資置換!K36 -> 135000
A43: 一般会計出資金 | B43: =02_将来年次投資置換!B37 -> 0 | C43: =02_将来年次投資置換!C37 -> 0 | D43: =02_将来年次投資置換!D37 -> 0 | E43: =02_将来年次投資置換!E37 -> 0 | F43: =02_将来年次投資置換!F37 -> 0 | G43: =02_将来年次投資置換!G37 -> 0 | H43: =02_将来年次投資置換!H37 -> 0 | I43: =02_将来年次投資置換!I37 -> 0 | ... K43: =02_将来年次投資置換!K37 -> 0
A44: 国庫補助金 | B44: =02_将来年次投資置換!B38 -> 0 | C44: =02_将来年次投資置換!C38 -> 64500 | D44: =02_将来年次投資置換!D38 -> 75000 | E44: =02_将来年次投資置換!E38 -> 147700 | F44: =02_将来年次投資置換!F38 -> 222000 | G44: =02_将来年次投資置換!G38 -> 105000 | H44: =02_将来年次投資置換!H38 -> 105000 | I44: =02_将来年次投資置換!I38 -> 0 | ... K44: =02_将来年次投資置換!K38 -> 0
A45: 固定資産売却代金 | B45: =02_将来年次投資置換!B39 -> 0 | C45: =02_将来年次投資置換!C39 -> 0 | D45: =02_将来年次投資置換!D39 -> 0 | E45: =02_将来年次投資置換!E39 -> 0 | F45: =02_将来年次投資置換!F39 -> 0 | G45: =02_将来年次投資置換!G39 -> 0 | H45: =02_将来年次投資置換!H39 -> 0 | I45: =02_将来年次投資置換!I39 -> 0 | ... K45: =02_将来年次投資置換!K39 -> 0
A46: 工事負担金 | B46: =02_将来年次投資置換!B40 -> 200900 | C46: =02_将来年次投資置換!C40 -> 0 | D46: =02_将来年次投資置換!D40 -> 0 | E46: =02_将来年次投資置換!E40 -> 0 | F46: =02_将来年次投資置換!F40 -> 0 | G46: =02_将来年次投資置換!G40 -> 0 | H46: =02_将来年次投資置換!H40 -> 0 | I46: =02_将来年次投資置換!I40 -> 0 | ... K46: =02_将来年次投資置換!K40 -> 0
A47: その他・調整 | B47: =02_将来年次投資置換!B41 -> 0 | C47: =02_将来年次投資置換!C41 -> 0 | D47: =02_将来年次投資置換!D41 -> 0 | E47: =02_将来年次投資置換!E41 -> 0 | F47: =02_将来年次投資置換!F41 -> 0 | G47: =02_将来年次投資置換!G41 -> 0 | H47: =02_将来年次投資置換!H41 -> 0 | I47: =02_将来年次投資置換!I41 -> 0 | ... K47: =02_将来年次投資置換!K41 -> 0
A49: 【資本的支出】
A50: 資本的支出 | B50: =02_将来年次投資置換!B44 -> 1123770 | C50: =02_将来年次投資置換!C44 -> 1684483 | D50: =02_将来年次投資置換!D44 -> 1131274 | E50: =02_将来年次投資置換!E44 -> 1433926 | F50: =02_将来年次投資置換!F44 -> 1196811 | G50: =02_将来年次投資置換!G44 -> 965587 | H50: =02_将来年次投資置換!H44 -> 945526 | I50: =02_将来年次投資置換!I44 -> 916106 | ... K50: =02_将来年次投資置換!K44 -> 763357
A51: 建設改良費 | B51: =02_将来年次投資置換!B45 -> 268741 | C51: =02_将来年次投資置換!C45 -> 888542 | D51: =02_将来年次投資置換!D45 -> 403455 | E51: =02_将来年次投資置換!E45 -> 761285 | F51: =02_将来年次投資置換!F45 -> 558200 | G51: =02_将来年次投資置換!G45 -> 389300 | H51: =02_将来年次投資置換!H45 -> 382930 | I51: =02_将来年次投資置換!I45 -> 368500 | ... K51: =02_将来年次投資置換!K45 -> 230500
A52: 企業債償還金 | B52: =02_将来年次投資置換!B46 -> 855029 | C52: =02_将来年次投資置換!C46 -> 795941 | D52: =02_将来年次投資置換!D46 -> 727819 | E52: =02_将来年次投資置換!E46 -> 672641 | F52: =02_将来年次投資置換!F46 -> 638611 | G52: =02_将来年次投資置換!G46 -> 576287 | H52: =02_将来年次投資置換!H46 -> 562596 | I52: =02_将来年次投資置換!I46 -> 547606 | ... K52: =02_将来年次投資置換!K46 -> 532857
A53: その他資本的支出 | B53: =02_将来年次投資置換!B47 -> 0 | C53: =02_将来年次投資置換!C47 -> 0 | D53: =02_将来年次投資置換!D47 -> 0 | E53: =02_将来年次投資置換!E47 -> 0 | F53: =02_将来年次投資置換!F47 -> 0 | G53: =02_将来年次投資置換!G47 -> 0 | H53: =02_将来年次投資置換!H47 -> 0 | I53: =02_将来年次投資置換!I47 -> 0 | ... K53: =02_将来年次投資置換!K47 -> 0
A54: 資本的収支不足額（収入－支出） | B54: =B40-B50 -> -424829 | C54: =C40-C50 -> -1020152 | D54: =D40-D50 -> -494866 | E54: =E40-E50 -> -718228 | F54: =F40-F50 -> -569162 | G54: =G40-G50 -> -395374 | H54: =H40-H50 -> -374188 | I54: =I40-I50 -> -379514 | ... K54: =K40-K50 -> -398357
A56: 【現預金・4条財源】
A57: 補てん可能財源相当（簡便CF） | B57: =B28+B21+B22-B14 -> 484942 | C57: =C28+C21+C22-C14 -> 477901 | D57: =D28+D21+D22-D14 -> 466726 | E57: =E28+E21+E22-E14 -> 454037 | F57: =F28+F21+F22-F14 -> 1253943.1 | G57: =G28+G21+G22-G14 -> 1242257.2 | H57: =H28+H21+H22-H14 -> 1222367.4 | I57: =I28+I21+I22-I14 -> 1201746.9 | ... K57: =K28+K21+K22-K14 -> 1161681.5
A58: 資本的収支不足額（再掲） | B58: =B54 -> -424829 | C58: =C54 -> -1020152 | D58: =D54 -> -494866 | E58: =E54 -> -718228 | F58: =F54 -> -569162 | G58: =G54 -> -395374 | H58: =H54 -> -374188 | I58: =I54 -> -379514 | ... K58: =K54 -> -398357
A59: 年度末現預金残高 | B59: =00_前提・検証!$B$6 -> 242588 | C59: =B59+C57+C58 -> -299663 | D59: =C59+D57+D58 -> -327803 | E59: =D59+E57+E58 -> -591994 | F59: =E59+F57+F58 -> 92787.109 | G59: =F59+G57+G58 -> 939670.3 | H59: =G59+H57+H58 -> 1787849.7 | I59: =H59+I57+I58 -> 2610082.6 | J59: =I59+J57+J58 -> 3385547.8 | K59: =J59+K57+K58 -> 4148872.3
A60: 最低現金目安との差額 | B60: =B59-00_前提・検証!$B$7 -> -57412 | C60: =C59-00_前提・検証!$B$7 -> -599663 | D60: =D59-00_前提・検証!$B$7 -> -627803 | E60: =E59-00_前提・検証!$B$7 -> -891994 | F60: =F59-00_前提・検証!$B$7 -> -207212.89 | G60: =G59-00_前提・検証!$B$7 -> 639670.3 | H60: =H59-00_前提・検証!$B$7 -> 1487849.7 | I60: =I59-00_前提・検証!$B$7 -> 2310082.6 | ... K60: =K59-00_前提・検証!$B$7 -> 3848872.3

Sheet SIM_置換後_3%
A1: SIM_置換後_3%
A2: 単位：千円、比率は％。料金改定率はR11〜R15の総括原価回収を基礎に算定し、R11以降の給水収益へ反映。
A3: 区分 | B3: 令和7年度 | C3: 令和8年度 | D3: 令和9年度 | E3: 令和10年度 | F3: 令和11年度 | G3: 令和12年度 | H3: 令和13年度 | I3: 令和14年度 | J3: 令和15年度 | K3: 令和16年度
A4: 資産維持費率 | B4: 0.03
A5: 年額資産維持費（千円） | B5: =00_前提・検証!$B$2*$B$4 -> 493660.92
A6: 料金改定率（R11以降・試算） | B6: =MAX(0,(SUMPRODUCT((02_将来年次投資置換!F18:J18+02_将来年次投資置換!F28:J28-02_将来年次投資置換!F12:J12-02_将来年次投資置換!F8:J8-02_将来年次投資置換!F11:J11+$B$5)-02_将来年次投資置換!F7:J7)/SUM(02_将来年次投資置換!F7:J7))) -> 0.48552338
A8: 【収益的収入】
A9: 営業収益 | B9: =SUM(B10:B12) -> 1261575 | C9: =SUM(C10:C12) -> 1249336 | D9: =SUM(D10:D12) -> 1237293 | E9: =SUM(E10:E12) -> 1225373 | F9: =SUM(F10:F12) -> 2361998 | G9: =SUM(G10:G12) -> 2338835.4 | H9: =SUM(H10:H12) -> 2315905.4 | I9: =SUM(I10:I12) -> 2293207.1 | ... K9: =SUM(K10:K12) -> 2248497.3
A10: 給水収益（改定反映後） | B10: =02_将来年次投資置換!B7*IF(7>=11,1+$B$6,1) -> 1231181 | C10: =02_将来年次投資置換!C7*IF(8>=11,1+$B$6,1) -> 1218869 | D10: =02_将来年次投資置換!D7*IF(9>=11,1+$B$6,1) -> 1206680 | E10: =02_将来年次投資置換!E7*IF(10>=11,1+$B$6,1) -> 1194613 | F10: =02_将来年次投資置換!F7*IF(11>=11,1+$B$6,1) -> 1756878 | G10: =02_将来年次投資置換!G7*IF(12>=11,1+$B$6,1) -> 1739308.7 | H10: =02_将来年次投資置換!H7*IF(13>=11,1+$B$6,1) -> 1721914.7 | I10: =02_将来年次投資置換!I7*IF(14>=11,1+$B$6,1) -> 1704694.5 | J10: =02_将来年次投資置換!J7*IF(15>=11,1+$B$6,1) -> 1687646.7 | K10: =02_将来年次投資置換!K7*IF(16>=11,1+$B$6,1) -> 1670769.6
A11: うち料金改定増収 | B11: =B10-02_将来年次投資置換!B7 -> 0 | C11: =C10-02_将来年次投資置換!C7 -> 0 | D11: =D10-02_将来年次投資置換!D7 -> 0 | E11: =E10-02_将来年次投資置換!E7 -> 0 | F11: =F10-02_将来年次投資置換!F7 -> 574211.99 | G11: =G10-02_将来年次投資置換!G7 -> 568469.71 | H11: =H10-02_将来年次投資置換!H7 -> 562784.71 | I11: =I10-02_将来年次投資置換!I7 -> 557156.53 | ... K11: =K10-02_将来年次投資置換!K7 -> 546068.63
A12: その他営業収益 | B12: =02_将来年次投資置換!B8 -> 30394 | C12: =02_将来年次投資置換!C8 -> 30467 | D12: =02_将来年次投資置換!D8 -> 30613 | E12: =02_将来年次投資置換!E8 -> 30760 | F12: =02_将来年次投資置換!F8 -> 30908 | G12: =02_将来年次投資置換!G8 -> 31057 | H12: =02_将来年次投資置換!H8 -> 31206 | I12: =02_将来年次投資置換!I8 -> 31356 | ... K12: =02_将来年次投資置換!K8 -> 31659
A13: 営業外収益 | B13: =02_将来年次投資置換!B9 -> 354909 | C13: =02_将来年次投資置換!C9 -> 355137 | D13: =02_将来年次投資置換!D9 -> 348767 | E13: =02_将来年次投資置換!E9 -> 343130 | F13: =02_将来年次投資置換!F9 -> 336658 | G13: =02_将来年次投資置換!G9 -> 342879 | H13: =02_将来年次投資置換!H9 -> 342324 | I13: =02_将来年次投資置換!I9 -> 332258 | ... K13: =02_将来年次投資置換!K9 -> 307297
A14: 長期前受金戻入 | B14: =02_将来年次投資置換!B12 -> 281625 | C14: =02_将来年次投資置換!C12 -> 283979 | D14: =02_将来年次投資置換!D12 -> 279812 | E14: =02_将来年次投資置換!E12 -> 276390 | F14: =02_将来年次投資置換!F12 -> 272168 | G14: =02_将来年次投資置換!G12 -> 272926 | H14: =02_将来年次投資置換!H12 -> 274600 | I14: =02_将来年次投資置換!I12 -> 266588 | ... K14: =02_将来年次投資置換!K12 -> 245134
A15: 繰入金・負担金等 | B15: =02_将来年次投資置換!B11 -> 73283 | C15: =02_将来年次投資置換!C11 -> 71157 | D15: =02_将来年次投資置換!D11 -> 68955 | E15: =02_将来年次投資置換!E11 -> 66740 | F15: =02_将来年次投資置換!F11 -> 64490 | G15: =02_将来年次投資置換!G11 -> 62175 | H15: =02_将来年次投資置換!H11 -> 59946 | I15: =02_将来年次投資置換!I11 -> 57892 | ... K15: =02_将来年次投資置換!K11 -> 54385
A16: 特別利益 | B16: =02_将来年次投資置換!B14 -> 2576 | C16: =02_将来年次投資置換!C14 -> 0 | D16: =02_将来年次投資置換!D14 -> 0 | E16: =02_将来年次投資置換!E14 -> 0 | F16: =02_将来年次投資置換!F14 -> 0 | G16: =02_将来年次投資置換!G14 -> 0 | H16: =02_将来年次投資置換!H14 -> 0 | I16: =02_将来年次投資置換!I14 -> 0 | ... K16: =02_将来年次投資置換!K14 -> 0
A17: 収益的収入合計 | B17: =SUM(B9,B13,B16) -> 1619060 | C17: =SUM(C9,C13,C16) -> 1604473 | D17: =SUM(D9,D13,D16) -> 1586060 | E17: =SUM(E9,E13,E16) -> 1568503 | F17: =SUM(F9,F13,F16) -> 2698656 | G17: =SUM(G9,G13,G16) -> 2681714.4 | H17: =SUM(H9,H13,H16) -> 2658229.4 | I17: =SUM(I9,I13,I16) -> 2625465.1 | ... K17: =SUM(K9,K13,K16) -> 2555794.3
A19: 【収益的支出】
A20: 営業費用 | B20: =02_将来年次投資置換!B18 -> 1479507 | C20: =02_将来年次投資置換!C18 -> 1476545 | D20: =02_将来年次投資置換!D18 -> 1474501 | E20: =02_将来年次投資置換!E18 -> 1471288 | F20: =02_将来年次投資置換!F18 -> 1471712 | G20: =02_将来年次投資置換!G18 -> 1476923 | H20: =02_将来年次投資置換!H18 -> 1486420 | I20: =02_将来年次投資置換!I18 -> 1484101 | ... K20: =02_将来年次投資置換!K18 -> 1469682
A21: 減価償却費 | B21: =02_将来年次投資置換!B25 -> 755782 | C21: =02_将来年次投資置換!C25 -> 754743 | D21: =02_将来年次投資置換!D25 -> 752391 | E21: =02_将来年次投資置換!E25 -> 748869 | F21: =02_将来年次投資置換!F25 -> 748983 | G21: =02_将来年次投資置換!G25 -> 753884 | H21: =02_将来年次投資置換!H25 -> 763070 | I21: =02_将来年次投資置換!I25 -> 760439 | ... K21: =02_将来年次投資置換!K25 -> 745393
A22: 資産減耗・除却費 | B22: =02_将来年次投資置換!B26 -> 0 | C22: =02_将来年次投資置換!C26 -> 0 | D22: =02_将来年次投資置換!D26 -> 0 | E22: =02_将来年次投資置換!E26 -> 0 | F22: =02_将来年次投資置換!F26 -> 0 | G22: =02_将来年次投資置換!G26 -> 0 | H22: =02_将来年次投資置換!H26 -> 0 | I22: =02_将来年次投資置換!I26 -> 0 | ... K22: =02_将来年次投資置換!K26 -> 0
A23: 営業外費用 | B23: =02_将来年次投資置換!B28 -> 128495 | C23: =02_将来年次投資置換!C28 -> 120518 | D23: =02_将来年次投資置換!D28 -> 117139 | E23: =02_将来年次投資置換!E28 -> 115384 | F23: =02_将来年次投資置換!F28 -> 113787 | G23: =02_将来年次投資置換!G28 -> 110821 | H23: =02_将来年次投資置換!H28 -> 108565 | I23: =02_将来年次投資置換!I28 -> 107412 | ... K23: =02_将来年次投資置換!K28 -> 105117
A24: 支払利息 | B24: =02_将来年次投資置換!B29 -> 118910 | C24: =02_将来年次投資置換!C29 -> 111872 | D24: =02_将来年次投資置換!D29 -> 108458 | E24: =02_将来年次投資置換!E29 -> 106668 | F24: =02_将来年次投資置換!F29 -> 105071 | G24: =02_将来年次投資置換!G29 -> 102070 | H24: =02_将来年次投資置換!H29 -> 99779 | I24: =02_将来年次投資置換!I29 -> 98626 | ... K24: =02_将来年次投資置換!K29 -> 96331
A25: 特別損失 | B25: =02_将来年次投資置換!B31 -> 273 | C25: =02_将来年次投資置換!C31 -> 273 | D25: =02_将来年次投資置換!D31 -> 273 | E25: =02_将来年次投資置換!E31 -> 273 | F25: =02_将来年次投資置換!F31 -> 273 | G25: =02_将来年次投資置換!G31 -> 273 | H25: =02_将来年次投資置換!H31 -> 273 | I25: =02_将来年次投資置換!I31 -> 273 | ... K25: =02_将来年次投資置換!K31 -> 273
A26: 収益的支出合計 | B26: =SUM(B20,B23,B25) -> 1608275 | C26: =SUM(C20,C23,C25) -> 1597336 | D26: =SUM(D20,D23,D25) -> 1591913 | E26: =SUM(E20,E23,E25) -> 1586945 | F26: =SUM(F20,F23,F25) -> 1585772 | G26: =SUM(G20,G23,G25) -> 1588017 | H26: =SUM(H20,H23,H25) -> 1595258 | I26: =SUM(I20,I23,I25) -> 1591786 | ... K26: =SUM(K20,K23,K25) -> 1575072
A27: 経常損益 | B27: =SUM(B9,B13)-SUM(B20,B23) -> 8482 | C27: =SUM(C9,C13)-SUM(C20,C23) -> 7410 | D27: =SUM(D9,D13)-SUM(D20,D23) -> -5580 | E27: =SUM(E9,E13)-SUM(E20,E23) -> -18169 | F27: =SUM(F9,F13)-SUM(F20,F23) -> 1113157 | G27: =SUM(G9,G13)-SUM(G20,G23) -> 1093970.4 | H27: =SUM(H9,H13)-SUM(H20,H23) -> 1063244.4 | I27: =SUM(I9,I13)-SUM(I20,I23) -> 1033952.1 | ... K27: =SUM(K9,K13)-SUM(K20,K23) -> 980995.26
A28: 純損益 | B28: =B27+B16-B25 -> 10785 | C28: =C27+C16-C25 -> 7137 | D28: =D27+D16-D25 -> -5853 | E28: =E27+E16-E25 -> -18442 | F28: =F27+F16-F25 -> 1112884 | G28: =G27+G16-G25 -> 1093697.4 | H28: =H27+H16-H25 -> 1062971.4 | I28: =I27+I16-I25 -> 1033679.1 | ... K28: =K27+K16-K25 -> 980722.26
A30: 【経営指標】
A31: 経常収支比率 | B31: =IFERROR((SUM(B9,B13)/SUM(B20,B23))*100,0) -> 100.52749 | C31: =IFERROR((SUM(C9,C13)/SUM(C20,C23))*100,0) -> 100.46398 | D31: =IFERROR((SUM(D9,D13)/SUM(D20,D23))*100,0) -> 99.649418 | E31: =IFERROR((SUM(E9,E13)/SUM(E20,E23))*100,0) -> 98.854899 | F31: =IFERROR((SUM(F9,F13)/SUM(F20,F23))*100,0) -> 170.20862 | G31: =IFERROR((SUM(G9,G13)/SUM(G20,G23))*100,0) -> 168.90093 | H31: =IFERROR((SUM(H9,H13)/SUM(H20,H23))*100,0) -> 166.66172 | I31: =IFERROR((SUM(I9,I13)/SUM(I20,I23))*100,0) -> 164.96661 | ... K31: =IFERROR((SUM(K9,K13)/SUM(K20,K23))*100,0) -> 162.29336
A32: 料金回収率（通常） | B32: =IFERROR(B10/B34*100,0) -> 92.822855 | C32: =IFERROR(C10/C34*100,0) -> 92.824907 | D32: =IFERROR(D10/D34*100,0) -> 91.98462 | E32: =IFERROR(E10/E34*100,0) -> 91.172206 | F32: =IFERROR(F10/F34*100,0) -> 133.77267 | G32: =IFERROR(G10/G34*100,0) -> 132.28513 | H32: =IFERROR(H10/H34*100,0) -> 130.41005 | I32: =IFERROR(I10/I34*100,0) -> 128.66347 | ... K32: =IFERROR(K10/K34*100,0) -> 125.65343
A33: 資産維持費込料金回収率 | B33: =IFERROR(B10/B35*100,0) -> 67.645898 | C33: =IFERROR(C10/C35*100,0) -> 67.462152 | D33: =IFERROR(D10/D35*100,0) -> 66.833974 | E33: =IFERROR(E10/E35*100,0) -> 66.222328 | F33: =IFERROR(F10/F35*100,0) -> 97.226666 | G33: =IFERROR(G10/G35*100,0) -> 96.175227 | H33: =IFERROR(H10/H35*100,0) -> 94.921231 | I33: =IFERROR(I10/I35*100,0) -> 93.737365 | ... K33: =IFERROR(K10/K35*100,0) -> 91.633076
A34: 給水原価対象費用 | B34: =SUM(B20,B23)-B14 -> 1326377 | C34: =SUM(C20,C23)-C14 -> 1313084 | D34: =SUM(D20,D23)-D14 -> 1311828 | E34: =SUM(E20,E23)-E14 -> 1310282 | F34: =SUM(F20,F23)-F14 -> 1313331 | G34: =SUM(G20,G23)-G14 -> 1314818 | H34: =SUM(H20,H23)-H14 -> 1320385 | I34: =SUM(I20,I23)-I14 -> 1324925 | ... K34: =SUM(K20,K23)-K14 -> 1329665
A35: 給水原価対象費用＋資産維持費 | B35: =B34+$B$5 -> 1820037.9 | C35: =C34+$B$5 -> 1806744.9 | D35: =D34+$B$5 -> 1805488.9 | E35: =E34+$B$5 -> 1803942.9 | F35: =F34+$B$5 -> 1806991.9 | G35: =G34+$B$5 -> 1808478.9 | H35: =H34+$B$5 -> 1814045.9 | I35: =I34+$B$5 -> 1818585.9 | ... K35: =K34+$B$5 -> 1823325.9
A36: 総括原価回収率（参考） | B36: =IFERROR(B10/(B20+B23-B14-B12-B15+$B$5)*100,0) -> 71.732057 | C36: =IFERROR(C10/(C20+C23-C14-C12-C15+$B$5)*100,0) -> 71.482848 | D36: =IFERROR(D10/(D20+D23-D14-D12-D15+$B$5)*100,0) -> 70.734815 | E36: =IFERROR(E10/(E20+E23-E14-E12-E15+$B$5)*100,0) -> 70.006033 | F36: =IFERROR(F10/(F20+F23-F14-F12-F15+$B$5)*100,0) -> 102.64573 | G36: =IFERROR(G10/(G20+G23-G14-G12-G15+$B$5)*100,0) -> 101.40282 | H36: =IFERROR(H10/(H20+H23-H14-H12-H15+$B$5)*100,0) -> 99.943165 | I36: =IFERROR(I10/(I20+I23-I14-I12-I15+$B$5)*100,0) -> 98.574981 | ... K36: =IFERROR(K10/(K20+K23-K14-K12-K15+$B$5)*100,0) -> 96.171474
A37: 検証：資産維持費込<=通常 | B37: =IF(B33<=B32,"OK","要確認") -> OK | C37: =IF(C33<=C32,"OK","要確認") -> OK | D37: =IF(D33<=D32,"OK","要確認") -> OK | E37: =IF(E33<=E32,"OK","要確認") -> OK | F37: =IF(F33<=F32,"OK","要確認") -> OK | G37: =IF(G33<=G32,"OK","要確認") -> OK | H37: =IF(H33<=H32,"OK","要確認") -> OK | I37: =IF(I33<=I32,"OK","要確認") -> OK | ... K37: =IF(K33<=K32,"OK","要確認") -> OK
A39: 【資本的収入】
A40: 資本的収入 | B40: =02_将来年次投資置換!B34 -> 698941 | C40: =02_将来年次投資置換!C34 -> 664331 | D40: =02_将来年次投資置換!D34 -> 636408 | E40: =02_将来年次投資置換!E34 -> 715698 | F40: =02_将来年次投資置換!F34 -> 627649 | G40: =02_将来年次投資置換!G34 -> 570213 | H40: =02_将来年次投資置換!H34 -> 571338 | I40: =02_将来年次投資置換!I34 -> 536592 | ... K40: =02_将来年次投資置換!K34 -> 365000
A41: 企業債 | B41: =02_将来年次投資置換!B35 -> 329000 | C41: =02_将来年次投資置換!C35 -> 435000 | D41: =02_将来年次投資置換!D35 -> 399000 | E41: =02_将来年次投資置換!E35 -> 400000 | F41: =02_将来年次投資置換!F35 -> 232000 | G41: =02_将来年次投資置換!G35 -> 283000 | H41: =02_将来年次投資置換!H35 -> 286000 | I41: =02_将来年次投資置換!I35 -> 368000 | ... K41: =02_将来年次投資置換!K35 -> 230000
A42: 一般会計負担金 | B42: =02_将来年次投資置換!B36 -> 169041 | C42: =02_将来年次投資置換!C36 -> 164831 | D42: =02_将来年次投資置換!D36 -> 162408 | E42: =02_将来年次投資置換!E36 -> 167998 | F42: =02_将来年次投資置換!F36 -> 173649 | G42: =02_将来年次投資置換!G36 -> 182213 | H42: =02_将来年次投資置換!H36 -> 180338 | I42: =02_将来年次投資置換!I36 -> 168592 | ... K42: =02_将来年次投資置換!K36 -> 135000
A43: 一般会計出資金 | B43: =02_将来年次投資置換!B37 -> 0 | C43: =02_将来年次投資置換!C37 -> 0 | D43: =02_将来年次投資置換!D37 -> 0 | E43: =02_将来年次投資置換!E37 -> 0 | F43: =02_将来年次投資置換!F37 -> 0 | G43: =02_将来年次投資置換!G37 -> 0 | H43: =02_将来年次投資置換!H37 -> 0 | I43: =02_将来年次投資置換!I37 -> 0 | ... K43: =02_将来年次投資置換!K37 -> 0
A44: 国庫補助金 | B44: =02_将来年次投資置換!B38 -> 0 | C44: =02_将来年次投資置換!C38 -> 64500 | D44: =02_将来年次投資置換!D38 -> 75000 | E44: =02_将来年次投資置換!E38 -> 147700 | F44: =02_将来年次投資置換!F38 -> 222000 | G44: =02_将来年次投資置換!G38 -> 105000 | H44: =02_将来年次投資置換!H38 -> 105000 | I44: =02_将来年次投資置換!I38 -> 0 | ... K44: =02_将来年次投資置換!K38 -> 0
A45: 固定資産売却代金 | B45: =02_将来年次投資置換!B39 -> 0 | C45: =02_将来年次投資置換!C39 -> 0 | D45: =02_将来年次投資置換!D39 -> 0 | E45: =02_将来年次投資置換!E39 -> 0 | F45: =02_将来年次投資置換!F39 -> 0 | G45: =02_将来年次投資置換!G39 -> 0 | H45: =02_将来年次投資置換!H39 -> 0 | I45: =02_将来年次投資置換!I39 -> 0 | ... K45: =02_将来年次投資置換!K39 -> 0
A46: 工事負担金 | B46: =02_将来年次投資置換!B40 -> 200900 | C46: =02_将来年次投資置換!C40 -> 0 | D46: =02_将来年次投資置換!D40 -> 0 | E46: =02_将来年次投資置換!E40 -> 0 | F46: =02_将来年次投資置換!F40 -> 0 | G46: =02_将来年次投資置換!G40 -> 0 | H46: =02_将来年次投資置換!H40 -> 0 | I46: =02_将来年次投資置換!I40 -> 0 | ... K46: =02_将来年次投資置換!K40 -> 0
A47: その他・調整 | B47: =02_将来年次投資置換!B41 -> 0 | C47: =02_将来年次投資置換!C41 -> 0 | D47: =02_将来年次投資置換!D41 -> 0 | E47: =02_将来年次投資置換!E41 -> 0 | F47: =02_将来年次投資置換!F41 -> 0 | G47: =02_将来年次投資置換!G41 -> 0 | H47: =02_将来年次投資置換!H41 -> 0 | I47: =02_将来年次投資置換!I41 -> 0 | ... K47: =02_将来年次投資置換!K41 -> 0
A49: 【資本的支出】
A50: 資本的支出 | B50: =02_将来年次投資置換!B44 -> 1123770 | C50: =02_将来年次投資置換!C44 -> 1684483 | D50: =02_将来年次投資置換!D44 -> 1131274 | E50: =02_将来年次投資置換!E44 -> 1433926 | F50: =02_将来年次投資置換!F44 -> 1196811 | G50: =02_将来年次投資置換!G44 -> 965587 | H50: =02_将来年次投資置換!H44 -> 945526 | I50: =02_将来年次投資置換!I44 -> 916106 | ... K50: =02_将来年次投資置換!K44 -> 763357
A51: 建設改良費 | B51: =02_将来年次投資置換!B45 -> 268741 | C51: =02_将来年次投資置換!C45 -> 888542 | D51: =02_将来年次投資置換!D45 -> 403455 | E51: =02_将来年次投資置換!E45 -> 761285 | F51: =02_将来年次投資置換!F45 -> 558200 | G51: =02_将来年次投資置換!G45 -> 389300 | H51: =02_将来年次投資置換!H45 -> 382930 | I51: =02_将来年次投資置換!I45 -> 368500 | ... K51: =02_将来年次投資置換!K45 -> 230500
A52: 企業債償還金 | B52: =02_将来年次投資置換!B46 -> 855029 | C52: =02_将来年次投資置換!C46 -> 795941 | D52: =02_将来年次投資置換!D46 -> 727819 | E52: =02_将来年次投資置換!E46 -> 672641 | F52: =02_将来年次投資置換!F46 -> 638611 | G52: =02_将来年次投資置換!G46 -> 576287 | H52: =02_将来年次投資置換!H46 -> 562596 | I52: =02_将来年次投資置換!I46 -> 547606 | ... K52: =02_将来年次投資置換!K46 -> 532857
A53: その他資本的支出 | B53: =02_将来年次投資置換!B47 -> 0 | C53: =02_将来年次投資置換!C47 -> 0 | D53: =02_将来年次投資置換!D47 -> 0 | E53: =02_将来年次投資置換!E47 -> 0 | F53: =02_将来年次投資置換!F47 -> 0 | G53: =02_将来年次投資置換!G47 -> 0 | H53: =02_将来年次投資置換!H47 -> 0 | I53: =02_将来年次投資置換!I47 -> 0 | ... K53: =02_将来年次投資置換!K47 -> 0
A54: 資本的収支不足額（収入－支出） | B54: =B40-B50 -> -424829 | C54: =C40-C50 -> -1020152 | D54: =D40-D50 -> -494866 | E54: =E40-E50 -> -718228 | F54: =F40-F50 -> -569162 | G54: =G40-G50 -> -395374 | H54: =H40-H50 -> -374188 | I54: =I40-I50 -> -379514 | ... K54: =K40-K50 -> -398357
A56: 【現預金・4条財源】
A57: 補てん可能財源相当（簡便CF） | B57: =B28+B21+B22-B14 -> 484942 | C57: =C28+C21+C22-C14 -> 477901 | D57: =D28+D21+D22-D14 -> 466726 | E57: =E28+E21+E22-E14 -> 454037 | F57: =F28+F21+F22-F14 -> 1589699 | G57: =G28+G21+G22-G14 -> 1574655.4 | H57: =H28+H21+H22-H14 -> 1551441.4 | I57: =I28+I21+I22-I14 -> 1527530.1 | ... K57: =K28+K21+K22-K14 -> 1480981.3
A58: 資本的収支不足額（再掲） | B58: =B54 -> -424829 | C58: =C54 -> -1020152 | D58: =D54 -> -494866 | E58: =E54 -> -718228 | F58: =F54 -> -569162 | G58: =G54 -> -395374 | H58: =H54 -> -374188 | I58: =I54 -> -379514 | ... K58: =K54 -> -398357
A59: 年度末現預金残高 | B59: =00_前提・検証!$B$6 -> 242588 | C59: =B59+C57+C58 -> -299663 | D59: =C59+D57+D58 -> -327803 | E59: =D59+E57+E58 -> -591994 | F59: =E59+F57+F58 -> 428542.98 | G59: =F59+G57+G58 -> 1607824.4 | H59: =G59+H57+H58 -> 2785077.8 | I59: =H59+I57+I58 -> 3933093.9 | J59: =I59+J57+J58 -> 5031084.2 | K59: =J59+K57+K58 -> 6113708.5
A60: 最低現金目安との差額 | B60: =B59-00_前提・検証!$B$7 -> -57412 | C60: =C59-00_前提・検証!$B$7 -> -599663 | D60: =D59-00_前提・検証!$B$7 -> -627803 | E60: =E59-00_前提・検証!$B$7 -> -891994 | F60: =F59-00_前提・検証!$B$7 -> 128542.98 | G60: =G59-00_前提・検証!$B$7 -> 1307824.4 | H60: =H59-00_前提・検証!$B$7 -> 2485077.8 | I60: =I59-00_前提・検証!$B$7 -> 3633093.9 | ... K60: =K59-00_前提・検証!$B$7 -> 5813708.5

Sheet 02_R8予算_年次計画置換
A1: R8予算反映・将来年次計画投資置換後の投資財政計画（R7〜R16）
A2: R8は当初予算書の収益的収支・資本的収入を反映。建設改良費は将来年次計画2025.12.2（2026.3.1シート）の調整後事業費計へ置換。単位：千円。 【修正】修繕費・動力費・薬品費・委託料・資産減耗費・その他営業費用は993作成資料上「物件費」の内数のため、営業費用の合計から除外（従来は二重計上）。R8予算年度のみ資産減耗費12,000を別掲加算。
A3: 区分 | B3: 令和7年度 | C3: 令和8年度 | D3: 令和9年度 | E3: 令和10年度 | F3: 令和11年度 | G3: 令和12年度 | H3: 令和13年度 | I3: 令和14年度 | J3: 令和15年度 | K3: 令和16年度
A4: 【収益的収入】
A5: 水道事業収益 | B5: =SUM(B6,B9,B14) -> 1619060 | C5: =SUM(C6,C9,C14) -> 1747782 | D5: =SUM(D6,D9,D14) -> 1586060 | E5: =SUM(E6,E9,E14) -> 1577158 | F5: =SUM(F6,F9,F14) -> 1558887 | G5: =SUM(G6,G9,G14) -> 1553430 | H5: =SUM(H6,H9,H14) -> 1541315 | I5: =SUM(I6,I9,I14) -> 1519807 | ... K5: =SUM(K6,K9,K14) -> 1472312
A6: 営業収益 | B6: =SUM(B7:B8) -> 1261575 | C6: =SUM(C7:C8) -> 1366275 | D6: =SUM(D7:D8) -> 1237293 | E6: =SUM(E7:E8) -> 1225373 | F6: =SUM(F7:F8) -> 1213574 | G6: =SUM(G7:G8) -> 1201896 | H6: =SUM(H7:H8) -> 1190336 | I6: =SUM(I7:I8) -> 1178894 | ... K6: =SUM(K7:K8) -> 1156360
A7: 給水収益 | B7: 1231181 | C7: 1331944 | D7: 1206680 | E7: 1194613 | F7: 1182666 | G7: 1170839 | H7: 1159130 | I7: 1147538 | J7: 1136062 | K7: 1124701
A8: その他営業収益 | B8: 30394 | C8: 34331 | D8: 30613 | E8: 30760 | F8: 30908 | G8: 31057 | H8: 31206 | I8: 31356 | J8: 31507 | K8: 31659
A9: 営業外収益 | B9: =SUM(B10:B13) -> 354909 | C9: =SUM(C10:C13) -> 351507 | D9: =SUM(D10:D13) -> 348767 | E9: =SUM(E10:E13) -> 351785 | F9: =SUM(F10:F13) -> 345313 | G9: =SUM(G10:G13) -> 351534 | H9: =SUM(H10:H13) -> 350979 | I9: =SUM(I10:I13) -> 340913 | ... K9: =SUM(K10:K13) -> 315952
A10: 受取利息 | B10: 1 | C10: 17 | D10: 0 | E10: 0 | F10: 0 | G10: 0 | H10: 0 | I10: 0 | J10: 0 | K10: 0
A11: 繰入金・負担金等 | B11: 73283 | C11: 72779 | D11: 68955 | E11: 66740 | F11: 64490 | G11: 62175 | H11: 59946 | I11: 57892 | J11: 56062 | K11: 54385
A12: 長期前受金戻入 | B12: 281625 | C12: 278623 | D12: 279812 | E12: =276390+05_建設仮勘定・企業債!E41 -> 285045 | F12: =272168+05_建設仮勘定・企業債!F41 -> 280823 | G12: =272926+05_建設仮勘定・企業債!G41 -> 281581 | H12: =274600+05_建設仮勘定・企業債!H41 -> 283255 | I12: =266588+05_建設仮勘定・企業債!I41 -> 275243 | J12: =250287+05_建設仮勘定・企業債!J41 -> 258942 | K12: =245134+05_建設仮勘定・企業債!K41 -> 253789
A13: その他営業外収益 | B13: 0 | C13: 88 | D13: 0 | E13: 0 | F13: 0 | G13: 7778 | H13: 7778 | I13: 7778 | J13: 7778 | K13: 7778
A14: 特別利益 | B14: 2576 | C14: 30000 | D14: 0 | E14: 0 | F14: 0 | G14: 0 | H14: 0 | I14: 0 | J14: 0 | K14: 0
A16: 【収益的支出】
A17: 水道事業費用 | B17: =SUM(B18,B28,B31) -> 1608275 | C17: =SUM(C18,C28,C31) -> 1710280 | D17: =SUM(D18,D28,D31) -> 1597736 | E17: =SUM(E18,E28,E31) -> 1602507 | F17: =SUM(F18,F28,F31) -> 1607640 | G17: =SUM(G18,G28,G31) -> 1612749 | H17: =SUM(H18,H28,H31) -> 1619689 | I17: =SUM(I18,I28,I31) -> 1615634 | ... K17: =SUM(K18,K28,K31) -> 1598706
A18: 営業費用 | B18: =SUM(B19,B20,B25,B26,B27) -> 1479507 | C18: =SUM(C19,C20,C25,C26,C27) -> 1546573 | D18: =SUM(D19,D20,D25,D26,D27) -> 1474501 | E18: =SUM(E19,E20,E25,E26,E27) -> 1482927 | F18: =SUM(F19,F20,F25,F26,F27) -> 1483351 | G18: =SUM(G19,G20,G25,G26,G27) -> 1488562 | H18: =SUM(H19,H20,H25,H26,H27) -> 1498059 | I18: =SUM(I19,I20,I25,I26,I27) -> 1495740 | ... K18: =SUM(K19,K20,K25,K26,K27) -> 1481321
A19: 人件費 | B19: 176462 | C19: 188373 | D19: 176462 | E19: 176462 | F19: 176462 | G19: 176462 | H19: 176462 | I19: 176462 | J19: 176462 | K19: 176462
A20: 物件費 | B20: 547263 | C20: 599689 | D20: 545648 | E20: 545957 | F20: 546267 | G20: 546577 | H20: 546888 | I20: 547200 | J20: 547513 | K20: 547827
A21: 修繕費（物件費の内数・参考） | B21: 65247 | C21: 0 | D21: 65000 | E21: 65000 | F21: 65000 | G21: 65000 | H21: 65000 | I21: 65000 | J21: 65000 | K21: 65000
A22: 動力費（物件費の内数・参考） | B22: 102261 | C22: 0 | D22: 102876 | E22: 103185 | F22: 103495 | G22: 103805 | H22: 104116 | I22: 104428 | J22: 104741 | K22: 105055
A23: 薬品費（物件費の内数・参考） | B23: 15316 | C23: 0 | D23: 15000 | E23: 15000 | F23: 15000 | G23: 15000 | H23: 15000 | I23: 15000 | J23: 15000 | K23: 15000
A24: 委託料（物件費の内数・参考） | B24: 304419 | C24: 0 | D24: 304000 | E24: 304000 | F24: 304000 | G24: 304000 | H24: 304000 | I24: 304000 | J24: 304000 | K24: 304000
A25: 減価償却費 | B25: 755782 | C25: 746511 | D25: 752391 | E25: =748869+05_建設仮勘定・企業債!E40 -> 760508 | F25: =748983+05_建設仮勘定・企業債!F40 -> 760622 | G25: =753884+05_建設仮勘定・企業債!G40 -> 765523 | H25: =763070+05_建設仮勘定・企業債!H40 -> 774709 | I25: =760439+05_建設仮勘定・企業債!I40 -> 772078 | J25: =744482+05_建設仮勘定・企業債!J40 -> 756121 | K25: =745393+05_建設仮勘定・企業債!K40 -> 757032
A26: 資産減耗・除却費（R8予算のみ別掲、他年度は物件費内数のため0） | B26: 0 | C26: 12000 | D26: 0 | E26: 0 | F26: 0 | G26: 0 | H26: 0 | I26: 0 | J26: 0 | K26: 0
A27: その他営業費用（物件費内数のため0） | B27: 0 | C27: 0 | D27: 0 | E27: 0 | F27: 0 | G27: 0 | H27: 0 | I27: 0 | J27: 0 | K27: 0
A28: 営業外費用 | B28: =SUM(B29:B30) -> 128495 | C28: =SUM(C29:C30) -> 163407 | D28: =SUM(D29:D30) -> 122962 | E28: =SUM(E29:E30) -> 119307 | F28: =SUM(F29:F30) -> 124016 | G28: =SUM(G29:G30) -> 123914 | H28: =SUM(H29:H30) -> 121357 | I28: =SUM(I29:I30) -> 119621 | ... K28: =SUM(K29:K30) -> 117112
A29: 支払利息 | B29: 118910 | C29: =113113+C58 -> 113113 | D29: =108458+D58 -> 114281 | E29: =106668+E58 -> 110591 | F29: =105071+F58 -> 115300 | G29: =102070+G58 -> 115163 | H29: =99779+H58 -> 112571 | I29: =98626+I58 -> 110835 | J29: =98322+J58 -> 110211 | K29: =96331+K58 -> 108326
A30: 雑支出 | B30: 9585 | C30: 50294 | D30: 8681 | E30: 8716 | F30: 8716 | G30: 8751 | H30: 8786 | I30: 8786 | J30: 8786 | K30: 8786
A31: 特別損失 | B31: 273 | C31: 300 | D31: 273 | E31: 273 | F31: 273 | G31: 273 | H31: 273 | I31: 273 | J31: 273 | K31: 273
A33: 【資本的収入】
A34: 資本的収入 | B34: 698941 | C34: =SUM(C35:C41) -> 1055380 | D34: =SUM(D35:D41) -> 577929 | E34: =SUM(E35:E41) -> 929283 | F34: =SUM(F35:F41) -> 731849 | G34: =SUM(G35:G41) -> 571513 | H34: =SUM(H35:H41) -> 563268 | I34: =SUM(I35:I41) -> 537092 | J34: =SUM(J35:J41) -> 421454 | K34: =SUM(K35:K41) -> 365500
A35: 企業債 | B35: 329000 | C35: =MAX(0,C45-C38-C40) -> 713997 | D35: =MAX(0,D45-D38-D40)+12066 -> 340521 | E35: =MAX(0,E45-E38-E40) -> 613585 | F35: =MAX(0,F45-F38-F40) -> 336200 | G35: =MAX(0,G45-G38-G40) -> 284300 | H35: =MAX(0,H45-H38-H40) -> 277930 | I35: =MAX(0,I45-I38-I40) -> 368500 | J35: =MAX(0,J45-J38-J40) -> 265720 | K35: =MAX(0,K45-K38-K40) -> 230500
A36: 一般会計負担金 | B36: 169041 | C36: 166838 | D36: 162408 | E36: 167998 | F36: 173649 | G36: 182213 | H36: 180338 | I36: 168592 | J36: 155734 | K36: 135000
A37: 一般会計出資金 | B37: 0 | C37: 0 | D37: 0 | E37: 0 | F37: 0 | G37: 0 | H37: 0 | I37: 0 | J37: 0 | K37: 0
A38: 国庫補助金 | B38: 0 | C38: 2000 | D38: 75000 | E38: 147700 | F38: 222000 | G38: 105000 | H38: 105000 | I38: 0 | J38: 0 | K38: 0
A39: 固定資産売却代金 | B39: 0 | C39: 0 | D39: 0 | E39: 0 | F39: 0 | G39: 0 | H39: 0 | I39: 0 | J39: 0 | K39: 0
A40: 工事負担金 | B40: 200900 | C40: 172545 | D40: 0 | E40: 0 | F40: 0 | G40: 0 | H40: 0 | I40: 0 | J40: 0 | K40: 0
A41: その他・調整 | B41: =B34-SUM(B35:B40) -> 0 | C41: 0 | D41: 0 | E41: 0 | F41: 0 | G41: 0 | H41: 0 | I41: 0 | J41: 0 | K41: 0
A43: 【資本的支出】
A44: 資本的支出 | B44: =SUM(B45:B47) -> 1123770 | C44: =SUM(C45:C47) -> 1684475 | D44: =SUM(D45:D47) -> 1136126 | E44: =SUM(E45:E47) -> 1437316 | F44: =SUM(F45:F47) -> 1205541 | G44: =SUM(G45:G47) -> 976922 | H44: =SUM(H45:H47) -> 956894 | I44: =SUM(I45:I47) -> 927272 | ... K44: =SUM(K45:K47) -> 774903
A45: 建設改良費 | B45: 268741 | C45: 888542 | D45: 403455 | E45: 761285 | F45: 558200 | G45: 389300 | H45: 382930 | I45: 368500 | J45: 265720 | K45: 230500
A46: 企業債償還金 | B46: 855029 | C46: =795933+C57 -> 795933 | D46: =727819+D57 -> 732671 | E46: =672641+E57 -> 676031 | F46: =638611+F57 -> 647341 | G46: =576287+G57 -> 587622 | H46: =562596+H57 -> 573964 | I46: =547606+I57 -> 558772 | J46: =546246+J57 -> 557424 | K46: =532857+K57 -> 544403
A47: その他資本的支出 | B47: 0 | C47: 0 | D47: 0 | E47: 0 | F47: 0 | G47: 0 | H47: 0 | I47: 0 | J47: 0 | K47: 0
A48: 資本的収支不足額（収入－支出） | B48: =B34-B44 -> -424829 | C48: =C34-C44 -> -629095 | D48: =D34-D44 -> -558197 | E48: =E34-E44 -> -508033 | F48: =F34-F44 -> -473692 | G48: =G34-G44 -> -405409 | H48: =H34-H44 -> -393626 | I48: =I34-I44 -> -390180 | ... K48: =K34-K44 -> -409403
A49: 【R8予算反映メモ】
A50: R8資本的収入は当初予算書の861,283千円を採用。企業債519,900、一般会計負担金166,838、国庫補助金2,000、工事負担金172,545。
A51: R8建設改良費は、投資側は将来年次計画の調整後事業費計888,542千円へ置換。予算上の建設改良費714,032千円との差は174,510千円。
A52: R8の収益的収支は当初予算書の給水収益1,331,944千円、営業費用1,546,573千円、支払利息113,113千円等を反映。
A53: 【企業債100%充当・建設仮勘定統合メモ】
A54: 企業債(R8〜R16)＝建設改良費−国庫補助金−工事負担金（充当率100%）。R9は過年度建設仮勘定純額12,066千円を追加借入。差分起債の利息・元金は下記Δモデルで支払利息・企業債償還金へ加算。R10以降の減価償却費・長期前受金戻入は建設仮勘定供用開始影響（+11,639／+8,655千円）を統合済み。
A55: 【企業債100%充当 差分（Δ）モデル】利率3%・40年元金均等・借入年度末借入（翌年度から償還・利息発生）。実際の起債条件確定後に要再計算。
A56: Δ起債（千円）＝100%充当起債−従来計画起債 | B56: 0 | C56: =C35-519900 -> 194097 | D56: =D35-399000 -> -58479 | E56: =E35-400000 -> 213585 | F56: =F35-232000 -> 104200 | G56: =G35-283000 -> 1300 | H56: =H35-286000 -> -8070 | I56: =I35-368000 -> 500 | J56: =J35-251000 -> 14720 | K56: =K35-230000 -> 500
A57: Δ元金償還（千円） | B57: 0 | C57: 0 | D57: =ROUND(SUM($C$56:C56)/40,0) -> 4852 | E57: =ROUND(SUM($C$56:D56)/40,0) -> 3390 | F57: =ROUND(SUM($C$56:E56)/40,0) -> 8730 | G57: =ROUND(SUM($C$56:F56)/40,0) -> 11335 | H57: =ROUND(SUM($C$56:G56)/40,0) -> 11368 | I57: =ROUND(SUM($C$56:H56)/40,0) -> 11166 | J57: =ROUND(SUM($C$56:I56)/40,0) -> 11178 | K57: =ROUND(SUM($C$56:J56)/40,0) -> 11546
A58: Δ支払利息（千円） | B58: 0 | C58: 0 | D58: =ROUND(C59*0.03,0) -> 5823 | E58: =ROUND(D59*0.03,0) -> 3923 | F58: =ROUND(E59*0.03,0) -> 10229 | G58: =ROUND(F59*0.03,0) -> 13093 | H58: =ROUND(G59*0.03,0) -> 12792 | I58: =ROUND(H59*0.03,0) -> 12209 | J58: =ROUND(I59*0.03,0) -> 11889 | K58: =ROUND(J59*0.03,0) -> 11995
A59: Δ企業債残高（期末・千円） | B59: 0 | C59: =B59+C56-C57 -> 194097 | D59: =C59+D56-D57 -> 130766 | E59: =D59+E56-E57 -> 340961 | F59: =E59+F56-F57 -> 436431 | G59: =F59+G56-G57 -> 426396 | H59: =G59+H56-H57 -> 406958 | I59: =H59+I56-I57 -> 396292 | J59: =I59+J56-J57 -> 399834 | K59: =J59+K56-K57 -> 388788

Sheet SIM_R8予算置換_0%
A1: SIM_R8予算置換_0%
A2: 単位：千円、比率は％。料金改定率はR11〜R15の総括原価回収を基礎に算定し、R11以降の給水収益へ反映。
A3: 区分 | B3: 令和7年度 | C3: 令和8年度 | D3: 令和9年度 | E3: 令和10年度 | F3: 令和11年度 | G3: 令和12年度 | H3: 令和13年度 | I3: 令和14年度 | J3: 令和15年度 | K3: 令和16年度
A4: 資産維持費率 | B4: 0
A5: 年額資産維持費（千円） | B5: =00_前提・検証!$B$2*$B$4 -> 0
A6: 料金改定率（R11以降・試算） | B6: =MAX(0,(SUM(02_R8予算_年次計画置換!F18:J18)+SUM(02_R8予算_年次計画置換!F28:J28)-SUM(02_R8予算_年次計画置換!F12:J12)-SUM(02_R8予算_年次計画置換!F8:J8)-SUM(02_R8予算_年次計画置換!F11:J11)+$B$5*5-SUM(02_R8予算_年次計画置換!F7:J7))/SUM(02_R8予算_年次計画置換!F7:J7)) -> 0.072639394
A8: 【収益的収入】
A9: 営業収益 | B9: =SUM(B10:B12) -> 1261575 | C9: =SUM(C10:C12) -> 1366275 | D9: =SUM(D10:D12) -> 1237293 | E9: =SUM(E10:E12) -> 1225373 | F9: =SUM(F10:F12) -> 1385390.3 | G9: =SUM(G10:G12) -> 1371994.1 | H9: =SUM(H10:H12) -> 1358733 | I9: =SUM(I10:I12) -> 1345606.9 | ... K9: =SUM(K10:K12) -> 1319755.2
A10: 給水収益（改定反映後） | B10: =02_R8予算_年次計画置換!B7*IF(7>=11,1+$B$6,1) -> 1231181 | C10: =02_R8予算_年次計画置換!C7*IF(8>=11,1+$B$6,1) -> 1331944 | D10: =02_R8予算_年次計画置換!D7*IF(9>=11,1+$B$6,1) -> 1206680 | E10: =02_R8予算_年次計画置換!E7*IF(10>=11,1+$B$6,1) -> 1194613 | F10: =02_R8予算_年次計画置換!F7*IF(11>=11,1+$B$6,1) -> 1268574.1 | G10: =02_R8予算_年次計画置換!G7*IF(12>=11,1+$B$6,1) -> 1255888 | H10: =02_R8予算_年次計画置換!H7*IF(13>=11,1+$B$6,1) -> 1243328.5 | I10: =02_R8予算_年次計画置換!I7*IF(14>=11,1+$B$6,1) -> 1230894.5 | J10: =02_R8予算_年次計画置換!J7*IF(15>=11,1+$B$6,1) -> 1218584.9 | K10: =02_R8予算_年次計画置換!K7*IF(16>=11,1+$B$6,1) -> 1206398.6
A11: うち料金改定増収 | B11: =B10-02_R8予算_年次計画置換!B7 -> 0 | C11: =C10-02_R8予算_年次計画置換!C7 -> 0 | D11: =D10-02_R8予算_年次計画置換!D7 -> 0 | E11: =E10-02_R8予算_年次計画置換!E7 -> 0 | F11: =F10-02_R8予算_年次計画置換!F7 -> 85908.142 | G11: =G10-02_R8予算_年次計画置換!G7 -> 85049.036 | H11: =H10-02_R8予算_年次計画置換!H7 -> 84198.501 | I11: =I10-02_R8予算_年次計画置換!I7 -> 83356.465 | ... K11: =K10-02_R8予算_年次計画置換!K7 -> 81697.599
A12: その他営業収益 | B12: =02_R8予算_年次計画置換!B8 -> 30394 | C12: =02_R8予算_年次計画置換!C8 -> 34331 | D12: =02_R8予算_年次計画置換!D8 -> 30613 | E12: =02_R8予算_年次計画置換!E8 -> 30760 | F12: =02_R8予算_年次計画置換!F8 -> 30908 | G12: =02_R8予算_年次計画置換!G8 -> 31057 | H12: =02_R8予算_年次計画置換!H8 -> 31206 | I12: =02_R8予算_年次計画置換!I8 -> 31356 | ... K12: =02_R8予算_年次計画置換!K8 -> 31659
A13: 営業外収益 | B13: =02_R8予算_年次計画置換!B9 -> 354909 | C13: =02_R8予算_年次計画置換!C9 -> 351507 | D13: =02_R8予算_年次計画置換!D9 -> 348767 | E13: =02_R8予算_年次計画置換!E9 -> 351785 | F13: =02_R8予算_年次計画置換!F9 -> 345313 | G13: =02_R8予算_年次計画置換!G9 -> 351534 | H13: =02_R8予算_年次計画置換!H9 -> 350979 | I13: =02_R8予算_年次計画置換!I9 -> 340913 | ... K13: =02_R8予算_年次計画置換!K9 -> 315952
A14: 長期前受金戻入 | B14: =02_R8予算_年次計画置換!B12 -> 281625 | C14: =02_R8予算_年次計画置換!C12 -> 278623 | D14: =02_R8予算_年次計画置換!D12 -> 279812 | E14: =02_R8予算_年次計画置換!E12 -> 285045 | F14: =02_R8予算_年次計画置換!F12 -> 280823 | G14: =02_R8予算_年次計画置換!G12 -> 281581 | H14: =02_R8予算_年次計画置換!H12 -> 283255 | I14: =02_R8予算_年次計画置換!I12 -> 275243 | ... K14: =02_R8予算_年次計画置換!K12 -> 253789
A15: 繰入金・負担金等 | B15: =02_R8予算_年次計画置換!B11 -> 73283 | C15: =02_R8予算_年次計画置換!C11 -> 72779 | D15: =02_R8予算_年次計画置換!D11 -> 68955 | E15: =02_R8予算_年次計画置換!E11 -> 66740 | F15: =02_R8予算_年次計画置換!F11 -> 64490 | G15: =02_R8予算_年次計画置換!G11 -> 62175 | H15: =02_R8予算_年次計画置換!H11 -> 59946 | I15: =02_R8予算_年次計画置換!I11 -> 57892 | ... K15: =02_R8予算_年次計画置換!K11 -> 54385
A16: 特別利益 | B16: =02_R8予算_年次計画置換!B14 -> 2576 | C16: =02_R8予算_年次計画置換!C14 -> 30000 | D16: =02_R8予算_年次計画置換!D14 -> 0 | E16: =02_R8予算_年次計画置換!E14 -> 0 | F16: =02_R8予算_年次計画置換!F14 -> 0 | G16: =02_R8予算_年次計画置換!G14 -> 0 | H16: =02_R8予算_年次計画置換!H14 -> 0 | I16: =02_R8予算_年次計画置換!I14 -> 0 | ... K16: =02_R8予算_年次計画置換!K14 -> 0
A17: 収益的収入合計 | B17: =SUM(B9,B13,B16) -> 1619060 | C17: =SUM(C9,C13,C16) -> 1747782 | D17: =SUM(D9,D13,D16) -> 1586060 | E17: =SUM(E9,E13,E16) -> 1577158 | F17: =SUM(F9,F13,F16) -> 1730703.3 | G17: =SUM(G9,G13,G16) -> 1723528.1 | H17: =SUM(H9,H13,H16) -> 1709712 | I17: =SUM(I9,I13,I16) -> 1686519.9 | ... K17: =SUM(K9,K13,K16) -> 1635707.2
A19: 【収益的支出】
A20: 営業費用 | B20: =02_R8予算_年次計画置換!B18 -> 1479507 | C20: =02_R8予算_年次計画置換!C18 -> 1546573 | D20: =02_R8予算_年次計画置換!D18 -> 1474501 | E20: =02_R8予算_年次計画置換!E18 -> 1482927 | F20: =02_R8予算_年次計画置換!F18 -> 1483351 | G20: =02_R8予算_年次計画置換!G18 -> 1488562 | H20: =02_R8予算_年次計画置換!H18 -> 1498059 | I20: =02_R8予算_年次計画置換!I18 -> 1495740 | ... K20: =02_R8予算_年次計画置換!K18 -> 1481321
A21: 減価償却費 | B21: =02_R8予算_年次計画置換!B25 -> 755782 | C21: =02_R8予算_年次計画置換!C25 -> 746511 | D21: =02_R8予算_年次計画置換!D25 -> 752391 | E21: =02_R8予算_年次計画置換!E25 -> 760508 | F21: =02_R8予算_年次計画置換!F25 -> 760622 | G21: =02_R8予算_年次計画置換!G25 -> 765523 | H21: =02_R8予算_年次計画置換!H25 -> 774709 | I21: =02_R8予算_年次計画置換!I25 -> 772078 | ... K21: =02_R8予算_年次計画置換!K25 -> 757032
A22: 資産減耗・除却費 | B22: =02_R8予算_年次計画置換!B26 -> 0 | C22: =02_R8予算_年次計画置換!C26 -> 12000 | D22: =02_R8予算_年次計画置換!D26 -> 0 | E22: =02_R8予算_年次計画置換!E26 -> 0 | F22: =02_R8予算_年次計画置換!F26 -> 0 | G22: =02_R8予算_年次計画置換!G26 -> 0 | H22: =02_R8予算_年次計画置換!H26 -> 0 | I22: =02_R8予算_年次計画置換!I26 -> 0 | ... K22: =02_R8予算_年次計画置換!K26 -> 0
A23: 営業外費用 | B23: =02_R8予算_年次計画置換!B28 -> 128495 | C23: =02_R8予算_年次計画置換!C28 -> 163407 | D23: =02_R8予算_年次計画置換!D28 -> 122962 | E23: =02_R8予算_年次計画置換!E28 -> 119307 | F23: =02_R8予算_年次計画置換!F28 -> 124016 | G23: =02_R8予算_年次計画置換!G28 -> 123914 | H23: =02_R8予算_年次計画置換!H28 -> 121357 | I23: =02_R8予算_年次計画置換!I28 -> 119621 | ... K23: =02_R8予算_年次計画置換!K28 -> 117112
A24: 支払利息 | B24: =02_R8予算_年次計画置換!B29 -> 118910 | C24: =02_R8予算_年次計画置換!C29 -> 113113 | D24: =02_R8予算_年次計画置換!D29 -> 114281 | E24: =02_R8予算_年次計画置換!E29 -> 110591 | F24: =02_R8予算_年次計画置換!F29 -> 115300 | G24: =02_R8予算_年次計画置換!G29 -> 115163 | H24: =02_R8予算_年次計画置換!H29 -> 112571 | I24: =02_R8予算_年次計画置換!I29 -> 110835 | ... K24: =02_R8予算_年次計画置換!K29 -> 108326
A25: 特別損失 | B25: =02_R8予算_年次計画置換!B31 -> 273 | C25: =02_R8予算_年次計画置換!C31 -> 300 | D25: =02_R8予算_年次計画置換!D31 -> 273 | E25: =02_R8予算_年次計画置換!E31 -> 273 | F25: =02_R8予算_年次計画置換!F31 -> 273 | G25: =02_R8予算_年次計画置換!G31 -> 273 | H25: =02_R8予算_年次計画置換!H31 -> 273 | I25: =02_R8予算_年次計画置換!I31 -> 273 | ... K25: =02_R8予算_年次計画置換!K31 -> 273
A26: 収益的支出合計 | B26: =SUM(B20,B23,B25) -> 1608275 | C26: =SUM(C20,C23,C25) -> 1710280 | D26: =SUM(D20,D23,D25) -> 1597736 | E26: =SUM(E20,E23,E25) -> 1602507 | F26: =SUM(F20,F23,F25) -> 1607640 | G26: =SUM(G20,G23,G25) -> 1612749 | H26: =SUM(H20,H23,H25) -> 1619689 | I26: =SUM(I20,I23,I25) -> 1615634 | ... K26: =SUM(K20,K23,K25) -> 1598706
A27: 経常損益 | B27: =SUM(B9,B13)-SUM(B20,B23) -> 8482 | C27: =SUM(C9,C13)-SUM(C20,C23) -> 7802 | D27: =SUM(D9,D13)-SUM(D20,D23) -> -11403 | E27: =SUM(E9,E13)-SUM(E20,E23) -> -25076 | F27: =SUM(F9,F13)-SUM(F20,F23) -> 123336.28 | G27: =SUM(G9,G13)-SUM(G20,G23) -> 111052.07 | H27: =SUM(H9,H13)-SUM(H20,H23) -> 90296.002 | I27: =SUM(I9,I13)-SUM(I20,I23) -> 71158.931 | ... K27: =SUM(K9,K13)-SUM(K20,K23) -> 37274.199
A28: 純損益 | B28: =B27+B16-B25 -> 10785 | C28: =C27+C16-C25 -> 37502 | D28: =D27+D16-D25 -> -11676 | E28: =E27+E16-E25 -> -25349 | F28: =F27+F16-F25 -> 123063.28 | G28: =G27+G16-G25 -> 110779.07 | H28: =H27+H16-H25 -> 90023.002 | I28: =I27+I16-I25 -> 70885.931 | ... K28: =K27+K16-K25 -> 37001.199
A30: 【経営指標】
A31: 経常収支比率 | B31: =IFERROR((SUM(B9,B13)/SUM(B20,B23))*100,0) -> 100.52749 | C31: =IFERROR((SUM(C9,C13)/SUM(C20,C23))*100,0) -> 100.45626 | D31: =IFERROR((SUM(D9,D13)/SUM(D20,D23))*100,0) -> 99.286181 | E31: =IFERROR((SUM(E9,E13)/SUM(E20,E23))*100,0) -> 98.434935 | F31: =IFERROR((SUM(F9,F13)/SUM(F20,F23))*100,0) -> 107.67319 | G31: =IFERROR((SUM(G9,G13)/SUM(G20,G23))*100,0) -> 106.88705 | H31: =IFERROR((SUM(H9,H13)/SUM(H20,H23))*100,0) -> 105.57584 | I31: =IFERROR((SUM(I9,I13)/SUM(I20,I23))*100,0) -> 104.40514 | ... K31: =IFERROR((SUM(K9,K13)/SUM(K20,K23))*100,0) -> 102.33192
A32: 料金回収率（通常） | B32: =IFERROR(B10/B34*100,0) -> 92.822855 | C32: =IFERROR(C10/C34*100,0) -> 93.054633 | D32: =IFERROR(D10/D34*100,0) -> 91.578119 | E32: =IFERROR(E10/E34*100,0) -> 90.694122 | F32: =IFERROR(F10/F34*100,0) -> 95.630009 | G32: =IFERROR(G10/G34*100,0) -> 94.364171 | H32: =IFERROR(H10/H34*100,0) -> 93.052297 | I32: =IFERROR(I10/I34*100,0) -> 91.849708 | ... K32: =IFERROR(K10/K34*100,0) -> 89.71881
A33: 資産維持費込料金回収率 | B33: =IFERROR(B10/B35*100,0) -> 92.822855 | C33: =IFERROR(C10/C35*100,0) -> 93.054633 | D33: =IFERROR(D10/D35*100,0) -> 91.578119 | E33: =IFERROR(E10/E35*100,0) -> 90.694122 | F33: =IFERROR(F10/F35*100,0) -> 95.630009 | G33: =IFERROR(G10/G35*100,0) -> 94.364171 | H33: =IFERROR(H10/H35*100,0) -> 93.052297 | I33: =IFERROR(I10/I35*100,0) -> 91.849708 | ... K33: =IFERROR(K10/K35*100,0) -> 89.71881
A34: 給水原価対象費用 | B34: =SUM(B20,B23)-B14 -> 1326377 | C34: =SUM(C20,C23)-C14 -> 1431357 | D34: =SUM(D20,D23)-D14 -> 1317651 | E34: =SUM(E20,E23)-E14 -> 1317189 | F34: =SUM(F20,F23)-F14 -> 1326544 | G34: =SUM(G20,G23)-G14 -> 1330895 | H34: =SUM(H20,H23)-H14 -> 1336161 | I34: =SUM(I20,I23)-I14 -> 1340118 | ... K34: =SUM(K20,K23)-K14 -> 1344644
A35: 給水原価対象費用＋資産維持費 | B35: =B34+$B$5 -> 1326377 | C35: =C34+$B$5 -> 1431357 | D35: =D34+$B$5 -> 1317651 | E35: =E34+$B$5 -> 1317189 | F35: =F34+$B$5 -> 1326544 | G35: =G34+$B$5 -> 1330895 | H35: =H34+$B$5 -> 1336161 | I35: =I34+$B$5 -> 1340118 | ... K35: =K34+$B$5 -> 1344644
A36: 総括原価回収率（参考） | B36: =IFERROR(B10/(B20+B23-B14-B12-B15+$B$5)*100,0) -> 100.69363 | C36: =IFERROR(C10/(C20+C23-C14-C12-C15+$B$5)*100,0) -> 100.58124 | D36: =IFERROR(D10/(D20+D23-D14-D12-D15+$B$5)*100,0) -> 99.063857 | E36: =IFERROR(E10/(E20+E23-E14-E12-E15+$B$5)*100,0) -> 97.944066 | F36: =IFERROR(F10/(F20+F23-F14-F12-F15+$B$5)*100,0) -> 103.04011 | G36: =IFERROR(G10/(G20+G23-G14-G12-G15+$B$5)*100,0) -> 101.47254 | H36: =IFERROR(H10/(H20+H23-H14-H12-H15+$B$5)*100,0) -> 99.865021 | I36: =IFERROR(I10/(I20+I23-I14-I12-I15+$B$5)*100,0) -> 98.403069 | ... K36: =IFERROR(K10/(K20+K23-K14-K12-K15+$B$5)*100,0) -> 95.852423
A37: 検証：資産維持費込<=通常 | B37: =IF(B33<=B32,"OK","要確認") -> OK | C37: =IF(C33<=C32,"OK","要確認") -> OK | D37: =IF(D33<=D32,"OK","要確認") -> OK | E37: =IF(E33<=E32,"OK","要確認") -> OK | F37: =IF(F33<=F32,"OK","要確認") -> OK | G37: =IF(G33<=G32,"OK","要確認") -> OK | H37: =IF(H33<=H32,"OK","要確認") -> OK | I37: =IF(I33<=I32,"OK","要確認") -> OK | ... K37: =IF(K33<=K32,"OK","要確認") -> OK
A39: 【資本的収入】
A40: 資本的収入 | B40: =02_R8予算_年次計画置換!B34 -> 698941 | C40: =02_R8予算_年次計画置換!C34 -> 1055380 | D40: =02_R8予算_年次計画置換!D34 -> 577929 | E40: =02_R8予算_年次計画置換!E34 -> 929283 | F40: =02_R8予算_年次計画置換!F34 -> 731849 | G40: =02_R8予算_年次計画置換!G34 -> 571513 | H40: =02_R8予算_年次計画置換!H34 -> 563268 | I40: =02_R8予算_年次計画置換!I34 -> 537092 | ... K40: =02_R8予算_年次計画置換!K34 -> 365500
A41: 企業債 | B41: =02_R8予算_年次計画置換!B35 -> 329000 | C41: =02_R8予算_年次計画置換!C35 -> 713997 | D41: =02_R8予算_年次計画置換!D35 -> 340521 | E41: =02_R8予算_年次計画置換!E35 -> 613585 | F41: =02_R8予算_年次計画置換!F35 -> 336200 | G41: =02_R8予算_年次計画置換!G35 -> 284300 | H41: =02_R8予算_年次計画置換!H35 -> 277930 | I41: =02_R8予算_年次計画置換!I35 -> 368500 | ... K41: =02_R8予算_年次計画置換!K35 -> 230500
A42: 一般会計負担金 | B42: =02_R8予算_年次計画置換!B36 -> 169041 | C42: =02_R8予算_年次計画置換!C36 -> 166838 | D42: =02_R8予算_年次計画置換!D36 -> 162408 | E42: =02_R8予算_年次計画置換!E36 -> 167998 | F42: =02_R8予算_年次計画置換!F36 -> 173649 | G42: =02_R8予算_年次計画置換!G36 -> 182213 | H42: =02_R8予算_年次計画置換!H36 -> 180338 | I42: =02_R8予算_年次計画置換!I36 -> 168592 | ... K42: =02_R8予算_年次計画置換!K36 -> 135000
A43: 一般会計出資金 | B43: =02_R8予算_年次計画置換!B37 -> 0 | C43: =02_R8予算_年次計画置換!C37 -> 0 | D43: =02_R8予算_年次計画置換!D37 -> 0 | E43: =02_R8予算_年次計画置換!E37 -> 0 | F43: =02_R8予算_年次計画置換!F37 -> 0 | G43: =02_R8予算_年次計画置換!G37 -> 0 | H43: =02_R8予算_年次計画置換!H37 -> 0 | I43: =02_R8予算_年次計画置換!I37 -> 0 | ... K43: =02_R8予算_年次計画置換!K37 -> 0
A44: 国庫補助金 | B44: =02_R8予算_年次計画置換!B38 -> 0 | C44: =02_R8予算_年次計画置換!C38 -> 2000 | D44: =02_R8予算_年次計画置換!D38 -> 75000 | E44: =02_R8予算_年次計画置換!E38 -> 147700 | F44: =02_R8予算_年次計画置換!F38 -> 222000 | G44: =02_R8予算_年次計画置換!G38 -> 105000 | H44: =02_R8予算_年次計画置換!H38 -> 105000 | I44: =02_R8予算_年次計画置換!I38 -> 0 | ... K44: =02_R8予算_年次計画置換!K38 -> 0
A45: 固定資産売却代金 | B45: =02_R8予算_年次計画置換!B39 -> 0 | C45: =02_R8予算_年次計画置換!C39 -> 0 | D45: =02_R8予算_年次計画置換!D39 -> 0 | E45: =02_R8予算_年次計画置換!E39 -> 0 | F45: =02_R8予算_年次計画置換!F39 -> 0 | G45: =02_R8予算_年次計画置換!G39 -> 0 | H45: =02_R8予算_年次計画置換!H39 -> 0 | I45: =02_R8予算_年次計画置換!I39 -> 0 | ... K45: =02_R8予算_年次計画置換!K39 -> 0
A46: 工事負担金 | B46: =02_R8予算_年次計画置換!B40 -> 200900 | C46: =02_R8予算_年次計画置換!C40 -> 172545 | D46: =02_R8予算_年次計画置換!D40 -> 0 | E46: =02_R8予算_年次計画置換!E40 -> 0 | F46: =02_R8予算_年次計画置換!F40 -> 0 | G46: =02_R8予算_年次計画置換!G40 -> 0 | H46: =02_R8予算_年次計画置換!H40 -> 0 | I46: =02_R8予算_年次計画置換!I40 -> 0 | ... K46: =02_R8予算_年次計画置換!K40 -> 0
A47: その他・調整 | B47: =02_R8予算_年次計画置換!B41 -> 0 | C47: =02_R8予算_年次計画置換!C41 -> 0 | D47: =02_R8予算_年次計画置換!D41 -> 0 | E47: =02_R8予算_年次計画置換!E41 -> 0 | F47: =02_R8予算_年次計画置換!F41 -> 0 | G47: =02_R8予算_年次計画置換!G41 -> 0 | H47: =02_R8予算_年次計画置換!H41 -> 0 | I47: =02_R8予算_年次計画置換!I41 -> 0 | ... K47: =02_R8予算_年次計画置換!K41 -> 0
A49: 【資本的支出】
A50: 資本的支出 | B50: =02_R8予算_年次計画置換!B44 -> 1123770 | C50: =02_R8予算_年次計画置換!C44 -> 1684475 | D50: =02_R8予算_年次計画置換!D44 -> 1136126 | E50: =02_R8予算_年次計画置換!E44 -> 1437316 | F50: =02_R8予算_年次計画置換!F44 -> 1205541 | G50: =02_R8予算_年次計画置換!G44 -> 976922 | H50: =02_R8予算_年次計画置換!H44 -> 956894 | I50: =02_R8予算_年次計画置換!I44 -> 927272 | ... K50: =02_R8予算_年次計画置換!K44 -> 774903
A51: 建設改良費 | B51: =02_R8予算_年次計画置換!B45 -> 268741 | C51: =02_R8予算_年次計画置換!C45 -> 888542 | D51: =02_R8予算_年次計画置換!D45 -> 403455 | E51: =02_R8予算_年次計画置換!E45 -> 761285 | F51: =02_R8予算_年次計画置換!F45 -> 558200 | G51: =02_R8予算_年次計画置換!G45 -> 389300 | H51: =02_R8予算_年次計画置換!H45 -> 382930 | I51: =02_R8予算_年次計画置換!I45 -> 368500 | ... K51: =02_R8予算_年次計画置換!K45 -> 230500
A52: 企業債償還金 | B52: =02_R8予算_年次計画置換!B46 -> 855029 | C52: =02_R8予算_年次計画置換!C46 -> 795933 | D52: =02_R8予算_年次計画置換!D46 -> 732671 | E52: =02_R8予算_年次計画置換!E46 -> 676031 | F52: =02_R8予算_年次計画置換!F46 -> 647341 | G52: =02_R8予算_年次計画置換!G46 -> 587622 | H52: =02_R8予算_年次計画置換!H46 -> 573964 | I52: =02_R8予算_年次計画置換!I46 -> 558772 | ... K52: =02_R8予算_年次計画置換!K46 -> 544403
A53: その他資本的支出 | B53: =02_R8予算_年次計画置換!B47 -> 0 | C53: =02_R8予算_年次計画置換!C47 -> 0 | D53: =02_R8予算_年次計画置換!D47 -> 0 | E53: =02_R8予算_年次計画置換!E47 -> 0 | F53: =02_R8予算_年次計画置換!F47 -> 0 | G53: =02_R8予算_年次計画置換!G47 -> 0 | H53: =02_R8予算_年次計画置換!H47 -> 0 | I53: =02_R8予算_年次計画置換!I47 -> 0 | ... K53: =02_R8予算_年次計画置換!K47 -> 0
A54: 資本的収支不足額（収入－支出） | B54: =B40-B50 -> -424829 | C54: =C40-C50 -> -629095 | D54: =D40-D50 -> -558197 | E54: =E40-E50 -> -508033 | F54: =F40-F50 -> -473692 | G54: =G40-G50 -> -405409 | H54: =H40-H50 -> -393626 | I54: =I40-I50 -> -390180 | ... K54: =K40-K50 -> -409403
A56: 【現預金・4条財源】
A57: 補てん可能財源相当（簡便CF） | B57: =B28+B21+B22-B14 -> 484942 | C57: =C28+C21+C22-C14 -> 517390 | D57: =D28+D21+D22-D14 -> 460903 | E57: =E28+E21+E22-E14 -> 450114 | F57: =F28+F21+F22-F14 -> 602862.28 | G57: =G28+G21+G22-G14 -> 594721.07 | H57: =H28+H21+H22-H14 -> 581477 | I57: =I28+I21+I22-I14 -> 567720.93 | ... K57: =K28+K21+K22-K14 -> 540244.2
A58: 資本的収支不足額（再掲） | B58: =B54 -> -424829 | C58: =C54 -> -629095 | D58: =D54 -> -558197 | E58: =E54 -> -508033 | F58: =F54 -> -473692 | G58: =G54 -> -405409 | H58: =H54 -> -393626 | I58: =I54 -> -390180 | ... K58: =K54 -> -409403
A59: 年度末現預金残高 | B59: =00_前提・検証!$B$6 -> 242588 | C59: =B59+C57+C58 -> 130883 | D59: =C59+D57+D58 -> 33589 | E59: =D59+E57+E58 -> -24330 | F59: =E59+F57+F58 -> 104840.28 | G59: =F59+G57+G58 -> 294152.36 | H59: =G59+H57+H58 -> 482003.36 | I59: =H59+I57+I58 -> 659544.29 | J59: =I59+J57+J58 -> 811064 | K59: =J59+K57+K58 -> 941905.2
A60: 最低現金目安との差額 | B60: =B59-00_前提・検証!$B$7 -> -57412 | C60: =C59-00_前提・検証!$B$7 -> -169117 | D60: =D59-00_前提・検証!$B$7 -> -266411 | E60: =E59-00_前提・検証!$B$7 -> -324330 | F60: =F59-00_前提・検証!$B$7 -> -195159.72 | G60: =G59-00_前提・検証!$B$7 -> -5847.6443 | H60: =H59-00_前提・検証!$B$7 -> 182003.36 | I60: =I59-00_前提・検証!$B$7 -> 359544.29 | ... K60: =K59-00_前提・検証!$B$7 -> 641905.2
A62: 【建設仮勘定・追加企業債影響：本体へ統合済み（参考ブロックは無効化）】
A63: 項目 | B63: 令和7年度 | C63: 令和8年度 | D63: 令和9年度 | E63: 令和10年度 | F63: 令和11年度 | G63: 令和12年度 | H63: 令和13年度 | I63: 令和14年度 | J63: 令和15年度 | K63: 令和16年度
A64: 減価償却費増加（本体統合済のため0） | B64: 0 | C64: 0 | D64: 0 | E64: 0 | F64: 0 | G64: 0 | H64: 0 | I64: 0 | J64: 0 | K64: 0
A65: 長期前受金戻入増加（本体統合済のため0） | B65: 0 | C65: 0 | D65: 0 | E65: 0 | F65: 0 | G65: 0 | H65: 0 | I65: 0 | J65: 0 | K65: 0
A66: 支払利息増加（本体統合済のため0） | B66: 0 | C66: 0 | D66: 0 | E66: 0 | F66: 0 | G66: 0 | H66: 0 | I66: 0 | J66: 0 | K66: 0
A67: 企業債元金償還増加（本体統合済のため0） | B67: 0 | C67: 0 | D67: 0 | E67: 0 | F67: 0 | G67: 0 | H67: 0 | I67: 0 | J67: 0 | K67: 0
A68: 3条純損益影響 | B68: =B64-B65+B66 -> 0 | C68: =C64-C65+C66 -> 0 | D68: =D64-D65+D66 -> 0 | E68: =E64-E65+E66 -> 0 | F68: =F64-F65+F66 -> 0 | G68: =G64-G65+G66 -> 0 | H68: =H64-H65+H66 -> 0 | I68: =I64-I65+I66 -> 0 | ... K68: =K64-K65+K66 -> 0
A69: 現金支出影響 | B69: =B66+B67 -> 0 | C69: =C66+C67 -> 0 | D69: =D66+D67 -> 0 | E69: =E66+E67 -> 0 | F69: =F66+F67 -> 0 | G69: =G66+G67 -> 0 | H69: =H66+H67 -> 0 | I69: =I66+I67 -> 0 | ... K69: =K66+K67 -> 0
A70: 年度末現預金残高（＝本体、統合後） | B70: =B59-B69 -> 242588 | C70: =C59-SUM($B$69:C69) -> 130883 | D70: =D59-SUM($B$69:D69) -> 33589 | E70: =E59-SUM($B$69:E69) -> -24330 | F70: =F59-SUM($B$69:F69) -> 104840.28 | G70: =G59-SUM($B$69:G69) -> 294152.36 | H70: =H59-SUM($B$69:H69) -> 482003.36 | I70: =I59-SUM($B$69:I69) -> 659544.29 | J70: =J59-SUM($B$69:J69) -> 811064 | K70: =K59-SUM($B$69:K69) -> 941905.2
A72: 補填財源残高（期末・簡便推計） | B72: 183463 | C72: =B72+C57+C58 -> 71758 | D72: =C72+D57+D58 -> -25536 | E72: =D72+E57+E58 -> -83455 | F72: =E72+F57+F58 -> 45715.284 | G72: =F72+G57+G58 -> 235027.36 | H72: =G72+H57+H58 -> 422878.36 | I72: =H72+I57+I58 -> 600419.29 | J72: =I72+J57+J58 -> 751939 | K72: =J72+K57+K58 -> 882780.2
A73: 注：起点はR7末補てん財源経過表（0708修正版）の183,463千円。発生・使用は簡便CF（純損益+減価償却+資産減耗−戻入、4条不足充当）ベースで、消費税資本的収支調整額・剰余金処分の時期差等は未反映。

Sheet SIM_R8予算置換_1%
A1: SIM_R8予算置換_1%
A2: 単位：千円、比率は％。料金改定率はR11〜R15の総括原価回収を基礎に算定し、R11以降の給水収益へ反映。
A3: 区分 | B3: 令和7年度 | C3: 令和8年度 | D3: 令和9年度 | E3: 令和10年度 | F3: 令和11年度 | G3: 令和12年度 | H3: 令和13年度 | I3: 令和14年度 | J3: 令和15年度 | K3: 令和16年度
A4: 資産維持費率 | B4: 0.01
A5: 年額資産維持費（千円） | B5: =00_前提・検証!$B$2*$B$4 -> 164553.64
A6: 料金改定率（R11以降・試算） | B6: =MAX(0,(SUM(02_R8予算_年次計画置換!F18:J18)+SUM(02_R8予算_年次計画置換!F28:J28)-SUM(02_R8予算_年次計画置換!F12:J12)-SUM(02_R8予算_年次計画置換!F8:J8)-SUM(02_R8予算_年次計画置換!F11:J11)+$B$5*5-SUM(02_R8予算_年次計画置換!F7:J7))/SUM(02_R8予算_年次計画置換!F7:J7)) -> 0.21458812
A8: 【収益的収入】
A9: 営業収益 | B9: =SUM(B10:B12) -> 1261575 | C9: =SUM(C10:C12) -> 1366275 | D9: =SUM(D10:D12) -> 1237293 | E9: =SUM(E10:E12) -> 1225373 | F9: =SUM(F10:F12) -> 1721146.2 | G9: =SUM(G10:G12) -> 1704392.3 | H9: =SUM(H10:H12) -> 1687807.1 | I9: =SUM(I10:I12) -> 1671390.1 | ... K9: =SUM(K10:K12) -> 1639055
A10: 給水収益（改定反映後） | B10: =02_R8予算_年次計画置換!B7*IF(7>=11,1+$B$6,1) -> 1231181 | C10: =02_R8予算_年次計画置換!C7*IF(8>=11,1+$B$6,1) -> 1331944 | D10: =02_R8予算_年次計画置換!D7*IF(9>=11,1+$B$6,1) -> 1206680 | E10: =02_R8予算_年次計画置換!E7*IF(10>=11,1+$B$6,1) -> 1194613 | F10: =02_R8予算_年次計画置換!F7*IF(11>=11,1+$B$6,1) -> 1436452.1 | G10: =02_R8予算_年次計画置換!G7*IF(12>=11,1+$B$6,1) -> 1422087.1 | H10: =02_R8予算_年次計画置換!H7*IF(13>=11,1+$B$6,1) -> 1407865.5 | I10: =02_R8予算_年次計画置換!I7*IF(14>=11,1+$B$6,1) -> 1393786 | J10: =02_R8予算_年次計画置換!J7*IF(15>=11,1+$B$6,1) -> 1379847.4 | K10: =02_R8予算_年次計画置換!K7*IF(16>=11,1+$B$6,1) -> 1366048.5
A11: うち料金改定増収 | B11: =B10-02_R8予算_年次計画置換!B7 -> 0 | C11: =C10-02_R8予算_年次計画置換!C7 -> 0 | D11: =D10-02_R8予算_年次計画置換!D7 -> 0 | E11: =E10-02_R8予算_年次計画置換!E7 -> 0 | F11: =F10-02_R8予算_年次計画置換!F7 -> 253786.08 | G11: =G10-02_R8予算_年次計画置換!G7 -> 251248.15 | H11: =H10-02_R8予算_年次計画置換!H7 -> 248735.53 | I11: =I10-02_R8予算_年次計画置換!I7 -> 246248.03 | ... K11: =K10-02_R8予算_年次計画置換!K7 -> 241347.48
A12: その他営業収益 | B12: =02_R8予算_年次計画置換!B8 -> 30394 | C12: =02_R8予算_年次計画置換!C8 -> 34331 | D12: =02_R8予算_年次計画置換!D8 -> 30613 | E12: =02_R8予算_年次計画置換!E8 -> 30760 | F12: =02_R8予算_年次計画置換!F8 -> 30908 | G12: =02_R8予算_年次計画置換!G8 -> 31057 | H12: =02_R8予算_年次計画置換!H8 -> 31206 | I12: =02_R8予算_年次計画置換!I8 -> 31356 | ... K12: =02_R8予算_年次計画置換!K8 -> 31659
A13: 営業外収益 | B13: =02_R8予算_年次計画置換!B9 -> 354909 | C13: =02_R8予算_年次計画置換!C9 -> 351507 | D13: =02_R8予算_年次計画置換!D9 -> 348767 | E13: =02_R8予算_年次計画置換!E9 -> 351785 | F13: =02_R8予算_年次計画置換!F9 -> 345313 | G13: =02_R8予算_年次計画置換!G9 -> 351534 | H13: =02_R8予算_年次計画置換!H9 -> 350979 | I13: =02_R8予算_年次計画置換!I9 -> 340913 | ... K13: =02_R8予算_年次計画置換!K9 -> 315952
A14: 長期前受金戻入 | B14: =02_R8予算_年次計画置換!B12 -> 281625 | C14: =02_R8予算_年次計画置換!C12 -> 278623 | D14: =02_R8予算_年次計画置換!D12 -> 279812 | E14: =02_R8予算_年次計画置換!E12 -> 285045 | F14: =02_R8予算_年次計画置換!F12 -> 280823 | G14: =02_R8予算_年次計画置換!G12 -> 281581 | H14: =02_R8予算_年次計画置換!H12 -> 283255 | I14: =02_R8予算_年次計画置換!I12 -> 275243 | ... K14: =02_R8予算_年次計画置換!K12 -> 253789
A15: 繰入金・負担金等 | B15: =02_R8予算_年次計画置換!B11 -> 73283 | C15: =02_R8予算_年次計画置換!C11 -> 72779 | D15: =02_R8予算_年次計画置換!D11 -> 68955 | E15: =02_R8予算_年次計画置換!E11 -> 66740 | F15: =02_R8予算_年次計画置換!F11 -> 64490 | G15: =02_R8予算_年次計画置換!G11 -> 62175 | H15: =02_R8予算_年次計画置換!H11 -> 59946 | I15: =02_R8予算_年次計画置換!I11 -> 57892 | ... K15: =02_R8予算_年次計画置換!K11 -> 54385
A16: 特別利益 | B16: =02_R8予算_年次計画置換!B14 -> 2576 | C16: =02_R8予算_年次計画置換!C14 -> 30000 | D16: =02_R8予算_年次計画置換!D14 -> 0 | E16: =02_R8予算_年次計画置換!E14 -> 0 | F16: =02_R8予算_年次計画置換!F14 -> 0 | G16: =02_R8予算_年次計画置換!G14 -> 0 | H16: =02_R8予算_年次計画置換!H14 -> 0 | I16: =02_R8予算_年次計画置換!I14 -> 0 | ... K16: =02_R8予算_年次計画置換!K14 -> 0
A17: 収益的収入合計 | B17: =SUM(B9,B13,B16) -> 1619060 | C17: =SUM(C9,C13,C16) -> 1747782 | D17: =SUM(D9,D13,D16) -> 1586060 | E17: =SUM(E9,E13,E16) -> 1577158 | F17: =SUM(F9,F13,F16) -> 2066459.2 | G17: =SUM(G9,G13,G16) -> 2055926.3 | H17: =SUM(H9,H13,H16) -> 2038786.1 | I17: =SUM(I9,I13,I16) -> 2012303.1 | ... K17: =SUM(K9,K13,K16) -> 1955007
A19: 【収益的支出】
A20: 営業費用 | B20: =02_R8予算_年次計画置換!B18 -> 1479507 | C20: =02_R8予算_年次計画置換!C18 -> 1546573 | D20: =02_R8予算_年次計画置換!D18 -> 1474501 | E20: =02_R8予算_年次計画置換!E18 -> 1482927 | F20: =02_R8予算_年次計画置換!F18 -> 1483351 | G20: =02_R8予算_年次計画置換!G18 -> 1488562 | H20: =02_R8予算_年次計画置換!H18 -> 1498059 | I20: =02_R8予算_年次計画置換!I18 -> 1495740 | ... K20: =02_R8予算_年次計画置換!K18 -> 1481321
A21: 減価償却費 | B21: =02_R8予算_年次計画置換!B25 -> 755782 | C21: =02_R8予算_年次計画置換!C25 -> 746511 | D21: =02_R8予算_年次計画置換!D25 -> 752391 | E21: =02_R8予算_年次計画置換!E25 -> 760508 | F21: =02_R8予算_年次計画置換!F25 -> 760622 | G21: =02_R8予算_年次計画置換!G25 -> 765523 | H21: =02_R8予算_年次計画置換!H25 -> 774709 | I21: =02_R8予算_年次計画置換!I25 -> 772078 | ... K21: =02_R8予算_年次計画置換!K25 -> 757032
A22: 資産減耗・除却費 | B22: =02_R8予算_年次計画置換!B26 -> 0 | C22: =02_R8予算_年次計画置換!C26 -> 12000 | D22: =02_R8予算_年次計画置換!D26 -> 0 | E22: =02_R8予算_年次計画置換!E26 -> 0 | F22: =02_R8予算_年次計画置換!F26 -> 0 | G22: =02_R8予算_年次計画置換!G26 -> 0 | H22: =02_R8予算_年次計画置換!H26 -> 0 | I22: =02_R8予算_年次計画置換!I26 -> 0 | ... K22: =02_R8予算_年次計画置換!K26 -> 0
A23: 営業外費用 | B23: =02_R8予算_年次計画置換!B28 -> 128495 | C23: =02_R8予算_年次計画置換!C28 -> 163407 | D23: =02_R8予算_年次計画置換!D28 -> 122962 | E23: =02_R8予算_年次計画置換!E28 -> 119307 | F23: =02_R8予算_年次計画置換!F28 -> 124016 | G23: =02_R8予算_年次計画置換!G28 -> 123914 | H23: =02_R8予算_年次計画置換!H28 -> 121357 | I23: =02_R8予算_年次計画置換!I28 -> 119621 | ... K23: =02_R8予算_年次計画置換!K28 -> 117112
A24: 支払利息 | B24: =02_R8予算_年次計画置換!B29 -> 118910 | C24: =02_R8予算_年次計画置換!C29 -> 113113 | D24: =02_R8予算_年次計画置換!D29 -> 114281 | E24: =02_R8予算_年次計画置換!E29 -> 110591 | F24: =02_R8予算_年次計画置換!F29 -> 115300 | G24: =02_R8予算_年次計画置換!G29 -> 115163 | H24: =02_R8予算_年次計画置換!H29 -> 112571 | I24: =02_R8予算_年次計画置換!I29 -> 110835 | ... K24: =02_R8予算_年次計画置換!K29 -> 108326
A25: 特別損失 | B25: =02_R8予算_年次計画置換!B31 -> 273 | C25: =02_R8予算_年次計画置換!C31 -> 300 | D25: =02_R8予算_年次計画置換!D31 -> 273 | E25: =02_R8予算_年次計画置換!E31 -> 273 | F25: =02_R8予算_年次計画置換!F31 -> 273 | G25: =02_R8予算_年次計画置換!G31 -> 273 | H25: =02_R8予算_年次計画置換!H31 -> 273 | I25: =02_R8予算_年次計画置換!I31 -> 273 | ... K25: =02_R8予算_年次計画置換!K31 -> 273
A26: 収益的支出合計 | B26: =SUM(B20,B23,B25) -> 1608275 | C26: =SUM(C20,C23,C25) -> 1710280 | D26: =SUM(D20,D23,D25) -> 1597736 | E26: =SUM(E20,E23,E25) -> 1602507 | F26: =SUM(F20,F23,F25) -> 1607640 | G26: =SUM(G20,G23,G25) -> 1612749 | H26: =SUM(H20,H23,H25) -> 1619689 | I26: =SUM(I20,I23,I25) -> 1615634 | ... K26: =SUM(K20,K23,K25) -> 1598706
A27: 経常損益 | B27: =SUM(B9,B13)-SUM(B20,B23) -> 8482 | C27: =SUM(C9,C13)-SUM(C20,C23) -> 7802 | D27: =SUM(D9,D13)-SUM(D20,D23) -> -11403 | E27: =SUM(E9,E13)-SUM(E20,E23) -> -25076 | F27: =SUM(F9,F13)-SUM(F20,F23) -> 459092.16 | G27: =SUM(G9,G13)-SUM(G20,G23) -> 443450.29 | H27: =SUM(H9,H13)-SUM(H20,H23) -> 419370.07 | I27: =SUM(I9,I13)-SUM(I20,I23) -> 396942.06 | ... K27: =SUM(K9,K13)-SUM(K20,K23) -> 356573.96
A28: 純損益 | B28: =B27+B16-B25 -> 10785 | C28: =C27+C16-C25 -> 37502 | D28: =D27+D16-D25 -> -11676 | E28: =E27+E16-E25 -> -25349 | F28: =F27+F16-F25 -> 458819.16 | G28: =G27+G16-G25 -> 443177.29 | H28: =H27+H16-H25 -> 419097.07 | I28: =I27+I16-I25 -> 396669.06 | ... K28: =K27+K16-K25 -> 356300.96
A30: 【経営指標】
A31: 経常収支比率 | B31: =IFERROR((SUM(B9,B13)/SUM(B20,B23))*100,0) -> 100.52749 | C31: =IFERROR((SUM(C9,C13)/SUM(C20,C23))*100,0) -> 100.45626 | D31: =IFERROR((SUM(D9,D13)/SUM(D20,D23))*100,0) -> 99.286181 | E31: =IFERROR((SUM(E9,E13)/SUM(E20,E23))*100,0) -> 98.434935 | F31: =IFERROR((SUM(F9,F13)/SUM(F20,F23))*100,0) -> 128.56175 | G31: =IFERROR((SUM(G9,G13)/SUM(G20,G23))*100,0) -> 127.5012 | H31: =IFERROR((SUM(H9,H13)/SUM(H20,H23))*100,0) -> 125.89638 | I31: =IFERROR((SUM(I9,I13)/SUM(I20,I23))*100,0) -> 124.57296 | ... K31: =IFERROR((SUM(K9,K13)/SUM(K20,K23))*100,0) -> 122.30772
A32: 料金回収率（通常） | B32: =IFERROR(B10/B34*100,0) -> 92.822855 | C32: =IFERROR(C10/C34*100,0) -> 93.054633 | D32: =IFERROR(D10/D34*100,0) -> 91.578119 | E32: =IFERROR(E10/E34*100,0) -> 90.694122 | F32: =IFERROR(F10/F34*100,0) -> 108.28529 | G32: =IFERROR(G10/G34*100,0) -> 106.85194 | H32: =IFERROR(H10/H34*100,0) -> 105.36646 | I32: =IFERROR(I10/I34*100,0) -> 104.00472 | ... K32: =IFERROR(K10/K34*100,0) -> 101.59183
A33: 資産維持費込料金回収率 | B33: =IFERROR(B10/B35*100,0) -> 82.57802 | C33: =IFERROR(C10/C35*100,0) -> 83.459811 | D33: =IFERROR(D10/D35*100,0) -> 81.411161 | E33: =IFERROR(E10/E35*100,0) -> 80.622165 | F33: =IFERROR(F10/F35*100,0) -> 96.335212 | G33: =IFERROR(G10/G35*100,0) -> 95.094349 | H33: =IFERROR(H10/H35*100,0) -> 93.813007 | I33: =IFERROR(I10/I35*100,0) -> 92.630577 | ... K33: =IFERROR(K10/K35*100,0) -> 90.514883
A34: 給水原価対象費用 | B34: =SUM(B20,B23)-B14 -> 1326377 | C34: =SUM(C20,C23)-C14 -> 1431357 | D34: =SUM(D20,D23)-D14 -> 1317651 | E34: =SUM(E20,E23)-E14 -> 1317189 | F34: =SUM(F20,F23)-F14 -> 1326544 | G34: =SUM(G20,G23)-G14 -> 1330895 | H34: =SUM(H20,H23)-H14 -> 1336161 | I34: =SUM(I20,I23)-I14 -> 1340118 | ... K34: =SUM(K20,K23)-K14 -> 1344644
A35: 給水原価対象費用＋資産維持費 | B35: =B34+$B$5 -> 1490930.6 | C35: =C34+$B$5 -> 1595910.6 | D35: =D34+$B$5 -> 1482204.6 | E35: =E34+$B$5 -> 1481742.6 | F35: =F34+$B$5 -> 1491097.6 | G35: =G34+$B$5 -> 1495448.6 | H35: =H34+$B$5 -> 1500714.6 | I35: =I34+$B$5 -> 1504671.6 | ... K35: =K34+$B$5 -> 1509197.6
A36: 総括原価回収率（参考） | B36: =IFERROR(B10/(B20+B23-B14-B12-B15+$B$5)*100,0) -> 88.749524 | C36: =IFERROR(C10/(C20+C23-C14-C12-C15+$B$5)*100,0) -> 89.464228 | D36: =IFERROR(D10/(D20+D23-D14-D12-D15+$B$5)*100,0) -> 87.273834 | E36: =IFERROR(E10/(E20+E23-E14-E12-E15+$B$5)*100,0) -> 86.300838 | F36: =IFERROR(F10/(F20+F23-F14-F12-F15+$B$5)*100,0) -> 102.91986 | G36: =IFERROR(G10/(G20+G23-G14-G12-G15+$B$5)*100,0) -> 101.41708 | H36: =IFERROR(H10/(H20+H23-H14-H12-H15+$B$5)*100,0) -> 99.8796 | I36: =IFERROR(I10/(I20+I23-I14-I12-I15+$B$5)*100,0) -> 98.471298 | ... K36: =IFERROR(K10/(K20+K23-K14-K12-K15+$B$5)*100,0) -> 95.987421
A37: 検証：資産維持費込<=通常 | B37: =IF(B33<=B32,"OK","要確認") -> OK | C37: =IF(C33<=C32,"OK","要確認") -> OK | D37: =IF(D33<=D32,"OK","要確認") -> OK | E37: =IF(E33<=E32,"OK","要確認") -> OK | F37: =IF(F33<=F32,"OK","要確認") -> OK | G37: =IF(G33<=G32,"OK","要確認") -> OK | H37: =IF(H33<=H32,"OK","要確認") -> OK | I37: =IF(I33<=I32,"OK","要確認") -> OK | ... K37: =IF(K33<=K32,"OK","要確認") -> OK
A39: 【資本的収入】
A40: 資本的収入 | B40: =02_R8予算_年次計画置換!B34 -> 698941 | C40: =02_R8予算_年次計画置換!C34 -> 1055380 | D40: =02_R8予算_年次計画置換!D34 -> 577929 | E40: =02_R8予算_年次計画置換!E34 -> 929283 | F40: =02_R8予算_年次計画置換!F34 -> 731849 | G40: =02_R8予算_年次計画置換!G34 -> 571513 | H40: =02_R8予算_年次計画置換!H34 -> 563268 | I40: =02_R8予算_年次計画置換!I34 -> 537092 | ... K40: =02_R8予算_年次計画置換!K34 -> 365500
A41: 企業債 | B41: =02_R8予算_年次計画置換!B35 -> 329000 | C41: =02_R8予算_年次計画置換!C35 -> 713997 | D41: =02_R8予算_年次計画置換!D35 -> 340521 | E41: =02_R8予算_年次計画置換!E35 -> 613585 | F41: =02_R8予算_年次計画置換!F35 -> 336200 | G41: =02_R8予算_年次計画置換!G35 -> 284300 | H41: =02_R8予算_年次計画置換!H35 -> 277930 | I41: =02_R8予算_年次計画置換!I35 -> 368500 | ... K41: =02_R8予算_年次計画置換!K35 -> 230500
A42: 一般会計負担金 | B42: =02_R8予算_年次計画置換!B36 -> 169041 | C42: =02_R8予算_年次計画置換!C36 -> 166838 | D42: =02_R8予算_年次計画置換!D36 -> 162408 | E42: =02_R8予算_年次計画置換!E36 -> 167998 | F42: =02_R8予算_年次計画置換!F36 -> 173649 | G42: =02_R8予算_年次計画置換!G36 -> 182213 | H42: =02_R8予算_年次計画置換!H36 -> 180338 | I42: =02_R8予算_年次計画置換!I36 -> 168592 | ... K42: =02_R8予算_年次計画置換!K36 -> 135000
A43: 一般会計出資金 | B43: =02_R8予算_年次計画置換!B37 -> 0 | C43: =02_R8予算_年次計画置換!C37 -> 0 | D43: =02_R8予算_年次計画置換!D37 -> 0 | E43: =02_R8予算_年次計画置換!E37 -> 0 | F43: =02_R8予算_年次計画置換!F37 -> 0 | G43: =02_R8予算_年次計画置換!G37 -> 0 | H43: =02_R8予算_年次計画置換!H37 -> 0 | I43: =02_R8予算_年次計画置換!I37 -> 0 | ... K43: =02_R8予算_年次計画置換!K37 -> 0
A44: 国庫補助金 | B44: =02_R8予算_年次計画置換!B38 -> 0 | C44: =02_R8予算_年次計画置換!C38 -> 2000 | D44: =02_R8予算_年次計画置換!D38 -> 75000 | E44: =02_R8予算_年次計画置換!E38 -> 147700 | F44: =02_R8予算_年次計画置換!F38 -> 222000 | G44: =02_R8予算_年次計画置換!G38 -> 105000 | H44: =02_R8予算_年次計画置換!H38 -> 105000 | I44: =02_R8予算_年次計画置換!I38 -> 0 | ... K44: =02_R8予算_年次計画置換!K38 -> 0
A45: 固定資産売却代金 | B45: =02_R8予算_年次計画置換!B39 -> 0 | C45: =02_R8予算_年次計画置換!C39 -> 0 | D45: =02_R8予算_年次計画置換!D39 -> 0 | E45: =02_R8予算_年次計画置換!E39 -> 0 | F45: =02_R8予算_年次計画置換!F39 -> 0 | G45: =02_R8予算_年次計画置換!G39 -> 0 | H45: =02_R8予算_年次計画置換!H39 -> 0 | I45: =02_R8予算_年次計画置換!I39 -> 0 | ... K45: =02_R8予算_年次計画置換!K39 -> 0
A46: 工事負担金 | B46: =02_R8予算_年次計画置換!B40 -> 200900 | C46: =02_R8予算_年次計画置換!C40 -> 172545 | D46: =02_R8予算_年次計画置換!D40 -> 0 | E46: =02_R8予算_年次計画置換!E40 -> 0 | F46: =02_R8予算_年次計画置換!F40 -> 0 | G46: =02_R8予算_年次計画置換!G40 -> 0 | H46: =02_R8予算_年次計画置換!H40 -> 0 | I46: =02_R8予算_年次計画置換!I40 -> 0 | ... K46: =02_R8予算_年次計画置換!K40 -> 0
A47: その他・調整 | B47: =02_R8予算_年次計画置換!B41 -> 0 | C47: =02_R8予算_年次計画置換!C41 -> 0 | D47: =02_R8予算_年次計画置換!D41 -> 0 | E47: =02_R8予算_年次計画置換!E41 -> 0 | F47: =02_R8予算_年次計画置換!F41 -> 0 | G47: =02_R8予算_年次計画置換!G41 -> 0 | H47: =02_R8予算_年次計画置換!H41 -> 0 | I47: =02_R8予算_年次計画置換!I41 -> 0 | ... K47: =02_R8予算_年次計画置換!K41 -> 0
A49: 【資本的支出】
A50: 資本的支出 | B50: =02_R8予算_年次計画置換!B44 -> 1123770 | C50: =02_R8予算_年次計画置換!C44 -> 1684475 | D50: =02_R8予算_年次計画置換!D44 -> 1136126 | E50: =02_R8予算_年次計画置換!E44 -> 1437316 | F50: =02_R8予算_年次計画置換!F44 -> 1205541 | G50: =02_R8予算_年次計画置換!G44 -> 976922 | H50: =02_R8予算_年次計画置換!H44 -> 956894 | I50: =02_R8予算_年次計画置換!I44 -> 927272 | ... K50: =02_R8予算_年次計画置換!K44 -> 774903
A51: 建設改良費 | B51: =02_R8予算_年次計画置換!B45 -> 268741 | C51: =02_R8予算_年次計画置換!C45 -> 888542 | D51: =02_R8予算_年次計画置換!D45 -> 403455 | E51: =02_R8予算_年次計画置換!E45 -> 761285 | F51: =02_R8予算_年次計画置換!F45 -> 558200 | G51: =02_R8予算_年次計画置換!G45 -> 389300 | H51: =02_R8予算_年次計画置換!H45 -> 382930 | I51: =02_R8予算_年次計画置換!I45 -> 368500 | ... K51: =02_R8予算_年次計画置換!K45 -> 230500
A52: 企業債償還金 | B52: =02_R8予算_年次計画置換!B46 -> 855029 | C52: =02_R8予算_年次計画置換!C46 -> 795933 | D52: =02_R8予算_年次計画置換!D46 -> 732671 | E52: =02_R8予算_年次計画置換!E46 -> 676031 | F52: =02_R8予算_年次計画置換!F46 -> 647341 | G52: =02_R8予算_年次計画置換!G46 -> 587622 | H52: =02_R8予算_年次計画置換!H46 -> 573964 | I52: =02_R8予算_年次計画置換!I46 -> 558772 | ... K52: =02_R8予算_年次計画置換!K46 -> 544403
A53: その他資本的支出 | B53: =02_R8予算_年次計画置換!B47 -> 0 | C53: =02_R8予算_年次計画置換!C47 -> 0 | D53: =02_R8予算_年次計画置換!D47 -> 0 | E53: =02_R8予算_年次計画置換!E47 -> 0 | F53: =02_R8予算_年次計画置換!F47 -> 0 | G53: =02_R8予算_年次計画置換!G47 -> 0 | H53: =02_R8予算_年次計画置換!H47 -> 0 | I53: =02_R8予算_年次計画置換!I47 -> 0 | ... K53: =02_R8予算_年次計画置換!K47 -> 0
A54: 資本的収支不足額（収入－支出） | B54: =B40-B50 -> -424829 | C54: =C40-C50 -> -629095 | D54: =D40-D50 -> -558197 | E54: =E40-E50 -> -508033 | F54: =F40-F50 -> -473692 | G54: =G40-G50 -> -405409 | H54: =H40-H50 -> -393626 | I54: =I40-I50 -> -390180 | ... K54: =K40-K50 -> -409403
A56: 【現預金・4条財源】
A57: 補てん可能財源相当（簡便CF） | B57: =B28+B21+B22-B14 -> 484942 | C57: =C28+C21+C22-C14 -> 517390 | D57: =D28+D21+D22-D14 -> 460903 | E57: =E28+E21+E22-E14 -> 450114 | F57: =F28+F21+F22-F14 -> 938618.16 | G57: =G28+G21+G22-G14 -> 927119.29 | H57: =H28+H21+H22-H14 -> 910551.07 | I57: =I28+I21+I22-I14 -> 893504.06 | ... K57: =K28+K21+K22-K14 -> 859543.96
A58: 資本的収支不足額（再掲） | B58: =B54 -> -424829 | C58: =C54 -> -629095 | D58: =D54 -> -558197 | E58: =E54 -> -508033 | F58: =F54 -> -473692 | G58: =G54 -> -405409 | H58: =H54 -> -393626 | I58: =I54 -> -390180 | ... K58: =K54 -> -409403
A59: 年度末現預金残高 | B59: =00_前提・検証!$B$6 -> 242588 | C59: =B59+C57+C58 -> 130883 | D59: =C59+D57+D58 -> 33589 | E59: =D59+E57+E58 -> -24330 | F59: =E59+F57+F58 -> 440596.16 | G59: =F59+G57+G58 -> 962306.45 | H59: =G59+H57+H58 -> 1479231.5 | I59: =H59+I57+I58 -> 1982555.6 | J59: =I59+J57+J58 -> 2456600.4 | K59: =J59+K57+K58 -> 2906741.4
A60: 最低現金目安との差額 | B60: =B59-00_前提・検証!$B$7 -> -57412 | C60: =C59-00_前提・検証!$B$7 -> -169117 | D60: =D59-00_前提・検証!$B$7 -> -266411 | E60: =E59-00_前提・検証!$B$7 -> -324330 | F60: =F59-00_前提・検証!$B$7 -> 140596.16 | G60: =G59-00_前提・検証!$B$7 -> 662306.45 | H60: =H59-00_前提・検証!$B$7 -> 1179231.5 | I60: =I59-00_前提・検証!$B$7 -> 1682555.6 | ... K60: =K59-00_前提・検証!$B$7 -> 2606741.4
A62: 【建設仮勘定・追加企業債影響：本体へ統合済み（参考ブロックは無効化）】
A63: 項目 | B63: 令和7年度 | C63: 令和8年度 | D63: 令和9年度 | E63: 令和10年度 | F63: 令和11年度 | G63: 令和12年度 | H63: 令和13年度 | I63: 令和14年度 | J63: 令和15年度 | K63: 令和16年度
A64: 減価償却費増加（本体統合済のため0） | B64: 0 | C64: 0 | D64: 0 | E64: 0 | F64: 0 | G64: 0 | H64: 0 | I64: 0 | J64: 0 | K64: 0
A65: 長期前受金戻入増加（本体統合済のため0） | B65: 0 | C65: 0 | D65: 0 | E65: 0 | F65: 0 | G65: 0 | H65: 0 | I65: 0 | J65: 0 | K65: 0
A66: 支払利息増加（本体統合済のため0） | B66: 0 | C66: 0 | D66: 0 | E66: 0 | F66: 0 | G66: 0 | H66: 0 | I66: 0 | J66: 0 | K66: 0
A67: 企業債元金償還増加（本体統合済のため0） | B67: 0 | C67: 0 | D67: 0 | E67: 0 | F67: 0 | G67: 0 | H67: 0 | I67: 0 | J67: 0 | K67: 0
A68: 3条純損益影響 | B68: =B64-B65+B66 -> 0 | C68: =C64-C65+C66 -> 0 | D68: =D64-D65+D66 -> 0 | E68: =E64-E65+E66 -> 0 | F68: =F64-F65+F66 -> 0 | G68: =G64-G65+G66 -> 0 | H68: =H64-H65+H66 -> 0 | I68: =I64-I65+I66 -> 0 | ... K68: =K64-K65+K66 -> 0
A69: 現金支出影響 | B69: =B66+B67 -> 0 | C69: =C66+C67 -> 0 | D69: =D66+D67 -> 0 | E69: =E66+E67 -> 0 | F69: =F66+F67 -> 0 | G69: =G66+G67 -> 0 | H69: =H66+H67 -> 0 | I69: =I66+I67 -> 0 | ... K69: =K66+K67 -> 0
A70: 年度末現預金残高（＝本体、統合後） | B70: =B59-B69 -> 242588 | C70: =C59-SUM($B$69:C69) -> 130883 | D70: =D59-SUM($B$69:D69) -> 33589 | E70: =E59-SUM($B$69:E69) -> -24330 | F70: =F59-SUM($B$69:F69) -> 440596.16 | G70: =G59-SUM($B$69:G69) -> 962306.45 | H70: =H59-SUM($B$69:H69) -> 1479231.5 | I70: =I59-SUM($B$69:I69) -> 1982555.6 | J70: =J59-SUM($B$69:J69) -> 2456600.4 | K70: =K59-SUM($B$69:K69) -> 2906741.4
A72: 補填財源残高（期末・簡便推計） | B72: 183463 | C72: =B72+C57+C58 -> 71758 | D72: =C72+D57+D58 -> -25536 | E72: =D72+E57+E58 -> -83455 | F72: =E72+F57+F58 -> 381471.16 | G72: =F72+G57+G58 -> 903181.45 | H72: =G72+H57+H58 -> 1420106.5 | I72: =H72+I57+I58 -> 1923430.6 | J72: =I72+J57+J58 -> 2397475.4 | K72: =J72+K57+K58 -> 2847616.4
A73: 注：起点はR7末補てん財源経過表（0708修正版）の183,463千円。発生・使用は簡便CF（純損益+減価償却+資産減耗−戻入、4条不足充当）ベースで、消費税資本的収支調整額・剰余金処分の時期差等は未反映。

Sheet SIM_R8予算置換_2%
A1: SIM_R8予算置換_2%
A2: 単位：千円、比率は％。料金改定率はR11〜R15の総括原価回収を基礎に算定し、R11以降の給水収益へ反映。
A3: 区分 | B3: 令和7年度 | C3: 令和8年度 | D3: 令和9年度 | E3: 令和10年度 | F3: 令和11年度 | G3: 令和12年度 | H3: 令和13年度 | I3: 令和14年度 | J3: 令和15年度 | K3: 令和16年度
A4: 資産維持費率 | B4: 0.02
A5: 年額資産維持費（千円） | B5: =00_前提・検証!$B$2*$B$4 -> 329107.28
A6: 料金改定率（R11以降・試算） | B6: =MAX(0,(SUM(02_R8予算_年次計画置換!F18:J18)+SUM(02_R8予算_年次計画置換!F28:J28)-SUM(02_R8予算_年次計画置換!F12:J12)-SUM(02_R8予算_年次計画置換!F8:J8)-SUM(02_R8予算_年次計画置換!F11:J11)+$B$5*5-SUM(02_R8予算_年次計画置換!F7:J7))/SUM(02_R8予算_年次計画置換!F7:J7)) -> 0.35653686
A8: 【収益的収入】
A9: 営業収益 | B9: =SUM(B10:B12) -> 1261575 | C9: =SUM(C10:C12) -> 1366275 | D9: =SUM(D10:D12) -> 1237293 | E9: =SUM(E10:E12) -> 1225373 | F9: =SUM(F10:F12) -> 2056902 | G9: =SUM(G10:G12) -> 2036790.5 | H9: =SUM(H10:H12) -> 2016881.1 | I9: =SUM(I10:I12) -> 1997173.2 | ... K9: =SUM(K10:K12) -> 1958354.7
A10: 給水収益（改定反映後） | B10: =02_R8予算_年次計画置換!B7*IF(7>=11,1+$B$6,1) -> 1231181 | C10: =02_R8予算_年次計画置換!C7*IF(8>=11,1+$B$6,1) -> 1331944 | D10: =02_R8予算_年次計画置換!D7*IF(9>=11,1+$B$6,1) -> 1206680 | E10: =02_R8予算_年次計画置換!E7*IF(10>=11,1+$B$6,1) -> 1194613 | F10: =02_R8予算_年次計画置換!F7*IF(11>=11,1+$B$6,1) -> 1604330 | G10: =02_R8予算_年次計画置換!G7*IF(12>=11,1+$B$6,1) -> 1588286.3 | H10: =02_R8予算_年次計画置換!H7*IF(13>=11,1+$B$6,1) -> 1572402.6 | I10: =02_R8予算_年次計画置換!I7*IF(14>=11,1+$B$6,1) -> 1556677.6 | J10: =02_R8予算_年次計画置換!J7*IF(15>=11,1+$B$6,1) -> 1541110 | K10: =02_R8予算_年次計画置換!K7*IF(16>=11,1+$B$6,1) -> 1525698.4
A11: うち料金改定増収 | B11: =B10-02_R8予算_年次計画置換!B7 -> 0 | C11: =C10-02_R8予算_年次計画置換!C7 -> 0 | D11: =D10-02_R8予算_年次計画置換!D7 -> 0 | E11: =E10-02_R8予算_年次計画置換!E7 -> 0 | F11: =F10-02_R8予算_年次計画置換!F7 -> 421664.02 | G11: =G10-02_R8予算_年次計画置換!G7 -> 417447.26 | H11: =H10-02_R8予算_年次計画置換!H7 -> 413272.57 | I11: =I10-02_R8予算_年次計画置換!I7 -> 409139.59 | ... K11: =K10-02_R8予算_年次計画置換!K7 -> 400997.36
A12: その他営業収益 | B12: =02_R8予算_年次計画置換!B8 -> 30394 | C12: =02_R8予算_年次計画置換!C8 -> 34331 | D12: =02_R8予算_年次計画置換!D8 -> 30613 | E12: =02_R8予算_年次計画置換!E8 -> 30760 | F12: =02_R8予算_年次計画置換!F8 -> 30908 | G12: =02_R8予算_年次計画置換!G8 -> 31057 | H12: =02_R8予算_年次計画置換!H8 -> 31206 | I12: =02_R8予算_年次計画置換!I8 -> 31356 | ... K12: =02_R8予算_年次計画置換!K8 -> 31659
A13: 営業外収益 | B13: =02_R8予算_年次計画置換!B9 -> 354909 | C13: =02_R8予算_年次計画置換!C9 -> 351507 | D13: =02_R8予算_年次計画置換!D9 -> 348767 | E13: =02_R8予算_年次計画置換!E9 -> 351785 | F13: =02_R8予算_年次計画置換!F9 -> 345313 | G13: =02_R8予算_年次計画置換!G9 -> 351534 | H13: =02_R8予算_年次計画置換!H9 -> 350979 | I13: =02_R8予算_年次計画置換!I9 -> 340913 | ... K13: =02_R8予算_年次計画置換!K9 -> 315952
A14: 長期前受金戻入 | B14: =02_R8予算_年次計画置換!B12 -> 281625 | C14: =02_R8予算_年次計画置換!C12 -> 278623 | D14: =02_R8予算_年次計画置換!D12 -> 279812 | E14: =02_R8予算_年次計画置換!E12 -> 285045 | F14: =02_R8予算_年次計画置換!F12 -> 280823 | G14: =02_R8予算_年次計画置換!G12 -> 281581 | H14: =02_R8予算_年次計画置換!H12 -> 283255 | I14: =02_R8予算_年次計画置換!I12 -> 275243 | ... K14: =02_R8予算_年次計画置換!K12 -> 253789
A15: 繰入金・負担金等 | B15: =02_R8予算_年次計画置換!B11 -> 73283 | C15: =02_R8予算_年次計画置換!C11 -> 72779 | D15: =02_R8予算_年次計画置換!D11 -> 68955 | E15: =02_R8予算_年次計画置換!E11 -> 66740 | F15: =02_R8予算_年次計画置換!F11 -> 64490 | G15: =02_R8予算_年次計画置換!G11 -> 62175 | H15: =02_R8予算_年次計画置換!H11 -> 59946 | I15: =02_R8予算_年次計画置換!I11 -> 57892 | ... K15: =02_R8予算_年次計画置換!K11 -> 54385
A16: 特別利益 | B16: =02_R8予算_年次計画置換!B14 -> 2576 | C16: =02_R8予算_年次計画置換!C14 -> 30000 | D16: =02_R8予算_年次計画置換!D14 -> 0 | E16: =02_R8予算_年次計画置換!E14 -> 0 | F16: =02_R8予算_年次計画置換!F14 -> 0 | G16: =02_R8予算_年次計画置換!G14 -> 0 | H16: =02_R8予算_年次計画置換!H14 -> 0 | I16: =02_R8予算_年次計画置換!I14 -> 0 | ... K16: =02_R8予算_年次計画置換!K14 -> 0
A17: 収益的収入合計 | B17: =SUM(B9,B13,B16) -> 1619060 | C17: =SUM(C9,C13,C16) -> 1747782 | D17: =SUM(D9,D13,D16) -> 1586060 | E17: =SUM(E9,E13,E16) -> 1577158 | F17: =SUM(F9,F13,F16) -> 2402215 | G17: =SUM(G9,G13,G16) -> 2388324.5 | H17: =SUM(H9,H13,H16) -> 2367860.1 | I17: =SUM(I9,I13,I16) -> 2338086.2 | ... K17: =SUM(K9,K13,K16) -> 2274306.7
A19: 【収益的支出】
A20: 営業費用 | B20: =02_R8予算_年次計画置換!B18 -> 1479507 | C20: =02_R8予算_年次計画置換!C18 -> 1546573 | D20: =02_R8予算_年次計画置換!D18 -> 1474501 | E20: =02_R8予算_年次計画置換!E18 -> 1482927 | F20: =02_R8予算_年次計画置換!F18 -> 1483351 | G20: =02_R8予算_年次計画置換!G18 -> 1488562 | H20: =02_R8予算_年次計画置換!H18 -> 1498059 | I20: =02_R8予算_年次計画置換!I18 -> 1495740 | ... K20: =02_R8予算_年次計画置換!K18 -> 1481321
A21: 減価償却費 | B21: =02_R8予算_年次計画置換!B25 -> 755782 | C21: =02_R8予算_年次計画置換!C25 -> 746511 | D21: =02_R8予算_年次計画置換!D25 -> 752391 | E21: =02_R8予算_年次計画置換!E25 -> 760508 | F21: =02_R8予算_年次計画置換!F25 -> 760622 | G21: =02_R8予算_年次計画置換!G25 -> 765523 | H21: =02_R8予算_年次計画置換!H25 -> 774709 | I21: =02_R8予算_年次計画置換!I25 -> 772078 | ... K21: =02_R8予算_年次計画置換!K25 -> 757032
A22: 資産減耗・除却費 | B22: =02_R8予算_年次計画置換!B26 -> 0 | C22: =02_R8予算_年次計画置換!C26 -> 12000 | D22: =02_R8予算_年次計画置換!D26 -> 0 | E22: =02_R8予算_年次計画置換!E26 -> 0 | F22: =02_R8予算_年次計画置換!F26 -> 0 | G22: =02_R8予算_年次計画置換!G26 -> 0 | H22: =02_R8予算_年次計画置換!H26 -> 0 | I22: =02_R8予算_年次計画置換!I26 -> 0 | ... K22: =02_R8予算_年次計画置換!K26 -> 0
A23: 営業外費用 | B23: =02_R8予算_年次計画置換!B28 -> 128495 | C23: =02_R8予算_年次計画置換!C28 -> 163407 | D23: =02_R8予算_年次計画置換!D28 -> 122962 | E23: =02_R8予算_年次計画置換!E28 -> 119307 | F23: =02_R8予算_年次計画置換!F28 -> 124016 | G23: =02_R8予算_年次計画置換!G28 -> 123914 | H23: =02_R8予算_年次計画置換!H28 -> 121357 | I23: =02_R8予算_年次計画置換!I28 -> 119621 | ... K23: =02_R8予算_年次計画置換!K28 -> 117112
A24: 支払利息 | B24: =02_R8予算_年次計画置換!B29 -> 118910 | C24: =02_R8予算_年次計画置換!C29 -> 113113 | D24: =02_R8予算_年次計画置換!D29 -> 114281 | E24: =02_R8予算_年次計画置換!E29 -> 110591 | F24: =02_R8予算_年次計画置換!F29 -> 115300 | G24: =02_R8予算_年次計画置換!G29 -> 115163 | H24: =02_R8予算_年次計画置換!H29 -> 112571 | I24: =02_R8予算_年次計画置換!I29 -> 110835 | ... K24: =02_R8予算_年次計画置換!K29 -> 108326
A25: 特別損失 | B25: =02_R8予算_年次計画置換!B31 -> 273 | C25: =02_R8予算_年次計画置換!C31 -> 300 | D25: =02_R8予算_年次計画置換!D31 -> 273 | E25: =02_R8予算_年次計画置換!E31 -> 273 | F25: =02_R8予算_年次計画置換!F31 -> 273 | G25: =02_R8予算_年次計画置換!G31 -> 273 | H25: =02_R8予算_年次計画置換!H31 -> 273 | I25: =02_R8予算_年次計画置換!I31 -> 273 | ... K25: =02_R8予算_年次計画置換!K31 -> 273
A26: 収益的支出合計 | B26: =SUM(B20,B23,B25) -> 1608275 | C26: =SUM(C20,C23,C25) -> 1710280 | D26: =SUM(D20,D23,D25) -> 1597736 | E26: =SUM(E20,E23,E25) -> 1602507 | F26: =SUM(F20,F23,F25) -> 1607640 | G26: =SUM(G20,G23,G25) -> 1612749 | H26: =SUM(H20,H23,H25) -> 1619689 | I26: =SUM(I20,I23,I25) -> 1615634 | ... K26: =SUM(K20,K23,K25) -> 1598706
A27: 経常損益 | B27: =SUM(B9,B13)-SUM(B20,B23) -> 8482 | C27: =SUM(C9,C13)-SUM(C20,C23) -> 7802 | D27: =SUM(D9,D13)-SUM(D20,D23) -> -11403 | E27: =SUM(E9,E13)-SUM(E20,E23) -> -25076 | F27: =SUM(F9,F13)-SUM(F20,F23) -> 794848.03 | G27: =SUM(G9,G13)-SUM(G20,G23) -> 775848.51 | H27: =SUM(H9,H13)-SUM(H20,H23) -> 748444.13 | I27: =SUM(I9,I13)-SUM(I20,I23) -> 722725.18 | ... K27: =SUM(K9,K13)-SUM(K20,K23) -> 675873.72
A28: 純損益 | B28: =B27+B16-B25 -> 10785 | C28: =C27+C16-C25 -> 37502 | D28: =D27+D16-D25 -> -11676 | E28: =E27+E16-E25 -> -25349 | F28: =F27+F16-F25 -> 794575.03 | G28: =G27+G16-G25 -> 775575.51 | H28: =H27+H16-H25 -> 748171.13 | I28: =I27+I16-I25 -> 722452.18 | ... K28: =K27+K16-K25 -> 675600.72
A30: 【経営指標】
A31: 経常収支比率 | B31: =IFERROR((SUM(B9,B13)/SUM(B20,B23))*100,0) -> 100.52749 | C31: =IFERROR((SUM(C9,C13)/SUM(C20,C23))*100,0) -> 100.45626 | D31: =IFERROR((SUM(D9,D13)/SUM(D20,D23))*100,0) -> 99.286181 | E31: =IFERROR((SUM(E9,E13)/SUM(E20,E23))*100,0) -> 98.434935 | F31: =IFERROR((SUM(F9,F13)/SUM(F20,F23))*100,0) -> 149.45031 | G31: =IFERROR((SUM(G9,G13)/SUM(G20,G23))*100,0) -> 148.11535 | H31: =IFERROR((SUM(H9,H13)/SUM(H20,H23))*100,0) -> 146.21692 | I31: =IFERROR((SUM(I9,I13)/SUM(I20,I23))*100,0) -> 144.74078 | ... K31: =IFERROR((SUM(K9,K13)/SUM(K20,K23))*100,0) -> 142.28352
A32: 料金回収率（通常） | B32: =IFERROR(B10/B34*100,0) -> 92.822855 | C32: =IFERROR(C10/C34*100,0) -> 93.054633 | D32: =IFERROR(D10/D34*100,0) -> 91.578119 | E32: =IFERROR(E10/E34*100,0) -> 90.694122 | F32: =IFERROR(F10/F34*100,0) -> 120.94058 | G32: =IFERROR(G10/G34*100,0) -> 119.33971 | H32: =IFERROR(H10/H34*100,0) -> 117.68062 | I32: =IFERROR(I10/I34*100,0) -> 116.15974 | ... K32: =IFERROR(K10/K34*100,0) -> 113.46485
A33: 資産維持費込料金回収率 | B33: =IFERROR(B10/B35*100,0) -> 74.369839 | C33: =IFERROR(C10/C35*100,0) -> 75.658678 | D33: =IFERROR(D10/D35*100,0) -> 73.276085 | E33: =IFERROR(E10/E35*100,0) -> 72.56367 | F33: =IFERROR(F10/F35*100,0) -> 96.900237 | G33: =IFERROR(G10/G35*100,0) -> 95.679763 | H33: =IFERROR(H10/H35*100,0) -> 94.423378 | I33: =IFERROR(I10/I35*100,0) -> 93.257489 | ... K33: =IFERROR(K10/K35*100,0) -> 91.154425
A34: 給水原価対象費用 | B34: =SUM(B20,B23)-B14 -> 1326377 | C34: =SUM(C20,C23)-C14 -> 1431357 | D34: =SUM(D20,D23)-D14 -> 1317651 | E34: =SUM(E20,E23)-E14 -> 1317189 | F34: =SUM(F20,F23)-F14 -> 1326544 | G34: =SUM(G20,G23)-G14 -> 1330895 | H34: =SUM(H20,H23)-H14 -> 1336161 | I34: =SUM(I20,I23)-I14 -> 1340118 | ... K34: =SUM(K20,K23)-K14 -> 1344644
A35: 給水原価対象費用＋資産維持費 | B35: =B34+$B$5 -> 1655484.3 | C35: =C34+$B$5 -> 1760464.3 | D35: =D34+$B$5 -> 1646758.3 | E35: =E34+$B$5 -> 1646296.3 | F35: =F34+$B$5 -> 1655651.3 | G35: =G34+$B$5 -> 1660002.3 | H35: =H34+$B$5 -> 1665268.3 | I35: =I34+$B$5 -> 1669225.3 | ... K35: =K34+$B$5 -> 1673751.3
A36: 総括原価回収率（参考） | B36: =IFERROR(B10/(B20+B23-B14-B12-B15+$B$5)*100,0) -> 79.338525 | C36: =IFERROR(C10/(C20+C23-C14-C12-C15+$B$5)*100,0) -> 80.560108 | D36: =IFERROR(D10/(D20+D23-D14-D12-D15+$B$5)*100,0) -> 77.9917 | E36: =IFERROR(E10/(E20+E23-E14-E12-E15+$B$5)*100,0) -> 77.131706 | F36: =IFERROR(F10/(F20+F23-F14-F12-F15+$B$5)*100,0) -> 102.82497 | G36: =IFERROR(G10/(G20+G23-G14-G12-G15+$B$5)*100,0) -> 101.37327 | H36: =IFERROR(H10/(H20+H23-H14-H12-H15+$B$5)*100,0) -> 99.891132 | I36: =IFERROR(I10/(I20+I23-I14-I12-I15+$B$5)*100,0) -> 98.525315 | ... K36: =IFERROR(K10/(K20+K23-K14-K12-K15+$B$5)*100,0) -> 96.094436
A37: 検証：資産維持費込<=通常 | B37: =IF(B33<=B32,"OK","要確認") -> OK | C37: =IF(C33<=C32,"OK","要確認") -> OK | D37: =IF(D33<=D32,"OK","要確認") -> OK | E37: =IF(E33<=E32,"OK","要確認") -> OK | F37: =IF(F33<=F32,"OK","要確認") -> OK | G37: =IF(G33<=G32,"OK","要確認") -> OK | H37: =IF(H33<=H32,"OK","要確認") -> OK | I37: =IF(I33<=I32,"OK","要確認") -> OK | ... K37: =IF(K33<=K32,"OK","要確認") -> OK
A39: 【資本的収入】
A40: 資本的収入 | B40: =02_R8予算_年次計画置換!B34 -> 698941 | C40: =02_R8予算_年次計画置換!C34 -> 1055380 | D40: =02_R8予算_年次計画置換!D34 -> 577929 | E40: =02_R8予算_年次計画置換!E34 -> 929283 | F40: =02_R8予算_年次計画置換!F34 -> 731849 | G40: =02_R8予算_年次計画置換!G34 -> 571513 | H40: =02_R8予算_年次計画置換!H34 -> 563268 | I40: =02_R8予算_年次計画置換!I34 -> 537092 | ... K40: =02_R8予算_年次計画置換!K34 -> 365500
A41: 企業債 | B41: =02_R8予算_年次計画置換!B35 -> 329000 | C41: =02_R8予算_年次計画置換!C35 -> 713997 | D41: =02_R8予算_年次計画置換!D35 -> 340521 | E41: =02_R8予算_年次計画置換!E35 -> 613585 | F41: =02_R8予算_年次計画置換!F35 -> 336200 | G41: =02_R8予算_年次計画置換!G35 -> 284300 | H41: =02_R8予算_年次計画置換!H35 -> 277930 | I41: =02_R8予算_年次計画置換!I35 -> 368500 | ... K41: =02_R8予算_年次計画置換!K35 -> 230500
A42: 一般会計負担金 | B42: =02_R8予算_年次計画置換!B36 -> 169041 | C42: =02_R8予算_年次計画置換!C36 -> 166838 | D42: =02_R8予算_年次計画置換!D36 -> 162408 | E42: =02_R8予算_年次計画置換!E36 -> 167998 | F42: =02_R8予算_年次計画置換!F36 -> 173649 | G42: =02_R8予算_年次計画置換!G36 -> 182213 | H42: =02_R8予算_年次計画置換!H36 -> 180338 | I42: =02_R8予算_年次計画置換!I36 -> 168592 | ... K42: =02_R8予算_年次計画置換!K36 -> 135000
A43: 一般会計出資金 | B43: =02_R8予算_年次計画置換!B37 -> 0 | C43: =02_R8予算_年次計画置換!C37 -> 0 | D43: =02_R8予算_年次計画置換!D37 -> 0 | E43: =02_R8予算_年次計画置換!E37 -> 0 | F43: =02_R8予算_年次計画置換!F37 -> 0 | G43: =02_R8予算_年次計画置換!G37 -> 0 | H43: =02_R8予算_年次計画置換!H37 -> 0 | I43: =02_R8予算_年次計画置換!I37 -> 0 | ... K43: =02_R8予算_年次計画置換!K37 -> 0
A44: 国庫補助金 | B44: =02_R8予算_年次計画置換!B38 -> 0 | C44: =02_R8予算_年次計画置換!C38 -> 2000 | D44: =02_R8予算_年次計画置換!D38 -> 75000 | E44: =02_R8予算_年次計画置換!E38 -> 147700 | F44: =02_R8予算_年次計画置換!F38 -> 222000 | G44: =02_R8予算_年次計画置換!G38 -> 105000 | H44: =02_R8予算_年次計画置換!H38 -> 105000 | I44: =02_R8予算_年次計画置換!I38 -> 0 | ... K44: =02_R8予算_年次計画置換!K38 -> 0
A45: 固定資産売却代金 | B45: =02_R8予算_年次計画置換!B39 -> 0 | C45: =02_R8予算_年次計画置換!C39 -> 0 | D45: =02_R8予算_年次計画置換!D39 -> 0 | E45: =02_R8予算_年次計画置換!E39 -> 0 | F45: =02_R8予算_年次計画置換!F39 -> 0 | G45: =02_R8予算_年次計画置換!G39 -> 0 | H45: =02_R8予算_年次計画置換!H39 -> 0 | I45: =02_R8予算_年次計画置換!I39 -> 0 | ... K45: =02_R8予算_年次計画置換!K39 -> 0
A46: 工事負担金 | B46: =02_R8予算_年次計画置換!B40 -> 200900 | C46: =02_R8予算_年次計画置換!C40 -> 172545 | D46: =02_R8予算_年次計画置換!D40 -> 0 | E46: =02_R8予算_年次計画置換!E40 -> 0 | F46: =02_R8予算_年次計画置換!F40 -> 0 | G46: =02_R8予算_年次計画置換!G40 -> 0 | H46: =02_R8予算_年次計画置換!H40 -> 0 | I46: =02_R8予算_年次計画置換!I40 -> 0 | ... K46: =02_R8予算_年次計画置換!K40 -> 0
A47: その他・調整 | B47: =02_R8予算_年次計画置換!B41 -> 0 | C47: =02_R8予算_年次計画置換!C41 -> 0 | D47: =02_R8予算_年次計画置換!D41 -> 0 | E47: =02_R8予算_年次計画置換!E41 -> 0 | F47: =02_R8予算_年次計画置換!F41 -> 0 | G47: =02_R8予算_年次計画置換!G41 -> 0 | H47: =02_R8予算_年次計画置換!H41 -> 0 | I47: =02_R8予算_年次計画置換!I41 -> 0 | ... K47: =02_R8予算_年次計画置換!K41 -> 0
A49: 【資本的支出】
A50: 資本的支出 | B50: =02_R8予算_年次計画置換!B44 -> 1123770 | C50: =02_R8予算_年次計画置換!C44 -> 1684475 | D50: =02_R8予算_年次計画置換!D44 -> 1136126 | E50: =02_R8予算_年次計画置換!E44 -> 1437316 | F50: =02_R8予算_年次計画置換!F44 -> 1205541 | G50: =02_R8予算_年次計画置換!G44 -> 976922 | H50: =02_R8予算_年次計画置換!H44 -> 956894 | I50: =02_R8予算_年次計画置換!I44 -> 927272 | ... K50: =02_R8予算_年次計画置換!K44 -> 774903
A51: 建設改良費 | B51: =02_R8予算_年次計画置換!B45 -> 268741 | C51: =02_R8予算_年次計画置換!C45 -> 888542 | D51: =02_R8予算_年次計画置換!D45 -> 403455 | E51: =02_R8予算_年次計画置換!E45 -> 761285 | F51: =02_R8予算_年次計画置換!F45 -> 558200 | G51: =02_R8予算_年次計画置換!G45 -> 389300 | H51: =02_R8予算_年次計画置換!H45 -> 382930 | I51: =02_R8予算_年次計画置換!I45 -> 368500 | ... K51: =02_R8予算_年次計画置換!K45 -> 230500
A52: 企業債償還金 | B52: =02_R8予算_年次計画置換!B46 -> 855029 | C52: =02_R8予算_年次計画置換!C46 -> 795933 | D52: =02_R8予算_年次計画置換!D46 -> 732671 | E52: =02_R8予算_年次計画置換!E46 -> 676031 | F52: =02_R8予算_年次計画置換!F46 -> 647341 | G52: =02_R8予算_年次計画置換!G46 -> 587622 | H52: =02_R8予算_年次計画置換!H46 -> 573964 | I52: =02_R8予算_年次計画置換!I46 -> 558772 | ... K52: =02_R8予算_年次計画置換!K46 -> 544403
A53: その他資本的支出 | B53: =02_R8予算_年次計画置換!B47 -> 0 | C53: =02_R8予算_年次計画置換!C47 -> 0 | D53: =02_R8予算_年次計画置換!D47 -> 0 | E53: =02_R8予算_年次計画置換!E47 -> 0 | F53: =02_R8予算_年次計画置換!F47 -> 0 | G53: =02_R8予算_年次計画置換!G47 -> 0 | H53: =02_R8予算_年次計画置換!H47 -> 0 | I53: =02_R8予算_年次計画置換!I47 -> 0 | ... K53: =02_R8予算_年次計画置換!K47 -> 0
A54: 資本的収支不足額（収入－支出） | B54: =B40-B50 -> -424829 | C54: =C40-C50 -> -629095 | D54: =D40-D50 -> -558197 | E54: =E40-E50 -> -508033 | F54: =F40-F50 -> -473692 | G54: =G40-G50 -> -405409 | H54: =H40-H50 -> -393626 | I54: =I40-I50 -> -390180 | ... K54: =K40-K50 -> -409403
A56: 【現預金・4条財源】
A57: 補てん可能財源相当（簡便CF） | B57: =B28+B21+B22-B14 -> 484942 | C57: =C28+C21+C22-C14 -> 517390 | D57: =D28+D21+D22-D14 -> 460903 | E57: =E28+E21+E22-E14 -> 450114 | F57: =F28+F21+F22-F14 -> 1274374 | G57: =G28+G21+G22-G14 -> 1259517.5 | H57: =H28+H21+H22-H14 -> 1239625.1 | I57: =I28+I21+I22-I14 -> 1219287.2 | ... K57: =K28+K21+K22-K14 -> 1178843.7
A58: 資本的収支不足額（再掲） | B58: =B54 -> -424829 | C58: =C54 -> -629095 | D58: =D54 -> -558197 | E58: =E54 -> -508033 | F58: =F54 -> -473692 | G58: =G54 -> -405409 | H58: =H54 -> -393626 | I58: =I54 -> -390180 | ... K58: =K54 -> -409403
A59: 年度末現預金残高 | B59: =00_前提・検証!$B$6 -> 242588 | C59: =B59+C57+C58 -> 130883 | D59: =C59+D57+D58 -> 33589 | E59: =D59+E57+E58 -> -24330 | F59: =E59+F57+F58 -> 776352.03 | G59: =F59+G57+G58 -> 1630460.5 | H59: =G59+H57+H58 -> 2476459.7 | I59: =H59+I57+I58 -> 3305566.9 | J59: =I59+J57+J58 -> 4102136.8 | K59: =J59+K57+K58 -> 4871577.5
A60: 最低現金目安との差額 | B60: =B59-00_前提・検証!$B$7 -> -57412 | C60: =C59-00_前提・検証!$B$7 -> -169117 | D60: =D59-00_前提・検証!$B$7 -> -266411 | E60: =E59-00_前提・検証!$B$7 -> -324330 | F60: =F59-00_前提・検証!$B$7 -> 476352.03 | G60: =G59-00_前提・検証!$B$7 -> 1330460.5 | H60: =H59-00_前提・検証!$B$7 -> 2176459.7 | I60: =I59-00_前提・検証!$B$7 -> 3005566.9 | ... K60: =K59-00_前提・検証!$B$7 -> 4571577.5
A62: 【建設仮勘定・追加企業債影響：本体へ統合済み（参考ブロックは無効化）】
A63: 項目 | B63: 令和7年度 | C63: 令和8年度 | D63: 令和9年度 | E63: 令和10年度 | F63: 令和11年度 | G63: 令和12年度 | H63: 令和13年度 | I63: 令和14年度 | J63: 令和15年度 | K63: 令和16年度
A64: 減価償却費増加（本体統合済のため0） | B64: 0 | C64: 0 | D64: 0 | E64: 0 | F64: 0 | G64: 0 | H64: 0 | I64: 0 | J64: 0 | K64: 0
